Workbook

Sheet Model_Info
A1: VHP.NZ -- Vital Healthcare Property Trust -- AFFO capitalization model
A2: Version 1.0, fresh build 2026-09-19. Supersedes nothing (first valuation of this ticker).
A3: Built by the dcf-analyst agent (Claude Fable 5.1) on 2026-09-19 at the research orchestrator's request.
A5: DATA VINTAGE
A6: Price NZ$1.92 -- Yahoo Finance, NZX regular close Fri 18-Sep-2026 (2026-09-18T05:00:01Z). Figures go stale; refresh the price before use.
A7: Balance sheet, units on issue (807.127m), NTA/unit ($2.41), borrowings, hedging: FY2026 annual report as at 30-Jun-2026, published 13-Aug-2026.
A8: AFFO 86.918m / 11.50 cpu FY2026: annual report note 12 (struck on 755.951m weighted diluted units).
A9: Guidance: FY2027 distribution 9.75 cpu (annual report, 13-Aug-2026).
A11: METHODOLOGY
A12: Model: AFFO capitalization at COST OF EQUITY. AFFO is post-interest and post-current-tax, so it is an equity flow -- net debt (1,414m) is never subtracted. Routed via dcf-methods SKILL.md REIT row.
A13: Explicit path: five years built bottom-up (NPI, other income/add-backs, G&A incl SBC, net finance cost, current tax, maintenance capex) -> AFFO. Terminal value = MAX(0, MIN(Gordon, 16x AFFO_FY31)), end-of-year discounting.
A14: Per-unit divisor is the 807.127m year-end unit count (not the 755.951m weighted average), held flat: DRP units are matched by retained cash; no raise assumed.
... A28: Row 3 headers; 4 year index; 5 NPI growth (driver); 6 NPI; 7 fee income + non-cash add-backs (driver); 8 G&A incl SBC (driver); 9 net finance cost (driver); 10 current tax (driver); 11 maintenance capex (driver); 12 AFFO; 13 AFFO cpu; 14 discount factor; 15 PV AFFO; 17 gross property income (dashboard engine revenue); 18 AFFO margin; 20 SBC memo; 22-35 valuation block; 38-40 street memo; 42-46 NTA cross-check.

Sheet Actuals
A1: Metric | B1: FY2018 | C1: FY2019 | D1: FY2020 | E1: FY2021 | F1: FY2022 | G1: FY2023 | H1: FY2024 | I1: FY2025 | J1: FY2026 | K1: Source
A2: AFFO (NZ$m) | B2: 47.074 | C2: 43.897 | D2: 47.211 | E2: 57.457 | F2: 67.824 | G2: 73.335 | H2: 72.899 | I2: 70.369 | J2: 86.918 | K2: Annual reports, 5-year summaries / note 12
A3: AFFO per unit (cpu, weighted diluted) | B3: 10.84 | C3: 9.9 | D3: 10.45 | E3: 11.54 | F3: 11.92 | G3: 11.18 | H3: 10.9 | I3: 10.41 | J3: 11.5 | K3: same
A4: Distribution per unit (cpu) | B4: 8.5 | C4: 8.75 | D4: 8.75 | E4: 8.88 | F4: 9.63 | G4: 9.75 | H4: 9.75 | I4: 9.75 | J4: 9.75 | K4: same
A5: NTA per unit ($) | D5: 2.38 | E5: 2.89 | F5: 3.34 | G5: 2.96 | H5: 2.69 | I5: 2.47 | J5: 2.41 | K5: FY21 AR p.6; FY26 AR 5-yr summary
A6: Net property income (NZ$m) | D6: 100.147 | E6: 109.663 | F6: 123.018 | G6: 145.224 | H6: 144.533 | I6: 148.834 | J6: 162.217 | K6: kpis / income statements
A7: Gross property income (NZ$m) | D7: 114.419 | E7: 126.144 | F7: 143.633 | G7: 171.315 | H7: 168.788 | I7: 177.101 | J7: 192.988 | K7: Metrics.csv Revenue
A8: Net interest expense (NZ$m) | E8: 27.719 | F8: 28.983 | G8: 37.77 | H8: 40.606 | I8: 45.169 | J8: 54.255 | K8: FY26 AR 5-yr summary
A9: Borrowings (NZ$m) | D9: 813.515 | E9: 929.3 | F9: 1018.777 | G9: 1239.156 | H9: 1287.477 | I9: 1363.639 | J9: 1427.838 | K9: balance sheets
A10: Gearing (debt/total assets %, Trust Deed) | F10: 30 | G10: 36.3 | H10: 39.1 | I10: 42.1 | J10: 39.6 | K10: FY26 AR
A11: Statutory net income (NZ$m) -- revaluation noise, NOT used | D11: 58.126 | E11: 278.392 | F11: 303.522 | G11: -152.401 | H11: -107.611 | I11: -51.22 | J11: -24.786 | K11: Metrics.csv
A12: Units on issue at year end (m) | H12: 671.923 | I12: 678.896 | J12: 807.127 | K12: FY26 AR note 10
A13: Current tax expense (NZ$m) | I13: 15.546 | J13: 7.933 | K13: FY26 AR note 6
A14: Northwest base management fee (NZ$m) | I14: 17.652 | J14: 8.885 | K14: FY26 AR note 24 (H1 only in FY26)
A15: FY-end price / NTA (x) | D15: 1.09 | E15: 1.09 | F15: 0.85 | G15: 0.8 | H15: 0.71 | I15: 0.82 | J15: 0.78 | K15: Yahoo June closes / NTA
A18: Guidance: FY2027 distribution 9.75 cpu payable quarterly, 'reviewed as development leasing progresses' (13-Aug-2026). No numeric AFFO guidance.
A19: Balance sheet 30-Jun-2026: borrowings 1,427.838m, cash 13.809m, net debt 1,414.029m (memo only), total assets 3,616.668m, unit holders funds 1,948.220m, investment property 3,512.6m at 5.54% cap rate.
A20: Buybacks: none in any year. Units issued FY26: 7.265m DRP + 120.966m placement/UPP (235m at $1.95 / $1.9124).

Sheet Assumptions
A1: Global inputs
A3: Current price (NZD) | B3: 1.92 | C3: Yahoo, NZX close 18-Sep-2026 05:00:01Z
A4: Price timestamp | B4: 2026-09-18T05:00:01Z regular close
A5: Units on issue (m) | B5: 807.127 | C5: FY26 AR note 10, 30-Jun-2026; flat across horizon
A6: NTA per unit (NZD) | B6: 2.41 | C6: FY26 AR, 30-Jun-2026
A7: Balance sheet date | B7: 2026-06-30
A8: FY2026 AFFO (NZ$m) | B8: 86.918 | C8: note 12
A9: FY2026 gross property income (NZ$m) | B9: 192.988 | C9: rentals 170.439 + recoveries 22.549
A10: FY2026 net property income (NZ$m) | B10: 162.217 | C10: income statement
A11: Hurdle rate for entry price | B11: 0.15 | C11: house standard
A12: Terminal value cap (x AFFO_FY31) | B12: 16 | C12: 6.25% exit AFFO yield; units traded 17-24x AFFO at FY22-FY25 year-ends, 16.7x now
A13: SBC run-rate (NZ$m/yr, LTIP) -- street add-back | B13: 1 | C13: FY26 H2 SBP expense 0.533m annualised; grows 3%/yr
A14: Net debt memo (NZ$m) -- NOT subtracted | B14: 1414.029 | C14: AFFO is post-interest
A15: FY2026 distribution (cpu) | B15: 9.75 | C15: FY27 guidance also 9.75
A17: Scenario inputs | B17: Bear | C17: Base | D17: Bull
A18: Cost of equity | B18: 0.105 | C18: 0.095 | D18: 0.09
A19: Terminal growth | B19: 0.02 | C19: 0.025 | D19: 0.03
A20: Probability weight | B20: 0.25 | C20: 0.5 | D20: 0.25
A21: Exit P/NTA (cross-check) | B21: 0.65 | C21: 0.8 | D21: 0.95
A22: NTA growth p.a. (cross-check) | B22: -0.02 | C22: 0.01 | D22: 0.02
A23: Weights sum (must be 1.00) | B23: =SUM(B20:D20)
A25: Cost of equity build: NZ 10yr ~4.5% + 0.75 beta x 6.0% ERP = 9.0%, +0.5% for 39.6% gearing / 20% unhedged debt, top-5 tenant concentration (65% of rent) and AUD translation = 9.5% base.
A27: Scenario narratives
A28: Bear: Australian hospital-operator stress leads to rent relief -- NPI +1.5%/yr; rates higher for longer, net finance cost +6%/yr to 71.5m; AFFO 8.8 cpu by FY31 and the distribution is cut from FY29. CoE 10.5%, g 2.0%.
A29: Base: NPI +4.8% fading to +3.9% (CPI/market reviews + Grace/RDX/committed pipeline at 6.3%); internal G&A 18.8m; net finance cost 58.0m rising to 68.5m as capitalised interest rolls off and hedges reprice; tax sheltered FY27-29 then fully taxed 17.0m in FY31. CoE 9.5%, g 2.5%.
A30: Bull: NPI +5.7%/yr, fee income to 7.5m, G&A flat, funding cost eases; AFFO 14.1 cpu by FY31, distribution lifted to 10.5 cpu. CoE 9.0%, g 3.0%; 16x cap binds.

Sheet AFFO_Bear
A1: VHP.NZ AFFO capitalization -- Bear (NZ$m unless stated)
A3: Year | B3: FY2026A | C3: FY2027E | D3: FY2028E | E3: FY2029E | F3: FY2030E | G3: FY2031E
A4: Year index | B4: 0 | C4: 1 | D4: 2 | E4: 3 | F4: 4 | G4: 5
A5: NPI growth YoY (driver) | C5: 0.017156 | D5: 0.015152 | E5: 0.014925 | F5: 0.014706 | G5: 0.014493
A6: Net property income | B6: =Assumptions!$B$10 | C6: =B6*(1+C5) | D6: =C6*(1+D5) | E6: =D6*(1+E5) | F6: =E6*(1+F5) | G6: =F6*(1+G5)
A7: Fee income + non-cash add-backs (driver) | B7: 5.3 | C7: 5 | D7: 5 | E7: 5 | F7: 5 | G7: 5 | I7: FY2026A components are memo values reconciling to note 12 (162.217+1.287 other+3.5 addbacks-20.355-52.1 net cash finance-5.118 net current tax-1.469 = 86.9).
A8: G&A incl SBC (driver, positive = cost) | B8: 20.355 | C8: 19 | D8: 19.6 | E8: 20.2 | F8: 20.8 | G8: 21.4
A9: Net finance cost, cash (driver) | B9: 52.1 | C9: 59 | D9: 62.5 | E9: 66 | F9: 69 | G9: 71.5
A10: Current tax (driver) | B10: 5.118 | C10: 3 | D10: 3.5 | E10: 4 | F10: 8 | G10: 14
A11: Maintenance capex (driver) | B11: 1.469 | C11: 1.5 | D11: 1.6 | E11: 1.7 | F11: 1.8 | G11: 1.9
A12: AFFO | B12: =Assumptions!$B$8 | C12: =C6+C7-C8-C9-C10-C11 | D12: =D6+D7-D8-D9-D10-D11 | E12: =E6+E7-E8-E9-E10-E11 | F12: =F6+F7-F8-F9-F10-F11 | G12: =G6+G7-G8-G9-G10-G11
A13: AFFO per unit (cpu) | B13: =B12/Assumptions!$B$5*100 | C13: =C12/Assumptions!$B$5*100 | D13: =D12/Assumptions!$B$5*100 | E13: =E12/Assumptions!$B$5*100 | F13: =F12/Assumptions!$B$5*100 | G13: =G12/Assumptions!$B$5*100
A14: Discount factor | C14: =1/(1+Assumptions!$B$18)^C4 | D14: =1/(1+Assumptions!$B$18)^D4 | E14: =1/(1+Assumptions!$B$18)^E4 | F14: =1/(1+Assumptions!$B$18)^F4 | G14: =1/(1+Assumptions!$B$18)^G4
A15: PV of AFFO | C15: =C12*C14 | D15: =D12*D14 | E15: =E12*E14 | F15: =F12*F14 | G15: =G12*G14
A17: Gross property income (engine revenue, grows with NPI) | B17: =Assumptions!$B$9 | C17: =B17*(1+C5) | D17: =C17*(1+D5) | E17: =D17*(1+E5) | F17: =E17*(1+F5) | G17: =F17*(1+G5)
A18: AFFO margin on gross property income | B18: =B12/B17 | C18: =C12/C17 | D18: =D12/D17 | E18: =E12/E17 | F18: =F12/F17 | G18: =G12/G17
A20: SBC memo (street add-back) | C20: =Assumptions!$B$13*1.03^(C4-1) | D20: =Assumptions!$B$13*1.03^(D4-1) | E20: =Assumptions!$B$13*1.03^(E4-1) | F20: =Assumptions!$B$13*1.03^(F4-1) | G20: =Assumptions!$B$13*1.03^(G4-1)
A22: Sum of PV of AFFO (FY27-FY31) | B22: =SUM(C15:G15)
A23: Terminal growth | B23: =Assumptions!$B$19
A24: Terminal-year AFFO x (1+g) | B24: =G12*(1+B23)
A25: Gordon terminal value | B25: =B24/(Assumptions!$B$18-B23)
A26: Capped terminal value (cap x AFFO_FY31) | B26: =Assumptions!$B$12*G12
A27: Terminal value used = MAX(0,MIN(Gordon,cap)) | B27: =MAX(0,MIN(B25,B26))
A28: Implied exit multiple (x AFFO_FY31) | B28: =B27/G12
A29: Implied exit AFFO yield | B29: =1/B28
A30: PV of terminal value | B30: =B27*G14
A31: Equity value (no net-debt deduction: AFFO is post-interest) | B31: =B22+B30
A32: Units on issue (m) | B32: =Assumptions!$B$5
A33: VALUE PER UNIT (NZD) | B33: =B31/B32
A34: Upside vs price | B34: =B33/Assumptions!$B$3-1
A35: Terminal value % of equity value | B35: =B30/B31
A38: Street memo: PV of explicit-period SBC | B38: =SUMPRODUCT(C20:G20/(1+Assumptions!$B$18)^C4:G4)
A39: Street memo: PV of terminal SBC | B39: =MIN(G20*(1+B23)/(Assumptions!$B$18-B23),Assumptions!$B$12*G20)*G14
A40: Street value per unit (SBC added back) | B40: =(B31+B38+B39)/B32
A42: Distribution per unit (cpu, driver) | C42: 9.75 | D42: 9.75 | E42: 9 | F42: 8.5 | G42: 8
A43: NTA cross-check: PV of DPU (NZD) | B43: =SUMPRODUCT(C42:G42/100*C14:G14)
A44: NTA per unit FY2031 | B44: =Assumptions!$B$6*(1+Assumptions!$B$22)^5
A45: Exit P/NTA | B45: =Assumptions!$B$21
A46: NTA cross-check value per unit (memo, not blended) | B46: =B43+B44*B45*G14

Sheet AFFO_Base
A1: VHP.NZ AFFO capitalization -- Base (NZ$m unless stated)
A3: Year | B3: FY2026A | C3: FY2027E | D3: FY2028E | E3: FY2029E | F3: FY2030E | G3: FY2031E
A4: Year index | B4: 0 | C4: 1 | D4: 2 | E4: 3 | F4: 4 | G4: 5
A5: NPI growth YoY (driver) | C5: 0.047979 | D5: 0.044118 | E5: 0.042254 | F5: 0.040541 | G5: 0.038961
A6: Net property income | B6: =Assumptions!$B$10 | C6: =B6*(1+C5) | D6: =C6*(1+D5) | E6: =D6*(1+E5) | F6: =E6*(1+F5) | G6: =F6*(1+G5)
A7: Fee income + non-cash add-backs (driver) | B7: 5.3 | C7: 5.3 | D7: 5.4 | E7: 5.5 | F7: 5.6 | G7: 5.7 | I7: FY2026A components are memo values reconciling to note 12 (162.217+1.287 other+3.5 addbacks-20.355-52.1 net cash finance-5.118 net current tax-1.469 = 86.9).
A8: G&A incl SBC (driver, positive = cost) | B8: 20.355 | C8: 18.8 | D8: 19.4 | E8: 20 | F8: 20.6 | G8: 21.2
A9: Net finance cost, cash (driver) | B9: 52.1 | C9: 58 | D9: 61.5 | E9: 64.5 | F9: 66.5 | G9: 68.5
A10: Current tax (driver) | B10: 5.118 | C10: 3 | D10: 3.5 | E10: 4 | F10: 8 | G10: 17
A11: Maintenance capex (driver) | B11: 1.469 | C11: 1.5 | D11: 1.6 | E11: 1.7 | F11: 1.8 | G11: 1.9
A12: AFFO | B12: =Assumptions!$B$8 | C12: =C6+C7-C8-C9-C10-C11 | D12: =D6+D7-D8-D9-D10-D11 | E12: =E6+E7-E8-E9-E10-E11 | F12: =F6+F7-F8-F9-F10-F11 | G12: =G6+G7-G8-G9-G10-G11
A13: AFFO per unit (cpu) | B13: =B12/Assumptions!$B$5*100 | C13: =C12/Assumptions!$B$5*100 | D13: =D12/Assumptions!$B$5*100 | E13: =E12/Assumptions!$B$5*100 | F13: =F12/Assumptions!$B$5*100 | G13: =G12/Assumptions!$B$5*100
A14: Discount factor | C14: =1/(1+Assumptions!$C$18)^C4 | D14: =1/(1+Assumptions!$C$18)^D4 | E14: =1/(1+Assumptions!$C$18)^E4 | F14: =1/(1+Assumptions!$C$18)^F4 | G14: =1/(1+Assumptions!$C$18)^G4
A15: PV of AFFO | C15: =C12*C14 | D15: =D12*D14 | E15: =E12*E14 | F15: =F12*F14 | G15: =G12*G14
A17: Gross property income (engine revenue, grows with NPI) | B17: =Assumptions!$B$9 | C17: =B17*(1+C5) | D17: =C17*(1+D5) | E17: =D17*(1+E5) | F17: =E17*(1+F5) | G17: =F17*(1+G5)
A18: AFFO margin on gross property income | B18: =B12/B17 | C18: =C12/C17 | D18: =D12/D17 | E18: =E12/E17 | F18: =F12/F17 | G18: =G12/G17
A20: SBC memo (street add-back) | C20: =Assumptions!$B$13*1.03^(C4-1) | D20: =Assumptions!$B$13*1.03^(D4-1) | E20: =Assumptions!$B$13*1.03^(E4-1) | F20: =Assumptions!$B$13*1.03^(F4-1) | G20: =Assumptions!$B$13*1.03^(G4-1)
A22: Sum of PV of AFFO (FY27-FY31) | B22: =SUM(C15:G15)
A23: Terminal growth | B23: =Assumptions!$C$19
A24: Terminal-year AFFO x (1+g) | B24: =G12*(1+B23)
A25: Gordon terminal value | B25: =B24/(Assumptions!$C$18-B23)
A26: Capped terminal value (cap x AFFO_FY31) | B26: =Assumptions!$B$12*G12
A27: Terminal value used = MAX(0,MIN(Gordon,cap)) | B27: =MAX(0,MIN(B25,B26))
A28: Implied exit multiple (x AFFO_FY31) | B28: =B27/G12
A29: Implied exit AFFO yield | B29: =1/B28
A30: PV of terminal value | B30: =B27*G14
A31: Equity value (no net-debt deduction: AFFO is post-interest) | B31: =B22+B30
A32: Units on issue (m) | B32: =Assumptions!$B$5
A33: VALUE PER UNIT (NZD) | B33: =B31/B32
A34: Upside vs price | B34: =B33/Assumptions!$B$3-1
A35: Terminal value % of equity value | B35: =B30/B31
A38: Street memo: PV of explicit-period SBC | B38: =SUMPRODUCT(C20:G20/(1+Assumptions!$C$18)^C4:G4)
A39: Street memo: PV of terminal SBC | B39: =MIN(G20*(1+B23)/(Assumptions!$C$18-B23),Assumptions!$B$12*G20)*G14
A40: Street value per unit (SBC added back) | B40: =(B31+B38+B39)/B32
A42: Distribution per unit (cpu, driver) | C42: 9.75 | D42: 9.75 | E42: 9.75 | F42: 9.75 | G42: 9.75
A43: NTA cross-check: PV of DPU (NZD) | B43: =SUMPRODUCT(C42:G42/100*C14:G14)
A44: NTA per unit FY2031 | B44: =Assumptions!$B$6*(1+Assumptions!$C$22)^5
A45: Exit P/NTA | B45: =Assumptions!$C$21
A46: NTA cross-check value per unit (memo, not blended) | B46: =B43+B44*B45*G14

Sheet AFFO_Bull
A1: VHP.NZ AFFO capitalization -- Bull (NZ$m unless stated)
A3: Year | B3: FY2026A | C3: FY2027E | D3: FY2028E | E3: FY2029E | F3: FY2030E | G3: FY2031E
A4: Year index | B4: 0 | C4: 1 | D4: 2 | E4: 3 | F4: 4 | G4: 5
A5: NPI growth YoY (driver) | C5: 0.057226 | D5: 0.050146 | E5: 0.049972 | F5: 0.049709 | G5: 0.050378
A6: Net property income | B6: =Assumptions!$B$10 | C6: =B6*(1+C5) | D6: =C6*(1+D5) | E6: =D6*(1+E5) | F6: =E6*(1+F5) | G6: =F6*(1+G5)
A7: Fee income + non-cash add-backs (driver) | B7: 5.3 | C7: 5.5 | D7: 6 | E7: 6.5 | F7: 7 | G7: 7.5 | I7: FY2026A components are memo values reconciling to note 12 (162.217+1.287 other+3.5 addbacks-20.355-52.1 net cash finance-5.118 net current tax-1.469 = 86.9).
A8: G&A incl SBC (driver, positive = cost) | B8: 20.355 | C8: 18.5 | D8: 18.9 | E8: 19.3 | F8: 19.7 | G8: 20.1
A9: Net finance cost, cash (driver) | B9: 52.1 | C9: 57 | D9: 59 | E9: 61 | F9: 62.5 | G9: 64
A10: Current tax (driver) | B10: 5.118 | C10: 3 | D10: 3.5 | E10: 4 | F10: 6 | G10: 16
A11: Maintenance capex (driver) | B11: 1.469 | C11: 1.5 | D11: 1.6 | E11: 1.7 | F11: 1.8 | G11: 1.9
A12: AFFO | B12: =Assumptions!$B$8 | C12: =C6+C7-C8-C9-C10-C11 | D12: =D6+D7-D8-D9-D10-D11 | E12: =E6+E7-E8-E9-E10-E11 | F12: =F6+F7-F8-F9-F10-F11 | G12: =G6+G7-G8-G9-G10-G11
A13: AFFO per unit (cpu) | B13: =B12/Assumptions!$B$5*100 | C13: =C12/Assumptions!$B$5*100 | D13: =D12/Assumptions!$B$5*100 | E13: =E12/Assumptions!$B$5*100 | F13: =F12/Assumptions!$B$5*100 | G13: =G12/Assumptions!$B$5*100
A14: Discount factor | C14: =1/(1+Assumptions!$D$18)^C4 | D14: =1/(1+Assumptions!$D$18)^D4 | E14: =1/(1+Assumptions!$D$18)^E4 | F14: =1/(1+Assumptions!$D$18)^F4 | G14: =1/(1+Assumptions!$D$18)^G4
A15: PV of AFFO | C15: =C12*C14 | D15: =D12*D14 | E15: =E12*E14 | F15: =F12*F14 | G15: =G12*G14
A17: Gross property income (engine revenue, grows with NPI) | B17: =Assumptions!$B$9 | C17: =B17*(1+C5) | D17: =C17*(1+D5) | E17: =D17*(1+E5) | F17: =E17*(1+F5) | G17: =F17*(1+G5)
A18: AFFO margin on gross property income | B18: =B12/B17 | C18: =C12/C17 | D18: =D12/D17 | E18: =E12/E17 | F18: =F12/F17 | G18: =G12/G17
A20: SBC memo (street add-back) | C20: =Assumptions!$B$13*1.03^(C4-1) | D20: =Assumptions!$B$13*1.03^(D4-1) | E20: =Assumptions!$B$13*1.03^(E4-1) | F20: =Assumptions!$B$13*1.03^(F4-1) | G20: =Assumptions!$B$13*1.03^(G4-1)
A22: Sum of PV of AFFO (FY27-FY31) | B22: =SUM(C15:G15)
A23: Terminal growth | B23: =Assumptions!$D$19
A24: Terminal-year AFFO x (1+g) | B24: =G12*(1+B23)
A25: Gordon terminal value | B25: =B24/(Assumptions!$D$18-B23)
A26: Capped terminal value (cap x AFFO_FY31) | B26: =Assumptions!$B$12*G12
A27: Terminal value used = MAX(0,MIN(Gordon,cap)) | B27: =MAX(0,MIN(B25,B26))
A28: Implied exit multiple (x AFFO_FY31) | B28: =B27/G12
A29: Implied exit AFFO yield | B29: =1/B28
A30: PV of terminal value | B30: =B27*G14
A31: Equity value (no net-debt deduction: AFFO is post-interest) | B31: =B22+B30
A32: Units on issue (m) | B32: =Assumptions!$B$5
A33: VALUE PER UNIT (NZD) | B33: =B31/B32
A34: Upside vs price | B34: =B33/Assumptions!$B$3-1
A35: Terminal value % of equity value | B35: =B30/B31
A38: Street memo: PV of explicit-period SBC | B38: =SUMPRODUCT(C20:G20/(1+Assumptions!$D$18)^C4:G4)
A39: Street memo: PV of terminal SBC | B39: =MIN(G20*(1+B23)/(Assumptions!$D$18-B23),Assumptions!$B$12*G20)*G14
A40: Street value per unit (SBC added back) | B40: =(B31+B38+B39)/B32
A42: Distribution per unit (cpu, driver) | C42: 9.75 | D42: 9.75 | E42: 10 | F42: 10.25 | G42: 10.5
A43: NTA cross-check: PV of DPU (NZD) | B43: =SUMPRODUCT(C42:G42/100*C14:G14)
A44: NTA per unit FY2031 | B44: =Assumptions!$B$6*(1+Assumptions!$D$22)^5
A45: Exit P/NTA | B45: =Assumptions!$D$21
A46: NTA cross-check value per unit (memo, not blended) | B46: =B43+B44*B45*G14

Sheet AFFO_Quality
A1: Statutory profit to AFFO reconciliation (FY26 AR note 12, NZ$000s)
A3: Line | B3: FY2026 | C3: FY2025
A4: Operating (loss)/profit before tax and other gains and losses | B4: -127248 | C4: 77438
A5: Current tax expense | B5: -7933 | C5: -15546
A6: Strategic and internalisation expenses | B6: 214653 | C6: 2848
A7: Current tax on translation of foreign currency funding | B7: 0 | C7: -59
A8: Current tax on property disposals | B8: 2815 | C8: 1214
A9: Share based payments expense | B9: 429 | C9: 0
A10: Reduction of contract asset | B10: 417 | C10: 0
A11: Amortisation of borrowing costs | B11: 2140 | C11: 2094
A12: Amortisation of leasing costs & tenant inducements | B12: 3651 | C12: 3604
A13: IFRS 16 operating lease accounting | B13: -537 | C13: -117
A14: Funds from operations (FFO) -- formula | B14: =SUM(B4:B13) | C14: =SUM(C4:C13)
A15: Actual capex from continuing operations | B15: -1469 | C15: -1108
A16: AFFO -- formula (must equal 86,918 / 70,368) | B16: =B14+B15 | C16: =C14+C15
A17: Weighted diluted units (000s) | B17: 755951 | C17: 675899
A18: AFFO per unit (cpu) -- formula | B18: =B16/B17*100 | C18: =C16/C17*100
A19: Units on issue at year end (000s) | B19: 807127 | C19: 678896
A20: AFFO per YEAR-END unit (cpu) -- the forward divisor | B20: =B16/B19*100 | C20: =C16/C19*100
A22: Memo: house basis treats the SBP add-back (429k FY26, ~1.0m/yr run-rate) as a cash cost; street basis keeps the Trust's definition.
A23: Memo: current tax fell 15.5m -> 7.9m on the internalisation deduction (49.9m DTA on ~178m of losses). Shelter is finite -- see scenario tabs row 10.
A24: Memo: reported OCF 85.191m less investing capex 75.818m = 9.4m 'free cash flow' -- development capex is growth capital and this figure is not used.

Sheet Valuation
A1: VHP.NZ valuation summary (NZD per unit)
A3: Scenario | B3: Value per unit | C3: Upside vs price | D3: Weight | E3: Street value per unit | F3: NTA cross-check | G3: Entry price @ hurdle | H3: Entry discount
A4: Bear | B4: =AFFO_Bear!B33 | C4: =B4/Assumptions!$B$3-1 | D4: =Assumptions!B20 | E4: =AFFO_Bear!B40 | F4: =AFFO_Bear!B46 | G4: =(SUMPRODUCT(AFFO_Bear!C12:G12/(1+Assumptions!$B$11)^AFFO_Bear!C4:G4)+MAX(0,MIN(AFFO_Bear!G12*(1+Assumptions!$B$19)/(Assumptions!$B$11-Assumptions!$B$19),Assumptions!$B$12*AFFO_Bear!G12))/(1+Assumptions!$B$11)^5)/Assumptions!$B$5 | H4: =G4/Assumptions!$B$3-1
A5: Base | B5: =AFFO_Base!B33 | C5: =B5/Assumptions!$B$3-1 | D5: =Assumptions!C20 | E5: =AFFO_Base!B40 | F5: =AFFO_Base!B46 | G5: =(SUMPRODUCT(AFFO_Base!C12:G12/(1+Assumptions!$B$11)^AFFO_Base!C4:G4)+MAX(0,MIN(AFFO_Base!G12*(1+Assumptions!$C$19)/(Assumptions!$B$11-Assumptions!$C$19),Assumptions!$B$12*AFFO_Base!G12))/(1+Assumptions!$B$11)^5)/Assumptions!$B$5 | H5: =G5/Assumptions!$B$3-1
A6: Bull | B6: =AFFO_Bull!B33 | C6: =B6/Assumptions!$B$3-1 | D6: =Assumptions!D20 | E6: =AFFO_Bull!B40 | F6: =AFFO_Bull!B46 | G6: =(SUMPRODUCT(AFFO_Bull!C12:G12/(1+Assumptions!$B$11)^AFFO_Bull!C4:G4)+MAX(0,MIN(AFFO_Bull!G12*(1+Assumptions!$D$19)/(Assumptions!$B$11-Assumptions!$D$19),Assumptions!$B$12*AFFO_Bull!G12))/(1+Assumptions!$B$11)^5)/Assumptions!$B$5 | H6: =G6/Assumptions!$B$3-1
A8: Probability-weighted value per unit | B8: =SUMPRODUCT(B4:B6,D4:D6)
A9: Margin of safety vs price (1 - price/weighted) | B9: =1-Assumptions!$B$3/B8
A10: Street weighted value per unit | B10: =SUMPRODUCT(E4:E6,D4:D6)
A11: Band position (0% = house, 100% = street) | B11: =(Assumptions!$B$3-B8)/(B10-B8)
A12: Weighted entry price (buy-below at 15% IRR) | B12: =SUMPRODUCT(G4:G6,D4:D6)
A13: Current price | B13: =Assumptions!$B$3
A14: Price / NTA | B14: =Assumptions!$B$3/Assumptions!$B$6
A15: Price / FY2026 AFFO (11.50 cpu) | B15: =Assumptions!$B$3/0.115
A17: Required-return table (Base case; TV rebuilt at each rate, capped at 16x)
A18: Required return | B18: Value per unit
A19: 0.09 | B19: =(SUMPRODUCT(AFFO_Base!C12:G12/(1+A19)^AFFO_Base!C4:G4)+MAX(0,MIN(AFFO_Base!G12*(1+Assumptions!$C$19)/(A19-Assumptions!$C$19),Assumptions!$B$12*AFFO_Base!G12))/(1+A19)^5)/Assumptions!$B$5
A20: 0.095 | B20: =(SUMPRODUCT(AFFO_Base!C12:G12/(1+A20)^AFFO_Base!C4:G4)+MAX(0,MIN(AFFO_Base!G12*(1+Assumptions!$C$19)/(A20-Assumptions!$C$19),Assumptions!$B$12*AFFO_Base!G12))/(1+A20)^5)/Assumptions!$B$5 | C20: Base cost-of-equity row: must equal AFFO_Base!B33
A21: 0.1 | B21: =(SUMPRODUCT(AFFO_Base!C12:G12/(1+A21)^AFFO_Base!C4:G4)+MAX(0,MIN(AFFO_Base!G12*(1+Assumptions!$C$19)/(A21-Assumptions!$C$19),Assumptions!$B$12*AFFO_Base!G12))/(1+A21)^5)/Assumptions!$B$5
A22: 0.11 | B22: =(SUMPRODUCT(AFFO_Base!C12:G12/(1+A22)^AFFO_Base!C4:G4)+MAX(0,MIN(AFFO_Base!G12*(1+Assumptions!$C$19)/(A22-Assumptions!$C$19),Assumptions!$B$12*AFFO_Base!G12))/(1+A22)^5)/Assumptions!$B$5
A23: 0.12 | B23: =(SUMPRODUCT(AFFO_Base!C12:G12/(1+A23)^AFFO_Base!C4:G4)+MAX(0,MIN(AFFO_Base!G12*(1+Assumptions!$C$19)/(A23-Assumptions!$C$19),Assumptions!$B$12*AFFO_Base!G12))/(1+A23)^5)/Assumptions!$B$5
A24: 0.15 | B24: =(SUMPRODUCT(AFFO_Base!C12:G12/(1+A24)^AFFO_Base!C4:G4)+MAX(0,MIN(AFFO_Base!G12*(1+Assumptions!$C$19)/(A24-Assumptions!$C$19),Assumptions!$B$12*AFFO_Base!G12))/(1+A24)^5)/Assumptions!$B$5 | C24: Hurdle row: must equal the Base entry price in G5
A27: Sensitivity: Base value per unit -- rows = cost of equity, columns = terminal growth
B28: 0.015 | C28: 0.02 | D28: 0.025 | E28: 0.03 | F28: 0.035
A29: 0.075 | B29: =IF($A29>B$28,(SUMPRODUCT(AFFO_Base!$C$12:$G$12/(1+$A29)^AFFO_Base!$C$4:$G$4)+MAX(0,MIN(AFFO_Base!$G$12*(1+B$28)/($A29-B$28),Assumptions!$B$12*AFFO_Base!$G$12))/(1+$A29)^5)/Assumptions!$B$5,"n/a") | C29: =IF($A29>C$28,(SUMPRODUCT(AFFO_Base!$C$12:$G$12/(1+$A29)^AFFO_Base!$C$4:$G$4)+MAX(0,MIN(AFFO_Base!$G$12*(1+C$28)/($A29-C$28),Assumptions!$B$12*AFFO_Base!$G$12))/(1+$A29)^5)/Assumptions!$B$5,"n/a") | D29: =IF($A29>D$28,(SUMPRODUCT(AFFO_Base!$C$12:$G$12/(1+$A29)^AFFO_Base!$C$4:$G$4)+MAX(0,MIN(AFFO_Base!$G$12*(1+D$28)/($A29-D$28),Assumptions!$B$12*AFFO_Base!$G$12))/(1+$A29)^5)/Assumptions!$B$5,"n/a") | E29: =IF($A29>E$28,(SUMPRODUCT(AFFO_Base!$C$12:$G$12/(1+$A29)^AFFO_Base!$C$4:$G$4)+MAX(0,MIN(AFFO_Base!$G$12*(1+E$28)/($A29-E$28),Assumptions!$B$12*AFFO_Base!$G$12))/(1+$A29)^5)/Assumptions!$B$5,"n/a") | F29: =IF($A29>F$28,(SUMPRODUCT(AFFO_Base!$C$12:$G$12/(1+$A29)^AFFO_Base!$C$4:$G$4)+MAX(0,MIN(AFFO_Base!$G$12*(1+F$28)/($A29-F$28),Assumptions!$B$12*AFFO_Base!$G$12))/(1+$A29)^5)/Assumptions!$B$5,"n/a")
A30: 0.085 | B30: =IF($A30>B$28,(SUMPRODUCT(AFFO_Base!$C$12:$G$12/(1+$A30)^AFFO_Base!$C$4:$G$4)+MAX(0,MIN(AFFO_Base!$G$12*(1+B$28)/($A30-B$28),Assumptions!$B$12*AFFO_Base!$G$12))/(1+$A30)^5)/Assumptions!$B$5,"n/a") | C30: =IF($A30>C$28,(SUMPRODUCT(AFFO_Base!$C$12:$G$12/(1+$A30)^AFFO_Base!$C$4:$G$4)+MAX(0,MIN(AFFO_Base!$G$12*(1+C$28)/($A30-C$28),Assumptions!$B$12*AFFO_Base!$G$12))/(1+$A30)^5)/Assumptions!$B$5,"n/a") | D30: =IF($A30>D$28,(SUMPRODUCT(AFFO_Base!$C$12:$G$12/(1+$A30)^AFFO_Base!$C$4:$G$4)+MAX(0,MIN(AFFO_Base!$G$12*(1+D$28)/($A30-D$28),Assumptions!$B$12*AFFO_Base!$G$12))/(1+$A30)^5)/Assumptions!$B$5,"n/a") | E30: =IF($A30>E$28,(SUMPRODUCT(AFFO_Base!$C$12:$G$12/(1+$A30)^AFFO_Base!$C$4:$G$4)+MAX(0,MIN(AFFO_Base!$G$12*(1+E$28)/($A30-E$28),Assumptions!$B$12*AFFO_Base!$G$12))/(1+$A30)^5)/Assumptions!$B$5,"n/a") | F30: =IF($A30>F$28,(SUMPRODUCT(AFFO_Base!$C$12:$G$12/(1+$A30)^AFFO_Base!$C$4:$G$4)+MAX(0,MIN(AFFO_Base!$G$12*(1+F$28)/($A30-F$28),Assumptions!$B$12*AFFO_Base!$G$12))/(1+$A30)^5)/Assumptions!$B$5,"n/a")
A31: 0.095 | B31: =IF($A31>B$28,(SUMPRODUCT(AFFO_Base!$C$12:$G$12/(1+$A31)^AFFO_Base!$C$4:$G$4)+MAX(0,MIN(AFFO_Base!$G$12*(1+B$28)/($A31-B$28),Assumptions!$B$12*AFFO_Base!$G$12))/(1+$A31)^5)/Assumptions!$B$5,"n/a") | C31: =IF($A31>C$28,(SUMPRODUCT(AFFO_Base!$C$12:$G$12/(1+$A31)^AFFO_Base!$C$4:$G$4)+MAX(0,MIN(AFFO_Base!$G$12*(1+C$28)/($A31-C$28),Assumptions!$B$12*AFFO_Base!$G$12))/(1+$A31)^5)/Assumptions!$B$5,"n/a") | D31: =IF($A31>D$28,(SUMPRODUCT(AFFO_Base!$C$12:$G$12/(1+$A31)^AFFO_Base!$C$4:$G$4)+MAX(0,MIN(AFFO_Base!$G$12*(1+D$28)/($A31-D$28),Assumptions!$B$12*AFFO_Base!$G$12))/(1+$A31)^5)/Assumptions!$B$5,"n/a") | E31: =IF($A31>E$28,(SUMPRODUCT(AFFO_Base!$C$12:$G$12/(1+$A31)^AFFO_Base!$C$4:$G$4)+MAX(0,MIN(AFFO_Base!$G$12*(1+E$28)/($A31-E$28),Assumptions!$B$12*AFFO_Base!$G$12))/(1+$A31)^5)/Assumptions!$B$5,"n/a") | F31: =IF($A31>F$28,(SUMPRODUCT(AFFO_Base!$C$12:$G$12/(1+$A31)^AFFO_Base!$C$4:$G$4)+MAX(0,MIN(AFFO_Base!$G$12*(1+F$28)/($A31-F$28),Assumptions!$B$12*AFFO_Base!$G$12))/(1+$A31)^5)/Assumptions!$B$5,"n/a")
A32: 0.105 | B32: =IF($A32>B$28,(SUMPRODUCT(AFFO_Base!$C$12:$G$12/(1+$A32)^AFFO_Base!$C$4:$G$4)+MAX(0,MIN(AFFO_Base!$G$12*(1+B$28)/($A32-B$28),Assumptions!$B$12*AFFO_Base!$G$12))/(1+$A32)^5)/Assumptions!$B$5,"n/a") | C32: =IF($A32>C$28,(SUMPRODUCT(AFFO_Base!$C$12:$G$12/(1+$A32)^AFFO_Base!$C$4:$G$4)+MAX(0,MIN(AFFO_Base!$G$12*(1+C$28)/($A32-C$28),Assumptions!$B$12*AFFO_Base!$G$12))/(1+$A32)^5)/Assumptions!$B$5,"n/a") | D32: =IF($A32>D$28,(SUMPRODUCT(AFFO_Base!$C$12:$G$12/(1+$A32)^AFFO_Base!$C$4:$G$4)+MAX(0,MIN(AFFO_Base!$G$12*(1+D$28)/($A32-D$28),Assumptions!$B$12*AFFO_Base!$G$12))/(1+$A32)^5)/Assumptions!$B$5,"n/a") | E32: =IF($A32>E$28,(SUMPRODUCT(AFFO_Base!$C$12:$G$12/(1+$A32)^AFFO_Base!$C$4:$G$4)+MAX(0,MIN(AFFO_Base!$G$12*(1+E$28)/($A32-E$28),Assumptions!$B$12*AFFO_Base!$G$12))/(1+$A32)^5)/Assumptions!$B$5,"n/a") | F32: =IF($A32>F$28,(SUMPRODUCT(AFFO_Base!$C$12:$G$12/(1+$A32)^AFFO_Base!$C$4:$G$4)+MAX(0,MIN(AFFO_Base!$G$12*(1+F$28)/($A32-F$28),Assumptions!$B$12*AFFO_Base!$G$12))/(1+$A32)^5)/Assumptions!$B$5,"n/a")
A33: 0.115 | B33: =IF($A33>B$28,(SUMPRODUCT(AFFO_Base!$C$12:$G$12/(1+$A33)^AFFO_Base!$C$4:$G$4)+MAX(0,MIN(AFFO_Base!$G$12*(1+B$28)/($A33-B$28),Assumptions!$B$12*AFFO_Base!$G$12))/(1+$A33)^5)/Assumptions!$B$5,"n/a") | C33: =IF($A33>C$28,(SUMPRODUCT(AFFO_Base!$C$12:$G$12/(1+$A33)^AFFO_Base!$C$4:$G$4)+MAX(0,MIN(AFFO_Base!$G$12*(1+C$28)/($A33-C$28),Assumptions!$B$12*AFFO_Base!$G$12))/(1+$A33)^5)/Assumptions!$B$5,"n/a") | D33: =IF($A33>D$28,(SUMPRODUCT(AFFO_Base!$C$12:$G$12/(1+$A33)^AFFO_Base!$C$4:$G$4)+MAX(0,MIN(AFFO_Base!$G$12*(1+D$28)/($A33-D$28),Assumptions!$B$12*AFFO_Base!$G$12))/(1+$A33)^5)/Assumptions!$B$5,"n/a") | E33: =IF($A33>E$28,(SUMPRODUCT(AFFO_Base!$C$12:$G$12/(1+$A33)^AFFO_Base!$C$4:$G$4)+MAX(0,MIN(AFFO_Base!$G$12*(1+E$28)/($A33-E$28),Assumptions!$B$12*AFFO_Base!$G$12))/(1+$A33)^5)/Assumptions!$B$5,"n/a") | F33: =IF($A33>F$28,(SUMPRODUCT(AFFO_Base!$C$12:$G$12/(1+$A33)^AFFO_Base!$C$4:$G$4)+MAX(0,MIN(AFFO_Base!$G$12*(1+F$28)/($A33-F$28),Assumptions!$B$12*AFFO_Base!$G$12))/(1+$A33)^5)/Assumptions!$B$5,"n/a")
