Workbook

Sheet DCF Model
A1: CB - Chubb Limited — Book Value Compounding Model (Base Case)
A2: Gray cells are INPUTS - adjust to see valuation change. Insurer model: BVPS compounding + exit P/B, NOT free-cash-flow DCF.
A4: KEY INPUTS
A5: Current Stock Price | B5: 333.37
A6: Shares Outstanding (M) | B6: 394.5995
A7: Total Debt (US$M) | B7: 15970
A8: Net Debt (held at zero - insurer model) | B8: 0
A9: Starting Book Value per Share (Q1 2026) | B9: 202.51
A10: Starting Payout Ratio (Year 1) | B10: 0.15
A12: Cost of Equity (Base) | B12: 0.09
A13: Exit Price-to-Book (Base) | B13: 1.55
A15: GROWTH & PAYOUT ASSUMPTIONS
C16: Year 1 | D16: Year 2 | E16: Year 3 | F16: Year 4 | G16: Year 5
A17: BVPS Growth Rate | C17: 0.12 | D17: 0.12 | E17: 0.115 | F17: 0.11 | G17: 0.105
A18: Payout Ratio (of implied EPS) | C18: 0.15 | D18: 0.15 | E18: 0.15 | F18: 0.15 | G18: 0.15
A20: PROJECTIONS
B21: Base Yr | C21: Year 1 | D21: Year 2 | E21: Year 3 | F21: Year 4 | G21: Year 5
A22: Book Value per Share (end of year, before dividend) | B22: =B9 | C22: =B22*(1+C17) | D22: =C22*(1+D17) | E22: =D22*(1+E17) | F22: =E22*(1+F17) | G22: =F22*(1+G17)
A23: Implied EPS (= BVPS growth $ / (1-payout)) | C23: =(C22-B22)/(1-C18) | D23: =(D22-C22)/(1-D18) | E23: =(E22-D22)/(1-E18) | F23: =(F22-E22)/(1-F18) | G23: =(G22-F22)/(1-G18)
A24: Dividend per Share (= Implied EPS x payout) | C24: =C23*C18 | D24: =D23*D18 | E24: =E23*E18 | F24: =F23*F18 | G24: =G23*G18
A25: Discount Factor (Cost of Equity) | C25: =1/(1+$B$12)^1 | D25: =1/(1+$B$12)^2 | E25: =1/(1+$B$12)^3 | F25: =1/(1+$B$12)^4 | G25: =1/(1+$B$12)^5
A26: PV of Dividend | C26: =C24*C25 | D26: =D24*D25 | E26: =E24*E25 | F26: =F24*F25 | G26: =G24*G25
A28: VALUATION
A29: Sum of PV of Dividends | B29: =SUM(C26:G26)
A30: Terminal BVPS (Year 5) | B30: =G22
A31: Exit Price-to-Book Multiple | B31: =B13
A32: Terminal Value per Share | B32: =B30*B31
A33: PV of Terminal Value | B33: =B32*G25
A34: INTRINSIC VALUE / SHARE | B34: =B29+B33
A35: Upside / (Downside) vs Current Price | B35: =(B34-B5)/B5
A37: ENTRY PRICE (15% Hurdle)
A38: Target CAGR (Hurdle Rate) | B38: 0.15
A39: PV of Dividends at Hurdle Rate | B39: =C24/(1+$B$38)^1+D24/(1+$B$38)^2+E24/(1+$B$38)^3+F24/(1+$B$38)^4+G24/(1+$B$38)^5
A40: PV of Terminal Value at Hurdle Rate | B40: =B32/(1+$B$38)^5
A41: Entry Price (15% Hurdle) | B41: =B39+B40
A42: Current Price vs Entry Price | B42: =(B5-B41)/B5
A44: Note: Book value per share is projected using management-guided/derived sustainable growth (ROE x retention).
A45: Dividend per share is BACKED OUT from the implied EPS needed to produce that growth at the assumed payout
A46: ratio (Chubb retains ~85% of earnings; payout ratio was 14.7%/15.6% in FY2025/FY2024). Discounting uses
A47: COST OF EQUITY (equity-holder view), not WACC. Net debt held at zero - see inputs.notes in the DCF JSON.

Sheet Bull-Bear Scenarios
A1: Bull / Bear Scenario Detail
A3: BULL CASE
A4: Cost of Equity | B4: 0.085
A5: Exit Price-to-Book | B5: 1.75
B6: Year 1 | C6: Year 2 | D6: Year 3 | E6: Year 4 | F6: Year 5
A7: BVPS Growth Rate | B7: 0.145 | C7: 0.14 | D7: 0.135 | E7: 0.13 | F7: 0.125
A8: Payout Ratio | C8: 0.13 | D8: 0.13 | E8: 0.13 | F8: 0.13 | G8: 0.13
A9: Book Value per Share | B9: ='DCF Model'!$B$9 | C9: =B9*(1+B7) | D9: =C9*(1+C7) | E9: =D9*(1+D7) | F9: =E9*(1+E7) | G9: =F9*(1+F7)
A10: Implied EPS | C10: =(C9-B9)/(1-C8) | D10: =(D9-C9)/(1-D8) | E10: =(E9-D9)/(1-E8) | F10: =(F9-E9)/(1-F8) | G10: =(G9-F9)/(1-G8)
A11: Dividend per Share | C11: =C10*C8 | D11: =D10*D8 | E11: =E10*E8 | F11: =F10*F8 | G11: =G10*G8
A12: Discount Factor | C12: =1/(1+B4)^1 | D12: =1/(1+B4)^2 | E12: =1/(1+B4)^3 | F12: =1/(1+B4)^4 | G12: =1/(1+B4)^5
A13: PV of Dividend | C13: =C11*C12 | D13: =D11*D12 | E13: =E11*E12 | F13: =F11*F12 | G13: =G11*G12
A15: Sum PV of Dividends | B15: =SUM(C13:G13)
A16: Terminal BVPS (Yr 5) | B16: =G9
A17: Terminal Value per Share | B17: =B16*B5
A18: PV of Terminal Value | B18: =B17*G12
A19: INTRINSIC VALUE / SHARE | B19: =B15+B18
A20: Upside / (Downside) | B20: =(B19-'DCF Model'!$B$5)/'DCF Model'!$B$5
A22: BEAR CASE
A23: Cost of Equity | B23: 0.095
A24: Exit Price-to-Book | B24: 1.25
B25: Year 1 | C25: Year 2 | D25: Year 3 | E25: Year 4 | F25: Year 5
A26: BVPS Growth Rate | B26: 0.07 | C26: 0.065 | D26: 0.06 | E26: 0.06 | F26: 0.055
A27: Payout Ratio | C27: 0.2 | D27: 0.2 | E27: 0.2 | F27: 0.2 | G27: 0.2
A28: Book Value per Share | B28: ='DCF Model'!$B$9 | C28: =B28*(1+B26) | D28: =C28*(1+C26) | E28: =D28*(1+D26) | F28: =E28*(1+E26) | G28: =F28*(1+F26)
A29: Implied EPS | C29: =(C28-B28)/(1-C27) | D29: =(D28-C28)/(1-D27) | E29: =(E28-D28)/(1-E27) | F29: =(F28-E28)/(1-F27) | G29: =(G28-F28)/(1-G27)
A30: Dividend per Share | C30: =C29*C27 | D30: =D29*D27 | E30: =E29*E27 | F30: =F29*F27 | G30: =G29*G27
A31: Discount Factor | C31: =1/(1+B23)^1 | D31: =1/(1+B23)^2 | E31: =1/(1+B23)^3 | F31: =1/(1+B23)^4 | G31: =1/(1+B23)^5
A32: PV of Dividend | C32: =C30*C31 | D32: =D30*D31 | E32: =E30*E31 | F32: =F30*F31 | G32: =G30*G31
A34: Sum PV of Dividends | B34: =SUM(C32:G32)
A35: Terminal BVPS (Yr 5) | B35: =G28
A36: Terminal Value per Share | B36: =B35*B24
A37: PV of Terminal Value | B37: =B36*G31
A38: INTRINSIC VALUE / SHARE | B38: =B34+B37
A39: Upside / (Downside) | B39: =(B38-'DCF Model'!$B$5)/'DCF Model'!$B$5

Sheet Sensitivity
A1: Sensitivity Analysis
A2: Intrinsic Value/Share by Cost of Equity & Exit Price-to-Book (base-case growth/payout path)
A4: CoE \ Exit P/B | B4: 1.25 | C4: 1.4 | D4: 1.55 | E4: 1.7 | F4: 1.85
A5: 0.07 | B5: =((((('DCF Model'!$B$9*(1+0.12))-'DCF Model'!$B$9)/(1-0.15))*0.15)/(1+0.07)^1+((((('DCF Model'!$B$9*(1+0.12))*(1+0.12))-('DCF Model'!$B$9*(1+0.12)))/(1-0.15))*0.15)/(1+0.07)^2+(((((('DCF Model'!$B$9*(1+0.12))*(1+0.12))*(1+0.115))-(('DCF Model'!$B$9*(1+0.12))*(1+0.12)))/(1-0.15))*0.15)/(1+0.07)^3+((((((('DCF Model'!$B$9*(1+0.12))*(1+0.12))*(1+0.115))*(1+0.11))-((('DCF Model'!$B$9*(1+0.12))*(1+0.12))*(1+0.115)))/(1-0.15))*0.15)/(1+0.07)^4+(((((((('DCF Model'!$B$9*(1+0.12))*(1+0.12))*(1+0.115))*(1+0.11))*(1+0.105))-(((('DCF Model'!$B$9*(1+0.12))*(1+0.12))*(1+0.115))*(1+0.11)))/(1-0.15))*0.15)/(1+0.07)^5)+(((((('DCF Model'!$B$9*(1+0.12))*(1+0.12))*(1+0.115))*(1+0.11))*(1+0.105))*1.25)/(1+0.07)^5 | C5: =((((('DCF Model'!$B$9*(1+0.12))-'DCF Model'!$B$9)/(1-0.15))*0.15)/(1+0.07)^1+((((('DCF Model'!$B$9*(1+0.12))*(1+0.12))-('DCF Model'!$B$9*(1+0.12)))/(1-0.15))*0.15)/(1+0.07)^2+(((((('DCF Model'!$B$9*(1+0.12))*(1+0.12))*(1+0.115))-(('DCF Model'!$B$9*(1+0.12))*(1+0.12)))/(1-0.15))*0.15)/(1+0.07)^3+((((((('DCF Model'!$B$9*(1+0.12))*(1+0.12))*(1+0.115))*(1+0.11))-((('DCF Model'!$B$9*(1+0.12))*(1+0.12))*(1+0.115)))/(1-0.15))*0.15)/(1+0.07)^4+(((((((('DCF Model'!$B$9*(1+0.12))*(1+0.12))*(1+0.115))*(1+0.11))*(1+0.105))-(((('DCF Model'!$B$9*(1+0.12))*(1+0.12))*(1+0.115))*(1+0.11)))/(1-0.15))*0.15)/(1+0.07)^5)+(((((('DCF Model'!$B$9*(1+0.12))*(1+0.12))*(1+0.115))*(1+0.11))*(1+0.105))*1.4)/(1+0.07)^5 | D5: =((((('DCF Model'!$B$9*(1+0.12))-'DCF Model'!$B$9)/(1-0.15))*0.15)/(1+0.07)^1+((((('DCF Model'!$B$9*(1+0.12))*(1+0.12))-('DCF Model'!$B$9*(1+0.12)))/(1-0.15))*0.15)/(1+0.07)^2+(((((('DCF Model'!$B$9*(1+0.12))*(1+0.12))*(1+0.115))-(('DCF Model'!$B$9*(1+0.12))*(1+0.12)))/(1-0.15))*0.15)/(1+0.07)^3+((((((('DCF Model'!$B$9*(1+0.12))*(1+0.12))*(1+0.115))*(1+0.11))-((('DCF Model'!$B$9*(1+0.12))*(1+0.12))*(1+0.115)))/(1-0.15))*0.15)/(1+0.07)^4+(((((((('DCF Model'!$B$9*(1+0.12))*(1+0.12))*(1+0.115))*(1+0.11))*(1+0.105))-(((('DCF Model'!$B$9*(1+0.12))*(1+0.12))*(1+0.115))*(1+0.11)))/(1-0.15))*0.15)/(1+0.07)^5)+(((((('DCF Model'!$B$9*(1+0.12))*(1+0.12))*(1+0.115))*(1+0.11))*(1+0.105))*1.55)/(1+0.07)^5 | E5: =((((('DCF Model'!$B$9*(1+0.12))-'DCF Model'!$B$9)/(1-0.15))*0.15)/(1+0.07)^1+((((('DCF Model'!$B$9*(1+0.12))*(1+0.12))-('DCF Model'!$B$9*(1+0.12)))/(1-0.15))*0.15)/(1+0.07)^2+(((((('DCF Model'!$B$9*(1+0.12))*(1+0.12))*(1+0.115))-(('DCF Model'!$B$9*(1+0.12))*(1+0.12)))/(1-0.15))*0.15)/(1+0.07)^3+((((((('DCF Model'!$B$9*(1+0.12))*(1+0.12))*(1+0.115))*(1+0.11))-((('DCF Model'!$B$9*(1+0.12))*(1+0.12))*(1+0.115)))/(1-0.15))*0.15)/(1+0.07)^4+(((((((('DCF Model'!$B$9*(1+0.12))*(1+0.12))*(1+0.115))*(1+0.11))*(1+0.105))-(((('DCF Model'!$B$9*(1+0.12))*(1+0.12))*(1+0.115))*(1+0.11)))/(1-0.15))*0.15)/(1+0.07)^5)+(((((('DCF Model'!$B$9*(1+0.12))*(1+0.12))*(1+0.115))*(1+0.11))*(1+0.105))*1.7)/(1+0.07)^5 | F5: =((((('DCF Model'!$B$9*(1+0.12))-'DCF Model'!$B$9)/(1-0.15))*0.15)/(1+0.07)^1+((((('DCF Model'!$B$9*(1+0.12))*(1+0.12))-('DCF Model'!$B$9*(1+0.12)))/(1-0.15))*0.15)/(1+0.07)^2+(((((('DCF Model'!$B$9*(1+0.12))*(1+0.12))*(1+0.115))-(('DCF Model'!$B$9*(1+0.12))*(1+0.12)))/(1-0.15))*0.15)/(1+0.07)^3+((((((('DCF Model'!$B$9*(1+0.12))*(1+0.12))*(1+0.115))*(1+0.11))-((('DCF Model'!$B$9*(1+0.12))*(1+0.12))*(1+0.115)))/(1-0.15))*0.15)/(1+0.07)^4+(((((((('DCF Model'!$B$9*(1+0.12))*(1+0.12))*(1+0.115))*(1+0.11))*(1+0.105))-(((('DCF Model'!$B$9*(1+0.12))*(1+0.12))*(1+0.115))*(1+0.11)))/(1-0.15))*0.15)/(1+0.07)^5)+(((((('DCF Model'!$B$9*(1+0.12))*(1+0.12))*(1+0.115))*(1+0.11))*(1+0.105))*1.85)/(1+0.07)^5
A6: 0.08 | B6: =((((('DCF Model'!$B$9*(1+0.12))-'DCF Model'!$B$9)/(1-0.15))*0.15)/(1+0.08)^1+((((('DCF Model'!$B$9*(1+0.12))*(1+0.12))-('DCF Model'!$B$9*(1+0.12)))/(1-0.15))*0.15)/(1+0.08)^2+(((((('DCF Model'!$B$9*(1+0.12))*(1+0.12))*(1+0.115))-(('DCF Model'!$B$9*(1+0.12))*(1+0.12)))/(1-0.15))*0.15)/(1+0.08)^3+((((((('DCF Model'!$B$9*(1+0.12))*(1+0.12))*(1+0.115))*(1+0.11))-((('DCF Model'!$B$9*(1+0.12))*(1+0.12))*(1+0.115)))/(1-0.15))*0.15)/(1+0.08)^4+(((((((('DCF Model'!$B$9*(1+0.12))*(1+0.12))*(1+0.115))*(1+0.11))*(1+0.105))-(((('DCF Model'!$B$9*(1+0.12))*(1+0.12))*(1+0.115))*(1+0.11)))/(1-0.15))*0.15)/(1+0.08)^5)+(((((('DCF Model'!$B$9*(1+0.12))*(1+0.12))*(1+0.115))*(1+0.11))*(1+0.105))*1.25)/(1+0.08)^5 | C6: =((((('DCF Model'!$B$9*(1+0.12))-'DCF Model'!$B$9)/(1-0.15))*0.15)/(1+0.08)^1+((((('DCF Model'!$B$9*(1+0.12))*(1+0.12))-('DCF Model'!$B$9*(1+0.12)))/(1-0.15))*0.15)/(1+0.08)^2+(((((('DCF Model'!$B$9*(1+0.12))*(1+0.12))*(1+0.115))-(('DCF Model'!$B$9*(1+0.12))*(1+0.12)))/(1-0.15))*0.15)/(1+0.08)^3+((((((('DCF Model'!$B$9*(1+0.12))*(1+0.12))*(1+0.115))*(1+0.11))-((('DCF Model'!$B$9*(1+0.12))*(1+0.12))*(1+0.115)))/(1-0.15))*0.15)/(1+0.08)^4+(((((((('DCF Model'!$B$9*(1+0.12))*(1+0.12))*(1+0.115))*(1+0.11))*(1+0.105))-(((('DCF Model'!$B$9*(1+0.12))*(1+0.12))*(1+0.115))*(1+0.11)))/(1-0.15))*0.15)/(1+0.08)^5)+(((((('DCF Model'!$B$9*(1+0.12))*(1+0.12))*(1+0.115))*(1+0.11))*(1+0.105))*1.4)/(1+0.08)^5 | D6: =((((('DCF Model'!$B$9*(1+0.12))-'DCF Model'!$B$9)/(1-0.15))*0.15)/(1+0.08)^1+((((('DCF Model'!$B$9*(1+0.12))*(1+0.12))-('DCF Model'!$B$9*(1+0.12)))/(1-0.15))*0.15)/(1+0.08)^2+(((((('DCF Model'!$B$9*(1+0.12))*(1+0.12))*(1+0.115))-(('DCF Model'!$B$9*(1+0.12))*(1+0.12)))/(1-0.15))*0.15)/(1+0.08)^3+((((((('DCF Model'!$B$9*(1+0.12))*(1+0.12))*(1+0.115))*(1+0.11))-((('DCF Model'!$B$9*(1+0.12))*(1+0.12))*(1+0.115)))/(1-0.15))*0.15)/(1+0.08)^4+(((((((('DCF Model'!$B$9*(1+0.12))*(1+0.12))*(1+0.115))*(1+0.11))*(1+0.105))-(((('DCF Model'!$B$9*(1+0.12))*(1+0.12))*(1+0.115))*(1+0.11)))/(1-0.15))*0.15)/(1+0.08)^5)+(((((('DCF Model'!$B$9*(1+0.12))*(1+0.12))*(1+0.115))*(1+0.11))*(1+0.105))*1.55)/(1+0.08)^5 | E6: =((((('DCF Model'!$B$9*(1+0.12))-'DCF Model'!$B$9)/(1-0.15))*0.15)/(1+0.08)^1+((((('DCF Model'!$B$9*(1+0.12))*(1+0.12))-('DCF Model'!$B$9*(1+0.12)))/(1-0.15))*0.15)/(1+0.08)^2+(((((('DCF Model'!$B$9*(1+0.12))*(1+0.12))*(1+0.115))-(('DCF Model'!$B$9*(1+0.12))*(1+0.12)))/(1-0.15))*0.15)/(1+0.08)^3+((((((('DCF Model'!$B$9*(1+0.12))*(1+0.12))*(1+0.115))*(1+0.11))-((('DCF Model'!$B$9*(1+0.12))*(1+0.12))*(1+0.115)))/(1-0.15))*0.15)/(1+0.08)^4+(((((((('DCF Model'!$B$9*(1+0.12))*(1+0.12))*(1+0.115))*(1+0.11))*(1+0.105))-(((('DCF Model'!$B$9*(1+0.12))*(1+0.12))*(1+0.115))*(1+0.11)))/(1-0.15))*0.15)/(1+0.08)^5)+(((((('DCF Model'!$B$9*(1+0.12))*(1+0.12))*(1+0.115))*(1+0.11))*(1+0.105))*1.7)/(1+0.08)^5 | F6: =((((('DCF Model'!$B$9*(1+0.12))-'DCF Model'!$B$9)/(1-0.15))*0.15)/(1+0.08)^1+((((('DCF Model'!$B$9*(1+0.12))*(1+0.12))-('DCF Model'!$B$9*(1+0.12)))/(1-0.15))*0.15)/(1+0.08)^2+(((((('DCF Model'!$B$9*(1+0.12))*(1+0.12))*(1+0.115))-(('DCF Model'!$B$9*(1+0.12))*(1+0.12)))/(1-0.15))*0.15)/(1+0.08)^3+((((((('DCF Model'!$B$9*(1+0.12))*(1+0.12))*(1+0.115))*(1+0.11))-((('DCF Model'!$B$9*(1+0.12))*(1+0.12))*(1+0.115)))/(1-0.15))*0.15)/(1+0.08)^4+(((((((('DCF Model'!$B$9*(1+0.12))*(1+0.12))*(1+0.115))*(1+0.11))*(1+0.105))-(((('DCF Model'!$B$9*(1+0.12))*(1+0.12))*(1+0.115))*(1+0.11)))/(1-0.15))*0.15)/(1+0.08)^5)+(((((('DCF Model'!$B$9*(1+0.12))*(1+0.12))*(1+0.115))*(1+0.11))*(1+0.105))*1.85)/(1+0.08)^5
A7: 0.09 | B7: =((((('DCF Model'!$B$9*(1+0.12))-'DCF Model'!$B$9)/(1-0.15))*0.15)/(1+0.09)^1+((((('DCF Model'!$B$9*(1+0.12))*(1+0.12))-('DCF Model'!$B$9*(1+0.12)))/(1-0.15))*0.15)/(1+0.09)^2+(((((('DCF Model'!$B$9*(1+0.12))*(1+0.12))*(1+0.115))-(('DCF Model'!$B$9*(1+0.12))*(1+0.12)))/(1-0.15))*0.15)/(1+0.09)^3+((((((('DCF Model'!$B$9*(1+0.12))*(1+0.12))*(1+0.115))*(1+0.11))-((('DCF Model'!$B$9*(1+0.12))*(1+0.12))*(1+0.115)))/(1-0.15))*0.15)/(1+0.09)^4+(((((((('DCF Model'!$B$9*(1+0.12))*(1+0.12))*(1+0.115))*(1+0.11))*(1+0.105))-(((('DCF Model'!$B$9*(1+0.12))*(1+0.12))*(1+0.115))*(1+0.11)))/(1-0.15))*0.15)/(1+0.09)^5)+(((((('DCF Model'!$B$9*(1+0.12))*(1+0.12))*(1+0.115))*(1+0.11))*(1+0.105))*1.25)/(1+0.09)^5 | C7: =((((('DCF Model'!$B$9*(1+0.12))-'DCF Model'!$B$9)/(1-0.15))*0.15)/(1+0.09)^1+((((('DCF Model'!$B$9*(1+0.12))*(1+0.12))-('DCF Model'!$B$9*(1+0.12)))/(1-0.15))*0.15)/(1+0.09)^2+(((((('DCF Model'!$B$9*(1+0.12))*(1+0.12))*(1+0.115))-(('DCF Model'!$B$9*(1+0.12))*(1+0.12)))/(1-0.15))*0.15)/(1+0.09)^3+((((((('DCF Model'!$B$9*(1+0.12))*(1+0.12))*(1+0.115))*(1+0.11))-((('DCF Model'!$B$9*(1+0.12))*(1+0.12))*(1+0.115)))/(1-0.15))*0.15)/(1+0.09)^4+(((((((('DCF Model'!$B$9*(1+0.12))*(1+0.12))*(1+0.115))*(1+0.11))*(1+0.105))-(((('DCF Model'!$B$9*(1+0.12))*(1+0.12))*(1+0.115))*(1+0.11)))/(1-0.15))*0.15)/(1+0.09)^5)+(((((('DCF Model'!$B$9*(1+0.12))*(1+0.12))*(1+0.115))*(1+0.11))*(1+0.105))*1.4)/(1+0.09)^5 | D7: =((((('DCF Model'!$B$9*(1+0.12))-'DCF Model'!$B$9)/(1-0.15))*0.15)/(1+0.09)^1+((((('DCF Model'!$B$9*(1+0.12))*(1+0.12))-('DCF Model'!$B$9*(1+0.12)))/(1-0.15))*0.15)/(1+0.09)^2+(((((('DCF Model'!$B$9*(1+0.12))*(1+0.12))*(1+0.115))-(('DCF Model'!$B$9*(1+0.12))*(1+0.12)))/(1-0.15))*0.15)/(1+0.09)^3+((((((('DCF Model'!$B$9*(1+0.12))*(1+0.12))*(1+0.115))*(1+0.11))-((('DCF Model'!$B$9*(1+0.12))*(1+0.12))*(1+0.115)))/(1-0.15))*0.15)/(1+0.09)^4+(((((((('DCF Model'!$B$9*(1+0.12))*(1+0.12))*(1+0.115))*(1+0.11))*(1+0.105))-(((('DCF Model'!$B$9*(1+0.12))*(1+0.12))*(1+0.115))*(1+0.11)))/(1-0.15))*0.15)/(1+0.09)^5)+(((((('DCF Model'!$B$9*(1+0.12))*(1+0.12))*(1+0.115))*(1+0.11))*(1+0.105))*1.55)/(1+0.09)^5 | E7: =((((('DCF Model'!$B$9*(1+0.12))-'DCF Model'!$B$9)/(1-0.15))*0.15)/(1+0.09)^1+((((('DCF Model'!$B$9*(1+0.12))*(1+0.12))-('DCF Model'!$B$9*(1+0.12)))/(1-0.15))*0.15)/(1+0.09)^2+(((((('DCF Model'!$B$9*(1+0.12))*(1+0.12))*(1+0.115))-(('DCF Model'!$B$9*(1+0.12))*(1+0.12)))/(1-0.15))*0.15)/(1+0.09)^3+((((((('DCF Model'!$B$9*(1+0.12))*(1+0.12))*(1+0.115))*(1+0.11))-((('DCF Model'!$B$9*(1+0.12))*(1+0.12))*(1+0.115)))/(1-0.15))*0.15)/(1+0.09)^4+(((((((('DCF Model'!$B$9*(1+0.12))*(1+0.12))*(1+0.115))*(1+0.11))*(1+0.105))-(((('DCF Model'!$B$9*(1+0.12))*(1+0.12))*(1+0.115))*(1+0.11)))/(1-0.15))*0.15)/(1+0.09)^5)+(((((('DCF Model'!$B$9*(1+0.12))*(1+0.12))*(1+0.115))*(1+0.11))*(1+0.105))*1.7)/(1+0.09)^5 | F7: =((((('DCF Model'!$B$9*(1+0.12))-'DCF Model'!$B$9)/(1-0.15))*0.15)/(1+0.09)^1+((((('DCF Model'!$B$9*(1+0.12))*(1+0.12))-('DCF Model'!$B$9*(1+0.12)))/(1-0.15))*0.15)/(1+0.09)^2+(((((('DCF Model'!$B$9*(1+0.12))*(1+0.12))*(1+0.115))-(('DCF Model'!$B$9*(1+0.12))*(1+0.12)))/(1-0.15))*0.15)/(1+0.09)^3+((((((('DCF Model'!$B$9*(1+0.12))*(1+0.12))*(1+0.115))*(1+0.11))-((('DCF Model'!$B$9*(1+0.12))*(1+0.12))*(1+0.115)))/(1-0.15))*0.15)/(1+0.09)^4+(((((((('DCF Model'!$B$9*(1+0.12))*(1+0.12))*(1+0.115))*(1+0.11))*(1+0.105))-(((('DCF Model'!$B$9*(1+0.12))*(1+0.12))*(1+0.115))*(1+0.11)))/(1-0.15))*0.15)/(1+0.09)^5)+(((((('DCF Model'!$B$9*(1+0.12))*(1+0.12))*(1+0.115))*(1+0.11))*(1+0.105))*1.85)/(1+0.09)^5
A8: 0.1 | B8: =((((('DCF Model'!$B$9*(1+0.12))-'DCF Model'!$B$9)/(1-0.15))*0.15)/(1+0.1)^1+((((('DCF Model'!$B$9*(1+0.12))*(1+0.12))-('DCF Model'!$B$9*(1+0.12)))/(1-0.15))*0.15)/(1+0.1)^2+(((((('DCF Model'!$B$9*(1+0.12))*(1+0.12))*(1+0.115))-(('DCF Model'!$B$9*(1+0.12))*(1+0.12)))/(1-0.15))*0.15)/(1+0.1)^3+((((((('DCF Model'!$B$9*(1+0.12))*(1+0.12))*(1+0.115))*(1+0.11))-((('DCF Model'!$B$9*(1+0.12))*(1+0.12))*(1+0.115)))/(1-0.15))*0.15)/(1+0.1)^4+(((((((('DCF Model'!$B$9*(1+0.12))*(1+0.12))*(1+0.115))*(1+0.11))*(1+0.105))-(((('DCF Model'!$B$9*(1+0.12))*(1+0.12))*(1+0.115))*(1+0.11)))/(1-0.15))*0.15)/(1+0.1)^5)+(((((('DCF Model'!$B$9*(1+0.12))*(1+0.12))*(1+0.115))*(1+0.11))*(1+0.105))*1.25)/(1+0.1)^5 | C8: =((((('DCF Model'!$B$9*(1+0.12))-'DCF Model'!$B$9)/(1-0.15))*0.15)/(1+0.1)^1+((((('DCF Model'!$B$9*(1+0.12))*(1+0.12))-('DCF Model'!$B$9*(1+0.12)))/(1-0.15))*0.15)/(1+0.1)^2+(((((('DCF Model'!$B$9*(1+0.12))*(1+0.12))*(1+0.115))-(('DCF Model'!$B$9*(1+0.12))*(1+0.12)))/(1-0.15))*0.15)/(1+0.1)^3+((((((('DCF Model'!$B$9*(1+0.12))*(1+0.12))*(1+0.115))*(1+0.11))-((('DCF Model'!$B$9*(1+0.12))*(1+0.12))*(1+0.115)))/(1-0.15))*0.15)/(1+0.1)^4+(((((((('DCF Model'!$B$9*(1+0.12))*(1+0.12))*(1+0.115))*(1+0.11))*(1+0.105))-(((('DCF Model'!$B$9*(1+0.12))*(1+0.12))*(1+0.115))*(1+0.11)))/(1-0.15))*0.15)/(1+0.1)^5)+(((((('DCF Model'!$B$9*(1+0.12))*(1+0.12))*(1+0.115))*(1+0.11))*(1+0.105))*1.4)/(1+0.1)^5 | D8: =((((('DCF Model'!$B$9*(1+0.12))-'DCF Model'!$B$9)/(1-0.15))*0.15)/(1+0.1)^1+((((('DCF Model'!$B$9*(1+0.12))*(1+0.12))-('DCF Model'!$B$9*(1+0.12)))/(1-0.15))*0.15)/(1+0.1)^2+(((((('DCF Model'!$B$9*(1+0.12))*(1+0.12))*(1+0.115))-(('DCF Model'!$B$9*(1+0.12))*(1+0.12)))/(1-0.15))*0.15)/(1+0.1)^3+((((((('DCF Model'!$B$9*(1+0.12))*(1+0.12))*(1+0.115))*(1+0.11))-((('DCF Model'!$B$9*(1+0.12))*(1+0.12))*(1+0.115)))/(1-0.15))*0.15)/(1+0.1)^4+(((((((('DCF Model'!$B$9*(1+0.12))*(1+0.12))*(1+0.115))*(1+0.11))*(1+0.105))-(((('DCF Model'!$B$9*(1+0.12))*(1+0.12))*(1+0.115))*(1+0.11)))/(1-0.15))*0.15)/(1+0.1)^5)+(((((('DCF Model'!$B$9*(1+0.12))*(1+0.12))*(1+0.115))*(1+0.11))*(1+0.105))*1.55)/(1+0.1)^5 | E8: =((((('DCF Model'!$B$9*(1+0.12))-'DCF Model'!$B$9)/(1-0.15))*0.15)/(1+0.1)^1+((((('DCF Model'!$B$9*(1+0.12))*(1+0.12))-('DCF Model'!$B$9*(1+0.12)))/(1-0.15))*0.15)/(1+0.1)^2+(((((('DCF Model'!$B$9*(1+0.12))*(1+0.12))*(1+0.115))-(('DCF Model'!$B$9*(1+0.12))*(1+0.12)))/(1-0.15))*0.15)/(1+0.1)^3+((((((('DCF Model'!$B$9*(1+0.12))*(1+0.12))*(1+0.115))*(1+0.11))-((('DCF Model'!$B$9*(1+0.12))*(1+0.12))*(1+0.115)))/(1-0.15))*0.15)/(1+0.1)^4+(((((((('DCF Model'!$B$9*(1+0.12))*(1+0.12))*(1+0.115))*(1+0.11))*(1+0.105))-(((('DCF Model'!$B$9*(1+0.12))*(1+0.12))*(1+0.115))*(1+0.11)))/(1-0.15))*0.15)/(1+0.1)^5)+(((((('DCF Model'!$B$9*(1+0.12))*(1+0.12))*(1+0.115))*(1+0.11))*(1+0.105))*1.7)/(1+0.1)^5 | F8: =((((('DCF Model'!$B$9*(1+0.12))-'DCF Model'!$B$9)/(1-0.15))*0.15)/(1+0.1)^1+((((('DCF Model'!$B$9*(1+0.12))*(1+0.12))-('DCF Model'!$B$9*(1+0.12)))/(1-0.15))*0.15)/(1+0.1)^2+(((((('DCF Model'!$B$9*(1+0.12))*(1+0.12))*(1+0.115))-(('DCF Model'!$B$9*(1+0.12))*(1+0.12)))/(1-0.15))*0.15)/(1+0.1)^3+((((((('DCF Model'!$B$9*(1+0.12))*(1+0.12))*(1+0.115))*(1+0.11))-((('DCF Model'!$B$9*(1+0.12))*(1+0.12))*(1+0.115)))/(1-0.15))*0.15)/(1+0.1)^4+(((((((('DCF Model'!$B$9*(1+0.12))*(1+0.12))*(1+0.115))*(1+0.11))*(1+0.105))-(((('DCF Model'!$B$9*(1+0.12))*(1+0.12))*(1+0.115))*(1+0.11)))/(1-0.15))*0.15)/(1+0.1)^5)+(((((('DCF Model'!$B$9*(1+0.12))*(1+0.12))*(1+0.115))*(1+0.11))*(1+0.105))*1.85)/(1+0.1)^5
A9: 0.11 | B9: =((((('DCF Model'!$B$9*(1+0.12))-'DCF Model'!$B$9)/(1-0.15))*0.15)/(1+0.11)^1+((((('DCF Model'!$B$9*(1+0.12))*(1+0.12))-('DCF Model'!$B$9*(1+0.12)))/(1-0.15))*0.15)/(1+0.11)^2+(((((('DCF Model'!$B$9*(1+0.12))*(1+0.12))*(1+0.115))-(('DCF Model'!$B$9*(1+0.12))*(1+0.12)))/(1-0.15))*0.15)/(1+0.11)^3+((((((('DCF Model'!$B$9*(1+0.12))*(1+0.12))*(1+0.115))*(1+0.11))-((('DCF Model'!$B$9*(1+0.12))*(1+0.12))*(1+0.115)))/(1-0.15))*0.15)/(1+0.11)^4+(((((((('DCF Model'!$B$9*(1+0.12))*(1+0.12))*(1+0.115))*(1+0.11))*(1+0.105))-(((('DCF Model'!$B$9*(1+0.12))*(1+0.12))*(1+0.115))*(1+0.11)))/(1-0.15))*0.15)/(1+0.11)^5)+(((((('DCF Model'!$B$9*(1+0.12))*(1+0.12))*(1+0.115))*(1+0.11))*(1+0.105))*1.25)/(1+0.11)^5 | C9: =((((('DCF Model'!$B$9*(1+0.12))-'DCF Model'!$B$9)/(1-0.15))*0.15)/(1+0.11)^1+((((('DCF Model'!$B$9*(1+0.12))*(1+0.12))-('DCF Model'!$B$9*(1+0.12)))/(1-0.15))*0.15)/(1+0.11)^2+(((((('DCF Model'!$B$9*(1+0.12))*(1+0.12))*(1+0.115))-(('DCF Model'!$B$9*(1+0.12))*(1+0.12)))/(1-0.15))*0.15)/(1+0.11)^3+((((((('DCF Model'!$B$9*(1+0.12))*(1+0.12))*(1+0.115))*(1+0.11))-((('DCF Model'!$B$9*(1+0.12))*(1+0.12))*(1+0.115)))/(1-0.15))*0.15)/(1+0.11)^4+(((((((('DCF Model'!$B$9*(1+0.12))*(1+0.12))*(1+0.115))*(1+0.11))*(1+0.105))-(((('DCF Model'!$B$9*(1+0.12))*(1+0.12))*(1+0.115))*(1+0.11)))/(1-0.15))*0.15)/(1+0.11)^5)+(((((('DCF Model'!$B$9*(1+0.12))*(1+0.12))*(1+0.115))*(1+0.11))*(1+0.105))*1.4)/(1+0.11)^5 | D9: =((((('DCF Model'!$B$9*(1+0.12))-'DCF Model'!$B$9)/(1-0.15))*0.15)/(1+0.11)^1+((((('DCF Model'!$B$9*(1+0.12))*(1+0.12))-('DCF Model'!$B$9*(1+0.12)))/(1-0.15))*0.15)/(1+0.11)^2+(((((('DCF Model'!$B$9*(1+0.12))*(1+0.12))*(1+0.115))-(('DCF Model'!$B$9*(1+0.12))*(1+0.12)))/(1-0.15))*0.15)/(1+0.11)^3+((((((('DCF Model'!$B$9*(1+0.12))*(1+0.12))*(1+0.115))*(1+0.11))-((('DCF Model'!$B$9*(1+0.12))*(1+0.12))*(1+0.115)))/(1-0.15))*0.15)/(1+0.11)^4+(((((((('DCF Model'!$B$9*(1+0.12))*(1+0.12))*(1+0.115))*(1+0.11))*(1+0.105))-(((('DCF Model'!$B$9*(1+0.12))*(1+0.12))*(1+0.115))*(1+0.11)))/(1-0.15))*0.15)/(1+0.11)^5)+(((((('DCF Model'!$B$9*(1+0.12))*(1+0.12))*(1+0.115))*(1+0.11))*(1+0.105))*1.55)/(1+0.11)^5 | E9: =((((('DCF Model'!$B$9*(1+0.12))-'DCF Model'!$B$9)/(1-0.15))*0.15)/(1+0.11)^1+((((('DCF Model'!$B$9*(1+0.12))*(1+0.12))-('DCF Model'!$B$9*(1+0.12)))/(1-0.15))*0.15)/(1+0.11)^2+(((((('DCF Model'!$B$9*(1+0.12))*(1+0.12))*(1+0.115))-(('DCF Model'!$B$9*(1+0.12))*(1+0.12)))/(1-0.15))*0.15)/(1+0.11)^3+((((((('DCF Model'!$B$9*(1+0.12))*(1+0.12))*(1+0.115))*(1+0.11))-((('DCF Model'!$B$9*(1+0.12))*(1+0.12))*(1+0.115)))/(1-0.15))*0.15)/(1+0.11)^4+(((((((('DCF Model'!$B$9*(1+0.12))*(1+0.12))*(1+0.115))*(1+0.11))*(1+0.105))-(((('DCF Model'!$B$9*(1+0.12))*(1+0.12))*(1+0.115))*(1+0.11)))/(1-0.15))*0.15)/(1+0.11)^5)+(((((('DCF Model'!$B$9*(1+0.12))*(1+0.12))*(1+0.115))*(1+0.11))*(1+0.105))*1.7)/(1+0.11)^5 | F9: =((((('DCF Model'!$B$9*(1+0.12))-'DCF Model'!$B$9)/(1-0.15))*0.15)/(1+0.11)^1+((((('DCF Model'!$B$9*(1+0.12))*(1+0.12))-('DCF Model'!$B$9*(1+0.12)))/(1-0.15))*0.15)/(1+0.11)^2+(((((('DCF Model'!$B$9*(1+0.12))*(1+0.12))*(1+0.115))-(('DCF Model'!$B$9*(1+0.12))*(1+0.12)))/(1-0.15))*0.15)/(1+0.11)^3+((((((('DCF Model'!$B$9*(1+0.12))*(1+0.12))*(1+0.115))*(1+0.11))-((('DCF Model'!$B$9*(1+0.12))*(1+0.12))*(1+0.115)))/(1-0.15))*0.15)/(1+0.11)^4+(((((((('DCF Model'!$B$9*(1+0.12))*(1+0.12))*(1+0.115))*(1+0.11))*(1+0.105))-(((('DCF Model'!$B$9*(1+0.12))*(1+0.12))*(1+0.115))*(1+0.11)))/(1-0.15))*0.15)/(1+0.11)^5)+(((((('DCF Model'!$B$9*(1+0.12))*(1+0.12))*(1+0.115))*(1+0.11))*(1+0.105))*1.85)/(1+0.11)^5
A11: Note: Rows = cost of equity (7%-11%). Columns = exit price-to-book multiple (1.25x-1.85x) applied to
A12: Year-5 book value per share. Base-case BVPS growth path (12%,12%,11.5%,11%,10.5%) and 15% payout ratio held constant.

Sheet Historical
A1: Historical Book Value per Share & Dividend
A3: FY | B3: BVPS ($) | C3: DPS ($)
A4: FY2015 | B4: 88.6 | C4: 2.56
A5: FY2016 | B5: 103.6
A6: FY2017 | B6: 108.6
A7: FY2018 | B7: 107.78
A8: FY2019 | B8: 120.57
A9: FY2020 | B9: 131.09
A10: FY2021 | B10: 131.61
A11: FY2022 | B11: 119.28 | C11: 3.29
A12: FY2023 | B12: 153.77 | C12: 3.41
A13: FY2024 | B13: 167.43 | C13: 3.59
A14: FY2025 | B14: 198.7 | C14: 3.82
A15: Q1 2026 | B15: 202.51 | C15: 0.97
A17: 10yr BVPS CAGR | B17: 0.084
A18: 5yr BVPS CAGR | B18: 0.087
A19: Note: FY2016-2021 DPS not disclosed in extracted metrics (spans 2016 ACE/Chubb merger share reset).

Sheet Sanity Check
A1: Sanity Check — Historical P/B Cross-Reference
A3: Base Intrinsic Value / Share | B3: ='DCF Model'!B34
A4: Implied P/B (Base IV / Q1-2026 BVPS) | B4: =B3/'DCF Model'!B9
A5: Normalized Core Operating EPS (mid-cycle, ~FY2025 run-rate) | B5: 26
A6: Implied P/E (Base IV / Normalized EPS) | B6: =B3/B5
A8: Historical / Peer P/B Context
A9: Current P/B (Q1 2026, price $333.37 / BVPS $202.51) | B9: 1.65
A10: Base-case Exit P/B assumption | B10: ='DCF Model'!B13
A11: Approx. quality-insurer historical P/B range (P&C large-cap peers) | B11: 1.1x - 1.85x
A13: Sanity Check Passed: | B13: YES
A15: Diagnosis:
A16: Base-case intrinsic value (~$369.63/share, computed in 'DCF Model') implies a P/B of ~1.83x on Q1-2026
A17: BVPS ($202.51) and ~14.2x normalized EPS (~$26/share) - both inside a plausible range for a
A18: high-quality, low-80s-combined-ratio P&C compouner with 14%+ core operating ROE, though at the upper
A19: end given the current 1.65x P/B. The model is BVPS-compounding based (management's own guided metric),
A20: not owner-FCF, because OCF/FCF for an insurer commingles float and investment-portfolio movements and
A21: is not a clean per-share signal. Weighted intrinsic value ($358.69) sits modestly above the current
A22: price ($333.37, +7.6%), consistent with a well-regarded, close-to-fairly-valued franchise rather than
A23: either a deep value opportunity or an obviously overvalued one.
