Workbook

Sheet Model_Info
A1: Ticker | B1: CNU.NZ
A2: Company | B2: Chorus Limited
A3: Valuation date | B3: 2026-09-25
A4: Current price | B4: 8.43
A5: Price as of | B5: 2026-09-25T05:00:31Z regular close (Yahoo Finance chart API)
A6: Balance sheet date | B6: 2026-06-30 (FY2026 year-end, net debt only per disclosed YoY movement; full FY2026 balance sheet not yet extracted)
A7: Model | B7: Unlevered owner-FCF enterprise DCF (net debt subtracted once; EV/EBITDA terminal cap binding over Gordon growth) -- regulated RAB/building-blocks infrastructure route per dcf-methods SKILL.md non-US/cyclical adaptations row
A8: Currency (model) | B8: NZD
A9: Currency (quote) | B9: NZD
A10: Units | B10: millions
A11: Convention | B11: Percents stored as percents; formulas divide by 100. Blue = input, green = link, black = formula. Terminal value = MIN(Gordon growth, EV/EBITDA cap x Year-10 EBITDA).
A12: Methodology | B12: Chorus is a regulated, high-leverage, income-oriented fibre network utility, not a growth compounder. The correct framing is dividend-plus-modest-growth (FY2026 dividend 60cps, FY2027 guided minimum 62cps ~7.4% yield at $8.43), underpinned by the Commerce Commission's PQ2 (2025-2028) building-blocks/RAB revenue-and-capex framework and a post-UFB-build capex taper that is inflecting reported FCF from structurally negative (-$258m FY2018) to positive and rising ($368m FY2026 free cash flow for capital allocation per management's own measure). This DCF is built on UNLEVERED (enterprise) owner FCF -- EBIT*(1-cash tax)+D&A-capex, with NO interest deduction -- discounted at WACC, with net debt subtracted once from enterprise value to reach equity value. This is standard enterprise-DCF practice and is essential here because Chorus's REPORTED FCF (OCF-capex, used in the Metrics.csv) is LEVERED (net of ~$175-220m/yr cash interest paid), and discounting levered FCF at WACC while also subtracting net debt would double-count Chorus's leverage. Given a market cap of only ~$3.75bn against ~$3.13bn of FY2026 net debt (net debt is ~83% of market cap and ~4.31x FY26 EBITDA on a net-debt/EBITDA-per-covenant basis of ~4.75x using the company's own gross measure), the equity value is extremely sensitive to WACC -- see the sensitivity matrix, which shows intrinsic value ranging from ~$10.82 at 5% WACC down to ~$5.9-6.2 at 9% WACC on an unchanged FCF path. This is a mechanical consequence of leverage (a fixed-dollar net debt deduction against a discount-rate-sensitive enterprise value), not a modelling artefact.
A13: WACC rationale | B13: approach: Bottom-up CAPM build, cross-checked against the Commerce Commission's own PQ2 allowed WACC determination. risk_free_rate_pct: 4.5 equity_risk_premium_pct: 5.5 asset_beta_unlevered: 0.4 asset_beta_rationale: Regulated network utility with contracted/RAB-set cash flows typically carries a low unlevered/asset beta (0.35-0.45); 0.40 used -- unchanged. Note: the Commerce Commission's 25-Aug-2026 Tranche 1 decision on the 2027 Fibre IM Review signalled a preliminary view (reported mid-Sep-2026) toward REDUCING the assessed systematic risk of fibre businesses for the PQ3 (from 2029) determination, which if it flows through to the Commission's own asset-beta assumption would argue for the low end of the 0.35-0.45 range, not a change today. Final cost-of-capital parameters are due Q4 2026, after this valuation date -- deliberately NOT pre-empted here; see risk_addon_rationale. debt_to_equity_for_relevering: 0.75 relevered_equity_beta: 0.62 cost_of_equity_pct: 7.9 pretax_cost_of_debt_pct: 4.9 cost_of_debt_basis: H1 FY2026 weighted average interest rate per company disclosure -- unchanged; Chorus issued EUR400m 7-year notes at 3.529% and repurchased EUR243m of 2026-maturity notes at 81.5% of face in Feb-2026, consistent with this cost-of-debt level. tax_rate_for_relevering_pct: 28 aftertax_cost_of_debt_pct: 3.53 weight_debt_pct: 45.5 weight_equity_pct: 54.5 capital_weights_basis: Market-value weights: FY26 net debt $3,129m / equity market cap ~$3,751m at current price $8.43 x 445m shares. bottom_up_wacc_pct: 5.92 regulatory_cross_check: The Commerce Commission has SET Chorus's allowed WACC at 7.68% PRE-TAX for the PQ2 period (1-Jan-2025 to 31-Dec-2028). Converted to a rough post-tax equivalent at the 28% statutory rate, that is approximately 5.53% post-tax -- broadly consistent with (slightly below) the ~5.9% bottom-up build. The regulatory figure uses the regulator's notional benchmark gearing for the RAB, not Chorus's actual capital structure or equity-holder risk, and does not price PQ3 (2029 reset) uncertainty or refinancing risk. regulatory_and_refinancing_risk_addon_pct: 1.08 risk_addon_rationale: Held UNCHANGED in this update (base WACC still 7.0%), deliberately not moved ahead of the Commerce Commission's Q4-2026 final cost-of-capital determination for PQ3, despite the Aug/Sep-2026 preliminary signal toward lower assessed systematic risk for fibre. That signal, if it firms up, is the upside catalyst already captured qualitatively in the bull scenario's lower WACC (6.3%) and reflected as the single largest swing factor named in the guidance commentary. Moving the base case WACC now on a preliminary, non-final regulatory signal would be pre-empting a determination that has not yet been made; the addon continues to reflect (a) PQ3 reset uncertainty generally, (b) refinancing/interest-rate risk on the EUR/AUD medium-term note stack recurring through 2032, and (c) leverage at the top of Chorus's own 4.75x net-debt/EBITDA policy tolerance (FY26 actual ~4.75x, no headroom), which if anything argues against lowering the addon this cycle even as the regulatory-risk component of it may ultimately fall. final_wacc_base_pct: 7.0 final_wacc_bull_pct: 6.3 final_wacc_bear_pct: 8.0 bull_bear_rationale: Bull reflects the Commerce Commission's preliminary lower-systematic-risk signal for fibre being confirmed at the Q4-2026 PQ3 determination plus an improving credit profile (S&P positive outlook) compressing WACC toward the bottom-up/regulatory-cross-check range; bear reflects an adverse PQ3 reset (assessed risk NOT reduced, or RAB rollforward pressured), higher-for-longer refinancing rates, and leverage stress given FY26 net debt/EBITDA is already at the ~4.75x policy ceiling with no headroom.
A14: Sanity check | B14: methodology: 10-year historical trading multiples computed from Yahoo Finance monthly closes aligned to Chorus's 30-June fiscal year-end, against FY-end shareholders' equity, revenue, and EBITDA. P/E is deliberately EXCLUDED (see growth_rate_rejections.pe_and_net_income_rejected) as meaningless given near-zero/negative-to-thin net income history. historical_multiples: fy_end_data: fy: FY2018 price: 4.31 pb: 1.81 ps: 1.87 ev_ebitda: 5.53; fy: FY2019 price: 5.53 pb: 2.48 ps: 2.5 ev_ebitda: 6.9; fy: FY2020 price: 7.46 pb: 3.58 ps: 3.46 ev_ebitda: 8.7; fy: FY2021 price: 6.16 pb: 2.78 ps: 2.88 ev_ebitda: 7.71; fy: FY2022 price: 7.99 pb: 3.47 ps: 3.7 ev_ebitda: 8.59; fy: FY2023 price: 8.6 pb: 3.58 ps: 3.89 ev_ebitda: 9.32; fy: FY2024 price: 7.9 pb: 4.08 ps: 3.39 ev_ebitda: 8.58; fy: FY2025 price: 8.715 pb: 6.69 ps: 3.74 ev_ebitda: 9.71 pb_median: 3.52 pb_range: 1.81; 6.69 ps_median: 3.43 ps_range: 1.87; 3.89 ev_ebitda_median: 8.59 ev_ebitda_range: 5.53; 9.71 ev_ebitda_recent_3yr_avg: 9.2 current_ev_ebitda_on_fy26_ebitda: 9.48 current_pb_on_h1_2026_equity: 8.72 note: FY2026 (30-Jun-2026) data point not yet added to the historical multiples table pending extraction of the FY2026 annual report (only the results announcement is in the Analysis JSON); current_ev_ebitda_on_fy26_ebitda uses today's price and FY26 actual EBITDA as a like-for-like cross-check instead. base_case_implied_multiples: implied_ev_ebitda_on_fy26_ebitda: 9.4 implied_pb_on_h1_2026_equity: 8.59 check_result: PASS note_on_calibration: This update re-verifies (does not re-derive) the prior build's Step-8c fix: an 8.0x base-case terminal EV/EBITDA cap was set on 2026-08-10 after an initial 9.0x cap produced an intrinsic value implying an EV/EBITDA (10.53-10.56x) above the entire 10-year historical trading range. With FY2026 actuals now in, the base case's implied EV/EBITDA on FY26 actual EBITDA is 9.4x -- within (near the top of) the 5.53x-9.71x historical range and close to the recent 3-year average of 9.20x -- confirming the 8.0x cap remains appropriately calibrated and does not need to move on this update's evidence. note_on_pb: P/B for Chorus remains a poor anchor because shareholders' equity is shrinking mechanically from the dividend policy (see growth_rate_rejections) even as FY26 net profit turned meaningfully positive ($37m). EV/EBITDA continues to be weighted more heavily as the reliable cross-check multiple.

Sheet Reconciliation
A1: Item | B1: Value | C1: Note
A2: Prior valuation_date | B2: 2026-08-10
A3: Prior price_then | B3: 8.41
A4: Prior bear | B4: 3.37
A5: Prior base | B5: 8.17
A6: Prior bull | B6: 12.57
A7: Prior weighted | B7: 8.07
A9: Bridge
A10: Prior weighted IV (2026-08-10 vintage) | B10: 8.07
A11: Price refresh $8.41 -> $8.43 (2026-09-25); negligible per-share effect, not a driver of IV | B11: 0
A12: Net debt anchor refreshed from H1-2026 ($3,175m) to FY2026 year-end actual ($3,129m, +$72m YoY per FY26 results) -- LOWER net debt by $46m adds value | B12: 0.1
A13: Year-1 (FY2027) driver re-judged to management's own FY27 guidance (EBITDA midpoint $745m, capex midpoint $395m) vs the prior build's un-anchored Year-1 projection ($740.1m EBITDA, $392m capex) -- immaterial net change since FY26 actuals landed almost exactly where the prior build had projected | B13: 0.02
A14: Years 2-10 taper paths: UNCHANGED (no new evidence moved copper-retirement timing, RAB growth assumptions, or the capex/D&A taper trajectory) | B14: 0
A15: Bull WACC/margin/capex assumptions: minor recalibration of Year-1 bull anchor to FY27 guidance context, and bull growth path trimmed slightly given no confirmed PQ3 favourable outcome yet (regulatory catalyst remains pending, not realized) | B15: -0.5
A16: Terminal EV/EBITDA cap (8.0x base): unchanged, re-verified against FY26 actual EBITDA -- still within the 10-year historical trading range | B16: 0
A17: Rounding / discounting precision | B17: 0.02
A18: New weighted IV | B18: 8.01 | C18: ties to probability_weighted.weighted_iv

Sheet Actuals
A1: Period | B1: Revenue | C1: CostOfRevenue | D1: GrossProfit | E1: GrossMargin | F1: OperatingIncome | G1: OperatingMargin | H1: EBITDA | I1: NetIncome | J1: NetMargin | K1: EPS | L1: OperatingCashFlow | M1: CapEx | N1: FreeCashFlow | O1: ShareholdersEquity | P1: TotalAssets | Q1: TotalLiabilities | R1: TotalDebt | S1: CashAndEquivalents | T1: SharesOutstanding | U1: StockBasedComp | V1: DividendPerShare | W1: EBITDABeforeSignificant | X1: RevenueContinuing | Y1: EBITDAContinuingBeforeSignificant | Z1: EBITContinuingBeforeSignificant | AA1: Units | AB1: Currency | AC1: BroadbandConnections | AD1: UnderlyingEBITDA
A2: H1-2018 | B2: 499.0 | F2: 137.0 | G2: 27.5 | H2: 329.0 | I2: 47.0 | J2: 9.418837675350701 | M2: 391.0 | R2: 1932.0 | S2: 40.0 | V2: 0.09 | AA2: millions | AB2: NZD
A3: FY2018 | B3: 990.0 | F3: 266.0 | G3: 26.86868686868687 | H3: 653.0 | I3: 85.0 | J3: 8.585858585858585 | K3: 0.2 | L3: 508.0 | M3: 766.0 | N3: -258.0 | O3: 1022.0 | P3: 4926.0 | Q3: 3904.0 | R3: 1807.0 | S3: 50.0 | T3: 429.6 | U3: 0.268 | V3: 0.22 | AA3: millions | AB3: NZD | AC3: 1187000.0
A4: H1-2019 | B4: 489.0 | F4: 122.0 | G4: 24.9 | H4: 318.0 | I4: 30.0 | J4: 6.134969325153374 | M4: 395.0 | V4: 0.095 | AA4: millions | AB4: NZD | AC4: 1186000.0
A5: FY2019 | B5: 970.0 | F5: 243.0 | G5: 25.051546391752577 | H5: 636.0 | I5: 53.0 | J5: 5.463917525773196 | K5: 0.12 | L5: 496.0 | M5: 806.0 | N5: -310.0 | O5: 979.0 | P5: 5618.0 | Q5: 4639.0 | R5: 2232.0 | S5: 273.0 | T5: 439.3 | U5: 0.334 | V5: 0.23 | AA5: millions | AB5: NZD
A6: H1-2020 | B6: 483.0 | F6: 134.0 | G6: 27.74327122153209 | H6: 332.0 | I6: 31.0 | J6: 6.418219461697723 | M6: 357.0 | R6: 2876.0 | S6: 678.0 | V6: 0.1 | AA6: millions | AB6: NZD
A7: FY2020 | B7: 959.0 | F7: 246.0 | G7: 25.651720542231494 | H7: 648.0 | I7: 52.0 | J7: 5.422314911366007 | K7: 0.12 | L7: 474.0 | M7: 679.0 | N7: -205.0 | O7: 927.0 | P7: 5642.0 | Q7: 4715.0 | R7: 2322.0 | S7: 0.0 | T7: 444.5 | U7: 0.392 | V7: 0.24 | AA7: millions | AB7: NZD
A8: H1-2021 | B8: 478.0 | F8: 118.0 | G8: 24.7 | H8: 328.0 | I8: 27.0 | J8: 5.6 | M8: 353.0 | R8: 2599.0 | S8: 268.0 | V8: 0.105 | AA8: millions | AB8: NZD
A9: FY2021 | B9: 955.0 | F9: 230.0 | G9: 24.083769633507853 | H9: 657.0 | I9: 51.0 | J9: 5.340314136125655 | K9: 0.11 | L9: 544.0 | M9: 647.0 | N9: -103.0 | O9: 989.0 | P9: 5860.0 | Q9: 4871.0 | R9: 2373.0 | S9: 53.0 | T9: 446.0 | U9: 0.468 | V9: 0.25 | AA9: millions | AB9: NZD
A10: H1-2022 | B10: 483.0 | F10: 132.0 | G10: 27.3 | H10: 347.0 | I10: 42.0 | J10: 8.695652173913043 | M10: 263.0 | R10: 2369.0 | S10: 84.0 | V10: 0.14 | AA10: millions | AB10: NZD | AD10: 332.0
A11: FY2022 | B11: 965.0 | F11: 248.0 | G11: 25.699481865284973 | H11: 675.0 | I11: 64.0 | J11: 6.632124352331606 | K11: 0.14 | L11: 570.0 | M11: 518.0 | N11: 52.0 | O11: 1029.0 | P11: 5846.0 | Q11: 4817.0 | R11: 2322.0 | S11: 88.0 | T11: 446.5 | U11: 0.527 | V11: 0.35 | AA11: millions | AB11: NZD
A12: H1-2023 | B12: 487.0 | F12: 120.0 | G12: 24.6 | H12: 342.0 | I12: 9.0 | J12: 1.8480492813141685 | M12: 222.0 | V12: 0.17 | AA12: millions | AB12: NZD | AD12: 342.0
A13: FY2023 | B13: 980.0 | F13: 226.0 | G13: 23.06122448979592 | H13: 672.0 | I13: 25.0 | J13: 2.5510204081632653 | K13: 0.06 | L13: 524.0 | M13: 495.0 | N13: 29.0 | O13: 1063.0 | P13: 6165.0 | Q13: 5102.0 | R13: 2528.0 | S13: 76.0 | T13: 443.0 | U13: 1.638 | V13: 0.425 | AA13: millions | AB13: NZD
A14: H1-2024 | B14: 503.0 | F14: 119.0 | G14: 23.7 | H14: 347.0 | I14: 5.0 | J14: 0.9940357852882704 | M14: 232.0 | R14: 2709.0 | S14: 87.0 | V14: 0.19 | AA14: millions | AB14: NZD | AD14: 349.0
A15: FY2024 | B15: 1010.0 | F15: 238.0 | G15: 23.564356435643564 | H15: 700.0 | I15: -9.0 | J15: -0.891089108910891 | K15: -0.02 | L15: 513.0 | M15: 442.0 | N15: 71.0 | O15: 841.0 | P15: 6012.0 | Q15: 5171.0 | R15: 2626.0 | S15: 45.0 | T15: 433.9 | U15: 0.0 | V15: 0.475 | AA15: millions | AB15: NZD
A16: H1-2025 | B16: 500.0 | F16: 111.0 | G16: 22.2 | H16: 346.0 | I16: -5.0 | J16: -1.0 | K16: -0.02 | L16: 257.0 | M16: 193.0 | N16: 64.0 | O16: 662.0 | P16: 6054.0 | Q16: 5392.0 | R16: 2887.0 | S16: 83.0 | T16: 435.0 | U16: 1.417 | V16: 0.23 | AA16: millions | AB16: NZD
A17: FY2025 | B17: 1014.0 | F17: 231.0 | G17: 22.781065088757398 | H17: 705.0 | I17: 4.0 | J17: 0.39447731755424065 | K17: 0.01 | L17: 559.0 | M17: 397.0 | N17: 162.0 | O17: 567.0 | P17: 6088.0 | Q17: 5521.0 | R17: 3138.0 | S17: 81.0 | T17: 435.0 | U17: 0.0 | V17: 0.575 | AA17: millions | AB17: NZD
A18: H1-2026 | B18: 506.0 | F18: 141.0 | G18: 27.865612648221344 | H18: 357.0 | I18: 15.0 | J18: 2.9644268774703555 | K18: 0.03 | L18: 228.0 | M18: 163.0 | N18: 65.0 | O18: 430.0 | P18: 6135.0 | Q18: 5705.0 | R18: 3336.0 | S18: 161.0 | T18: 445.0 | U18: 0.354 | V18: 0.24 | AA18: millions | AB18: NZD

Sheet Assumptions
A1: Input | B1: Value
A2: Current price (NZD) | B2: 8.43
A3: Shares outstanding, final (m) | B3: 445
A4: Net debt (NZD m) | B4: 3129
A5: Hurdle rate (%) | B5: 15
A6: FY0 revenue anchor (NZD m, FY2026 actual) | B6: 1024
A7: Currency / units | B7: None millions
A10: BEAR | C10: Y1 | D10: Y2 | E10: Y3 | F10: Y4 | G10: Y5 | H10: Y6 | I10: Y7 | J10: Y8 | K10: Y9 | L10: Y10
A11: Revenue growth (%) | C11: 1.3 | D11: 1.2 | E11: 1.1 | F11: 1.1 | G11: 1 | H11: 1 | I11: 1 | J11: 1 | K11: 1 | L11: 1
A12: EBITDA margin (%) | C12: 69.5 | D12: 69.8 | E12: 69.8 | F12: 69.6 | G12: 69.3 | H12: 69 | I12: 68.8 | J12: 68.8 | K12: 68.8 | L12: 68.8
A13: D&A (% of revenue) | C13: 42.5 | D13: 40.5 | E13: 38 | F13: 35.5 | G13: 34 | H13: 33 | I13: 32.5 | J13: 32 | K13: 32 | L13: 32
A14: Capex (NZD m, absolute) | C14: 405 | D14: 388 | E14: 375 | F14: 361 | G14: 348 | H14: 335 | I14: 325 | J14: 318 | K14: 314 | L14: 312
A15: Cash tax rate (%) | C15: 12 | D15: 16 | E15: 19 | F15: 22 | G15: 24 | H15: 26 | I15: 27 | J15: 28 | K15: 28 | L15: 28
A17: WACC (%) | B17: 8
A18: Terminal growth (%) | B18: 2
A19: Terminal EV/EBITDA cap (x) | B19: 7
A20: Scenario weight | B20: 0.25
A23: BASE | C23: Y1 | D23: Y2 | E23: Y3 | F23: Y4 | G23: Y5 | H23: Y6 | I23: Y7 | J23: Y8 | K23: Y9 | L23: Y10
A24: Revenue growth (%) | C24: 2.6 | D24: 2.6 | E24: 2.5 | F24: 2.5 | G24: 2.4 | H24: 2.4 | I24: 2.3 | J24: 2.3 | K24: 2.3 | L24: 2.3
A25: EBITDA margin (%) | C25: 70.9 | D25: 71.6 | E25: 71.9 | F25: 72.1 | G25: 72.2 | H25: 72.3 | I25: 72.3 | J25: 72.3 | K25: 72.3 | L25: 72.3
A26: D&A (% of revenue) | C26: 40.5 | D26: 38 | E26: 35 | F26: 32.5 | G26: 31 | H26: 30 | I26: 29.5 | J26: 29 | K26: 29 | L26: 29
A27: Capex (NZD m, absolute) | C27: 395 | D27: 370 | E27: 346 | F27: 323 | G27: 301 | H27: 281 | I27: 263 | J27: 251 | K27: 243 | L27: 237
A28: Cash tax rate (%) | C28: 10 | D28: 13 | E28: 16 | F28: 19 | G28: 21 | H28: 23 | I28: 25 | J28: 26 | K28: 27 | L28: 28
A30: WACC (%) | B30: 7
A31: Terminal growth (%) | B31: 2.3
A32: Terminal EV/EBITDA cap (x) | B32: 8
A33: Scenario weight | B33: 0.5
A36: BULL | C36: Y1 | D36: Y2 | E36: Y3 | F36: Y4 | G36: Y5 | H36: Y6 | I36: Y7 | J36: Y8 | K36: Y9 | L36: Y10
A37: Revenue growth (%) | C37: 3.4 | D37: 3.3 | E37: 3.2 | F37: 3.1 | G37: 3 | H37: 2.9 | I37: 2.8 | J37: 2.7 | K37: 2.6 | L37: 2.6
A38: EBITDA margin (%) | C38: 71.5 | D38: 72.3 | E38: 73 | F38: 73.5 | G38: 73.8 | H38: 74 | I38: 74 | J38: 74 | K38: 74 | L38: 74
A39: D&A (% of revenue) | C39: 39.5 | D39: 37 | E39: 34 | F39: 31 | G39: 29.5 | H39: 28 | I39: 27 | J39: 26.5 | K39: 26.5 | L39: 26.5
A40: Capex (NZD m, absolute) | C40: 390 | D40: 360 | E40: 332 | F40: 304 | G40: 278 | H40: 257 | I40: 240 | J40: 230 | K40: 224 | L40: 220
A41: Cash tax rate (%) | C41: 8 | D41: 10 | E41: 13 | F41: 16 | G41: 18 | H41: 20 | I41: 22 | J41: 24 | K41: 26 | L41: 28
A43: WACC (%) | B43: 6.3
A44: Terminal growth (%) | B44: 2.5
A45: Terminal EV/EBITDA cap (x) | B45: 9
A46: Scenario weight | B46: 0.25

Sheet DCF_Bear
A1: Line | B1: Y1 | C1: Y2 | D1: Y3 | E1: Y4 | F1: Y5 | G1: Y6 | H1: Y7 | I1: Y8 | J1: Y9 | K1: Y10
A2: Revenue (NZD m) | B2: =Assumptions!$B$6*(1+Assumptions!$C$11/100) -> 1037.312 | C2: =$B$2*(1+Assumptions!$D$11/100) -> 1049.7597 | D2: =$C$2*(1+Assumptions!$E$11/100) -> 1061.3071 | E2: =$D$2*(1+Assumptions!$F$11/100) -> 1072.9815 | F2: =$E$2*(1+Assumptions!$G$11/100) -> 1083.7113 | G2: =$F$2*(1+Assumptions!$H$11/100) -> 1094.5484 | H2: =$G$2*(1+Assumptions!$I$11/100) -> 1105.4939 | I2: =$H$2*(1+Assumptions!$J$11/100) -> 1116.5488 | J2: =$I$2*(1+Assumptions!$K$11/100) -> 1127.7143 | K2: =$J$2*(1+Assumptions!$L$11/100) -> 1138.9915
A3: EBITDA margin (%) | B3: =Assumptions!$C$12 -> 69.5 | C3: =Assumptions!$D$12 -> 69.8 | D3: =Assumptions!$E$12 -> 69.8 | E3: =Assumptions!$F$12 -> 69.6 | F3: =Assumptions!$G$12 -> 69.3 | G3: =Assumptions!$H$12 -> 69 | H3: =Assumptions!$I$12 -> 68.8 | I3: =Assumptions!$J$12 -> 68.8 | J3: =Assumptions!$K$12 -> 68.8 | K3: =Assumptions!$L$12 -> 68.8
A4: EBITDA (NZD m) | B4: =$B$2*$B$3/100 -> 720.93184 | C4: =$C$2*$C$3/100 -> 732.7323 | D4: =$D$2*$D$3/100 -> 740.79236 | E4: =$E$2*$E$3/100 -> 746.79511 | F4: =$F$2*$F$3/100 -> 751.01193 | G4: =$G$2*$G$3/100 -> 755.2384 | H4: =$H$2*$H$3/100 -> 760.5798 | I4: =$I$2*$I$3/100 -> 768.1856 | J4: =$J$2*$J$3/100 -> 775.86745 | K4: =$K$2*$K$3/100 -> 783.62613
A5: D&A (% of revenue) | B5: =Assumptions!$C$13 -> 42.5 | C5: =Assumptions!$D$13 -> 40.5 | D5: =Assumptions!$E$13 -> 38 | E5: =Assumptions!$F$13 -> 35.5 | F5: =Assumptions!$G$13 -> 34 | G5: =Assumptions!$H$13 -> 33 | H5: =Assumptions!$I$13 -> 32.5 | I5: =Assumptions!$J$13 -> 32 | J5: =Assumptions!$K$13 -> 32 | K5: =Assumptions!$L$13 -> 32
A6: D&A (NZD m) | B6: =$B$2*$B$5/100 -> 440.8576 | C6: =$C$2*$C$5/100 -> 425.1527 | D6: =$D$2*$D$5/100 -> 403.2967 | E6: =$E$2*$E$5/100 -> 380.90843 | F6: =$F$2*$F$5/100 -> 368.46184 | G6: =$G$2*$G$5/100 -> 361.20097 | H6: =$H$2*$H$5/100 -> 359.28551 | I6: =$I$2*$I$5/100 -> 357.29563 | J6: =$J$2*$J$5/100 -> 360.86858 | K6: =$K$2*$K$5/100 -> 364.47727
A7: EBIT (NZD m) | B7: =$B$4-$B$6 -> 280.07424 | C7: =$C$4-$C$6 -> 307.5796 | D7: =$D$4-$D$6 -> 337.49566 | E7: =$E$4-$E$6 -> 365.88668 | F7: =$F$4-$F$6 -> 382.55009 | G7: =$G$4-$G$6 -> 394.03743 | H7: =$H$4-$H$6 -> 401.29428 | I7: =$I$4-$I$6 -> 410.88997 | J7: =$J$4-$J$6 -> 414.99887 | K7: =$K$4-$K$6 -> 419.14886
A8: Cash tax rate (%) | B8: =Assumptions!$C$15 -> 12 | C8: =Assumptions!$D$15 -> 16 | D8: =Assumptions!$E$15 -> 19 | E8: =Assumptions!$F$15 -> 22 | F8: =Assumptions!$G$15 -> 24 | G8: =Assumptions!$H$15 -> 26 | H8: =Assumptions!$I$15 -> 27 | I8: =Assumptions!$J$15 -> 28 | J8: =Assumptions!$K$15 -> 28 | K8: =Assumptions!$L$15 -> 28
A9: NOPAT (NZD m) | B9: =$B$7*(1-$B$8/100) -> 246.46533 | C9: =$C$7*(1-$C$8/100) -> 258.36687 | D9: =$D$7*(1-$D$8/100) -> 273.37148 | E9: =$E$7*(1-$E$8/100) -> 285.39161 | F9: =$F$7*(1-$F$8/100) -> 290.73807 | G9: =$G$7*(1-$G$8/100) -> 291.5877 | H9: =$H$7*(1-$H$8/100) -> 292.94483 | I9: =$I$7*(1-$I$8/100) -> 295.84078 | J9: =$J$7*(1-$J$8/100) -> 298.79919 | K9: =$K$7*(1-$K$8/100) -> 301.78718
A10: Capex (NZD m) | B10: =Assumptions!$C$14 -> 405 | C10: =Assumptions!$D$14 -> 388 | D10: =Assumptions!$E$14 -> 375 | E10: =Assumptions!$F$14 -> 361 | F10: =Assumptions!$G$14 -> 348 | G10: =Assumptions!$H$14 -> 335 | H10: =Assumptions!$I$14 -> 325 | I10: =Assumptions!$J$14 -> 318 | J10: =Assumptions!$K$14 -> 314 | K10: =Assumptions!$L$14 -> 312
A11: SBC (NZD m, 0.15% of revenue) | B11: =$B$2*0.15/100 -> 1.555968 | C11: =$C$2*0.15/100 -> 1.5746396 | D11: =$D$2*0.15/100 -> 1.5919607 | E11: =$E$2*0.15/100 -> 1.6094722 | F11: =$F$2*0.15/100 -> 1.6255669 | G11: =$G$2*0.15/100 -> 1.6418226 | H11: =$H$2*0.15/100 -> 1.6582408 | I11: =$I$2*0.15/100 -> 1.6748232 | J11: =$J$2*0.15/100 -> 1.6915715 | K11: =$K$2*0.15/100 -> 1.7084872
A12: Owner FCF (unlevered, NZD m) | B12: =$B$9+$B$6-$B$10-$B$11 -> 280.76696 | C12: =$C$9+$C$6-$C$10-$C$11 -> 293.94492 | D12: =$D$9+$D$6-$D$10-$D$11 -> 300.07622 | E12: =$E$9+$E$6-$E$10-$E$11 -> 303.69057 | F12: =$F$9+$F$6-$F$10-$F$11 -> 309.57434 | G12: =$G$9+$G$6-$G$10-$G$11 -> 316.14685 | H12: =$H$9+$H$6-$H$10-$H$11 -> 325.5721 | I12: =$I$9+$I$6-$I$10-$I$11 -> 333.46158 | J12: =$J$9+$J$6-$J$10-$J$11 -> 343.9762 | K12: =$K$9+$K$6-$K$10-$K$11 -> 352.55596
A13: Discount factor | B13: =1/(1+Assumptions!$B$17/100)^1 -> 0.92592593 | C13: =1/(1+Assumptions!$B$17/100)^2 -> 0.85733882 | D13: =1/(1+Assumptions!$B$17/100)^3 -> 0.79383224 | E13: =1/(1+Assumptions!$B$17/100)^4 -> 0.73502985 | F13: =1/(1+Assumptions!$B$17/100)^5 -> 0.6805832 | G13: =1/(1+Assumptions!$B$17/100)^6 -> 0.63016963 | H13: =1/(1+Assumptions!$B$17/100)^7 -> 0.5834904 | I13: =1/(1+Assumptions!$B$17/100)^8 -> 0.54026888 | J13: =1/(1+Assumptions!$B$17/100)^9 -> 0.50024897 | K13: =1/(1+Assumptions!$B$17/100)^10 -> 0.46319349
A14: PV of FCF (NZD m) | B14: =$B$12*$B$13 -> 259.96941 | C14: =$C$12*$C$13 -> 252.0104 | D14: =$D$12*$D$13 -> 238.21018 | E14: =$E$12*$E$13 -> 223.22163 | F14: =$F$12*$F$13 -> 210.69109 | G14: =$G$12*$G$13 -> 199.22614 | H14: =$H$12*$H$13 -> 189.96819 | I14: =$I$12*$I$13 -> 180.15892 | J14: =$J$12*$J$13 -> 172.07374 | K14: =$K$12*$K$13 -> 163.30162
A16: Sum PV of interim FCF (NZD m) | B16: =SUM(B14:K14) -> 2088.8313
A17: Gordon terminal value (NZD m) | B17: =$K$12*(1+Assumptions!$B$18/100)/(Assumptions!$B$17/100-Assumptions!$B$18/100) -> 5993.4513
A18: EV/EBITDA cap terminal value (NZD m) | B18: =$K$4*Assumptions!$B$19 -> 5485.3829
A19: Terminal value used (MIN, NZD m) | B19: =MIN(B17,B18) -> 5485.3829
A20: PV of terminal value (NZD m) | B20: =B19*$K$13 -> 2540.7936
A21: Enterprise value (NZD m) | B21: =B16+B20 -> 4629.625
A22: Net debt (NZD m) | B22: =Assumptions!$B$4 -> 3129
A23: Equity value (NZD m) | B23: =B21-B22 -> 1500.625
A24: Shares outstanding (m) | B24: =Assumptions!$B$3 -> 445
A25: Intrinsic value per share (NZD) | B25: =B23/B24 -> 3.3721909
A26: Upside / (downside) vs current price (%) | B26: =(B25/Assumptions!$B$2-1)*100 -> -59.997735

Sheet DCF_Base
A1: Line | B1: Y1 | C1: Y2 | D1: Y3 | E1: Y4 | F1: Y5 | G1: Y6 | H1: Y7 | I1: Y8 | J1: Y9 | K1: Y10
A2: Revenue (NZD m) | B2: =Assumptions!$B$6*(1+Assumptions!$C$24/100) -> 1050.624 | C2: =$B$2*(1+Assumptions!$D$24/100) -> 1077.9402 | D2: =$C$2*(1+Assumptions!$E$24/100) -> 1104.8887 | E2: =$D$2*(1+Assumptions!$F$24/100) -> 1132.5109 | F2: =$E$2*(1+Assumptions!$G$24/100) -> 1159.6912 | G2: =$F$2*(1+Assumptions!$H$24/100) -> 1187.5238 | H2: =$G$2*(1+Assumptions!$I$24/100) -> 1214.8368 | I2: =$H$2*(1+Assumptions!$J$24/100) -> 1242.7781 | J2: =$I$2*(1+Assumptions!$K$24/100) -> 1271.362 | K2: =$J$2*(1+Assumptions!$L$24/100) -> 1300.6033
A3: EBITDA margin (%) | B3: =Assumptions!$C$25 -> 70.9 | C3: =Assumptions!$D$25 -> 71.6 | D3: =Assumptions!$E$25 -> 71.9 | E3: =Assumptions!$F$25 -> 72.1 | F3: =Assumptions!$G$25 -> 72.2 | G3: =Assumptions!$H$25 -> 72.3 | H3: =Assumptions!$I$25 -> 72.3 | I3: =Assumptions!$J$25 -> 72.3 | J3: =Assumptions!$K$25 -> 72.3 | K3: =Assumptions!$L$25 -> 72.3
A4: EBITDA (NZD m) | B4: =$B$2*$B$3/100 -> 744.89242 | C4: =$C$2*$C$3/100 -> 771.8052 | D4: =$D$2*$D$3/100 -> 794.415 | E4: =$E$2*$E$3/100 -> 816.54039 | F4: =$F$2*$F$3/100 -> 837.29705 | G4: =$G$2*$G$3/100 -> 858.57971 | H4: =$H$2*$H$3/100 -> 878.32704 | I4: =$I$2*$I$3/100 -> 898.52856 | J4: =$J$2*$J$3/100 -> 919.19472 | K4: =$K$2*$K$3/100 -> 940.3362
A5: D&A (% of revenue) | B5: =Assumptions!$C$26 -> 40.5 | C5: =Assumptions!$D$26 -> 38 | D5: =Assumptions!$E$26 -> 35 | E5: =Assumptions!$F$26 -> 32.5 | F5: =Assumptions!$G$26 -> 31 | G5: =Assumptions!$H$26 -> 30 | H5: =Assumptions!$I$26 -> 29.5 | I5: =Assumptions!$J$26 -> 29 | J5: =Assumptions!$K$26 -> 29 | K5: =Assumptions!$L$26 -> 29
A6: D&A (NZD m) | B6: =$B$2*$B$5/100 -> 425.50272 | C6: =$C$2*$C$5/100 -> 409.61729 | D6: =$D$2*$D$5/100 -> 386.71106 | E6: =$E$2*$E$5/100 -> 368.06606 | F6: =$F$2*$F$5/100 -> 359.50428 | G6: =$G$2*$G$5/100 -> 356.25714 | H6: =$H$2*$H$5/100 -> 358.37687 | I6: =$I$2*$I$5/100 -> 360.40565 | J6: =$J$2*$J$5/100 -> 368.69498 | K6: =$K$2*$K$5/100 -> 377.17496
A7: EBIT (NZD m) | B7: =$B$4-$B$6 -> 319.3897 | C7: =$C$4-$C$6 -> 362.18792 | D7: =$D$4-$D$6 -> 407.70394 | E7: =$E$4-$E$6 -> 448.47434 | F7: =$F$4-$F$6 -> 477.79278 | G7: =$G$4-$G$6 -> 502.32257 | H7: =$H$4-$H$6 -> 519.95017 | I7: =$I$4-$I$6 -> 538.12291 | J7: =$J$4-$J$6 -> 550.49974 | K7: =$K$4-$K$6 -> 563.16124
A8: Cash tax rate (%) | B8: =Assumptions!$C$28 -> 10 | C8: =Assumptions!$D$28 -> 13 | D8: =Assumptions!$E$28 -> 16 | E8: =Assumptions!$F$28 -> 19 | F8: =Assumptions!$G$28 -> 21 | G8: =Assumptions!$H$28 -> 23 | H8: =Assumptions!$I$28 -> 25 | I8: =Assumptions!$J$28 -> 26 | J8: =Assumptions!$K$28 -> 27 | K8: =Assumptions!$L$28 -> 28
A9: NOPAT (NZD m) | B9: =$B$7*(1-$B$8/100) -> 287.45073 | C9: =$C$7*(1-$C$8/100) -> 315.10349 | D9: =$D$7*(1-$D$8/100) -> 342.47131 | E9: =$E$7*(1-$E$8/100) -> 363.26421 | F9: =$F$7*(1-$F$8/100) -> 377.4563 | G9: =$G$7*(1-$G$8/100) -> 386.78838 | H9: =$H$7*(1-$H$8/100) -> 389.96263 | I9: =$I$7*(1-$I$8/100) -> 398.21096 | J9: =$J$7*(1-$J$8/100) -> 401.86481 | K9: =$K$7*(1-$K$8/100) -> 405.47609
A10: Capex (NZD m) | B10: =Assumptions!$C$27 -> 395 | C10: =Assumptions!$D$27 -> 370 | D10: =Assumptions!$E$27 -> 346 | E10: =Assumptions!$F$27 -> 323 | F10: =Assumptions!$G$27 -> 301 | G10: =Assumptions!$H$27 -> 281 | H10: =Assumptions!$I$27 -> 263 | I10: =Assumptions!$J$27 -> 251 | J10: =Assumptions!$K$27 -> 243 | K10: =Assumptions!$L$27 -> 237
A11: SBC (NZD m, 0.15% of revenue) | B11: =$B$2*0.15/100 -> 1.575936 | C11: =$C$2*0.15/100 -> 1.6169103 | D11: =$D$2*0.15/100 -> 1.6573331 | E11: =$E$2*0.15/100 -> 1.6987664 | F11: =$F$2*0.15/100 -> 1.7395368 | G11: =$G$2*0.15/100 -> 1.7812857 | H11: =$H$2*0.15/100 -> 1.8222553 | I11: =$I$2*0.15/100 -> 1.8641671 | J11: =$J$2*0.15/100 -> 1.907043 | K11: =$K$2*0.15/100 -> 1.950905
A12: Owner FCF (unlevered, NZD m) | B12: =$B$9+$B$6-$B$10-$B$11 -> 316.37751 | C12: =$C$9+$C$6-$C$10-$C$11 -> 353.10386 | D12: =$D$9+$D$6-$D$10-$D$11 -> 381.52503 | E12: =$E$9+$E$6-$E$10-$E$11 -> 406.6315 | F12: =$F$9+$F$6-$F$10-$F$11 -> 434.22103 | G12: =$G$9+$G$6-$G$10-$G$11 -> 460.26423 | H12: =$H$9+$H$6-$H$10-$H$11 -> 483.51724 | I12: =$I$9+$I$6-$I$10-$I$11 -> 505.75244 | J12: =$J$9+$J$6-$J$10-$J$11 -> 525.65275 | K12: =$K$9+$K$6-$K$10-$K$11 -> 543.70015
A13: Discount factor | B13: =1/(1+Assumptions!$B$30/100)^1 -> 0.93457944 | C13: =1/(1+Assumptions!$B$30/100)^2 -> 0.87343873 | D13: =1/(1+Assumptions!$B$30/100)^3 -> 0.81629788 | E13: =1/(1+Assumptions!$B$30/100)^4 -> 0.76289521 | F13: =1/(1+Assumptions!$B$30/100)^5 -> 0.71298618 | G13: =1/(1+Assumptions!$B$30/100)^6 -> 0.66634222 | H13: =1/(1+Assumptions!$B$30/100)^7 -> 0.62274974 | I13: =1/(1+Assumptions!$B$30/100)^8 -> 0.5820091 | J13: =1/(1+Assumptions!$B$30/100)^9 -> 0.54393374 | K13: =1/(1+Assumptions!$B$30/100)^10 -> 0.50834929
A14: PV of FCF (NZD m) | B14: =$B$12*$B$13 -> 295.67992 | C14: =$C$12*$C$13 -> 308.41459 | D14: =$D$12*$D$13 -> 311.43807 | E14: =$E$12*$E$13 -> 310.21723 | F14: =$F$12*$F$13 -> 309.5936 | G14: =$G$12*$G$13 -> 306.69349 | H14: =$H$12*$H$13 -> 301.11024 | I14: =$I$12*$I$13 -> 294.35252 | J14: =$J$12*$J$13 -> 285.92027 | K14: =$K$12*$K$13 -> 276.38958
A16: Sum PV of interim FCF (NZD m) | B16: =SUM(B14:K14) -> 2999.8095
A17: Gordon terminal value (NZD m) | B17: =$K$12*(1+Assumptions!$B$31/100)/(Assumptions!$B$30/100-Assumptions!$B$31/100) -> 11834.154
A18: EV/EBITDA cap terminal value (NZD m) | B18: =$K$4*Assumptions!$B$32 -> 7522.6896
A19: Terminal value used (MIN, NZD m) | B19: =MIN(B17,B18) -> 7522.6896
A20: PV of terminal value (NZD m) | B20: =B19*$K$13 -> 3824.1539
A21: Enterprise value (NZD m) | B21: =B16+B20 -> 6823.9634
A22: Net debt (NZD m) | B22: =Assumptions!$B$4 -> 3129
A23: Equity value (NZD m) | B23: =B21-B22 -> 3694.9634
A24: Shares outstanding (m) | B24: =Assumptions!$B$3 -> 445
A25: Intrinsic value per share (NZD) | B25: =B23/B24 -> 8.3032886
A26: Upside / (downside) vs current price (%) | B26: =(B25/Assumptions!$B$2-1)*100 -> -1.5031008

Sheet DCF_Bull
A1: Line | B1: Y1 | C1: Y2 | D1: Y3 | E1: Y4 | F1: Y5 | G1: Y6 | H1: Y7 | I1: Y8 | J1: Y9 | K1: Y10
A2: Revenue (NZD m) | B2: =Assumptions!$B$6*(1+Assumptions!$C$37/100) -> 1058.816 | C2: =$B$2*(1+Assumptions!$D$37/100) -> 1093.7569 | D2: =$C$2*(1+Assumptions!$E$37/100) -> 1128.7571 | E2: =$D$2*(1+Assumptions!$F$37/100) -> 1163.7486 | F2: =$E$2*(1+Assumptions!$G$37/100) -> 1198.6611 | G2: =$F$2*(1+Assumptions!$H$37/100) -> 1233.4223 | H2: =$G$2*(1+Assumptions!$I$37/100) -> 1267.9581 | I2: =$H$2*(1+Assumptions!$J$37/100) -> 1302.1929 | J2: =$I$2*(1+Assumptions!$K$37/100) -> 1336.05 | K2: =$J$2*(1+Assumptions!$L$37/100) -> 1370.7873
A3: EBITDA margin (%) | B3: =Assumptions!$C$38 -> 71.5 | C3: =Assumptions!$D$38 -> 72.3 | D3: =Assumptions!$E$38 -> 73 | E3: =Assumptions!$F$38 -> 73.5 | F3: =Assumptions!$G$38 -> 73.8 | G3: =Assumptions!$H$38 -> 74 | H3: =Assumptions!$I$38 -> 74 | I3: =Assumptions!$J$38 -> 74 | J3: =Assumptions!$K$38 -> 74 | K3: =Assumptions!$L$38 -> 74
A4: EBITDA (NZD m) | B4: =$B$2*$B$3/100 -> 757.05344 | C4: =$C$2*$C$3/100 -> 790.78626 | D4: =$D$2*$D$3/100 -> 823.99272 | E4: =$E$2*$E$3/100 -> 855.35524 | F4: =$F$2*$F$3/100 -> 884.61188 | G4: =$G$2*$G$3/100 -> 912.73247 | H4: =$H$2*$H$3/100 -> 938.28898 | I4: =$I$2*$I$3/100 -> 963.62278 | J4: =$J$2*$J$3/100 -> 988.67697 | K4: =$K$2*$K$3/100 -> 1014.3826
A5: D&A (% of revenue) | B5: =Assumptions!$C$39 -> 39.5 | C5: =Assumptions!$D$39 -> 37 | D5: =Assumptions!$E$39 -> 34 | E5: =Assumptions!$F$39 -> 31 | F5: =Assumptions!$G$39 -> 29.5 | G5: =Assumptions!$H$39 -> 28 | H5: =Assumptions!$I$39 -> 27 | I5: =Assumptions!$J$39 -> 26.5 | J5: =Assumptions!$K$39 -> 26.5 | K5: =Assumptions!$L$39 -> 26.5
A6: D&A (NZD m) | B6: =$B$2*$B$5/100 -> 418.23232 | C6: =$C$2*$C$5/100 -> 404.69006 | D6: =$D$2*$D$5/100 -> 383.77743 | E6: =$E$2*$E$5/100 -> 360.76207 | F6: =$F$2*$F$5/100 -> 353.60502 | G6: =$G$2*$G$5/100 -> 345.35823 | H6: =$H$2*$H$5/100 -> 342.34868 | I6: =$I$2*$I$5/100 -> 345.08113 | J6: =$J$2*$J$5/100 -> 354.05324 | K6: =$K$2*$K$5/100 -> 363.25862
A7: EBIT (NZD m) | B7: =$B$4-$B$6 -> 338.82112 | C7: =$C$4-$C$6 -> 386.0962 | D7: =$D$4-$D$6 -> 440.21529 | E7: =$E$4-$E$6 -> 494.59316 | F7: =$F$4-$F$6 -> 531.00686 | G7: =$G$4-$G$6 -> 567.37424 | H7: =$H$4-$H$6 -> 595.94029 | I7: =$I$4-$I$6 -> 618.54165 | J7: =$J$4-$J$6 -> 634.62373 | K7: =$K$4-$K$6 -> 651.12395
A8: Cash tax rate (%) | B8: =Assumptions!$C$41 -> 8 | C8: =Assumptions!$D$41 -> 10 | D8: =Assumptions!$E$41 -> 13 | E8: =Assumptions!$F$41 -> 16 | F8: =Assumptions!$G$41 -> 18 | G8: =Assumptions!$H$41 -> 20 | H8: =Assumptions!$I$41 -> 22 | I8: =Assumptions!$J$41 -> 24 | J8: =Assumptions!$K$41 -> 26 | K8: =Assumptions!$L$41 -> 28
A9: NOPAT (NZD m) | B9: =$B$7*(1-$B$8/100) -> 311.71543 | C9: =$C$7*(1-$C$8/100) -> 347.48658 | D9: =$D$7*(1-$D$8/100) -> 382.9873 | E9: =$E$7*(1-$E$8/100) -> 415.45826 | F9: =$F$7*(1-$F$8/100) -> 435.42562 | G9: =$G$7*(1-$G$8/100) -> 453.89939 | H9: =$H$7*(1-$H$8/100) -> 464.83343 | I9: =$I$7*(1-$I$8/100) -> 470.09165 | J9: =$J$7*(1-$J$8/100) -> 469.62156 | K9: =$K$7*(1-$K$8/100) -> 468.80924
A10: Capex (NZD m) | B10: =Assumptions!$C$40 -> 390 | C10: =Assumptions!$D$40 -> 360 | D10: =Assumptions!$E$40 -> 332 | E10: =Assumptions!$F$40 -> 304 | F10: =Assumptions!$G$40 -> 278 | G10: =Assumptions!$H$40 -> 257 | H10: =Assumptions!$I$40 -> 240 | I10: =Assumptions!$J$40 -> 230 | J10: =Assumptions!$K$40 -> 224 | K10: =Assumptions!$L$40 -> 220
A11: SBC (NZD m, 0.15% of revenue) | B11: =$B$2*0.15/100 -> 1.588224 | C11: =$C$2*0.15/100 -> 1.6406354 | D11: =$D$2*0.15/100 -> 1.6931357 | E11: =$E$2*0.15/100 -> 1.7456229 | F11: =$F$2*0.15/100 -> 1.7979916 | G11: =$G$2*0.15/100 -> 1.8501334 | H11: =$H$2*0.15/100 -> 1.9019371 | I11: =$I$2*0.15/100 -> 1.9532894 | J11: =$J$2*0.15/100 -> 2.0040749 | K11: =$K$2*0.15/100 -> 2.0561809
A12: Owner FCF (unlevered, NZD m) | B12: =$B$9+$B$6-$B$10-$B$11 -> 338.35953 | C12: =$C$9+$C$6-$C$10-$C$11 -> 390.536 | D12: =$D$9+$D$6-$D$10-$D$11 -> 433.0716 | E12: =$E$9+$E$6-$E$10-$E$11 -> 470.47471 | F12: =$F$9+$F$6-$F$10-$F$11 -> 509.23265 | G12: =$G$9+$G$6-$G$10-$G$11 -> 540.40749 | H12: =$H$9+$H$6-$H$10-$H$11 -> 565.28017 | I12: =$I$9+$I$6-$I$10-$I$11 -> 583.21949 | J12: =$J$9+$J$6-$J$10-$J$11 -> 597.67072 | K12: =$K$9+$K$6-$K$10-$K$11 -> 610.01168
A13: Discount factor | B13: =1/(1+Assumptions!$B$43/100)^1 -> 0.94073377 | C13: =1/(1+Assumptions!$B$43/100)^2 -> 0.88498003 | D13: =1/(1+Assumptions!$B$43/100)^3 -> 0.8325306 | E13: =1/(1+Assumptions!$B$43/100)^4 -> 0.78318965 | F13: =1/(1+Assumptions!$B$43/100)^5 -> 0.73677296 | G13: =1/(1+Assumptions!$B$43/100)^6 -> 0.6931072 | H13: =1/(1+Assumptions!$B$43/100)^7 -> 0.65202935 | I13: =1/(1+Assumptions!$B$43/100)^8 -> 0.61338603 | J13: =1/(1+Assumptions!$B$43/100)^9 -> 0.57703296 | K13: =1/(1+Assumptions!$B$43/100)^10 -> 0.54283439
A14: PV of FCF (NZD m) | B14: =$B$12*$B$13 -> 318.30623 | C14: =$C$12*$C$13 -> 345.61656 | D14: =$D$12*$D$13 -> 360.54536 | E14: =$E$12*$E$13 -> 368.47092 | F14: =$F$12*$F$13 -> 375.18885 | G14: =$G$12*$G$13 -> 374.56032 | H14: =$H$12*$H$13 -> 368.57927 | I14: =$I$12*$I$13 -> 357.73869 | J14: =$J$12*$J$13 -> 344.87571 | K14: =$K$12*$K$13 -> 331.13532
A16: Sum PV of interim FCF (NZD m) | B16: =SUM(B14:K14) -> 3545.0172
A17: Gordon terminal value (NZD m) | B17: =$K$12*(1+Assumptions!$B$44/100)/(Assumptions!$B$43/100-Assumptions!$B$44/100) -> 16454.263
A18: EV/EBITDA cap terminal value (NZD m) | B18: =$K$4*Assumptions!$B$45 -> 9129.4431
A19: Terminal value used (MIN, NZD m) | B19: =MIN(B17,B18) -> 9129.4431
A20: PV of terminal value (NZD m) | B20: =B19*$K$13 -> 4955.7757
A21: Enterprise value (NZD m) | B21: =B16+B20 -> 8500.7929
A22: Net debt (NZD m) | B22: =Assumptions!$B$4 -> 3129
A23: Equity value (NZD m) | B23: =B21-B22 -> 5371.7929
A24: Shares outstanding (m) | B24: =Assumptions!$B$3 -> 445
A25: Intrinsic value per share (NZD) | B25: =B23/B24 -> 12.071445
A26: Upside / (downside) vs current price (%) | B26: =(B25/Assumptions!$B$2-1)*100 -> 43.196261

Sheet Valuation
A1: Probability-weighted valuation
A3: Scenario | B3: Weight | C3: Intrinsic value (NZD) | D3: Weighted contribution
A4: BEAR | B4: =Assumptions!$B$20 -> 0.25 | C4: =DCF_Bear!$B$25 -> 3.3721909 | D4: =B4*C4 -> 0.84304772
A5: BASE | B5: =Assumptions!$B$33 -> 0.5 | C5: =DCF_Base!$B$25 -> 8.3032886 | D5: =B5*C5 -> 4.1516443
A6: BULL | B6: =Assumptions!$B$46 -> 0.25 | C6: =DCF_Bull!$B$25 -> 12.071445 | D6: =B6*C6 -> 3.0178612
A7: Weighted intrinsic value (NZD) | B7: =SUM(D4:D6) -> 8.0125532
A8: Current price (NZD) | B8: =Assumptions!$B$2 -> 8.43
A9: Weighted upside / (downside) (%) | B9: =(B7/B8-1)*100 -> -4.951919
A11: Entry price @ 15% hurdle (NZD, memo -- see interpretation) | B11: 1.8
A12: Interpretation | B12: The 15%-IRR entry price of ~$1.80 sits far below both intrinsic value ($8.30) and the current price ($8.43). This is the mechanically correct output, not a formula error: Chorus's projected growth (2.3-2.6%/yr) is far below the 15% hurdle, AND net debt (~$3,129m, a FIXED dollar amount) is ~83% of the current $3.75bn market cap. When cash flows and terminal value are discounted at 15% instead of the 7% WACC, enterprise value shrinks sharply while the fixed net-debt deduction does not -- crushing the thin equity residual. PRACTICALLY: Chorus is not a stock that can be bought today to manufacture a 15% IRR from fundamentals alone -- it is priced (and should be evaluated) as a ~7.4% dividend-yield regulated-utility income holding (FY2027 guided minimum 62cps / $8.43), where the relevant comparison is the WACC-based intrinsic value and the dividend yield, not a growth-IRR entry price. Unchanged conclusion from the prior build.
A14: Sensitivity: WACC (rows) x Terminal growth (cols)
A15: WACC \ g | B15: 1.3 | C15: 1.8 | D15: 2.3 | E15: 2.8 | F15: 3.3
A16: 5 | B16: 10.82 | C16: 10.82 | D16: 10.82 | E16: 10.82 | F16: 10.82
A17: 6 | B17: 9.5 | C17: 9.5 | D17: 9.5 | E17: 9.5 | F17: 9.5
A18: 7 | B18: 8.3 | C18: 8.3 | D18: 8.3 | E18: 8.3 | F18: 8.3
A19: 8 | B19: 7.21 | C19: 7.21 | D19: 7.21 | E19: 7.21 | F19: 7.21
A20: 9 | B20: 5.86 | C20: 6.21 | D20: 6.21 | E20: 6.21 | F20: 6.21
A22: Rows are near-flat across terminal growth because the 8.0x EV/EBITDA cap (not Gordon growth) binds the terminal value at every WACC/g combination shown. The real sensitivity is to WACC: intrinsic value ranges from ~$10.82/share at 5% WACC down to ~$5.9-6.2/share at 9% WACC -- an ~80% swing in equity value for a 4-point WACC range, roughly double the swing a similarly-profiled unlevered company would show, the direct consequence of Chorus's leverage (net debt ~83% of market cap). This is the single most important sensitivity in this model and should be surfaced prominently on the dashboard.
