Workbook

Sheet Executive Summary
A1: ACCENTURE PLC (NYSE: ACN) - DCF VALUATION MODEL
A2: As of December 8, 2025
A4: COMPANY OVERVIEW
A5: Sector: | B5: Information Technology Services
A6: Industry: | B6: IT Consulting & Professional Services
A7: Headquarters: | B7: Dublin, Ireland
A8: Employees: | B8: ~800,000
A9: Fiscal Year End: | B9: August 31
A11: KEY FINANCIAL METRICS (FY2025)
A12: Revenue ($B): | B12: 69.67
A13: Net Income ($B): | B13: 7.678
A14: Free Cash Flow ($B): | B14: 9.5
A15: Operating Margin (Adj): | B15: 0.156
A16: Net Margin: | B16: =B13/B12 -> 0.11020525
A18: MARKET DATA
A19: Current Stock Price: | B19: 266.59
A20: Shares Outstanding (M): | B20: 622.6
A21: Market Cap ($B): | B21: =B19*B20/1000 -> 165.97893
A22: 52-Week Range: | B22: $229.40 - $398.35
A23: Dividend Yield: | B23: 0.0245
A25: VALUATION SUMMARY
A26: DCF Fair Value (per share): | B26: =DCF!B45 -> 337.14389
A27: Current Price: | B27: =B19 -> 266.59
A28: Upside/(Downside): | B28: =(B26-B27)/B27 -> 0.26465317
A30: TRADING MULTIPLES
A31: P/E (TTM): | B31: =B19/(B13*1000/B20) -> 21.61747
A32: P/FCF: | B32: =B21/B14 -> 17.471467
A33: EV/EBITDA (Est.): | B33: 13.3

Sheet DCF
A1: DCF VALUATION - ACCENTURE PLC (ACN)
A3: KEY ASSUMPTIONS
A4: Risk-Free Rate | B4: 0.042 | C4: 10-Year US Treasury
A5: Market Risk Premium | B5: 0.055 | C5: Historical equity premium
A6: Beta (Levered) | B6: 1.05 | C6: 5-year monthly regression
A7: Cost of Equity | B7: =B4+B5*B6 -> 0.09975 | C7: CAPM formula
A8: Cost of Debt (Pre-tax) | B8: 0.045 | C8: Corporate bond yield
A9: Tax Rate | B9: 0.235 | C9: FY2025 effective rate
A10: After-Tax Cost of Debt | B10: =B8*(1-B9) -> 0.034425
A11: Weight of Equity | B11: 0.97 | C11: Market value weights
A12: Weight of Debt | B12: 0.03 | C12: Market value weights
A13: WACC | B13: =B7*B11+B10*B12 -> 0.09779025 | C13: Weighted Average
A16: GROWTH ASSUMPTIONS
A17: Base Year FCF ($B) | B17: 9.5 | C17: FY2025 Actual
A18: Year 1-2 Growth Rate | B18: 0.1 | C18: Historical FCF growth ~11%
A19: Year 3-5 Growth Rate | B19: 0.08 | C19: Revenue growth trend ~8.5%
A20: Year 6-10 Growth Rate | B20: 0.06 | C20: Maturing but strong
A21: Terminal Growth Rate | B21: 0.03 | C21: Premium to GDP
A24: FREE CASH FLOW PROJECTIONS ($B)
B25: FY2025 | C25: FY2026 | D25: FY2027 | E25: FY2028 | F25: FY2029 | G25: FY2030 | H25: FY2031 | I25: FY2032 | J25: FY2033 | K25: FY2034 | L25: FY2035 | M25: Terminal
A26: Year | B26: 0 | C26: 1 | D26: 2 | E26: 3 | F26: 4 | G26: 5 | H26: 6 | I26: 7 | J26: 8 | K26: 9 | L26: 10 | M26: 11
A27: Growth Rate | B27: - | C27: =$B$18 -> 0.1 | D27: =$B$18 -> 0.1 | E27: =$B$19 -> 0.08 | F27: =$B$19 -> 0.08 | G27: =$B$19 -> 0.08 | H27: =$B$20 -> 0.06 | I27: =$B$20 -> 0.06 | J27: =$B$20 -> 0.06 | K27: =$B$20 -> 0.06 | L27: =$B$20 -> 0.06 | M27: =$B$21 -> 0.03
A28: Free Cash Flow | B28: =$B$17 -> 9.5 | C28: =B28*(1+C27) -> 10.45 | D28: =C28*(1+D27) -> 11.495 | E28: =D28*(1+E27) -> 12.4146 | F28: =E28*(1+F27) -> 13.407768 | G28: =F28*(1+G27) -> 14.480389 | H28: =G28*(1+H27) -> 15.349213 | I28: =H28*(1+I27) -> 16.270166 | J28: =I28*(1+J27) -> 17.246376 | ... L28: =K28*(1+L27) -> 19.378028
A29: Discount Factor | B29: 1 | C29: =1/(1+$B$13)^C26 -> 0.91092082 | D29: =1/(1+$B$13)^D26 -> 0.82977675 | E29: =1/(1+$B$13)^E26 -> 0.75586092 | F29: =1/(1+$B$13)^F26 -> 0.68852945 | G29: =1/(1+$B$13)^G26 -> 0.62719582 | H29: =1/(1+$B$13)^H26 -> 0.57132573 | I29: =1/(1+$B$13)^I26 -> 0.52043251 | J29: =1/(1+$B$13)^J26 -> 0.47407281 | ... L29: =1/(1+$B$13)^L26 -> 0.39337459
A30: PV of FCF | B30: - | C30: =C28*C29 -> 9.5191226 | D30: =D28*D29 -> 9.5382837 | E30: =E28*E29 -> 9.383711 | F30: =F28*F29 -> 9.2316432 | G30: =G28*G29 -> 9.0820397 | H30: =H28*H29 -> 8.7694002 | I30: =I28*I29 -> 8.4675231 | J30: =J28*J29 -> 8.1760377 | ... L30: =L28*L29 -> 7.6228237
A33: TERMINAL VALUE CALCULATION
A34: Terminal Year FCF ($B) | B34: =L28*(1+$B$21) -> 19.959368
A35: Terminal Value ($B) | B35: =B34/($B$13-$B$21) -> 294.4283 | C35: Gordon Growth Model
A36: PV of Terminal Value ($B) | B36: =B35*L29 -> 115.82061
A39: VALUATION SUMMARY
A40: Sum of PV of FCFs ($B) | B40: =SUM(C30:L30) -> 87.685171
A41: PV of Terminal Value ($B) | B41: =B36 -> 115.82061
A42: Enterprise Value ($B) | B42: =B40+B41 -> 203.50579
A43: Less: Net Debt ($B) | B43: -6.4 | C43: Net cash position (Cash - Debt)
A44: Equity Value ($B) | B44: =B42-B43 -> 209.90579
A45: Fair Value per Share | B45: =B44*1000/'Executive Summary'!B20 -> 337.14389
A47: Current Price | B47: ='Executive Summary'!B19 -> 266.59
A48: Upside/(Downside) | B48: =(B45-B47)/B47 -> 0.26465317

Sheet Sensitivity
A1: SENSITIVITY ANALYSIS - FAIR VALUE PER SHARE
A3: WACC vs Terminal Growth Rate
B4: Terminal Growth Rate
A5: WACC | C5: 0.02 | D5: 0.025 | E5: 0.03 | F5: 0.035 | G5: 0.04
B6: 0.07 | C6: =((DCF!$B$17*(1+DCF!$B$18)/(1+0.07)^1)+(DCF!$B$17*(1+DCF!$B$18)^2/(1+0.07)^2)+(DCF!$B$17*(1+DCF!$B$18)^2*(1+DCF!$B$19)/(1+0.07)^3)+(DCF!$B$17*(1+DCF!$B$18)^2*(1+DCF!$B$19)^2/(1+0.07)^4)+(DCF!$B$17*(1+DCF!$B$18)^2*(1+DCF!$B$19)^3/(1+0.07)^5)+(DCF!$B$17*(1+DCF!$B$18)^2*(1+DCF!$B$19)^3*(1+DCF!$B$20)/(1+0.07)^6)+(DCF!$B$17*(1+DCF!$B$18)^2*(1+DCF!$B$19)^3*(1+DCF!$B$20)^2/(1+0.07)^7)+(DCF!$B$17*(1+DCF!$B$18)^2*(1+DCF!$B$19)^3*(1+DCF!$B$20)^3/(1+0.07)^8)+(DCF!$B$17*(1+DCF!$B$18)^2*(1+DCF!$B$19)^3*(1+DCF!$B$20)^4/(1+0.07)^9)+(DCF!$B$17*(1+DCF!$B$18)^2*(1+DCF!$B$19)^3*(1+DCF!$B$20)^5/(1+0.07)^10)+((DCF!$B$17*(1+DCF!$B$18)^2*(1+DCF!$B$19)^3*(1+DCF!$B$20)^5*(1+0.02)/(0.07-0.02))/(1+0.07)^10)-DCF!$B$43)*1000/'Executive Summary'!$B$20 -> 494.76743 | D6: =((DCF!$B$17*(1+DCF!$B$18)/(1+0.07)^1)+(DCF!$B$17*(1+DCF!$B$18)^2/(1+0.07)^2)+(DCF!$B$17*(1+DCF!$B$18)^2*(1+DCF!$B$19)/(1+0.07)^3)+(DCF!$B$17*(1+DCF!$B$18)^2*(1+DCF!$B$19)^2/(1+0.07)^4)+(DCF!$B$17*(1+DCF!$B$18)^2*(1+DCF!$B$19)^3/(1+0.07)^5)+(DCF!$B$17*(1+DCF!$B$18)^2*(1+DCF!$B$19)^3*(1+DCF!$B$20)/(1+0.07)^6)+(DCF!$B$17*(1+DCF!$B$18)^2*(1+DCF!$B$19)^3*(1+DCF!$B$20)^2/(1+0.07)^7)+(DCF!$B$17*(1+DCF!$B$18)^2*(1+DCF!$B$19)^3*(1+DCF!$B$20)^3/(1+0.07)^8)+(DCF!$B$17*(1+DCF!$B$18)^2*(1+DCF!$B$19)^3*(1+DCF!$B$20)^4/(1+0.07)^9)+(DCF!$B$17*(1+DCF!$B$18)^2*(1+DCF!$B$19)^3*(1+DCF!$B$20)^5/(1+0.07)^10)+((DCF!$B$17*(1+DCF!$B$18)^2*(1+DCF!$B$19)^3*(1+DCF!$B$20)^5*(1+0.025)/(0.07-0.025))/(1+0.07)^10)-DCF!$B$43)*1000/'Executive Summary'!$B$20 -> 532.38874 | E6: =((DCF!$B$17*(1+DCF!$B$18)/(1+0.07)^1)+(DCF!$B$17*(1+DCF!$B$18)^2/(1+0.07)^2)+(DCF!$B$17*(1+DCF!$B$18)^2*(1+DCF!$B$19)/(1+0.07)^3)+(DCF!$B$17*(1+DCF!$B$18)^2*(1+DCF!$B$19)^2/(1+0.07)^4)+(DCF!$B$17*(1+DCF!$B$18)^2*(1+DCF!$B$19)^3/(1+0.07)^5)+(DCF!$B$17*(1+DCF!$B$18)^2*(1+DCF!$B$19)^3*(1+DCF!$B$20)/(1+0.07)^6)+(DCF!$B$17*(1+DCF!$B$18)^2*(1+DCF!$B$19)^3*(1+DCF!$B$20)^2/(1+0.07)^7)+(DCF!$B$17*(1+DCF!$B$18)^2*(1+DCF!$B$19)^3*(1+DCF!$B$20)^3/(1+0.07)^8)+(DCF!$B$17*(1+DCF!$B$18)^2*(1+DCF!$B$19)^3*(1+DCF!$B$20)^4/(1+0.07)^9)+(DCF!$B$17*(1+DCF!$B$18)^2*(1+DCF!$B$19)^3*(1+DCF!$B$20)^5/(1+0.07)^10)+((DCF!$B$17*(1+DCF!$B$18)^2*(1+DCF!$B$19)^3*(1+DCF!$B$20)^5*(1+0.03)/(0.07-0.03))/(1+0.07)^10)-DCF!$B$43)*1000/'Executive Summary'!$B$20 -> 579.41538 | F6: =((DCF!$B$17*(1+DCF!$B$18)/(1+0.07)^1)+(DCF!$B$17*(1+DCF!$B$18)^2/(1+0.07)^2)+(DCF!$B$17*(1+DCF!$B$18)^2*(1+DCF!$B$19)/(1+0.07)^3)+(DCF!$B$17*(1+DCF!$B$18)^2*(1+DCF!$B$19)^2/(1+0.07)^4)+(DCF!$B$17*(1+DCF!$B$18)^2*(1+DCF!$B$19)^3/(1+0.07)^5)+(DCF!$B$17*(1+DCF!$B$18)^2*(1+DCF!$B$19)^3*(1+DCF!$B$20)/(1+0.07)^6)+(DCF!$B$17*(1+DCF!$B$18)^2*(1+DCF!$B$19)^3*(1+DCF!$B$20)^2/(1+0.07)^7)+(DCF!$B$17*(1+DCF!$B$18)^2*(1+DCF!$B$19)^3*(1+DCF!$B$20)^3/(1+0.07)^8)+(DCF!$B$17*(1+DCF!$B$18)^2*(1+DCF!$B$19)^3*(1+DCF!$B$20)^4/(1+0.07)^9)+(DCF!$B$17*(1+DCF!$B$18)^2*(1+DCF!$B$19)^3*(1+DCF!$B$20)^5/(1+0.07)^10)+((DCF!$B$17*(1+DCF!$B$18)^2*(1+DCF!$B$19)^3*(1+DCF!$B$20)^5*(1+0.035)/(0.07-0.035))/(1+0.07)^10)-DCF!$B$43)*1000/'Executive Summary'!$B$20 -> 639.8782 | G6: =((DCF!$B$17*(1+DCF!$B$18)/(1+0.07)^1)+(DCF!$B$17*(1+DCF!$B$18)^2/(1+0.07)^2)+(DCF!$B$17*(1+DCF!$B$18)^2*(1+DCF!$B$19)/(1+0.07)^3)+(DCF!$B$17*(1+DCF!$B$18)^2*(1+DCF!$B$19)^2/(1+0.07)^4)+(DCF!$B$17*(1+DCF!$B$18)^2*(1+DCF!$B$19)^3/(1+0.07)^5)+(DCF!$B$17*(1+DCF!$B$18)^2*(1+DCF!$B$19)^3*(1+DCF!$B$20)/(1+0.07)^6)+(DCF!$B$17*(1+DCF!$B$18)^2*(1+DCF!$B$19)^3*(1+DCF!$B$20)^2/(1+0.07)^7)+(DCF!$B$17*(1+DCF!$B$18)^2*(1+DCF!$B$19)^3*(1+DCF!$B$20)^3/(1+0.07)^8)+(DCF!$B$17*(1+DCF!$B$18)^2*(1+DCF!$B$19)^3*(1+DCF!$B$20)^4/(1+0.07)^9)+(DCF!$B$17*(1+DCF!$B$18)^2*(1+DCF!$B$19)^3*(1+DCF!$B$20)^5/(1+0.07)^10)+((DCF!$B$17*(1+DCF!$B$18)^2*(1+DCF!$B$19)^3*(1+DCF!$B$20)^5*(1+0.04)/(0.07-0.04))/(1+0.07)^10)-DCF!$B$43)*1000/'Executive Summary'!$B$20 -> 720.4953
B7: 0.075 | C7: =((DCF!$B$17*(1+DCF!$B$18)/(1+0.075)^1)+(DCF!$B$17*(1+DCF!$B$18)^2/(1+0.075)^2)+(DCF!$B$17*(1+DCF!$B$18)^2*(1+DCF!$B$19)/(1+0.075)^3)+(DCF!$B$17*(1+DCF!$B$18)^2*(1+DCF!$B$19)^2/(1+0.075)^4)+(DCF!$B$17*(1+DCF!$B$18)^2*(1+DCF!$B$19)^3/(1+0.075)^5)+(DCF!$B$17*(1+DCF!$B$18)^2*(1+DCF!$B$19)^3*(1+DCF!$B$20)/(1+0.075)^6)+(DCF!$B$17*(1+DCF!$B$18)^2*(1+DCF!$B$19)^3*(1+DCF!$B$20)^2/(1+0.075)^7)+(DCF!$B$17*(1+DCF!$B$18)^2*(1+DCF!$B$19)^3*(1+DCF!$B$20)^3/(1+0.075)^8)+(DCF!$B$17*(1+DCF!$B$18)^2*(1+DCF!$B$19)^3*(1+DCF!$B$20)^4/(1+0.075)^9)+(DCF!$B$17*(1+DCF!$B$18)^2*(1+DCF!$B$19)^3*(1+DCF!$B$20)^5/(1+0.075)^10)+((DCF!$B$17*(1+DCF!$B$18)^2*(1+DCF!$B$19)^3*(1+DCF!$B$20)^5*(1+0.02)/(0.075-0.02))/(1+0.075)^10)-DCF!$B$43)*1000/'Executive Summary'!$B$20 -> 447.98197 | D7: =((DCF!$B$17*(1+DCF!$B$18)/(1+0.075)^1)+(DCF!$B$17*(1+DCF!$B$18)^2/(1+0.075)^2)+(DCF!$B$17*(1+DCF!$B$18)^2*(1+DCF!$B$19)/(1+0.075)^3)+(DCF!$B$17*(1+DCF!$B$18)^2*(1+DCF!$B$19)^2/(1+0.075)^4)+(DCF!$B$17*(1+DCF!$B$18)^2*(1+DCF!$B$19)^3/(1+0.075)^5)+(DCF!$B$17*(1+DCF!$B$18)^2*(1+DCF!$B$19)^3*(1+DCF!$B$20)/(1+0.075)^6)+(DCF!$B$17*(1+DCF!$B$18)^2*(1+DCF!$B$19)^3*(1+DCF!$B$20)^2/(1+0.075)^7)+(DCF!$B$17*(1+DCF!$B$18)^2*(1+DCF!$B$19)^3*(1+DCF!$B$20)^3/(1+0.075)^8)+(DCF!$B$17*(1+DCF!$B$18)^2*(1+DCF!$B$19)^3*(1+DCF!$B$20)^4/(1+0.075)^9)+(DCF!$B$17*(1+DCF!$B$18)^2*(1+DCF!$B$19)^3*(1+DCF!$B$20)^5/(1+0.075)^10)+((DCF!$B$17*(1+DCF!$B$18)^2*(1+DCF!$B$19)^3*(1+DCF!$B$20)^5*(1+0.025)/(0.075-0.025))/(1+0.075)^10)-DCF!$B$43)*1000/'Executive Summary'!$B$20 -> 477.49824 | E7: =((DCF!$B$17*(1+DCF!$B$18)/(1+0.075)^1)+(DCF!$B$17*(1+DCF!$B$18)^2/(1+0.075)^2)+(DCF!$B$17*(1+DCF!$B$18)^2*(1+DCF!$B$19)/(1+0.075)^3)+(DCF!$B$17*(1+DCF!$B$18)^2*(1+DCF!$B$19)^2/(1+0.075)^4)+(DCF!$B$17*(1+DCF!$B$18)^2*(1+DCF!$B$19)^3/(1+0.075)^5)+(DCF!$B$17*(1+DCF!$B$18)^2*(1+DCF!$B$19)^3*(1+DCF!$B$20)/(1+0.075)^6)+(DCF!$B$17*(1+DCF!$B$18)^2*(1+DCF!$B$19)^3*(1+DCF!$B$20)^2/(1+0.075)^7)+(DCF!$B$17*(1+DCF!$B$18)^2*(1+DCF!$B$19)^3*(1+DCF!$B$20)^3/(1+0.075)^8)+(DCF!$B$17*(1+DCF!$B$18)^2*(1+DCF!$B$19)^3*(1+DCF!$B$20)^4/(1+0.075)^9)+(DCF!$B$17*(1+DCF!$B$18)^2*(1+DCF!$B$19)^3*(1+DCF!$B$20)^5/(1+0.075)^10)+((DCF!$B$17*(1+DCF!$B$18)^2*(1+DCF!$B$19)^3*(1+DCF!$B$20)^5*(1+0.03)/(0.075-0.03))/(1+0.075)^10)-DCF!$B$43)*1000/'Executive Summary'!$B$20 -> 513.57369 | F7: =((DCF!$B$17*(1+DCF!$B$18)/(1+0.075)^1)+(DCF!$B$17*(1+DCF!$B$18)^2/(1+0.075)^2)+(DCF!$B$17*(1+DCF!$B$18)^2*(1+DCF!$B$19)/(1+0.075)^3)+(DCF!$B$17*(1+DCF!$B$18)^2*(1+DCF!$B$19)^2/(1+0.075)^4)+(DCF!$B$17*(1+DCF!$B$18)^2*(1+DCF!$B$19)^3/(1+0.075)^5)+(DCF!$B$17*(1+DCF!$B$18)^2*(1+DCF!$B$19)^3*(1+DCF!$B$20)/(1+0.075)^6)+(DCF!$B$17*(1+DCF!$B$18)^2*(1+DCF!$B$19)^3*(1+DCF!$B$20)^2/(1+0.075)^7)+(DCF!$B$17*(1+DCF!$B$18)^2*(1+DCF!$B$19)^3*(1+DCF!$B$20)^3/(1+0.075)^8)+(DCF!$B$17*(1+DCF!$B$18)^2*(1+DCF!$B$19)^3*(1+DCF!$B$20)^4/(1+0.075)^9)+(DCF!$B$17*(1+DCF!$B$18)^2*(1+DCF!$B$19)^3*(1+DCF!$B$20)^5/(1+0.075)^10)+((DCF!$B$17*(1+DCF!$B$18)^2*(1+DCF!$B$19)^3*(1+DCF!$B$20)^5*(1+0.035)/(0.075-0.035))/(1+0.075)^10)-DCF!$B$43)*1000/'Executive Summary'!$B$20 -> 558.66801 | G7: =((DCF!$B$17*(1+DCF!$B$18)/(1+0.075)^1)+(DCF!$B$17*(1+DCF!$B$18)^2/(1+0.075)^2)+(DCF!$B$17*(1+DCF!$B$18)^2*(1+DCF!$B$19)/(1+0.075)^3)+(DCF!$B$17*(1+DCF!$B$18)^2*(1+DCF!$B$19)^2/(1+0.075)^4)+(DCF!$B$17*(1+DCF!$B$18)^2*(1+DCF!$B$19)^3/(1+0.075)^5)+(DCF!$B$17*(1+DCF!$B$18)^2*(1+DCF!$B$19)^3*(1+DCF!$B$20)/(1+0.075)^6)+(DCF!$B$17*(1+DCF!$B$18)^2*(1+DCF!$B$19)^3*(1+DCF!$B$20)^2/(1+0.075)^7)+(DCF!$B$17*(1+DCF!$B$18)^2*(1+DCF!$B$19)^3*(1+DCF!$B$20)^3/(1+0.075)^8)+(DCF!$B$17*(1+DCF!$B$18)^2*(1+DCF!$B$19)^3*(1+DCF!$B$20)^4/(1+0.075)^9)+(DCF!$B$17*(1+DCF!$B$18)^2*(1+DCF!$B$19)^3*(1+DCF!$B$20)^5/(1+0.075)^10)+((DCF!$B$17*(1+DCF!$B$18)^2*(1+DCF!$B$19)^3*(1+DCF!$B$20)^5*(1+0.04)/(0.075-0.04))/(1+0.075)^10)-DCF!$B$43)*1000/'Executive Summary'!$B$20 -> 616.64641
B8: 0.08 | C8: =((DCF!$B$17*(1+DCF!$B$18)/(1+0.08)^1)+(DCF!$B$17*(1+DCF!$B$18)^2/(1+0.08)^2)+(DCF!$B$17*(1+DCF!$B$18)^2*(1+DCF!$B$19)/(1+0.08)^3)+(DCF!$B$17*(1+DCF!$B$18)^2*(1+DCF!$B$19)^2/(1+0.08)^4)+(DCF!$B$17*(1+DCF!$B$18)^2*(1+DCF!$B$19)^3/(1+0.08)^5)+(DCF!$B$17*(1+DCF!$B$18)^2*(1+DCF!$B$19)^3*(1+DCF!$B$20)/(1+0.08)^6)+(DCF!$B$17*(1+DCF!$B$18)^2*(1+DCF!$B$19)^3*(1+DCF!$B$20)^2/(1+0.08)^7)+(DCF!$B$17*(1+DCF!$B$18)^2*(1+DCF!$B$19)^3*(1+DCF!$B$20)^3/(1+0.08)^8)+(DCF!$B$17*(1+DCF!$B$18)^2*(1+DCF!$B$19)^3*(1+DCF!$B$20)^4/(1+0.08)^9)+(DCF!$B$17*(1+DCF!$B$18)^2*(1+DCF!$B$19)^3*(1+DCF!$B$20)^5/(1+0.08)^10)+((DCF!$B$17*(1+DCF!$B$18)^2*(1+DCF!$B$19)^3*(1+DCF!$B$20)^5*(1+0.02)/(0.08-0.02))/(1+0.08)^10)-DCF!$B$43)*1000/'Executive Summary'!$B$20 -> 409.07363 | D8: =((DCF!$B$17*(1+DCF!$B$18)/(1+0.08)^1)+(DCF!$B$17*(1+DCF!$B$18)^2/(1+0.08)^2)+(DCF!$B$17*(1+DCF!$B$18)^2*(1+DCF!$B$19)/(1+0.08)^3)+(DCF!$B$17*(1+DCF!$B$18)^2*(1+DCF!$B$19)^2/(1+0.08)^4)+(DCF!$B$17*(1+DCF!$B$18)^2*(1+DCF!$B$19)^3/(1+0.08)^5)+(DCF!$B$17*(1+DCF!$B$18)^2*(1+DCF!$B$19)^3*(1+DCF!$B$20)/(1+0.08)^6)+(DCF!$B$17*(1+DCF!$B$18)^2*(1+DCF!$B$19)^3*(1+DCF!$B$20)^2/(1+0.08)^7)+(DCF!$B$17*(1+DCF!$B$18)^2*(1+DCF!$B$19)^3*(1+DCF!$B$20)^3/(1+0.08)^8)+(DCF!$B$17*(1+DCF!$B$18)^2*(1+DCF!$B$19)^3*(1+DCF!$B$20)^4/(1+0.08)^9)+(DCF!$B$17*(1+DCF!$B$18)^2*(1+DCF!$B$19)^3*(1+DCF!$B$20)^5/(1+0.08)^10)+((DCF!$B$17*(1+DCF!$B$18)^2*(1+DCF!$B$19)^3*(1+DCF!$B$20)^5*(1+0.025)/(0.08-0.025))/(1+0.08)^10)-DCF!$B$43)*1000/'Executive Summary'!$B$20 -> 432.66443 | E8: =((DCF!$B$17*(1+DCF!$B$18)/(1+0.08)^1)+(DCF!$B$17*(1+DCF!$B$18)^2/(1+0.08)^2)+(DCF!$B$17*(1+DCF!$B$18)^2*(1+DCF!$B$19)/(1+0.08)^3)+(DCF!$B$17*(1+DCF!$B$18)^2*(1+DCF!$B$19)^2/(1+0.08)^4)+(DCF!$B$17*(1+DCF!$B$18)^2*(1+DCF!$B$19)^3/(1+0.08)^5)+(DCF!$B$17*(1+DCF!$B$18)^2*(1+DCF!$B$19)^3*(1+DCF!$B$20)/(1+0.08)^6)+(DCF!$B$17*(1+DCF!$B$18)^2*(1+DCF!$B$19)^3*(1+DCF!$B$20)^2/(1+0.08)^7)+(DCF!$B$17*(1+DCF!$B$18)^2*(1+DCF!$B$19)^3*(1+DCF!$B$20)^3/(1+0.08)^8)+(DCF!$B$17*(1+DCF!$B$18)^2*(1+DCF!$B$19)^3*(1+DCF!$B$20)^4/(1+0.08)^9)+(DCF!$B$17*(1+DCF!$B$18)^2*(1+DCF!$B$19)^3*(1+DCF!$B$20)^5/(1+0.08)^10)+((DCF!$B$17*(1+DCF!$B$18)^2*(1+DCF!$B$19)^3*(1+DCF!$B$20)^5*(1+0.03)/(0.08-0.03))/(1+0.08)^10)-DCF!$B$43)*1000/'Executive Summary'!$B$20 -> 460.97339 | F8: =((DCF!$B$17*(1+DCF!$B$18)/(1+0.08)^1)+(DCF!$B$17*(1+DCF!$B$18)^2/(1+0.08)^2)+(DCF!$B$17*(1+DCF!$B$18)^2*(1+DCF!$B$19)/(1+0.08)^3)+(DCF!$B$17*(1+DCF!$B$18)^2*(1+DCF!$B$19)^2/(1+0.08)^4)+(DCF!$B$17*(1+DCF!$B$18)^2*(1+DCF!$B$19)^3/(1+0.08)^5)+(DCF!$B$17*(1+DCF!$B$18)^2*(1+DCF!$B$19)^3*(1+DCF!$B$20)/(1+0.08)^6)+(DCF!$B$17*(1+DCF!$B$18)^2*(1+DCF!$B$19)^3*(1+DCF!$B$20)^2/(1+0.08)^7)+(DCF!$B$17*(1+DCF!$B$18)^2*(1+DCF!$B$19)^3*(1+DCF!$B$20)^3/(1+0.08)^8)+(DCF!$B$17*(1+DCF!$B$18)^2*(1+DCF!$B$19)^3*(1+DCF!$B$20)^4/(1+0.08)^9)+(DCF!$B$17*(1+DCF!$B$18)^2*(1+DCF!$B$19)^3*(1+DCF!$B$20)^5/(1+0.08)^10)+((DCF!$B$17*(1+DCF!$B$18)^2*(1+DCF!$B$19)^3*(1+DCF!$B$20)^5*(1+0.035)/(0.08-0.035))/(1+0.08)^10)-DCF!$B$43)*1000/'Executive Summary'!$B$20 -> 495.57324 | G8: =((DCF!$B$17*(1+DCF!$B$18)/(1+0.08)^1)+(DCF!$B$17*(1+DCF!$B$18)^2/(1+0.08)^2)+(DCF!$B$17*(1+DCF!$B$18)^2*(1+DCF!$B$19)/(1+0.08)^3)+(DCF!$B$17*(1+DCF!$B$18)^2*(1+DCF!$B$19)^2/(1+0.08)^4)+(DCF!$B$17*(1+DCF!$B$18)^2*(1+DCF!$B$19)^3/(1+0.08)^5)+(DCF!$B$17*(1+DCF!$B$18)^2*(1+DCF!$B$19)^3*(1+DCF!$B$20)/(1+0.08)^6)+(DCF!$B$17*(1+DCF!$B$18)^2*(1+DCF!$B$19)^3*(1+DCF!$B$20)^2/(1+0.08)^7)+(DCF!$B$17*(1+DCF!$B$18)^2*(1+DCF!$B$19)^3*(1+DCF!$B$20)^3/(1+0.08)^8)+(DCF!$B$17*(1+DCF!$B$18)^2*(1+DCF!$B$19)^3*(1+DCF!$B$20)^4/(1+0.08)^9)+(DCF!$B$17*(1+DCF!$B$18)^2*(1+DCF!$B$19)^3*(1+DCF!$B$20)^5/(1+0.08)^10)+((DCF!$B$17*(1+DCF!$B$18)^2*(1+DCF!$B$19)^3*(1+DCF!$B$20)^5*(1+0.04)/(0.08-0.04))/(1+0.08)^10)-DCF!$B$43)*1000/'Executive Summary'!$B$20 -> 538.82304
B9: 0.085 | C9: =((DCF!$B$17*(1+DCF!$B$18)/(1+0.085)^1)+(DCF!$B$17*(1+DCF!$B$18)^2/(1+0.085)^2)+(DCF!$B$17*(1+DCF!$B$18)^2*(1+DCF!$B$19)/(1+0.085)^3)+(DCF!$B$17*(1+DCF!$B$18)^2*(1+DCF!$B$19)^2/(1+0.085)^4)+(DCF!$B$17*(1+DCF!$B$18)^2*(1+DCF!$B$19)^3/(1+0.085)^5)+(DCF!$B$17*(1+DCF!$B$18)^2*(1+DCF!$B$19)^3*(1+DCF!$B$20)/(1+0.085)^6)+(DCF!$B$17*(1+DCF!$B$18)^2*(1+DCF!$B$19)^3*(1+DCF!$B$20)^2/(1+0.085)^7)+(DCF!$B$17*(1+DCF!$B$18)^2*(1+DCF!$B$19)^3*(1+DCF!$B$20)^3/(1+0.085)^8)+(DCF!$B$17*(1+DCF!$B$18)^2*(1+DCF!$B$19)^3*(1+DCF!$B$20)^4/(1+0.085)^9)+(DCF!$B$17*(1+DCF!$B$18)^2*(1+DCF!$B$19)^3*(1+DCF!$B$20)^5/(1+0.085)^10)+((DCF!$B$17*(1+DCF!$B$18)^2*(1+DCF!$B$19)^3*(1+DCF!$B$20)^5*(1+0.02)/(0.085-0.02))/(1+0.085)^10)-DCF!$B$43)*1000/'Executive Summary'!$B$20 -> 376.2217 | D9: =((DCF!$B$17*(1+DCF!$B$18)/(1+0.085)^1)+(DCF!$B$17*(1+DCF!$B$18)^2/(1+0.085)^2)+(DCF!$B$17*(1+DCF!$B$18)^2*(1+DCF!$B$19)/(1+0.085)^3)+(DCF!$B$17*(1+DCF!$B$18)^2*(1+DCF!$B$19)^2/(1+0.085)^4)+(DCF!$B$17*(1+DCF!$B$18)^2*(1+DCF!$B$19)^3/(1+0.085)^5)+(DCF!$B$17*(1+DCF!$B$18)^2*(1+DCF!$B$19)^3*(1+DCF!$B$20)/(1+0.085)^6)+(DCF!$B$17*(1+DCF!$B$18)^2*(1+DCF!$B$19)^3*(1+DCF!$B$20)^2/(1+0.085)^7)+(DCF!$B$17*(1+DCF!$B$18)^2*(1+DCF!$B$19)^3*(1+DCF!$B$20)^3/(1+0.085)^8)+(DCF!$B$17*(1+DCF!$B$18)^2*(1+DCF!$B$19)^3*(1+DCF!$B$20)^4/(1+0.085)^9)+(DCF!$B$17*(1+DCF!$B$18)^2*(1+DCF!$B$19)^3*(1+DCF!$B$20)^5/(1+0.085)^10)+((DCF!$B$17*(1+DCF!$B$18)^2*(1+DCF!$B$19)^3*(1+DCF!$B$20)^5*(1+0.025)/(0.085-0.025))/(1+0.085)^10)-DCF!$B$43)*1000/'Executive Summary'!$B$20 -> 395.37035 | E9: =((DCF!$B$17*(1+DCF!$B$18)/(1+0.085)^1)+(DCF!$B$17*(1+DCF!$B$18)^2/(1+0.085)^2)+(DCF!$B$17*(1+DCF!$B$18)^2*(1+DCF!$B$19)/(1+0.085)^3)+(DCF!$B$17*(1+DCF!$B$18)^2*(1+DCF!$B$19)^2/(1+0.085)^4)+(DCF!$B$17*(1+DCF!$B$18)^2*(1+DCF!$B$19)^3/(1+0.085)^5)+(DCF!$B$17*(1+DCF!$B$18)^2*(1+DCF!$B$19)^3*(1+DCF!$B$20)/(1+0.085)^6)+(DCF!$B$17*(1+DCF!$B$18)^2*(1+DCF!$B$19)^3*(1+DCF!$B$20)^2/(1+0.085)^7)+(DCF!$B$17*(1+DCF!$B$18)^2*(1+DCF!$B$19)^3*(1+DCF!$B$20)^3/(1+0.085)^8)+(DCF!$B$17*(1+DCF!$B$18)^2*(1+DCF!$B$19)^3*(1+DCF!$B$20)^4/(1+0.085)^9)+(DCF!$B$17*(1+DCF!$B$18)^2*(1+DCF!$B$19)^3*(1+DCF!$B$20)^5/(1+0.085)^10)+((DCF!$B$17*(1+DCF!$B$18)^2*(1+DCF!$B$19)^3*(1+DCF!$B$20)^5*(1+0.03)/(0.085-0.03))/(1+0.085)^10)-DCF!$B$43)*1000/'Executive Summary'!$B$20 -> 418.00057 | F9: =((DCF!$B$17*(1+DCF!$B$18)/(1+0.085)^1)+(DCF!$B$17*(1+DCF!$B$18)^2/(1+0.085)^2)+(DCF!$B$17*(1+DCF!$B$18)^2*(1+DCF!$B$19)/(1+0.085)^3)+(DCF!$B$17*(1+DCF!$B$18)^2*(1+DCF!$B$19)^2/(1+0.085)^4)+(DCF!$B$17*(1+DCF!$B$18)^2*(1+DCF!$B$19)^3/(1+0.085)^5)+(DCF!$B$17*(1+DCF!$B$18)^2*(1+DCF!$B$19)^3*(1+DCF!$B$20)/(1+0.085)^6)+(DCF!$B$17*(1+DCF!$B$18)^2*(1+DCF!$B$19)^3*(1+DCF!$B$20)^2/(1+0.085)^7)+(DCF!$B$17*(1+DCF!$B$18)^2*(1+DCF!$B$19)^3*(1+DCF!$B$20)^3/(1+0.085)^8)+(DCF!$B$17*(1+DCF!$B$18)^2*(1+DCF!$B$19)^3*(1+DCF!$B$20)^4/(1+0.085)^9)+(DCF!$B$17*(1+DCF!$B$18)^2*(1+DCF!$B$19)^3*(1+DCF!$B$20)^5/(1+0.085)^10)+((DCF!$B$17*(1+DCF!$B$18)^2*(1+DCF!$B$19)^3*(1+DCF!$B$20)^5*(1+0.035)/(0.085-0.035))/(1+0.085)^10)-DCF!$B$43)*1000/'Executive Summary'!$B$20 -> 445.15684 | G9: =((DCF!$B$17*(1+DCF!$B$18)/(1+0.085)^1)+(DCF!$B$17*(1+DCF!$B$18)^2/(1+0.085)^2)+(DCF!$B$17*(1+DCF!$B$18)^2*(1+DCF!$B$19)/(1+0.085)^3)+(DCF!$B$17*(1+DCF!$B$18)^2*(1+DCF!$B$19)^2/(1+0.085)^4)+(DCF!$B$17*(1+DCF!$B$18)^2*(1+DCF!$B$19)^3/(1+0.085)^5)+(DCF!$B$17*(1+DCF!$B$18)^2*(1+DCF!$B$19)^3*(1+DCF!$B$20)/(1+0.085)^6)+(DCF!$B$17*(1+DCF!$B$18)^2*(1+DCF!$B$19)^3*(1+DCF!$B$20)^2/(1+0.085)^7)+(DCF!$B$17*(1+DCF!$B$18)^2*(1+DCF!$B$19)^3*(1+DCF!$B$20)^3/(1+0.085)^8)+(DCF!$B$17*(1+DCF!$B$18)^2*(1+DCF!$B$19)^3*(1+DCF!$B$20)^4/(1+0.085)^9)+(DCF!$B$17*(1+DCF!$B$18)^2*(1+DCF!$B$19)^3*(1+DCF!$B$20)^5/(1+0.085)^10)+((DCF!$B$17*(1+DCF!$B$18)^2*(1+DCF!$B$19)^3*(1+DCF!$B$20)^5*(1+0.04)/(0.085-0.04))/(1+0.085)^10)-DCF!$B$43)*1000/'Executive Summary'!$B$20 -> 478.34784
B10: 0.09 | C10: =((DCF!$B$17*(1+DCF!$B$18)/(1+0.09)^1)+(DCF!$B$17*(1+DCF!$B$18)^2/(1+0.09)^2)+(DCF!$B$17*(1+DCF!$B$18)^2*(1+DCF!$B$19)/(1+0.09)^3)+(DCF!$B$17*(1+DCF!$B$18)^2*(1+DCF!$B$19)^2/(1+0.09)^4)+(DCF!$B$17*(1+DCF!$B$18)^2*(1+DCF!$B$19)^3/(1+0.09)^5)+(DCF!$B$17*(1+DCF!$B$18)^2*(1+DCF!$B$19)^3*(1+DCF!$B$20)/(1+0.09)^6)+(DCF!$B$17*(1+DCF!$B$18)^2*(1+DCF!$B$19)^3*(1+DCF!$B$20)^2/(1+0.09)^7)+(DCF!$B$17*(1+DCF!$B$18)^2*(1+DCF!$B$19)^3*(1+DCF!$B$20)^3/(1+0.09)^8)+(DCF!$B$17*(1+DCF!$B$18)^2*(1+DCF!$B$19)^3*(1+DCF!$B$20)^4/(1+0.09)^9)+(DCF!$B$17*(1+DCF!$B$18)^2*(1+DCF!$B$19)^3*(1+DCF!$B$20)^5/(1+0.09)^10)+((DCF!$B$17*(1+DCF!$B$18)^2*(1+DCF!$B$19)^3*(1+DCF!$B$20)^5*(1+0.02)/(0.09-0.02))/(1+0.09)^10)-DCF!$B$43)*1000/'Executive Summary'!$B$20 -> 348.1258 | D10: =((DCF!$B$17*(1+DCF!$B$18)/(1+0.09)^1)+(DCF!$B$17*(1+DCF!$B$18)^2/(1+0.09)^2)+(DCF!$B$17*(1+DCF!$B$18)^2*(1+DCF!$B$19)/(1+0.09)^3)+(DCF!$B$17*(1+DCF!$B$18)^2*(1+DCF!$B$19)^2/(1+0.09)^4)+(DCF!$B$17*(1+DCF!$B$18)^2*(1+DCF!$B$19)^3/(1+0.09)^5)+(DCF!$B$17*(1+DCF!$B$18)^2*(1+DCF!$B$19)^3*(1+DCF!$B$20)/(1+0.09)^6)+(DCF!$B$17*(1+DCF!$B$18)^2*(1+DCF!$B$19)^3*(1+DCF!$B$20)^2/(1+0.09)^7)+(DCF!$B$17*(1+DCF!$B$18)^2*(1+DCF!$B$19)^3*(1+DCF!$B$20)^3/(1+0.09)^8)+(DCF!$B$17*(1+DCF!$B$18)^2*(1+DCF!$B$19)^3*(1+DCF!$B$20)^4/(1+0.09)^9)+(DCF!$B$17*(1+DCF!$B$18)^2*(1+DCF!$B$19)^3*(1+DCF!$B$20)^5/(1+0.09)^10)+((DCF!$B$17*(1+DCF!$B$18)^2*(1+DCF!$B$19)^3*(1+DCF!$B$20)^5*(1+0.025)/(0.09-0.025))/(1+0.09)^10)-DCF!$B$43)*1000/'Executive Summary'!$B$20 -> 363.87362 | E10: =((DCF!$B$17*(1+DCF!$B$18)/(1+0.09)^1)+(DCF!$B$17*(1+DCF!$B$18)^2/(1+0.09)^2)+(DCF!$B$17*(1+DCF!$B$18)^2*(1+DCF!$B$19)/(1+0.09)^3)+(DCF!$B$17*(1+DCF!$B$18)^2*(1+DCF!$B$19)^2/(1+0.09)^4)+(DCF!$B$17*(1+DCF!$B$18)^2*(1+DCF!$B$19)^3/(1+0.09)^5)+(DCF!$B$17*(1+DCF!$B$18)^2*(1+DCF!$B$19)^3*(1+DCF!$B$20)/(1+0.09)^6)+(DCF!$B$17*(1+DCF!$B$18)^2*(1+DCF!$B$19)^3*(1+DCF!$B$20)^2/(1+0.09)^7)+(DCF!$B$17*(1+DCF!$B$18)^2*(1+DCF!$B$19)^3*(1+DCF!$B$20)^3/(1+0.09)^8)+(DCF!$B$17*(1+DCF!$B$18)^2*(1+DCF!$B$19)^3*(1+DCF!$B$20)^4/(1+0.09)^9)+(DCF!$B$17*(1+DCF!$B$18)^2*(1+DCF!$B$19)^3*(1+DCF!$B$20)^5/(1+0.09)^10)+((DCF!$B$17*(1+DCF!$B$18)^2*(1+DCF!$B$19)^3*(1+DCF!$B$20)^5*(1+0.03)/(0.09-0.03))/(1+0.09)^10)-DCF!$B$43)*1000/'Executive Summary'!$B$20 -> 382.24608 | F10: =((DCF!$B$17*(1+DCF!$B$18)/(1+0.09)^1)+(DCF!$B$17*(1+DCF!$B$18)^2/(1+0.09)^2)+(DCF!$B$17*(1+DCF!$B$18)^2*(1+DCF!$B$19)/(1+0.09)^3)+(DCF!$B$17*(1+DCF!$B$18)^2*(1+DCF!$B$19)^2/(1+0.09)^4)+(DCF!$B$17*(1+DCF!$B$18)^2*(1+DCF!$B$19)^3/(1+0.09)^5)+(DCF!$B$17*(1+DCF!$B$18)^2*(1+DCF!$B$19)^3*(1+DCF!$B$20)/(1+0.09)^6)+(DCF!$B$17*(1+DCF!$B$18)^2*(1+DCF!$B$19)^3*(1+DCF!$B$20)^2/(1+0.09)^7)+(DCF!$B$17*(1+DCF!$B$18)^2*(1+DCF!$B$19)^3*(1+DCF!$B$20)^3/(1+0.09)^8)+(DCF!$B$17*(1+DCF!$B$18)^2*(1+DCF!$B$19)^3*(1+DCF!$B$20)^4/(1+0.09)^9)+(DCF!$B$17*(1+DCF!$B$18)^2*(1+DCF!$B$19)^3*(1+DCF!$B$20)^5/(1+0.09)^10)+((DCF!$B$17*(1+DCF!$B$18)^2*(1+DCF!$B$19)^3*(1+DCF!$B$20)^5*(1+0.035)/(0.09-0.035))/(1+0.09)^10)-DCF!$B$43)*1000/'Executive Summary'!$B$20 -> 403.959 | G10: =((DCF!$B$17*(1+DCF!$B$18)/(1+0.09)^1)+(DCF!$B$17*(1+DCF!$B$18)^2/(1+0.09)^2)+(DCF!$B$17*(1+DCF!$B$18)^2*(1+DCF!$B$19)/(1+0.09)^3)+(DCF!$B$17*(1+DCF!$B$18)^2*(1+DCF!$B$19)^2/(1+0.09)^4)+(DCF!$B$17*(1+DCF!$B$18)^2*(1+DCF!$B$19)^3/(1+0.09)^5)+(DCF!$B$17*(1+DCF!$B$18)^2*(1+DCF!$B$19)^3*(1+DCF!$B$20)/(1+0.09)^6)+(DCF!$B$17*(1+DCF!$B$18)^2*(1+DCF!$B$19)^3*(1+DCF!$B$20)^2/(1+0.09)^7)+(DCF!$B$17*(1+DCF!$B$18)^2*(1+DCF!$B$19)^3*(1+DCF!$B$20)^3/(1+0.09)^8)+(DCF!$B$17*(1+DCF!$B$18)^2*(1+DCF!$B$19)^3*(1+DCF!$B$20)^4/(1+0.09)^9)+(DCF!$B$17*(1+DCF!$B$18)^2*(1+DCF!$B$19)^3*(1+DCF!$B$20)^5/(1+0.09)^10)+((DCF!$B$17*(1+DCF!$B$18)^2*(1+DCF!$B$19)^3*(1+DCF!$B$20)^5*(1+0.04)/(0.09-0.04))/(1+0.09)^10)-DCF!$B$43)*1000/'Executive Summary'!$B$20 -> 430.01449
B11: 0.095 | C11: =((DCF!$B$17*(1+DCF!$B$18)/(1+0.095)^1)+(DCF!$B$17*(1+DCF!$B$18)^2/(1+0.095)^2)+(DCF!$B$17*(1+DCF!$B$18)^2*(1+DCF!$B$19)/(1+0.095)^3)+(DCF!$B$17*(1+DCF!$B$18)^2*(1+DCF!$B$19)^2/(1+0.095)^4)+(DCF!$B$17*(1+DCF!$B$18)^2*(1+DCF!$B$19)^3/(1+0.095)^5)+(DCF!$B$17*(1+DCF!$B$18)^2*(1+DCF!$B$19)^3*(1+DCF!$B$20)/(1+0.095)^6)+(DCF!$B$17*(1+DCF!$B$18)^2*(1+DCF!$B$19)^3*(1+DCF!$B$20)^2/(1+0.095)^7)+(DCF!$B$17*(1+DCF!$B$18)^2*(1+DCF!$B$19)^3*(1+DCF!$B$20)^3/(1+0.095)^8)+(DCF!$B$17*(1+DCF!$B$18)^2*(1+DCF!$B$19)^3*(1+DCF!$B$20)^4/(1+0.095)^9)+(DCF!$B$17*(1+DCF!$B$18)^2*(1+DCF!$B$19)^3*(1+DCF!$B$20)^5/(1+0.095)^10)+((DCF!$B$17*(1+DCF!$B$18)^2*(1+DCF!$B$19)^3*(1+DCF!$B$20)^5*(1+0.02)/(0.095-0.02))/(1+0.095)^10)-DCF!$B$43)*1000/'Executive Summary'!$B$20 -> 323.83242 | D11: =((DCF!$B$17*(1+DCF!$B$18)/(1+0.095)^1)+(DCF!$B$17*(1+DCF!$B$18)^2/(1+0.095)^2)+(DCF!$B$17*(1+DCF!$B$18)^2*(1+DCF!$B$19)/(1+0.095)^3)+(DCF!$B$17*(1+DCF!$B$18)^2*(1+DCF!$B$19)^2/(1+0.095)^4)+(DCF!$B$17*(1+DCF!$B$18)^2*(1+DCF!$B$19)^3/(1+0.095)^5)+(DCF!$B$17*(1+DCF!$B$18)^2*(1+DCF!$B$19)^3*(1+DCF!$B$20)/(1+0.095)^6)+(DCF!$B$17*(1+DCF!$B$18)^2*(1+DCF!$B$19)^3*(1+DCF!$B$20)^2/(1+0.095)^7)+(DCF!$B$17*(1+DCF!$B$18)^2*(1+DCF!$B$19)^3*(1+DCF!$B$20)^3/(1+0.095)^8)+(DCF!$B$17*(1+DCF!$B$18)^2*(1+DCF!$B$19)^3*(1+DCF!$B$20)^4/(1+0.095)^9)+(DCF!$B$17*(1+DCF!$B$18)^2*(1+DCF!$B$19)^3*(1+DCF!$B$20)^5/(1+0.095)^10)+((DCF!$B$17*(1+DCF!$B$18)^2*(1+DCF!$B$19)^3*(1+DCF!$B$20)^5*(1+0.025)/(0.095-0.025))/(1+0.095)^10)-DCF!$B$43)*1000/'Executive Summary'!$B$20 -> 336.92979 | E11: =((DCF!$B$17*(1+DCF!$B$18)/(1+0.095)^1)+(DCF!$B$17*(1+DCF!$B$18)^2/(1+0.095)^2)+(DCF!$B$17*(1+DCF!$B$18)^2*(1+DCF!$B$19)/(1+0.095)^3)+(DCF!$B$17*(1+DCF!$B$18)^2*(1+DCF!$B$19)^2/(1+0.095)^4)+(DCF!$B$17*(1+DCF!$B$18)^2*(1+DCF!$B$19)^3/(1+0.095)^5)+(DCF!$B$17*(1+DCF!$B$18)^2*(1+DCF!$B$19)^3*(1+DCF!$B$20)/(1+0.095)^6)+(DCF!$B$17*(1+DCF!$B$18)^2*(1+DCF!$B$19)^3*(1+DCF!$B$20)^2/(1+0.095)^7)+(DCF!$B$17*(1+DCF!$B$18)^2*(1+DCF!$B$19)^3*(1+DCF!$B$20)^3/(1+0.095)^8)+(DCF!$B$17*(1+DCF!$B$18)^2*(1+DCF!$B$19)^3*(1+DCF!$B$20)^4/(1+0.095)^9)+(DCF!$B$17*(1+DCF!$B$18)^2*(1+DCF!$B$19)^3*(1+DCF!$B$20)^5/(1+0.095)^10)+((DCF!$B$17*(1+DCF!$B$18)^2*(1+DCF!$B$19)^3*(1+DCF!$B$20)^5*(1+0.03)/(0.095-0.03))/(1+0.095)^10)-DCF!$B$43)*1000/'Executive Summary'!$B$20 -> 352.04214 | F11: =((DCF!$B$17*(1+DCF!$B$18)/(1+0.095)^1)+(DCF!$B$17*(1+DCF!$B$18)^2/(1+0.095)^2)+(DCF!$B$17*(1+DCF!$B$18)^2*(1+DCF!$B$19)/(1+0.095)^3)+(DCF!$B$17*(1+DCF!$B$18)^2*(1+DCF!$B$19)^2/(1+0.095)^4)+(DCF!$B$17*(1+DCF!$B$18)^2*(1+DCF!$B$19)^3/(1+0.095)^5)+(DCF!$B$17*(1+DCF!$B$18)^2*(1+DCF!$B$19)^3*(1+DCF!$B$20)/(1+0.095)^6)+(DCF!$B$17*(1+DCF!$B$18)^2*(1+DCF!$B$19)^3*(1+DCF!$B$20)^2/(1+0.095)^7)+(DCF!$B$17*(1+DCF!$B$18)^2*(1+DCF!$B$19)^3*(1+DCF!$B$20)^3/(1+0.095)^8)+(DCF!$B$17*(1+DCF!$B$18)^2*(1+DCF!$B$19)^3*(1+DCF!$B$20)^4/(1+0.095)^9)+(DCF!$B$17*(1+DCF!$B$18)^2*(1+DCF!$B$19)^3*(1+DCF!$B$20)^5/(1+0.095)^10)+((DCF!$B$17*(1+DCF!$B$18)^2*(1+DCF!$B$19)^3*(1+DCF!$B$20)^5*(1+0.035)/(0.095-0.035))/(1+0.095)^10)-DCF!$B$43)*1000/'Executive Summary'!$B$20 -> 369.67322 | G11: =((DCF!$B$17*(1+DCF!$B$18)/(1+0.095)^1)+(DCF!$B$17*(1+DCF!$B$18)^2/(1+0.095)^2)+(DCF!$B$17*(1+DCF!$B$18)^2*(1+DCF!$B$19)/(1+0.095)^3)+(DCF!$B$17*(1+DCF!$B$18)^2*(1+DCF!$B$19)^2/(1+0.095)^4)+(DCF!$B$17*(1+DCF!$B$18)^2*(1+DCF!$B$19)^3/(1+0.095)^5)+(DCF!$B$17*(1+DCF!$B$18)^2*(1+DCF!$B$19)^3*(1+DCF!$B$20)/(1+0.095)^6)+(DCF!$B$17*(1+DCF!$B$18)^2*(1+DCF!$B$19)^3*(1+DCF!$B$20)^2/(1+0.095)^7)+(DCF!$B$17*(1+DCF!$B$18)^2*(1+DCF!$B$19)^3*(1+DCF!$B$20)^3/(1+0.095)^8)+(DCF!$B$17*(1+DCF!$B$18)^2*(1+DCF!$B$19)^3*(1+DCF!$B$20)^4/(1+0.095)^9)+(DCF!$B$17*(1+DCF!$B$18)^2*(1+DCF!$B$19)^3*(1+DCF!$B$20)^5/(1+0.095)^10)+((DCF!$B$17*(1+DCF!$B$18)^2*(1+DCF!$B$19)^3*(1+DCF!$B$20)^5*(1+0.04)/(0.095-0.04))/(1+0.095)^10)-DCF!$B$43)*1000/'Executive Summary'!$B$20 -> 390.50994
B12: 0.1 | C12: =((DCF!$B$17*(1+DCF!$B$18)/(1+0.1)^1)+(DCF!$B$17*(1+DCF!$B$18)^2/(1+0.1)^2)+(DCF!$B$17*(1+DCF!$B$18)^2*(1+DCF!$B$19)/(1+0.1)^3)+(DCF!$B$17*(1+DCF!$B$18)^2*(1+DCF!$B$19)^2/(1+0.1)^4)+(DCF!$B$17*(1+DCF!$B$18)^2*(1+DCF!$B$19)^3/(1+0.1)^5)+(DCF!$B$17*(1+DCF!$B$18)^2*(1+DCF!$B$19)^3*(1+DCF!$B$20)/(1+0.1)^6)+(DCF!$B$17*(1+DCF!$B$18)^2*(1+DCF!$B$19)^3*(1+DCF!$B$20)^2/(1+0.1)^7)+(DCF!$B$17*(1+DCF!$B$18)^2*(1+DCF!$B$19)^3*(1+DCF!$B$20)^3/(1+0.1)^8)+(DCF!$B$17*(1+DCF!$B$18)^2*(1+DCF!$B$19)^3*(1+DCF!$B$20)^4/(1+0.1)^9)+(DCF!$B$17*(1+DCF!$B$18)^2*(1+DCF!$B$19)^3*(1+DCF!$B$20)^5/(1+0.1)^10)+((DCF!$B$17*(1+DCF!$B$18)^2*(1+DCF!$B$19)^3*(1+DCF!$B$20)^5*(1+0.02)/(0.1-0.02))/(1+0.1)^10)-DCF!$B$43)*1000/'Executive Summary'!$B$20 -> 302.62655 | D12: =((DCF!$B$17*(1+DCF!$B$18)/(1+0.1)^1)+(DCF!$B$17*(1+DCF!$B$18)^2/(1+0.1)^2)+(DCF!$B$17*(1+DCF!$B$18)^2*(1+DCF!$B$19)/(1+0.1)^3)+(DCF!$B$17*(1+DCF!$B$18)^2*(1+DCF!$B$19)^2/(1+0.1)^4)+(DCF!$B$17*(1+DCF!$B$18)^2*(1+DCF!$B$19)^3/(1+0.1)^5)+(DCF!$B$17*(1+DCF!$B$18)^2*(1+DCF!$B$19)^3*(1+DCF!$B$20)/(1+0.1)^6)+(DCF!$B$17*(1+DCF!$B$18)^2*(1+DCF!$B$19)^3*(1+DCF!$B$20)^2/(1+0.1)^7)+(DCF!$B$17*(1+DCF!$B$18)^2*(1+DCF!$B$19)^3*(1+DCF!$B$20)^3/(1+0.1)^8)+(DCF!$B$17*(1+DCF!$B$18)^2*(1+DCF!$B$19)^3*(1+DCF!$B$20)^4/(1+0.1)^9)+(DCF!$B$17*(1+DCF!$B$18)^2*(1+DCF!$B$19)^3*(1+DCF!$B$20)^5/(1+0.1)^10)+((DCF!$B$17*(1+DCF!$B$18)^2*(1+DCF!$B$19)^3*(1+DCF!$B$20)^5*(1+0.025)/(0.1-0.025))/(1+0.1)^10)-DCF!$B$43)*1000/'Executive Summary'!$B$20 -> 313.62635 | E12: =((DCF!$B$17*(1+DCF!$B$18)/(1+0.1)^1)+(DCF!$B$17*(1+DCF!$B$18)^2/(1+0.1)^2)+(DCF!$B$17*(1+DCF!$B$18)^2*(1+DCF!$B$19)/(1+0.1)^3)+(DCF!$B$17*(1+DCF!$B$18)^2*(1+DCF!$B$19)^2/(1+0.1)^4)+(DCF!$B$17*(1+DCF!$B$18)^2*(1+DCF!$B$19)^3/(1+0.1)^5)+(DCF!$B$17*(1+DCF!$B$18)^2*(1+DCF!$B$19)^3*(1+DCF!$B$20)/(1+0.1)^6)+(DCF!$B$17*(1+DCF!$B$18)^2*(1+DCF!$B$19)^3*(1+DCF!$B$20)^2/(1+0.1)^7)+(DCF!$B$17*(1+DCF!$B$18)^2*(1+DCF!$B$19)^3*(1+DCF!$B$20)^3/(1+0.1)^8)+(DCF!$B$17*(1+DCF!$B$18)^2*(1+DCF!$B$19)^3*(1+DCF!$B$20)^4/(1+0.1)^9)+(DCF!$B$17*(1+DCF!$B$18)^2*(1+DCF!$B$19)^3*(1+DCF!$B$20)^5/(1+0.1)^10)+((DCF!$B$17*(1+DCF!$B$18)^2*(1+DCF!$B$19)^3*(1+DCF!$B$20)^5*(1+0.03)/(0.1-0.03))/(1+0.1)^10)-DCF!$B$43)*1000/'Executive Summary'!$B$20 -> 326.19756 | F12: =((DCF!$B$17*(1+DCF!$B$18)/(1+0.1)^1)+(DCF!$B$17*(1+DCF!$B$18)^2/(1+0.1)^2)+(DCF!$B$17*(1+DCF!$B$18)^2*(1+DCF!$B$19)/(1+0.1)^3)+(DCF!$B$17*(1+DCF!$B$18)^2*(1+DCF!$B$19)^2/(1+0.1)^4)+(DCF!$B$17*(1+DCF!$B$18)^2*(1+DCF!$B$19)^3/(1+0.1)^5)+(DCF!$B$17*(1+DCF!$B$18)^2*(1+DCF!$B$19)^3*(1+DCF!$B$20)/(1+0.1)^6)+(DCF!$B$17*(1+DCF!$B$18)^2*(1+DCF!$B$19)^3*(1+DCF!$B$20)^2/(1+0.1)^7)+(DCF!$B$17*(1+DCF!$B$18)^2*(1+DCF!$B$19)^3*(1+DCF!$B$20)^3/(1+0.1)^8)+(DCF!$B$17*(1+DCF!$B$18)^2*(1+DCF!$B$19)^3*(1+DCF!$B$20)^4/(1+0.1)^9)+(DCF!$B$17*(1+DCF!$B$18)^2*(1+DCF!$B$19)^3*(1+DCF!$B$20)^5/(1+0.1)^10)+((DCF!$B$17*(1+DCF!$B$18)^2*(1+DCF!$B$19)^3*(1+DCF!$B$20)^5*(1+0.035)/(0.1-0.035))/(1+0.1)^10)-DCF!$B$43)*1000/'Executive Summary'!$B$20 -> 340.7028 | G12: =((DCF!$B$17*(1+DCF!$B$18)/(1+0.1)^1)+(DCF!$B$17*(1+DCF!$B$18)^2/(1+0.1)^2)+(DCF!$B$17*(1+DCF!$B$18)^2*(1+DCF!$B$19)/(1+0.1)^3)+(DCF!$B$17*(1+DCF!$B$18)^2*(1+DCF!$B$19)^2/(1+0.1)^4)+(DCF!$B$17*(1+DCF!$B$18)^2*(1+DCF!$B$19)^3/(1+0.1)^5)+(DCF!$B$17*(1+DCF!$B$18)^2*(1+DCF!$B$19)^3*(1+DCF!$B$20)/(1+0.1)^6)+(DCF!$B$17*(1+DCF!$B$18)^2*(1+DCF!$B$19)^3*(1+DCF!$B$20)^2/(1+0.1)^7)+(DCF!$B$17*(1+DCF!$B$18)^2*(1+DCF!$B$19)^3*(1+DCF!$B$20)^3/(1+0.1)^8)+(DCF!$B$17*(1+DCF!$B$18)^2*(1+DCF!$B$19)^3*(1+DCF!$B$20)^4/(1+0.1)^9)+(DCF!$B$17*(1+DCF!$B$18)^2*(1+DCF!$B$19)^3*(1+DCF!$B$20)^5/(1+0.1)^10)+((DCF!$B$17*(1+DCF!$B$18)^2*(1+DCF!$B$19)^3*(1+DCF!$B$20)^5*(1+0.04)/(0.1-0.04))/(1+0.1)^10)-DCF!$B$43)*1000/'Executive Summary'!$B$20 -> 357.62558
A15: Yellow = Base Case

Sheet Historical
A1: HISTORICAL FINANCIAL SUMMARY - ACCENTURE (ACN)
A3: Metric | B3: FY2020 | C3: FY2021 | D3: FY2022 | E3: FY2023 | F3: FY2024 | G3: FY2025
A4: Revenue ($B) | B4: 43.2 | C4: 50.5 | D4: 61.6 | E4: 64.1 | F4: 64.9 | G4: 69.67
A5: Revenue Growth | B5: - | C5: =C4/B4-1 -> 0.16898148 | D5: =D4/C4-1 -> 0.21980198 | E5: =E4/D4-1 -> 0.040584416 | F5: =F4/E4-1 -> 0.012480499 | G5: =G4/F4-1 -> 0.073497689
A6: Operating Income ($B) | B6: 6.1 | C6: 7.6 | D6: 9.1 | E6: 9.1 | F6: 9.8 | G6: 10.6
A7: Operating Margin | B7: =B6/B4 -> 0.1412037 | C7: =C6/C4 -> 0.15049505 | D7: =D6/D4 -> 0.14772727 | E7: =E6/E4 -> 0.14196568 | F7: =F6/F4 -> 0.15100154 | G7: =G6/G4 -> 0.15214583
A8: Net Income ($B) | B8: 5.1 | C8: 5.9 | D8: 6.9 | E8: 6.9 | F8: 7.3 | G8: 7.7
A9: Net Margin | B9: =B8/B4 -> 0.11805556 | C9: =C8/C4 -> 0.11683168 | D9: =D8/D4 -> 0.11201299 | E9: =E8/E4 -> 0.10764431 | F9: =F8/F4 -> 0.11248074 | G9: =G8/G4 -> 0.11052103
A10: EPS (Diluted) | B10: 7.89 | C10: 9.16 | D10: 10.71 | E10: 10.77 | F10: 11.44 | G10: 12.29
A11: Free Cash Flow ($B) | B11: 7.1 | C11: 8.4 | D11: 8.8 | E11: 9 | F11: 8.6 | G11: 9.5
A12: FCF Margin | B12: =B11/B4 -> 0.16435185 | C12: =C11/C4 -> 0.16633663 | D12: =D11/D4 -> 0.14285714 | E12: =E11/E4 -> 0.14040562 | F12: =F11/F4 -> 0.13251156 | G12: =G11/G4 -> 0.13635711
A13: Dividends per Share | B13: 3.2 | C13: 3.52 | D13: 3.88 | E13: 4.48 | F13: 5 | G13: 5.92
A14: Shares Outstanding (M) | B14: 643 | C14: 639 | D14: 635 | E14: 632 | F14: 629 | G14: 623
A17: KEY RATIOS & METRICS
A18: 5-Year Revenue CAGR | B18: =((G4/B4)^(1/5))-1 -> 0.10030329
A19: 5-Year EPS CAGR | B19: =((G10/B10)^(1/5))-1 -> 0.092684987
A20: 5-Year FCF CAGR | B20: =((G11/B11)^(1/5))-1 -> 0.059968725
A21: Avg Operating Margin | B21: =AVERAGE(B7:G7) -> 0.14742318
A22: Avg FCF Margin | B22: =AVERAGE(B12:G12) -> 0.14713665

Sheet Notes
A1: MODEL NOTES & DATA SOURCES
A3: DATA SOURCES
A4: 1. Financial data: Accenture Q4 FY2025 Earnings Release (September 25, 2025)
A5: 2. Stock price data: NYSE as of December 5, 2025
A6: 3. Analyst estimates: Bloomberg, FactSet consensus
A7: 4. Beta: 5-year monthly regression vs S&P 500
A8: 5. Risk-free rate: 10-Year US Treasury yield
A9: 6. Market risk premium: Damodaran historical equity premium
A12: KEY ASSUMPTIONS
A13: • Historical growth rates: EPS 10.8%, Equity 18.2%, FCF 11.2%, Revenue 8.5%
A14: • Near-term FCF growth assumes 10% (slightly below historical 11.2%)
A15: • Mid-term growth of 8% reflects strong revenue growth track record
... A39: growth assumptions to account for estimation uncertainty.
