Workbook

Sheet Model_Info
A1: Ticker | B1: ATO
A2: Company | B2: Atmos Energy Corporation
A3: Valuation date | B3: 2026-09-26
A4: Current price (USD) | B4: 157.21
A5: Price as of | B5: 2026-09-25T20:00:03Z regular close (Yahoo Finance chart API)
A6: Balance sheet date | B6: 2026-03-31 (Q2 FY2026 10-Q; latest balance sheet extracted -- Q3 FY2026 10-Q results are cited qualitatively in the Analysis JSON from the August 2026 earnings release but were not yet in the XBRL-parsed core_metrics table at build time)
A7: Currency / Quote currency | B7: USD / USD
A8: Model | B8: Regulated-utility dividend discount model: EPS/dividend growth at cost of equity, exit-P/E capped terminal value (hand-built, non-component route)
A9: Engine | B9: Hand-built (non-component route) -- regulated-utility DDM, see .claude/skills/dcf-methods/SKILL.md
A10: Shares outstanding (diluted, millions) | B10: 169.374
A11: Total debt (millions) | B11: 10251.258
A12: Cash (millions) | B12: 520.953
A13: Net debt (millions, NOT subtracted -- see notes) | B13: 9730.305
A14: Source JSON | B14: ATO_DCF.json
A16: Method note | B16: NOT a WACC-discounted owner-FCF model. Atmos is a fully regulated natural-gas distribution/transmission utility (Analysis JSON) whose reported OCF is deliberately and structurally exhausted (and exceeded) by a ~$4.2B/yr rate-base capex program funded by continuous debt AND equity issuance -- FY2025 OCF of $2,049M against guided FY2026 capex of ~$4,200M, with total debt more than tripling since FY2018 and shares outstanding up ~53% over the same period via ATM equity raises. 'Free cash flow' in this business is a capex-timing artifact, not a signal, exactly the pattern the dcf-methods skill flags for REITs/banks/land subdividers: the owner-FCF engine's SBC/capex/working-capital machinery does not fit a company whose entire growth algorithm is 'invest more in rate base, earn allowed ROE on it, finance the gap externally.' Instead this model discounts the flow that actually accrues to equity holders post-financing-cost -- dividends per share on the company's own guided EPS growth path -- at the COST OF EQUITY, and never subtracts net debt again (interest expense is already inside the EPS/dividend flow, exactly as for the AFFO/residual-income/BVPS-compounding families in .claude/skills/dcf-methods/SKILL.md). Cost of equity built bottom-up: 10-year UST ~5.0-5.2% as of 2026-09-25 (Yahoo ^TNX) + a utility equity spread of ~2.0pp base case (low-beta ~0.55-0.65 regulated gas LDC; CAPM cross-check: rf 5.0% + beta 0.6 x broad ERP ~7.5% implies ~9.5% unlevered-style, moderated down for the bond-proxy, AA-adjacent-credit, highly regulated cash-flow character investors actually price ATO on -- 7.0% base is consistent with where utility dividend yields + guided growth trade today). Bull case lowers CoE to 6.0% (rate relief / spread compression); bear case raises it to 8.5% (rates stay higher-for-longer, funding costs and dilution cost rise, as flagged as a financial risk in the Analysis JSON).

Sheet Actuals
A1: FY | B1: Revenue ($M) | C1: Net income ($M) | D1: Diluted EPS ($) | E1: Shareholders' equity ($M) | F1: Shares outstanding (M) | G1: Total debt ($M) | H1: Cash ($M) | I1: Book value/share ($)
A2: 2015 | C2: 315.075 | D2: 3.09 | E2: 3194.797 | F2: 101.892 | G2: 2437.515 | H2: 28.653 | I2: =E2/F2 -> 31.354738
A3: 2016 | B3: 2454.648 | C3: 350.104 | D3: 3.38 | E3: 3463.059 | F3: 103.524 | G3: 2438.779 | H3: 47.534 | I3: =E3/F3 -> 33.45175
A4: 2017 | B4: 2759.735 | C4: 396.421 | D4: 3.73 | E4: 3898.666 | F4: 106.1 | G4: 3067.045 | H4: 26.409 | I4: =E4/F4 -> 36.745203
A5: 2018 | B5: 3115.546 | C5: 603.064 | D5: 5.43 | E5: 4769.951 | F5: 111.012 | G5: 3068.665 | H5: 13.771 | I5: =E5/F5 -> 42.967886
A6: 2019 | B6: 2901.848 | C6: 511.406 | D6: 4.35 | E6: 5750.223 | F6: 117.461 | G6: 3529.452 | H6: 24.55 | I6: =E6/F6 -> 48.954317
A7: 2020 | B7: 2821.137 | C7: 601.443 | D7: 4.89 | E7: 6791.203 | F7: 122.872 | G7: 4531.944 | H7: 20.808 | I7: =E7/F7 -> 55.27055
A8: 2021 | B8: 3407.49 | C8: 665.563 | D8: 5.12 | E8: 7906.889 | F8: 129.834 | G8: 7330.657 | H8: 116.723 | I8: =E8/F8 -> 60.899988
A9: 2022 | B9: 4201.662 | C9: 774.398 | D9: 5.6 | E9: 9419.091 | F9: 138.096 | G9: 7962.104 | H9: 51.554 | I9: =E9/F9 -> 68.206834
A10: 2023 | B10: 4275.357 | C10: 885.862 | D10: 6.1 | E10: 10870.064 | F10: 145.166 | G10: 6555.701 | H10: 15.404 | I10: =E10/F10 -> 74.880234
A11: 2024 | B11: 4165.187 | C11: 1042.895 | D11: 6.83 | E11: 12157.669 | F11: 152.666 | G11: 7785.297 | H11: 307.34 | I11: =E11/F11 -> 79.635734
A12: 2025 | B12: 4702.755 | C12: 1198.754 | D12: 7.46 | E12: 13558.89 | F12: 160.573 | G12: 8918.944 | H12: 202.687 | I12: =E12/F12 -> 84.440659
A14: Q2 FY2026 (latest, 10-Q, 2026-03-31)
A15: Shares outstanding (M) | B15: 169.374
A16: Total debt ($M) | B16: 10251.258
A17: Cash ($M) | B17: 520.953
A18: Shareholders' equity ($M) | B18: 15258.058

Sheet Assumptions
A1: Driver | B1: Y1 | C1: Y2 | D1: Y3 | E1: Y4 | F1: Y5 | G1: Y6 | H1: Y7 | I1: Y8 | J1: Y9 | K1: Y10 | L1: Notes
A2: EPS growth rate (%) -- BASE | B2: 0.075 | C2: 0.07 | D2: 0.07 | E2: 0.065 | F2: 0.065 | G2: 0.06 | H2: 0.06 | I2: 0.055 | J2: 0.055 | K2: 0.05
A3: Payout ratio (%) -- BASE | B3: 0.47 | C3: 0.475 | D3: 0.48 | E3: 0.485 | F3: 0.49 | G3: 0.495 | H3: 0.5 | I3: 0.5 | J3: 0.5 | K3: 0.5
A5: EPS growth rate (%) -- BULL | B5: 0.085 | C5: 0.08 | D5: 0.08 | E5: 0.075 | F5: 0.075 | G5: 0.07 | H5: 0.07 | I5: 0.065 | J5: 0.065 | K5: 0.06
A6: Payout ratio (%) -- BULL | B6: 0.47 | C6: 0.475 | D6: 0.48 | E6: 0.485 | F6: 0.49 | G6: 0.495 | H6: 0.5 | I6: 0.505 | J6: 0.51 | K6: 0.515
A8: EPS growth rate (%) -- BEAR | B8: 0.05 | C8: 0.045 | D8: 0.045 | E8: 0.04 | F8: 0.04 | G8: 0.035 | H8: 0.035 | I8: 0.03 | J8: 0.03 | K8: 0.03
A9: Payout ratio (%) -- BEAR | B9: 0.47 | C9: 0.465 | D9: 0.46 | E9: 0.455 | F9: 0.45 | G9: 0.445 | H9: 0.44 | I9: 0.44 | J9: 0.44 | K9: 0.44
A11: Current price (USD) | B11: 157.21
A12: Shares outstanding, diluted (M) | B12: 169.374
A13: Total debt (M, disclosure only) | B13: 10251.258
A14: Cash (M, disclosure only) | B14: 520.953
A15: Net debt (M, NOT subtracted -- see Model_Info) | B15: 9730.305
A16: FY0 EPS (guidance midpoint, $) | B16: 8.45
A17: FY0 annualized dividend ($) | B17: 4
A18: Cost of equity -- BASE | B18: 0.07
A19: Cost of equity -- BULL | B19: 0.06
A20: Cost of equity -- BEAR | B20: 0.085
A21: Terminal dividend growth -- BASE | B21: 0.04
A22: Terminal dividend growth -- BULL | B22: 0.045
... A30: Probability weight -- Bull | B30: 0.25

Sheet DCF_Base
A1: Line | B1: Y1 | C1: Y2 | D1: Y3 | E1: Y4 | F1: Y5 | G1: Y6 | H1: Y7 | I1: Y8 | J1: Y9 | K1: Y10
A2: EPS growth rate | B2: =Assumptions!B2 -> 0.075 | C2: =Assumptions!C2 -> 0.07 | D2: =Assumptions!D2 -> 0.07 | E2: =Assumptions!E2 -> 0.065 | F2: =Assumptions!F2 -> 0.065 | G2: =Assumptions!G2 -> 0.06 | H2: =Assumptions!H2 -> 0.06 | I2: =Assumptions!I2 -> 0.055 | ... K2: =Assumptions!K2 -> 0.05
A3: EPS ($) | B3: =Assumptions!$B$16*(1+B2) -> 9.08375 | C3: =B3*(1+C2) -> 9.7196125 | D3: =C3*(1+D2) -> 10.399985 | E3: =D3*(1+E2) -> 11.075984 | F3: =E3*(1+F2) -> 11.795923 | G3: =F3*(1+G2) -> 12.503679 | H3: =G3*(1+H2) -> 13.2539 | I3: =H3*(1+I2) -> 13.982864 | J3: =I3*(1+J2) -> 14.751922 | K3: =J3*(1+K2) -> 15.489518
A4: Payout ratio | B4: =Assumptions!B3 -> 0.47 | C4: =Assumptions!C3 -> 0.475 | D4: =Assumptions!D3 -> 0.48 | E4: =Assumptions!E3 -> 0.485 | F4: =Assumptions!F3 -> 0.49 | G4: =Assumptions!G3 -> 0.495 | H4: =Assumptions!H3 -> 0.5 | I4: =Assumptions!I3 -> 0.5 | ... K4: =Assumptions!K3 -> 0.5
A5: Dividend per share ($) | B5: =B3*B4 -> 4.2693625 | C5: =C3*C4 -> 4.6168159 | D5: =D3*D4 -> 4.991993 | E5: =E3*E4 -> 5.3718524 | F5: =F3*F4 -> 5.7800025 | G5: =G3*G4 -> 6.189321 | H5: =H3*H4 -> 6.6269498 | I5: =I3*I4 -> 6.991432 | ... K5: =K3*K4 -> 7.7447588
A6: Discount factor | B6: =1/(1+Assumptions!$B$18)^1 -> 0.93457944 | C6: =1/(1+Assumptions!$B$18)^2 -> 0.87343873 | D6: =1/(1+Assumptions!$B$18)^3 -> 0.81629788 | E6: =1/(1+Assumptions!$B$18)^4 -> 0.76289521 | F6: =1/(1+Assumptions!$B$18)^5 -> 0.71298618 | G6: =1/(1+Assumptions!$B$18)^6 -> 0.66634222 | H6: =1/(1+Assumptions!$B$18)^7 -> 0.62274974 | I6: =1/(1+Assumptions!$B$18)^8 -> 0.5820091 | J6: =1/(1+Assumptions!$B$18)^9 -> 0.54393374 | K6: =1/(1+Assumptions!$B$18)^10 -> 0.50834929
A7: PV of dividend ($) | B7: =B5*B6 -> 3.9900584 | C7: =C5*C6 -> 4.0325058 | D7: =D5*D6 -> 4.0749533 | E7: =E5*E6 -> 4.0981605 | F7: =F5*F6 -> 4.1210619 | G7: =G5*G6 -> 4.1242059 | H7: =H5*H6 -> 4.1269313 | I7: =I5*I6 -> 4.0690771 | ... K7: =K5*K6 -> 3.9370427
A9: Sum PV(dividends), Y1-10 | B9: =SUM(B7:K7) -> 40.586031
A10: Terminal EPS (Y10) | B10: =K3 -> 15.489518
A11: Terminal value (Gordon on Y10 dividend) | B11: =K5*(1+Assumptions!$B$21)/(Assumptions!$B$18-Assumptions!$B$21) -> 268.48497
A12: Terminal value (exit P/E x terminal EPS) | B12: =Assumptions!$B$24*B10 -> 294.30083
A13: Terminal value (MIN of the two, floored at 0) | B13: =MAX(0,MIN(B11,B12)) -> 268.48497
A14: PV of terminal value | B14: =B13*K6 -> 136.48415
A16: VALUE PER SHARE (Sum PV div + PV terminal) | B16: =B9+B14 -> 177.07018
A17: Terminal value % of total value | B17: =B14/B16 -> 0.77079127
A19: -- Entry price at 15% hurdle (TV rebuilt at hurdle) --
A20: Discount factor @ hurdle | B20: =1/(1+Assumptions!$B$27)^1 -> 0.86956522 | C20: =1/(1+Assumptions!$B$27)^2 -> 0.75614367 | D20: =1/(1+Assumptions!$B$27)^3 -> 0.65751623 | E20: =1/(1+Assumptions!$B$27)^4 -> 0.57175325 | F20: =1/(1+Assumptions!$B$27)^5 -> 0.49717674 | G20: =1/(1+Assumptions!$B$27)^6 -> 0.4323276 | H20: =1/(1+Assumptions!$B$27)^7 -> 0.37593704 | I20: =1/(1+Assumptions!$B$27)^8 -> 0.32690177 | J20: =1/(1+Assumptions!$B$27)^9 -> 0.28426241 | K20: =1/(1+Assumptions!$B$27)^10 -> 0.24718471
A21: PV of dividend @ hurdle | B21: =B5*B20 -> 3.7124891 | C21: =C5*C20 -> 3.4909761 | D21: =D5*D20 -> 3.2823164 | E21: =E5*E20 -> 3.0713741 | F21: =F5*F20 -> 2.8736828 | G21: =G5*G20 -> 2.6758143 | H21: =H5*H20 -> 2.4913159 | I21: =I5*I20 -> 2.2855115 | ... K21: =K5*K20 -> 1.9143859
A22: Sum PV(dividends) @ hurdle | B22: =SUM(B21:K21) -> 27.894575
A23: Terminal value @ hurdle (Gordon on Y10 div) | B23: =K5*(1+Assumptions!$B$21)/(Assumptions!$B$27-Assumptions!$B$21) -> 73.223174
A24: Terminal value @ hurdle (exit P/E cap) | B24: =Assumptions!$B$24*B10 -> 294.30083
A25: Terminal value @ hurdle (MIN, floored at 0) | B25: =MAX(0,MIN(B23,B24)) -> 73.223174
A26: PV of terminal value @ hurdle | B26: =B25*K20 -> 18.099649
A28: ENTRY PRICE @ 15% HURDLE | B28: =B22+B26 -> 45.994223

Sheet DCF_Bull
A1: Line | B1: Y1 | C1: Y2 | D1: Y3 | E1: Y4 | F1: Y5 | G1: Y6 | H1: Y7 | I1: Y8 | J1: Y9 | K1: Y10
A2: EPS growth rate | B2: =Assumptions!B5 -> 0.085 | C2: =Assumptions!C5 -> 0.08 | D2: =Assumptions!D5 -> 0.08 | E2: =Assumptions!E5 -> 0.075 | F2: =Assumptions!F5 -> 0.075 | G2: =Assumptions!G5 -> 0.07 | H2: =Assumptions!H5 -> 0.07 | I2: =Assumptions!I5 -> 0.065 | ... K2: =Assumptions!K5 -> 0.06
A3: EPS ($) | B3: =Assumptions!$B$16*(1+B2) -> 9.16825 | C3: =B3*(1+C2) -> 9.90171 | D3: =C3*(1+D2) -> 10.693847 | E3: =D3*(1+E2) -> 11.495885 | F3: =E3*(1+F2) -> 12.358077 | G3: =F3*(1+G2) -> 13.223142 | H3: =G3*(1+H2) -> 14.148762 | I3: =H3*(1+I2) -> 15.068432 | J3: =I3*(1+J2) -> 16.04788 | K3: =J3*(1+K2) -> 17.010752
A4: Payout ratio | B4: =Assumptions!B6 -> 0.47 | C4: =Assumptions!C6 -> 0.475 | D4: =Assumptions!D6 -> 0.48 | E4: =Assumptions!E6 -> 0.485 | F4: =Assumptions!F6 -> 0.49 | G4: =Assumptions!G6 -> 0.495 | H4: =Assumptions!H6 -> 0.5 | I4: =Assumptions!I6 -> 0.505 | ... K4: =Assumptions!K6 -> 0.515
A5: Dividend per share ($) | B5: =B3*B4 -> 4.3090775 | C5: =C3*C4 -> 4.7033122 | D5: =D3*D4 -> 5.1330465 | E5: =E3*E4 -> 5.5755044 | F5: =F3*F4 -> 6.0554576 | G5: =G3*G4 -> 6.5454553 | H5: =H3*H4 -> 7.074381 | I5: =I3*I4 -> 7.6095579 | ... K5: =K3*K4 -> 8.7605375
A6: Discount factor | B6: =1/(1+Assumptions!$B$19)^1 -> 0.94339623 | C6: =1/(1+Assumptions!$B$19)^2 -> 0.88999644 | D6: =1/(1+Assumptions!$B$19)^3 -> 0.83961928 | E6: =1/(1+Assumptions!$B$19)^4 -> 0.79209366 | F6: =1/(1+Assumptions!$B$19)^5 -> 0.74725817 | G6: =1/(1+Assumptions!$B$19)^6 -> 0.70496054 | H6: =1/(1+Assumptions!$B$19)^7 -> 0.66505711 | I6: =1/(1+Assumptions!$B$19)^8 -> 0.62741237 | J6: =1/(1+Assumptions!$B$19)^9 -> 0.59189846 | K6: =1/(1+Assumptions!$B$19)^10 -> 0.55839478
A7: PV of dividend ($) | B7: =B5*B6 -> 4.0651675 | C7: =C5*C6 -> 4.1859312 | D7: =D5*D6 -> 4.3098048 | E7: =E5*E6 -> 4.4163217 | F7: =F5*F6 -> 4.5249902 | G7: =G5*G6 -> 4.6142877 | H7: =H5*H6 -> 4.7048674 | I7: =I5*I6 -> 4.7743308 | ... K7: =K5*K6 -> 4.8918384
A9: Sum PV(dividends), Y1-10 | B9: =SUM(B7:K7) -> 45.331884
A10: Terminal EPS (Y10) | B10: =K3 -> 17.010752
A11: Terminal value (Gordon on Y10 dividend) | B11: =K5*(1+Assumptions!$B$22)/(Assumptions!$B$19-Assumptions!$B$22) -> 610.31744
A12: Terminal value (exit P/E x terminal EPS) | B12: =Assumptions!$B$25*B10 -> 357.2258
A13: Terminal value (MIN of the two, floored at 0) | B13: =MAX(0,MIN(B11,B12)) -> 357.2258
A14: PV of terminal value | B14: =B13*K6 -> 199.47302
A16: VALUE PER SHARE (Sum PV div + PV terminal) | B16: =B9+B14 -> 244.80491
A17: Terminal value % of total value | B17: =B14/B16 -> 0.81482444
A19: -- Entry price at 15% hurdle (TV rebuilt at hurdle) --
A20: Discount factor @ hurdle | B20: =1/(1+Assumptions!$B$27)^1 -> 0.86956522 | C20: =1/(1+Assumptions!$B$27)^2 -> 0.75614367 | D20: =1/(1+Assumptions!$B$27)^3 -> 0.65751623 | E20: =1/(1+Assumptions!$B$27)^4 -> 0.57175325 | F20: =1/(1+Assumptions!$B$27)^5 -> 0.49717674 | G20: =1/(1+Assumptions!$B$27)^6 -> 0.4323276 | H20: =1/(1+Assumptions!$B$27)^7 -> 0.37593704 | I20: =1/(1+Assumptions!$B$27)^8 -> 0.32690177 | J20: =1/(1+Assumptions!$B$27)^9 -> 0.28426241 | K20: =1/(1+Assumptions!$B$27)^10 -> 0.24718471
A21: PV of dividend @ hurdle | B21: =B5*B20 -> 3.7470239 | C21: =C5*C20 -> 3.5563798 | D21: =D5*D20 -> 3.3750614 | E21: =E5*E20 -> 3.1878127 | F21: =F5*F20 -> 3.0106326 | G21: =G5*G20 -> 2.829781 | H21: =H5*H20 -> 2.6595219 | I21: =I5*I20 -> 2.487578 | ... K21: =K5*K20 -> 2.1654709
A22: Sum PV(dividends) @ hurdle | B22: =SUM(B21:K21) -> 29.345785
A23: Terminal value @ hurdle (Gordon on Y10 div) | B23: =K5*(1+Assumptions!$B$22)/(Assumptions!$B$27-Assumptions!$B$22) -> 87.188206
A24: Terminal value @ hurdle (exit P/E cap) | B24: =Assumptions!$B$25*B10 -> 357.2258
A25: Terminal value @ hurdle (MIN, floored at 0) | B25: =MAX(0,MIN(B23,B24)) -> 87.188206
A26: PV of terminal value @ hurdle | B26: =B25*K20 -> 21.551591
A28: ENTRY PRICE @ 15% HURDLE | B28: =B22+B26 -> 50.897376

Sheet DCF_Bear
A1: Line | B1: Y1 | C1: Y2 | D1: Y3 | E1: Y4 | F1: Y5 | G1: Y6 | H1: Y7 | I1: Y8 | J1: Y9 | K1: Y10
A2: EPS growth rate | B2: =Assumptions!B8 -> 0.05 | C2: =Assumptions!C8 -> 0.045 | D2: =Assumptions!D8 -> 0.045 | E2: =Assumptions!E8 -> 0.04 | F2: =Assumptions!F8 -> 0.04 | G2: =Assumptions!G8 -> 0.035 | H2: =Assumptions!H8 -> 0.035 | I2: =Assumptions!I8 -> 0.03 | ... K2: =Assumptions!K8 -> 0.03
A3: EPS ($) | B3: =Assumptions!$B$16*(1+B2) -> 8.8725 | C3: =B3*(1+C2) -> 9.2717625 | D3: =C3*(1+D2) -> 9.6889918 | E3: =D3*(1+E2) -> 10.076551 | F3: =E3*(1+F2) -> 10.479614 | G3: =F3*(1+G2) -> 10.8464 | H3: =G3*(1+H2) -> 11.226024 | I3: =H3*(1+I2) -> 11.562805 | J3: =I3*(1+J2) -> 11.909689 | K3: =J3*(1+K2) -> 12.26698
A4: Payout ratio | B4: =Assumptions!B9 -> 0.47 | C4: =Assumptions!C9 -> 0.465 | D4: =Assumptions!D9 -> 0.46 | E4: =Assumptions!E9 -> 0.455 | F4: =Assumptions!F9 -> 0.45 | G4: =Assumptions!G9 -> 0.445 | H4: =Assumptions!H9 -> 0.44 | I4: =Assumptions!I9 -> 0.44 | ... K4: =Assumptions!K9 -> 0.44
A5: Dividend per share ($) | B5: =B3*B4 -> 4.170075 | C5: =C3*C4 -> 4.3113696 | D5: =D3*D4 -> 4.4569362 | E5: =E3*E4 -> 4.5848309 | F5: =F3*F4 -> 4.7158261 | G5: =G3*G4 -> 4.826648 | H5: =H3*H4 -> 4.9394506 | I5: =I3*I4 -> 5.0876341 | ... K5: =K3*K4 -> 5.397471
A6: Discount factor | B6: =1/(1+Assumptions!$B$20)^1 -> 0.92165899 | C6: =1/(1+Assumptions!$B$20)^2 -> 0.84945529 | D6: =1/(1+Assumptions!$B$20)^3 -> 0.7829081 | E6: =1/(1+Assumptions!$B$20)^4 -> 0.72157428 | F6: =1/(1+Assumptions!$B$20)^5 -> 0.66504542 | G6: =1/(1+Assumptions!$B$20)^6 -> 0.61294509 | H6: =1/(1+Assumptions!$B$20)^7 -> 0.56492635 | I6: =1/(1+Assumptions!$B$20)^8 -> 0.52066945 | J6: =1/(1+Assumptions!$B$20)^9 -> 0.47987968 | K6: =1/(1+Assumptions!$B$20)^10 -> 0.44228542
A7: PV of dividend ($) | B7: =B5*B6 -> 3.8433871 | C7: =C5*C6 -> 3.6623157 | D7: =D5*D6 -> 3.4893715 | E7: =E5*E6 -> 3.3082961 | F7: =F5*F6 -> 3.1362386 | G7: =G5*G6 -> 2.9584702 | H7: =H5*H6 -> 2.7904258 | I7: =I5*I6 -> 2.6489756 | ... K7: =K5*K6 -> 2.3872227
A9: Sum PV(dividends), Y1-10 | B9: =SUM(B7:K7) -> 30.739399
A10: Terminal EPS (Y10) | B10: =K3 -> 12.26698
A11: Terminal value (Gordon on Y10 dividend) | B11: =K5*(1+Assumptions!$B$23)/(Assumptions!$B$20-Assumptions!$B$23) -> 101.07991
A12: Terminal value (exit P/E x terminal EPS) | B12: =Assumptions!$B$26*B10 -> 184.00469
A13: Terminal value (MIN of the two, floored at 0) | B13: =MAX(0,MIN(B11,B12)) -> 101.07991
A14: PV of terminal value | B14: =B13*K6 -> 44.706171
A16: VALUE PER SHARE (Sum PV div + PV terminal) | B16: =B9+B14 -> 75.44557
A17: Terminal value % of total value | B17: =B14/B16 -> 0.59256191
A19: -- Entry price at 15% hurdle (TV rebuilt at hurdle) --
A20: Discount factor @ hurdle | B20: =1/(1+Assumptions!$B$27)^1 -> 0.86956522 | C20: =1/(1+Assumptions!$B$27)^2 -> 0.75614367 | D20: =1/(1+Assumptions!$B$27)^3 -> 0.65751623 | E20: =1/(1+Assumptions!$B$27)^4 -> 0.57175325 | F20: =1/(1+Assumptions!$B$27)^5 -> 0.49717674 | G20: =1/(1+Assumptions!$B$27)^6 -> 0.4323276 | H20: =1/(1+Assumptions!$B$27)^7 -> 0.37593704 | I20: =1/(1+Assumptions!$B$27)^8 -> 0.32690177 | J20: =1/(1+Assumptions!$B$27)^9 -> 0.28426241 | K20: =1/(1+Assumptions!$B$27)^10 -> 0.24718471
A21: PV of dividend @ hurdle | B21: =B5*B20 -> 3.6261522 | C21: =C5*C20 -> 3.2600148 | D21: =D5*D20 -> 2.9305079 | E21: =E5*E20 -> 2.621392 | F21: =F5*F20 -> 2.344599 | G21: =G5*G20 -> 2.0866931 | H21: =H5*H20 -> 1.8569224 | I21: =I5*I20 -> 1.6631566 | ... K21: =K5*K20 -> 1.3341723
A22: Sum PV(dividends) @ hurdle | B22: =SUM(B21:K21) -> 23.21322
A23: Terminal value @ hurdle (Gordon on Y10 div) | B23: =K5*(1+Assumptions!$B$23)/(Assumptions!$B$27-Assumptions!$B$23) -> 46.328293
A24: Terminal value @ hurdle (exit P/E cap) | B24: =Assumptions!$B$26*B10 -> 184.00469
A25: Terminal value @ hurdle (MIN, floored at 0) | B25: =MAX(0,MIN(B23,B24)) -> 46.328293
A26: PV of terminal value @ hurdle | B26: =B25*K20 -> 11.451645
A28: ENTRY PRICE @ 15% HURDLE | B28: =B22+B26 -> 34.664866

Sheet Valuation
A1: Scenario | B1: Intrinsic value ($/sh) | C1: Entry price @15% ($/sh) | D1: Weight | E1: Upside vs current
A2: Bear | B2: =DCF_Bear!B16 -> 75.44557 | C2: =DCF_Bear!B28 -> 34.664866 | D2: =Assumptions!$B$28 -> 0.25 | E2: =B2/Assumptions!$B$11-1 -> -0.52009688
A3: Base | B3: =DCF_Base!B16 -> 177.07018 | C3: =DCF_Base!B28 -> 45.994223 | D3: =Assumptions!$B$29 -> 0.5 | E3: =B3/Assumptions!$B$11-1 -> 0.12632896
A4: Bull | B4: =DCF_Bull!B16 -> 244.80491 | C4: =DCF_Bull!B28 -> 50.897376 | D4: =Assumptions!$B$30 -> 0.25 | E4: =B4/Assumptions!$B$11-1 -> 0.55718405
A5: WEIGHTED (SUMPRODUCT) | B5: =SUMPRODUCT(B2:B4,D2:D4) -> 168.59771 | C5: =SUMPRODUCT(C2:C4,D2:D4) -> 44.387672 | E5: =B5/Assumptions!$B$11-1 -> 0.072436275
A7: Current price | B7: =Assumptions!$B$11 -> 157.21
A9: Required-return table (BASE case, TV rebuilt at each rate)
A10: Required return | B10: 6% | C10: 7% | D10: 8% | E10: 9% | F10: 10% | G10: 12% | H10: 15%
A11: Value per share ($) | B11: =SUMPRODUCT(DCF_Base!B5:K5,1/(1+0.06)^{1,2,3,4,5,6,7,8,9,10})+MAX(0,MIN(DCF_Base!K5*(1+Assumptions!$B$21)/(0.06-Assumptions!$B$21),Assumptions!$B$24*DCF_Base!K3))/(1+0.06)^10 -> 207.08573 | C11: =SUMPRODUCT(DCF_Base!B5:K5,1/(1+0.07)^{1,2,3,4,5,6,7,8,9,10})+MAX(0,MIN(DCF_Base!K5*(1+Assumptions!$B$21)/(0.07-Assumptions!$B$21),Assumptions!$B$24*DCF_Base!K3))/(1+0.07)^10 -> 177.07018 | D11: =SUMPRODUCT(DCF_Base!B5:K5,1/(1+0.08)^{1,2,3,4,5,6,7,8,9,10})+MAX(0,MIN(DCF_Base!K5*(1+Assumptions!$B$21)/(0.08-Assumptions!$B$21),Assumptions!$B$24*DCF_Base!K3))/(1+0.08)^10 -> 131.84818 | E11: =SUMPRODUCT(DCF_Base!B5:K5,1/(1+0.09)^{1,2,3,4,5,6,7,8,9,10})+MAX(0,MIN(DCF_Base!K5*(1+Assumptions!$B$21)/(0.09-Assumptions!$B$21),Assumptions!$B$24*DCF_Base!K3))/(1+0.09)^10 -> 104.75818 | F11: =SUMPRODUCT(DCF_Base!B5:K5,1/(1+0.1)^{1,2,3,4,5,6,7,8,9,10})+MAX(0,MIN(DCF_Base!K5*(1+Assumptions!$B$21)/(0.1-Assumptions!$B$21),Assumptions!$B$24*DCF_Base!K3))/(1+0.1)^10 -> 86.731616 | G11: =SUMPRODUCT(DCF_Base!B5:K5,1/(1+0.12)^{1,2,3,4,5,6,7,8,9,10})+MAX(0,MIN(DCF_Base!K5*(1+Assumptions!$B$21)/(0.12-Assumptions!$B$21),Assumptions!$B$24*DCF_Base!K3))/(1+0.12)^10 -> 64.266705 | H11: =SUMPRODUCT(DCF_Base!B5:K5,1/(1+0.15)^{1,2,3,4,5,6,7,8,9,10})+MAX(0,MIN(DCF_Base!K5*(1+Assumptions!$B$21)/(0.15-Assumptions!$B$21),Assumptions!$B$24*DCF_Base!K3))/(1+0.15)^10 -> 45.994223
A13: Check: 7% row = Base IV; 15% row = Base entry price
A15: Sensitivity: Cost of equity (rows) x Terminal dividend growth (cols) -- BASE case
A16: CoE \ g | B16: 2% | C16: 3% | D16: 4% | E16: 5% | F16: 6%
A17: 5% | B17: =SUMPRODUCT(DCF_Base!B5:K5,1/(1+0.05)^{1,2,3,4,5,6,7,8,9,10})+IF(0.02>=0.05,Assumptions!$B$24*DCF_Base!K3,MAX(0,MIN(DCF_Base!K5*(1+0.02)/(0.05-0.02),Assumptions!$B$24*DCF_Base!K3)))/(1+0.05)^10 -> 206.74039 | C17: =SUMPRODUCT(DCF_Base!B5:K5,1/(1+0.05)^{1,2,3,4,5,6,7,8,9,10})+IF(0.03>=0.05,Assumptions!$B$24*DCF_Base!K3,MAX(0,MIN(DCF_Base!K5*(1+0.03)/(0.05-0.03),Assumptions!$B$24*DCF_Base!K3)))/(1+0.05)^10 -> 225.75883 | D17: =SUMPRODUCT(DCF_Base!B5:K5,1/(1+0.05)^{1,2,3,4,5,6,7,8,9,10})+IF(0.04>=0.05,Assumptions!$B$24*DCF_Base!K3,MAX(0,MIN(DCF_Base!K5*(1+0.04)/(0.05-0.04),Assumptions!$B$24*DCF_Base!K3)))/(1+0.05)^10 -> 225.75883 | E17: =SUMPRODUCT(DCF_Base!B5:K5,1/(1+0.05)^{1,2,3,4,5,6,7,8,9,10})+IF(0.05>=0.05,Assumptions!$B$24*DCF_Base!K3,MAX(0,MIN(DCF_Base!K5*(1+0.05)/(0.05-0.05),Assumptions!$B$24*DCF_Base!K3)))/(1+0.05)^10 -> 225.75883 | F17: =SUMPRODUCT(DCF_Base!B5:K5,1/(1+0.05)^{1,2,3,4,5,6,7,8,9,10})+IF(0.06>=0.05,Assumptions!$B$24*DCF_Base!K3,MAX(0,MIN(DCF_Base!K5*(1+0.06)/(0.05-0.06),Assumptions!$B$24*DCF_Base!K3)))/(1+0.05)^10 -> 225.75883
A18: 6% | B18: =SUMPRODUCT(DCF_Base!B5:K5,1/(1+0.06)^{1,2,3,4,5,6,7,8,9,10})+IF(0.02>=0.06,Assumptions!$B$24*DCF_Base!K3,MAX(0,MIN(DCF_Base!K5*(1+0.02)/(0.06-0.02),Assumptions!$B$24*DCF_Base!K3)))/(1+0.06)^10 -> 153.02782 | C18: =SUMPRODUCT(DCF_Base!B5:K5,1/(1+0.06)^{1,2,3,4,5,6,7,8,9,10})+IF(0.03>=0.06,Assumptions!$B$24*DCF_Base!K3,MAX(0,MIN(DCF_Base!K5*(1+0.03)/(0.06-0.03),Assumptions!$B$24*DCF_Base!K3)))/(1+0.06)^10 -> 191.22874 | D18: =SUMPRODUCT(DCF_Base!B5:K5,1/(1+0.06)^{1,2,3,4,5,6,7,8,9,10})+IF(0.04>=0.06,Assumptions!$B$24*DCF_Base!K3,MAX(0,MIN(DCF_Base!K5*(1+0.04)/(0.06-0.04),Assumptions!$B$24*DCF_Base!K3)))/(1+0.06)^10 -> 207.08573 | E18: =SUMPRODUCT(DCF_Base!B5:K5,1/(1+0.06)^{1,2,3,4,5,6,7,8,9,10})+IF(0.05>=0.06,Assumptions!$B$24*DCF_Base!K3,MAX(0,MIN(DCF_Base!K5*(1+0.05)/(0.06-0.05),Assumptions!$B$24*DCF_Base!K3)))/(1+0.06)^10 -> 207.08573 | F18: =SUMPRODUCT(DCF_Base!B5:K5,1/(1+0.06)^{1,2,3,4,5,6,7,8,9,10})+IF(0.06>=0.06,Assumptions!$B$24*DCF_Base!K3,MAX(0,MIN(DCF_Base!K5*(1+0.06)/(0.06-0.06),Assumptions!$B$24*DCF_Base!K3)))/(1+0.06)^10 -> 207.08573
A19: 7% | B19: =SUMPRODUCT(DCF_Base!B5:K5,1/(1+0.07)^{1,2,3,4,5,6,7,8,9,10})+IF(0.02>=0.07,Assumptions!$B$24*DCF_Base!K3,MAX(0,MIN(DCF_Base!K5*(1+0.02)/(0.07-0.02),Assumptions!$B$24*DCF_Base!K3)))/(1+0.07)^10 -> 120.9017 | C19: =SUMPRODUCT(DCF_Base!B5:K5,1/(1+0.07)^{1,2,3,4,5,6,7,8,9,10})+IF(0.03>=0.07,Assumptions!$B$24*DCF_Base!K3,MAX(0,MIN(DCF_Base!K5*(1+0.03)/(0.07-0.03),Assumptions!$B$24*DCF_Base!K3)))/(1+0.07)^10 -> 141.96488 | D19: =SUMPRODUCT(DCF_Base!B5:K5,1/(1+0.07)^{1,2,3,4,5,6,7,8,9,10})+IF(0.04>=0.07,Assumptions!$B$24*DCF_Base!K3,MAX(0,MIN(DCF_Base!K5*(1+0.04)/(0.07-0.04),Assumptions!$B$24*DCF_Base!K3)))/(1+0.07)^10 -> 177.07018 | E19: =SUMPRODUCT(DCF_Base!B5:K5,1/(1+0.07)^{1,2,3,4,5,6,7,8,9,10})+IF(0.05>=0.07,Assumptions!$B$24*DCF_Base!K3,MAX(0,MIN(DCF_Base!K5*(1+0.05)/(0.07-0.05),Assumptions!$B$24*DCF_Base!K3)))/(1+0.07)^10 -> 190.19365 | F19: =SUMPRODUCT(DCF_Base!B5:K5,1/(1+0.07)^{1,2,3,4,5,6,7,8,9,10})+IF(0.06>=0.07,Assumptions!$B$24*DCF_Base!K3,MAX(0,MIN(DCF_Base!K5*(1+0.06)/(0.07-0.06),Assumptions!$B$24*DCF_Base!K3)))/(1+0.07)^10 -> 190.19365
A20: 8% | B20: =SUMPRODUCT(DCF_Base!B5:K5,1/(1+0.08)^{1,2,3,4,5,6,7,8,9,10})+IF(0.02>=0.08,Assumptions!$B$24*DCF_Base!K3,MAX(0,MIN(DCF_Base!K5*(1+0.02)/(0.08-0.02),Assumptions!$B$24*DCF_Base!K3)))/(1+0.08)^10 -> 99.562285 | C20: =SUMPRODUCT(DCF_Base!B5:K5,1/(1+0.08)^{1,2,3,4,5,6,7,8,9,10})+IF(0.03>=0.08,Assumptions!$B$24*DCF_Base!K3,MAX(0,MIN(DCF_Base!K5*(1+0.03)/(0.08-0.03),Assumptions!$B$24*DCF_Base!K3)))/(1+0.08)^10 -> 112.47664 | D20: =SUMPRODUCT(DCF_Base!B5:K5,1/(1+0.08)^{1,2,3,4,5,6,7,8,9,10})+IF(0.04>=0.08,Assumptions!$B$24*DCF_Base!K3,MAX(0,MIN(DCF_Base!K5*(1+0.04)/(0.08-0.04),Assumptions!$B$24*DCF_Base!K3)))/(1+0.08)^10 -> 131.84818 | E20: =SUMPRODUCT(DCF_Base!B5:K5,1/(1+0.08)^{1,2,3,4,5,6,7,8,9,10})+IF(0.05>=0.08,Assumptions!$B$24*DCF_Base!K3,MAX(0,MIN(DCF_Base!K5*(1+0.05)/(0.08-0.05),Assumptions!$B$24*DCF_Base!K3)))/(1+0.08)^10 -> 164.13408 | F20: =SUMPRODUCT(DCF_Base!B5:K5,1/(1+0.08)^{1,2,3,4,5,6,7,8,9,10})+IF(0.06>=0.08,Assumptions!$B$24*DCF_Base!K3,MAX(0,MIN(DCF_Base!K5*(1+0.06)/(0.08-0.06),Assumptions!$B$24*DCF_Base!K3)))/(1+0.08)^10 -> 174.89604
A21: 9% | B21: =SUMPRODUCT(DCF_Base!B5:K5,1/(1+0.09)^{1,2,3,4,5,6,7,8,9,10})+IF(0.02>=0.09,Assumptions!$B$24*DCF_Base!K3,MAX(0,MIN(DCF_Base!K5*(1+0.02)/(0.09-0.02),Assumptions!$B$24*DCF_Base!K3)))/(1+0.09)^10 -> 84.381601 | C21: =SUMPRODUCT(DCF_Base!B5:K5,1/(1+0.09)^{1,2,3,4,5,6,7,8,9,10})+IF(0.03>=0.09,Assumptions!$B$24*DCF_Base!K3,MAX(0,MIN(DCF_Base!K5*(1+0.03)/(0.09-0.03),Assumptions!$B$24*DCF_Base!K3)))/(1+0.09)^10 -> 92.871844 | D21: =SUMPRODUCT(DCF_Base!B5:K5,1/(1+0.09)^{1,2,3,4,5,6,7,8,9,10})+IF(0.04>=0.09,Assumptions!$B$24*DCF_Base!K3,MAX(0,MIN(DCF_Base!K5*(1+0.04)/(0.09-0.04),Assumptions!$B$24*DCF_Base!K3)))/(1+0.09)^10 -> 104.75818 | E21: =SUMPRODUCT(DCF_Base!B5:K5,1/(1+0.09)^{1,2,3,4,5,6,7,8,9,10})+IF(0.05>=0.09,Assumptions!$B$24*DCF_Base!K3,MAX(0,MIN(DCF_Base!K5*(1+0.05)/(0.09-0.05),Assumptions!$B$24*DCF_Base!K3)))/(1+0.09)^10 -> 122.5877 | F21: =SUMPRODUCT(DCF_Base!B5:K5,1/(1+0.09)^{1,2,3,4,5,6,7,8,9,10})+IF(0.06>=0.09,Assumptions!$B$24*DCF_Base!K3,MAX(0,MIN(DCF_Base!K5*(1+0.06)/(0.09-0.06),Assumptions!$B$24*DCF_Base!K3)))/(1+0.09)^10 -> 152.30355
