Workbook

Sheet Model_Info
A1: WIN.NZ Winton Land Limited - blended NTA exit-P/B + earnings exit-P/E model
A2: Version 1.1, update 2026-09-21 (same day as v1.0). Anchors re-sourced to WIN.NZ_Metrics.csv FY2026 row (financial-parser adjudicated; ties to the v1.0 manual anchors exactly). FY27/FY28 NPAT re-judged on pre-sale cover; FY29-31 unchanged.
A3: Built by the dcf-analyst agent (Claude Fable 5.1) at the research orchestrator's request, 21-Sep-2026.
A5: DATA VINTAGE (figures go stale; refresh after each NZX print)
A6: Price NZ$1.11 as of 2026-09-20T22:47:01Z (Yahoo, live intraday 21-Sep-2026 10:47 NZST). 52-week range 1.045-2.40.
A7: Balance sheet 30-Jun-2026 from WIN.NZ_Metrics.csv FY2026 row (source filing: audited FY26 annual report, NZX 478541, 26-Aug-2026): cash 38.788, borrowings 44.232, equity 555.405, intangibles 0.957, NTA 186.9 cps.
A8: Shares 296,613,736 basic, unchanged since IPO. 10.332m options at $3.887 strike are far out of the money and are NOT counted (treasury-stock dilution nil).
A9: FY26 result (CSV): revenue 188.841 (development 147.8 / hospitality 35.8 / other 5.2), EBITDA 45.582, NPAT 22.665, EPS 7.64c, 430 units settled, OCF 105.949, CapEx 9.406, CSV FCF 96.543 (inventory run-down, not a run-rate). Pre-sale book 27.4 at Jun-26 vs 248.0 at Jun-25 and 419.3 at Jun-23. Dividend paused.
A10: Guidance: none quantitative. Board 'cautiously positive' on FY27 trading, 'cautious and constrained' on capital; no recovery expected until unemployment (5.6% Jun-26) peaks.
A12: METHODOLOGY
A13: Model routed via dcf-methods SKILL.md row 'Land subdivider, inventory-heavy developer' (CDI.NZ precedent). Reported FCF is inventory timing (FY22-24 negative on land-bank build, FY26 +80m on a run-down), so no FCF DCF.
A14: Value per share = 50% x [PV(year-5 NTA x exit P/B) + PV(dividends)] + 50% x [PV(year-5 NPAT x exit P/E / shares) + PV(dividends)], five-year horizon, end-of-year discounting at the cost of equity.
... A24: CELL LEGEND: blue = hardcoded input; yellow fill = key lever; black = formula; green = cross-sheet link. Sheet names have no spaces.

Sheet Actuals
A1: Reported history (FY ends 30 June). Source: WIN.NZ_Metrics.csv (FY21-FY26, all rows now adjudicated into core_metrics). Prices: Yahoo monthly closes.
A2: Metric | B2: FY2021 | C2: FY2022 | D2: FY2023 | E2: FY2024 | F2: FY2025 | G2: FY2026
A3: Revenue (NZ$m) | B3: 177 | C3: 159.5 | D3: 211.4 | E3: 173.6 | F3: 155.4 | G3: 188.841
A4: EBITDA (NZ$m) | B4: 70.4 | C4: 45 | D4: 95.6 | E4: 29.6 | F4: 21.2 | G4: 45.582
A5: NPAT (NZ$m) | B5: 46.1 | C5: 31.7 | D5: 64.6 | E5: 15.8 | F5: 10.3 | G5: 22.665
A6: Units settled | B6: 553 | C6: 449 | D6: 565 | E6: 345 | F6: 266 | G6: 430
A7: Reported FCF per CSV = OCF - PP&E capex (NZ$m) - inventory timing, not used | B7: 83.7 | C7: -16.1 | D7: -14.3 | E7: -27.8 | F7: 22.8 | G7: 96.543
A8: Shareholders equity (NZ$m) | B8: 83.8 | C8: 454.1 | D8: 510.4 | E8: 519.5 | F8: 531.2 | G8: 555.405
A9: NTA per share (cents) | C9: 153.1 | D9: 171.2 | E9: 174.5 | F9: 178.6 | G9: 186.9
A10: June-close price (NZ$) | C10: 2.55 | D10: 2.39 | E10: 1.88 | F10: 2.07 | G10: 1.14
A11: Cash (NZ$m) | B11: 35 | C11: 204.8 | D11: 76.3 | E11: 41.7 | F11: 20.3 | G11: 38.788
A12: Borrowings (NZ$m) | B12: 128.7 | C12: 0 | D12: 0 | E12: 64 | F12: 99.4 | G12: 44.232
A13: Dividends paid (NZ$m) | B13: 18.8 | C13: 0 | D13: 9.3 | E13: 8 | F13: 0 | G13: 0
A14: Share-based payment expense (NZ$m) | B14: 0 | C14: 0.6 | D14: 0.54 | E14: 1.2 | F14: 1.2 | G14: 1.281
A15: Price / NTA (x) | C15: =C10/(C9/100) | D15: =D10/(D9/100) | E15: =E10/(E9/100) | F15: =F10/(F9/100) | G15: =G10/(G9/100)
A16: ROE on closing equity (%) | B16: =100*B5/B8 | C16: =100*C5/C8 | D16: =100*D5/D8 | E16: =100*E5/E8 | F16: =100*F5/F8 | G16: =100*G5/G8
A17: Pre-sale book at 30 June (NZ$m, gross, unconditional + conditional) | D17: 419.3 | F17: 248 | G17: 27.4
A18: Balance-sheet snapshot 30-Jun-2026: cash 38.788; borrowings 44.232 (BNZ/Sunfield 25.7 to Aug-27, MCCB/Cracker Bay 18.2 to Nov-27, non-recourse); lease liabilities 23.477; residents' loans 18.157; deferred tax 31.417; equity 555.405; intangibles 0.957. Inventories 172.254 of which 16.233 'expected to settle within one year' (Jun-25: 46.368).
A19: Share count 296,613,736 basic; 10.332m options at $3.887 (note 10.12), treasury-stock dilution nil at any price in this model. No buybacks ever; dividends paused since FY25.
A20: FY26 CSV FCF 96.543 = OCF 105.949 - CapEx 9.406 (PP&E only). Net of investment-property purchases (16.4) and intangibles (0.06) it is 80.1. Either figure is an inventory run-down (-53.4m) converting to cash and repaying the Lakeside/Northlake facilities, not owner earnings.

Sheet Assumptions
A1: Global inputs
A2: Cost of equity (all scenarios) | B2: 0.155 | C2: rf 4.4% + 1.2x5.5% ERP + 2.0pp size/illiquidity + 2.5pp governance/control
A3: Hurdle rate (entry price) | B3: 0.15 | C3: House 15% IRR hurdle
A4: Shares outstanding (m) | B4: 296.61374 | C4: Basic, flat; options far out of the money
A5: Opening NTA per share (NZ$) | B5: 1.8693 | C5: (555.405 - 0.957) / 296.614 at 30-Jun-2026
A6: Book equity (NZ$m) | B6: 555.405 | C6: 30-Jun-2026 audited
A7: Intangibles (NZ$m) | B7: 0.957 | C7: customer contracts + software
A8: Current price (NZ$) | B8: 1.11 | C8: 2026-09-20T22:47:01Z (Yahoo regularMarketTime; 10:47 NZST Monday 21-Sep-2026, live intraday NZX quote, currency NZD)
A9: Blend weight on NTA leg | B9: 0.5 | C9: 50% NTA leg / 50% earnings leg
A10: SBC expense per year (NZ$m) | B10: 1.281 | C10: Street basis adds this back to NPAT
A11: Net debt (NZ$m) - memo only, inside book equity | B11: 5.444 | C11: 44.232 borrowings - 38.788 cash; NOT added to value
A13: Scenario drivers (NZ$m NPAT; payout as fraction of NPAT; exit multiples applied to year-5 NTA and NPAT)
A14: Scenario | B14: FY2027 | C14: FY2028 | D14: FY2029 | E14: FY2030 | F14: FY2031 | H14: Exit P/B | I14: Exit P/E | J14: Weight
A15: bear NPAT | B15: -4 | C15: 3 | D15: 10 | E15: 13 | F15: 15 | H15: 0.55 | I15: 8 | J15: 0.3
A16: bear payout ratio | B16: 0 | C16: 0 | D16: 0 | E16: 0.3 | F16: 0.3
A17: bear narrative | B17: FY27 loss: the $27.4m opening pre-sale book plus $16.2m of 'within one year' inventory (at cost) is all the booked cover there is; in-year sales are thin, the High Court quashes the Sunfield consent (or remits it for years), the Auckland market stays subdued, legal and restructuring costs run through FY27-28 and the board/majority-holder standoff recurs. NPAT -4 (FY27, ~$90m revenue) and 3 (FY28) before recovering only to ~$15m by FY31 (FY24 level); no dividend until FY30, exit P/B 0.55x (a step below today's 0.59x) and exit P/E 8x. Not modelled: a Sunfield inventory impairment if the consent is quashed.
A19: base NPAT | B19: 5 | C19: 14 | D19: 25 | E19: 30 | F19: 32 | H19: 0.8 | I19: 11 | J19: 0.5
A20: base payout ratio | B20: 0 | C20: 0.4 | D20: 0.4 | E20: 0.4 | F20: 0.4
A21: base narrative | B21: FY27 is a gap year: the $248.0m Jun-25 pre-sale book (which covered FY26's $147.8m development revenue 1.7x) was consumed and partly cancelled when the Kainga Ora land-supply agreement concluded, leaving $27.4m at 30-Jun-26 against a hospitality/other floor of ~$45m revenue. FY27 revenue ~$110m (development ~$65m: $27m contracted plus in-year Northlake/Lakeside/Launch Bay lot sales) and NPAT ~$5m; FY28 ~$14m as the pipeline sold during FY27 settles and Goodfellows (campaign Oct-26) / Northbrook Stage 2 (2027) open. From FY29 the path is unchanged: earnings rebuild to a ~$32m mid-cycle by FY31 (6-year FY21-26 average $31.9m; ~5.2% ROE). Sunfield survives the Auckland Council appeal but contributes little inside the horizon. Dividend resumes at ~40% payout from FY28 ($5.6m, easily funded from $38.8m cash). Exit P/B 0.80x, exit P/E 11x.
A23: bull NPAT | B23: 9 | C23: 22 | D23: 36 | E23: 45 | F23: 50 | H23: 1.05 | I23: 13 | J23: 0.2
A24: bull payout ratio | B24: 0 | C24: 0.5 | D24: 0.5 | E24: 0.5 | F24: 0.5
A25: bull narrative | B25: FY27 is still thin (NPAT ~$9m on ~$125m revenue: even a strong market cannot settle what was not pre-sold at 30-Jun-26), then the cycle turns: unemployment peaks in 2027, Queenstown-Lakes stays strong, FY28 NPAT ~$22m; Sunfield's fast-track consent is upheld and first stages settle FY29-31; Goodfellows and Northbrook scale ORA income; the Stiassny board lands a credible CEO and the majority holder either accepts minority protections or sells down. NPAT reaches ~$50m by FY31 (FY21 level; ~7.8% ROE), payout 50% from FY28, exit P/B 1.05x (back to the FY24-25 regime) and exit P/E 13x.
A27: Weights check (must be 1.0) | B27: =J15+J19+J23
A28: Bear 30% (up from the 15% house default): FY27 has no pre-sale cover, the Sunfield consent is before the High Court in Sept-2026, the shareholder-level governance dispute is unresolved (the 55% holder declined minority protections and has just left the board, which removes a distraction but not the control), and the company has no permanent CEO or CFO. Bull 20% (down from 35%): it needs a housing-cycle turn, a Sunfield win and a governance normalisation, three largely independent events. Base 50%.

Sheet Val_Bear
A1: BEAR scenario - blended NTA / earnings valuation (NZ$m, NZ$ per share)
A3: Year | B3: FY2027E | C3: FY2028E | D3: FY2029E | E3: FY2030E | F3: FY2031E
A4: Index | B4: 1 | C4: 2 | D4: 3 | E4: 4 | F4: 5
A5: NPAT (NZ$m) | B5: =Assumptions!B15 | C5: =Assumptions!C15 | D5: =Assumptions!D15 | E5: =Assumptions!E15 | F5: =Assumptions!F15
A6: Payout ratio | B6: =Assumptions!B16 | C6: =Assumptions!C16 | D6: =Assumptions!D16 | E6: =Assumptions!E16 | F6: =Assumptions!F16
A7: Dividends (NZ$m) | B7: =B5*B6 | C7: =C5*C6 | D7: =D5*D6 | E7: =E5*E6 | F7: =F5*F6
A8: Retained earnings (NZ$m) | B8: =B5-B7 | C8: =C5-C7 | D8: =D5-D7 | E8: =E5-E7 | F8: =F5-F7
A9: NTA per share (NZ$) | B9: =Assumptions!$B$5+B8/Assumptions!$B$4 | C9: =B9+C8/Assumptions!$B$4 | D9: =C9+D8/Assumptions!$B$4 | E9: =D9+E8/Assumptions!$B$4 | F9: =E9+F8/Assumptions!$B$4
A10: Dividend per share (NZ$) | B10: =B7/Assumptions!$B$4 | C10: =C7/Assumptions!$B$4 | D10: =D7/Assumptions!$B$4 | E10: =E7/Assumptions!$B$4 | F10: =F7/Assumptions!$B$4
A11: Discount factor @ CoE | B11: =1/(1+Assumptions!$B$2)^B4 | C11: =1/(1+Assumptions!$B$2)^C4 | D11: =1/(1+Assumptions!$B$2)^D4 | E11: =1/(1+Assumptions!$B$2)^E4 | F11: =1/(1+Assumptions!$B$2)^F4
A12: PV dividend per share | B12: =B10*B11 | C12: =C10*C11 | D12: =D10*D11 | E12: =E10*E11 | F12: =F10*F11
A15: Sum PV dividends per share | B15: =SUM(B12:F12)
A16: Year-5 NTA per share | B16: =F9
A17: Exit P/B | B17: =Assumptions!H15
A18: NTA exit value per share | B18: =B16*B17
A19: PV of NTA exit value | B19: =B18*F11
A20: NTA leg value per share | B20: =B19+B15
A21: Year-5 NPAT (NZ$m) | B21: =F5
A22: Exit P/E | B22: =Assumptions!I15
A23: Earnings exit value per share | B23: =B21*B22/Assumptions!$B$4
A24: PV of earnings exit value | B24: =B23*F11
A25: Earnings leg value per share | B25: =B24+B15
A26: Blend weight on NTA leg | B26: =Assumptions!$B$9
A27: INTRINSIC VALUE PER SHARE (house) | B27: =B26*B20+(1-B26)*B25
A28: Upside vs price (%) | B28: =100*(B27/Assumptions!$B$8-1)
A29: Terminal share of value (%) | B29: =100*(B26*B19+(1-B26)*B24)/B27
A30: Implied year-5 P/B on blended exit | B30: =(B26*B18+(1-B26)*B23)/B16
A31: Year-5 ROE (%) | B31: =100*B21/(B16*Assumptions!$B$4+Assumptions!$B$7)
A33: Street IV per share (SBC added back to NPAT each year) | B33: =B27+B26*(Assumptions!$B$10*SUMPRODUCT(1-B6:F6)/Assumptions!$B$4*B17*F11+SUMPRODUCT(B6:F6,B11:F11)*Assumptions!$B$10/Assumptions!$B$4)+(1-B26)*(Assumptions!$B$10*B22/Assumptions!$B$4*F11+SUMPRODUCT(B6:F6,B11:F11)*Assumptions!$B$10/Assumptions!$B$4)
A35: ENTRY PRICE at hurdle (same exit multiples, rediscounted) | B35: =B26*(B18/(1+Assumptions!$B$3)^5+SUMPRODUCT(B10:F10,1/(1+Assumptions!$B$3)^B4:F4))+(1-B26)*(B23/(1+Assumptions!$B$3)^5+SUMPRODUCT(B10:F10,1/(1+Assumptions!$B$3)^B4:F4))
A36: Entry price vs current (%) | B36: =100*(B35/Assumptions!$B$8-1)

Sheet Val_Base
A1: BASE scenario - blended NTA / earnings valuation (NZ$m, NZ$ per share)
A3: Year | B3: FY2027E | C3: FY2028E | D3: FY2029E | E3: FY2030E | F3: FY2031E
A4: Index | B4: 1 | C4: 2 | D4: 3 | E4: 4 | F4: 5
A5: NPAT (NZ$m) | B5: =Assumptions!B19 | C5: =Assumptions!C19 | D5: =Assumptions!D19 | E5: =Assumptions!E19 | F5: =Assumptions!F19
A6: Payout ratio | B6: =Assumptions!B20 | C6: =Assumptions!C20 | D6: =Assumptions!D20 | E6: =Assumptions!E20 | F6: =Assumptions!F20
A7: Dividends (NZ$m) | B7: =B5*B6 | C7: =C5*C6 | D7: =D5*D6 | E7: =E5*E6 | F7: =F5*F6
A8: Retained earnings (NZ$m) | B8: =B5-B7 | C8: =C5-C7 | D8: =D5-D7 | E8: =E5-E7 | F8: =F5-F7
A9: NTA per share (NZ$) | B9: =Assumptions!$B$5+B8/Assumptions!$B$4 | C9: =B9+C8/Assumptions!$B$4 | D9: =C9+D8/Assumptions!$B$4 | E9: =D9+E8/Assumptions!$B$4 | F9: =E9+F8/Assumptions!$B$4
A10: Dividend per share (NZ$) | B10: =B7/Assumptions!$B$4 | C10: =C7/Assumptions!$B$4 | D10: =D7/Assumptions!$B$4 | E10: =E7/Assumptions!$B$4 | F10: =F7/Assumptions!$B$4
A11: Discount factor @ CoE | B11: =1/(1+Assumptions!$B$2)^B4 | C11: =1/(1+Assumptions!$B$2)^C4 | D11: =1/(1+Assumptions!$B$2)^D4 | E11: =1/(1+Assumptions!$B$2)^E4 | F11: =1/(1+Assumptions!$B$2)^F4
A12: PV dividend per share | B12: =B10*B11 | C12: =C10*C11 | D12: =D10*D11 | E12: =E10*E11 | F12: =F10*F11
A15: Sum PV dividends per share | B15: =SUM(B12:F12)
A16: Year-5 NTA per share | B16: =F9
A17: Exit P/B | B17: =Assumptions!H19
A18: NTA exit value per share | B18: =B16*B17
A19: PV of NTA exit value | B19: =B18*F11
A20: NTA leg value per share | B20: =B19+B15
A21: Year-5 NPAT (NZ$m) | B21: =F5
A22: Exit P/E | B22: =Assumptions!I19
A23: Earnings exit value per share | B23: =B21*B22/Assumptions!$B$4
A24: PV of earnings exit value | B24: =B23*F11
A25: Earnings leg value per share | B25: =B24+B15
A26: Blend weight on NTA leg | B26: =Assumptions!$B$9
A27: INTRINSIC VALUE PER SHARE (house) | B27: =B26*B20+(1-B26)*B25
A28: Upside vs price (%) | B28: =100*(B27/Assumptions!$B$8-1)
A29: Terminal share of value (%) | B29: =100*(B26*B19+(1-B26)*B24)/B27
A30: Implied year-5 P/B on blended exit | B30: =(B26*B18+(1-B26)*B23)/B16
A31: Year-5 ROE (%) | B31: =100*B21/(B16*Assumptions!$B$4+Assumptions!$B$7)
A33: Street IV per share (SBC added back to NPAT each year) | B33: =B27+B26*(Assumptions!$B$10*SUMPRODUCT(1-B6:F6)/Assumptions!$B$4*B17*F11+SUMPRODUCT(B6:F6,B11:F11)*Assumptions!$B$10/Assumptions!$B$4)+(1-B26)*(Assumptions!$B$10*B22/Assumptions!$B$4*F11+SUMPRODUCT(B6:F6,B11:F11)*Assumptions!$B$10/Assumptions!$B$4)
A35: ENTRY PRICE at hurdle (same exit multiples, rediscounted) | B35: =B26*(B18/(1+Assumptions!$B$3)^5+SUMPRODUCT(B10:F10,1/(1+Assumptions!$B$3)^B4:F4))+(1-B26)*(B23/(1+Assumptions!$B$3)^5+SUMPRODUCT(B10:F10,1/(1+Assumptions!$B$3)^B4:F4))
A36: Entry price vs current (%) | B36: =100*(B35/Assumptions!$B$8-1)

Sheet Val_Bull
A1: BULL scenario - blended NTA / earnings valuation (NZ$m, NZ$ per share)
A3: Year | B3: FY2027E | C3: FY2028E | D3: FY2029E | E3: FY2030E | F3: FY2031E
A4: Index | B4: 1 | C4: 2 | D4: 3 | E4: 4 | F4: 5
A5: NPAT (NZ$m) | B5: =Assumptions!B23 | C5: =Assumptions!C23 | D5: =Assumptions!D23 | E5: =Assumptions!E23 | F5: =Assumptions!F23
A6: Payout ratio | B6: =Assumptions!B24 | C6: =Assumptions!C24 | D6: =Assumptions!D24 | E6: =Assumptions!E24 | F6: =Assumptions!F24
A7: Dividends (NZ$m) | B7: =B5*B6 | C7: =C5*C6 | D7: =D5*D6 | E7: =E5*E6 | F7: =F5*F6
A8: Retained earnings (NZ$m) | B8: =B5-B7 | C8: =C5-C7 | D8: =D5-D7 | E8: =E5-E7 | F8: =F5-F7
A9: NTA per share (NZ$) | B9: =Assumptions!$B$5+B8/Assumptions!$B$4 | C9: =B9+C8/Assumptions!$B$4 | D9: =C9+D8/Assumptions!$B$4 | E9: =D9+E8/Assumptions!$B$4 | F9: =E9+F8/Assumptions!$B$4
A10: Dividend per share (NZ$) | B10: =B7/Assumptions!$B$4 | C10: =C7/Assumptions!$B$4 | D10: =D7/Assumptions!$B$4 | E10: =E7/Assumptions!$B$4 | F10: =F7/Assumptions!$B$4
A11: Discount factor @ CoE | B11: =1/(1+Assumptions!$B$2)^B4 | C11: =1/(1+Assumptions!$B$2)^C4 | D11: =1/(1+Assumptions!$B$2)^D4 | E11: =1/(1+Assumptions!$B$2)^E4 | F11: =1/(1+Assumptions!$B$2)^F4
A12: PV dividend per share | B12: =B10*B11 | C12: =C10*C11 | D12: =D10*D11 | E12: =E10*E11 | F12: =F10*F11
A15: Sum PV dividends per share | B15: =SUM(B12:F12)
A16: Year-5 NTA per share | B16: =F9
A17: Exit P/B | B17: =Assumptions!H23
A18: NTA exit value per share | B18: =B16*B17
A19: PV of NTA exit value | B19: =B18*F11
A20: NTA leg value per share | B20: =B19+B15
A21: Year-5 NPAT (NZ$m) | B21: =F5
A22: Exit P/E | B22: =Assumptions!I23
A23: Earnings exit value per share | B23: =B21*B22/Assumptions!$B$4
A24: PV of earnings exit value | B24: =B23*F11
A25: Earnings leg value per share | B25: =B24+B15
A26: Blend weight on NTA leg | B26: =Assumptions!$B$9
A27: INTRINSIC VALUE PER SHARE (house) | B27: =B26*B20+(1-B26)*B25
A28: Upside vs price (%) | B28: =100*(B27/Assumptions!$B$8-1)
A29: Terminal share of value (%) | B29: =100*(B26*B19+(1-B26)*B24)/B27
A30: Implied year-5 P/B on blended exit | B30: =(B26*B18+(1-B26)*B23)/B16
A31: Year-5 ROE (%) | B31: =100*B21/(B16*Assumptions!$B$4+Assumptions!$B$7)
A33: Street IV per share (SBC added back to NPAT each year) | B33: =B27+B26*(Assumptions!$B$10*SUMPRODUCT(1-B6:F6)/Assumptions!$B$4*B17*F11+SUMPRODUCT(B6:F6,B11:F11)*Assumptions!$B$10/Assumptions!$B$4)+(1-B26)*(Assumptions!$B$10*B22/Assumptions!$B$4*F11+SUMPRODUCT(B6:F6,B11:F11)*Assumptions!$B$10/Assumptions!$B$4)
A35: ENTRY PRICE at hurdle (same exit multiples, rediscounted) | B35: =B26*(B18/(1+Assumptions!$B$3)^5+SUMPRODUCT(B10:F10,1/(1+Assumptions!$B$3)^B4:F4))+(1-B26)*(B23/(1+Assumptions!$B$3)^5+SUMPRODUCT(B10:F10,1/(1+Assumptions!$B$3)^B4:F4))
A36: Entry price vs current (%) | B36: =100*(B35/Assumptions!$B$8-1)

Sheet Valuation
A1: Valuation summary (NZ$ per share)
A2: Scenario | B2: Intrinsic value | C2: Upside % | D2: Weight | E2: Street IV | F2: Entry price @15%
A3: bear | B3: =Val_Bear!B27 | C3: =Val_Bear!B28 | D3: =Assumptions!J15 | E3: =Val_Bear!B33 | F3: =Val_Bear!B35
A4: base | B4: =Val_Base!B27 | C4: =Val_Base!B28 | D4: =Assumptions!J19 | E4: =Val_Base!B33 | F4: =Val_Base!B35
A5: bull | B5: =Val_Bull!B27 | C5: =Val_Bull!B28 | D5: =Assumptions!J23 | E5: =Val_Bull!B33 | F5: =Val_Bull!B35
A7: Probability-weighted IV | B7: =SUMPRODUCT(B3:B5,D3:D5)
A8: Current price | B8: =Assumptions!$B$8
A9: Margin of safety (%) | B9: =100*(1-B8/B7)
A10: Street weighted IV | B10: =SUMPRODUCT(E3:E5,D3:D5)
A11: Band position (price-house)/(street-house) | B11: =IF(ABS(B10-B7)<0.0001,"n/a",(B8-B7)/(B10-B7))
A12: Weighted entry price @15% | B12: =SUMPRODUCT(F3:F5,D3:D5)
A13: Price / opening NTA (x) | B13: =Assumptions!$B$8/Assumptions!$B$5
A15: Required-return table (base): value per share at rate r, exit multiples held at base
A16: r | B16: 0.09 | C16: 0.1 | D16: 0.11 | E16: 0.12 | F16: 0.15 | G16: =Assumptions!$B$2
A17: Value per share | B17: =Val_Base!$B$26*(Val_Base!$B$18/(1+B$16)^5+SUMPRODUCT(Val_Base!$B$10:$F$10,1/(1+B$16)^Val_Base!$B$4:$F$4))+(1-Val_Base!$B$26)*(Val_Base!$B$23/(1+B$16)^5+SUMPRODUCT(Val_Base!$B$10:$F$10,1/(1+B$16)^Val_Base!$B$4:$F$4)) | C17: =Val_Base!$B$26*(Val_Base!$B$18/(1+C$16)^5+SUMPRODUCT(Val_Base!$B$10:$F$10,1/(1+C$16)^Val_Base!$B$4:$F$4))+(1-Val_Base!$B$26)*(Val_Base!$B$23/(1+C$16)^5+SUMPRODUCT(Val_Base!$B$10:$F$10,1/(1+C$16)^Val_Base!$B$4:$F$4)) | D17: =Val_Base!$B$26*(Val_Base!$B$18/(1+D$16)^5+SUMPRODUCT(Val_Base!$B$10:$F$10,1/(1+D$16)^Val_Base!$B$4:$F$4))+(1-Val_Base!$B$26)*(Val_Base!$B$23/(1+D$16)^5+SUMPRODUCT(Val_Base!$B$10:$F$10,1/(1+D$16)^Val_Base!$B$4:$F$4)) | E17: =Val_Base!$B$26*(Val_Base!$B$18/(1+E$16)^5+SUMPRODUCT(Val_Base!$B$10:$F$10,1/(1+E$16)^Val_Base!$B$4:$F$4))+(1-Val_Base!$B$26)*(Val_Base!$B$23/(1+E$16)^5+SUMPRODUCT(Val_Base!$B$10:$F$10,1/(1+E$16)^Val_Base!$B$4:$F$4)) | F17: =Val_Base!$B$26*(Val_Base!$B$18/(1+F$16)^5+SUMPRODUCT(Val_Base!$B$10:$F$10,1/(1+F$16)^Val_Base!$B$4:$F$4))+(1-Val_Base!$B$26)*(Val_Base!$B$23/(1+F$16)^5+SUMPRODUCT(Val_Base!$B$10:$F$10,1/(1+F$16)^Val_Base!$B$4:$F$4)) | G17: =Val_Base!$B$26*(Val_Base!$B$18/(1+G$16)^5+SUMPRODUCT(Val_Base!$B$10:$F$10,1/(1+G$16)^Val_Base!$B$4:$F$4))+(1-Val_Base!$B$26)*(Val_Base!$B$23/(1+G$16)^5+SUMPRODUCT(Val_Base!$B$10:$F$10,1/(1+G$16)^Val_Base!$B$4:$F$4))
A20: Sensitivity (base): cost of equity (rows) x exit P/B (cols); exit P/E scaled = base P/E x P/B / base P/B
A21: CoE \ P/B | B21: 0.6 | C21: 0.7 | D21: 0.8 | E21: 0.9 | F21: 1
A22: 0.115 | B22: =Val_Base!$B$26*(Val_Base!$B$16*B$21/(1+$A22)^5+SUMPRODUCT(Val_Base!$B$10:$F$10,1/(1+$A22)^Val_Base!$B$4:$F$4))+(1-Val_Base!$B$26)*(Val_Base!$B$21*Val_Base!$B$22*B$21/Val_Base!$B$17/Assumptions!$B$4/(1+$A22)^5+SUMPRODUCT(Val_Base!$B$10:$F$10,1/(1+$A22)^Val_Base!$B$4:$F$4)) | C22: =Val_Base!$B$26*(Val_Base!$B$16*C$21/(1+$A22)^5+SUMPRODUCT(Val_Base!$B$10:$F$10,1/(1+$A22)^Val_Base!$B$4:$F$4))+(1-Val_Base!$B$26)*(Val_Base!$B$21*Val_Base!$B$22*C$21/Val_Base!$B$17/Assumptions!$B$4/(1+$A22)^5+SUMPRODUCT(Val_Base!$B$10:$F$10,1/(1+$A22)^Val_Base!$B$4:$F$4)) | D22: =Val_Base!$B$26*(Val_Base!$B$16*D$21/(1+$A22)^5+SUMPRODUCT(Val_Base!$B$10:$F$10,1/(1+$A22)^Val_Base!$B$4:$F$4))+(1-Val_Base!$B$26)*(Val_Base!$B$21*Val_Base!$B$22*D$21/Val_Base!$B$17/Assumptions!$B$4/(1+$A22)^5+SUMPRODUCT(Val_Base!$B$10:$F$10,1/(1+$A22)^Val_Base!$B$4:$F$4)) | E22: =Val_Base!$B$26*(Val_Base!$B$16*E$21/(1+$A22)^5+SUMPRODUCT(Val_Base!$B$10:$F$10,1/(1+$A22)^Val_Base!$B$4:$F$4))+(1-Val_Base!$B$26)*(Val_Base!$B$21*Val_Base!$B$22*E$21/Val_Base!$B$17/Assumptions!$B$4/(1+$A22)^5+SUMPRODUCT(Val_Base!$B$10:$F$10,1/(1+$A22)^Val_Base!$B$4:$F$4)) | F22: =Val_Base!$B$26*(Val_Base!$B$16*F$21/(1+$A22)^5+SUMPRODUCT(Val_Base!$B$10:$F$10,1/(1+$A22)^Val_Base!$B$4:$F$4))+(1-Val_Base!$B$26)*(Val_Base!$B$21*Val_Base!$B$22*F$21/Val_Base!$B$17/Assumptions!$B$4/(1+$A22)^5+SUMPRODUCT(Val_Base!$B$10:$F$10,1/(1+$A22)^Val_Base!$B$4:$F$4))
A23: 0.135 | B23: =Val_Base!$B$26*(Val_Base!$B$16*B$21/(1+$A23)^5+SUMPRODUCT(Val_Base!$B$10:$F$10,1/(1+$A23)^Val_Base!$B$4:$F$4))+(1-Val_Base!$B$26)*(Val_Base!$B$21*Val_Base!$B$22*B$21/Val_Base!$B$17/Assumptions!$B$4/(1+$A23)^5+SUMPRODUCT(Val_Base!$B$10:$F$10,1/(1+$A23)^Val_Base!$B$4:$F$4)) | C23: =Val_Base!$B$26*(Val_Base!$B$16*C$21/(1+$A23)^5+SUMPRODUCT(Val_Base!$B$10:$F$10,1/(1+$A23)^Val_Base!$B$4:$F$4))+(1-Val_Base!$B$26)*(Val_Base!$B$21*Val_Base!$B$22*C$21/Val_Base!$B$17/Assumptions!$B$4/(1+$A23)^5+SUMPRODUCT(Val_Base!$B$10:$F$10,1/(1+$A23)^Val_Base!$B$4:$F$4)) | D23: =Val_Base!$B$26*(Val_Base!$B$16*D$21/(1+$A23)^5+SUMPRODUCT(Val_Base!$B$10:$F$10,1/(1+$A23)^Val_Base!$B$4:$F$4))+(1-Val_Base!$B$26)*(Val_Base!$B$21*Val_Base!$B$22*D$21/Val_Base!$B$17/Assumptions!$B$4/(1+$A23)^5+SUMPRODUCT(Val_Base!$B$10:$F$10,1/(1+$A23)^Val_Base!$B$4:$F$4)) | E23: =Val_Base!$B$26*(Val_Base!$B$16*E$21/(1+$A23)^5+SUMPRODUCT(Val_Base!$B$10:$F$10,1/(1+$A23)^Val_Base!$B$4:$F$4))+(1-Val_Base!$B$26)*(Val_Base!$B$21*Val_Base!$B$22*E$21/Val_Base!$B$17/Assumptions!$B$4/(1+$A23)^5+SUMPRODUCT(Val_Base!$B$10:$F$10,1/(1+$A23)^Val_Base!$B$4:$F$4)) | F23: =Val_Base!$B$26*(Val_Base!$B$16*F$21/(1+$A23)^5+SUMPRODUCT(Val_Base!$B$10:$F$10,1/(1+$A23)^Val_Base!$B$4:$F$4))+(1-Val_Base!$B$26)*(Val_Base!$B$21*Val_Base!$B$22*F$21/Val_Base!$B$17/Assumptions!$B$4/(1+$A23)^5+SUMPRODUCT(Val_Base!$B$10:$F$10,1/(1+$A23)^Val_Base!$B$4:$F$4))
A24: 0.155 | B24: =Val_Base!$B$26*(Val_Base!$B$16*B$21/(1+$A24)^5+SUMPRODUCT(Val_Base!$B$10:$F$10,1/(1+$A24)^Val_Base!$B$4:$F$4))+(1-Val_Base!$B$26)*(Val_Base!$B$21*Val_Base!$B$22*B$21/Val_Base!$B$17/Assumptions!$B$4/(1+$A24)^5+SUMPRODUCT(Val_Base!$B$10:$F$10,1/(1+$A24)^Val_Base!$B$4:$F$4)) | C24: =Val_Base!$B$26*(Val_Base!$B$16*C$21/(1+$A24)^5+SUMPRODUCT(Val_Base!$B$10:$F$10,1/(1+$A24)^Val_Base!$B$4:$F$4))+(1-Val_Base!$B$26)*(Val_Base!$B$21*Val_Base!$B$22*C$21/Val_Base!$B$17/Assumptions!$B$4/(1+$A24)^5+SUMPRODUCT(Val_Base!$B$10:$F$10,1/(1+$A24)^Val_Base!$B$4:$F$4)) | D24: =Val_Base!$B$26*(Val_Base!$B$16*D$21/(1+$A24)^5+SUMPRODUCT(Val_Base!$B$10:$F$10,1/(1+$A24)^Val_Base!$B$4:$F$4))+(1-Val_Base!$B$26)*(Val_Base!$B$21*Val_Base!$B$22*D$21/Val_Base!$B$17/Assumptions!$B$4/(1+$A24)^5+SUMPRODUCT(Val_Base!$B$10:$F$10,1/(1+$A24)^Val_Base!$B$4:$F$4)) | E24: =Val_Base!$B$26*(Val_Base!$B$16*E$21/(1+$A24)^5+SUMPRODUCT(Val_Base!$B$10:$F$10,1/(1+$A24)^Val_Base!$B$4:$F$4))+(1-Val_Base!$B$26)*(Val_Base!$B$21*Val_Base!$B$22*E$21/Val_Base!$B$17/Assumptions!$B$4/(1+$A24)^5+SUMPRODUCT(Val_Base!$B$10:$F$10,1/(1+$A24)^Val_Base!$B$4:$F$4)) | F24: =Val_Base!$B$26*(Val_Base!$B$16*F$21/(1+$A24)^5+SUMPRODUCT(Val_Base!$B$10:$F$10,1/(1+$A24)^Val_Base!$B$4:$F$4))+(1-Val_Base!$B$26)*(Val_Base!$B$21*Val_Base!$B$22*F$21/Val_Base!$B$17/Assumptions!$B$4/(1+$A24)^5+SUMPRODUCT(Val_Base!$B$10:$F$10,1/(1+$A24)^Val_Base!$B$4:$F$4))
A25: 0.175 | B25: =Val_Base!$B$26*(Val_Base!$B$16*B$21/(1+$A25)^5+SUMPRODUCT(Val_Base!$B$10:$F$10,1/(1+$A25)^Val_Base!$B$4:$F$4))+(1-Val_Base!$B$26)*(Val_Base!$B$21*Val_Base!$B$22*B$21/Val_Base!$B$17/Assumptions!$B$4/(1+$A25)^5+SUMPRODUCT(Val_Base!$B$10:$F$10,1/(1+$A25)^Val_Base!$B$4:$F$4)) | C25: =Val_Base!$B$26*(Val_Base!$B$16*C$21/(1+$A25)^5+SUMPRODUCT(Val_Base!$B$10:$F$10,1/(1+$A25)^Val_Base!$B$4:$F$4))+(1-Val_Base!$B$26)*(Val_Base!$B$21*Val_Base!$B$22*C$21/Val_Base!$B$17/Assumptions!$B$4/(1+$A25)^5+SUMPRODUCT(Val_Base!$B$10:$F$10,1/(1+$A25)^Val_Base!$B$4:$F$4)) | D25: =Val_Base!$B$26*(Val_Base!$B$16*D$21/(1+$A25)^5+SUMPRODUCT(Val_Base!$B$10:$F$10,1/(1+$A25)^Val_Base!$B$4:$F$4))+(1-Val_Base!$B$26)*(Val_Base!$B$21*Val_Base!$B$22*D$21/Val_Base!$B$17/Assumptions!$B$4/(1+$A25)^5+SUMPRODUCT(Val_Base!$B$10:$F$10,1/(1+$A25)^Val_Base!$B$4:$F$4)) | E25: =Val_Base!$B$26*(Val_Base!$B$16*E$21/(1+$A25)^5+SUMPRODUCT(Val_Base!$B$10:$F$10,1/(1+$A25)^Val_Base!$B$4:$F$4))+(1-Val_Base!$B$26)*(Val_Base!$B$21*Val_Base!$B$22*E$21/Val_Base!$B$17/Assumptions!$B$4/(1+$A25)^5+SUMPRODUCT(Val_Base!$B$10:$F$10,1/(1+$A25)^Val_Base!$B$4:$F$4)) | F25: =Val_Base!$B$26*(Val_Base!$B$16*F$21/(1+$A25)^5+SUMPRODUCT(Val_Base!$B$10:$F$10,1/(1+$A25)^Val_Base!$B$4:$F$4))+(1-Val_Base!$B$26)*(Val_Base!$B$21*Val_Base!$B$22*F$21/Val_Base!$B$17/Assumptions!$B$4/(1+$A25)^5+SUMPRODUCT(Val_Base!$B$10:$F$10,1/(1+$A25)^Val_Base!$B$4:$F$4))
A26: 0.195 | B26: =Val_Base!$B$26*(Val_Base!$B$16*B$21/(1+$A26)^5+SUMPRODUCT(Val_Base!$B$10:$F$10,1/(1+$A26)^Val_Base!$B$4:$F$4))+(1-Val_Base!$B$26)*(Val_Base!$B$21*Val_Base!$B$22*B$21/Val_Base!$B$17/Assumptions!$B$4/(1+$A26)^5+SUMPRODUCT(Val_Base!$B$10:$F$10,1/(1+$A26)^Val_Base!$B$4:$F$4)) | C26: =Val_Base!$B$26*(Val_Base!$B$16*C$21/(1+$A26)^5+SUMPRODUCT(Val_Base!$B$10:$F$10,1/(1+$A26)^Val_Base!$B$4:$F$4))+(1-Val_Base!$B$26)*(Val_Base!$B$21*Val_Base!$B$22*C$21/Val_Base!$B$17/Assumptions!$B$4/(1+$A26)^5+SUMPRODUCT(Val_Base!$B$10:$F$10,1/(1+$A26)^Val_Base!$B$4:$F$4)) | D26: =Val_Base!$B$26*(Val_Base!$B$16*D$21/(1+$A26)^5+SUMPRODUCT(Val_Base!$B$10:$F$10,1/(1+$A26)^Val_Base!$B$4:$F$4))+(1-Val_Base!$B$26)*(Val_Base!$B$21*Val_Base!$B$22*D$21/Val_Base!$B$17/Assumptions!$B$4/(1+$A26)^5+SUMPRODUCT(Val_Base!$B$10:$F$10,1/(1+$A26)^Val_Base!$B$4:$F$4)) | E26: =Val_Base!$B$26*(Val_Base!$B$16*E$21/(1+$A26)^5+SUMPRODUCT(Val_Base!$B$10:$F$10,1/(1+$A26)^Val_Base!$B$4:$F$4))+(1-Val_Base!$B$26)*(Val_Base!$B$21*Val_Base!$B$22*E$21/Val_Base!$B$17/Assumptions!$B$4/(1+$A26)^5+SUMPRODUCT(Val_Base!$B$10:$F$10,1/(1+$A26)^Val_Base!$B$4:$F$4)) | F26: =Val_Base!$B$26*(Val_Base!$B$16*F$21/(1+$A26)^5+SUMPRODUCT(Val_Base!$B$10:$F$10,1/(1+$A26)^Val_Base!$B$4:$F$4))+(1-Val_Base!$B$26)*(Val_Base!$B$21*Val_Base!$B$22*F$21/Val_Base!$B$17/Assumptions!$B$4/(1+$A26)^5+SUMPRODUCT(Val_Base!$B$10:$F$10,1/(1+$A26)^Val_Base!$B$4:$F$4))
