Workbook

Sheet Model_Info
A1: PGG Wrightson Limited (PGW.NZ) - DCF Model v1.0 (fresh build, supersedes nothing)
A2: Built by: dcf-analyst agent (Claude, claude-fable-5), 2026-08-25, at the user's request via the research workflow
A4: DATA VINTAGE
A5: Price: NZD 2.31, NZX regular close, verified 2026-08-25 (Yahoo Finance, live fetch by orchestrating session)
A6: Balance sheet: 30 June 2026 (FY2026 annual report, announced 11 Aug 2026)
A7: Share count: 75.484m ordinary shares (FY2026 annual report; flat since Aug-2019 1:10 consolidation; no options/SBC)
A8: Guidance: none for FY2027 (management declined at the Aug-2026 result; update expected at the 30 Oct 2026 ASM)
A10: METHODOLOGY CHOICES
A11: Model: owner-FCF DCF, mid-cycle variant - reported FCF (range -$65.5m to +$50.9m FY2017-26) is seasonal WC noise, so the base is component-built from mid-cycle EBITDA margin (6.0%, FY2020-26 avg), normalized capex (1.5% rev), 28% cash tax, full lease payment charged.
A12: Lease treatment (ONE treatment): leases as operating cost - full lease payment (principal + lease interest, 2.66% of revenue) deducted in flows; lease liabilities ($100.5m) EXCLUDED from net debt. Net debt $88.0m is bank debt $92.0m less cash $4.0m, matching PGW's own definition. No double count.
A13: Bank interest is NOT in the flows - bank debt charged once via the net-debt bridge.
A14: SBC: zero (NZX SBC-zero market). SBC rows kept explicit at 0%; house = street basis; band position n/a.
... A24: Scenario tabs: only rows 5, 7, 9, 14 are hardcoded drivers; everything else flows from Assumptions.

Sheet Actuals
A1: PGW.NZ reported history, NZD millions (source: PGW annual reports FY2020-FY2026 / Metrics.csv; all hardcoded)
A3: Metric | B3: FY2020 | C3: FY2021 | D3: FY2022 | E3: FY2023 | F3: FY2024 | G3: FY2025 | H3: FY2026
A4: Revenue | B4: 788.036 | C4: 847.815 | D4: 952.7 | E4: 975.692 | F4: 915.946 | G4: 975.344 | H4: 1074.384
A5: Operating EBITDA | B5: 45.19 | C5: 56.029 | D5: 67.153 | E5: 61.194 | F5: 44.17 | G5: 56.131 | H5: 64.31
A6: EBITDA margin % | B6: 5.73 | C6: 6.61 | D6: 7.05 | E6: 6.27 | F6: 4.82 | G6: 5.76 | H6: 5.99
A7: EBIT | B7: 15.051 | C7: 35.034 | D7: 37.646 | E7: 33.509 | F7: 15.355 | G7: 26.184 | H7: 29.74
A8: NPAT | B8: 7.84 | C8: 22.713 | D8: 24.286 | E8: 17.518 | F8: 3.064 | G8: 10.664 | H8: 15.571
A9: Operating cash flow | B9: 34.227 | C9: 57.671 | D9: 23.66 | E9: 25.509 | F9: 57.733 | G9: 12.397 | H9: 52.593
A10: Capex | B10: -11.875 | C10: -6.809 | D10: -8.807 | E10: -17.176 | F10: -22.845 | G10: -17.428 | H10: -6.585
A11: Reported FCF (OCF-capex) | B11: 22.352 | C11: 50.862 | D11: 14.853 | E11: 8.333 | F11: 34.888 | G11: -5.031 | H11: 46.008
A12: Lease principal repaid | B12: -17.586 | C12: -18.299 | D12: -18.873 | E12: -19.532 | F12: -21.203 | G12: -22.608 | H12: -24.03
A13: Shareholders equity | B13: 156.702 | C13: 173.538 | D13: 172.684 | E13: 169.261 | F13: 164.733 | G13: 173.81 | H13: 182.567
A14: Bank debt (excl leases) | B14: 30 | C14: 9.9 | D14: 37.5 | E14: 69.96 | F14: 63 | G14: 88.182 | H14: 92
A15: Cash | B15: 16.868 | C15: 3.367 | D15: 4.676 | E15: 4.643 | F15: 3.785 | G15: 2.613 | H15: 3.995
A16: Dividends paid | B16: -12.564 | C16: -9.343 | D16: -23.331 | E16: -21.712 | F16: -7.763 | G16: -1.899 | H16: -6.455
A18: Balance sheet snapshot 30-Jun-2026: lease liabilities 23.185 ST + 77.291 LT = 100.476 (excluded from net debt by design).
A19: FY2026 net interest: bank/other -6.256, lease interest -4.524, total -10.780. GO-STOCK interest revenue +8.011 (operating, stays in EBITDA).
A20: Buybacks: zero in every year FY2017-FY2026 (financing activities). Dividend FY2026: 10.0 cps fully imputed.
A21: Note: FY2017-FY2019 deliberately omitted - they include the Seeds business sold in FY2019 and the pre-capital-return balance sheet; not comparable.

Sheet Assumptions
A1: Global assumptions (blue = input)
A3: WACC (additive NZD build, see Model_Info) | B3: 0.135
A4: Lease payment % of revenue (FY2026: (24.030+4.524)/1074.384) | B4: 0.0265772
A5: Owned-asset D&A % of revenue (total D&A less ROU depreciation) | B5: 0.011
A6: Normalized capex % of revenue (run-rate $17-23m recent years) | B6: 0.015
A7: Working-capital capture (drag) per $ of revenue change | B7: 0.15
A8: Cash tax rate (NZ corporate 28%; recent low cash tax is trough timing) | B8: 0.28
A9: Net debt 30-Jun-2026 (bank debt 92.0 less cash 3.995; leases excluded) | B9: 88.005
A10: Shares outstanding, millions (flat: no SBC, no buybacks) | B10: 75.484
A11: Current price NZD (NZX close 2026-08-25) | B11: 2.31
A12: Hurdle rate for entry price | B12: 0.15
A14: Scenario | B14: Terminal growth | C14: Exit cap (EV/EBITDA) | D14: Probability weight
A15: Bear | B15: 0.01 | C15: 4.6 | D15: 0.25
A16: Base | B16: 0.02 | C16: 5.1 | D16: 0.5
A17: Bull | B17: 0.025 | C17: 6.2 | D17: 0.25
A18: Weight check (must equal 1.0) | D18: =SUM(D15:D17)
A20: Base narrative: NZ ag mid-cycle - farmgate returns normalize from FY2026 highs (Fonterra cut the 2026/27 milk forecast 50c to $9.25/kgMS Jul-2026); revenue +2-2.5%/yr, EBITDA margin holds the 6.0% FY2020-26 average; Nexan/Blue Ag gains offset Farmlands price competition; working capital absorbs ~15c per incremental revenue dollar.
A21: Bull narrative: commodity strength persists (record $62bn primary exports); livestock agency and rural real estate - the high-operating-leverage segments - keep inflecting; vertical integration lifts margin to 6.8% (below the 7.05% FY2022 peak); growth 5% fading to 2.5%.
A22: Bear narrative: FY2027-28 downturn - milk price to the low end of the $8.00-10.50 range plus El Nino; revenue -5% then -3%, margin troughs at 4.8% (FY2024 actual), recovering only to 5.5% as Farmlands below-cost pricing and wool structural decline bite; WC release cushions the down years.
A23: Weights rationale: house default 15/50/35 moved to 25/50/25 - bear raised (milk forecast already cut, no FY2027 guidance, >56% Agria/Elders bloc action risk), bull trimmed (needs commodity prices AND margin capture to land).

Sheet DCF_Bear
A3: Year | B3: FY2026A | C3: FY2027E | D3: FY2028E | E3: FY2029E | F3: FY2030E | G3: FY2031E | H3: FY2032E | I3: FY2033E | J3: FY2034E | K3: FY2035E | L3: FY2036E
A4: Index | B4: 0 | C4: 1 | D4: 2 | E4: 3 | F4: 4 | G4: 5 | H4: 6 | I4: 7 | J4: 8 | K4: 9 | L4: 10
A5: Revenue growth YoY | C5: -0.05 | D5: -0.03 | E5: 0.02 | F5: 0.02 | G5: 0.015 | H5: 0.015 | I5: 0.015 | J5: 0.015 | K5: 0.015 | L5: 0.015
A6: Revenue | B6: 1074.384 | C6: =B6*(1+C5) | D6: =C6*(1+D5) | E6: =D6*(1+E5) | F6: =E6*(1+F5) | G6: =F6*(1+G5) | H6: =G6*(1+H5) | I6: =H6*(1+I5) | J6: =I6*(1+J5) | ... L6: =K6*(1+L5)
A7: Operating EBITDA margin | B7: 0.0599 | C7: 0.052 | D7: 0.048 | E7: 0.052 | F7: 0.055 | G7: 0.055 | H7: 0.055 | I7: 0.055 | J7: 0.055 | K7: 0.055 | L7: 0.055
A8: Operating EBITDA | B8: 64.31 | C8: =C6*C7 | D8: =D6*D7 | E8: =E6*E7 | F8: =F6*F7 | G8: =G6*G7 | H8: =H6*H7 | I8: =I6*I7 | J8: =J6*J7 | ... L8: =L6*L7
A9: SBC % of revenue (SBC-zero market) | C9: 0 | D9: 0 | E9: 0 | F9: 0 | G9: 0 | H9: 0 | I9: 0 | J9: 0 | K9: 0 | L9: 0
A10: SBC | C10: =-C6*C9 | D10: =-D6*D9 | E10: =-E6*E9 | F10: =-F6*F9 | G10: =-G6*G9 | H10: =-H6*H9 | I10: =-I6*I9 | J10: =-J6*J9 | ... L10: =-L6*L9
A11: Lease payment (principal + lease interest) | C11: =-C6*Assumptions!$B$4 | D11: =-D6*Assumptions!$B$4 | E11: =-E6*Assumptions!$B$4 | F11: =-F6*Assumptions!$B$4 | G11: =-G6*Assumptions!$B$4 | H11: =-H6*Assumptions!$B$4 | I11: =-I6*Assumptions!$B$4 | J11: =-J6*Assumptions!$B$4 | ... L11: =-L6*Assumptions!$B$4
A12: Owned-asset D&A | C12: =-C6*Assumptions!$B$5 | D12: =-D6*Assumptions!$B$5 | E12: =-E6*Assumptions!$B$5 | F12: =-F6*Assumptions!$B$5 | G12: =-G6*Assumptions!$B$5 | H12: =-H6*Assumptions!$B$5 | I12: =-I6*Assumptions!$B$5 | J12: =-J6*Assumptions!$B$5 | ... L12: =-L6*Assumptions!$B$5
A13: Owner EBIT (post lease, post SBC) | C13: =C8+C10+C11+C12 | D13: =D8+D10+D11+D12 | E13: =E8+E10+E11+E12 | F13: =F8+F10+F11+F12 | G13: =G8+G10+G11+G12 | H13: =H8+H10+H11+H12 | I13: =I8+I10+I11+I12 | J13: =J8+J10+J11+J12 | ... L13: =L8+L10+L11+L12
A14: Cash tax rate | C14: 0.28 | D14: 0.28 | E14: 0.28 | F14: 0.28 | G14: 0.28 | H14: 0.28 | I14: 0.28 | J14: 0.28 | K14: 0.28 | L14: 0.28
A15: Cash tax | C15: =-MAX(0,C13)*C14 | D15: =-MAX(0,D13)*D14 | E15: =-MAX(0,E13)*E14 | F15: =-MAX(0,F13)*F14 | G15: =-MAX(0,G13)*G14 | H15: =-MAX(0,H13)*H14 | I15: =-MAX(0,I13)*I14 | J15: =-MAX(0,J13)*J14 | ... L15: =-MAX(0,L13)*L14
A16: NOPAT | C16: =C13+C15 | D16: =D13+D15 | E16: =E13+E15 | F16: =F13+F15 | G16: =G13+G15 | H16: =H13+H15 | I16: =I13+I15 | J16: =J13+J15 | ... L16: =L13+L15
A17: Add back owned D&A | C17: =-C12 | D17: =-D12 | E17: =-E12 | F17: =-F12 | G17: =-G12 | H17: =-H12 | I17: =-I12 | J17: =-J12 | ... L17: =-L12
A18: Capex | C18: =-C6*Assumptions!$B$6 | D18: =-D6*Assumptions!$B$6 | E18: =-E6*Assumptions!$B$6 | F18: =-F6*Assumptions!$B$6 | G18: =-G6*Assumptions!$B$6 | H18: =-H6*Assumptions!$B$6 | I18: =-I6*Assumptions!$B$6 | J18: =-J6*Assumptions!$B$6 | ... L18: =-L6*Assumptions!$B$6
A19: Working capital (on revenue change) | C19: =-Assumptions!$B$7*(C6-B6) | D19: =-Assumptions!$B$7*(D6-C6) | E19: =-Assumptions!$B$7*(E6-D6) | F19: =-Assumptions!$B$7*(F6-E6) | G19: =-Assumptions!$B$7*(G6-F6) | H19: =-Assumptions!$B$7*(H6-G6) | I19: =-Assumptions!$B$7*(I6-H6) | J19: =-Assumptions!$B$7*(J6-I6) | ... L19: =-Assumptions!$B$7*(L6-K6)
A20: Unlevered owner FCF | C20: =C16+C17+C18+C19 | D20: =D16+D17+D18+D19 | E20: =E16+E17+E18+E19 | F20: =F16+F17+F18+F19 | G20: =G16+G17+G18+G19 | H20: =H16+H17+H18+H19 | I20: =I16+I17+I18+I19 | J20: =J16+J17+J18+J19 | ... L20: =L16+L17+L18+L19
A21: Discount factor | C21: =1/(1+Assumptions!$B$3)^C4 | D21: =1/(1+Assumptions!$B$3)^D4 | E21: =1/(1+Assumptions!$B$3)^E4 | F21: =1/(1+Assumptions!$B$3)^F4 | G21: =1/(1+Assumptions!$B$3)^G4 | H21: =1/(1+Assumptions!$B$3)^H4 | I21: =1/(1+Assumptions!$B$3)^I4 | J21: =1/(1+Assumptions!$B$3)^J4 | ... L21: =1/(1+Assumptions!$B$3)^L4
A22: PV of FCF | C22: =C20*C21 | D22: =D20*D21 | E22: =E20*E21 | F22: =F20*F21 | G22: =G20*G21 | H22: =H20*H21 | I22: =I20*I21 | J22: =J20*J21 | ... L22: =L20*L21
A24: Memo: owner FCF margin | C24: =C20/C6 | D24: =D20/D6 | E24: =E20/E6 | F24: =F20/F6 | G24: =G20/G6 | H24: =H20/H6 | I24: =I20/I6 | J24: =J20/J6 | ... L24: =L20/L6
A26: Sum PV of FCF | B26: =SUM(C22:L22)
A27: Terminal growth | B27: =Assumptions!$B$15
A28: Terminal FCF | B28: =L20*(1+B27)
A29: Gordon TV | B29: =IF(Assumptions!$B$3>B27,B28/(Assumptions!$B$3-B27),"n/a")
A30: Exit-cap TV (cap x terminal EBITDA) | B30: =Assumptions!$C$15*L8
A31: TV used = MAX(0,MIN(Gordon,cap)) | B31: =MAX(0,MIN(B29,B30))
A32: Implied exit multiple on FCF | B32: =IF(L20>0,B31/L20,"n/a")
A33: PV of terminal value | B33: =B31*L21
A34: Enterprise value | B34: =B26+B33
A35: Less net debt | B35: =-Assumptions!$B$9
A36: Equity value | B36: =B34+B35
A37: Diluted shares (m) | B37: =Assumptions!$B$10
A38: VALUE PER SHARE | B38: =B36/B37
A39: Upside vs price | B39: =B38/Assumptions!$B$11-1
A41: Street value per share (= house; SBC-zero) | B41: =B38
A43: Memo: market-convention value (exit cap AS the TV) | B43: =(B26+B30*L21+B35)/B37

Sheet DCF_Base
A3: Year | B3: FY2026A | C3: FY2027E | D3: FY2028E | E3: FY2029E | F3: FY2030E | G3: FY2031E | H3: FY2032E | I3: FY2033E | J3: FY2034E | K3: FY2035E | L3: FY2036E
A4: Index | B4: 0 | C4: 1 | D4: 2 | E4: 3 | F4: 4 | G4: 5 | H4: 6 | I4: 7 | J4: 8 | K4: 9 | L4: 10
A5: Revenue growth YoY | C5: 0.02 | D5: 0.025 | E5: 0.025 | F5: 0.025 | G5: 0.025 | H5: 0.02 | I5: 0.02 | J5: 0.02 | K5: 0.02 | L5: 0.02
A6: Revenue | B6: 1074.384 | C6: =B6*(1+C5) | D6: =C6*(1+D5) | E6: =D6*(1+E5) | F6: =E6*(1+F5) | G6: =F6*(1+G5) | H6: =G6*(1+H5) | I6: =H6*(1+I5) | J6: =I6*(1+J5) | ... L6: =K6*(1+L5)
A7: Operating EBITDA margin | B7: 0.0599 | C7: 0.06 | D7: 0.06 | E7: 0.06 | F7: 0.06 | G7: 0.06 | H7: 0.06 | I7: 0.06 | J7: 0.06 | K7: 0.06 | L7: 0.06
A8: Operating EBITDA | B8: 64.31 | C8: =C6*C7 | D8: =D6*D7 | E8: =E6*E7 | F8: =F6*F7 | G8: =G6*G7 | H8: =H6*H7 | I8: =I6*I7 | J8: =J6*J7 | ... L8: =L6*L7
A9: SBC % of revenue (SBC-zero market) | C9: 0 | D9: 0 | E9: 0 | F9: 0 | G9: 0 | H9: 0 | I9: 0 | J9: 0 | K9: 0 | L9: 0
A10: SBC | C10: =-C6*C9 | D10: =-D6*D9 | E10: =-E6*E9 | F10: =-F6*F9 | G10: =-G6*G9 | H10: =-H6*H9 | I10: =-I6*I9 | J10: =-J6*J9 | ... L10: =-L6*L9
A11: Lease payment (principal + lease interest) | C11: =-C6*Assumptions!$B$4 | D11: =-D6*Assumptions!$B$4 | E11: =-E6*Assumptions!$B$4 | F11: =-F6*Assumptions!$B$4 | G11: =-G6*Assumptions!$B$4 | H11: =-H6*Assumptions!$B$4 | I11: =-I6*Assumptions!$B$4 | J11: =-J6*Assumptions!$B$4 | ... L11: =-L6*Assumptions!$B$4
A12: Owned-asset D&A | C12: =-C6*Assumptions!$B$5 | D12: =-D6*Assumptions!$B$5 | E12: =-E6*Assumptions!$B$5 | F12: =-F6*Assumptions!$B$5 | G12: =-G6*Assumptions!$B$5 | H12: =-H6*Assumptions!$B$5 | I12: =-I6*Assumptions!$B$5 | J12: =-J6*Assumptions!$B$5 | ... L12: =-L6*Assumptions!$B$5
A13: Owner EBIT (post lease, post SBC) | C13: =C8+C10+C11+C12 | D13: =D8+D10+D11+D12 | E13: =E8+E10+E11+E12 | F13: =F8+F10+F11+F12 | G13: =G8+G10+G11+G12 | H13: =H8+H10+H11+H12 | I13: =I8+I10+I11+I12 | J13: =J8+J10+J11+J12 | ... L13: =L8+L10+L11+L12
A14: Cash tax rate | C14: 0.28 | D14: 0.28 | E14: 0.28 | F14: 0.28 | G14: 0.28 | H14: 0.28 | I14: 0.28 | J14: 0.28 | K14: 0.28 | L14: 0.28
A15: Cash tax | C15: =-MAX(0,C13)*C14 | D15: =-MAX(0,D13)*D14 | E15: =-MAX(0,E13)*E14 | F15: =-MAX(0,F13)*F14 | G15: =-MAX(0,G13)*G14 | H15: =-MAX(0,H13)*H14 | I15: =-MAX(0,I13)*I14 | J15: =-MAX(0,J13)*J14 | ... L15: =-MAX(0,L13)*L14
A16: NOPAT | C16: =C13+C15 | D16: =D13+D15 | E16: =E13+E15 | F16: =F13+F15 | G16: =G13+G15 | H16: =H13+H15 | I16: =I13+I15 | J16: =J13+J15 | ... L16: =L13+L15
A17: Add back owned D&A | C17: =-C12 | D17: =-D12 | E17: =-E12 | F17: =-F12 | G17: =-G12 | H17: =-H12 | I17: =-I12 | J17: =-J12 | ... L17: =-L12
A18: Capex | C18: =-C6*Assumptions!$B$6 | D18: =-D6*Assumptions!$B$6 | E18: =-E6*Assumptions!$B$6 | F18: =-F6*Assumptions!$B$6 | G18: =-G6*Assumptions!$B$6 | H18: =-H6*Assumptions!$B$6 | I18: =-I6*Assumptions!$B$6 | J18: =-J6*Assumptions!$B$6 | ... L18: =-L6*Assumptions!$B$6
A19: Working capital (on revenue change) | C19: =-Assumptions!$B$7*(C6-B6) | D19: =-Assumptions!$B$7*(D6-C6) | E19: =-Assumptions!$B$7*(E6-D6) | F19: =-Assumptions!$B$7*(F6-E6) | G19: =-Assumptions!$B$7*(G6-F6) | H19: =-Assumptions!$B$7*(H6-G6) | I19: =-Assumptions!$B$7*(I6-H6) | J19: =-Assumptions!$B$7*(J6-I6) | ... L19: =-Assumptions!$B$7*(L6-K6)
A20: Unlevered owner FCF | C20: =C16+C17+C18+C19 | D20: =D16+D17+D18+D19 | E20: =E16+E17+E18+E19 | F20: =F16+F17+F18+F19 | G20: =G16+G17+G18+G19 | H20: =H16+H17+H18+H19 | I20: =I16+I17+I18+I19 | J20: =J16+J17+J18+J19 | ... L20: =L16+L17+L18+L19
A21: Discount factor | C21: =1/(1+Assumptions!$B$3)^C4 | D21: =1/(1+Assumptions!$B$3)^D4 | E21: =1/(1+Assumptions!$B$3)^E4 | F21: =1/(1+Assumptions!$B$3)^F4 | G21: =1/(1+Assumptions!$B$3)^G4 | H21: =1/(1+Assumptions!$B$3)^H4 | I21: =1/(1+Assumptions!$B$3)^I4 | J21: =1/(1+Assumptions!$B$3)^J4 | ... L21: =1/(1+Assumptions!$B$3)^L4
A22: PV of FCF | C22: =C20*C21 | D22: =D20*D21 | E22: =E20*E21 | F22: =F20*F21 | G22: =G20*G21 | H22: =H20*H21 | I22: =I20*I21 | J22: =J20*J21 | ... L22: =L20*L21
A24: Memo: owner FCF margin | C24: =C20/C6 | D24: =D20/D6 | E24: =E20/E6 | F24: =F20/F6 | G24: =G20/G6 | H24: =H20/H6 | I24: =I20/I6 | J24: =J20/J6 | ... L24: =L20/L6
A26: Sum PV of FCF | B26: =SUM(C22:L22)
A27: Terminal growth | B27: =Assumptions!$B$16
A28: Terminal FCF | B28: =L20*(1+B27)
A29: Gordon TV | B29: =IF(Assumptions!$B$3>B27,B28/(Assumptions!$B$3-B27),"n/a")
A30: Exit-cap TV (cap x terminal EBITDA) | B30: =Assumptions!$C$16*L8
A31: TV used = MAX(0,MIN(Gordon,cap)) | B31: =MAX(0,MIN(B29,B30))
A32: Implied exit multiple on FCF | B32: =IF(L20>0,B31/L20,"n/a")
A33: PV of terminal value | B33: =B31*L21
A34: Enterprise value | B34: =B26+B33
A35: Less net debt | B35: =-Assumptions!$B$9
A36: Equity value | B36: =B34+B35
A37: Diluted shares (m) | B37: =Assumptions!$B$10
A38: VALUE PER SHARE | B38: =B36/B37
A39: Upside vs price | B39: =B38/Assumptions!$B$11-1
A41: Street value per share (= house; SBC-zero) | B41: =B38
A43: Memo: market-convention value (exit cap AS the TV) | B43: =(B26+B30*L21+B35)/B37

Sheet DCF_Bull
A3: Year | B3: FY2026A | C3: FY2027E | D3: FY2028E | E3: FY2029E | F3: FY2030E | G3: FY2031E | H3: FY2032E | I3: FY2033E | J3: FY2034E | K3: FY2035E | L3: FY2036E
A4: Index | B4: 0 | C4: 1 | D4: 2 | E4: 3 | F4: 4 | G4: 5 | H4: 6 | I4: 7 | J4: 8 | K4: 9 | L4: 10
A5: Revenue growth YoY | C5: 0.05 | D5: 0.04 | E5: 0.035 | F5: 0.03 | G5: 0.03 | H5: 0.025 | I5: 0.025 | J5: 0.025 | K5: 0.025 | L5: 0.025
A6: Revenue | B6: 1074.384 | C6: =B6*(1+C5) | D6: =C6*(1+D5) | E6: =D6*(1+E5) | F6: =E6*(1+F5) | G6: =F6*(1+G5) | H6: =G6*(1+H5) | I6: =H6*(1+I5) | J6: =I6*(1+J5) | ... L6: =K6*(1+L5)
A7: Operating EBITDA margin | B7: 0.0599 | C7: 0.062 | D7: 0.064 | E7: 0.066 | F7: 0.068 | G7: 0.068 | H7: 0.068 | I7: 0.068 | J7: 0.068 | K7: 0.068 | L7: 0.068
A8: Operating EBITDA | B8: 64.31 | C8: =C6*C7 | D8: =D6*D7 | E8: =E6*E7 | F8: =F6*F7 | G8: =G6*G7 | H8: =H6*H7 | I8: =I6*I7 | J8: =J6*J7 | ... L8: =L6*L7
A9: SBC % of revenue (SBC-zero market) | C9: 0 | D9: 0 | E9: 0 | F9: 0 | G9: 0 | H9: 0 | I9: 0 | J9: 0 | K9: 0 | L9: 0
A10: SBC | C10: =-C6*C9 | D10: =-D6*D9 | E10: =-E6*E9 | F10: =-F6*F9 | G10: =-G6*G9 | H10: =-H6*H9 | I10: =-I6*I9 | J10: =-J6*J9 | ... L10: =-L6*L9
A11: Lease payment (principal + lease interest) | C11: =-C6*Assumptions!$B$4 | D11: =-D6*Assumptions!$B$4 | E11: =-E6*Assumptions!$B$4 | F11: =-F6*Assumptions!$B$4 | G11: =-G6*Assumptions!$B$4 | H11: =-H6*Assumptions!$B$4 | I11: =-I6*Assumptions!$B$4 | J11: =-J6*Assumptions!$B$4 | ... L11: =-L6*Assumptions!$B$4
A12: Owned-asset D&A | C12: =-C6*Assumptions!$B$5 | D12: =-D6*Assumptions!$B$5 | E12: =-E6*Assumptions!$B$5 | F12: =-F6*Assumptions!$B$5 | G12: =-G6*Assumptions!$B$5 | H12: =-H6*Assumptions!$B$5 | I12: =-I6*Assumptions!$B$5 | J12: =-J6*Assumptions!$B$5 | ... L12: =-L6*Assumptions!$B$5
A13: Owner EBIT (post lease, post SBC) | C13: =C8+C10+C11+C12 | D13: =D8+D10+D11+D12 | E13: =E8+E10+E11+E12 | F13: =F8+F10+F11+F12 | G13: =G8+G10+G11+G12 | H13: =H8+H10+H11+H12 | I13: =I8+I10+I11+I12 | J13: =J8+J10+J11+J12 | ... L13: =L8+L10+L11+L12
A14: Cash tax rate | C14: 0.28 | D14: 0.28 | E14: 0.28 | F14: 0.28 | G14: 0.28 | H14: 0.28 | I14: 0.28 | J14: 0.28 | K14: 0.28 | L14: 0.28
A15: Cash tax | C15: =-MAX(0,C13)*C14 | D15: =-MAX(0,D13)*D14 | E15: =-MAX(0,E13)*E14 | F15: =-MAX(0,F13)*F14 | G15: =-MAX(0,G13)*G14 | H15: =-MAX(0,H13)*H14 | I15: =-MAX(0,I13)*I14 | J15: =-MAX(0,J13)*J14 | ... L15: =-MAX(0,L13)*L14
A16: NOPAT | C16: =C13+C15 | D16: =D13+D15 | E16: =E13+E15 | F16: =F13+F15 | G16: =G13+G15 | H16: =H13+H15 | I16: =I13+I15 | J16: =J13+J15 | ... L16: =L13+L15
A17: Add back owned D&A | C17: =-C12 | D17: =-D12 | E17: =-E12 | F17: =-F12 | G17: =-G12 | H17: =-H12 | I17: =-I12 | J17: =-J12 | ... L17: =-L12
A18: Capex | C18: =-C6*Assumptions!$B$6 | D18: =-D6*Assumptions!$B$6 | E18: =-E6*Assumptions!$B$6 | F18: =-F6*Assumptions!$B$6 | G18: =-G6*Assumptions!$B$6 | H18: =-H6*Assumptions!$B$6 | I18: =-I6*Assumptions!$B$6 | J18: =-J6*Assumptions!$B$6 | ... L18: =-L6*Assumptions!$B$6
A19: Working capital (on revenue change) | C19: =-Assumptions!$B$7*(C6-B6) | D19: =-Assumptions!$B$7*(D6-C6) | E19: =-Assumptions!$B$7*(E6-D6) | F19: =-Assumptions!$B$7*(F6-E6) | G19: =-Assumptions!$B$7*(G6-F6) | H19: =-Assumptions!$B$7*(H6-G6) | I19: =-Assumptions!$B$7*(I6-H6) | J19: =-Assumptions!$B$7*(J6-I6) | ... L19: =-Assumptions!$B$7*(L6-K6)
A20: Unlevered owner FCF | C20: =C16+C17+C18+C19 | D20: =D16+D17+D18+D19 | E20: =E16+E17+E18+E19 | F20: =F16+F17+F18+F19 | G20: =G16+G17+G18+G19 | H20: =H16+H17+H18+H19 | I20: =I16+I17+I18+I19 | J20: =J16+J17+J18+J19 | ... L20: =L16+L17+L18+L19
A21: Discount factor | C21: =1/(1+Assumptions!$B$3)^C4 | D21: =1/(1+Assumptions!$B$3)^D4 | E21: =1/(1+Assumptions!$B$3)^E4 | F21: =1/(1+Assumptions!$B$3)^F4 | G21: =1/(1+Assumptions!$B$3)^G4 | H21: =1/(1+Assumptions!$B$3)^H4 | I21: =1/(1+Assumptions!$B$3)^I4 | J21: =1/(1+Assumptions!$B$3)^J4 | ... L21: =1/(1+Assumptions!$B$3)^L4
A22: PV of FCF | C22: =C20*C21 | D22: =D20*D21 | E22: =E20*E21 | F22: =F20*F21 | G22: =G20*G21 | H22: =H20*H21 | I22: =I20*I21 | J22: =J20*J21 | ... L22: =L20*L21
A24: Memo: owner FCF margin | C24: =C20/C6 | D24: =D20/D6 | E24: =E20/E6 | F24: =F20/F6 | G24: =G20/G6 | H24: =H20/H6 | I24: =I20/I6 | J24: =J20/J6 | ... L24: =L20/L6
A26: Sum PV of FCF | B26: =SUM(C22:L22)
A27: Terminal growth | B27: =Assumptions!$B$17
A28: Terminal FCF | B28: =L20*(1+B27)
A29: Gordon TV | B29: =IF(Assumptions!$B$3>B27,B28/(Assumptions!$B$3-B27),"n/a")
A30: Exit-cap TV (cap x terminal EBITDA) | B30: =Assumptions!$C$17*L8
A31: TV used = MAX(0,MIN(Gordon,cap)) | B31: =MAX(0,MIN(B29,B30))
A32: Implied exit multiple on FCF | B32: =IF(L20>0,B31/L20,"n/a")
A33: PV of terminal value | B33: =B31*L21
A34: Enterprise value | B34: =B26+B33
A35: Less net debt | B35: =-Assumptions!$B$9
A36: Equity value | B36: =B34+B35
A37: Diluted shares (m) | B37: =Assumptions!$B$10
A38: VALUE PER SHARE | B38: =B36/B37
A39: Upside vs price | B39: =B38/Assumptions!$B$11-1
A41: Street value per share (= house; SBC-zero) | B41: =B38
A43: Memo: market-convention value (exit cap AS the TV) | B43: =(B26+B30*L21+B35)/B37

Sheet FCF_Quality
A1: Reported FCF reconciled to owner FCF, NZD millions (SBC-zero: the only owner adjustment is the IFRS-16 lease principal)
A3: Line | B3: FY2020 | C3: FY2021 | D3: FY2022 | E3: FY2023 | F3: FY2024 | G3: FY2025 | H3: FY2026
A4: Free cash flow (company definition, OCF less capex) | B4: 22.352 | C4: 50.862 | D4: 14.853 | E4: 8.333 | F4: 34.888 | G4: -5.031 | H4: 46.008
A5: less: lease principal repaid (financing activities) | B5: -17.586 | C5: -18.299 | D5: -18.873 | E5: -19.532 | F5: -21.203 | G5: -22.608 | H5: -24.03
A6: less: SBC incl equity-award taxes (none - SBC-zero) | B6: 0 | C6: 0 | D6: 0 | E6: 0 | F6: 0 | G6: 0 | H6: 0
A7: less: interest income strip (n/a - net debt position) | B7: 0 | C7: 0 | D7: 0 | E7: 0 | F7: 0 | G7: 0 | H7: 0
A8: Owner FCF (after leases) | B8: =B4+B5+B6+B7 | C8: =C4+C5+C6+C7 | D8: =D4+D5+D6+D7 | E8: =E4+E5+E6+E7 | F8: =F4+F5+F6+F7 | G8: =G4+G5+G6+G7 | H8: =H4+H5+H6+H7
A9: Reported FCF margin | B9: =B4/B11 | C9: =C4/C11 | D9: =D4/D11 | E9: =E4/E11 | F9: =F4/F11 | G9: =G4/G11 | H9: =H4/H11
A10: Owner FCF margin | B10: =B8/B11 | C10: =C8/C11 | D10: =D8/D11 | E10: =E8/E11 | F10: =F8/F11 | G10: =G8/G11 | H10: =H8/H11
A11: Memo: revenue | B11: 788.036 | C11: 847.815 | D11: 952.7 | E11: 975.692 | F11: 915.946 | G11: 975.344 | H11: 1074.384
A12: Memo: cash taxes paid (abnormally low FY2024-26 - trough timing; model uses 28%) | B12: -4.968 | D12: -5.623 | E12: -13.846 | F12: -2.102 | G12: 0 | H12: -2.157
A14: Seven-year owner FCF total | B14: =SUM(B8:H8)
A15: Empirical cross-check: FY2020-26 dividends $70.5m + Nexan $19.7m were funded by net debt rising $74.9m -> cumulative underlying FCFE ~$15m over six years (~$2.5m/yr). The headline FY2026 FCF of $46.0m is working-capital timing plus a capex holiday, not earnings power.

Sheet Valuation
A1: PGW.NZ valuation summary (NZD)
A3: Scenario | B3: Value/share | C3: Upside vs price | D3: Weight | E3: Street value/share | F3: Market-convention memo
A4: Bear | B4: =DCF_Bear!$B$38 | C4: =B4/Assumptions!$B$11-1 | D4: =Assumptions!$D$15 | E4: =DCF_Bear!$B$41 | F4: =DCF_Bear!$B$43
A5: Base | B5: =DCF_Base!$B$38 | C5: =B5/Assumptions!$B$11-1 | D5: =Assumptions!$D$16 | E5: =DCF_Base!$B$41 | F5: =DCF_Base!$B$43
A6: Bull | B6: =DCF_Bull!$B$38 | C6: =B6/Assumptions!$B$11-1 | D6: =Assumptions!$D$17 | E6: =DCF_Bull!$B$41 | F6: =DCF_Bull!$B$43
A8: Probability-weighted intrinsic value | B8: =SUMPRODUCT(B4:B6,D4:D6)
A9: Weighted market-convention memo | B9: =SUMPRODUCT(F4:F6,D4:D6)
A10: Margin of safety vs weighted IV | B10: =1-Assumptions!$B$11/B8
A11: Band position (house vs street) | B11: n/a - SBC-zero market, house and street coincide
A13: Entry prices at 15% IRR hurdle (interim FCF + capped TV at WACC, discounted at hurdle, less net debt)
A14: Bear | B14: =(SUMPRODUCT(DCF_Bear!C20:L20/(1+Assumptions!$B$12)^DCF_Bear!C4:L4)+DCF_Bear!B31/(1+Assumptions!$B$12)^10-Assumptions!$B$9)/Assumptions!$B$10
A15: Base | B15: =(SUMPRODUCT(DCF_Base!C20:L20/(1+Assumptions!$B$12)^DCF_Base!C4:L4)+DCF_Base!B31/(1+Assumptions!$B$12)^10-Assumptions!$B$9)/Assumptions!$B$10
A16: Bull | B16: =(SUMPRODUCT(DCF_Bull!C20:L20/(1+Assumptions!$B$12)^DCF_Bull!C4:L4)+DCF_Bull!B31/(1+Assumptions!$B$12)^10-Assumptions!$B$9)/Assumptions!$B$10
A17: Weighted entry price | B17: =SUMPRODUCT(B14:B16,D4:D6)
A19: Required-return table (base case): value per share at required return r
A20: r | B20: Value/share
A21: 0.09 | B21: =IF($A21>Assumptions!$B$16,(SUMPRODUCT(DCF_Base!$C$20:$L$20/(1+$A21)^DCF_Base!$C$4:$L$4)+MAX(0,MIN(DCF_Base!$L$20*(1+Assumptions!$B$16)/($A21-Assumptions!$B$16),Assumptions!$C$16*DCF_Base!$L$8))/(1+$A21)^10-Assumptions!$B$9)/Assumptions!$B$10,"n/a")
A22: 0.1 | B22: =IF($A22>Assumptions!$B$16,(SUMPRODUCT(DCF_Base!$C$20:$L$20/(1+$A22)^DCF_Base!$C$4:$L$4)+MAX(0,MIN(DCF_Base!$L$20*(1+Assumptions!$B$16)/($A22-Assumptions!$B$16),Assumptions!$C$16*DCF_Base!$L$8))/(1+$A22)^10-Assumptions!$B$9)/Assumptions!$B$10,"n/a")
A23: 0.11 | B23: =IF($A23>Assumptions!$B$16,(SUMPRODUCT(DCF_Base!$C$20:$L$20/(1+$A23)^DCF_Base!$C$4:$L$4)+MAX(0,MIN(DCF_Base!$L$20*(1+Assumptions!$B$16)/($A23-Assumptions!$B$16),Assumptions!$C$16*DCF_Base!$L$8))/(1+$A23)^10-Assumptions!$B$9)/Assumptions!$B$10,"n/a")
A24: 0.12 | B24: =IF($A24>Assumptions!$B$16,(SUMPRODUCT(DCF_Base!$C$20:$L$20/(1+$A24)^DCF_Base!$C$4:$L$4)+MAX(0,MIN(DCF_Base!$L$20*(1+Assumptions!$B$16)/($A24-Assumptions!$B$16),Assumptions!$C$16*DCF_Base!$L$8))/(1+$A24)^10-Assumptions!$B$9)/Assumptions!$B$10,"n/a")
A25: 0.135 | B25: =IF($A25>Assumptions!$B$16,(SUMPRODUCT(DCF_Base!$C$20:$L$20/(1+$A25)^DCF_Base!$C$4:$L$4)+MAX(0,MIN(DCF_Base!$L$20*(1+Assumptions!$B$16)/($A25-Assumptions!$B$16),Assumptions!$C$16*DCF_Base!$L$8))/(1+$A25)^10-Assumptions!$B$9)/Assumptions!$B$10,"n/a")
A26: 0.15 | B26: =IF($A26>Assumptions!$B$16,(SUMPRODUCT(DCF_Base!$C$20:$L$20/(1+$A26)^DCF_Base!$C$4:$L$4)+MAX(0,MIN(DCF_Base!$L$20*(1+Assumptions!$B$16)/($A26-Assumptions!$B$16),Assumptions!$C$16*DCF_Base!$L$8))/(1+$A26)^10-Assumptions!$B$9)/Assumptions!$B$10,"n/a")
A29: Sensitivity: value per share, WACC (rows) x terminal growth (cols), base case
B30: 0.01 | C30: 0.015 | D30: 0.02 | E30: 0.025 | F30: 0.03
A31: 0.115 | B31: =IF($A31>B$30,(SUMPRODUCT(DCF_Base!$C$20:$L$20/(1+$A31)^DCF_Base!$C$4:$L$4)+MAX(0,MIN(DCF_Base!$L$20*(1+B$30)/($A31-B$30),Assumptions!$C$16*DCF_Base!$L$8))/(1+$A31)^10-Assumptions!$B$9)/Assumptions!$B$10,"n/a") | C31: =IF($A31>C$30,(SUMPRODUCT(DCF_Base!$C$20:$L$20/(1+$A31)^DCF_Base!$C$4:$L$4)+MAX(0,MIN(DCF_Base!$L$20*(1+C$30)/($A31-C$30),Assumptions!$C$16*DCF_Base!$L$8))/(1+$A31)^10-Assumptions!$B$9)/Assumptions!$B$10,"n/a") | D31: =IF($A31>D$30,(SUMPRODUCT(DCF_Base!$C$20:$L$20/(1+$A31)^DCF_Base!$C$4:$L$4)+MAX(0,MIN(DCF_Base!$L$20*(1+D$30)/($A31-D$30),Assumptions!$C$16*DCF_Base!$L$8))/(1+$A31)^10-Assumptions!$B$9)/Assumptions!$B$10,"n/a") | E31: =IF($A31>E$30,(SUMPRODUCT(DCF_Base!$C$20:$L$20/(1+$A31)^DCF_Base!$C$4:$L$4)+MAX(0,MIN(DCF_Base!$L$20*(1+E$30)/($A31-E$30),Assumptions!$C$16*DCF_Base!$L$8))/(1+$A31)^10-Assumptions!$B$9)/Assumptions!$B$10,"n/a") | F31: =IF($A31>F$30,(SUMPRODUCT(DCF_Base!$C$20:$L$20/(1+$A31)^DCF_Base!$C$4:$L$4)+MAX(0,MIN(DCF_Base!$L$20*(1+F$30)/($A31-F$30),Assumptions!$C$16*DCF_Base!$L$8))/(1+$A31)^10-Assumptions!$B$9)/Assumptions!$B$10,"n/a")
A32: 0.125 | B32: =IF($A32>B$30,(SUMPRODUCT(DCF_Base!$C$20:$L$20/(1+$A32)^DCF_Base!$C$4:$L$4)+MAX(0,MIN(DCF_Base!$L$20*(1+B$30)/($A32-B$30),Assumptions!$C$16*DCF_Base!$L$8))/(1+$A32)^10-Assumptions!$B$9)/Assumptions!$B$10,"n/a") | C32: =IF($A32>C$30,(SUMPRODUCT(DCF_Base!$C$20:$L$20/(1+$A32)^DCF_Base!$C$4:$L$4)+MAX(0,MIN(DCF_Base!$L$20*(1+C$30)/($A32-C$30),Assumptions!$C$16*DCF_Base!$L$8))/(1+$A32)^10-Assumptions!$B$9)/Assumptions!$B$10,"n/a") | D32: =IF($A32>D$30,(SUMPRODUCT(DCF_Base!$C$20:$L$20/(1+$A32)^DCF_Base!$C$4:$L$4)+MAX(0,MIN(DCF_Base!$L$20*(1+D$30)/($A32-D$30),Assumptions!$C$16*DCF_Base!$L$8))/(1+$A32)^10-Assumptions!$B$9)/Assumptions!$B$10,"n/a") | E32: =IF($A32>E$30,(SUMPRODUCT(DCF_Base!$C$20:$L$20/(1+$A32)^DCF_Base!$C$4:$L$4)+MAX(0,MIN(DCF_Base!$L$20*(1+E$30)/($A32-E$30),Assumptions!$C$16*DCF_Base!$L$8))/(1+$A32)^10-Assumptions!$B$9)/Assumptions!$B$10,"n/a") | F32: =IF($A32>F$30,(SUMPRODUCT(DCF_Base!$C$20:$L$20/(1+$A32)^DCF_Base!$C$4:$L$4)+MAX(0,MIN(DCF_Base!$L$20*(1+F$30)/($A32-F$30),Assumptions!$C$16*DCF_Base!$L$8))/(1+$A32)^10-Assumptions!$B$9)/Assumptions!$B$10,"n/a")
A33: 0.135 | B33: =IF($A33>B$30,(SUMPRODUCT(DCF_Base!$C$20:$L$20/(1+$A33)^DCF_Base!$C$4:$L$4)+MAX(0,MIN(DCF_Base!$L$20*(1+B$30)/($A33-B$30),Assumptions!$C$16*DCF_Base!$L$8))/(1+$A33)^10-Assumptions!$B$9)/Assumptions!$B$10,"n/a") | C33: =IF($A33>C$30,(SUMPRODUCT(DCF_Base!$C$20:$L$20/(1+$A33)^DCF_Base!$C$4:$L$4)+MAX(0,MIN(DCF_Base!$L$20*(1+C$30)/($A33-C$30),Assumptions!$C$16*DCF_Base!$L$8))/(1+$A33)^10-Assumptions!$B$9)/Assumptions!$B$10,"n/a") | D33: =IF($A33>D$30,(SUMPRODUCT(DCF_Base!$C$20:$L$20/(1+$A33)^DCF_Base!$C$4:$L$4)+MAX(0,MIN(DCF_Base!$L$20*(1+D$30)/($A33-D$30),Assumptions!$C$16*DCF_Base!$L$8))/(1+$A33)^10-Assumptions!$B$9)/Assumptions!$B$10,"n/a") | E33: =IF($A33>E$30,(SUMPRODUCT(DCF_Base!$C$20:$L$20/(1+$A33)^DCF_Base!$C$4:$L$4)+MAX(0,MIN(DCF_Base!$L$20*(1+E$30)/($A33-E$30),Assumptions!$C$16*DCF_Base!$L$8))/(1+$A33)^10-Assumptions!$B$9)/Assumptions!$B$10,"n/a") | F33: =IF($A33>F$30,(SUMPRODUCT(DCF_Base!$C$20:$L$20/(1+$A33)^DCF_Base!$C$4:$L$4)+MAX(0,MIN(DCF_Base!$L$20*(1+F$30)/($A33-F$30),Assumptions!$C$16*DCF_Base!$L$8))/(1+$A33)^10-Assumptions!$B$9)/Assumptions!$B$10,"n/a")
A34: 0.145 | B34: =IF($A34>B$30,(SUMPRODUCT(DCF_Base!$C$20:$L$20/(1+$A34)^DCF_Base!$C$4:$L$4)+MAX(0,MIN(DCF_Base!$L$20*(1+B$30)/($A34-B$30),Assumptions!$C$16*DCF_Base!$L$8))/(1+$A34)^10-Assumptions!$B$9)/Assumptions!$B$10,"n/a") | C34: =IF($A34>C$30,(SUMPRODUCT(DCF_Base!$C$20:$L$20/(1+$A34)^DCF_Base!$C$4:$L$4)+MAX(0,MIN(DCF_Base!$L$20*(1+C$30)/($A34-C$30),Assumptions!$C$16*DCF_Base!$L$8))/(1+$A34)^10-Assumptions!$B$9)/Assumptions!$B$10,"n/a") | D34: =IF($A34>D$30,(SUMPRODUCT(DCF_Base!$C$20:$L$20/(1+$A34)^DCF_Base!$C$4:$L$4)+MAX(0,MIN(DCF_Base!$L$20*(1+D$30)/($A34-D$30),Assumptions!$C$16*DCF_Base!$L$8))/(1+$A34)^10-Assumptions!$B$9)/Assumptions!$B$10,"n/a") | E34: =IF($A34>E$30,(SUMPRODUCT(DCF_Base!$C$20:$L$20/(1+$A34)^DCF_Base!$C$4:$L$4)+MAX(0,MIN(DCF_Base!$L$20*(1+E$30)/($A34-E$30),Assumptions!$C$16*DCF_Base!$L$8))/(1+$A34)^10-Assumptions!$B$9)/Assumptions!$B$10,"n/a") | F34: =IF($A34>F$30,(SUMPRODUCT(DCF_Base!$C$20:$L$20/(1+$A34)^DCF_Base!$C$4:$L$4)+MAX(0,MIN(DCF_Base!$L$20*(1+F$30)/($A34-F$30),Assumptions!$C$16*DCF_Base!$L$8))/(1+$A34)^10-Assumptions!$B$9)/Assumptions!$B$10,"n/a")
A35: 0.155 | B35: =IF($A35>B$30,(SUMPRODUCT(DCF_Base!$C$20:$L$20/(1+$A35)^DCF_Base!$C$4:$L$4)+MAX(0,MIN(DCF_Base!$L$20*(1+B$30)/($A35-B$30),Assumptions!$C$16*DCF_Base!$L$8))/(1+$A35)^10-Assumptions!$B$9)/Assumptions!$B$10,"n/a") | C35: =IF($A35>C$30,(SUMPRODUCT(DCF_Base!$C$20:$L$20/(1+$A35)^DCF_Base!$C$4:$L$4)+MAX(0,MIN(DCF_Base!$L$20*(1+C$30)/($A35-C$30),Assumptions!$C$16*DCF_Base!$L$8))/(1+$A35)^10-Assumptions!$B$9)/Assumptions!$B$10,"n/a") | D35: =IF($A35>D$30,(SUMPRODUCT(DCF_Base!$C$20:$L$20/(1+$A35)^DCF_Base!$C$4:$L$4)+MAX(0,MIN(DCF_Base!$L$20*(1+D$30)/($A35-D$30),Assumptions!$C$16*DCF_Base!$L$8))/(1+$A35)^10-Assumptions!$B$9)/Assumptions!$B$10,"n/a") | E35: =IF($A35>E$30,(SUMPRODUCT(DCF_Base!$C$20:$L$20/(1+$A35)^DCF_Base!$C$4:$L$4)+MAX(0,MIN(DCF_Base!$L$20*(1+E$30)/($A35-E$30),Assumptions!$C$16*DCF_Base!$L$8))/(1+$A35)^10-Assumptions!$B$9)/Assumptions!$B$10,"n/a") | F35: =IF($A35>F$30,(SUMPRODUCT(DCF_Base!$C$20:$L$20/(1+$A35)^DCF_Base!$C$4:$L$4)+MAX(0,MIN(DCF_Base!$L$20*(1+F$30)/($A35-F$30),Assumptions!$C$16*DCF_Base!$L$8))/(1+$A35)^10-Assumptions!$B$9)/Assumptions!$B$10,"n/a")
A37: House cell: WACC 13.5% x g 2.0%. Values can be negative - equity value below zero under those parameters.
