Workbook

Sheet Inputs
A1: CWP.AX blended NTA / earnings model (AUD, millions)
A3: Current price (AUD) | B3: 6.53 | D3: Historical June-close multiples
A4: Diluted shares FY2026 (m) | B4: 85.504 | D4: FY | E4: P/B | F4: P/E
A5: NTA at 30-Jun-2026 ($m) | B5: 540.2326 | D5: FY2015 | E5: 1.46 | F5: 9.7
A6: FY2026 NPAT ($m) | B6: 65.643 | D6: FY2016 | E6: 1.19 | F6: 8.4
A7: FY2026 diluted EPS | B7: 0.768 | D7: FY2017 | E7: 1.18 | F7: 8.5
A8: Dividend payout ratio | B8: 0.5 | D8: FY2018 | E8: 1.38 | F8: 11.4
A9: Annual share growth | B9: 0.01 | D9: FY2019 | E9: 1.37 | F9: 10.5
A10: Cost of equity | B10: 0.12 | D10: FY2020 | E10: 1.09 | F10: 20
A11: Hurdle rate | B11: 0.15 | D11: FY2021 | E11: 1.35 | F11: 16.3
A12: Weight bear | B12: 0.25 | D12: FY2022 | E12: 0.82 | F12: 9.1
A13: Weight base | B13: 0.5 | D13: FY2023 | E13: 0.97 | F13: 13.1
A14: Weight bull | B14: 0.25 | D14: FY2024 | E14: 0.89 | F14: 10.1
D15: FY2025 | E15: 1.26 | F15: 12.7
D16: FY2026 | E16: 1.1 | F16: 9

Sheet Base
A1: Base scenario
A2: Exit P/B | B2: 1.1
A3: Exit P/E | B3: 10
A4: Cost of equity | B4: =Inputs!B10
A5: Hurdle rate | B5: =Inputs!B11
A7: Line | B7: FY2026 | C7: FY2027 | D7: FY2028 | E7: FY2029 | F7: FY2030 | G7: FY2031
A8: NPAT ($m) | B8: =Inputs!B6 | C8: 75.5 | D8: 72 | E8: 66 | F8: 64 | G8: 68
A9: Dividends ($m) | C9: =C8*Inputs!$B$8 | D9: =D8*Inputs!$B$8 | E9: =E8*Inputs!$B$8 | F9: =F8*Inputs!$B$8 | G9: =G8*Inputs!$B$8
A10: Shares (m) | B10: =Inputs!B4 | C10: =B10*(1+Inputs!$B$9) | D10: =C10*(1+Inputs!$B$9) | E10: =D10*(1+Inputs!$B$9) | F10: =E10*(1+Inputs!$B$9) | G10: =F10*(1+Inputs!$B$9)
A11: NTA ($m) | B11: =Inputs!B5 | C11: =B11+C8-C9 | D11: =C11+D8-D9 | E11: =D11+E8-E9 | F11: =E11+F8-F9 | G11: =F11+G8-G9
A12: NTA/share | B12: =B11/B10 | C12: =C11/C10 | D12: =D11/D10 | E12: =E11/E10 | F12: =F11/F10 | G12: =G11/G10
A13: DPS | C13: =C9/C10 | D13: =D9/D10 | E13: =E9/E10 | F13: =F9/F10 | G13: =G9/G10
A14: EPS | C14: =C8/C10 | D14: =D8/D10 | E14: =E8/E10 | F14: =F8/F10 | G14: =G8/G10
A15: Discount factor @CoE | C15: =1/(1+$B$4)^1 | D15: =1/(1+$B$4)^2 | E15: =1/(1+$B$4)^3 | F15: =1/(1+$B$4)^4 | G15: =1/(1+$B$4)^5
A16: PV DPS @CoE | C16: =C13*C15 | D16: =D13*D15 | E16: =E13*E15 | F16: =F13*F15 | G16: =G13*G15
A17: Discount factor @hurdle | C17: =1/(1+$B$5)^1 | D17: =1/(1+$B$5)^2 | E17: =1/(1+$B$5)^3 | F17: =1/(1+$B$5)^4 | G17: =1/(1+$B$5)^5
A18: PV DPS @hurdle | C18: =C13*C17 | D18: =D13*D17 | E18: =E13*E17 | F18: =F13*F17 | G18: =G13*G17
A20: Sum PV dividends/share @CoE | B20: =SUM(C16:G16)
A21: NTA exit value/share (Y5 NTA/share x P/B) | B21: =G12*B2
A22: Earnings exit value/share (Y5 NPAT x P/E / shares) | B22: =G8*B3/G10
A23: NTA leg IV | B23: =B21*G15+B20
A24: Earnings leg IV | B24: =B22*G15+B20
A25: Blended intrinsic value (50/50) | B25: =0.5*B23+0.5*B24
A26: Upside vs price | B26: =B25/Inputs!B3-1
A27: Sum PV dividends/share @hurdle | B27: =SUM(C18:G18)
A28: Entry price @hurdle (blended) | B28: =(0.5*B21+0.5*B22)*G17+B27
A29: Entry discount vs price | B29: =B28/Inputs!B3-1

Sheet Bull
A1: Bull scenario
A2: Exit P/B | B2: 1.3
A3: Exit P/E | B3: 11.5
A4: Cost of equity | B4: =Inputs!B10
A5: Hurdle rate | B5: =Inputs!B11
A7: Line | B7: FY2026 | C7: FY2027 | D7: FY2028 | E7: FY2029 | F7: FY2030 | G7: FY2031
A8: NPAT ($m) | B8: =Inputs!B6 | C8: 78 | D8: 82 | E8: 86 | F8: 90 | G8: 94
A9: Dividends ($m) | C9: =C8*Inputs!$B$8 | D9: =D8*Inputs!$B$8 | E9: =E8*Inputs!$B$8 | F9: =F8*Inputs!$B$8 | G9: =G8*Inputs!$B$8
A10: Shares (m) | B10: =Inputs!B4 | C10: =B10*(1+Inputs!$B$9) | D10: =C10*(1+Inputs!$B$9) | E10: =D10*(1+Inputs!$B$9) | F10: =E10*(1+Inputs!$B$9) | G10: =F10*(1+Inputs!$B$9)
A11: NTA ($m) | B11: =Inputs!B5 | C11: =B11+C8-C9 | D11: =C11+D8-D9 | E11: =D11+E8-E9 | F11: =E11+F8-F9 | G11: =F11+G8-G9
A12: NTA/share | B12: =B11/B10 | C12: =C11/C10 | D12: =D11/D10 | E12: =E11/E10 | F12: =F11/F10 | G12: =G11/G10
A13: DPS | C13: =C9/C10 | D13: =D9/D10 | E13: =E9/E10 | F13: =F9/F10 | G13: =G9/G10
A14: EPS | C14: =C8/C10 | D14: =D8/D10 | E14: =E8/E10 | F14: =F8/F10 | G14: =G8/G10
A15: Discount factor @CoE | C15: =1/(1+$B$4)^1 | D15: =1/(1+$B$4)^2 | E15: =1/(1+$B$4)^3 | F15: =1/(1+$B$4)^4 | G15: =1/(1+$B$4)^5
A16: PV DPS @CoE | C16: =C13*C15 | D16: =D13*D15 | E16: =E13*E15 | F16: =F13*F15 | G16: =G13*G15
A17: Discount factor @hurdle | C17: =1/(1+$B$5)^1 | D17: =1/(1+$B$5)^2 | E17: =1/(1+$B$5)^3 | F17: =1/(1+$B$5)^4 | G17: =1/(1+$B$5)^5
A18: PV DPS @hurdle | C18: =C13*C17 | D18: =D13*D17 | E18: =E13*E17 | F18: =F13*F17 | G18: =G13*G17
A20: Sum PV dividends/share @CoE | B20: =SUM(C16:G16)
A21: NTA exit value/share (Y5 NTA/share x P/B) | B21: =G12*B2
A22: Earnings exit value/share (Y5 NPAT x P/E / shares) | B22: =G8*B3/G10
A23: NTA leg IV | B23: =B21*G15+B20
A24: Earnings leg IV | B24: =B22*G15+B20
A25: Blended intrinsic value (50/50) | B25: =0.5*B23+0.5*B24
A26: Upside vs price | B26: =B25/Inputs!B3-1
A27: Sum PV dividends/share @hurdle | B27: =SUM(C18:G18)
A28: Entry price @hurdle (blended) | B28: =(0.5*B21+0.5*B22)*G17+B27
A29: Entry discount vs price | B29: =B28/Inputs!B3-1

Sheet Bear
A1: Bear scenario
A2: Exit P/B | B2: 0.85
A3: Exit P/E | B3: 8
A4: Cost of equity | B4: =Inputs!B10
A5: Hurdle rate | B5: =Inputs!B11
A7: Line | B7: FY2026 | C7: FY2027 | D7: FY2028 | E7: FY2029 | F7: FY2030 | G7: FY2031
A8: NPAT ($m) | B8: =Inputs!B6 | C8: 60 | D8: 42 | E8: 35 | F8: 40 | G8: 46
A9: Dividends ($m) | C9: =C8*Inputs!$B$8 | D9: =D8*Inputs!$B$8 | E9: =E8*Inputs!$B$8 | F9: =F8*Inputs!$B$8 | G9: =G8*Inputs!$B$8
A10: Shares (m) | B10: =Inputs!B4 | C10: =B10*(1+Inputs!$B$9) | D10: =C10*(1+Inputs!$B$9) | E10: =D10*(1+Inputs!$B$9) | F10: =E10*(1+Inputs!$B$9) | G10: =F10*(1+Inputs!$B$9)
A11: NTA ($m) | B11: =Inputs!B5 | C11: =B11+C8-C9 | D11: =C11+D8-D9 | E11: =D11+E8-E9 | F11: =E11+F8-F9 | G11: =F11+G8-G9
A12: NTA/share | B12: =B11/B10 | C12: =C11/C10 | D12: =D11/D10 | E12: =E11/E10 | F12: =F11/F10 | G12: =G11/G10
A13: DPS | C13: =C9/C10 | D13: =D9/D10 | E13: =E9/E10 | F13: =F9/F10 | G13: =G9/G10
A14: EPS | C14: =C8/C10 | D14: =D8/D10 | E14: =E8/E10 | F14: =F8/F10 | G14: =G8/G10
A15: Discount factor @CoE | C15: =1/(1+$B$4)^1 | D15: =1/(1+$B$4)^2 | E15: =1/(1+$B$4)^3 | F15: =1/(1+$B$4)^4 | G15: =1/(1+$B$4)^5
A16: PV DPS @CoE | C16: =C13*C15 | D16: =D13*D15 | E16: =E13*E15 | F16: =F13*F15 | G16: =G13*G15
A17: Discount factor @hurdle | C17: =1/(1+$B$5)^1 | D17: =1/(1+$B$5)^2 | E17: =1/(1+$B$5)^3 | F17: =1/(1+$B$5)^4 | G17: =1/(1+$B$5)^5
A18: PV DPS @hurdle | C18: =C13*C17 | D18: =D13*D17 | E18: =E13*E17 | F18: =F13*F17 | G18: =G13*G17
A20: Sum PV dividends/share @CoE | B20: =SUM(C16:G16)
A21: NTA exit value/share (Y5 NTA/share x P/B) | B21: =G12*B2
A22: Earnings exit value/share (Y5 NPAT x P/E / shares) | B22: =G8*B3/G10
A23: NTA leg IV | B23: =B21*G15+B20
A24: Earnings leg IV | B24: =B22*G15+B20
A25: Blended intrinsic value (50/50) | B25: =0.5*B23+0.5*B24
A26: Upside vs price | B26: =B25/Inputs!B3-1
A27: Sum PV dividends/share @hurdle | B27: =SUM(C18:G18)
A28: Entry price @hurdle (blended) | B28: =(0.5*B21+0.5*B22)*G17+B27
A29: Entry discount vs price | B29: =B28/Inputs!B3-1

Sheet Summary
A1: Probability-weighted summary
A3: Scenario | B3: Weight | C3: Intrinsic value | D3: Entry price @hurdle
A4: bear | B4: =Inputs!B12 | C4: =Bear!B25 | D4: =Bear!B28
A5: base | B5: =Inputs!B13 | C5: =Base!B25 | D5: =Base!B28
A6: bull | B6: =Inputs!B14 | C6: =Bull!B25 | D6: =Bull!B28
A8: Weighted IV | B8: =SUMPRODUCT(B4:B6,C4:C6)
A9: Weighted entry price | B9: =SUMPRODUCT(B4:B6,D4:D6)
A10: Current price | B10: =Inputs!B3
A11: Weighted upside | B11: =B8/B10-1
A12: Implied P/E on FY2026 diluted EPS | B12: =B8/Inputs!B7
A13: Implied P/B on FY2026 NTA/share | B13: =B8/(Inputs!B5/85.076)
