Workbook

Sheet Summary
B2: Adyen N.V. — DCF Valuation
B3: ADYEN.AS (Euronext Amsterdam) / ADYEY (OTC ADR, 100 ADRs = 1 ordinary share)
B4: Built July 18, 2026 · All figures €m unless noted · FY2025 actuals per Adyen H2 2025 release
B6: COMPANY SNAPSHOT (FY2025)
B7: Net revenue | C7: =Historicals!J6 -> 2364.2 | D7: +18% YoY reported, +21% constant currency
B8: EBITDA | C8: =Historicals!J7 -> 1245.7 | D8: 53% margin (H2 exit rate: 55%)
B9: Net income | C9: =Historicals!J9 -> 1062.5 | D9: +15% YoY
B10: Free cash flow (87% EBITDA conversion) | C10: =Historicals!J10 -> 1081.3 | D10: CapEx held at 5% of net revenue
B11: Processed volume (€bn) | C11: 1394.3 | D11: +21% ex-eBay, +8% incl.
B13: VALUATION OUTPUT (per ADR, USD)
B14: Scenario | C14: Value / ADR | D14: Current ADR | E14: Upside
B15: Bear | C15: =DCF!C16 -> 8.6591924 | D15: =Assumptions!$C$15 -> 9.450056 | E15: =(C15-D15)/D15 -> -0.083688772
B16: Base | C16: =DCF!D16 -> 13.830942 | D16: =Assumptions!$C$15 -> 9.450056 | E16: =(C16-D16)/D16 -> 0.46358311
B17: Bull | C17: =DCF!E16 -> 19.78874 | D17: =Assumptions!$C$15 -> 9.450056 | E17: =(C17-D17)/D17 -> 1.0940341
B19: Probability-weighted value / ADR | C19: =SUMPRODUCT(C15:C17,Assumptions!D28:D30) -> 14.027454
B20: Implied upside (weighted) | C20: =(C19-Assumptions!C15)/Assumptions!C15 -> 0.48437789
B22: WHY THE STOCK IS DOWN ~72% FROM 2021 HIGHS / ~42% YTD 2026
B23: • Feb 2026: FY25 results — Q4 net revenue ~2% below consensus (USD FX drag); 2026 guide of 20–22% cc vs ~23% expected; stock fell ~17–20%.
B24: • 2026 EBITDA margin guided flat vs 2025 (investment year); >55% margin pushed to 2028.
B25: • May 2026: CFO departure announced (surprise to market); Q1 take rate softer per JPM.
B26: • Jun 2026: analyst downgrades on European enterprise pricing pressure.
B27: • Sector-wide payments derating: stablecoin / agentic-commerce disruption fears.
B28: • Apr 2026: Talon.One acquisition (~€750m / $876m) and Orb — first acquisitions in company history.
B29: • Leadership: co-founder/Co-CEO van der Does stepped back (health); CFO exit effective Aug 31, 2026.
B30: •
B31: • SEGMENT MIX FY2025: Digital ~56% of net rev (+9% rep.) · Unified Commerce ~32% (+30%) · Platforms ~12%.
B32: • Growth is being carried by Unified Commerce/POS while core Digital decelerates — central to the bear case.

Sheet Assumptions
B2: Assumptions & Inputs
B3: Yellow cells = key inputs to flex. Blue font = hardcoded.
B5: SHARED INPUTS
B6: Net cash (own): cash − merchant payables − debt | C6: =Historicals!J16 -> 4173.2 | D6: Derived: €10,797.4m − €6,371.8m − €252.4m = €4,173.2m (FY2025 balance sheet per user CSV)
B7: Ordinary shares outstanding (m) | C7: 31.55 | D7: Per MSN/Morningstar, mid-2026
B8: ADRs per ordinary share | C8: 100 | D8: ADYEY ratio 100:1
B9: EUR/USD | C9: 1.16 | D9: Spot estimate Jul 2026 — update
B10: Current price, ordinary (€) | C10: 814.66 | D10: ADYEN.AS approx mid-Jul 2026 — update
B11: D&A (% of net revenue) | C11: 0.04 | D11: Historical ~4%
B12: CapEx (% of net revenue) | C12: 0.05 | D12: Company guidance: up to 5%
B13: Change in WC (% of Δ net revenue) | C13: 0.005 | D13: Minimal; asset-light
B14: Tax rate | C14: 0.258 | D14: Dutch statutory 25.8%
B15: Current price / ADR (USD, derived) | C15: =C10*C9/C8 -> 9.450056
B16: Market cap (€m, derived) | C16: =C10*C7 -> 25702.523
B18: SCENARIO DRIVERS
B19: Driver | C19: Bear | D19: Base | E19: Bull
B20: 2026 net revenue growth (reported €) | C20: 0.15 | D20: 0.19 | E20: 0.21 | F20: Guide 20–22% cc; reported nets off USD drag
B21: 2035 net revenue growth (fade to, linear) | C21: 0.05 | D21: 0.09 | E21: 0.12 | F21: Terminal-year growth
B22: 2026 EBITDA margin | C22: 0.53 | D22: 0.53 | E22: 0.54 | F22: Guided broadly in line with FY25 (53%)
B23: Terminal EBITDA margin (reached 2030) | C23: 0.54 | D23: 0.57 | E23: 0.6 | F23: Company targets >55% by 2028
B24: WACC (effectively cost of equity; no debt) | C24: 0.105 | D24: 0.095 | E24: 0.09 | F24: EUR rf ~2.7% + β~1.3 × ERP ~5%
B25: Terminal growth g | C25: 0.025 | D25: 0.03 | E25: 0.035 | F25: ≤ long-run nominal EU GDP
B27: SCENARIO WEIGHTS
B28: Bear | D28: 0.25
B29: Base | D29: 0.5
B30: Bull | D30: 0.25
B31: Check: weights sum | D31: =SUM(D28:D30) -> 1

Sheet Historicals
B2: Historical Financials FY2018-FY2025 (€m)
C4: FY2018 | D4: FY2019 | E4: FY2020 | F4: FY2021 | G4: FY2022 | H4: FY2023 | I4: FY2024 | J4: FY2025 | K4: Source / note
B5: Processed volume (€bn) | C5: 159 | D5: 239.6 | E5: 303.6 | F5: 516 | G5: 767.5 | H5: 970.1 | I5: 1285.9 | J5: 1394.3 | K5: User CSV; FY25 per press release
B6: Net revenue | C6: 348.9 | D6: 496.7 | E6: 684.2 | F6: 1001.5 | G6: 1330.2 | H6: 1626.1 | I6: 1996.1 | J6: 2364.2 | K6: FY25 per H2 2025 press release (12 Feb 2026)
B7: EBITDA | C7: 181.9 | D7: 279.3 | E7: 402.5 | F7: 629.9 | G7: 728.3 | H7: 743 | I7: 992.3 | J7: 1245.7 | K7: FY25 +26% YoY
B8: EBITDA margin | C8: =C7/C6 -> 0.52135282 | D8: =D7/D6 -> 0.56231125 | E8: =E7/E6 -> 0.58827828 | F8: =F7/F6 -> 0.62895657 | G8: =G7/G6 -> 0.54751165 | H8: =H7/H6 -> 0.45692147 | I8: =I7/I6 -> 0.49711938 | J8: =J7/J6 -> 0.52690128 | K8: formula
B9: Net income | C9: 131.1 | D9: 204 | E9: 261 | F9: 469.7 | G9: 564.1 | H9: 698.3 | I9: 925.2 | J9: 1062.5 | K9: FY25 = H1 €481.0m + H2 €581.6m
B10: Free cash flow | C10: 168.1 | D10: 259.3 | E10: 346.3 | F10: 544.6 | G10: 607.1 | H10: 639.5 | I10: 859.8 | J10: 1081.3 | K10: Actuals per CSV; FY25 conversion 86.8%
B11: Net revenue growth YoY | D11: =D6/C6-1 -> 0.42361708 | E11: =E6/D6-1 -> 0.37749144 | F11: =F6/E6-1 -> 0.46375329 | G11: =G6/F6-1 -> 0.32820769 | H11: =H6/G6-1 -> 0.22244775 | I11: =I6/H6-1 -> 0.22753828 | J11: =J6/I6-1 -> 0.1844096 | K11: formula
B12: Take rate (bps) | C12: =C6/(C5*1000)*10000 -> 21.943396 | D12: =D6/(D5*1000)*10000 -> 20.730384 | E12: =E6/(E5*1000)*10000 -> 22.536232 | F12: =F6/(F5*1000)*10000 -> 19.408915 | G12: =G6/(G5*1000)*10000 -> 17.331596 | H12: =H6/(H5*1000)*10000 -> 16.762189 | I12: =I6/(I5*1000)*10000 -> 15.52298 | J12: =J6/(J5*1000)*10000 -> 16.956179 | K12: 21.9bps (2018) -> 15.5 (2024) -> 17.0 (2025): compression then mix-driven recovery
B13: Cash & equivalents | C13: 1231.9 | D13: 1745.4 | E13: 2737.5 | F13: 4616.1 | G13: 6522.3 | H13: 8307 | I13: 9965 | J13: 10797.4 | K13: Includes merchant settlement float
B14: Payables to merchants | C14: 1186.9 | D14: 1521.4 | E14: 2588.9 | F14: 3608.5 | G14: 4795.8 | H14: 5953.6 | I14: 6684.7 | J14: 6371.8 | K14: Pass-through liability
B15: Total debt | C15: 0 | D15: 50.9 | E15: 131.5 | F15: 143 | G15: 203.1 | H15: 223.1 | I15: 228.3 | J15: 252.4 | K15: Mostly lease liabilities
B16: Own net cash (cash - merchant payables - debt) | C16: =C13-C14-C15 -> 45 | D16: =D13-D14-D15 -> 173.1 | E16: =E13-E14-E15 -> 17.1 | F16: =F13-F14-F15 -> 864.6 | G16: =G13-G14-G15 -> 1523.4 | H16: =H13-H14-H15 -> 2130.3 | I16: =I13-I14-I15 -> 3052 | J16: =J13-J14-J15 -> 4173.2 | K16: Feeds the DCF bridge (Assumptions!C6)
B17: Shareholders' equity | C17: 582.4 | D17: 868.3 | E17: 1218.1 | F17: 1810.4 | G17: 2412.1 | H17: 3159.6 | I17: 4231.5 | J17: 5285.4 | K17: User CSV
B18: FTEs | C18: 873 | D18: 1182 | E18: 1747 | F18: 2180 | G18: 3332 | H18: 4196 | I18: 4345 | J18: 4771 | K18: Headcount discipline post-2023
B20: Data: user-provided ADYEY_Metrics.csv (semi-annual series 2018-2025); FY2025 row reconciles exactly to Adyen's official release.

Sheet Forecast
B2: FCFF Forecast 2026–2035 (€m)
B4: Period | C4: 1 | D4: 2 | E4: 3 | F4: 4 | G4: 5 | H4: 6 | I4: 7 | J4: 8 | K4: 9 | L4: 10
C5: 2026 | D5: 2027 | E5: 2028 | F5: 2029 | G5: 2030 | H5: 2031 | I5: 2032 | J5: 2033 | K5: 2034 | L5: 2035
B6: BEAR CASE
B7: Net revenue growth | C7: =Assumptions!$C$20+(Assumptions!$C$21-Assumptions!$C$20)*(C$4-1)/9 -> 0.15 | D7: =Assumptions!$C$20+(Assumptions!$C$21-Assumptions!$C$20)*(D$4-1)/9 -> 0.13888889 | E7: =Assumptions!$C$20+(Assumptions!$C$21-Assumptions!$C$20)*(E$4-1)/9 -> 0.12777778 | F7: =Assumptions!$C$20+(Assumptions!$C$21-Assumptions!$C$20)*(F$4-1)/9 -> 0.11666667 | G7: =Assumptions!$C$20+(Assumptions!$C$21-Assumptions!$C$20)*(G$4-1)/9 -> 0.10555556 | H7: =Assumptions!$C$20+(Assumptions!$C$21-Assumptions!$C$20)*(H$4-1)/9 -> 0.094444444 | I7: =Assumptions!$C$20+(Assumptions!$C$21-Assumptions!$C$20)*(I$4-1)/9 -> 0.083333333 | J7: =Assumptions!$C$20+(Assumptions!$C$21-Assumptions!$C$20)*(J$4-1)/9 -> 0.072222222 | ... L7: =Assumptions!$C$20+(Assumptions!$C$21-Assumptions!$C$20)*(L$4-1)/9 -> 0.05
B8: Net revenue | C8: =Historicals!$J$6*(1+C7) -> 2718.83 | D8: =C8*(1+D7) -> 3096.4453 | E8: =D8*(1+E7) -> 3492.1022 | F8: =E8*(1+F7) -> 3899.5141 | G8: =F8*(1+G7) -> 4311.1295 | H8: =G8*(1+H7) -> 4718.2917 | I8: =H8*(1+I7) -> 5111.4827 | J8: =I8*(1+J7) -> 5480.6453 | K8: =J8*(1+K7) -> 5815.5736 | L8: =K8*(1+L7) -> 6106.3523
B9: EBITDA margin | C9: =Assumptions!$C$22+(Assumptions!$C$23-Assumptions!$C$22)*MIN((C$4-1)/4,1) -> 0.53 | D9: =Assumptions!$C$22+(Assumptions!$C$23-Assumptions!$C$22)*MIN((D$4-1)/4,1) -> 0.5325 | E9: =Assumptions!$C$22+(Assumptions!$C$23-Assumptions!$C$22)*MIN((E$4-1)/4,1) -> 0.535 | F9: =Assumptions!$C$22+(Assumptions!$C$23-Assumptions!$C$22)*MIN((F$4-1)/4,1) -> 0.5375 | G9: =Assumptions!$C$22+(Assumptions!$C$23-Assumptions!$C$22)*MIN((G$4-1)/4,1) -> 0.54 | H9: =Assumptions!$C$22+(Assumptions!$C$23-Assumptions!$C$22)*MIN((H$4-1)/4,1) -> 0.54 | I9: =Assumptions!$C$22+(Assumptions!$C$23-Assumptions!$C$22)*MIN((I$4-1)/4,1) -> 0.54 | J9: =Assumptions!$C$22+(Assumptions!$C$23-Assumptions!$C$22)*MIN((J$4-1)/4,1) -> 0.54 | ... L9: =Assumptions!$C$22+(Assumptions!$C$23-Assumptions!$C$22)*MIN((L$4-1)/4,1) -> 0.54
B10: EBITDA | C10: =C8*C9 -> 1440.9799 | D10: =D8*D9 -> 1648.8571 | E10: =E8*E9 -> 1868.2747 | F10: =F8*F9 -> 2095.9888 | G10: =G8*G9 -> 2328.0099 | H10: =H8*H9 -> 2547.8775 | I10: =I8*I9 -> 2760.2006 | J10: =J8*J9 -> 2959.5485 | ... L10: =L8*L9 -> 3297.4303
B11: D&A | C11: =-C8*Assumptions!$C$11 -> -108.7532 | D11: =-D8*Assumptions!$C$11 -> -123.85781 | E11: =-E8*Assumptions!$C$11 -> -139.68409 | F11: =-F8*Assumptions!$C$11 -> -155.98056 | G11: =-G8*Assumptions!$C$11 -> -172.44518 | H11: =-H8*Assumptions!$C$11 -> -188.73167 | I11: =-I8*Assumptions!$C$11 -> -204.45931 | J11: =-J8*Assumptions!$C$11 -> -219.22581 | ... L11: =-L8*Assumptions!$C$11 -> -244.25409
B12: EBIT | C12: =C10+C11 -> 1332.2267 | D12: =D10+D11 -> 1524.9993 | E12: =E10+E11 -> 1728.5906 | F12: =F10+F11 -> 1940.0083 | G12: =G10+G11 -> 2155.5647 | H12: =H10+H11 -> 2359.1458 | I12: =I10+I11 -> 2555.7413 | J12: =J10+J11 -> 2740.3227 | ... L12: =L10+L11 -> 3053.1762
B13: Tax on EBIT | C13: =-C12*Assumptions!$C$14 -> -343.71449 | D13: =-D12*Assumptions!$C$14 -> -393.44982 | E13: =-E12*Assumptions!$C$14 -> -445.97637 | F13: =-F12*Assumptions!$C$14 -> -500.52213 | G13: =-G12*Assumptions!$C$14 -> -556.1357 | H13: =-H12*Assumptions!$C$14 -> -608.65963 | I13: =-I12*Assumptions!$C$14 -> -659.38126 | J13: =-J12*Assumptions!$C$14 -> -707.00325 | ... L13: =-L12*Assumptions!$C$14 -> -787.71945
B14: NOPAT | C14: =C12+C13 -> 988.51221 | D14: =D12+D13 -> 1131.5495 | E14: =E12+E13 -> 1282.6142 | F14: =F12+F13 -> 1439.4861 | G14: =G12+G13 -> 1599.429 | H14: =H12+H13 -> 1750.4862 | I14: =I12+I13 -> 1896.3601 | J14: =J12+J13 -> 2033.3194 | ... L14: =L12+L13 -> 2265.4567
B15: CapEx | C15: =-C8*Assumptions!$C$12 -> -135.9415 | D15: =-D8*Assumptions!$C$12 -> -154.82226 | E15: =-E8*Assumptions!$C$12 -> -174.60511 | F15: =-F8*Assumptions!$C$12 -> -194.9757 | G15: =-G8*Assumptions!$C$12 -> -215.55647 | H15: =-H8*Assumptions!$C$12 -> -235.91458 | I15: =-I8*Assumptions!$C$12 -> -255.57413 | J15: =-J8*Assumptions!$C$12 -> -274.03227 | ... L15: =-L8*Assumptions!$C$12 -> -305.31762
B16: Δ Working capital | C16: =-(C8-Historicals!$J$6)*Assumptions!$C$13 -> -1.77315 | D16: =-(D8-C8)*Assumptions!$C$13 -> -1.8880764 | E16: =-(E8-D8)*Assumptions!$C$13 -> -1.9782845 | F16: =-(F8-E8)*Assumptions!$C$13 -> -2.0370596 | G16: =-(G8-F8)*Assumptions!$C$13 -> -2.0580769 | H16: =-(H8-G8)*Assumptions!$C$13 -> -2.0358111 | I16: =-(I8-H8)*Assumptions!$C$13 -> -1.9659549 | J16: =-(J8-I8)*Assumptions!$C$13 -> -1.8458132 | K16: =-(K8-J8)*Assumptions!$C$13 -> -1.6746416 | L16: =-(L8-K8)*Assumptions!$C$13 -> -1.4538934
B17: FCFF | C17: =C14-C11+C15+C16 -> 959.55076 | D17: =D14-D11+D15+D16 -> 1098.697 | E17: =E14-E11+E15+E16 -> 1245.7149 | F17: =F14-F11+F15+F16 -> 1398.4539 | G17: =G14-G11+G15+G16 -> 1554.2597 | H17: =H14-H11+H15+H16 -> 1701.2675 | I17: =I14-I11+I15+I16 -> 1843.2793 | J17: =J14-J11+J15+J16 -> 1976.6671 | ... L17: =L14-L11+L15+L16 -> 2202.9393
B19: BASE CASE
B20: Net revenue growth | C20: =Assumptions!$D$20+(Assumptions!$D$21-Assumptions!$D$20)*(C$4-1)/9 -> 0.19 | D20: =Assumptions!$D$20+(Assumptions!$D$21-Assumptions!$D$20)*(D$4-1)/9 -> 0.17888889 | E20: =Assumptions!$D$20+(Assumptions!$D$21-Assumptions!$D$20)*(E$4-1)/9 -> 0.16777778 | F20: =Assumptions!$D$20+(Assumptions!$D$21-Assumptions!$D$20)*(F$4-1)/9 -> 0.15666667 | G20: =Assumptions!$D$20+(Assumptions!$D$21-Assumptions!$D$20)*(G$4-1)/9 -> 0.14555556 | H20: =Assumptions!$D$20+(Assumptions!$D$21-Assumptions!$D$20)*(H$4-1)/9 -> 0.13444444 | I20: =Assumptions!$D$20+(Assumptions!$D$21-Assumptions!$D$20)*(I$4-1)/9 -> 0.12333333 | J20: =Assumptions!$D$20+(Assumptions!$D$21-Assumptions!$D$20)*(J$4-1)/9 -> 0.11222222 | ... L20: =Assumptions!$D$20+(Assumptions!$D$21-Assumptions!$D$20)*(L$4-1)/9 -> 0.09
B21: Net revenue | C21: =Historicals!$J$6*(1+C20) -> 2813.398 | D21: =C21*(1+D20) -> 3316.6836 | E21: =D21*(1+E20) -> 3873.1495 | F21: =E21*(1+F20) -> 4479.9429 | G21: =F21*(1+G20) -> 5132.0234 | H21: =G21*(1+H20) -> 5821.9955 | I21: =H21*(1+I20) -> 6540.0416 | J21: =I21*(1+J20) -> 7273.9796 | K21: =J21*(1+K20) -> 8009.4597 | L21: =K21*(1+L20) -> 8730.3111
B22: EBITDA margin | C22: =Assumptions!$D$22+(Assumptions!$D$23-Assumptions!$D$22)*MIN((C$4-1)/4,1) -> 0.53 | D22: =Assumptions!$D$22+(Assumptions!$D$23-Assumptions!$D$22)*MIN((D$4-1)/4,1) -> 0.54 | E22: =Assumptions!$D$22+(Assumptions!$D$23-Assumptions!$D$22)*MIN((E$4-1)/4,1) -> 0.55 | F22: =Assumptions!$D$22+(Assumptions!$D$23-Assumptions!$D$22)*MIN((F$4-1)/4,1) -> 0.56 | G22: =Assumptions!$D$22+(Assumptions!$D$23-Assumptions!$D$22)*MIN((G$4-1)/4,1) -> 0.57 | H22: =Assumptions!$D$22+(Assumptions!$D$23-Assumptions!$D$22)*MIN((H$4-1)/4,1) -> 0.57 | I22: =Assumptions!$D$22+(Assumptions!$D$23-Assumptions!$D$22)*MIN((I$4-1)/4,1) -> 0.57 | J22: =Assumptions!$D$22+(Assumptions!$D$23-Assumptions!$D$22)*MIN((J$4-1)/4,1) -> 0.57 | ... L22: =Assumptions!$D$22+(Assumptions!$D$23-Assumptions!$D$22)*MIN((L$4-1)/4,1) -> 0.57
B23: EBITDA | C23: =C21*C22 -> 1491.1009 | D23: =D21*D22 -> 1791.0092 | E23: =E21*E22 -> 2130.2322 | F23: =F21*F22 -> 2508.768 | G23: =G21*G22 -> 2925.2534 | H23: =H21*H22 -> 3318.5374 | I23: =I21*I22 -> 3727.8237 | J23: =J21*J22 -> 4146.1684 | ... L23: =L21*L22 -> 4976.2773
B24: D&A | C24: =-C21*Assumptions!$C$11 -> -112.53592 | D24: =-D21*Assumptions!$C$11 -> -132.66735 | E24: =-E21*Assumptions!$C$11 -> -154.92598 | F24: =-F21*Assumptions!$C$11 -> -179.19771 | G24: =-G21*Assumptions!$C$11 -> -205.28094 | H24: =-H21*Assumptions!$C$11 -> -232.87982 | I24: =-I21*Assumptions!$C$11 -> -261.60166 | J24: =-J21*Assumptions!$C$11 -> -290.95918 | ... L24: =-L21*Assumptions!$C$11 -> -349.21245
B25: EBIT | C25: =C23+C24 -> 1378.565 | D25: =D23+D24 -> 1658.3418 | E25: =E23+E24 -> 1975.3062 | F25: =F23+F24 -> 2329.5703 | G25: =G23+G24 -> 2719.9724 | H25: =H23+H24 -> 3085.6576 | I25: =I23+I24 -> 3466.222 | J25: =J23+J24 -> 3855.2092 | ... L25: =L23+L24 -> 4627.0649
B26: Tax on EBIT | C26: =-C25*Assumptions!$C$14 -> -355.66978 | D26: =-D25*Assumptions!$C$14 -> -427.85219 | E26: =-E25*Assumptions!$C$14 -> -509.62901 | F26: =-F25*Assumptions!$C$14 -> -601.02914 | G26: =-G25*Assumptions!$C$14 -> -701.75289 | H26: =-H25*Assumptions!$C$14 -> -796.09966 | I26: =-I25*Assumptions!$C$14 -> -894.28529 | J26: =-J25*Assumptions!$C$14 -> -994.64397 | ... L26: =-L25*Assumptions!$C$14 -> -1193.7827
B27: NOPAT | C27: =C25+C26 -> 1022.8952 | D27: =D25+D26 -> 1230.4896 | E27: =E25+E26 -> 1465.6772 | F27: =F25+F26 -> 1728.5412 | G27: =G25+G26 -> 2018.2195 | H27: =H25+H26 -> 2289.5579 | I27: =I25+I26 -> 2571.9368 | J27: =J25+J26 -> 2860.5652 | ... L27: =L25+L26 -> 3433.2822
B28: CapEx | C28: =-C21*Assumptions!$C$12 -> -140.6699 | D28: =-D21*Assumptions!$C$12 -> -165.83418 | E28: =-E21*Assumptions!$C$12 -> -193.65747 | F28: =-F21*Assumptions!$C$12 -> -223.99714 | G28: =-G21*Assumptions!$C$12 -> -256.60117 | H28: =-H21*Assumptions!$C$12 -> -291.09977 | I28: =-I21*Assumptions!$C$12 -> -327.00208 | J28: =-J21*Assumptions!$C$12 -> -363.69898 | ... L28: =-L21*Assumptions!$C$12 -> -436.51556
B29: Δ Working capital | C29: =-(C21-Historicals!$J$6)*Assumptions!$C$13 -> -2.24599 | D29: =-(D21-C21)*Assumptions!$C$13 -> -2.5164282 | E29: =-(E21-D21)*Assumptions!$C$13 -> -2.7823291 | F29: =-(F21-E21)*Assumptions!$C$13 -> -3.0339671 | G29: =-(G21-F21)*Assumptions!$C$13 -> -3.2604029 | H29: =-(H21-G21)*Assumptions!$C$13 -> -3.4498602 | I29: =-(I21-H21)*Assumptions!$C$13 -> -3.5902305 | J29: =-(J21-I21)*Assumptions!$C$13 -> -3.66969 | K29: =-(K21-J21)*Assumptions!$C$13 -> -3.6774008 | L29: =-(L21-K21)*Assumptions!$C$13 -> -3.6042569
B30: FCFF | C30: =C27-C24+C28+C29 -> 992.51527 | D30: =D27-D24+D28+D29 -> 1194.8064 | E30: =E27-E24+E28+E29 -> 1424.1634 | F30: =F27-F24+F28+F29 -> 1680.7078 | G30: =G27-G24+G28+G29 -> 1963.6389 | H30: =H27-H24+H28+H29 -> 2227.8881 | I30: =I27-I24+I28+I29 -> 2502.9461 | J30: =J27-J24+J28+J29 -> 2784.1557 | ... L30: =L27-L24+L28+L29 -> 3342.3748
B32: BULL CASE
B33: Net revenue growth | C33: =Assumptions!$E$20+(Assumptions!$E$21-Assumptions!$E$20)*(C$4-1)/9 -> 0.21 | D33: =Assumptions!$E$20+(Assumptions!$E$21-Assumptions!$E$20)*(D$4-1)/9 -> 0.2 | E33: =Assumptions!$E$20+(Assumptions!$E$21-Assumptions!$E$20)*(E$4-1)/9 -> 0.19 | F33: =Assumptions!$E$20+(Assumptions!$E$21-Assumptions!$E$20)*(F$4-1)/9 -> 0.18 | G33: =Assumptions!$E$20+(Assumptions!$E$21-Assumptions!$E$20)*(G$4-1)/9 -> 0.17 | H33: =Assumptions!$E$20+(Assumptions!$E$21-Assumptions!$E$20)*(H$4-1)/9 -> 0.16 | I33: =Assumptions!$E$20+(Assumptions!$E$21-Assumptions!$E$20)*(I$4-1)/9 -> 0.15 | J33: =Assumptions!$E$20+(Assumptions!$E$21-Assumptions!$E$20)*(J$4-1)/9 -> 0.14 | ... L33: =Assumptions!$E$20+(Assumptions!$E$21-Assumptions!$E$20)*(L$4-1)/9 -> 0.12
B34: Net revenue | C34: =Historicals!$J$6*(1+C33) -> 2860.682 | D34: =C34*(1+D33) -> 3432.8184 | E34: =D34*(1+E33) -> 4085.0539 | F34: =E34*(1+F33) -> 4820.3636 | G34: =F34*(1+G33) -> 5639.8254 | H34: =G34*(1+H33) -> 6542.1975 | I34: =H34*(1+I33) -> 7523.5271 | J34: =I34*(1+J33) -> 8576.8209 | K34: =J34*(1+K33) -> 9691.8076 | L34: =K34*(1+L33) -> 10854.825
B35: EBITDA margin | C35: =Assumptions!$E$22+(Assumptions!$E$23-Assumptions!$E$22)*MIN((C$4-1)/4,1) -> 0.54 | D35: =Assumptions!$E$22+(Assumptions!$E$23-Assumptions!$E$22)*MIN((D$4-1)/4,1) -> 0.555 | E35: =Assumptions!$E$22+(Assumptions!$E$23-Assumptions!$E$22)*MIN((E$4-1)/4,1) -> 0.57 | F35: =Assumptions!$E$22+(Assumptions!$E$23-Assumptions!$E$22)*MIN((F$4-1)/4,1) -> 0.585 | G35: =Assumptions!$E$22+(Assumptions!$E$23-Assumptions!$E$22)*MIN((G$4-1)/4,1) -> 0.6 | H35: =Assumptions!$E$22+(Assumptions!$E$23-Assumptions!$E$22)*MIN((H$4-1)/4,1) -> 0.6 | I35: =Assumptions!$E$22+(Assumptions!$E$23-Assumptions!$E$22)*MIN((I$4-1)/4,1) -> 0.6 | J35: =Assumptions!$E$22+(Assumptions!$E$23-Assumptions!$E$22)*MIN((J$4-1)/4,1) -> 0.6 | ... L35: =Assumptions!$E$22+(Assumptions!$E$23-Assumptions!$E$22)*MIN((L$4-1)/4,1) -> 0.6
B36: EBITDA | C36: =C34*C35 -> 1544.7683 | D36: =D34*D35 -> 1905.2142 | E36: =E34*E35 -> 2328.4807 | F36: =F34*F35 -> 2819.9127 | G36: =G34*G35 -> 3383.8952 | H36: =H34*H35 -> 3925.3185 | I36: =I34*I35 -> 4514.1163 | J36: =J34*J35 -> 5146.0925 | ... L36: =L34*L35 -> 6512.8947
B37: D&A | C37: =-C34*Assumptions!$C$11 -> -114.42728 | D37: =-D34*Assumptions!$C$11 -> -137.31274 | E37: =-E34*Assumptions!$C$11 -> -163.40216 | F37: =-F34*Assumptions!$C$11 -> -192.81454 | G37: =-G34*Assumptions!$C$11 -> -225.59302 | H37: =-H34*Assumptions!$C$11 -> -261.6879 | I37: =-I34*Assumptions!$C$11 -> -300.94108 | J37: =-J34*Assumptions!$C$11 -> -343.07284 | ... L37: =-L34*Assumptions!$C$11 -> -434.19298
B38: EBIT | C38: =C36+C37 -> 1430.341 | D38: =D36+D37 -> 1767.9015 | E38: =E36+E37 -> 2165.0786 | F38: =F36+F37 -> 2627.0982 | G38: =G36+G37 -> 3158.3022 | H38: =H36+H37 -> 3663.6306 | I38: =I36+I37 -> 4213.1752 | J38: =J36+J37 -> 4803.0197 | ... L38: =L36+L37 -> 6078.7017
B39: Tax on EBIT | C39: =-C38*Assumptions!$C$14 -> -369.02798 | D39: =-D38*Assumptions!$C$14 -> -456.11858 | E39: =-E38*Assumptions!$C$14 -> -558.59027 | F39: =-F38*Assumptions!$C$14 -> -677.79133 | G39: =-G38*Assumptions!$C$14 -> -814.84198 | H39: =-H38*Assumptions!$C$14 -> -945.21669 | I39: =-I38*Assumptions!$C$14 -> -1086.9992 | J39: =-J38*Assumptions!$C$14 -> -1239.1791 | ... L39: =-L38*Assumptions!$C$14 -> -1568.305
B40: NOPAT | C40: =C38+C39 -> 1061.313 | D40: =D38+D39 -> 1311.7829 | E40: =E38+E39 -> 1606.4883 | F40: =F38+F39 -> 1949.3068 | G40: =G38+G39 -> 2343.4603 | H40: =H38+H39 -> 2718.4139 | I40: =I38+I39 -> 3126.176 | J40: =J38+J39 -> 3563.8406 | ... L40: =L38+L39 -> 4510.3967
B41: CapEx | C41: =-C34*Assumptions!$C$12 -> -143.0341 | D41: =-D34*Assumptions!$C$12 -> -171.64092 | E41: =-E34*Assumptions!$C$12 -> -204.25269 | F41: =-F34*Assumptions!$C$12 -> -241.01818 | G41: =-G34*Assumptions!$C$12 -> -281.99127 | H41: =-H34*Assumptions!$C$12 -> -327.10987 | I41: =-I34*Assumptions!$C$12 -> -376.17635 | J41: =-J34*Assumptions!$C$12 -> -428.84104 | ... L41: =-L34*Assumptions!$C$12 -> -542.74123
B42: Δ Working capital | C42: =-(C34-Historicals!$J$6)*Assumptions!$C$13 -> -2.48241 | D42: =-(D34-C34)*Assumptions!$C$13 -> -2.860682 | E42: =-(E34-D34)*Assumptions!$C$13 -> -3.2611775 | F42: =-(F34-E34)*Assumptions!$C$13 -> -3.6765485 | G42: =-(G34-F34)*Assumptions!$C$13 -> -4.0973091 | H42: =-(H34-G34)*Assumptions!$C$13 -> -4.5118603 | I42: =-(I34-H34)*Assumptions!$C$13 -> -4.9066481 | J42: =-(J34-I34)*Assumptions!$C$13 -> -5.266469 | K42: =-(K34-J34)*Assumptions!$C$13 -> -5.5749336 | L42: =-(L34-K34)*Assumptions!$C$13 -> -5.8150846
B43: FCFF | C43: =C40-C37+C41+C42 -> 1030.2238 | D43: =D40-D37+D41+D42 -> 1274.594 | E43: =E40-E37+E41+E42 -> 1562.3766 | F43: =F40-F37+F41+F42 -> 1897.4267 | G43: =G40-G37+G41+G42 -> 2282.9647 | H43: =H40-H37+H41+H42 -> 2648.4801 | I43: =I40-I37+I41+I42 -> 3046.0341 | J43: =J40-J37+J41+J42 -> 3472.8059 | ... L43: =L40-L37+L41+L42 -> 4396.0334

Sheet DCF
B2: DCF Valuation (€m unless noted)
C4: Bear | D4: Base | E4: Bull
B5: PV of FCFF 2026–2035 | C5: =SUMPRODUCT(Forecast!$C$17:$L$17/(1+Assumptions!$C$24)^Forecast!$C$4:$L$4) -> 8978.7824 | D5: =SUMPRODUCT(Forecast!$C$30:$L$30/(1+Assumptions!$D$24)^Forecast!$C$4:$L$4) -> 12072.94 | E5: =SUMPRODUCT(Forecast!$C$43:$L$43/(1+Assumptions!$E$24)^Forecast!$C$4:$L$4) -> 14704.676
B6: Terminal value (Gordon, on 2035 FCFF) | C6: =Forecast!$L$17*(1+Assumptions!$C$25)/(Assumptions!$C$24-Assumptions!$C$25) -> 28225.16 | D6: =Forecast!$L$30*(1+Assumptions!$D$25)/(Assumptions!$D$24-Assumptions!$D$25) -> 52963.785 | E6: =Forecast!$L$43*(1+Assumptions!$E$25)/(Assumptions!$E$24-Assumptions!$E$25) -> 82725.355
B7: PV of terminal value | C7: =C6/(1+Assumptions!$C$24)^10 -> 10399.528 | D7: =D6/(1+Assumptions!$D$24)^10 -> 21371.639 | E7: =E6/(1+Assumptions!$E$24)^10 -> 34944.084
B8: Enterprise value | C8: =C5+C7 -> 19378.31 | D8: =D5+D7 -> 33444.578 | E8: =E5+E7 -> 49648.76
B9: (+) Net cash (own) | C9: =Assumptions!$C$6 -> 4173.2 | D9: =Assumptions!$C$6 -> 4173.2 | E9: =Assumptions!$C$6 -> 4173.2
B10: Equity value | C10: =C8+C9 -> 23551.51 | D10: =D8+D9 -> 37617.778 | E10: =E8+E9 -> 53821.96
B11: Value per ordinary share (€) | C11: =C10/Assumptions!$C$7 -> 746.48211 | D11: =D10/Assumptions!$C$7 -> 1192.3226 | E11: =E10/Assumptions!$C$7 -> 1705.9258
B12: Upside vs current (€ ordinary) | C12: =C11/Assumptions!$C$10-1 -> -0.083688772 | D12: =D11/Assumptions!$C$10-1 -> 0.46358311 | E12: =E11/Assumptions!$C$10-1 -> 1.0940341
B13: TV as % of EV | C13: =C7/C8 -> 0.53665814 | D13: =D7/D8 -> 0.63901654 | E13: =E7/E8 -> 0.70382591
B14: Implied EV / 2026E EBITDA | C14: =C8/Forecast!$C$10 -> 13.448009 | D14: =D8/Forecast!$C$23 -> 22.429453 | E14: =E8/Forecast!$C$36 -> 32.13994
B16: Value per ADR (USD) | C16: =C11*Assumptions!$C$9/Assumptions!$C$8 -> 8.6591924 | D16: =D11*Assumptions!$C$9/Assumptions!$C$8 -> 13.830942 | E16: =E11*Assumptions!$C$9/Assumptions!$C$8 -> 19.78874
B19: REVERSE DCF — what the market is pricing in
B20: Market cap (€m) | C20: =Assumptions!$C$10*Assumptions!$C$7 -> 25702.523
B21: Implied EV (market cap − net cash) | C21: =C20-Assumptions!$C$6 -> 21529.323
B22: Implied EV / 2026E FCFF (base rev/margin path) | C22: =C21/Forecast!$C$30 -> 21.691679
B23: Implied EV / 2026E EBITDA | C23: =C21/Forecast!$C$23 -> 14.438542
B24: Bear-case value ≈ current price ⇒ market is pricing roughly the bear path (growth fading to ~5%, no margin expansion).

Sheet Sensitivity
B2: Sensitivity — Base-case value per ADR (USD)
B3: Rows: WACC · Columns: terminal growth g. Uses base-case FCFF path from Forecast.
B5: WACC \ g | C5: 0.02 | D5: 0.025 | E5: 0.03 | F5: 0.035 | G5: 0.04
B6: 0.08 | C6: =IF($B6<=C$5,"n/m",(SUMPRODUCT(Forecast!$C$30:$L$30/(1+$B6)^Forecast!$C$4:$L$4)+Forecast!$L$30*(1+C$5)/($B6-C$5)/(1+$B6)^10+Assumptions!$C$6)/Assumptions!$C$7*Assumptions!$C$9/Assumptions!$C$8) -> 16.026105 | D6: =IF($B6<=D$5,"n/m",(SUMPRODUCT(Forecast!$C$30:$L$30/(1+$B6)^Forecast!$C$4:$L$4)+Forecast!$L$30*(1+D$5)/($B6-D$5)/(1+$B6)^10+Assumptions!$C$6)/Assumptions!$C$7*Assumptions!$C$9/Assumptions!$C$8) -> 16.957547 | E6: =IF($B6<=E$5,"n/m",(SUMPRODUCT(Forecast!$C$30:$L$30/(1+$B6)^Forecast!$C$4:$L$4)+Forecast!$L$30*(1+E$5)/($B6-E$5)/(1+$B6)^10+Assumptions!$C$6)/Assumptions!$C$7*Assumptions!$C$9/Assumptions!$C$8) -> 18.075278 | F6: =IF($B6<=F$5,"n/m",(SUMPRODUCT(Forecast!$C$30:$L$30/(1+$B6)^Forecast!$C$4:$L$4)+Forecast!$L$30*(1+F$5)/($B6-F$5)/(1+$B6)^10+Assumptions!$C$6)/Assumptions!$C$7*Assumptions!$C$9/Assumptions!$C$8) -> 19.441394 | G6: =IF($B6<=G$5,"n/m",(SUMPRODUCT(Forecast!$C$30:$L$30/(1+$B6)^Forecast!$C$4:$L$4)+Forecast!$L$30*(1+G$5)/($B6-G$5)/(1+$B6)^10+Assumptions!$C$6)/Assumptions!$C$7*Assumptions!$C$9/Assumptions!$C$8) -> 21.149038
B7: 0.085 | C7: =IF($B7<=C$5,"n/m",(SUMPRODUCT(Forecast!$C$30:$L$30/(1+$B7)^Forecast!$C$4:$L$4)+Forecast!$L$30*(1+C$5)/($B7-C$5)/(1+$B7)^10+Assumptions!$C$6)/Assumptions!$C$7*Assumptions!$C$9/Assumptions!$C$8) -> 14.748367 | D7: =IF($B7<=D$5,"n/m",(SUMPRODUCT(Forecast!$C$30:$L$30/(1+$B7)^Forecast!$C$4:$L$4)+Forecast!$L$30*(1+D$5)/($B7-D$5)/(1+$B7)^10+Assumptions!$C$6)/Assumptions!$C$7*Assumptions!$C$9/Assumptions!$C$8) -> 15.504419 | E7: =IF($B7<=E$5,"n/m",(SUMPRODUCT(Forecast!$C$30:$L$30/(1+$B7)^Forecast!$C$4:$L$4)+Forecast!$L$30*(1+E$5)/($B7-E$5)/(1+$B7)^10+Assumptions!$C$6)/Assumptions!$C$7*Assumptions!$C$9/Assumptions!$C$8) -> 16.397935 | F7: =IF($B7<=F$5,"n/m",(SUMPRODUCT(Forecast!$C$30:$L$30/(1+$B7)^Forecast!$C$4:$L$4)+Forecast!$L$30*(1+F$5)/($B7-F$5)/(1+$B7)^10+Assumptions!$C$6)/Assumptions!$C$7*Assumptions!$C$9/Assumptions!$C$8) -> 17.470154 | G7: =IF($B7<=G$5,"n/m",(SUMPRODUCT(Forecast!$C$30:$L$30/(1+$B7)^Forecast!$C$4:$L$4)+Forecast!$L$30*(1+G$5)/($B7-G$5)/(1+$B7)^10+Assumptions!$C$6)/Assumptions!$C$7*Assumptions!$C$9/Assumptions!$C$8) -> 18.780643
B8: 0.09 | C8: =IF($B8<=C$5,"n/m",(SUMPRODUCT(Forecast!$C$30:$L$30/(1+$B8)^Forecast!$C$4:$L$4)+Forecast!$L$30*(1+C$5)/($B8-C$5)/(1+$B8)^10+Assumptions!$C$6)/Assumptions!$C$7*Assumptions!$C$9/Assumptions!$C$8) -> 13.65792 | D8: =IF($B8<=D$5,"n/m",(SUMPRODUCT(Forecast!$C$30:$L$30/(1+$B8)^Forecast!$C$4:$L$4)+Forecast!$L$30*(1+D$5)/($B8-D$5)/(1+$B8)^10+Assumptions!$C$6)/Assumptions!$C$7*Assumptions!$C$9/Assumptions!$C$8) -> 14.279695 | E8: =IF($B8<=E$5,"n/m",(SUMPRODUCT(Forecast!$C$30:$L$30/(1+$B8)^Forecast!$C$4:$L$4)+Forecast!$L$30*(1+E$5)/($B8-E$5)/(1+$B8)^10+Assumptions!$C$6)/Assumptions!$C$7*Assumptions!$C$9/Assumptions!$C$8) -> 15.005101 | F8: =IF($B8<=F$5,"n/m",(SUMPRODUCT(Forecast!$C$30:$L$30/(1+$B8)^Forecast!$C$4:$L$4)+Forecast!$L$30*(1+F$5)/($B8-F$5)/(1+$B8)^10+Assumptions!$C$6)/Assumptions!$C$7*Assumptions!$C$9/Assumptions!$C$8) -> 15.862398 | G8: =IF($B8<=G$5,"n/m",(SUMPRODUCT(Forecast!$C$30:$L$30/(1+$B8)^Forecast!$C$4:$L$4)+Forecast!$L$30*(1+G$5)/($B8-G$5)/(1+$B8)^10+Assumptions!$C$6)/Assumptions!$C$7*Assumptions!$C$9/Assumptions!$C$8) -> 16.891154
B9: 0.095 | C9: =IF($B9<=C$5,"n/m",(SUMPRODUCT(Forecast!$C$30:$L$30/(1+$B9)^Forecast!$C$4:$L$4)+Forecast!$L$30*(1+C$5)/($B9-C$5)/(1+$B9)^10+Assumptions!$C$6)/Assumptions!$C$7*Assumptions!$C$9/Assumptions!$C$8) -> 12.71713 | D9: =IF($B9<=D$5,"n/m",(SUMPRODUCT(Forecast!$C$30:$L$30/(1+$B9)^Forecast!$C$4:$L$4)+Forecast!$L$30*(1+D$5)/($B9-D$5)/(1+$B9)^10+Assumptions!$C$6)/Assumptions!$C$7*Assumptions!$C$9/Assumptions!$C$8) -> 13.234257 | E9: =IF($B9<=E$5,"n/m",(SUMPRODUCT(Forecast!$C$30:$L$30/(1+$B9)^Forecast!$C$4:$L$4)+Forecast!$L$30*(1+E$5)/($B9-E$5)/(1+$B9)^10+Assumptions!$C$6)/Assumptions!$C$7*Assumptions!$C$9/Assumptions!$C$8) -> 13.830942 | F9: =IF($B9<=F$5,"n/m",(SUMPRODUCT(Forecast!$C$30:$L$30/(1+$B9)^Forecast!$C$4:$L$4)+Forecast!$L$30*(1+F$5)/($B9-F$5)/(1+$B9)^10+Assumptions!$C$6)/Assumptions!$C$7*Assumptions!$C$9/Assumptions!$C$8) -> 14.527075 | G9: =IF($B9<=G$5,"n/m",(SUMPRODUCT(Forecast!$C$30:$L$30/(1+$B9)^Forecast!$C$4:$L$4)+Forecast!$L$30*(1+G$5)/($B9-G$5)/(1+$B9)^10+Assumptions!$C$6)/Assumptions!$C$7*Assumptions!$C$9/Assumptions!$C$8) -> 15.349778
B10: 0.1 | C10: =IF($B10<=C$5,"n/m",(SUMPRODUCT(Forecast!$C$30:$L$30/(1+$B10)^Forecast!$C$4:$L$4)+Forecast!$L$30*(1+C$5)/($B10-C$5)/(1+$B10)^10+Assumptions!$C$6)/Assumptions!$C$7*Assumptions!$C$9/Assumptions!$C$8) -> 11.897783 | D10: =IF($B10<=D$5,"n/m",(SUMPRODUCT(Forecast!$C$30:$L$30/(1+$B10)^Forecast!$C$4:$L$4)+Forecast!$L$30*(1+D$5)/($B10-D$5)/(1+$B10)^10+Assumptions!$C$6)/Assumptions!$C$7*Assumptions!$C$9/Assumptions!$C$8) -> 12.332091 | E10: =IF($B10<=E$5,"n/m",(SUMPRODUCT(Forecast!$C$30:$L$30/(1+$B10)^Forecast!$C$4:$L$4)+Forecast!$L$30*(1+E$5)/($B10-E$5)/(1+$B10)^10+Assumptions!$C$6)/Assumptions!$C$7*Assumptions!$C$9/Assumptions!$C$8) -> 12.828444 | F10: =IF($B10<=F$5,"n/m",(SUMPRODUCT(Forecast!$C$30:$L$30/(1+$B10)^Forecast!$C$4:$L$4)+Forecast!$L$30*(1+F$5)/($B10-F$5)/(1+$B10)^10+Assumptions!$C$6)/Assumptions!$C$7*Assumptions!$C$9/Assumptions!$C$8) -> 13.401158 | G10: =IF($B10<=G$5,"n/m",(SUMPRODUCT(Forecast!$C$30:$L$30/(1+$B10)^Forecast!$C$4:$L$4)+Forecast!$L$30*(1+G$5)/($B10-G$5)/(1+$B10)^10+Assumptions!$C$6)/Assumptions!$C$7*Assumptions!$C$9/Assumptions!$C$8) -> 14.069325
B11: 0.105 | C11: =IF($B11<=C$5,"n/m",(SUMPRODUCT(Forecast!$C$30:$L$30/(1+$B11)^Forecast!$C$4:$L$4)+Forecast!$L$30*(1+C$5)/($B11-C$5)/(1+$B11)^10+Assumptions!$C$6)/Assumptions!$C$7*Assumptions!$C$9/Assumptions!$C$8) -> 11.178308 | D11: =IF($B11<=D$5,"n/m",(SUMPRODUCT(Forecast!$C$30:$L$30/(1+$B11)^Forecast!$C$4:$L$4)+Forecast!$L$30*(1+D$5)/($B11-D$5)/(1+$B11)^10+Assumptions!$C$6)/Assumptions!$C$7*Assumptions!$C$9/Assumptions!$C$8) -> 11.546194 | E11: =IF($B11<=E$5,"n/m",(SUMPRODUCT(Forecast!$C$30:$L$30/(1+$B11)^Forecast!$C$4:$L$4)+Forecast!$L$30*(1+E$5)/($B11-E$5)/(1+$B11)^10+Assumptions!$C$6)/Assumptions!$C$7*Assumptions!$C$9/Assumptions!$C$8) -> 11.963133 | F11: =IF($B11<=F$5,"n/m",(SUMPRODUCT(Forecast!$C$30:$L$30/(1+$B11)^Forecast!$C$4:$L$4)+Forecast!$L$30*(1+F$5)/($B11-F$5)/(1+$B11)^10+Assumptions!$C$6)/Assumptions!$C$7*Assumptions!$C$9/Assumptions!$C$8) -> 12.439634 | G11: =IF($B11<=G$5,"n/m",(SUMPRODUCT(Forecast!$C$30:$L$30/(1+$B11)^Forecast!$C$4:$L$4)+Forecast!$L$30*(1+G$5)/($B11-G$5)/(1+$B11)^10+Assumptions!$C$6)/Assumptions!$C$7*Assumptions!$C$9/Assumptions!$C$8) -> 12.989443
B12: 0.11 | C12: =IF($B12<=C$5,"n/m",(SUMPRODUCT(Forecast!$C$30:$L$30/(1+$B12)^Forecast!$C$4:$L$4)+Forecast!$L$30*(1+C$5)/($B12-C$5)/(1+$B12)^10+Assumptions!$C$6)/Assumptions!$C$7*Assumptions!$C$9/Assumptions!$C$8) -> 10.541934 | D12: =IF($B12<=D$5,"n/m",(SUMPRODUCT(Forecast!$C$30:$L$30/(1+$B12)^Forecast!$C$4:$L$4)+Forecast!$L$30*(1+D$5)/($B12-D$5)/(1+$B12)^10+Assumptions!$C$6)/Assumptions!$C$7*Assumptions!$C$9/Assumptions!$C$8) -> 10.855923 | E12: =IF($B12<=E$5,"n/m",(SUMPRODUCT(Forecast!$C$30:$L$30/(1+$B12)^Forecast!$C$4:$L$4)+Forecast!$L$30*(1+E$5)/($B12-E$5)/(1+$B12)^10+Assumptions!$C$6)/Assumptions!$C$7*Assumptions!$C$9/Assumptions!$C$8) -> 11.209162 | F12: =IF($B12<=F$5,"n/m",(SUMPRODUCT(Forecast!$C$30:$L$30/(1+$B12)^Forecast!$C$4:$L$4)+Forecast!$L$30*(1+F$5)/($B12-F$5)/(1+$B12)^10+Assumptions!$C$6)/Assumptions!$C$7*Assumptions!$C$9/Assumptions!$C$8) -> 11.609499 | G12: =IF($B12<=G$5,"n/m",(SUMPRODUCT(Forecast!$C$30:$L$30/(1+$B12)^Forecast!$C$4:$L$4)+Forecast!$L$30*(1+G$5)/($B12-G$5)/(1+$B12)^10+Assumptions!$C$6)/Assumptions!$C$7*Assumptions!$C$9/Assumptions!$C$8) -> 12.067027
B14: Current ADR price (USD): | C14: =Assumptions!$C$10*Assumptions!$C$9/Assumptions!$C$8 -> 9.450056

Sheet Notes
B2: Notes, Caveats & Sources
B4: KEY CAVEATS
B5: 1. NET CASH now DERIVED from FY2025 balance sheet (user CSV): cash €10,797.4m − merchant payables €6,371.8m − debt €252.4m = €4,173.2m.
B6: Cross-checked vs equity €5,285.4m; plausible. Residual risk: other own financial investments / restricted cash not captured.
B7: 2. Float income (~€260-270m/yr, ~25% of FY2025 net income) is EXCLUDED from FCFF; net cash added separately. This matters:
B8: a rate-sensitive quarter of net income is NOT in the operating valuation — which is why FCFF, not net income, anchors this model.
B9: 3. Forecast is in reported EUR. 2026 guidance (20–22%) is constant currency; base case of 19% reported assumes ~2pt USD drag persists.
B10: 4. Talon.One acquisition (~€750m reported, Apr 2026) not separately modelled; treat as roughly value-neutral use of net cash.
B11: 5. The ADR is unsponsored (Adyen explicitly disclaims sponsorship). Liquidity is thin vs Amsterdam line; NZ brokers may access either.
B13: KEY DEBATE POINTS FOR THE THESIS
B14: • Take rate: 21.9bps (2018) -> 15.5 (2024) -> 17.0 (2025). Long-run compression is structural; 2025 recovery is mix. JPM flagged Q1 26 softness.
B15: • Segment: Digital (56% of rev) grew only ~9% reported in FY25; Unified Commerce (+30%) is carrying growth. Stripe (>$900bn US volume, ~45% growth) contests the core.
... B27: • Prices: ADYEN.AS ~€880 / ADYEY ~$9.85–10.20, Jul 2026 (update Assumptions!C10 and C9 before relying on upside numbers)
