Workbook

Sheet Summary
A1: ALIBABA GROUP HOLDING LIMITED (BABA)
A2: Discounted Cash Flow Valuation Model
A3: Analysis Date: December 2025
A5: KEY VALUATION METRICS
A6: Metric | B6: Value | C6: Notes
A7: Current Stock Price (USD) | B7: 158 | C7: As of Dec 2025
A8: Shares Outstanding (B) | B8: 2.39 | C8: Source: Company filings
A9: Market Cap (USD B) | B9: =B7*B8 -> 377.62
A10: Total Debt (USD B) | B10: 31.1 | C10: Book value of debt
A11: Cash & Investments (USD B) | B11: 50.2 | C11: Net cash position
A12: Enterprise Value (USD B) | B12: =B9+B10-B11 -> 358.52
A13: Net Debt (USD B) | B13: =B10-B11 -> -19.1
A16: DCF VALUATION RESULTS
A17: Scenario | B17: Implied Share Price | C17: Upside/Downside
A18: Base Case | B18: =DCF!B33 -> 157.93314 | C18: =(B18-$B$7)/$B$7 -> -0.00042315549
A19: Bull Case | B19: =DCF!G41 -> 179.18641 | C19: =(B19-$B$7)/$B$7 -> 0.13409119
A20: Bear Case | B20: =DCF!G42 -> 136.67987 | C20: =(B20-$B$7)/$B$7 -> -0.13493751
A23: COMPANY OVERVIEW
A24: Alibaba Group is China's largest e-commerce and cloud computing company.
A26: Key Business Segments:
A27: • Taobao & Tmall Group - Dominant China retail platforms (~53% of revenue)
A28: • Cloud Intelligence Group - #1 in China, #4 globally (growing 18-34% YoY)
A29: • International Digital Commerce - AliExpress, Lazada, Trendyol (~15% of revenue)
A30: • Local Services - Ele.me food delivery, Amap navigation
A31: • Cainiao Logistics - Smart logistics network
A33: Investment Thesis:
A34: • AI-driven cloud growth accelerating (triple-digit AI revenue growth)
A35: • E-commerce monetization improving via Quanzhantui ad platform
A36: • $53B committed AI infrastructure investment over 3 years
... A43: • Margin pressure from quick commerce investments

Sheet Assumptions
A1: KEY MODEL ASSUMPTIONS
A3: REVENUE GROWTH ASSUMPTIONS
A4: Segment | B4: FY2025A | C4: FY2026E | D4: FY2027E | E4: FY2028E | F4: FY2029E | G4: FY2030E | H4: Source/Notes
A5: Taobao & Tmall (% YoY) | B5: 0.05 | C5: 0.07 | D5: 0.08 | E5: 0.08 | F5: 0.07 | G5: 0.06 | H5: Improving take rates
A6: Cloud Intelligence (% YoY) | B6: 0.18 | C6: 0.27 | D6: 0.31 | E6: 0.28 | F6: 0.25 | G6: 0.22 | H6: AI-driven demand
A7: International (% YoY) | B7: 0.25 | C7: 0.2 | D7: 0.17 | E7: 0.15 | F7: 0.12 | G7: 0.1 | H7: Lazada expansion
A8: Local Services (% YoY) | B8: 0.1 | C8: 0.12 | D8: 0.1 | E8: 0.08 | F8: 0.06 | G8: 0.05 | H8: Quick commerce
A9: Other Segments (% YoY) | B9: 0.02 | C9: 0.03 | D9: 0.04 | E9: 0.04 | F9: 0.03 | G9: 0.03 | H9: Cainiao, Health
A12: MARGIN ASSUMPTIONS
A13: Metric | B13: FY2025A | C13: FY2026E | D13: FY2027E | E13: FY2028E | F13: FY2029E | G13: FY2030E | H13: Notes
A14: Gross Margin | B14: 0.4 | C14: 0.405 | D14: 0.41 | E14: 0.415 | F14: 0.42 | G14: 0.425 | H14: Scale benefits
A15: EBITDA Margin | B15: 0.17 | C15: 0.175 | D15: 0.185 | E15: 0.195 | F15: 0.2 | G15: 0.205 | H15: Operating leverage
A16: D&A as % of Revenue | B16: 0.043 | C16: 0.05 | D16: 0.055 | E16: 0.055 | F16: 0.053 | G16: 0.05 | H16: Heavy AI capex
A17: Tax Rate | B17: 0.2 | C17: 0.2 | D17: 0.2 | E17: 0.2 | F17: 0.2 | G17: 0.2 | H17: China effective
A18: CapEx as % of Revenue | B18: 0.05 | C18: 0.08 | D18: 0.1 | E18: 0.09 | F18: 0.08 | G18: 0.06 | H18: AI infrastructure
A19: NWC as % of Revenue Change | B19: 0.02 | C19: 0.02 | D19: 0.02 | E19: 0.02 | F19: 0.02 | G19: 0.02
A22: WACC CALCULATION
A23: Component | B23: Value | C23: Source
A24: Risk-Free Rate | B24: 0.043 | C24: 10-Year US Treasury
A25: Equity Risk Premium | B25: 0.055 | C25: Damodaran ERP
A26: Beta (Levered) | B26: 0.95 | C26: 5-year monthly
A27: Country Risk Premium | B27: 0.015 | C27: China CDS
A28: Cost of Equity | B28: =B24+B25*B26+B27 -> 0.11025 | C28: CAPM + Country Risk
A30: Cost of Debt (Pre-tax) | B30: 0.0374 | C30: Int Exp / Avg Debt
A31: Tax Rate (WACC) | B31: 0.2
A32: Cost of Debt (After-tax) | B32: =B30*(1-B31) -> 0.02992
A34: Market Value Equity (B) | B34: 377.8 | C34: Shares x Price
A35: Market Value Debt (B) | B35: 31.1 | C35: Book value proxy
A36: Weight of Equity | B36: =B34/(B34+B35) -> 0.92394228
A37: Weight of Debt | B37: =B35/(B34+B35) -> 0.076057716
A39: WACC | B39: =B36*B28+B37*B32 -> 0.10414028
A42: TERMINAL VALUE ASSUMPTIONS
A43: Parameter | B43: Value | C43: Notes
A44: Terminal Growth Rate | B44: 0.03 | C44: Long-term GDP
A45: Exit EV/EBITDA Multiple | B45: 12 | C45: Peer median

Sheet Financials
A1: ALIBABA GROUP - HISTORICAL & PROJECTED FINANCIALS
A2: All figures in USD Billions
A4: REVENUE BY SEGMENT
A5: Segment | B5: FY2024A | C5: FY2025A | D5: FY2026E | E5: FY2027E | F5: FY2028E | G5: FY2029E | H5: FY2030E | I5: CAGR '25-'30
A6: Taobao & Tmall | B6: 69.2 | C6: 72.7 | D6: =C6*(1+Assumptions!C5) -> 77.789 | E6: =D6*(1+Assumptions!D5) -> 84.01212 | F6: =E6*(1+Assumptions!E5) -> 90.73309 | G6: =F6*(1+Assumptions!F5) -> 97.084406 | H6: =G6*(1+Assumptions!G5) -> 102.90947 | I6: =(H6/C6)^(1/5)-1 -> 0.071973838
A7: Cloud Intelligence | B7: 15.8 | C7: 18.6 | D7: =C7*(1+Assumptions!C6) -> 23.622 | E7: =D7*(1+Assumptions!D6) -> 30.94482 | F7: =E7*(1+Assumptions!E6) -> 39.60937 | G7: =F7*(1+Assumptions!F6) -> 49.511712 | H7: =G7*(1+Assumptions!G6) -> 60.404289 | I7: =(H7/C7)^(1/5)-1 -> 0.26564226
A8: International | B8: 17.3 | C8: 21.6 | D8: =C8*(1+Assumptions!C7) -> 25.92 | E8: =D8*(1+Assumptions!D7) -> 30.3264 | F8: =E8*(1+Assumptions!E7) -> 34.87536 | G8: =F8*(1+Assumptions!F7) -> 39.060403 | H8: =G8*(1+Assumptions!G7) -> 42.966444 | I8: =(H8/C8)^(1/5)-1 -> 0.1474536
A9: Local Services | B9: 10.1 | C9: 11.1 | D9: =C9*(1+Assumptions!C8) -> 12.432 | E9: =D9*(1+Assumptions!D8) -> 13.6752 | F9: =E9*(1+Assumptions!E8) -> 14.769216 | G9: =F9*(1+Assumptions!F8) -> 15.655369 | H9: =G9*(1+Assumptions!G8) -> 16.438137 | I9: =(H9/C9)^(1/5)-1 -> 0.081697748
A10: Other Segments | B10: 17.9 | C10: 18.3 | D10: =C10*(1+Assumptions!C9) -> 18.849 | E10: =D10*(1+Assumptions!D9) -> 19.60296 | F10: =E10*(1+Assumptions!E9) -> 20.387078 | G10: =F10*(1+Assumptions!F9) -> 20.998691 | H10: =G10*(1+Assumptions!G9) -> 21.628651 | I10: =(H10/C10)^(1/5)-1 -> 0.033988409
A11: Total Revenue | B11: =SUM(B6:B10) -> 130.3 | C11: =SUM(C6:C10) -> 142.3 | D11: =SUM(D6:D10) -> 158.612 | E11: =SUM(E6:E10) -> 178.5615 | F11: =SUM(F6:F10) -> 200.37411 | G11: =SUM(G6:G10) -> 222.31058 | H11: =SUM(H6:H10) -> 244.34699 | I11: =(H11/C11)^(1/5)-1 -> 0.11419298
A12: YoY Growth | C12: =(C11-B11)/B11 -> 0.092095165 | D12: =(D11-C11)/C11 -> 0.11463106 | E12: =(E11-D11)/D11 -> 0.12577548 | F12: =(F11-E11)/E11 -> 0.12215743 | G12: =(G11-F11)/F11 -> 0.10947755 | H12: =(H11-G11)/G11 -> 0.099124434
A15: INCOME STATEMENT SUMMARY
A16: Line Item | B16: FY2024A | C16: FY2025A | D16: FY2026E | E16: FY2027E | F16: FY2028E | G16: FY2029E | H16: FY2030E
A17: Revenue | B17: =B11 -> 130.3 | C17: =C11 -> 142.3 | D17: =D11 -> 158.612 | E17: =E11 -> 178.5615 | F17: =F11 -> 200.37411 | G17: =G11 -> 222.31058 | H17: =H11 -> 244.34699
A18: Gross Profit | B18: =B17*0.39 -> 50.817 | C18: =C17*Assumptions!B14 -> 56.92 | D18: =D17*Assumptions!C14 -> 64.23786 | E18: =E17*Assumptions!D14 -> 73.210215 | F18: =F17*Assumptions!E14 -> 83.155257 | G18: =G17*Assumptions!F14 -> 93.370444 | H18: =H17*Assumptions!G14 -> 103.84747
A19: Gross Margin | B19: =B18/B17 -> 0.39 | C19: =C18/C17 -> 0.4 | D19: =D18/D17 -> 0.405 | E19: =E18/E17 -> 0.41 | F19: =F18/F17 -> 0.415 | G19: =G18/G17 -> 0.42 | H19: =H18/H17 -> 0.425
A21: EBITDA | B21: =B17*0.165 -> 21.4995 | C21: =C17*Assumptions!B15 -> 24.191 | D21: =D17*Assumptions!C15 -> 27.7571 | E21: =E17*Assumptions!D15 -> 33.033878 | F21: =F17*Assumptions!E15 -> 39.072952 | G21: =G17*Assumptions!F15 -> 44.462116 | H21: =H17*Assumptions!G15 -> 50.091133
A22: EBITDA Margin | B22: =B21/B17 -> 0.165 | C22: =C21/C17 -> 0.17 | D22: =D21/D17 -> 0.175 | E22: =E21/E17 -> 0.185 | F22: =F21/F17 -> 0.195 | G22: =G21/G17 -> 0.2 | H22: =H21/H17 -> 0.205
A23: D&A | B23: =B17*0.043 -> 5.6029 | C23: =C17*Assumptions!B16 -> 6.1189 | D23: =D17*Assumptions!C16 -> 7.9306 | E23: =E17*Assumptions!D16 -> 9.8208825 | F23: =F17*Assumptions!E16 -> 11.020576 | G23: =G17*Assumptions!F16 -> 11.782461 | H23: =H17*Assumptions!G16 -> 12.21735
A24: EBIT | B24: =B21-B23 -> 15.8966 | C24: =C21-C23 -> 18.0721 | D24: =D21-D23 -> 19.8265 | E24: =E21-E23 -> 23.212995 | F24: =F21-F23 -> 28.052376 | G24: =G21-G23 -> 32.679655 | H24: =H21-H23 -> 37.873784
A25: EBIT Margin | B25: =B24/B17 -> 0.122 | C25: =C24/C17 -> 0.127 | D25: =D24/D17 -> 0.125 | E25: =E24/E17 -> 0.13 | F25: =F24/F17 -> 0.14 | G25: =G24/G17 -> 0.147 | H25: =H24/H17 -> 0.155
A27: Taxes (@ 20%) | B27: =B24*0.2 -> 3.17932 | C27: =C24*0.2 -> 3.61442 | D27: =D24*0.2 -> 3.9653 | E27: =E24*0.2 -> 4.642599 | F27: =F24*0.2 -> 5.6104752 | G27: =G24*0.2 -> 6.5359311 | H27: =H24*0.2 -> 7.5747567
A28: NOPAT | B28: =B24-B27 -> 12.71728 | C28: =C24-C27 -> 14.45768 | D28: =D24-D27 -> 15.8612 | E28: =E24-E27 -> 18.570396 | F28: =F24-F27 -> 22.441901 | G28: =G24-G27 -> 26.143724 | H28: =H24-H27 -> 30.299027
A31: FREE CASH FLOW BUILD
A32: Line Item | B32: FY2024A | C32: FY2025A | D32: FY2026E | E32: FY2027E | F32: FY2028E | G32: FY2029E | H32: FY2030E
A33: NOPAT | B33: =B28 -> 12.71728 | C33: =C28 -> 14.45768 | D33: =D28 -> 15.8612 | E33: =E28 -> 18.570396 | F33: =F28 -> 22.441901 | G33: =G28 -> 26.143724 | H33: =H28 -> 30.299027
A34: (+) D&A | B34: =B23 -> 5.6029 | C34: =C23 -> 6.1189 | D34: =D23 -> 7.9306 | E34: =E23 -> 9.8208825 | F34: =F23 -> 11.020576 | G34: =G23 -> 11.782461 | H34: =H23 -> 12.21735
A35: (-) CapEx | B35: =-B17*0.05 -> -6.515 | C35: =-C17*Assumptions!B18 -> -7.115 | D35: =-D17*Assumptions!C18 -> -12.68896 | E35: =-E17*Assumptions!D18 -> -17.85615 | F35: =-F17*Assumptions!E18 -> -18.03367 | G35: =-G17*Assumptions!F18 -> -17.784846 | H35: =-H17*Assumptions!G18 -> -14.660819
A36: (-) Change in NWC | B36: =-1.5 -> -1.5 | C36: =-(C17-B17)*0.02 -> -0.24 | D36: =-(D17-C17)*0.02 -> -0.32624 | E36: =-(E17-D17)*0.02 -> -0.39899 | F36: =-(F17-E17)*0.02 -> -0.43625227 | G36: =-(G17-F17)*0.02 -> -0.43872934 | H36: =-(H17-G17)*0.02 -> -0.44072821
A37: Unlevered FCF | B37: =B33+B34+B35+B36 -> 10.30518 | C37: =C33+C34+C35+C36 -> 13.22158 | D37: =D33+D34+D35+D36 -> 10.7766 | E37: =E33+E34+E35+E36 -> 10.136138 | F37: =F33+F34+F35+F36 -> 14.992554 | G37: =G33+G34+G35+G36 -> 19.702609 | H37: =H33+H34+H35+H36 -> 27.414829
A38: FCF Margin | B38: =B37/B17 -> 0.079088104 | C38: =C37/C17 -> 0.092913422 | D38: =D37/D17 -> 0.067943157 | E38: =E37/E17 -> 0.056765532 | F38: =F37/F17 -> 0.074822811 | G38: =G37/G17 -> 0.088626503 | H38: =H37/H17 -> 0.1121963

Sheet DCF
A1: DISCOUNTED CASH FLOW VALUATION
A3: DCF INPUTS
A4: Parameter | B4: Value | C4: Source
A5: WACC | B5: =Assumptions!B39 -> 0.10414028 | C5: Calculated
A6: Terminal Growth Rate | B6: =Assumptions!B44 -> 0.03 | C6: Long-term
A7: Exit Multiple (EV/EBITDA) | B7: =Assumptions!B45 -> 12 | C7: Peer comp
A8: Shares Outstanding (B) | B8: =Summary!B8 -> 2.39
A9: Net Debt (USD B) | B9: =Summary!B13 -> -19.1
A12: DCF CALCULATION
B13: FY2026E | C13: FY2027E | D13: FY2028E | E13: FY2029E | F13: FY2030E | G13: Terminal
A14: Year | B14: 1 | C14: 2 | D14: 3 | E14: 4 | F14: 5
A15: Unlevered FCF | B15: =Financials!D37 -> 10.7766 | C15: =Financials!E37 -> 10.136138 | D15: =Financials!F37 -> 14.992554 | E15: =Financials!G37 -> 19.702609 | F15: =Financials!H37 -> 27.414829
A16: EBITDA (for TV) | F16: =Financials!H21 -> 50.091133 | H16: For Exit Multiple
A17: Terminal Value (Perpetuity) | G17: =F15*(1+$B$6)/($B$5-$B$6) -> 380.86277 | H17: Gordon Growth
A18: Terminal Value (Exit Mult) | G18: =F16*$B$7 -> 601.0936 | H18: EV/EBITDA
A19: Terminal Value (Blended) | G19: =(G17+G18)/2 -> 490.97818 | H19: Average
A21: Discount Factor | B21: =1/(1+$B$5)^B14 -> 0.90568202 | C21: =1/(1+$B$5)^C14 -> 0.82025992 | D21: =1/(1+$B$5)^D14 -> 0.74289466 | E21: =1/(1+$B$5)^E14 -> 0.67282633 | F21: =1/(1+$B$5)^F14 -> 0.60936671 | G21: =1/(1+$B$5)^5 -> 0.60936671
A22: PV of FCF | B22: =B15*B21 -> 9.7601728 | C22: =C15*C21 -> 8.3142681 | D22: =D15*D21 -> 11.137889 | E22: =E15*E21 -> 13.256434 | F22: =F15*F21 -> 16.705684 | G22: =G19*G21 -> 299.18576
A25: VALUATION SUMMARY
A26: Component | B26: Value (USD B) | C26: Per Share (USD)
A27: PV of FCF (Years 1-5) | B27: =SUM(B22:F22) -> 59.174448 | C27: =B27/$B$8 -> 24.759183
A28: PV of Terminal Value | B28: =G22 -> 299.18576 | C28: =B28/$B$8 -> 125.18233
A29: Enterprise Value | B29: =B27+B28 -> 358.36021 | C29: =B29/$B$8 -> 149.94151
A30: Less: Net Debt | B30: =$B$9 -> -19.1 | C30: =B30/$B$8 -> -7.9916318
A31: Equity Value | B31: =B29-B30 -> 377.46021 | C31: =B31/$B$8 -> 157.93314
A33: Implied Share Price | B33: =C31 -> 157.93314
A34: Current Price | B34: =Summary!B7 -> 158
A35: Upside/(Downside) | B35: =(B33-B34)/B34 -> -0.00042315549
A38: SCENARIO ANALYSIS
A39: Scenario | B39: WACC | C39: Term Growth | D39: Exit Mult | E39: EV (USD B) | F39: Equity (USD B) | G39: Share Price
A40: Base Case | B40: =B5 -> 0.10414028 | C40: =B6 -> 0.03 | D40: =B7 -> 12 | E40: =B29 -> 358.36021 | F40: =B31 -> 377.46021 | G40: =B33 -> 157.93314
A41: Bull Case | B41: 0.07 | C41: 0.035 | D41: 14 | E41: =SUM(B22:F22)*1.1+G22*1.15 -> 409.15552 | F41: =E41-$B$9 -> 428.25552 | G41: =F41/$B$8 -> 179.18641
A42: Bear Case | B42: 0.095 | C42: 0.02 | D42: 10 | E42: =SUM(B22:F22)*0.9+G22*0.85 -> 307.5649 | F42: =E42-$B$9 -> 326.6649 | G42: =F42/$B$8 -> 136.67987

Sheet Sensitivity
A1: SENSITIVITY ANALYSIS
A2: Implied Share Price under different WACC and Terminal Growth assumptions
A4: IMPLIED SHARE PRICE: WACC vs TERMINAL GROWTH RATE
A5: Terminal Growth → | B5: 0.02 | C5: 0.025 | D5: 0.03 | E5: 0.035 | F5: 0.04
A6: 0.065 | B6: 150.77 | C6: 166.13 | D6: 185.88 | E6: 212.21 | F6: 249.07
A7: 0.07 | B7: 136.55 | C7: 148.61 | D7: 163.69 | E7: 183.07 | F7: 208.91
A8: 0.075 | B8: 124.98 | C8: 134.67 | D8: 146.5 | E8: 161.3 | F8: 180.32
A9: 0.08 | B9: 115.39 | C9: 123.31 | D9: 132.82 | E9: 144.44 | F9: 158.96
A10: 0.085 | B10: 107.33 | C10: 113.91 | D10: 121.68 | E10: 131.02 | F10: 142.42
A11: 0.09 | B11: 100.46 | C11: 106 | D11: 112.46 | E11: 120.09 | F11: 129.25
A12: 0.095 | B12: 94.55 | C12: 99.26 | D12: 104.69 | E12: 111.04 | F12: 118.53
A15: IMPLIED SHARE PRICE: EXIT MULTIPLE vs WACC
A16: Exit Multiple → | B16: 10 | C16: 11 | D16: 12 | E16: 13 | F16: 14
A17: 0.065 | B17: 139.98 | C17: 150.67 | D17: 161.36 | E17: 172.05 | F17: 182.74
A18: 0.07 | B18: 137.51 | C18: 147.95 | D18: 158.39 | E18: 168.83 | F18: 179.27
A19: 0.075 | B19: 135.1 | C19: 145.3 | D19: 155.5 | E19: 165.7 | F19: 175.91
A20: 0.08 | B20: 132.76 | C20: 142.73 | D20: 152.7 | E20: 162.66 | F20: 172.63
A21: 0.085 | B21: 130.49 | C21: 140.23 | D21: 149.97 | E21: 159.71 | F21: 169.44
A22: 0.09 | B22: 128.27 | C22: 137.79 | D22: 147.31 | E22: 156.83 | F22: 166.35
A23: 0.095 | B23: 126.12 | C23: 135.42 | D23: 144.73 | E23: 154.03 | F23: 163.33

Sheet Comps
A1: COMPARABLE COMPANY ANALYSIS
A2: Trading Multiples as of December 2025
A4: E-COMMERCE & CLOUD PEERS
A5: Company | B5: Ticker | C5: Mkt Cap ($B) | D5: EV ($B) | E5: Rev ($B) | F5: EV/Rev | G5: EV/EBITDA | H5: P/E | I5: Rev Gr | J5: EBITDA %
A6: Alibaba | B6: BABA | C6: 378 | D6: 359 | E6: 142 | F6: =D6/E6 -> 2.528169 | G6: =D6/24 -> 14.958333 | H6: 21.5 | I6: 0.06 | J6: 0.17
A7: Amazon | B7: AMZN | C7: 2100 | D7: 2150 | E7: 620 | F7: =D7/E7 -> 3.4677419 | G7: =D7/95 -> 22.631579 | H7: 42 | I7: 0.11 | J7: 0.15
A8: JD.com | B8: JD | C8: 55 | D8: 42 | E8: 158 | F8: =D8/E8 -> 0.26582278 | G8: =D8/5.2 -> 8.0769231 | H8: 12.5 | I8: 0.05 | J8: 0.033
A9: PDD Holdings | B9: PDD | C9: 145 | D9: 105 | E9: 55 | F9: =D9/E9 -> 1.9090909 | G9: =D9/15 -> 7 | H9: 9.5 | I9: 0.45 | J9: 0.27
A10: MercadoLibre | B10: MELI | C10: 105 | D10: 100 | E10: 18 | F10: =D10/E10 -> 5.5555556 | G10: =D10/3.2 -> 31.25 | H10: 55 | I10: 0.35 | J10: 0.18
A11: Sea Limited | B11: SE | C11: 60 | D11: 55 | E11: 16 | F11: =D11/E11 -> 3.4375 | G11: =D11/2.1 -> 26.190476 | H11: 35 | I11: 0.22 | J11: 0.13
A13: Cloud Peers
A14: Microsoft | B14: MSFT | C14: 3100 | D14: 3050 | E14: 245 | F14: =D14/E14 -> 12.44898 | G14: =D14/125 -> 24.4 | H14: 35 | I14: 0.15 | J14: 0.51
A15: Google | B15: GOOGL | C15: 2200 | D15: 2100 | E15: 350 | F15: =D15/E15 -> 6 | G15: =D15/110 -> 19.090909 | H15: 24 | I15: 0.12 | J15: 0.31
A17: Median (E-com) | F17: =MEDIAN(F6:F11) -> 2.9828345 | G17: =MEDIAN(G6:G11) -> 18.794956 | H17: =MEDIAN(H6:H11) -> 28.25 | I17: =MEDIAN(I6:I11) -> 0.165 | J17: =MEDIAN(J6:J11) -> 0.16
A18: Mean (E-com) | F18: =AVERAGE(F6:F11) -> 2.8606467 | G18: =AVERAGE(G6:G11) -> 18.351219 | H18: =AVERAGE(H6:H11) -> 29.25 | I18: =AVERAGE(I6:I11) -> 0.20666667 | J18: =AVERAGE(J6:J11) -> 0.1555
A19: BABA vs Median | F19: =F6/F17-1 -> -0.15242733 | G19: =G6/G17-1 -> -0.20413045 | H19: =H6/H17-1 -> -0.23893805
A22: VALUATION COMMENTARY
A23: • Alibaba trades at significant discount to global e-commerce peers
A24: • Discount reflects China risk premium and regulatory concerns
A25: • Cloud business undervalued vs AWS/Azure despite faster growth
A26: • Key catalysts: AI monetization, regulatory clarity, buybacks
A27: • Sum-of-parts suggests upside to current valuation
