Workbook

Sheet Model_Info
A1: NZK.NZ DCF Model — New Zealand King Salmon Investments Ltd
A2: Version | B2: v1.0, fresh build 2026-08-23. Supersedes: nothing (first DCF for this ticker).
A3: Built by | B3: dcf-analyst agent (Claude, model claude-fable-5), 2026-08-23, at the user's request via the research workflow.
A4: Model | B4: Owner-FCF DCF, 10-year component build, three probability-weighted scenarios (bear 30 / base 50 / bull 20). Routed via dcf-methods SKILL.md: cyclical operating company.
A5: Data vintage — price | B5: NZ$0.24, Yahoo regular close Fri 2026-08-21 (04:59:51 UTC). Latest close as of valuation date Sun 2026-08-23. Figures go stale; refresh at next close.
A6: Data vintage — balance sheet | B6: 31 Mar 2026 (H1 FY2026 interims): cash $40.155m, borrowings $1.934m, lease liabilities $9.225m, equity $211.256m.
A7: Data vintage — shares | B7: 538,182,273 ordinary shares (FY25(Sept) annual report + H1 FY2026 interims). Held flat; SBC (~0.07% of revenue) fully expensed.
A8: Data vintage — guidance | B8: Aug-2026 upgrade: FY26 Pro-Forma EBITDA $30-34m, PF EBIT $21-25m, harvest 5,950-6,050t, capex $18-25m; FY27 harvest 7,200-7,600t, FY28 8,500-9,100t.
A9: Fiscal calendar | B9: Balance date changed TWICE. FY2016-20 = years to 30 Jun; FY2021-7mo = stub; FY2022-FY2025(Jan) = years to 31 Jan; FY2025-8mo = stub to 30 Sep 2025; now years to 30 Sep. FY0 here = FY2026E (12mo to 30 Sep 2026). Stubs never annualized.
A10: Choice — leases | B10: IFRS 16 treatment B: lease principal (~$1.9m/yr, ~1% of revenue) expensed inside the EBITDA margin path; lease liabilities EXCLUDED from net debt. Net debt = borrowings - cash = -$38.221m.
A11: Choice — interest income | B11: Stripped (~$0.9m/yr): net cash far exceeds the FCF base; leaving it in would double-count the cash pile.
A12: Choice — GAAP vs Pro-Forma | B12: Management guides Pro-Forma EBITDA (strips IAS 41 biological fair-value swings); it diverges materially from GAAP (H1 FY26: GAAP $24.0m vs PF $17.2m). Model uses PF level as cash anchor, mid-cycle GAAP-consistent margins thereafter.
A13: Choice — WACC 17.5% | B13: NZD-built: NZ small-cap base ~11.5% + biological/climate fat-tail 1.75% + illiquidity 2.0% + single-species/region 1.25% + consent dependence 1.0%. Single WACC for all scenarios; discrete mortality-recurrence risk lives in the 30% bear WEIGHT instead.
... A19: Cell legend | B19: BLUE font = hardcoded input. YELLOW fill = key lever (driver rows). Black = formula. GREEN font = cross-sheet link.

Sheet Actuals
A1: Reported history (NZ$m, per Metrics.csv / filings; stubs marked). Hardcoded.
A3: Period | B3: Basis | C3: Revenue | D3: EBITDA (GAAP) | E3: NPAT | F3: Op CF | G3: Capex | H3: Reported FCF | I3: Equity | J3: Cash | K3: Borrowings | L3: Shares (m)
A4: FY2016 | B4: 12mo to Jun-16 | C4: 114.06 | D4: 13.816 | E4: 2.593 | F4: 4.05 | G4: -6.972 | H4: -2.922 | I4: 37.014 | J4: 2.419 | K4: 19
A5: FY2017 | B5: 12mo to Jun-17 | C5: 136.351 | D5: 38.533 | E5: 22.764 | F5: 5.33 | G5: -7.449 | H5: -2.119 | I5: 158.675 | J5: 10.647 | K5: 0.414 | L5: 138.32
A6: FY2018 | B6: 12mo to Jun-18 | C6: 160.271 | D6: 28.482 | E6: 16.125 | F6: 24.838 | G6: -14.022 | H6: 10.816 | I6: 166.301 | J6: 14.428 | K6: 0.461 | L6: 138.32
A7: FY2019 | B7: 12mo to Jun-19 | C7: 172.609 | D7: 23.063 | E7: 11.35 | F7: 10.841 | G7: -14.191 | H7: -3.35 | I7: 168.752 | J7: 6.231 | K7: 0.416 | L7: 138.32
A8: FY2020 | B8: 12mo to Jun-20 | C8: 155.344 | D8: 36.074 | E8: 18.004 | F8: 4.224 | G8: -16.148 | H8: -11.924 | I8: 184.314 | J8: 7.115 | K8: 1.132 | L8: 138.99
A9: FY2021-7mo | B9: STUB 7mo to Jan-21 | C9: 95.239 | D9: 9.964 | E9: -7.079 | F9: -0.881 | G9: -4.837 | H9: -5.718 | I9: 192.543 | J9: 3.479 | K9: 3.024 | L9: 138.986
A10: FY2022 | B10: 12mo to Jan-22 CRISIS | C10: 174.53 | D10: -15.593 | E10: -73.202 | F10: 7.008 | G10: -10.295 | H10: -3.287 | I10: 111.229 | J10: 2.913 | K10: 0 | L10: 139.004
A11: FY2023 | B11: 12mo to Jan-23 | C11: 167.131 | D11: 11.698 | E11: 1.891 | F11: 10.475 | G11: -4.557 | H11: 5.918 | I11: 167.906 | J11: 19.221 | K11: 0.75 | L11: 541.455
A12: FY2024 | B12: 12mo to Jan-24 | C12: 187.106 | D12: 46.99 | E12: 28.452 | F12: 13.213 | G12: -6.049 | H12: 7.164 | I12: 190.295 | J12: 20.908 | K12: 3.417 | L12: 541.455
A13: FY2025-Jan | B13: 12mo to Jan-25 | C13: 210.993 | D13: 26.384 | E13: 13.359 | F13: 38.458 | G13: -10.743 | H13: 27.715 | I13: 197.031 | J13: 49.738 | K13: 4.505 | L13: 538.433
A14: FY2025-8mo | B14: STUB 8mo to Sep-25 | C14: 117.719 | D14: -3.709 | E14: -6.327 | F14: 10.63 | G14: -12.864 | H14: -2.234 | I14: 197.338 | J14: 45.629 | K14: 2 | L14: 538.182
A15: H1 FY2026-Jul | B15: 6mo to Jul-25 (orphaned half) | C15: 94.471 | D15: -25.065 | E15: -20.845 | F15: 19.645 | G15: -8.501 | H15: 11.144 | I15: 183.565 | J15: 57.354 | K15: 2.358 | L15: 538.182
A16: H1 FY2026-Mar | B16: 6mo to Mar-26 (current basis) | C16: 100.253 | D16: 23.954 | E16: 13.808 | F16: 7.306 | G16: -12.304 | H16: -4.998 | I16: 211.256 | J16: 40.155 | K16: 1.934 | L16: 538.182
A19: FY2026 guidance (Aug-2026 upgrade): Pro-Forma EBITDA $30-34m; PF EBIT $21-25m; harvest 5,950-6,050t; capex $18-25m. FY27 harvest 7,200-7,600t; FY28 8,500-9,100t. Source: NZX announcement Aug-2026.
A20: Balance sheet snapshot 31-Mar-2026: cash 40.155, borrowings 1.934, lease liabilities 9.225 (excluded from net debt, treatment B), equity 211.256. No dividend paid. No buybacks (buyback_cash = 0).
A21: Recapitalization: 2022 rights issue at NZ$0.20 took shares 139m to 541m. Yahoo price history pre-Apr-2022 carries a ~0.50 TERP adjustment factor.

Sheet Assumptions
A1: Global assumptions (BLUE = input)
A3: WACC | B3: 0.175 | C3: NZD-built: 11.5% NZ small-cap base + 1.75% biological fat-tail + 2.0% illiquidity + 1.25% concentration + 1.0% consent dependence. One WACC for all scenarios.
A4: Terminal growth | B4: 0.02 | C4: Capacity-constrained biological producer
A5: TV cap multiple (x FCF) | B5: 12 | C5: Low end of cyclical 12-15x band; Gordon (~6.6x) binds anyway
A6: D&A % of revenue | B6: 0.05 | C6: FY26E D&A ~ $9m (PF EBITDA minus PF EBIT) on $191m revenue
A7: WC capture on d(revenue) | B7: -0.2 | C7: Biomass build consumes ~20% of each revenue increment; destocking returns cash when revenue falls (observed FY2025-Jan)
A8: Net debt (NZ$m) | B8: -38.221 | C8: Borrowings 1.934 - cash 40.155, Mar-2026. Lease liabilities excluded (treatment B). Negative = net cash
A9: Diluted shares (m) | B9: 538.18227 | C9: FY25(Sept) AR + H1 FY2026 interims; held flat
A10: Current price (NZ$) | B10: 0.24 | C10: Yahoo close Fri 2026-08-21
A11: Hurdle rate (entry price) | B11: 0.15 | C11: NOTE: below the 17.5% WACC, so hurdle entry prices sit ABOVE IV; the binding buy price is weighted IV
A13: Scenario probability weights
A14: Bear | B14: 0.3
A15: Base | B15: 0.5
A16: Bull | B16: 0.2
A17: Sum (must be 1.0) | B17: =SUM(B14:B16)
A19: Bear (30%) | B19: Warm-summer mortality event recurs FY2028 (observed outcome: FY2022 lost $73.2m NPAT at up to ~42% site mortality). Revenue -18% in the event year, margin ~1%, recovery to a 14% mid-cycle only; Blue Endeavour shelved; tax losses suppress cash tax; survives on net cash without a raise — a crisis-terms raise is the residual risk BELOW this case. Weight doubled from the 15% default: recurrence is real, recent and structural.
A20: Base (50%) | B20: Guided inshore ramp mostly delivers with a haircut for NZK's record of missed biological forecasts: +15% then +12% revenue (vs guided FY27/FY28 harvest ramp), margins recover to a 17% post-lease mid-cycle (below FY2024's 25% peak), capex elevated through the pilot phase then fading to 5%, tax ramping to 28% statutory. No catastrophe, no full Blue Endeavour.
A21: Bull (20%) | B21: Recovery is structural (thermotolerant breeding, wellboat, summer diet); ramp delivers in full and the Blue Endeavour pilot succeeds, supporting a phased PARTIAL scale-up (~half-scale by year 10, not the $350m ambition). Margins reach 19%; capex 10% of revenue for five years. Weight cut from 35%: needs several independent things to go right.

Sheet DCF_Bear
A3: Year | B3: FY2026E (FY0) | C3: FY2027E | D3: FY2028E | E3: FY2029E | F3: FY2030E | G3: FY2031E | H3: FY2032E | I3: FY2033E | J3: FY2034E | K3: FY2035E | L3: FY2036E
A4: Index | B4: 0 | C4: 1 | D4: 2 | E4: 3 | F4: 4 | G4: 5 | H4: 6 | I4: 7 | J4: 8 | K4: 9 | L4: 10
A5: Revenue growth YoY | C5: 0.1 | D5: -0.18 | E5: 0.02 | F5: 0.12 | G5: 0.08 | H5: 0.04 | I5: 0.03 | J5: 0.02 | K5: 0.02 | L5: 0.02
A6: Revenue | B6: 191 | C6: =B6*(1+C5) | D6: =C6*(1+D5) | E6: =D6*(1+E5) | F6: =E6*(1+F5) | G6: =F6*(1+G5) | H6: =G6*(1+H5) | I6: =H6*(1+I5) | J6: =I6*(1+J5) | ... L6: =K6*(1+L5)
A7: Adj EBITDA margin (post-lease) | B7: 0.1575 | C7: 0.14 | D7: 0.01 | E7: 0.06 | F7: 0.11 | G7: 0.13 | H7: 0.135 | I7: 0.14 | J7: 0.14 | K7: 0.14 | L7: 0.14
A8: Adjusted EBITDA | C8: =C6*C7 | D8: =D6*D7 | E8: =E6*E7 | F8: =F6*F7 | G8: =G6*G7 | H8: =H6*H7 | I8: =I6*I7 | J8: =J6*J7 | ... L8: =L6*L7
A9: SBC % of revenue | C9: 0.0007 | D9: 0.0007 | E9: 0.0007 | F9: 0.0007 | G9: 0.0007 | H9: 0.0007 | I9: 0.0007 | J9: 0.0007 | K9: 0.0007 | L9: 0.0007
A10: SBC $ | C10: =-C6*C9 | D10: =-D6*D9 | E10: =-E6*E9 | F10: =-F6*F9 | G10: =-G6*G9 | H10: =-H6*H9 | I10: =-I6*I9 | J10: =-J6*J9 | ... L10: =-L6*L9
A11: Owner EBITDA | C11: =C8+C10 | D11: =D8+D10 | E11: =E8+E10 | F11: =F8+F10 | G11: =G8+G10 | H11: =H8+H10 | I11: =I8+I10 | J11: =J8+J10 | ... L11: =L8+L10
A12: D&A | C12: =-C6*Assumptions!$B$6 | D12: =-D6*Assumptions!$B$6 | E12: =-E6*Assumptions!$B$6 | F12: =-F6*Assumptions!$B$6 | G12: =-G6*Assumptions!$B$6 | H12: =-H6*Assumptions!$B$6 | I12: =-I6*Assumptions!$B$6 | J12: =-J6*Assumptions!$B$6 | ... L12: =-L6*Assumptions!$B$6
A13: EBIT (SBC expensed) | C13: =C11+C12 | D13: =D11+D12 | E13: =E11+E12 | F13: =F11+F12 | G13: =G11+G12 | H13: =H11+H12 | I13: =I11+I12 | J13: =J11+J12 | ... L13: =L11+L12
A14: Cash tax rate | C14: 0.18 | D14: 0 | E14: 0.05 | F14: 0.15 | G14: 0.24 | H14: 0.28 | I14: 0.28 | J14: 0.28 | K14: 0.28 | L14: 0.28
A15: NOPAT | C15: =C13*(1-C14) | D15: =D13*(1-D14) | E15: =E13*(1-E14) | F15: =F13*(1-F14) | G15: =G13*(1-G14) | H15: =H13*(1-H14) | I15: =I13*(1-I14) | J15: =J13*(1-J14) | ... L15: =L13*(1-L14)
A16: add back D&A | C16: =-C12 | D16: =-D12 | E16: =-E12 | F16: =-F12 | G16: =-G12 | H16: =-H12 | I16: =-I12 | J16: =-J12 | ... L16: =-L12
A17: Capex % of revenue | C17: 0.095 | D17: 0.08 | E17: 0.06 | F17: 0.055 | G17: 0.055 | H17: 0.055 | I17: 0.05 | J17: 0.05 | K17: 0.05 | L17: 0.05
A18: Capex $ | C18: =-C6*C17 | D18: =-D6*D17 | E18: =-E6*E17 | F18: =-F6*F17 | G18: =-G6*G17 | H18: =-H6*H17 | I18: =-I6*I17 | J18: =-J6*J17 | ... L18: =-L6*L17
A19: Working capital (on d rev) | C19: =Assumptions!$B$7*(C6-B6) | D19: =Assumptions!$B$7*(D6-C6) | E19: =Assumptions!$B$7*(E6-D6) | F19: =Assumptions!$B$7*(F6-E6) | G19: =Assumptions!$B$7*(G6-F6) | H19: =Assumptions!$B$7*(H6-G6) | I19: =Assumptions!$B$7*(I6-H6) | J19: =Assumptions!$B$7*(J6-I6) | ... L19: =Assumptions!$B$7*(L6-K6)
A20: Unlevered owner FCF | C20: =C15+C16+C18+C19 | D20: =D15+D16+D18+D19 | E20: =E15+E16+E18+E19 | F20: =F15+F16+F18+F19 | G20: =G15+G16+G18+G19 | H20: =H15+H16+H18+H19 | I20: =I15+I16+I18+I19 | J20: =J15+J16+J18+J19 | ... L20: =L15+L16+L18+L19
A21: Discount factor | C21: =1/(1+Assumptions!$B$3)^C4 | D21: =1/(1+Assumptions!$B$3)^D4 | E21: =1/(1+Assumptions!$B$3)^E4 | F21: =1/(1+Assumptions!$B$3)^F4 | G21: =1/(1+Assumptions!$B$3)^G4 | H21: =1/(1+Assumptions!$B$3)^H4 | I21: =1/(1+Assumptions!$B$3)^I4 | J21: =1/(1+Assumptions!$B$3)^J4 | ... L21: =1/(1+Assumptions!$B$3)^L4
A22: PV of FCF | C22: =C20*C21 | D22: =D20*D21 | E22: =E20*E21 | F22: =F20*F21 | G22: =G20*G21 | H22: =H20*H21 | I22: =I20*I21 | J22: =J20*J21 | ... L22: =L20*L21
A24: Memo: FCF before SBC | C24: =C20-C10 | D24: =D20-D10 | E24: =E20-E10 | F24: =F20-F10 | G24: =G20-G10 | H24: =H20-H10 | I24: =I20-I10 | J24: =J20-J10 | ... L24: =L20-L10
A25: Memo: owner FCF margin | C25: =C20/C6 | D25: =D20/D6 | E25: =E20/E6 | F25: =F20/F6 | G25: =G20/G6 | H25: =H20/H6 | I25: =I20/I6 | J25: =J20/J6 | ... L25: =L20/L6
A27: Sum of PV (explicit) | B27: =SUM(C22:L22)
A28: Terminal growth | B28: =Assumptions!$B$4
A29: Terminal FCF | B29: =L20*(1+B28)
A30: Gordon TV | B30: =B29/(Assumptions!$B$3-B28)
A31: Cap TV (12x) | B31: =Assumptions!$B$5*L20
A32: TV used = MAX(0,MIN(Gordon,Cap)) | B32: =MAX(0,MIN(B30,B31))
A33: Implied exit multiple | B33: =IF(L20>0,B32/L20,"n/a")
A34: PV of TV | B34: =B32*L21
A35: Enterprise value | B35: =B27+B34
A36: add net cash | B36: =-Assumptions!$B$8
A37: Equity value | B37: =B35+B36
A38: Diluted shares (m) | B38: =Assumptions!$B$9
A39: VALUE PER SHARE (NZ$) | B39: =B37/B38
A40: Upside vs price | B40: =B39/Assumptions!$B$10-1
A42: Street memo: PV explicit SBC | B42: =SUMPRODUCT(-C10:L10/(1+Assumptions!$B$3)^C4:L4)
A43: Street memo: PV terminal SBC | B43: =(-L10*(1+B28)/(Assumptions!$B$3-B28))*L21
A44: Street value per share | B44: =(B37+B42+B43)/B38

Sheet DCF_Base
A3: Year | B3: FY2026E (FY0) | C3: FY2027E | D3: FY2028E | E3: FY2029E | F3: FY2030E | G3: FY2031E | H3: FY2032E | I3: FY2033E | J3: FY2034E | K3: FY2035E | L3: FY2036E
A4: Index | B4: 0 | C4: 1 | D4: 2 | E4: 3 | F4: 4 | G4: 5 | H4: 6 | I4: 7 | J4: 8 | K4: 9 | L4: 10
A5: Revenue growth YoY | C5: 0.15 | D5: 0.12 | E5: 0.08 | F5: 0.06 | G5: 0.05 | H5: 0.04 | I5: 0.03 | J5: 0.025 | K5: 0.025 | L5: 0.02
A6: Revenue | B6: 191 | C6: =B6*(1+C5) | D6: =C6*(1+D5) | E6: =D6*(1+E5) | F6: =E6*(1+F5) | G6: =F6*(1+G5) | H6: =G6*(1+H5) | I6: =H6*(1+I5) | J6: =I6*(1+J5) | ... L6: =K6*(1+L5)
A7: Adj EBITDA margin (post-lease) | B7: 0.1575 | C7: 0.15 | D7: 0.155 | E7: 0.16 | F7: 0.165 | G7: 0.17 | H7: 0.17 | I7: 0.17 | J7: 0.17 | K7: 0.17 | L7: 0.17
A8: Adjusted EBITDA | C8: =C6*C7 | D8: =D6*D7 | E8: =E6*E7 | F8: =F6*F7 | G8: =G6*G7 | H8: =H6*H7 | I8: =I6*I7 | J8: =J6*J7 | ... L8: =L6*L7
A9: SBC % of revenue | C9: 0.0007 | D9: 0.0007 | E9: 0.0007 | F9: 0.0007 | G9: 0.0007 | H9: 0.0007 | I9: 0.0007 | J9: 0.0007 | K9: 0.0007 | L9: 0.0007
A10: SBC $ | C10: =-C6*C9 | D10: =-D6*D9 | E10: =-E6*E9 | F10: =-F6*F9 | G10: =-G6*G9 | H10: =-H6*H9 | I10: =-I6*I9 | J10: =-J6*J9 | ... L10: =-L6*L9
A11: Owner EBITDA | C11: =C8+C10 | D11: =D8+D10 | E11: =E8+E10 | F11: =F8+F10 | G11: =G8+G10 | H11: =H8+H10 | I11: =I8+I10 | J11: =J8+J10 | ... L11: =L8+L10
A12: D&A | C12: =-C6*Assumptions!$B$6 | D12: =-D6*Assumptions!$B$6 | E12: =-E6*Assumptions!$B$6 | F12: =-F6*Assumptions!$B$6 | G12: =-G6*Assumptions!$B$6 | H12: =-H6*Assumptions!$B$6 | I12: =-I6*Assumptions!$B$6 | J12: =-J6*Assumptions!$B$6 | ... L12: =-L6*Assumptions!$B$6
A13: EBIT (SBC expensed) | C13: =C11+C12 | D13: =D11+D12 | E13: =E11+E12 | F13: =F11+F12 | G13: =G11+G12 | H13: =H11+H12 | I13: =I11+I12 | J13: =J11+J12 | ... L13: =L11+L12
A14: Cash tax rate | C14: 0.18 | D14: 0.24 | E14: 0.28 | F14: 0.28 | G14: 0.28 | H14: 0.28 | I14: 0.28 | J14: 0.28 | K14: 0.28 | L14: 0.28
A15: NOPAT | C15: =C13*(1-C14) | D15: =D13*(1-D14) | E15: =E13*(1-E14) | F15: =F13*(1-F14) | G15: =G13*(1-G14) | H15: =H13*(1-H14) | I15: =I13*(1-I14) | J15: =J13*(1-J14) | ... L15: =L13*(1-L14)
A16: add back D&A | C16: =-C12 | D16: =-D12 | E16: =-E12 | F16: =-F12 | G16: =-G12 | H16: =-H12 | I16: =-I12 | J16: =-J12 | ... L16: =-L12
A17: Capex % of revenue | C17: 0.095 | D17: 0.09 | E17: 0.08 | F17: 0.07 | G17: 0.065 | H17: 0.06 | I17: 0.055 | J17: 0.055 | K17: 0.05 | L17: 0.05
A18: Capex $ | C18: =-C6*C17 | D18: =-D6*D17 | E18: =-E6*E17 | F18: =-F6*F17 | G18: =-G6*G17 | H18: =-H6*H17 | I18: =-I6*I17 | J18: =-J6*J17 | ... L18: =-L6*L17
A19: Working capital (on d rev) | C19: =Assumptions!$B$7*(C6-B6) | D19: =Assumptions!$B$7*(D6-C6) | E19: =Assumptions!$B$7*(E6-D6) | F19: =Assumptions!$B$7*(F6-E6) | G19: =Assumptions!$B$7*(G6-F6) | H19: =Assumptions!$B$7*(H6-G6) | I19: =Assumptions!$B$7*(I6-H6) | J19: =Assumptions!$B$7*(J6-I6) | ... L19: =Assumptions!$B$7*(L6-K6)
A20: Unlevered owner FCF | C20: =C15+C16+C18+C19 | D20: =D15+D16+D18+D19 | E20: =E15+E16+E18+E19 | F20: =F15+F16+F18+F19 | G20: =G15+G16+G18+G19 | H20: =H15+H16+H18+H19 | I20: =I15+I16+I18+I19 | J20: =J15+J16+J18+J19 | ... L20: =L15+L16+L18+L19
A21: Discount factor | C21: =1/(1+Assumptions!$B$3)^C4 | D21: =1/(1+Assumptions!$B$3)^D4 | E21: =1/(1+Assumptions!$B$3)^E4 | F21: =1/(1+Assumptions!$B$3)^F4 | G21: =1/(1+Assumptions!$B$3)^G4 | H21: =1/(1+Assumptions!$B$3)^H4 | I21: =1/(1+Assumptions!$B$3)^I4 | J21: =1/(1+Assumptions!$B$3)^J4 | ... L21: =1/(1+Assumptions!$B$3)^L4
A22: PV of FCF | C22: =C20*C21 | D22: =D20*D21 | E22: =E20*E21 | F22: =F20*F21 | G22: =G20*G21 | H22: =H20*H21 | I22: =I20*I21 | J22: =J20*J21 | ... L22: =L20*L21
A24: Memo: FCF before SBC | C24: =C20-C10 | D24: =D20-D10 | E24: =E20-E10 | F24: =F20-F10 | G24: =G20-G10 | H24: =H20-H10 | I24: =I20-I10 | J24: =J20-J10 | ... L24: =L20-L10
A25: Memo: owner FCF margin | C25: =C20/C6 | D25: =D20/D6 | E25: =E20/E6 | F25: =F20/F6 | G25: =G20/G6 | H25: =H20/H6 | I25: =I20/I6 | J25: =J20/J6 | ... L25: =L20/L6
A27: Sum of PV (explicit) | B27: =SUM(C22:L22)
A28: Terminal growth | B28: =Assumptions!$B$4
A29: Terminal FCF | B29: =L20*(1+B28)
A30: Gordon TV | B30: =B29/(Assumptions!$B$3-B28)
A31: Cap TV (12x) | B31: =Assumptions!$B$5*L20
A32: TV used = MAX(0,MIN(Gordon,Cap)) | B32: =MAX(0,MIN(B30,B31))
A33: Implied exit multiple | B33: =IF(L20>0,B32/L20,"n/a")
A34: PV of TV | B34: =B32*L21
A35: Enterprise value | B35: =B27+B34
A36: add net cash | B36: =-Assumptions!$B$8
A37: Equity value | B37: =B35+B36
A38: Diluted shares (m) | B38: =Assumptions!$B$9
A39: VALUE PER SHARE (NZ$) | B39: =B37/B38
A40: Upside vs price | B40: =B39/Assumptions!$B$10-1
A42: Street memo: PV explicit SBC | B42: =SUMPRODUCT(-C10:L10/(1+Assumptions!$B$3)^C4:L4)
A43: Street memo: PV terminal SBC | B43: =(-L10*(1+B28)/(Assumptions!$B$3-B28))*L21
A44: Street value per share | B44: =(B37+B42+B43)/B38

Sheet DCF_Bull
A3: Year | B3: FY2026E (FY0) | C3: FY2027E | D3: FY2028E | E3: FY2029E | F3: FY2030E | G3: FY2031E | H3: FY2032E | I3: FY2033E | J3: FY2034E | K3: FY2035E | L3: FY2036E
A4: Index | B4: 0 | C4: 1 | D4: 2 | E4: 3 | F4: 4 | G4: 5 | H4: 6 | I4: 7 | J4: 8 | K4: 9 | L4: 10
A5: Revenue growth YoY | C5: 0.17 | D5: 0.16 | E5: 0.14 | F5: 0.13 | G5: 0.12 | H5: 0.1 | I5: 0.08 | J5: 0.06 | K5: 0.05 | L5: 0.04
A6: Revenue | B6: 191 | C6: =B6*(1+C5) | D6: =C6*(1+D5) | E6: =D6*(1+E5) | F6: =E6*(1+F5) | G6: =F6*(1+G5) | H6: =G6*(1+H5) | I6: =H6*(1+I5) | J6: =I6*(1+J5) | ... L6: =K6*(1+L5)
A7: Adj EBITDA margin (post-lease) | B7: 0.1575 | C7: 0.155 | D7: 0.165 | E7: 0.175 | F7: 0.18 | G7: 0.185 | H7: 0.19 | I7: 0.19 | J7: 0.19 | K7: 0.19 | L7: 0.19
A8: Adjusted EBITDA | C8: =C6*C7 | D8: =D6*D7 | E8: =E6*E7 | F8: =F6*F7 | G8: =G6*G7 | H8: =H6*H7 | I8: =I6*I7 | J8: =J6*J7 | ... L8: =L6*L7
A9: SBC % of revenue | C9: 0.0007 | D9: 0.0007 | E9: 0.0007 | F9: 0.0007 | G9: 0.0007 | H9: 0.0007 | I9: 0.0007 | J9: 0.0007 | K9: 0.0007 | L9: 0.0007
A10: SBC $ | C10: =-C6*C9 | D10: =-D6*D9 | E10: =-E6*E9 | F10: =-F6*F9 | G10: =-G6*G9 | H10: =-H6*H9 | I10: =-I6*I9 | J10: =-J6*J9 | ... L10: =-L6*L9
A11: Owner EBITDA | C11: =C8+C10 | D11: =D8+D10 | E11: =E8+E10 | F11: =F8+F10 | G11: =G8+G10 | H11: =H8+H10 | I11: =I8+I10 | J11: =J8+J10 | ... L11: =L8+L10
A12: D&A | C12: =-C6*Assumptions!$B$6 | D12: =-D6*Assumptions!$B$6 | E12: =-E6*Assumptions!$B$6 | F12: =-F6*Assumptions!$B$6 | G12: =-G6*Assumptions!$B$6 | H12: =-H6*Assumptions!$B$6 | I12: =-I6*Assumptions!$B$6 | J12: =-J6*Assumptions!$B$6 | ... L12: =-L6*Assumptions!$B$6
A13: EBIT (SBC expensed) | C13: =C11+C12 | D13: =D11+D12 | E13: =E11+E12 | F13: =F11+F12 | G13: =G11+G12 | H13: =H11+H12 | I13: =I11+I12 | J13: =J11+J12 | ... L13: =L11+L12
A14: Cash tax rate | C14: 0.18 | D14: 0.24 | E14: 0.28 | F14: 0.28 | G14: 0.28 | H14: 0.28 | I14: 0.28 | J14: 0.28 | K14: 0.28 | L14: 0.28
A15: NOPAT | C15: =C13*(1-C14) | D15: =D13*(1-D14) | E15: =E13*(1-E14) | F15: =F13*(1-F14) | G15: =G13*(1-G14) | H15: =H13*(1-H14) | I15: =I13*(1-I14) | J15: =J13*(1-J14) | ... L15: =L13*(1-L14)
A16: add back D&A | C16: =-C12 | D16: =-D12 | E16: =-E12 | F16: =-F12 | G16: =-G12 | H16: =-H12 | I16: =-I12 | J16: =-J12 | ... L16: =-L12
A17: Capex % of revenue | C17: 0.1 | D17: 0.1 | E17: 0.1 | F17: 0.09 | G17: 0.08 | H17: 0.07 | I17: 0.06 | J17: 0.055 | K17: 0.05 | L17: 0.05
A18: Capex $ | C18: =-C6*C17 | D18: =-D6*D17 | E18: =-E6*E17 | F18: =-F6*F17 | G18: =-G6*G17 | H18: =-H6*H17 | I18: =-I6*I17 | J18: =-J6*J17 | ... L18: =-L6*L17
A19: Working capital (on d rev) | C19: =Assumptions!$B$7*(C6-B6) | D19: =Assumptions!$B$7*(D6-C6) | E19: =Assumptions!$B$7*(E6-D6) | F19: =Assumptions!$B$7*(F6-E6) | G19: =Assumptions!$B$7*(G6-F6) | H19: =Assumptions!$B$7*(H6-G6) | I19: =Assumptions!$B$7*(I6-H6) | J19: =Assumptions!$B$7*(J6-I6) | ... L19: =Assumptions!$B$7*(L6-K6)
A20: Unlevered owner FCF | C20: =C15+C16+C18+C19 | D20: =D15+D16+D18+D19 | E20: =E15+E16+E18+E19 | F20: =F15+F16+F18+F19 | G20: =G15+G16+G18+G19 | H20: =H15+H16+H18+H19 | I20: =I15+I16+I18+I19 | J20: =J15+J16+J18+J19 | ... L20: =L15+L16+L18+L19
A21: Discount factor | C21: =1/(1+Assumptions!$B$3)^C4 | D21: =1/(1+Assumptions!$B$3)^D4 | E21: =1/(1+Assumptions!$B$3)^E4 | F21: =1/(1+Assumptions!$B$3)^F4 | G21: =1/(1+Assumptions!$B$3)^G4 | H21: =1/(1+Assumptions!$B$3)^H4 | I21: =1/(1+Assumptions!$B$3)^I4 | J21: =1/(1+Assumptions!$B$3)^J4 | ... L21: =1/(1+Assumptions!$B$3)^L4
A22: PV of FCF | C22: =C20*C21 | D22: =D20*D21 | E22: =E20*E21 | F22: =F20*F21 | G22: =G20*G21 | H22: =H20*H21 | I22: =I20*I21 | J22: =J20*J21 | ... L22: =L20*L21
A24: Memo: FCF before SBC | C24: =C20-C10 | D24: =D20-D10 | E24: =E20-E10 | F24: =F20-F10 | G24: =G20-G10 | H24: =H20-H10 | I24: =I20-I10 | J24: =J20-J10 | ... L24: =L20-L10
A25: Memo: owner FCF margin | C25: =C20/C6 | D25: =D20/D6 | E25: =E20/E6 | F25: =F20/F6 | G25: =G20/G6 | H25: =H20/H6 | I25: =I20/I6 | J25: =J20/J6 | ... L25: =L20/L6
A27: Sum of PV (explicit) | B27: =SUM(C22:L22)
A28: Terminal growth | B28: =Assumptions!$B$4
A29: Terminal FCF | B29: =L20*(1+B28)
A30: Gordon TV | B30: =B29/(Assumptions!$B$3-B28)
A31: Cap TV (12x) | B31: =Assumptions!$B$5*L20
A32: TV used = MAX(0,MIN(Gordon,Cap)) | B32: =MAX(0,MIN(B30,B31))
A33: Implied exit multiple | B33: =IF(L20>0,B32/L20,"n/a")
A34: PV of TV | B34: =B32*L21
A35: Enterprise value | B35: =B27+B34
A36: add net cash | B36: =-Assumptions!$B$8
A37: Equity value | B37: =B35+B36
A38: Diluted shares (m) | B38: =Assumptions!$B$9
A39: VALUE PER SHARE (NZ$) | B39: =B37/B38
A40: Upside vs price | B40: =B39/Assumptions!$B$10-1
A42: Street memo: PV explicit SBC | B42: =SUMPRODUCT(-C10:L10/(1+Assumptions!$B$3)^C4:L4)
A43: Street memo: PV terminal SBC | B43: =(-L10*(1+B28)/(Assumptions!$B$3-B28))*L21
A44: Street value per share | B44: =(B37+B42+B43)/B38

Sheet FCF_Quality
A1: Reported FCF reconciled to owner FCF (NZ$m). Treatment B: lease principal also deducted. Stubs/halves marked — never annualized.
A3: Period | B3: FY2023 (12mo Jan) | C3: FY2024 (12mo Jan) | D3: FY2025-Jan (12mo) | E3: FY2025-8mo STUB | F3: H1 FY2026-Mar (6mo) | G3: FY2026E (12mo Sep)
A4: Revenue | B4: 167.131 | C4: 187.106 | D4: 210.993 | E4: 117.719 | F4: 100.253 | G4: 191
A5: Free cash flow (company definition) | B5: 5.918 | C5: 7.164 | D5: 27.715 | E5: -2.234 | F5: -4.998 | G5: 5.4
A6: less: SBC | B6: 0 | C6: 0.026 | D6: 0.14 | E6: 0.069 | F6: 0.069 | G6: 0.14
A7: less: interest income | B7: 0.337 | C7: 1.051 | D7: 1.466 | E7: 1.042 | F7: 0.432 | G7: 0.87
A8: less: lease principal (IFRS 16) | B8: 1.573 | C8: 1.264 | D8: 1.58 | E8: 1.268 | F8: 0.919 | G8: 1.9
A9: Owner FCF (FCF less SBC, interest, lease principal) | B9: =B5-B6-B7-B8 | C9: =C5-C6-C7-C8 | D9: =D5-D6-D7-D8 | E9: =E5-E6-E7-E8 | F9: =F5-F6-F7-F8 | G9: =G5-G6-G7-G8
A10: Reported FCF margin | B10: =B5/B4 | C10: =C5/C4 | D10: =D5/D4 | E10: =E5/E4 | F10: =F5/F4 | G10: =G5/G4
A11: Owner FCF margin | B11: =B9/B4 | C11: =C9/C4 | D11: =D9/D4 | E11: =E9/E4 | F11: =F9/F4 | G11: =G9/G4
A13: Memo: FY2025-Jan owner FCF (+$24.5m) was destocking-inflated (biomass rundown after reduced feed-outs) — NOT a repeatable base. FY2025-8mo and H1 FY2026 owner FCF are negative on growth capex (Blue Endeavour pilot, RAS, wellboat).
A14: Memo: cash tax currently below the 28% NZ statutory rate (FY2025-8mo held a $2.66m tax credit); model ramps 18% -> 28% by year 3.
A15: Sources: FY2023/FY2024/FY2025(Jan)/FY25(Sept) annual reports and H1 FY2026 interims — cash flow statements (interest received, payment of lease liabilities) and SBP notes.

Sheet Valuation
A1: Valuation summary — NZK.NZ (NZ$)
A3: Scenario | B3: Value/share | C3: Upside vs price | D3: Weight | E3: Street value/share
A4: Bear | B4: =DCF_Bear!$B$39 | C4: =B4/Assumptions!$B$10-1 | D4: =Assumptions!$B$14 | E4: =DCF_Bear!$B$44
A5: Base | B5: =DCF_Base!$B$39 | C5: =B5/Assumptions!$B$10-1 | D5: =Assumptions!$B$15 | E5: =DCF_Base!$B$44
A6: Bull | B6: =DCF_Bull!$B$39 | C6: =B6/Assumptions!$B$10-1 | D6: =Assumptions!$B$16 | E6: =DCF_Bull!$B$44
A8: Probability-weighted IV | B8: =SUMPRODUCT(B4:B6,D4:D6)
A9: Margin of safety vs price | B9: =1-Assumptions!$B$10/B8
A10: Street weighted IV | B10: =SUMPRODUCT(E4:E6,D4:D6)
A11: Band position | B11: n/a — SBC ~0.07% of revenue; house and street coincide (spread ~NZ$0.002)
A14: Required-return table (base case): value per share at required return r
A15: r = | B15: 0.09 | C15: 0.1 | D15: 0.11 | E15: 0.12 | F15: 0.15 | G15: 0.175
A16: Value/share | B16: =(SUMPRODUCT(DCF_Base!$C$20:$L$20/(1+0.09)^DCF_Base!$C$4:$L$4)+MAX(0,MIN(DCF_Base!$L$20*(1+Assumptions!$B$4)/(Assumptions!$B$3-Assumptions!$B$4),Assumptions!$B$5*DCF_Base!$L$20))/(1+0.09)^10-Assumptions!$B$8)/Assumptions!$B$9 | C16: =(SUMPRODUCT(DCF_Base!$C$20:$L$20/(1+0.1)^DCF_Base!$C$4:$L$4)+MAX(0,MIN(DCF_Base!$L$20*(1+Assumptions!$B$4)/(Assumptions!$B$3-Assumptions!$B$4),Assumptions!$B$5*DCF_Base!$L$20))/(1+0.1)^10-Assumptions!$B$8)/Assumptions!$B$9 | D16: =(SUMPRODUCT(DCF_Base!$C$20:$L$20/(1+0.11)^DCF_Base!$C$4:$L$4)+MAX(0,MIN(DCF_Base!$L$20*(1+Assumptions!$B$4)/(Assumptions!$B$3-Assumptions!$B$4),Assumptions!$B$5*DCF_Base!$L$20))/(1+0.11)^10-Assumptions!$B$8)/Assumptions!$B$9 | E16: =(SUMPRODUCT(DCF_Base!$C$20:$L$20/(1+0.12)^DCF_Base!$C$4:$L$4)+MAX(0,MIN(DCF_Base!$L$20*(1+Assumptions!$B$4)/(Assumptions!$B$3-Assumptions!$B$4),Assumptions!$B$5*DCF_Base!$L$20))/(1+0.12)^10-Assumptions!$B$8)/Assumptions!$B$9 | F16: =(SUMPRODUCT(DCF_Base!$C$20:$L$20/(1+0.15)^DCF_Base!$C$4:$L$4)+MAX(0,MIN(DCF_Base!$L$20*(1+Assumptions!$B$4)/(Assumptions!$B$3-Assumptions!$B$4),Assumptions!$B$5*DCF_Base!$L$20))/(1+0.15)^10-Assumptions!$B$8)/Assumptions!$B$9 | G16: =(SUMPRODUCT(DCF_Base!$C$20:$L$20/(1+0.175)^DCF_Base!$C$4:$L$4)+MAX(0,MIN(DCF_Base!$L$20*(1+Assumptions!$B$4)/(Assumptions!$B$3-Assumptions!$B$4),Assumptions!$B$5*DCF_Base!$L$20))/(1+0.175)^10-Assumptions!$B$8)/Assumptions!$B$9
A17: Read: today's NZ$0.24 implies ~18.5% required return on the base path — above the model's 17.5% WACC.
A20: 15%-hurdle entry prices (interim FCF + TV at WACC, discounted at hurdle; minus net debt)
A21: Bear | B21: =(SUMPRODUCT(DCF_Bear!$C$20:$L$20/(1+Assumptions!$B$11)^DCF_Bear!$C$4:$L$4)+MAX(0,MIN(DCF_Bear!$L$20*(1+Assumptions!$B$4)/(Assumptions!$B$3-Assumptions!$B$4),Assumptions!$B$5*DCF_Bear!$L$20))/(1+Assumptions!$B$11)^10-Assumptions!$B$8)/Assumptions!$B$9
A22: Base | B22: =(SUMPRODUCT(DCF_Base!$C$20:$L$20/(1+Assumptions!$B$11)^DCF_Base!$C$4:$L$4)+MAX(0,MIN(DCF_Base!$L$20*(1+Assumptions!$B$4)/(Assumptions!$B$3-Assumptions!$B$4),Assumptions!$B$5*DCF_Base!$L$20))/(1+Assumptions!$B$11)^10-Assumptions!$B$8)/Assumptions!$B$9
A23: Bull | B23: =(SUMPRODUCT(DCF_Bull!$C$20:$L$20/(1+Assumptions!$B$11)^DCF_Bull!$C$4:$L$4)+MAX(0,MIN(DCF_Bull!$L$20*(1+Assumptions!$B$4)/(Assumptions!$B$3-Assumptions!$B$4),Assumptions!$B$5*DCF_Bull!$L$20))/(1+Assumptions!$B$11)^10-Assumptions!$B$8)/Assumptions!$B$9
A24: Weighted entry price | B24: =SUMPRODUCT(B21:B23,D4:D6)
A25: NOTE: hurdle 15% < WACC 17.5%, so entry prices sit ABOVE IV. The binding buy-below price is the weighted IV (B8), not B24.
A28: Sensitivity: value per share, WACC (rows) x terminal growth (cols), base case
B29: 0.01 | C29: 0.015 | D29: 0.02 | E29: 0.025 | F29: 0.03
A30: 0.155 | B30: =IF($A30>B$29,(SUMPRODUCT(DCF_Base!$C$20:$L$20/(1+$A30)^DCF_Base!$C$4:$L$4)+MAX(0,MIN(DCF_Base!$L$20*(1+B$29)/($A30-B$29),Assumptions!$B$5*DCF_Base!$L$20))/(1+$A30)^10-Assumptions!$B$8)/Assumptions!$B$9,"n/a") | C30: =IF($A30>C$29,(SUMPRODUCT(DCF_Base!$C$20:$L$20/(1+$A30)^DCF_Base!$C$4:$L$4)+MAX(0,MIN(DCF_Base!$L$20*(1+C$29)/($A30-C$29),Assumptions!$B$5*DCF_Base!$L$20))/(1+$A30)^10-Assumptions!$B$8)/Assumptions!$B$9,"n/a") | D30: =IF($A30>D$29,(SUMPRODUCT(DCF_Base!$C$20:$L$20/(1+$A30)^DCF_Base!$C$4:$L$4)+MAX(0,MIN(DCF_Base!$L$20*(1+D$29)/($A30-D$29),Assumptions!$B$5*DCF_Base!$L$20))/(1+$A30)^10-Assumptions!$B$8)/Assumptions!$B$9,"n/a") | E30: =IF($A30>E$29,(SUMPRODUCT(DCF_Base!$C$20:$L$20/(1+$A30)^DCF_Base!$C$4:$L$4)+MAX(0,MIN(DCF_Base!$L$20*(1+E$29)/($A30-E$29),Assumptions!$B$5*DCF_Base!$L$20))/(1+$A30)^10-Assumptions!$B$8)/Assumptions!$B$9,"n/a") | F30: =IF($A30>F$29,(SUMPRODUCT(DCF_Base!$C$20:$L$20/(1+$A30)^DCF_Base!$C$4:$L$4)+MAX(0,MIN(DCF_Base!$L$20*(1+F$29)/($A30-F$29),Assumptions!$B$5*DCF_Base!$L$20))/(1+$A30)^10-Assumptions!$B$8)/Assumptions!$B$9,"n/a")
A31: 0.165 | B31: =IF($A31>B$29,(SUMPRODUCT(DCF_Base!$C$20:$L$20/(1+$A31)^DCF_Base!$C$4:$L$4)+MAX(0,MIN(DCF_Base!$L$20*(1+B$29)/($A31-B$29),Assumptions!$B$5*DCF_Base!$L$20))/(1+$A31)^10-Assumptions!$B$8)/Assumptions!$B$9,"n/a") | C31: =IF($A31>C$29,(SUMPRODUCT(DCF_Base!$C$20:$L$20/(1+$A31)^DCF_Base!$C$4:$L$4)+MAX(0,MIN(DCF_Base!$L$20*(1+C$29)/($A31-C$29),Assumptions!$B$5*DCF_Base!$L$20))/(1+$A31)^10-Assumptions!$B$8)/Assumptions!$B$9,"n/a") | D31: =IF($A31>D$29,(SUMPRODUCT(DCF_Base!$C$20:$L$20/(1+$A31)^DCF_Base!$C$4:$L$4)+MAX(0,MIN(DCF_Base!$L$20*(1+D$29)/($A31-D$29),Assumptions!$B$5*DCF_Base!$L$20))/(1+$A31)^10-Assumptions!$B$8)/Assumptions!$B$9,"n/a") | E31: =IF($A31>E$29,(SUMPRODUCT(DCF_Base!$C$20:$L$20/(1+$A31)^DCF_Base!$C$4:$L$4)+MAX(0,MIN(DCF_Base!$L$20*(1+E$29)/($A31-E$29),Assumptions!$B$5*DCF_Base!$L$20))/(1+$A31)^10-Assumptions!$B$8)/Assumptions!$B$9,"n/a") | F31: =IF($A31>F$29,(SUMPRODUCT(DCF_Base!$C$20:$L$20/(1+$A31)^DCF_Base!$C$4:$L$4)+MAX(0,MIN(DCF_Base!$L$20*(1+F$29)/($A31-F$29),Assumptions!$B$5*DCF_Base!$L$20))/(1+$A31)^10-Assumptions!$B$8)/Assumptions!$B$9,"n/a")
A32: 0.175 | B32: =IF($A32>B$29,(SUMPRODUCT(DCF_Base!$C$20:$L$20/(1+$A32)^DCF_Base!$C$4:$L$4)+MAX(0,MIN(DCF_Base!$L$20*(1+B$29)/($A32-B$29),Assumptions!$B$5*DCF_Base!$L$20))/(1+$A32)^10-Assumptions!$B$8)/Assumptions!$B$9,"n/a") | C32: =IF($A32>C$29,(SUMPRODUCT(DCF_Base!$C$20:$L$20/(1+$A32)^DCF_Base!$C$4:$L$4)+MAX(0,MIN(DCF_Base!$L$20*(1+C$29)/($A32-C$29),Assumptions!$B$5*DCF_Base!$L$20))/(1+$A32)^10-Assumptions!$B$8)/Assumptions!$B$9,"n/a") | D32: =IF($A32>D$29,(SUMPRODUCT(DCF_Base!$C$20:$L$20/(1+$A32)^DCF_Base!$C$4:$L$4)+MAX(0,MIN(DCF_Base!$L$20*(1+D$29)/($A32-D$29),Assumptions!$B$5*DCF_Base!$L$20))/(1+$A32)^10-Assumptions!$B$8)/Assumptions!$B$9,"n/a") | E32: =IF($A32>E$29,(SUMPRODUCT(DCF_Base!$C$20:$L$20/(1+$A32)^DCF_Base!$C$4:$L$4)+MAX(0,MIN(DCF_Base!$L$20*(1+E$29)/($A32-E$29),Assumptions!$B$5*DCF_Base!$L$20))/(1+$A32)^10-Assumptions!$B$8)/Assumptions!$B$9,"n/a") | F32: =IF($A32>F$29,(SUMPRODUCT(DCF_Base!$C$20:$L$20/(1+$A32)^DCF_Base!$C$4:$L$4)+MAX(0,MIN(DCF_Base!$L$20*(1+F$29)/($A32-F$29),Assumptions!$B$5*DCF_Base!$L$20))/(1+$A32)^10-Assumptions!$B$8)/Assumptions!$B$9,"n/a")
A33: 0.185 | B33: =IF($A33>B$29,(SUMPRODUCT(DCF_Base!$C$20:$L$20/(1+$A33)^DCF_Base!$C$4:$L$4)+MAX(0,MIN(DCF_Base!$L$20*(1+B$29)/($A33-B$29),Assumptions!$B$5*DCF_Base!$L$20))/(1+$A33)^10-Assumptions!$B$8)/Assumptions!$B$9,"n/a") | C33: =IF($A33>C$29,(SUMPRODUCT(DCF_Base!$C$20:$L$20/(1+$A33)^DCF_Base!$C$4:$L$4)+MAX(0,MIN(DCF_Base!$L$20*(1+C$29)/($A33-C$29),Assumptions!$B$5*DCF_Base!$L$20))/(1+$A33)^10-Assumptions!$B$8)/Assumptions!$B$9,"n/a") | D33: =IF($A33>D$29,(SUMPRODUCT(DCF_Base!$C$20:$L$20/(1+$A33)^DCF_Base!$C$4:$L$4)+MAX(0,MIN(DCF_Base!$L$20*(1+D$29)/($A33-D$29),Assumptions!$B$5*DCF_Base!$L$20))/(1+$A33)^10-Assumptions!$B$8)/Assumptions!$B$9,"n/a") | E33: =IF($A33>E$29,(SUMPRODUCT(DCF_Base!$C$20:$L$20/(1+$A33)^DCF_Base!$C$4:$L$4)+MAX(0,MIN(DCF_Base!$L$20*(1+E$29)/($A33-E$29),Assumptions!$B$5*DCF_Base!$L$20))/(1+$A33)^10-Assumptions!$B$8)/Assumptions!$B$9,"n/a") | F33: =IF($A33>F$29,(SUMPRODUCT(DCF_Base!$C$20:$L$20/(1+$A33)^DCF_Base!$C$4:$L$4)+MAX(0,MIN(DCF_Base!$L$20*(1+F$29)/($A33-F$29),Assumptions!$B$5*DCF_Base!$L$20))/(1+$A33)^10-Assumptions!$B$8)/Assumptions!$B$9,"n/a")
A34: 0.195 | B34: =IF($A34>B$29,(SUMPRODUCT(DCF_Base!$C$20:$L$20/(1+$A34)^DCF_Base!$C$4:$L$4)+MAX(0,MIN(DCF_Base!$L$20*(1+B$29)/($A34-B$29),Assumptions!$B$5*DCF_Base!$L$20))/(1+$A34)^10-Assumptions!$B$8)/Assumptions!$B$9,"n/a") | C34: =IF($A34>C$29,(SUMPRODUCT(DCF_Base!$C$20:$L$20/(1+$A34)^DCF_Base!$C$4:$L$4)+MAX(0,MIN(DCF_Base!$L$20*(1+C$29)/($A34-C$29),Assumptions!$B$5*DCF_Base!$L$20))/(1+$A34)^10-Assumptions!$B$8)/Assumptions!$B$9,"n/a") | D34: =IF($A34>D$29,(SUMPRODUCT(DCF_Base!$C$20:$L$20/(1+$A34)^DCF_Base!$C$4:$L$4)+MAX(0,MIN(DCF_Base!$L$20*(1+D$29)/($A34-D$29),Assumptions!$B$5*DCF_Base!$L$20))/(1+$A34)^10-Assumptions!$B$8)/Assumptions!$B$9,"n/a") | E34: =IF($A34>E$29,(SUMPRODUCT(DCF_Base!$C$20:$L$20/(1+$A34)^DCF_Base!$C$4:$L$4)+MAX(0,MIN(DCF_Base!$L$20*(1+E$29)/($A34-E$29),Assumptions!$B$5*DCF_Base!$L$20))/(1+$A34)^10-Assumptions!$B$8)/Assumptions!$B$9,"n/a") | F34: =IF($A34>F$29,(SUMPRODUCT(DCF_Base!$C$20:$L$20/(1+$A34)^DCF_Base!$C$4:$L$4)+MAX(0,MIN(DCF_Base!$L$20*(1+F$29)/($A34-F$29),Assumptions!$B$5*DCF_Base!$L$20))/(1+$A34)^10-Assumptions!$B$8)/Assumptions!$B$9,"n/a")
