Workbook

Sheet Model_Info
A1: Solution Dynamics (SDL.NZ) owner-FCF DCF workbook
A2: Version | B2: 2026-09-08 tier-2 refresh rebuild; supersedes the 2026-06-25 workbook (weighted IV NZ$1.539)
A3: Built by | B3: dcf-analyst agent (Claude), 2026-09-08, at the orchestrating agent's request; mirrors SDL.NZ_DCF.json
A4: Price | B4: NZ$0.625, Yahoo regularMarketPrice 2026-09-08T03:11Z (NZX regular session); cum the 4.0c dividend ex 10-Sep-2026
A5: Balance sheet | B5: 31-Dec-2025 (H1 FY2026 interim, parsed) rolled forward by ESTIMATE to 2026-09-08: net cash NZ$7.17m, shares 14.43m
A6: FY2026 result | B6: Revenue ~NZ$31.4m / NPAT ~NZ$0.38m from a third-party aggregator; annual report UNPARSED -- verify before relying on anything here
A7: Model | B7: Owner-FCF DCF + net cash, 5-year horizon (margins flat by FY2030-31), end-of-year discounting, TV = MAX(0, MIN(Gordon, 12x FCF5))
A8: Leases | B8: Treatment B: full lease cash cost (~NZ$0.83m/yr) charged in flows; lease liabilities excluded from net cash
A9: Interest income | B9: Stripped from flows (cash added back in bridge). SBC immaterial (NZ$21k FY2025): SBC rows kept at 0%, house = street
A10: WACC | B10: 17.5% NZD: 11.5% small-cap + 2.0% concentration + 2.0% illiquidity + 1.0% mail decline + 1.0% management transition
A11: Drivers | B11: Rows 5, 7, 9, 18 of each DCF tab (growth, IFRS-16 EBITDA margin, SBC %, capex) are the agent's 2026-09-08 judgment; tax rate row 15 is a formula (28% on positive EBIT)
A12: Entry price | B12: 15% hurdle with TV rebuilt at the hurdle; hurdle < WACC so entry > IV -- weighted IV is the operative buy-below
A13: Refresh after next print | B13: Parsed FY2026 closing cash + deposits, closing shares, FY2027 guidance, nGAGE site count, any water-entity contract
A14: Legend | B14: blue = hardcoded input, yellow fill = key lever, black = formula, green = cross-sheet link. Figures go stale.

Sheet Reconciliation
A1: Bridge from the 2026-06-25 model (approximate; live cells authoritative)
A3: Prior weighted IV (2026-06-25 model, price then NZ$0.58; re-based to NZ$0.625 on 2026-08-20) | B3: 1.54
A4: Anchor refresh: net cash 8.355 -> 7.17 (est.) and shares 14.682 -> 14.43 (buyback), old driver paths held | B4: -0.055
A5: WACC 17.0% -> 17.5% (management-transition premium 0.5% -> 1.0%) | B5: -0.033
A6: Driver re-judgment: normalized FCF rebuilt from components on the confirmed ~NZ$31m base (base terminal FCF 2.24 -> 1.23; bull 3.34 -> 2.45; bear 1.42 -> -0.32 with TV floored at 0) plus 12x TV cap policy | B6: -0.521
A7: Scenario weights 50/25/25 -> base 45 / bull 20 / bear 35 | B7: -0.071
A8: New weighted IV | B8: 0.861
A9: Live weighted IV (link) | B9: =Valuation!B7

Sheet Actuals
A1: Period | B1: Revenue | C1: EBITDA | D1: NetIncome | E1: OCF | F1: CapEx | G1: ReportedFCF | H1: LeasePrincipal | I1: LeaseInterest | J1: InterestIncome | K1: OwnerFCF | L1: Cash | M1: Shares
A2: FY2017 | B2: 19.991 | C2: 2.087 | D2: 1.31 | E2: 1.681 | F2: 0.206 | G2: 1.475 | H2: 0 | I2: 0 | J2: 0.015 | K2: =G2-H2-I2-J2 | L2: 2.08 | M2: 14.06
A3: FY2018 | B3: 22.732 | C3: 2.273 | D3: 1.332 | E3: 1.622 | F3: 0.188 | G3: 1.434 | H3: 0 | I3: 0 | J3: 0.006 | K3: =G3-H3-I3-J3 | L3: 1.956 | M3: 14.56
A4: FY2019 | B4: 25.155 | C4: 1.373 | D4: 0.67 | E4: 0.356 | F4: 0.386 | G4: -0.03 | H4: 0 | I4: 0 | J4: 0.005 | K4: =G4-H4-I4-J4 | L4: 1.182 | M4: 14.64
A5: FY2020 | B5: 34.03 | C5: 4.354 | D5: 1.866 | E5: 5.766 | F5: 0.222 | G5: 5.544 | H5: 0.85 | I5: 0.124 | J5: 0.004 | K5: =G5-H5-I5-J5 | L5: 5.012 | M5: 14.64
A6: FY2021 | B6: 35.445 | C6: 4.214 | D6: 2.034 | E6: 2.608 | F6: 0.749 | G6: 1.859 | H6: 0.85 | I6: 0.07 | J6: 0 | K6: =G6-H6-I6-J6 | L6: 4.713 | M6: 14.64
A7: FY2022 | B7: 40.127 | C7: 4.519 | D7: 2.563 | E7: 2.979 | F7: 0.154 | G7: 2.825 | H7: 0.816 | I7: 0.059 | J7: 0.004 | K7: =G7-H7-I7-J7 | L7: 5.009 | M7: 14.72
A8: FY2023 | B8: 40.385 | C8: 5.712 | D8: 3.425 | E8: 4.843 | F8: 0.275 | G8: 4.568 | H8: 0.871 | I8: 0.136 | J8: 0.118 | K8: =G8-H8-I8-J8 | L8: 6.628 | M8: 14.72
A9: FY2024 | B9: 38.668 | C9: 4.835 | D9: 2.819 | E9: 3.355 | F9: 0.081 | G9: 3.274 | H9: 0.825 | I9: 0.125 | J9: 0.25 | K9: =G9-H9-I9-J9 | L9: 7.95 | M9: 14.72
A10: FY2025 | B10: 41.324 | C10: 4.446 | D10: 2.619 | E10: 4.293 | F10: 0.065 | G10: 4.228 | H10: 0.731 | I10: 0.094 | J10: 0.217 | K10: =G10-H10-I10-J10 | L10: 11.193 | M10: 14.706
A11: H1 FY2026 | B11: 17.092 | C11: 0.69 | D11: 0.214 | E11: -0.766 | F11: 1.309 | G11: -2.075 | H11: 0.368 | I11: 0.045 | J11: 0.108 | K11: =G11-H11-I11-J11 | L11: 8.355 | M11: 14.682
A14: Source: SDL.NZ_Metrics.csv (parsed); lease/interest lines from the annual reports (FY2020-21 lease principal approximated). FY2026 full year is unparsed (aggregator: revenue ~31.4, NPAT ~0.38).

Sheet Assumptions
A1: Global inputs
A3: WACC | B3: 0.175
A4: Lease cash cost NZ$m/yr | B4: 0.83
A5: Non-ROU D&A NZ$m/yr | B5: 0.4
A6: Cash tax rate on positive EBIT | B6: 0.28
A7: WC capture on revenue change | B7: -0.03
A8: Net cash NZ$m (ESTIMATE 2026-09-08) | B8: 7.17
A9: Shares m (ESTIMATE) | B9: 14.43
A10: Price NZ$ | B10: 0.625
A11: TV cap multiple | B11: 12
A12: FY2026 revenue NZ$m (aggregator) | B12: 31.4
A13: Hurdle rate | B13: 0.15
A16: Scenario | B16: Terminal growth | C16: Probability
A17: bear | B17: 0.01 | C17: 0.35
A18: base | B18: 0.02 | C18: 0.45
A19: bull | B19: 0.03 | C19: 0.2
A20: Weights sum | C20: =SUM(C17:C19)
A22: Narratives
A23: Bear: attrition continues, IFRS-16 margin 3-3.5% ~ lease cost, owner FCF negative from FY2028, TV floors at zero -- residual is cash after burn.
A24: Base: ~NZ$31m base holds, margin 6% -> 9% as cost-out completes; no LWDW / nGAGE revenue credited. FCF 0.56 -> 1.23.
A25: Bull: water-entity billing wins + nGAGE scales + permanent CEO; growth from FY2028, margin to 12%; terminal FCF 2.45 still below the old base.

Sheet DCF_Bear
A1: Owner-FCF DCF -- bear (NZ$m)
A3: Year | B3: FY2026A(est) | C3: FY2027E | D3: FY2028E | E3: FY2029E | F3: FY2030E | G3: FY2031E
A4: Index | B4: 0 | C4: 1 | D4: 2 | E4: 3 | F4: 4 | G4: 5
A5: Revenue growth | C5: -0.08 | D5: -0.06 | E5: -0.04 | F5: -0.03 | G5: -0.02
A6: Revenue | B6: =Assumptions!$B$12 | C6: =B6*(1+C5) | D6: =C6*(1+D5) | E6: =D6*(1+E5) | F6: =E6*(1+F5) | G6: =F6*(1+G5)
A7: EBITDA margin (IFRS-16) | C7: 0.035 | D7: 0.03 | E7: 0.03 | F7: 0.03 | G7: 0.03
A8: EBITDA | C8: =C6*C7 | D8: =D6*D7 | E8: =E6*E7 | F8: =F6*F7 | G8: =G6*G7
A9: SBC % revenue | C9: 0 | D9: 0 | E9: 0 | F9: 0 | G9: 0
A10: SBC | C10: =-C6*C9 | D10: =-D6*D9 | E10: =-E6*E9 | F10: =-F6*F9 | G10: =-G6*G9
A11: Lease cash cost | C11: =-Assumptions!$B$4 | D11: =-Assumptions!$B$4 | E11: =-Assumptions!$B$4 | F11: =-Assumptions!$B$4 | G11: =-Assumptions!$B$4
A12: Owner EBITDA pre-IFRS16 | C12: =C8+C10+C11 | D12: =D8+D10+D11 | E12: =E8+E10+E11 | F12: =F8+F10+F11 | G12: =G8+G10+G11
A13: D&A (non-ROU) | C13: =-Assumptions!$B$5 | D13: =-Assumptions!$B$5 | E13: =-Assumptions!$B$5 | F13: =-Assumptions!$B$5 | G13: =-Assumptions!$B$5
A14: EBIT | C14: =C12+C13 | D14: =D12+D13 | E14: =E12+E13 | F14: =F12+F13 | G14: =G12+G13
A15: Cash tax rate | C15: =IF(C14>0,Assumptions!$B$6,0) | D15: =IF(D14>0,Assumptions!$B$6,0) | E15: =IF(E14>0,Assumptions!$B$6,0) | F15: =IF(F14>0,Assumptions!$B$6,0) | G15: =IF(G14>0,Assumptions!$B$6,0)
A16: NOPAT | C16: =C14*(1-C15) | D16: =D14*(1-D15) | E16: =E14*(1-E15) | F16: =F14*(1-F15) | G16: =G14*(1-G15)
A17: add back D&A | C17: =-C13 | D17: =-D13 | E17: =-E13 | F17: =-F13 | G17: =-G13
A18: Capex | C18: -0.25 | D18: -0.25 | E18: -0.25 | F18: -0.25 | G18: -0.25
A19: Working capital | C19: =Assumptions!$B$7*(C6-B6) | D19: =Assumptions!$B$7*(D6-C6) | E19: =Assumptions!$B$7*(E6-D6) | F19: =Assumptions!$B$7*(F6-E6) | G19: =Assumptions!$B$7*(G6-F6)
A20: Owner FCF | C20: =C16+C17+C18+C19 | D20: =D16+D17+D18+D19 | E20: =E16+E17+E18+E19 | F20: =F16+F17+F18+F19 | G20: =G16+G17+G18+G19
A21: Discount factor | C21: =1/(1+Assumptions!$B$3)^C4 | D21: =1/(1+Assumptions!$B$3)^D4 | E21: =1/(1+Assumptions!$B$3)^E4 | F21: =1/(1+Assumptions!$B$3)^F4 | G21: =1/(1+Assumptions!$B$3)^G4
A22: PV of FCF | C22: =C20*C21 | D22: =D20*D21 | E22: =E20*E21 | F22: =F20*F21 | G22: =G20*G21
A24: Memo: owner FCF margin | C24: =C20/C6 | D24: =D20/D6 | E24: =E20/E6 | F24: =F20/F6 | G24: =G20/G6
A26: Sum of PV (explicit) | B26: =SUM(C22:G22)
A27: Terminal growth | B27: =Assumptions!$B$17
A28: Terminal FCF (FY2031 x (1+g)) | B28: =G20*(1+B27)
A29: Gordon TV | B29: =B28/(Assumptions!$B$3-B27)
A30: Cap TV | B30: =Assumptions!$B$11*G20
A31: TV used = MAX(0,MIN(Gordon,Cap)) | B31: =MAX(0,MIN(B29,B30))
A32: Implied exit multiple | B32: =IF(G20>0,B31/G20,"n/a")
A33: PV of TV | B33: =B31*G21
A34: Enterprise value | B34: =B26+B33
A35: add net cash | B35: =Assumptions!$B$8
A36: Equity value | B36: =B34+B35
A37: Shares (m) | B37: =Assumptions!$B$9
A38: Value per share NZ$ | B38: =B36/B37
A39: Upside vs price | B39: =B38/Assumptions!$B$10-1
A41: Street memo: SBC is 0% so street value = house value
B43: =B38

Sheet DCF_Base
A1: Owner-FCF DCF -- base (NZ$m)
A3: Year | B3: FY2026A(est) | C3: FY2027E | D3: FY2028E | E3: FY2029E | F3: FY2030E | G3: FY2031E
A4: Index | B4: 0 | C4: 1 | D4: 2 | E4: 3 | F4: 4 | G4: 5
A5: Revenue growth | C5: -0.038 | D5: -0.01 | E5: 0.01 | F5: 0.02 | G5: 0.02
A6: Revenue | B6: =Assumptions!$B$12 | C6: =B6*(1+C5) | D6: =C6*(1+D5) | E6: =D6*(1+E5) | F6: =E6*(1+F5) | G6: =F6*(1+G5)
A7: EBITDA margin (IFRS-16) | C7: 0.06 | D7: 0.075 | E7: 0.085 | F7: 0.09 | G7: 0.09
A8: EBITDA | C8: =C6*C7 | D8: =D6*D7 | E8: =E6*E7 | F8: =F6*F7 | G8: =G6*G7
A9: SBC % revenue | C9: 0 | D9: 0 | E9: 0 | F9: 0 | G9: 0
A10: SBC | C10: =-C6*C9 | D10: =-D6*D9 | E10: =-E6*E9 | F10: =-F6*F9 | G10: =-G6*G9
A11: Lease cash cost | C11: =-Assumptions!$B$4 | D11: =-Assumptions!$B$4 | E11: =-Assumptions!$B$4 | F11: =-Assumptions!$B$4 | G11: =-Assumptions!$B$4
A12: Owner EBITDA pre-IFRS16 | C12: =C8+C10+C11 | D12: =D8+D10+D11 | E12: =E8+E10+E11 | F12: =F8+F10+F11 | G12: =G8+G10+G11
A13: D&A (non-ROU) | C13: =-Assumptions!$B$5 | D13: =-Assumptions!$B$5 | E13: =-Assumptions!$B$5 | F13: =-Assumptions!$B$5 | G13: =-Assumptions!$B$5
A14: EBIT | C14: =C12+C13 | D14: =D12+D13 | E14: =E12+E13 | F14: =F12+F13 | G14: =G12+G13
A15: Cash tax rate | C15: =IF(C14>0,Assumptions!$B$6,0) | D15: =IF(D14>0,Assumptions!$B$6,0) | E15: =IF(E14>0,Assumptions!$B$6,0) | F15: =IF(F14>0,Assumptions!$B$6,0) | G15: =IF(G14>0,Assumptions!$B$6,0)
A16: NOPAT | C16: =C14*(1-C15) | D16: =D14*(1-D15) | E16: =E14*(1-E15) | F16: =F14*(1-F15) | G16: =G14*(1-G15)
A17: add back D&A | C17: =-C13 | D17: =-D13 | E17: =-E13 | F17: =-F13 | G17: =-G13
A18: Capex | C18: -0.3 | D18: -0.3 | E18: -0.3 | F18: -0.3 | G18: -0.3
A19: Working capital | C19: =Assumptions!$B$7*(C6-B6) | D19: =Assumptions!$B$7*(D6-C6) | E19: =Assumptions!$B$7*(E6-D6) | F19: =Assumptions!$B$7*(F6-E6) | G19: =Assumptions!$B$7*(G6-F6)
A20: Owner FCF | C20: =C16+C17+C18+C19 | D20: =D16+D17+D18+D19 | E20: =E16+E17+E18+E19 | F20: =F16+F17+F18+F19 | G20: =G16+G17+G18+G19
A21: Discount factor | C21: =1/(1+Assumptions!$B$3)^C4 | D21: =1/(1+Assumptions!$B$3)^D4 | E21: =1/(1+Assumptions!$B$3)^E4 | F21: =1/(1+Assumptions!$B$3)^F4 | G21: =1/(1+Assumptions!$B$3)^G4
A22: PV of FCF | C22: =C20*C21 | D22: =D20*D21 | E22: =E20*E21 | F22: =F20*F21 | G22: =G20*G21
A24: Memo: owner FCF margin | C24: =C20/C6 | D24: =D20/D6 | E24: =E20/E6 | F24: =F20/F6 | G24: =G20/G6
A26: Sum of PV (explicit) | B26: =SUM(C22:G22)
A27: Terminal growth | B27: =Assumptions!$B$18
A28: Terminal FCF (FY2031 x (1+g)) | B28: =G20*(1+B27)
A29: Gordon TV | B29: =B28/(Assumptions!$B$3-B27)
A30: Cap TV | B30: =Assumptions!$B$11*G20
A31: TV used = MAX(0,MIN(Gordon,Cap)) | B31: =MAX(0,MIN(B29,B30))
A32: Implied exit multiple | B32: =IF(G20>0,B31/G20,"n/a")
A33: PV of TV | B33: =B31*G21
A34: Enterprise value | B34: =B26+B33
A35: add net cash | B35: =Assumptions!$B$8
A36: Equity value | B36: =B34+B35
A37: Shares (m) | B37: =Assumptions!$B$9
A38: Value per share NZ$ | B38: =B36/B37
A39: Upside vs price | B39: =B38/Assumptions!$B$10-1
A41: Street memo: SBC is 0% so street value = house value
B43: =B38

Sheet DCF_Bull
A1: Owner-FCF DCF -- bull (NZ$m)
A3: Year | B3: FY2026A(est) | C3: FY2027E | D3: FY2028E | E3: FY2029E | F3: FY2030E | G3: FY2031E
A4: Index | B4: 0 | C4: 1 | D4: 2 | E4: 3 | F4: 4 | G4: 5
A5: Revenue growth | C5: 0 | D5: 0.05 | E5: 0.07 | F5: 0.06 | G5: 0.05
A6: Revenue | B6: =Assumptions!$B$12 | C6: =B6*(1+C5) | D6: =C6*(1+D5) | E6: =D6*(1+E5) | F6: =E6*(1+F5) | G6: =F6*(1+G5)
A7: EBITDA margin (IFRS-16) | C7: 0.07 | D7: 0.09 | E7: 0.105 | F7: 0.115 | G7: 0.12
A8: EBITDA | C8: =C6*C7 | D8: =D6*D7 | E8: =E6*E7 | F8: =F6*F7 | G8: =G6*G7
A9: SBC % revenue | C9: 0 | D9: 0 | E9: 0 | F9: 0 | G9: 0
A10: SBC | C10: =-C6*C9 | D10: =-D6*D9 | E10: =-E6*E9 | F10: =-F6*F9 | G10: =-G6*G9
A11: Lease cash cost | C11: =-Assumptions!$B$4 | D11: =-Assumptions!$B$4 | E11: =-Assumptions!$B$4 | F11: =-Assumptions!$B$4 | G11: =-Assumptions!$B$4
A12: Owner EBITDA pre-IFRS16 | C12: =C8+C10+C11 | D12: =D8+D10+D11 | E12: =E8+E10+E11 | F12: =F8+F10+F11 | G12: =G8+G10+G11
A13: D&A (non-ROU) | C13: =-Assumptions!$B$5 | D13: =-Assumptions!$B$5 | E13: =-Assumptions!$B$5 | F13: =-Assumptions!$B$5 | G13: =-Assumptions!$B$5
A14: EBIT | C14: =C12+C13 | D14: =D12+D13 | E14: =E12+E13 | F14: =F12+F13 | G14: =G12+G13
A15: Cash tax rate | C15: =IF(C14>0,Assumptions!$B$6,0) | D15: =IF(D14>0,Assumptions!$B$6,0) | E15: =IF(E14>0,Assumptions!$B$6,0) | F15: =IF(F14>0,Assumptions!$B$6,0) | G15: =IF(G14>0,Assumptions!$B$6,0)
A16: NOPAT | C16: =C14*(1-C15) | D16: =D14*(1-D15) | E16: =E14*(1-E15) | F16: =F14*(1-F15) | G16: =G14*(1-G15)
A17: add back D&A | C17: =-C13 | D17: =-D13 | E17: =-E13 | F17: =-F13 | G17: =-G13
A18: Capex | C18: -0.3 | D18: -0.35 | E18: -0.4 | F18: -0.4 | G18: -0.4
A19: Working capital | C19: =Assumptions!$B$7*(C6-B6) | D19: =Assumptions!$B$7*(D6-C6) | E19: =Assumptions!$B$7*(E6-D6) | F19: =Assumptions!$B$7*(F6-E6) | G19: =Assumptions!$B$7*(G6-F6)
A20: Owner FCF | C20: =C16+C17+C18+C19 | D20: =D16+D17+D18+D19 | E20: =E16+E17+E18+E19 | F20: =F16+F17+F18+F19 | G20: =G16+G17+G18+G19
A21: Discount factor | C21: =1/(1+Assumptions!$B$3)^C4 | D21: =1/(1+Assumptions!$B$3)^D4 | E21: =1/(1+Assumptions!$B$3)^E4 | F21: =1/(1+Assumptions!$B$3)^F4 | G21: =1/(1+Assumptions!$B$3)^G4
A22: PV of FCF | C22: =C20*C21 | D22: =D20*D21 | E22: =E20*E21 | F22: =F20*F21 | G22: =G20*G21
A24: Memo: owner FCF margin | C24: =C20/C6 | D24: =D20/D6 | E24: =E20/E6 | F24: =F20/F6 | G24: =G20/G6
A26: Sum of PV (explicit) | B26: =SUM(C22:G22)
A27: Terminal growth | B27: =Assumptions!$B$19
A28: Terminal FCF (FY2031 x (1+g)) | B28: =G20*(1+B27)
A29: Gordon TV | B29: =B28/(Assumptions!$B$3-B27)
A30: Cap TV | B30: =Assumptions!$B$11*G20
A31: TV used = MAX(0,MIN(Gordon,Cap)) | B31: =MAX(0,MIN(B29,B30))
A32: Implied exit multiple | B32: =IF(G20>0,B31/G20,"n/a")
A33: PV of TV | B33: =B31*G21
A34: Enterprise value | B34: =B26+B33
A35: add net cash | B35: =Assumptions!$B$8
A36: Equity value | B36: =B34+B35
A37: Shares (m) | B37: =Assumptions!$B$9
A38: Value per share NZ$ | B38: =B36/B37
A39: Upside vs price | B39: =B38/Assumptions!$B$10-1
A41: Street memo: SBC is 0% so street value = house value
B43: =B38

Sheet Valuation
A1: Valuation summary (NZ$ per share)
A3: Scenario | B3: Value/share | C3: Upside | D3: Weight | E3: Entry @ hurdle
A4: bear | B4: =DCF_Bear!B38 | C4: =B4/Assumptions!$B$10-1 | D4: =Assumptions!$C$17 | E4: =(SUMPRODUCT(DCF_Bear!$C$20:$G$20/(1+Assumptions!$B$13)^DCF_Bear!$C$4:$G$4)+MAX(0,MIN(DCF_Bear!$G$20*(1+Assumptions!$B$17)/(Assumptions!$B$13-Assumptions!$B$17),Assumptions!$B$11*DCF_Bear!$G$20))/(1+Assumptions!$B$13)^5+Assumptions!$B$8)/Assumptions!$B$9
A5: base | B5: =DCF_Base!B38 | C5: =B5/Assumptions!$B$10-1 | D5: =Assumptions!$C$18 | E5: =(SUMPRODUCT(DCF_Base!$C$20:$G$20/(1+Assumptions!$B$13)^DCF_Base!$C$4:$G$4)+MAX(0,MIN(DCF_Base!$G$20*(1+Assumptions!$B$18)/(Assumptions!$B$13-Assumptions!$B$18),Assumptions!$B$11*DCF_Base!$G$20))/(1+Assumptions!$B$13)^5+Assumptions!$B$8)/Assumptions!$B$9
A6: bull | B6: =DCF_Bull!B38 | C6: =B6/Assumptions!$B$10-1 | D6: =Assumptions!$C$19 | E6: =(SUMPRODUCT(DCF_Bull!$C$20:$G$20/(1+Assumptions!$B$13)^DCF_Bull!$C$4:$G$4)+MAX(0,MIN(DCF_Bull!$G$20*(1+Assumptions!$B$19)/(Assumptions!$B$13-Assumptions!$B$19),Assumptions!$B$11*DCF_Bull!$G$20))/(1+Assumptions!$B$13)^5+Assumptions!$B$8)/Assumptions!$B$9
A7: Probability-weighted IV | B7: =SUMPRODUCT(B4:B6,D4:D6)
A8: Weighted upside | B8: =B7/Assumptions!$B$10-1
A9: Weighted entry price @ hurdle | B9: =SUMPRODUCT(E4:E6,D4:D6)
A10: Net cash per share | B10: =Assumptions!$B$8/Assumptions!$B$9
A11: Operating business per share (weighted) | B11: =B7-B10
A13: Required-return table (base)
A14: Required return | B14: 0.09 | C14: 0.1 | D14: 0.11 | E14: 0.12 | F14: 0.15 | G14: 0.175
A15: Value/share | B15: =(SUMPRODUCT(DCF_Base!$C$20:$G$20/(1+B$14)^DCF_Base!$C$4:$G$4)+MAX(0,MIN(DCF_Base!$G$20*(1+Assumptions!$B$18)/(B$14-Assumptions!$B$18),Assumptions!$B$11*DCF_Base!$G$20))/(1+B$14)^5+Assumptions!$B$8)/Assumptions!$B$9 | C15: =(SUMPRODUCT(DCF_Base!$C$20:$G$20/(1+C$14)^DCF_Base!$C$4:$G$4)+MAX(0,MIN(DCF_Base!$G$20*(1+Assumptions!$B$18)/(C$14-Assumptions!$B$18),Assumptions!$B$11*DCF_Base!$G$20))/(1+C$14)^5+Assumptions!$B$8)/Assumptions!$B$9 | D15: =(SUMPRODUCT(DCF_Base!$C$20:$G$20/(1+D$14)^DCF_Base!$C$4:$G$4)+MAX(0,MIN(DCF_Base!$G$20*(1+Assumptions!$B$18)/(D$14-Assumptions!$B$18),Assumptions!$B$11*DCF_Base!$G$20))/(1+D$14)^5+Assumptions!$B$8)/Assumptions!$B$9 | E15: =(SUMPRODUCT(DCF_Base!$C$20:$G$20/(1+E$14)^DCF_Base!$C$4:$G$4)+MAX(0,MIN(DCF_Base!$G$20*(1+Assumptions!$B$18)/(E$14-Assumptions!$B$18),Assumptions!$B$11*DCF_Base!$G$20))/(1+E$14)^5+Assumptions!$B$8)/Assumptions!$B$9 | F15: =(SUMPRODUCT(DCF_Base!$C$20:$G$20/(1+F$14)^DCF_Base!$C$4:$G$4)+MAX(0,MIN(DCF_Base!$G$20*(1+Assumptions!$B$18)/(F$14-Assumptions!$B$18),Assumptions!$B$11*DCF_Base!$G$20))/(1+F$14)^5+Assumptions!$B$8)/Assumptions!$B$9 | G15: =(SUMPRODUCT(DCF_Base!$C$20:$G$20/(1+G$14)^DCF_Base!$C$4:$G$4)+MAX(0,MIN(DCF_Base!$G$20*(1+Assumptions!$B$18)/(G$14-Assumptions!$B$18),Assumptions!$B$11*DCF_Base!$G$20))/(1+G$14)^5+Assumptions!$B$8)/Assumptions!$B$9
A17: Sensitivity (base): WACC down, terminal g across
B18: 0.01 | C18: 0.015 | D18: 0.02 | E18: 0.025 | F18: 0.03
A19: 0.155 | B19: =IF($A19>B$18,(SUMPRODUCT(DCF_Base!$C$20:$G$20/(1+$A19)^DCF_Base!$C$4:$G$4)+MAX(0,MIN(DCF_Base!$G$20*(1+B$18)/($A19-B$18),Assumptions!$B$11*DCF_Base!$G$20))/(1+$A19)^5+Assumptions!$B$8)/Assumptions!$B$9,"n/a") | C19: =IF($A19>C$18,(SUMPRODUCT(DCF_Base!$C$20:$G$20/(1+$A19)^DCF_Base!$C$4:$G$4)+MAX(0,MIN(DCF_Base!$G$20*(1+C$18)/($A19-C$18),Assumptions!$B$11*DCF_Base!$G$20))/(1+$A19)^5+Assumptions!$B$8)/Assumptions!$B$9,"n/a") | D19: =IF($A19>D$18,(SUMPRODUCT(DCF_Base!$C$20:$G$20/(1+$A19)^DCF_Base!$C$4:$G$4)+MAX(0,MIN(DCF_Base!$G$20*(1+D$18)/($A19-D$18),Assumptions!$B$11*DCF_Base!$G$20))/(1+$A19)^5+Assumptions!$B$8)/Assumptions!$B$9,"n/a") | E19: =IF($A19>E$18,(SUMPRODUCT(DCF_Base!$C$20:$G$20/(1+$A19)^DCF_Base!$C$4:$G$4)+MAX(0,MIN(DCF_Base!$G$20*(1+E$18)/($A19-E$18),Assumptions!$B$11*DCF_Base!$G$20))/(1+$A19)^5+Assumptions!$B$8)/Assumptions!$B$9,"n/a") | F19: =IF($A19>F$18,(SUMPRODUCT(DCF_Base!$C$20:$G$20/(1+$A19)^DCF_Base!$C$4:$G$4)+MAX(0,MIN(DCF_Base!$G$20*(1+F$18)/($A19-F$18),Assumptions!$B$11*DCF_Base!$G$20))/(1+$A19)^5+Assumptions!$B$8)/Assumptions!$B$9,"n/a")
A20: 0.165 | B20: =IF($A20>B$18,(SUMPRODUCT(DCF_Base!$C$20:$G$20/(1+$A20)^DCF_Base!$C$4:$G$4)+MAX(0,MIN(DCF_Base!$G$20*(1+B$18)/($A20-B$18),Assumptions!$B$11*DCF_Base!$G$20))/(1+$A20)^5+Assumptions!$B$8)/Assumptions!$B$9,"n/a") | C20: =IF($A20>C$18,(SUMPRODUCT(DCF_Base!$C$20:$G$20/(1+$A20)^DCF_Base!$C$4:$G$4)+MAX(0,MIN(DCF_Base!$G$20*(1+C$18)/($A20-C$18),Assumptions!$B$11*DCF_Base!$G$20))/(1+$A20)^5+Assumptions!$B$8)/Assumptions!$B$9,"n/a") | D20: =IF($A20>D$18,(SUMPRODUCT(DCF_Base!$C$20:$G$20/(1+$A20)^DCF_Base!$C$4:$G$4)+MAX(0,MIN(DCF_Base!$G$20*(1+D$18)/($A20-D$18),Assumptions!$B$11*DCF_Base!$G$20))/(1+$A20)^5+Assumptions!$B$8)/Assumptions!$B$9,"n/a") | E20: =IF($A20>E$18,(SUMPRODUCT(DCF_Base!$C$20:$G$20/(1+$A20)^DCF_Base!$C$4:$G$4)+MAX(0,MIN(DCF_Base!$G$20*(1+E$18)/($A20-E$18),Assumptions!$B$11*DCF_Base!$G$20))/(1+$A20)^5+Assumptions!$B$8)/Assumptions!$B$9,"n/a") | F20: =IF($A20>F$18,(SUMPRODUCT(DCF_Base!$C$20:$G$20/(1+$A20)^DCF_Base!$C$4:$G$4)+MAX(0,MIN(DCF_Base!$G$20*(1+F$18)/($A20-F$18),Assumptions!$B$11*DCF_Base!$G$20))/(1+$A20)^5+Assumptions!$B$8)/Assumptions!$B$9,"n/a")
A21: 0.175 | B21: =IF($A21>B$18,(SUMPRODUCT(DCF_Base!$C$20:$G$20/(1+$A21)^DCF_Base!$C$4:$G$4)+MAX(0,MIN(DCF_Base!$G$20*(1+B$18)/($A21-B$18),Assumptions!$B$11*DCF_Base!$G$20))/(1+$A21)^5+Assumptions!$B$8)/Assumptions!$B$9,"n/a") | C21: =IF($A21>C$18,(SUMPRODUCT(DCF_Base!$C$20:$G$20/(1+$A21)^DCF_Base!$C$4:$G$4)+MAX(0,MIN(DCF_Base!$G$20*(1+C$18)/($A21-C$18),Assumptions!$B$11*DCF_Base!$G$20))/(1+$A21)^5+Assumptions!$B$8)/Assumptions!$B$9,"n/a") | D21: =IF($A21>D$18,(SUMPRODUCT(DCF_Base!$C$20:$G$20/(1+$A21)^DCF_Base!$C$4:$G$4)+MAX(0,MIN(DCF_Base!$G$20*(1+D$18)/($A21-D$18),Assumptions!$B$11*DCF_Base!$G$20))/(1+$A21)^5+Assumptions!$B$8)/Assumptions!$B$9,"n/a") | E21: =IF($A21>E$18,(SUMPRODUCT(DCF_Base!$C$20:$G$20/(1+$A21)^DCF_Base!$C$4:$G$4)+MAX(0,MIN(DCF_Base!$G$20*(1+E$18)/($A21-E$18),Assumptions!$B$11*DCF_Base!$G$20))/(1+$A21)^5+Assumptions!$B$8)/Assumptions!$B$9,"n/a") | F21: =IF($A21>F$18,(SUMPRODUCT(DCF_Base!$C$20:$G$20/(1+$A21)^DCF_Base!$C$4:$G$4)+MAX(0,MIN(DCF_Base!$G$20*(1+F$18)/($A21-F$18),Assumptions!$B$11*DCF_Base!$G$20))/(1+$A21)^5+Assumptions!$B$8)/Assumptions!$B$9,"n/a")
A22: 0.185 | B22: =IF($A22>B$18,(SUMPRODUCT(DCF_Base!$C$20:$G$20/(1+$A22)^DCF_Base!$C$4:$G$4)+MAX(0,MIN(DCF_Base!$G$20*(1+B$18)/($A22-B$18),Assumptions!$B$11*DCF_Base!$G$20))/(1+$A22)^5+Assumptions!$B$8)/Assumptions!$B$9,"n/a") | C22: =IF($A22>C$18,(SUMPRODUCT(DCF_Base!$C$20:$G$20/(1+$A22)^DCF_Base!$C$4:$G$4)+MAX(0,MIN(DCF_Base!$G$20*(1+C$18)/($A22-C$18),Assumptions!$B$11*DCF_Base!$G$20))/(1+$A22)^5+Assumptions!$B$8)/Assumptions!$B$9,"n/a") | D22: =IF($A22>D$18,(SUMPRODUCT(DCF_Base!$C$20:$G$20/(1+$A22)^DCF_Base!$C$4:$G$4)+MAX(0,MIN(DCF_Base!$G$20*(1+D$18)/($A22-D$18),Assumptions!$B$11*DCF_Base!$G$20))/(1+$A22)^5+Assumptions!$B$8)/Assumptions!$B$9,"n/a") | E22: =IF($A22>E$18,(SUMPRODUCT(DCF_Base!$C$20:$G$20/(1+$A22)^DCF_Base!$C$4:$G$4)+MAX(0,MIN(DCF_Base!$G$20*(1+E$18)/($A22-E$18),Assumptions!$B$11*DCF_Base!$G$20))/(1+$A22)^5+Assumptions!$B$8)/Assumptions!$B$9,"n/a") | F22: =IF($A22>F$18,(SUMPRODUCT(DCF_Base!$C$20:$G$20/(1+$A22)^DCF_Base!$C$4:$G$4)+MAX(0,MIN(DCF_Base!$G$20*(1+F$18)/($A22-F$18),Assumptions!$B$11*DCF_Base!$G$20))/(1+$A22)^5+Assumptions!$B$8)/Assumptions!$B$9,"n/a")
A23: 0.195 | B23: =IF($A23>B$18,(SUMPRODUCT(DCF_Base!$C$20:$G$20/(1+$A23)^DCF_Base!$C$4:$G$4)+MAX(0,MIN(DCF_Base!$G$20*(1+B$18)/($A23-B$18),Assumptions!$B$11*DCF_Base!$G$20))/(1+$A23)^5+Assumptions!$B$8)/Assumptions!$B$9,"n/a") | C23: =IF($A23>C$18,(SUMPRODUCT(DCF_Base!$C$20:$G$20/(1+$A23)^DCF_Base!$C$4:$G$4)+MAX(0,MIN(DCF_Base!$G$20*(1+C$18)/($A23-C$18),Assumptions!$B$11*DCF_Base!$G$20))/(1+$A23)^5+Assumptions!$B$8)/Assumptions!$B$9,"n/a") | D23: =IF($A23>D$18,(SUMPRODUCT(DCF_Base!$C$20:$G$20/(1+$A23)^DCF_Base!$C$4:$G$4)+MAX(0,MIN(DCF_Base!$G$20*(1+D$18)/($A23-D$18),Assumptions!$B$11*DCF_Base!$G$20))/(1+$A23)^5+Assumptions!$B$8)/Assumptions!$B$9,"n/a") | E23: =IF($A23>E$18,(SUMPRODUCT(DCF_Base!$C$20:$G$20/(1+$A23)^DCF_Base!$C$4:$G$4)+MAX(0,MIN(DCF_Base!$G$20*(1+E$18)/($A23-E$18),Assumptions!$B$11*DCF_Base!$G$20))/(1+$A23)^5+Assumptions!$B$8)/Assumptions!$B$9,"n/a") | F23: =IF($A23>F$18,(SUMPRODUCT(DCF_Base!$C$20:$G$20/(1+$A23)^DCF_Base!$C$4:$G$4)+MAX(0,MIN(DCF_Base!$G$20*(1+F$18)/($A23-F$18),Assumptions!$B$11*DCF_Base!$G$20))/(1+$A23)^5+Assumptions!$B$8)/Assumptions!$B$9,"n/a")
