Workbook

Sheet DCF Model
A1: PYPL DCF Valuation Model
A2: Gray cells are INPUTS - adjust to see valuation change
A4: KEY INPUTS
A5: Current Stock Price | B5: 41
A6: Shares Outstanding (M) | B6: 1039
A7: Cash & Equivalents (M) | B7: 6561
A8: Total Debt (M) | B8: 9879
A9: Net Debt (M) | B9: =B8-B7 -> 0
A10: Base Year FCF (M) | B10: 6767
A12: WACC | B12: 0.1
A13: Terminal Growth Rate | B13: 0.03
A15: GROWTH ASSUMPTIONS | B15: Year 1 | C15: Year 2 | D15: Year 3 | E15: Year 4 | F15: Year 5
A16: FCF Growth Rate | B16: 0.06 | C16: 0.055 | D16: 0.05 | E16: 0.045 | F16: 0.04
A18: PROJECTIONS
B19: Base | C19: Year 1 | D19: Year 2 | E19: Year 3 | F19: Year 4 | G19: Year 5
A20: Free Cash Flow | B20: =B10 -> 0 | C20: =B20*(1+B16) -> 0 | D20: =C20*(1+C16) -> 0 | E20: =D20*(1+D16) -> 0 | F20: =E20*(1+E16) -> 0 | G20: =F20*(1+F16) -> 0
A21: Discount Factor | C21: =1/(1+$B$12)^1 -> 0 | D21: =1/(1+$B$12)^2 -> 0 | E21: =1/(1+$B$12)^3 -> 0 | F21: =1/(1+$B$12)^4 -> 0 | G21: =1/(1+$B$12)^5 -> 0
A22: PV of FCF | C22: =C20*C21 -> 0 | D22: =D20*D21 -> 0 | E22: =E20*E21 -> 0 | F22: =F20*F21 -> 0 | G22: =G20*G21 -> 0
A24: VALUATION
A25: Sum of PV of FCF | B25: =SUM(C22:G22) -> 0
A26: Terminal FCF (Year 5 * (1+g)) | B26: =G20*(1+$B$13) -> 0
A27: Terminal Value | B27: =B26/($B$12-$B$13) -> 0
A28: PV of Terminal Value | B28: =B27*G21 -> 0
A29: Enterprise Value | B29: =B25+B28 -> 0
A30: Less: Net Debt | B30: =B9 -> 0
A31: Equity Value | B31: =B29-B30 -> 0
A32: INTRINSIC VALUE/SHARE | B32: =B31/B6 -> 0
A34: ENTRY PRICE (15% CAGR Target)
A35: Terminal Value per Share | B35: =B27/B6 -> 0
A36: Entry Price (15% CAGR) | B36: =B35/(1.15^5) -> 0
A38: Upside to IV | B38: =(B32-B5)/B5 -> 0
A39: Upside to Entry Price | B39: =(B5-B36)/B5 -> 0

Sheet Sensitivity
A1: Sensitivity Analysis
A2: Intrinsic Value by WACC & Terminal Growth
A4: WACC \ Term G | B4: 0.02 | C4: 0.025 | D4: 0.03 | E4: 0.035 | F4: 0.04
A5: 0.08 | B5: =('DCF Model'!$B$10*(1+'DCF Model'!$B$16)*(1+'DCF Model'!$C$16)*(1+'DCF Model'!$D$16)*(1+'DCF Model'!$E$16)*(1+'DCF Model'!$F$16)*(1+0.02)/(0.08-0.02))/(1+0.08)^5/'DCF Model'!$B$6 -> 0 | C5: =('DCF Model'!$B$10*(1+'DCF Model'!$B$16)*(1+'DCF Model'!$C$16)*(1+'DCF Model'!$D$16)*(1+'DCF Model'!$E$16)*(1+'DCF Model'!$F$16)*(1+0.025)/(0.08-0.025))/(1+0.08)^5/'DCF Model'!$B$6 -> 0 | D5: =('DCF Model'!$B$10*(1+'DCF Model'!$B$16)*(1+'DCF Model'!$C$16)*(1+'DCF Model'!$D$16)*(1+'DCF Model'!$E$16)*(1+'DCF Model'!$F$16)*(1+0.03)/(0.08-0.03))/(1+0.08)^5/'DCF Model'!$B$6 -> 0 | E5: =('DCF Model'!$B$10*(1+'DCF Model'!$B$16)*(1+'DCF Model'!$C$16)*(1+'DCF Model'!$D$16)*(1+'DCF Model'!$E$16)*(1+'DCF Model'!$F$16)*(1+0.035)/(0.08-0.035))/(1+0.08)^5/'DCF Model'!$B$6 -> 0 | F5: =('DCF Model'!$B$10*(1+'DCF Model'!$B$16)*(1+'DCF Model'!$C$16)*(1+'DCF Model'!$D$16)*(1+'DCF Model'!$E$16)*(1+'DCF Model'!$F$16)*(1+0.04)/(0.08-0.04))/(1+0.08)^5/'DCF Model'!$B$6 -> 0
A6: 0.09 | B6: =('DCF Model'!$B$10*(1+'DCF Model'!$B$16)*(1+'DCF Model'!$C$16)*(1+'DCF Model'!$D$16)*(1+'DCF Model'!$E$16)*(1+'DCF Model'!$F$16)*(1+0.02)/(0.09-0.02))/(1+0.09)^5/'DCF Model'!$B$6 -> 0 | C6: =('DCF Model'!$B$10*(1+'DCF Model'!$B$16)*(1+'DCF Model'!$C$16)*(1+'DCF Model'!$D$16)*(1+'DCF Model'!$E$16)*(1+'DCF Model'!$F$16)*(1+0.025)/(0.09-0.025))/(1+0.09)^5/'DCF Model'!$B$6 -> 0 | D6: =('DCF Model'!$B$10*(1+'DCF Model'!$B$16)*(1+'DCF Model'!$C$16)*(1+'DCF Model'!$D$16)*(1+'DCF Model'!$E$16)*(1+'DCF Model'!$F$16)*(1+0.03)/(0.09-0.03))/(1+0.09)^5/'DCF Model'!$B$6 -> 0 | E6: =('DCF Model'!$B$10*(1+'DCF Model'!$B$16)*(1+'DCF Model'!$C$16)*(1+'DCF Model'!$D$16)*(1+'DCF Model'!$E$16)*(1+'DCF Model'!$F$16)*(1+0.035)/(0.09-0.035))/(1+0.09)^5/'DCF Model'!$B$6 -> 0 | F6: =('DCF Model'!$B$10*(1+'DCF Model'!$B$16)*(1+'DCF Model'!$C$16)*(1+'DCF Model'!$D$16)*(1+'DCF Model'!$E$16)*(1+'DCF Model'!$F$16)*(1+0.04)/(0.09-0.04))/(1+0.09)^5/'DCF Model'!$B$6 -> 0
A7: 0.1 | B7: =('DCF Model'!$B$10*(1+'DCF Model'!$B$16)*(1+'DCF Model'!$C$16)*(1+'DCF Model'!$D$16)*(1+'DCF Model'!$E$16)*(1+'DCF Model'!$F$16)*(1+0.02)/(0.1-0.02))/(1+0.1)^5/'DCF Model'!$B$6 -> 0 | C7: =('DCF Model'!$B$10*(1+'DCF Model'!$B$16)*(1+'DCF Model'!$C$16)*(1+'DCF Model'!$D$16)*(1+'DCF Model'!$E$16)*(1+'DCF Model'!$F$16)*(1+0.025)/(0.1-0.025))/(1+0.1)^5/'DCF Model'!$B$6 -> 0 | D7: =('DCF Model'!$B$10*(1+'DCF Model'!$B$16)*(1+'DCF Model'!$C$16)*(1+'DCF Model'!$D$16)*(1+'DCF Model'!$E$16)*(1+'DCF Model'!$F$16)*(1+0.03)/(0.1-0.03))/(1+0.1)^5/'DCF Model'!$B$6 -> 0 | E7: =('DCF Model'!$B$10*(1+'DCF Model'!$B$16)*(1+'DCF Model'!$C$16)*(1+'DCF Model'!$D$16)*(1+'DCF Model'!$E$16)*(1+'DCF Model'!$F$16)*(1+0.035)/(0.1-0.035))/(1+0.1)^5/'DCF Model'!$B$6 -> 0 | F7: =('DCF Model'!$B$10*(1+'DCF Model'!$B$16)*(1+'DCF Model'!$C$16)*(1+'DCF Model'!$D$16)*(1+'DCF Model'!$E$16)*(1+'DCF Model'!$F$16)*(1+0.04)/(0.1-0.04))/(1+0.1)^5/'DCF Model'!$B$6 -> 0
A8: 0.11 | B8: =('DCF Model'!$B$10*(1+'DCF Model'!$B$16)*(1+'DCF Model'!$C$16)*(1+'DCF Model'!$D$16)*(1+'DCF Model'!$E$16)*(1+'DCF Model'!$F$16)*(1+0.02)/(0.11-0.02))/(1+0.11)^5/'DCF Model'!$B$6 -> 0 | C8: =('DCF Model'!$B$10*(1+'DCF Model'!$B$16)*(1+'DCF Model'!$C$16)*(1+'DCF Model'!$D$16)*(1+'DCF Model'!$E$16)*(1+'DCF Model'!$F$16)*(1+0.025)/(0.11-0.025))/(1+0.11)^5/'DCF Model'!$B$6 -> 0 | D8: =('DCF Model'!$B$10*(1+'DCF Model'!$B$16)*(1+'DCF Model'!$C$16)*(1+'DCF Model'!$D$16)*(1+'DCF Model'!$E$16)*(1+'DCF Model'!$F$16)*(1+0.03)/(0.11-0.03))/(1+0.11)^5/'DCF Model'!$B$6 -> 0 | E8: =('DCF Model'!$B$10*(1+'DCF Model'!$B$16)*(1+'DCF Model'!$C$16)*(1+'DCF Model'!$D$16)*(1+'DCF Model'!$E$16)*(1+'DCF Model'!$F$16)*(1+0.035)/(0.11-0.035))/(1+0.11)^5/'DCF Model'!$B$6 -> 0 | F8: =('DCF Model'!$B$10*(1+'DCF Model'!$B$16)*(1+'DCF Model'!$C$16)*(1+'DCF Model'!$D$16)*(1+'DCF Model'!$E$16)*(1+'DCF Model'!$F$16)*(1+0.04)/(0.11-0.04))/(1+0.11)^5/'DCF Model'!$B$6 -> 0
A9: 0.12 | B9: =('DCF Model'!$B$10*(1+'DCF Model'!$B$16)*(1+'DCF Model'!$C$16)*(1+'DCF Model'!$D$16)*(1+'DCF Model'!$E$16)*(1+'DCF Model'!$F$16)*(1+0.02)/(0.12-0.02))/(1+0.12)^5/'DCF Model'!$B$6 -> 0 | C9: =('DCF Model'!$B$10*(1+'DCF Model'!$B$16)*(1+'DCF Model'!$C$16)*(1+'DCF Model'!$D$16)*(1+'DCF Model'!$E$16)*(1+'DCF Model'!$F$16)*(1+0.025)/(0.12-0.025))/(1+0.12)^5/'DCF Model'!$B$6 -> 0 | D9: =('DCF Model'!$B$10*(1+'DCF Model'!$B$16)*(1+'DCF Model'!$C$16)*(1+'DCF Model'!$D$16)*(1+'DCF Model'!$E$16)*(1+'DCF Model'!$F$16)*(1+0.03)/(0.12-0.03))/(1+0.12)^5/'DCF Model'!$B$6 -> 0 | E9: =('DCF Model'!$B$10*(1+'DCF Model'!$B$16)*(1+'DCF Model'!$C$16)*(1+'DCF Model'!$D$16)*(1+'DCF Model'!$E$16)*(1+'DCF Model'!$F$16)*(1+0.035)/(0.12-0.035))/(1+0.12)^5/'DCF Model'!$B$6 -> 0 | F9: =('DCF Model'!$B$10*(1+'DCF Model'!$B$16)*(1+'DCF Model'!$C$16)*(1+'DCF Model'!$D$16)*(1+'DCF Model'!$E$16)*(1+'DCF Model'!$F$16)*(1+0.04)/(0.12-0.04))/(1+0.12)^5/'DCF Model'!$B$6 -> 0

Sheet Historical
A1: Historical Growth Rates
A3: Metric | B3: 3-Year CAGR | C3: 5-Year CAGR
A4: Revenue | B4: 0.078 | C4: 0.123
A5: EPS | B5: 0.043 | C5: 0.141
A6: Equity | B6: -0.021 | C6: 0.039
A7: FCF | B7: 0.076 | C7: 0.15
A9: Selected Growth Rate: | B9: 0.078
A10: Source: | B10: revenue_3yr_cagr
A12: Warning: | B12: Equity 3yr CAGR is negative (-2.1%) due to aggressive share buybacks reducing book value. Using revenue 3yr CAGR (7.8%) as primary growth indicator given competitive headwinds and CEO transition.

Sheet Scenario Comparison
A1: Scenario Comparison
A3: Scenario | B3: Bear | C3: Base | D3: Bull
A5: ASSUMPTIONS
A6: Year 1 Growth | B6: 0.02 | C6: 0.06 | D6: 0.12
A7: WACC | B7: 0.11 | C7: 0.1 | D7: 0.09
A8: Terminal Growth | B8: 0.02 | C8: 0.03 | D8: 0.035
A10: VALUATION RESULTS
A11: Intrinsic Value | B11: 57.54 | C11: 101.48 | D11: 173.95
A12: Upside / (Downside) | B12: 0.403 | C12: 1.475 | D12: 3.243
A14: Entry Price (15% CAGR) | B14: 33.1 | C14: 60.87 | D14: 106.63
A16: Probability Weighted IV | C16: 108.61
