Workbook

Sheet Model_Info
A1: Austal Limited (ASB.AX) -- owner-FCF DCF model
A2: Version | B2: v1.0, 2026-09-21. First valuation of this ticker; supersedes nothing.
A3: Built by | B3: dcf-analyst agent (Claude Fable 5.1) on 2026-09-21 at the orchestrator's request for the ASB.AX research run.
A4: Model | B4: Component-built owner-FCF DCF, 10-year explicit horizon, end-of-year discounting, terminal value = MAX(0, MIN(Gordon, cap x FCF10)); three probability-weighted scenarios; hurdle entry price with TV rebuilt at 15%.
A5: Price | B5: A$4.54 -- 2026-09-21T06:10:32Z (ASX regular close, 957k shares traded; not after-hours)
A6: Balance sheet | B6: Borrowings A$130.150m (31-Dec-2025, H1 FY2026 BS) less cash A$312m at 30-Jun-2026 (FY2026 results release, 31-Aug-2026). Lease liabilities A$142.6m EXCLUDED (lease treatment B). Cross-check: on the same definition the company reported net cash A$241.4m at 31-Dec-2025 = 371.575 - 130.150, which ties exactly.
A7: Balance sheet date | B7: 2025-12-31 (latest extracted filing, H1 FY2026); cash refreshed to 2026-06-30 from the FY2026 results release, borrowings carried from 2025-12-31
A8: Share count | B8: 422,050,221 ordinary shares on issue at 31-Dec-2025 (H1 FY2026 note 7; includes 2.45m reserved shares held by the employee share trust) plus 1,522,405 service rights disclosed as dilutive in the FY2025 EPS note; held FLAT because SBC is expensed in the flows. Replace with the FY2026 annual report count when extracted.
A9: FY0 revenue | B9: FY2026 (year to 30-Jun-2026) revenue A$2,027m per the FY2026 results release (31-Aug-2026), not yet in Metrics.csv. FY2026 statutory EBIT ~ -A$125.2m / NPAT ~ -A$53.6m after a non-cash onerous-contract provision on the T-ATS, OPC, T-AGOS, AFDM and LCU programs at Austal USA.
A10: Lease treatment | B10: B -- leases as operating cost: lease_cost_pct 1.0% of revenue (FY2025 principal A$11.8m + estimated lease interest ~A$7m on A$136m of liabilities at the ~5% IBR, ~1.05% of revenue) charged inside owner EBITDA; lease liabilities excluded from net debt; da_pct 3.5% is D&A EX right-of-use depreciation (FY2025: 73.131 total - 13.073 ROU = 60.1 = 3.3% of revenue, lifted to 3.5% for the new US facilities).
A11: Onerous contracts | B11: The FY2026 provision is non-cash when booked but IS cash as the T-ATS/OPC/T-AGOS/AFDM/LCU hulls are built. Base ebitda_margin_path is therefore stated net of an estimated cash unwind of ~3.5pp/2.5pp/1.0pp of revenue in FY2027-FY2029 (underlying 9.0/9.25/9.5%); bear ~4.5/3.5/1.5pp on a lower 8% underlying (further overruns); bull ~2.5/1.5/0.5pp on 10-11% underlying (REA recoveries). Folding it into the margin keeps the component engine exact.
A12: Capex basis | B12: capex_pct_path is NET of government infrastructure grant receipts (FY2025 gross A$194.9m less A$46.0m grants; FY2022-FY2025 grants averaged A$28m/yr). The US$1.2bn Mobile expansion (FA2, MMF3, steel panel line, San Diego dry dock) keeps net capex at 11%/8.5% of revenue in FY2027/FY2028 before fading to a 3.75% maintenance level (D&A ex-ROU 3.5%).
A13: Working capital | B13: Milestone-billed shipbuilder with A$875m of progress payments received in advance (31-Dec-2025) against contract assets; growth in the order book generates advance cash. wc_capture 5% of the revenue change in base, 0% bear, 8% bull -- deliberately modest given the H1 FY2026 unwind.
... A19: Colour legend | B19: Blue font = hardcoded input; yellow fill = key lever; black = formula; green font = cross-sheet link.

Sheet Actuals
A1: Period | B1: Revenue | C1: EBITDA | D1: EBIT | E1: NetIncome | F1: OCF | G1: CapEx(gross) | H1: ReportedFCF | I1: SBC | J1: InterestIncome | K1: LeasePrincipal | L1: GrantsReceived | M1: OwnerFCF | N1: Source
A2: FY2019 | B2: 1852.074 | C2: 135.001 | D2: 92.795 | E2: 61.384 | F2: 164.517 | G2: 43.098 | H2: 121.419 | I2: 3.087 | J2: 1.053 | K2: 0 | L2: 0 | M2: =IF(ISNUMBER(H2),H2-I2-J2-K2,"n/a")
A3: FY2020 | B3: 2086.001 | C3: 176.139 | D3: 130.396 | E3: 88.978 | F3: 164.472 | G3: 18.361 | H3: 146.111 | I3: 1.178 | J3: 1.384 | K3: 6.01 | L3: 0 | M3: =IF(ISNUMBER(H3),H3-I3-J3-K3,"n/a")
A4: FY2021 | B4: 1572.175 | C4: 160.326 | D4: 114.619 | E4: 81.057 | F4: 93.464 | G4: 77.152 | H4: 16.312 | I4: 0.5 | J4: 0.368 | K4: 7.585 | L4: 18.469 | M4: =IF(ISNUMBER(H4),H4-I4-J4-K4,"n/a")
A5: FY2022 | B5: 1429.044 | C5: 165.35 | D5: 120.662 | E5: 79.565 | F5: 37.499 | G5: 117.096 | H5: -79.597 | I5: 0.5 | J5: 0.135 | K5: 8.638 | L5: 31.625 | M5: =IF(ISNUMBER(H5),H5-I5-J5-K5,"n/a")
A6: FY2023 | B6: 1585.034 | C6: 54.973 | D6: -4.842 | E6: -13.774 | F6: 86.714 | G6: 127.324 | H6: -40.61 | I6: 0.76 | J6: 1.784 | K6: 9.088 | L6: 24.785 | M6: =IF(ISNUMBER(H6),H6-I6-J6-K6,"n/a")
A7: FY2024 | B7: 1468.907 | C7: 123.741 | D7: 56.465 | E7: 14.876 | F7: -13.047 | G7: 69.916 | H7: -82.963 | I7: 2.127 | J7: 3.901 | K7: 9.514 | L7: 9.047 | M7: =IF(ISNUMBER(H7),H7-I7-J7-K7,"n/a")
A8: FY2025 | B8: 1823.337 | C8: 186.485 | D8: 113.354 | E8: 89.733 | F8: 406.322 | G8: 195.644 | H8: 210.678 | I8: 2.96 | J8: 13.275 | K8: 11.812 | L8: 45.954 | M8: =IF(ISNUMBER(H8),H8-I8-J8-K8,"n/a")
A9: H1 FY2026 | B9: 1109.394 | C9: 93.922 | D9: 60.346 | E9: 30.496 | F9: -62.893 | G9: 154.724 | H9: -217.617 | I9: 2.26 | J9: 7.616 | K9: 6.984 | L9: 8.977 | M9: =IF(ISNUMBER(H9),H9-I9-J9-K9,"n/a")
A10: FY2026 (release) | B10: 2027 | D10: -125.2 | E10: -53.6 | M10: =IF(ISNUMBER(H10),H10-I10-J10-K10,"n/a")
A12: Balance sheet / count anchors
A13: Cash A$m 30-Jun-2026 (results release) | B13: 312
A14: Borrowings A$m 31-Dec-2025 | B14: 130.15
A15: Lease liabilities A$m 31-Dec-2025 (excluded, treatment B) | B15: 142.645
A16: Shares on issue 31-Dec-2025 (m) | B16: 422.05022
A17: Dilutive service rights (m), FY2025 EPS note | B17: 1.522405
A18: Progress payments received in advance A$m 31-Dec-2025 | B18: 875.402
A19: Onerous contract provision A$m 31-Dec-2025 (T-ATS+AFDM only, pre FY2026 charge) | B19: 39.731
A20: Buybacks FY2019-FY2025 | B20: 0

Sheet Assumptions
A1: Global inputs
A3: WACC | B3: 0.1 | C3: AUD-built: ACGB ~4.3% + 5.5% ERP x beta 1.1; same for every scenario (risk charged in flows/weights)
A4: D&A % revenue (ex right-of-use) | B4: 0.035 | C4: FY2025 60.1/1823 = 3.3%, lifted for new US facilities
A5: Lease cost % revenue (principal + interest) | B5: 0.01 | C5: Treatment B: FY2025 11.8 principal + ~7 interest
A6: Net cash A$m (positive = cash) | B6: 181.85 | C6: Borrowings A$130.150m (31-Dec-2025, H1 FY2026 BS) less cash A$312m at 30-Jun-2026 (FY2026
A7: Diluted shares (m) | B7: 423.572 | C7: 422.05m issued 31-Dec-2025 + 1.52m service rights; FLAT
A8: Price A$ | B8: 4.54 | C8: 2026-09-21T06:10:32Z (ASX regular close, 957k shares traded; not after-hours)
A9: Hurdle rate | B9: 0.15 | C9: Entry-price IRR; TV rebuilt at this rate
A10: FY0 revenue A$m (FY2026) | B10: 2027 | C10: FY2026 results release
A11: SBC % revenue (all years, all scenarios) | B11: 0.0015 | C11: FY2025 2.96/1823 = 0.16%
A13: Per scenario
A14: Scenario | B14: Terminal growth | C14: Probability | D14: TV cap (x FCF10) | E14: WC capture % of rev change
A15: Bear | B15: 0.02 | C15: 0.25 | D15: 10 | E15: 0
A16: Base | B16: 0.025 | C16: 0.45 | D16: 13 | E16: 0.05
A17: Bull | B17: 0.03 | C17: 0.3 | D17: 18 | E17: 0.08
B18: Weights sum | C18: =SUM(C15:C17)
A20: Scenario narratives
A21: Bear | B21: Deal breaks and the estimation problem is structural. Both Austal USA proposals lapse or are blocked (CFIUS/political preference for domestic ownership, or Hanwha's FIRB conditions); the T-ATS/OPC/T-AGOS/AFDM/LCU programs generate a further round of overruns beyond the FY2026 provision (a repeat of 2016->2024), REAs recover little, and the steel transition keeps USA Shipbuilding at breakeven. Australasia's SSA pipeline still grows but only offsets a shrinking US book, so group revenue rises 2-4%/yr. Net capex stays at 12%/9% of revenue for two years because the Mobile facilities are contractually committed, burning most of the A$182m net cash. Mature cash EBITDA margin 7.5%, 10x terminal cap. Nothing in this path breaks solvency, but equity value collapses to the residual net cash plus a thin 1.6% FCF margin.
A22: Base | B22: Standalone mid-cycle, deal uncertain. FY2027 returns to statutory profitability as guided, but ~A$70m/A$60m/A$25m of the onerous-contract provision is paid out in cash over FY2027-FY2029 as the hulls are built, so cash EBITDA margins are 5.5%/6.75%/8.5% before settling at 9.5% (history: FY2019-FY2025 average 8.5%, peak 11.6%). Revenue grows 8%/8%/7% on the A$1.03bn LC-M award, OPC, T-AGOS and submarine modules, decelerating to 2.5%. The US$1.2bn Mobile expansion holds net capex at 11%/8.5% before fading to 3.75%. Cash tax ramps 10%->27% as FY2026 losses are utilised. Owner FCF is negative in FY2027-FY2028 and reaches a 3.3% mature margin; the 13x cap binds the terminal value.
A23: Bull | B23: Execution fixed, Australia doubles, and a strategic buyer sets the exit multiple. REAs recover a meaningful share of the FY2026 charge (unwind only 2.5/1.5/0.5pp), steel programs stabilise, Support grows as a share of mix and Australasia shipbuilding doubles by FY2031 per guidance, lifting cash EBITDA to 11.5%. Revenue compounds 12%/12%/10%/9%/8% off the A$16.5bn order book. Capex fades faster (3.5% maintenance) because the Navy and Commonwealth co-fund facilities. The 18x terminal cap is the strategic-buyer multiple evidenced by the Hanwha/Wildcat bids (~11-12x FY2025 Austal USA EBITDA); Gordon at 3% still binds below it. This is the scenario in which the market's current price is roughly fair on a standalone basis.

Sheet DCF_Bear
A3: Year | B3: 2026A | C3: FY2027E | D3: FY2028E | E3: FY2029E | F3: FY2030E | G3: FY2031E | H3: FY2032E | I3: FY2033E | J3: FY2034E | K3: FY2035E | L3: FY2036E
A4: Index | B4: 0 | C4: 1 | D4: 2 | E4: 3 | F4: 4 | G4: 5 | H4: 6 | I4: 7 | J4: 8 | K4: 9 | L4: 10
A5: Revenue growth YoY | C5: 0.04 | D5: 0.03 | E5: 0.02 | F5: 0.02 | G5: 0.02 | H5: 0.02 | I5: 0.02 | J5: 0.02 | K5: 0.02 | L5: 0.02
A6: Revenue A$m | B6: =Assumptions!$B$10 | C6: =B6*(1+C5) | D6: =C6*(1+D5) | E6: =D6*(1+E5) | F6: =E6*(1+F5) | G6: =F6*(1+G5) | H6: =G6*(1+H5) | I6: =H6*(1+I5) | J6: =I6*(1+J5) | ... L6: =K6*(1+L5)
A7: EBITDA margin (cash basis, post-IFRS16, net of onerous unwind) | C7: 0.035 | D7: 0.045 | E7: 0.065 | F7: 0.075 | G7: 0.075 | H7: 0.075 | I7: 0.075 | J7: 0.075 | K7: 0.075 | L7: 0.075
A8: Adjusted EBITDA | C8: =C6*C7 | D8: =D6*D7 | E8: =E6*E7 | F8: =F6*F7 | G8: =G6*G7 | H8: =H6*H7 | I8: =I6*I7 | J8: =J6*J7 | ... L8: =L6*L7
A9: SBC % revenue | C9: =Assumptions!$B$11 | D9: =Assumptions!$B$11 | E9: =Assumptions!$B$11 | F9: =Assumptions!$B$11 | G9: =Assumptions!$B$11 | H9: =Assumptions!$B$11 | I9: =Assumptions!$B$11 | J9: =Assumptions!$B$11 | ... L9: =Assumptions!$B$11
A10: SBC A$m (negative) | C10: =-C6*C9 | D10: =-D6*D9 | E10: =-E6*E9 | F10: =-F6*F9 | G10: =-G6*G9 | H10: =-H6*H9 | I10: =-I6*I9 | J10: =-J6*J9 | ... L10: =-L6*L9
A11: Owner EBITDA (after SBC and lease cost) | C11: =C8+C10-C6*Assumptions!$B$5 | D11: =D8+D10-D6*Assumptions!$B$5 | E11: =E8+E10-E6*Assumptions!$B$5 | F11: =F8+F10-F6*Assumptions!$B$5 | G11: =G8+G10-G6*Assumptions!$B$5 | H11: =H8+H10-H6*Assumptions!$B$5 | I11: =I8+I10-I6*Assumptions!$B$5 | J11: =J8+J10-J6*Assumptions!$B$5 | ... L11: =L8+L10-L6*Assumptions!$B$5
A12: D&A ex-ROU (negative) | C12: =-C6*Assumptions!$B$4 | D12: =-D6*Assumptions!$B$4 | E12: =-E6*Assumptions!$B$4 | F12: =-F6*Assumptions!$B$4 | G12: =-G6*Assumptions!$B$4 | H12: =-H6*Assumptions!$B$4 | I12: =-I6*Assumptions!$B$4 | J12: =-J6*Assumptions!$B$4 | ... L12: =-L6*Assumptions!$B$4
A13: EBIT, SBC expensed | C13: =C11+C12 | D13: =D11+D12 | E13: =E11+E12 | F13: =F11+F12 | G13: =G11+G12 | H13: =H11+H12 | I13: =I11+I12 | J13: =J11+J12 | ... L13: =L11+L12
A14: Cash tax rate | C14: 0 | D14: 0 | E14: 0.15 | F14: 0.22 | G14: 0.27 | H14: 0.27 | I14: 0.27 | J14: 0.27 | K14: 0.27 | L14: 0.27
A15: NOPAT | C15: =C13*(1-C14) | D15: =D13*(1-D14) | E15: =E13*(1-E14) | F15: =F13*(1-F14) | G15: =G13*(1-G14) | H15: =H13*(1-H14) | I15: =I13*(1-I14) | J15: =J13*(1-J14) | ... L15: =L13*(1-L14)
A16: add back D&A | C16: =-C12 | D16: =-D12 | E16: =-E12 | F16: =-F12 | G16: =-G12 | H16: =-H12 | I16: =-I12 | J16: =-J12 | ... L16: =-L12
A17: less capex (net of grants) | C17: =-C6*C25 | D17: =-D6*D25 | E17: =-E6*E25 | F17: =-F6*F25 | G17: =-G6*G25 | H17: =-H6*H25 | I17: =-I6*I25 | J17: =-J6*J25 | ... L17: =-L6*L25
A18: add working capital | C18: =Assumptions!$E$15*(C6-B6) | D18: =Assumptions!$E$15*(D6-C6) | E18: =Assumptions!$E$15*(E6-D6) | F18: =Assumptions!$E$15*(F6-E6) | G18: =Assumptions!$E$15*(G6-F6) | H18: =Assumptions!$E$15*(H6-G6) | I18: =Assumptions!$E$15*(I6-H6) | J18: =Assumptions!$E$15*(J6-I6) | ... L18: =Assumptions!$E$15*(L6-K6)
A19: Unlevered owner FCF | C19: =C15+C16+C17+C18 | D19: =D15+D16+D17+D18 | E19: =E15+E16+E17+E18 | F19: =F15+F16+F17+F18 | G19: =G15+G16+G17+G18 | H19: =H15+H16+H17+H18 | I19: =I15+I16+I17+I18 | J19: =J15+J16+J17+J18 | ... L19: =L15+L16+L17+L18
A20: Discount factor | C20: =1/(1+Assumptions!$B$3)^C4 | D20: =1/(1+Assumptions!$B$3)^D4 | E20: =1/(1+Assumptions!$B$3)^E4 | F20: =1/(1+Assumptions!$B$3)^F4 | G20: =1/(1+Assumptions!$B$3)^G4 | H20: =1/(1+Assumptions!$B$3)^H4 | I20: =1/(1+Assumptions!$B$3)^I4 | J20: =1/(1+Assumptions!$B$3)^J4 | ... L20: =1/(1+Assumptions!$B$3)^L4
A21: PV of FCF | C21: =C19*C20 | D21: =D19*D20 | E21: =E19*E20 | F21: =F19*F20 | G21: =G19*G20 | H21: =H19*H20 | I21: =I19*I20 | J21: =J19*J20 | ... L21: =L19*L20
A23: Memo: FCF before SBC (company-style) | C23: =C19-C10 | D23: =D19-D10 | E23: =E19-E10 | F23: =F19-F10 | G23: =G19-G10 | H23: =H19-H10 | I23: =I19-I10 | J23: =J19-J10 | ... L23: =L19-L10
A24: Memo: owner-FCF margin | C24: =C19/C6 | D24: =D19/D6 | E24: =E19/E6 | F24: =F19/F6 | G24: =G19/G6 | H24: =H19/H6 | I24: =I19/I6 | J24: =J19/J6 | ... L24: =L19/L6
A25: Capex % revenue (net of grants) -- driver | C25: 0.12 | D25: 0.09 | E25: 0.065 | F25: 0.05 | G25: 0.045 | H25: 0.04 | I25: 0.04 | J25: 0.04 | K25: 0.04 | L25: 0.04
A26: Sum of PV of FCF | B26: =SUM(C21:L21)
A27: Terminal growth | B27: =Assumptions!$B$15
A28: Terminal FCF (FY10 x (1+g)) | B28: =L19*(1+B27)
A29: Gordon TV | B29: =B28/(Assumptions!$B$3-B27)
A30: Cap TV | B30: =Assumptions!$D$15*L19
A31: TV used = MAX(0,MIN(Gordon,cap)) | B31: =MAX(0,MIN(B29,B30))
A32: Implied exit multiple | B32: =IF(L19<>0,B31/L19,"n/a")
A33: PV of TV | B33: =B31*L20
A34: Enterprise value | B34: =B26+B33
A35: add net cash | B35: =Assumptions!$B$6
A36: Equity value | B36: =B34+B35
A37: Diluted shares (m) | B37: =Assumptions!$B$7
A38: Value per share A$ | B38: =B36/B37
A39: Upside vs price | B39: =B38/Assumptions!$B$8-1
A41: Street memo: PV of explicit SBC | B41: =SUMPRODUCT(-C10:L10/(1+Assumptions!$B$3)^C4:L4)
A42: Street memo: PV of terminal SBC | B42: =(-L10*(1+B27)/(Assumptions!$B$3-B27))*L20
A43: Street value per share A$ | B43: =(B36+B41+B42)/B37

Sheet DCF_Base
A3: Year | B3: 2026A | C3: FY2027E | D3: FY2028E | E3: FY2029E | F3: FY2030E | G3: FY2031E | H3: FY2032E | I3: FY2033E | J3: FY2034E | K3: FY2035E | L3: FY2036E
A4: Index | B4: 0 | C4: 1 | D4: 2 | E4: 3 | F4: 4 | G4: 5 | H4: 6 | I4: 7 | J4: 8 | K4: 9 | L4: 10
A5: Revenue growth YoY | C5: 0.08 | D5: 0.08 | E5: 0.07 | F5: 0.06 | G5: 0.05 | H5: 0.04 | I5: 0.035 | J5: 0.03 | K5: 0.03 | L5: 0.025
A6: Revenue A$m | B6: =Assumptions!$B$10 | C6: =B6*(1+C5) | D6: =C6*(1+D5) | E6: =D6*(1+E5) | F6: =E6*(1+F5) | G6: =F6*(1+G5) | H6: =G6*(1+H5) | I6: =H6*(1+I5) | J6: =I6*(1+J5) | ... L6: =K6*(1+L5)
A7: EBITDA margin (cash basis, post-IFRS16, net of onerous unwind) | C7: 0.055 | D7: 0.0675 | E7: 0.085 | F7: 0.095 | G7: 0.095 | H7: 0.095 | I7: 0.095 | J7: 0.095 | K7: 0.095 | L7: 0.095
A8: Adjusted EBITDA | C8: =C6*C7 | D8: =D6*D7 | E8: =E6*E7 | F8: =F6*F7 | G8: =G6*G7 | H8: =H6*H7 | I8: =I6*I7 | J8: =J6*J7 | ... L8: =L6*L7
A9: SBC % revenue | C9: =Assumptions!$B$11 | D9: =Assumptions!$B$11 | E9: =Assumptions!$B$11 | F9: =Assumptions!$B$11 | G9: =Assumptions!$B$11 | H9: =Assumptions!$B$11 | I9: =Assumptions!$B$11 | J9: =Assumptions!$B$11 | ... L9: =Assumptions!$B$11
A10: SBC A$m (negative) | C10: =-C6*C9 | D10: =-D6*D9 | E10: =-E6*E9 | F10: =-F6*F9 | G10: =-G6*G9 | H10: =-H6*H9 | I10: =-I6*I9 | J10: =-J6*J9 | ... L10: =-L6*L9
A11: Owner EBITDA (after SBC and lease cost) | C11: =C8+C10-C6*Assumptions!$B$5 | D11: =D8+D10-D6*Assumptions!$B$5 | E11: =E8+E10-E6*Assumptions!$B$5 | F11: =F8+F10-F6*Assumptions!$B$5 | G11: =G8+G10-G6*Assumptions!$B$5 | H11: =H8+H10-H6*Assumptions!$B$5 | I11: =I8+I10-I6*Assumptions!$B$5 | J11: =J8+J10-J6*Assumptions!$B$5 | ... L11: =L8+L10-L6*Assumptions!$B$5
A12: D&A ex-ROU (negative) | C12: =-C6*Assumptions!$B$4 | D12: =-D6*Assumptions!$B$4 | E12: =-E6*Assumptions!$B$4 | F12: =-F6*Assumptions!$B$4 | G12: =-G6*Assumptions!$B$4 | H12: =-H6*Assumptions!$B$4 | I12: =-I6*Assumptions!$B$4 | J12: =-J6*Assumptions!$B$4 | ... L12: =-L6*Assumptions!$B$4
A13: EBIT, SBC expensed | C13: =C11+C12 | D13: =D11+D12 | E13: =E11+E12 | F13: =F11+F12 | G13: =G11+G12 | H13: =H11+H12 | I13: =I11+I12 | J13: =J11+J12 | ... L13: =L11+L12
A14: Cash tax rate | C14: 0.1 | D14: 0.15 | E14: 0.22 | F14: 0.26 | G14: 0.27 | H14: 0.27 | I14: 0.27 | J14: 0.27 | K14: 0.27 | L14: 0.27
A15: NOPAT | C15: =C13*(1-C14) | D15: =D13*(1-D14) | E15: =E13*(1-E14) | F15: =F13*(1-F14) | G15: =G13*(1-G14) | H15: =H13*(1-H14) | I15: =I13*(1-I14) | J15: =J13*(1-J14) | ... L15: =L13*(1-L14)
A16: add back D&A | C16: =-C12 | D16: =-D12 | E16: =-E12 | F16: =-F12 | G16: =-G12 | H16: =-H12 | I16: =-I12 | J16: =-J12 | ... L16: =-L12
A17: less capex (net of grants) | C17: =-C6*C25 | D17: =-D6*D25 | E17: =-E6*E25 | F17: =-F6*F25 | G17: =-G6*G25 | H17: =-H6*H25 | I17: =-I6*I25 | J17: =-J6*J25 | ... L17: =-L6*L25
A18: add working capital | C18: =Assumptions!$E$16*(C6-B6) | D18: =Assumptions!$E$16*(D6-C6) | E18: =Assumptions!$E$16*(E6-D6) | F18: =Assumptions!$E$16*(F6-E6) | G18: =Assumptions!$E$16*(G6-F6) | H18: =Assumptions!$E$16*(H6-G6) | I18: =Assumptions!$E$16*(I6-H6) | J18: =Assumptions!$E$16*(J6-I6) | ... L18: =Assumptions!$E$16*(L6-K6)
A19: Unlevered owner FCF | C19: =C15+C16+C17+C18 | D19: =D15+D16+D17+D18 | E19: =E15+E16+E17+E18 | F19: =F15+F16+F17+F18 | G19: =G15+G16+G17+G18 | H19: =H15+H16+H17+H18 | I19: =I15+I16+I17+I18 | J19: =J15+J16+J17+J18 | ... L19: =L15+L16+L17+L18
A20: Discount factor | C20: =1/(1+Assumptions!$B$3)^C4 | D20: =1/(1+Assumptions!$B$3)^D4 | E20: =1/(1+Assumptions!$B$3)^E4 | F20: =1/(1+Assumptions!$B$3)^F4 | G20: =1/(1+Assumptions!$B$3)^G4 | H20: =1/(1+Assumptions!$B$3)^H4 | I20: =1/(1+Assumptions!$B$3)^I4 | J20: =1/(1+Assumptions!$B$3)^J4 | ... L20: =1/(1+Assumptions!$B$3)^L4
A21: PV of FCF | C21: =C19*C20 | D21: =D19*D20 | E21: =E19*E20 | F21: =F19*F20 | G21: =G19*G20 | H21: =H19*H20 | I21: =I19*I20 | J21: =J19*J20 | ... L21: =L19*L20
A23: Memo: FCF before SBC (company-style) | C23: =C19-C10 | D23: =D19-D10 | E23: =E19-E10 | F23: =F19-F10 | G23: =G19-G10 | H23: =H19-H10 | I23: =I19-I10 | J23: =J19-J10 | ... L23: =L19-L10
A24: Memo: owner-FCF margin | C24: =C19/C6 | D24: =D19/D6 | E24: =E19/E6 | F24: =F19/F6 | G24: =G19/G6 | H24: =H19/H6 | I24: =I19/I6 | J24: =J19/J6 | ... L24: =L19/L6
A25: Capex % revenue (net of grants) -- driver | C25: 0.11 | D25: 0.085 | E25: 0.06 | F25: 0.045 | G25: 0.04 | H25: 0.0375 | I25: 0.0375 | J25: 0.0375 | K25: 0.0375 | L25: 0.0375
A26: Sum of PV of FCF | B26: =SUM(C21:L21)
A27: Terminal growth | B27: =Assumptions!$B$16
A28: Terminal FCF (FY10 x (1+g)) | B28: =L19*(1+B27)
A29: Gordon TV | B29: =B28/(Assumptions!$B$3-B27)
A30: Cap TV | B30: =Assumptions!$D$16*L19
A31: TV used = MAX(0,MIN(Gordon,cap)) | B31: =MAX(0,MIN(B29,B30))
A32: Implied exit multiple | B32: =IF(L19<>0,B31/L19,"n/a")
A33: PV of TV | B33: =B31*L20
A34: Enterprise value | B34: =B26+B33
A35: add net cash | B35: =Assumptions!$B$6
A36: Equity value | B36: =B34+B35
A37: Diluted shares (m) | B37: =Assumptions!$B$7
A38: Value per share A$ | B38: =B36/B37
A39: Upside vs price | B39: =B38/Assumptions!$B$8-1
A41: Street memo: PV of explicit SBC | B41: =SUMPRODUCT(-C10:L10/(1+Assumptions!$B$3)^C4:L4)
A42: Street memo: PV of terminal SBC | B42: =(-L10*(1+B27)/(Assumptions!$B$3-B27))*L20
A43: Street value per share A$ | B43: =(B36+B41+B42)/B37

Sheet DCF_Bull
A3: Year | B3: 2026A | C3: FY2027E | D3: FY2028E | E3: FY2029E | F3: FY2030E | G3: FY2031E | H3: FY2032E | I3: FY2033E | J3: FY2034E | K3: FY2035E | L3: FY2036E
A4: Index | B4: 0 | C4: 1 | D4: 2 | E4: 3 | F4: 4 | G4: 5 | H4: 6 | I4: 7 | J4: 8 | K4: 9 | L4: 10
A5: Revenue growth YoY | C5: 0.12 | D5: 0.12 | E5: 0.1 | F5: 0.09 | G5: 0.08 | H5: 0.06 | I5: 0.05 | J5: 0.04 | K5: 0.035 | L5: 0.03
A6: Revenue A$m | B6: =Assumptions!$B$10 | C6: =B6*(1+C5) | D6: =C6*(1+D5) | E6: =D6*(1+E5) | F6: =E6*(1+F5) | G6: =F6*(1+G5) | H6: =G6*(1+H5) | I6: =H6*(1+I5) | J6: =I6*(1+J5) | ... L6: =K6*(1+L5)
A7: EBITDA margin (cash basis, post-IFRS16, net of onerous unwind) | C7: 0.075 | D7: 0.09 | E7: 0.105 | F7: 0.115 | G7: 0.115 | H7: 0.115 | I7: 0.115 | J7: 0.115 | K7: 0.115 | L7: 0.115
A8: Adjusted EBITDA | C8: =C6*C7 | D8: =D6*D7 | E8: =E6*E7 | F8: =F6*F7 | G8: =G6*G7 | H8: =H6*H7 | I8: =I6*I7 | J8: =J6*J7 | ... L8: =L6*L7
A9: SBC % revenue | C9: =Assumptions!$B$11 | D9: =Assumptions!$B$11 | E9: =Assumptions!$B$11 | F9: =Assumptions!$B$11 | G9: =Assumptions!$B$11 | H9: =Assumptions!$B$11 | I9: =Assumptions!$B$11 | J9: =Assumptions!$B$11 | ... L9: =Assumptions!$B$11
A10: SBC A$m (negative) | C10: =-C6*C9 | D10: =-D6*D9 | E10: =-E6*E9 | F10: =-F6*F9 | G10: =-G6*G9 | H10: =-H6*H9 | I10: =-I6*I9 | J10: =-J6*J9 | ... L10: =-L6*L9
A11: Owner EBITDA (after SBC and lease cost) | C11: =C8+C10-C6*Assumptions!$B$5 | D11: =D8+D10-D6*Assumptions!$B$5 | E11: =E8+E10-E6*Assumptions!$B$5 | F11: =F8+F10-F6*Assumptions!$B$5 | G11: =G8+G10-G6*Assumptions!$B$5 | H11: =H8+H10-H6*Assumptions!$B$5 | I11: =I8+I10-I6*Assumptions!$B$5 | J11: =J8+J10-J6*Assumptions!$B$5 | ... L11: =L8+L10-L6*Assumptions!$B$5
A12: D&A ex-ROU (negative) | C12: =-C6*Assumptions!$B$4 | D12: =-D6*Assumptions!$B$4 | E12: =-E6*Assumptions!$B$4 | F12: =-F6*Assumptions!$B$4 | G12: =-G6*Assumptions!$B$4 | H12: =-H6*Assumptions!$B$4 | I12: =-I6*Assumptions!$B$4 | J12: =-J6*Assumptions!$B$4 | ... L12: =-L6*Assumptions!$B$4
A13: EBIT, SBC expensed | C13: =C11+C12 | D13: =D11+D12 | E13: =E11+E12 | F13: =F11+F12 | G13: =G11+G12 | H13: =H11+H12 | I13: =I11+I12 | J13: =J11+J12 | ... L13: =L11+L12
A14: Cash tax rate | C14: 0.1 | D14: 0.15 | E14: 0.22 | F14: 0.26 | G14: 0.27 | H14: 0.27 | I14: 0.27 | J14: 0.27 | K14: 0.27 | L14: 0.27
A15: NOPAT | C15: =C13*(1-C14) | D15: =D13*(1-D14) | E15: =E13*(1-E14) | F15: =F13*(1-F14) | G15: =G13*(1-G14) | H15: =H13*(1-H14) | I15: =I13*(1-I14) | J15: =J13*(1-J14) | ... L15: =L13*(1-L14)
A16: add back D&A | C16: =-C12 | D16: =-D12 | E16: =-E12 | F16: =-F12 | G16: =-G12 | H16: =-H12 | I16: =-I12 | J16: =-J12 | ... L16: =-L12
A17: less capex (net of grants) | C17: =-C6*C25 | D17: =-D6*D25 | E17: =-E6*E25 | F17: =-F6*F25 | G17: =-G6*G25 | H17: =-H6*H25 | I17: =-I6*I25 | J17: =-J6*J25 | ... L17: =-L6*L25
A18: add working capital | C18: =Assumptions!$E$17*(C6-B6) | D18: =Assumptions!$E$17*(D6-C6) | E18: =Assumptions!$E$17*(E6-D6) | F18: =Assumptions!$E$17*(F6-E6) | G18: =Assumptions!$E$17*(G6-F6) | H18: =Assumptions!$E$17*(H6-G6) | I18: =Assumptions!$E$17*(I6-H6) | J18: =Assumptions!$E$17*(J6-I6) | ... L18: =Assumptions!$E$17*(L6-K6)
A19: Unlevered owner FCF | C19: =C15+C16+C17+C18 | D19: =D15+D16+D17+D18 | E19: =E15+E16+E17+E18 | F19: =F15+F16+F17+F18 | G19: =G15+G16+G17+G18 | H19: =H15+H16+H17+H18 | I19: =I15+I16+I17+I18 | J19: =J15+J16+J17+J18 | ... L19: =L15+L16+L17+L18
A20: Discount factor | C20: =1/(1+Assumptions!$B$3)^C4 | D20: =1/(1+Assumptions!$B$3)^D4 | E20: =1/(1+Assumptions!$B$3)^E4 | F20: =1/(1+Assumptions!$B$3)^F4 | G20: =1/(1+Assumptions!$B$3)^G4 | H20: =1/(1+Assumptions!$B$3)^H4 | I20: =1/(1+Assumptions!$B$3)^I4 | J20: =1/(1+Assumptions!$B$3)^J4 | ... L20: =1/(1+Assumptions!$B$3)^L4
A21: PV of FCF | C21: =C19*C20 | D21: =D19*D20 | E21: =E19*E20 | F21: =F19*F20 | G21: =G19*G20 | H21: =H19*H20 | I21: =I19*I20 | J21: =J19*J20 | ... L21: =L19*L20
A23: Memo: FCF before SBC (company-style) | C23: =C19-C10 | D23: =D19-D10 | E23: =E19-E10 | F23: =F19-F10 | G23: =G19-G10 | H23: =H19-H10 | I23: =I19-I10 | J23: =J19-J10 | ... L23: =L19-L10
A24: Memo: owner-FCF margin | C24: =C19/C6 | D24: =D19/D6 | E24: =E19/E6 | F24: =F19/F6 | G24: =G19/G6 | H24: =H19/H6 | I24: =I19/I6 | J24: =J19/J6 | ... L24: =L19/L6
A25: Capex % revenue (net of grants) -- driver | C25: 0.11 | D25: 0.08 | E25: 0.055 | F25: 0.04 | G25: 0.035 | H25: 0.035 | I25: 0.035 | J25: 0.035 | K25: 0.035 | L25: 0.035
A26: Sum of PV of FCF | B26: =SUM(C21:L21)
A27: Terminal growth | B27: =Assumptions!$B$17
A28: Terminal FCF (FY10 x (1+g)) | B28: =L19*(1+B27)
A29: Gordon TV | B29: =B28/(Assumptions!$B$3-B27)
A30: Cap TV | B30: =Assumptions!$D$17*L19
A31: TV used = MAX(0,MIN(Gordon,cap)) | B31: =MAX(0,MIN(B29,B30))
A32: Implied exit multiple | B32: =IF(L19<>0,B31/L19,"n/a")
A33: PV of TV | B33: =B31*L20
A34: Enterprise value | B34: =B26+B33
A35: add net cash | B35: =Assumptions!$B$6
A36: Equity value | B36: =B34+B35
A37: Diluted shares (m) | B37: =Assumptions!$B$7
A38: Value per share A$ | B38: =B36/B37
A39: Upside vs price | B39: =B38/Assumptions!$B$8-1
A41: Street memo: PV of explicit SBC | B41: =SUMPRODUCT(-C10:L10/(1+Assumptions!$B$3)^C4:L4)
A42: Street memo: PV of terminal SBC | B42: =(-L10*(1+B27)/(Assumptions!$B$3-B27))*L20
A43: Street value per share A$ | B43: =(B36+B41+B42)/B37

Sheet FCF_Quality
A1: Reported FCF reconciled to owner FCF (A$m); links to Actuals
A2: Period | B2: FY2019 | C2: FY2020 | D2: FY2021 | E2: FY2022 | F2: FY2023 | G2: FY2024 | H2: FY2025 | I2: H1 FY2026
A3: Free cash flow (company definition: OCF - gross capex) | B3: =Actuals!H2 | C3: =Actuals!H3 | D3: =Actuals!H4 | E3: =Actuals!H5 | F3: =Actuals!H6 | G3: =Actuals!H7 | H3: =Actuals!H8 | I3: =Actuals!H9
A4: less: SBC | B4: =-Actuals!I2 | C4: =-Actuals!I3 | D4: =-Actuals!I4 | E4: =-Actuals!I5 | F4: =-Actuals!I6 | G4: =-Actuals!I7 | H4: =-Actuals!I8 | I4: =-Actuals!I9
A5: less: interest income | B5: =-Actuals!J2 | C5: =-Actuals!J3 | D5: =-Actuals!J4 | E5: =-Actuals!J5 | F5: =-Actuals!J6 | G5: =-Actuals!J7 | H5: =-Actuals!J8 | I5: =-Actuals!J9
A6: less: lease principal (treatment B; lease interest already in OCF) | B6: =-Actuals!K2 | C6: =-Actuals!K3 | D6: =-Actuals!K4 | E6: =-Actuals!K5 | F6: =-Actuals!K6 | G6: =-Actuals!K7 | H6: =-Actuals!K8 | I6: =-Actuals!K9
A7: Owner FCF (sum of the four lines above) | B7: =SUM(B3:B6) | C7: =SUM(C3:C6) | D7: =SUM(D3:D6) | E7: =SUM(E3:E6) | F7: =SUM(F3:F6) | G7: =SUM(G3:G6) | H7: =SUM(H3:H6) | I7: =SUM(I3:I6)
A8: Revenue | B8: =Actuals!B2 | C8: =Actuals!B3 | D8: =Actuals!B4 | E8: =Actuals!B5 | F8: =Actuals!B6 | G8: =Actuals!B7 | H8: =Actuals!B8 | I8: =Actuals!B9
A9: Reported FCF margin | B9: =B3/B8 | C9: =C3/C8 | D9: =D3/D8 | E9: =E3/E8 | F9: =F3/F8 | G9: =G3/G8 | H9: =H3/H8 | I9: =I3/I8
A10: Owner FCF margin | B10: =B7/B8 | C10: =C7/C8 | D10: =D7/D8 | E10: =E7/E8 | F10: =F7/F8 | G10: =G7/G8 | H10: =H7/H8 | I10: =I7/I8
A11: Memo: grants received (capex offset, not credited) | B11: =Actuals!L2 | C11: =Actuals!L3 | D11: =Actuals!L4 | E11: =Actuals!L5 | F11: =Actuals!L6 | G11: =Actuals!L7 | H11: =Actuals!L8 | I11: =Actuals!L9
A12: Memo: OCF - EBITDA (working-capital timing) | B12: =Actuals!F2-Actuals!C2 | C12: =Actuals!F3-Actuals!C3 | D12: =Actuals!F4-Actuals!C4 | E12: =Actuals!F5-Actuals!C5 | F12: =Actuals!F6-Actuals!C6 | G12: =Actuals!F7-Actuals!C7 | H12: =Actuals!F8-Actuals!C8 | I12: =Actuals!F9-Actuals!C9
A13: Memo: cash tax paid | B13: 7.261 | C13: 13.584 | D13: 26.692 | E13: 28.339 | G13: 41.586 | H13: 160.102 | I13: 35.631
A15: FY2025 cash tax of A$160m (147% of PBT) and OCF exceeding EBITDA by A$220m are both flagged abnormal: progress-payment timing and tax on the prior-year US gain; neither is a run-rate.

Sheet Valuation
A1: Scenario summary
A2: Scenario | B2: Value/share A$ | C2: Upside vs price | D2: Probability | E2: Street value/share | F2: Entry price @15% hurdle | G2: Terminal growth | H2: TV cap
A3: Bear | B3: =DCF_Bear!$B$38 | C3: =B3/Assumptions!$B$8-1 | D3: =Assumptions!$C$15 | E3: =DCF_Bear!$B$43 | F3: =IF(Assumptions!$B$9>Assumptions!$B$15,(SUMPRODUCT(DCF_Bear!$C$19:$L$19/(1+Assumptions!$B$9)^DCF_Bear!$C$4:$L$4)+MAX(0,MIN(DCF_Bear!$L$19*(1+Assumptions!$B$15)/(Assumptions!$B$9-Assumptions!$B$15),Assumptions!$D$15*DCF_Bear!$L$19))/(1+Assumptions!$B$9)^10+Assumptions!$B$6)/Assumptions!$B$7,"n/a") | G3: =Assumptions!$B$15 | H3: =Assumptions!$D$15
A4: Base | B4: =DCF_Base!$B$38 | C4: =B4/Assumptions!$B$8-1 | D4: =Assumptions!$C$16 | E4: =DCF_Base!$B$43 | F4: =IF(Assumptions!$B$9>Assumptions!$B$16,(SUMPRODUCT(DCF_Base!$C$19:$L$19/(1+Assumptions!$B$9)^DCF_Base!$C$4:$L$4)+MAX(0,MIN(DCF_Base!$L$19*(1+Assumptions!$B$16)/(Assumptions!$B$9-Assumptions!$B$16),Assumptions!$D$16*DCF_Base!$L$19))/(1+Assumptions!$B$9)^10+Assumptions!$B$6)/Assumptions!$B$7,"n/a") | G4: =Assumptions!$B$16 | H4: =Assumptions!$D$16
A5: Bull | B5: =DCF_Bull!$B$38 | C5: =B5/Assumptions!$B$8-1 | D5: =Assumptions!$C$17 | E5: =DCF_Bull!$B$43 | F5: =IF(Assumptions!$B$9>Assumptions!$B$17,(SUMPRODUCT(DCF_Bull!$C$19:$L$19/(1+Assumptions!$B$9)^DCF_Bull!$C$4:$L$4)+MAX(0,MIN(DCF_Bull!$L$19*(1+Assumptions!$B$17)/(Assumptions!$B$9-Assumptions!$B$17),Assumptions!$D$17*DCF_Bull!$L$19))/(1+Assumptions!$B$9)^10+Assumptions!$B$6)/Assumptions!$B$7,"n/a") | G5: =Assumptions!$B$17 | H5: =Assumptions!$D$17
A7: Probability-weighted value/share (house) | B7: =SUMPRODUCT(B3:B5,D3:D5)
A8: Margin of safety vs price | B8: =1-Assumptions!$B$8/B7
A9: Probability-weighted value/share (street) | B9: =SUMPRODUCT(E3:E5,D3:D5)
A10: Band position (price-house)/(street-house) | B10: =IF(ABS(B9-B7)<0.005,"n/a",(Assumptions!$B$8-B7)/(B9-B7)) | C10: Degenerate: SBC is 0.15% of revenue so the band is ~A$0.12 wide; reported as null in the JSON.
A11: Probability-weighted entry price @15% (buy-below) | B11: =SUMPRODUCT(F3:F5,D3:D5)
A13: Required-return table (base case; TV rebuilt at each rate)
A14: Required return | B14: 0.09 | C14: 0.1 | D14: 0.11 | E14: 0.12 | F14: 0.15 | G14: =Assumptions!$B$3 | H14: <- model WACC
A15: Value per share A$ | B15: =IF(B$14>Assumptions!$B$16,(SUMPRODUCT(DCF_Base!$C$19:$L$19/(1+B$14)^DCF_Base!$C$4:$L$4)+MAX(0,MIN(DCF_Base!$L$19*(1+Assumptions!$B$16)/(B$14-Assumptions!$B$16),Assumptions!$D$16*DCF_Base!$L$19))/(1+B$14)^10+Assumptions!$B$6)/Assumptions!$B$7,"n/a") | C15: =IF(C$14>Assumptions!$B$16,(SUMPRODUCT(DCF_Base!$C$19:$L$19/(1+C$14)^DCF_Base!$C$4:$L$4)+MAX(0,MIN(DCF_Base!$L$19*(1+Assumptions!$B$16)/(C$14-Assumptions!$B$16),Assumptions!$D$16*DCF_Base!$L$19))/(1+C$14)^10+Assumptions!$B$6)/Assumptions!$B$7,"n/a") | D15: =IF(D$14>Assumptions!$B$16,(SUMPRODUCT(DCF_Base!$C$19:$L$19/(1+D$14)^DCF_Base!$C$4:$L$4)+MAX(0,MIN(DCF_Base!$L$19*(1+Assumptions!$B$16)/(D$14-Assumptions!$B$16),Assumptions!$D$16*DCF_Base!$L$19))/(1+D$14)^10+Assumptions!$B$6)/Assumptions!$B$7,"n/a") | E15: =IF(E$14>Assumptions!$B$16,(SUMPRODUCT(DCF_Base!$C$19:$L$19/(1+E$14)^DCF_Base!$C$4:$L$4)+MAX(0,MIN(DCF_Base!$L$19*(1+Assumptions!$B$16)/(E$14-Assumptions!$B$16),Assumptions!$D$16*DCF_Base!$L$19))/(1+E$14)^10+Assumptions!$B$6)/Assumptions!$B$7,"n/a") | F15: =IF(F$14>Assumptions!$B$16,(SUMPRODUCT(DCF_Base!$C$19:$L$19/(1+F$14)^DCF_Base!$C$4:$L$4)+MAX(0,MIN(DCF_Base!$L$19*(1+Assumptions!$B$16)/(F$14-Assumptions!$B$16),Assumptions!$D$16*DCF_Base!$L$19))/(1+F$14)^10+Assumptions!$B$6)/Assumptions!$B$7,"n/a") | G15: =IF(G$14>Assumptions!$B$16,(SUMPRODUCT(DCF_Base!$C$19:$L$19/(1+G$14)^DCF_Base!$C$4:$L$4)+MAX(0,MIN(DCF_Base!$L$19*(1+Assumptions!$B$16)/(G$14-Assumptions!$B$16),Assumptions!$D$16*DCF_Base!$L$19))/(1+G$14)^10+Assumptions!$B$6)/Assumptions!$B$7,"n/a")
A17: Sensitivity: base value/share, WACC (rows) x terminal growth (cols)
B18: 0.015 | C18: 0.02 | D18: 0.025 | E18: 0.03 | F18: 0.035
A19: 0.08 | B19: =IF($A19>B$18,(SUMPRODUCT(DCF_Base!$C$19:$L$19/(1+$A19)^DCF_Base!$C$4:$L$4)+MAX(0,MIN(DCF_Base!$L$19*(1+B$18)/($A19-B$18),Assumptions!$D$16*DCF_Base!$L$19))/(1+$A19)^10+Assumptions!$B$6)/Assumptions!$B$7,"n/a") | C19: =IF($A19>C$18,(SUMPRODUCT(DCF_Base!$C$19:$L$19/(1+$A19)^DCF_Base!$C$4:$L$4)+MAX(0,MIN(DCF_Base!$L$19*(1+C$18)/($A19-C$18),Assumptions!$D$16*DCF_Base!$L$19))/(1+$A19)^10+Assumptions!$B$6)/Assumptions!$B$7,"n/a") | D19: =IF($A19>D$18,(SUMPRODUCT(DCF_Base!$C$19:$L$19/(1+$A19)^DCF_Base!$C$4:$L$4)+MAX(0,MIN(DCF_Base!$L$19*(1+D$18)/($A19-D$18),Assumptions!$D$16*DCF_Base!$L$19))/(1+$A19)^10+Assumptions!$B$6)/Assumptions!$B$7,"n/a") | E19: =IF($A19>E$18,(SUMPRODUCT(DCF_Base!$C$19:$L$19/(1+$A19)^DCF_Base!$C$4:$L$4)+MAX(0,MIN(DCF_Base!$L$19*(1+E$18)/($A19-E$18),Assumptions!$D$16*DCF_Base!$L$19))/(1+$A19)^10+Assumptions!$B$6)/Assumptions!$B$7,"n/a") | F19: =IF($A19>F$18,(SUMPRODUCT(DCF_Base!$C$19:$L$19/(1+$A19)^DCF_Base!$C$4:$L$4)+MAX(0,MIN(DCF_Base!$L$19*(1+F$18)/($A19-F$18),Assumptions!$D$16*DCF_Base!$L$19))/(1+$A19)^10+Assumptions!$B$6)/Assumptions!$B$7,"n/a")
A20: 0.09 | B20: =IF($A20>B$18,(SUMPRODUCT(DCF_Base!$C$19:$L$19/(1+$A20)^DCF_Base!$C$4:$L$4)+MAX(0,MIN(DCF_Base!$L$19*(1+B$18)/($A20-B$18),Assumptions!$D$16*DCF_Base!$L$19))/(1+$A20)^10+Assumptions!$B$6)/Assumptions!$B$7,"n/a") | C20: =IF($A20>C$18,(SUMPRODUCT(DCF_Base!$C$19:$L$19/(1+$A20)^DCF_Base!$C$4:$L$4)+MAX(0,MIN(DCF_Base!$L$19*(1+C$18)/($A20-C$18),Assumptions!$D$16*DCF_Base!$L$19))/(1+$A20)^10+Assumptions!$B$6)/Assumptions!$B$7,"n/a") | D20: =IF($A20>D$18,(SUMPRODUCT(DCF_Base!$C$19:$L$19/(1+$A20)^DCF_Base!$C$4:$L$4)+MAX(0,MIN(DCF_Base!$L$19*(1+D$18)/($A20-D$18),Assumptions!$D$16*DCF_Base!$L$19))/(1+$A20)^10+Assumptions!$B$6)/Assumptions!$B$7,"n/a") | E20: =IF($A20>E$18,(SUMPRODUCT(DCF_Base!$C$19:$L$19/(1+$A20)^DCF_Base!$C$4:$L$4)+MAX(0,MIN(DCF_Base!$L$19*(1+E$18)/($A20-E$18),Assumptions!$D$16*DCF_Base!$L$19))/(1+$A20)^10+Assumptions!$B$6)/Assumptions!$B$7,"n/a") | F20: =IF($A20>F$18,(SUMPRODUCT(DCF_Base!$C$19:$L$19/(1+$A20)^DCF_Base!$C$4:$L$4)+MAX(0,MIN(DCF_Base!$L$19*(1+F$18)/($A20-F$18),Assumptions!$D$16*DCF_Base!$L$19))/(1+$A20)^10+Assumptions!$B$6)/Assumptions!$B$7,"n/a")
A21: 0.1 | B21: =IF($A21>B$18,(SUMPRODUCT(DCF_Base!$C$19:$L$19/(1+$A21)^DCF_Base!$C$4:$L$4)+MAX(0,MIN(DCF_Base!$L$19*(1+B$18)/($A21-B$18),Assumptions!$D$16*DCF_Base!$L$19))/(1+$A21)^10+Assumptions!$B$6)/Assumptions!$B$7,"n/a") | C21: =IF($A21>C$18,(SUMPRODUCT(DCF_Base!$C$19:$L$19/(1+$A21)^DCF_Base!$C$4:$L$4)+MAX(0,MIN(DCF_Base!$L$19*(1+C$18)/($A21-C$18),Assumptions!$D$16*DCF_Base!$L$19))/(1+$A21)^10+Assumptions!$B$6)/Assumptions!$B$7,"n/a") | D21: =IF($A21>D$18,(SUMPRODUCT(DCF_Base!$C$19:$L$19/(1+$A21)^DCF_Base!$C$4:$L$4)+MAX(0,MIN(DCF_Base!$L$19*(1+D$18)/($A21-D$18),Assumptions!$D$16*DCF_Base!$L$19))/(1+$A21)^10+Assumptions!$B$6)/Assumptions!$B$7,"n/a") | E21: =IF($A21>E$18,(SUMPRODUCT(DCF_Base!$C$19:$L$19/(1+$A21)^DCF_Base!$C$4:$L$4)+MAX(0,MIN(DCF_Base!$L$19*(1+E$18)/($A21-E$18),Assumptions!$D$16*DCF_Base!$L$19))/(1+$A21)^10+Assumptions!$B$6)/Assumptions!$B$7,"n/a") | F21: =IF($A21>F$18,(SUMPRODUCT(DCF_Base!$C$19:$L$19/(1+$A21)^DCF_Base!$C$4:$L$4)+MAX(0,MIN(DCF_Base!$L$19*(1+F$18)/($A21-F$18),Assumptions!$D$16*DCF_Base!$L$19))/(1+$A21)^10+Assumptions!$B$6)/Assumptions!$B$7,"n/a")
A22: 0.11 | B22: =IF($A22>B$18,(SUMPRODUCT(DCF_Base!$C$19:$L$19/(1+$A22)^DCF_Base!$C$4:$L$4)+MAX(0,MIN(DCF_Base!$L$19*(1+B$18)/($A22-B$18),Assumptions!$D$16*DCF_Base!$L$19))/(1+$A22)^10+Assumptions!$B$6)/Assumptions!$B$7,"n/a") | C22: =IF($A22>C$18,(SUMPRODUCT(DCF_Base!$C$19:$L$19/(1+$A22)^DCF_Base!$C$4:$L$4)+MAX(0,MIN(DCF_Base!$L$19*(1+C$18)/($A22-C$18),Assumptions!$D$16*DCF_Base!$L$19))/(1+$A22)^10+Assumptions!$B$6)/Assumptions!$B$7,"n/a") | D22: =IF($A22>D$18,(SUMPRODUCT(DCF_Base!$C$19:$L$19/(1+$A22)^DCF_Base!$C$4:$L$4)+MAX(0,MIN(DCF_Base!$L$19*(1+D$18)/($A22-D$18),Assumptions!$D$16*DCF_Base!$L$19))/(1+$A22)^10+Assumptions!$B$6)/Assumptions!$B$7,"n/a") | E22: =IF($A22>E$18,(SUMPRODUCT(DCF_Base!$C$19:$L$19/(1+$A22)^DCF_Base!$C$4:$L$4)+MAX(0,MIN(DCF_Base!$L$19*(1+E$18)/($A22-E$18),Assumptions!$D$16*DCF_Base!$L$19))/(1+$A22)^10+Assumptions!$B$6)/Assumptions!$B$7,"n/a") | F22: =IF($A22>F$18,(SUMPRODUCT(DCF_Base!$C$19:$L$19/(1+$A22)^DCF_Base!$C$4:$L$4)+MAX(0,MIN(DCF_Base!$L$19*(1+F$18)/($A22-F$18),Assumptions!$D$16*DCF_Base!$L$19))/(1+$A22)^10+Assumptions!$B$6)/Assumptions!$B$7,"n/a")
A23: 0.12 | B23: =IF($A23>B$18,(SUMPRODUCT(DCF_Base!$C$19:$L$19/(1+$A23)^DCF_Base!$C$4:$L$4)+MAX(0,MIN(DCF_Base!$L$19*(1+B$18)/($A23-B$18),Assumptions!$D$16*DCF_Base!$L$19))/(1+$A23)^10+Assumptions!$B$6)/Assumptions!$B$7,"n/a") | C23: =IF($A23>C$18,(SUMPRODUCT(DCF_Base!$C$19:$L$19/(1+$A23)^DCF_Base!$C$4:$L$4)+MAX(0,MIN(DCF_Base!$L$19*(1+C$18)/($A23-C$18),Assumptions!$D$16*DCF_Base!$L$19))/(1+$A23)^10+Assumptions!$B$6)/Assumptions!$B$7,"n/a") | D23: =IF($A23>D$18,(SUMPRODUCT(DCF_Base!$C$19:$L$19/(1+$A23)^DCF_Base!$C$4:$L$4)+MAX(0,MIN(DCF_Base!$L$19*(1+D$18)/($A23-D$18),Assumptions!$D$16*DCF_Base!$L$19))/(1+$A23)^10+Assumptions!$B$6)/Assumptions!$B$7,"n/a") | E23: =IF($A23>E$18,(SUMPRODUCT(DCF_Base!$C$19:$L$19/(1+$A23)^DCF_Base!$C$4:$L$4)+MAX(0,MIN(DCF_Base!$L$19*(1+E$18)/($A23-E$18),Assumptions!$D$16*DCF_Base!$L$19))/(1+$A23)^10+Assumptions!$B$6)/Assumptions!$B$7,"n/a") | F23: =IF($A23>F$18,(SUMPRODUCT(DCF_Base!$C$19:$L$19/(1+$A23)^DCF_Base!$C$4:$L$4)+MAX(0,MIN(DCF_Base!$L$19*(1+F$18)/($A23-F$18),Assumptions!$D$16*DCF_Base!$L$19))/(1+$A23)^10+Assumptions!$B$6)/Assumptions!$B$7,"n/a")
A26: Takeover overlay memo (hardcoded from JSON; deal is for Austal USA only)
A27: Austal USA bid range, US$m EV | B27: 1,050 / 1,200 / 1,350
A28: AUDUSD used | B28: 0.7138
A29: SOTP deal-completes A$/share low / mid / high | B29: 3.99 / 4.94 / 5.94
A30: Deal probability (judgment) | B30: 0.5
A31: Deal-adjusted IV A$/share | B31: 3.74
A32: Market-implied deal probability at mid SOTP | B32: 0.83
