Workbook

Sheet DCF Model
A1: IFT.NZ DCF Valuation Model
A2: Gray cells are INPUTS - adjust to see valuation change
A3: Infratil is an investment holding company - FCF based on normalized distributable earnings
A5: KEY INPUTS
A6: Current Stock Price (NZD) | B6: 11.03
A7: Shares Outstanding (M) | B7: 979.6
A8: Net Debt (NZD M) | B8: 2622.2
A10: Base Year FCF (NZD M) | B10: 600 | C10: Normalized from FY22-24 avg adjusted for growth
A12: WACC | B12: 0.105
A13: Terminal Growth Rate | B13: 0.03
A16: GROWTH ASSUMPTIONS | B16: Year 1 | C16: Year 2 | D16: Year 3 | E16: Year 4 | F16: Year 5
A17: FCF Growth Rate | B17: 0.18 | C17: 0.16 | D17: 0.14 | E17: 0.12 | F17: 0.1
A19: PROJECTIONS
B20: Base | C20: Year 1 | D20: Year 2 | E20: Year 3 | F20: Year 4 | G20: Year 5
A21: Free Cash Flow (NZD M) | B21: =B10 -> 0 | C21: =B21*(1+B17) -> 0 | D21: =C21*(1+C17) -> 0 | E21: =D21*(1+D17) -> 0 | F21: =E21*(1+E17) -> 0 | G21: =F21*(1+F17) -> 0
A22: Discount Factor | C22: =1/(1+$B$12)^1 -> 0 | D22: =1/(1+$B$12)^2 -> 0 | E22: =1/(1+$B$12)^3 -> 0 | F22: =1/(1+$B$12)^4 -> 0 | G22: =1/(1+$B$12)^5 -> 0
A23: PV of FCF | C23: =C21*C22 -> 0 | D23: =D21*D22 -> 0 | E23: =E21*E22 -> 0 | F23: =F21*F22 -> 0 | G23: =G21*G22 -> 0
A25: VALUATION
A26: Sum of PV of FCF | B26: =SUM(C23:G23) -> 0
A27: Terminal FCF (Year 5 * (1+g)) | B27: =G21*(1+$B$13) -> 0
A28: Terminal Value | B28: =B27/($B$12-$B$13) -> 0
A29: PV of Terminal Value | B29: =B28*G22 -> 0
A30: Enterprise Value | B30: =B26+B29 -> 0
A31: Less: Net Debt | B31: =B8 -> 0
A32: Equity Value | B32: =B30-B31 -> 0
A33: INTRINSIC VALUE/SHARE | B33: =B32/B7 -> 0
A34: Upside to IV | B34: =(B33-B6)/B6 -> 0
A36: ENTRY PRICE (15% CAGR Target)
A37: Terminal Value per Share | B37: =B28/B7 -> 0
A38: Entry Price (15% CAGR) | B38: =B37/(1.15^5) -> 0
A39: Discount from Current Price | B39: =(B38-B6)/B6 -> 0
A41: SCENARIO COMPARISON
A42: Scenario | B42: Base | C42: Bull | D42: Bear
A43: Intrinsic Value | B43: =B33 -> 0 | C43: 16.44 | D43: 4.82
A44: Upside/Downside | B44: =B34 -> 0 | C44: 0.49 | D44: -0.563
A45: Entry Price (15% CAGR) | B45: =B38 -> 0 | C45: 11.66 | D45: 4.19

Sheet Sensitivity
A1: Sensitivity Analysis
A2: Intrinsic Value by WACC & Terminal Growth Rate
A4: WACC \ Term G | B4: 0.02 | C4: 0.025 | D4: 0.03 | E4: 0.035 | F4: 0.04
A5: 0.085 | B5: =(('DCF Model'!$B$10*1.18*1.16*1.14*1.12*1.10*(1+0.02))/(0.085-0.02))/(1+0.085)^5/('DCF Model'!$B$7)+('DCF Model'!$B$10*1.18/(1+0.085)+'DCF Model'!$B$10*1.18*1.16/(1+0.085)^2+'DCF Model'!$B$10*1.18*1.16*1.14/(1+0.085)^3+'DCF Model'!$B$10*1.18*1.16*1.14*1.12/(1+0.085)^4+'DCF Model'!$B$10*1.18*1.16*1.14*1.12*1.10/(1+0.085)^5)/'DCF Model'!$B$7-'DCF Model'!$B$8/'DCF Model'!$B$7 -> 0 | C5: =(('DCF Model'!$B$10*1.18*1.16*1.14*1.12*1.10*(1+0.025))/(0.085-0.025))/(1+0.085)^5/('DCF Model'!$B$7)+('DCF Model'!$B$10*1.18/(1+0.085)+'DCF Model'!$B$10*1.18*1.16/(1+0.085)^2+'DCF Model'!$B$10*1.18*1.16*1.14/(1+0.085)^3+'DCF Model'!$B$10*1.18*1.16*1.14*1.12/(1+0.085)^4+'DCF Model'!$B$10*1.18*1.16*1.14*1.12*1.10/(1+0.085)^5)/'DCF Model'!$B$7-'DCF Model'!$B$8/'DCF Model'!$B$7 -> 0 | D5: =(('DCF Model'!$B$10*1.18*1.16*1.14*1.12*1.10*(1+0.03))/(0.085-0.03))/(1+0.085)^5/('DCF Model'!$B$7)+('DCF Model'!$B$10*1.18/(1+0.085)+'DCF Model'!$B$10*1.18*1.16/(1+0.085)^2+'DCF Model'!$B$10*1.18*1.16*1.14/(1+0.085)^3+'DCF Model'!$B$10*1.18*1.16*1.14*1.12/(1+0.085)^4+'DCF Model'!$B$10*1.18*1.16*1.14*1.12*1.10/(1+0.085)^5)/'DCF Model'!$B$7-'DCF Model'!$B$8/'DCF Model'!$B$7 -> 0 | E5: =(('DCF Model'!$B$10*1.18*1.16*1.14*1.12*1.10*(1+0.035))/(0.085-0.035))/(1+0.085)^5/('DCF Model'!$B$7)+('DCF Model'!$B$10*1.18/(1+0.085)+'DCF Model'!$B$10*1.18*1.16/(1+0.085)^2+'DCF Model'!$B$10*1.18*1.16*1.14/(1+0.085)^3+'DCF Model'!$B$10*1.18*1.16*1.14*1.12/(1+0.085)^4+'DCF Model'!$B$10*1.18*1.16*1.14*1.12*1.10/(1+0.085)^5)/'DCF Model'!$B$7-'DCF Model'!$B$8/'DCF Model'!$B$7 -> 0 | F5: =(('DCF Model'!$B$10*1.18*1.16*1.14*1.12*1.10*(1+0.04))/(0.085-0.04))/(1+0.085)^5/('DCF Model'!$B$7)+('DCF Model'!$B$10*1.18/(1+0.085)+'DCF Model'!$B$10*1.18*1.16/(1+0.085)^2+'DCF Model'!$B$10*1.18*1.16*1.14/(1+0.085)^3+'DCF Model'!$B$10*1.18*1.16*1.14*1.12/(1+0.085)^4+'DCF Model'!$B$10*1.18*1.16*1.14*1.12*1.10/(1+0.085)^5)/'DCF Model'!$B$7-'DCF Model'!$B$8/'DCF Model'!$B$7 -> 0
A6: 0.095 | B6: =(('DCF Model'!$B$10*1.18*1.16*1.14*1.12*1.10*(1+0.02))/(0.095-0.02))/(1+0.095)^5/('DCF Model'!$B$7)+('DCF Model'!$B$10*1.18/(1+0.095)+'DCF Model'!$B$10*1.18*1.16/(1+0.095)^2+'DCF Model'!$B$10*1.18*1.16*1.14/(1+0.095)^3+'DCF Model'!$B$10*1.18*1.16*1.14*1.12/(1+0.095)^4+'DCF Model'!$B$10*1.18*1.16*1.14*1.12*1.10/(1+0.095)^5)/'DCF Model'!$B$7-'DCF Model'!$B$8/'DCF Model'!$B$7 -> 0 | C6: =(('DCF Model'!$B$10*1.18*1.16*1.14*1.12*1.10*(1+0.025))/(0.095-0.025))/(1+0.095)^5/('DCF Model'!$B$7)+('DCF Model'!$B$10*1.18/(1+0.095)+'DCF Model'!$B$10*1.18*1.16/(1+0.095)^2+'DCF Model'!$B$10*1.18*1.16*1.14/(1+0.095)^3+'DCF Model'!$B$10*1.18*1.16*1.14*1.12/(1+0.095)^4+'DCF Model'!$B$10*1.18*1.16*1.14*1.12*1.10/(1+0.095)^5)/'DCF Model'!$B$7-'DCF Model'!$B$8/'DCF Model'!$B$7 -> 0 | D6: =(('DCF Model'!$B$10*1.18*1.16*1.14*1.12*1.10*(1+0.03))/(0.095-0.03))/(1+0.095)^5/('DCF Model'!$B$7)+('DCF Model'!$B$10*1.18/(1+0.095)+'DCF Model'!$B$10*1.18*1.16/(1+0.095)^2+'DCF Model'!$B$10*1.18*1.16*1.14/(1+0.095)^3+'DCF Model'!$B$10*1.18*1.16*1.14*1.12/(1+0.095)^4+'DCF Model'!$B$10*1.18*1.16*1.14*1.12*1.10/(1+0.095)^5)/'DCF Model'!$B$7-'DCF Model'!$B$8/'DCF Model'!$B$7 -> 0 | E6: =(('DCF Model'!$B$10*1.18*1.16*1.14*1.12*1.10*(1+0.035))/(0.095-0.035))/(1+0.095)^5/('DCF Model'!$B$7)+('DCF Model'!$B$10*1.18/(1+0.095)+'DCF Model'!$B$10*1.18*1.16/(1+0.095)^2+'DCF Model'!$B$10*1.18*1.16*1.14/(1+0.095)^3+'DCF Model'!$B$10*1.18*1.16*1.14*1.12/(1+0.095)^4+'DCF Model'!$B$10*1.18*1.16*1.14*1.12*1.10/(1+0.095)^5)/'DCF Model'!$B$7-'DCF Model'!$B$8/'DCF Model'!$B$7 -> 0 | F6: =(('DCF Model'!$B$10*1.18*1.16*1.14*1.12*1.10*(1+0.04))/(0.095-0.04))/(1+0.095)^5/('DCF Model'!$B$7)+('DCF Model'!$B$10*1.18/(1+0.095)+'DCF Model'!$B$10*1.18*1.16/(1+0.095)^2+'DCF Model'!$B$10*1.18*1.16*1.14/(1+0.095)^3+'DCF Model'!$B$10*1.18*1.16*1.14*1.12/(1+0.095)^4+'DCF Model'!$B$10*1.18*1.16*1.14*1.12*1.10/(1+0.095)^5)/'DCF Model'!$B$7-'DCF Model'!$B$8/'DCF Model'!$B$7 -> 0
A7: 0.105 | B7: =(('DCF Model'!$B$10*1.18*1.16*1.14*1.12*1.10*(1+0.02))/(0.105-0.02))/(1+0.105)^5/('DCF Model'!$B$7)+('DCF Model'!$B$10*1.18/(1+0.105)+'DCF Model'!$B$10*1.18*1.16/(1+0.105)^2+'DCF Model'!$B$10*1.18*1.16*1.14/(1+0.105)^3+'DCF Model'!$B$10*1.18*1.16*1.14*1.12/(1+0.105)^4+'DCF Model'!$B$10*1.18*1.16*1.14*1.12*1.10/(1+0.105)^5)/'DCF Model'!$B$7-'DCF Model'!$B$8/'DCF Model'!$B$7 -> 0 | C7: =(('DCF Model'!$B$10*1.18*1.16*1.14*1.12*1.10*(1+0.025))/(0.105-0.025))/(1+0.105)^5/('DCF Model'!$B$7)+('DCF Model'!$B$10*1.18/(1+0.105)+'DCF Model'!$B$10*1.18*1.16/(1+0.105)^2+'DCF Model'!$B$10*1.18*1.16*1.14/(1+0.105)^3+'DCF Model'!$B$10*1.18*1.16*1.14*1.12/(1+0.105)^4+'DCF Model'!$B$10*1.18*1.16*1.14*1.12*1.10/(1+0.105)^5)/'DCF Model'!$B$7-'DCF Model'!$B$8/'DCF Model'!$B$7 -> 0 | D7: =(('DCF Model'!$B$10*1.18*1.16*1.14*1.12*1.10*(1+0.03))/(0.105-0.03))/(1+0.105)^5/('DCF Model'!$B$7)+('DCF Model'!$B$10*1.18/(1+0.105)+'DCF Model'!$B$10*1.18*1.16/(1+0.105)^2+'DCF Model'!$B$10*1.18*1.16*1.14/(1+0.105)^3+'DCF Model'!$B$10*1.18*1.16*1.14*1.12/(1+0.105)^4+'DCF Model'!$B$10*1.18*1.16*1.14*1.12*1.10/(1+0.105)^5)/'DCF Model'!$B$7-'DCF Model'!$B$8/'DCF Model'!$B$7 -> 0 | E7: =(('DCF Model'!$B$10*1.18*1.16*1.14*1.12*1.10*(1+0.035))/(0.105-0.035))/(1+0.105)^5/('DCF Model'!$B$7)+('DCF Model'!$B$10*1.18/(1+0.105)+'DCF Model'!$B$10*1.18*1.16/(1+0.105)^2+'DCF Model'!$B$10*1.18*1.16*1.14/(1+0.105)^3+'DCF Model'!$B$10*1.18*1.16*1.14*1.12/(1+0.105)^4+'DCF Model'!$B$10*1.18*1.16*1.14*1.12*1.10/(1+0.105)^5)/'DCF Model'!$B$7-'DCF Model'!$B$8/'DCF Model'!$B$7 -> 0 | F7: =(('DCF Model'!$B$10*1.18*1.16*1.14*1.12*1.10*(1+0.04))/(0.105-0.04))/(1+0.105)^5/('DCF Model'!$B$7)+('DCF Model'!$B$10*1.18/(1+0.105)+'DCF Model'!$B$10*1.18*1.16/(1+0.105)^2+'DCF Model'!$B$10*1.18*1.16*1.14/(1+0.105)^3+'DCF Model'!$B$10*1.18*1.16*1.14*1.12/(1+0.105)^4+'DCF Model'!$B$10*1.18*1.16*1.14*1.12*1.10/(1+0.105)^5)/'DCF Model'!$B$7-'DCF Model'!$B$8/'DCF Model'!$B$7 -> 0
A8: 0.115 | B8: =(('DCF Model'!$B$10*1.18*1.16*1.14*1.12*1.10*(1+0.02))/(0.115-0.02))/(1+0.115)^5/('DCF Model'!$B$7)+('DCF Model'!$B$10*1.18/(1+0.115)+'DCF Model'!$B$10*1.18*1.16/(1+0.115)^2+'DCF Model'!$B$10*1.18*1.16*1.14/(1+0.115)^3+'DCF Model'!$B$10*1.18*1.16*1.14*1.12/(1+0.115)^4+'DCF Model'!$B$10*1.18*1.16*1.14*1.12*1.10/(1+0.115)^5)/'DCF Model'!$B$7-'DCF Model'!$B$8/'DCF Model'!$B$7 -> 0 | C8: =(('DCF Model'!$B$10*1.18*1.16*1.14*1.12*1.10*(1+0.025))/(0.115-0.025))/(1+0.115)^5/('DCF Model'!$B$7)+('DCF Model'!$B$10*1.18/(1+0.115)+'DCF Model'!$B$10*1.18*1.16/(1+0.115)^2+'DCF Model'!$B$10*1.18*1.16*1.14/(1+0.115)^3+'DCF Model'!$B$10*1.18*1.16*1.14*1.12/(1+0.115)^4+'DCF Model'!$B$10*1.18*1.16*1.14*1.12*1.10/(1+0.115)^5)/'DCF Model'!$B$7-'DCF Model'!$B$8/'DCF Model'!$B$7 -> 0 | D8: =(('DCF Model'!$B$10*1.18*1.16*1.14*1.12*1.10*(1+0.03))/(0.115-0.03))/(1+0.115)^5/('DCF Model'!$B$7)+('DCF Model'!$B$10*1.18/(1+0.115)+'DCF Model'!$B$10*1.18*1.16/(1+0.115)^2+'DCF Model'!$B$10*1.18*1.16*1.14/(1+0.115)^3+'DCF Model'!$B$10*1.18*1.16*1.14*1.12/(1+0.115)^4+'DCF Model'!$B$10*1.18*1.16*1.14*1.12*1.10/(1+0.115)^5)/'DCF Model'!$B$7-'DCF Model'!$B$8/'DCF Model'!$B$7 -> 0 | E8: =(('DCF Model'!$B$10*1.18*1.16*1.14*1.12*1.10*(1+0.035))/(0.115-0.035))/(1+0.115)^5/('DCF Model'!$B$7)+('DCF Model'!$B$10*1.18/(1+0.115)+'DCF Model'!$B$10*1.18*1.16/(1+0.115)^2+'DCF Model'!$B$10*1.18*1.16*1.14/(1+0.115)^3+'DCF Model'!$B$10*1.18*1.16*1.14*1.12/(1+0.115)^4+'DCF Model'!$B$10*1.18*1.16*1.14*1.12*1.10/(1+0.115)^5)/'DCF Model'!$B$7-'DCF Model'!$B$8/'DCF Model'!$B$7 -> 0 | F8: =(('DCF Model'!$B$10*1.18*1.16*1.14*1.12*1.10*(1+0.04))/(0.115-0.04))/(1+0.115)^5/('DCF Model'!$B$7)+('DCF Model'!$B$10*1.18/(1+0.115)+'DCF Model'!$B$10*1.18*1.16/(1+0.115)^2+'DCF Model'!$B$10*1.18*1.16*1.14/(1+0.115)^3+'DCF Model'!$B$10*1.18*1.16*1.14*1.12/(1+0.115)^4+'DCF Model'!$B$10*1.18*1.16*1.14*1.12*1.10/(1+0.115)^5)/'DCF Model'!$B$7-'DCF Model'!$B$8/'DCF Model'!$B$7 -> 0
A9: 0.125 | B9: =(('DCF Model'!$B$10*1.18*1.16*1.14*1.12*1.10*(1+0.02))/(0.125-0.02))/(1+0.125)^5/('DCF Model'!$B$7)+('DCF Model'!$B$10*1.18/(1+0.125)+'DCF Model'!$B$10*1.18*1.16/(1+0.125)^2+'DCF Model'!$B$10*1.18*1.16*1.14/(1+0.125)^3+'DCF Model'!$B$10*1.18*1.16*1.14*1.12/(1+0.125)^4+'DCF Model'!$B$10*1.18*1.16*1.14*1.12*1.10/(1+0.125)^5)/'DCF Model'!$B$7-'DCF Model'!$B$8/'DCF Model'!$B$7 -> 0 | C9: =(('DCF Model'!$B$10*1.18*1.16*1.14*1.12*1.10*(1+0.025))/(0.125-0.025))/(1+0.125)^5/('DCF Model'!$B$7)+('DCF Model'!$B$10*1.18/(1+0.125)+'DCF Model'!$B$10*1.18*1.16/(1+0.125)^2+'DCF Model'!$B$10*1.18*1.16*1.14/(1+0.125)^3+'DCF Model'!$B$10*1.18*1.16*1.14*1.12/(1+0.125)^4+'DCF Model'!$B$10*1.18*1.16*1.14*1.12*1.10/(1+0.125)^5)/'DCF Model'!$B$7-'DCF Model'!$B$8/'DCF Model'!$B$7 -> 0 | D9: =(('DCF Model'!$B$10*1.18*1.16*1.14*1.12*1.10*(1+0.03))/(0.125-0.03))/(1+0.125)^5/('DCF Model'!$B$7)+('DCF Model'!$B$10*1.18/(1+0.125)+'DCF Model'!$B$10*1.18*1.16/(1+0.125)^2+'DCF Model'!$B$10*1.18*1.16*1.14/(1+0.125)^3+'DCF Model'!$B$10*1.18*1.16*1.14*1.12/(1+0.125)^4+'DCF Model'!$B$10*1.18*1.16*1.14*1.12*1.10/(1+0.125)^5)/'DCF Model'!$B$7-'DCF Model'!$B$8/'DCF Model'!$B$7 -> 0 | E9: =(('DCF Model'!$B$10*1.18*1.16*1.14*1.12*1.10*(1+0.035))/(0.125-0.035))/(1+0.125)^5/('DCF Model'!$B$7)+('DCF Model'!$B$10*1.18/(1+0.125)+'DCF Model'!$B$10*1.18*1.16/(1+0.125)^2+'DCF Model'!$B$10*1.18*1.16*1.14/(1+0.125)^3+'DCF Model'!$B$10*1.18*1.16*1.14*1.12/(1+0.125)^4+'DCF Model'!$B$10*1.18*1.16*1.14*1.12*1.10/(1+0.125)^5)/'DCF Model'!$B$7-'DCF Model'!$B$8/'DCF Model'!$B$7 -> 0 | F9: =(('DCF Model'!$B$10*1.18*1.16*1.14*1.12*1.10*(1+0.04))/(0.125-0.04))/(1+0.125)^5/('DCF Model'!$B$7)+('DCF Model'!$B$10*1.18/(1+0.125)+'DCF Model'!$B$10*1.18*1.16/(1+0.125)^2+'DCF Model'!$B$10*1.18*1.16*1.14/(1+0.125)^3+'DCF Model'!$B$10*1.18*1.16*1.14*1.12/(1+0.125)^4+'DCF Model'!$B$10*1.18*1.16*1.14*1.12*1.10/(1+0.125)^5)/'DCF Model'!$B$7-'DCF Model'!$B$8/'DCF Model'!$B$7 -> 0
A11: Current Price: | B11: ="NZ$" & TEXT('DCF Model'!B6,"0.00") -> 0

Sheet Historical
A1: Historical Growth Rates
A3: Metric | B3: 3-Year CAGR | C3: 5-Year CAGR
A4: ShareOfEBITDAF (Revenue) | B4: 0.218
A5: TotalEquity (Book Value) | B5: 0.286
A7: Selected Growth Rate: | B7: 0.2
A8: Source: | B8: equity_3yr_cagr_adjusted
A10: Note:
A11: Infratil as an investment holding company has volatile net income/FCF due to revaluations. Using ShareOfEBITDAF (21.8% CAGR) and TotalEquity (28.6% CAGR) as primary growth indicators. Selected 20% conservative rate given strong CDC/Longroad growth drivers.
A15: Historical Financials (NZD M)
A16: Fiscal Year | B16: FY2022 | C16: FY2023 | D16: FY2024 | E16: FY2025
A17: ShareOfEBITDAF | B17: 507 | C17: 533.3 | D17: 863.8 | E17: 917.8
A18: NetParentSurplus | B18: 1169.3 | C18: 643.1 | D18: 769.9 | E18: -286.3
A19: TotalEquity | B19: 7679.2 | C19: 9182.3 | D19: 11944.3 | E19: 16115.9

Sheet Assumptions
A1: Infratil DCF Valuation - Key Assumptions & Notes
A4: VALUATION APPROACH
A5: Infratil is an infrastructure investment holding company, not an operating business. Traditional DCF is challenging due to: (1) Volatile net income from portfolio revaluations, (2) No traditional revenue/operating margins, (3) Value primarily from portfolio NAV appreciation and distributions. This DCF uses normalized FCF based on proportionate EBITDAF trends and historical distribution capacity.
A8: GROWTH RATE JUSTIFICATION
A9: Base case 18-10% declining growth over 5 years reflects: (1) CDC targeting to double FY25 EBITDAF by FY27 (implies ~40% CAGR near-term), (2) Longroad scaling from 3.5GW to 10GW by 2028, (3) Contact-Manawa merger synergies, (4) Offset by One NZ maturity and NZ economic headwinds, (5) Deceleration toward terminal as high-growth projects mature.
A12: WACC CALCULATION
A13: Base WACC 10.5% = Risk-free rate 4.5% (NZ 10-year govt bond) + Beta 1.2 (infrastructure with growth premium) × Equity risk premium 5% + Small cap premium 0.5%. Bull case 9.5% assumes de-risking as CDC/Longroad deliver. Bear case 12% reflects elevated interest rates and execution risk premium.
A16: TERMINAL GROWTH JUSTIFICATION
A17: 3% terminal growth aligns with long-term GDP growth for diversified NZ/Australia/US portfolio. Infrastructure assets should grow with nominal GDP. Below historical given mature portfolio mix in terminal year.
A20: KEY CONSIDERATIONS
A21: • CDC concentration (41% of portfolio) drives much of the growth outlook - bull/bear cases heavily dependent on data centre demand trajectory
A22: • Current price NZ$11.03 is below analyst consensus NZ$13.58, suggesting market pricing in execution risks or CDC valuation concerns
... A37: Fair Value NZ$10.33 (base case) implies limited upside from current NZ$11.03, but probability-weighted IV of NZ$11.10 suggests Hold. Stock is fairly valued for balanced bull/bear risk. Entry price NZ$7.81 would provide attractive 15% CAGR to terminal. Monitor: (1) CDC contract announcements, (2) Divestment execution, (3) NZ economic recovery, (4) Interest rate trajectory.
