Workbook

Sheet Model_Info
A1: CAP.PA - Capgemini SE DCF model
A2: Version | B2: v1 2026-09-01 - fresh build, no prior DCF superseded
A3: Built by | B3: dcf-analyst agent (Claude Fable 5), 2026-09-01, at the user's request via the research pipeline
A4: Model | B4: Owner-FCF component DCF, 10-year horizon, three scenarios at a single EUR 8.0% WACC; terminal = MAX(0, MIN(Gordon, 15x FCF_N))
A5: Why this model | B5: Global IT-services operating company (asset-light, cash-generative) - dcf-methods routing table row 1/2; section 7 adaptations applied (EUR WACC, IFRS-16 leases, statutory margins)
A6: Price anchor | B6: EUR 107.25, Yahoo regular close 2026-08-31T15:35:13Z. Goes stale immediately - refresh before use.
A7: Balance sheet anchor | B7: 2026-06-30 (H1 FY2026 interim report): net debt EUR 6,454m COMPANY-DISCLOSED (ex-lease, nets cash-management assets; NOT total_debt-cash), shares 168.3m basic outstanding
A8: FY0 flows | B8: FY2025 annual report: OCF 2,482 - capex 287 - lease principal 296 - SBC 266 = owner FCF EUR 1,633m
A9: Guidance vintage | B9: H1-2026 results 2026-07-30: FY2026 cc growth raised to +8.5/9.0%, APM margin 13.6-13.8% maintained, organic FCF ~EUR 1.8-1.9bn maintained
A10: Margin basis | B10: STATUTORY, not the operating-margin APM: the APM excludes recurring Fit-for-Growth restructuring (~EUR 700m FY2026-27), M&A amortization and SBC. H1-2026: statutory 7.3% vs APM 12.5%.
A11: Lease treatment | B11: Treatment B (owner-fcf.md 7b): lease cash charged in the flows (1.3% of revenue), lease liabilities EXCLUDED from net debt - matches Capgemini's own ex-lease net-debt APM. da_pct 1.8% is non-lease D&A only.
A12: SBC / share count | B12: SBC (1.1% of revenue) fully expensed AND count flat at 168.3m - charge once. Diluted 174.4m not used: ~6m of the gap is unvested performance shares whose cost IS the SBC line. Buybacks (EUR 543m FY2025) fund the flat count.
A13: Scenario drivers | B13: Agent judgment, set 2026-09-01 from FY2025 URD + H1-2026 report + Analysis JSON. Bear weighted 30% (AI structural deflation + leverage + goodwill>equity); base 50%; bull 20%.
... A17: Staleness | B17: All figures go stale. Anchors dated above; do not reuse without refreshing price, net debt and share count.

Sheet Actuals
A1: Actuals (EUR millions; source CAP.PA_Metrics.csv from the annual reports; pre-2019 = pre-IFRS16, leases in opex)
A2: Period | B2: FY2015 | C2: FY2016 | D2: FY2017 | E2: FY2018 | F2: FY2019 | G2: FY2020 | H2: FY2021 | I2: FY2022 | J2: FY2023 | K2: FY2024 | L2: FY2025
A3: Revenue | B3: 11915 | C3: 12539 | D3: 12792 | E3: 13197 | F3: 14125 | G3: 15848 | H3: 18160 | I3: 21995 | J3: 22522 | K3: 22096 | L3: 22465
A4: Operating income (statutory) | B4: 1022 | C4: 1148 | D4: 1183 | E4: 1251 | F4: 1433 | G4: 1502 | H4: 1839 | I4: 2393 | J4: 2346 | K4: 2356 | L4: 2199
A5: Operating margin % (statutory) | B5: 8.6 | C5: 9.2 | D5: 9.2 | E5: 9.5 | F5: 10.1 | G5: 9.5 | H5: 10.1 | I5: 10.9 | J5: 10.4 | K5: 10.7 | L5: 9.8
A6: Operating margin APM (EUR m) | B6: 1262 | C6: 1440 | D6: 1493 | E6: 1597 | F6: 1741 | G6: 1879 | H6: 2340 | I6: 2867 | J6: 2991 | K6: 2934 | L6: 2983
A7: Net income | B7: 1107 | C7: 908 | D7: 808 | E7: 724 | F7: 852 | G7: 955 | H7: 1159 | I7: 1550 | J7: 1668 | K7: 1677 | L7: 1607
A8: EPS (EUR) | B8: 6.67 | C8: 5.44 | D8: 4.88 | E8: 4.37 | F8: 5.15 | G8: 5.71 | H8: 6.87 | I8: 9.09 | J8: 9.7 | K8: 9.82 | L8: 9.46
A9: Operating cash flow | B9: 1004 | C9: 1319 | D9: 1330 | E9: 1396 | F9: 1794 | G9: 1661 | H9: 2581 | I9: 2517 | J9: 2525 | K9: 2526 | L9: 2482
A10: Capex | B10: 198 | C10: 197 | D10: 241 | E10: 236 | F10: 222 | G10: 206 | H10: 266 | I10: 290 | J10: 259 | K10: 315 | L10: 287
A11: Lease principal repaid | B11: 0 | C11: 0 | D11: 0 | E11: 0 | F11: 272 | G11: 291 | H11: 320 | I11: 311 | J11: 297 | K11: 292 | L11: 296
A12: SBC (cash-flow add-back) | B12: 32 | C12: 54 | D12: 64 | E12: 84 | F12: 88 | G12: 93 | H12: 125 | I12: 164 | J12: 252 | K12: 273 | L12: 266
A13: Cash taxes paid | B13: 137 | C13: 167 | D13: 139 | E13: 205 | F13: 217 | G13: 351 | H13: 440 | I13: 451 | J13: 463 | K13: 521 | L13: 474
A14: Shareholders equity | B14: 6887 | C14: 7272 | D14: 6956 | E14: 7480 | F14: 8424 | G14: 6103 | H14: 8467 | I14: 9727 | J14: 10454 | K14: 11775 | L14: 11648
A15: Shares outstanding (m) | B15: 168.5 | C15: 169.5 | D15: 168.1 | E15: 167.1 | F15: 166.2 | G15: 167.6 | H15: 168.6 | I15: 170.3 | J15: 171.4 | K15: 170.2 | L15: 169.3
A17: Balance sheet snapshot 2026-06-30 (H1 FY2026 interim report)
A18: Total borrowings | B18: 9056
A19: Cash and equivalents | B19: 2279
A20: Net debt (company APM, ex-lease, nets cash-mgmt assets) | B20: 6454
A21: Goodwill | B21: 14674
A22: Equity attributable to owners | B22: 11615
A23: Shares outstanding H1 FY2026 (m, basic avg) | B23: 168.3
A24: Diluted shares H1 FY2026 (m) - NOT used, see Model_Info | B24: 174.4
A25: Buybacks H1 2026 (EUR m) | B25: 315
A26: Dividend per share FY2025 (EUR) | B26: 3.4
A28: FY2026 guidance (raised 2026-07-30)
A29: Revenue growth cc | B29: +8.5% to +9.0% (~5pts WNS/Cloud4C scope)
A30: Operating margin APM | B30: 13.6% - 13.8%
A31: Organic FCF (company APM) | B31: ~EUR 1.8-1.9bn (incl ~EUR 200m extra restructuring cash)

Sheet Assumptions
A1: Globals (identical across scenarios - risk is charged once, in the flows)
A2: WACC | B2: 0.08 | C2: EUR-built: Bund 2.6% + 5.0% ERP x beta 1.2 = CoE 8.6%; debt 3.0% after tax; 74/26 weights. Same rate all scenarios (owner-fcf.md 7f).
A3: D&A % of revenue (non-lease) | B3: 0.018 | C3: FY2025 total D&A 698 less ~300 ROU depreciation = ~400 = 1.8% of revenue. Lease charge lives on its own row.
A4: Capex % of revenue | B4: 0.013 | C4: FY2025 actual 287/22,465 = 1.28%; asset-light.
A5: Lease cost % of revenue | B5: 0.013 | C5: FY2025 lease principal 296/22,465 = 1.32%. Treatment B: charged in flows, lease liabilities excluded from net debt.
A6: WC capture % of revenue change | B6: -0.1 | C6: NEGATIVE: services receivables consume ~10% of incremental revenue. Not a deferred-revenue business.
A7: Net debt (EUR m, 2026-06-30) | B7: 6454 | C7: Company-disclosed APM, ex-lease. NOT 9,056-2,279=6,777 (cash-mgmt assets netted) and NOT the stale FY2025 5,306.
A8: Diluted shares used (m) | B8: 168.3 | C8: Basic H1 FY2026; flat - SBC expensed instead of diluted. See Model_Info.
A9: Current price (EUR) | B9: 107.25 | C9: Yahoo regular close 2026-08-31T15:35:13Z.
A10: Terminal FCF cap multiple | B10: 15 | C10: Below the 20x house default - structurally slower/cyclical business. Cap binds in base and bull.
A11: Hurdle rate | B11: 0.15 | C11: Entry-price IRR; terminal value REBUILT at the hurdle.
A13: Per scenario
A14: Terminal growth - Base | B14: 0.02
A15: Terminal growth - Bull | B15: 0.025
A16: Terminal growth - Bear | B16: 0
A17: Weight - Base | B17: 0.5 | C17: Bear 30%: structural AI deflation conceded in Capgemini's own URD, arriving at peak leverage with goodwill (14.7bn) > equity (11.6bn). Bull 20%: needs WNS synergies, statutory margin delivery AND sovereignty spend simultaneously.
A18: Weight - Bull | B18: 0.2
A19: Weight - Bear | B19: 0.3
A20: Weights sum (must be 1.00) | B20: =SUM(B17:B19)
A22: Scenario narratives
A23: Base | C23: FY2026 lands at guidance (+8.0% reported; ~5pts WNS/Cloud4C scope, FX ~-1pt), then growth fades to ~3% organic as the European recovery holds but AI compresses pricing on the staffing-pyramid work roughly in line with the productivity Capgemini passes through. Gross-EBITDA margin dips to 13.6% in FY2026 (Fit-for-Growth restructuring ~EUR 450m, statutory basis) then recovers to 14.8% - statutory EBIT ~10.6%, the middle of the FY2022-24 range, i.e. Fit-for-Growth pays for itself but no more, and ~EUR 150-200m/yr of restructuring remains a permanent cost of the model transition. Cash tax ramps 23%->26%. Owner-FCF margin matures at 8.1% by FY2035.
A24: Bull | C24: Capgemini's Intelligent Operations bet works: WNS cross-sell (100+ joint pipeline), European sovereignty/defense spend and the agentic-AI transformation cycle make it a share gainer rather than a deflation victim. Growth holds 5-5.5% for three years post-WNS-lap, fading to 3%. Fit-for-Growth delivers the guided margin structure ON A STATUTORY BASIS: gross margin reaches 15.8% (statutory EBIT ~11.6%) as restructuring falls away after FY2027 and the pyramid reshapes toward outcome-based pricing.
A25: Bear | C25: The AI-deflation thesis is right - Capgemini's own URD concedes 'pricing to execution mismatches'. After the WNS lap (FY2026 +6.5%), agentic AI deflates billable hours faster than volume grows: revenue DECLINES 1-2.5%/yr for most of the decade (a real decline path, not slower growth). Pricing pressure plus under-utilized onshore Europe compresses gross margin 13.2%->11.0% (statutory EBIT ~6.8%) with restructuring permanent. Terminal growth 0%. The EUR 6.5bn net debt and goodwill > equity (EUR 14.7bn vs 11.6bn at Jun-2026) make this scenario a deleveraging grind with likely impairments - equity survives but compounds nothing.

Sheet DCF_Bear
A1: Bear scenario - owner-FCF build (EUR m). Drivers (yellow): rows 5, 7, 9, 15.
A3: Year | B3: 2025A | C3: 2026E | D3: 2027E | E3: 2028E | F3: 2029E | G3: 2030E | H3: 2031E | I3: 2032E | J3: 2033E | K3: 2034E | L3: 2035E
A4: Year index | B4: 0 | C4: 1 | D4: 2 | E4: 3 | F4: 4 | G4: 5 | H4: 6 | I4: 7 | J4: 8 | K4: 9 | L4: 10
A5: Revenue growth YoY | C5: 0.065 | D5: -0.01 | E5: -0.025 | F5: -0.025 | G5: -0.02 | H5: -0.015 | I5: -0.01 | J5: -0.01 | K5: -0.005 | L5: -0.005
A6: Revenue | B6: 22465 | C6: =B6*(1+C5) | D6: =C6*(1+D5) | E6: =D6*(1+E5) | F6: =E6*(1+F5) | G6: =F6*(1+G5) | H6: =G6*(1+H5) | I6: =H6*(1+I5) | J6: =I6*(1+J5) | ... L6: =K6*(1+L5)
A7: Adj EBITDA margin (gross of SBC/lease/D&A, statutory basis) | C7: 0.132 | D7: 0.13 | E7: 0.125 | F7: 0.12 | G7: 0.116 | H7: 0.113 | I7: 0.11 | J7: 0.11 | K7: 0.11 | L7: 0.11
A8: Adjusted EBITDA | C8: =C6*C7 | D8: =D6*D7 | E8: =E6*E7 | F8: =F6*F7 | G8: =G6*G7 | H8: =H6*H7 | I8: =I6*I7 | J8: =J6*J7 | ... L8: =L6*L7
A9: SBC % of revenue | C9: 0.011 | D9: 0.011 | E9: 0.011 | F9: 0.011 | G9: 0.011 | H9: 0.011 | I9: 0.011 | J9: 0.011 | K9: 0.011 | L9: 0.011
A10: SBC (expensed) | C10: =-C6*C9 | D10: =-D6*D9 | E10: =-E6*E9 | F10: =-F6*F9 | G10: =-G6*G9 | H10: =-H6*H9 | I10: =-I6*I9 | J10: =-J6*J9 | ... L10: =-L6*L9
A11: Lease cost (IFRS-16 principal, treatment B) | C11: =-C6*Assumptions!$B$5 | D11: =-D6*Assumptions!$B$5 | E11: =-E6*Assumptions!$B$5 | F11: =-F6*Assumptions!$B$5 | G11: =-G6*Assumptions!$B$5 | H11: =-H6*Assumptions!$B$5 | I11: =-I6*Assumptions!$B$5 | J11: =-J6*Assumptions!$B$5 | ... L11: =-L6*Assumptions!$B$5
A12: Owner EBITDA | C12: =C8+C10+C11 | D12: =D8+D10+D11 | E12: =E8+E10+E11 | F12: =F8+F10+F11 | G12: =G8+G10+G11 | H12: =H8+H10+H11 | I12: =I8+I10+I11 | J12: =J8+J10+J11 | ... L12: =L8+L10+L11
A13: D&A (non-lease) | C13: =-C6*Assumptions!$B$3 | D13: =-D6*Assumptions!$B$3 | E13: =-E6*Assumptions!$B$3 | F13: =-F6*Assumptions!$B$3 | G13: =-G6*Assumptions!$B$3 | H13: =-H6*Assumptions!$B$3 | I13: =-I6*Assumptions!$B$3 | J13: =-J6*Assumptions!$B$3 | ... L13: =-L6*Assumptions!$B$3
A14: EBIT (SBC and lease expensed) | C14: =C12+C13 | D14: =D12+D13 | E14: =E12+E13 | F14: =F12+F13 | G14: =G12+G13 | H14: =H12+H13 | I14: =I12+I13 | J14: =J12+J13 | ... L14: =L12+L13
A15: Cash tax rate | C15: 0.23 | D15: 0.24 | E15: 0.25 | F15: 0.26 | G15: 0.26 | H15: 0.26 | I15: 0.26 | J15: 0.26 | K15: 0.26 | L15: 0.26
A16: NOPAT | C16: =C14-MAX(0,C14)*C15 | D16: =D14-MAX(0,D14)*D15 | E16: =E14-MAX(0,E14)*E15 | F16: =F14-MAX(0,F14)*F15 | G16: =G14-MAX(0,G14)*G15 | H16: =H14-MAX(0,H14)*H15 | I16: =I14-MAX(0,I14)*I15 | J16: =J14-MAX(0,J14)*J15 | ... L16: =L14-MAX(0,L14)*L15
A17: add back D&A | C17: =-C13 | D17: =-D13 | E17: =-E13 | F17: =-F13 | G17: =-G13 | H17: =-H13 | I17: =-I13 | J17: =-J13 | ... L17: =-L13
A18: less capex | C18: =-C6*Assumptions!$B$4 | D18: =-D6*Assumptions!$B$4 | E18: =-E6*Assumptions!$B$4 | F18: =-F6*Assumptions!$B$4 | G18: =-G6*Assumptions!$B$4 | H18: =-H6*Assumptions!$B$4 | I18: =-I6*Assumptions!$B$4 | J18: =-J6*Assumptions!$B$4 | ... L18: =-L6*Assumptions!$B$4
A19: add working capital (on revenue CHANGE) | C19: =Assumptions!$B$6*(C6-B6) | D19: =Assumptions!$B$6*(D6-C6) | E19: =Assumptions!$B$6*(E6-D6) | F19: =Assumptions!$B$6*(F6-E6) | G19: =Assumptions!$B$6*(G6-F6) | H19: =Assumptions!$B$6*(H6-G6) | I19: =Assumptions!$B$6*(I6-H6) | J19: =Assumptions!$B$6*(J6-I6) | ... L19: =Assumptions!$B$6*(L6-K6)
A20: Unlevered owner FCF | C20: =C16+C17+C18+C19 | D20: =D16+D17+D18+D19 | E20: =E16+E17+E18+E19 | F20: =F16+F17+F18+F19 | G20: =G16+G17+G18+G19 | H20: =H16+H17+H18+H19 | I20: =I16+I17+I18+I19 | J20: =J16+J17+J18+J19 | ... L20: =L16+L17+L18+L19
A21: Discount factor | C21: =1/(1+Assumptions!$B$2)^C4 | D21: =1/(1+Assumptions!$B$2)^D4 | E21: =1/(1+Assumptions!$B$2)^E4 | F21: =1/(1+Assumptions!$B$2)^F4 | G21: =1/(1+Assumptions!$B$2)^G4 | H21: =1/(1+Assumptions!$B$2)^H4 | I21: =1/(1+Assumptions!$B$2)^I4 | J21: =1/(1+Assumptions!$B$2)^J4 | ... L21: =1/(1+Assumptions!$B$2)^L4
A22: PV of FCF | C22: =C20*C21 | D22: =D20*D21 | E22: =E20*E21 | F22: =F20*F21 | G22: =G20*G21 | H22: =H20*H21 | I22: =I20*I21 | J22: =J20*J21 | ... L22: =L20*L21
A24: Memo: FCF before SBC (company-style) | C24: =C20-C10 | D24: =D20-D10 | E24: =E20-E10 | F24: =F20-F10 | G24: =G20-G10 | H24: =H20-H10 | I24: =I20-I10 | J24: =J20-J10 | ... L24: =L20-L10
A25: Memo: implied owner-FCF margin | C25: =C20/C6 | D25: =D20/D6 | E25: =E20/E6 | F25: =F20/F6 | G25: =G20/G6 | H25: =H20/H6 | I25: =I20/I6 | J25: =J20/J6 | ... L25: =L20/L6
A27: Sum PV of FCF | B27: =SUM(C22:L22)
A28: Terminal growth | B28: =Assumptions!$B$16
A29: Terminal FCF | B29: =L20*(1+B28)
A30: Gordon TV | B30: =IF(Assumptions!$B$2>B28,B29/(Assumptions!$B$2-B28),1E+15)
A31: Cap TV | B31: =Assumptions!$B$10*L20
A32: TV used | B32: =MAX(0,MIN(B30,B31))
A33: Implied exit multiple (TV/FCF_N) | B33: =B32/L20
A34: PV of TV | B34: =B32*L21
A35: Enterprise value | B35: =B27+B34
A36: less net debt | B36: =-Assumptions!$B$7
A37: Equity value | B37: =B35+B36
A38: Diluted shares (m) | B38: =Assumptions!$B$8
A39: Value per share (EUR) | B39: =B37/B38
A40: Upside vs price | B40: =B39/Assumptions!$B$9-1
A42: Street memo: PV of explicit-period SBC | B42: =SUMPRODUCT(-C10:L10/(1+Assumptions!$B$2)^C4:L4)
A43: Street memo: PV of terminal SBC (Gordon) | B43: =(-L10*(1+B28)/(Assumptions!$B$2-B28))*L21
A44: Street value per share (SBC as non-cash) | B44: =(B37+B42+B43)/B38

Sheet DCF_Base
A1: Base scenario - owner-FCF build (EUR m). Drivers (yellow): rows 5, 7, 9, 15.
A3: Year | B3: 2025A | C3: 2026E | D3: 2027E | E3: 2028E | F3: 2029E | G3: 2030E | H3: 2031E | I3: 2032E | J3: 2033E | K3: 2034E | L3: 2035E
A4: Year index | B4: 0 | C4: 1 | D4: 2 | E4: 3 | F4: 4 | G4: 5 | H4: 6 | I4: 7 | J4: 8 | K4: 9 | L4: 10
A5: Revenue growth YoY | C5: 0.08 | D5: 0.04 | E5: 0.035 | F5: 0.03 | G5: 0.03 | H5: 0.03 | I5: 0.025 | J5: 0.025 | K5: 0.025 | L5: 0.02
A6: Revenue | B6: 22465 | C6: =B6*(1+C5) | D6: =C6*(1+D5) | E6: =D6*(1+E5) | F6: =E6*(1+F5) | G6: =F6*(1+G5) | H6: =G6*(1+H5) | I6: =H6*(1+I5) | J6: =I6*(1+J5) | ... L6: =K6*(1+L5)
A7: Adj EBITDA margin (gross of SBC/lease/D&A, statutory basis) | C7: 0.136 | D7: 0.144 | E7: 0.146 | F7: 0.147 | G7: 0.148 | H7: 0.148 | I7: 0.148 | J7: 0.148 | K7: 0.148 | L7: 0.148
A8: Adjusted EBITDA | C8: =C6*C7 | D8: =D6*D7 | E8: =E6*E7 | F8: =F6*F7 | G8: =G6*G7 | H8: =H6*H7 | I8: =I6*I7 | J8: =J6*J7 | ... L8: =L6*L7
A9: SBC % of revenue | C9: 0.011 | D9: 0.011 | E9: 0.011 | F9: 0.011 | G9: 0.011 | H9: 0.011 | I9: 0.011 | J9: 0.011 | K9: 0.011 | L9: 0.011
A10: SBC (expensed) | C10: =-C6*C9 | D10: =-D6*D9 | E10: =-E6*E9 | F10: =-F6*F9 | G10: =-G6*G9 | H10: =-H6*H9 | I10: =-I6*I9 | J10: =-J6*J9 | ... L10: =-L6*L9
A11: Lease cost (IFRS-16 principal, treatment B) | C11: =-C6*Assumptions!$B$5 | D11: =-D6*Assumptions!$B$5 | E11: =-E6*Assumptions!$B$5 | F11: =-F6*Assumptions!$B$5 | G11: =-G6*Assumptions!$B$5 | H11: =-H6*Assumptions!$B$5 | I11: =-I6*Assumptions!$B$5 | J11: =-J6*Assumptions!$B$5 | ... L11: =-L6*Assumptions!$B$5
A12: Owner EBITDA | C12: =C8+C10+C11 | D12: =D8+D10+D11 | E12: =E8+E10+E11 | F12: =F8+F10+F11 | G12: =G8+G10+G11 | H12: =H8+H10+H11 | I12: =I8+I10+I11 | J12: =J8+J10+J11 | ... L12: =L8+L10+L11
A13: D&A (non-lease) | C13: =-C6*Assumptions!$B$3 | D13: =-D6*Assumptions!$B$3 | E13: =-E6*Assumptions!$B$3 | F13: =-F6*Assumptions!$B$3 | G13: =-G6*Assumptions!$B$3 | H13: =-H6*Assumptions!$B$3 | I13: =-I6*Assumptions!$B$3 | J13: =-J6*Assumptions!$B$3 | ... L13: =-L6*Assumptions!$B$3
A14: EBIT (SBC and lease expensed) | C14: =C12+C13 | D14: =D12+D13 | E14: =E12+E13 | F14: =F12+F13 | G14: =G12+G13 | H14: =H12+H13 | I14: =I12+I13 | J14: =J12+J13 | ... L14: =L12+L13
A15: Cash tax rate | C15: 0.23 | D15: 0.24 | E15: 0.25 | F15: 0.26 | G15: 0.26 | H15: 0.26 | I15: 0.26 | J15: 0.26 | K15: 0.26 | L15: 0.26
A16: NOPAT | C16: =C14-MAX(0,C14)*C15 | D16: =D14-MAX(0,D14)*D15 | E16: =E14-MAX(0,E14)*E15 | F16: =F14-MAX(0,F14)*F15 | G16: =G14-MAX(0,G14)*G15 | H16: =H14-MAX(0,H14)*H15 | I16: =I14-MAX(0,I14)*I15 | J16: =J14-MAX(0,J14)*J15 | ... L16: =L14-MAX(0,L14)*L15
A17: add back D&A | C17: =-C13 | D17: =-D13 | E17: =-E13 | F17: =-F13 | G17: =-G13 | H17: =-H13 | I17: =-I13 | J17: =-J13 | ... L17: =-L13
A18: less capex | C18: =-C6*Assumptions!$B$4 | D18: =-D6*Assumptions!$B$4 | E18: =-E6*Assumptions!$B$4 | F18: =-F6*Assumptions!$B$4 | G18: =-G6*Assumptions!$B$4 | H18: =-H6*Assumptions!$B$4 | I18: =-I6*Assumptions!$B$4 | J18: =-J6*Assumptions!$B$4 | ... L18: =-L6*Assumptions!$B$4
A19: add working capital (on revenue CHANGE) | C19: =Assumptions!$B$6*(C6-B6) | D19: =Assumptions!$B$6*(D6-C6) | E19: =Assumptions!$B$6*(E6-D6) | F19: =Assumptions!$B$6*(F6-E6) | G19: =Assumptions!$B$6*(G6-F6) | H19: =Assumptions!$B$6*(H6-G6) | I19: =Assumptions!$B$6*(I6-H6) | J19: =Assumptions!$B$6*(J6-I6) | ... L19: =Assumptions!$B$6*(L6-K6)
A20: Unlevered owner FCF | C20: =C16+C17+C18+C19 | D20: =D16+D17+D18+D19 | E20: =E16+E17+E18+E19 | F20: =F16+F17+F18+F19 | G20: =G16+G17+G18+G19 | H20: =H16+H17+H18+H19 | I20: =I16+I17+I18+I19 | J20: =J16+J17+J18+J19 | ... L20: =L16+L17+L18+L19
A21: Discount factor | C21: =1/(1+Assumptions!$B$2)^C4 | D21: =1/(1+Assumptions!$B$2)^D4 | E21: =1/(1+Assumptions!$B$2)^E4 | F21: =1/(1+Assumptions!$B$2)^F4 | G21: =1/(1+Assumptions!$B$2)^G4 | H21: =1/(1+Assumptions!$B$2)^H4 | I21: =1/(1+Assumptions!$B$2)^I4 | J21: =1/(1+Assumptions!$B$2)^J4 | ... L21: =1/(1+Assumptions!$B$2)^L4
A22: PV of FCF | C22: =C20*C21 | D22: =D20*D21 | E22: =E20*E21 | F22: =F20*F21 | G22: =G20*G21 | H22: =H20*H21 | I22: =I20*I21 | J22: =J20*J21 | ... L22: =L20*L21
A24: Memo: FCF before SBC (company-style) | C24: =C20-C10 | D24: =D20-D10 | E24: =E20-E10 | F24: =F20-F10 | G24: =G20-G10 | H24: =H20-H10 | I24: =I20-I10 | J24: =J20-J10 | ... L24: =L20-L10
A25: Memo: implied owner-FCF margin | C25: =C20/C6 | D25: =D20/D6 | E25: =E20/E6 | F25: =F20/F6 | G25: =G20/G6 | H25: =H20/H6 | I25: =I20/I6 | J25: =J20/J6 | ... L25: =L20/L6
A27: Sum PV of FCF | B27: =SUM(C22:L22)
A28: Terminal growth | B28: =Assumptions!$B$14
A29: Terminal FCF | B29: =L20*(1+B28)
A30: Gordon TV | B30: =IF(Assumptions!$B$2>B28,B29/(Assumptions!$B$2-B28),1E+15)
A31: Cap TV | B31: =Assumptions!$B$10*L20
A32: TV used | B32: =MAX(0,MIN(B30,B31))
A33: Implied exit multiple (TV/FCF_N) | B33: =B32/L20
A34: PV of TV | B34: =B32*L21
A35: Enterprise value | B35: =B27+B34
A36: less net debt | B36: =-Assumptions!$B$7
A37: Equity value | B37: =B35+B36
A38: Diluted shares (m) | B38: =Assumptions!$B$8
A39: Value per share (EUR) | B39: =B37/B38
A40: Upside vs price | B40: =B39/Assumptions!$B$9-1
A42: Street memo: PV of explicit-period SBC | B42: =SUMPRODUCT(-C10:L10/(1+Assumptions!$B$2)^C4:L4)
A43: Street memo: PV of terminal SBC (Gordon) | B43: =(-L10*(1+B28)/(Assumptions!$B$2-B28))*L21
A44: Street value per share (SBC as non-cash) | B44: =(B37+B42+B43)/B38

Sheet DCF_Bull
A1: Bull scenario - owner-FCF build (EUR m). Drivers (yellow): rows 5, 7, 9, 15.
A3: Year | B3: 2025A | C3: 2026E | D3: 2027E | E3: 2028E | F3: 2029E | G3: 2030E | H3: 2031E | I3: 2032E | J3: 2033E | K3: 2034E | L3: 2035E
A4: Year index | B4: 0 | C4: 1 | D4: 2 | E4: 3 | F4: 4 | G4: 5 | H4: 6 | I4: 7 | J4: 8 | K4: 9 | L4: 10
A5: Revenue growth YoY | C5: 0.085 | D5: 0.055 | E5: 0.05 | F5: 0.05 | G5: 0.045 | H5: 0.04 | I5: 0.04 | J5: 0.035 | K5: 0.035 | L5: 0.03
A6: Revenue | B6: 22465 | C6: =B6*(1+C5) | D6: =C6*(1+D5) | E6: =D6*(1+E5) | F6: =E6*(1+F5) | G6: =F6*(1+G5) | H6: =G6*(1+H5) | I6: =H6*(1+I5) | J6: =I6*(1+J5) | ... L6: =K6*(1+L5)
A7: Adj EBITDA margin (gross of SBC/lease/D&A, statutory basis) | C7: 0.138 | D7: 0.148 | E7: 0.152 | F7: 0.155 | G7: 0.156 | H7: 0.157 | I7: 0.158 | J7: 0.158 | K7: 0.158 | L7: 0.158
A8: Adjusted EBITDA | C8: =C6*C7 | D8: =D6*D7 | E8: =E6*E7 | F8: =F6*F7 | G8: =G6*G7 | H8: =H6*H7 | I8: =I6*I7 | J8: =J6*J7 | ... L8: =L6*L7
A9: SBC % of revenue | C9: 0.011 | D9: 0.011 | E9: 0.011 | F9: 0.011 | G9: 0.011 | H9: 0.011 | I9: 0.011 | J9: 0.011 | K9: 0.011 | L9: 0.011
A10: SBC (expensed) | C10: =-C6*C9 | D10: =-D6*D9 | E10: =-E6*E9 | F10: =-F6*F9 | G10: =-G6*G9 | H10: =-H6*H9 | I10: =-I6*I9 | J10: =-J6*J9 | ... L10: =-L6*L9
A11: Lease cost (IFRS-16 principal, treatment B) | C11: =-C6*Assumptions!$B$5 | D11: =-D6*Assumptions!$B$5 | E11: =-E6*Assumptions!$B$5 | F11: =-F6*Assumptions!$B$5 | G11: =-G6*Assumptions!$B$5 | H11: =-H6*Assumptions!$B$5 | I11: =-I6*Assumptions!$B$5 | J11: =-J6*Assumptions!$B$5 | ... L11: =-L6*Assumptions!$B$5
A12: Owner EBITDA | C12: =C8+C10+C11 | D12: =D8+D10+D11 | E12: =E8+E10+E11 | F12: =F8+F10+F11 | G12: =G8+G10+G11 | H12: =H8+H10+H11 | I12: =I8+I10+I11 | J12: =J8+J10+J11 | ... L12: =L8+L10+L11
A13: D&A (non-lease) | C13: =-C6*Assumptions!$B$3 | D13: =-D6*Assumptions!$B$3 | E13: =-E6*Assumptions!$B$3 | F13: =-F6*Assumptions!$B$3 | G13: =-G6*Assumptions!$B$3 | H13: =-H6*Assumptions!$B$3 | I13: =-I6*Assumptions!$B$3 | J13: =-J6*Assumptions!$B$3 | ... L13: =-L6*Assumptions!$B$3
A14: EBIT (SBC and lease expensed) | C14: =C12+C13 | D14: =D12+D13 | E14: =E12+E13 | F14: =F12+F13 | G14: =G12+G13 | H14: =H12+H13 | I14: =I12+I13 | J14: =J12+J13 | ... L14: =L12+L13
A15: Cash tax rate | C15: 0.23 | D15: 0.24 | E15: 0.25 | F15: 0.26 | G15: 0.26 | H15: 0.26 | I15: 0.26 | J15: 0.26 | K15: 0.26 | L15: 0.26
A16: NOPAT | C16: =C14-MAX(0,C14)*C15 | D16: =D14-MAX(0,D14)*D15 | E16: =E14-MAX(0,E14)*E15 | F16: =F14-MAX(0,F14)*F15 | G16: =G14-MAX(0,G14)*G15 | H16: =H14-MAX(0,H14)*H15 | I16: =I14-MAX(0,I14)*I15 | J16: =J14-MAX(0,J14)*J15 | ... L16: =L14-MAX(0,L14)*L15
A17: add back D&A | C17: =-C13 | D17: =-D13 | E17: =-E13 | F17: =-F13 | G17: =-G13 | H17: =-H13 | I17: =-I13 | J17: =-J13 | ... L17: =-L13
A18: less capex | C18: =-C6*Assumptions!$B$4 | D18: =-D6*Assumptions!$B$4 | E18: =-E6*Assumptions!$B$4 | F18: =-F6*Assumptions!$B$4 | G18: =-G6*Assumptions!$B$4 | H18: =-H6*Assumptions!$B$4 | I18: =-I6*Assumptions!$B$4 | J18: =-J6*Assumptions!$B$4 | ... L18: =-L6*Assumptions!$B$4
A19: add working capital (on revenue CHANGE) | C19: =Assumptions!$B$6*(C6-B6) | D19: =Assumptions!$B$6*(D6-C6) | E19: =Assumptions!$B$6*(E6-D6) | F19: =Assumptions!$B$6*(F6-E6) | G19: =Assumptions!$B$6*(G6-F6) | H19: =Assumptions!$B$6*(H6-G6) | I19: =Assumptions!$B$6*(I6-H6) | J19: =Assumptions!$B$6*(J6-I6) | ... L19: =Assumptions!$B$6*(L6-K6)
A20: Unlevered owner FCF | C20: =C16+C17+C18+C19 | D20: =D16+D17+D18+D19 | E20: =E16+E17+E18+E19 | F20: =F16+F17+F18+F19 | G20: =G16+G17+G18+G19 | H20: =H16+H17+H18+H19 | I20: =I16+I17+I18+I19 | J20: =J16+J17+J18+J19 | ... L20: =L16+L17+L18+L19
A21: Discount factor | C21: =1/(1+Assumptions!$B$2)^C4 | D21: =1/(1+Assumptions!$B$2)^D4 | E21: =1/(1+Assumptions!$B$2)^E4 | F21: =1/(1+Assumptions!$B$2)^F4 | G21: =1/(1+Assumptions!$B$2)^G4 | H21: =1/(1+Assumptions!$B$2)^H4 | I21: =1/(1+Assumptions!$B$2)^I4 | J21: =1/(1+Assumptions!$B$2)^J4 | ... L21: =1/(1+Assumptions!$B$2)^L4
A22: PV of FCF | C22: =C20*C21 | D22: =D20*D21 | E22: =E20*E21 | F22: =F20*F21 | G22: =G20*G21 | H22: =H20*H21 | I22: =I20*I21 | J22: =J20*J21 | ... L22: =L20*L21
A24: Memo: FCF before SBC (company-style) | C24: =C20-C10 | D24: =D20-D10 | E24: =E20-E10 | F24: =F20-F10 | G24: =G20-G10 | H24: =H20-H10 | I24: =I20-I10 | J24: =J20-J10 | ... L24: =L20-L10
A25: Memo: implied owner-FCF margin | C25: =C20/C6 | D25: =D20/D6 | E25: =E20/E6 | F25: =F20/F6 | G25: =G20/G6 | H25: =H20/H6 | I25: =I20/I6 | J25: =J20/J6 | ... L25: =L20/L6
A27: Sum PV of FCF | B27: =SUM(C22:L22)
A28: Terminal growth | B28: =Assumptions!$B$15
A29: Terminal FCF | B29: =L20*(1+B28)
A30: Gordon TV | B30: =IF(Assumptions!$B$2>B28,B29/(Assumptions!$B$2-B28),1E+15)
A31: Cap TV | B31: =Assumptions!$B$10*L20
A32: TV used | B32: =MAX(0,MIN(B30,B31))
A33: Implied exit multiple (TV/FCF_N) | B33: =B32/L20
A34: PV of TV | B34: =B32*L21
A35: Enterprise value | B35: =B27+B34
A36: less net debt | B36: =-Assumptions!$B$7
A37: Equity value | B37: =B35+B36
A38: Diluted shares (m) | B38: =Assumptions!$B$8
A39: Value per share (EUR) | B39: =B37/B38
A40: Upside vs price | B40: =B39/Assumptions!$B$9-1
A42: Street memo: PV of explicit-period SBC | B42: =SUMPRODUCT(-C10:L10/(1+Assumptions!$B$2)^C4:L4)
A43: Street memo: PV of terminal SBC (Gordon) | B43: =(-L10*(1+B28)/(Assumptions!$B$2-B28))*L21
A44: Street value per share (SBC as non-cash) | B44: =(B37+B42+B43)/B38

Sheet FCF_Quality
A1: Reported FCF reconciled to owner FCF, every historical year (EUR m). Links to Actuals.
A2: Period | B2: FY2015 | C2: FY2016 | D2: FY2017 | E2: FY2018 | F2: FY2019 | G2: FY2020 | H2: FY2021 | I2: FY2022 | J2: FY2023 | K2: FY2024 | L2: FY2025
A3: Operating cash flow | B3: =Actuals!B9 | C3: =Actuals!C9 | D3: =Actuals!D9 | E3: =Actuals!E9 | F3: =Actuals!F9 | G3: =Actuals!G9 | H3: =Actuals!H9 | I3: =Actuals!I9 | ... L3: =Actuals!L9
A4: less capex | B4: =-Actuals!B10 | C4: =-Actuals!C10 | D4: =-Actuals!D10 | E4: =-Actuals!E10 | F4: =-Actuals!F10 | G4: =-Actuals!G10 | H4: =-Actuals!H10 | I4: =-Actuals!I10 | ... L4: =-Actuals!L10
A5: Free cash flow (OCF - capex) | B5: =B3+B4 | C5: =C3+C4 | D5: =D3+D4 | E5: =E3+E4 | F5: =F3+F4 | G5: =G3+G4 | H5: =H3+H4 | I5: =I3+I4 | ... L5: =L3+L4
A6: less lease principal repaid (IFRS-16) | B6: =-Actuals!B11 | C6: =-Actuals!C11 | D6: =-Actuals!D11 | E6: =-Actuals!E11 | F6: =-Actuals!F11 | G6: =-Actuals!G11 | H6: =-Actuals!H11 | I6: =-Actuals!I11 | ... L6: =-Actuals!L11
A7: less SBC | B7: =-Actuals!B12 | C7: =-Actuals!C12 | D7: =-Actuals!D12 | E7: =-Actuals!E12 | F7: =-Actuals!F12 | G7: =-Actuals!G12 | H7: =-Actuals!H12 | I7: =-Actuals!I12 | ... L7: =-Actuals!L12
A8: Owner FCF | B8: =B5+B6+B7 | C8: =C5+C6+C7 | D8: =D5+D6+D7 | E8: =E5+E6+E7 | F8: =F5+F6+F7 | G8: =G5+G6+G7 | H8: =H5+H6+H7 | I8: =I5+I6+I7 | ... L8: =L5+L6+L7
A9: Reported FCF margin | B9: =B5/Actuals!B3 | C9: =C5/Actuals!C3 | D9: =D5/Actuals!D3 | E9: =E5/Actuals!E3 | F9: =F5/Actuals!F3 | G9: =G5/Actuals!G3 | H9: =H5/Actuals!H3 | I9: =I5/Actuals!I3 | ... L9: =L5/Actuals!L3
A10: Owner FCF margin | B10: =B8/Actuals!B3 | C10: =C8/Actuals!C3 | D10: =D8/Actuals!D3 | E10: =E8/Actuals!E3 | F10: =F8/Actuals!F3 | G10: =G8/Actuals!G3 | H10: =H8/Actuals!H3 | I10: =I8/Actuals!I3 | ... L10: =L8/Actuals!L3
A11: Memo: cash taxes paid | B11: =Actuals!B13 | C11: =Actuals!C13 | D11: =Actuals!D13 | E11: =Actuals!E13 | F11: =Actuals!F13 | G11: =Actuals!G13 | H11: =Actuals!H13 | I11: =Actuals!I13 | ... L11: =Actuals!L13
A12: Memo: cash tax / statutory op income | B12: =B11/Actuals!B4 | C12: =C11/Actuals!C4 | D12: =D11/Actuals!D4 | E12: =E11/Actuals!E4 | F12: =F11/Actuals!F4 | G12: =G11/Actuals!G4 | H12: =H11/Actuals!H4 | I12: =I11/Actuals!I4 | ... L12: =L11/Actuals!L4
A14: Notes: pre-2019 lease costs sat in opex (pre-IFRS16), so the series is comparable across the break. Interest income is NOT stripped - Capgemini books interest in financing, outside OCF. Owner FCF 3yr CAGR is -2.3% vs reported -0.5%: SBC nearly doubled FY2021-23.

Sheet Valuation
A1: Valuation summary (EUR)
A2: Scenario | B2: Value/share | C2: Upside | D2: Probability | E2: Street value/share | F2: Entry @15%
A3: Bear | B3: =DCF_Bear!$B$39 | C3: =B3/Assumptions!$B$9-1 | D3: =Assumptions!$B$19 | E3: =DCF_Bear!$B$44 | F3: =(SUMPRODUCT(DCF_Bear!$C$20:$L$20/(1+Assumptions!$B$11)^DCF_Bear!$C$4:$L$4)+MAX(0,MIN(IF(Assumptions!$B$11>DCF_Bear!$B$28,DCF_Bear!$L$20*(1+DCF_Bear!$B$28)/(Assumptions!$B$11-DCF_Bear!$B$28),1E+15),Assumptions!$B$10*DCF_Bear!$L$20))/(1+Assumptions!$B$11)^10-Assumptions!$B$7)/Assumptions!$B$8
A4: Base | B4: =DCF_Base!$B$39 | C4: =B4/Assumptions!$B$9-1 | D4: =Assumptions!$B$17 | E4: =DCF_Base!$B$44 | F4: =(SUMPRODUCT(DCF_Base!$C$20:$L$20/(1+Assumptions!$B$11)^DCF_Base!$C$4:$L$4)+MAX(0,MIN(IF(Assumptions!$B$11>DCF_Base!$B$28,DCF_Base!$L$20*(1+DCF_Base!$B$28)/(Assumptions!$B$11-DCF_Base!$B$28),1E+15),Assumptions!$B$10*DCF_Base!$L$20))/(1+Assumptions!$B$11)^10-Assumptions!$B$7)/Assumptions!$B$8
A5: Bull | B5: =DCF_Bull!$B$39 | C5: =B5/Assumptions!$B$9-1 | D5: =Assumptions!$B$18 | E5: =DCF_Bull!$B$44 | F5: =(SUMPRODUCT(DCF_Bull!$C$20:$L$20/(1+Assumptions!$B$11)^DCF_Bull!$C$4:$L$4)+MAX(0,MIN(IF(Assumptions!$B$11>DCF_Bull!$B$28,DCF_Bull!$L$20*(1+DCF_Bull!$B$28)/(Assumptions!$B$11-DCF_Bull!$B$28),1E+15),Assumptions!$B$10*DCF_Bull!$L$20))/(1+Assumptions!$B$11)^10-Assumptions!$B$7)/Assumptions!$B$8
A7: Probability-weighted IV | B7: =SUMPRODUCT(B3:B5,D3:D5)
A8: Margin of safety vs price | B8: =1-Assumptions!$B$9/B7
A9: Street weighted IV | B9: =SUMPRODUCT(E3:E5,D3:D5)
A10: Band position (0%=house, 100%=street) | B10: =(Assumptions!$B$9-B7)/(B9-B7)
A11: Weighted entry price @15% hurdle | B11: =SUMPRODUCT(F3:F5,D3:D5)
A13: Required-return table (base case; TV rebuilt at each rate)
A14: Required return | B14: 0.08 | C14: 0.09 | D14: 0.1 | E14: 0.11 | F14: 0.12 | G14: 0.15
A15: Value per share | B15: =(SUMPRODUCT(DCF_Base!$C$20:$L$20/(1+B$14)^DCF_Base!$C$4:$L$4)+MAX(0,MIN(IF(B$14>DCF_Base!$B$28,DCF_Base!$L$20*(1+DCF_Base!$B$28)/(B$14-DCF_Base!$B$28),1E+15),Assumptions!$B$10*DCF_Base!$L$20))/(1+B$14)^10-Assumptions!$B$7)/Assumptions!$B$8 | C15: =(SUMPRODUCT(DCF_Base!$C$20:$L$20/(1+C$14)^DCF_Base!$C$4:$L$4)+MAX(0,MIN(IF(C$14>DCF_Base!$B$28,DCF_Base!$L$20*(1+DCF_Base!$B$28)/(C$14-DCF_Base!$B$28),1E+15),Assumptions!$B$10*DCF_Base!$L$20))/(1+C$14)^10-Assumptions!$B$7)/Assumptions!$B$8 | D15: =(SUMPRODUCT(DCF_Base!$C$20:$L$20/(1+D$14)^DCF_Base!$C$4:$L$4)+MAX(0,MIN(IF(D$14>DCF_Base!$B$28,DCF_Base!$L$20*(1+DCF_Base!$B$28)/(D$14-DCF_Base!$B$28),1E+15),Assumptions!$B$10*DCF_Base!$L$20))/(1+D$14)^10-Assumptions!$B$7)/Assumptions!$B$8 | E15: =(SUMPRODUCT(DCF_Base!$C$20:$L$20/(1+E$14)^DCF_Base!$C$4:$L$4)+MAX(0,MIN(IF(E$14>DCF_Base!$B$28,DCF_Base!$L$20*(1+DCF_Base!$B$28)/(E$14-DCF_Base!$B$28),1E+15),Assumptions!$B$10*DCF_Base!$L$20))/(1+E$14)^10-Assumptions!$B$7)/Assumptions!$B$8 | F15: =(SUMPRODUCT(DCF_Base!$C$20:$L$20/(1+F$14)^DCF_Base!$C$4:$L$4)+MAX(0,MIN(IF(F$14>DCF_Base!$B$28,DCF_Base!$L$20*(1+DCF_Base!$B$28)/(F$14-DCF_Base!$B$28),1E+15),Assumptions!$B$10*DCF_Base!$L$20))/(1+F$14)^10-Assumptions!$B$7)/Assumptions!$B$8 | G15: =(SUMPRODUCT(DCF_Base!$C$20:$L$20/(1+G$14)^DCF_Base!$C$4:$L$4)+MAX(0,MIN(IF(G$14>DCF_Base!$B$28,DCF_Base!$L$20*(1+DCF_Base!$B$28)/(G$14-DCF_Base!$B$28),1E+15),Assumptions!$B$10*DCF_Base!$L$20))/(1+G$14)^10-Assumptions!$B$7)/Assumptions!$B$8
A16: Note: the 8% column ties to DCF_Base!B39 and the 15% column to the base entry price - the table, entry price and DCF agree by construction.
A18: Sensitivity: WACC x terminal growth (base case)
B19: 0.01 | C19: 0.015 | D19: 0.02 | E19: 0.025 | F19: 0.03
A20: 0.06 | B20: =(SUMPRODUCT(DCF_Base!$C$20:$L$20/(1+$A20)^DCF_Base!$C$4:$L$4)+MAX(0,MIN(IF($A20>B$19,DCF_Base!$L$20*(1+B$19)/($A20-B$19),1E+15),Assumptions!$B$10*DCF_Base!$L$20))/(1+$A20)^10-Assumptions!$B$7)/Assumptions!$B$8 | C20: =(SUMPRODUCT(DCF_Base!$C$20:$L$20/(1+$A20)^DCF_Base!$C$4:$L$4)+MAX(0,MIN(IF($A20>C$19,DCF_Base!$L$20*(1+C$19)/($A20-C$19),1E+15),Assumptions!$B$10*DCF_Base!$L$20))/(1+$A20)^10-Assumptions!$B$7)/Assumptions!$B$8 | D20: =(SUMPRODUCT(DCF_Base!$C$20:$L$20/(1+$A20)^DCF_Base!$C$4:$L$4)+MAX(0,MIN(IF($A20>D$19,DCF_Base!$L$20*(1+D$19)/($A20-D$19),1E+15),Assumptions!$B$10*DCF_Base!$L$20))/(1+$A20)^10-Assumptions!$B$7)/Assumptions!$B$8 | E20: =(SUMPRODUCT(DCF_Base!$C$20:$L$20/(1+$A20)^DCF_Base!$C$4:$L$4)+MAX(0,MIN(IF($A20>E$19,DCF_Base!$L$20*(1+E$19)/($A20-E$19),1E+15),Assumptions!$B$10*DCF_Base!$L$20))/(1+$A20)^10-Assumptions!$B$7)/Assumptions!$B$8 | F20: =(SUMPRODUCT(DCF_Base!$C$20:$L$20/(1+$A20)^DCF_Base!$C$4:$L$4)+MAX(0,MIN(IF($A20>F$19,DCF_Base!$L$20*(1+F$19)/($A20-F$19),1E+15),Assumptions!$B$10*DCF_Base!$L$20))/(1+$A20)^10-Assumptions!$B$7)/Assumptions!$B$8
A21: 0.07 | B21: =(SUMPRODUCT(DCF_Base!$C$20:$L$20/(1+$A21)^DCF_Base!$C$4:$L$4)+MAX(0,MIN(IF($A21>B$19,DCF_Base!$L$20*(1+B$19)/($A21-B$19),1E+15),Assumptions!$B$10*DCF_Base!$L$20))/(1+$A21)^10-Assumptions!$B$7)/Assumptions!$B$8 | C21: =(SUMPRODUCT(DCF_Base!$C$20:$L$20/(1+$A21)^DCF_Base!$C$4:$L$4)+MAX(0,MIN(IF($A21>C$19,DCF_Base!$L$20*(1+C$19)/($A21-C$19),1E+15),Assumptions!$B$10*DCF_Base!$L$20))/(1+$A21)^10-Assumptions!$B$7)/Assumptions!$B$8 | D21: =(SUMPRODUCT(DCF_Base!$C$20:$L$20/(1+$A21)^DCF_Base!$C$4:$L$4)+MAX(0,MIN(IF($A21>D$19,DCF_Base!$L$20*(1+D$19)/($A21-D$19),1E+15),Assumptions!$B$10*DCF_Base!$L$20))/(1+$A21)^10-Assumptions!$B$7)/Assumptions!$B$8 | E21: =(SUMPRODUCT(DCF_Base!$C$20:$L$20/(1+$A21)^DCF_Base!$C$4:$L$4)+MAX(0,MIN(IF($A21>E$19,DCF_Base!$L$20*(1+E$19)/($A21-E$19),1E+15),Assumptions!$B$10*DCF_Base!$L$20))/(1+$A21)^10-Assumptions!$B$7)/Assumptions!$B$8 | F21: =(SUMPRODUCT(DCF_Base!$C$20:$L$20/(1+$A21)^DCF_Base!$C$4:$L$4)+MAX(0,MIN(IF($A21>F$19,DCF_Base!$L$20*(1+F$19)/($A21-F$19),1E+15),Assumptions!$B$10*DCF_Base!$L$20))/(1+$A21)^10-Assumptions!$B$7)/Assumptions!$B$8
A22: 0.08 | B22: =(SUMPRODUCT(DCF_Base!$C$20:$L$20/(1+$A22)^DCF_Base!$C$4:$L$4)+MAX(0,MIN(IF($A22>B$19,DCF_Base!$L$20*(1+B$19)/($A22-B$19),1E+15),Assumptions!$B$10*DCF_Base!$L$20))/(1+$A22)^10-Assumptions!$B$7)/Assumptions!$B$8 | C22: =(SUMPRODUCT(DCF_Base!$C$20:$L$20/(1+$A22)^DCF_Base!$C$4:$L$4)+MAX(0,MIN(IF($A22>C$19,DCF_Base!$L$20*(1+C$19)/($A22-C$19),1E+15),Assumptions!$B$10*DCF_Base!$L$20))/(1+$A22)^10-Assumptions!$B$7)/Assumptions!$B$8 | D22: =(SUMPRODUCT(DCF_Base!$C$20:$L$20/(1+$A22)^DCF_Base!$C$4:$L$4)+MAX(0,MIN(IF($A22>D$19,DCF_Base!$L$20*(1+D$19)/($A22-D$19),1E+15),Assumptions!$B$10*DCF_Base!$L$20))/(1+$A22)^10-Assumptions!$B$7)/Assumptions!$B$8 | E22: =(SUMPRODUCT(DCF_Base!$C$20:$L$20/(1+$A22)^DCF_Base!$C$4:$L$4)+MAX(0,MIN(IF($A22>E$19,DCF_Base!$L$20*(1+E$19)/($A22-E$19),1E+15),Assumptions!$B$10*DCF_Base!$L$20))/(1+$A22)^10-Assumptions!$B$7)/Assumptions!$B$8 | F22: =(SUMPRODUCT(DCF_Base!$C$20:$L$20/(1+$A22)^DCF_Base!$C$4:$L$4)+MAX(0,MIN(IF($A22>F$19,DCF_Base!$L$20*(1+F$19)/($A22-F$19),1E+15),Assumptions!$B$10*DCF_Base!$L$20))/(1+$A22)^10-Assumptions!$B$7)/Assumptions!$B$8
A23: 0.09 | B23: =(SUMPRODUCT(DCF_Base!$C$20:$L$20/(1+$A23)^DCF_Base!$C$4:$L$4)+MAX(0,MIN(IF($A23>B$19,DCF_Base!$L$20*(1+B$19)/($A23-B$19),1E+15),Assumptions!$B$10*DCF_Base!$L$20))/(1+$A23)^10-Assumptions!$B$7)/Assumptions!$B$8 | C23: =(SUMPRODUCT(DCF_Base!$C$20:$L$20/(1+$A23)^DCF_Base!$C$4:$L$4)+MAX(0,MIN(IF($A23>C$19,DCF_Base!$L$20*(1+C$19)/($A23-C$19),1E+15),Assumptions!$B$10*DCF_Base!$L$20))/(1+$A23)^10-Assumptions!$B$7)/Assumptions!$B$8 | D23: =(SUMPRODUCT(DCF_Base!$C$20:$L$20/(1+$A23)^DCF_Base!$C$4:$L$4)+MAX(0,MIN(IF($A23>D$19,DCF_Base!$L$20*(1+D$19)/($A23-D$19),1E+15),Assumptions!$B$10*DCF_Base!$L$20))/(1+$A23)^10-Assumptions!$B$7)/Assumptions!$B$8 | E23: =(SUMPRODUCT(DCF_Base!$C$20:$L$20/(1+$A23)^DCF_Base!$C$4:$L$4)+MAX(0,MIN(IF($A23>E$19,DCF_Base!$L$20*(1+E$19)/($A23-E$19),1E+15),Assumptions!$B$10*DCF_Base!$L$20))/(1+$A23)^10-Assumptions!$B$7)/Assumptions!$B$8 | F23: =(SUMPRODUCT(DCF_Base!$C$20:$L$20/(1+$A23)^DCF_Base!$C$4:$L$4)+MAX(0,MIN(IF($A23>F$19,DCF_Base!$L$20*(1+F$19)/($A23-F$19),1E+15),Assumptions!$B$10*DCF_Base!$L$20))/(1+$A23)^10-Assumptions!$B$7)/Assumptions!$B$8
A24: 0.1 | B24: =(SUMPRODUCT(DCF_Base!$C$20:$L$20/(1+$A24)^DCF_Base!$C$4:$L$4)+MAX(0,MIN(IF($A24>B$19,DCF_Base!$L$20*(1+B$19)/($A24-B$19),1E+15),Assumptions!$B$10*DCF_Base!$L$20))/(1+$A24)^10-Assumptions!$B$7)/Assumptions!$B$8 | C24: =(SUMPRODUCT(DCF_Base!$C$20:$L$20/(1+$A24)^DCF_Base!$C$4:$L$4)+MAX(0,MIN(IF($A24>C$19,DCF_Base!$L$20*(1+C$19)/($A24-C$19),1E+15),Assumptions!$B$10*DCF_Base!$L$20))/(1+$A24)^10-Assumptions!$B$7)/Assumptions!$B$8 | D24: =(SUMPRODUCT(DCF_Base!$C$20:$L$20/(1+$A24)^DCF_Base!$C$4:$L$4)+MAX(0,MIN(IF($A24>D$19,DCF_Base!$L$20*(1+D$19)/($A24-D$19),1E+15),Assumptions!$B$10*DCF_Base!$L$20))/(1+$A24)^10-Assumptions!$B$7)/Assumptions!$B$8 | E24: =(SUMPRODUCT(DCF_Base!$C$20:$L$20/(1+$A24)^DCF_Base!$C$4:$L$4)+MAX(0,MIN(IF($A24>E$19,DCF_Base!$L$20*(1+E$19)/($A24-E$19),1E+15),Assumptions!$B$10*DCF_Base!$L$20))/(1+$A24)^10-Assumptions!$B$7)/Assumptions!$B$8 | F24: =(SUMPRODUCT(DCF_Base!$C$20:$L$20/(1+$A24)^DCF_Base!$C$4:$L$4)+MAX(0,MIN(IF($A24>F$19,DCF_Base!$L$20*(1+F$19)/($A24-F$19),1E+15),Assumptions!$B$10*DCF_Base!$L$20))/(1+$A24)^10-Assumptions!$B$7)/Assumptions!$B$8
A26: Flat rows at low WACC are the 15x terminal-FCF cap binding regardless of terminal growth.
