Workbook

Sheet DCF Model
A1: FISV DCF Valuation Model
A2: Gray cells are INPUTS - adjust to see valuation change
A3: Turnaround situation: 2026 transition year with recovery expected 2027+
A5: KEY INPUTS
A6: Current Stock Price | B6: 115
A7: Shares Outstanding (M) | B7: 582.1
A8: Cash & Equivalents (M) | B8: 1236
A9: Total Debt (M) | B9: 24840
A10: Net Debt (M) | B10: =B9-B8 -> 0
A11: Base Year FCF (M) | B11: 5062
A13: WACC | B13: 0.095
A14: Terminal Growth Rate | B14: 0.03
A16: GROWTH ASSUMPTIONS | B16: Year 1 | C16: Year 2 | D16: Year 3 | E16: Year 4 | F16: Year 5
A17: FCF Growth Rate | B17: 0.04 | C17: 0.035 | D17: 0.05 | E17: 0.065 | F17: 0.07
A19: PROJECTIONS
B20: Base | C20: Year 1 | D20: Year 2 | E20: Year 3 | F20: Year 4 | G20: Year 5
A21: Free Cash Flow | B21: =B11 -> 0 | C21: =B21*(1+B17) -> 0 | D21: =C21*(1+C17) -> 0 | E21: =D21*(1+D17) -> 0 | F21: =E21*(1+E17) -> 0 | G21: =F21*(1+F17) -> 0
A22: Discount Factor | C22: =1/(1+$B$13)^1 -> 0 | D22: =1/(1+$B$13)^2 -> 0 | E22: =1/(1+$B$13)^3 -> 0 | F22: =1/(1+$B$13)^4 -> 0 | G22: =1/(1+$B$13)^5 -> 0
A23: PV of FCF | C23: =C21*C22 -> 0 | D23: =D21*D22 -> 0 | E23: =E21*E22 -> 0 | F23: =F21*F22 -> 0 | G23: =G21*G22 -> 0
A25: VALUATION
A26: Sum of PV of FCF | B26: =SUM(C23:G23) -> 0
A27: Terminal FCF (Year 5 * (1+g)) | B27: =G21*(1+$B$14) -> 0
A28: Terminal Value | B28: =B27/($B$13-$B$14) -> 0
A29: PV of Terminal Value | B29: =B28*G22 -> 0
A30: Enterprise Value | B30: =B26+B29 -> 0
A31: Less: Net Debt | B31: =B10 -> 0
A32: Equity Value | B32: =B30-B31 -> 0
A33: INTRINSIC VALUE/SHARE | B33: =B32/B7 -> 0
A35: ENTRY PRICE (15% CAGR Target)
A36: Terminal Value per Share | B36: =B28/B7 -> 0
A37: Entry Price (15% CAGR) | B37: =B36/(1.15^5) -> 0
A39: Upside to IV | B39: =(B33-B6)/B6 -> 0
A40: Discount to Entry Price | B40: =(B6-B37)/B37 -> 0
A42: SCENARIO COMPARISON
B43: Base Case | C43: Bull Case | D43: Bear Case
A44: Y1-Y5 Avg Growth | B44: 0.052 | C44: 0.086 | D44: 0.025
A45: Terminal FCF | B45: 6513 | C45: 8472 | D45: 5218
A46: Intrinsic Value | B46: 105.57 | C46: 199.04 | D46: 52.35
A47: Upside/Downside | B47: -0.082 | C47: 0.731 | D47: -0.545
A48: Entry Price (15% CAGR) | B48: 85.59 | C48: 144.72 | D48: 52.43

Sheet Sensitivity
A1: Sensitivity Analysis
A2: Intrinsic Value by WACC & Terminal Growth (Base Case)
A4: WACC \ Term G | B4: 0.02 | C4: 0.025 | D4: 0.03 | E4: 0.035 | F4: 0.04
A5: 0.075 | B5: =(('DCF Model'!B11*1.04/(1+0.075))+('DCF Model'!B11*1.04*1.035/(1+0.075)^2)+('DCF Model'!B11*1.04*1.035*1.05/(1+0.075)^3)+('DCF Model'!B11*1.04*1.035*1.05*1.065/(1+0.075)^4)+('DCF Model'!B11*1.04*1.035*1.05*1.065*1.07/(1+0.075)^5)+(('DCF Model'!B11*1.04*1.035*1.05*1.065*1.07*(1+0.02))/(0.075-0.02))/(1+0.075)^5-'DCF Model'!B10)/'DCF Model'!B7 -> 0 | C5: =(('DCF Model'!B11*1.04/(1+0.075))+('DCF Model'!B11*1.04*1.035/(1+0.075)^2)+('DCF Model'!B11*1.04*1.035*1.05/(1+0.075)^3)+('DCF Model'!B11*1.04*1.035*1.05*1.065/(1+0.075)^4)+('DCF Model'!B11*1.04*1.035*1.05*1.065*1.07/(1+0.075)^5)+(('DCF Model'!B11*1.04*1.035*1.05*1.065*1.07*(1+0.025))/(0.075-0.025))/(1+0.075)^5-'DCF Model'!B10)/'DCF Model'!B7 -> 0 | D5: =(('DCF Model'!B11*1.04/(1+0.075))+('DCF Model'!B11*1.04*1.035/(1+0.075)^2)+('DCF Model'!B11*1.04*1.035*1.05/(1+0.075)^3)+('DCF Model'!B11*1.04*1.035*1.05*1.065/(1+0.075)^4)+('DCF Model'!B11*1.04*1.035*1.05*1.065*1.07/(1+0.075)^5)+(('DCF Model'!B11*1.04*1.035*1.05*1.065*1.07*(1+0.03))/(0.075-0.03))/(1+0.075)^5-'DCF Model'!B10)/'DCF Model'!B7 -> 0 | E5: =(('DCF Model'!B11*1.04/(1+0.075))+('DCF Model'!B11*1.04*1.035/(1+0.075)^2)+('DCF Model'!B11*1.04*1.035*1.05/(1+0.075)^3)+('DCF Model'!B11*1.04*1.035*1.05*1.065/(1+0.075)^4)+('DCF Model'!B11*1.04*1.035*1.05*1.065*1.07/(1+0.075)^5)+(('DCF Model'!B11*1.04*1.035*1.05*1.065*1.07*(1+0.035))/(0.075-0.035))/(1+0.075)^5-'DCF Model'!B10)/'DCF Model'!B7 -> 0 | F5: =(('DCF Model'!B11*1.04/(1+0.075))+('DCF Model'!B11*1.04*1.035/(1+0.075)^2)+('DCF Model'!B11*1.04*1.035*1.05/(1+0.075)^3)+('DCF Model'!B11*1.04*1.035*1.05*1.065/(1+0.075)^4)+('DCF Model'!B11*1.04*1.035*1.05*1.065*1.07/(1+0.075)^5)+(('DCF Model'!B11*1.04*1.035*1.05*1.065*1.07*(1+0.04))/(0.075-0.04))/(1+0.075)^5-'DCF Model'!B10)/'DCF Model'!B7 -> 0
A6: 0.085 | B6: =(('DCF Model'!B11*1.04/(1+0.085))+('DCF Model'!B11*1.04*1.035/(1+0.085)^2)+('DCF Model'!B11*1.04*1.035*1.05/(1+0.085)^3)+('DCF Model'!B11*1.04*1.035*1.05*1.065/(1+0.085)^4)+('DCF Model'!B11*1.04*1.035*1.05*1.065*1.07/(1+0.085)^5)+(('DCF Model'!B11*1.04*1.035*1.05*1.065*1.07*(1+0.02))/(0.085-0.02))/(1+0.085)^5-'DCF Model'!B10)/'DCF Model'!B7 -> 0 | C6: =(('DCF Model'!B11*1.04/(1+0.085))+('DCF Model'!B11*1.04*1.035/(1+0.085)^2)+('DCF Model'!B11*1.04*1.035*1.05/(1+0.085)^3)+('DCF Model'!B11*1.04*1.035*1.05*1.065/(1+0.085)^4)+('DCF Model'!B11*1.04*1.035*1.05*1.065*1.07/(1+0.085)^5)+(('DCF Model'!B11*1.04*1.035*1.05*1.065*1.07*(1+0.025))/(0.085-0.025))/(1+0.085)^5-'DCF Model'!B10)/'DCF Model'!B7 -> 0 | D6: =(('DCF Model'!B11*1.04/(1+0.085))+('DCF Model'!B11*1.04*1.035/(1+0.085)^2)+('DCF Model'!B11*1.04*1.035*1.05/(1+0.085)^3)+('DCF Model'!B11*1.04*1.035*1.05*1.065/(1+0.085)^4)+('DCF Model'!B11*1.04*1.035*1.05*1.065*1.07/(1+0.085)^5)+(('DCF Model'!B11*1.04*1.035*1.05*1.065*1.07*(1+0.03))/(0.085-0.03))/(1+0.085)^5-'DCF Model'!B10)/'DCF Model'!B7 -> 0 | E6: =(('DCF Model'!B11*1.04/(1+0.085))+('DCF Model'!B11*1.04*1.035/(1+0.085)^2)+('DCF Model'!B11*1.04*1.035*1.05/(1+0.085)^3)+('DCF Model'!B11*1.04*1.035*1.05*1.065/(1+0.085)^4)+('DCF Model'!B11*1.04*1.035*1.05*1.065*1.07/(1+0.085)^5)+(('DCF Model'!B11*1.04*1.035*1.05*1.065*1.07*(1+0.035))/(0.085-0.035))/(1+0.085)^5-'DCF Model'!B10)/'DCF Model'!B7 -> 0 | F6: =(('DCF Model'!B11*1.04/(1+0.085))+('DCF Model'!B11*1.04*1.035/(1+0.085)^2)+('DCF Model'!B11*1.04*1.035*1.05/(1+0.085)^3)+('DCF Model'!B11*1.04*1.035*1.05*1.065/(1+0.085)^4)+('DCF Model'!B11*1.04*1.035*1.05*1.065*1.07/(1+0.085)^5)+(('DCF Model'!B11*1.04*1.035*1.05*1.065*1.07*(1+0.04))/(0.085-0.04))/(1+0.085)^5-'DCF Model'!B10)/'DCF Model'!B7 -> 0
A7: 0.095 | B7: =(('DCF Model'!B11*1.04/(1+0.095))+('DCF Model'!B11*1.04*1.035/(1+0.095)^2)+('DCF Model'!B11*1.04*1.035*1.05/(1+0.095)^3)+('DCF Model'!B11*1.04*1.035*1.05*1.065/(1+0.095)^4)+('DCF Model'!B11*1.04*1.035*1.05*1.065*1.07/(1+0.095)^5)+(('DCF Model'!B11*1.04*1.035*1.05*1.065*1.07*(1+0.02))/(0.095-0.02))/(1+0.095)^5-'DCF Model'!B10)/'DCF Model'!B7 -> 0 | C7: =(('DCF Model'!B11*1.04/(1+0.095))+('DCF Model'!B11*1.04*1.035/(1+0.095)^2)+('DCF Model'!B11*1.04*1.035*1.05/(1+0.095)^3)+('DCF Model'!B11*1.04*1.035*1.05*1.065/(1+0.095)^4)+('DCF Model'!B11*1.04*1.035*1.05*1.065*1.07/(1+0.095)^5)+(('DCF Model'!B11*1.04*1.035*1.05*1.065*1.07*(1+0.025))/(0.095-0.025))/(1+0.095)^5-'DCF Model'!B10)/'DCF Model'!B7 -> 0 | D7: =(('DCF Model'!B11*1.04/(1+0.095))+('DCF Model'!B11*1.04*1.035/(1+0.095)^2)+('DCF Model'!B11*1.04*1.035*1.05/(1+0.095)^3)+('DCF Model'!B11*1.04*1.035*1.05*1.065/(1+0.095)^4)+('DCF Model'!B11*1.04*1.035*1.05*1.065*1.07/(1+0.095)^5)+(('DCF Model'!B11*1.04*1.035*1.05*1.065*1.07*(1+0.03))/(0.095-0.03))/(1+0.095)^5-'DCF Model'!B10)/'DCF Model'!B7 -> 0 | E7: =(('DCF Model'!B11*1.04/(1+0.095))+('DCF Model'!B11*1.04*1.035/(1+0.095)^2)+('DCF Model'!B11*1.04*1.035*1.05/(1+0.095)^3)+('DCF Model'!B11*1.04*1.035*1.05*1.065/(1+0.095)^4)+('DCF Model'!B11*1.04*1.035*1.05*1.065*1.07/(1+0.095)^5)+(('DCF Model'!B11*1.04*1.035*1.05*1.065*1.07*(1+0.035))/(0.095-0.035))/(1+0.095)^5-'DCF Model'!B10)/'DCF Model'!B7 -> 0 | F7: =(('DCF Model'!B11*1.04/(1+0.095))+('DCF Model'!B11*1.04*1.035/(1+0.095)^2)+('DCF Model'!B11*1.04*1.035*1.05/(1+0.095)^3)+('DCF Model'!B11*1.04*1.035*1.05*1.065/(1+0.095)^4)+('DCF Model'!B11*1.04*1.035*1.05*1.065*1.07/(1+0.095)^5)+(('DCF Model'!B11*1.04*1.035*1.05*1.065*1.07*(1+0.04))/(0.095-0.04))/(1+0.095)^5-'DCF Model'!B10)/'DCF Model'!B7 -> 0
A8: 0.105 | B8: =(('DCF Model'!B11*1.04/(1+0.105))+('DCF Model'!B11*1.04*1.035/(1+0.105)^2)+('DCF Model'!B11*1.04*1.035*1.05/(1+0.105)^3)+('DCF Model'!B11*1.04*1.035*1.05*1.065/(1+0.105)^4)+('DCF Model'!B11*1.04*1.035*1.05*1.065*1.07/(1+0.105)^5)+(('DCF Model'!B11*1.04*1.035*1.05*1.065*1.07*(1+0.02))/(0.105-0.02))/(1+0.105)^5-'DCF Model'!B10)/'DCF Model'!B7 -> 0 | C8: =(('DCF Model'!B11*1.04/(1+0.105))+('DCF Model'!B11*1.04*1.035/(1+0.105)^2)+('DCF Model'!B11*1.04*1.035*1.05/(1+0.105)^3)+('DCF Model'!B11*1.04*1.035*1.05*1.065/(1+0.105)^4)+('DCF Model'!B11*1.04*1.035*1.05*1.065*1.07/(1+0.105)^5)+(('DCF Model'!B11*1.04*1.035*1.05*1.065*1.07*(1+0.025))/(0.105-0.025))/(1+0.105)^5-'DCF Model'!B10)/'DCF Model'!B7 -> 0 | D8: =(('DCF Model'!B11*1.04/(1+0.105))+('DCF Model'!B11*1.04*1.035/(1+0.105)^2)+('DCF Model'!B11*1.04*1.035*1.05/(1+0.105)^3)+('DCF Model'!B11*1.04*1.035*1.05*1.065/(1+0.105)^4)+('DCF Model'!B11*1.04*1.035*1.05*1.065*1.07/(1+0.105)^5)+(('DCF Model'!B11*1.04*1.035*1.05*1.065*1.07*(1+0.03))/(0.105-0.03))/(1+0.105)^5-'DCF Model'!B10)/'DCF Model'!B7 -> 0 | E8: =(('DCF Model'!B11*1.04/(1+0.105))+('DCF Model'!B11*1.04*1.035/(1+0.105)^2)+('DCF Model'!B11*1.04*1.035*1.05/(1+0.105)^3)+('DCF Model'!B11*1.04*1.035*1.05*1.065/(1+0.105)^4)+('DCF Model'!B11*1.04*1.035*1.05*1.065*1.07/(1+0.105)^5)+(('DCF Model'!B11*1.04*1.035*1.05*1.065*1.07*(1+0.035))/(0.105-0.035))/(1+0.105)^5-'DCF Model'!B10)/'DCF Model'!B7 -> 0 | F8: =(('DCF Model'!B11*1.04/(1+0.105))+('DCF Model'!B11*1.04*1.035/(1+0.105)^2)+('DCF Model'!B11*1.04*1.035*1.05/(1+0.105)^3)+('DCF Model'!B11*1.04*1.035*1.05*1.065/(1+0.105)^4)+('DCF Model'!B11*1.04*1.035*1.05*1.065*1.07/(1+0.105)^5)+(('DCF Model'!B11*1.04*1.035*1.05*1.065*1.07*(1+0.04))/(0.105-0.04))/(1+0.105)^5-'DCF Model'!B10)/'DCF Model'!B7 -> 0
A9: 0.115 | B9: =(('DCF Model'!B11*1.04/(1+0.115))+('DCF Model'!B11*1.04*1.035/(1+0.115)^2)+('DCF Model'!B11*1.04*1.035*1.05/(1+0.115)^3)+('DCF Model'!B11*1.04*1.035*1.05*1.065/(1+0.115)^4)+('DCF Model'!B11*1.04*1.035*1.05*1.065*1.07/(1+0.115)^5)+(('DCF Model'!B11*1.04*1.035*1.05*1.065*1.07*(1+0.02))/(0.115-0.02))/(1+0.115)^5-'DCF Model'!B10)/'DCF Model'!B7 -> 0 | C9: =(('DCF Model'!B11*1.04/(1+0.115))+('DCF Model'!B11*1.04*1.035/(1+0.115)^2)+('DCF Model'!B11*1.04*1.035*1.05/(1+0.115)^3)+('DCF Model'!B11*1.04*1.035*1.05*1.065/(1+0.115)^4)+('DCF Model'!B11*1.04*1.035*1.05*1.065*1.07/(1+0.115)^5)+(('DCF Model'!B11*1.04*1.035*1.05*1.065*1.07*(1+0.025))/(0.115-0.025))/(1+0.115)^5-'DCF Model'!B10)/'DCF Model'!B7 -> 0 | D9: =(('DCF Model'!B11*1.04/(1+0.115))+('DCF Model'!B11*1.04*1.035/(1+0.115)^2)+('DCF Model'!B11*1.04*1.035*1.05/(1+0.115)^3)+('DCF Model'!B11*1.04*1.035*1.05*1.065/(1+0.115)^4)+('DCF Model'!B11*1.04*1.035*1.05*1.065*1.07/(1+0.115)^5)+(('DCF Model'!B11*1.04*1.035*1.05*1.065*1.07*(1+0.03))/(0.115-0.03))/(1+0.115)^5-'DCF Model'!B10)/'DCF Model'!B7 -> 0 | E9: =(('DCF Model'!B11*1.04/(1+0.115))+('DCF Model'!B11*1.04*1.035/(1+0.115)^2)+('DCF Model'!B11*1.04*1.035*1.05/(1+0.115)^3)+('DCF Model'!B11*1.04*1.035*1.05*1.065/(1+0.115)^4)+('DCF Model'!B11*1.04*1.035*1.05*1.065*1.07/(1+0.115)^5)+(('DCF Model'!B11*1.04*1.035*1.05*1.065*1.07*(1+0.035))/(0.115-0.035))/(1+0.115)^5-'DCF Model'!B10)/'DCF Model'!B7 -> 0 | F9: =(('DCF Model'!B11*1.04/(1+0.115))+('DCF Model'!B11*1.04*1.035/(1+0.115)^2)+('DCF Model'!B11*1.04*1.035*1.05/(1+0.115)^3)+('DCF Model'!B11*1.04*1.035*1.05*1.065/(1+0.115)^4)+('DCF Model'!B11*1.04*1.035*1.05*1.065*1.07/(1+0.115)^5)+(('DCF Model'!B11*1.04*1.035*1.05*1.065*1.07*(1+0.04))/(0.115-0.04))/(1+0.115)^5-'DCF Model'!B10)/'DCF Model'!B7 -> 0
A11: Note: Sensitivity matrix uses Base Case growth rates (4%, 3.5%, 5%, 6.5%, 7%) with varying WACC and Terminal Growth

Sheet Historical
A1: Historical Growth Rates
A2: Note: FY2019 includes First Data merger
A4: Metric | B4: 3-Year CAGR | C4: 5-Year CAGR
A5: Revenue | B5: 0.08 | C5: 0.15
A6: EPS | B6: 0.393 | C6: 0.258
A7: Equity | B7: -0.044 | C7: -0.039
A8: FCF | B8: 0.206 | C8: 0.196
A10: Selected Growth Rate: | B10: 0.08
A11: Source: | B11: revenue_3yr_cagr
A13: Key Context:
A14: - Equity CAGR negative due to share buybacks & First Data debt
A15: - Post-merger revenue CAGR (FY2020-2024): 8.3%
A16: - 2025 guidance: 3.5-4% organic growth (down from 10%)
A17: - 2026: Transition year with low single-digit growth
A18: - 2027+: Targeted return to double-digit EPS growth
A19: - Stock down 70% from peak after Oct 2025 guidance cut

Sheet Company Overview
A1: FISV - Fiserv, Inc.
A2: Valuation Date: 2026-02-02
A4: Investment Thesis:
A5: Fiserv presents a classic turnaround opportunity following a 70% stock decline driven by execution missteps rather than structural business deterioration. The company retains formidable competitive advantages (99% core banking retention, 90B annual transactions, high switching costs) and operates in attractive end markets (digital payments, fintech infrastructure). New leadership team, 2026 reset year positioning, and deeply oversold sentiment create potential for significant returns IF management can execute on operational improvements and restore credibility. However, substantial risk remains given competitive losses, Clover strategy failures, high leverage (Altman Z-Score 1.41), and securities litigation overhang. This is NOT a low-risk value play but rather a turnaround speculation requiring conviction in management's ability to deliver.
A10: Recent Developments:
A11: - Oct 29, 2025: Stock crashed 44% on earnings miss and guidance cut
A12: - 2025 EPS guidance: $8.50-$8.60 (from $10.15-$10.30)
A13: - Organic growth: 3.5-4% (from 10%)
A14: - New leadership: Co-Presidents, CFO, board members appointed
A15: - Clover forced migrations caused 16% attrition
A16: - Securities class action lawsuit filed by shareholders
A17: - 2026 positioned as "transition year" before recovery
A19: Key Financials (FY2024):
A20: Revenue: | B20: $20,456M
A21: Free Cash Flow: | B21: $5,062M (24.7% margin)
A22: Net Debt: | B22: $23,604M
A23: Shares Outstanding: | B23: 582.1M
A25: Probability-Weighted IV:
A26: Weighted Intrinsic Value: | B26: $113.31
A27: Weights: | B27: Bull 30%, Base 45%, Bear 25%
