Workbook

Sheet Inputs
A1: Ticker | B1: CGF.AX
A2: Model | B2: BVPS compounding x exit P/B (insurer route)
A3: Valuation date | B3: 2026-09-22
A4: Current price (AUD) | B4: 10.36
A5: Price as of | B5: 2026-09-22T06:10:05Z (ASX regular close 16:10 AEST)
A6: Shareholders' equity 30 Jun 2026 (A$m) | B6: 4064.5
A7: Shares issued 30 Jun 2026 (m) | B7: 683.8
A8: BVPS (AUD) | B8: =B6/B7
A9: Hurdle rate | B9: 0.15
A10: Horizon (years) | B10: 5
A11: Weight bear | B11: 0.25
A12: Weight base | B12: 0.5
A13: Weight bull | B13: 0.25
A15: Scenario drivers
A16: Driver | B16: Base | C16: Bull | D16: Bear
A17: Cost of equity (%) | B17: 10.5 | C17: 10 | D17: 11.5
A18: Exit P/B | B18: 1.3 | C18: 1.6 | D18: 0.95
A19: Payout % of operating NPAT | B19: 47 | C19: 47 | D19: 47
A20: ROE Y1 (%) | B20: 12 | C20: 13 | D20: 10.5
A21: ROE Y2 (%) | B21: 12.25 | C21: 13.5 | D21: 10
A22: ROE Y3 (%) | B22: 12.5 | C22: 14 | D22: 9.5
A23: ROE Y4 (%) | B23: 12.5 | C23: 14 | D23: 9.5
A24: ROE Y5 (%) | B24: 12.5 | C24: 14 | D24: 9.5
A25: Buy-back Y1 (A$m) | B25: 362 | C25: 362 | D25: 362
A26: Buy-back Y2 (A$m) | B26: 100 | C26: 200 | D26: 0
A27: Buy-back Y3 (A$m) | B27: 100 | C27: 200 | D27: 0
A28: Buy-back Y4 (A$m) | B28: 100 | C28: 200 | D28: 0
A29: Buy-back Y5 (A$m) | B29: 100 | C29: 200 | D29: 0

Sheet Base
A1: Year | B1: FY2026 | C1: FY2027 | D1: FY2028 | E1: FY2029 | F1: FY2030 | G1: FY2031
A2: Opening equity (A$m) | C2: =B9 | D2: =C9 | E2: =D9 | F2: =E9 | G2: =F9
A3: ROE (%) | C3: =Inputs!B20 | D3: =Inputs!B21 | E3: =Inputs!B22 | F3: =Inputs!B23 | G3: =Inputs!B24
A4: Operating NPAT (A$m) | C4: =C3/100*C2 | D4: =D3/100*D2 | E4: =E3/100*E2 | F4: =F3/100*F2 | G4: =G3/100*G2
A5: Dividends (A$m) | C5: =Inputs!B19/100*C4 | D5: =Inputs!B19/100*D4 | E5: =Inputs!B19/100*E4 | F5: =Inputs!B19/100*F4 | G5: =Inputs!B19/100*G4
A6: Buy-back (A$m) | C6: =Inputs!B25 | D6: =Inputs!B26 | E6: =Inputs!B27 | F6: =Inputs!B28 | G6: =Inputs!B29
A7: Buy-back price (AUD) | C7: =Inputs!B4 | D7: =C12*Inputs!B18 | E7: =D12*Inputs!B18 | F7: =E12*Inputs!B18 | G7: =F12*Inputs!B18
A8: Shares bought (m) | C8: =C6/C7 | D8: =D6/D7 | E8: =E6/E7 | F8: =F6/F7 | G8: =G6/G7
A9: Closing equity (A$m) | B9: =Inputs!B6 | C9: =C2+C4-C5-C6 | D9: =D2+D4-D5-D6 | E9: =E2+E4-E5-E6 | F9: =F2+F4-F5-F6 | G9: =G2+G4-G5-G6
A10: Opening shares (m) | C10: =B11 | D10: =C11 | E10: =D11 | F10: =E11 | G10: =F11
A11: Closing shares (m) | B11: =Inputs!B7 | C11: =C10-C8 | D11: =D10-D8 | E11: =E10-E8 | F11: =F10-F8 | G11: =G10-G8
A12: BVPS (AUD) | B12: =Inputs!B8 | C12: =C9/C11 | D12: =D9/D11 | E12: =E9/E11 | F12: =F9/F11 | G12: =G9/G11
A13: DPS (AUD) | C13: =C5/C10 | D13: =D5/D10 | E13: =E5/E10 | F13: =F5/F10 | G13: =G5/G10
A14: EPS (AUD) | C14: =C4/((C10+C11)/2) | D14: =D4/((D10+D11)/2) | E14: =E4/((E10+E11)/2) | F14: =F4/((F10+F11)/2) | G14: =G4/((G10+G11)/2)
A15: Discount factor | C15: =1/(1+Inputs!B17/100)^1 | D15: =1/(1+Inputs!B17/100)^2 | E15: =1/(1+Inputs!B17/100)^3 | F15: =1/(1+Inputs!B17/100)^4 | G15: =1/(1+Inputs!B17/100)^5
A16: PV dividend (AUD) | C16: =C13*C15 | D16: =D13*D15 | E16: =E13*E15 | F16: =F13*F15 | G16: =G13*G15
A18: Sum PV dividends | B18: =SUM(C16:G16)
A19: Terminal BVPS | B19: =G12
A20: Exit P/B | B20: =Inputs!B18
A21: Terminal value / share | B21: =B19*B20
A22: PV terminal value | B22: =B21*G15
A23: Intrinsic value / share | B23: =B18+B22
A24: Upside vs price (%) | B24: =(B23/Inputs!B4-1)*100
A25: Implied exit P/E | B25: =B21/G14
A26: Terminal % of value | B26: =B22/B23*100
A27: Entry price @ hurdle | B27: =SUMPRODUCT(C13:G13,1/(1+Inputs!$B$9)^{1,2,3,4,5})+B21/(1+Inputs!$B$9)^Inputs!$B$10

Sheet Bull
A1: Year | B1: FY2026 | C1: FY2027 | D1: FY2028 | E1: FY2029 | F1: FY2030 | G1: FY2031
A2: Opening equity (A$m) | C2: =B9 | D2: =C9 | E2: =D9 | F2: =E9 | G2: =F9
A3: ROE (%) | C3: =Inputs!C20 | D3: =Inputs!C21 | E3: =Inputs!C22 | F3: =Inputs!C23 | G3: =Inputs!C24
A4: Operating NPAT (A$m) | C4: =C3/100*C2 | D4: =D3/100*D2 | E4: =E3/100*E2 | F4: =F3/100*F2 | G4: =G3/100*G2
A5: Dividends (A$m) | C5: =Inputs!C19/100*C4 | D5: =Inputs!C19/100*D4 | E5: =Inputs!C19/100*E4 | F5: =Inputs!C19/100*F4 | G5: =Inputs!C19/100*G4
A6: Buy-back (A$m) | C6: =Inputs!C25 | D6: =Inputs!C26 | E6: =Inputs!C27 | F6: =Inputs!C28 | G6: =Inputs!C29
A7: Buy-back price (AUD) | C7: =Inputs!B4 | D7: =C12*Inputs!C18 | E7: =D12*Inputs!C18 | F7: =E12*Inputs!C18 | G7: =F12*Inputs!C18
A8: Shares bought (m) | C8: =C6/C7 | D8: =D6/D7 | E8: =E6/E7 | F8: =F6/F7 | G8: =G6/G7
A9: Closing equity (A$m) | B9: =Inputs!B6 | C9: =C2+C4-C5-C6 | D9: =D2+D4-D5-D6 | E9: =E2+E4-E5-E6 | F9: =F2+F4-F5-F6 | G9: =G2+G4-G5-G6
A10: Opening shares (m) | C10: =B11 | D10: =C11 | E10: =D11 | F10: =E11 | G10: =F11
A11: Closing shares (m) | B11: =Inputs!B7 | C11: =C10-C8 | D11: =D10-D8 | E11: =E10-E8 | F11: =F10-F8 | G11: =G10-G8
A12: BVPS (AUD) | B12: =Inputs!B8 | C12: =C9/C11 | D12: =D9/D11 | E12: =E9/E11 | F12: =F9/F11 | G12: =G9/G11
A13: DPS (AUD) | C13: =C5/C10 | D13: =D5/D10 | E13: =E5/E10 | F13: =F5/F10 | G13: =G5/G10
A14: EPS (AUD) | C14: =C4/((C10+C11)/2) | D14: =D4/((D10+D11)/2) | E14: =E4/((E10+E11)/2) | F14: =F4/((F10+F11)/2) | G14: =G4/((G10+G11)/2)
A15: Discount factor | C15: =1/(1+Inputs!C17/100)^1 | D15: =1/(1+Inputs!C17/100)^2 | E15: =1/(1+Inputs!C17/100)^3 | F15: =1/(1+Inputs!C17/100)^4 | G15: =1/(1+Inputs!C17/100)^5
A16: PV dividend (AUD) | C16: =C13*C15 | D16: =D13*D15 | E16: =E13*E15 | F16: =F13*F15 | G16: =G13*G15
A18: Sum PV dividends | B18: =SUM(C16:G16)
A19: Terminal BVPS | B19: =G12
A20: Exit P/B | B20: =Inputs!C18
A21: Terminal value / share | B21: =B19*B20
A22: PV terminal value | B22: =B21*G15
A23: Intrinsic value / share | B23: =B18+B22
A24: Upside vs price (%) | B24: =(B23/Inputs!B4-1)*100
A25: Implied exit P/E | B25: =B21/G14
A26: Terminal % of value | B26: =B22/B23*100
A27: Entry price @ hurdle | B27: =SUMPRODUCT(C13:G13,1/(1+Inputs!$B$9)^{1,2,3,4,5})+B21/(1+Inputs!$B$9)^Inputs!$B$10

Sheet Bear
A1: Year | B1: FY2026 | C1: FY2027 | D1: FY2028 | E1: FY2029 | F1: FY2030 | G1: FY2031
A2: Opening equity (A$m) | C2: =B9 | D2: =C9 | E2: =D9 | F2: =E9 | G2: =F9
A3: ROE (%) | C3: =Inputs!D20 | D3: =Inputs!D21 | E3: =Inputs!D22 | F3: =Inputs!D23 | G3: =Inputs!D24
A4: Operating NPAT (A$m) | C4: =C3/100*C2 | D4: =D3/100*D2 | E4: =E3/100*E2 | F4: =F3/100*F2 | G4: =G3/100*G2
A5: Dividends (A$m) | C5: =Inputs!D19/100*C4 | D5: =Inputs!D19/100*D4 | E5: =Inputs!D19/100*E4 | F5: =Inputs!D19/100*F4 | G5: =Inputs!D19/100*G4
A6: Buy-back (A$m) | C6: =Inputs!D25 | D6: =Inputs!D26 | E6: =Inputs!D27 | F6: =Inputs!D28 | G6: =Inputs!D29
A7: Buy-back price (AUD) | C7: =Inputs!B4 | D7: =C12*Inputs!D18 | E7: =D12*Inputs!D18 | F7: =E12*Inputs!D18 | G7: =F12*Inputs!D18
A8: Shares bought (m) | C8: =C6/C7 | D8: =D6/D7 | E8: =E6/E7 | F8: =F6/F7 | G8: =G6/G7
A9: Closing equity (A$m) | B9: =Inputs!B6 | C9: =C2+C4-C5-C6 | D9: =D2+D4-D5-D6 | E9: =E2+E4-E5-E6 | F9: =F2+F4-F5-F6 | G9: =G2+G4-G5-G6
A10: Opening shares (m) | C10: =B11 | D10: =C11 | E10: =D11 | F10: =E11 | G10: =F11
A11: Closing shares (m) | B11: =Inputs!B7 | C11: =C10-C8 | D11: =D10-D8 | E11: =E10-E8 | F11: =F10-F8 | G11: =G10-G8
A12: BVPS (AUD) | B12: =Inputs!B8 | C12: =C9/C11 | D12: =D9/D11 | E12: =E9/E11 | F12: =F9/F11 | G12: =G9/G11
A13: DPS (AUD) | C13: =C5/C10 | D13: =D5/D10 | E13: =E5/E10 | F13: =F5/F10 | G13: =G5/G10
A14: EPS (AUD) | C14: =C4/((C10+C11)/2) | D14: =D4/((D10+D11)/2) | E14: =E4/((E10+E11)/2) | F14: =F4/((F10+F11)/2) | G14: =G4/((G10+G11)/2)
A15: Discount factor | C15: =1/(1+Inputs!D17/100)^1 | D15: =1/(1+Inputs!D17/100)^2 | E15: =1/(1+Inputs!D17/100)^3 | F15: =1/(1+Inputs!D17/100)^4 | G15: =1/(1+Inputs!D17/100)^5
A16: PV dividend (AUD) | C16: =C13*C15 | D16: =D13*D15 | E16: =E13*E15 | F16: =F13*F15 | G16: =G13*G15
A18: Sum PV dividends | B18: =SUM(C16:G16)
A19: Terminal BVPS | B19: =G12
A20: Exit P/B | B20: =Inputs!D18
A21: Terminal value / share | B21: =B19*B20
A22: PV terminal value | B22: =B21*G15
A23: Intrinsic value / share | B23: =B18+B22
A24: Upside vs price (%) | B24: =(B23/Inputs!B4-1)*100
A25: Implied exit P/E | B25: =B21/G14
A26: Terminal % of value | B26: =B22/B23*100
A27: Entry price @ hurdle | B27: =SUMPRODUCT(C13:G13,1/(1+Inputs!$B$9)^{1,2,3,4,5})+B21/(1+Inputs!$B$9)^Inputs!$B$10

Sheet Summary
A1: Scenario | B1: Intrinsic value | C1: Entry price @15% | D1: Weight
A2: Bear | B2: =Bear!B23 | C2: =Bear!B27 | D2: =Inputs!B11
A3: Base | B3: =Base!B23 | C3: =Base!B27 | D3: =Inputs!B12
A4: Bull | B4: =Bull!B23 | C4: =Bull!B27 | D4: =Inputs!B13
A5: Weighted | B5: =SUMPRODUCT(B2:B4,D2:D4) | C5: =SUMPRODUCT(C2:C4,D2:D4) | D5: =SUM(D2:D4)
A6: Current price | B6: =Inputs!B4
A7: Weighted upside (%) | B7: =(B5/B6-1)*100
A9: Sensitivity (base flows): rows CoE %, cols exit P/B -- static values from the JSON
A10: CoE \ P/B | B10: 1 | C10: 1.15 | D10: 1.3 | E10: 1.45 | F10: 1.6
A11: 9 | B11: 6.5 | C11: 7.26 | D11: 8.01 | E11: 8.77 | F11: 9.52
A12: 10 | B12: 6.24 | C12: 6.96 | D12: 7.68 | E12: 8.4 | F12: 9.12
A13: 10.5 | B13: 6.11 | C13: 6.82 | D13: 7.52 | E13: 8.23 | F13: 8.93
A14: 11 | B14: 5.99 | C14: 6.68 | D14: 7.37 | E14: 8.06 | F14: 8.75
A15: 12 | B15: 5.75 | C15: 6.41 | D15: 7.07 | E15: 7.73 | F15: 8.39
A18: Required return (base flows)
A19: CoE % | B19: 9 | C19: 10 | D19: 11 | E19: 12 | F19: 15
A20: Value / share | B20: 8.01 | C20: 7.68 | D20: 7.37 | E20: 7.07 | F20: 6.26
