Workbook

Sheet Model_Info
A1: Temple & Webster Group (TPW.AX) owner-FCF DCF model
A2: Version | B2: 1.0 fresh build 2026-08-26; supersedes nothing (no prior TPW.AX DCF)
A3: Built by | B3: dcf-analyst agent (Claude Fable 5) on 2026-08-26 at the research-stock orchestrator's request
A4: Price | B4: A$4.82 ASX regular close 2026-08-26 06:10 UTC (Yahoo) — goes stale; refresh before use
A5: Balance sheet | B5: 30-Jun-2026 FY2026 Annual Report: cash A$122.694m, borrowings nil, lease liabilities A$42.372m
A6: Share count | B6: 121.903m fully diluted = 116.547m on issue 30-Jun-2026 + 5.356m dilutive effect (note 34); held flat (SBC expensed)
A7: Guidance | B7: FY27 underlying EBITDA A$33-40m (5-6% margin), no revenue guidance; first 7 weeks FY27 checkout revenue −13% YoY (19-Aug-2026)
A8: Method: model | B8: Owner-FCF DCF, 10-year component build, TV = MAX(0,MIN(Gordon, 15x FCF10)), end-year discounting, WACC 11.5% AUD-built, same in all scenarios
A9: Method: SBC | B9: Expensed as % of revenue in the flows; share count flat (charge once). Street memo adds SBC PV back
A10: Method: interest | B10: Interest income stripped from FCF; cash added in the bridge
A11: Method: leases | B11: Treatment B — lease cash charged in flows at 1.8% of revenue; lease liabilities EXCLUDED from net debt; D&A and capex ex-ROU
A12: Method: working capital | B12: Capture rate x change in revenue (negative-WC model unwinds on decline)
A13: Method: tax | B13: 30% AU statutory on SBC-expensed EBIT
... A17: Layout | B17: DCF tabs: row 3 years, 4 index, 5 growth, 6 revenue, 7 EBITDA margin, 8 EBITDA, 9 SBC%, 10 SBC$, 11 lease cost, 12 owner EBITDA after lease, 13 D&A, 14 EBIT, 15 tax rate, 16 NOPAT, 17 add D&A, 18 capex, 19 WC, 20 owner FCF, 21 DF, 22 PV; valuation block rows 27-40; street memo 42-44

Sheet Actuals
A1: FY | B1: Revenue | C1: Reported FCF | D1: SBC | E1: Interest income | F1: Lease principal | G1: EPS (c) | H1: Equity | I1: Shares (m) | J1: EBITDA | K1: Cash | L1: Net income
A2: FY2019 | B2: 101.613 | C2: 3.624 | D2: 1.047 | E2: 0.142 | F2: 0 | G2: 3.37 | H2: 15.213 | I2: 111.871 | J2: 1.109 | K2: 13.539 | L2: 3.764
A3: FY2020 | B3: 176.342 | C3: 24.933 | D3: 0.909 | E3: 0.229 | F3: 0 | G3: 12.28 | H3: 29.984 | I3: 113.226 | J3: 8.484 | K3: 38.082 | L3: 13.909
A4: FY2021 | B4: 326.344 | C4: 23.03 | D4: 1.238 | E4: 0.438 | F4: 1 | G4: 11.6 | H4: 84.004 | I4: 120.336 | J4: 20.504 | K4: 97.504 | L4: 13.953
A5: FY2022 | B5: 426.335 | C5: 7.6 | D5: 1.717 | E5: 0.419 | F5: 2.2 | G5: 9.93 | H5: 102.912 | I5: 120.465 | J5: 16.191 | K5: 101.011 | L5: 11.968
A6: FY2023 | B6: 395.513 | C6: 19.216 | D6: 3.103 | E6: 3.367 | F6: 4.6 | G6: 6.82 | H6: 107.731 | I6: 121.77 | J6: 14.809 | K6: 105.14 | L6: 8.305
A7: FY2024 | B7: 497.841 | C7: 29.442 | D7: 3.854 | E7: 4.964 | F7: 5.7 | G7: 1.5 | H7: 106.523 | I7: 119.175 | J7: 8.431 | K7: 107.152 | L7: 1.786
A8: FY2025 | B8: 600.719 | C8: 44.734 | D8: 4.88 | E8: 5.674 | F8: 6.798 | G8: 9.52 | H8: 148.077 | I8: 118.733 | J8: 18.791 | K8: 144.346 | L8: 11.302
A9: FY2026 | B9: 664.586 | C9: 14.055 | D9: 4.177 | E9: 4.847 | F9: 6.615 | G9: 3.62 | H9: 105.634 | I9: 118.83 | J9: 21.905 | K9: 122.694 | L9: 4.304
A11: Source: TPW.AX_Metrics.csv (annual reports, AUD m); lease principal from cash-flow statements; FY2019-22 lease principal approximated from lease notes
A12: FY27 guidance: underlying EBITDA A$33-40m; no revenue guidance; 7-week checkout revenue −13%

Sheet Assumptions
A1: Global inputs
A3: WACC | B3: 0.115 | C3: AUD-built: rf 4.2% + 5.5% ERP x beta 1.35; same all scenarios
A4: D&A % revenue (ex-ROU) | B4: 0.005 | C4: FY26 ex-ROU D&A 1.6m = 0.24%; normalised 0.5%
A5: Capex % revenue (cash, ex-ROU) | B5: 0.008 | C5: FY26 1.5% (warehouse fit-out), FY25 0.2%; normalised 0.8%
A6: Lease cash cost % revenue | B6: 0.018 | C6: FY26 8.6m = 1.3%; liability doubled to 42.4m so payments step up to ~12m
A7: Cash tax rate | B7: 0.3 | C7: AU statutory 30%
A8: Net cash (A$m) 30-Jun-2026 | B8: 122.694 | C8: cash 122.694; leases excluded (treatment B)
A9: Diluted shares (m) | B9: 121.903 | C9: 116.547 on issue + 5.356 dilutive (note 34)
A10: Price (A$) | B10: 4.82 | C10: ASX close 2026-08-26
A11: TV cap (x FCF10) | B11: 15 | C11: cyclical retailer cap
A12: Hurdle rate | B12: 0.15 | C12: entry price IRR
A14: Scenario | B14: Terminal growth | C14: Weight | D14: WC capture
A15: bear | B15: 0.025 | C15: 0.25 | D15: 0.08
A16: base | B16: 0.03 | C16: 0.5 | D16: 0.1
A17: bull | B17: 0.035 | C17: 0.25 | D17: 0.12
A18: Weights sum | B18: =SUM(C15:C17)
A20: Narratives
A21: Bear: −13% opening is demand; Amazon/Kogan discounting; revenue −10% FY27 then 3-4%; margin 3-4.5%; WC unwinds.
A22: Base: FY27 −3% then 8-10% re-acceleration; A$1bn revenue ~FY32; EBITDA margin 4.6% -> 7.5%; lease 1.8%; tax 30%.
A23: Bull: comp artefact; 14-15% growth, A$1bn by FY30; private-label and AI lift margin to 9%.

Sheet DCF_Bear
A1: Bear case owner-FCF DCF (A$m)
A3: Year | B3: FY2026A | C3: FY2027E | D3: FY2028E | E3: FY2029E | F3: FY2030E | G3: FY2031E | H3: FY2032E | I3: FY2033E | J3: FY2034E | K3: FY2035E | L3: FY2036E
A4: Index | B4: 0 | C4: 1 | D4: 2 | E4: 3 | F4: 4 | G4: 5 | H4: 6 | I4: 7 | J4: 8 | K4: 9 | L4: 10
A5: Revenue growth | C5: -0.1 | D5: 0 | E5: 0.03 | F5: 0.04 | G5: 0.04 | H5: 0.04 | I5: 0.035 | J5: 0.03 | K5: 0.03 | L5: 0.03
A6: Revenue | B6: 664.586 | C6: =B6*(1+C5) | D6: =C6*(1+D5) | E6: =D6*(1+E5) | F6: =E6*(1+F5) | G6: =F6*(1+G5) | H6: =G6*(1+H5) | I6: =H6*(1+I5) | J6: =I6*(1+J5) | ... L6: =K6*(1+L5)
A7: Adj EBITDA margin (post-AASB16) | C7: 0.03 | D7: 0.03 | E7: 0.035 | F7: 0.04 | G7: 0.04 | H7: 0.045 | I7: 0.045 | J7: 0.045 | K7: 0.045 | L7: 0.045
A8: Adj EBITDA | B8: 21.905 | C8: =C6*C7 | D8: =D6*D7 | E8: =E6*E7 | F8: =F6*F7 | G8: =G6*G7 | H8: =H6*H7 | I8: =I6*I7 | J8: =J6*J7 | ... L8: =L6*L7
A9: SBC % revenue | C9: 0.0065 | D9: 0.0065 | E9: 0.0065 | F9: 0.0065 | G9: 0.0065 | H9: 0.0065 | I9: 0.0065 | J9: 0.0065 | K9: 0.0065 | L9: 0.0065
A10: SBC | B10: -4.177 | C10: =-C6*C9 | D10: =-D6*D9 | E10: =-E6*E9 | F10: =-F6*F9 | G10: =-G6*G9 | H10: =-H6*H9 | I10: =-I6*I9 | J10: =-J6*J9 | ... L10: =-L6*L9
A11: Lease cash cost | C11: =-C6*Assumptions!$B$6 | D11: =-D6*Assumptions!$B$6 | E11: =-E6*Assumptions!$B$6 | F11: =-F6*Assumptions!$B$6 | G11: =-G6*Assumptions!$B$6 | H11: =-H6*Assumptions!$B$6 | I11: =-I6*Assumptions!$B$6 | J11: =-J6*Assumptions!$B$6 | ... L11: =-L6*Assumptions!$B$6
A12: Owner EBITDA after lease | C12: =C8+C10+C11 | D12: =D8+D10+D11 | E12: =E8+E10+E11 | F12: =F8+F10+F11 | G12: =G8+G10+G11 | H12: =H8+H10+H11 | I12: =I8+I10+I11 | J12: =J8+J10+J11 | ... L12: =L8+L10+L11
A13: D&A (ex-ROU) | C13: =-C6*Assumptions!$B$4 | D13: =-D6*Assumptions!$B$4 | E13: =-E6*Assumptions!$B$4 | F13: =-F6*Assumptions!$B$4 | G13: =-G6*Assumptions!$B$4 | H13: =-H6*Assumptions!$B$4 | I13: =-I6*Assumptions!$B$4 | J13: =-J6*Assumptions!$B$4 | ... L13: =-L6*Assumptions!$B$4
A14: EBIT (SBC expensed) | C14: =C12+C13 | D14: =D12+D13 | E14: =E12+E13 | F14: =F12+F13 | G14: =G12+G13 | H14: =H12+H13 | I14: =I12+I13 | J14: =J12+J13 | ... L14: =L12+L13
A15: Cash tax rate | C15: 0.3 | D15: 0.3 | E15: 0.3 | F15: 0.3 | G15: 0.3 | H15: 0.3 | I15: 0.3 | J15: 0.3 | K15: 0.3 | L15: 0.3
A16: NOPAT | C16: =C14*(1-C15) | D16: =D14*(1-D15) | E16: =E14*(1-E15) | F16: =F14*(1-F15) | G16: =G14*(1-G15) | H16: =H14*(1-H15) | I16: =I14*(1-I15) | J16: =J14*(1-J15) | ... L16: =L14*(1-L15)
A17: add back D&A | C17: =-C13 | D17: =-D13 | E17: =-E13 | F17: =-F13 | G17: =-G13 | H17: =-H13 | I17: =-I13 | J17: =-J13 | ... L17: =-L13
A18: less capex | C18: =-C6*Assumptions!$B$5 | D18: =-D6*Assumptions!$B$5 | E18: =-E6*Assumptions!$B$5 | F18: =-F6*Assumptions!$B$5 | G18: =-G6*Assumptions!$B$5 | H18: =-H6*Assumptions!$B$5 | I18: =-I6*Assumptions!$B$5 | J18: =-J6*Assumptions!$B$5 | ... L18: =-L6*Assumptions!$B$5
A19: add working capital | C19: =Assumptions!$D$15*(C6-B6) | D19: =Assumptions!$D$15*(D6-C6) | E19: =Assumptions!$D$15*(E6-D6) | F19: =Assumptions!$D$15*(F6-E6) | G19: =Assumptions!$D$15*(G6-F6) | H19: =Assumptions!$D$15*(H6-G6) | I19: =Assumptions!$D$15*(I6-H6) | J19: =Assumptions!$D$15*(J6-I6) | ... L19: =Assumptions!$D$15*(L6-K6)
A20: Unlevered owner FCF | B20: -1.584 | C20: =C16+C17+C18+C19 | D20: =D16+D17+D18+D19 | E20: =E16+E17+E18+E19 | F20: =F16+F17+F18+F19 | G20: =G16+G17+G18+G19 | H20: =H16+H17+H18+H19 | I20: =I16+I17+I18+I19 | J20: =J16+J17+J18+J19 | ... L20: =L16+L17+L18+L19
A21: Discount factor | C21: =1/(1+Assumptions!$B$3)^C4 | D21: =1/(1+Assumptions!$B$3)^D4 | E21: =1/(1+Assumptions!$B$3)^E4 | F21: =1/(1+Assumptions!$B$3)^F4 | G21: =1/(1+Assumptions!$B$3)^G4 | H21: =1/(1+Assumptions!$B$3)^H4 | I21: =1/(1+Assumptions!$B$3)^I4 | J21: =1/(1+Assumptions!$B$3)^J4 | ... L21: =1/(1+Assumptions!$B$3)^L4
A22: PV of FCF | C22: =C20*C21 | D22: =D20*D21 | E22: =E20*E21 | F22: =F20*F21 | G22: =G20*G21 | H22: =H20*H21 | I22: =I20*I21 | J22: =J20*J21 | ... L22: =L20*L21
A24: Memo: FCF before SBC | C24: =C20-C10 | D24: =D20-D10 | E24: =E20-E10 | F24: =F20-F10 | G24: =G20-G10 | H24: =H20-H10 | I24: =I20-I10 | J24: =J20-J10 | ... L24: =L20-L10
A25: Memo: owner FCF margin | C25: =C20/C6 | D25: =D20/D6 | E25: =E20/E6 | F25: =F20/F6 | G25: =G20/G6 | H25: =H20/H6 | I25: =I20/I6 | J25: =J20/J6 | ... L25: =L20/L6
A27: Sum of PV FCF | B27: =SUM(C22:L22)
A28: Terminal growth | B28: =Assumptions!$B$15
A29: Terminal FCF (FCF10 x (1+g)) | B29: =L20*(1+B28)
A30: Gordon TV | B30: =B29/(Assumptions!$B$3-B28)
A31: Cap TV | B31: =Assumptions!$B$11*L20
A32: TV used | B32: =MAX(0,MIN(B30,B31))
A33: Implied exit multiple (TV/FCF10) | B33: =IF(L20=0,"n/a",B32/L20)
A34: PV of TV | B34: =B32*L21
A35: Enterprise value | B35: =B27+B34
A36: add net cash | B36: =Assumptions!$B$8
A37: Equity value | B37: =B35+B36
A38: Diluted shares | B38: =Assumptions!$B$9
A39: Value per share (A$) | B39: =B37/B38
A40: Upside vs price | B40: =B39/Assumptions!$B$10-1
A42: Street memo: PV explicit SBC | B42: =SUMPRODUCT(-C10:L10/(1+Assumptions!$B$3)^C4:L4)
A43: Street memo: PV terminal SBC | B43: =(-L10*(1+B28)/(Assumptions!$B$3-B28))*L21
A44: Street value per share | B44: =(B37+B42+B43)/B38

Sheet DCF_Base
A1: Base case owner-FCF DCF (A$m)
A3: Year | B3: FY2026A | C3: FY2027E | D3: FY2028E | E3: FY2029E | F3: FY2030E | G3: FY2031E | H3: FY2032E | I3: FY2033E | J3: FY2034E | K3: FY2035E | L3: FY2036E
A4: Index | B4: 0 | C4: 1 | D4: 2 | E4: 3 | F4: 4 | G4: 5 | H4: 6 | I4: 7 | J4: 8 | K4: 9 | L4: 10
A5: Revenue growth | C5: -0.03 | D5: 0.08 | E5: 0.1 | F5: 0.09 | G5: 0.08 | H5: 0.07 | I5: 0.06 | J5: 0.05 | K5: 0.04 | L5: 0.035
A6: Revenue | B6: 664.586 | C6: =B6*(1+C5) | D6: =C6*(1+D5) | E6: =D6*(1+E5) | F6: =E6*(1+F5) | G6: =F6*(1+G5) | H6: =G6*(1+H5) | I6: =H6*(1+I5) | J6: =I6*(1+J5) | ... L6: =K6*(1+L5)
A7: Adj EBITDA margin (post-AASB16) | C7: 0.046 | D7: 0.05 | E7: 0.055 | F7: 0.06 | G7: 0.065 | H7: 0.07 | I7: 0.075 | J7: 0.075 | K7: 0.075 | L7: 0.075
A8: Adj EBITDA | B8: 21.905 | C8: =C6*C7 | D8: =D6*D7 | E8: =E6*E7 | F8: =F6*F7 | G8: =G6*G7 | H8: =H6*H7 | I8: =I6*I7 | J8: =J6*J7 | ... L8: =L6*L7
A9: SBC % revenue | C9: 0.0065 | D9: 0.0063 | E9: 0.0061 | F9: 0.0059 | G9: 0.0057 | H9: 0.0055 | I9: 0.0053 | J9: 0.0051 | K9: 0.005 | L9: 0.005
A10: SBC | B10: -4.177 | C10: =-C6*C9 | D10: =-D6*D9 | E10: =-E6*E9 | F10: =-F6*F9 | G10: =-G6*G9 | H10: =-H6*H9 | I10: =-I6*I9 | J10: =-J6*J9 | ... L10: =-L6*L9
A11: Lease cash cost | C11: =-C6*Assumptions!$B$6 | D11: =-D6*Assumptions!$B$6 | E11: =-E6*Assumptions!$B$6 | F11: =-F6*Assumptions!$B$6 | G11: =-G6*Assumptions!$B$6 | H11: =-H6*Assumptions!$B$6 | I11: =-I6*Assumptions!$B$6 | J11: =-J6*Assumptions!$B$6 | ... L11: =-L6*Assumptions!$B$6
A12: Owner EBITDA after lease | C12: =C8+C10+C11 | D12: =D8+D10+D11 | E12: =E8+E10+E11 | F12: =F8+F10+F11 | G12: =G8+G10+G11 | H12: =H8+H10+H11 | I12: =I8+I10+I11 | J12: =J8+J10+J11 | ... L12: =L8+L10+L11
A13: D&A (ex-ROU) | C13: =-C6*Assumptions!$B$4 | D13: =-D6*Assumptions!$B$4 | E13: =-E6*Assumptions!$B$4 | F13: =-F6*Assumptions!$B$4 | G13: =-G6*Assumptions!$B$4 | H13: =-H6*Assumptions!$B$4 | I13: =-I6*Assumptions!$B$4 | J13: =-J6*Assumptions!$B$4 | ... L13: =-L6*Assumptions!$B$4
A14: EBIT (SBC expensed) | C14: =C12+C13 | D14: =D12+D13 | E14: =E12+E13 | F14: =F12+F13 | G14: =G12+G13 | H14: =H12+H13 | I14: =I12+I13 | J14: =J12+J13 | ... L14: =L12+L13
A15: Cash tax rate | C15: 0.3 | D15: 0.3 | E15: 0.3 | F15: 0.3 | G15: 0.3 | H15: 0.3 | I15: 0.3 | J15: 0.3 | K15: 0.3 | L15: 0.3
A16: NOPAT | C16: =C14*(1-C15) | D16: =D14*(1-D15) | E16: =E14*(1-E15) | F16: =F14*(1-F15) | G16: =G14*(1-G15) | H16: =H14*(1-H15) | I16: =I14*(1-I15) | J16: =J14*(1-J15) | ... L16: =L14*(1-L15)
A17: add back D&A | C17: =-C13 | D17: =-D13 | E17: =-E13 | F17: =-F13 | G17: =-G13 | H17: =-H13 | I17: =-I13 | J17: =-J13 | ... L17: =-L13
A18: less capex | C18: =-C6*Assumptions!$B$5 | D18: =-D6*Assumptions!$B$5 | E18: =-E6*Assumptions!$B$5 | F18: =-F6*Assumptions!$B$5 | G18: =-G6*Assumptions!$B$5 | H18: =-H6*Assumptions!$B$5 | I18: =-I6*Assumptions!$B$5 | J18: =-J6*Assumptions!$B$5 | ... L18: =-L6*Assumptions!$B$5
A19: add working capital | C19: =Assumptions!$D$16*(C6-B6) | D19: =Assumptions!$D$16*(D6-C6) | E19: =Assumptions!$D$16*(E6-D6) | F19: =Assumptions!$D$16*(F6-E6) | G19: =Assumptions!$D$16*(G6-F6) | H19: =Assumptions!$D$16*(H6-G6) | I19: =Assumptions!$D$16*(I6-H6) | J19: =Assumptions!$D$16*(J6-I6) | ... L19: =Assumptions!$D$16*(L6-K6)
A20: Unlevered owner FCF | B20: -1.584 | C20: =C16+C17+C18+C19 | D20: =D16+D17+D18+D19 | E20: =E16+E17+E18+E19 | F20: =F16+F17+F18+F19 | G20: =G16+G17+G18+G19 | H20: =H16+H17+H18+H19 | I20: =I16+I17+I18+I19 | J20: =J16+J17+J18+J19 | ... L20: =L16+L17+L18+L19
A21: Discount factor | C21: =1/(1+Assumptions!$B$3)^C4 | D21: =1/(1+Assumptions!$B$3)^D4 | E21: =1/(1+Assumptions!$B$3)^E4 | F21: =1/(1+Assumptions!$B$3)^F4 | G21: =1/(1+Assumptions!$B$3)^G4 | H21: =1/(1+Assumptions!$B$3)^H4 | I21: =1/(1+Assumptions!$B$3)^I4 | J21: =1/(1+Assumptions!$B$3)^J4 | ... L21: =1/(1+Assumptions!$B$3)^L4
A22: PV of FCF | C22: =C20*C21 | D22: =D20*D21 | E22: =E20*E21 | F22: =F20*F21 | G22: =G20*G21 | H22: =H20*H21 | I22: =I20*I21 | J22: =J20*J21 | ... L22: =L20*L21
A24: Memo: FCF before SBC | C24: =C20-C10 | D24: =D20-D10 | E24: =E20-E10 | F24: =F20-F10 | G24: =G20-G10 | H24: =H20-H10 | I24: =I20-I10 | J24: =J20-J10 | ... L24: =L20-L10
A25: Memo: owner FCF margin | C25: =C20/C6 | D25: =D20/D6 | E25: =E20/E6 | F25: =F20/F6 | G25: =G20/G6 | H25: =H20/H6 | I25: =I20/I6 | J25: =J20/J6 | ... L25: =L20/L6
A27: Sum of PV FCF | B27: =SUM(C22:L22)
A28: Terminal growth | B28: =Assumptions!$B$16
A29: Terminal FCF (FCF10 x (1+g)) | B29: =L20*(1+B28)
A30: Gordon TV | B30: =B29/(Assumptions!$B$3-B28)
A31: Cap TV | B31: =Assumptions!$B$11*L20
A32: TV used | B32: =MAX(0,MIN(B30,B31))
A33: Implied exit multiple (TV/FCF10) | B33: =IF(L20=0,"n/a",B32/L20)
A34: PV of TV | B34: =B32*L21
A35: Enterprise value | B35: =B27+B34
A36: add net cash | B36: =Assumptions!$B$8
A37: Equity value | B37: =B35+B36
A38: Diluted shares | B38: =Assumptions!$B$9
A39: Value per share (A$) | B39: =B37/B38
A40: Upside vs price | B40: =B39/Assumptions!$B$10-1
A42: Street memo: PV explicit SBC | B42: =SUMPRODUCT(-C10:L10/(1+Assumptions!$B$3)^C4:L4)
A43: Street memo: PV terminal SBC | B43: =(-L10*(1+B28)/(Assumptions!$B$3-B28))*L21
A44: Street value per share | B44: =(B37+B42+B43)/B38

Sheet DCF_Bull
A1: Bull case owner-FCF DCF (A$m)
A3: Year | B3: FY2026A | C3: FY2027E | D3: FY2028E | E3: FY2029E | F3: FY2030E | G3: FY2031E | H3: FY2032E | I3: FY2033E | J3: FY2034E | K3: FY2035E | L3: FY2036E
A4: Index | B4: 0 | C4: 1 | D4: 2 | E4: 3 | F4: 4 | G4: 5 | H4: 6 | I4: 7 | J4: 8 | K4: 9 | L4: 10
A5: Revenue growth | C5: 0.03 | D5: 0.14 | E5: 0.15 | F5: 0.14 | G5: 0.12 | H5: 0.1 | I5: 0.08 | J5: 0.07 | K5: 0.06 | L5: 0.05
A6: Revenue | B6: 664.586 | C6: =B6*(1+C5) | D6: =C6*(1+D5) | E6: =D6*(1+E5) | F6: =E6*(1+F5) | G6: =F6*(1+G5) | H6: =G6*(1+H5) | I6: =H6*(1+I5) | J6: =I6*(1+J5) | ... L6: =K6*(1+L5)
A7: Adj EBITDA margin (post-AASB16) | C7: 0.052 | D7: 0.062 | E7: 0.07 | F7: 0.08 | G7: 0.085 | H7: 0.09 | I7: 0.09 | J7: 0.09 | K7: 0.09 | L7: 0.09
A8: Adj EBITDA | B8: 21.905 | C8: =C6*C7 | D8: =D6*D7 | E8: =E6*E7 | F8: =F6*F7 | G8: =G6*G7 | H8: =H6*H7 | I8: =I6*I7 | J8: =J6*J7 | ... L8: =L6*L7
A9: SBC % revenue | C9: 0.0065 | D9: 0.0063 | E9: 0.0061 | F9: 0.0059 | G9: 0.0057 | H9: 0.0055 | I9: 0.0053 | J9: 0.0051 | K9: 0.005 | L9: 0.005
A10: SBC | B10: -4.177 | C10: =-C6*C9 | D10: =-D6*D9 | E10: =-E6*E9 | F10: =-F6*F9 | G10: =-G6*G9 | H10: =-H6*H9 | I10: =-I6*I9 | J10: =-J6*J9 | ... L10: =-L6*L9
A11: Lease cash cost | C11: =-C6*Assumptions!$B$6 | D11: =-D6*Assumptions!$B$6 | E11: =-E6*Assumptions!$B$6 | F11: =-F6*Assumptions!$B$6 | G11: =-G6*Assumptions!$B$6 | H11: =-H6*Assumptions!$B$6 | I11: =-I6*Assumptions!$B$6 | J11: =-J6*Assumptions!$B$6 | ... L11: =-L6*Assumptions!$B$6
A12: Owner EBITDA after lease | C12: =C8+C10+C11 | D12: =D8+D10+D11 | E12: =E8+E10+E11 | F12: =F8+F10+F11 | G12: =G8+G10+G11 | H12: =H8+H10+H11 | I12: =I8+I10+I11 | J12: =J8+J10+J11 | ... L12: =L8+L10+L11
A13: D&A (ex-ROU) | C13: =-C6*Assumptions!$B$4 | D13: =-D6*Assumptions!$B$4 | E13: =-E6*Assumptions!$B$4 | F13: =-F6*Assumptions!$B$4 | G13: =-G6*Assumptions!$B$4 | H13: =-H6*Assumptions!$B$4 | I13: =-I6*Assumptions!$B$4 | J13: =-J6*Assumptions!$B$4 | ... L13: =-L6*Assumptions!$B$4
A14: EBIT (SBC expensed) | C14: =C12+C13 | D14: =D12+D13 | E14: =E12+E13 | F14: =F12+F13 | G14: =G12+G13 | H14: =H12+H13 | I14: =I12+I13 | J14: =J12+J13 | ... L14: =L12+L13
A15: Cash tax rate | C15: 0.3 | D15: 0.3 | E15: 0.3 | F15: 0.3 | G15: 0.3 | H15: 0.3 | I15: 0.3 | J15: 0.3 | K15: 0.3 | L15: 0.3
A16: NOPAT | C16: =C14*(1-C15) | D16: =D14*(1-D15) | E16: =E14*(1-E15) | F16: =F14*(1-F15) | G16: =G14*(1-G15) | H16: =H14*(1-H15) | I16: =I14*(1-I15) | J16: =J14*(1-J15) | ... L16: =L14*(1-L15)
A17: add back D&A | C17: =-C13 | D17: =-D13 | E17: =-E13 | F17: =-F13 | G17: =-G13 | H17: =-H13 | I17: =-I13 | J17: =-J13 | ... L17: =-L13
A18: less capex | C18: =-C6*Assumptions!$B$5 | D18: =-D6*Assumptions!$B$5 | E18: =-E6*Assumptions!$B$5 | F18: =-F6*Assumptions!$B$5 | G18: =-G6*Assumptions!$B$5 | H18: =-H6*Assumptions!$B$5 | I18: =-I6*Assumptions!$B$5 | J18: =-J6*Assumptions!$B$5 | ... L18: =-L6*Assumptions!$B$5
A19: add working capital | C19: =Assumptions!$D$17*(C6-B6) | D19: =Assumptions!$D$17*(D6-C6) | E19: =Assumptions!$D$17*(E6-D6) | F19: =Assumptions!$D$17*(F6-E6) | G19: =Assumptions!$D$17*(G6-F6) | H19: =Assumptions!$D$17*(H6-G6) | I19: =Assumptions!$D$17*(I6-H6) | J19: =Assumptions!$D$17*(J6-I6) | ... L19: =Assumptions!$D$17*(L6-K6)
A20: Unlevered owner FCF | B20: -1.584 | C20: =C16+C17+C18+C19 | D20: =D16+D17+D18+D19 | E20: =E16+E17+E18+E19 | F20: =F16+F17+F18+F19 | G20: =G16+G17+G18+G19 | H20: =H16+H17+H18+H19 | I20: =I16+I17+I18+I19 | J20: =J16+J17+J18+J19 | ... L20: =L16+L17+L18+L19
A21: Discount factor | C21: =1/(1+Assumptions!$B$3)^C4 | D21: =1/(1+Assumptions!$B$3)^D4 | E21: =1/(1+Assumptions!$B$3)^E4 | F21: =1/(1+Assumptions!$B$3)^F4 | G21: =1/(1+Assumptions!$B$3)^G4 | H21: =1/(1+Assumptions!$B$3)^H4 | I21: =1/(1+Assumptions!$B$3)^I4 | J21: =1/(1+Assumptions!$B$3)^J4 | ... L21: =1/(1+Assumptions!$B$3)^L4
A22: PV of FCF | C22: =C20*C21 | D22: =D20*D21 | E22: =E20*E21 | F22: =F20*F21 | G22: =G20*G21 | H22: =H20*H21 | I22: =I20*I21 | J22: =J20*J21 | ... L22: =L20*L21
A24: Memo: FCF before SBC | C24: =C20-C10 | D24: =D20-D10 | E24: =E20-E10 | F24: =F20-F10 | G24: =G20-G10 | H24: =H20-H10 | I24: =I20-I10 | J24: =J20-J10 | ... L24: =L20-L10
A25: Memo: owner FCF margin | C25: =C20/C6 | D25: =D20/D6 | E25: =E20/E6 | F25: =F20/F6 | G25: =G20/G6 | H25: =H20/H6 | I25: =I20/I6 | J25: =J20/J6 | ... L25: =L20/L6
A27: Sum of PV FCF | B27: =SUM(C22:L22)
A28: Terminal growth | B28: =Assumptions!$B$17
A29: Terminal FCF (FCF10 x (1+g)) | B29: =L20*(1+B28)
A30: Gordon TV | B30: =B29/(Assumptions!$B$3-B28)
A31: Cap TV | B31: =Assumptions!$B$11*L20
A32: TV used | B32: =MAX(0,MIN(B30,B31))
A33: Implied exit multiple (TV/FCF10) | B33: =IF(L20=0,"n/a",B32/L20)
A34: PV of TV | B34: =B32*L21
A35: Enterprise value | B35: =B27+B34
A36: add net cash | B36: =Assumptions!$B$8
A37: Equity value | B37: =B35+B36
A38: Diluted shares | B38: =Assumptions!$B$9
A39: Value per share (A$) | B39: =B37/B38
A40: Upside vs price | B40: =B39/Assumptions!$B$10-1
A42: Street memo: PV explicit SBC | B42: =SUMPRODUCT(-C10:L10/(1+Assumptions!$B$3)^C4:L4)
A43: Street memo: PV terminal SBC | B43: =(-L10*(1+B28)/(Assumptions!$B$3-B28))*L21
A44: Street value per share | B44: =(B37+B42+B43)/B38

Sheet FCF_Quality
A1: FY | B1: Reported FCF | C1: less SBC | D1: less interest income | E1: less lease principal | F1: Owner FCF | G1: Revenue | H1: Reported FCF margin | I1: Owner FCF margin | J1: Cash tax rate memo
A2: FY2019 | B2: 3.624 | C2: -1.047 | D2: -0.142 | E2: 0 | F2: =SUM(B2:E2) | G2: 101.613 | H2: =B2/G2 | I2: =F2/G2
A3: FY2020 | B3: 24.933 | C3: -0.909 | D3: -0.229 | E3: 0 | F3: =SUM(B3:E3) | G3: 176.342 | H3: =B3/G3 | I3: =F3/G3
A4: FY2021 | B4: 23.03 | C4: -1.238 | D4: -0.438 | E4: -1 | F4: =SUM(B4:E4) | G4: 326.344 | H4: =B4/G4 | I4: =F4/G4
A5: FY2022 | B5: 7.6 | C5: -1.717 | D5: -0.419 | E5: -2.2 | F5: =SUM(B5:E5) | G5: 426.335 | H5: =B5/G5 | I5: =F5/G5
A6: FY2023 | B6: 19.216 | C6: -3.103 | D6: -3.367 | E6: -4.6 | F6: =SUM(B6:E6) | G6: 395.513 | H6: =B6/G6 | I6: =F6/G6
A7: FY2024 | B7: 29.442 | C7: -3.854 | D7: -4.964 | E7: -5.7 | F7: =SUM(B7:E7) | G7: 497.841 | H7: =B7/G7 | I7: =F7/G7
A8: FY2025 | B8: 44.734 | C8: -4.88 | D8: -5.674 | E8: -6.798 | F8: =SUM(B8:E8) | G8: 600.719 | H8: =B8/G8 | I8: =F8/G8
A9: FY2026 | B9: 14.055 | C9: -4.177 | D9: -4.847 | E9: -6.615 | F9: =SUM(B9:E9) | G9: 664.586 | H9: =B9/G9 | I9: =F9/G9
A11: Memo: FY2025 OCF 45.9 vs NPAT 11.3 — ~A$20m of negative-working-capital inflow (deferred revenue 21.2 -> 27.8); FY2026 deferred revenue fell to 22.5 and the inflow stopped
A12: Memo: cash tax paid FY2026 A$3.6m on PBT A$11.9m (30%); SBC non-deductible

Sheet Valuation
A1: Scenario summary
A2: Scenario | B2: Value/share | C2: Upside | D2: Weight | E2: Street value/share | F2: Entry price @ hurdle | G2: Street entry @ hurdle
A3: bear | B3: =DCF_Bear!$B$39 | C3: =B3/Assumptions!$B$10-1 | D3: =Assumptions!$C$15 | E3: =DCF_Bear!$B$44 | F3: =(SUMPRODUCT(DCF_Bear!$C$20:$L$20/(1+Assumptions!$B$12)^DCF_Bear!$C$4:$L$4)+MAX(0,MIN(DCF_Bear!$L$20*(1+Assumptions!$B$15)/(Assumptions!$B$3-Assumptions!$B$15),Assumptions!$B$11*DCF_Bear!$L$20))/(1+Assumptions!$B$12)^10+Assumptions!$B$8)/Assumptions!$B$9 | G3: =(SUMPRODUCT(DCF_Bear!$C$20:$L$20/(1+Assumptions!$B$12)^DCF_Bear!$C$4:$L$4)+MAX(0,MIN(DCF_Bear!$L$20*(1+Assumptions!$B$15)/(Assumptions!$B$3-Assumptions!$B$15),Assumptions!$B$11*DCF_Bear!$L$20))/(1+Assumptions!$B$12)^10+Assumptions!$B$8+SUMPRODUCT(-DCF_Bear!$C$10:$L$10/(1+Assumptions!$B$12)^DCF_Bear!$C$4:$L$4)+(-DCF_Bear!$L$10*(1+Assumptions!$B$15)/(Assumptions!$B$3-Assumptions!$B$15))/(1+Assumptions!$B$12)^10)/Assumptions!$B$9
A4: base | B4: =DCF_Base!$B$39 | C4: =B4/Assumptions!$B$10-1 | D4: =Assumptions!$C$16 | E4: =DCF_Base!$B$44 | F4: =(SUMPRODUCT(DCF_Base!$C$20:$L$20/(1+Assumptions!$B$12)^DCF_Base!$C$4:$L$4)+MAX(0,MIN(DCF_Base!$L$20*(1+Assumptions!$B$16)/(Assumptions!$B$3-Assumptions!$B$16),Assumptions!$B$11*DCF_Base!$L$20))/(1+Assumptions!$B$12)^10+Assumptions!$B$8)/Assumptions!$B$9 | G4: =(SUMPRODUCT(DCF_Base!$C$20:$L$20/(1+Assumptions!$B$12)^DCF_Base!$C$4:$L$4)+MAX(0,MIN(DCF_Base!$L$20*(1+Assumptions!$B$16)/(Assumptions!$B$3-Assumptions!$B$16),Assumptions!$B$11*DCF_Base!$L$20))/(1+Assumptions!$B$12)^10+Assumptions!$B$8+SUMPRODUCT(-DCF_Base!$C$10:$L$10/(1+Assumptions!$B$12)^DCF_Base!$C$4:$L$4)+(-DCF_Base!$L$10*(1+Assumptions!$B$16)/(Assumptions!$B$3-Assumptions!$B$16))/(1+Assumptions!$B$12)^10)/Assumptions!$B$9
A5: bull | B5: =DCF_Bull!$B$39 | C5: =B5/Assumptions!$B$10-1 | D5: =Assumptions!$C$17 | E5: =DCF_Bull!$B$44 | F5: =(SUMPRODUCT(DCF_Bull!$C$20:$L$20/(1+Assumptions!$B$12)^DCF_Bull!$C$4:$L$4)+MAX(0,MIN(DCF_Bull!$L$20*(1+Assumptions!$B$17)/(Assumptions!$B$3-Assumptions!$B$17),Assumptions!$B$11*DCF_Bull!$L$20))/(1+Assumptions!$B$12)^10+Assumptions!$B$8)/Assumptions!$B$9 | G5: =(SUMPRODUCT(DCF_Bull!$C$20:$L$20/(1+Assumptions!$B$12)^DCF_Bull!$C$4:$L$4)+MAX(0,MIN(DCF_Bull!$L$20*(1+Assumptions!$B$17)/(Assumptions!$B$3-Assumptions!$B$17),Assumptions!$B$11*DCF_Bull!$L$20))/(1+Assumptions!$B$12)^10+Assumptions!$B$8+SUMPRODUCT(-DCF_Bull!$C$10:$L$10/(1+Assumptions!$B$12)^DCF_Bull!$C$4:$L$4)+(-DCF_Bull!$L$10*(1+Assumptions!$B$17)/(Assumptions!$B$3-Assumptions!$B$17))/(1+Assumptions!$B$12)^10)/Assumptions!$B$9
A7: Probability-weighted value | B7: =SUMPRODUCT(B3:B5,D3:D5)
A8: Margin of safety | B8: =1-Assumptions!$B$10/B7
A9: Street weighted value | B9: =SUMPRODUCT(E3:E5,D3:D5)
A10: Band position (0=house,1=street) | B10: =IF(B9=B7,"n/a",(Assumptions!$B$10-B7)/(B9-B7))
A11: Weighted entry price @ hurdle | B11: =SUMPRODUCT(F3:F5,D3:D5)
A12: Street weighted entry price | B12: =SUMPRODUCT(G3:G5,D3:D5)
A14: Required-return table (base)
A15: Required return | B15: Value/share
A16: 0.09 | B16: =(SUMPRODUCT(DCF_Base!$C$20:$L$20/(1+$A$16)^DCF_Base!$C$4:$L$4)+MAX(0,MIN(DCF_Base!$L$20*(1+Assumptions!$B$16)/(Assumptions!$B$3-Assumptions!$B$16),Assumptions!$B$11*DCF_Base!$L$20))/(1+$A$16)^10+Assumptions!$B$8)/Assumptions!$B$9
A17: 0.1 | B17: =(SUMPRODUCT(DCF_Base!$C$20:$L$20/(1+$A$17)^DCF_Base!$C$4:$L$4)+MAX(0,MIN(DCF_Base!$L$20*(1+Assumptions!$B$16)/(Assumptions!$B$3-Assumptions!$B$16),Assumptions!$B$11*DCF_Base!$L$20))/(1+$A$17)^10+Assumptions!$B$8)/Assumptions!$B$9
A18: 0.11 | B18: =(SUMPRODUCT(DCF_Base!$C$20:$L$20/(1+$A$18)^DCF_Base!$C$4:$L$4)+MAX(0,MIN(DCF_Base!$L$20*(1+Assumptions!$B$16)/(Assumptions!$B$3-Assumptions!$B$16),Assumptions!$B$11*DCF_Base!$L$20))/(1+$A$18)^10+Assumptions!$B$8)/Assumptions!$B$9
A19: 0.12 | B19: =(SUMPRODUCT(DCF_Base!$C$20:$L$20/(1+$A$19)^DCF_Base!$C$4:$L$4)+MAX(0,MIN(DCF_Base!$L$20*(1+Assumptions!$B$16)/(Assumptions!$B$3-Assumptions!$B$16),Assumptions!$B$11*DCF_Base!$L$20))/(1+$A$19)^10+Assumptions!$B$8)/Assumptions!$B$9
A20: 0.15 | B20: =(SUMPRODUCT(DCF_Base!$C$20:$L$20/(1+$A$20)^DCF_Base!$C$4:$L$4)+MAX(0,MIN(DCF_Base!$L$20*(1+Assumptions!$B$16)/(Assumptions!$B$3-Assumptions!$B$16),Assumptions!$B$11*DCF_Base!$L$20))/(1+$A$20)^10+Assumptions!$B$8)/Assumptions!$B$9
A21: =Assumptions!$B$3 | B21: =(SUMPRODUCT(DCF_Base!$C$20:$L$20/(1+$A$21)^DCF_Base!$C$4:$L$4)+MAX(0,MIN(DCF_Base!$L$20*(1+Assumptions!$B$16)/(Assumptions!$B$3-Assumptions!$B$16),Assumptions!$B$11*DCF_Base!$L$20))/(1+$A$21)^10+Assumptions!$B$8)/Assumptions!$B$9
A23: Sensitivity: base value/share, WACC (rows) x terminal growth (cols)
B24: 0.02 | C24: 0.025 | D24: 0.03 | E24: 0.035 | F24: 0.04
A25: 0.095 | B25: =IF($A$25>B$24,(SUMPRODUCT(DCF_Base!$C$20:$L$20/(1+$A$25)^DCF_Base!$C$4:$L$4)+MAX(0,MIN(DCF_Base!$L$20*(1+B$24)/($A$25-B$24),Assumptions!$B$11*DCF_Base!$L$20))/(1+$A$25)^10+Assumptions!$B$8)/Assumptions!$B$9,"n/a") | C25: =IF($A$25>C$24,(SUMPRODUCT(DCF_Base!$C$20:$L$20/(1+$A$25)^DCF_Base!$C$4:$L$4)+MAX(0,MIN(DCF_Base!$L$20*(1+C$24)/($A$25-C$24),Assumptions!$B$11*DCF_Base!$L$20))/(1+$A$25)^10+Assumptions!$B$8)/Assumptions!$B$9,"n/a") | D25: =IF($A$25>D$24,(SUMPRODUCT(DCF_Base!$C$20:$L$20/(1+$A$25)^DCF_Base!$C$4:$L$4)+MAX(0,MIN(DCF_Base!$L$20*(1+D$24)/($A$25-D$24),Assumptions!$B$11*DCF_Base!$L$20))/(1+$A$25)^10+Assumptions!$B$8)/Assumptions!$B$9,"n/a") | E25: =IF($A$25>E$24,(SUMPRODUCT(DCF_Base!$C$20:$L$20/(1+$A$25)^DCF_Base!$C$4:$L$4)+MAX(0,MIN(DCF_Base!$L$20*(1+E$24)/($A$25-E$24),Assumptions!$B$11*DCF_Base!$L$20))/(1+$A$25)^10+Assumptions!$B$8)/Assumptions!$B$9,"n/a") | F25: =IF($A$25>F$24,(SUMPRODUCT(DCF_Base!$C$20:$L$20/(1+$A$25)^DCF_Base!$C$4:$L$4)+MAX(0,MIN(DCF_Base!$L$20*(1+F$24)/($A$25-F$24),Assumptions!$B$11*DCF_Base!$L$20))/(1+$A$25)^10+Assumptions!$B$8)/Assumptions!$B$9,"n/a")
A26: 0.105 | B26: =IF($A$26>B$24,(SUMPRODUCT(DCF_Base!$C$20:$L$20/(1+$A$26)^DCF_Base!$C$4:$L$4)+MAX(0,MIN(DCF_Base!$L$20*(1+B$24)/($A$26-B$24),Assumptions!$B$11*DCF_Base!$L$20))/(1+$A$26)^10+Assumptions!$B$8)/Assumptions!$B$9,"n/a") | C26: =IF($A$26>C$24,(SUMPRODUCT(DCF_Base!$C$20:$L$20/(1+$A$26)^DCF_Base!$C$4:$L$4)+MAX(0,MIN(DCF_Base!$L$20*(1+C$24)/($A$26-C$24),Assumptions!$B$11*DCF_Base!$L$20))/(1+$A$26)^10+Assumptions!$B$8)/Assumptions!$B$9,"n/a") | D26: =IF($A$26>D$24,(SUMPRODUCT(DCF_Base!$C$20:$L$20/(1+$A$26)^DCF_Base!$C$4:$L$4)+MAX(0,MIN(DCF_Base!$L$20*(1+D$24)/($A$26-D$24),Assumptions!$B$11*DCF_Base!$L$20))/(1+$A$26)^10+Assumptions!$B$8)/Assumptions!$B$9,"n/a") | E26: =IF($A$26>E$24,(SUMPRODUCT(DCF_Base!$C$20:$L$20/(1+$A$26)^DCF_Base!$C$4:$L$4)+MAX(0,MIN(DCF_Base!$L$20*(1+E$24)/($A$26-E$24),Assumptions!$B$11*DCF_Base!$L$20))/(1+$A$26)^10+Assumptions!$B$8)/Assumptions!$B$9,"n/a") | F26: =IF($A$26>F$24,(SUMPRODUCT(DCF_Base!$C$20:$L$20/(1+$A$26)^DCF_Base!$C$4:$L$4)+MAX(0,MIN(DCF_Base!$L$20*(1+F$24)/($A$26-F$24),Assumptions!$B$11*DCF_Base!$L$20))/(1+$A$26)^10+Assumptions!$B$8)/Assumptions!$B$9,"n/a")
A27: 0.115 | B27: =IF($A$27>B$24,(SUMPRODUCT(DCF_Base!$C$20:$L$20/(1+$A$27)^DCF_Base!$C$4:$L$4)+MAX(0,MIN(DCF_Base!$L$20*(1+B$24)/($A$27-B$24),Assumptions!$B$11*DCF_Base!$L$20))/(1+$A$27)^10+Assumptions!$B$8)/Assumptions!$B$9,"n/a") | C27: =IF($A$27>C$24,(SUMPRODUCT(DCF_Base!$C$20:$L$20/(1+$A$27)^DCF_Base!$C$4:$L$4)+MAX(0,MIN(DCF_Base!$L$20*(1+C$24)/($A$27-C$24),Assumptions!$B$11*DCF_Base!$L$20))/(1+$A$27)^10+Assumptions!$B$8)/Assumptions!$B$9,"n/a") | D27: =IF($A$27>D$24,(SUMPRODUCT(DCF_Base!$C$20:$L$20/(1+$A$27)^DCF_Base!$C$4:$L$4)+MAX(0,MIN(DCF_Base!$L$20*(1+D$24)/($A$27-D$24),Assumptions!$B$11*DCF_Base!$L$20))/(1+$A$27)^10+Assumptions!$B$8)/Assumptions!$B$9,"n/a") | E27: =IF($A$27>E$24,(SUMPRODUCT(DCF_Base!$C$20:$L$20/(1+$A$27)^DCF_Base!$C$4:$L$4)+MAX(0,MIN(DCF_Base!$L$20*(1+E$24)/($A$27-E$24),Assumptions!$B$11*DCF_Base!$L$20))/(1+$A$27)^10+Assumptions!$B$8)/Assumptions!$B$9,"n/a") | F27: =IF($A$27>F$24,(SUMPRODUCT(DCF_Base!$C$20:$L$20/(1+$A$27)^DCF_Base!$C$4:$L$4)+MAX(0,MIN(DCF_Base!$L$20*(1+F$24)/($A$27-F$24),Assumptions!$B$11*DCF_Base!$L$20))/(1+$A$27)^10+Assumptions!$B$8)/Assumptions!$B$9,"n/a")
A28: 0.125 | B28: =IF($A$28>B$24,(SUMPRODUCT(DCF_Base!$C$20:$L$20/(1+$A$28)^DCF_Base!$C$4:$L$4)+MAX(0,MIN(DCF_Base!$L$20*(1+B$24)/($A$28-B$24),Assumptions!$B$11*DCF_Base!$L$20))/(1+$A$28)^10+Assumptions!$B$8)/Assumptions!$B$9,"n/a") | C28: =IF($A$28>C$24,(SUMPRODUCT(DCF_Base!$C$20:$L$20/(1+$A$28)^DCF_Base!$C$4:$L$4)+MAX(0,MIN(DCF_Base!$L$20*(1+C$24)/($A$28-C$24),Assumptions!$B$11*DCF_Base!$L$20))/(1+$A$28)^10+Assumptions!$B$8)/Assumptions!$B$9,"n/a") | D28: =IF($A$28>D$24,(SUMPRODUCT(DCF_Base!$C$20:$L$20/(1+$A$28)^DCF_Base!$C$4:$L$4)+MAX(0,MIN(DCF_Base!$L$20*(1+D$24)/($A$28-D$24),Assumptions!$B$11*DCF_Base!$L$20))/(1+$A$28)^10+Assumptions!$B$8)/Assumptions!$B$9,"n/a") | E28: =IF($A$28>E$24,(SUMPRODUCT(DCF_Base!$C$20:$L$20/(1+$A$28)^DCF_Base!$C$4:$L$4)+MAX(0,MIN(DCF_Base!$L$20*(1+E$24)/($A$28-E$24),Assumptions!$B$11*DCF_Base!$L$20))/(1+$A$28)^10+Assumptions!$B$8)/Assumptions!$B$9,"n/a") | F28: =IF($A$28>F$24,(SUMPRODUCT(DCF_Base!$C$20:$L$20/(1+$A$28)^DCF_Base!$C$4:$L$4)+MAX(0,MIN(DCF_Base!$L$20*(1+F$24)/($A$28-F$24),Assumptions!$B$11*DCF_Base!$L$20))/(1+$A$28)^10+Assumptions!$B$8)/Assumptions!$B$9,"n/a")
A29: 0.135 | B29: =IF($A$29>B$24,(SUMPRODUCT(DCF_Base!$C$20:$L$20/(1+$A$29)^DCF_Base!$C$4:$L$4)+MAX(0,MIN(DCF_Base!$L$20*(1+B$24)/($A$29-B$24),Assumptions!$B$11*DCF_Base!$L$20))/(1+$A$29)^10+Assumptions!$B$8)/Assumptions!$B$9,"n/a") | C29: =IF($A$29>C$24,(SUMPRODUCT(DCF_Base!$C$20:$L$20/(1+$A$29)^DCF_Base!$C$4:$L$4)+MAX(0,MIN(DCF_Base!$L$20*(1+C$24)/($A$29-C$24),Assumptions!$B$11*DCF_Base!$L$20))/(1+$A$29)^10+Assumptions!$B$8)/Assumptions!$B$9,"n/a") | D29: =IF($A$29>D$24,(SUMPRODUCT(DCF_Base!$C$20:$L$20/(1+$A$29)^DCF_Base!$C$4:$L$4)+MAX(0,MIN(DCF_Base!$L$20*(1+D$24)/($A$29-D$24),Assumptions!$B$11*DCF_Base!$L$20))/(1+$A$29)^10+Assumptions!$B$8)/Assumptions!$B$9,"n/a") | E29: =IF($A$29>E$24,(SUMPRODUCT(DCF_Base!$C$20:$L$20/(1+$A$29)^DCF_Base!$C$4:$L$4)+MAX(0,MIN(DCF_Base!$L$20*(1+E$24)/($A$29-E$24),Assumptions!$B$11*DCF_Base!$L$20))/(1+$A$29)^10+Assumptions!$B$8)/Assumptions!$B$9,"n/a") | F29: =IF($A$29>F$24,(SUMPRODUCT(DCF_Base!$C$20:$L$20/(1+$A$29)^DCF_Base!$C$4:$L$4)+MAX(0,MIN(DCF_Base!$L$20*(1+F$24)/($A$29-F$24),Assumptions!$B$11*DCF_Base!$L$20))/(1+$A$29)^10+Assumptions!$B$8)/Assumptions!$B$9,"n/a")
