Workbook

Sheet Inputs
A1: PFI.NZ — Blended AFFO-capitalization / NTA model (NZ REIT)
A2: Valuation date | B2: 2026-08-25
A3: Current price (NZD) | B3: 2.37
A4: Shares outstanding (m, 30-Jun-2026) | B4: 502.433
A5: NTA per share (cents, FY2026) | B5: 290
A6: FY2026 AFFO (cps, reported) | B6: 10.93
A7: FY2026 AFFO normalized ex GrainCorp surrender (cps) | B7: 9.91
A8: FY2027 base-year AFFO (cps, guidance-implied: 9.80 div / 95% payout) | B8: 10.3
A9: Net debt incl. $19.4m deferred settlements (NZ$m) — NOT deducted anywhere | B9: 799.24
A10: Risk-free (NZ 10yr, %) | B10: 4.35
A11: Equity risk premium (%) | B11: 5.5
A12: Beta | B12: 0.7
A13: CAPM = rf + beta*ERP (%) | B13: =B10+B12*B11
A14: Auckland concentration premium (%) | B14: 0.4
A15: Base cost of equity (%) = CAPM + premium | B15: =B13+B14
A16: Bull cost of equity (%) | B16: 7.9
A17: Bear cost of equity (%) | B17: 9.6
A18: Hurdle rate for entry price (%) | B18: 15
A19: Blend weights: AFFO leg / NTA leg | B19: 0.5
A20: Scenario weights bear/base/bull | B20: 0.20 / 0.55 / 0.25
A21: NOTE: AFFO is POST-INTEREST — capitalized at cost of equity; net debt is never subtracted (would double-count leverage).

Sheet Base
A1: Base scenario — all per-share figures in CENTS unless noted
A2: Cost of equity (%) | B2: 8.6
A3: Terminal growth (%) | B3: 2.75
A4: Exit AFFO yield (%) = CoE - g | B4: =B2-B3
A6: Year | B6: FY2027 | C6: FY2028 | D6: FY2029 | E6: FY2030 | F6: FY2031
A7: AFFO per share (cps) | B7: 10.3 | C7: =B7*(1+4.5/100) | D7: =C7*(1+4.5/100) | E7: =D7*(1+4.0/100) | F7: =E7*(1+3.5/100)
A8: AFFO growth (%) | B8: n/a (anchor) | C8: 4.5 | D8: 4.5 | E8: 4 | F8: 3.5
A9: Discount factor @ CoE | B9: =1/(1+$B$2/100)^1 | C9: =1/(1+$B$2/100)^2 | D9: =1/(1+$B$2/100)^3 | E9: =1/(1+$B$2/100)^4 | F9: =1/(1+$B$2/100)^5
A10: PV of AFFO (cps) | B10: =B7*B9 | C10: =C7*C9 | D10: =D7*D9 | E10: =E7*E9 | F10: =F7*F9
A11: DPS (cps) | B11: 9.8 | C11: 10.15 | D11: 10.55 | E11: 10.95 | F11: 11.35
A12: PV of DPS (cps) | B12: =B11*B9 | C12: =C11*C9 | D12: =D11*D9 | E12: =E11*E9 | F12: =F11*F9
A13: NTA per share (cps) | B13: =290*(1+2.5/100) | C13: =B13*(1+2.5/100) | D13: =C13*(1+2.5/100) | E13: =D13*(1+2.5/100) | F13: =E13*(1+2.5/100)
A15: AFFO-CAPITALIZATION LEG
A16: Sum PV AFFO (cps) | B16: =SUM(B10:F10)
A17: Terminal value (cps) = AFFO_Y5*(1+g)/exit yield | B17: =F7*(1+B3/100)/(B4/100)
A18: PV terminal (cps) | B18: =B17*F9
A19: AFFO-leg IV ($/share) | B19: =(B16+B18)/100
A21: NTA LEG
A22: PV of dividends (cps) | B22: =SUM(B12:F12)
A23: Exit P/NTA | B23: 0.85
A24: Year-5 exit value (cps) = NTA_Y5 x exit P/NTA | B24: =F13*B23
A25: PV exit value (cps) | B25: =B24*F9
A26: NTA-leg IV ($/share) | B26: =(B22+B25)/100
A28: BLENDED IV ($/share) 50/50 | B28: =0.5*B19+0.5*B26
A29: Upside vs $2.37 (%) | B29: =(B28/Inputs!$B$3-1)*100
A31: ENTRY PRICE @ 15% hurdle (AFFO leg)
A32: PV interim AFFO @15% (cps) | B32: =B7/(1.15^1)+C7/(1.15^2)+D7/(1.15^3)+E7/(1.15^4)+F7/(1.15^5)
A33: PV terminal @15% (cps) | B33: =B17/(1.15^5)
A34: Entry price ($/share) | B34: =(B32+B33)/100

Sheet Bull
A1: Bull scenario — all per-share figures in CENTS unless noted
A2: Cost of equity (%) | B2: 7.9
A3: Terminal growth (%) | B3: 3
A4: Exit AFFO yield (%) = CoE - g | B4: =B2-B3
A6: Year | B6: FY2027 | C6: FY2028 | D6: FY2029 | E6: FY2030 | F6: FY2031
A7: AFFO per share (cps) | B7: 10.55 | C7: =B7*(1+5.5/100) | D7: =C7*(1+5.5/100) | E7: =D7*(1+5.0/100) | F7: =E7*(1+4.5/100)
A8: AFFO growth (%) | B8: n/a (anchor) | C8: 5.5 | D8: 5.5 | E8: 5 | F8: 4.5
A9: Discount factor @ CoE | B9: =1/(1+$B$2/100)^1 | C9: =1/(1+$B$2/100)^2 | D9: =1/(1+$B$2/100)^3 | E9: =1/(1+$B$2/100)^4 | F9: =1/(1+$B$2/100)^5
A10: PV of AFFO (cps) | B10: =B7*B9 | C10: =C7*C9 | D10: =D7*D9 | E10: =E7*E9 | F10: =F7*F9
A11: DPS (cps) | B11: 9.85 | C11: 10.35 | D11: 10.9 | E11: 11.45 | F11: 12
A12: PV of DPS (cps) | B12: =B11*B9 | C12: =C11*C9 | D12: =D11*D9 | E12: =E11*E9 | F12: =F11*F9
A13: NTA per share (cps) | B13: =290*(1+4.0/100) | C13: =B13*(1+4.0/100) | D13: =C13*(1+4.0/100) | E13: =D13*(1+4.0/100) | F13: =E13*(1+4.0/100)
A15: AFFO-CAPITALIZATION LEG
A16: Sum PV AFFO (cps) | B16: =SUM(B10:F10)
A17: Terminal value (cps) = AFFO_Y5*(1+g)/exit yield | B17: =F7*(1+B3/100)/(B4/100)
A18: PV terminal (cps) | B18: =B17*F9
A19: AFFO-leg IV ($/share) | B19: =(B16+B18)/100
A21: NTA LEG
A22: PV of dividends (cps) | B22: =SUM(B12:F12)
A23: Exit P/NTA | B23: 1
A24: Year-5 exit value (cps) = NTA_Y5 x exit P/NTA | B24: =F13*B23
A25: PV exit value (cps) | B25: =B24*F9
A26: NTA-leg IV ($/share) | B26: =(B22+B25)/100
A28: BLENDED IV ($/share) 50/50 | B28: =0.5*B19+0.5*B26
A29: Upside vs $2.37 (%) | B29: =(B28/Inputs!$B$3-1)*100
A31: ENTRY PRICE @ 15% hurdle (AFFO leg)
A32: PV interim AFFO @15% (cps) | B32: =B7/(1.15^1)+C7/(1.15^2)+D7/(1.15^3)+E7/(1.15^4)+F7/(1.15^5)
A33: PV terminal @15% (cps) | B33: =B17/(1.15^5)
A34: Entry price ($/share) | B34: =(B32+B33)/100

Sheet Bear
A1: Bear scenario — all per-share figures in CENTS unless noted
A2: Cost of equity (%) | B2: 9.6
A3: Terminal growth (%) | B3: 2
A4: Exit AFFO yield (%) = CoE - g | B4: =B2-B3
A6: Year | B6: FY2027 | C6: FY2028 | D6: FY2029 | E6: FY2030 | F6: FY2031
A7: AFFO per share (cps) | B7: 10 | C7: =B7*(1+1.5/100) | D7: =C7*(1+1.0/100) | E7: =D7*(1+1.5/100) | F7: =E7*(1+2.0/100)
A8: AFFO growth (%) | B8: n/a (anchor) | C8: 1.5 | D8: 1 | E8: 1.5 | F8: 2
A9: Discount factor @ CoE | B9: =1/(1+$B$2/100)^1 | C9: =1/(1+$B$2/100)^2 | D9: =1/(1+$B$2/100)^3 | E9: =1/(1+$B$2/100)^4 | F9: =1/(1+$B$2/100)^5
A10: PV of AFFO (cps) | B10: =B7*B9 | C10: =C7*C9 | D10: =D7*D9 | E10: =E7*E9 | F10: =F7*F9
A11: DPS (cps) | B11: 9.75 | C11: 9.75 | D11: 9.75 | E11: 9.8 | F11: 9.9
A12: PV of DPS (cps) | B12: =B11*B9 | C12: =C11*C9 | D12: =D11*D9 | E12: =E11*E9 | F12: =F11*F9
A13: NTA per share (cps) | B13: =290*(1+-1.0/100) | C13: =B13*(1+-1.0/100) | D13: =C13*(1+-1.0/100) | E13: =D13*(1+-1.0/100) | F13: =E13*(1+-1.0/100)
A15: AFFO-CAPITALIZATION LEG
A16: Sum PV AFFO (cps) | B16: =SUM(B10:F10)
A17: Terminal value (cps) = AFFO_Y5*(1+g)/exit yield | B17: =F7*(1+B3/100)/(B4/100)
A18: PV terminal (cps) | B18: =B17*F9
A19: AFFO-leg IV ($/share) | B19: =(B16+B18)/100
A21: NTA LEG
A22: PV of dividends (cps) | B22: =SUM(B12:F12)
A23: Exit P/NTA | B23: 0.7
A24: Year-5 exit value (cps) = NTA_Y5 x exit P/NTA | B24: =F13*B23
A25: PV exit value (cps) | B25: =B24*F9
A26: NTA-leg IV ($/share) | B26: =(B22+B25)/100
A28: BLENDED IV ($/share) 50/50 | B28: =0.5*B19+0.5*B26
A29: Upside vs $2.37 (%) | B29: =(B28/Inputs!$B$3-1)*100
A31: ENTRY PRICE @ 15% hurdle (AFFO leg)
A32: PV interim AFFO @15% (cps) | B32: =B7/(1.15^1)+C7/(1.15^2)+D7/(1.15^3)+E7/(1.15^4)+F7/(1.15^5)
A33: PV terminal @15% (cps) | B33: =B17/(1.15^5)
A34: Entry price ($/share) | B34: =(B32+B33)/100

Sheet Summary
A1: PFI.NZ probability-weighted valuation
B3: Bear | C3: Base | D3: Bull
A4: Blended IV ($) | B4: =Bear!B28 | C4: =Base!B28 | D4: =Bull!B28
A5: Weight | B5: 0.2 | C5: 0.55 | D5: 0.25
A6: Entry price @15% ($) | B6: =Bear!B34 | C6: =Base!B34 | D6: =Bull!B34
A8: Weighted IV ($) | B8: =SUMPRODUCT(B4:D4,B5:D5)
A9: Current price ($) | B9: =Inputs!B3
A10: Weighted upside (%) | B10: =(B8/B9-1)*100
A11: Weighted entry price ($) | B11: =SUMPRODUCT(B6:D6,B5:D5)
A13: Python cross-check IVs (static) | B13: 1.444 | C13: 2.052 | D13: 2.582
A14: Match? (formula vs static, must all be ~0) | B14: =B4-B13 | C14: =C4-C13 | D14: =D4-D13

Sheet Sensitivity
A1: AFFO-cap leg IV ($/share), base AFFO path
A2: Rows: cost of equity % | Cols: exit AFFO yield %
B4: 4.85 | C4: 5.35 | D4: 5.85 | E4: 6.35 | F4: 6.85
A5: 7.6 | B5: =(10.300000/(1+7.6/100)^1+10.763500/(1+7.6/100)^2+11.247858/(1+7.6/100)^3+11.697772/(1+7.6/100)^4+12.107194/(1+7.6/100)^5+12.107194*1.0275/(4.85/100)/(1+7.6/100)^5)/100 | C5: =(10.300000/(1+7.6/100)^1+10.763500/(1+7.6/100)^2+11.247858/(1+7.6/100)^3+11.697772/(1+7.6/100)^4+12.107194/(1+7.6/100)^5+12.107194*1.0275/(5.35/100)/(1+7.6/100)^5)/100 | D5: =(10.300000/(1+7.6/100)^1+10.763500/(1+7.6/100)^2+11.247858/(1+7.6/100)^3+11.697772/(1+7.6/100)^4+12.107194/(1+7.6/100)^5+12.107194*1.0275/(5.85/100)/(1+7.6/100)^5)/100 | E5: =(10.300000/(1+7.6/100)^1+10.763500/(1+7.6/100)^2+11.247858/(1+7.6/100)^3+11.697772/(1+7.6/100)^4+12.107194/(1+7.6/100)^5+12.107194*1.0275/(6.35/100)/(1+7.6/100)^5)/100 | F5: =(10.300000/(1+7.6/100)^1+10.763500/(1+7.6/100)^2+11.247858/(1+7.6/100)^3+11.697772/(1+7.6/100)^4+12.107194/(1+7.6/100)^5+12.107194*1.0275/(6.85/100)/(1+7.6/100)^5)/100
A6: 8.1 | B6: =(10.300000/(1+8.1/100)^1+10.763500/(1+8.1/100)^2+11.247858/(1+8.1/100)^3+11.697772/(1+8.1/100)^4+12.107194/(1+8.1/100)^5+12.107194*1.0275/(4.85/100)/(1+8.1/100)^5)/100 | C6: =(10.300000/(1+8.1/100)^1+10.763500/(1+8.1/100)^2+11.247858/(1+8.1/100)^3+11.697772/(1+8.1/100)^4+12.107194/(1+8.1/100)^5+12.107194*1.0275/(5.35/100)/(1+8.1/100)^5)/100 | D6: =(10.300000/(1+8.1/100)^1+10.763500/(1+8.1/100)^2+11.247858/(1+8.1/100)^3+11.697772/(1+8.1/100)^4+12.107194/(1+8.1/100)^5+12.107194*1.0275/(5.85/100)/(1+8.1/100)^5)/100 | E6: =(10.300000/(1+8.1/100)^1+10.763500/(1+8.1/100)^2+11.247858/(1+8.1/100)^3+11.697772/(1+8.1/100)^4+12.107194/(1+8.1/100)^5+12.107194*1.0275/(6.35/100)/(1+8.1/100)^5)/100 | F6: =(10.300000/(1+8.1/100)^1+10.763500/(1+8.1/100)^2+11.247858/(1+8.1/100)^3+11.697772/(1+8.1/100)^4+12.107194/(1+8.1/100)^5+12.107194*1.0275/(6.85/100)/(1+8.1/100)^5)/100
A7: 8.6 | B7: =(10.300000/(1+8.6/100)^1+10.763500/(1+8.6/100)^2+11.247858/(1+8.6/100)^3+11.697772/(1+8.6/100)^4+12.107194/(1+8.6/100)^5+12.107194*1.0275/(4.85/100)/(1+8.6/100)^5)/100 | C7: =(10.300000/(1+8.6/100)^1+10.763500/(1+8.6/100)^2+11.247858/(1+8.6/100)^3+11.697772/(1+8.6/100)^4+12.107194/(1+8.6/100)^5+12.107194*1.0275/(5.35/100)/(1+8.6/100)^5)/100 | D7: =(10.300000/(1+8.6/100)^1+10.763500/(1+8.6/100)^2+11.247858/(1+8.6/100)^3+11.697772/(1+8.6/100)^4+12.107194/(1+8.6/100)^5+12.107194*1.0275/(5.85/100)/(1+8.6/100)^5)/100 | E7: =(10.300000/(1+8.6/100)^1+10.763500/(1+8.6/100)^2+11.247858/(1+8.6/100)^3+11.697772/(1+8.6/100)^4+12.107194/(1+8.6/100)^5+12.107194*1.0275/(6.35/100)/(1+8.6/100)^5)/100 | F7: =(10.300000/(1+8.6/100)^1+10.763500/(1+8.6/100)^2+11.247858/(1+8.6/100)^3+11.697772/(1+8.6/100)^4+12.107194/(1+8.6/100)^5+12.107194*1.0275/(6.85/100)/(1+8.6/100)^5)/100
A8: 9.1 | B8: =(10.300000/(1+9.1/100)^1+10.763500/(1+9.1/100)^2+11.247858/(1+9.1/100)^3+11.697772/(1+9.1/100)^4+12.107194/(1+9.1/100)^5+12.107194*1.0275/(4.85/100)/(1+9.1/100)^5)/100 | C8: =(10.300000/(1+9.1/100)^1+10.763500/(1+9.1/100)^2+11.247858/(1+9.1/100)^3+11.697772/(1+9.1/100)^4+12.107194/(1+9.1/100)^5+12.107194*1.0275/(5.35/100)/(1+9.1/100)^5)/100 | D8: =(10.300000/(1+9.1/100)^1+10.763500/(1+9.1/100)^2+11.247858/(1+9.1/100)^3+11.697772/(1+9.1/100)^4+12.107194/(1+9.1/100)^5+12.107194*1.0275/(5.85/100)/(1+9.1/100)^5)/100 | E8: =(10.300000/(1+9.1/100)^1+10.763500/(1+9.1/100)^2+11.247858/(1+9.1/100)^3+11.697772/(1+9.1/100)^4+12.107194/(1+9.1/100)^5+12.107194*1.0275/(6.35/100)/(1+9.1/100)^5)/100 | F8: =(10.300000/(1+9.1/100)^1+10.763500/(1+9.1/100)^2+11.247858/(1+9.1/100)^3+11.697772/(1+9.1/100)^4+12.107194/(1+9.1/100)^5+12.107194*1.0275/(6.85/100)/(1+9.1/100)^5)/100
A9: 9.6 | B9: =(10.300000/(1+9.6/100)^1+10.763500/(1+9.6/100)^2+11.247858/(1+9.6/100)^3+11.697772/(1+9.6/100)^4+12.107194/(1+9.6/100)^5+12.107194*1.0275/(4.85/100)/(1+9.6/100)^5)/100 | C9: =(10.300000/(1+9.6/100)^1+10.763500/(1+9.6/100)^2+11.247858/(1+9.6/100)^3+11.697772/(1+9.6/100)^4+12.107194/(1+9.6/100)^5+12.107194*1.0275/(5.35/100)/(1+9.6/100)^5)/100 | D9: =(10.300000/(1+9.6/100)^1+10.763500/(1+9.6/100)^2+11.247858/(1+9.6/100)^3+11.697772/(1+9.6/100)^4+12.107194/(1+9.6/100)^5+12.107194*1.0275/(5.85/100)/(1+9.6/100)^5)/100 | E9: =(10.300000/(1+9.6/100)^1+10.763500/(1+9.6/100)^2+11.247858/(1+9.6/100)^3+11.697772/(1+9.6/100)^4+12.107194/(1+9.6/100)^5+12.107194*1.0275/(6.35/100)/(1+9.6/100)^5)/100 | F9: =(10.300000/(1+9.6/100)^1+10.763500/(1+9.6/100)^2+11.247858/(1+9.6/100)^3+11.697772/(1+9.6/100)^4+12.107194/(1+9.6/100)^5+12.107194*1.0275/(6.85/100)/(1+9.6/100)^5)/100

Sheet History_Sanity
A1: FY-end price vs NTA / AFFO / EBITDA (Dec-end FY2018-23; Jun-end FY2024 stub, FY2025-26)
A3: Year | B3: FY-end price | C3: NTA (cps) | D3: AFFO (cps) | E3: P/NTA | F3: P/AFFO
A4: FY2018 | B4: 1.81 | C4: 177.7 | D4: 7.46 | E4: =B4/(C4/100) | F4: =B4/(D4/100)
A5: FY2019 | B5: 2.44 | C5: 205.5 | D5: 7.79 | E5: =B5/(C5/100) | F5: =B5/(D5/100)
A6: FY2020 | B6: 2.93 | C6: 220.9 | D6: 8.03 | E6: =B6/(C6/100) | F6: =B6/(D6/100)
A7: FY2021 | B7: 2.98 | C7: 303.4 | D7: 9.29 | E7: =B7/(C7/100) | F7: =B7/(D7/100)
A8: FY2022 | B8: 2.3 | C8: 298.8 | D8: 8.83 | E8: =B8/(C8/100) | F8: =B8/(D8/100)
A9: FY2023 | B9: 2.25 | C9: 270.9 | D9: 8.92 | E9: =B9/(C9/100) | F9: =B9/(D9/100)
A10: FY2024 (6mo stub) | B10: 2.15 | C10: 270.7 | E10: =B10/(C10/100)
A11: FY2025 | B11: 2.23 | C11: 283.6 | D11: 9.59 | E11: =B11/(C11/100) | F11: =B11/(D11/100)
A12: FY2026 | B12: 2.42 | C12: 290 | D12: 10.93 | E12: =B12/(C12/100) | F12: =B12/(D12/100)
A14: Averages | E14: =AVERAGE(E4:E12) | F14: =AVERAGE(F4:F12)
A16: Implied at base blended IV $2.052:
A17: P/NTA | B17: =Base!B28/(290/100)
A18: P/AFFO (FY2027 10.30c) | B18: =Base!B28/(10.30/100)
A20: Sanity: all implied multiples BELOW historical avg/max — no overvaluation trip. Implied P/NTA ~0.71x sits slightly below the 8yr min (0.77x): consequence of requiring 8.6% CoE vs the ~7.3-7.5% the market has accepted. Conclusion: fully priced at our required return.
