Workbook

Sheet Model_Info
A1: Adobe Inc. (ADBE) -- Owner-FCF DCF Model
A3: Version | B3: 2026-08-28 rebuild. Supersedes the 2026-06-30 model (price-refreshed 2026-08-12).
A4: Supersedes | B4: Prior model valued ADBE on reported FCF with SBC as non-cash, a FLAT 41.45% FCF margin, a 5-year horizon, a stale 397.5m share count, and the pre-2026-07-21 entry-price formula.
A5: Built by | B5: dcf-analyst agent (Claude Opus 5), 2026-08-28, at the user's request.
A6: Model | B6: Owner-FCF DCF, three scenarios, probability-weighted, 10-year explicit horizon.
A7: Routing | B7: dcf-methods/SKILL.md routes an application-software operating company to owner-FCF. Confirmed, not assumed.
A9: DATA VINTAGE | B9: Every figure below goes stale. Refresh before relying on this file.
A10: Price | B10: $289.15 USD, Yahoo regularMarketPrice, as of 2026-08-27T20:00:00Z regular close (Yahoo regularMarketPrice).
A11: 52-week range | B11: $190.12 - $370.86.
A12: Balance sheet | B12: Q2-FY2026 10-Q dated 2026-05-29: cash $4,919m, debt $6,645m, net DEBT $1,726m.
A13: Share count | B13: 402.5m fully diluted, Q2-FY2026 10-Q. Held FLAT (see SBC policy).
A14: FY0 base | B14: TTM = FY2025 + H1-FY2026 - H1-FY2025. Revenue $25,198m, reported FCF $10,280m, owner FCF $7,833m.
A15: Guidance | B15: FY2026 revenue $26.50-26.60bn (raised); non-GAAP EPS $24.35-24.45; non-GAAP op margin ~45%; total ending ARR growth ~10.2% incl. ~$480m acquired Semrush ARR.
A16: Fiscal year | B16: Friday nearest Nov 30 (52/53-week). FY2025 ended 2025-11-28.
A18: METHODOLOGY
A19: SBC policy | B19: SBC is EXPENSED in the flows (incl. $418m cash taxes on net-share settlement) AND the share count is held FLAT. Charging both would double-count grant dilution. Buybacks are therefore value-neutral here: they are the mechanism keeping the count flat.
A20: Interest income | B20: NOT stripped. Adobe holds net DEBT ($1,726m), not net cash. Interest income is stripped only when net cash is added back to EV; that does not apply.
A21: Margin build | B21: Components per year: adj EBITDA -> less SBC -> less D&A -> tax -> add D&A -> less capex -> add working capital. The latest FCF margin is never carried forward flat.
A22: Working capital | B22: Modelled on the CHANGE in revenue (deferred revenue tracks bookings growth). 5-year actual dDR/dRevenue averaged 29%; base uses 25%, bear 15%.
A23: Horizon | B23: 10 years. Base owner-FCF margin is flat by year 5, but bear compresses through year 8, so a 5-year capitalization would misstate the downside.
A24: WACC | B24: 9.5% USD: 4.3% risk-free + 1.15 beta x 5.0% ERP = 10.05% CoE, blended with ~3.0% after-tax cost of debt at 94.6/5.4 weights = 9.67%, rounded to 9.5%. Applied UNIFORMLY across scenarios so risk is charged once -- in the flows, not again in the discount rate.
A25: Terminal value | B25: MAX(0, MIN(Gordon, cap x FCF_10)). Cap 17x base / 20x bull / 12x bear, set from the DE-RATED recent multiple range, NOT the FY2020-21 bubble (85.9x P/E in FY2021).
A26: Entry price | B26: Price at which interim FCF + terminal value deliver a 15% IRR, less net debt, per share. Terminal value itself is still built at WACC (it is the fair exit price); only the discounting back uses 15%.
A28: SCENARIO JUDGMENT | B28: Driver paths are the dcf-analyst agent's, set 2026-08-28 on Q2-FY2026 actuals and FY2026 guidance. Weights 30/50/20 bear/base/bull -- NOT the 15/50/35 house default; raised bear for two unresolved leadership vacancies and a structural (not cyclical) downside case.
A30: REFRESH AFTER NEXT PRINT | B30: Q3-FY2026 results due mid-September 2026. Refresh: price, the Q3 balance sheet (net debt, diluted shares after continued buybacks and the Semrush/Topaz cash outlays), FY2026 guidance, and above all NET-NEW DIGITAL MEDIA ARR -- management has pre-warned it will look soft by design. Also watch for a permanent CEO.
A31: ARR WARNING | B31: Digital Media ARR ($19.20bn FY2025) and Total Adobe ARR ($25.20bn FY2025, $27.10bn Q2-FY2026) are DIFFERENT definitions after the FY2026 redefinition. Never chain them: 19,200 -> 26,060 is not 36% growth. Reported growth is ~10-11%.
A33: COLOUR LEGEND | B33: Blue bold = hardcoded input. Yellow fill = key lever (edit these). Black = formula. Green = cross-sheet link. Light green fill = headline result.
A34: Editing | B34: Only rows 5, 7, 9 and 14 on each DCF tab are drivers. Everything else is formula-derived; never paste a value over a formula.

Sheet Reconciliation
A1: Reconciliation -- prior model (2026-06-30) to this one
A3: Prior version dated 2026-06-30, price then $275.30. Figures below hardcoded; bridge is approximate.
A5: Prior per-share values (hardcoded)
A6: Bear | B6: 271.86
A7: Base | B7: 444.4
A8: Bull | B8: 641.19
A9: Weighted (25/50/25) | B9: 450.46
A11: Bridge to new weighted IV
A12: Item | B12: $/share | C12: Running
A13: Prior weighted IV (25/50/25 weights) | B13: 450.46
A14: Reweight to 30/50/20 for unresolved CEO/CFO vacancies and structural (not cyclical) bear case | B14: -18.46 | C14: 432
A15: New driver paths, 10-year horizon, TTM base, component margin build, refreshed 402.5m share count -- measured on the STREET basis so it is comparable with the prior SBC-as-non-cash treatment | B15: -4.12 | C15: 427.87
A16: SBC expensed in full (incl. $418m cash taxes on net-share settlement), share count held flat -- the house owner-FCF policy the prior version did not apply | B16: -98.85 | C16: 329.03
A17: New weighted IV | B17: 329.03
A19: New weighted IV (LIVE -- authoritative) | B19: =Valuation!B12
A21: Nature of change
A22: METHODOLOGY REBUILD, not a driver refresh. The prior DCF predates this repo's owner-FCF policy: it valued Adobe on reported FCF with SBC treated as non-cash, carried a FLAT 41.45% FCF margin forward instead of building margins from components, ran a 5-year horizon, used a stale 397.5m share count, and computed the entry price as terminal-value-per-share discounted at 15% (the formula corrected on 2026-07-21, which the memory notes made entry prices 40-50% too low). Every scenario driver has therefore been re-judged deliberately, which is the exception to the usual do-not-re-derive rule and is stated here explicitly.
A24: Deliberately unchanged
A25: WACC 9.5% -- effectively unchanged (prior base 10%, scenario-varied 9-12%). Now built explicitly from a USD CAPM (4.3% rf, 5.0% ERP, beta 1.15 => 9.67%) and applied UNIFORMLY, because the prior model's per-scenario WACC spread charged risk twice -- once in the flows and again in the discount rate. Would move on a material change in the risk-free rate or Adobe's beta.
A26: Terminal growth 3.0% base -- unchanged from prior. Still consistent with long-run nominal GDP for a dominant subscription platform. Bear cut to 1.0% to match a genuinely eroding business; bull 3.5%.
A27: Net debt $1,726m -- unchanged. Same Q2-FY2026 (2026-05-29) balance sheet as the prior version -- $6,645m debt less $4,919m cash. Would move on the Q3-FY2026 10-Q, especially given continued buybacks and the Semrush/Topaz cash outlays.
A28: Equity CAGR rejected as growth driver -- unchanged judgment. Still a buyback artifact, not deterioration. Would only move if buybacks stopped and equity kept falling.

Sheet Actuals
A1: Reported actuals and current guidance (all hardcoded)
A3: USD millions except shares | B3: FY2020 | C3: FY2021 | D3: FY2022 | E3: FY2023 | F3: FY2024 | G3: FY2025 | H3: TTM
A4: Revenue | B4: 12868 | C4: 15785 | D4: 17606 | E4: 19409 | F4: 21505 | G4: 23769 | H4: 25198
A5: Operating cash flow | B5: 5727 | C5: 7230 | D5: 7838 | E5: 7302 | F5: 8056 | G5: 10031 | H5: 10481
A6: Capex | B6: 419 | C6: 348 | D6: 442 | E6: 360 | F6: 183 | G6: 179 | H6: 201
A7: Free cash flow (reported) | B7: 5308 | C7: 6882 | D7: 7396 | E7: 6942 | F7: 7873 | G7: 9852 | H7: 10280
A8: SBC (cash flow add-back) | B8: 909 | C8: 1069 | D8: 1440 | E8: 1718 | F8: 1833 | G8: 1942 | H8: 2029
A9: Equity-award cash taxes | B9: 681 | C9: 719 | D9: 518 | E9: 589 | F9: 677 | G9: 475 | H9: 418
A10: D&A | B10: 757 | C10: 788 | D10: 856 | E10: 872 | F10: 857 | G10: 818 | H10: 759
A11: Cash taxes paid | B11: 469 | C11: 843 | D11: 778 | E11: 1854 | F11: 1727 | G11: 2219 | H11: 2126
A12: Interest income | B12: 43 | C12: 17 | D12: 61 | E12: 269 | F12: 341 | G12: 264 | H12: 264
A13: Net income | B13: 5260 | C13: 4822 | D13: 4756 | E13: 5428 | F13: 5560 | G13: 7130 | H13: 7229
A14: Shareholders equity | B14: 13264 | C14: 14797 | D14: 14051 | E14: 16518 | F14: 14105 | G14: 11623 | H14: 11518
A15: Deferred revenue | B15: 3629 | C15: 4733 | D15: 5297 | E15: 5837 | F15: 6131 | G15: 6905
A16: Buybacks | B16: 3050 | C16: 3950 | D16: 6550 | E16: 4400 | F16: 9500 | G16: 11281
A17: Diluted shares | B17: 485.5 | C17: 481 | D17: 470.9 | E17: 459.1 | F17: 449.7 | G17: 427 | H17: 402.5
A19: Source: FY2020-FY2025 10-K filings; TTM = FY2025 + H1-FY2026 - H1-FY2025 per the Q2-FY2026 10-Q (2026-05-29).
A21: Balance sheet snapshot at 2026-05-29
A22: Cash and equivalents | B22: 4919
A23: Total debt | B23: 6645
A24: Net DEBT | B24: 1726
A25: Diluted shares (m) | B25: 402.5
A27: Buyback status
A28: Two authorizations totalling $50bn run to March 2028 and April 2030, against a ~$116bn market cap. FY2025 repurchases were $11,281m; H1-FY2026 $4,589m. The flat share count in this model is genuinely funded, not a convention.
A30: FY2026 guidance (Q2-FY2026, 11 June 2026)
A31: Revenue | B31: $26.50-26.60bn (raised)
A32: Non-GAAP EPS | B32: $24.35-24.45 (raised)
A33: Non-GAAP operating margin | B33: ~45% (maintained)
A34: Total ending ARR growth | B34: ~10.2% incl. ~$480m acquired Semrush ARR
A35: Q3-FY2026 revenue | B35: $6.67-6.72bn

Sheet Assumptions
A1: Global assumptions and scenario settings
A3: Globals
A4: WACC | B4: 0.095 | E4: USD CAPM: 4.3% rf + 1.15 beta x 5.0% ERP = 10.05% CoE; blended with ~3.0% after-tax cost of debt at 94.6/5.4 weights = 9.67%, rounded. Same rate in all three scenarios so risk is charged once.
A5: Working capital capture | B5: 0.25 | E5: Share of the YoY revenue INCREASE that converts to cash via deferred revenue. 5-year actual dDR/dRevenue averaged 29%. Bear uses 15% on its own tab.
A6: Net debt (USD m) | B6: 1726 | E6: Positive = net debt. $6,645m debt less $4,919m cash at 2026-05-29.
A7: Diluted shares (m) | B7: 402.5 | E7: Q2-FY2026 10-Q, fully diluted. HELD FLAT because SBC is expensed.
A8: Current price (USD) | B8: 289.15 | E8: Yahoo close 2026-08-27T20:00:00Z. 52-week range $190.12-$370.86.
A9: FY0 revenue (USD m) | B9: 25198 | E9: TTM = FY2025 + H1-FY2026 - H1-FY2025.
A10: FY0 owner FCF (USD m) | B10: 7833 | E10: Reported FCF $10,280m less SBC $2,029m less equity-award taxes $418m.
A12: Per scenario
B13: Bear | C13: Base | D13: Bull
A14: Terminal growth | B14: 0.01 | C14: 0.03 | D14: 0.035
A15: Terminal cap (x FCF_10) | B15: 12 | C15: 17 | D15: 20
A16: WC capture | B16: 0.15 | C16: 0.25 | D16: 0.28
A17: Probability weight | B17: 0.3 | C17: 0.5 | D17: 0.2
A18: Weights check (must be 100%) | B18: =SUM(B17:D17)
A20: Weights rationale | B20: Deliberately NOT the 15/50/35 house default. Bear is raised to 30% and bull cut to 20% because the bear case here is structural rather than cyclical, and three independent things would each have to go right for the bull: freemium conversion at scale, Firefly monetization outrunning substitution, and a successful CEO transition. Adobe has two unresolved leadership vacancies (no permanent CEO five months after the March 2026 announcement; interim CFO), has itself deferred planned Creative Cloud price increases, and AI-first ARR is still under 2% of the ~$27bn base -- so the disruption risk is immediate and already visible while the offset is unproven. Offsetting that, ~96-97% subscription revenue, $10bn+ of annual cash generation and an investment-grade balance sheet mean the bear case is margin and growth erosion, NOT solvency, which is why bear stays at 30% rather than higher.
A22: Bear narrative | B22: The structural-decline case, which is what the market is actually pricing. Deferring the planned Creative Cloud price increases is treated as what it looks like: an admission that AI-native substitutes have become good enough to cap what Adobe can charge its professional base. Growth decelerates to roughly 1% by FY2028 and turns mildly negative as seats churn to Canva, Figma and generative tools, so revenue is lower in year 10 than in year 1. The freemium pivot plus AI compute permanently compresses adjusted EBITDA margin from 48% to 38%, and SBC RISES as a share of a shrinking top line because retention comp in a decline is sticky. The deferred-revenue tailwind collapses with growth. This is a genuine erosion path, not a haircut.
A23: Base narrative | B23: Adobe grows into the low-to-mid single digits off the TTM base as the deliberate freemium pivot trades near-term ARR growth for funnel: FY2026 lands on the raised $26.50-26.60bn guidance (~5.5% off the $25.2bn TTM base, ~12% off FY2025 including roughly $480m of acquired Semrush ARR), reaccelerates modestly in FY2027-28 as paid conversion and AI-credit monetization begin to land, then fades to a 3% terminal. Adjusted EBITDA margin holds near management's ~45% non-GAAP operating-margin target plus D&A (48-49%), absorbing AI inference costs against subscription scale. SBC eases from 9.7% to 8.0% of revenue. The axes here are Creative Cloud pricing power against Canva/OpenAI substitution, and whether the 90M+ freemium MAU funnel converts before the legacy $20bn+ base erodes.
A24: Bull narrative | B24: The freemium bet pays off: AI-first ARR compounds off its $500m base, Firefly monetization scales, and paid conversion from the 90M+ creative freemium MAUs (growing 70%+ YoY) reaccelerates total growth to double digits from FY2027, exactly as management has guided investors to expect. Enterprise ($10m+ ARR) customers keep growing 20%+, GenStudio establishes the content supply chain as a category, and Semrush plus Topaz prove accretive. Operating leverage carries adjusted EBITDA margin to 52% while SBC falls to 7.5% of revenue. A permanent AI-native CEO is named and the leadership discount unwinds.

Sheet DCF_Bear
A1: ADBE owner-FCF DCF -- Bear case
A2: Only rows 5, 7, 9 and 14 are drivers (yellow). Everything else is formula-derived.
A3: USD millions | B3: FY0 TTM | C3: FY2026E | D3: FY2027E | E3: FY2028E | F3: FY2029E | G3: FY2030E | H3: FY2031E | I3: FY2032E | J3: FY2033E | K3: FY2034E | L3: FY2035E
A4: Year index | B4: 0 | C4: 1 | D4: 2 | E4: 3 | F4: 4 | G4: 5 | H4: 6 | I4: 7 | J4: 8 | K4: 9 | L4: 10
A5: Revenue growth YoY | C5: 0.045 | D5: 0.03 | E5: 0.015 | F5: 0.005 | G5: 0 | H5: -0.005 | I5: -0.01 | J5: -0.01 | K5: -0.005 | L5: 0
A6: Revenue | B6: =Assumptions!$B$9 | C6: =B6*(1+C5) | D6: =C6*(1+D5) | E6: =D6*(1+E5) | F6: =E6*(1+F5) | G6: =F6*(1+G5) | H6: =G6*(1+H5) | I6: =H6*(1+I5) | J6: =I6*(1+J5) | ... L6: =K6*(1+L5)
A7: Adj EBITDA margin | C7: 0.47 | D7: 0.455 | E7: 0.44 | F7: 0.425 | G7: 0.41 | H7: 0.4 | I7: 0.39 | J7: 0.385 | K7: 0.38 | L7: 0.38
A8: Adjusted EBITDA | C8: =C6*C7 | D8: =D6*D7 | E8: =E6*E7 | F8: =F6*F7 | G8: =G6*G7 | H8: =H6*H7 | I8: =I6*I7 | J8: =J6*J7 | ... L8: =L6*L7
A9: SBC % of revenue | C9: 0.098 | D9: 0.1 | E9: 0.102 | F9: 0.105 | G9: 0.108 | H9: 0.11 | I9: 0.11 | J9: 0.11 | K9: 0.11 | L9: 0.11
A10: SBC (incl. equity-award taxes) | C10: =-C6*C9 | D10: =-D6*D9 | E10: =-E6*E9 | F10: =-F6*F9 | G10: =-G6*G9 | H10: =-H6*H9 | I10: =-I6*I9 | J10: =-J6*J9 | ... L10: =-L6*L9
A11: Owner EBITDA (post-SBC) | C11: =C8+C10 | D11: =D8+D10 | E11: =E8+E10 | F11: =F8+F10 | G11: =G8+G10 | H11: =H8+H10 | I11: =I8+I10 | J11: =J8+J10 | ... L11: =L8+L10
A12: D&A | C12: =-C6*0.033 | D12: =-D6*0.034 | E12: =-E6*0.035 | F12: =-F6*0.035 | G12: =-G6*0.036000000000000004 | H12: =-H6*0.036000000000000004 | I12: =-I6*0.036000000000000004 | J12: =-J6*0.036000000000000004 | K12: =-K6*0.036000000000000004 | L12: =-L6*0.036000000000000004
A13: EBIT (SBC expensed) | C13: =C11+C12 | D13: =D11+D12 | E13: =E11+E12 | F13: =F11+F12 | G13: =G11+G12 | H13: =H11+H12 | I13: =I11+I12 | J13: =J11+J12 | ... L13: =L11+L12
A14: Cash tax rate | C14: 0.27 | D14: 0.27 | E14: 0.27 | F14: 0.275 | G14: 0.275 | H14: 0.28 | I14: 0.28 | J14: 0.28 | K14: 0.28 | L14: 0.28
A15: NOPAT | C15: =C13*(1-C14) | D15: =D13*(1-D14) | E15: =E13*(1-E14) | F15: =F13*(1-F14) | G15: =G13*(1-G14) | H15: =H13*(1-H14) | I15: =I13*(1-I14) | J15: =J13*(1-J14) | ... L15: =L13*(1-L14)
A16: add back D&A | C16: =-C12 | D16: =-D12 | E16: =-E12 | F16: =-F12 | G16: =-G12 | H16: =-H12 | I16: =-I12 | J16: =-J12 | ... L16: =-L12
A17: less capex | C17: =-C6*0.011000000000000001 | D17: =-D6*0.012 | E17: =-E6*0.013000000000000001 | F17: =-F6*0.013999999999999999 | G17: =-G6*0.013999999999999999 | H17: =-H6*0.015 | I17: =-I6*0.015 | J17: =-J6*0.015 | K17: =-K6*0.015 | L17: =-L6*0.015
A18: add working capital | C18: =Assumptions!$B$16*(C6-B6) | D18: =Assumptions!$B$16*(D6-C6) | E18: =Assumptions!$B$16*(E6-D6) | F18: =Assumptions!$B$16*(F6-E6) | G18: =Assumptions!$B$16*(G6-F6) | H18: =Assumptions!$B$16*(H6-G6) | I18: =Assumptions!$B$16*(I6-H6) | J18: =Assumptions!$B$16*(J6-I6) | ... L18: =Assumptions!$B$16*(L6-K6)
A19: Unlevered owner FCF | C19: =C15+C16+C17+C18 | D19: =D15+D16+D17+D18 | E19: =E15+E16+E17+E18 | F19: =F15+F16+F17+F18 | G19: =G15+G16+G17+G18 | H19: =H15+H16+H17+H18 | I19: =I15+I16+I17+I18 | J19: =J15+J16+J17+J18 | ... L19: =L15+L16+L17+L18
A20: Discount factor | C20: =1/(1+Assumptions!$B$4)^C4 | D20: =1/(1+Assumptions!$B$4)^D4 | E20: =1/(1+Assumptions!$B$4)^E4 | F20: =1/(1+Assumptions!$B$4)^F4 | G20: =1/(1+Assumptions!$B$4)^G4 | H20: =1/(1+Assumptions!$B$4)^H4 | I20: =1/(1+Assumptions!$B$4)^I4 | J20: =1/(1+Assumptions!$B$4)^J4 | ... L20: =1/(1+Assumptions!$B$4)^L4
A21: PV of FCF | C21: =C19*C20 | D21: =D19*D20 | E21: =E19*E20 | F21: =F19*F20 | G21: =G19*G20 | H21: =H19*H20 | I21: =I19*I20 | J21: =J19*J20 | ... L21: =L19*L20
A23: Memo: FCF before SBC (street) | C23: =C19-C10 | D23: =D19-D10 | E23: =E19-E10 | F23: =F19-F10 | G23: =G19-G10 | H23: =H19-H10 | I23: =I19-I10 | J23: =J19-J10 | ... L23: =L19-L10
A24: Memo: owner-FCF margin | C24: =C19/C6 | D24: =D19/D6 | E24: =E19/E6 | F24: =F19/F6 | G24: =G19/G6 | H24: =H19/H6 | I24: =I19/I6 | J24: =J19/J6 | ... L24: =L19/L6
A26: Sum of PV of FCF | B26: =SUM(C21:L21)
A27: Terminal growth | B27: =Assumptions!$B$14
A28: Terminal-year FCF x (1+g) | B28: =L19*(1+B27)
A29: Gordon terminal value | B29: =B28/(Assumptions!$B$4-B27)
A30: Cap terminal value | B30: =Assumptions!$B$15*L19
A31: Terminal value used | B31: =MAX(0,MIN(B29,B30)) | C31: TV = MAX(0, MIN(Gordon, cap)). The zero floor matters when terminal FCF is negative.
A32: Implied exit multiple | B32: =B31/L19
A33: PV of terminal value | B33: =B31*L20
A34: Enterprise value | B34: =B26+B33
A35: less net debt | B35: =-Assumptions!$B$6
A36: Equity value | B36: =B34+B35
A37: Diluted shares (m) | B37: =Assumptions!$B$7
A38: VALUE PER SHARE | B38: =B36/B37
A39: Upside vs current price | B39: =B38/Assumptions!$B$8-1
A41: Street memo: PV of SBC (explicit) | B41: =SUMPRODUCT(-C10:L10,1/(1+Assumptions!$B$4)^C4:L4)
A42: Street memo: PV of SBC (terminal) | B42: =(-L10*(1+B27)/(Assumptions!$B$4-B27))*L20
A43: Street value per share | B43: =(B36+B41+B42)/B37

Sheet DCF_Base
A1: ADBE owner-FCF DCF -- Base case
A2: Only rows 5, 7, 9 and 14 are drivers (yellow). Everything else is formula-derived.
A3: USD millions | B3: FY0 TTM | C3: FY2026E | D3: FY2027E | E3: FY2028E | F3: FY2029E | G3: FY2030E | H3: FY2031E | I3: FY2032E | J3: FY2033E | K3: FY2034E | L3: FY2035E
A4: Year index | B4: 0 | C4: 1 | D4: 2 | E4: 3 | F4: 4 | G4: 5 | H4: 6 | I4: 7 | J4: 8 | K4: 9 | L4: 10
A5: Revenue growth YoY | C5: 0.055 | D5: 0.075 | E5: 0.07 | F5: 0.065 | G5: 0.06 | H5: 0.055 | I5: 0.05 | J5: 0.045 | K5: 0.04 | L5: 0.035
A6: Revenue | B6: =Assumptions!$B$9 | C6: =B6*(1+C5) | D6: =C6*(1+D5) | E6: =D6*(1+E5) | F6: =E6*(1+F5) | G6: =F6*(1+G5) | H6: =G6*(1+H5) | I6: =H6*(1+I5) | J6: =I6*(1+J5) | ... L6: =K6*(1+L5)
A7: Adj EBITDA margin | C7: 0.48 | D7: 0.48 | E7: 0.482 | F7: 0.484 | G7: 0.486 | H7: 0.488 | I7: 0.49 | J7: 0.49 | K7: 0.49 | L7: 0.49
A8: Adjusted EBITDA | C8: =C6*C7 | D8: =D6*D7 | E8: =E6*E7 | F8: =F6*F7 | G8: =G6*G7 | H8: =H6*H7 | I8: =I6*I7 | J8: =J6*J7 | ... L8: =L6*L7
A9: SBC % of revenue | C9: 0.096 | D9: 0.094 | E9: 0.092 | F9: 0.09 | G9: 0.088 | H9: 0.086 | I9: 0.084 | J9: 0.082 | K9: 0.08 | L9: 0.08
A10: SBC (incl. equity-award taxes) | C10: =-C6*C9 | D10: =-D6*D9 | E10: =-E6*E9 | F10: =-F6*F9 | G10: =-G6*G9 | H10: =-H6*H9 | I10: =-I6*I9 | J10: =-J6*J9 | ... L10: =-L6*L9
A11: Owner EBITDA (post-SBC) | C11: =C8+C10 | D11: =D8+D10 | E11: =E8+E10 | F11: =F8+F10 | G11: =G8+G10 | H11: =H8+H10 | I11: =I8+I10 | J11: =J8+J10 | ... L11: =L8+L10
A12: D&A | C12: =-C6*0.032 | D12: =-D6*0.032 | E12: =-E6*0.031 | F12: =-F6*0.03 | G12: =-G6*0.03 | H12: =-H6*0.028999999999999998 | I12: =-I6*0.028999999999999998 | J12: =-J6*0.027999999999999997 | K12: =-K6*0.027999999999999997 | L12: =-L6*0.027999999999999997
A13: EBIT (SBC expensed) | C13: =C11+C12 | D13: =D11+D12 | E13: =E11+E12 | F13: =F11+F12 | G13: =G11+G12 | H13: =H11+H12 | I13: =I11+I12 | J13: =J11+J12 | ... L13: =L11+L12
A14: Cash tax rate | C14: 0.26 | D14: 0.26 | E14: 0.265 | F14: 0.265 | G14: 0.27 | H14: 0.27 | I14: 0.27 | J14: 0.27 | K14: 0.27 | L14: 0.27
A15: NOPAT | C15: =C13*(1-C14) | D15: =D13*(1-D14) | E15: =E13*(1-E14) | F15: =F13*(1-F14) | G15: =G13*(1-G14) | H15: =H13*(1-H14) | I15: =I13*(1-I14) | J15: =J13*(1-J14) | ... L15: =L13*(1-L14)
A16: add back D&A | C16: =-C12 | D16: =-D12 | E16: =-E12 | F16: =-F12 | G16: =-G12 | H16: =-H12 | I16: =-I12 | J16: =-J12 | ... L16: =-L12
A17: less capex | C17: =-C6*0.01 | D17: =-D6*0.011000000000000001 | E17: =-E6*0.012 | F17: =-F6*0.012 | G17: =-G6*0.013000000000000001 | H17: =-H6*0.013000000000000001 | I17: =-I6*0.013000000000000001 | J17: =-J6*0.013000000000000001 | K17: =-K6*0.013000000000000001 | L17: =-L6*0.013000000000000001
A18: add working capital | C18: =Assumptions!$C$16*(C6-B6) | D18: =Assumptions!$C$16*(D6-C6) | E18: =Assumptions!$C$16*(E6-D6) | F18: =Assumptions!$C$16*(F6-E6) | G18: =Assumptions!$C$16*(G6-F6) | H18: =Assumptions!$C$16*(H6-G6) | I18: =Assumptions!$C$16*(I6-H6) | J18: =Assumptions!$C$16*(J6-I6) | ... L18: =Assumptions!$C$16*(L6-K6)
A19: Unlevered owner FCF | C19: =C15+C16+C17+C18 | D19: =D15+D16+D17+D18 | E19: =E15+E16+E17+E18 | F19: =F15+F16+F17+F18 | G19: =G15+G16+G17+G18 | H19: =H15+H16+H17+H18 | I19: =I15+I16+I17+I18 | J19: =J15+J16+J17+J18 | ... L19: =L15+L16+L17+L18
A20: Discount factor | C20: =1/(1+Assumptions!$B$4)^C4 | D20: =1/(1+Assumptions!$B$4)^D4 | E20: =1/(1+Assumptions!$B$4)^E4 | F20: =1/(1+Assumptions!$B$4)^F4 | G20: =1/(1+Assumptions!$B$4)^G4 | H20: =1/(1+Assumptions!$B$4)^H4 | I20: =1/(1+Assumptions!$B$4)^I4 | J20: =1/(1+Assumptions!$B$4)^J4 | ... L20: =1/(1+Assumptions!$B$4)^L4
A21: PV of FCF | C21: =C19*C20 | D21: =D19*D20 | E21: =E19*E20 | F21: =F19*F20 | G21: =G19*G20 | H21: =H19*H20 | I21: =I19*I20 | J21: =J19*J20 | ... L21: =L19*L20
A23: Memo: FCF before SBC (street) | C23: =C19-C10 | D23: =D19-D10 | E23: =E19-E10 | F23: =F19-F10 | G23: =G19-G10 | H23: =H19-H10 | I23: =I19-I10 | J23: =J19-J10 | ... L23: =L19-L10
A24: Memo: owner-FCF margin | C24: =C19/C6 | D24: =D19/D6 | E24: =E19/E6 | F24: =F19/F6 | G24: =G19/G6 | H24: =H19/H6 | I24: =I19/I6 | J24: =J19/J6 | ... L24: =L19/L6
A26: Sum of PV of FCF | B26: =SUM(C21:L21)
A27: Terminal growth | B27: =Assumptions!$C$14
A28: Terminal-year FCF x (1+g) | B28: =L19*(1+B27)
A29: Gordon terminal value | B29: =B28/(Assumptions!$B$4-B27)
A30: Cap terminal value | B30: =Assumptions!$C$15*L19
A31: Terminal value used | B31: =MAX(0,MIN(B29,B30)) | C31: TV = MAX(0, MIN(Gordon, cap)). The zero floor matters when terminal FCF is negative.
A32: Implied exit multiple | B32: =B31/L19
A33: PV of terminal value | B33: =B31*L20
A34: Enterprise value | B34: =B26+B33
A35: less net debt | B35: =-Assumptions!$B$6
A36: Equity value | B36: =B34+B35
A37: Diluted shares (m) | B37: =Assumptions!$B$7
A38: VALUE PER SHARE | B38: =B36/B37
A39: Upside vs current price | B39: =B38/Assumptions!$B$8-1
A41: Street memo: PV of SBC (explicit) | B41: =SUMPRODUCT(-C10:L10,1/(1+Assumptions!$B$4)^C4:L4)
A42: Street memo: PV of SBC (terminal) | B42: =(-L10*(1+B27)/(Assumptions!$B$4-B27))*L20
A43: Street value per share | B43: =(B36+B41+B42)/B37

Sheet DCF_Bull
A1: ADBE owner-FCF DCF -- Bull case
A2: Only rows 5, 7, 9 and 14 are drivers (yellow). Everything else is formula-derived.
A3: USD millions | B3: FY0 TTM | C3: FY2026E | D3: FY2027E | E3: FY2028E | F3: FY2029E | G3: FY2030E | H3: FY2031E | I3: FY2032E | J3: FY2033E | K3: FY2034E | L3: FY2035E
A4: Year index | B4: 0 | C4: 1 | D4: 2 | E4: 3 | F4: 4 | G4: 5 | H4: 6 | I4: 7 | J4: 8 | K4: 9 | L4: 10
A5: Revenue growth YoY | C5: 0.06 | D5: 0.1 | E5: 0.11 | F5: 0.105 | G5: 0.1 | H5: 0.09 | I5: 0.08 | J5: 0.07 | K5: 0.06 | L5: 0.05
A6: Revenue | B6: =Assumptions!$B$9 | C6: =B6*(1+C5) | D6: =C6*(1+D5) | E6: =D6*(1+E5) | F6: =E6*(1+F5) | G6: =F6*(1+G5) | H6: =G6*(1+H5) | I6: =H6*(1+I5) | J6: =I6*(1+J5) | ... L6: =K6*(1+L5)
A7: Adj EBITDA margin | C7: 0.482 | D7: 0.488 | E7: 0.495 | F7: 0.5 | G7: 0.505 | H7: 0.51 | I7: 0.515 | J7: 0.52 | K7: 0.52 | L7: 0.52
A8: Adjusted EBITDA | C8: =C6*C7 | D8: =D6*D7 | E8: =E6*E7 | F8: =F6*F7 | G8: =G6*G7 | H8: =H6*H7 | I8: =I6*I7 | J8: =J6*J7 | ... L8: =L6*L7
A9: SBC % of revenue | C9: 0.095 | D9: 0.092 | E9: 0.088 | F9: 0.085 | G9: 0.082 | H9: 0.08 | I9: 0.078 | J9: 0.075 | K9: 0.075 | L9: 0.075
A10: SBC (incl. equity-award taxes) | C10: =-C6*C9 | D10: =-D6*D9 | E10: =-E6*E9 | F10: =-F6*F9 | G10: =-G6*G9 | H10: =-H6*H9 | I10: =-I6*I9 | J10: =-J6*J9 | ... L10: =-L6*L9
A11: Owner EBITDA (post-SBC) | C11: =C8+C10 | D11: =D8+D10 | E11: =E8+E10 | F11: =F8+F10 | G11: =G8+G10 | H11: =H8+H10 | I11: =I8+I10 | J11: =J8+J10 | ... L11: =L8+L10
A12: D&A | C12: =-C6*0.032 | D12: =-D6*0.031 | E12: =-E6*0.03 | F12: =-F6*0.028999999999999998 | G12: =-G6*0.027999999999999997 | H12: =-H6*0.027999999999999997 | I12: =-I6*0.027000000000000003 | J12: =-J6*0.027000000000000003 | K12: =-K6*0.026000000000000002 | L12: =-L6*0.026000000000000002
A13: EBIT (SBC expensed) | C13: =C11+C12 | D13: =D11+D12 | E13: =E11+E12 | F13: =F11+F12 | G13: =G11+G12 | H13: =H11+H12 | I13: =I11+I12 | J13: =J11+J12 | ... L13: =L11+L12
A14: Cash tax rate | C14: 0.26 | D14: 0.26 | E14: 0.265 | F14: 0.265 | G14: 0.27 | H14: 0.27 | I14: 0.27 | J14: 0.27 | K14: 0.27 | L14: 0.27
A15: NOPAT | C15: =C13*(1-C14) | D15: =D13*(1-D14) | E15: =E13*(1-E14) | F15: =F13*(1-F14) | G15: =G13*(1-G14) | H15: =H13*(1-H14) | I15: =I13*(1-I14) | J15: =J13*(1-J14) | ... L15: =L13*(1-L14)
A16: add back D&A | C16: =-C12 | D16: =-D12 | E16: =-E12 | F16: =-F12 | G16: =-G12 | H16: =-H12 | I16: =-I12 | J16: =-J12 | ... L16: =-L12
A17: less capex | C17: =-C6*0.01 | D17: =-D6*0.011000000000000001 | E17: =-E6*0.012 | F17: =-F6*0.012 | G17: =-G6*0.012 | H17: =-H6*0.012 | I17: =-I6*0.012 | J17: =-J6*0.012 | K17: =-K6*0.012 | L17: =-L6*0.012
A18: add working capital | C18: =Assumptions!$D$16*(C6-B6) | D18: =Assumptions!$D$16*(D6-C6) | E18: =Assumptions!$D$16*(E6-D6) | F18: =Assumptions!$D$16*(F6-E6) | G18: =Assumptions!$D$16*(G6-F6) | H18: =Assumptions!$D$16*(H6-G6) | I18: =Assumptions!$D$16*(I6-H6) | J18: =Assumptions!$D$16*(J6-I6) | ... L18: =Assumptions!$D$16*(L6-K6)
A19: Unlevered owner FCF | C19: =C15+C16+C17+C18 | D19: =D15+D16+D17+D18 | E19: =E15+E16+E17+E18 | F19: =F15+F16+F17+F18 | G19: =G15+G16+G17+G18 | H19: =H15+H16+H17+H18 | I19: =I15+I16+I17+I18 | J19: =J15+J16+J17+J18 | ... L19: =L15+L16+L17+L18
A20: Discount factor | C20: =1/(1+Assumptions!$B$4)^C4 | D20: =1/(1+Assumptions!$B$4)^D4 | E20: =1/(1+Assumptions!$B$4)^E4 | F20: =1/(1+Assumptions!$B$4)^F4 | G20: =1/(1+Assumptions!$B$4)^G4 | H20: =1/(1+Assumptions!$B$4)^H4 | I20: =1/(1+Assumptions!$B$4)^I4 | J20: =1/(1+Assumptions!$B$4)^J4 | ... L20: =1/(1+Assumptions!$B$4)^L4
A21: PV of FCF | C21: =C19*C20 | D21: =D19*D20 | E21: =E19*E20 | F21: =F19*F20 | G21: =G19*G20 | H21: =H19*H20 | I21: =I19*I20 | J21: =J19*J20 | ... L21: =L19*L20
A23: Memo: FCF before SBC (street) | C23: =C19-C10 | D23: =D19-D10 | E23: =E19-E10 | F23: =F19-F10 | G23: =G19-G10 | H23: =H19-H10 | I23: =I19-I10 | J23: =J19-J10 | ... L23: =L19-L10
A24: Memo: owner-FCF margin | C24: =C19/C6 | D24: =D19/D6 | E24: =E19/E6 | F24: =F19/F6 | G24: =G19/G6 | H24: =H19/H6 | I24: =I19/I6 | J24: =J19/J6 | ... L24: =L19/L6
A26: Sum of PV of FCF | B26: =SUM(C21:L21)
A27: Terminal growth | B27: =Assumptions!$D$14
A28: Terminal-year FCF x (1+g) | B28: =L19*(1+B27)
A29: Gordon terminal value | B29: =B28/(Assumptions!$B$4-B27)
A30: Cap terminal value | B30: =Assumptions!$D$15*L19
A31: Terminal value used | B31: =MAX(0,MIN(B29,B30)) | C31: TV = MAX(0, MIN(Gordon, cap)). The zero floor matters when terminal FCF is negative.
A32: Implied exit multiple | B32: =B31/L19
A33: PV of terminal value | B33: =B31*L20
A34: Enterprise value | B34: =B26+B33
A35: less net debt | B35: =-Assumptions!$B$6
A36: Equity value | B36: =B34+B35
A37: Diluted shares (m) | B37: =Assumptions!$B$7
A38: VALUE PER SHARE | B38: =B36/B37
A39: Upside vs current price | B39: =B38/Assumptions!$B$8-1
A41: Street memo: PV of SBC (explicit) | B41: =SUMPRODUCT(-C10:L10,1/(1+Assumptions!$B$4)^C4:L4)
A42: Street memo: PV of SBC (terminal) | B42: =(-L10*(1+B27)/(Assumptions!$B$4-B27))*L20
A43: Street value per share | B43: =(B36+B41+B42)/B37

Sheet FCF_Quality
A1: Reported FCF reconciled to owner FCF
A2: Shows how much of headline FCF is compensation cost and working-capital timing.
A4: USD millions | B4: FY2020 | C4: FY2021 | D4: FY2022 | E4: FY2023 | F4: FY2024 | G4: FY2025 | H4: TTM
A5: Free cash flow (company definition) | B5: =Actuals!B7 | C5: =Actuals!C7 | D5: =Actuals!D7 | E5: =Actuals!E7 | F5: =Actuals!F7 | G5: =Actuals!G7 | H5: =Actuals!H7
A6: less: SBC (cash flow add-back) | B6: =-Actuals!B8 | C6: =-Actuals!C8 | D6: =-Actuals!D8 | E6: =-Actuals!E8 | F6: =-Actuals!F8 | G6: =-Actuals!G8 | H6: =-Actuals!H8
A7: less: equity-award cash taxes | B7: =-Actuals!B9 | C7: =-Actuals!C9 | D7: =-Actuals!D9 | E7: =-Actuals!E9 | F7: =-Actuals!F9 | G7: =-Actuals!G9 | H7: =-Actuals!H9
A8: less: interest income | B8: =0 | C8: =0 | D8: =0 | E8: =0 | F8: =0 | G8: =0 | H8: =0
A9: Owner FCF | B9: =SUM(B5:B8) | C9: =SUM(C5:C8) | D9: =SUM(D5:D8) | E9: =SUM(E5:E8) | F9: =SUM(F5:F8) | G9: =SUM(G5:G8) | H9: =SUM(H5:H8)
A10: Reported FCF margin | B10: =Actuals!B7/Actuals!B4 | C10: =Actuals!C7/Actuals!C4 | D10: =Actuals!D7/Actuals!D4 | E10: =Actuals!E7/Actuals!E4 | F10: =Actuals!F7/Actuals!F4 | G10: =Actuals!G7/Actuals!G4 | H10: =Actuals!H7/Actuals!H4
A11: Owner FCF margin | B11: =B9/Actuals!B4 | C11: =C9/Actuals!C4 | D11: =D9/Actuals!D4 | E11: =E9/Actuals!E4 | F11: =F9/Actuals!F4 | G11: =G9/Actuals!G4 | H11: =H9/Actuals!H4
A13: Memo: deferred-revenue increase | C13: =Actuals!C15-Actuals!B15 | D13: =Actuals!D15-Actuals!C15 | E13: =Actuals!E15-Actuals!D15 | F13: =Actuals!F15-Actuals!E15 | G13: =Actuals!G15-Actuals!F15
A14: as % of reported FCF | C14: =(Actuals!C15-Actuals!B15)/Actuals!C7 | D14: =(Actuals!D15-Actuals!C15)/Actuals!D7 | E14: =(Actuals!E15-Actuals!D15)/Actuals!E7 | F14: =(Actuals!F15-Actuals!E15)/Actuals!F7 | G14: =(Actuals!G15-Actuals!F15)/Actuals!G7
A16: Memo: cash tax rate (cash taxes / net income) | B16: =Actuals!B11/Actuals!B13 | C16: =Actuals!C11/Actuals!C13 | D16: =Actuals!D11/Actuals!D13 | E16: =Actuals!E11/Actuals!E13 | F16: =Actuals!F11/Actuals!F13 | G16: =Actuals!G11/Actuals!G13 | H16: =Actuals!H11/Actuals!H13
A17: Cash tax rate stepped up sharply at FY2023 (8.9% of net income in FY2020 to ~31% FY2023-25) as prior-year benefits ran out. The forward model uses 26-27% of EBIT, NOT the depressed early-period rate.
A19: Interest income is NOT deducted: Adobe carries net DEBT of $1,726m, so its cash is netted against debt in the bridge rather than added to enterprise value. Stripping the interest as well would understate value.

Sheet Valuation
A1: Valuation summary
A3: Scenario | B3: Value/share | C3: Upside | D3: Probability | E3: Street value/share
A4: Bear | B4: =DCF_Bear!$B$38 | C4: =B4/Assumptions!$B$8-1 | D4: =Assumptions!$B$17 | E4: =DCF_Bear!$B$43
A5: Base | B5: =DCF_Base!$B$38 | C5: =B5/Assumptions!$B$8-1 | D5: =Assumptions!$C$17 | E5: =DCF_Base!$B$43
A6: Bull | B6: =DCF_Bull!$B$38 | C6: =B6/Assumptions!$B$8-1 | D6: =Assumptions!$D$17 | E6: =DCF_Bull!$B$43
A8: Probability-weighted value | B8: =SUMPRODUCT(B4:B6,D4:D6) | E8: =SUMPRODUCT(E4:E6,D4:D6)
A9: Current price | B9: =Assumptions!$B$8
A10: Upside vs weighted | B10: =B8/Assumptions!$B$8-1
A11: Margin of safety | B11: =1-Assumptions!$B$8/B8
A12: Band position (0% house, 100% street) | B12: =(Assumptions!$B$8-B8)/(E8-B8)
A13: Band position is NEGATIVE: the market is paying less than the fully-SBC-expensed house value, i.e. below the floor of the accounting-regime band.
A15: Required-return table (base case)
A16: Required return | B16: Value per share
A17: 0.09 | B17: =(SUMPRODUCT(DCF_Base!C19:DCF_Base!L19,1/(1+$A$17)^DCF_Base!C4:DCF_Base!L4)+MAX(0,MIN(DCF_Base!$B$29,DCF_Base!$B$30))/(1+$A$17)^10-Assumptions!$B$6)/Assumptions!$B$7
A18: 0.095 | B18: =(SUMPRODUCT(DCF_Base!C19:DCF_Base!L19,1/(1+$A$18)^DCF_Base!C4:DCF_Base!L4)+MAX(0,MIN(DCF_Base!$B$29,DCF_Base!$B$30))/(1+$A$18)^10-Assumptions!$B$6)/Assumptions!$B$7
A19: 0.1 | B19: =(SUMPRODUCT(DCF_Base!C19:DCF_Base!L19,1/(1+$A$19)^DCF_Base!C4:DCF_Base!L4)+MAX(0,MIN(DCF_Base!$B$29,DCF_Base!$B$30))/(1+$A$19)^10-Assumptions!$B$6)/Assumptions!$B$7
A20: 0.11 | B20: =(SUMPRODUCT(DCF_Base!C19:DCF_Base!L19,1/(1+$A$20)^DCF_Base!C4:DCF_Base!L4)+MAX(0,MIN(DCF_Base!$B$29,DCF_Base!$B$30))/(1+$A$20)^10-Assumptions!$B$6)/Assumptions!$B$7
A21: 0.12 | B21: =(SUMPRODUCT(DCF_Base!C19:DCF_Base!L19,1/(1+$A$21)^DCF_Base!C4:DCF_Base!L4)+MAX(0,MIN(DCF_Base!$B$29,DCF_Base!$B$30))/(1+$A$21)^10-Assumptions!$B$6)/Assumptions!$B$7
A22: 0.15 | B22: =(SUMPRODUCT(DCF_Base!C19:DCF_Base!L19,1/(1+$A$22)^DCF_Base!C4:DCF_Base!L4)+MAX(0,MIN(DCF_Base!$B$29,DCF_Base!$B$30))/(1+$A$22)^10-Assumptions!$B$6)/Assumptions!$B$7
A23: 9.5% is the model's own WACC. Today's price implies roughly a 12.6% IRR on base-case flows.
A25: 15% hurdle entry price
A26: Scenario | B26: Entry price | C26: Probability
A27: Bear | B27: =(SUMPRODUCT(DCF_Bear!C19:DCF_Bear!L19,1/(1+0.15)^DCF_Bear!C4:DCF_Bear!L4)+MAX(0,MIN(DCF_Bear!$B$29,DCF_Bear!$B$30))/(1+0.15)^10-Assumptions!$B$6)/Assumptions!$B$7 | C27: =Assumptions!$B$17
A28: Base | B28: =(SUMPRODUCT(DCF_Base!C19:DCF_Base!L19,1/(1+0.15)^DCF_Base!C4:DCF_Base!L4)+MAX(0,MIN(DCF_Base!$B$29,DCF_Base!$B$30))/(1+0.15)^10-Assumptions!$B$6)/Assumptions!$B$7 | C28: =Assumptions!$C$17
A29: Bull | B29: =(SUMPRODUCT(DCF_Bull!C19:DCF_Bull!L19,1/(1+0.15)^DCF_Bull!C4:DCF_Bull!L4)+MAX(0,MIN(DCF_Bull!$B$29,DCF_Bull!$B$30))/(1+0.15)^10-Assumptions!$B$6)/Assumptions!$B$7 | C29: =Assumptions!$D$17
A30: Weighted entry price (buy below) | B30: =SUMPRODUCT(B27:B29,C27:C29)
A31: Discount to current price | B31: =B30/Assumptions!$B$8-1
A33: Sensitivity: WACC (rows) x terminal growth (cols), base case
A34: WACC \ g | B34: 0.02 | C34: 0.025 | D34: 0.03 | E34: 0.035 | F34: 0.04
A35: 0.075 | B35: =IF($A$35>B34,(SUMPRODUCT(DCF_Base!C19:DCF_Base!L19,1/(1+$A$35)^DCF_Base!C4:DCF_Base!L4)+MAX(0,MIN(DCF_Base!$L$19*(1+B34)/($A$35-B34),Assumptions!$C$15*DCF_Base!$L$19))/(1+$A$35)^10-Assumptions!$B$6)/Assumptions!$B$7,"n/a") | C35: =IF($A$35>C34,(SUMPRODUCT(DCF_Base!C19:DCF_Base!L19,1/(1+$A$35)^DCF_Base!C4:DCF_Base!L4)+MAX(0,MIN(DCF_Base!$L$19*(1+C34)/($A$35-C34),Assumptions!$C$15*DCF_Base!$L$19))/(1+$A$35)^10-Assumptions!$B$6)/Assumptions!$B$7,"n/a") | D35: =IF($A$35>D34,(SUMPRODUCT(DCF_Base!C19:DCF_Base!L19,1/(1+$A$35)^DCF_Base!C4:DCF_Base!L4)+MAX(0,MIN(DCF_Base!$L$19*(1+D34)/($A$35-D34),Assumptions!$C$15*DCF_Base!$L$19))/(1+$A$35)^10-Assumptions!$B$6)/Assumptions!$B$7,"n/a") | E35: =IF($A$35>E34,(SUMPRODUCT(DCF_Base!C19:DCF_Base!L19,1/(1+$A$35)^DCF_Base!C4:DCF_Base!L4)+MAX(0,MIN(DCF_Base!$L$19*(1+E34)/($A$35-E34),Assumptions!$C$15*DCF_Base!$L$19))/(1+$A$35)^10-Assumptions!$B$6)/Assumptions!$B$7,"n/a") | F35: =IF($A$35>F34,(SUMPRODUCT(DCF_Base!C19:DCF_Base!L19,1/(1+$A$35)^DCF_Base!C4:DCF_Base!L4)+MAX(0,MIN(DCF_Base!$L$19*(1+F34)/($A$35-F34),Assumptions!$C$15*DCF_Base!$L$19))/(1+$A$35)^10-Assumptions!$B$6)/Assumptions!$B$7,"n/a")
A36: 0.085 | B36: =IF($A$36>B34,(SUMPRODUCT(DCF_Base!C19:DCF_Base!L19,1/(1+$A$36)^DCF_Base!C4:DCF_Base!L4)+MAX(0,MIN(DCF_Base!$L$19*(1+B34)/($A$36-B34),Assumptions!$C$15*DCF_Base!$L$19))/(1+$A$36)^10-Assumptions!$B$6)/Assumptions!$B$7,"n/a") | C36: =IF($A$36>C34,(SUMPRODUCT(DCF_Base!C19:DCF_Base!L19,1/(1+$A$36)^DCF_Base!C4:DCF_Base!L4)+MAX(0,MIN(DCF_Base!$L$19*(1+C34)/($A$36-C34),Assumptions!$C$15*DCF_Base!$L$19))/(1+$A$36)^10-Assumptions!$B$6)/Assumptions!$B$7,"n/a") | D36: =IF($A$36>D34,(SUMPRODUCT(DCF_Base!C19:DCF_Base!L19,1/(1+$A$36)^DCF_Base!C4:DCF_Base!L4)+MAX(0,MIN(DCF_Base!$L$19*(1+D34)/($A$36-D34),Assumptions!$C$15*DCF_Base!$L$19))/(1+$A$36)^10-Assumptions!$B$6)/Assumptions!$B$7,"n/a") | E36: =IF($A$36>E34,(SUMPRODUCT(DCF_Base!C19:DCF_Base!L19,1/(1+$A$36)^DCF_Base!C4:DCF_Base!L4)+MAX(0,MIN(DCF_Base!$L$19*(1+E34)/($A$36-E34),Assumptions!$C$15*DCF_Base!$L$19))/(1+$A$36)^10-Assumptions!$B$6)/Assumptions!$B$7,"n/a") | F36: =IF($A$36>F34,(SUMPRODUCT(DCF_Base!C19:DCF_Base!L19,1/(1+$A$36)^DCF_Base!C4:DCF_Base!L4)+MAX(0,MIN(DCF_Base!$L$19*(1+F34)/($A$36-F34),Assumptions!$C$15*DCF_Base!$L$19))/(1+$A$36)^10-Assumptions!$B$6)/Assumptions!$B$7,"n/a")
A37: 0.095 | B37: =IF($A$37>B34,(SUMPRODUCT(DCF_Base!C19:DCF_Base!L19,1/(1+$A$37)^DCF_Base!C4:DCF_Base!L4)+MAX(0,MIN(DCF_Base!$L$19*(1+B34)/($A$37-B34),Assumptions!$C$15*DCF_Base!$L$19))/(1+$A$37)^10-Assumptions!$B$6)/Assumptions!$B$7,"n/a") | C37: =IF($A$37>C34,(SUMPRODUCT(DCF_Base!C19:DCF_Base!L19,1/(1+$A$37)^DCF_Base!C4:DCF_Base!L4)+MAX(0,MIN(DCF_Base!$L$19*(1+C34)/($A$37-C34),Assumptions!$C$15*DCF_Base!$L$19))/(1+$A$37)^10-Assumptions!$B$6)/Assumptions!$B$7,"n/a") | D37: =IF($A$37>D34,(SUMPRODUCT(DCF_Base!C19:DCF_Base!L19,1/(1+$A$37)^DCF_Base!C4:DCF_Base!L4)+MAX(0,MIN(DCF_Base!$L$19*(1+D34)/($A$37-D34),Assumptions!$C$15*DCF_Base!$L$19))/(1+$A$37)^10-Assumptions!$B$6)/Assumptions!$B$7,"n/a") | E37: =IF($A$37>E34,(SUMPRODUCT(DCF_Base!C19:DCF_Base!L19,1/(1+$A$37)^DCF_Base!C4:DCF_Base!L4)+MAX(0,MIN(DCF_Base!$L$19*(1+E34)/($A$37-E34),Assumptions!$C$15*DCF_Base!$L$19))/(1+$A$37)^10-Assumptions!$B$6)/Assumptions!$B$7,"n/a") | F37: =IF($A$37>F34,(SUMPRODUCT(DCF_Base!C19:DCF_Base!L19,1/(1+$A$37)^DCF_Base!C4:DCF_Base!L4)+MAX(0,MIN(DCF_Base!$L$19*(1+F34)/($A$37-F34),Assumptions!$C$15*DCF_Base!$L$19))/(1+$A$37)^10-Assumptions!$B$6)/Assumptions!$B$7,"n/a")
A38: 0.105 | B38: =IF($A$38>B34,(SUMPRODUCT(DCF_Base!C19:DCF_Base!L19,1/(1+$A$38)^DCF_Base!C4:DCF_Base!L4)+MAX(0,MIN(DCF_Base!$L$19*(1+B34)/($A$38-B34),Assumptions!$C$15*DCF_Base!$L$19))/(1+$A$38)^10-Assumptions!$B$6)/Assumptions!$B$7,"n/a") | C38: =IF($A$38>C34,(SUMPRODUCT(DCF_Base!C19:DCF_Base!L19,1/(1+$A$38)^DCF_Base!C4:DCF_Base!L4)+MAX(0,MIN(DCF_Base!$L$19*(1+C34)/($A$38-C34),Assumptions!$C$15*DCF_Base!$L$19))/(1+$A$38)^10-Assumptions!$B$6)/Assumptions!$B$7,"n/a") | D38: =IF($A$38>D34,(SUMPRODUCT(DCF_Base!C19:DCF_Base!L19,1/(1+$A$38)^DCF_Base!C4:DCF_Base!L4)+MAX(0,MIN(DCF_Base!$L$19*(1+D34)/($A$38-D34),Assumptions!$C$15*DCF_Base!$L$19))/(1+$A$38)^10-Assumptions!$B$6)/Assumptions!$B$7,"n/a") | E38: =IF($A$38>E34,(SUMPRODUCT(DCF_Base!C19:DCF_Base!L19,1/(1+$A$38)^DCF_Base!C4:DCF_Base!L4)+MAX(0,MIN(DCF_Base!$L$19*(1+E34)/($A$38-E34),Assumptions!$C$15*DCF_Base!$L$19))/(1+$A$38)^10-Assumptions!$B$6)/Assumptions!$B$7,"n/a") | F38: =IF($A$38>F34,(SUMPRODUCT(DCF_Base!C19:DCF_Base!L19,1/(1+$A$38)^DCF_Base!C4:DCF_Base!L4)+MAX(0,MIN(DCF_Base!$L$19*(1+F34)/($A$38-F34),Assumptions!$C$15*DCF_Base!$L$19))/(1+$A$38)^10-Assumptions!$B$6)/Assumptions!$B$7,"n/a")
A39: 0.115 | B39: =IF($A$39>B34,(SUMPRODUCT(DCF_Base!C19:DCF_Base!L19,1/(1+$A$39)^DCF_Base!C4:DCF_Base!L4)+MAX(0,MIN(DCF_Base!$L$19*(1+B34)/($A$39-B34),Assumptions!$C$15*DCF_Base!$L$19))/(1+$A$39)^10-Assumptions!$B$6)/Assumptions!$B$7,"n/a") | C39: =IF($A$39>C34,(SUMPRODUCT(DCF_Base!C19:DCF_Base!L19,1/(1+$A$39)^DCF_Base!C4:DCF_Base!L4)+MAX(0,MIN(DCF_Base!$L$19*(1+C34)/($A$39-C34),Assumptions!$C$15*DCF_Base!$L$19))/(1+$A$39)^10-Assumptions!$B$6)/Assumptions!$B$7,"n/a") | D39: =IF($A$39>D34,(SUMPRODUCT(DCF_Base!C19:DCF_Base!L19,1/(1+$A$39)^DCF_Base!C4:DCF_Base!L4)+MAX(0,MIN(DCF_Base!$L$19*(1+D34)/($A$39-D34),Assumptions!$C$15*DCF_Base!$L$19))/(1+$A$39)^10-Assumptions!$B$6)/Assumptions!$B$7,"n/a") | E39: =IF($A$39>E34,(SUMPRODUCT(DCF_Base!C19:DCF_Base!L19,1/(1+$A$39)^DCF_Base!C4:DCF_Base!L4)+MAX(0,MIN(DCF_Base!$L$19*(1+E34)/($A$39-E34),Assumptions!$C$15*DCF_Base!$L$19))/(1+$A$39)^10-Assumptions!$B$6)/Assumptions!$B$7,"n/a") | F39: =IF($A$39>F34,(SUMPRODUCT(DCF_Base!C19:DCF_Base!L19,1/(1+$A$39)^DCF_Base!C4:DCF_Base!L4)+MAX(0,MIN(DCF_Base!$L$19*(1+F34)/($A$39-F34),Assumptions!$C$15*DCF_Base!$L$19))/(1+$A$39)^10-Assumptions!$B$6)/Assumptions!$B$7,"n/a")
A40: Highlighted cell is the house pair (9.5% WACC, 3.0% terminal growth). Flat regions at low WACC are the 17x terminal cap binding, which is intended.
