Workbook

Sheet Inputs
A1: Seazen Group (1030.HK) -- haircut NAV x exit multiple model
A2: Price (HKD) | B2: 1.43
A3: FX CNY->HKD | B3: 1.1721
A4: Shares (m) | B4: 7263.7415
A5: Book equity attributable (RMB m) | B5: 47658.489
A6: NCI (RMB m) | B6: 34883.474
A7: Total equity (RMB m) | B7: 82541.963
A8: Attributable fraction k | B8: =B5/B7
A9: Hurdle rate | B9: 0.15
A10: Horizon years | B10: 5
A12: Balance-sheet items (100% basis, RMB m)
A13: Properties held for sale / under development | B13: 64807.62
A14: Trade & other receivables and prepayments | B14: 31362.763
A15: Investments in JVs and associates | B15: 19572.332
A16: Deferred tax assets | B16: 5836.502
A17: Investment properties (Wuyue Plazas, IAS 40 fair value) | B17: 123852.13
A18: Contingent purchaser-mortgage guarantees (off-BS) | B18: 11200

Sheet Scenarios
B1: Bear | C1: Base | D1: Bull
A2: Haircuts (% of carrying amount)
A3: Properties held for sale / under development | B3: 25 | C3: 10 | D3: 5
A4: Trade & other receivables and prepayments | B4: 35 | C4: 15 | D4: 10
A5: Investments in JVs and associates | B5: 40 | C5: 20 | D5: 10
A6: Deferred tax assets | B6: 100 | C6: 50 | D6: 25
A7: Investment properties (Wuyue Plazas, IAS 40 fair value) | B7: 10 | C7: 0 | D7: 0
A8: Contingent purchaser-mortgage guarantees (off-BS) | B8: 10 | C8: 2 | D8: 0
A9: Adjustment total, 100% basis (RMB m) | B9: =-(Inputs!$B$13*B3/100+Inputs!$B$14*B4/100+Inputs!$B$15*B5/100+Inputs!$B$16*B6/100+Inputs!$B$17*B7/100+Inputs!$B$18*B8/100) | C9: =-(Inputs!$B$13*C3/100+Inputs!$B$14*C4/100+Inputs!$B$15*C5/100+Inputs!$B$16*C6/100+Inputs!$B$17*C7/100+Inputs!$B$18*C8/100) | D9: =-(Inputs!$B$13*D3/100+Inputs!$B$14*D4/100+Inputs!$B$15*D5/100+Inputs!$B$16*D6/100+Inputs!$B$17*D7/100+Inputs!$B$18*D8/100)
A10: Adjustment attributable (x k) | B10: =B9*Inputs!$B$8 | C10: =C9*Inputs!$B$8 | D10: =D9*Inputs!$B$8
A11: Adjusted NAV today (RMB m) | B11: =Inputs!$B$5+B10 | C11: =Inputs!$B$5+C10 | D11: =Inputs!$B$5+D10
A12: Adjusted NAV / share (RMB) | B12: =B11/Inputs!$B$4 | C12: =C11/Inputs!$B$4 | D12: =D11/Inputs!$B$4
A14: Attributable NPAT path (RMB m)
A15: FY2026E | B15: 0 | C15: 850 | D15: 1300
A16: FY2027E | B16: 100 | C16: 893 | D16: 1404
A17: FY2028E | B17: 200 | C17: 937 | D17: 1516
A18: FY2029E | B18: 250 | C18: 984 | D18: 1638
A19: FY2030E | B19: 300 | C19: 1033 | D19: 1769
A20: NAV year 5 (RMB m) = NAV0 + sum(NPAT) | B20: =B11+SUM(B15:B19) | C20: =C11+SUM(C15:C19) | D20: =D11+SUM(D15:D19)
A21: NAV5 / share (RMB) | B21: =B20/Inputs!$B$4 | C21: =C20/Inputs!$B$4 | D21: =D20/Inputs!$B$4
A22: EPS year 5 (RMB) | B22: =B19/Inputs!$B$4 | C22: =C19/Inputs!$B$4 | D22: =D19/Inputs!$B$4
A24: Exit P/NAV | B24: 0.15 | C24: 0.45 | D24: 0.6
A25: Exit P/E | B25: 6 | C25: 9 | D25: 12
A26: NAV weight | B26: 0.7 | C26: 0.7 | D26: 0.7
A27: Cost of equity % | B27: 14.5 | C27: 12.5 | D27: 11.5
A28: Scenario weight | B28: 0.35 | C28: 0.45 | D28: 0.2
A30: Year-5 exit value / share (RMB) | B30: =B26*B21*B24+(1-B26)*B22*B25 | C30: =C26*C21*C24+(1-C26)*C22*C25 | D30: =D26*D21*D24+(1-D26)*D22*D25
A31: Intrinsic value / share (RMB) | B31: =B30/(1+B27/100)^Inputs!$B$10 | C31: =C30/(1+C27/100)^Inputs!$B$10 | D31: =D30/(1+D27/100)^Inputs!$B$10
A32: Intrinsic value / share (HKD) | B32: =B31*Inputs!$B$3 | C32: =C31*Inputs!$B$3 | D32: =D31*Inputs!$B$3
A33: Upside vs price % | B33: =100*(B32/Inputs!$B$2-1) | C33: =100*(C32/Inputs!$B$2-1) | D33: =100*(D32/Inputs!$B$2-1)
A34: Entry price at hurdle (HKD) | B34: =B30/(1+Inputs!$B$9)^Inputs!$B$10*Inputs!$B$3 | C34: =C30/(1+Inputs!$B$9)^Inputs!$B$10*Inputs!$B$3 | D34: =D30/(1+Inputs!$B$9)^Inputs!$B$10*Inputs!$B$3
A36: Probability-weighted IV (HKD) | B36: =SUMPRODUCT(B28:D28,B32:D32)
A37: Probability-weighted entry (HKD) | B37: =SUMPRODUCT(B28:D28,B34:D34)

Sheet Sensitivity
A1: Base IV (HKD): rows exit P/NAV, cols cost of equity %
A2: P/NAV \ CoE | B2: 10.5 | C2: 11.5 | D2: 12.5 | E2: 13.5 | F2: 14.5
A3: 0.25 | B3: =(Scenarios!$C$26*Scenarios!$C$21*$A3+(1-Scenarios!$C$26)*Scenarios!$C$22*Scenarios!$C$25)/(1+B$2/100)^Inputs!$B$10*Inputs!$B$3 | C3: =(Scenarios!$C$26*Scenarios!$C$21*$A3+(1-Scenarios!$C$26)*Scenarios!$C$22*Scenarios!$C$25)/(1+C$2/100)^Inputs!$B$10*Inputs!$B$3 | D3: =(Scenarios!$C$26*Scenarios!$C$21*$A3+(1-Scenarios!$C$26)*Scenarios!$C$22*Scenarios!$C$25)/(1+D$2/100)^Inputs!$B$10*Inputs!$B$3 | E3: =(Scenarios!$C$26*Scenarios!$C$21*$A3+(1-Scenarios!$C$26)*Scenarios!$C$22*Scenarios!$C$25)/(1+E$2/100)^Inputs!$B$10*Inputs!$B$3 | F3: =(Scenarios!$C$26*Scenarios!$C$21*$A3+(1-Scenarios!$C$26)*Scenarios!$C$22*Scenarios!$C$25)/(1+F$2/100)^Inputs!$B$10*Inputs!$B$3
A4: 0.35 | B4: =(Scenarios!$C$26*Scenarios!$C$21*$A4+(1-Scenarios!$C$26)*Scenarios!$C$22*Scenarios!$C$25)/(1+B$2/100)^Inputs!$B$10*Inputs!$B$3 | C4: =(Scenarios!$C$26*Scenarios!$C$21*$A4+(1-Scenarios!$C$26)*Scenarios!$C$22*Scenarios!$C$25)/(1+C$2/100)^Inputs!$B$10*Inputs!$B$3 | D4: =(Scenarios!$C$26*Scenarios!$C$21*$A4+(1-Scenarios!$C$26)*Scenarios!$C$22*Scenarios!$C$25)/(1+D$2/100)^Inputs!$B$10*Inputs!$B$3 | E4: =(Scenarios!$C$26*Scenarios!$C$21*$A4+(1-Scenarios!$C$26)*Scenarios!$C$22*Scenarios!$C$25)/(1+E$2/100)^Inputs!$B$10*Inputs!$B$3 | F4: =(Scenarios!$C$26*Scenarios!$C$21*$A4+(1-Scenarios!$C$26)*Scenarios!$C$22*Scenarios!$C$25)/(1+F$2/100)^Inputs!$B$10*Inputs!$B$3
A5: 0.45 | B5: =(Scenarios!$C$26*Scenarios!$C$21*$A5+(1-Scenarios!$C$26)*Scenarios!$C$22*Scenarios!$C$25)/(1+B$2/100)^Inputs!$B$10*Inputs!$B$3 | C5: =(Scenarios!$C$26*Scenarios!$C$21*$A5+(1-Scenarios!$C$26)*Scenarios!$C$22*Scenarios!$C$25)/(1+C$2/100)^Inputs!$B$10*Inputs!$B$3 | D5: =(Scenarios!$C$26*Scenarios!$C$21*$A5+(1-Scenarios!$C$26)*Scenarios!$C$22*Scenarios!$C$25)/(1+D$2/100)^Inputs!$B$10*Inputs!$B$3 | E5: =(Scenarios!$C$26*Scenarios!$C$21*$A5+(1-Scenarios!$C$26)*Scenarios!$C$22*Scenarios!$C$25)/(1+E$2/100)^Inputs!$B$10*Inputs!$B$3 | F5: =(Scenarios!$C$26*Scenarios!$C$21*$A5+(1-Scenarios!$C$26)*Scenarios!$C$22*Scenarios!$C$25)/(1+F$2/100)^Inputs!$B$10*Inputs!$B$3
A6: 0.55 | B6: =(Scenarios!$C$26*Scenarios!$C$21*$A6+(1-Scenarios!$C$26)*Scenarios!$C$22*Scenarios!$C$25)/(1+B$2/100)^Inputs!$B$10*Inputs!$B$3 | C6: =(Scenarios!$C$26*Scenarios!$C$21*$A6+(1-Scenarios!$C$26)*Scenarios!$C$22*Scenarios!$C$25)/(1+C$2/100)^Inputs!$B$10*Inputs!$B$3 | D6: =(Scenarios!$C$26*Scenarios!$C$21*$A6+(1-Scenarios!$C$26)*Scenarios!$C$22*Scenarios!$C$25)/(1+D$2/100)^Inputs!$B$10*Inputs!$B$3 | E6: =(Scenarios!$C$26*Scenarios!$C$21*$A6+(1-Scenarios!$C$26)*Scenarios!$C$22*Scenarios!$C$25)/(1+E$2/100)^Inputs!$B$10*Inputs!$B$3 | F6: =(Scenarios!$C$26*Scenarios!$C$21*$A6+(1-Scenarios!$C$26)*Scenarios!$C$22*Scenarios!$C$25)/(1+F$2/100)^Inputs!$B$10*Inputs!$B$3
A7: 0.65 | B7: =(Scenarios!$C$26*Scenarios!$C$21*$A7+(1-Scenarios!$C$26)*Scenarios!$C$22*Scenarios!$C$25)/(1+B$2/100)^Inputs!$B$10*Inputs!$B$3 | C7: =(Scenarios!$C$26*Scenarios!$C$21*$A7+(1-Scenarios!$C$26)*Scenarios!$C$22*Scenarios!$C$25)/(1+C$2/100)^Inputs!$B$10*Inputs!$B$3 | D7: =(Scenarios!$C$26*Scenarios!$C$21*$A7+(1-Scenarios!$C$26)*Scenarios!$C$22*Scenarios!$C$25)/(1+D$2/100)^Inputs!$B$10*Inputs!$B$3 | E7: =(Scenarios!$C$26*Scenarios!$C$21*$A7+(1-Scenarios!$C$26)*Scenarios!$C$22*Scenarios!$C$25)/(1+E$2/100)^Inputs!$B$10*Inputs!$B$3 | F7: =(Scenarios!$C$26*Scenarios!$C$21*$A7+(1-Scenarios!$C$26)*Scenarios!$C$22*Scenarios!$C$25)/(1+F$2/100)^Inputs!$B$10*Inputs!$B$3
A9: Required return table (base, HKD)
A10: Return % | B10: 9 | C10: 10 | D10: 11 | E10: 12 | F10: 15
A11: Value / share | B11: =Scenarios!$C$30/(1+B10/100)^Inputs!$B$10*Inputs!$B$3 | C11: =Scenarios!$C$30/(1+C10/100)^Inputs!$B$10*Inputs!$B$3 | D11: =Scenarios!$C$30/(1+D10/100)^Inputs!$B$10*Inputs!$B$3 | E11: =Scenarios!$C$30/(1+E10/100)^Inputs!$B$10*Inputs!$B$3 | F11: =Scenarios!$C$30/(1+F10/100)^Inputs!$B$10*Inputs!$B$3
