Workbook

Sheet DCF Model
A1: PayPal Holdings, Inc. (PYPL) - Discounted Cash Flow Valuation
A2: As of December 11, 2025
A3: All figures in millions USD unless otherwise stated
A5: KEY ASSUMPTIONS
A6: Risk-Free Rate | B6: 0.042 | C6: 10-Year Treasury
A7: Equity Risk Premium | B7: 0.055
A8: Beta (Levered) | B8: 1.2
A9: Cost of Equity | B9: =B6+B8*B7 -> 0.108
A10: Pre-Tax Cost of Debt | B10: 0.045
A11: Tax Rate | B11: 0.22
A12: After-Tax Cost of Debt | B12: =B10*(1-B11) -> 0.0351
A13: Debt Weight | B13: 0.16
A14: Equity Weight | B14: 0.84
A15: WACC | B15: =B9*B14+B12*B13 -> 0.096336
A16: Terminal Growth Rate | B16: 0.025 | C16: Long-term GDP growth
A18: COMPANY DATA (as of Dec 2025)
A19: Current Stock Price | B19: 61
A20: Shares Outstanding (mm) | B20: 936
A21: Market Cap | B21: =B19*B20 -> 57096
A22: Total Debt | B22: 11400
A23: Cash & Equivalents | B23: 10800
A24: Net Debt | B24: =B22-B23 -> 600
A25: Enterprise Value (Market) | B25: =B21+B24 -> 57696
A27: HISTORICAL FINANCIALS
B28: 2020A | C28: 2021A | D28: 2022A | E28: 2023A | F28: 2024A
A29: Revenue | B29: 21454 | C29: 25371 | D29: 27518 | E29: 29771 | F29: 31797
A30: YoY Growth % | C30: =(C29-B29)/B29 -> 0.18257668 | D30: =(D29-C29)/C29 -> 0.084624177 | E30: =(E29-D29)/D29 -> 0.081873683 | F30: =(F29-E29)/E29 -> 0.068052803
A31: Operating Income | B31: 3289 | C31: 4262 | D31: 3837 | E31: 5028 | F31: 5325
A32: Operating Margin % | B32: =B31/B29 -> 0.15330475 | C32: =C31/C29 -> 0.16798707 | D32: =D31/D29 -> 0.13943601 | E32: =E31/E29 -> 0.16888919 | F32: =F31/F29 -> 0.16746863
A33: D&A | B33: 954 | C33: 1050 | D33: 1247 | E33: 705 | F33: 697
A34: EBITDA | B34: =B31+B33 -> 4243 | C34: =C31+C33 -> 5312 | D34: =D31+D33 -> 5084 | E34: =E31+E33 -> 5733 | F34: =F31+F33 -> 6022
A35: CapEx | B35: 866 | C35: 908 | D35: 706 | E35: 611 | F35: 625
A36: Free Cash Flow | B36: 5044 | C36: 5400 | D36: 5107 | E36: 4843 | F36: 6800
A38: PROJECTED FINANCIALS (5-Year Forecast)
B39: 2025E | C39: 2026E | D39: 2027E | E39: 2028E | F39: 2029E
A40: Revenue Growth % | B40: 0.04 | C40: 0.055 | D40: 0.06 | E40: 0.055 | F40: 0.05
A41: Revenue | B41: =F29*(1+B40) -> 33068.88 | C41: =B41*(1+C40) -> 34887.668 | D41: =C41*(1+D40) -> 36980.929 | E41: =D41*(1+E40) -> 39014.88 | F41: =E41*(1+F40) -> 40965.624
A42: Operating Margin % | B42: 0.175 | C42: 0.18 | D42: 0.185 | E42: 0.19 | F42: 0.195
A43: Operating Income (EBIT) | B43: =B41*B42 -> 5787.054 | C43: =C41*C42 -> 6279.7803 | D43: =D41*D42 -> 6841.4718 | E43: =E41*E42 -> 7412.8271 | F43: =F41*F42 -> 7988.2966
A44: Less: Taxes | B44: =-B43*$B$11 -> -1273.1519 | C44: =-C43*$B$11 -> -1381.5517 | D44: =-D43*$B$11 -> -1505.1238 | E44: =-E43*$B$11 -> -1630.822 | F44: =-F43*$B$11 -> -1757.4253
A45: NOPAT | B45: =B43+B44 -> 4513.9021 | C45: =C43+C44 -> 4898.2286 | D45: =D43+D44 -> 5336.348 | E45: =E43+E44 -> 5782.0052 | F45: =F43+F44 -> 6230.8713
A46: D&A (% of Revenue) | B46: 0.022 | C46: 0.022 | D46: 0.021 | E46: 0.021 | F46: 0.02
A47: Add: D&A | B47: =B41*B46 -> 727.51536 | C47: =C41*C46 -> 767.5287 | D47: =D41*D46 -> 776.5995 | E47: =E41*E46 -> 819.31247 | F47: =F41*F46 -> 819.31247
A48: CapEx (% of Revenue) | B48: 0.02 | C48: 0.02 | D48: 0.019 | E48: 0.019 | F48: 0.018
A49: Less: CapEx | B49: =-B41*B48 -> -661.3776 | C49: =-C41*C48 -> -697.75337 | D49: =-D41*D48 -> -702.63764 | E49: =-E41*E48 -> -741.28271 | F49: =-F41*F48 -> -737.38122
A50: NWC Change (% of Rev Δ) | B50: 0.03 | C50: 0.03 | D50: 0.03 | E50: 0.03 | F50: 0.03
A51: Less: Change in NWC | B51: =-(B41-F29)*B50 -> -38.1564 | C51: =-(C41-B41)*C50 -> -54.563652 | D51: =-(D41-C41)*D50 -> -62.797803 | E51: =-(E41-D41)*E50 -> -61.018532 | F51: =-(F41-E41)*F50 -> -58.522319
A52: Unlevered Free Cash Flow | B52: =B45+B47+B49+B51 -> 4541.8835 | C52: =C45+C47+C49+C51 -> 4913.4403 | D52: =D45+D47+D49+D51 -> 5347.512 | E52: =E45+E47+E49+E51 -> 5799.0164 | F52: =F45+F47+F49+F51 -> 6254.2803
A54: DCF VALUATION
A55: Period | B55: 1 | C55: 2 | D55: 3 | E55: 4 | F55: 5
A56: Discount Factor | B56: =1/((1+$B$15)^B55) -> 0.91212913 | C56: =1/((1+$B$15)^C55) -> 0.83197955 | D56: =1/((1+$B$15)^D55) -> 0.75887278 | E56: =1/((1+$B$15)^E55) -> 0.69218997 | F56: =1/((1+$B$15)^F55) -> 0.63136663
A57: PV of FCF | B57: =B52*B56 -> 4142.7842 | C57: =C52*C56 -> 4087.8819 | D57: =D52*D56 -> 4058.0813 | E57: =E52*E56 -> 4014.021 | F57: =F52*F56 -> 3948.7439
A59: Sum of PV of FCFs | B59: =SUM(B57:F57) -> 20251.512
A61: Terminal Value Calculation
A62: Final Year FCF (2029E) | B62: =F52 -> 6254.2803
A63: Terminal Value (Gordon Growth) | B63: =B62*(1+$B$16)/($B$15-$B$16) -> 89865.387
A64: PV of Terminal Value | B64: =B63/(1+$B$15)^5 -> 56738.007
A66: VALUATION SUMMARY
A67: PV of Forecast FCFs | B67: =B59 -> 20251.512
A68: PV of Terminal Value | B68: =B64 -> 56738.007
A69: Enterprise Value (DCF) | B69: =B67+B68 -> 76989.519
A70: Less: Net Debt | B70: =-B24 -> -600
A71: Equity Value | B71: =B69+B70 -> 76389.519
A72: Shares Outstanding | B72: =B20 -> 936
A73: Implied Share Price | B73: =B71/B72 -> 81.612734
A74: Current Stock Price | B74: =B19 -> 61
A75: Upside / (Downside) | B75: =(B73-B74)/B74 -> 0.33791367
A77: Terminal Value as % of EV | B77: =B68/B69 -> 0.73695754
A78: Implied Exit EV/EBITDA | B78: =B63/(F43+F47) -> 10.203154

Sheet Sensitivity Analysis
A1: SENSITIVITY ANALYSIS - Implied Share Price
A3: WACC vs Terminal Growth Rate
A5: WACC \ TGR | B5: 0.015 | C5: 0.02 | D5: 0.025 | E5: 0.03 | F5: 0.035
A6: 0.07 | B6: =(('DCF Model'!B59+'DCF Model'!F52*(1+0.015)/(0.07-0.015)/(1+0.07)^5)-'DCF Model'!B24)/'DCF Model'!B20 -> 108.91486 | C6: =(('DCF Model'!B59+'DCF Model'!F52*(1+0.02)/(0.07-0.02)/(1+0.07)^5)-'DCF Model'!B24)/'DCF Model'!B20 -> 118.18323 | D6: =(('DCF Model'!B59+'DCF Model'!F52*(1+0.025)/(0.07-0.025)/(1+0.07)^5)-'DCF Model'!B24)/'DCF Model'!B20 -> 129.51125 | E6: =(('DCF Model'!B59+'DCF Model'!F52*(1+0.03)/(0.07-0.03)/(1+0.07)^5)-'DCF Model'!B24)/'DCF Model'!B20 -> 143.67127 | F6: =(('DCF Model'!B59+'DCF Model'!F52*(1+0.035)/(0.07-0.035)/(1+0.07)^5)-'DCF Model'!B24)/'DCF Model'!B20 -> 161.87701
A7: 0.08 | B7: =(('DCF Model'!B59+'DCF Model'!F52*(1+0.015)/(0.08-0.015)/(1+0.08)^5)-'DCF Model'!B24)/'DCF Model'!B20 -> 92.007803 | C7: =(('DCF Model'!B59+'DCF Model'!F52*(1+0.02)/(0.08-0.02)/(1+0.08)^5)-'DCF Model'!B24)/'DCF Model'!B20 -> 98.304486 | D7: =(('DCF Model'!B59+'DCF Model'!F52*(1+0.025)/(0.08-0.025)/(1+0.08)^5)-'DCF Model'!B24)/'DCF Model'!B20 -> 105.74602 | E7: =(('DCF Model'!B59+'DCF Model'!F52*(1+0.03)/(0.08-0.03)/(1+0.08)^5)-'DCF Model'!B24)/'DCF Model'!B20 -> 114.67586 | F7: =(('DCF Model'!B59+'DCF Model'!F52*(1+0.035)/(0.08-0.035)/(1+0.08)^5)-'DCF Model'!B24)/'DCF Model'!B20 -> 125.59011
A8: 0.09 | B8: =(('DCF Model'!B59+'DCF Model'!F52*(1+0.015)/(0.09-0.015)/(1+0.09)^5)-'DCF Model'!B24)/'DCF Model'!B20 -> 79.767653 | C8: =(('DCF Model'!B59+'DCF Model'!F52*(1+0.02)/(0.09-0.02)/(1+0.09)^5)-'DCF Model'!B24)/'DCF Model'!B20 -> 84.275885 | D8: =(('DCF Model'!B59+'DCF Model'!F52*(1+0.025)/(0.09-0.025)/(1+0.09)^5)-'DCF Model'!B24)/'DCF Model'!B20 -> 89.47769 | E8: =(('DCF Model'!B59+'DCF Model'!F52*(1+0.03)/(0.09-0.03)/(1+0.09)^5)-'DCF Model'!B24)/'DCF Model'!B20 -> 95.546463 | F8: =(('DCF Model'!B59+'DCF Model'!F52*(1+0.035)/(0.09-0.035)/(1+0.09)^5)-'DCF Model'!B24)/'DCF Model'!B20 -> 102.71865
A9: 0.1 | B9: =(('DCF Model'!B59+'DCF Model'!F52*(1+0.015)/(0.1-0.015)/(1+0.1)^5)-'DCF Model'!B24)/'DCF Model'!B20 -> 70.538534 | C9: =(('DCF Model'!B59+'DCF Model'!F52*(1+0.02)/(0.1-0.02)/(1+0.1)^5)-'DCF Model'!B24)/'DCF Model'!B20 -> 73.894301 | D9: =(('DCF Model'!B59+'DCF Model'!F52*(1+0.025)/(0.1-0.025)/(1+0.1)^5)-'DCF Model'!B24)/'DCF Model'!B20 -> 77.697504 | E9: =(('DCF Model'!B59+'DCF Model'!F52*(1+0.03)/(0.1-0.03)/(1+0.1)^5)-'DCF Model'!B24)/'DCF Model'!B20 -> 82.044022 | F9: =(('DCF Model'!B59+'DCF Model'!F52*(1+0.035)/(0.1-0.035)/(1+0.1)^5)-'DCF Model'!B24)/'DCF Model'!B20 -> 87.059235
A10: 0.11 | B10: =(('DCF Model'!B59+'DCF Model'!F52*(1+0.015)/(0.11-0.015)/(1+0.11)^5)-'DCF Model'!B24)/'DCF Model'!B20 -> 63.362334 | C10: =(('DCF Model'!B59+'DCF Model'!F52*(1+0.02)/(0.11-0.02)/(1+0.11)^5)-'DCF Model'!B24)/'DCF Model'!B20 -> 65.936363 | D10: =(('DCF Model'!B59+'DCF Model'!F52*(1+0.025)/(0.11-0.025)/(1+0.11)^5)-'DCF Model'!B24)/'DCF Model'!B20 -> 68.813219 | E10: =(('DCF Model'!B59+'DCF Model'!F52*(1+0.03)/(0.11-0.03)/(1+0.11)^5)-'DCF Model'!B24)/'DCF Model'!B20 -> 72.049683 | F10: =(('DCF Model'!B59+'DCF Model'!F52*(1+0.035)/(0.11-0.035)/(1+0.11)^5)-'DCF Model'!B24)/'DCF Model'!B20 -> 75.717674
A12: Note: Green cell = base case assumptions (9.0% WACC, 2.5% Terminal Growth)
A15: Operating Margin vs Revenue CAGR (5-Year)
A17: Margin \ Growth | B17: 0.03 | C17: 0.04 | D17: 0.05 | E17: 0.06 | F17: 0.07
A18: 0.16 | B18: 68.36 | C18: 71.39 | D18: 74.53 | E18: 77.79 | F18: 81.17
A19: 0.175 | B19: 74.83 | C19: 78.14 | D19: 81.58 | E19: 85.15 | F19: 88.84
A20: 0.19 | B20: 81.3 | C20: 84.9 | D20: 88.63 | E20: 92.5 | F20: 96.51
A21: 0.205 | B21: 87.76 | C21: 91.65 | D21: 95.68 | E21: 99.85 | F21: 104.18
A22: 0.22 | B22: 94.23 | C22: 98.4 | D22: 102.73 | E22: 107.21 | F22: 111.85

Sheet Company Overview
A1: PAYPAL HOLDINGS, INC. (NASDAQ: PYPL)
A3: COMPANY PROFILE
A4: Sector | B4: Financial Services / Fintech
A5: Industry | B5: Digital Payments / Credit Services
A6: Headquarters | B6: San Jose, California
A7: CEO | B7: Alex Chriss (since September 2023)
A8: Founded | B8: 1998 (spun off from eBay in 2015)
A9: Employees | B9: ~25,000
A10: Active Accounts | B10: 434 million (Dec 2024)
A11: Total Payment Volume (2024) | B11: $1.68 trillion
A12: 2024 Revenue | B12: $31.8 billion
A13: 2024 Free Cash Flow | B13: $6.8 billion
A16: BUSINESS SEGMENTS
A17: PayPal Checkout | B17: Core digital wallet for online/mobile merchant transactions
A18: Venmo | B18: P2P payments platform with 90M+ users, Pay with Venmo for merchants
A19: Braintree | B19: Full-stack payments for enterprise (Uber, Airbnb, Dropbox)
A20: Xoom | B20: International money transfer service
A21: Buy Now, Pay Later | B21: Short-term installment products, $33B TPV in 2024 (+21% YoY)
A22: PayPal Credit | B22: Consumer credit product in the US
A25: KEY METRICS & TRENDS
A26: Q4 2024 Revenue Growth | B26: 4% YoY ($8.4B)
A27: 2024 TPV Growth | B27: 10% YoY to $1.68 trillion
A28: Q3 2025 Revenue Growth | B28: 7% YoY ($8.4B, beat estimates)
A29: Non-GAAP EPS (Q3 2025) | B29: $1.34 (+12% YoY)
A30: Transaction Margin Trend | B30: Improving via Braintree repricing strategy
A31: Active Account Growth | B31: +8.8 million in 2024 to 434 million
A34: INVESTMENT THESIS
A35: BULL CASE
B36: • Strong FCF generation ($6.8B in 2024) supports buybacks ($15B new authorization)
B37: • AI commerce partnerships (OpenAI, Perplexity) position for agentic payments
B38: • Fastlane checkout improving conversion rates (+100bps, 40% latency reduction)
B39: • Venmo monetization accelerating (+20% debit card/Pay with Venmo growth)
B40: • Trading at 11-12x forward P/E vs historical 50x average - potential re-rating
A41: BEAR CASE
B42: • Branded checkout deceleration (management flagged slower growth Dec 2025)
B43: • Braintree repricing causing ~5pt revenue headwind in 2025
B44: • Competition from Apple Pay, Google Pay, Block (Square), traditional card networks
B45: • Interest rate sensitivity (~$150M headwind from rate cuts in 2025)
B46: • Execution risk during multi-year business transformation
A47: CATALYST WATCH
B48: • Fastlane adoption scaling in 2025
B49: • Shopify partnership integration (PayPal in Shopify Payments)
B50: • SMB market share gains via Complete Payments platform
A52: ANALYST CONSENSUS
A53: Average Price Target | B53: $84 (range $61 - $126)
A54: Consensus Rating | B54: Moderate Buy / Hold
A55: 2025E Revenue | B55: $34.0 billion (+7%)
A56: 2025E EPS | B56: $5.45
A57: 2026E Revenue | B57: $35.9 billion (+6%)
A58: 2026E EPS | B58: $5.95
