Workbook
Name pubhtml: 'MKT CAP - Price'!$A$1

Sheet Template
S1: input cells
B2: Name | C2: LINK TO RESEARCH | S2: result cells
B3: STOCK PRICE | C3: ='COMPARATIVE TABLE'!C39 -> 226.79 | F3: DIVIDEND PAYOUT RATIO | I3: 0
B4: COMPARATIVE TABLE'!A1 | N4: Terminal Value | O4: Growth rate
B5: Scenario 1 | C5: Earnings per share | D5: 2025 | E5: =D5+1 -> 2026 | F5: =E5+1 -> 2027 | G5: =F5+1 -> 2028 | H5: =G5+1 -> 2029 | I5: =H5+1 -> 2030 | J5: =I5+1 -> 2031 | K5: =J5+1 -> 2032 | L5: =K5+1 -> 2033 | M5: =L5+1 -> 2034 | N5: 2034 | O5: 0 | P5: next 5 years
B6: normal case | C6: 0 | D6: =C6*(1+$O$5) -> 0 | E6: =D6*(1+$O$5) -> 0 | F6: =E6*(1+$O$5) -> 0 | G6: =F6*(1+$O$5) -> 0 | H6: =G6*(1+$O$5) -> 0 | I6: =H6*(1+$O$6) -> 0 | J6: =I6*(1+$O$6) -> 0 | K6: =J6*(1+$O$6) -> 0 | L6: =K6*(1+$O$6) -> 0 | M6: =L6*(1+$O$6) -> 0 | N6: =L6*O8 -> 0 | O6: 0 | P6: 5 to 10 years
C7: =CONCATENATE(R8,O7*100,S8) -> PV(10%) | D7: =D6*(1+$O$7)^($D$5-D5-1)*$I$3 -> 0 | E7: =E6*(1+$O$7)^($D$5-E5-1)*$I$3 -> 0 | F7: =F6*(1+$O$7)^($D$5-F5-1)*$I$3 -> 0 | G7: =G6*(1+$O$7)^($D$5-G5-1)*$I$3 -> 0 | H7: =H6*(1+$O$7)^($D$5-H5-1)*$I$3 -> 0 | I7: =I6*(1+$O$7)^($D$5-I5-1)*$I$3 -> 0 | J7: =J6*(1+$O$7)^($D$5-J5-1)*$I$3 -> 0 | K7: =K6*(1+$O$7)^($D$5-K5-1)*$I$3 -> 0 | ... M7: =M6*(1+$O$7)^($D$5-M5-1)*$I$3 -> 0 | N7: =N6*(1+$O$7)^($D$5-N5-1) -> 0 | O7: 0.1 | P7: Discount rate
C8: INTRINSIC VALUE | D8: =SUM(D7:N7) -> 0 | O8: 15 | P8: Terminal multiple | R8: PV( | S8: %)
N10: Terminal Value | O10: Growth rate
B11: Scenario 2 | C11: =C5 -> Earnings per share | D11: =D5 -> 2025 | E11: =D11+1 -> 2026 | F11: =E11+1 -> 2027 | G11: =F11+1 -> 2028 | H11: =G11+1 -> 2029 | I11: =H11+1 -> 2030 | J11: =I11+1 -> 2031 | K11: =J11+1 -> 2032 | L11: =K11+1 -> 2033 | M11: =L11+1 -> 2034 | N11: =N5 -> 2034 | O11: 0 | P11: next 5 years
B12: best case | C12: =C6 -> 0 | D12: =C12*(1+$O$11) -> 0 | E12: =D12*(1+$O$11) -> 0 | F12: =E12*(1+$O$11) -> 0 | G12: =F12*(1+$O$11) -> 0 | H12: =G12*(1+$O$11) -> 0 | I12: =H12*(1+$O$12) -> 0 | J12: =I12*(1+$O$12) -> 0 | K12: =J12*(1+$O$12) -> 0 | L12: =K12*(1+$O$12) -> 0 | M12: =L12*(1+$O$12) -> 0 | N12: =L12*O14 -> 0 | O12: 0 | P12: 5 to 10 years
B13: =B7 -> 0 | C13: =C7 -> PV(10%) | D13: =D12*(1+$O$13)^($D$11-D11-1)*$I$3 -> 0 | E13: =E12*(1+$O$13)^($D$11-E11-1)*$I$3 -> 0 | F13: =F12*(1+$O$13)^($D$11-F11-1)*$I$3 -> 0 | G13: =G12*(1+$O$13)^($D$11-G11-1)*$I$3 -> 0 | H13: =H12*(1+$O$13)^($D$11-H11-1)*$I$3 -> 0 | I13: =I12*(1+$O$13)^($D$11-I11-1)*$I$3 -> 0 | J13: =J12*(1+$O$13)^($D$11-J11-1)*$I$3 -> 0 | K13: =K12*(1+$O$13)^($D$11-K11-1)*$I$3 -> 0 | ... M13: =M12*(1+$O$13)^($D$11-M11-1)*$I$3 -> 0 | N13: =N12*(1+$O$7)^($D$5-N11-1) -> 0 | O13: =O7 -> 0.1 | P13: Discount rate
C14: Present value sum | D14: =SUM(D13:N13) -> 0 | O14: 20 | P14: Terminal multiple
N16: Terminal Value | O16: Growth rate
B17: Scenario 3 | C17: =C11 -> Earnings per share | D17: =D11 -> 2025 | E17: =D17+1 -> 2026 | F17: =E17+1 -> 2027 | G17: =F17+1 -> 2028 | H17: =G17+1 -> 2029 | I17: =H17+1 -> 2030 | J17: =I17+1 -> 2031 | K17: =J17+1 -> 2032 | L17: =K17+1 -> 2033 | M17: =L17+1 -> 2034 | N17: =N11 -> 2034 | O17: 0 | P17: next 5 years
B18: worst case | C18: =C12 -> 0 | D18: =C18*(1+$O$17) -> 0 | E18: =D18*(1+$O$17) -> 0 | F18: =E18*(1+$O$17) -> 0 | G18: =F18*(1+$O$17) -> 0 | H18: =G18*(1+$O$17) -> 0 | I18: =H18*(1+$O$18) -> 0 | J18: =I18*(1+$O$18) -> 0 | K18: =J18*(1+$O$18) -> 0 | L18: =K18*(1+$O$18) -> 0 | M18: =L18*(1+$O$18) -> 0 | N18: =L18*O20 -> 0 | O18: 0 | P18: 5 to 10 years
B19: MARGIN OF | C19: =C13 -> PV(10%) | D19: =D18*(1+$O$19)^($D$17-D17-1)*$I$3 -> 0 | E19: =E18*(1+$O$19)^($D$17-E17-1)*$I$3 -> 0 | F19: =F18*(1+$O$19)^($D$17-F17-1)*$I$3 -> 0 | G19: =G18*(1+$O$19)^($D$17-G17-1)*$I$3 -> 0 | H19: =H18*(1+$O$19)^($D$17-H17-1)*$I$3 -> 0 | I19: =I18*(1+$O$19)^($D$17-I17-1)*$I$3 -> 0 | J19: =J18*(1+$O$19)^($D$17-J17-1)*$I$3 -> 0 | K19: =K18*(1+$O$19)^($D$17-K17-1)*$I$3 -> 0 | ... M19: =M18*(1+$O$19)^($D$17-M17-1)*$I$3 -> 0 | N19: =N18*(1+$O$19)^($D$17-N17-1) -> 0 | O19: =O13 -> 0.1 | P19: Discount rate
B20: SAFETY | C20: Present value sum | D20: =SUM(D19:N19) -> 0 | O20: 10 | P20: Terminal multiple
C22: Scenario | D22: Probability | E22: PV | F22: Part
C23: Scenario 1 (normal case) | D23: 0.34 | E23: =D8 -> 0 | F23: =E23*D23 -> 0
C24: Scenario 2 (best case) | D24: 0.33 | E24: =D14 -> 0 | F24: =E24*D24 -> 0
C25: Scenario 3 (worst case) | D25: 0.33 | E25: =D20 -> 0 | F25: =E25*D25 -> 0
C26: STOCK PRICE NOW | D26: =C3 -> 226.79 | E26: Sum | F26: =SUM(F23:F25) -> 0
B28: Disclaimer: This is just for educational purposes and not for investing advice!
B30: MADE BY | C30: STOCK MARKET RESEARCH PLATFORM

Sheet COMPARATIVE TABLE
A1: STOCK | B1: TICKER | C1: Stock Price/MKT Cap | D1: 10% RETURN | E1: Ratio | F1: LINK to RESEARCH | G1: INTRINSIC | H1: UPDATED | I1: TYPE | J1: Comment | K1: MAIN RISK & MARGIN OF SAFETY (MOS) REQUIREMENT FOR RISKS (MOS IS ALWAYS LOW PRICE - if BUY, ok) | L1: Strategy | M1: WOULD I BUY THIS AT A CERTAIN PRICE (what to think about deeper in such a case)
A2: THIS IS JUST AN OVERVIEW, NOT INVESTMENT ADVICE! THIS IS JUST FOR EDUCATIONAL PURPOSES TO SHOW WHAT IS PRICED IN BY THE MARKET AND WHAT GROWTH OR DIVIDENDS SHOULD BE REACHED FOR A IMMAGINARY RETURN - IN THIS CASE 10%
A3: AHOLD | B3: AMS:AD | C3: ='MKT CAP - Price'!D4 -> 34.42 | D3: =Ahold!F26 -> 23.937824 | E3: =D3/C3 -> 0.69546262 | F3: https://sven-carlin-research-platform.teachable.com/courses/335443/lectures/45225403 | G3: Ahold!A1 | H3: 45839 | I3: Slow growth | J3: A good US/Dutch retailer but pricy | K3: Retail, recessions in US and Europe
A4: Alibaba | B4: BABA | C4: ='MKT CAP - Price'!C98 -> 143.93 | D4: =BABA!F26 -> 95.030015 | E4: =D4/C4 -> 0.66025162 | F4: https://sven-carlin-research-platform.teachable.com/courses/335443/lectures/43880623 | G4: BABA!A1 | H4: 45901 | I4: Growth | J4: China e-commerce/fintech/cloud with global scaling ambitions | K4: China
A5: ACOMO | B5: ACOMO | C5: ='MKT CAP - Price'!C99 -> 22.9 | D5: =ACOMO!F26 -> 22.436316 | E5: =D5/C5 -> 0.97975179 | F5: https://sven-carlin-research-platform.teachable.com/courses/335443/lectures/44136947 | G5: ACOMO!A1 | H5: 45901 | I5: Food | J5: European spice trader | K5: Dutch stock market
A6: Archer Daniels | B6: ADM | C6: ='MKT CAP - Price'!E91 -> 61.41 | D6: =ADM!F26 -> 38.188779 | E6: =D6/C6 -> 0.6218658 | F6: https://sven-carlin-research-platform.teachable.com/courses/335443/lectures/59274915 | G6: ADM!A1 | H6: 45901 | I6: Food | J6: Cyclical, global food processing company
A7: AKER BP | C7: ='MKT CAP - Price'!C127 -> 25.11 | D7: =AKER!F26 -> 27.784211 | E7: =D7/C7 -> 1.1064998 | G7: AKER!A1 | H7: 45901 | I7: Oil | J7: Low cost producer
A8: ABF | B8: LSE: ABF | C8: ='MKT CAP - Price'!C100 -> 1997 | D8: =ABF!F26 -> 1275.3724 | E8: =D8/C8 -> 0.63864414 | F8: https://sven-carlin-research-platform.teachable.com/courses/335443/lectures/47872443 | G8: ABF!A1 | H8: 45901 | I8: food-other | J8: Food and Primark
A9: Berkshire | B9: BRK | C9: ='MKT CAP - Price'!J6 -> 1061.6746 | D9: =BRK.B!F26 -> 460.39879 | E9: =D9/C9 -> 0.43365341 | F9: https://sven-carlin-research-platform.teachable.com/courses/335443/lectures/44788692 | G9: BRK.B!A1 | H9: 45901 | I9: Buffett | J9: The fortress…
A10: Brasilagro | B10: LND | C10: ='MKT CAP - Price'!C101 -> 3.88 | D10: =LND!F26 -> 3.3544476 | E10: =D10/C10 -> 0.86454836 | F10: https://sven-carlin-research-platform.teachable.com/courses/335443/lectures/58576359 | G10: LND!A1 | H10: 45901 | I10: Land | J10: Land ownership in Brazil
A11: Cembre | B11: BIT:CMB | C11: ='MKT CAP - Price'!C102 -> 60.2 | D11: =CEMBRE!F26 -> 31.276446 | E11: =D11/C11 -> 0.51954229 | F11: https://sven-carlin-research-platform.teachable.com/courses/335443/lectures/45991763 | G11: CEMBRE!A1 | H11: 45901 | I11: Ita industrial | J11: Italy industrial
A12: China Mobile | B12: 941 | C12: ='MKT CAP - Price'!C103 -> 87.5 | D12: =CHM!F26 -> 88.630037 | E12: =D12/C12 -> 1.0129147 | F12: https://sven-carlin-research-platform.teachable.com/courses/335443/lectures/45806485 | G12: CHM!A1 | H12: 45901 | I12: telco | J12: China government owned telco, US SANCTIONED
A13: CK Hutchison | B13: 0001 | C13: ='MKT CAP - Price'!C104 -> 52.1 | D13: =CK!F26 -> 41.476928 | E13: =D13/C13 -> 0.79610226 | F13: https://sven-carlin-research-platform.teachable.com/courses/335443/lectures/51704170 | G13: CK!A1 | H13: 45901 | I13: mix | J13: Global conglomerate listed in HK
A14: Clarksons | B14: LON:CKN | C14: ='MKT CAP - Price'!C105 -> 3455 | D14: =Clarks!F26 -> 2297.8594 | E14: =D14/C14 -> 0.66508231 | F14: https://sven-carlin-research-platform.teachable.com/courses/335443/lectures/49464822 | G14: Clarks!A1 | H14: 45901 | I14: Shipping | J14: shipping broker, no ships
A15: First Pacific | B15: 142 | C15: ='MKT CAP - Price'!C106 -> 6.67 | D15: =FP!F26 -> 4.2143239 | E15: =D15/C15 -> 0.63183268 | F15: https://sven-carlin-research-platform.teachable.com/courses/335443/lectures/54079430 | G15: FP!A1 | H15: 45901 | I15: Phillipines | J15: Conglomerate
A16: Flow Traders | B16: AMS:FLOW | C16: ='MKT CAP - Price'!C107 -> 24.92 | D16: =FLOW!F26 -> 39.828939 | E16: =D16/C16 -> 1.598272 | F16: https://sven-carlin-research-platform.teachable.com/courses/335443/lectures/45447020 | G16: FLOW!A1 | H16: 45901 | I16: Operator | J16: Flow operators, liquidity provider and trading
A17: Glencore | B17: LON:GLEN | C17: ='MKT CAP - Price'!C124/1000000000 -> 35.194536 | D17: =GLEN!D8 -> 39.462855 | E17: =D17/C17 -> 1.1212779 | F17: https://sven-carlin-research-platform.teachable.com/courses/335443/lectures/60682625 | G17: GLEN!A1 | H17: 45901 | I17: Cyclical | J17: Cyclical commodities
A18: ICL Group | B18: ICL | C18: ='MKT CAP - Price'!C108 -> 6.25 | D18: =ICL!F26 -> 4.505649 | E18: =D18/C18 -> 0.72090383 | F18: https://sven-carlin-research-platform.teachable.com/courses/335443/lectures/57859152 | G18: ICL!A1 | H18: 45901 | I18: fertilizer | J18: Fertilizer
A19: Lanxess | C19: ='MKT CAP - Price'!C128 -> 23 | D19: =LXS!F26 -> 27.412555 | E19: =D19/C19 -> 1.1918502 | G19: LXS!A1 | H19: 45901 | I19: Chemical | J19: Cycle
A20: Liberty Global | B20: LBTYK | C20: ='MKT CAP - Price'!C109 -> 11.71 | D20: =LBTYK!F26 -> 12.740721 | E20: =D20/C20 -> 1.0880206 | F20: https://sven-carlin-research-platform.teachable.com/courses/335443/lectures/45722067 | G20: LBTYK!A1 | H20: 45901 | I20: EU/UK Telco | J20: Telco UK, Netherlands, Belgium
A21: Lundin | B21: LUNMF | C21: ='MKT CAP - Price'!C110 -> 11.76 | D21: =LUNDIN!F26 -> 5.8796968 | E21: =D21/C21 -> 0.49997422 | F21: https://sven-carlin-research-platform.teachable.com/courses/335443/lectures/52353280 | G21: LUNDIN!A1 | H21: 45901 | I21: copper | J21: Copper miner
A22: Maersk | B22: AMKBY | C22: ='MKT CAP - Price'!C111 -> 10.26 | D22: =Maersk!F26 -> 7.6169348 | E22: =D22/C22 -> 0.74239131 | F22: https://sven-carlin-research-platform.teachable.com/courses/335443/lectures/50403317 | G22: Maersk!A1 | H22: 45901 | I22: shipping | J22: Global shipping
A23: Nine Dragons | B23: 2689 | C23: ='MKT CAP - Price'!C112 -> 5.95 | D23: ='Nine D'!F26 -> 6.4341068 | E23: =D23/C23 -> 1.0813625 | F23: https://sven-carlin-research-platform.teachable.com/courses/335443/lectures/17571825 | G23: Nine D'!A1 | H23: 45901 | I23: Paper China | J23: Largest paper in China
A24: Nutrien | B24: NTR | C24: ='MKT CAP - Price'!C113 -> 57.41 | D24: =NTR!F26 -> 42.801656 | E24: =D24/C24 -> 0.74554356 | F24: https://sven-carlin-research-platform.teachable.com/courses/335443/lectures/54527058 | G24: NTR!A1 | H24: 45901 | I24: fertilizer | J24: Fertilizer
A25: Mosaic | B25: MOS | C25: ='MKT CAP - Price'!C114 -> 33.41 | D25: =MOS!F26 -> 18.826609 | E25: =D25/C25 -> 0.56350222 | F25: https://sven-carlin-research-platform.teachable.com/courses/335443/lectures/54527058 | G25: MOS!A1 | H25: 45901 | I25: fertilizer | J25: Fertilizer
A26: RHI Magnesita | B26: LON:RHIM | C26: ='MKT CAP - Price'!C115 -> 2085 | D26: =RHIM!F26 -> 2594.4344 | E26: =D26/C26 -> 1.2443331 | F26: https://sven-carlin-research-platform.teachable.com/courses/335443/lectures/49610686 | G26: RHIM!A1 | H26: 45901 | I26: refraction | J26: Global refraction
A27: Rubis | B27: EPA: RUI | C27: ='MKT CAP - Price'!C116 -> 28.16 | D27: =RUI!F26 -> 26.367784 | E27: =D27/C27 -> 0.93635596 | F27: https://sven-carlin-research-platform.teachable.com/courses/335443/lectures/54002769 | G27: RUI!A1 | H27: 45901 | I27: oil distribution | J27: Africa Carribean oil distribution, French solar
A28: Signify | B28: AMS: LIGHT | C28: ='MKT CAP - Price'!M5 -> 23.06 | D28: =LIGHT!F26 -> 25.404899 | E28: =D28/C28 -> 1.1016869 | F28: https://sven-carlin-research-platform.teachable.com/courses/335443/lectures/59805978 | G28: LIGHT!A1 | H28: 45901 | I28: Lighting | J28: cyclical downturn, but can get worse
A29: SiriusXM | B29: SIRI | C29: ='MKT CAP - Price'!C117 -> 23.81 | D29: =SIRI!F26 -> 27.632941 | E29: =D29/C29 -> 1.1605603 | F29: https://sven-carlin-research-platform.teachable.com/courses/335443/lectures/53497824 | G29: SIRI!A1 | H29: 45901 | I29: Radio | J29: US radio
A30: Sunrise | B30: SNRE | C30: ='MKT CAP - Price'!C118 -> 48.98 | D30: =SNRE!F26 -> 47.797386 | E30: =D30/C30 -> 0.97585516 | F30: https://sven-carlin-research-platform.teachable.com/courses/335443/lectures/57072847 | G30: SNRE!A1 | H30: 45901 | I30: CHF telco | J30: Swiss telco, recent spin from Liberty
A31: TITLIS | B31: TIBN | C31: ='MKT CAP - Price'!M6 -> 43.1 | D31: =TIBN!F26 -> 57.831493 | E31: =D31/C31 -> 1.341798 | F31: https://sven-carlin-research-platform.teachable.com/courses/335443/lectures/45664225 | G31: TIBN!A1 | H31: 45901 | I31: Asset | J31: Swiss Asset with growth
A32: Wilmar | B32: F34 | C32: 2.95 | D32: =Wilmar!F26 -> 2.8504033 | E32: =D32/C32 -> 0.96623839 | F32: https://sven-carlin-research-platform.teachable.com/courses/335443/lectures/45064788 | G32: Wilmar!A1 | H32: 45901 | I32: FoodAsia | J32: Asia food owned 22.5% by ADM
E33: =D33/C33 -> #DIV/0!
E34: =D34/C34 -> #DIV/0!
E35: =D35/C35 -> #DIV/0!
A38: some from the YouTube analyses I made, just for reference
A39: Apple | B39: AAPL | C39: ='MKT CAP - Price'!C45 -> 226.79 | D39: =APPLE!F26 -> 85.489249 | E39: =D39/C39 -> 0.37695335 | G39: APPLE!A1 | H39: 45658 | I39: Stalwarth | J39: Good growth stock with a strong position. | K39: As always: competition, slower than expected growth and valuation contraction based on higher interest rates - iphone cycle
A40: S&P 500 | B40: SPY | C40: ='MKT CAP - Price'!C13 -> 6522.1 | D40: ='S&P 500'!F26 -> 3351.9049 | E40: =D40/C40 -> 0.51393031 | G40: S&P 500'!A1 | H40: 45658 | I40: INDEX | J40: US index fund - good businesses but risky valuations | K40: US economy, interest rates, valuation, tech profitability etc. taxes
A41: Van Eck Gold Miners | B41: GDX | C41: ='MKT CAP - Price'!C92 -> 68.5 | D41: =GDX!F26 -> 15.79298 | E41: =D41/C41 -> 0.23055445 | F41: Gold miner vid | G41: GDX!A1 | H41: 45658 | I41: GOLD
A42: Amazon | B42: AMZN | C42: =AMZN!C3 -> 2456.4487 | D42: =AMZN!F26 -> 1261.2997 | E42: =D42/C42 -> 0.51346471 | F42: Amazon | G42: AMZN!A1 | H42: 45658 | I42: Growth
A43: McDonalds | B43: MCD | C43: ='MKT CAP - Price'!C59 -> 305.94 | D43: =MCD!F26 -> 183.69574 | E43: =D43/C43 -> 0.6004306 | F43: MCD Vid | G43: MCD!A1 | H43: 45658 | I43: Stalwarth
A44: Nestle | B44: NESN | C44: ='MKT CAP - Price'!H26 -> 73.6 | D44: =NESN!F26 -> 59.288466 | E44: =D44/C44 -> 0.80554982 | F44: Nestle Vid | G44: NESN!A1 | H44: 45658 | I44: Stalwarth
A45: Nike | B45: NKE | C45: ='MKT CAP - Price'!C93 -> 74.25 | D45: =NKE!F26 -> 45.980283 | E45: =D45/C45 -> 0.61926307 | F45: Nike Vid | G45: NKE!A1 | H45: 45658 | I45: Stalwarth
A46: DHL | B46: DHL | C46: ='MKT CAP - Price'!C94 -> 38.5 | D46: =DHL!F26 -> 36.404224 | E46: =D46/C46 -> 0.94556426 | F46: DHL Vid | G46: DHL!A1 | H46: 45658 | I46: Stalwarth
A47: Schwab div etf | B47: SCHD | C47: ='MKT CAP - Price'!C95 -> 27.5 | D47: =SCHD!F26 -> 16.396952 | E47: =D47/C47 -> 0.5962528 | F47: SCHD Vid | G47: SCHD!A1 | H47: 45658 | I47: Dividend
A48: Google | B48: GOOG | C48: =GOOG!C3 -> 239.56 | D48: =GOOG!F26 -> 144.81415 | E48: =D48/C48 -> 0.60450053 | F48: Google Vid | G48: GOOG!A1 | H48: 45658 | I48: Growth
A49: Petrobras | B49: PBR | C49: ='MKT CAP - Price'!C96 -> 12.76 | D49: =PBR!F26 -> 17.282328 | E49: =D49/C49 -> 1.3544144 | F49: PBR Vid | G49: PBR!A1 | H49: 45658 | I49: Dividend
A50: Archer Daniels | B50: ADM | C50: =ADM!C3 -> 61.41 | D50: =ADM!F26 -> 38.188779 | E50: =D50/C50 -> 0.6218658 | F50: ADM Vid | G50: ADM!A1 | H50: 45658 | I50: Stalwarth
A51: Berkshire | B51: BRK | C51: ='MKT CAP - Price'!I6/1000000000 -> 1061.6746 | D51: =BRK!F26 -> 485.74938 | E51: =D51/C51 -> 0.45753133 | G51: BRK!A1 | H51: 45658 | I51: Hedge
A52: Mondelez | B52: MDLZ | C52: ='MKT CAP - Price'!C97 -> 62.27 | D52: =MDLZ!F26 -> 38.83689 | E52: =D52/C52 -> 0.6236854 | G52: MDLZ!A1 | H52: 45658 | I52: Stalwarth
A53: Verizon | B53: VZ | C53: ='MKT CAP - Price'!C33 -> 43.49 | D53: =VZ!F26 -> 38.609236 | E53: =D53/C53 -> 0.88777274 | G53: VZ!A1 | H53: 45658 | I53: Dividend

Sheet MKT CAP - Price
A1: INTRINSIC MARKET CAPS : Sheet1
B3: KROGER | C3: 44317272466 | E3: ASML | F3: 678.1 | G3: 1.1689344 | L3: Kraft Heinz | M3: 26.65
B4: AHOLD | C4: 31247565451 | D4: 34.42 | E4: Siemens | F4: 228.8 | L4: Jdepeets | M4: 31.26
B5: MELCO RESORTS | C5: 3798660904 | E5: ADYEN | F5: 1355.4 | L5: Signify | M5: 23.06
B6: BRK | C6: 490.08 | E6: Deutsche Borse | F6: 242.6 | H6: brk market cap | I6: 1061674568342 | J6: 1061.6746 | L6: Titlis | M6: 43.1
B7: Fresenius | C7: 26663649133 | E7: Aedifica | F7: 62.15 | L7: CNH Industria | M7: 11.24
B8: FRE MED | C8: 12490612605 | E8: Akzo Nobel | F8: 60.48
B9: Google | C9: 239.56 | E9: Alfen | F9: 9.27 | H9: Google mkcap | I9: 2894200931242
B10: MSFT | C10: 3719333735495 | E10: Facebook | F10: 41.1
B11: APPLE | C11: 3365651948463 | E11: APAM | F11: 26.98
B12: NIO | C12: 96323410562 | E12: BYND | F12: 190848839
B13: S&P 500 | C13: 6522.1 | E13: ArcelorMittal | F13: 25235175553 | G13: 25.235176
B14: Tencent | C14: 5774355028500 | E14: 629.5 | F14: 17.96 | I14: 7.7867672 | J14: 741559995623
B15: TSM | C15: 260.44 | E15: B&S | F15: 496646196
B16: Kroger | C16: 44317272466 | E16: CCEP | F16: 40507719806 | G16: 40.50772
B17: SFM | C17: 13105556048 | E17: CRBN | F17: 998409763
B18: Norsk Hydro | C18: 13096476776 | E18: CTP | F18: 8627117400 | G18: 9.9349262 | H18: 130112530642
B19: BABA | C19: 143.93 | E19: KMI | F19: 27.38
B20: Tesla | C20: 1089789558075 | E20: DSM | F20: #N/A
B21: Amazon | C21: 2456448739828 | E21: Berry | F21: #N/A | G21: AMZN | H21: 347.79 | L21: da
B22: AT&T | C22: 208791218255 | E22: Bjs wholesale | F22: 97.44
B23: Ahold | C23: 31247565451 | F23: 63.2
B24: Wiener | C24: 28.6 | F24: 793.14
B25: WBA | C25: 10369413195 | F25: 793.14
B26: Nestle | C26: 189631868068 | F26: 793.14 | G26: NESN | H26: 73.6
B27: STOR CAPITAL | C27: #N/A | F27: 793.14
B28: Douglas Emmet | C28: 2747793757 | F28: 793.14
B29: Smart Centres | C29: #N/A | F29: 793.14
B30: Abbvie | C30: 211.64 | F30: 793.14
B31: BMY | C31: 47.15 | E31: ASML | F31: 793.14
B32: Merck | C32: 84.03 | E32: ASML | F32: 793.14
B33: VZ | C33: 43.49 | E33: ASML | F33: 793.14
B34: Nutrien | C34: 38710385357 | E34: ASML | F34: 793.14
B35: Chebron | C35: 323058127724 | E35: ASML | F35: 793.14
B36: Lukoil | C36: #N/A | D36: #N/A | E36: ASML | F36: 793.14
B37: Barrick Gold | C37: 356401384 | E37: ASML | F37: 793.14
B38: AngloGold | C38: 469490393524 | E38: ASML | F38: 793.14
B39: CYCP | C39: data not available to google finance | E39: ASML | F39: 793.14 | G39: 85.292648
B40: USDCNY | C40: 7.1212492 | E40: ASML | F40: 793.14
B41: baidu | C41: 291340894228 | E41: ASML | F41: 793.14
B42: MMM | C42: 153.57 | E42: ASML | F42: 793.14
B43: American Express | C43: 323.35 | E43: ASML | F43: 793.14
B44: Amgen | C44: 278.51 | E44: ASML | F44: 793.14
B45: Apple | C45: 226.79 | E45: ASML | F45: 793.14
B46: Boeing | C46: 227.52 | E46: ASML | F46: 793.14
B47: Caterpillar | C47: 422.91 | E47: ASML | F47: 793.14
B48: Chevron | C48: 153.57 | E48: ASML | F48: 793.14
B49: Cisco | C49: 68.13 | E49: ASML | F49: 793.14
B50: Coca Cola | C50: 67.82 | E50: ASML | F50: 793.14
B51: Dow | C51: 23.83 | E51: ASML | F51: 793.14
... B59: McDonalds | C59: 305.94 | E59: ASML | F59: 793.14
B60: Merch | C60: 84.03
B61: Microsoft | C61: 500.37 | D61: 3719333735495
B62: Nike | C62: 74.25
B63: P&G | C63: 157.35
B64: Salesforce | C64: 242.57
B65: Travelers | C65: 272.33
B66: UnitedHealth | C66: 346.78
B67: Verizon | C67: 43.49
B68: Visa | C68: 338.12
B69: Walgreens | C69: 222
B70: Walmart | C70: 100.41
B71: Walt Disney | C71: 115.79
B72: Markel | C72: 24301183149
B73: XIAOMI | C73: 54.7
... B81: adobe | C81: 350.16
B82: ATVI | C82: #N/A | E82: #N/A
B83: best buy | C83: 76.61
B84: WBD | C84: 12.54
B85: Unilever | C85: 113337321840
B86: DPZ | C86: 15296025312 | F86: EURUSD | G86: 1.1689344
B87: Meta Platform | C87: 751.98 | F87: EURCAD | G87: 1.622515
B88: Devro | C88: #N/A | F88: EURHKD | G88: 9.10211
B89: rubis | C89: 28.68 | F89: EURRUB | G89: 99.7123
B90: NEWMOND | C90: 86151355405 | F90: EURGBP | G90: 0.864955
B91: ADM | C91: 29505324871 | E91: 61.41 | F91: USDGBP | G91: 0.73998431
B92: Van eck GDX | C92: 68.5 | F92: USDAUD | G92: 1.512928
B93: Nike | C93: 74.25 | F93: USD BRL
B94: DHL | C94: 38.5
B95: SCHD | C95: 27.5
B96: Petrobras | C96: 12.76 | E96: 425823622293
B97: Mondelez | C97: 62.27
B98: Alibaba | C98: 143.93
B99: Acomo | C99: 22.9
B100: ABF | C100: 1997
B101: Brasilagro | C101: 3.88 | D101: 1
B102: Cembre | C102: 60.2 | D102: 2
B103: China Mobile | C103: 87.5 | D103: 3
B104: CK Hutchison | C104: 52.1 | D104: 4
B105: Clarksons | C105: 3455 | D105: 5
B106: First Pacific | C106: 6.67 | D106: 6
B107: Flow Traders | C107: 24.92 | D107: 7
B108: ICL | C108: 6.25 | D108: 8
B109: Liberty | C109: 11.71 | D109: 9
B110: Lundin | C110: 11.76 | D110: 10
B111: Maerks | C111: 10.26 | D111: 11
B112: Nine Dragons | C112: 5.95 | D112: 12
... B118: Sunrise | C118: 48.98 | D118: 18
B119: Wilmar | C119: #N/A | D119: 19
D120: 20
...

Sheet LXS
S1: input cells
B2: Name | C2: LINK TO RESEARCH | S2: result cells
B3: STOCK PRICE | C3: ='COMPARATIVE TABLE'!C39 -> 226.79 | F3: DIVIDEND PAYOUT RATIO | I3: 0.6
B4: COMPARATIVE TABLE'!A1 | N4: Terminal Value | O4: Growth rate
B5: Scenario 1 | C5: FCF | D5: 2025 | E5: =D5+1 -> 2026 | F5: =E5+1 -> 2027 | G5: =F5+1 -> 2028 | H5: =G5+1 -> 2029 | I5: =H5+1 -> 2030 | J5: =I5+1 -> 2031 | K5: =J5+1 -> 2032 | L5: =K5+1 -> 2033 | M5: =L5+1 -> 2034 | N5: 2034 | O5: 0.04 | P5: next 5 years
B6: normal case | C6: 2.5 | D6: =C6*(1+$O$5) -> 2.6 | E6: =D6*(1+$O$5) -> 2.704 | F6: =E6*(1+$O$5) -> 2.81216 | G6: =F6*(1+$O$5) -> 2.9246464 | H6: =G6*(1+$O$5) -> 3.0416323 | I6: =H6*(1+$O$6) -> 3.1328812 | J6: =I6*(1+$O$6) -> 3.2268677 | K6: =J6*(1+$O$6) -> 3.3236737 | L6: =K6*(1+$O$6) -> 3.4233839 | M6: =L6*(1+$O$6) -> 3.5260854 | N6: =L6*O8 -> 68.467678 | O6: 0.03 | P6: 5 to 10 years
C7: =CONCATENATE(R8,O7*100,S8) -> PV(10%) | F7: =F6*(1+$O$7)^($D$5-F5-1)*$I$3 -> 1.2676905 | G7: =G6*(1+$O$7)^($D$5-G5-1)*$I$3 -> 1.1985437 | H7: =H6*(1+$O$7)^($D$5-H5-1)*$I$3 -> 1.1331686 | I7: =I6*(1+$O$7)^($D$5-I5-1)*$I$3 -> 1.0610579 | J7: =J6*(1+$O$7)^($D$5-J5-1)*$I$3 -> 0.993536 | K7: =K6*(1+$O$7)^($D$5-K5-1)*$I$3 -> 0.93031098 | L7: =L6*(1+$O$7)^($D$5-L5-1)*$I$3 -> 0.87110938 | M7: =M6*(1+$O$7)^($D$5-M5-1)*$I$3 -> 0.81567514 | N7: =N6*(1+$O$7)^($D$5-N5-1) -> 26.397254 | O7: 0.1 | P7: Discount rate
C8: INTRINSIC VALUE | D8: =SUM(D7:N7) -> 34.668346 | O8: 20 | P8: Terminal multiple | R8: PV( | S8: %)
N10: Terminal Value | O10: Growth rate
B11: Scenario 2 | C11: =C5 -> FCF | D11: =D5 -> 2025 | E11: =D11+1 -> 2026 | F11: =E11+1 -> 2027 | G11: =F11+1 -> 2028 | H11: =G11+1 -> 2029 | I11: =H11+1 -> 2030 | J11: =I11+1 -> 2031 | K11: =J11+1 -> 2032 | L11: =K11+1 -> 2033 | M11: =L11+1 -> 2034 | N11: =N5 -> 2034 | O11: 0 | P11: next 5 years
B12: best case | C12: =C6 -> 2.5 | D12: =C12*(1+$O$11) -> 2.5 | E12: =D12*(1+$O$11) -> 2.5 | F12: =E12*(1+$O$11) -> 2.5 | G12: =F12*(1+$O$11) -> 2.5 | H12: =G12*(1+$O$11) -> 2.5 | I12: =H12*(1+$O$12) -> 2.5 | J12: =I12*(1+$O$12) -> 2.5 | K12: =J12*(1+$O$12) -> 2.5 | L12: =K12*(1+$O$12) -> 2.5 | M12: =L12*(1+$O$12) -> 2.5 | N12: =L12*O14 -> 50 | O12: 0 | P12: 5 to 10 years
B13: =B7 -> 0 | C13: =C7 -> PV(10%) | D13: =D12*(1+$O$13)^($D$11-D11-1)*$I$3 -> 1.3636364 | E13: =E12*(1+$O$13)^($D$11-E11-1)*$I$3 -> 1.2396694 | F13: =F12*(1+$O$13)^($D$11-F11-1)*$I$3 -> 1.1269722 | G13: =G12*(1+$O$13)^($D$11-G11-1)*$I$3 -> 1.0245202 | H13: =H12*(1+$O$13)^($D$11-H11-1)*$I$3 -> 0.93138198 | I13: =I12*(1+$O$13)^($D$11-I11-1)*$I$3 -> 0.8467109 | J13: =J12*(1+$O$13)^($D$11-J11-1)*$I$3 -> 0.76973718 | K13: =K12*(1+$O$13)^($D$11-K11-1)*$I$3 -> 0.69976107 | ... M13: =M12*(1+$O$13)^($D$11-M11-1)*$I$3 -> 0.57831493 | N13: =N12*(1+$O$7)^($D$5-N11-1) -> 19.277164 | O13: =O7 -> 0.1 | P13: Discount rate
C14: Present value sum | D14: =SUM(D13:N13) -> 28.494015 | O14: 20 | P14: Terminal multiple
N16: Terminal Value | O16: Growth rate
B17: Scenario 3 | C17: =C11 -> FCF | D17: =D11 -> 2025 | E17: =D17+1 -> 2026 | F17: =E17+1 -> 2027 | G17: =F17+1 -> 2028 | H17: =G17+1 -> 2029 | I17: =H17+1 -> 2030 | J17: =I17+1 -> 2031 | K17: =J17+1 -> 2032 | L17: =K17+1 -> 2033 | M17: =L17+1 -> 2034 | N17: =N11 -> 2034 | O17: 0 | P17: next 5 years
B18: worst case | C18: =C12 -> 2.5 | D18: =C18*(1+$O$17) -> 2.5 | E18: =D18*(1+$O$17) -> 2.5 | F18: =E18*(1+$O$17) -> 2.5 | G18: =F18*(1+$O$17) -> 2.5 | H18: =G18*(1+$O$17) -> 2.5 | I18: =H18*(1+$O$18) -> 2.5 | J18: =I18*(1+$O$18) -> 2.5 | K18: =J18*(1+$O$18) -> 2.5 | L18: =K18*(1+$O$18) -> 2.5 | M18: =L18*(1+$O$18) -> 2.5 | N18: =L18*O20 -> 25 | O18: 0 | P18: 5 to 10 years
B19: MARGIN OF | C19: =C13 -> PV(10%) | D19: =D18*(1+$O$19)^($D$17-D17-1)*$I$3 -> 1.3636364 | E19: =E18*(1+$O$19)^($D$17-E17-1)*$I$3 -> 1.2396694 | F19: =F18*(1+$O$19)^($D$17-F17-1)*$I$3 -> 1.1269722 | G19: =G18*(1+$O$19)^($D$17-G17-1)*$I$3 -> 1.0245202 | H19: =H18*(1+$O$19)^($D$17-H17-1)*$I$3 -> 0.93138198 | I19: =I18*(1+$O$19)^($D$17-I17-1)*$I$3 -> 0.8467109 | J19: =J18*(1+$O$19)^($D$17-J17-1)*$I$3 -> 0.76973718 | K19: =K18*(1+$O$19)^($D$17-K17-1)*$I$3 -> 0.69976107 | ... M19: =M18*(1+$O$19)^($D$17-M17-1)*$I$3 -> 0.57831493 | N19: =N18*(1+$O$19)^($D$17-N17-1) -> 9.6385822 | O19: =O13 -> 0.1 | P19: Discount rate
B20: SAFETY | C20: Present value sum | D20: =SUM(D19:N19) -> 18.855433 | O20: 10 | P20: Terminal multiple
C22: Scenario | D22: Probability | E22: PV | F22: Part
C23: Scenario 1 (normal case) | D23: 0.34 | E23: =D8 -> 34.668346 | F23: =E23*D23 -> 11.787238
C24: Scenario 2 (best case) | D24: 0.33 | E24: =D14 -> 28.494015 | F24: =E24*D24 -> 9.403025
C25: Scenario 3 (worst case) | D25: 0.33 | E25: =D20 -> 18.855433 | F25: =E25*D25 -> 6.2222929
C26: STOCK PRICE NOW | D26: =C3 -> 226.79 | E26: Sum | F26: =SUM(F23:F25) -> 27.412555
B28: Disclaimer: This is just for educational purposes and not for investing advice!
B30: MADE BY | C30: STOCK MARKET RESEARCH PLATFORM

Sheet AKER
S1: input cells
B2: AKER | C2: LINK TO RESEARCH | S2: result cells
B3: STOCK PRICE | F3: DIVIDEND PAYOUT RATIO | I3: 0.75 | J3: Norway tax
B4: COMPARATIVE TABLE'!A1 | N4: Terminal Value | O4: Growth rate
B5: Scenario 1 | C5: Dividend | D5: 2025 | E5: =D5+1 -> 2026 | F5: =E5+1 -> 2027 | G5: =F5+1 -> 2028 | H5: =G5+1 -> 2029 | I5: =H5+1 -> 2030 | J5: =I5+1 -> 2031 | K5: =J5+1 -> 2032 | L5: =K5+1 -> 2033 | M5: =L5+1 -> 2034 | N5: 2034 | O5: 0.05 | P5: next 5 years
B6: normal case | C6: 2.52 | D6: =C6*(1+$O$5) -> 2.646 | E6: =D6*(1+$O$5) -> 2.7783 | F6: =E6*(1+$O$5) -> 2.917215 | G6: =F6*(1+$O$5) -> 3.0630758 | H6: =G6*(1+$O$5) -> 3.2162295 | I6: =H6*(1+$O$6) -> 3.2162295 | J6: =I6*(1+$O$6) -> 3.2162295 | K6: =J6*(1+$O$6) -> 3.2162295 | L6: =K6*(1+$O$6) -> 3.2162295 | M6: =L6*(1+$O$6) -> 3.2162295 | N6: =L6*O8 -> 32.162295 | O6: 0 | P6: 5 to 10 years
C7: =CONCATENATE(R8,O7*100,S8) -> PV(10%) | D7: =D6*(1+$O$7)^($D$5-D5-1)*$I$3 -> 1.8040909 | E7: =E6*(1+$O$7)^($D$5-E5-1)*$I$3 -> 1.7220868 | F7: =F6*(1+$O$7)^($D$5-F5-1)*$I$3 -> 1.6438101 | G7: =G6*(1+$O$7)^($D$5-G5-1)*$I$3 -> 1.5690915 | H7: =H6*(1+$O$7)^($D$5-H5-1)*$I$3 -> 1.4977691 | I7: =I6*(1+$O$7)^($D$5-I5-1)*$I$3 -> 1.3616083 | J7: =J6*(1+$O$7)^($D$5-J5-1)*$I$3 -> 1.2378257 | K7: =K6*(1+$O$7)^($D$5-K5-1)*$I$3 -> 1.1252961 | ... M7: =M6*(1+$O$7)^($D$5-M5-1)*$I$3 -> 0.92999679 | N7: =N6*(1+$O$7)^($D$5-N5-1) -> 12.399957 | O7: 0.1 | P7: Discount rate
C8: INTRINSIC VALUE | D8: =SUM(D7:N7) -> 26.314529 | O8: 10 | P8: Terminal multiple | R8: PV( | S8: %)
N10: Terminal Value | O10: Growth rate
B11: Scenario 2 | C11: =C5 -> Dividend | D11: =D5 -> 2025 | E11: =D11+1 -> 2026 | F11: =E11+1 -> 2027 | G11: =F11+1 -> 2028 | H11: =G11+1 -> 2029 | I11: =H11+1 -> 2030 | J11: =I11+1 -> 2031 | K11: =J11+1 -> 2032 | L11: =K11+1 -> 2033 | M11: =L11+1 -> 2034 | N11: =N5 -> 2034 | O11: 0.07 | P11: next 5 years
B12: best case | C12: =C6 -> 2.52 | D12: =C12*(1+$O$11) -> 2.6964 | E12: =D12*(1+$O$11) -> 2.885148 | F12: =E12*(1+$O$11) -> 3.0871084 | G12: =F12*(1+$O$11) -> 3.3032059 | H12: =G12*(1+$O$11) -> 3.5344304 | I12: =H12*(1+$O$12) -> 3.7111519 | J12: =I12*(1+$O$12) -> 3.8967095 | K12: =J12*(1+$O$12) -> 4.0915449 | L12: =K12*(1+$O$12) -> 4.2961222 | M12: =L12*(1+$O$12) -> 4.5109283 | N12: =L12*O14 -> 51.553466 | O12: 0.05 | P12: 5 to 10 years
B13: =B7 -> 0 | C13: =C7 -> PV(10%) | D13: =D12*(1+$O$13)^($D$11-D11-1)*$I$3 -> 1.8384545 | E13: =E12*(1+$O$13)^($D$11-E11-1)*$I$3 -> 1.7883149 | F13: =F12*(1+$O$13)^($D$11-F11-1)*$I$3 -> 1.7395427 | G13: =G12*(1+$O$13)^($D$11-G11-1)*$I$3 -> 1.6921006 | H13: =H12*(1+$O$13)^($D$11-H11-1)*$I$3 -> 1.6459524 | I13: =I12*(1+$O$13)^($D$11-I11-1)*$I$3 -> 1.5711364 | J13: =J12*(1+$O$13)^($D$11-J11-1)*$I$3 -> 1.4997211 | K13: =K12*(1+$O$13)^($D$11-K11-1)*$I$3 -> 1.4315519 | ... M13: =M12*(1+$O$13)^($D$11-M11-1)*$I$3 -> 1.3043686 | N13: =N12*(1+$O$7)^($D$5-N11-1) -> 19.876093 | O13: =O7 -> 0.1 | P13: Discount rate
C14: Present value sum | D14: =SUM(D13:N13) -> 35.753717 | O14: 12 | P14: Terminal multiple
N16: Terminal Value | O16: Growth rate
B17: Scenario 3 | C17: =C11 -> Dividend | D17: =D11 -> 2025 | E17: =D17+1 -> 2026 | F17: =E17+1 -> 2027 | G17: =F17+1 -> 2028 | H17: =G17+1 -> 2029 | I17: =H17+1 -> 2030 | J17: =I17+1 -> 2031 | K17: =J17+1 -> 2032 | L17: =K17+1 -> 2033 | M17: =L17+1 -> 2034 | N17: =N11 -> 2034 | O17: 0 | P17: next 5 years
B18: worst case | C18: =C12 -> 2.52 | D18: =C18*(1+$O$17) -> 2.52 | E18: =D18*(1+$O$17) -> 2.52 | F18: =E18*(1+$O$17) -> 2.52 | G18: =F18*(1+$O$17) -> 2.52 | H18: =G18*(1+$O$17) -> 2.52 | I18: =H18*(1+$O$18) -> 2.52 | J18: =I18*(1+$O$18) -> 2.52 | K18: =J18*(1+$O$18) -> 2.52 | L18: =K18*(1+$O$18) -> 2.52 | M18: =L18*(1+$O$18) -> 2.52 | N18: =L18*O20 -> 25.2 | O18: 0 | P18: 5 to 10 years
B19: MARGIN OF | C19: =C13 -> PV(10%) | D19: =D18*(1+$O$19)^($D$17-D17-1)*$I$3 -> 1.7181818 | E19: =E18*(1+$O$19)^($D$17-E17-1)*$I$3 -> 1.5619835 | F19: =F18*(1+$O$19)^($D$17-F17-1)*$I$3 -> 1.419985 | G19: =G18*(1+$O$19)^($D$17-G17-1)*$I$3 -> 1.2908954 | H19: =H18*(1+$O$19)^($D$17-H17-1)*$I$3 -> 1.1735413 | I19: =I18*(1+$O$19)^($D$17-I17-1)*$I$3 -> 1.0668557 | J19: =J18*(1+$O$19)^($D$17-J17-1)*$I$3 -> 0.96986884 | K19: =K18*(1+$O$19)^($D$17-K17-1)*$I$3 -> 0.88169895 | ... M19: =M18*(1+$O$19)^($D$17-M17-1)*$I$3 -> 0.72867682 | N19: =N18*(1+$O$19)^($D$17-N17-1) -> 9.7156909 | O19: =O13 -> 0.1 | P19: Discount rate
B20: SAFETY | C20: Present value sum | D20: =SUM(D19:N19) -> 21.328923 | O20: 10 | P20: Terminal multiple
C22: Scenario | D22: Probability | E22: PV | F22: Part
C23: Scenario 1 (normal case) | D23: 0.34 | E23: =D8 -> 26.314529 | F23: =E23*D23 -> 8.9469398
C24: Scenario 2 (best case) | D24: 0.33 | E24: =D14 -> 35.753717 | F24: =E24*D24 -> 11.798727
C25: Scenario 3 (worst case) | D25: 0.33 | E25: =D20 -> 21.328923 | F25: =E25*D25 -> 7.0385445
C26: STOCK PRICE NOW | D26: =C3 -> 0 | E26: Sum | F26: =SUM(F23:F25) -> 27.784211
B28: Disclaimer: This is just for educational purposes and not for investing advice!
B30: MADE BY | C30: STOCK MARKET RESEARCH PLATFORM

Sheet Ahold
S1: input cells
B2: Ahold | C2: LINK TO RESEARCH | S2: result cells
B3: STOCK PRICE | C3: ='COMPARATIVE TABLE'!C3 -> 34.42 | F3: DIVIDEND PAYOUT RATIO | I3: 1
B4: COMPARATIVE TABLE'!A1 | N4: Terminal Value | O4: Growth rate
B5: Scenario 1 | C5: Dividend | D5: 2025 | E5: =D5+1 -> 2026 | F5: =E5+1 -> 2027 | G5: =F5+1 -> 2028 | H5: =G5+1 -> 2029 | I5: =H5+1 -> 2030 | J5: =I5+1 -> 2031 | K5: =J5+1 -> 2032 | L5: =K5+1 -> 2033 | M5: =L5+1 -> 2034 | N5: 2034 | O5: 0.05 | P5: next 5 years
B6: normal case | C6: 1.17 | D6: =C6*(1+$O$5) -> 1.2285 | E6: =D6*(1+$O$5) -> 1.289925 | F6: =E6*(1+$O$5) -> 1.3544213 | G6: =F6*(1+$O$5) -> 1.4221423 | H6: =G6*(1+$O$5) -> 1.4932494 | I6: =H6*(1+$O$6) -> 1.5679119 | J6: =I6*(1+$O$6) -> 1.6463075 | K6: =J6*(1+$O$6) -> 1.7286229 | L6: =K6*(1+$O$6) -> 1.815054 | M6: =L6*(1+$O$6) -> 1.9058067 | N6: =L6*O8 -> 36.30108 | O6: 0.05 | P6: 5 to 10 years
C7: =CONCATENATE(R8,O7*100,S8) -> PV(10%) | D7: =D6*(1+$O$7)^($D$5-D5-1)*$I$3 -> 1.1168182 | E7: =E6*(1+$O$7)^($D$5-E5-1)*$I$3 -> 1.0660537 | F7: =F6*(1+$O$7)^($D$5-F5-1)*$I$3 -> 1.0175967 | G7: =G6*(1+$O$7)^($D$5-G5-1)*$I$3 -> 0.97134233 | H7: =H6*(1+$O$7)^($D$5-H5-1)*$I$3 -> 0.92719041 | I7: =I6*(1+$O$7)^($D$5-I5-1)*$I$3 -> 0.88504539 | J7: =J6*(1+$O$7)^($D$5-J5-1)*$I$3 -> 0.84481606 | K7: =K6*(1+$O$7)^($D$5-K5-1)*$I$3 -> 0.80641533 | ... M7: =M6*(1+$O$7)^($D$5-M5-1)*$I$3 -> 0.73477099 | N7: =N6*(1+$O$7)^($D$5-N5-1) -> 13.995638 | O7: 0.1 | P7: Discount rate
C8: INTRINSIC VALUE | D8: =SUM(D7:N7) -> 23.135447 | O8: 20 | P8: Terminal multiple | R8: PV( | S8: %)
N10: Terminal Value | O10: Growth rate
B11: Scenario 2 | C11: =C5 -> Dividend | D11: =D5 -> 2025 | E11: =D11+1 -> 2026 | F11: =E11+1 -> 2027 | G11: =F11+1 -> 2028 | H11: =G11+1 -> 2029 | I11: =H11+1 -> 2030 | J11: =I11+1 -> 2031 | K11: =J11+1 -> 2032 | L11: =K11+1 -> 2033 | M11: =L11+1 -> 2034 | N11: =N5 -> 2034 | O11: 0.06 | P11: next 5 years
B12: best case | C12: =C6 -> 1.17 | D12: =C12*(1+$O$11) -> 1.2402 | E12: =D12*(1+$O$11) -> 1.314612 | F12: =E12*(1+$O$11) -> 1.3934887 | G12: =F12*(1+$O$11) -> 1.477098 | H12: =G12*(1+$O$11) -> 1.5657239 | I12: =H12*(1+$O$12) -> 1.6596674 | J12: =I12*(1+$O$12) -> 1.7592474 | K12: =J12*(1+$O$12) -> 1.8648022 | L12: =K12*(1+$O$12) -> 1.9766904 | M12: =L12*(1+$O$12) -> 2.0952918 | N12: =L12*O14 -> 65.230783 | O12: 0.06 | P12: 5 to 10 years
B13: =B7 -> 0 | C13: =C7 -> PV(10%) | D13: =D12*(1+$O$13)^($D$11-D11-1)*$I$3 -> 1.1274545 | E13: =E12*(1+$O$13)^($D$11-E11-1)*$I$3 -> 1.0864562 | F13: =F12*(1+$O$13)^($D$11-F11-1)*$I$3 -> 1.0469487 | G13: =G12*(1+$O$13)^($D$11-G11-1)*$I$3 -> 1.0088778 | H13: =H12*(1+$O$13)^($D$11-H11-1)*$I$3 -> 0.97219137 | I13: =I12*(1+$O$13)^($D$11-I11-1)*$I$3 -> 0.93683896 | J13: =J12*(1+$O$13)^($D$11-J11-1)*$I$3 -> 0.90277209 | K13: =K12*(1+$O$13)^($D$11-K11-1)*$I$3 -> 0.86994401 | ... M13: =M12*(1+$O$13)^($D$11-M11-1)*$I$3 -> 0.80782569 | N13: =N12*(1+$O$7)^($D$5-N11-1) -> 25.14929 | O13: =O7 -> 0.1 | P13: Discount rate
C14: Present value sum | D14: =SUM(D13:N13) -> 34.74691 | O14: 33 | P14: Terminal multiple
N16: Terminal Value | O16: Growth rate
B17: Scenario 3 | C17: =C11 -> Dividend | D17: =D11 -> 2025 | E17: =D17+1 -> 2026 | F17: =E17+1 -> 2027 | G17: =F17+1 -> 2028 | H17: =G17+1 -> 2029 | I17: =H17+1 -> 2030 | J17: =I17+1 -> 2031 | K17: =J17+1 -> 2032 | L17: =K17+1 -> 2033 | M17: =L17+1 -> 2034 | N17: =N11 -> 2034 | O17: 0 | P17: next 5 years
B18: worst case | C18: =C12 -> 1.17 | D18: =C18*(1+$O$17) -> 1.17 | E18: =D18*(1+$O$17) -> 1.17 | F18: =E18*(1+$O$17) -> 1.17 | G18: =F18*(1+$O$17) -> 1.17 | H18: =G18*(1+$O$17) -> 1.17 | I18: =H18*(1+$O$18) -> 1.17 | J18: =I18*(1+$O$18) -> 1.17 | K18: =J18*(1+$O$18) -> 1.17 | L18: =K18*(1+$O$18) -> 1.17 | M18: =L18*(1+$O$18) -> 1.17 | N18: =L18*O20 -> 17.55 | O18: 0 | P18: 5 to 10 years
B19: MARGIN OF | C19: =C13 -> PV(10%) | D19: =D18*(1+$O$19)^($D$17-D17-1)*$I$3 -> 1.0636364 | E19: =E18*(1+$O$19)^($D$17-E17-1)*$I$3 -> 0.96694215 | F19: =F18*(1+$O$19)^($D$17-F17-1)*$I$3 -> 0.87903832 | G19: =G18*(1+$O$19)^($D$17-G17-1)*$I$3 -> 0.79912574 | H19: =H18*(1+$O$19)^($D$17-H17-1)*$I$3 -> 0.72647795 | I19: =I18*(1+$O$19)^($D$17-I17-1)*$I$3 -> 0.6604345 | J19: =J18*(1+$O$19)^($D$17-J17-1)*$I$3 -> 0.600395 | K19: =K18*(1+$O$19)^($D$17-K17-1)*$I$3 -> 0.54581363 | ... M19: =M18*(1+$O$19)^($D$17-M17-1)*$I$3 -> 0.45108565 | N19: =N18*(1+$O$19)^($D$17-N17-1) -> 6.7662847 | O19: =O13 -> 0.1 | P19: Discount rate
B20: SAFETY | C20: Present value sum | D20: =SUM(D19:N19) -> 13.955428 | O20: 15 | P20: Terminal multiple
C22: Scenario | D22: Probability | E22: PV | F22: Part
C23: Scenario 1 (normal case) | D23: 0.34 | E23: =D8 -> 23.135447 | F23: =E23*D23 -> 7.866052
C24: Scenario 2 (best case) | D24: 0.33 | E24: =D14 -> 34.74691 | F24: =E24*D24 -> 11.46648
C25: Scenario 3 (worst case) | D25: 0.33 | E25: =D20 -> 13.955428 | F25: =E25*D25 -> 4.6052913
C26: STOCK PRICE NOW | D26: =C3 -> 34.42 | E26: Sum | F26: =SUM(F23:F25) -> 23.937824
B28: Disclaimer: This is just for educational purposes and not for investing advice!
B30: MADE BY | C30: STOCK MARKET RESEARCH PLATFORM

Sheet BABA
S1: input cells
B2: Alibaba | C2: LINK TO RESEARCH | S2: result cells
B3: STOCK PRICE | C3: ='COMPARATIVE TABLE'!C4 -> 143.93 | F3: DIVIDEND PAYOUT RATIO | I3: 0.2
B4: COMPARATIVE TABLE'!A1 | N4: Terminal Value | O4: Growth rate
B5: Scenario 1 | C5: FCF | D5: 2026 | E5: =D5+1 -> 2027 | F5: =E5+1 -> 2028 | G5: =F5+1 -> 2029 | H5: =G5+1 -> 2030 | I5: =H5+1 -> 2031 | J5: =I5+1 -> 2032 | K5: =J5+1 -> 2033 | L5: =K5+1 -> 2034 | M5: =L5+1 -> 2035 | N5: 2035 | O5: 0.07 | P5: next 5 years
B6: normal case | C6: 8 | D6: =C6*(1+$O$5) -> 8.56 | E6: =D6*(1+$O$5) -> 9.1592 | F6: =E6*(1+$O$5) -> 9.800344 | G6: =F6*(1+$O$5) -> 10.486368 | H6: =G6*(1+$O$5) -> 11.220414 | I6: =H6*(1+$O$6) -> 11.781435 | J6: =I6*(1+$O$6) -> 12.370506 | K6: =J6*(1+$O$6) -> 12.989032 | L6: =K6*(1+$O$6) -> 13.638483 | M6: =L6*(1+$O$6) -> 14.320407 | N6: =L6*O8 -> 204.57725 | O6: 0.05 | P6: 5 to 10 years
C7: =CONCATENATE(R8,O7*100,S8) -> PV(10%) | D7: =D6*(1+$O$7)^($D$5-D5-1)*$I$3 -> 1.5563636 | E7: =E6*(1+$O$7)^($D$5-E5-1)*$I$3 -> 1.5139174 | F7: =F6*(1+$O$7)^($D$5-F5-1)*$I$3 -> 1.4726287 | G7: =G6*(1+$O$7)^($D$5-G5-1)*$I$3 -> 1.4324661 | H7: =H6*(1+$O$7)^($D$5-H5-1)*$I$3 -> 1.3933988 | I7: =I6*(1+$O$7)^($D$5-I5-1)*$I$3 -> 1.3300625 | J7: =J6*(1+$O$7)^($D$5-J5-1)*$I$3 -> 1.2696051 | K7: =K6*(1+$O$7)^($D$5-K5-1)*$I$3 -> 1.2118958 | ... M7: =M6*(1+$O$7)^($D$5-M5-1)*$I$3 -> 1.1042274 | N7: =N6*(1+$O$7)^($D$5-N5-1) -> 78.873385 | O7: 0.1 | P7: Discount rate
C8: INTRINSIC VALUE | D8: =SUM(D7:N7) -> 92.31476 | O8: 15 | P8: Terminal multiple | R8: PV( | S8: %)
N10: Terminal Value | O10: Growth rate
B11: Scenario 2 | C11: =C5 -> FCF | D11: =D5 -> 2026 | E11: =D11+1 -> 2027 | F11: =E11+1 -> 2028 | G11: =F11+1 -> 2029 | H11: =G11+1 -> 2030 | I11: =H11+1 -> 2031 | J11: =I11+1 -> 2032 | K11: =J11+1 -> 2033 | L11: =K11+1 -> 2034 | M11: =L11+1 -> 2035 | N11: =N5 -> 2035 | O11: 0.09 | P11: next 5 years
B12: best case | C12: =C6 -> 8 | D12: =C12*(1+$O$11) -> 8.72 | E12: =D12*(1+$O$11) -> 9.5048 | F12: =E12*(1+$O$11) -> 10.360232 | G12: =F12*(1+$O$11) -> 11.292653 | H12: =G12*(1+$O$11) -> 12.308992 | I12: =H12*(1+$O$12) -> 13.047531 | J12: =I12*(1+$O$12) -> 13.830383 | K12: =J12*(1+$O$12) -> 14.660206 | L12: =K12*(1+$O$12) -> 15.539818 | M12: =L12*(1+$O$12) -> 16.472207 | N12: =L12*O14 -> 310.79637 | O12: 0.06 | P12: 5 to 10 years
B13: =B7 -> 0 | C13: =C7 -> PV(10%) | D13: =D12*(1+$O$13)^($D$11-D11-1)*$I$3 -> 1.5854545 | E13: =E12*(1+$O$13)^($D$11-E11-1)*$I$3 -> 1.5710413 | F13: =F12*(1+$O$13)^($D$11-F11-1)*$I$3 -> 1.5567591 | G13: =G12*(1+$O$13)^($D$11-G11-1)*$I$3 -> 1.5426068 | H13: =H12*(1+$O$13)^($D$11-H11-1)*$I$3 -> 1.5285831 | I13: =I12*(1+$O$13)^($D$11-I11-1)*$I$3 -> 1.4729982 | J13: =J12*(1+$O$13)^($D$11-J11-1)*$I$3 -> 1.4194347 | K13: =K12*(1+$O$13)^($D$11-K11-1)*$I$3 -> 1.3678189 | ... M13: =M12*(1+$O$13)^($D$11-M11-1)*$I$3 -> 1.2701498 | N13: =N12*(1+$O$7)^($D$5-N11-1) -> 119.82545 | O13: =O7 -> 0.1 | P13: Discount rate
C14: Present value sum | D14: =SUM(D13:N13) -> 134.45838 | O14: 20 | P14: Terminal multiple
N16: Terminal Value | O16: Growth rate
B17: Scenario 3 | C17: =C11 -> FCF | D17: =D11 -> 2026 | E17: =D17+1 -> 2027 | F17: =E17+1 -> 2028 | G17: =F17+1 -> 2029 | H17: =G17+1 -> 2030 | I17: =H17+1 -> 2031 | J17: =I17+1 -> 2032 | K17: =J17+1 -> 2033 | L17: =K17+1 -> 2034 | M17: =L17+1 -> 2035 | N17: =N11 -> 2035 | O17: 0.05 | P17: next 5 years
B18: worst case | C18: =C12 -> 8 | D18: =C18*(1+$O$17) -> 8.4 | E18: =D18*(1+$O$17) -> 8.82 | F18: =E18*(1+$O$17) -> 9.261 | G18: =F18*(1+$O$17) -> 9.72405 | H18: =G18*(1+$O$17) -> 10.210253 | I18: =H18*(1+$O$18) -> 10.618663 | J18: =I18*(1+$O$18) -> 11.043409 | K18: =J18*(1+$O$18) -> 11.485145 | L18: =K18*(1+$O$18) -> 11.944551 | M18: =L18*(1+$O$18) -> 12.422333 | N18: =L18*O20 -> 119.44551 | O18: 0.04 | P18: 5 to 10 years
B19: MARGIN OF | C19: =C13 -> PV(10%) | D19: =D18*(1+$O$19)^($D$17-D17-1)*$I$3 -> 1.5272727 | E19: =E18*(1+$O$19)^($D$17-E17-1)*$I$3 -> 1.4578512 | F19: =F18*(1+$O$19)^($D$17-F17-1)*$I$3 -> 1.3915853 | G19: =G18*(1+$O$19)^($D$17-G17-1)*$I$3 -> 1.3283314 | H19: =H18*(1+$O$19)^($D$17-H17-1)*$I$3 -> 1.2679527 | I19: =I18*(1+$O$19)^($D$17-I17-1)*$I$3 -> 1.1987916 | J19: =J18*(1+$O$19)^($D$17-J17-1)*$I$3 -> 1.133403 | K19: =K18*(1+$O$19)^($D$17-K17-1)*$I$3 -> 1.071581 | ... M19: =M18*(1+$O$19)^($D$17-M17-1)*$I$3 -> 0.95786945 | N19: =N18*(1+$O$19)^($D$17-N17-1) -> 46.051416 | O19: =O13 -> 0.1 | P19: Discount rate
B20: SAFETY | C20: Present value sum | D20: =SUM(D19:N19) -> 58.399186 | O20: 10 | P20: Terminal multiple
C22: Scenario | D22: Probability | E22: PV | F22: Part
C23: Scenario 1 (normal case) | D23: 0.34 | E23: =D8 -> 92.31476 | F23: =E23*D23 -> 31.387018
C24: Scenario 2 (best case) | D24: 0.33 | E24: =D14 -> 134.45838 | F24: =E24*D24 -> 44.371265
C25: Scenario 3 (worst case) | D25: 0.33 | E25: =D20 -> 58.399186 | F25: =E25*D25 -> 19.271731
C26: STOCK PRICE NOW | D26: =C3 -> 143.93 | E26: Sum | F26: =SUM(F23:F25) -> 95.030015
B28: Disclaimer: This is just for educational purposes and not for investing advice!
B30: MADE BY | C30: STOCK MARKET RESEARCH PLATFORM

Sheet ACOMO
S1: input cells
B2: ACOMO | C2: LINK TO RESEARCH | S2: result cells
B3: STOCK PRICE | C3: ='COMPARATIVE TABLE'!C5 -> 22.9 | F3: DIVIDEND PAYOUT RATIO | I3: 1
B4: COMPARATIVE TABLE'!A1 | N4: Terminal Value | O4: Growth rate
B5: Scenario 1 | C5: DIVIDEND PER SHARE | D5: 2026 | E5: =D5+1 -> 2027 | F5: =E5+1 -> 2028 | G5: =F5+1 -> 2029 | H5: =G5+1 -> 2030 | I5: =H5+1 -> 2031 | J5: =I5+1 -> 2032 | K5: =J5+1 -> 2033 | L5: =K5+1 -> 2034 | M5: =L5+1 -> 2035 | N5: 2035 | O5: 0.05 | P5: next 5 years
B6: normal case | C6: 1.3 | D6: =C6*(1+$O$5) -> 1.365 | E6: =D6*(1+$O$5) -> 1.43325 | F6: =E6*(1+$O$5) -> 1.5049125 | G6: =F6*(1+$O$5) -> 1.5801581 | H6: =G6*(1+$O$5) -> 1.659166 | I6: =H6*(1+$O$6) -> 1.7421243 | J6: =I6*(1+$O$6) -> 1.8292305 | K6: =J6*(1+$O$6) -> 1.9206921 | L6: =K6*(1+$O$6) -> 2.0167267 | M6: =L6*(1+$O$6) -> 2.117563 | N6: =L6*O8 -> 30.2509 | O6: 0.05 | P6: 5 to 10 years
C7: =CONCATENATE(R8,O7*100,S8) -> PV(10%) | D7: =D6*(1+$O$7)^($D$5-D5-1)*$I$3 -> 1.2409091 | E7: =E6*(1+$O$7)^($D$5-E5-1)*$I$3 -> 1.1845041 | F7: =F6*(1+$O$7)^($D$5-F5-1)*$I$3 -> 1.130663 | G7: =G6*(1+$O$7)^($D$5-G5-1)*$I$3 -> 1.0792693 | H7: =H6*(1+$O$7)^($D$5-H5-1)*$I$3 -> 1.0302116 | I7: =I6*(1+$O$7)^($D$5-I5-1)*$I$3 -> 0.98338377 | J7: =J6*(1+$O$7)^($D$5-J5-1)*$I$3 -> 0.93868451 | K7: =K6*(1+$O$7)^($D$5-K5-1)*$I$3 -> 0.89601703 | ... M7: =M6*(1+$O$7)^($D$5-M5-1)*$I$3 -> 0.81641221 | N7: =N6*(1+$O$7)^($D$5-N5-1) -> 11.663032 | O7: 0.1 | P7: Discount rate
C8: INTRINSIC VALUE | D8: =SUM(D7:N7) -> 21.818375 | O8: 15 | P8: Terminal multiple | R8: PV( | S8: %)
N10: Terminal Value | O10: Growth rate
B11: Scenario 2 | C11: =C5 -> DIVIDEND PER SHARE | D11: =D5 -> 2026 | E11: =D11+1 -> 2027 | F11: =E11+1 -> 2028 | G11: =F11+1 -> 2029 | H11: =G11+1 -> 2030 | I11: =H11+1 -> 2031 | J11: =I11+1 -> 2032 | K11: =J11+1 -> 2033 | L11: =K11+1 -> 2034 | M11: =L11+1 -> 2035 | N11: =N5 -> 2035 | O11: 0.07 | P11: next 5 years
B12: best case | C12: =C6 -> 1.3 | D12: =C12*(1+$O$11) -> 1.391 | E12: =D12*(1+$O$11) -> 1.48837 | F12: =E12*(1+$O$11) -> 1.5925559 | G12: =F12*(1+$O$11) -> 1.7040348 | H12: =G12*(1+$O$11) -> 1.8233172 | I12: =H12*(1+$O$12) -> 1.9509495 | J12: =I12*(1+$O$12) -> 2.0875159 | K12: =J12*(1+$O$12) -> 2.233642 | L12: =K12*(1+$O$12) -> 2.389997 | M12: =L12*(1+$O$12) -> 2.5572968 | N12: =L12*O14 -> 47.79994 | O12: 0.07 | P12: 5 to 10 years
B13: =B7 -> 0 | C13: =C7 -> PV(10%) | D13: =D12*(1+$O$13)^($D$11-D11-1)*$I$3 -> 1.2645455 | E13: =E12*(1+$O$13)^($D$11-E11-1)*$I$3 -> 1.2300579 | F13: =F12*(1+$O$13)^($D$11-F11-1)*$I$3 -> 1.1965108 | G13: =G12*(1+$O$13)^($D$11-G11-1)*$I$3 -> 1.1638787 | H13: =H12*(1+$O$13)^($D$11-H11-1)*$I$3 -> 1.1321366 | I13: =I12*(1+$O$13)^($D$11-I11-1)*$I$3 -> 1.1012601 | J13: =J12*(1+$O$13)^($D$11-J11-1)*$I$3 -> 1.0712257 | K13: =K12*(1+$O$13)^($D$11-K11-1)*$I$3 -> 1.0420105 | ... M13: =M12*(1+$O$13)^($D$11-M11-1)*$I$3 -> 0.98594861 | N13: =N12*(1+$O$7)^($D$5-N11-1) -> 18.428946 | O13: =O7 -> 0.1 | P13: Discount rate
C14: Present value sum | D14: =SUM(D13:N13) -> 29.630112 | O14: 20 | P14: Terminal multiple
N16: Terminal Value | O16: Growth rate
B17: Scenario 3 | C17: =C11 -> DIVIDEND PER SHARE | D17: =D11 -> 2026 | E17: =D17+1 -> 2027 | F17: =E17+1 -> 2028 | G17: =F17+1 -> 2029 | H17: =G17+1 -> 2030 | I17: =H17+1 -> 2031 | J17: =I17+1 -> 2032 | K17: =J17+1 -> 2033 | L17: =K17+1 -> 2034 | M17: =L17+1 -> 2035 | N17: =N11 -> 2035 | O17: 0.03 | P17: next 5 years
B18: worst case | C18: =C12 -> 1.3 | D18: =C18*(1+$O$17) -> 1.339 | E18: =D18*(1+$O$17) -> 1.37917 | F18: =E18*(1+$O$17) -> 1.4205451 | G18: =F18*(1+$O$17) -> 1.4631615 | H18: =G18*(1+$O$17) -> 1.5070563 | I18: =H18*(1+$O$18) -> 1.5070563 | J18: =I18*(1+$O$18) -> 1.5070563 | K18: =J18*(1+$O$18) -> 1.5070563 | L18: =K18*(1+$O$18) -> 1.5070563 | M18: =L18*(1+$O$18) -> 1.5070563 | N18: =L18*O20 -> 18.084676 | O18: 0 | P18: 5 to 10 years
B19: MARGIN OF | C19: =C13 -> PV(10%) | D19: =D18*(1+$O$19)^($D$17-D17-1)*$I$3 -> 1.2172727 | E19: =E18*(1+$O$19)^($D$17-E17-1)*$I$3 -> 1.1398099 | F19: =F18*(1+$O$19)^($D$17-F17-1)*$I$3 -> 1.0672766 | G19: =G18*(1+$O$19)^($D$17-G17-1)*$I$3 -> 0.99935896 | H19: =H18*(1+$O$19)^($D$17-H17-1)*$I$3 -> 0.93576339 | I19: =I18*(1+$O$19)^($D$17-I17-1)*$I$3 -> 0.85069399 | J19: =J18*(1+$O$19)^($D$17-J17-1)*$I$3 -> 0.77335817 | K19: =K18*(1+$O$19)^($D$17-K17-1)*$I$3 -> 0.70305288 | ... M19: =M18*(1+$O$19)^($D$17-M17-1)*$I$3 -> 0.58103544 | N19: =N18*(1+$O$19)^($D$17-N17-1) -> 6.9724253 | O19: =O13 -> 0.1 | P19: Discount rate
B20: SAFETY | C20: Present value sum | D20: =SUM(D19:N19) -> 15.879186 | O20: 12 | P20: Terminal multiple
C22: Scenario | D22: Probability | E22: PV | F22: Part
C23: Scenario 1 (normal case) | D23: 0.34 | E23: =D8 -> 21.818375 | F23: =E23*D23 -> 7.4182476
C24: Scenario 2 (best case) | D24: 0.33 | E24: =D14 -> 29.630112 | F24: =E24*D24 -> 9.7779371
C25: Scenario 3 (worst case) | D25: 0.33 | E25: =D20 -> 15.879186 | F25: =E25*D25 -> 5.2401315
C26: STOCK PRICE NOW | D26: =C3 -> 22.9 | E26: Sum | F26: =SUM(F23:F25) -> 22.436316
B28: Disclaimer: This is just for educational purposes and not for investing advice!
B30: MADE BY | C30: STOCK MARKET RESEARCH PLATFORM

Sheet ADM
S1: input cells
B2: ADM | C2: LINK TO RESEARCH | S2: result cells
B3: STOCK PRICE | C3: ='MKT CAP - Price'!E91 -> 61.41 | F3: DIVIDEND PAYOUT RATIO | I3: 1
B4: COMPARATIVE TABLE'!A1 | N4: Terminal Value | O4: Growth rate
B5: Scenario 1 | C5: Dividend per share | D5: 2025 | E5: =D5+1 -> 2026 | F5: =E5+1 -> 2027 | G5: =F5+1 -> 2028 | H5: =G5+1 -> 2029 | I5: =H5+1 -> 2030 | J5: =I5+1 -> 2031 | K5: =J5+1 -> 2032 | L5: =K5+1 -> 2033 | M5: =L5+1 -> 2034 | N5: 2034 | O5: 0.02 | P5: next 5 years
B6: normal case | C6: 2.04 | D6: =C6*(1+$O$5) -> 2.0808 | E6: =D6*(1+$O$5) -> 2.122416 | F6: =E6*(1+$O$5) -> 2.1648643 | G6: =F6*(1+$O$5) -> 2.2081616 | H6: =G6*(1+$O$5) -> 2.2523248 | I6: =H6*(1+$O$6) -> 2.3874643 | J6: =I6*(1+$O$6) -> 2.5307122 | K6: =J6*(1+$O$6) -> 2.6825549 | L6: =K6*(1+$O$6) -> 2.8435082 | M6: =L6*(1+$O$6) -> 3.0141187 | N6: =L6*O8 -> 56.870164 | O6: 0.06 | P6: 5 to 10 years
C7: =CONCATENATE(R8,O7*100,S8) -> PV(10%) | D7: =D6*(1+$O$7)^($D$5-D5-1)*$I$3 -> 1.8916364 | E7: =E6*(1+$O$7)^($D$5-E5-1)*$I$3 -> 1.7540628 | F7: =F6*(1+$O$7)^($D$5-F5-1)*$I$3 -> 1.6264946 | G7: =G6*(1+$O$7)^($D$5-G5-1)*$I$3 -> 1.5082041 | H7: =H6*(1+$O$7)^($D$5-H5-1)*$I$3 -> 1.3985165 | I7: =I6*(1+$O$7)^($D$5-I5-1)*$I$3 -> 1.3476614 | J7: =J6*(1+$O$7)^($D$5-J5-1)*$I$3 -> 1.2986555 | K7: =K6*(1+$O$7)^($D$5-K5-1)*$I$3 -> 1.2514317 | ... M7: =M6*(1+$O$7)^($D$5-M5-1)*$I$3 -> 1.1620732 | N7: =N6*(1+$O$7)^($D$5-N5-1) -> 21.92591 | O7: 0.1 | P7: Discount rate
C8: INTRINSIC VALUE | D8: =SUM(D7:N7) -> 36.370571 | O8: 20 | P8: Terminal multiple | R8: PV( | S8: %)
N10: Terminal Value | O10: Growth rate
B11: Scenario 2 | C11: =C5 -> Dividend per share | D11: =D5 -> 2025 | E11: =D11+1 -> 2026 | F11: =E11+1 -> 2027 | G11: =F11+1 -> 2028 | H11: =G11+1 -> 2029 | I11: =H11+1 -> 2030 | J11: =I11+1 -> 2031 | K11: =J11+1 -> 2032 | L11: =K11+1 -> 2033 | M11: =L11+1 -> 2034 | N11: =N5 -> 2034 | O11: 0.06 | P11: next 5 years
B12: best case | C12: =C6 -> 2.04 | D12: =C12*(1+$O$11) -> 2.1624 | E12: =D12*(1+$O$11) -> 2.292144 | F12: =E12*(1+$O$11) -> 2.4296726 | G12: =F12*(1+$O$11) -> 2.575453 | H12: =G12*(1+$O$11) -> 2.7299802 | I12: =H12*(1+$O$12) -> 2.893779 | J12: =I12*(1+$O$12) -> 3.0674057 | K12: =J12*(1+$O$12) -> 3.2514501 | L12: =K12*(1+$O$12) -> 3.4465371 | M12: =L12*(1+$O$12) -> 3.6533293 | N12: =L12*O14 -> 86.163427 | O12: 0.06 | P12: 5 to 10 years
B13: =B7 -> 0 | C13: =C7 -> PV(10%) | D13: =D12*(1+$O$13)^($D$11-D11-1) -> 1.9658182 | E13: =E12*(1+$O$13)^($D$11-E11-1) -> 1.8943339 | F13: =F12*(1+$O$13)^($D$11-F11-1) -> 1.825449 | G13: =G12*(1+$O$13)^($D$11-G11-1) -> 1.7590691 | H13: =H12*(1+$O$13)^($D$11-H11-1) -> 1.6951029 | I13: =I12*(1+$O$13)^($D$11-I11-1) -> 1.6334628 | J13: =J12*(1+$O$13)^($D$11-J11-1) -> 1.5740642 | K13: =K12*(1+$O$13)^($D$11-K11-1) -> 1.5168255 | ... M13: =M12*(1+$O$13)^($D$11-M11-1) -> 1.4085166 | N13: =N12*(1+$O$7)^($D$5-N11-1) -> 33.219731 | O13: =O7 -> 0.1 | P13: Discount rate
C14: Present value sum | D14: =SUM(D13:N13) -> 49.954041 | O14: 25 | P14: Terminal multiple
N16: Terminal Value | O16: Growth rate
B17: Scenario 3 | C17: =C11 -> Dividend per share | D17: =D11 -> 2025 | E17: =D17+1 -> 2026 | F17: =E17+1 -> 2027 | G17: =F17+1 -> 2028 | H17: =G17+1 -> 2029 | I17: =H17+1 -> 2030 | J17: =I17+1 -> 2031 | K17: =J17+1 -> 2032 | L17: =K17+1 -> 2033 | M17: =L17+1 -> 2034 | N17: =N11 -> 2034 | O17: 0.02 | P17: next 5 years
B18: worst case | C18: =C12 -> 2.04 | D18: =C18*(1+$O$17) -> 2.0808 | E18: =D18*(1+$O$17) -> 2.122416 | F18: =E18*(1+$O$17) -> 2.1648643 | G18: =F18*(1+$O$17) -> 2.2081616 | H18: =G18*(1+$O$17) -> 2.2523248 | I18: =H18*(1+$O$18) -> 2.2973713 | J18: =I18*(1+$O$18) -> 2.3433188 | K18: =J18*(1+$O$18) -> 2.3901851 | L18: =K18*(1+$O$18) -> 2.4379888 | M18: =L18*(1+$O$18) -> 2.4867486 | N18: =L18*O20 -> 36.569833 | O18: 0.02 | P18: 5 to 10 years
B19: MARGIN OF | C19: =C13 -> PV(10%) | D19: =D18*(1+$O$19)^($D$17-D17-1)*$I$3 -> 1.8916364 | E19: =E18*(1+$O$19)^($D$17-E17-1)*$I$3 -> 1.7540628 | F19: =F18*(1+$O$19)^($D$17-F17-1)*$I$3 -> 1.6264946 | G19: =G18*(1+$O$19)^($D$17-G17-1)*$I$3 -> 1.5082041 | H19: =H18*(1+$O$19)^($D$17-H17-1)*$I$3 -> 1.3985165 | I19: =I18*(1+$O$19)^($D$17-I17-1)*$I$3 -> 1.2968062 | J19: =J18*(1+$O$19)^($D$17-J17-1)*$I$3 -> 1.202493 | K19: =K18*(1+$O$19)^($D$17-K17-1)*$I$3 -> 1.115039 | ... M19: =M18*(1+$O$19)^($D$17-M17-1)*$I$3 -> 0.95874924 | N19: =N18*(1+$O$19)^($D$17-N17-1) -> 14.099254 | O19: =O13 -> 0.1 | P19: Discount rate
B20: SAFETY | C20: Present value sum | D20: =SUM(D19:N19) -> 27.885201 | O20: 15 | P20: Terminal multiple
C22: Scenario | D22: Probability | E22: PV | F22: Part
C23: Scenario 1 (normal case) | D23: 0.33 | E23: =D8 -> 36.370571 | F23: =E23*D23 -> 12.002289
C24: Scenario 2 (best case) | D24: 0.34 | E24: =D14 -> 49.954041 | F24: =E24*D24 -> 16.984374
C25: Scenario 3 (worst case) | D25: 0.33 | E25: =D20 -> 27.885201 | F25: =E25*D25 -> 9.2021162
C26: STOCK PRICE NOW | D26: =C3 -> 61.41 | E26: Sum | F26: =SUM(F23:F25) -> 38.188779
B28: Disclaimer: This is just for educational purposes and not for investing advice!
B30: MADE BY | C30: STOCK MARKET RESEARCH PLATFORM

Sheet ABF
S1: input cells
B2: ABF | C2: LINK TO RESEARCH | S2: result cells
B3: STOCK PRICE | C3: ='MKT CAP - Price'!C100 -> 1997 | F3: DIVIDEND PAYOUT RATIO | I3: 1
B4: COMPARATIVE TABLE'!A1 | N4: Terminal Value | O4: Growth rate
B5: Scenario 1 | C5: Dividend per share | D5: 2025 | E5: =D5+1 -> 2026 | F5: =E5+1 -> 2027 | G5: =F5+1 -> 2028 | H5: =G5+1 -> 2029 | I5: =H5+1 -> 2030 | J5: =I5+1 -> 2031 | K5: =J5+1 -> 2032 | L5: =K5+1 -> 2033 | M5: =L5+1 -> 2034 | N5: 2034 | O5: 0.05 | P5: next 5 years
B6: normal case | C6: 63 | D6: =C6*(1+$O$5) -> 66.15 | E6: =D6*(1+$O$5) -> 69.4575 | F6: =E6*(1+$O$5) -> 72.930375 | G6: =F6*(1+$O$5) -> 76.576894 | H6: =G6*(1+$O$5) -> 80.405738 | I6: =H6*(1+$O$6) -> 84.426025 | J6: =I6*(1+$O$6) -> 88.647327 | K6: =J6*(1+$O$6) -> 93.079693 | L6: =K6*(1+$O$6) -> 97.733678 | M6: =L6*(1+$O$6) -> 102.62036 | N6: =L6*O8 -> 1954.6736 | O6: 0.05 | P6: 5 to 10 years
C7: =CONCATENATE(R8,O7*100,S8) -> PV(10%) | D7: =D6*(1+$O$7)^($D$5-D5-1)*$I$3 -> 60.136364 | E7: =E6*(1+$O$7)^($D$5-E5-1)*$I$3 -> 57.402893 | F7: =F6*(1+$O$7)^($D$5-F5-1)*$I$3 -> 54.79367 | G7: =G6*(1+$O$7)^($D$5-G5-1)*$I$3 -> 52.303049 | H7: =H6*(1+$O$7)^($D$5-H5-1)*$I$3 -> 49.925637 | I7: =I6*(1+$O$7)^($D$5-I5-1)*$I$3 -> 47.65629 | J7: =J6*(1+$O$7)^($D$5-J5-1)*$I$3 -> 45.490095 | K7: =K6*(1+$O$7)^($D$5-K5-1)*$I$3 -> 43.422364 | ... M7: =M6*(1+$O$7)^($D$5-M5-1)*$I$3 -> 39.564592 | N7: =N6*(1+$O$7)^($D$5-N5-1) -> 753.61127 | O7: 0.1 | P7: Discount rate
C8: INTRINSIC VALUE | D8: =SUM(D7:N7) -> 1245.7548 | O8: 20 | P8: Terminal multiple | R8: PV( | S8: %)
N10: Terminal Value | O10: Growth rate
B11: Scenario 2 | C11: =C5 -> Dividend per share | D11: =D5 -> 2025 | E11: =D11+1 -> 2026 | F11: =E11+1 -> 2027 | G11: =F11+1 -> 2028 | H11: =G11+1 -> 2029 | I11: =H11+1 -> 2030 | J11: =I11+1 -> 2031 | K11: =J11+1 -> 2032 | L11: =K11+1 -> 2033 | M11: =L11+1 -> 2034 | N11: =N5 -> 2034 | O11: 0.07 | P11: next 5 years
B12: best case | C12: =C6 -> 63 | D12: =C12*(1+$O$11) -> 67.41 | E12: =D12*(1+$O$11) -> 72.1287 | F12: =E12*(1+$O$11) -> 77.177709 | G12: =F12*(1+$O$11) -> 82.580149 | H12: =G12*(1+$O$11) -> 88.360759 | I12: =H12*(1+$O$12) -> 94.546012 | J12: =I12*(1+$O$12) -> 101.16423 | K12: =J12*(1+$O$12) -> 108.24573 | L12: =K12*(1+$O$12) -> 115.82293 | M12: =L12*(1+$O$12) -> 123.93054 | N12: =L12*O14 -> 2895.5733 | O12: 0.07 | P12: 5 to 10 years
B13: =B7 -> 0 | C13: =C7 -> PV(10%) | D13: =D12*(1+$O$13)^($D$11-D11-1)*$I$3 -> 61.281818 | E13: =E12*(1+$O$13)^($D$11-E11-1)*$I$3 -> 59.610496 | F13: =F12*(1+$O$13)^($D$11-F11-1)*$I$3 -> 57.984755 | G13: =G12*(1+$O$13)^($D$11-G11-1)*$I$3 -> 56.403353 | H13: =H12*(1+$O$13)^($D$11-H11-1)*$I$3 -> 54.865079 | I13: =I12*(1+$O$13)^($D$11-I11-1)*$I$3 -> 53.368759 | J13: =J12*(1+$O$13)^($D$11-J11-1)*$I$3 -> 51.913247 | K13: =K12*(1+$O$13)^($D$11-K11-1)*$I$3 -> 50.497432 | ... M13: =M12*(1+$O$13)^($D$11-M11-1)*$I$3 -> 47.780586 | N13: =N12*(1+$O$7)^($D$5-N11-1) -> 1116.3688 | O13: =O7 -> 0.1 | P13: Discount rate
C14: Present value sum | D14: =SUM(D13:N13) -> 1659.1946 | O14: 25 | P14: Terminal multiple
N16: Terminal Value | O16: Growth rate
B17: Scenario 3 | C17: =C11 -> Dividend per share | D17: =D11 -> 2025 | E17: =D17+1 -> 2026 | F17: =E17+1 -> 2027 | G17: =F17+1 -> 2028 | H17: =G17+1 -> 2029 | I17: =H17+1 -> 2030 | J17: =I17+1 -> 2031 | K17: =J17+1 -> 2032 | L17: =K17+1 -> 2033 | M17: =L17+1 -> 2034 | N17: =N11 -> 2034 | O17: 0.03 | P17: next 5 years
B18: worst case | C18: =C12 -> 63 | D18: =C18*(1+$O$17) -> 64.89 | E18: =D18*(1+$O$17) -> 66.8367 | F18: =E18*(1+$O$17) -> 68.841801 | G18: =F18*(1+$O$17) -> 70.907055 | H18: =G18*(1+$O$17) -> 73.034267 | I18: =H18*(1+$O$18) -> 75.225295 | J18: =I18*(1+$O$18) -> 77.482054 | K18: =J18*(1+$O$18) -> 79.806515 | L18: =K18*(1+$O$18) -> 82.200711 | M18: =L18*(1+$O$18) -> 84.666732 | N18: =L18*O20 -> 1233.0107 | O18: 0.03 | P18: 5 to 10 years
B19: MARGIN OF | C19: =C13 -> PV(10%) | D19: =D18*(1+$O$19)^($D$17-D17-1)*$I$3 -> 58.990909 | E19: =E18*(1+$O$19)^($D$17-E17-1)*$I$3 -> 55.236942 | F19: =F18*(1+$O$19)^($D$17-F17-1)*$I$3 -> 51.721864 | G19: =G18*(1+$O$19)^($D$17-G17-1)*$I$3 -> 48.430473 | H19: =H18*(1+$O$19)^($D$17-H17-1)*$I$3 -> 45.348533 | I19: =I18*(1+$O$19)^($D$17-I17-1)*$I$3 -> 42.462718 | J19: =J18*(1+$O$19)^($D$17-J17-1)*$I$3 -> 39.760545 | K19: =K18*(1+$O$19)^($D$17-K17-1)*$I$3 -> 37.230328 | ... M19: =M18*(1+$O$19)^($D$17-M17-1)*$I$3 -> 32.64269 | N19: =N18*(1+$O$19)^($D$17-N17-1) -> 475.37899 | O19: =O13 -> 0.1 | P19: Discount rate
B20: SAFETY | C20: Present value sum | D20: =SUM(D19:N19) -> 922.06511 | O20: 15 | P20: Terminal multiple
C22: Scenario | D22: Probability | E22: PV | F22: Part
C23: Scenario 1 (normal case) | D23: 0.34 | E23: =D8 -> 1245.7548 | F23: =E23*D23 -> 423.55665
C24: Scenario 2 (best case) | D24: 0.33 | E24: =D14 -> 1659.1946 | F24: =E24*D24 -> 547.53422
C25: Scenario 3 (worst case) | D25: 0.33 | E25: =D20 -> 922.06511 | F25: =E25*D25 -> 304.28149
C26: STOCK PRICE NOW | D26: =C3 -> 1997 | E26: Sum | F26: =SUM(F23:F25) -> 1275.3724
B28: Disclaimer: This is just for educational purposes and not for investing advice!
B30: MADE BY | C30: STOCK MARKET RESEARCH PLATFORM

Sheet BRK.B
S1: input cells
B2: BRK.B | C2: LINK TO RESEARCH | S2: result cells
B3: STOCK PRICE | C3: ='COMPARATIVE TABLE'!C9 -> 1061.6746 | F3: DIVIDEND PAYOUT RATIO | I3: 0
B4: COMPARATIVE TABLE'!A1 | N4: Terminal Value | O4: Growth rate
B5: Scenario 1 | C5: EARNINGS IN BILLIONS | D5: 2026 | E5: =D5+1 -> 2027 | F5: =E5+1 -> 2028 | G5: =F5+1 -> 2029 | H5: =G5+1 -> 2030 | I5: =H5+1 -> 2031 | J5: =I5+1 -> 2032 | K5: =J5+1 -> 2033 | L5: =K5+1 -> 2034 | M5: =L5+1 -> 2035 | N5: 2035 | O5: 0.07 | P5: next 5 years
B6: normal case | C6: 40 | D6: =C6*(1+$O$5) -> 42.8 | E6: =D6*(1+$O$5) -> 45.796 | F6: =E6*(1+$O$5) -> 49.00172 | G6: =F6*(1+$O$5) -> 52.43184 | H6: =G6*(1+$O$5) -> 56.102069 | I6: =H6*(1+$O$6) -> 60.029214 | J6: =I6*(1+$O$6) -> 64.231259 | K6: =J6*(1+$O$6) -> 68.727447 | L6: =K6*(1+$O$6) -> 73.538368 | M6: =L6*(1+$O$6) -> 78.686054 | N6: =L6*O8 -> 1103.0755 | O6: 0.07 | P6: 5 to 10 years
C7: =CONCATENATE(R8,O7*100,S8) -> PV(10%) | D7: =D6*(1+$O$7)^($D$5-D5-1)*$I$3 -> 0 | E7: =E6*(1+$O$7)^($D$5-E5-1)*$I$3 -> 0 | F7: =F6*(1+$O$7)^($D$5-F5-1)*$I$3 -> 0 | G7: =G6*(1+$O$7)^($D$5-G5-1)*$I$3 -> 0 | H7: =H6*(1+$O$7)^($D$5-H5-1)*$I$3 -> 0 | I7: =I6*(1+$O$7)^($D$5-I5-1)*$I$3 -> 0 | J7: =J6*(1+$O$7)^($D$5-J5-1)*$I$3 -> 0 | K7: =K6*(1+$O$7)^($D$5-K5-1)*$I$3 -> 0 | ... M7: =M6*(1+$O$7)^($D$5-M5-1)*$I$3 -> 0 | N7: =N6*(1+$O$7)^($D$5-N5-1) -> 425.28337 | O7: 0.1 | P7: Discount rate
C8: INTRINSIC VALUE | D8: =SUM(D7:N7) -> 425.28337 | O8: 15 | P8: Terminal multiple | R8: PV( | S8: %)
N10: Terminal Value | O10: Growth rate
B11: Scenario 2 | C11: =C5 -> EARNINGS IN BILLIONS | D11: =D5 -> 2026 | E11: =D11+1 -> 2027 | F11: =E11+1 -> 2028 | G11: =F11+1 -> 2029 | H11: =G11+1 -> 2030 | I11: =H11+1 -> 2031 | J11: =I11+1 -> 2032 | K11: =J11+1 -> 2033 | L11: =K11+1 -> 2034 | M11: =L11+1 -> 2035 | N11: =N5 -> 2035 | O11: 0.09 | P11: next 5 years
B12: best case | C12: =C6 -> 40 | D12: =C12*(1+$O$11) -> 43.6 | E12: =D12*(1+$O$11) -> 47.524 | F12: =E12*(1+$O$11) -> 51.80116 | G12: =F12*(1+$O$11) -> 56.463264 | H12: =G12*(1+$O$11) -> 61.544958 | I12: =H12*(1+$O$12) -> 67.084004 | J12: =I12*(1+$O$12) -> 73.121565 | K12: =J12*(1+$O$12) -> 79.702506 | L12: =K12*(1+$O$12) -> 86.875731 | M12: =L12*(1+$O$12) -> 94.694547 | N12: =L12*O14 -> 1737.5146 | O12: 0.09 | P12: 5 to 10 years
B13: =B7 -> 0 | C13: =C7 -> PV(10%) | D13: =D12*(1+$O$13)^($D$11-D11-1)*$I$3 -> 0 | E13: =E12*(1+$O$13)^($D$11-E11-1)*$I$3 -> 0 | F13: =F12*(1+$O$13)^($D$11-F11-1)*$I$3 -> 0 | G13: =G12*(1+$O$13)^($D$11-G11-1)*$I$3 -> 0 | H13: =H12*(1+$O$13)^($D$11-H11-1)*$I$3 -> 0 | I13: =I12*(1+$O$13)^($D$11-I11-1)*$I$3 -> 0 | J13: =J12*(1+$O$13)^($D$11-J11-1)*$I$3 -> 0 | K13: =K12*(1+$O$13)^($D$11-K11-1)*$I$3 -> 0 | ... M13: =M12*(1+$O$13)^($D$11-M11-1)*$I$3 -> 0 | N13: =N12*(1+$O$7)^($D$5-N11-1) -> 669.8871 | O13: =O7 -> 0.1 | P13: Discount rate
C14: Present value sum | D14: =SUM(D13:N13) -> 669.8871 | O14: 20 | P14: Terminal multiple
N16: Terminal Value | O16: Growth rate
B17: Scenario 3 | C17: =C11 -> EARNINGS IN BILLIONS | D17: =D11 -> 2026 | E17: =D17+1 -> 2027 | F17: =E17+1 -> 2028 | G17: =F17+1 -> 2029 | H17: =G17+1 -> 2030 | I17: =H17+1 -> 2031 | J17: =I17+1 -> 2032 | K17: =J17+1 -> 2033 | L17: =K17+1 -> 2034 | M17: =L17+1 -> 2035 | N17: =N11 -> 2035 | O17: 0.05 | P17: next 5 years
B18: worst case | C18: =C12 -> 40 | D18: =C18*(1+$O$17) -> 42 | E18: =D18*(1+$O$17) -> 44.1 | F18: =E18*(1+$O$17) -> 46.305 | G18: =F18*(1+$O$17) -> 48.62025 | H18: =G18*(1+$O$17) -> 51.051263 | I18: =H18*(1+$O$18) -> 53.603826 | J18: =I18*(1+$O$18) -> 56.284017 | K18: =J18*(1+$O$18) -> 59.098218 | L18: =K18*(1+$O$18) -> 62.053129 | M18: =L18*(1+$O$18) -> 65.155785 | N18: =L18*O20 -> 744.63754 | O18: 0.05 | P18: 5 to 10 years
B19: MARGIN OF | C19: =C13 -> PV(10%) | D19: =D18*(1+$O$19)^($D$17-D17-1)*$I$3 -> 0 | E19: =E18*(1+$O$19)^($D$17-E17-1)*$I$3 -> 0 | F19: =F18*(1+$O$19)^($D$17-F17-1)*$I$3 -> 0 | G19: =G18*(1+$O$19)^($D$17-G17-1)*$I$3 -> 0 | H19: =H18*(1+$O$19)^($D$17-H17-1)*$I$3 -> 0 | I19: =I18*(1+$O$19)^($D$17-I17-1)*$I$3 -> 0 | J19: =J18*(1+$O$19)^($D$17-J17-1)*$I$3 -> 0 | K19: =K18*(1+$O$19)^($D$17-K17-1)*$I$3 -> 0 | ... M19: =M18*(1+$O$19)^($D$17-M17-1)*$I$3 -> 0 | N19: =N18*(1+$O$19)^($D$17-N17-1) -> 287.09001 | O19: =O13 -> 0.1 | P19: Discount rate
B20: SAFETY | C20: Present value sum | D20: =SUM(D19:N19) -> 287.09001 | O20: 12 | P20: Terminal multiple
C22: Scenario | D22: Probability | E22: PV | F22: Part
C23: Scenario 1 (normal case) | D23: 0.34 | E23: =D8 -> 425.28337 | F23: =E23*D23 -> 144.59634
C24: Scenario 2 (best case) | D24: 0.33 | E24: =D14 -> 669.8871 | F24: =E24*D24 -> 221.06274
C25: Scenario 3 (worst case) | D25: 0.33 | E25: =D20 -> 287.09001 | F25: =E25*D25 -> 94.739703
C26: STOCK PRICE NOW | D26: =C3 -> 1061.6746 | E26: Sum | F26: =SUM(F23:F25) -> 460.39879
B28: Disclaimer: This is just for educational purposes and not for investing advice!
B30: MADE BY | C30: STOCK MARKET RESEARCH PLATFORM

Sheet LND
S1: input cells
B2: Brasilagro | C2: LINK TO RESEARCH | S2: result cells
B3: STOCK PRICE | C3: ='COMPARATIVE TABLE'!C10 -> 3.88 | F3: DIVIDEND PAYOUT RATIO | I3: 0.5
B4: COMPARATIVE TABLE'!A1 | N4: Terminal Value | O4: Growth rate
B5: Scenario 1 | C5: Earnings per share | D5: 2025 | E5: =D5+1 -> 2026 | F5: =E5+1 -> 2027 | G5: =F5+1 -> 2028 | H5: =G5+1 -> 2029 | I5: =H5+1 -> 2030 | J5: =I5+1 -> 2031 | K5: =J5+1 -> 2032 | L5: =K5+1 -> 2033 | M5: =L5+1 -> 2034 | N5: 2034 | O5: 0.05 | P5: next 5 years
B6: normal case | C6: 0.25 | D6: =C6*(1+$O$5) -> 0.2625 | E6: =D6*(1+$O$5) -> 0.275625 | F6: =E6*(1+$O$5) -> 0.28940625 | G6: =F6*(1+$O$5) -> 0.30387656 | H6: =G6*(1+$O$5) -> 0.31907039 | I6: =H6*(1+$O$6) -> 0.33502391 | J6: =I6*(1+$O$6) -> 0.35177511 | K6: =J6*(1+$O$6) -> 0.36936386 | L6: =K6*(1+$O$6) -> 0.38783205 | M6: =L6*(1+$O$6) -> 0.40722366 | N6: =L6*O8 -> 5.8174808 | O6: 0.05 | P6: 5 to 10 years
C7: =CONCATENATE(R8,O7*100,S8) -> PV(10%) | D7: =D6*(1+$O$7)^($D$5-D5-1)*$I$3 -> 0.11931818 | E7: =E6*(1+$O$7)^($D$5-E5-1)*$I$3 -> 0.11389463 | F7: =F6*(1+$O$7)^($D$5-F5-1)*$I$3 -> 0.1087176 | G7: =G6*(1+$O$7)^($D$5-G5-1)*$I$3 -> 0.10377589 | H7: =H6*(1+$O$7)^($D$5-H5-1)*$I$3 -> 0.099058805 | I7: =I6*(1+$O$7)^($D$5-I5-1)*$I$3 -> 0.094556132 | J7: =J6*(1+$O$7)^($D$5-J5-1)*$I$3 -> 0.090258126 | K7: =K6*(1+$O$7)^($D$5-K5-1)*$I$3 -> 0.086155484 | ... M7: =M6*(1+$O$7)^($D$5-M5-1)*$I$3 -> 0.078501174 | N7: =N6*(1+$O$7)^($D$5-N5-1) -> 2.2428907 | O7: 0.1 | P7: Discount rate
C8: INTRINSIC VALUE | D8: =SUM(D7:N7) -> 3.219366 | O8: 15 | P8: Terminal multiple | R8: PV( | S8: %)
N10: Terminal Value | O10: Growth rate
B11: Scenario 2 | C11: =C5 -> Earnings per share | D11: =D5 -> 2025 | E11: =D11+1 -> 2026 | F11: =E11+1 -> 2027 | G11: =F11+1 -> 2028 | H11: =G11+1 -> 2029 | I11: =H11+1 -> 2030 | J11: =I11+1 -> 2031 | K11: =J11+1 -> 2032 | L11: =K11+1 -> 2033 | M11: =L11+1 -> 2034 | N11: =N5 -> 2034 | O11: 0.07 | P11: next 5 years
B12: best case | C12: =C6 -> 0.25 | D12: =C12*(1+$O$11) -> 0.2675 | E12: =D12*(1+$O$11) -> 0.286225 | F12: =E12*(1+$O$11) -> 0.30626075 | G12: =F12*(1+$O$11) -> 0.327699 | H12: =G12*(1+$O$11) -> 0.35063793 | I12: =H12*(1+$O$12) -> 0.37518259 | J12: =I12*(1+$O$12) -> 0.40144537 | K12: =J12*(1+$O$12) -> 0.42954654 | L12: =K12*(1+$O$12) -> 0.4596148 | M12: =L12*(1+$O$12) -> 0.49178784 | N12: =L12*O14 -> 9.1922961 | O12: 0.07 | P12: 5 to 10 years
B13: =B7 -> 0 | C13: =C7 -> PV(10%) | D13: =D12*(1+$O$13)^($D$11-D11-1)*$I$3 -> 0.12159091 | E13: =E12*(1+$O$13)^($D$11-E11-1)*$I$3 -> 0.11827479 | F13: =F12*(1+$O$13)^($D$11-F11-1)*$I$3 -> 0.11504912 | G13: =G12*(1+$O$13)^($D$11-G11-1)*$I$3 -> 0.11191141 | H13: =H12*(1+$O$13)^($D$11-H11-1)*$I$3 -> 0.10885928 | I13: =I12*(1+$O$13)^($D$11-I11-1)*$I$3 -> 0.10589039 | J13: =J12*(1+$O$13)^($D$11-J11-1)*$I$3 -> 0.10300248 | K13: =K12*(1+$O$13)^($D$11-K11-1)*$I$3 -> 0.10019332 | ... M13: =M12*(1+$O$13)^($D$11-M11-1)*$I$3 -> 0.094802751 | N13: =N12*(1+$O$7)^($D$5-N11-1) -> 3.5440281 | O13: =O7 -> 0.1 | P13: Discount rate
C14: Present value sum | D14: =SUM(D13:N13) -> 4.6210633 | O14: 20 | P14: Terminal multiple
N16: Terminal Value | O16: Growth rate
B17: Scenario 3 | C17: =C11 -> Earnings per share | D17: =D11 -> 2025 | E17: =D17+1 -> 2026 | F17: =E17+1 -> 2027 | G17: =F17+1 -> 2028 | H17: =G17+1 -> 2029 | I17: =H17+1 -> 2030 | J17: =I17+1 -> 2031 | K17: =J17+1 -> 2032 | L17: =K17+1 -> 2033 | M17: =L17+1 -> 2034 | N17: =N11 -> 2034 | O17: 0.02 | P17: next 5 years
B18: worst case | C18: =C12 -> 0.25 | D18: =C18*(1+$O$17) -> 0.255 | E18: =D18*(1+$O$17) -> 0.2601 | F18: =E18*(1+$O$17) -> 0.265302 | G18: =F18*(1+$O$17) -> 0.27060804 | H18: =G18*(1+$O$17) -> 0.2760202 | I18: =H18*(1+$O$18) -> 0.2815406 | J18: =I18*(1+$O$18) -> 0.28717142 | K18: =J18*(1+$O$18) -> 0.29291485 | L18: =K18*(1+$O$18) -> 0.29877314 | M18: =L18*(1+$O$18) -> 0.3047486 | N18: =L18*O20 -> 3.5852777 | O18: 0.02 | P18: 5 to 10 years
B19: MARGIN OF | C19: =C13 -> PV(10%) | D19: =D18*(1+$O$19)^($D$17-D17-1)*$I$3 -> 0.11590909 | E19: =E18*(1+$O$19)^($D$17-E17-1)*$I$3 -> 0.10747934 | F19: =F18*(1+$O$19)^($D$17-F17-1)*$I$3 -> 0.09966266 | G19: =G18*(1+$O$19)^($D$17-G17-1)*$I$3 -> 0.092414466 | H19: =H18*(1+$O$19)^($D$17-H17-1)*$I$3 -> 0.085693414 | I19: =I18*(1+$O$19)^($D$17-I17-1)*$I$3 -> 0.079461166 | J19: =J18*(1+$O$19)^($D$17-J17-1)*$I$3 -> 0.073682172 | K19: =K18*(1+$O$19)^($D$17-K17-1)*$I$3 -> 0.068323469 | ... M19: =M18*(1+$O$19)^($D$17-M17-1)*$I$3 -> 0.05874689 | N19: =N18*(1+$O$19)^($D$17-N17-1) -> 1.3822798 | O19: =O13 -> 0.1 | P19: Discount rate
B20: SAFETY | C20: Present value sum | D20: =SUM(D19:N19) -> 2.2270069 | O20: 12 | P20: Terminal multiple
C22: Scenario | D22: Probability | E22: PV | F22: Part
C23: Scenario 1 (normal case) | D23: 0.34 | E23: =D8 -> 3.219366 | F23: =E23*D23 -> 1.0945845
C24: Scenario 2 (best case) | D24: 0.33 | E24: =D14 -> 4.6210633 | F24: =E24*D24 -> 1.5249509
C25: Scenario 3 (worst case) | D25: 0.33 | E25: =D20 -> 2.2270069 | F25: =E25*D25 -> 0.73491228
C26: STOCK PRICE NOW | D26: =C3 -> 3.88 | E26: Sum | F26: =SUM(F23:F25) -> 3.3544476
B28: Disclaimer: This is just for educational purposes and not for investing advice!
B30: MADE BY | C30: STOCK MARKET RESEARCH PLATFORM

Sheet CEMBRE
S1: input cells
B2: CEMBRE | C2: LINK TO RESEARCH | S2: result cells
B3: STOCK PRICE | C3: ='COMPARATIVE TABLE'!C11 -> 60.2 | F3: DIVIDEND PAYOUT RATIO | I3: 1
B4: COMPARATIVE TABLE'!A1 | N4: Terminal Value | O4: Growth rate
B5: Scenario 1 | C5: DIVIDEND PER SHARE | D5: 2025 | E5: =D5+1 -> 2026 | F5: =E5+1 -> 2027 | G5: =F5+1 -> 2028 | H5: =G5+1 -> 2029 | I5: =H5+1 -> 2030 | J5: =I5+1 -> 2031 | K5: =J5+1 -> 2032 | L5: =K5+1 -> 2033 | M5: =L5+1 -> 2034 | N5: 2034 | O5: 0.03 | P5: next 5 years
B6: normal case | C6: 1.81 | D6: =C6*(1+$O$5) -> 1.8643 | E6: =D6*(1+$O$5) -> 1.920229 | F6: =E6*(1+$O$5) -> 1.9778359 | G6: =F6*(1+$O$5) -> 2.0371709 | H6: =G6*(1+$O$5) -> 2.0982861 | I6: =H6*(1+$O$6) -> 2.1612347 | J6: =I6*(1+$O$6) -> 2.2260717 | K6: =J6*(1+$O$6) -> 2.2928538 | L6: =K6*(1+$O$6) -> 2.3616395 | M6: =L6*(1+$O$6) -> 2.4324886 | N6: =L6*O8 -> 47.232789 | O6: 0.03 | P6: 5 to 10 years
C7: =CONCATENATE(R8,O7*100,S8) -> PV(10%) | D7: =D6*(1+$O$7)^($D$5-D5-1)*$I$3 -> 1.6948182 | E7: =E6*(1+$O$7)^($D$5-E5-1)*$I$3 -> 1.5869661 | F7: =F6*(1+$O$7)^($D$5-F5-1)*$I$3 -> 1.4859774 | G7: =G6*(1+$O$7)^($D$5-G5-1)*$I$3 -> 1.3914152 | H7: =H6*(1+$O$7)^($D$5-H5-1)*$I$3 -> 1.3028706 | I7: =I6*(1+$O$7)^($D$5-I5-1)*$I$3 -> 1.2199606 | J7: =J6*(1+$O$7)^($D$5-J5-1)*$I$3 -> 1.1423268 | K7: =K6*(1+$O$7)^($D$5-K5-1)*$I$3 -> 1.0696332 | ... M7: =M6*(1+$O$7)^($D$5-M5-1)*$I$3 -> 0.93782967 | N7: =N6*(1+$O$7)^($D$5-N5-1) -> 18.210285 | O7: 0.1 | P7: Discount rate
C8: INTRINSIC VALUE | D8: =SUM(D7:N7) -> 31.043648 | O8: 20 | P8: Terminal multiple | R8: PV( | S8: %)
N10: Terminal Value | O10: Growth rate
B11: Scenario 2 | C11: =C5 -> DIVIDEND PER SHARE | D11: =D5 -> 2025 | E11: =D11+1 -> 2026 | F11: =E11+1 -> 2027 | G11: =F11+1 -> 2028 | H11: =G11+1 -> 2029 | I11: =H11+1 -> 2030 | J11: =I11+1 -> 2031 | K11: =J11+1 -> 2032 | L11: =K11+1 -> 2033 | M11: =L11+1 -> 2034 | N11: =N5 -> 2034 | O11: 0.05 | P11: next 5 years
B12: best case | C12: =C6 -> 1.81 | D12: =C12*(1+$O$11) -> 1.9005 | E12: =D12*(1+$O$11) -> 1.995525 | F12: =E12*(1+$O$11) -> 2.0953013 | G12: =F12*(1+$O$11) -> 2.2000663 | H12: =G12*(1+$O$11) -> 2.3100696 | I12: =H12*(1+$O$12) -> 2.4255731 | J12: =I12*(1+$O$12) -> 2.5468518 | K12: =J12*(1+$O$12) -> 2.6741944 | L12: =K12*(1+$O$12) -> 2.8079041 | M12: =L12*(1+$O$12) -> 2.9482993 | N12: =L12*O14 -> 70.197602 | O12: 0.05 | P12: 5 to 10 years
B13: =B7 -> 0 | C13: =C7 -> PV(10%) | D13: =D12*(1+$O$13)^($D$11-D11-1)*$I$3 -> 1.7277273 | E13: =E12*(1+$O$13)^($D$11-E11-1)*$I$3 -> 1.6491942 | F13: =F12*(1+$O$13)^($D$11-F11-1)*$I$3 -> 1.5742308 | G13: =G12*(1+$O$13)^($D$11-G11-1)*$I$3 -> 1.5026749 | H13: =H12*(1+$O$13)^($D$11-H11-1)*$I$3 -> 1.4343715 | I13: =I12*(1+$O$13)^($D$11-I11-1)*$I$3 -> 1.3691728 | J13: =J12*(1+$O$13)^($D$11-J11-1)*$I$3 -> 1.3069377 | K13: =K12*(1+$O$13)^($D$11-K11-1)*$I$3 -> 1.2475314 | ... M13: =M12*(1+$O$13)^($D$11-M11-1)*$I$3 -> 1.136697 | N13: =N12*(1+$O$7)^($D$5-N11-1) -> 27.064214 | O13: =O7 -> 0.1 | P13: Discount rate
C14: Present value sum | D14: =SUM(D13:N13) -> 41.203577 | O14: 25 | P14: Terminal multiple
N16: Terminal Value | O16: Growth rate
B17: Scenario 3 | C17: =C11 -> DIVIDEND PER SHARE | D17: =D11 -> 2025 | E17: =D17+1 -> 2026 | F17: =E17+1 -> 2027 | G17: =F17+1 -> 2028 | H17: =G17+1 -> 2029 | I17: =H17+1 -> 2030 | J17: =I17+1 -> 2031 | K17: =J17+1 -> 2032 | L17: =K17+1 -> 2033 | M17: =L17+1 -> 2034 | N17: =N11 -> 2034 | O17: 0 | P17: next 5 years
B18: worst case | C18: =C12 -> 1.81 | D18: =C18*(1+$O$17) -> 1.81 | E18: =D18*(1+$O$17) -> 1.81 | F18: =E18*(1+$O$17) -> 1.81 | G18: =F18*(1+$O$17) -> 1.81 | H18: =G18*(1+$O$17) -> 1.81 | I18: =H18*(1+$O$18) -> 1.81 | J18: =I18*(1+$O$18) -> 1.81 | K18: =J18*(1+$O$18) -> 1.81 | L18: =K18*(1+$O$18) -> 1.81 | M18: =L18*(1+$O$18) -> 1.81 | N18: =L18*O20 -> 27.15 | O18: 0 | P18: 5 to 10 years
B19: MARGIN OF | C19: =C13 -> PV(10%) | D19: =D18*(1+$O$19)^($D$17-D17-1)*$I$3 -> 1.6454545 | E19: =E18*(1+$O$19)^($D$17-E17-1)*$I$3 -> 1.4958678 | F19: =F18*(1+$O$19)^($D$17-F17-1)*$I$3 -> 1.3598798 | G19: =G18*(1+$O$19)^($D$17-G17-1)*$I$3 -> 1.2362544 | H19: =H18*(1+$O$19)^($D$17-H17-1)*$I$3 -> 1.1238676 | I19: =I18*(1+$O$19)^($D$17-I17-1)*$I$3 -> 1.0216978 | J19: =J18*(1+$O$19)^($D$17-J17-1)*$I$3 -> 0.92881619 | K19: =K18*(1+$O$19)^($D$17-K17-1)*$I$3 -> 0.84437836 | ... M19: =M18*(1+$O$19)^($D$17-M17-1)*$I$3 -> 0.69783335 | N19: =N18*(1+$O$19)^($D$17-N17-1) -> 10.4675 | O19: =O13 -> 0.1 | P19: Discount rate
B20: SAFETY | C20: Present value sum | D20: =SUM(D19:N19) -> 21.589167 | O20: 15 | P20: Terminal multiple
C22: Scenario | D22: Probability | E22: PV | F22: Part
C23: Scenario 1 (normal case) | D23: 0.34 | E23: =D8 -> 31.043648 | F23: =E23*D23 -> 10.55484
C24: Scenario 2 (best case) | D24: 0.33 | E24: =D14 -> 41.203577 | F24: =E24*D24 -> 13.597181
C25: Scenario 3 (worst case) | D25: 0.33 | E25: =D20 -> 21.589167 | F25: =E25*D25 -> 7.124425
C26: STOCK PRICE NOW | D26: =C3 -> 60.2 | E26: Sum | F26: =SUM(F23:F25) -> 31.276446
B28: Disclaimer: This is just for educational purposes and not for investing advice!
B30: MADE BY | C30: STOCK MARKET RESEARCH PLATFORM

Sheet CHM
S1: input cells
B2: Name | C2: LINK TO RESEARCH | S2: result cells
B3: STOCK PRICE | C3: ='COMPARATIVE TABLE'!C12 -> 87.5 | F3: DIVIDEND PAYOUT RATIO | I3: 1
B4: COMPARATIVE TABLE'!A1 | N4: Terminal Value | O4: Growth rate
B5: Scenario 1 | C5: Dividend per share HKD | D5: 2026 | E5: =D5+1 -> 2027 | F5: =E5+1 -> 2028 | G5: =F5+1 -> 2029 | H5: =G5+1 -> 2030 | I5: =H5+1 -> 2031 | J5: =I5+1 -> 2032 | K5: =J5+1 -> 2033 | L5: =K5+1 -> 2034 | M5: =L5+1 -> 2035 | N5: 2035 | O5: 0.05 | P5: next 5 years
B6: normal case | C6: 5.2 | D6: =C6*(1+$O$5) -> 5.46 | E6: =D6*(1+$O$5) -> 5.733 | F6: =E6*(1+$O$5) -> 6.01965 | G6: =F6*(1+$O$5) -> 6.3206325 | H6: =G6*(1+$O$5) -> 6.6366641 | I6: =H6*(1+$O$6) -> 6.9684973 | J6: =I6*(1+$O$6) -> 7.3169222 | K6: =J6*(1+$O$6) -> 7.6827683 | L6: =K6*(1+$O$6) -> 8.0669067 | M6: =L6*(1+$O$6) -> 8.4702521 | N6: =L6*O8 -> 121.0036 | O6: 0.05 | P6: 5 to 10 years
C7: =CONCATENATE(R8,O7*100,S8) -> PV(10%) | D7: =D6*(1+$O$7)^($D$5-D5-1)*$I$3 -> 4.9636364 | E7: =E6*(1+$O$7)^($D$5-E5-1)*$I$3 -> 4.7380165 | F7: =F6*(1+$O$7)^($D$5-F5-1)*$I$3 -> 4.5226521 | G7: =G6*(1+$O$7)^($D$5-G5-1)*$I$3 -> 4.317077 | H7: =H6*(1+$O$7)^($D$5-H5-1)*$I$3 -> 4.1208463 | I7: =I6*(1+$O$7)^($D$5-I5-1)*$I$3 -> 3.9335351 | J7: =J6*(1+$O$7)^($D$5-J5-1)*$I$3 -> 3.754738 | K7: =K6*(1+$O$7)^($D$5-K5-1)*$I$3 -> 3.5840681 | ... M7: =M6*(1+$O$7)^($D$5-M5-1)*$I$3 -> 3.2656488 | N7: =N6*(1+$O$7)^($D$5-N5-1) -> 46.652126 | O7: 0.1 | P7: Discount rate
C8: INTRINSIC VALUE | D8: =SUM(D7:N7) -> 87.273501 | O8: 15 | P8: Terminal multiple | R8: PV( | S8: %)
N10: Terminal Value | O10: Growth rate
B11: Scenario 2 | C11: =C5 -> Dividend per share HKD | D11: =D5 -> 2026 | E11: =D11+1 -> 2027 | F11: =E11+1 -> 2028 | G11: =F11+1 -> 2029 | H11: =G11+1 -> 2030 | I11: =H11+1 -> 2031 | J11: =I11+1 -> 2032 | K11: =J11+1 -> 2033 | L11: =K11+1 -> 2034 | M11: =L11+1 -> 2035 | N11: =N5 -> 2035 | O11: 0.06 | P11: next 5 years
B12: best case | C12: =C6 -> 5.2 | D12: =C12*(1+$O$11) -> 5.512 | E12: =D12*(1+$O$11) -> 5.84272 | F12: =E12*(1+$O$11) -> 6.1932832 | G12: =F12*(1+$O$11) -> 6.5648802 | H12: =G12*(1+$O$11) -> 6.958773 | I12: =H12*(1+$O$12) -> 7.3762994 | J12: =I12*(1+$O$12) -> 7.8188773 | K12: =J12*(1+$O$12) -> 8.28801 | L12: =K12*(1+$O$12) -> 8.7852906 | M12: =L12*(1+$O$12) -> 9.312408 | N12: =L12*O14 -> 175.70581 | O12: 0.06 | P12: 5 to 10 years
B13: =B7 -> 0 | C13: =C7 -> PV(10%) | D13: =D12*(1+$O$13)^($D$11-D11-1)*$I$3 -> 5.0109091 | E13: =E12*(1+$O$13)^($D$11-E11-1)*$I$3 -> 4.8286942 | F13: =F12*(1+$O$13)^($D$11-F11-1)*$I$3 -> 4.6531053 | G13: =G12*(1+$O$13)^($D$11-G11-1)*$I$3 -> 4.4839015 | H13: =H12*(1+$O$13)^($D$11-H11-1)*$I$3 -> 4.3208505 | I13: =I12*(1+$O$13)^($D$11-I11-1)*$I$3 -> 4.1637287 | J13: =J12*(1+$O$13)^($D$11-J11-1)*$I$3 -> 4.0123204 | K13: =K12*(1+$O$13)^($D$11-K11-1)*$I$3 -> 3.8664178 | ... M13: =M12*(1+$O$13)^($D$11-M11-1)*$I$3 -> 3.5903364 | N13: =N12*(1+$O$7)^($D$5-N11-1) -> 67.742197 | O13: =O7 -> 0.1 | P13: Discount rate
C14: Present value sum | D14: =SUM(D13:N13) -> 110.39828 | O14: 20 | P14: Terminal multiple
N16: Terminal Value | O16: Growth rate
B17: Scenario 3 | C17: =C11 -> Dividend per share HKD | D17: =D11 -> 2026 | E17: =D17+1 -> 2027 | F17: =E17+1 -> 2028 | G17: =F17+1 -> 2029 | H17: =G17+1 -> 2030 | I17: =H17+1 -> 2031 | J17: =I17+1 -> 2032 | K17: =J17+1 -> 2033 | L17: =K17+1 -> 2034 | M17: =L17+1 -> 2035 | N17: =N11 -> 2035 | O17: 0.03 | P17: next 5 years
B18: worst case | C18: =C12 -> 5.2 | D18: =C18*(1+$O$17) -> 5.356 | E18: =D18*(1+$O$17) -> 5.51668 | F18: =E18*(1+$O$17) -> 5.6821804 | G18: =F18*(1+$O$17) -> 5.8526458 | H18: =G18*(1+$O$17) -> 6.0282252 | I18: =H18*(1+$O$18) -> 6.2090719 | J18: =I18*(1+$O$18) -> 6.3953441 | K18: =J18*(1+$O$18) -> 6.5872044 | L18: =K18*(1+$O$18) -> 6.7848206 | M18: =L18*(1+$O$18) -> 6.9883652 | N18: =L18*O20 -> 81.417847 | O18: 0.03 | P18: 5 to 10 years
B19: MARGIN OF | C19: =C13 -> PV(10%) | D19: =D18*(1+$O$19)^($D$17-D17-1)*$I$3 -> 4.8690909 | E19: =E18*(1+$O$19)^($D$17-E17-1)*$I$3 -> 4.5592397 | F19: =F18*(1+$O$19)^($D$17-F17-1)*$I$3 -> 4.2691062 | G19: =G18*(1+$O$19)^($D$17-G17-1)*$I$3 -> 3.9974358 | H19: =H18*(1+$O$19)^($D$17-H17-1)*$I$3 -> 3.7430536 | I19: =I18*(1+$O$19)^($D$17-I17-1)*$I$3 -> 3.5048592 | J19: =J18*(1+$O$19)^($D$17-J17-1)*$I$3 -> 3.2818227 | K19: =K18*(1+$O$19)^($D$17-K17-1)*$I$3 -> 3.0729795 | ... M19: =M18*(1+$O$19)^($D$17-M17-1)*$I$3 -> 2.6943173 | N19: =N18*(1+$O$19)^($D$17-N17-1) -> 31.390104 | O19: =O13 -> 0.1 | P19: Discount rate
B20: SAFETY | C20: Present value sum | D20: =SUM(D19:N19) -> 68.259436 | O20: 12 | P20: Terminal multiple
C22: Scenario | D22: Probability | E22: PV | F22: Part
C23: Scenario 1 (normal case) | D23: 0.34 | E23: =D8 -> 87.273501 | F23: =E23*D23 -> 29.67299
C24: Scenario 2 (best case) | D24: 0.33 | E24: =D14 -> 110.39828 | F24: =E24*D24 -> 36.431433
C25: Scenario 3 (worst case) | D25: 0.33 | E25: =D20 -> 68.259436 | F25: =E25*D25 -> 22.525614
C26: STOCK PRICE NOW | D26: =C3 -> 87.5 | E26: Sum | F26: =SUM(F23:F25) -> 88.630037
B28: Disclaimer: This is just for educational purposes and not for investing advice!
B30: MADE BY | C30: STOCK MARKET RESEARCH PLATFORM

Sheet CK
S1: input cells
B2: CK Hutchison | C2: LINK TO RESEARCH | S2: result cells
B3: STOCK PRICE | C3: ='COMPARATIVE TABLE'!C13 -> 52.1 | F3: DIVIDEND PAYOUT RATIO | I3: 1
B4: COMPARATIVE TABLE'!A1 | N4: Terminal Value | O4: Growth rate
B5: Scenario 1 | C5: Dividend per share | D5: 2025 | E5: =D5+1 -> 2026 | F5: =E5+1 -> 2027 | G5: =F5+1 -> 2028 | H5: =G5+1 -> 2029 | I5: =H5+1 -> 2030 | J5: =I5+1 -> 2031 | K5: =J5+1 -> 2032 | L5: =K5+1 -> 2033 | M5: =L5+1 -> 2034 | N5: 2034 | O5: 0.04 | P5: next 5 years
B6: normal case | C6: 2.2 | D6: =C6*(1+$O$5) -> 2.288 | E6: =D6*(1+$O$5) -> 2.37952 | F6: =E6*(1+$O$5) -> 2.4747008 | G6: =F6*(1+$O$5) -> 2.5736888 | H6: =G6*(1+$O$5) -> 2.6766364 | I6: =H6*(1+$O$6) -> 2.7837018 | J6: =I6*(1+$O$6) -> 2.8950499 | K6: =J6*(1+$O$6) -> 3.0108519 | L6: =K6*(1+$O$6) -> 3.131286 | M6: =L6*(1+$O$6) -> 3.2565374 | N6: =L6*O8 -> 62.62572 | O6: 0.04 | P6: 5 to 10 years
C7: =CONCATENATE(R8,O7*100,S8) -> PV(10%) | D7: =D6*(1+$O$7)^($D$5-D5-1)*$I$3 -> 2.08 | E7: =E6*(1+$O$7)^($D$5-E5-1)*$I$3 -> 1.9665455 | F7: =F6*(1+$O$7)^($D$5-F5-1)*$I$3 -> 1.8592793 | G7: =G6*(1+$O$7)^($D$5-G5-1)*$I$3 -> 1.7578641 | H7: =H6*(1+$O$7)^($D$5-H5-1)*$I$3 -> 1.6619806 | I7: =I6*(1+$O$7)^($D$5-I5-1)*$I$3 -> 1.5713271 | J7: =J6*(1+$O$7)^($D$5-J5-1)*$I$3 -> 1.4856184 | K7: =K6*(1+$O$7)^($D$5-K5-1)*$I$3 -> 1.4045846 | ... M7: =M6*(1+$O$7)^($D$5-M5-1)*$I$3 -> 1.2555362 | N7: =N6*(1+$O$7)^($D$5-N5-1) -> 24.144926 | O7: 0.1 | P7: Discount rate
C8: INTRINSIC VALUE | D8: =SUM(D7:N7) -> 40.515633 | O8: 20 | P8: Terminal multiple | R8: PV( | S8: %)
N10: Terminal Value | O10: Growth rate
B11: Scenario 2 | C11: =C5 -> Dividend per share | D11: =D5 -> 2025 | E11: =D11+1 -> 2026 | F11: =E11+1 -> 2027 | G11: =F11+1 -> 2028 | H11: =G11+1 -> 2029 | I11: =H11+1 -> 2030 | J11: =I11+1 -> 2031 | K11: =J11+1 -> 2032 | L11: =K11+1 -> 2033 | M11: =L11+1 -> 2034 | N11: =N5 -> 2034 | O11: 0.06 | P11: next 5 years
B12: best case | C12: =C6 -> 2.2 | D12: =C12*(1+$O$11) -> 2.332 | E12: =D12*(1+$O$11) -> 2.47192 | F12: =E12*(1+$O$11) -> 2.6202352 | G12: =F12*(1+$O$11) -> 2.7774493 | H12: =G12*(1+$O$11) -> 2.9440963 | I12: =H12*(1+$O$12) -> 3.120742 | J12: =I12*(1+$O$12) -> 3.3079866 | K12: =J12*(1+$O$12) -> 3.5064658 | L12: =K12*(1+$O$12) -> 3.7168537 | M12: =L12*(1+$O$12) -> 3.9398649 | N12: =L12*O14 -> 92.921343 | O12: 0.06 | P12: 5 to 10 years
B13: =B7 -> 0 | C13: =C7 -> PV(10%) | D13: =D12*(1+$O$13)^($D$11-D11-1)*$I$3 -> 2.12 | E13: =E12*(1+$O$13)^($D$11-E11-1)*$I$3 -> 2.0429091 | F13: =F12*(1+$O$13)^($D$11-F11-1)*$I$3 -> 1.9686215 | G13: =G12*(1+$O$13)^($D$11-G11-1)*$I$3 -> 1.8970353 | H13: =H12*(1+$O$13)^($D$11-H11-1)*$I$3 -> 1.8280522 | I13: =I12*(1+$O$13)^($D$11-I11-1)*$I$3 -> 1.7615775 | J13: =J12*(1+$O$13)^($D$11-J11-1)*$I$3 -> 1.6975202 | K13: =K12*(1+$O$13)^($D$11-K11-1)*$I$3 -> 1.6357922 | ... M13: =M12*(1+$O$13)^($D$11-M11-1)*$I$3 -> 1.5189885 | N13: =N12*(1+$O$7)^($D$5-N11-1) -> 35.8252 | O13: =O7 -> 0.1 | P13: Discount rate
C14: Present value sum | D14: =SUM(D13:N13) -> 53.872005 | O14: 25 | P14: Terminal multiple
N16: Terminal Value | O16: Growth rate
B17: Scenario 3 | C17: =C11 -> Dividend per share | D17: =D11 -> 2025 | E17: =D17+1 -> 2026 | F17: =E17+1 -> 2027 | G17: =F17+1 -> 2028 | H17: =G17+1 -> 2029 | I17: =H17+1 -> 2030 | J17: =I17+1 -> 2031 | K17: =J17+1 -> 2032 | L17: =K17+1 -> 2033 | M17: =L17+1 -> 2034 | N17: =N11 -> 2034 | O17: 0.02 | P17: next 5 years
B18: worst case | C18: =C12 -> 2.2 | D18: =C18*(1+$O$17) -> 2.244 | E18: =D18*(1+$O$17) -> 2.28888 | F18: =E18*(1+$O$17) -> 2.3346576 | G18: =F18*(1+$O$17) -> 2.3813508 | H18: =G18*(1+$O$17) -> 2.4289778 | I18: =H18*(1+$O$18) -> 2.4775573 | J18: =I18*(1+$O$18) -> 2.5271085 | K18: =J18*(1+$O$18) -> 2.5776506 | L18: =K18*(1+$O$18) -> 2.6292037 | M18: =L18*(1+$O$18) -> 2.6817877 | N18: =L18*O20 -> 39.438055 | O18: 0.02 | P18: 5 to 10 years
B19: MARGIN OF | C19: =C13 -> PV(10%) | D19: =D18*(1+$O$19)^($D$17-D17-1)*$I$3 -> 2.04 | E19: =E18*(1+$O$19)^($D$17-E17-1)*$I$3 -> 1.8916364 | F19: =F18*(1+$O$19)^($D$17-F17-1)*$I$3 -> 1.7540628 | G19: =G18*(1+$O$19)^($D$17-G17-1)*$I$3 -> 1.6264946 | H19: =H18*(1+$O$19)^($D$17-H17-1)*$I$3 -> 1.5082041 | I19: =I18*(1+$O$19)^($D$17-I17-1)*$I$3 -> 1.3985165 | J19: =J18*(1+$O$19)^($D$17-J17-1)*$I$3 -> 1.2968062 | K19: =K18*(1+$O$19)^($D$17-K17-1)*$I$3 -> 1.202493 | ... M19: =M18*(1+$O$19)^($D$17-M17-1)*$I$3 -> 1.0339453 | N19: =N18*(1+$O$19)^($D$17-N17-1) -> 15.205077 | O19: =O13 -> 0.1 | P19: Discount rate
B20: SAFETY | C20: Present value sum | D20: =SUM(D19:N19) -> 30.072275 | O20: 15 | P20: Terminal multiple
C22: Scenario | D22: Probability | E22: PV | F22: Part
C23: Scenario 1 (normal case) | D23: 0.34 | E23: =D8 -> 40.515633 | F23: =E23*D23 -> 13.775315
C24: Scenario 2 (best case) | D24: 0.33 | E24: =D14 -> 53.872005 | F24: =E24*D24 -> 17.777762
C25: Scenario 3 (worst case) | D25: 0.33 | E25: =D20 -> 30.072275 | F25: =E25*D25 -> 9.9238508
C26: STOCK PRICE NOW | D26: =C3 -> 52.1 | E26: Sum | F26: =SUM(F23:F25) -> 41.476928
B28: Disclaimer: This is just for educational purposes and not for investing advice!
B30: MADE BY | C30: STOCK MARKET RESEARCH PLATFORM

Sheet Clarks
S1: input cells
B2: Clarksons | C2: LINK TO RESEARCH | S2: result cells
B3: STOCK PRICE | C3: ='COMPARATIVE TABLE'!C14 -> 3455 | F3: DIVIDEND PAYOUT RATIO | I3: 1
B4: COMPARATIVE TABLE'!A1 | N4: Terminal Value | O4: Growth rate
B5: Scenario 1 | C5: Dividend per share | D5: 2025 | E5: =D5+1 -> 2026 | F5: =E5+1 -> 2027 | G5: =F5+1 -> 2028 | H5: =G5+1 -> 2029 | I5: =H5+1 -> 2030 | J5: =I5+1 -> 2031 | K5: =J5+1 -> 2032 | L5: =K5+1 -> 2033 | M5: =L5+1 -> 2034 | N5: 2034 | O5: 0.06 | P5: next 5 years
B6: normal case | C6: 109 | D6: =C6*(1+$O$5) -> 115.54 | E6: =D6*(1+$O$5) -> 122.4724 | F6: =E6*(1+$O$5) -> 129.82074 | G6: =F6*(1+$O$5) -> 137.60999 | H6: =G6*(1+$O$5) -> 145.86659 | I6: =H6*(1+$O$6) -> 154.61858 | J6: =I6*(1+$O$6) -> 163.8957 | K6: =J6*(1+$O$6) -> 173.72944 | L6: =K6*(1+$O$6) -> 184.15321 | M6: =L6*(1+$O$6) -> 195.2024 | N6: =L6*O8 -> 3683.0641 | O6: 0.06 | P6: 5 to 10 years
C7: =CONCATENATE(R8,O7*100,S8) -> PV(10%) | D7: =D6*(1+$O$7)^($D$5-D5-1)*$I$3 -> 105.03636 | E7: =E6*(1+$O$7)^($D$5-E5-1)*$I$3 -> 101.21686 | F7: =F6*(1+$O$7)^($D$5-F5-1)*$I$3 -> 97.536246 | G7: =G6*(1+$O$7)^($D$5-G5-1)*$I$3 -> 93.989474 | H7: =H6*(1+$O$7)^($D$5-H5-1)*$I$3 -> 90.571675 | I7: =I6*(1+$O$7)^($D$5-I5-1)*$I$3 -> 87.278159 | J7: =J6*(1+$O$7)^($D$5-J5-1)*$I$3 -> 84.104408 | K7: =K6*(1+$O$7)^($D$5-K5-1)*$I$3 -> 81.046066 | ... M7: =M6*(1+$O$7)^($D$5-M5-1)*$I$3 -> 75.258975 | N7: =N6*(1+$O$7)^($D$5-N5-1) -> 1419.9807 | O7: 0.1 | P7: Discount rate
C8: INTRINSIC VALUE | D8: =SUM(D7:N7) -> 2314.1178 | O8: 20 | P8: Terminal multiple | R8: PV( | S8: %)
N10: Terminal Value | O10: Growth rate
B11: Scenario 2 | C11: =C5 -> Dividend per share | D11: =D5 -> 2025 | E11: =D11+1 -> 2026 | F11: =E11+1 -> 2027 | G11: =F11+1 -> 2028 | H11: =G11+1 -> 2029 | I11: =H11+1 -> 2030 | J11: =I11+1 -> 2031 | K11: =J11+1 -> 2032 | L11: =K11+1 -> 2033 | M11: =L11+1 -> 2034 | N11: =N5 -> 2034 | O11: 0.07 | P11: next 5 years
B12: best case | C12: =C6 -> 109 | D12: =C12*(1+$O$11) -> 116.63 | E12: =D12*(1+$O$11) -> 124.7941 | F12: =E12*(1+$O$11) -> 133.52969 | G12: =F12*(1+$O$11) -> 142.87677 | H12: =G12*(1+$O$11) -> 152.87814 | I12: =H12*(1+$O$12) -> 163.57961 | J12: =I12*(1+$O$12) -> 175.03018 | K12: =J12*(1+$O$12) -> 187.28229 | L12: =K12*(1+$O$12) -> 200.39205 | M12: =L12*(1+$O$12) -> 214.4195 | N12: =L12*O14 -> 5009.8014 | O12: 0.07 | P12: 5 to 10 years
B13: =B7 -> 0 | C13: =C7 -> PV(10%) | D13: =D12*(1+$O$13)^($D$11-D11-1)*$I$3 -> 106.02727 | E13: =E12*(1+$O$13)^($D$11-E11-1)*$I$3 -> 103.13562 | F13: =F12*(1+$O$13)^($D$11-F11-1)*$I$3 -> 100.32283 | G13: =G12*(1+$O$13)^($D$11-G11-1)*$I$3 -> 97.586753 | H13: =H12*(1+$O$13)^($D$11-H11-1)*$I$3 -> 94.925296 | I13: =I12*(1+$O$13)^($D$11-I11-1)*$I$3 -> 92.336424 | J13: =J12*(1+$O$13)^($D$11-J11-1)*$I$3 -> 89.818158 | K13: =K12*(1+$O$13)^($D$11-K11-1)*$I$3 -> 87.368572 | ... M13: =M12*(1+$O$13)^($D$11-M11-1)*$I$3 -> 82.667999 | N13: =N12*(1+$O$7)^($D$5-N11-1) -> 1931.4953 | O13: =O7 -> 0.1 | P13: Discount rate
C14: Present value sum | D14: =SUM(D13:N13) -> 2870.67 | O14: 25 | P14: Terminal multiple
N16: Terminal Value | O16: Growth rate
B17: Scenario 3 | C17: =C11 -> Dividend per share | D17: =D11 -> 2025 | E17: =D17+1 -> 2026 | F17: =E17+1 -> 2027 | G17: =F17+1 -> 2028 | H17: =G17+1 -> 2029 | I17: =H17+1 -> 2030 | J17: =I17+1 -> 2031 | K17: =J17+1 -> 2032 | L17: =K17+1 -> 2033 | M17: =L17+1 -> 2034 | N17: =N11 -> 2034 | O17: 0.04 | P17: next 5 years
B18: worst case | C18: =C12 -> 109 | D18: =C18*(1+$O$17) -> 113.36 | E18: =D18*(1+$O$17) -> 117.8944 | F18: =E18*(1+$O$17) -> 122.61018 | G18: =F18*(1+$O$17) -> 127.51458 | H18: =G18*(1+$O$17) -> 132.61517 | I18: =H18*(1+$O$18) -> 137.91977 | J18: =I18*(1+$O$18) -> 143.43656 | K18: =J18*(1+$O$18) -> 149.17403 | L18: =K18*(1+$O$18) -> 155.14099 | M18: =L18*(1+$O$18) -> 161.34663 | N18: =L18*O20 -> 2327.1148 | O18: 0.04 | P18: 5 to 10 years
B19: MARGIN OF | C19: =C13 -> PV(10%) | D19: =D18*(1+$O$19)^($D$17-D17-1)*$I$3 -> 103.05455 | E19: =E18*(1+$O$19)^($D$17-E17-1)*$I$3 -> 97.433388 | F19: =F18*(1+$O$19)^($D$17-F17-1)*$I$3 -> 92.11884 | G19: =G18*(1+$O$19)^($D$17-G17-1)*$I$3 -> 87.094176 | H19: =H18*(1+$O$19)^($D$17-H17-1)*$I$3 -> 82.343585 | I19: =I18*(1+$O$19)^($D$17-I17-1)*$I$3 -> 77.852116 | J19: =J18*(1+$O$19)^($D$17-J17-1)*$I$3 -> 73.605637 | K19: =K18*(1+$O$19)^($D$17-K17-1)*$I$3 -> 69.590784 | ... M19: =M18*(1+$O$19)^($D$17-M17-1)*$I$3 -> 62.206109 | N19: =N18*(1+$O$19)^($D$17-N17-1) -> 897.2035 | O19: =O13 -> 0.1 | P19: Discount rate
B20: SAFETY | C20: Present value sum | D20: =SUM(D19:N19) -> 1708.2976 | O20: 15 | P20: Terminal multiple
C22: Scenario | D22: Probability | E22: PV | F22: Part
C23: Scenario 1 (normal case) | D23: 0.34 | E23: =D8 -> 2314.1178 | F23: =E23*D23 -> 786.80006
C24: Scenario 2 (best case) | D24: 0.33 | E24: =D14 -> 2870.67 | F24: =E24*D24 -> 947.3211
C25: Scenario 3 (worst case) | D25: 0.33 | E25: =D20 -> 1708.2976 | F25: =E25*D25 -> 563.73821
C26: STOCK PRICE NOW | D26: =C3 -> 3455 | E26: Sum | F26: =SUM(F23:F25) -> 2297.8594
B28: Disclaimer: This is just for educational purposes and not for investing advice!
B30: MADE BY | C30: STOCK MARKET RESEARCH PLATFORM

Sheet FP
S1: input cells
B2: First Pacific | C2: LINK TO RESEARCH | S2: result cells
B3: STOCK PRICE | C3: ='COMPARATIVE TABLE'!C15 -> 6.67 | F3: DIVIDEND PAYOUT RATIO | I3: 1
B4: COMPARATIVE TABLE'!A1 | N4: Terminal Value | O4: Growth rate
B5: Scenario 1 | C5: Dividend per share | D5: 2025 | E5: =D5+1 -> 2026 | F5: =E5+1 -> 2027 | G5: =F5+1 -> 2028 | H5: =G5+1 -> 2029 | I5: =H5+1 -> 2030 | J5: =I5+1 -> 2031 | K5: =J5+1 -> 2032 | L5: =K5+1 -> 2033 | M5: =L5+1 -> 2034 | N5: 2034 | O5: 0.05 | P5: next 5 years
B6: normal case | C6: 0.24 | D6: =C6*(1+$O$5) -> 0.252 | E6: =D6*(1+$O$5) -> 0.2646 | F6: =E6*(1+$O$5) -> 0.27783 | G6: =F6*(1+$O$5) -> 0.2917215 | H6: =G6*(1+$O$5) -> 0.30630758 | I6: =H6*(1+$O$6) -> 0.32162295 | J6: =I6*(1+$O$6) -> 0.3377041 | K6: =J6*(1+$O$6) -> 0.35458931 | L6: =K6*(1+$O$6) -> 0.37231877 | M6: =L6*(1+$O$6) -> 0.39093471 | N6: =L6*O8 -> 5.5847816 | O6: 0.05 | P6: 5 to 10 years
C7: =CONCATENATE(R8,O7*100,S8) -> PV(10%) | D7: =D6*(1+$O$7)^($D$5-D5-1)*$I$3 -> 0.22909091 | E7: =E6*(1+$O$7)^($D$5-E5-1)*$I$3 -> 0.21867769 | F7: =F6*(1+$O$7)^($D$5-F5-1)*$I$3 -> 0.20873779 | G7: =G6*(1+$O$7)^($D$5-G5-1)*$I$3 -> 0.19924971 | H7: =H6*(1+$O$7)^($D$5-H5-1)*$I$3 -> 0.1901929 | I7: =I6*(1+$O$7)^($D$5-I5-1)*$I$3 -> 0.18154777 | J7: =J6*(1+$O$7)^($D$5-J5-1)*$I$3 -> 0.1732956 | K7: =K6*(1+$O$7)^($D$5-K5-1)*$I$3 -> 0.16541853 | ... M7: =M6*(1+$O$7)^($D$5-M5-1)*$I$3 -> 0.15072225 | N7: =N6*(1+$O$7)^($D$5-N5-1) -> 2.1531751 | O7: 0.1 | P7: Discount rate
C8: INTRINSIC VALUE | D8: =SUM(D7:N7) -> 4.0280077 | O8: 15 | P8: Terminal multiple | R8: PV( | S8: %)
N10: Terminal Value | O10: Growth rate
B11: Scenario 2 | C11: =C5 -> Dividend per share | D11: =D5 -> 2025 | E11: =D11+1 -> 2026 | F11: =E11+1 -> 2027 | G11: =F11+1 -> 2028 | H11: =G11+1 -> 2029 | I11: =H11+1 -> 2030 | J11: =I11+1 -> 2031 | K11: =J11+1 -> 2032 | L11: =K11+1 -> 2033 | M11: =L11+1 -> 2034 | N11: =N5 -> 2034 | O11: 0.07 | P11: next 5 years
B12: best case | C12: =C6 -> 0.24 | D12: =C12*(1+$O$11) -> 0.2568 | E12: =D12*(1+$O$11) -> 0.274776 | F12: =E12*(1+$O$11) -> 0.29401032 | G12: =F12*(1+$O$11) -> 0.31459104 | H12: =G12*(1+$O$11) -> 0.33661242 | I12: =H12*(1+$O$12) -> 0.36017528 | J12: =I12*(1+$O$12) -> 0.38538755 | K12: =J12*(1+$O$12) -> 0.41236468 | L12: =K12*(1+$O$12) -> 0.44123021 | M12: =L12*(1+$O$12) -> 0.47211633 | N12: =L12*O14 -> 8.8246042 | O12: 0.07 | P12: 5 to 10 years
B13: =B7 -> 0 | C13: =C7 -> PV(10%) | D13: =D12*(1+$O$13)^($D$11-D11-1)*$I$3 -> 0.23345455 | E13: =E12*(1+$O$13)^($D$11-E11-1)*$I$3 -> 0.2270876 | F13: =F12*(1+$O$13)^($D$11-F11-1)*$I$3 -> 0.22089431 | G13: =G12*(1+$O$13)^($D$11-G11-1)*$I$3 -> 0.21486991 | H13: =H12*(1+$O$13)^($D$11-H11-1)*$I$3 -> 0.20900983 | I13: =I12*(1+$O$13)^($D$11-I11-1)*$I$3 -> 0.20330956 | J13: =J12*(1+$O$13)^($D$11-J11-1)*$I$3 -> 0.19776475 | K13: =K12*(1+$O$13)^($D$11-K11-1)*$I$3 -> 0.19237117 | ... M13: =M12*(1+$O$13)^($D$11-M11-1)*$I$3 -> 0.18202128 | N13: =N12*(1+$O$7)^($D$5-N11-1) -> 3.4022669 | O13: =O7 -> 0.1 | P13: Discount rate
C14: Present value sum | D14: =SUM(D13:N13) -> 5.4701746 | O14: 20 | P14: Terminal multiple
N16: Terminal Value | O16: Growth rate
B17: Scenario 3 | C17: =C11 -> Dividend per share | D17: =D11 -> 2025 | E17: =D17+1 -> 2026 | F17: =E17+1 -> 2027 | G17: =F17+1 -> 2028 | H17: =G17+1 -> 2029 | I17: =H17+1 -> 2030 | J17: =I17+1 -> 2031 | K17: =J17+1 -> 2032 | L17: =K17+1 -> 2033 | M17: =L17+1 -> 2034 | N17: =N11 -> 2034 | O17: 0.03 | P17: next 5 years
B18: worst case | C18: =C12 -> 0.24 | D18: =C18*(1+$O$17) -> 0.2472 | E18: =D18*(1+$O$17) -> 0.254616 | F18: =E18*(1+$O$17) -> 0.26225448 | G18: =F18*(1+$O$17) -> 0.27012211 | H18: =G18*(1+$O$17) -> 0.27822578 | I18: =H18*(1+$O$18) -> 0.28657255 | J18: =I18*(1+$O$18) -> 0.29516973 | K18: =J18*(1+$O$18) -> 0.30402482 | L18: =K18*(1+$O$18) -> 0.31314556 | M18: =L18*(1+$O$18) -> 0.32253993 | N18: =L18*O20 -> 3.7577468 | O18: 0.03 | P18: 5 to 10 years
B19: MARGIN OF | C19: =C13 -> PV(10%) | D19: =D18*(1+$O$19)^($D$17-D17-1)*$I$3 -> 0.22472727 | E19: =E18*(1+$O$19)^($D$17-E17-1)*$I$3 -> 0.21042645 | F19: =F18*(1+$O$19)^($D$17-F17-1)*$I$3 -> 0.19703567 | G19: =G18*(1+$O$19)^($D$17-G17-1)*$I$3 -> 0.18449704 | H19: =H18*(1+$O$19)^($D$17-H17-1)*$I$3 -> 0.17275632 | I19: =I18*(1+$O$19)^($D$17-I17-1)*$I$3 -> 0.16176273 | J19: =J18*(1+$O$19)^($D$17-J17-1)*$I$3 -> 0.15146874 | K19: =K18*(1+$O$19)^($D$17-K17-1)*$I$3 -> 0.14182982 | ... M19: =M18*(1+$O$19)^($D$17-M17-1)*$I$3 -> 0.12435311 | N19: =N18*(1+$O$19)^($D$17-N17-1) -> 1.4487741 | O19: =O13 -> 0.1 | P19: Discount rate
B20: SAFETY | C20: Present value sum | D20: =SUM(D19:N19) -> 3.1504355 | O20: 12 | P20: Terminal multiple
C22: Scenario | D22: Probability | E22: PV | F22: Part
C23: Scenario 1 (normal case) | D23: 0.34 | E23: =D8 -> 4.0280077 | F23: =E23*D23 -> 1.3695226
C24: Scenario 2 (best case) | D24: 0.33 | E24: =D14 -> 5.4701746 | F24: =E24*D24 -> 1.8051576
C25: Scenario 3 (worst case) | D25: 0.33 | E25: =D20 -> 3.1504355 | F25: =E25*D25 -> 1.0396437
C26: STOCK PRICE NOW | D26: =C3 -> 6.67 | E26: Sum | F26: =SUM(F23:F25) -> 4.2143239
B28: Disclaimer: This is just for educational purposes and not for investing advice!
B30: MADE BY | C30: STOCK MARKET RESEARCH PLATFORM

Sheet FLOW
S1: input cells
B2: FLOW TRADERS | C2: LINK TO RESEARCH | S2: result cells
B3: STOCK PRICE | C3: ='COMPARATIVE TABLE'!C16 -> 24.92 | F3: DIVIDEND PAYOUT RATIO | I3: 0
B4: COMPARATIVE TABLE'!A1 | N4: Terminal Value | O4: Growth rate
B5: Scenario 1 | C5: Earnings per share | D5: 2025 | E5: =D5+1 -> 2026 | F5: =E5+1 -> 2027 | G5: =F5+1 -> 2028 | H5: =G5+1 -> 2029 | I5: =H5+1 -> 2030 | J5: =I5+1 -> 2031 | K5: =J5+1 -> 2032 | L5: =K5+1 -> 2033 | M5: =L5+1 -> 2034 | N5: 2034 | O5: 0.1 | P5: next 5 years
B6: normal case | C6: 3 | D6: =C6*(1+$O$5) -> 3.3 | E6: =D6*(1+$O$5) -> 3.63 | F6: =E6*(1+$O$5) -> 3.993 | G6: =F6*(1+$O$5) -> 4.3923 | H6: =G6*(1+$O$5) -> 4.83153 | I6: =H6*(1+$O$6) -> 5.1697371 | J6: =I6*(1+$O$6) -> 5.5316187 | K6: =J6*(1+$O$6) -> 5.918832 | L6: =K6*(1+$O$6) -> 6.3331502 | M6: =L6*(1+$O$6) -> 6.7764708 | N6: =L6*O8 -> 94.997254 | O6: 0.07 | P6: 5 to 10 years
C7: =CONCATENATE(R8,O7*100,S8) -> PV(10%) | D7: =D6*(1+$O$7)^($D$5-D5-1)*$I$3 -> 0 | E7: =E6*(1+$O$7)^($D$5-E5-1)*$I$3 -> 0 | F7: =F6*(1+$O$7)^($D$5-F5-1)*$I$3 -> 0 | G7: =G6*(1+$O$7)^($D$5-G5-1)*$I$3 -> 0 | H7: =H6*(1+$O$7)^($D$5-H5-1)*$I$3 -> 0 | I7: =I6*(1+$O$7)^($D$5-I5-1)*$I$3 -> 0 | J7: =J6*(1+$O$7)^($D$5-J5-1)*$I$3 -> 0 | K7: =K6*(1+$O$7)^($D$5-K5-1)*$I$3 -> 0 | ... M7: =M6*(1+$O$7)^($D$5-M5-1)*$I$3 -> 0 | N7: =N6*(1+$O$7)^($D$5-N5-1) -> 36.625554 | O7: 0.1 | P7: Discount rate
C8: INTRINSIC VALUE | D8: =SUM(D7:N7) -> 36.625554 | O8: 15 | P8: Terminal multiple | R8: PV( | S8: %)
N10: Terminal Value | O10: Growth rate
B11: Scenario 2 | C11: =C5 -> Earnings per share | D11: =D5 -> 2025 | E11: =D11+1 -> 2026 | F11: =E11+1 -> 2027 | G11: =F11+1 -> 2028 | H11: =G11+1 -> 2029 | I11: =H11+1 -> 2030 | J11: =I11+1 -> 2031 | K11: =J11+1 -> 2032 | L11: =K11+1 -> 2033 | M11: =L11+1 -> 2034 | N11: =N5 -> 2034 | O11: 0.15 | P11: next 5 years
B12: best case | C12: =C6 -> 3 | D12: =C12*(1+$O$11) -> 3.45 | E12: =D12*(1+$O$11) -> 3.9675 | F12: =E12*(1+$O$11) -> 4.562625 | G12: =F12*(1+$O$11) -> 5.2470187 | H12: =G12*(1+$O$11) -> 6.0340716 | I12: =H12*(1+$O$12) -> 6.6374787 | J12: =I12*(1+$O$12) -> 7.3012266 | K12: =J12*(1+$O$12) -> 8.0313492 | L12: =K12*(1+$O$12) -> 8.8344842 | M12: =L12*(1+$O$12) -> 9.7179326 | N12: =L12*O14 -> 176.68968 | O12: 0.1 | P12: 5 to 10 years
B13: =B7 -> 0 | C13: =C7 -> PV(10%) | D13: =D12*(1+$O$13)^($D$11-D11-1)*$I$3 -> 0 | E13: =E12*(1+$O$13)^($D$11-E11-1)*$I$3 -> 0 | F13: =F12*(1+$O$13)^($D$11-F11-1)*$I$3 -> 0 | G13: =G12*(1+$O$13)^($D$11-G11-1)*$I$3 -> 0 | H13: =H12*(1+$O$13)^($D$11-H11-1)*$I$3 -> 0 | I13: =I12*(1+$O$13)^($D$11-I11-1)*$I$3 -> 0 | J13: =J12*(1+$O$13)^($D$11-J11-1)*$I$3 -> 0 | K13: =K12*(1+$O$13)^($D$11-K11-1)*$I$3 -> 0 | ... M13: =M12*(1+$O$13)^($D$11-M11-1)*$I$3 -> 0 | N13: =N12*(1+$O$7)^($D$5-N11-1) -> 68.121522 | O13: =O7 -> 0.1 | P13: Discount rate
C14: Present value sum | D14: =SUM(D13:N13) -> 68.121522 | O14: 20 | P14: Terminal multiple
N16: Terminal Value | O16: Growth rate
B17: Scenario 3 | C17: =C11 -> Earnings per share | D17: =D11 -> 2025 | E17: =D17+1 -> 2026 | F17: =E17+1 -> 2027 | G17: =F17+1 -> 2028 | H17: =G17+1 -> 2029 | I17: =H17+1 -> 2030 | J17: =I17+1 -> 2031 | K17: =J17+1 -> 2032 | L17: =K17+1 -> 2033 | M17: =L17+1 -> 2034 | N17: =N11 -> 2034 | O17: 0.05 | P17: next 5 years
B18: worst case | C18: =C12 -> 3 | D18: =C18*(1+$O$17) -> 3.15 | E18: =D18*(1+$O$17) -> 3.3075 | F18: =E18*(1+$O$17) -> 3.472875 | G18: =F18*(1+$O$17) -> 3.6465188 | H18: =G18*(1+$O$17) -> 3.8288447 | I18: =H18*(1+$O$18) -> 4.0202869 | J18: =I18*(1+$O$18) -> 4.2213013 | K18: =J18*(1+$O$18) -> 4.4323663 | L18: =K18*(1+$O$18) -> 4.6539846 | M18: =L18*(1+$O$18) -> 4.8866839 | N18: =L18*O20 -> 46.539846 | O18: 0.05 | P18: 5 to 10 years
B19: MARGIN OF | C19: =C13 -> PV(10%) | D19: =D18*(1+$O$19)^($D$17-D17-1)*$I$3 -> 0 | E19: =E18*(1+$O$19)^($D$17-E17-1)*$I$3 -> 0 | F19: =F18*(1+$O$19)^($D$17-F17-1)*$I$3 -> 0 | G19: =G18*(1+$O$19)^($D$17-G17-1)*$I$3 -> 0 | H19: =H18*(1+$O$19)^($D$17-H17-1)*$I$3 -> 0 | I19: =I18*(1+$O$19)^($D$17-I17-1)*$I$3 -> 0 | J19: =J18*(1+$O$19)^($D$17-J17-1)*$I$3 -> 0 | K19: =K18*(1+$O$19)^($D$17-K17-1)*$I$3 -> 0 | ... M19: =M18*(1+$O$19)^($D$17-M17-1)*$I$3 -> 0 | N19: =N18*(1+$O$19)^($D$17-N17-1) -> 17.943126 | O19: =O13 -> 0.1 | P19: Discount rate
B20: SAFETY | C20: Present value sum | D20: =SUM(D19:N19) -> 17.943126 | O20: 10 | P20: Terminal multiple
C22: Scenario | D22: Probability | E22: PV | F22: Part
C23: Scenario 1 (normal case) | D23: 0.5 | E23: =D8 -> 36.625554 | F23: =E23*D23 -> 18.312777
C24: Scenario 2 (best case) | D24: 0.25 | E24: =D14 -> 68.121522 | F24: =E24*D24 -> 17.03038
C25: Scenario 3 (worst case) | D25: 0.25 | E25: =D20 -> 17.943126 | F25: =E25*D25 -> 4.4857814
C26: STOCK PRICE NOW | D26: =C3 -> 24.92 | E26: Sum | F26: =SUM(F23:F25) -> 39.828939
B28: Disclaimer: This is just for educational purposes and not for investing advice!
B30: MADE BY | C30: STOCK MARKET RESEARCH PLATFORM

Sheet ICL
S1: input cells
B2: ICL | C2: LINK TO RESEARCH | S2: result cells
B3: STOCK PRICE | C3: ='COMPARATIVE TABLE'!C18 -> 6.25 | F3: DIVIDEND PAYOUT RATIO | I3: 0.5
B4: COMPARATIVE TABLE'!A1 | N4: Terminal Value | O4: Growth rate
B5: Scenario 1 | C5: FCF | D5: 2025 | E5: =D5+1 -> 2026 | F5: =E5+1 -> 2027 | G5: =F5+1 -> 2028 | H5: =G5+1 -> 2029 | I5: =H5+1 -> 2030 | J5: =I5+1 -> 2031 | K5: =J5+1 -> 2032 | L5: =K5+1 -> 2033 | M5: =L5+1 -> 2034 | N5: 2034 | O5: 0.04 | P5: next 5 years
B6: normal case | C6: 0.4 | D6: =C6*(1+$O$5) -> 0.416 | E6: =D6*(1+$O$5) -> 0.43264 | F6: =E6*(1+$O$5) -> 0.4499456 | G6: =F6*(1+$O$5) -> 0.46794342 | H6: =G6*(1+$O$5) -> 0.48666116 | I6: =H6*(1+$O$6) -> 0.50612761 | J6: =I6*(1+$O$6) -> 0.52637271 | K6: =J6*(1+$O$6) -> 0.54742762 | L6: =K6*(1+$O$6) -> 0.56932472 | M6: =L6*(1+$O$6) -> 0.59209771 | N6: =L6*O8 -> 6.8318967 | O6: 0.04 | P6: 5 to 10 years
C7: =CONCATENATE(R8,O7*100,S8) -> PV(10%) | D7: =D6*(1+$O$7)^($D$5-D5-1)*$I$3 -> 0.18909091 | E7: =E6*(1+$O$7)^($D$5-E5-1)*$I$3 -> 0.17877686 | F7: =F6*(1+$O$7)^($D$5-F5-1)*$I$3 -> 0.16902539 | G7: =G6*(1+$O$7)^($D$5-G5-1)*$I$3 -> 0.15980583 | H7: =H6*(1+$O$7)^($D$5-H5-1)*$I$3 -> 0.15108915 | I7: =I6*(1+$O$7)^($D$5-I5-1)*$I$3 -> 0.14284792 | J7: =J6*(1+$O$7)^($D$5-J5-1)*$I$3 -> 0.13505622 | K7: =K6*(1+$O$7)^($D$5-K5-1)*$I$3 -> 0.12768951 | ... M7: =M6*(1+$O$7)^($D$5-M5-1)*$I$3 -> 0.11413965 | N7: =N6*(1+$O$7)^($D$5-N5-1) -> 2.6339919 | O7: 0.1 | P7: Discount rate
C8: INTRINSIC VALUE | D8: =SUM(D7:N7) -> 4.122238 | O8: 12 | P8: Terminal multiple | R8: PV( | S8: %)
N10: Terminal Value | O10: Growth rate
B11: Scenario 2 | C11: =C5 -> FCF | D11: =D5 -> 2025 | E11: =D11+1 -> 2026 | F11: =E11+1 -> 2027 | G11: =F11+1 -> 2028 | H11: =G11+1 -> 2029 | I11: =H11+1 -> 2030 | J11: =I11+1 -> 2031 | K11: =J11+1 -> 2032 | L11: =K11+1 -> 2033 | M11: =L11+1 -> 2034 | N11: =N5 -> 2034 | O11: 0.07 | P11: next 5 years
B12: best case | C12: =C6 -> 0.4 | D12: =C12*(1+$O$11) -> 0.428 | E12: =D12*(1+$O$11) -> 0.45796 | F12: =E12*(1+$O$11) -> 0.4900172 | G12: =F12*(1+$O$11) -> 0.5243184 | H12: =G12*(1+$O$11) -> 0.56102069 | I12: =H12*(1+$O$12) -> 0.60029214 | J12: =I12*(1+$O$12) -> 0.64231259 | K12: =J12*(1+$O$12) -> 0.68727447 | L12: =K12*(1+$O$12) -> 0.73538368 | M12: =L12*(1+$O$12) -> 0.78686054 | N12: =L12*O14 -> 11.030755 | O12: 0.07 | P12: 5 to 10 years
B13: =B7 -> 0 | C13: =C7 -> PV(10%) | D13: =D12*(1+$O$13)^($D$11-D11-1)*$I$3 -> 0.19454545 | E13: =E12*(1+$O$13)^($D$11-E11-1)*$I$3 -> 0.18923967 | F13: =F12*(1+$O$13)^($D$11-F11-1)*$I$3 -> 0.18407859 | G13: =G12*(1+$O$13)^($D$11-G11-1)*$I$3 -> 0.17905826 | H13: =H12*(1+$O$13)^($D$11-H11-1)*$I$3 -> 0.17417486 | I13: =I12*(1+$O$13)^($D$11-I11-1)*$I$3 -> 0.16942463 | J13: =J12*(1+$O$13)^($D$11-J11-1)*$I$3 -> 0.16480396 | K13: =K12*(1+$O$13)^($D$11-K11-1)*$I$3 -> 0.16030931 | ... M13: =M12*(1+$O$13)^($D$11-M11-1)*$I$3 -> 0.1516844 | N13: =N12*(1+$O$7)^($D$5-N11-1) -> 4.2528337 | O13: =O7 -> 0.1 | P13: Discount rate
C14: Present value sum | D14: =SUM(D13:N13) -> 5.97609 | O14: 15 | P14: Terminal multiple
N16: Terminal Value | O16: Growth rate
B17: Scenario 3 | C17: =C11 -> FCF | D17: =D11 -> 2025 | E17: =D17+1 -> 2026 | F17: =E17+1 -> 2027 | G17: =F17+1 -> 2028 | H17: =G17+1 -> 2029 | I17: =H17+1 -> 2030 | J17: =I17+1 -> 2031 | K17: =J17+1 -> 2032 | L17: =K17+1 -> 2033 | M17: =L17+1 -> 2034 | N17: =N11 -> 2034 | O17: 0.03 | P17: next 5 years
B18: worst case | C18: =C12 -> 0.4 | D18: =C18*(1+$O$17) -> 0.412 | E18: =D18*(1+$O$17) -> 0.42436 | F18: =E18*(1+$O$17) -> 0.4370908 | G18: =F18*(1+$O$17) -> 0.45020352 | H18: =G18*(1+$O$17) -> 0.46370963 | I18: =H18*(1+$O$18) -> 0.47762092 | J18: =I18*(1+$O$18) -> 0.49194955 | K18: =J18*(1+$O$18) -> 0.50670803 | L18: =K18*(1+$O$18) -> 0.52190927 | M18: =L18*(1+$O$18) -> 0.53756655 | N18: =L18*O20 -> 5.2190927 | O18: 0.03 | P18: 5 to 10 years
B19: MARGIN OF | C19: =C13 -> PV(10%) | D19: =D18*(1+$O$19)^($D$17-D17-1)*$I$3 -> 0.18727273 | E19: =E18*(1+$O$19)^($D$17-E17-1)*$I$3 -> 0.17535537 | F19: =F18*(1+$O$19)^($D$17-F17-1)*$I$3 -> 0.16419639 | G19: =G18*(1+$O$19)^($D$17-G17-1)*$I$3 -> 0.15374753 | H19: =H18*(1+$O$19)^($D$17-H17-1)*$I$3 -> 0.1439636 | I19: =I18*(1+$O$19)^($D$17-I17-1)*$I$3 -> 0.13480228 | J19: =J18*(1+$O$19)^($D$17-J17-1)*$I$3 -> 0.12622395 | K19: =K18*(1+$O$19)^($D$17-K17-1)*$I$3 -> 0.11819152 | ... M19: =M18*(1+$O$19)^($D$17-M17-1)*$I$3 -> 0.10362759 | N19: =N18*(1+$O$19)^($D$17-N17-1) -> 2.0121862 | O19: =O13 -> 0.1 | P19: Discount rate
B20: SAFETY | C20: Present value sum | D20: =SUM(D19:N19) -> 3.4302374 | O20: 10 | P20: Terminal multiple
C22: Scenario | D22: Probability | E22: PV | F22: Part
C23: Scenario 1 (normal case) | D23: 0.34 | E23: =D8 -> 4.122238 | F23: =E23*D23 -> 1.4015609
C24: Scenario 2 (best case) | D24: 0.33 | E24: =D14 -> 5.97609 | F24: =E24*D24 -> 1.9721097
C25: Scenario 3 (worst case) | D25: 0.33 | E25: =D20 -> 3.4302374 | F25: =E25*D25 -> 1.1319783
C26: STOCK PRICE NOW | D26: =C3 -> 6.25 | E26: Sum | F26: =SUM(F23:F25) -> 4.505649
B28: Disclaimer: This is just for educational purposes and not for investing advice!
B30: MADE BY | C30: STOCK MARKET RESEARCH PLATFORM

Sheet LBTYK
S1: input cells
B2: Liberty Global | C2: LINK TO RESEARCH | S2: result cells
B3: STOCK PRICE | C3: ='COMPARATIVE TABLE'!C20 -> 11.71 | F3: DIVIDEND PAYOUT RATIO | I3: 0
B4: COMPARATIVE TABLE'!A1 | N4: Terminal Value | O4: Growth rate
B5: Scenario 1 | C5: FCF (500 million) | D5: 2025 | E5: =D5+1 -> 2026 | F5: =E5+1 -> 2027 | G5: =F5+1 -> 2028 | H5: =G5+1 -> 2029 | I5: =H5+1 -> 2030 | J5: =I5+1 -> 2031 | K5: =J5+1 -> 2032 | L5: =K5+1 -> 2033 | M5: =L5+1 -> 2034 | N5: 2034 | O5: 0.07 | P5: next 5 years
B6: normal case | C6: 1.44 | D6: =C6*(1+$O$5) -> 1.5408 | E6: =D6*(1+$O$5) -> 1.648656 | F6: =E6*(1+$O$5) -> 1.7640619 | G6: =F6*(1+$O$5) -> 1.8875463 | H6: =G6*(1+$O$5) -> 2.0196745 | I6: =H6*(1+$O$6) -> 2.1610517 | J6: =I6*(1+$O$6) -> 2.3123253 | K6: =J6*(1+$O$6) -> 2.4741881 | L6: =K6*(1+$O$6) -> 2.6473813 | M6: =L6*(1+$O$6) -> 2.832698 | N6: =L6*O8 -> 31.768575 | O6: 0.07 | P6: 5 to 10 years
C7: =CONCATENATE(R8,O7*100,S8) -> PV(10%) | D7: =D6*(1+$O$7)^($D$5-D5-1)*$I$3 -> 0 | E7: =E6*(1+$O$7)^($D$5-E5-1)*$I$3 -> 0 | F7: =F6*(1+$O$7)^($D$5-F5-1)*$I$3 -> 0 | G7: =G6*(1+$O$7)^($D$5-G5-1)*$I$3 -> 0 | H7: =H6*(1+$O$7)^($D$5-H5-1)*$I$3 -> 0 | I7: =I6*(1+$O$7)^($D$5-I5-1)*$I$3 -> 0 | J7: =J6*(1+$O$7)^($D$5-J5-1)*$I$3 -> 0 | K7: =K6*(1+$O$7)^($D$5-K5-1)*$I$3 -> 0 | ... M7: =M6*(1+$O$7)^($D$5-M5-1)*$I$3 -> 0 | N7: =N6*(1+$O$7)^($D$5-N5-1) -> 12.248161 | O7: 0.1 | P7: Discount rate
C8: INTRINSIC VALUE | D8: =SUM(D7:N7) -> 12.248161 | O8: 12 | P8: Terminal multiple | R8: PV( | S8: %)
N10: Terminal Value | O10: Growth rate
B11: Scenario 2 | C11: =C5 -> FCF (500 million) | D11: =D5 -> 2025 | E11: =D11+1 -> 2026 | F11: =E11+1 -> 2027 | G11: =F11+1 -> 2028 | H11: =G11+1 -> 2029 | I11: =H11+1 -> 2030 | J11: =I11+1 -> 2031 | K11: =J11+1 -> 2032 | L11: =K11+1 -> 2033 | M11: =L11+1 -> 2034 | N11: =N5 -> 2034 | O11: 0.09 | P11: next 5 years
B12: best case | C12: =C6 -> 1.44 | D12: =C12*(1+$O$11) -> 1.5696 | E12: =D12*(1+$O$11) -> 1.710864 | F12: =E12*(1+$O$11) -> 1.8648418 | G12: =F12*(1+$O$11) -> 2.0326775 | H12: =G12*(1+$O$11) -> 2.2156185 | I12: =H12*(1+$O$12) -> 2.4150242 | J12: =I12*(1+$O$12) -> 2.6323763 | K12: =J12*(1+$O$12) -> 2.8692902 | L12: =K12*(1+$O$12) -> 3.1275263 | M12: =L12*(1+$O$12) -> 3.4090037 | N12: =L12*O14 -> 46.912895 | O12: 0.09 | P12: 5 to 10 years
B13: =B7 -> 0 | C13: =C7 -> PV(10%) | D13: =D12*(1+$O$13)^($D$11-D11-1)*$I$3 -> 0 | E13: =E12*(1+$O$13)^($D$11-E11-1)*$I$3 -> 0 | F13: =F12*(1+$O$13)^($D$11-F11-1)*$I$3 -> 0 | G13: =G12*(1+$O$13)^($D$11-G11-1)*$I$3 -> 0 | H13: =H12*(1+$O$13)^($D$11-H11-1)*$I$3 -> 0 | I13: =I12*(1+$O$13)^($D$11-I11-1)*$I$3 -> 0 | J13: =J12*(1+$O$13)^($D$11-J11-1)*$I$3 -> 0 | K13: =K12*(1+$O$13)^($D$11-K11-1)*$I$3 -> 0 | ... M13: =M12*(1+$O$13)^($D$11-M11-1)*$I$3 -> 0 | N13: =N12*(1+$O$7)^($D$5-N11-1) -> 18.086952 | O13: =O7 -> 0.1 | P13: Discount rate
C14: Present value sum | D14: =SUM(D13:N13) -> 18.086952 | O14: 15 | P14: Terminal multiple
N16: Terminal Value | O16: Growth rate
B17: Scenario 3 | C17: =C11 -> FCF (500 million) | D17: =D11 -> 2025 | E17: =D17+1 -> 2026 | F17: =E17+1 -> 2027 | G17: =F17+1 -> 2028 | H17: =G17+1 -> 2029 | I17: =H17+1 -> 2030 | J17: =I17+1 -> 2031 | K17: =J17+1 -> 2032 | L17: =K17+1 -> 2033 | M17: =L17+1 -> 2034 | N17: =N11 -> 2034 | O17: 0.04 | P17: next 5 years
B18: worst case | C18: =C12 -> 1.44 | D18: =C18*(1+$O$17) -> 1.4976 | E18: =D18*(1+$O$17) -> 1.557504 | F18: =E18*(1+$O$17) -> 1.6198042 | G18: =F18*(1+$O$17) -> 1.6845963 | H18: =G18*(1+$O$17) -> 1.7519802 | I18: =H18*(1+$O$18) -> 1.8220594 | J18: =I18*(1+$O$18) -> 1.8949418 | K18: =J18*(1+$O$18) -> 1.9707394 | L18: =K18*(1+$O$18) -> 2.049569 | M18: =L18*(1+$O$18) -> 2.1315518 | N18: =L18*O20 -> 20.49569 | O18: 0.04 | P18: 5 to 10 years
B19: MARGIN OF | C19: =C13 -> PV(10%) | D19: =D18*(1+$O$19)^($D$17-D17-1)*$I$3 -> 0 | E19: =E18*(1+$O$19)^($D$17-E17-1)*$I$3 -> 0 | F19: =F18*(1+$O$19)^($D$17-F17-1)*$I$3 -> 0 | G19: =G18*(1+$O$19)^($D$17-G17-1)*$I$3 -> 0 | H19: =H18*(1+$O$19)^($D$17-H17-1)*$I$3 -> 0 | I19: =I18*(1+$O$19)^($D$17-I17-1)*$I$3 -> 0 | J19: =J18*(1+$O$19)^($D$17-J17-1)*$I$3 -> 0 | K19: =K18*(1+$O$19)^($D$17-K17-1)*$I$3 -> 0 | ... M19: =M18*(1+$O$19)^($D$17-M17-1)*$I$3 -> 0 | N19: =N18*(1+$O$19)^($D$17-N17-1) -> 7.9019758 | O19: =O13 -> 0.1 | P19: Discount rate
B20: SAFETY | C20: Present value sum | D20: =SUM(D19:N19) -> 7.9019758 | O20: 10 | P20: Terminal multiple
C22: Scenario | D22: Probability | E22: PV | F22: Part
C23: Scenario 1 (normal case) | D23: 0.34 | E23: =D8 -> 12.248161 | F23: =E23*D23 -> 4.1643747
C24: Scenario 2 (best case) | D24: 0.33 | E24: =D14 -> 18.086952 | F24: =E24*D24 -> 5.9686941
C25: Scenario 3 (worst case) | D25: 0.33 | E25: =D20 -> 7.9019758 | F25: =E25*D25 -> 2.607652
C26: STOCK PRICE NOW | D26: =C3 -> 11.71 | E26: Sum | F26: =SUM(F23:F25) -> 12.740721
B28: Disclaimer: This is just for educational purposes and not for investing advice!
B30: MADE BY | C30: STOCK MARKET RESEARCH PLATFORM

Sheet LUNDIN
S1: input cells
B2: Lundin | C2: LINK TO RESEARCH | S2: result cells
B3: STOCK PRICE | C3: ='COMPARATIVE TABLE'!C21 -> 11.76 | F3: DIVIDEND PAYOUT RATIO | I3: 0.4
B4: COMPARATIVE TABLE'!A1 | N4: Terminal Value | O4: Growth rate
B5: Scenario 1 | C5: FCF Per Share | D5: 2025 | E5: =D5+1 -> 2026 | F5: =E5+1 -> 2027 | G5: =F5+1 -> 2028 | H5: =G5+1 -> 2029 | I5: =H5+1 -> 2030 | J5: =I5+1 -> 2031 | K5: =J5+1 -> 2032 | L5: =K5+1 -> 2033 | M5: =L5+1 -> 2034 | N5: 2034 | O5: 0.05 | P5: next 5 years
B6: normal case | C6: 0.47 | D6: =C6*(1+$O$5) -> 0.4935 | E6: =D6*(1+$O$5) -> 0.518175 | F6: =E6*(1+$O$5) -> 0.54408375 | G6: =F6*(1+$O$5) -> 0.57128794 | H6: =G6*(1+$O$5) -> 0.59985233 | I6: =H6*(1+$O$6) -> 0.65983757 | J6: =I6*(1+$O$6) -> 0.72582132 | K6: =J6*(1+$O$6) -> 0.79840346 | L6: =K6*(1+$O$6) -> 0.8782438 | M6: =L6*(1+$O$6) -> 0.96606818 | N6: =L6*O8 -> 10.538926 | O6: 0.1 | P6: 5 to 10 years
C7: =CONCATENATE(R8,O7*100,S8) -> PV(10%) | D7: =D6*(1+$O$7)^($D$5-D5-1)*$I$3 -> 0.17945455 | E7: =E6*(1+$O$7)^($D$5-E5-1)*$I$3 -> 0.17129752 | F7: =F6*(1+$O$7)^($D$5-F5-1)*$I$3 -> 0.16351127 | G7: =G6*(1+$O$7)^($D$5-G5-1)*$I$3 -> 0.15607894 | H7: =H6*(1+$O$7)^($D$5-H5-1)*$I$3 -> 0.14898444 | I7: =I6*(1+$O$7)^($D$5-I5-1)*$I$3 -> 0.14898444 | J7: =J6*(1+$O$7)^($D$5-J5-1)*$I$3 -> 0.14898444 | K7: =K6*(1+$O$7)^($D$5-K5-1)*$I$3 -> 0.14898444 | ... M7: =M6*(1+$O$7)^($D$5-M5-1)*$I$3 -> 0.14898444 | N7: =N6*(1+$O$7)^($D$5-N5-1) -> 4.0632121 | O7: 0.1 | P7: Discount rate
C8: INTRINSIC VALUE | D8: =SUM(D7:N7) -> 5.627461 | O8: 12 | P8: Terminal multiple | R8: PV( | S8: %)
N10: Terminal Value | O10: Growth rate
B11: Scenario 2 | C11: =C5 -> FCF Per Share | D11: =D5 -> 2025 | E11: =D11+1 -> 2026 | F11: =E11+1 -> 2027 | G11: =F11+1 -> 2028 | H11: =G11+1 -> 2029 | I11: =H11+1 -> 2030 | J11: =I11+1 -> 2031 | K11: =J11+1 -> 2032 | L11: =K11+1 -> 2033 | M11: =L11+1 -> 2034 | N11: =N5 -> 2034 | O11: 0.05 | P11: next 5 years
B12: best case | C12: =C6 -> 0.47 | D12: =C12*(1+$O$11) -> 0.4935 | E12: =D12*(1+$O$11) -> 0.518175 | F12: =E12*(1+$O$11) -> 0.54408375 | G12: =F12*(1+$O$11) -> 0.57128794 | H12: =G12*(1+$O$11) -> 0.59985233 | I12: =H12*(1+$O$12) -> 0.68983018 | J12: =I12*(1+$O$12) -> 0.79330471 | K12: =J12*(1+$O$12) -> 0.91230042 | L12: =K12*(1+$O$12) -> 1.0491455 | M12: =L12*(1+$O$12) -> 1.2065173 | N12: =L12*O14 -> 15.737182 | O12: 0.15 | P12: 5 to 10 years
B13: =B7 -> 0 | C13: =C7 -> PV(10%) | D13: =D12*(1+$O$13)^($D$11-D11-1)*$I$3 -> 0.17945455 | E13: =E12*(1+$O$13)^($D$11-E11-1)*$I$3 -> 0.17129752 | F13: =F12*(1+$O$13)^($D$11-F11-1)*$I$3 -> 0.16351127 | G13: =G12*(1+$O$13)^($D$11-G11-1)*$I$3 -> 0.15607894 | H13: =H12*(1+$O$13)^($D$11-H11-1)*$I$3 -> 0.14898444 | I13: =I12*(1+$O$13)^($D$11-I11-1)*$I$3 -> 0.15575646 | J13: =J12*(1+$O$13)^($D$11-J11-1)*$I$3 -> 0.1628363 | K13: =K12*(1+$O$13)^($D$11-K11-1)*$I$3 -> 0.17023795 | ... M13: =M12*(1+$O$13)^($D$11-M11-1)*$I$3 -> 0.18606586 | N13: =N12*(1+$O$7)^($D$5-N11-1) -> 6.067365 | O13: =O7 -> 0.1 | P13: Discount rate
C14: Present value sum | D14: =SUM(D13:N13) -> 7.7395643 | O14: 15 | P14: Terminal multiple
N16: Terminal Value | O16: Growth rate
B17: Scenario 3 | C17: =C11 -> FCF Per Share | D17: =D11 -> 2025 | E17: =D17+1 -> 2026 | F17: =E17+1 -> 2027 | G17: =F17+1 -> 2028 | H17: =G17+1 -> 2029 | I17: =H17+1 -> 2030 | J17: =I17+1 -> 2031 | K17: =J17+1 -> 2032 | L17: =K17+1 -> 2033 | M17: =L17+1 -> 2034 | N17: =N11 -> 2034 | O17: 0.05 | P17: next 5 years
B18: worst case | C18: =C12 -> 0.47 | D18: =C18*(1+$O$17) -> 0.4935 | E18: =D18*(1+$O$17) -> 0.518175 | F18: =E18*(1+$O$17) -> 0.54408375 | G18: =F18*(1+$O$17) -> 0.57128794 | H18: =G18*(1+$O$17) -> 0.59985233 | I18: =H18*(1+$O$18) -> 0.62984495 | J18: =I18*(1+$O$18) -> 0.6613372 | K18: =J18*(1+$O$18) -> 0.69440406 | L18: =K18*(1+$O$18) -> 0.72912426 | M18: =L18*(1+$O$18) -> 0.76558047 | N18: =L18*O20 -> 7.2912426 | O18: 0.05 | P18: 5 to 10 years
B19: MARGIN OF | C19: =C13 -> PV(10%) | D19: =D18*(1+$O$19)^($D$17-D17-1)*$I$3 -> 0.17945455 | E19: =E18*(1+$O$19)^($D$17-E17-1)*$I$3 -> 0.17129752 | F19: =F18*(1+$O$19)^($D$17-F17-1)*$I$3 -> 0.16351127 | G19: =G18*(1+$O$19)^($D$17-G17-1)*$I$3 -> 0.15607894 | H19: =H18*(1+$O$19)^($D$17-H17-1)*$I$3 -> 0.14898444 | I19: =I18*(1+$O$19)^($D$17-I17-1)*$I$3 -> 0.14221242 | J19: =J18*(1+$O$19)^($D$17-J17-1)*$I$3 -> 0.13574822 | K19: =K18*(1+$O$19)^($D$17-K17-1)*$I$3 -> 0.12957785 | ... M19: =M18*(1+$O$19)^($D$17-M17-1)*$I$3 -> 0.11806577 | N19: =N18*(1+$O$19)^($D$17-N17-1) -> 2.8110897 | O19: =O13 -> 0.1 | P19: Discount rate
B20: SAFETY | C20: Present value sum | D20: =SUM(D19:N19) -> 4.2797086 | O20: 10 | P20: Terminal multiple
C22: Scenario | D22: Probability | E22: PV | F22: Part
C23: Scenario 1 (normal case) | D23: 0.34 | E23: =D8 -> 5.627461 | F23: =E23*D23 -> 1.9133367
C24: Scenario 2 (best case) | D24: 0.33 | E24: =D14 -> 7.7395643 | F24: =E24*D24 -> 2.5540562
C25: Scenario 3 (worst case) | D25: 0.33 | E25: =D20 -> 4.2797086 | F25: =E25*D25 -> 1.4123038
C26: STOCK PRICE NOW | D26: =C3 -> 11.76 | E26: Sum | F26: =SUM(F23:F25) -> 5.8796968
B28: Disclaimer: This is just for educational purposes and not for investing advice!
B30: MADE BY | C30: STOCK MARKET RESEARCH PLATFORM

Sheet Maersk
S1: input cells
B2: Maersk | C2: LINK TO RESEARCH | S2: result cells
B3: STOCK PRICE | C3: ='COMPARATIVE TABLE'!C22 -> 10.26 | F3: DIVIDEND PAYOUT RATIO | I3: 0.4
B4: COMPARATIVE TABLE'!A1 | N4: Terminal Value | O4: Growth rate
B5: Scenario 1 | C5: FCF | D5: 2025 | E5: =D5+1 -> 2026 | F5: =E5+1 -> 2027 | G5: =F5+1 -> 2028 | H5: =G5+1 -> 2029 | I5: =H5+1 -> 2030 | J5: =I5+1 -> 2031 | K5: =J5+1 -> 2032 | L5: =K5+1 -> 2033 | M5: =L5+1 -> 2034 | N5: 2034 | O5: 0.05 | P5: next 5 years
B6: normal case | C6: 0.7 | D6: =C6*(1+$O$5) -> 0.735 | E6: =D6*(1+$O$5) -> 0.77175 | F6: =E6*(1+$O$5) -> 0.8103375 | G6: =F6*(1+$O$5) -> 0.85085438 | H6: =G6*(1+$O$5) -> 0.89339709 | I6: =H6*(1+$O$6) -> 0.93806695 | J6: =I6*(1+$O$6) -> 0.9849703 | K6: =J6*(1+$O$6) -> 1.0342188 | L6: =K6*(1+$O$6) -> 1.0859298 | M6: =L6*(1+$O$6) -> 1.1402262 | N6: =L6*O8 -> 14.117087 | O6: 0.05 | P6: 5 to 10 years
C7: =CONCATENATE(R8,O7*100,S8) -> PV(10%) | D7: =D6*(1+$O$7)^($D$5-D5-1)*$I$3 -> 0.26727273 | E7: =E6*(1+$O$7)^($D$5-E5-1)*$I$3 -> 0.25512397 | F7: =F6*(1+$O$7)^($D$5-F5-1)*$I$3 -> 0.24352742 | G7: =G6*(1+$O$7)^($D$5-G5-1)*$I$3 -> 0.23245799 | H7: =H6*(1+$O$7)^($D$5-H5-1)*$I$3 -> 0.22189172 | I7: =I6*(1+$O$7)^($D$5-I5-1)*$I$3 -> 0.21180573 | J7: =J6*(1+$O$7)^($D$5-J5-1)*$I$3 -> 0.2021782 | K7: =K6*(1+$O$7)^($D$5-K5-1)*$I$3 -> 0.19298828 | ... M7: =M6*(1+$O$7)^($D$5-M5-1)*$I$3 -> 0.17584263 | N7: =N6*(1+$O$7)^($D$5-N5-1) -> 5.4427481 | O7: 0.1 | P7: Discount rate
C8: INTRINSIC VALUE | D8: =SUM(D7:N7) -> 7.6300528 | O8: 13 | P8: Terminal multiple | R8: PV( | S8: %)
N10: Terminal Value | O10: Growth rate
B11: Scenario 2 | C11: =C5 -> FCF | D11: =D5 -> 2025 | E11: =D11+1 -> 2026 | F11: =E11+1 -> 2027 | G11: =F11+1 -> 2028 | H11: =G11+1 -> 2029 | I11: =H11+1 -> 2030 | J11: =I11+1 -> 2031 | K11: =J11+1 -> 2032 | L11: =K11+1 -> 2033 | M11: =L11+1 -> 2034 | N11: =N5 -> 2034 | O11: 0.07 | P11: next 5 years
B12: best case | C12: =C6 -> 0.7 | D12: =C12*(1+$O$11) -> 0.749 | E12: =D12*(1+$O$11) -> 0.80143 | F12: =E12*(1+$O$11) -> 0.8575301 | G12: =F12*(1+$O$11) -> 0.91755721 | H12: =G12*(1+$O$11) -> 0.98178621 | I12: =H12*(1+$O$12) -> 1.0308755 | J12: =I12*(1+$O$12) -> 1.0824193 | K12: =J12*(1+$O$12) -> 1.1365403 | L12: =K12*(1+$O$12) -> 1.1933673 | M12: =L12*(1+$O$12) -> 1.2530356 | N12: =L12*O14 -> 19.093876 | O12: 0.05 | P12: 5 to 10 years
B13: =B7 -> 0 | C13: =C7 -> PV(10%) | D13: =D12*(1+$O$13)^($D$11-D11-1)*$I$3 -> 0.27236364 | E13: =E12*(1+$O$13)^($D$11-E11-1)*$I$3 -> 0.26493554 | F13: =F12*(1+$O$13)^($D$11-F11-1)*$I$3 -> 0.25771002 | G13: =G12*(1+$O$13)^($D$11-G11-1)*$I$3 -> 0.25068157 | H13: =H12*(1+$O$13)^($D$11-H11-1)*$I$3 -> 0.2438448 | I13: =I12*(1+$O$13)^($D$11-I11-1)*$I$3 -> 0.23276094 | J13: =J12*(1+$O$13)^($D$11-J11-1)*$I$3 -> 0.2221809 | K13: =K12*(1+$O$13)^($D$11-K11-1)*$I$3 -> 0.21208177 | ... M13: =M12*(1+$O$13)^($D$11-M11-1)*$I$3 -> 0.19323979 | N13: =N12*(1+$O$7)^($D$5-N11-1) -> 7.3615159 | O13: =O7 -> 0.1 | P13: Discount rate
C14: Present value sum | D14: =SUM(D13:N13) -> 9.7137566 | O14: 16 | P14: Terminal multiple
N16: Terminal Value | O16: Growth rate
B17: Scenario 3 | C17: =C11 -> FCF | D17: =D11 -> 2025 | E17: =D17+1 -> 2026 | F17: =E17+1 -> 2027 | G17: =F17+1 -> 2028 | H17: =G17+1 -> 2029 | I17: =H17+1 -> 2030 | J17: =I17+1 -> 2031 | K17: =J17+1 -> 2032 | L17: =K17+1 -> 2033 | M17: =L17+1 -> 2034 | N17: =N11 -> 2034 | O17: 0.03 | P17: next 5 years
B18: worst case | C18: =C12 -> 0.7 | D18: =C18*(1+$O$17) -> 0.721 | E18: =D18*(1+$O$17) -> 0.74263 | F18: =E18*(1+$O$17) -> 0.7649089 | G18: =F18*(1+$O$17) -> 0.78785617 | H18: =G18*(1+$O$17) -> 0.81149185 | I18: =H18*(1+$O$18) -> 0.83583661 | J18: =I18*(1+$O$18) -> 0.86091171 | K18: =J18*(1+$O$18) -> 0.88673906 | L18: =K18*(1+$O$18) -> 0.91334123 | M18: =L18*(1+$O$18) -> 0.94074147 | N18: =L18*O20 -> 9.1334123 | O18: 0.03 | P18: 5 to 10 years
B19: MARGIN OF | C19: =C13 -> PV(10%) | D19: =D18*(1+$O$19)^($D$17-D17-1)*$I$3 -> 0.26218182 | E19: =E18*(1+$O$19)^($D$17-E17-1)*$I$3 -> 0.24549752 | F19: =F18*(1+$O$19)^($D$17-F17-1)*$I$3 -> 0.22987495 | G19: =G18*(1+$O$19)^($D$17-G17-1)*$I$3 -> 0.21524655 | H19: =H18*(1+$O$19)^($D$17-H17-1)*$I$3 -> 0.20154904 | I19: =I18*(1+$O$19)^($D$17-I17-1)*$I$3 -> 0.18872319 | J19: =J18*(1+$O$19)^($D$17-J17-1)*$I$3 -> 0.17671353 | K19: =K18*(1+$O$19)^($D$17-K17-1)*$I$3 -> 0.16546813 | ... M19: =M18*(1+$O$19)^($D$17-M17-1)*$I$3 -> 0.14507862 | N19: =N18*(1+$O$19)^($D$17-N17-1) -> 3.5213258 | O19: =O13 -> 0.1 | P19: Discount rate
B20: SAFETY | C20: Present value sum | D20: =SUM(D19:N19) -> 5.5065975 | O20: 10 | P20: Terminal multiple
C22: Scenario | D22: Probability | E22: PV | F22: Part
C23: Scenario 1 (normal case) | D23: 0.34 | E23: =D8 -> 7.6300528 | F23: =E23*D23 -> 2.594218
C24: Scenario 2 (best case) | D24: 0.33 | E24: =D14 -> 9.7137566 | F24: =E24*D24 -> 3.2055397
C25: Scenario 3 (worst case) | D25: 0.33 | E25: =D20 -> 5.5065975 | F25: =E25*D25 -> 1.8171772
C26: STOCK PRICE NOW | D26: =C3 -> 10.26 | E26: Sum | F26: =SUM(F23:F25) -> 7.6169348
B28: Disclaimer: This is just for educational purposes and not for investing advice!
B30: MADE BY | C30: STOCK MARKET RESEARCH PLATFORM

Sheet Nine D
S1: input cells
B2: nine dragons | C2: LINK TO RESEARCH | S2: result cells
B3: STOCK PRICE | C3: ='COMPARATIVE TABLE'!C23 -> 5.95 | F3: DIVIDEND PAYOUT RATIO | I3: 1
B4: COMPARATIVE TABLE'!A1 | N4: Terminal Value | O4: Growth rate
B5: Scenario 1 | C5: Dividend | D5: 2025 | E5: =D5+1 -> 2026 | F5: =E5+1 -> 2027 | G5: =F5+1 -> 2028 | H5: =G5+1 -> 2029 | I5: =H5+1 -> 2030 | J5: =I5+1 -> 2031 | K5: =J5+1 -> 2032 | L5: =K5+1 -> 2033 | M5: =L5+1 -> 2034 | N5: 2034 | O5: 0.04 | P5: next 5 years
B6: normal case | C6: 0.4 | D6: =C6*(1+$O$5) -> 0.416 | E6: =D6*(1+$O$5) -> 0.43264 | F6: =E6*(1+$O$5) -> 0.4499456 | G6: =F6*(1+$O$5) -> 0.46794342 | H6: =G6*(1+$O$5) -> 0.48666116 | I6: =H6*(1+$O$6) -> 0.50612761 | J6: =I6*(1+$O$6) -> 0.52637271 | K6: =J6*(1+$O$6) -> 0.54742762 | L6: =K6*(1+$O$6) -> 0.56932472 | M6: =L6*(1+$O$6) -> 0.59209771 | N6: =L6*O8 -> 8.5398709 | O6: 0.04 | P6: 5 to 10 years
C7: =CONCATENATE(R8,O7*100,S8) -> PV(10%) | D7: =D6*(1+$O$7)^($D$5-D5-1)*$I$3 -> 0.37818182 | E7: =E6*(1+$O$7)^($D$5-E5-1)*$I$3 -> 0.35755372 | F7: =F6*(1+$O$7)^($D$5-F5-1)*$I$3 -> 0.33805079 | G7: =G6*(1+$O$7)^($D$5-G5-1)*$I$3 -> 0.31961165 | H7: =H6*(1+$O$7)^($D$5-H5-1)*$I$3 -> 0.30217829 | I7: =I6*(1+$O$7)^($D$5-I5-1)*$I$3 -> 0.28569584 | J7: =J6*(1+$O$7)^($D$5-J5-1)*$I$3 -> 0.27011243 | K7: =K6*(1+$O$7)^($D$5-K5-1)*$I$3 -> 0.25537902 | ... M7: =M6*(1+$O$7)^($D$5-M5-1)*$I$3 -> 0.2282793 | N7: =N6*(1+$O$7)^($D$5-N5-1) -> 3.2924899 | O7: 0.1 | P7: Discount rate
C8: INTRINSIC VALUE | D8: =SUM(D7:N7) -> 6.268982 | O8: 15 | P8: Terminal multiple | R8: PV( | S8: %)
N10: Terminal Value | O10: Growth rate
B11: Scenario 2 | C11: =C5 -> Dividend | D11: =D5 -> 2025 | E11: =D11+1 -> 2026 | F11: =E11+1 -> 2027 | G11: =F11+1 -> 2028 | H11: =G11+1 -> 2029 | I11: =H11+1 -> 2030 | J11: =I11+1 -> 2031 | K11: =J11+1 -> 2032 | L11: =K11+1 -> 2033 | M11: =L11+1 -> 2034 | N11: =N5 -> 2034 | O11: 0.06 | P11: next 5 years
B12: best case | C12: =C6 -> 0.4 | D12: =C12*(1+$O$11) -> 0.424 | E12: =D12*(1+$O$11) -> 0.44944 | F12: =E12*(1+$O$11) -> 0.4764064 | G12: =F12*(1+$O$11) -> 0.50499078 | H12: =G12*(1+$O$11) -> 0.53529023 | I12: =H12*(1+$O$12) -> 0.56740764 | J12: =I12*(1+$O$12) -> 0.6014521 | K12: =J12*(1+$O$12) -> 0.63753923 | L12: =K12*(1+$O$12) -> 0.67579158 | M12: =L12*(1+$O$12) -> 0.71633908 | N12: =L12*O14 -> 13.515832 | O12: 0.06 | P12: 5 to 10 years
B13: =B7 -> 0 | C13: =C7 -> PV(10%) | D13: =D12*(1+$O$13)^($D$11-D11-1)*$I$3 -> 0.38545455 | E13: =E12*(1+$O$13)^($D$11-E11-1)*$I$3 -> 0.37143802 | F13: =F12*(1+$O$13)^($D$11-F11-1)*$I$3 -> 0.35793118 | G13: =G12*(1+$O$13)^($D$11-G11-1)*$I$3 -> 0.3449155 | H13: =H12*(1+$O$13)^($D$11-H11-1)*$I$3 -> 0.33237312 | I13: =I12*(1+$O$13)^($D$11-I11-1)*$I$3 -> 0.32028682 | J13: =J12*(1+$O$13)^($D$11-J11-1)*$I$3 -> 0.30864003 | K13: =K12*(1+$O$13)^($D$11-K11-1)*$I$3 -> 0.29741676 | ... M13: =M12*(1+$O$13)^($D$11-M11-1)*$I$3 -> 0.27617972 | N13: =N12*(1+$O$7)^($D$5-N11-1) -> 5.2109382 | O13: =O7 -> 0.1 | P13: Discount rate
C14: Present value sum | D14: =SUM(D13:N13) -> 8.4921755 | O14: 20 | P14: Terminal multiple
N16: Terminal Value | O16: Growth rate
B17: Scenario 3 | C17: =C11 -> Dividend | D17: =D11 -> 2025 | E17: =D17+1 -> 2026 | F17: =E17+1 -> 2027 | G17: =F17+1 -> 2028 | H17: =G17+1 -> 2029 | I17: =H17+1 -> 2030 | J17: =I17+1 -> 2031 | K17: =J17+1 -> 2032 | L17: =K17+1 -> 2033 | M17: =L17+1 -> 2034 | N17: =N11 -> 2034 | O17: 0.02 | P17: next 5 years
B18: worst case | C18: =C12 -> 0.4 | D18: =C18*(1+$O$17) -> 0.408 | E18: =D18*(1+$O$17) -> 0.41616 | F18: =E18*(1+$O$17) -> 0.4244832 | G18: =F18*(1+$O$17) -> 0.43297286 | H18: =G18*(1+$O$17) -> 0.44163232 | I18: =H18*(1+$O$18) -> 0.45046497 | J18: =I18*(1+$O$18) -> 0.45947427 | K18: =J18*(1+$O$18) -> 0.46866375 | L18: =K18*(1+$O$18) -> 0.47803703 | M18: =L18*(1+$O$18) -> 0.48759777 | N18: =L18*O20 -> 4.7803703 | O18: 0.02 | P18: 5 to 10 years
B19: MARGIN OF | C19: =C13 -> PV(10%) | D19: =D18*(1+$O$19)^($D$17-D17-1)*$I$3 -> 0.37090909 | E19: =E18*(1+$O$19)^($D$17-E17-1)*$I$3 -> 0.34393388 | F19: =F18*(1+$O$19)^($D$17-F17-1)*$I$3 -> 0.31892051 | G19: =G18*(1+$O$19)^($D$17-G17-1)*$I$3 -> 0.29572629 | H19: =H18*(1+$O$19)^($D$17-H17-1)*$I$3 -> 0.27421893 | I19: =I18*(1+$O$19)^($D$17-I17-1)*$I$3 -> 0.25427573 | J19: =J18*(1+$O$19)^($D$17-J17-1)*$I$3 -> 0.23578295 | K19: =K18*(1+$O$19)^($D$17-K17-1)*$I$3 -> 0.2186351 | ... M19: =M18*(1+$O$19)^($D$17-M17-1)*$I$3 -> 0.18799005 | N19: =N18*(1+$O$19)^($D$17-N17-1) -> 1.8430397 | O19: =O13 -> 0.1 | P19: Discount rate
B20: SAFETY | C20: Present value sum | D20: =SUM(D19:N19) -> 4.5461666 | O20: 10 | P20: Terminal multiple
C22: Scenario | D22: Probability | E22: PV | F22: Part
C23: Scenario 1 (normal case) | D23: 0.34 | E23: =D8 -> 6.268982 | F23: =E23*D23 -> 2.1314539
C24: Scenario 2 (best case) | D24: 0.33 | E24: =D14 -> 8.4921755 | F24: =E24*D24 -> 2.8024179
C25: Scenario 3 (worst case) | D25: 0.33 | E25: =D20 -> 4.5461666 | F25: =E25*D25 -> 1.500235
C26: STOCK PRICE NOW | D26: =C3 -> 5.95 | E26: Sum | F26: =SUM(F23:F25) -> 6.4341068
B28: Disclaimer: This is just for educational purposes and not for investing advice!
B30: MADE BY | C30: STOCK MARKET RESEARCH PLATFORM

Sheet NTR
S1: input cells
B2: Nutrien | C2: LINK TO RESEARCH | S2: result cells
B3: STOCK PRICE | C3: ='COMPARATIVE TABLE'!C24 -> 57.41 | F3: DIVIDEND PAYOUT RATIO | I3: 1
B4: COMPARATIVE TABLE'!A1 | N4: Terminal Value | O4: Growth rate
B5: Scenario 1 | C5: Dividend | D5: 2025 | E5: =D5+1 -> 2026 | F5: =E5+1 -> 2027 | G5: =F5+1 -> 2028 | H5: =G5+1 -> 2029 | I5: =H5+1 -> 2030 | J5: =I5+1 -> 2031 | K5: =J5+1 -> 2032 | L5: =K5+1 -> 2033 | M5: =L5+1 -> 2034 | N5: 2034 | O5: 0.05 | P5: next 5 years
B6: normal case | C6: 2.18 | D6: =C6*(1+$O$5) -> 2.289 | E6: =D6*(1+$O$5) -> 2.40345 | F6: =E6*(1+$O$5) -> 2.5236225 | G6: =F6*(1+$O$5) -> 2.6498036 | H6: =G6*(1+$O$5) -> 2.7822938 | I6: =H6*(1+$O$6) -> 2.9214085 | J6: =I6*(1+$O$6) -> 3.0674789 | K6: =J6*(1+$O$6) -> 3.2208529 | L6: =K6*(1+$O$6) -> 3.3818955 | M6: =L6*(1+$O$6) -> 3.5509903 | N6: =L6*O8 -> 67.63791 | O6: 0.05 | P6: 5 to 10 years
C7: =CONCATENATE(R8,O7*100,S8) -> PV(10%) | D7: =D6*(1+$O$7)^($D$5-D5-1)*$I$3 -> 2.0809091 | E7: =E6*(1+$O$7)^($D$5-E5-1)*$I$3 -> 1.9863223 | F7: =F6*(1+$O$7)^($D$5-F5-1)*$I$3 -> 1.8960349 | G7: =G6*(1+$O$7)^($D$5-G5-1)*$I$3 -> 1.8098515 | H7: =H6*(1+$O$7)^($D$5-H5-1)*$I$3 -> 1.7275856 | I7: =I6*(1+$O$7)^($D$5-I5-1)*$I$3 -> 1.6490589 | J7: =J6*(1+$O$7)^($D$5-J5-1)*$I$3 -> 1.5741017 | K7: =K6*(1+$O$7)^($D$5-K5-1)*$I$3 -> 1.5025516 | ... M7: =M6*(1+$O$7)^($D$5-M5-1)*$I$3 -> 1.3690605 | N7: =N6*(1+$O$7)^($D$5-N5-1) -> 26.077342 | O7: 0.1 | P7: Discount rate
C8: INTRINSIC VALUE | D8: =SUM(D7:N7) -> 43.107072 | O8: 20 | P8: Terminal multiple | R8: PV( | S8: %)
N10: Terminal Value | O10: Growth rate
B11: Scenario 2 | C11: =C5 -> Dividend | D11: =D5 -> 2025 | E11: =D11+1 -> 2026 | F11: =E11+1 -> 2027 | G11: =F11+1 -> 2028 | H11: =G11+1 -> 2029 | I11: =H11+1 -> 2030 | J11: =I11+1 -> 2031 | K11: =J11+1 -> 2032 | L11: =K11+1 -> 2033 | M11: =L11+1 -> 2034 | N11: =N5 -> 2034 | O11: 0.06 | P11: next 5 years
B12: best case | C12: =C6 -> 2.18 | D12: =C12*(1+$O$11) -> 2.3108 | E12: =D12*(1+$O$11) -> 2.449448 | F12: =E12*(1+$O$11) -> 2.5964149 | G12: =F12*(1+$O$11) -> 2.7521998 | H12: =G12*(1+$O$11) -> 2.9173318 | I12: =H12*(1+$O$12) -> 3.0923717 | J12: =I12*(1+$O$12) -> 3.277914 | K12: =J12*(1+$O$12) -> 3.4745888 | L12: =K12*(1+$O$12) -> 3.6830641 | M12: =L12*(1+$O$12) -> 3.904048 | N12: =L12*O14 -> 92.076603 | O12: 0.06 | P12: 5 to 10 years
B13: =B7 -> 0 | C13: =C7 -> PV(10%) | D13: =D12*(1+$O$13)^($D$11-D11-1)*$I$3 -> 2.1007273 | E13: =E12*(1+$O$13)^($D$11-E11-1)*$I$3 -> 2.0243372 | F13: =F12*(1+$O$13)^($D$11-F11-1)*$I$3 -> 1.9507249 | G13: =G12*(1+$O$13)^($D$11-G11-1)*$I$3 -> 1.8797895 | H13: =H12*(1+$O$13)^($D$11-H11-1)*$I$3 -> 1.8114335 | I13: =I12*(1+$O$13)^($D$11-I11-1)*$I$3 -> 1.7455632 | J13: =J12*(1+$O$13)^($D$11-J11-1)*$I$3 -> 1.6820882 | K13: =K12*(1+$O$13)^($D$11-K11-1)*$I$3 -> 1.6209213 | ... M13: =M12*(1+$O$13)^($D$11-M11-1)*$I$3 -> 1.5051795 | N13: =N12*(1+$O$7)^($D$5-N11-1) -> 35.499517 | O13: =O7 -> 0.1 | P13: Discount rate
C14: Present value sum | D14: =SUM(D13:N13) -> 53.38226 | O14: 25 | P14: Terminal multiple
N16: Terminal Value | O16: Growth rate
B17: Scenario 3 | C17: =C11 -> Dividend | D17: =D11 -> 2025 | E17: =D17+1 -> 2026 | F17: =E17+1 -> 2027 | G17: =F17+1 -> 2028 | H17: =G17+1 -> 2029 | I17: =H17+1 -> 2030 | J17: =I17+1 -> 2031 | K17: =J17+1 -> 2032 | L17: =K17+1 -> 2033 | M17: =L17+1 -> 2034 | N17: =N11 -> 2034 | O17: 0.03 | P17: next 5 years
B18: worst case | C18: =C12 -> 2.18 | D18: =C18*(1+$O$17) -> 2.2454 | E18: =D18*(1+$O$17) -> 2.312762 | F18: =E18*(1+$O$17) -> 2.3821449 | G18: =F18*(1+$O$17) -> 2.4536092 | H18: =G18*(1+$O$17) -> 2.5272175 | I18: =H18*(1+$O$18) -> 2.603034 | J18: =I18*(1+$O$18) -> 2.681125 | K18: =J18*(1+$O$18) -> 2.7615588 | L18: =K18*(1+$O$18) -> 2.8444055 | M18: =L18*(1+$O$18) -> 2.9297377 | N18: =L18*O20 -> 42.666083 | O18: 0.03 | P18: 5 to 10 years
B19: MARGIN OF | C19: =C13 -> PV(10%) | D19: =D18*(1+$O$19)^($D$17-D17-1)*$I$3 -> 2.0412727 | E19: =E18*(1+$O$19)^($D$17-E17-1)*$I$3 -> 1.9113736 | F19: =F18*(1+$O$19)^($D$17-F17-1)*$I$3 -> 1.7897407 | G19: =G18*(1+$O$19)^($D$17-G17-1)*$I$3 -> 1.6758481 | H19: =H18*(1+$O$19)^($D$17-H17-1)*$I$3 -> 1.5692032 | I19: =I18*(1+$O$19)^($D$17-I17-1)*$I$3 -> 1.4693448 | J19: =J18*(1+$O$19)^($D$17-J17-1)*$I$3 -> 1.3758411 | K19: =K18*(1+$O$19)^($D$17-K17-1)*$I$3 -> 1.2882876 | ... M19: =M18*(1+$O$19)^($D$17-M17-1)*$I$3 -> 1.1295407 | N19: =N18*(1+$O$19)^($D$17-N17-1) -> 16.449622 | O19: =O13 -> 0.1 | P19: Discount rate
B20: SAFETY | C20: Present value sum | D20: =SUM(D19:N19) -> 31.90638 | O20: 15 | P20: Terminal multiple
C22: Scenario | D22: Probability | E22: PV | F22: Part
C23: Scenario 1 (normal case) | D23: 0.34 | E23: =D8 -> 43.107072 | F23: =E23*D23 -> 14.656405
C24: Scenario 2 (best case) | D24: 0.33 | E24: =D14 -> 53.38226 | F24: =E24*D24 -> 17.616146
C25: Scenario 3 (worst case) | D25: 0.33 | E25: =D20 -> 31.90638 | F25: =E25*D25 -> 10.529105
C26: STOCK PRICE NOW | D26: =C3 -> 57.41 | E26: Sum | F26: =SUM(F23:F25) -> 42.801656
B28: Disclaimer: This is just for educational purposes and not for investing advice!
B30: MADE BY | C30: STOCK MARKET RESEARCH PLATFORM

Sheet MOS
S1: input cells
B2: Mosaic | C2: LINK TO RESEARCH | S2: result cells
B3: STOCK PRICE | C3: ='COMPARATIVE TABLE'!C25 -> 33.41 | F3: DIVIDEND PAYOUT RATIO | I3: 1
B4: COMPARATIVE TABLE'!A1 | N4: Terminal Value | O4: Growth rate
B5: Scenario 1 | C5: Dividend per share | D5: 2025 | E5: =D5+1 -> 2026 | F5: =E5+1 -> 2027 | G5: =F5+1 -> 2028 | H5: =G5+1 -> 2029 | I5: =H5+1 -> 2030 | J5: =I5+1 -> 2031 | K5: =J5+1 -> 2032 | L5: =K5+1 -> 2033 | M5: =L5+1 -> 2034 | N5: 2034 | O5: 0.06 | P5: next 5 years
B6: normal case | C6: 0.88 | D6: =C6*(1+$O$5) -> 0.9328 | E6: =D6*(1+$O$5) -> 0.988768 | F6: =E6*(1+$O$5) -> 1.0480941 | G6: =F6*(1+$O$5) -> 1.1109797 | H6: =G6*(1+$O$5) -> 1.1776385 | I6: =H6*(1+$O$6) -> 1.2482968 | J6: =I6*(1+$O$6) -> 1.3231946 | K6: =J6*(1+$O$6) -> 1.4025863 | L6: =K6*(1+$O$6) -> 1.4867415 | M6: =L6*(1+$O$6) -> 1.575946 | N6: =L6*O8 -> 29.73483 | O6: 0.06 | P6: 5 to 10 years
C7: =CONCATENATE(R8,O7*100,S8) -> PV(10%) | D7: =D6*(1+$O$7)^($D$5-D5-1)*$I$3 -> 0.848 | E7: =E6*(1+$O$7)^($D$5-E5-1)*$I$3 -> 0.81716364 | F7: =F6*(1+$O$7)^($D$5-F5-1)*$I$3 -> 0.7874486 | G7: =G6*(1+$O$7)^($D$5-G5-1)*$I$3 -> 0.7588141 | H7: =H6*(1+$O$7)^($D$5-H5-1)*$I$3 -> 0.73122086 | I7: =I6*(1+$O$7)^($D$5-I5-1)*$I$3 -> 0.70463101 | J7: =J6*(1+$O$7)^($D$5-J5-1)*$I$3 -> 0.67900807 | K7: =K6*(1+$O$7)^($D$5-K5-1)*$I$3 -> 0.65431686 | ... M7: =M6*(1+$O$7)^($D$5-M5-1)*$I$3 -> 0.60759539 | N7: =N6*(1+$O$7)^($D$5-N5-1) -> 11.464064 | O7: 0.1 | P7: Discount rate
C8: INTRINSIC VALUE | D8: =SUM(D7:N7) -> 18.682786 | O8: 20 | P8: Terminal multiple | R8: PV( | S8: %)
N10: Terminal Value | O10: Growth rate
B11: Scenario 2 | C11: =C5 -> Dividend per share | D11: =D5 -> 2025 | E11: =D11+1 -> 2026 | F11: =E11+1 -> 2027 | G11: =F11+1 -> 2028 | H11: =G11+1 -> 2029 | I11: =H11+1 -> 2030 | J11: =I11+1 -> 2031 | K11: =J11+1 -> 2032 | L11: =K11+1 -> 2033 | M11: =L11+1 -> 2034 | N11: =N5 -> 2034 | O11: 0.08 | P11: next 5 years
B12: best case | C12: =C6 -> 0.88 | D12: =C12*(1+$O$11) -> 0.9504 | E12: =D12*(1+$O$11) -> 1.026432 | F12: =E12*(1+$O$11) -> 1.1085466 | G12: =F12*(1+$O$11) -> 1.1972303 | H12: =G12*(1+$O$11) -> 1.2930087 | I12: =H12*(1+$O$12) -> 1.3964494 | J12: =I12*(1+$O$12) -> 1.5081654 | K12: =J12*(1+$O$12) -> 1.6288186 | L12: =K12*(1+$O$12) -> 1.7591241 | M12: =L12*(1+$O$12) -> 1.899854 | N12: =L12*O14 -> 43.978102 | O12: 0.08 | P12: 5 to 10 years
B13: =B7 -> 0 | C13: =C7 -> PV(10%) | D13: =D12*(1+$O$13)^($D$11-D11-1)*$I$3 -> 0.864 | E13: =E12*(1+$O$13)^($D$11-E11-1)*$I$3 -> 0.84829091 | F13: =F12*(1+$O$13)^($D$11-F11-1)*$I$3 -> 0.83286744 | G13: =G12*(1+$O$13)^($D$11-G11-1)*$I$3 -> 0.81772439 | H13: =H12*(1+$O$13)^($D$11-H11-1)*$I$3 -> 0.80285668 | I13: =I12*(1+$O$13)^($D$11-I11-1)*$I$3 -> 0.78825928 | J13: =J12*(1+$O$13)^($D$11-J11-1)*$I$3 -> 0.7739273 | K13: =K12*(1+$O$13)^($D$11-K11-1)*$I$3 -> 0.75985589 | ... M13: =M12*(1+$O$13)^($D$11-M11-1)*$I$3 -> 0.73247596 | N13: =N12*(1+$O$7)^($D$5-N11-1) -> 16.955462 | O13: =O7 -> 0.1 | P13: Discount rate
C14: Present value sum | D14: =SUM(D13:N13) -> 24.92176 | O14: 25 | P14: Terminal multiple
N16: Terminal Value | O16: Growth rate
B17: Scenario 3 | C17: =C11 -> Dividend per share | D17: =D11 -> 2025 | E17: =D17+1 -> 2026 | F17: =E17+1 -> 2027 | G17: =F17+1 -> 2028 | H17: =G17+1 -> 2029 | I17: =H17+1 -> 2030 | J17: =I17+1 -> 2031 | K17: =J17+1 -> 2032 | L17: =K17+1 -> 2033 | M17: =L17+1 -> 2034 | N17: =N11 -> 2034 | O17: 0.03 | P17: next 5 years
B18: worst case | C18: =C12 -> 0.88 | D18: =C18*(1+$O$17) -> 0.9064 | E18: =D18*(1+$O$17) -> 0.933592 | F18: =E18*(1+$O$17) -> 0.96159976 | G18: =F18*(1+$O$17) -> 0.99044775 | H18: =G18*(1+$O$17) -> 1.0201612 | I18: =H18*(1+$O$18) -> 1.050766 | J18: =I18*(1+$O$18) -> 1.082289 | K18: =J18*(1+$O$18) -> 1.1147577 | L18: =K18*(1+$O$18) -> 1.1482004 | M18: =L18*(1+$O$18) -> 1.1826464 | N18: =L18*O20 -> 17.223006 | O18: 0.03 | P18: 5 to 10 years
B19: MARGIN OF | C19: =C13 -> PV(10%) | D19: =D18*(1+$O$19)^($D$17-D17-1)*$I$3 -> 0.824 | E19: =E18*(1+$O$19)^($D$17-E17-1)*$I$3 -> 0.77156364 | F19: =F18*(1+$O$19)^($D$17-F17-1)*$I$3 -> 0.72246413 | G19: =G18*(1+$O$19)^($D$17-G17-1)*$I$3 -> 0.67648914 | H19: =H18*(1+$O$19)^($D$17-H17-1)*$I$3 -> 0.63343983 | I19: =I18*(1+$O$19)^($D$17-I17-1)*$I$3 -> 0.59313003 | J19: =J18*(1+$O$19)^($D$17-J17-1)*$I$3 -> 0.55538539 | K19: =K18*(1+$O$19)^($D$17-K17-1)*$I$3 -> 0.52004268 | ... M19: =M18*(1+$O$19)^($D$17-M17-1)*$I$3 -> 0.45596139 | N19: =N18*(1+$O$19)^($D$17-N17-1) -> 6.6402144 | O19: =O13 -> 0.1 | P19: Discount rate
B20: SAFETY | C20: Present value sum | D20: =SUM(D19:N19) -> 12.87964 | O20: 15 | P20: Terminal multiple
C22: Scenario | D22: Probability | E22: PV | F22: Part
C23: Scenario 1 (normal case) | D23: 0.34 | E23: =D8 -> 18.682786 | F23: =E23*D23 -> 6.3521473
C24: Scenario 2 (best case) | D24: 0.33 | E24: =D14 -> 24.92176 | F24: =E24*D24 -> 8.2241809
C25: Scenario 3 (worst case) | D25: 0.33 | E25: =D20 -> 12.87964 | F25: =E25*D25 -> 4.2502811
C26: STOCK PRICE NOW | D26: =C3 -> 33.41 | E26: Sum | F26: =SUM(F23:F25) -> 18.826609
B28: Disclaimer: This is just for educational purposes and not for investing advice!
B30: MADE BY | C30: STOCK MARKET RESEARCH PLATFORM

Sheet RHIM
S1: input cells
B2: RHI Magnesit | C2: LINK TO RESEARCH | S2: result cells
B3: STOCK PRICE | C3: ='COMPARATIVE TABLE'!C26 -> 2085 | F3: DIVIDEND PAYOUT RATIO | I3: 0.5
B4: COMPARATIVE TABLE'!A1 | N4: Terminal Value | O4: Growth rate
B5: Scenario 1 | C5: Earnings per share | D5: 2025 | E5: =D5+1 -> 2026 | F5: =E5+1 -> 2027 | G5: =F5+1 -> 2028 | H5: =G5+1 -> 2029 | I5: =H5+1 -> 2030 | J5: =I5+1 -> 2031 | K5: =J5+1 -> 2032 | L5: =K5+1 -> 2033 | M5: =L5+1 -> 2034 | N5: 2034 | O5: 0.05 | P5: next 5 years
B6: normal case | C6: 250 | D6: =C6*(1+$O$5) -> 262.5 | E6: =D6*(1+$O$5) -> 275.625 | F6: =E6*(1+$O$5) -> 289.40625 | G6: =F6*(1+$O$5) -> 303.87656 | H6: =G6*(1+$O$5) -> 319.07039 | I6: =H6*(1+$O$6) -> 335.02391 | J6: =I6*(1+$O$6) -> 351.77511 | K6: =J6*(1+$O$6) -> 369.36386 | L6: =K6*(1+$O$6) -> 387.83205 | M6: =L6*(1+$O$6) -> 407.22366 | N6: =L6*O8 -> 4653.9846 | O6: 0.05 | P6: 5 to 10 years
C7: =CONCATENATE(R8,O7*100,S8) -> PV(10%) | D7: =D6*(1+$O$7)^($D$5-D5-1)*$I$3 -> 119.31818 | E7: =E6*(1+$O$7)^($D$5-E5-1)*$I$3 -> 113.89463 | F7: =F6*(1+$O$7)^($D$5-F5-1)*$I$3 -> 108.7176 | G7: =G6*(1+$O$7)^($D$5-G5-1)*$I$3 -> 103.77589 | H7: =H6*(1+$O$7)^($D$5-H5-1)*$I$3 -> 99.058805 | I7: =I6*(1+$O$7)^($D$5-I5-1)*$I$3 -> 94.556132 | J7: =J6*(1+$O$7)^($D$5-J5-1)*$I$3 -> 90.258126 | K7: =K6*(1+$O$7)^($D$5-K5-1)*$I$3 -> 86.155484 | ... M7: =M6*(1+$O$7)^($D$5-M5-1)*$I$3 -> 78.501174 | N7: =N6*(1+$O$7)^($D$5-N5-1) -> 1794.3126 | O7: 0.1 | P7: Discount rate
C8: INTRINSIC VALUE | D8: =SUM(D7:N7) -> 2770.7879 | O8: 12 | P8: Terminal multiple | R8: PV( | S8: %)
N10: Terminal Value | O10: Growth rate
B11: Scenario 2 | C11: =C5 -> Earnings per share | D11: =D5 -> 2025 | E11: =D11+1 -> 2026 | F11: =E11+1 -> 2027 | G11: =F11+1 -> 2028 | H11: =G11+1 -> 2029 | I11: =H11+1 -> 2030 | J11: =I11+1 -> 2031 | K11: =J11+1 -> 2032 | L11: =K11+1 -> 2033 | M11: =L11+1 -> 2034 | N11: =N5 -> 2034 | O11: 0.06 | P11: next 5 years
B12: best case | C12: =C6 -> 250 | D12: =C12*(1+$O$11) -> 265 | E12: =D12*(1+$O$11) -> 280.9 | F12: =E12*(1+$O$11) -> 297.754 | G12: =F12*(1+$O$11) -> 315.61924 | H12: =G12*(1+$O$11) -> 334.55639 | I12: =H12*(1+$O$12) -> 354.62978 | J12: =I12*(1+$O$12) -> 375.90756 | K12: =J12*(1+$O$12) -> 398.46202 | L12: =K12*(1+$O$12) -> 422.36974 | M12: =L12*(1+$O$12) -> 447.71192 | N12: =L12*O14 -> 6335.5461 | O12: 0.06 | P12: 5 to 10 years
B13: =B7 -> 0 | C13: =C7 -> PV(10%) | D13: =D12*(1+$O$13)^($D$11-D11-1)*$I$3 -> 120.45455 | E13: =E12*(1+$O$13)^($D$11-E11-1)*$I$3 -> 116.07438 | F13: =F12*(1+$O$13)^($D$11-F11-1)*$I$3 -> 111.85349 | G13: =G12*(1+$O$13)^($D$11-G11-1)*$I$3 -> 107.78609 | H13: =H12*(1+$O$13)^($D$11-H11-1)*$I$3 -> 103.8666 | I13: =I12*(1+$O$13)^($D$11-I11-1)*$I$3 -> 100.08963 | J13: =J12*(1+$O$13)^($D$11-J11-1)*$I$3 -> 96.450009 | K13: =K12*(1+$O$13)^($D$11-K11-1)*$I$3 -> 92.942736 | ... M13: =M12*(1+$O$13)^($D$11-M11-1)*$I$3 -> 86.306164 | N13: =N12*(1+$O$7)^($D$5-N11-1) -> 2442.6273 | O13: =O7 -> 0.1 | P13: Discount rate
C14: Present value sum | D14: =SUM(D13:N13) -> 3468.0139 | O14: 15 | P14: Terminal multiple
N16: Terminal Value | O16: Growth rate
B17: Scenario 3 | C17: =C11 -> Earnings per share | D17: =D11 -> 2025 | E17: =D17+1 -> 2026 | F17: =E17+1 -> 2027 | G17: =F17+1 -> 2028 | H17: =G17+1 -> 2029 | I17: =H17+1 -> 2030 | J17: =I17+1 -> 2031 | K17: =J17+1 -> 2032 | L17: =K17+1 -> 2033 | M17: =L17+1 -> 2034 | N17: =N11 -> 2034 | O17: 0 | P17: next 5 years
B18: worst case | C18: =C12 -> 250 | D18: =C18*(1+$O$17) -> 250 | E18: =D18*(1+$O$17) -> 250 | F18: =E18*(1+$O$17) -> 250 | G18: =F18*(1+$O$17) -> 250 | H18: =G18*(1+$O$17) -> 250 | I18: =H18*(1+$O$18) -> 250 | J18: =I18*(1+$O$18) -> 250 | K18: =J18*(1+$O$18) -> 250 | L18: =K18*(1+$O$18) -> 250 | M18: =L18*(1+$O$18) -> 250 | N18: =L18*O20 -> 2000 | O18: 0 | P18: 5 to 10 years
B19: MARGIN OF | C19: =C13 -> PV(10%) | D19: =D18*(1+$O$19)^($D$17-D17-1)*$I$3 -> 113.63636 | E19: =E18*(1+$O$19)^($D$17-E17-1)*$I$3 -> 103.30579 | F19: =F18*(1+$O$19)^($D$17-F17-1)*$I$3 -> 93.91435 | G19: =G18*(1+$O$19)^($D$17-G17-1)*$I$3 -> 85.376682 | H19: =H18*(1+$O$19)^($D$17-H17-1)*$I$3 -> 77.615165 | I19: =I18*(1+$O$19)^($D$17-I17-1)*$I$3 -> 70.559241 | J19: =J18*(1+$O$19)^($D$17-J17-1)*$I$3 -> 64.144765 | K19: =K18*(1+$O$19)^($D$17-K17-1)*$I$3 -> 58.313423 | ... M19: =M18*(1+$O$19)^($D$17-M17-1)*$I$3 -> 48.192911 | N19: =N18*(1+$O$19)^($D$17-N17-1) -> 771.08658 | O19: =O13 -> 0.1 | P19: Discount rate
B20: SAFETY | C20: Present value sum | D20: =SUM(D19:N19) -> 1539.1575 | O20: 8 | P20: Terminal multiple
C22: Scenario | D22: Probability | E22: PV | F22: Part
C23: Scenario 1 (normal case) | D23: 0.34 | E23: =D8 -> 2770.7879 | F23: =E23*D23 -> 942.06788
C24: Scenario 2 (best case) | D24: 0.33 | E24: =D14 -> 3468.0139 | F24: =E24*D24 -> 1144.4446
C25: Scenario 3 (worst case) | D25: 0.33 | E25: =D20 -> 1539.1575 | F25: =E25*D25 -> 507.92196
C26: STOCK PRICE NOW | D26: =C3 -> 2085 | E26: Sum | F26: =SUM(F23:F25) -> 2594.4344
B28: Disclaimer: This is just for educational purposes and not for investing advice!
B30: MADE BY | C30: STOCK MARKET RESEARCH PLATFORM

Sheet RUI
S1: input cells
B2: RUBIS | C2: LINK TO RESEARCH | S2: result cells
B3: STOCK PRICE | C3: ='COMPARATIVE TABLE'!C27 -> 28.16 | F3: DIVIDEND PAYOUT RATIO | I3: 1
B4: COMPARATIVE TABLE'!A1 | N4: Terminal Value | O4: Growth rate
B5: Scenario 1 | C5: Dividend per share | D5: 2025 | E5: =D5+1 -> 2026 | F5: =E5+1 -> 2027 | G5: =F5+1 -> 2028 | H5: =G5+1 -> 2029 | I5: =H5+1 -> 2030 | J5: =I5+1 -> 2031 | K5: =J5+1 -> 2032 | L5: =K5+1 -> 2033 | M5: =L5+1 -> 2034 | N5: 2034 | O5: 0.03 | P5: next 5 years
B6: normal case | C6: 2.03 | D6: =C6*(1+$O$5) -> 2.0909 | E6: =D6*(1+$O$5) -> 2.153627 | F6: =E6*(1+$O$5) -> 2.2182358 | G6: =F6*(1+$O$5) -> 2.2847829 | H6: =G6*(1+$O$5) -> 2.3533264 | I6: =H6*(1+$O$6) -> 2.4239262 | J6: =I6*(1+$O$6) -> 2.4966439 | K6: =J6*(1+$O$6) -> 2.5715433 | L6: =K6*(1+$O$6) -> 2.6486896 | M6: =L6*(1+$O$6) -> 2.7281503 | N6: =L6*O8 -> 29.135585 | O6: 0.03 | P6: 5 to 10 years
C7: =CONCATENATE(R8,O7*100,S8) -> PV(10%) | D7: =D6*(1+$O$7)^($D$5-D5-1)*$I$3 -> 1.9008182 | E7: =E6*(1+$O$7)^($D$5-E5-1)*$I$3 -> 1.779857 | F7: =F6*(1+$O$7)^($D$5-F5-1)*$I$3 -> 1.6665934 | G7: =G6*(1+$O$7)^($D$5-G5-1)*$I$3 -> 1.5605375 | H7: =H6*(1+$O$7)^($D$5-H5-1)*$I$3 -> 1.4612305 | I7: =I6*(1+$O$7)^($D$5-I5-1)*$I$3 -> 1.3682431 | J7: =J6*(1+$O$7)^($D$5-J5-1)*$I$3 -> 1.2811731 | K7: =K6*(1+$O$7)^($D$5-K5-1)*$I$3 -> 1.1996439 | ... M7: =M6*(1+$O$7)^($D$5-M5-1)*$I$3 -> 1.05182 | N7: =N6*(1+$O$7)^($D$5-N5-1) -> 11.233029 | O7: 0.1 | P7: Discount rate
C8: INTRINSIC VALUE | D8: =SUM(D7:N7) -> 25.626249 | O8: 11 | P8: Terminal multiple | R8: PV( | S8: %)
N10: Terminal Value | O10: Growth rate
B11: Scenario 2 | C11: =C5 -> Dividend per share | D11: =D5 -> 2025 | E11: =D11+1 -> 2026 | F11: =E11+1 -> 2027 | G11: =F11+1 -> 2028 | H11: =G11+1 -> 2029 | I11: =H11+1 -> 2030 | J11: =I11+1 -> 2031 | K11: =J11+1 -> 2032 | L11: =K11+1 -> 2033 | M11: =L11+1 -> 2034 | N11: =N5 -> 2034 | O11: 0.05 | P11: next 5 years
B12: best case | C12: =C6 -> 2.03 | D12: =C12*(1+$O$11) -> 2.1315 | E12: =D12*(1+$O$11) -> 2.238075 | F12: =E12*(1+$O$11) -> 2.3499788 | G12: =F12*(1+$O$11) -> 2.4674777 | H12: =G12*(1+$O$11) -> 2.5908516 | I12: =H12*(1+$O$12) -> 2.7203942 | J12: =I12*(1+$O$12) -> 2.8564139 | K12: =J12*(1+$O$12) -> 2.9992346 | L12: =K12*(1+$O$12) -> 3.1491963 | M12: =L12*(1+$O$12) -> 3.3066561 | N12: =L12*O14 -> 37.790355 | O12: 0.05 | P12: 5 to 10 years
B13: =B7 -> 0 | C13: =C7 -> PV(10%) | D13: =D12*(1+$O$13)^($D$11-D11-1)*$I$3 -> 1.9377273 | E13: =E12*(1+$O$13)^($D$11-E11-1)*$I$3 -> 1.8496488 | F13: =F12*(1+$O$13)^($D$11-F11-1)*$I$3 -> 1.7655738 | G13: =G12*(1+$O$13)^($D$11-G11-1)*$I$3 -> 1.6853205 | H13: =H12*(1+$O$13)^($D$11-H11-1)*$I$3 -> 1.608715 | I13: =I12*(1+$O$13)^($D$11-I11-1)*$I$3 -> 1.5355916 | J13: =J12*(1+$O$13)^($D$11-J11-1)*$I$3 -> 1.465792 | K13: =K12*(1+$O$13)^($D$11-K11-1)*$I$3 -> 1.3991651 | ... M13: =M12*(1+$O$13)^($D$11-M11-1)*$I$3 -> 1.2748591 | N13: =N12*(1+$O$7)^($D$5-N11-1) -> 14.569818 | O13: =O7 -> 0.1 | P13: Discount rate
C14: Present value sum | D14: =SUM(D13:N13) -> 30.427778 | O14: 12 | P14: Terminal multiple
N16: Terminal Value | O16: Growth rate
B17: Scenario 3 | C17: =C11 -> Dividend per share | D17: =D11 -> 2025 | E17: =D17+1 -> 2026 | F17: =E17+1 -> 2027 | G17: =F17+1 -> 2028 | H17: =G17+1 -> 2029 | I17: =H17+1 -> 2030 | J17: =I17+1 -> 2031 | K17: =J17+1 -> 2032 | L17: =K17+1 -> 2033 | M17: =L17+1 -> 2034 | N17: =N11 -> 2034 | O17: 0.02 | P17: next 5 years
B18: worst case | C18: =C12 -> 2.03 | D18: =C18*(1+$O$17) -> 2.0706 | E18: =D18*(1+$O$17) -> 2.112012 | F18: =E18*(1+$O$17) -> 2.1542522 | G18: =F18*(1+$O$17) -> 2.1973373 | H18: =G18*(1+$O$17) -> 2.241284 | I18: =H18*(1+$O$18) -> 2.2861097 | J18: =I18*(1+$O$18) -> 2.3318319 | K18: =J18*(1+$O$18) -> 2.3784685 | L18: =K18*(1+$O$18) -> 2.4260379 | M18: =L18*(1+$O$18) -> 2.4745587 | N18: =L18*O20 -> 24.260379 | O18: 0.02 | P18: 5 to 10 years
B19: MARGIN OF | C19: =C13 -> PV(10%) | D19: =D18*(1+$O$19)^($D$17-D17-1)*$I$3 -> 1.8823636 | E19: =E18*(1+$O$19)^($D$17-E17-1)*$I$3 -> 1.7454645 | F19: =F18*(1+$O$19)^($D$17-F17-1)*$I$3 -> 1.6185216 | G19: =G18*(1+$O$19)^($D$17-G17-1)*$I$3 -> 1.5008109 | H19: =H18*(1+$O$19)^($D$17-H17-1)*$I$3 -> 1.391661 | I19: =I18*(1+$O$19)^($D$17-I17-1)*$I$3 -> 1.2904493 | J19: =J18*(1+$O$19)^($D$17-J17-1)*$I$3 -> 1.1965985 | K19: =K18*(1+$O$19)^($D$17-K17-1)*$I$3 -> 1.1095731 | ... M19: =M18*(1+$O$19)^($D$17-M17-1)*$I$3 -> 0.95404949 | N19: =N18*(1+$O$19)^($D$17-N17-1) -> 9.3534264 | O19: =O13 -> 0.1 | P19: Discount rate
B20: SAFETY | C20: Present value sum | D20: =SUM(D19:N19) -> 23.071795 | O20: 10 | P20: Terminal multiple
C22: Scenario | D22: Probability | E22: PV | F22: Part
C23: Scenario 1 (normal case) | D23: 0.34 | E23: =D8 -> 25.626249 | F23: =E23*D23 -> 8.7129247
C24: Scenario 2 (best case) | D24: 0.33 | E24: =D14 -> 30.427778 | F24: =E24*D24 -> 10.041167
C25: Scenario 3 (worst case) | D25: 0.33 | E25: =D20 -> 23.071795 | F25: =E25*D25 -> 7.6136925
C26: STOCK PRICE NOW | D26: =C3 -> 28.16 | E26: Sum | F26: =SUM(F23:F25) -> 26.367784
B28: Disclaimer: This is just for educational purposes and not for investing advice!
B30: MADE BY | C30: STOCK MARKET RESEARCH PLATFORM

Sheet LIGHT
S1: input cells
B2: Signify | C2: LINK TO RESEARCH | S2: result cells
B3: STOCK PRICE | C3: ='COMPARATIVE TABLE'!C28 -> 23.06 | F3: DIVIDEND PAYOUT RATIO | I3: 0.55
B4: COMPARATIVE TABLE'!A1 | N4: Terminal Value | O4: Growth rate
B5: Scenario 1 | C5: FCF Per Share | D5: 2025 | E5: =D5+1 -> 2026 | F5: =E5+1 -> 2027 | G5: =F5+1 -> 2028 | H5: =G5+1 -> 2029 | I5: =H5+1 -> 2030 | J5: =I5+1 -> 2031 | K5: =J5+1 -> 2032 | L5: =K5+1 -> 2033 | M5: =L5+1 -> 2034 | N5: 2034 | O5: 0 | P5: next 5 years
B6: normal case | C6: 3.13 | D6: =C6*(1+$O$5) -> 3.13 | E6: =D6*(1+$O$5) -> 3.13 | F6: =E6*(1+$O$5) -> 3.13 | G6: =F6*(1+$O$5) -> 3.13 | H6: =G6*(1+$O$5) -> 3.13 | I6: =H6*(1+$O$6) -> 3.13 | J6: =I6*(1+$O$6) -> 3.13 | K6: =J6*(1+$O$6) -> 3.13 | L6: =K6*(1+$O$6) -> 3.13 | M6: =L6*(1+$O$6) -> 3.13 | N6: =L6*O8 -> 31.3 | O6: 0 | P6: 5 to 10 years
C7: =CONCATENATE(R8,O7*100,S8) -> PV(10%) | D7: =D6*(1+$O$7)^($D$5-D5-1)*$I$3 -> 1.565 | E7: =E6*(1+$O$7)^($D$5-E5-1)*$I$3 -> 1.4227273 | F7: =F6*(1+$O$7)^($D$5-F5-1)*$I$3 -> 1.2933884 | G7: =G6*(1+$O$7)^($D$5-G5-1)*$I$3 -> 1.1758077 | H7: =H6*(1+$O$7)^($D$5-H5-1)*$I$3 -> 1.0689161 | I7: =I6*(1+$O$7)^($D$5-I5-1)*$I$3 -> 0.97174187 | J7: =J6*(1+$O$7)^($D$5-J5-1)*$I$3 -> 0.8834017 | K7: =K6*(1+$O$7)^($D$5-K5-1)*$I$3 -> 0.80309246 | ... M7: =M6*(1+$O$7)^($D$5-M5-1)*$I$3 -> 0.66371277 | N7: =N6*(1+$O$7)^($D$5-N5-1) -> 12.067505 | O7: 0.1 | P7: Discount rate
C8: INTRINSIC VALUE | D8: =SUM(D7:N7) -> 22.645377 | O8: 10 | P8: Terminal multiple | R8: PV( | S8: %)
N10: Terminal Value | O10: Growth rate
B11: Scenario 2 | C11: =C5 -> FCF Per Share | D11: =D5 -> 2025 | E11: =D11+1 -> 2026 | F11: =E11+1 -> 2027 | G11: =F11+1 -> 2028 | H11: =G11+1 -> 2029 | I11: =H11+1 -> 2030 | J11: =I11+1 -> 2031 | K11: =J11+1 -> 2032 | L11: =K11+1 -> 2033 | M11: =L11+1 -> 2034 | N11: =N5 -> 2034 | O11: 0.04 | P11: next 5 years
B12: best case | C12: =C6 -> 3.13 | D12: =C12*(1+$O$11) -> 3.2552 | E12: =D12*(1+$O$11) -> 3.385408 | F12: =E12*(1+$O$11) -> 3.5208243 | G12: =F12*(1+$O$11) -> 3.6616573 | H12: =G12*(1+$O$11) -> 3.8081236 | I12: =H12*(1+$O$12) -> 3.9604485 | J12: =I12*(1+$O$12) -> 4.1188665 | K12: =J12*(1+$O$12) -> 4.2836211 | L12: =K12*(1+$O$12) -> 4.454966 | M12: =L12*(1+$O$12) -> 4.6331646 | N12: =L12*O14 -> 53.459592 | O12: 0.04 | P12: 5 to 10 years
B13: =B7 -> 0 | C13: =C7 -> PV(10%) | D13: =D12*(1+$O$13)^($D$11-D11-1)*$I$3 -> 1.6276 | E13: =E12*(1+$O$13)^($D$11-E11-1)*$I$3 -> 1.5388218 | F13: =F12*(1+$O$13)^($D$11-F11-1)*$I$3 -> 1.4548861 | G13: =G12*(1+$O$13)^($D$11-G11-1)*$I$3 -> 1.3755287 | H13: =H12*(1+$O$13)^($D$11-H11-1)*$I$3 -> 1.3004998 | I13: =I12*(1+$O$13)^($D$11-I11-1)*$I$3 -> 1.2295635 | J13: =J12*(1+$O$13)^($D$11-J11-1)*$I$3 -> 1.1624964 | K13: =K12*(1+$O$13)^($D$11-K11-1)*$I$3 -> 1.0990875 | ... M13: =M12*(1+$O$13)^($D$11-M11-1)*$I$3 -> 0.98245704 | N13: =N12*(1+$O$7)^($D$5-N11-1) -> 20.610987 | O13: =O7 -> 0.1 | P13: Discount rate
C14: Present value sum | D14: =SUM(D13:N13) -> 33.421065 | O14: 12 | P14: Terminal multiple
N16: Terminal Value | O16: Growth rate
B17: Scenario 3 | C17: =C11 -> FCF Per Share | D17: =D11 -> 2025 | E17: =D17+1 -> 2026 | F17: =E17+1 -> 2027 | G17: =F17+1 -> 2028 | H17: =G17+1 -> 2029 | I17: =H17+1 -> 2030 | J17: =I17+1 -> 2031 | K17: =J17+1 -> 2032 | L17: =K17+1 -> 2033 | M17: =L17+1 -> 2034 | N17: =N11 -> 2034 | O17: 0 | P17: next 5 years
B18: worst case | C18: =C12 -> 3.13 | D18: =C18*(1+$O$17) -> 3.13 | E18: =D18*(1+$O$17) -> 3.13 | F18: =E18*(1+$O$17) -> 3.13 | G18: =F18*(1+$O$17) -> 3.13 | H18: =G18*(1+$O$17) -> 3.13 | I18: =H18*(1+$O$18) -> 3.13 | J18: =I18*(1+$O$18) -> 3.13 | K18: =J18*(1+$O$18) -> 3.13 | L18: =K18*(1+$O$18) -> 3.13 | M18: =L18*(1+$O$18) -> 3.13 | N18: =L18*O20 -> 25.04 | O18: 0 | P18: 5 to 10 years
B19: MARGIN OF | C19: =C13 -> PV(10%) | D19: =D18*(1+$O$19)^($D$17-D17-1)*$I$3 -> 1.565 | E19: =E18*(1+$O$19)^($D$17-E17-1)*$I$3 -> 1.4227273 | F19: =F18*(1+$O$19)^($D$17-F17-1)*$I$3 -> 1.2933884 | G19: =G18*(1+$O$19)^($D$17-G17-1)*$I$3 -> 1.1758077 | H19: =H18*(1+$O$19)^($D$17-H17-1)*$I$3 -> 1.0689161 | I19: =I18*(1+$O$19)^($D$17-I17-1)*$I$3 -> 0.97174187 | J19: =J18*(1+$O$19)^($D$17-J17-1)*$I$3 -> 0.8834017 | K19: =K18*(1+$O$19)^($D$17-K17-1)*$I$3 -> 0.80309246 | ... M19: =M18*(1+$O$19)^($D$17-M17-1)*$I$3 -> 0.66371277 | N19: =N18*(1+$O$19)^($D$17-N17-1) -> 9.654004 | O19: =O13 -> 0.1 | P19: Discount rate
B20: SAFETY | C20: Present value sum | D20: =SUM(D19:N19) -> 20.231876 | O20: 8 | P20: Terminal multiple
C22: Scenario | D22: Probability | E22: PV | F22: Part
C23: Scenario 1 (normal case) | D23: 0.34 | E23: =D8 -> 22.645377 | F23: =E23*D23 -> 7.6994283
C24: Scenario 2 (best case) | D24: 0.33 | E24: =D14 -> 33.421065 | F24: =E24*D24 -> 11.028951
C25: Scenario 3 (worst case) | D25: 0.33 | E25: =D20 -> 20.231876 | F25: =E25*D25 -> 6.6765192
C26: STOCK PRICE NOW | D26: =C3 -> 23.06 | E26: Sum | F26: =SUM(F23:F25) -> 25.404899
B28: Disclaimer: This is just for educational purposes and not for investing advice!
B30: MADE BY | C30: STOCK MARKET RESEARCH PLATFORM

Sheet SIRI
S1: input cells
B2: SiriusXM | C2: LINK TO RESEARCH | S2: result cells
B3: STOCK PRICE | C3: ='COMPARATIVE TABLE'!C29 -> 23.81 | F3: DIVIDEND PAYOUT RATIO | I3: 0.4
B4: COMPARATIVE TABLE'!A1 | N4: Terminal Value | O4: Growth rate
B5: Scenario 1 | C5: FCF per share | D5: 2025 | E5: =D5+1 -> 2026 | F5: =E5+1 -> 2027 | G5: =F5+1 -> 2028 | H5: =G5+1 -> 2029 | I5: =H5+1 -> 2030 | J5: =I5+1 -> 2031 | K5: =J5+1 -> 2032 | L5: =K5+1 -> 2033 | M5: =L5+1 -> 2034 | N5: 2034 | O5: 0.1 | P5: next 5 years
B6: normal case | C6: 3.3 | D6: =C6*(1+$O$5) -> 3.63 | E6: =D6*(1+$O$5) -> 3.993 | F6: =E6*(1+$O$5) -> 4.3923 | G6: =F6*(1+$O$5) -> 4.83153 | H6: =G6*(1+$O$5) -> 5.314683 | I6: =H6*(1+$O$6) -> 5.0489489 | J6: =I6*(1+$O$6) -> 4.7965014 | K6: =J6*(1+$O$6) -> 4.5566763 | L6: =K6*(1+$O$6) -> 4.3288425 | M6: =L6*(1+$O$6) -> 4.1124004 | N6: =L6*O8 -> 43.288425 | O6: -0.05 | P6: 5 to 10 years
C7: =CONCATENATE(R8,O7*100,S8) -> PV(10%) | D7: =D6*(1+$O$7)^($D$5-D5-1)*$I$3 -> 1.32 | E7: =E6*(1+$O$7)^($D$5-E5-1)*$I$3 -> 1.32 | F7: =F6*(1+$O$7)^($D$5-F5-1)*$I$3 -> 1.32 | G7: =G6*(1+$O$7)^($D$5-G5-1)*$I$3 -> 1.32 | H7: =H6*(1+$O$7)^($D$5-H5-1)*$I$3 -> 1.32 | I7: =I6*(1+$O$7)^($D$5-I5-1)*$I$3 -> 1.14 | J7: =J6*(1+$O$7)^($D$5-J5-1)*$I$3 -> 0.98454545 | K7: =K6*(1+$O$7)^($D$5-K5-1)*$I$3 -> 0.85028926 | ... M7: =M6*(1+$O$7)^($D$5-M5-1)*$I$3 -> 0.63420335 | N7: =N6*(1+$O$7)^($D$5-N5-1) -> 16.689562 | O7: 0.1 | P7: Discount rate
C8: INTRINSIC VALUE | D8: =SUM(D7:N7) -> 27.632941 | O8: 10 | P8: Terminal multiple | R8: PV( | S8: %)
N10: Terminal Value | O10: Growth rate
B11: Scenario 2 | C11: =C5 -> FCF per share | D11: =D5 -> 2025 | E11: =D11+1 -> 2026 | F11: =E11+1 -> 2027 | G11: =F11+1 -> 2028 | H11: =G11+1 -> 2029 | I11: =H11+1 -> 2030 | J11: =I11+1 -> 2031 | K11: =J11+1 -> 2032 | L11: =K11+1 -> 2033 | M11: =L11+1 -> 2034 | N11: =N5 -> 2034 | O11: 0.03 | P11: next 5 years
B12: best case | C12: =C6 -> 3.3 | D12: =C12*(1+$O$11) -> 3.399 | E12: =D12*(1+$O$11) -> 3.50097 | F12: =E12*(1+$O$11) -> 3.6059991 | G12: =F12*(1+$O$11) -> 3.7141791 | H12: =G12*(1+$O$11) -> 3.8256044 | I12: =H12*(1+$O$12) -> 3.9403726 | J12: =I12*(1+$O$12) -> 4.0585838 | K12: =J12*(1+$O$12) -> 4.1803413 | L12: =K12*(1+$O$12) -> 4.3057515 | M12: =L12*(1+$O$12) -> 4.4349241 | N12: =L12*O14 -> 51.669018 | O12: 0.03 | P12: 5 to 10 years
B13: =B7 -> 0 | C13: =C7 -> PV(10%) | D13: =D12*(1+$O$13)^($D$11-D11-1)*$I$3 -> 1.236 | E13: =E12*(1+$O$13)^($D$11-E11-1)*$I$3 -> 1.1573455 | F13: =F12*(1+$O$13)^($D$11-F11-1)*$I$3 -> 1.0836962 | G13: =G12*(1+$O$13)^($D$11-G11-1)*$I$3 -> 1.0147337 | H13: =H12*(1+$O$13)^($D$11-H11-1)*$I$3 -> 0.95015975 | I13: =I12*(1+$O$13)^($D$11-I11-1)*$I$3 -> 0.88969504 | J13: =J12*(1+$O$13)^($D$11-J11-1)*$I$3 -> 0.83307808 | K13: =K12*(1+$O$13)^($D$11-K11-1)*$I$3 -> 0.78006402 | ... M13: =M12*(1+$O$13)^($D$11-M11-1)*$I$3 -> 0.68394208 | N13: =N12*(1+$O$7)^($D$5-N11-1) -> 19.920643 | O13: =O7 -> 0.1 | P13: Discount rate
C14: Present value sum | D14: =SUM(D13:N13) -> 29.279781 | O14: 12 | P14: Terminal multiple
N16: Terminal Value | O16: Growth rate
B17: Scenario 3 | C17: =C11 -> FCF per share | D17: =D11 -> 2025 | E17: =D17+1 -> 2026 | F17: =E17+1 -> 2027 | G17: =F17+1 -> 2028 | H17: =G17+1 -> 2029 | I17: =H17+1 -> 2030 | J17: =I17+1 -> 2031 | K17: =J17+1 -> 2032 | L17: =K17+1 -> 2033 | M17: =L17+1 -> 2034 | N17: =N11 -> 2034 | O17: -0.03 | P17: next 5 years
B18: worst case | C18: =C12 -> 3.3 | D18: =C18*(1+$O$17) -> 3.201 | E18: =D18*(1+$O$17) -> 3.10497 | F18: =E18*(1+$O$17) -> 3.0118209 | G18: =F18*(1+$O$17) -> 2.9214663 | H18: =G18*(1+$O$17) -> 2.8338223 | I18: =H18*(1+$O$18) -> 2.6921312 | J18: =I18*(1+$O$18) -> 2.5575246 | K18: =J18*(1+$O$18) -> 2.4296484 | L18: =K18*(1+$O$18) -> 2.308166 | M18: =L18*(1+$O$18) -> 2.1927577 | N18: =L18*O20 -> 23.08166 | O18: -0.05 | P18: 5 to 10 years
B19: MARGIN OF | C19: =C13 -> PV(10%) | D19: =D18*(1+$O$19)^($D$17-D17-1)*$I$3 -> 1.164 | E19: =E18*(1+$O$19)^($D$17-E17-1)*$I$3 -> 1.0264364 | F19: =F18*(1+$O$19)^($D$17-F17-1)*$I$3 -> 0.90513025 | G19: =G18*(1+$O$19)^($D$17-G17-1)*$I$3 -> 0.79816031 | H19: =H18*(1+$O$19)^($D$17-H17-1)*$I$3 -> 0.70383227 | I19: =I18*(1+$O$19)^($D$17-I17-1)*$I$3 -> 0.60785514 | J19: =J18*(1+$O$19)^($D$17-J17-1)*$I$3 -> 0.52496581 | K19: =K18*(1+$O$19)^($D$17-K17-1)*$I$3 -> 0.45337956 | ... M19: =M18*(1+$O$19)^($D$17-M17-1)*$I$3 -> 0.3381612 | N19: =N18*(1+$O$19)^($D$17-N17-1) -> 8.898979 | O19: =O13 -> 0.1 | P19: Discount rate
B20: SAFETY | C20: Present value sum | D20: =SUM(D19:N19) -> 15.812455 | O20: 10 | P20: Terminal multiple
C22: Scenario | D22: Probability | E22: PV | F22: Part
C23: Scenario 1 (normal case) | D23: 1 | E23: =D8 -> 27.632941 | F23: =E23*D23 -> 27.632941
C24: Scenario 2 (best case) | D24: 0 | E24: =D14 -> 29.279781 | F24: =E24*D24 -> 0
C25: Scenario 3 (worst case) | D25: 0 | E25: =D20 -> 15.812455 | F25: =E25*D25 -> 0
C26: STOCK PRICE NOW | D26: =C3 -> 23.81 | E26: Sum | F26: =SUM(F23:F25) -> 27.632941
B28: Disclaimer: This is just for educational purposes and not for investing advice!
B30: MADE BY | C30: STOCK MARKET RESEARCH PLATFORM

Sheet SNRE
S1: input cells
B2: Sunrise | C2: LINK TO RESEARCH | S2: result cells
B3: STOCK PRICE | C3: ='COMPARATIVE TABLE'!C30 -> 48.98 | F3: DIVIDEND PAYOUT RATIO | I3: 1
B4: COMPARATIVE TABLE'!A1 | N4: Terminal Value | O4: Growth rate
B5: Scenario 1 | C5: Dividend per share CHF | D5: 2025 | E5: =D5+1 -> 2026 | F5: =E5+1 -> 2027 | G5: =F5+1 -> 2028 | H5: =G5+1 -> 2029 | I5: =H5+1 -> 2030 | J5: =I5+1 -> 2031 | K5: =J5+1 -> 2032 | L5: =K5+1 -> 2033 | M5: =L5+1 -> 2034 | N5: 2034 | O5: 0.03 | P5: next 5 years
B6: normal case | C6: 3.33 | D6: =C6*(1+$O$5) -> 3.4299 | E6: =D6*(1+$O$5) -> 3.532797 | F6: =E6*(1+$O$5) -> 3.6387809 | G6: =F6*(1+$O$5) -> 3.7479443 | H6: =G6*(1+$O$5) -> 3.8603827 | I6: =H6*(1+$O$6) -> 3.9761941 | J6: =I6*(1+$O$6) -> 4.09548 | K6: =J6*(1+$O$6) -> 4.2183444 | L6: =K6*(1+$O$6) -> 4.3448947 | M6: =L6*(1+$O$6) -> 4.4752415 | N6: =L6*O8 -> 65.173421 | O6: 0.03 | P6: 5 to 10 years
C7: =CONCATENATE(R8,O7*100,S8) -> PV(10%) | D7: =D6*(1+$O$7)^($D$5-D5-1)*$I$3 -> 3.1180909 | E7: =E6*(1+$O$7)^($D$5-E5-1)*$I$3 -> 2.9196669 | F7: =F6*(1+$O$7)^($D$5-F5-1)*$I$3 -> 2.73387 | G7: =G6*(1+$O$7)^($D$5-G5-1)*$I$3 -> 2.5598964 | H7: =H6*(1+$O$7)^($D$5-H5-1)*$I$3 -> 2.3969939 | I7: =I6*(1+$O$7)^($D$5-I5-1)*$I$3 -> 2.2444579 | J7: =J6*(1+$O$7)^($D$5-J5-1)*$I$3 -> 2.1016288 | K7: =K6*(1+$O$7)^($D$5-K5-1)*$I$3 -> 1.9678888 | ... M7: =M6*(1+$O$7)^($D$5-M5-1)*$I$3 -> 1.7253993 | N7: =N6*(1+$O$7)^($D$5-N5-1) -> 25.127175 | O7: 0.1 | P7: Discount rate
C8: INTRINSIC VALUE | D8: =SUM(D7:N7) -> 48.737727 | O8: 15 | P8: Terminal multiple | R8: PV( | S8: %)
N10: Terminal Value | O10: Growth rate
B11: Scenario 2 | C11: =C5 -> Dividend per share CHF | D11: =D5 -> 2025 | E11: =D11+1 -> 2026 | F11: =E11+1 -> 2027 | G11: =F11+1 -> 2028 | H11: =G11+1 -> 2029 | I11: =H11+1 -> 2030 | J11: =I11+1 -> 2031 | K11: =J11+1 -> 2032 | L11: =K11+1 -> 2033 | M11: =L11+1 -> 2034 | N11: =N5 -> 2034 | O11: 0.04 | P11: next 5 years
B12: best case | C12: =C6 -> 3.33 | D12: =C12*(1+$O$11) -> 3.4632 | E12: =D12*(1+$O$11) -> 3.601728 | F12: =E12*(1+$O$11) -> 3.7457971 | G12: =F12*(1+$O$11) -> 3.895629 | H12: =G12*(1+$O$11) -> 4.0514542 | I12: =H12*(1+$O$12) -> 4.2135123 | J12: =I12*(1+$O$12) -> 4.3820528 | K12: =J12*(1+$O$12) -> 4.5573349 | L12: =K12*(1+$O$12) -> 4.7396283 | M12: =L12*(1+$O$12) -> 4.9292135 | N12: =L12*O14 -> 94.792567 | O12: 0.04 | P12: 5 to 10 years
B13: =B7 -> 0 | C13: =C7 -> PV(10%) | D13: =D12*(1+$O$13)^($D$11-D11-1)*$I$3 -> 3.1483636 | E13: =E12*(1+$O$13)^($D$11-E11-1)*$I$3 -> 2.9766347 | F13: =F12*(1+$O$13)^($D$11-F11-1)*$I$3 -> 2.8142728 | G13: =G12*(1+$O$13)^($D$11-G11-1)*$I$3 -> 2.660767 | H13: =H12*(1+$O$13)^($D$11-H11-1)*$I$3 -> 2.5156343 | I13: =I12*(1+$O$13)^($D$11-I11-1)*$I$3 -> 2.3784179 | J13: =J12*(1+$O$13)^($D$11-J11-1)*$I$3 -> 2.248686 | K13: =K12*(1+$O$13)^($D$11-K11-1)*$I$3 -> 2.1260304 | ... M13: =M12*(1+$O$13)^($D$11-M11-1)*$I$3 -> 1.9004252 | N13: =N12*(1+$O$7)^($D$5-N11-1) -> 36.546638 | O13: =O7 -> 0.1 | P13: Discount rate
C14: Present value sum | D14: =SUM(D13:N13) -> 61.325935 | O14: 20 | P14: Terminal multiple
N16: Terminal Value | O16: Growth rate
B17: Scenario 3 | C17: =C11 -> Dividend per share CHF | D17: =D11 -> 2025 | E17: =D17+1 -> 2026 | F17: =E17+1 -> 2027 | G17: =F17+1 -> 2028 | H17: =G17+1 -> 2029 | I17: =H17+1 -> 2030 | J17: =I17+1 -> 2031 | K17: =J17+1 -> 2032 | L17: =K17+1 -> 2033 | M17: =L17+1 -> 2034 | N17: =N11 -> 2034 | O17: 0 | P17: next 5 years
B18: worst case | C18: =C12 -> 3.33 | D18: =C18*(1+$O$17) -> 3.33 | E18: =D18*(1+$O$17) -> 3.33 | F18: =E18*(1+$O$17) -> 3.33 | G18: =F18*(1+$O$17) -> 3.33 | H18: =G18*(1+$O$17) -> 3.33 | I18: =H18*(1+$O$18) -> 3.33 | J18: =I18*(1+$O$18) -> 3.33 | K18: =J18*(1+$O$18) -> 3.33 | L18: =K18*(1+$O$18) -> 3.33 | M18: =L18*(1+$O$18) -> 3.33 | N18: =L18*O20 -> 33.3 | O18: 0 | P18: 5 to 10 years
B19: MARGIN OF | C19: =C13 -> PV(10%) | D19: =D18*(1+$O$19)^($D$17-D17-1)*$I$3 -> 3.0272727 | E19: =E18*(1+$O$19)^($D$17-E17-1)*$I$3 -> 2.7520661 | F19: =F18*(1+$O$19)^($D$17-F17-1)*$I$3 -> 2.5018783 | G19: =G18*(1+$O$19)^($D$17-G17-1)*$I$3 -> 2.2744348 | H19: =H18*(1+$O$19)^($D$17-H17-1)*$I$3 -> 2.067668 | I19: =I18*(1+$O$19)^($D$17-I17-1)*$I$3 -> 1.8796982 | J19: =J18*(1+$O$19)^($D$17-J17-1)*$I$3 -> 1.7088165 | K19: =K18*(1+$O$19)^($D$17-K17-1)*$I$3 -> 1.5534696 | ... M19: =M18*(1+$O$19)^($D$17-M17-1)*$I$3 -> 1.2838592 | N19: =N18*(1+$O$19)^($D$17-N17-1) -> 12.838592 | O19: =O13 -> 0.1 | P19: Discount rate
B20: SAFETY | C20: Present value sum | D20: =SUM(D19:N19) -> 33.3 | O20: 10 | P20: Terminal multiple
C22: Scenario | D22: Probability | E22: PV | F22: Part
C23: Scenario 1 (normal case) | D23: 0.34 | E23: =D8 -> 48.737727 | F23: =E23*D23 -> 16.570827
C24: Scenario 2 (best case) | D24: 0.33 | E24: =D14 -> 61.325935 | F24: =E24*D24 -> 20.237559
C25: Scenario 3 (worst case) | D25: 0.33 | E25: =D20 -> 33.3 | F25: =E25*D25 -> 10.989
C26: STOCK PRICE NOW | D26: =C3 -> 48.98 | E26: Sum | F26: =SUM(F23:F25) -> 47.797386
B28: Disclaimer: This is just for educational purposes and not for investing advice!
B30: MADE BY | C30: STOCK MARKET RESEARCH PLATFORM

Sheet TIBN
S1: input cells
B2: Titlis | C2: LINK TO RESEARCH | S2: result cells
B3: STOCK PRICE | C3: ='COMPARATIVE TABLE'!C31 -> 43.1 | F3: DIVIDEND PAYOUT RATIO | I3: 0
B4: COMPARATIVE TABLE'!A1 | N4: Terminal Value | O4: Growth rate
B5: Scenario 1 | C5: Earnings per share | D5: 2025 | E5: =D5+1 -> 2026 | F5: =E5+1 -> 2027 | G5: =F5+1 -> 2028 | H5: =G5+1 -> 2029 | I5: =H5+1 -> 2030 | J5: =I5+1 -> 2031 | K5: =J5+1 -> 2032 | L5: =K5+1 -> 2033 | M5: =L5+1 -> 2034 | N5: 2034 | O5: 0 | P5: next 5 years
B6: normal case | C6: 0 | D6: =C6*(1+$O$5) -> 0 | E6: =D6*(1+$O$5) -> 0 | F6: =E6*(1+$O$5) -> 0 | G6: =F6*(1+$O$5) -> 0 | H6: =G6*(1+$O$5) -> 0 | I6: =H6*(1+$O$6) -> 0 | J6: =I6*(1+$O$6) -> 0 | K6: =J6*(1+$O$6) -> 0 | L6: 10 | M6: 10 | N6: =L6*O8 -> 150 | O6: 0 | P6: 5 to 10 years
C7: =CONCATENATE(R8,O7*100,S8) -> PV(10%) | D7: =D6*(1+$O$7)^($D$5-D5-1)*$I$3 -> 0 | E7: =E6*(1+$O$7)^($D$5-E5-1)*$I$3 -> 0 | F7: =F6*(1+$O$7)^($D$5-F5-1)*$I$3 -> 0 | G7: =G6*(1+$O$7)^($D$5-G5-1)*$I$3 -> 0 | H7: =H6*(1+$O$7)^($D$5-H5-1)*$I$3 -> 0 | I7: =I6*(1+$O$7)^($D$5-I5-1)*$I$3 -> 0 | J7: =J6*(1+$O$7)^($D$5-J5-1)*$I$3 -> 0 | K7: =K6*(1+$O$7)^($D$5-K5-1)*$I$3 -> 0 | ... M7: =M6*(1+$O$7)^($D$5-M5-1)*$I$3 -> 0 | N7: =N6*(1+$O$7)^($D$5-N5-1) -> 57.831493 | O7: 0.1 | P7: Discount rate
C8: INTRINSIC VALUE | D8: =SUM(D7:N7) -> 57.831493 | O8: 15 | P8: Terminal multiple | R8: PV( | S8: %)
N10: Terminal Value | O10: Growth rate
B11: Scenario 2 | C11: =C5 -> Earnings per share | D11: =D5 -> 2025 | E11: =D11+1 -> 2026 | F11: =E11+1 -> 2027 | G11: =F11+1 -> 2028 | H11: =G11+1 -> 2029 | I11: =H11+1 -> 2030 | J11: =I11+1 -> 2031 | K11: =J11+1 -> 2032 | L11: =K11+1 -> 2033 | M11: =L11+1 -> 2034 | N11: =N5 -> 2034 | O11: 0 | P11: next 5 years
B12: best case | C12: =C6 -> 0 | D12: =C12*(1+$O$11) -> 0 | E12: =D12*(1+$O$11) -> 0 | F12: =E12*(1+$O$11) -> 0 | G12: =F12*(1+$O$11) -> 0 | H12: =G12*(1+$O$11) -> 0 | I12: =H12*(1+$O$12) -> 0 | J12: =I12*(1+$O$12) -> 0 | K12: =J12*(1+$O$12) -> 0 | L12: =K12*(1+$O$12) -> 0 | M12: =L12*(1+$O$12) -> 0 | N12: =L12*O14 -> 0 | O12: 0 | P12: 5 to 10 years
B13: =B7 -> 0 | C13: =C7 -> PV(10%) | D13: =D12*(1+$O$13)^($D$11-D11-1)*$I$3 -> 0 | E13: =E12*(1+$O$13)^($D$11-E11-1)*$I$3 -> 0 | F13: =F12*(1+$O$13)^($D$11-F11-1)*$I$3 -> 0 | G13: =G12*(1+$O$13)^($D$11-G11-1)*$I$3 -> 0 | H13: =H12*(1+$O$13)^($D$11-H11-1)*$I$3 -> 0 | I13: =I12*(1+$O$13)^($D$11-I11-1)*$I$3 -> 0 | J13: =J12*(1+$O$13)^($D$11-J11-1)*$I$3 -> 0 | K13: =K12*(1+$O$13)^($D$11-K11-1)*$I$3 -> 0 | ... M13: =M12*(1+$O$13)^($D$11-M11-1)*$I$3 -> 0 | N13: =N12*(1+$O$7)^($D$5-N11-1) -> 0 | O13: =O7 -> 0.1 | P13: Discount rate
C14: Present value sum | D14: =SUM(D13:N13) -> 0 | O14: 20 | P14: Terminal multiple
N16: Terminal Value | O16: Growth rate
B17: Scenario 3 | C17: =C11 -> Earnings per share | D17: =D11 -> 2025 | E17: =D17+1 -> 2026 | F17: =E17+1 -> 2027 | G17: =F17+1 -> 2028 | H17: =G17+1 -> 2029 | I17: =H17+1 -> 2030 | J17: =I17+1 -> 2031 | K17: =J17+1 -> 2032 | L17: =K17+1 -> 2033 | M17: =L17+1 -> 2034 | N17: =N11 -> 2034 | O17: 0 | P17: next 5 years
B18: worst case | C18: =C12 -> 0 | D18: =C18*(1+$O$17) -> 0 | E18: =D18*(1+$O$17) -> 0 | F18: =E18*(1+$O$17) -> 0 | G18: =F18*(1+$O$17) -> 0 | H18: =G18*(1+$O$17) -> 0 | I18: =H18*(1+$O$18) -> 0 | J18: =I18*(1+$O$18) -> 0 | K18: =J18*(1+$O$18) -> 0 | L18: =K18*(1+$O$18) -> 0 | M18: =L18*(1+$O$18) -> 0 | N18: =L18*O20 -> 0 | O18: 0 | P18: 5 to 10 years
B19: MARGIN OF | C19: =C13 -> PV(10%) | D19: =D18*(1+$O$19)^($D$17-D17-1)*$I$3 -> 0 | E19: =E18*(1+$O$19)^($D$17-E17-1)*$I$3 -> 0 | F19: =F18*(1+$O$19)^($D$17-F17-1)*$I$3 -> 0 | G19: =G18*(1+$O$19)^($D$17-G17-1)*$I$3 -> 0 | H19: =H18*(1+$O$19)^($D$17-H17-1)*$I$3 -> 0 | I19: =I18*(1+$O$19)^($D$17-I17-1)*$I$3 -> 0 | J19: =J18*(1+$O$19)^($D$17-J17-1)*$I$3 -> 0 | K19: =K18*(1+$O$19)^($D$17-K17-1)*$I$3 -> 0 | ... M19: =M18*(1+$O$19)^($D$17-M17-1)*$I$3 -> 0 | N19: =N18*(1+$O$19)^($D$17-N17-1) -> 0 | O19: =O13 -> 0.1 | P19: Discount rate
B20: SAFETY | C20: Present value sum | D20: =SUM(D19:N19) -> 0 | O20: 10 | P20: Terminal multiple
C22: Scenario | D22: Probability | E22: PV | F22: Part
C23: Scenario 1 (normal case) | D23: 1 | E23: =D8 -> 57.831493 | F23: =E23*D23 -> 57.831493
C24: Scenario 2 (best case) | D24: 0 | E24: =D14 -> 0 | F24: =E24*D24 -> 0
C25: Scenario 3 (worst case) | D25: 0 | E25: =D20 -> 0 | F25: =E25*D25 -> 0
C26: STOCK PRICE NOW | D26: =C3 -> 43.1 | E26: Sum | F26: =SUM(F23:F25) -> 57.831493
B28: Disclaimer: This is just for educational purposes and not for investing advice!
B30: MADE BY | C30: STOCK MARKET RESEARCH PLATFORM

Sheet Wilmar
S1: input cells
B2: Wilmar | C2: LINK TO RESEARCH | S2: result cells
B3: STOCK PRICE | C3: ='COMPARATIVE TABLE'!C32 -> 2.95 | F3: DIVIDEND PAYOUT RATIO | I3: 1
B4: COMPARATIVE TABLE'!A1 | N4: Terminal Value | O4: Growth rate
B5: Scenario 1 | C5: Dividend | D5: 2025 | E5: =D5+1 -> 2026 | F5: =E5+1 -> 2027 | G5: =F5+1 -> 2028 | H5: =G5+1 -> 2029 | I5: =H5+1 -> 2030 | J5: =I5+1 -> 2031 | K5: =J5+1 -> 2032 | L5: =K5+1 -> 2033 | M5: =L5+1 -> 2034 | N5: 2034 | O5: 0.05 | P5: next 5 years
B6: normal case | C6: 0.17 | D6: =C6*(1+$O$5) -> 0.1785 | E6: =D6*(1+$O$5) -> 0.187425 | F6: =E6*(1+$O$5) -> 0.19679625 | G6: =F6*(1+$O$5) -> 0.20663606 | H6: =G6*(1+$O$5) -> 0.21696787 | I6: =H6*(1+$O$6) -> 0.22781626 | J6: =I6*(1+$O$6) -> 0.23920707 | K6: =J6*(1+$O$6) -> 0.25116743 | L6: =K6*(1+$O$6) -> 0.2637258 | M6: =L6*(1+$O$6) -> 0.27691209 | N6: =L6*O8 -> 3.955887 | O6: 0.05 | P6: 5 to 10 years
C7: =CONCATENATE(R8,O7*100,S8) -> PV(10%) | D7: =D6*(1+$O$7)^($D$5-D5-1)*$I$3 -> 0.16227273 | E7: =E6*(1+$O$7)^($D$5-E5-1)*$I$3 -> 0.15489669 | F7: =F6*(1+$O$7)^($D$5-F5-1)*$I$3 -> 0.14785594 | G7: =G6*(1+$O$7)^($D$5-G5-1)*$I$3 -> 0.14113521 | H7: =H6*(1+$O$7)^($D$5-H5-1)*$I$3 -> 0.13471997 | I7: =I6*(1+$O$7)^($D$5-I5-1)*$I$3 -> 0.12859634 | J7: =J6*(1+$O$7)^($D$5-J5-1)*$I$3 -> 0.12275105 | K7: =K6*(1+$O$7)^($D$5-K5-1)*$I$3 -> 0.11717146 | ... M7: =M6*(1+$O$7)^($D$5-M5-1)*$I$3 -> 0.1067616 | N7: =N6*(1+$O$7)^($D$5-N5-1) -> 1.5251657 | O7: 0.1 | P7: Discount rate
C8: INTRINSIC VALUE | D8: =SUM(D7:N7) -> 2.8531721 | O8: 15 | P8: Terminal multiple | R8: PV( | S8: %)
N10: Terminal Value | O10: Growth rate
B11: Scenario 2 | C11: =C5 -> Dividend | D11: =D5 -> 2025 | E11: =D11+1 -> 2026 | F11: =E11+1 -> 2027 | G11: =F11+1 -> 2028 | H11: =G11+1 -> 2029 | I11: =H11+1 -> 2030 | J11: =I11+1 -> 2031 | K11: =J11+1 -> 2032 | L11: =K11+1 -> 2033 | M11: =L11+1 -> 2034 | N11: =N5 -> 2034 | O11: 0.06 | P11: next 5 years
B12: best case | C12: =C6 -> 0.17 | D12: =C12*(1+$O$11) -> 0.1802 | E12: =D12*(1+$O$11) -> 0.191012 | F12: =E12*(1+$O$11) -> 0.20247272 | G12: =F12*(1+$O$11) -> 0.21462108 | H12: =G12*(1+$O$11) -> 0.22749835 | I12: =H12*(1+$O$12) -> 0.24114825 | J12: =I12*(1+$O$12) -> 0.25561714 | K12: =J12*(1+$O$12) -> 0.27095417 | L12: =K12*(1+$O$12) -> 0.28721142 | M12: =L12*(1+$O$12) -> 0.30444411 | N12: =L12*O14 -> 5.7442285 | O12: 0.06 | P12: 5 to 10 years
B13: =B7 -> 0 | C13: =C7 -> PV(10%) | D13: =D12*(1+$O$13)^($D$11-D11-1)*$I$3 -> 0.16381818 | E13: =E12*(1+$O$13)^($D$11-E11-1)*$I$3 -> 0.15786116 | F13: =F12*(1+$O$13)^($D$11-F11-1)*$I$3 -> 0.15212075 | G13: =G12*(1+$O$13)^($D$11-G11-1)*$I$3 -> 0.14658909 | H13: =H12*(1+$O$13)^($D$11-H11-1)*$I$3 -> 0.14125858 | I13: =I12*(1+$O$13)^($D$11-I11-1)*$I$3 -> 0.1361219 | J13: =J12*(1+$O$13)^($D$11-J11-1)*$I$3 -> 0.13117201 | K13: =K12*(1+$O$13)^($D$11-K11-1)*$I$3 -> 0.12640212 | ... M13: =M12*(1+$O$13)^($D$11-M11-1)*$I$3 -> 0.11737638 | N13: =N12*(1+$O$7)^($D$5-N11-1) -> 2.2146487 | O13: =O7 -> 0.1 | P13: Discount rate
C14: Present value sum | D14: =SUM(D13:N13) -> 3.6091746 | O14: 20 | P14: Terminal multiple
N16: Terminal Value | O16: Growth rate
B17: Scenario 3 | C17: =C11 -> Dividend | D17: =D11 -> 2025 | E17: =D17+1 -> 2026 | F17: =E17+1 -> 2027 | G17: =F17+1 -> 2028 | H17: =G17+1 -> 2029 | I17: =H17+1 -> 2030 | J17: =I17+1 -> 2031 | K17: =J17+1 -> 2032 | L17: =K17+1 -> 2033 | M17: =L17+1 -> 2034 | N17: =N11 -> 2034 | O17: 0.02 | P17: next 5 years
B18: worst case | C18: =C12 -> 0.17 | D18: =C18*(1+$O$17) -> 0.1734 | E18: =D18*(1+$O$17) -> 0.176868 | F18: =E18*(1+$O$17) -> 0.18040536 | G18: =F18*(1+$O$17) -> 0.18401347 | H18: =G18*(1+$O$17) -> 0.18769374 | I18: =H18*(1+$O$18) -> 0.19144761 | J18: =I18*(1+$O$18) -> 0.19527656 | K18: =J18*(1+$O$18) -> 0.19918209 | L18: =K18*(1+$O$18) -> 0.20316574 | M18: =L18*(1+$O$18) -> 0.20722905 | N18: =L18*O20 -> 2.4379888 | O18: 0.02 | P18: 5 to 10 years
B19: MARGIN OF | C19: =C13 -> PV(10%) | D19: =D18*(1+$O$19)^($D$17-D17-1)*$I$3 -> 0.15763636 | E19: =E18*(1+$O$19)^($D$17-E17-1)*$I$3 -> 0.1461719 | F19: =F18*(1+$O$19)^($D$17-F17-1)*$I$3 -> 0.13554122 | G19: =G18*(1+$O$19)^($D$17-G17-1)*$I$3 -> 0.12568367 | H19: =H18*(1+$O$19)^($D$17-H17-1)*$I$3 -> 0.11654304 | I19: =I18*(1+$O$19)^($D$17-I17-1)*$I$3 -> 0.10806719 | J19: =J18*(1+$O$19)^($D$17-J17-1)*$I$3 -> 0.10020775 | K19: =K18*(1+$O$19)^($D$17-K17-1)*$I$3 -> 0.092919917 | ... M19: =M18*(1+$O$19)^($D$17-M17-1)*$I$3 -> 0.07989577 | N19: =N18*(1+$O$19)^($D$17-N17-1) -> 0.93995024 | O19: =O13 -> 0.1 | P19: Discount rate
B20: SAFETY | C20: Present value sum | D20: =SUM(D19:N19) -> 2.0887792 | O20: 12 | P20: Terminal multiple
C22: Scenario | D22: Probability | E22: PV | F22: Part
C23: Scenario 1 (normal case) | D23: 0.34 | E23: =D8 -> 2.8531721 | F23: =E23*D23 -> 0.97007853
C24: Scenario 2 (best case) | D24: 0.33 | E24: =D14 -> 3.6091746 | F24: =E24*D24 -> 1.1910276
C25: Scenario 3 (worst case) | D25: 0.33 | E25: =D20 -> 2.0887792 | F25: =E25*D25 -> 0.68929713
C26: STOCK PRICE NOW | D26: =C3 -> 2.95 | E26: Sum | F26: =SUM(F23:F25) -> 2.8504033
B28: Disclaimer: This is just for educational purposes and not for investing advice!
B30: MADE BY | C30: STOCK MARKET RESEARCH PLATFORM

Sheet GLEN
S1: input cells
B2: Glencore | C2: LINK TO RESEARCH | S2: result cells
B3: STOCK PRICE | C3: ='COMPARATIVE TABLE'!C17 -> 35.194536 | F3: DIVIDEND PAYOUT RATIO | I3: 0.33
B4: COMPARATIVE TABLE'!A1 | N4: Terminal Value | O4: Growth rate
B5: Scenario 1 | C5: FCF GBP in billions | D5: 2025 | E5: =D5+1 -> 2026 | F5: =E5+1 -> 2027 | G5: =F5+1 -> 2028 | H5: =G5+1 -> 2029 | I5: =H5+1 -> 2030 | J5: =I5+1 -> 2031 | K5: =J5+1 -> 2032 | L5: =K5+1 -> 2033 | M5: =L5+1 -> 2034 | N5: 2034 | O5: 0.06 | P5: next 5 years
B6: normal case | C6: 3.75 | D6: =C6*(1+$O$5) -> 3.975 | E6: =D6*(1+$O$5) -> 4.2135 | F6: =E6*(1+$O$5) -> 4.46631 | G6: =F6*(1+$O$5) -> 4.7342886 | H6: =G6*(1+$O$5) -> 5.0183459 | I6: =H6*(1+$O$6) -> 5.3194467 | J6: =I6*(1+$O$6) -> 5.6386135 | K6: =J6*(1+$O$6) -> 5.9769303 | L6: =K6*(1+$O$6) -> 6.3355461 | M6: =L6*(1+$O$6) -> 6.7156789 | N6: =L6*O8 -> 76.026553 | O6: 0.06 | P6: 5 to 10 years
C7: =CONCATENATE(R8,O7*100,S8) -> PV(10%) | D7: =D6*(1+$O$7)^($D$5-D5-1)*$I$3 -> 1.1925 | E7: =E6*(1+$O$7)^($D$5-E5-1)*$I$3 -> 1.1491364 | F7: =F6*(1+$O$7)^($D$5-F5-1)*$I$3 -> 1.1073496 | G7: =G6*(1+$O$7)^($D$5-G5-1)*$I$3 -> 1.0670823 | H7: =H6*(1+$O$7)^($D$5-H5-1)*$I$3 -> 1.0282793 | I7: =I6*(1+$O$7)^($D$5-I5-1)*$I$3 -> 0.99088736 | J7: =J6*(1+$O$7)^($D$5-J5-1)*$I$3 -> 0.95485509 | K7: =K6*(1+$O$7)^($D$5-K5-1)*$I$3 -> 0.92013309 | ... M7: =M6*(1+$O$7)^($D$5-M5-1)*$I$3 -> 0.85443102 | N7: =N6*(1+$O$7)^($D$5-N5-1) -> 29.311527 | O7: 0.1 | P7: Discount rate
C8: INTRINSIC VALUE | D8: =SUM(D7:N7) -> 39.462855 | O8: 12 | P8: Terminal multiple | R8: PV( | S8: %)
N10: Terminal Value | O10: Growth rate
B11: Scenario 2 | C11: =C5 -> FCF GBP in billions | D11: =D5 -> 2025 | E11: =D11+1 -> 2026 | F11: =E11+1 -> 2027 | G11: =F11+1 -> 2028 | H11: =G11+1 -> 2029 | I11: =H11+1 -> 2030 | J11: =I11+1 -> 2031 | K11: =J11+1 -> 2032 | L11: =K11+1 -> 2033 | M11: =L11+1 -> 2034 | N11: =N5 -> 2034 | O11: 0.08 | P11: next 5 years
B12: best case | C12: =C6 -> 3.75 | D12: =C12*(1+$O$11) -> 4.05 | E12: =D12*(1+$O$11) -> 4.374 | F12: =E12*(1+$O$11) -> 4.72392 | G12: =F12*(1+$O$11) -> 5.1018336 | H12: =G12*(1+$O$11) -> 5.5099803 | I12: =H12*(1+$O$12) -> 5.9507787 | J12: =I12*(1+$O$12) -> 6.426841 | K12: =J12*(1+$O$12) -> 6.9409883 | L12: =K12*(1+$O$12) -> 7.4962674 | M12: =L12*(1+$O$12) -> 8.0959687 | N12: =L12*O14 -> 112.44401 | O12: 0.08 | P12: 5 to 10 years
B13: =B7 -> 0 | C13: =C7 -> PV(10%) | D13: =D12*(1+$O$13)^($D$11-D11-1)*$I$3 -> 1.215 | E13: =E12*(1+$O$13)^($D$11-E11-1)*$I$3 -> 1.1929091 | F13: =F12*(1+$O$13)^($D$11-F11-1)*$I$3 -> 1.1712198 | G13: =G12*(1+$O$13)^($D$11-G11-1)*$I$3 -> 1.1499249 | H13: =H12*(1+$O$13)^($D$11-H11-1)*$I$3 -> 1.1290172 | I13: =I12*(1+$O$13)^($D$11-I11-1)*$I$3 -> 1.1084896 | J13: =J12*(1+$O$13)^($D$11-J11-1)*$I$3 -> 1.0883353 | K13: =K12*(1+$O$13)^($D$11-K11-1)*$I$3 -> 1.0685473 | ... M13: =M12*(1+$O$13)^($D$11-M11-1)*$I$3 -> 1.0300443 | N13: =N12*(1+$O$7)^($D$5-N11-1) -> 43.352034 | O13: =O7 -> 0.1 | P13: Discount rate
C14: Present value sum | D14: =SUM(D13:N13) -> 54.55464 | O14: 15 | P14: Terminal multiple
N16: Terminal Value | O16: Growth rate
B17: Scenario 3 | C17: =C11 -> FCF GBP in billions | D17: =D11 -> 2025 | E17: =D17+1 -> 2026 | F17: =E17+1 -> 2027 | G17: =F17+1 -> 2028 | H17: =G17+1 -> 2029 | I17: =H17+1 -> 2030 | J17: =I17+1 -> 2031 | K17: =J17+1 -> 2032 | L17: =K17+1 -> 2033 | M17: =L17+1 -> 2034 | N17: =N11 -> 2034 | O17: 0.02 | P17: next 5 years
B18: worst case | C18: =C12 -> 3.75 | D18: =C18*(1+$O$17) -> 3.825 | E18: =D18*(1+$O$17) -> 3.9015 | F18: =E18*(1+$O$17) -> 3.97953 | G18: =F18*(1+$O$17) -> 4.0591206 | H18: =G18*(1+$O$17) -> 4.140303 | I18: =H18*(1+$O$18) -> 4.2231091 | J18: =I18*(1+$O$18) -> 4.3075713 | K18: =J18*(1+$O$18) -> 4.3937227 | L18: =K18*(1+$O$18) -> 4.4815971 | M18: =L18*(1+$O$18) -> 4.5712291 | N18: =L18*O20 -> 44.815971 | O18: 0.02 | P18: 5 to 10 years
B19: MARGIN OF | C19: =C13 -> PV(10%) | D19: =D18*(1+$O$19)^($D$17-D17-1)*$I$3 -> 1.1475 | E19: =E18*(1+$O$19)^($D$17-E17-1)*$I$3 -> 1.0640455 | F19: =F18*(1+$O$19)^($D$17-F17-1)*$I$3 -> 0.98666033 | G19: =G18*(1+$O$19)^($D$17-G17-1)*$I$3 -> 0.91490322 | H19: =H18*(1+$O$19)^($D$17-H17-1)*$I$3 -> 0.8483648 | I19: =I18*(1+$O$19)^($D$17-I17-1)*$I$3 -> 0.78666554 | J19: =J18*(1+$O$19)^($D$17-J17-1)*$I$3 -> 0.7294535 | K19: =K18*(1+$O$19)^($D$17-K17-1)*$I$3 -> 0.67640234 | ... M19: =M18*(1+$O$19)^($D$17-M17-1)*$I$3 -> 0.58159421 | N19: =N18*(1+$O$19)^($D$17-N17-1) -> 17.278497 | O19: =O13 -> 0.1 | P19: Discount rate
B20: SAFETY | C20: Present value sum | D20: =SUM(D19:N19) -> 25.641296 | O20: 10 | P20: Terminal multiple
C22: Scenario | D22: Probability | E22: PV | F22: Part
C23: Scenario 1 (normal case) | D23: 0.34 | E23: =D8 -> 39.462855 | F23: =E23*D23 -> 13.417371
C24: Scenario 2 (best case) | D24: 0.33 | E24: =D14 -> 54.55464 | F24: =E24*D24 -> 18.003031
C25: Scenario 3 (worst case) | D25: 0.33 | E25: =D20 -> 25.641296 | F25: =E25*D25 -> 8.4616276
C26: STOCK PRICE NOW | D26: =C3 -> 35.194536 | E26: Sum | F26: =SUM(F23:F25) -> 39.88203
B28: Disclaimer: This is just for educational purposes and not for investing advice!
B30: MADE BY | C30: STOCK MARKET RESEARCH PLATFORM

Sheet VZ
S1: input cells
B2: Verizon | C2: LINK TO RESEARCH | S2: result cells
B3: STOCK PRICE | C3: ='COMPARATIVE TABLE'!C53 -> 43.49 | F3: DIVIDEND PAYOUT RATIO | I3: 1
B4: COMPARATIVE TABLE'!A1 | N4: Terminal Value | O4: Growth rate
B5: Scenario 1 | C5: DIVIDEND | D5: 2025 | E5: =D5+1 -> 2026 | F5: =E5+1 -> 2027 | G5: =F5+1 -> 2028 | H5: =G5+1 -> 2029 | I5: =H5+1 -> 2030 | J5: =I5+1 -> 2031 | K5: =J5+1 -> 2032 | L5: =K5+1 -> 2033 | M5: =L5+1 -> 2034 | N5: 2034 | O5: 0.03 | P5: next 5 years
B6: normal case | C6: 2.62 | D6: =C6*(1+$O$5) -> 2.6986 | E6: =D6*(1+$O$5) -> 2.779558 | F6: =E6*(1+$O$5) -> 2.8629447 | G6: =F6*(1+$O$5) -> 2.9488331 | H6: =G6*(1+$O$5) -> 3.0372981 | I6: =H6*(1+$O$6) -> 3.128417 | J6: =I6*(1+$O$6) -> 3.2222695 | K6: =J6*(1+$O$6) -> 3.3189376 | L6: =K6*(1+$O$6) -> 3.4185057 | M6: =L6*(1+$O$6) -> 3.5210609 | N6: =L6*O8 -> 51.277586 | O6: 0.03 | P6: 5 to 10 years
C7: =CONCATENATE(R8,O7*100,S8) -> PV(10%) | D7: =D6*(1+$O$7)^($D$5-D5-1)*$I$3 -> 2.4532727 | E7: =E6*(1+$O$7)^($D$5-E5-1)*$I$3 -> 2.2971554 | F7: =F6*(1+$O$7)^($D$5-F5-1)*$I$3 -> 2.1509728 | G7: =G6*(1+$O$7)^($D$5-G5-1)*$I$3 -> 2.0140927 | H7: =H6*(1+$O$7)^($D$5-H5-1)*$I$3 -> 1.8859231 | I7: =I6*(1+$O$7)^($D$5-I5-1)*$I$3 -> 1.7659098 | J7: =J6*(1+$O$7)^($D$5-J5-1)*$I$3 -> 1.6535338 | K7: =K6*(1+$O$7)^($D$5-K5-1)*$I$3 -> 1.5483089 | ... M7: =M6*(1+$O$7)^($D$5-M5-1)*$I$3 -> 1.3575214 | N7: =N6*(1+$O$7)^($D$5-N5-1) -> 19.769729 | O7: 0.1 | P7: Discount rate
C8: INTRINSIC VALUE | D8: =SUM(D7:N7) -> 38.3462 | O8: 15 | P8: Terminal multiple | R8: PV( | S8: %)
N10: Terminal Value | O10: Growth rate
B11: Scenario 2 | C11: =C5 -> DIVIDEND | D11: =D5 -> 2025 | E11: =D11+1 -> 2026 | F11: =E11+1 -> 2027 | G11: =F11+1 -> 2028 | H11: =G11+1 -> 2029 | I11: =H11+1 -> 2030 | J11: =I11+1 -> 2031 | K11: =J11+1 -> 2032 | L11: =K11+1 -> 2033 | M11: =L11+1 -> 2034 | N11: =N5 -> 2034 | O11: 0.05 | P11: next 5 years
B12: best case | C12: =C6 -> 2.62 | D12: =C12*(1+$O$11) -> 2.751 | E12: =D12*(1+$O$11) -> 2.88855 | F12: =E12*(1+$O$11) -> 3.0329775 | G12: =F12*(1+$O$11) -> 3.1846264 | H12: =G12*(1+$O$11) -> 3.3438577 | I12: =H12*(1+$O$12) -> 3.5110506 | J12: =I12*(1+$O$12) -> 3.6866031 | K12: =J12*(1+$O$12) -> 3.8709333 | L12: =K12*(1+$O$12) -> 4.0644799 | M12: =L12*(1+$O$12) -> 4.2677039 | N12: =L12*O14 -> 81.289599 | O12: 0.05 | P12: 5 to 10 years
B13: =B7 -> 0 | C13: =C7 -> PV(10%) | D13: =D12*(1+$O$13)^($D$11-D11-1)*$I$3 -> 2.5009091 | E13: =E12*(1+$O$13)^($D$11-E11-1)*$I$3 -> 2.3872314 | F13: =F12*(1+$O$13)^($D$11-F11-1)*$I$3 -> 2.2787209 | G13: =G12*(1+$O$13)^($D$11-G11-1)*$I$3 -> 2.1751427 | H13: =H12*(1+$O$13)^($D$11-H11-1)*$I$3 -> 2.0762725 | I13: =I12*(1+$O$13)^($D$11-I11-1)*$I$3 -> 1.9818965 | J13: =J12*(1+$O$13)^($D$11-J11-1)*$I$3 -> 1.8918103 | K13: =K12*(1+$O$13)^($D$11-K11-1)*$I$3 -> 1.8058189 | ... M13: =M12*(1+$O$13)^($D$11-M11-1)*$I$3 -> 1.6453846 | N13: =N12*(1+$O$7)^($D$5-N11-1) -> 31.340659 | O13: =O7 -> 0.1 | P13: Discount rate
C14: Present value sum | D14: =SUM(D13:N13) -> 51.807582 | O14: 20 | P14: Terminal multiple
N16: Terminal Value | O16: Growth rate
B17: Scenario 3 | C17: =C11 -> DIVIDEND | D17: =D11 -> 2025 | E17: =D17+1 -> 2026 | F17: =E17+1 -> 2027 | G17: =F17+1 -> 2028 | H17: =G17+1 -> 2029 | I17: =H17+1 -> 2030 | J17: =I17+1 -> 2031 | K17: =J17+1 -> 2032 | L17: =K17+1 -> 2033 | M17: =L17+1 -> 2034 | N17: =N11 -> 2034 | O17: 0 | P17: next 5 years
B18: worst case | C18: =C12 -> 2.62 | D18: =C18*(1+$O$17) -> 2.62 | E18: =D18*(1+$O$17) -> 2.62 | F18: =E18*(1+$O$17) -> 2.62 | G18: =F18*(1+$O$17) -> 2.62 | H18: =G18*(1+$O$17) -> 2.62 | I18: =H18*(1+$O$18) -> 2.62 | J18: =I18*(1+$O$18) -> 2.62 | K18: =J18*(1+$O$18) -> 2.62 | L18: =K18*(1+$O$18) -> 2.62 | M18: =L18*(1+$O$18) -> 2.62 | N18: =L18*O20 -> 26.2 | O18: 0 | P18: 5 to 10 years
B19: MARGIN OF | C19: =C13 -> PV(10%) | D19: =D18*(1+$O$19)^($D$17-D17-1)*$I$3 -> 2.3818182 | E19: =E18*(1+$O$19)^($D$17-E17-1)*$I$3 -> 2.1652893 | F19: =F18*(1+$O$19)^($D$17-F17-1)*$I$3 -> 1.9684448 | G19: =G18*(1+$O$19)^($D$17-G17-1)*$I$3 -> 1.7894953 | H19: =H18*(1+$O$19)^($D$17-H17-1)*$I$3 -> 1.6268139 | I19: =I18*(1+$O$19)^($D$17-I17-1)*$I$3 -> 1.4789217 | J19: =J18*(1+$O$19)^($D$17-J17-1)*$I$3 -> 1.3444743 | K19: =K18*(1+$O$19)^($D$17-K17-1)*$I$3 -> 1.2222493 | ... M19: =M18*(1+$O$19)^($D$17-M17-1)*$I$3 -> 1.0101234 | N19: =N18*(1+$O$19)^($D$17-N17-1) -> 10.101234 | O19: =O13 -> 0.1 | P19: Discount rate
B20: SAFETY | C20: Present value sum | D20: =SUM(D19:N19) -> 26.2 | O20: 10 | P20: Terminal multiple
C22: Scenario | D22: Probability | E22: PV | F22: Part
C23: Scenario 1 (normal case) | D23: 0.6 | E23: =D8 -> 38.3462 | F23: =E23*D23 -> 23.00772
C24: Scenario 2 (best case) | D24: 0.2 | E24: =D14 -> 51.807582 | F24: =E24*D24 -> 10.361516
C25: Scenario 3 (worst case) | D25: 0.2 | E25: =D20 -> 26.2 | F25: =E25*D25 -> 5.24
C26: STOCK PRICE NOW | D26: =C3 -> 43.49 | E26: Sum | F26: =SUM(F23:F25) -> 38.609236
B28: Disclaimer: This is just for educational purposes and not for investing advice!
B30: MADE BY | C30: STOCK MARKET RESEARCH PLATFORM

Sheet MDLZ
S1: input cells
B2: MDLZ | C2: LINK TO RESEARCH | S2: result cells
B3: STOCK PRICE | C3: ='COMPARATIVE TABLE'!C52 -> 62.27 | F3: DIVIDEND PAYOUT RATIO | I3: 0.6
B4: COMPARATIVE TABLE'!A1 | N4: Terminal Value | O4: Growth rate
B5: Scenario 1 | C5: FCF PER SHARE | D5: 2025 | E5: =D5+1 -> 2026 | F5: =E5+1 -> 2027 | G5: =F5+1 -> 2028 | H5: =G5+1 -> 2029 | I5: =H5+1 -> 2030 | J5: =I5+1 -> 2031 | K5: =J5+1 -> 2032 | L5: =K5+1 -> 2033 | M5: =L5+1 -> 2034 | N5: 2034 | O5: 0.05 | P5: next 5 years
B6: normal case | C6: 2.75 | D6: =C6*(1+$O$5) -> 2.8875 | E6: =D6*(1+$O$5) -> 3.031875 | F6: =E6*(1+$O$5) -> 3.1834688 | G6: =F6*(1+$O$5) -> 3.3426422 | H6: =G6*(1+$O$5) -> 3.5097743 | I6: =H6*(1+$O$6) -> 3.685263 | J6: =I6*(1+$O$6) -> 3.8695262 | K6: =J6*(1+$O$6) -> 4.0630025 | L6: =K6*(1+$O$6) -> 4.2661526 | M6: =L6*(1+$O$6) -> 4.4794602 | N6: =L6*O8 -> 63.992289 | O6: 0.05 | P6: 5 to 10 years
C7: =CONCATENATE(R8,O7*100,S8) -> PV(10%) | D7: =D6*(1+$O$7)^($D$5-D5-1)*$I$3 -> 1.575 | E7: =E6*(1+$O$7)^($D$5-E5-1)*$I$3 -> 1.5034091 | F7: =F6*(1+$O$7)^($D$5-F5-1)*$I$3 -> 1.4350723 | G7: =G6*(1+$O$7)^($D$5-G5-1)*$I$3 -> 1.3698418 | H7: =H6*(1+$O$7)^($D$5-H5-1)*$I$3 -> 1.3075762 | I7: =I6*(1+$O$7)^($D$5-I5-1)*$I$3 -> 1.2481409 | J7: =J6*(1+$O$7)^($D$5-J5-1)*$I$3 -> 1.1914073 | K7: =K6*(1+$O$7)^($D$5-K5-1)*$I$3 -> 1.1372524 | ... M7: =M6*(1+$O$7)^($D$5-M5-1)*$I$3 -> 1.0362155 | N7: =N6*(1+$O$7)^($D$5-N5-1) -> 24.671798 | O7: 0.1 | P7: Discount rate
C8: INTRINSIC VALUE | D8: =SUM(D7:N7) -> 37.561272 | O8: 15 | P8: Terminal multiple | R8: PV( | S8: %)
N10: Terminal Value | O10: Growth rate
B11: Scenario 2 | C11: =C5 -> FCF PER SHARE | D11: =D5 -> 2025 | E11: =D11+1 -> 2026 | F11: =E11+1 -> 2027 | G11: =F11+1 -> 2028 | H11: =G11+1 -> 2029 | I11: =H11+1 -> 2030 | J11: =I11+1 -> 2031 | K11: =J11+1 -> 2032 | L11: =K11+1 -> 2033 | M11: =L11+1 -> 2034 | N11: =N5 -> 2034 | O11: 0.07 | P11: next 5 years
B12: best case | C12: =C6 -> 2.75 | D12: =C12*(1+$O$11) -> 2.9425 | E12: =D12*(1+$O$11) -> 3.148475 | F12: =E12*(1+$O$11) -> 3.3688683 | G12: =F12*(1+$O$11) -> 3.604689 | H12: =G12*(1+$O$11) -> 3.8570173 | I12: =H12*(1+$O$12) -> 4.1270085 | J12: =I12*(1+$O$12) -> 4.4158991 | K12: =J12*(1+$O$12) -> 4.725012 | L12: =K12*(1+$O$12) -> 5.0557628 | M12: =L12*(1+$O$12) -> 5.4096662 | N12: =L12*O14 -> 101.11526 | O12: 0.07 | P12: 5 to 10 years
B13: =B7 -> 0 | C13: =C7 -> PV(10%) | D13: =D12*(1+$O$13)^($D$11-D11-1)*$I$3 -> 1.605 | E13: =E12*(1+$O$13)^($D$11-E11-1)*$I$3 -> 1.5612273 | F13: =F12*(1+$O$13)^($D$11-F11-1)*$I$3 -> 1.5186483 | G13: =G12*(1+$O$13)^($D$11-G11-1)*$I$3 -> 1.4772307 | H13: =H12*(1+$O$13)^($D$11-H11-1)*$I$3 -> 1.4369426 | I13: =I12*(1+$O$13)^($D$11-I11-1)*$I$3 -> 1.3977532 | J13: =J12*(1+$O$13)^($D$11-J11-1)*$I$3 -> 1.3596327 | K13: =K12*(1+$O$13)^($D$11-K11-1)*$I$3 -> 1.3225518 | ... M13: =M12*(1+$O$13)^($D$11-M11-1)*$I$3 -> 1.2513963 | N13: =N12*(1+$O$7)^($D$5-N11-1) -> 38.984309 | O13: =O7 -> 0.1 | P13: Discount rate
C14: Present value sum | D14: =SUM(D13:N13) -> 53.201174 | O14: 20 | P14: Terminal multiple
N16: Terminal Value | O16: Growth rate
B17: Scenario 3 | C17: =C11 -> FCF PER SHARE | D17: =D11 -> 2025 | E17: =D17+1 -> 2026 | F17: =E17+1 -> 2027 | G17: =F17+1 -> 2028 | H17: =G17+1 -> 2029 | I17: =H17+1 -> 2030 | J17: =I17+1 -> 2031 | K17: =J17+1 -> 2032 | L17: =K17+1 -> 2033 | M17: =L17+1 -> 2034 | N17: =N11 -> 2034 | O17: 0.03 | P17: next 5 years
B18: worst case | C18: =C12 -> 2.75 | D18: =C18*(1+$O$17) -> 2.8325 | E18: =D18*(1+$O$17) -> 2.917475 | F18: =E18*(1+$O$17) -> 3.0049993 | G18: =F18*(1+$O$17) -> 3.0951492 | H18: =G18*(1+$O$17) -> 3.1880037 | I18: =H18*(1+$O$18) -> 3.2836438 | J18: =I18*(1+$O$18) -> 3.3821531 | K18: =J18*(1+$O$18) -> 3.4836177 | L18: =K18*(1+$O$18) -> 3.5881263 | M18: =L18*(1+$O$18) -> 3.69577 | N18: =L18*O20 -> 43.057515 | O18: 0.03 | P18: 5 to 10 years
B19: MARGIN OF | C19: =C13 -> PV(10%) | D19: =D18*(1+$O$19)^($D$17-D17-1)*$I$3 -> 1.545 | E19: =E18*(1+$O$19)^($D$17-E17-1)*$I$3 -> 1.4466818 | F19: =F18*(1+$O$19)^($D$17-F17-1)*$I$3 -> 1.3546202 | G19: =G18*(1+$O$19)^($D$17-G17-1)*$I$3 -> 1.2684171 | H19: =H18*(1+$O$19)^($D$17-H17-1)*$I$3 -> 1.1876997 | I19: =I18*(1+$O$19)^($D$17-I17-1)*$I$3 -> 1.1121188 | J19: =J18*(1+$O$19)^($D$17-J17-1)*$I$3 -> 1.0413476 | K19: =K18*(1+$O$19)^($D$17-K17-1)*$I$3 -> 0.97508003 | ... M19: =M18*(1+$O$19)^($D$17-M17-1)*$I$3 -> 0.8549276 | N19: =N18*(1+$O$19)^($D$17-N17-1) -> 16.600536 | O19: =O13 -> 0.1 | P19: Discount rate
B20: SAFETY | C20: Present value sum | D20: =SUM(D19:N19) -> 28.299458 | O20: 12 | P20: Terminal multiple
C22: Scenario | D22: Probability | E22: PV | F22: Part
C23: Scenario 1 (normal case) | D23: 0.6 | E23: =D8 -> 37.561272 | F23: =E23*D23 -> 22.536763
C24: Scenario 2 (best case) | D24: 0.2 | E24: =D14 -> 53.201174 | F24: =E24*D24 -> 10.640235
C25: Scenario 3 (worst case) | D25: 0.2 | E25: =D20 -> 28.299458 | F25: =E25*D25 -> 5.6598917
C26: STOCK PRICE NOW | D26: =C3 -> 62.27 | E26: Sum | F26: =SUM(F23:F25) -> 38.83689
B28: Disclaimer: This is just for educational purposes and not for investing advice!
B30: MADE BY | C30: STOCK MARKET RESEARCH PLATFORM

Sheet APPLE
S1: input cells
B2: APPLE | C2: LINK TO RESEARCH | S2: result cells
B3: STOCK PRICE | C3: ='COMPARATIVE TABLE'!C39 -> 226.79 | F3: DIVIDEND PAYOUT RATIO | I3: 0.16
B4: COMPARATIVE TABLE'!A1 | N4: Terminal Value | O4: Growth rate
B5: Scenario 1 | C5: Earnings per share | D5: 2025 | E5: =D5+1 -> 2026 | F5: =E5+1 -> 2027 | G5: =F5+1 -> 2028 | H5: =G5+1 -> 2029 | I5: =H5+1 -> 2030 | J5: =I5+1 -> 2031 | K5: =J5+1 -> 2032 | L5: =K5+1 -> 2033 | M5: =L5+1 -> 2034 | N5: 2034 | O5: 0.05 | P5: next 5 years
B6: normal case | C6: 6.08 | D6: =C6*(1+$O$5) -> 6.384 | E6: =D6*(1+$O$5) -> 6.7032 | F6: =E6*(1+$O$5) -> 7.03836 | G6: =F6*(1+$O$5) -> 7.390278 | H6: =G6*(1+$O$5) -> 7.7597919 | I6: =H6*(1+$O$6) -> 8.1477815 | J6: =I6*(1+$O$6) -> 8.5551706 | K6: =J6*(1+$O$6) -> 8.9829291 | L6: =K6*(1+$O$6) -> 9.4320756 | M6: =L6*(1+$O$6) -> 9.9036793 | N6: =L6*O8 -> 188.64151 | O6: 0.05 | P6: 5 to 10 years
C7: =CONCATENATE(R8,O7*100,S8) -> PV(10%) | D7: =D6*(1+$O$7)^($D$5-D5-1)*$I$3 -> 0.92858182 | E7: =E6*(1+$O$7)^($D$5-E5-1)*$I$3 -> 0.88637355 | F7: =F6*(1+$O$7)^($D$5-F5-1)*$I$3 -> 0.84608385 | G7: =G6*(1+$O$7)^($D$5-G5-1)*$I$3 -> 0.80762549 | H7: =H6*(1+$O$7)^($D$5-H5-1)*$I$3 -> 0.77091524 | I7: =I6*(1+$O$7)^($D$5-I5-1)*$I$3 -> 0.73587364 | J7: =J6*(1+$O$7)^($D$5-J5-1)*$I$3 -> 0.70242484 | K7: =K6*(1+$O$7)^($D$5-K5-1)*$I$3 -> 0.67049644 | ... M7: =M6*(1+$O$7)^($D$5-M5-1)*$I$3 -> 0.61092754 | N7: =N6*(1+$O$7)^($D$5-N5-1) -> 72.729469 | O7: 0.1 | P7: Discount rate
C8: INTRINSIC VALUE | D8: =SUM(D7:N7) -> 80.32879 | O8: 20 | P8: Terminal multiple | R8: PV( | S8: %)
N10: Terminal Value | O10: Growth rate
B11: Scenario 2 | C11: =C5 -> Earnings per share | D11: =D5 -> 2025 | E11: =D11+1 -> 2026 | F11: =E11+1 -> 2027 | G11: =F11+1 -> 2028 | H11: =G11+1 -> 2029 | I11: =H11+1 -> 2030 | J11: =I11+1 -> 2031 | K11: =J11+1 -> 2032 | L11: =K11+1 -> 2033 | M11: =L11+1 -> 2034 | N11: =N5 -> 2034 | O11: 0.07 | P11: next 5 years
B12: best case | C12: =C6 -> 6.08 | D12: =C12*(1+$O$11) -> 6.5056 | E12: =D12*(1+$O$11) -> 6.960992 | F12: =E12*(1+$O$11) -> 7.4482614 | G12: =F12*(1+$O$11) -> 7.9696397 | H12: =G12*(1+$O$11) -> 8.5275145 | I12: =H12*(1+$O$12) -> 9.1244405 | J12: =I12*(1+$O$12) -> 9.7631514 | K12: =J12*(1+$O$12) -> 10.446572 | L12: =K12*(1+$O$12) -> 11.177832 | M12: =L12*(1+$O$12) -> 11.96028 | N12: =L12*O14 -> 335.33496 | O12: 0.07 | P12: 5 to 10 years
B13: =B7 -> 0 | C13: =C7 -> PV(10%) | D13: =D12*(1+$O$13)^($D$11-D11-1)*$I$3 -> 0.94626909 | E13: =E12*(1+$O$13)^($D$11-E11-1)*$I$3 -> 0.92046175 | F13: =F12*(1+$O$13)^($D$11-F11-1)*$I$3 -> 0.89535825 | G13: =G12*(1+$O$13)^($D$11-G11-1)*$I$3 -> 0.87093939 | H13: =H12*(1+$O$13)^($D$11-H11-1)*$I$3 -> 0.8471865 | I13: =I12*(1+$O$13)^($D$11-I11-1)*$I$3 -> 0.82408141 | J13: =J12*(1+$O$13)^($D$11-J11-1)*$I$3 -> 0.80160646 | K13: =K12*(1+$O$13)^($D$11-K11-1)*$I$3 -> 0.77974447 | ... M13: =M12*(1+$O$13)^($D$11-M11-1)*$I$3 -> 0.73779293 | N13: =N12*(1+$O$7)^($D$5-N11-1) -> 129.28614 | O13: =O7 -> 0.1 | P13: Discount rate
C14: Present value sum | D14: =SUM(D13:N13) -> 137.66806 | O14: 30 | P14: Terminal multiple
N16: Terminal Value | O16: Growth rate
B17: Scenario 3 | C17: =C11 -> Earnings per share | D17: =D11 -> 2025 | E17: =D17+1 -> 2026 | F17: =E17+1 -> 2027 | G17: =F17+1 -> 2028 | H17: =G17+1 -> 2029 | I17: =H17+1 -> 2030 | J17: =I17+1 -> 2031 | K17: =J17+1 -> 2032 | L17: =K17+1 -> 2033 | M17: =L17+1 -> 2034 | N17: =N11 -> 2034 | O17: 0.02 | P17: next 5 years
B18: worst case | C18: =C12 -> 6.08 | D18: =C18*(1+$O$17) -> 6.2016 | E18: =D18*(1+$O$17) -> 6.325632 | F18: =E18*(1+$O$17) -> 6.4521446 | G18: =F18*(1+$O$17) -> 6.5811875 | H18: =G18*(1+$O$17) -> 6.7128113 | I18: =H18*(1+$O$18) -> 6.8470675 | J18: =I18*(1+$O$18) -> 6.9840089 | K18: =J18*(1+$O$18) -> 7.123689 | L18: =K18*(1+$O$18) -> 7.2661628 | M18: =L18*(1+$O$18) -> 7.4114861 | N18: =L18*O20 -> 87.193954 | O18: 0.02 | P18: 5 to 10 years
B19: MARGIN OF | C19: =C13 -> PV(10%) | D19: =D18*(1+$O$19)^($D$17-D17-1)*$I$3 -> 0.90205091 | E19: =E18*(1+$O$19)^($D$17-E17-1)*$I$3 -> 0.83644721 | F19: =F18*(1+$O$19)^($D$17-F17-1)*$I$3 -> 0.77561468 | G19: =G18*(1+$O$19)^($D$17-G17-1)*$I$3 -> 0.71920634 | H19: =H18*(1+$O$19)^($D$17-H17-1)*$I$3 -> 0.66690043 | I19: =I18*(1+$O$19)^($D$17-I17-1)*$I$3 -> 0.61839858 | J19: =J18*(1+$O$19)^($D$17-J17-1)*$I$3 -> 0.57342414 | K19: =K18*(1+$O$19)^($D$17-K17-1)*$I$3 -> 0.53172056 | ... M19: =M18*(1+$O$19)^($D$17-M17-1)*$I$3 -> 0.4571918 | N19: =N18*(1+$O$19)^($D$17-N17-1) -> 33.617044 | O19: =O13 -> 0.1 | P19: Discount rate
B20: SAFETY | C20: Present value sum | D20: =SUM(D19:N19) -> 40.191048 | O20: 12 | P20: Terminal multiple
C22: Scenario | D22: Probability | E22: PV | F22: Part
C23: Scenario 1 (normal case) | D23: 0.4 | E23: =D8 -> 80.32879 | F23: =E23*D23 -> 32.131516
C24: Scenario 2 (best case) | D24: 0.3 | E24: =D14 -> 137.66806 | F24: =E24*D24 -> 41.300419
C25: Scenario 3 (worst case) | D25: 0.3 | E25: =D20 -> 40.191048 | F25: =E25*D25 -> 12.057315
C26: STOCK PRICE NOW | D26: =C3 -> 226.79 | E26: Sum | F26: =SUM(F23:F25) -> 85.489249
B28: Disclaimer: This is just for educational purposes and not for investing advice!
B30: MADE BY | C30: STOCK MARKET RESEARCH PLATFORM

Sheet S&P 500
S1: input cells
B2: NAME | C2: LINK TO RESEARCH | S2: result cells
B3: STOCK PRICE | C3: ='MKT CAP - Price'!C13 -> 6522.1 | F3: DIVIDEND PAYOUT RATIO | I3: 0.4
B4: COMPARATIVE TABLE'!A1 | N4: Terminal Value | O4: Growth rate
B5: Scenario 1 | C5: Earnings per share | D5: 2025 | E5: =D5+1 -> 2026 | F5: =E5+1 -> 2027 | G5: =F5+1 -> 2028 | H5: =G5+1 -> 2029 | I5: =H5+1 -> 2030 | J5: =I5+1 -> 2031 | K5: =J5+1 -> 2032 | L5: =K5+1 -> 2033 | M5: =L5+1 -> 2034 | N5: 2034 | O5: 0.05 | P5: next 5 years
B6: normal case | C6: 200 | D6: =C6*(1+$O$5) -> 210 | E6: =D6*(1+$O$5) -> 220.5 | F6: =E6*(1+$O$5) -> 231.525 | G6: =F6*(1+$O$5) -> 243.10125 | H6: =G6*(1+$O$5) -> 255.25631 | I6: =H6*(1+$O$6) -> 268.01913 | J6: =I6*(1+$O$6) -> 281.42008 | K6: =J6*(1+$O$6) -> 295.49109 | L6: =K6*(1+$O$6) -> 310.26564 | M6: =L6*(1+$O$6) -> 325.77893 | N6: =L6*O8 -> 4653.9846 | O6: 0.05 | P6: 5 to 10 years
C7: =CONCATENATE(R8,O7*100,S8) -> PV(10%) | D7: =D6*(1+$O$7)^($D$5-D5-1)*$I$3 -> 76.363636 | E7: =E6*(1+$O$7)^($D$5-E5-1)*$I$3 -> 72.892562 | F7: =F6*(1+$O$7)^($D$5-F5-1)*$I$3 -> 69.579264 | G7: =G6*(1+$O$7)^($D$5-G5-1)*$I$3 -> 66.41657 | H7: =H6*(1+$O$7)^($D$5-H5-1)*$I$3 -> 63.397635 | I7: =I6*(1+$O$7)^($D$5-I5-1)*$I$3 -> 60.515924 | J7: =J6*(1+$O$7)^($D$5-J5-1)*$I$3 -> 57.7652 | K7: =K6*(1+$O$7)^($D$5-K5-1)*$I$3 -> 55.139509 | ... M7: =M6*(1+$O$7)^($D$5-M5-1)*$I$3 -> 50.240751 | N7: =N6*(1+$O$7)^($D$5-N5-1) -> 1794.3126 | O7: 0.1 | P7: Discount rate
C8: INTRINSIC VALUE | D8: =SUM(D7:N7) -> 2419.2568 | O8: 15 | P8: Terminal multiple | R8: PV( | S8: %)
N10: Terminal Value | O10: Growth rate
B11: Scenario 2 | C11: =C5 -> Earnings per share | D11: =D5 -> 2025 | E11: =D11+1 -> 2026 | F11: =E11+1 -> 2027 | G11: =F11+1 -> 2028 | H11: =G11+1 -> 2029 | I11: =H11+1 -> 2030 | J11: =I11+1 -> 2031 | K11: =J11+1 -> 2032 | L11: =K11+1 -> 2033 | M11: =L11+1 -> 2034 | N11: =N5 -> 2034 | O11: 0.1 | P11: next 5 years
B12: best case | C12: =C6 -> 200 | D12: =C12*(1+$O$11) -> 220 | E12: =D12*(1+$O$11) -> 242 | F12: =E12*(1+$O$11) -> 266.2 | G12: =F12*(1+$O$11) -> 292.82 | H12: =G12*(1+$O$11) -> 322.102 | I12: =H12*(1+$O$12) -> 354.3122 | J12: =I12*(1+$O$12) -> 389.74342 | K12: =J12*(1+$O$12) -> 428.71776 | L12: =K12*(1+$O$12) -> 471.58954 | M12: =L12*(1+$O$12) -> 518.74849 | N12: =L12*O14 -> 14147.686 | O12: 0.1 | P12: 5 to 10 years
B13: =B7 -> 0 | C13: =C7 -> PV(10%) | D13: =D12*(1+$O$13)^($D$11-D11-1)*$I$3 -> 80 | E13: =E12*(1+$O$13)^($D$11-E11-1)*$I$3 -> 80 | F13: =F12*(1+$O$13)^($D$11-F11-1)*$I$3 -> 80 | G13: =G12*(1+$O$13)^($D$11-G11-1)*$I$3 -> 80 | H13: =H12*(1+$O$13)^($D$11-H11-1)*$I$3 -> 80 | I13: =I12*(1+$O$13)^($D$11-I11-1)*$I$3 -> 80 | J13: =J12*(1+$O$13)^($D$11-J11-1)*$I$3 -> 80 | K13: =K12*(1+$O$13)^($D$11-K11-1)*$I$3 -> 80 | ... M13: =M12*(1+$O$13)^($D$11-M11-1)*$I$3 -> 80 | N13: =N12*(1+$O$7)^($D$5-N11-1) -> 5454.5455 | O13: =O7 -> 0.1 | P13: Discount rate
C14: Present value sum | D14: =SUM(D13:N13) -> 6254.5455 | O14: 30 | P14: Terminal multiple
N16: Terminal Value | O16: Growth rate
B17: Scenario 3 | C17: =C11 -> Earnings per share | D17: =D11 -> 2025 | E17: =D17+1 -> 2026 | F17: =E17+1 -> 2027 | G17: =F17+1 -> 2028 | H17: =G17+1 -> 2029 | I17: =H17+1 -> 2030 | J17: =I17+1 -> 2031 | K17: =J17+1 -> 2032 | L17: =K17+1 -> 2033 | M17: =L17+1 -> 2034 | N17: =N11 -> 2034 | O17: 0.04 | P17: next 5 years
B18: worst case | C18: =C12 -> 200 | D18: =C18*(1+$O$17) -> 208 | E18: =D18*(1+$O$17) -> 216.32 | F18: =E18*(1+$O$17) -> 224.9728 | G18: =F18*(1+$O$17) -> 233.97171 | H18: =G18*(1+$O$17) -> 243.33058 | I18: =H18*(1+$O$18) -> 253.0638 | J18: =I18*(1+$O$18) -> 263.18636 | K18: =J18*(1+$O$18) -> 273.71381 | L18: =K18*(1+$O$18) -> 284.66236 | M18: =L18*(1+$O$18) -> 296.04886 | N18: =L18*O20 -> 2846.6236 | O18: 0.04 | P18: 5 to 10 years
B19: MARGIN OF | C19: =C13 -> PV(10%) | D19: =D18*(1+$O$19)^($D$17-D17-1)*$I$3 -> 75.636364 | E19: =E18*(1+$O$19)^($D$17-E17-1)*$I$3 -> 71.510744 | F19: =F18*(1+$O$19)^($D$17-F17-1)*$I$3 -> 67.610158 | G19: =G18*(1+$O$19)^($D$17-G17-1)*$I$3 -> 63.922331 | H19: =H18*(1+$O$19)^($D$17-H17-1)*$I$3 -> 60.435658 | I19: =I18*(1+$O$19)^($D$17-I17-1)*$I$3 -> 57.139168 | J19: =J18*(1+$O$19)^($D$17-J17-1)*$I$3 -> 54.022486 | K19: =K18*(1+$O$19)^($D$17-K17-1)*$I$3 -> 51.075805 | ... M19: =M18*(1+$O$19)^($D$17-M17-1)*$I$3 -> 45.65586 | N19: =N18*(1+$O$19)^($D$17-N17-1) -> 1097.4966 | O19: =O13 -> 0.1 | P19: Discount rate
B20: SAFETY | C20: Present value sum | D20: =SUM(D19:N19) -> 1692.7951 | O20: 10 | P20: Terminal multiple
C22: Scenario | D22: Probability | E22: PV | F22: Part
C23: Scenario 1 (normal case) | D23: 0.4 | E23: =D8 -> 2419.2568 | F23: =E23*D23 -> 967.70271
C24: Scenario 2 (best case) | D24: 0.3 | E24: =D14 -> 6254.5455 | F24: =E24*D24 -> 1876.3636
C25: Scenario 3 (worst case) | D25: 0.3 | E25: =D20 -> 1692.7951 | F25: =E25*D25 -> 507.83852
C26: STOCK PRICE NOW | D26: =C3 -> 6522.1 | E26: Sum | F26: =SUM(F23:F25) -> 3351.9049
B28: Disclaimer: This is just for educational purposes and not for investing advice!
B30: MADE BY | C30: STOCK MARKET RESEARCH PLATFORM

Sheet GDX
S1: input cells
B2: GDX | C2: LINK TO RESEARCH | S2: result cells
B3: STOCK PRICE | C3: ='MKT CAP - Price'!C92 -> 68.5 | F3: DIVIDEND PAYOUT RATIO | I3: 1
B4: COMPARATIVE TABLE'!A1 | N4: Terminal Value | O4: Growth rate
B5: Scenario 1 | C5: Dividend per share | D5: 2025 | E5: =D5+1 -> 2026 | F5: =E5+1 -> 2027 | G5: =F5+1 -> 2028 | H5: =G5+1 -> 2029 | I5: =H5+1 -> 2030 | J5: =I5+1 -> 2031 | K5: =J5+1 -> 2032 | L5: =K5+1 -> 2033 | M5: =L5+1 -> 2034 | N5: 2034 | O5: 0.05 | P5: next 5 years
B6: normal case | C6: 0.4 | D6: =C6*(1+$O$5) -> 0.42 | E6: =D6*(1+$O$5) -> 0.441 | F6: =E6*(1+$O$5) -> 0.46305 | G6: =F6*(1+$O$5) -> 0.4862025 | H6: =G6*(1+$O$5) -> 0.51051263 | I6: =H6*(1+$O$6) -> 0.53603826 | J6: =I6*(1+$O$6) -> 0.56284017 | K6: =J6*(1+$O$6) -> 0.59098218 | L6: =K6*(1+$O$6) -> 0.62053129 | M6: =L6*(1+$O$6) -> 0.65155785 | N6: =L6*O8 -> 20.477532 | O6: 0.05 | P6: 5 to 10 years
C7: =CONCATENATE(R8,O7*100,S8) -> PV(10%) | D7: =D6*(1+$O$7)^($D$5-D5-1)*$I$3 -> 0.38181818 | E7: =E6*(1+$O$7)^($D$5-E5-1)*$I$3 -> 0.36446281 | F7: =F6*(1+$O$7)^($D$5-F5-1)*$I$3 -> 0.34789632 | G7: =G6*(1+$O$7)^($D$5-G5-1)*$I$3 -> 0.33208285 | H7: =H6*(1+$O$7)^($D$5-H5-1)*$I$3 -> 0.31698817 | I7: =I6*(1+$O$7)^($D$5-I5-1)*$I$3 -> 0.30257962 | J7: =J6*(1+$O$7)^($D$5-J5-1)*$I$3 -> 0.288826 | K7: =K6*(1+$O$7)^($D$5-K5-1)*$I$3 -> 0.27569755 | ... M7: =M6*(1+$O$7)^($D$5-M5-1)*$I$3 -> 0.25120376 | N7: =N6*(1+$O$7)^($D$5-N5-1) -> 7.8949752 | O7: 0.1 | P7: Discount rate
C8: INTRINSIC VALUE | D8: =SUM(D7:N7) -> 11.019696 | O8: 33 | P8: Terminal multiple | R8: PV( | S8: %)
N10: Terminal Value | O10: Growth rate
B11: Scenario 2 | C11: =C5 -> Dividend per share | D11: =D5 -> 2025 | E11: =D11+1 -> 2026 | F11: =E11+1 -> 2027 | G11: =F11+1 -> 2028 | H11: =G11+1 -> 2029 | I11: =H11+1 -> 2030 | J11: =I11+1 -> 2031 | K11: =J11+1 -> 2032 | L11: =K11+1 -> 2033 | M11: =L11+1 -> 2034 | N11: =N5 -> 2034 | O11: 0.1 | P11: next 5 years
B12: best case | C12: =C6 -> 0.4 | D12: =C12*(1+$O$11) -> 0.44 | E12: =D12*(1+$O$11) -> 0.484 | F12: =E12*(1+$O$11) -> 0.5324 | G12: =F12*(1+$O$11) -> 0.58564 | H12: =G12*(1+$O$11) -> 0.644204 | I12: =H12*(1+$O$12) -> 0.7086244 | J12: =I12*(1+$O$12) -> 0.77948684 | K12: =J12*(1+$O$12) -> 0.85743552 | L12: =K12*(1+$O$12) -> 0.94317908 | M12: =L12*(1+$O$12) -> 1.037497 | N12: =L12*O14 -> 94.317908 | O12: 0.1 | P12: 5 to 10 years
B13: =B7 -> 0 | C13: =C7 -> PV(10%) | D13: =D12*(1+$O$13)^($D$11-D11-1)*$I$3 -> 0.4 | E13: =E12*(1+$O$13)^($D$11-E11-1)*$I$3 -> 0.4 | F13: =F12*(1+$O$13)^($D$11-F11-1)*$I$3 -> 0.4 | G13: =G12*(1+$O$13)^($D$11-G11-1)*$I$3 -> 0.4 | H13: =H12*(1+$O$13)^($D$11-H11-1)*$I$3 -> 0.4 | I13: =I12*(1+$O$13)^($D$11-I11-1)*$I$3 -> 0.4 | J13: =J12*(1+$O$13)^($D$11-J11-1)*$I$3 -> 0.4 | K13: =K12*(1+$O$13)^($D$11-K11-1)*$I$3 -> 0.4 | ... M13: =M12*(1+$O$13)^($D$11-M11-1)*$I$3 -> 0.4 | N13: =N12*(1+$O$7)^($D$5-N11-1) -> 36.363636 | O13: =O7 -> 0.1 | P13: Discount rate
C14: Present value sum | D14: =SUM(D13:N13) -> 40.363636 | O14: 100 | P14: Terminal multiple
N16: Terminal Value | O16: Growth rate
B17: Scenario 3 | C17: =C11 -> Dividend per share | D17: =D11 -> 2025 | E17: =D17+1 -> 2026 | F17: =E17+1 -> 2027 | G17: =F17+1 -> 2028 | H17: =G17+1 -> 2029 | I17: =H17+1 -> 2030 | J17: =I17+1 -> 2031 | K17: =J17+1 -> 2032 | L17: =K17+1 -> 2033 | M17: =L17+1 -> 2034 | N17: =N11 -> 2034 | O17: 0 | P17: next 5 years
B18: worst case | C18: =C12 -> 0.4 | D18: =C18*(1+$O$17) -> 0.4 | E18: =D18*(1+$O$17) -> 0.4 | F18: =E18*(1+$O$17) -> 0.4 | G18: =F18*(1+$O$17) -> 0.4 | H18: =G18*(1+$O$17) -> 0.4 | I18: =H18*(1+$O$18) -> 0.4 | J18: =I18*(1+$O$18) -> 0.4 | K18: =J18*(1+$O$18) -> 0.4 | L18: =K18*(1+$O$18) -> 0.4 | M18: =L18*(1+$O$18) -> 0.4 | N18: =L18*O20 -> 8 | O18: 0 | P18: 5 to 10 years
B19: MARGIN OF | C19: =C13 -> PV(10%) | D19: =D18*(1+$O$19)^($D$17-D17-1)*$I$3 -> 0.36363636 | E19: =E18*(1+$O$19)^($D$17-E17-1)*$I$3 -> 0.33057851 | F19: =F18*(1+$O$19)^($D$17-F17-1)*$I$3 -> 0.30052592 | G19: =G18*(1+$O$19)^($D$17-G17-1)*$I$3 -> 0.27320538 | H19: =H18*(1+$O$19)^($D$17-H17-1)*$I$3 -> 0.24836853 | I19: =I18*(1+$O$19)^($D$17-I17-1)*$I$3 -> 0.22578957 | J19: =J18*(1+$O$19)^($D$17-J17-1)*$I$3 -> 0.20526325 | K19: =K18*(1+$O$19)^($D$17-K17-1)*$I$3 -> 0.18660295 | ... M19: =M18*(1+$O$19)^($D$17-M17-1)*$I$3 -> 0.15421732 | N19: =N18*(1+$O$19)^($D$17-N17-1) -> 3.0843463 | O19: =O13 -> 0.1 | P19: Discount rate
B20: SAFETY | C20: Present value sum | D20: =SUM(D19:N19) -> 5.5421732 | O20: 20 | P20: Terminal multiple
C22: Scenario | D22: Probability | E22: PV | F22: Part
C23: Scenario 1 (normal case) | D23: 0.6 | E23: =D8 -> 11.019696 | F23: =E23*D23 -> 6.6118178
C24: Scenario 2 (best case) | D24: 0.2 | E24: =D14 -> 40.363636 | F24: =E24*D24 -> 8.0727273
C25: Scenario 3 (worst case) | D25: 0.2 | E25: =D20 -> 5.5421732 | F25: =E25*D25 -> 1.1084346
C26: STOCK PRICE NOW | D26: =C3 -> 68.5 | E26: Sum | F26: =SUM(F23:F25) -> 15.79298
B28: Disclaimer: This is just for educational purposes and not for investing advice!
B30: MADE BY | C30: STOCK MARKET RESEARCH PLATFORM

Sheet AMZN
S1: input cells
