Workbook

Sheet DCF Model
A1: FRFHF - Fairfax Financial Holdings — Book Value Compounding Model (Base Case)
A2: Gray cells are INPUTS - adjust to see valuation change. Insurer model: BVPS compounding + exit P/B, NOT free-cash-flow DCF.
A4: KEY INPUTS
A5: Current Stock Price | B5: 1652
A6: Shares Outstanding (M) | B6: 20.6
A7: Cash & Equivalents (US$M) | B7: 9492.2
A8: Total Debt (US$M) | B8: 14048.8
A9: Net Debt (US$M) | B9: =B8-B7
A10: Starting BVPS (Q1 2026) | B10: 1250.14
A11: Annual Dividend per Share | B11: 15
A13: Cost of Equity (Base) | B13: 0.095
A14: Exit Price-to-Book (Base) | B14: 1.1
A16: GROWTH ASSUMPTIONS (BVPS growth, net of dividend already added back)
B17: Year 1 | C17: Year 2 | D17: Year 3 | E17: Year 4 | F17: Year 5
A18: BVPS Growth Rate | B18: 0.12 | C18: 0.115 | D18: 0.115 | E18: 0.11 | F18: 0.11
A20: PROJECTIONS
B21: Base Yr | C21: Year 1 | D21: Year 2 | E21: Year 3 | F21: Year 4 | G21: Year 5
A22: Book Value per Share | B22: =B10 | C22: =B22*(1+B18)-$B$11 | D22: =C22*(1+C18)-$B$11 | E22: =D22*(1+D18)-$B$11 | F22: =E22*(1+E18)-$B$11 | G22: =F22*(1+F18)-$B$11
A23: Dividend per Share | C23: =$B$11 | D23: =$B$11 | E23: =$B$11 | F23: =$B$11 | G23: =$B$11
A24: Discount Factor (Cost of Equity) | C24: =1/(1+$B$13)^1 | D24: =1/(1+$B$13)^2 | E24: =1/(1+$B$13)^3 | F24: =1/(1+$B$13)^4 | G24: =1/(1+$B$13)^5
A25: PV of Dividend | C25: =C23*C24 | D25: =D23*D24 | E25: =E23*E24 | F25: =F23*F24 | G25: =G23*G24
A27: VALUATION
A28: Sum of PV of Dividends | B28: =SUM(C25:G25)
A29: Terminal BVPS (Year 5) | B29: =G22
A30: Exit Price-to-Book Multiple | B30: =B14
A31: Terminal Value per Share | B31: =B29*B30
A32: PV of Terminal Value | B32: =B31*G24
A33: INTRINSIC VALUE / SHARE | B33: =B28+B32
A34: Upside / (Downside) vs Current Price | B34: =(B33-B5)/B5
A36: ENTRY PRICE (15% CAGR Target)
A37: Target CAGR | B37: 0.15
A38: Reinvested Dividends FV (at target CAGR, to Yr 5) | B38: =C23*(1+$B$37)^4+D23*(1+$B$37)^3+E23*(1+$B$37)^2+F23*(1+$B$37)^1+G23*(1+$B$37)^0
A39: Total Year-5 Value (Terminal Value + Reinvested Divs) | B39: =B31+B38
A40: Entry Price (15% CAGR) | B40: =B39/(1+$B$37)^5
A41: Current Price vs Entry Price | B41: =(B5-B40)/B5
A43: Note: BVPS growth rate is net-of-dividend total value creation (dividend added back before compounding,
A44: consistent with management's own 'BVPS growth adjusted for dividend' convention). Discounting uses
A45: COST OF EQUITY (equity-holder view), not WACC — this is a per-share valuation, not enterprise value.

Sheet Bull-Bear Scenarios
A1: Bull / Bear Scenario Detail
A3: BULL CASE
A4: Cost of Equity | B4: 0.09
A5: Exit Price-to-Book | B5: 1.3
B6: Year 1 | C6: Year 2 | D6: Year 3 | E6: Year 4 | F6: Year 5
A7: BVPS Growth Rate | B7: 0.15 | C7: 0.145 | D7: 0.14 | E7: 0.14 | F7: 0.135
A8: BVPS | B8: ='DCF Model'!$B$10 | C8: =B8*(1+B7)-'DCF Model'!$B$11 | D8: =C8*(1+C7)-'DCF Model'!$B$11 | E8: =D8*(1+D7)-'DCF Model'!$B$11 | F8: =E8*(1+E7)-'DCF Model'!$B$11 | G8: =F8*(1+F7)-'DCF Model'!$B$11
A9: Dividend per Share | C9: ='DCF Model'!$B$11 | D9: ='DCF Model'!$B$11 | E9: ='DCF Model'!$B$11 | F9: ='DCF Model'!$B$11 | G9: ='DCF Model'!$B$11
A10: Discount Factor | C10: =1/(1+B4)^1 | D10: =1/(1+B4)^2 | E10: =1/(1+B4)^3 | F10: =1/(1+B4)^4 | G10: =1/(1+B4)^5
A11: PV of Dividend | C11: =C9*C10 | D11: =D9*D10 | E11: =E9*E10 | F11: =F9*F10 | G11: =G9*G10
A13: Sum PV of Dividends | B13: =SUM(C11:G11)
A14: Terminal BVPS (Yr 5) | B14: =G8
A15: Terminal Value per Share | B15: =B14*B5
A16: PV of Terminal Value | B16: =B15*G10
A17: INTRINSIC VALUE / SHARE | B17: =B13+B16
A18: Upside / (Downside) | B18: =(B17-'DCF Model'!$B$5)/'DCF Model'!$B$5
A20: BEAR CASE
A21: Cost of Equity | B21: 0.105
A22: Exit Price-to-Book | B22: 0.9
B23: Year 1 | C23: Year 2 | D23: Year 3 | E23: Year 4 | F23: Year 5
A24: BVPS Growth Rate | B24: 0.08 | C24: 0.075 | D24: 0.075 | E24: 0.07 | F24: 0.07
A25: BVPS | B25: ='DCF Model'!$B$10 | C25: =B25*(1+B24)-'DCF Model'!$B$11 | D25: =C25*(1+C24)-'DCF Model'!$B$11 | E25: =D25*(1+D24)-'DCF Model'!$B$11 | F25: =E25*(1+E24)-'DCF Model'!$B$11 | G25: =F25*(1+F24)-'DCF Model'!$B$11
A26: Dividend per Share | C26: ='DCF Model'!$B$11 | D26: ='DCF Model'!$B$11 | E26: ='DCF Model'!$B$11 | F26: ='DCF Model'!$B$11 | G26: ='DCF Model'!$B$11
A27: Discount Factor | C27: =1/(1+B21)^1 | D27: =1/(1+B21)^2 | E27: =1/(1+B21)^3 | F27: =1/(1+B21)^4 | G27: =1/(1+B21)^5
A28: PV of Dividend | C28: =C26*C27 | D28: =D26*D27 | E28: =E26*E27 | F28: =F26*F27 | G28: =G26*G27
A30: Sum PV of Dividends | B30: =SUM(C28:G28)
A31: Terminal BVPS (Yr 5) | B31: =G25
A32: Terminal Value per Share | B32: =B31*B22
A33: PV of Terminal Value | B33: =B32*G27
A34: INTRINSIC VALUE / SHARE | B34: =B30+B33
A35: Upside / (Downside) | B35: =(B34-'DCF Model'!$B$5)/'DCF Model'!$B$5

Sheet Sensitivity
A1: Sensitivity Analysis
A2: Intrinsic Value/Share by BVPS Growth Rate (avg, base 5yr path shifted uniformly) & Exit Price-to-Book
A4: Growth \ Exit P/B | B4: 0.9 | C4: 1 | D4: 1.1 | E4: 1.2 | F4: 1.3
A5: 0.074 | B5: =('DCF Model'!$B$11*(1/(1+0.095)^1)+'DCF Model'!$B$11*(1/(1+0.095)^2)+'DCF Model'!$B$11*(1/(1+0.095)^3)+'DCF Model'!$B$11*(1/(1+0.095)^4)+'DCF Model'!$B$11*(1/(1+0.095)^5))+((((('DCF Model'!$B$10*(1+0.08)-'DCF Model'!$B$11)*(1+0.075)-'DCF Model'!$B$11)*(1+0.075)-'DCF Model'!$B$11)*(1+0.07)-'DCF Model'!$B$11)*(1+0.07)-'DCF Model'!$B$11)*0.9*(1/(1+0.095)^5) | C5: =('DCF Model'!$B$11*(1/(1+0.095)^1)+'DCF Model'!$B$11*(1/(1+0.095)^2)+'DCF Model'!$B$11*(1/(1+0.095)^3)+'DCF Model'!$B$11*(1/(1+0.095)^4)+'DCF Model'!$B$11*(1/(1+0.095)^5))+((((('DCF Model'!$B$10*(1+0.08)-'DCF Model'!$B$11)*(1+0.075)-'DCF Model'!$B$11)*(1+0.075)-'DCF Model'!$B$11)*(1+0.07)-'DCF Model'!$B$11)*(1+0.07)-'DCF Model'!$B$11)*1.0*(1/(1+0.095)^5) | D5: =('DCF Model'!$B$11*(1/(1+0.095)^1)+'DCF Model'!$B$11*(1/(1+0.095)^2)+'DCF Model'!$B$11*(1/(1+0.095)^3)+'DCF Model'!$B$11*(1/(1+0.095)^4)+'DCF Model'!$B$11*(1/(1+0.095)^5))+((((('DCF Model'!$B$10*(1+0.08)-'DCF Model'!$B$11)*(1+0.075)-'DCF Model'!$B$11)*(1+0.075)-'DCF Model'!$B$11)*(1+0.07)-'DCF Model'!$B$11)*(1+0.07)-'DCF Model'!$B$11)*1.1*(1/(1+0.095)^5) | E5: =('DCF Model'!$B$11*(1/(1+0.095)^1)+'DCF Model'!$B$11*(1/(1+0.095)^2)+'DCF Model'!$B$11*(1/(1+0.095)^3)+'DCF Model'!$B$11*(1/(1+0.095)^4)+'DCF Model'!$B$11*(1/(1+0.095)^5))+((((('DCF Model'!$B$10*(1+0.08)-'DCF Model'!$B$11)*(1+0.075)-'DCF Model'!$B$11)*(1+0.075)-'DCF Model'!$B$11)*(1+0.07)-'DCF Model'!$B$11)*(1+0.07)-'DCF Model'!$B$11)*1.2*(1/(1+0.095)^5) | F5: =('DCF Model'!$B$11*(1/(1+0.095)^1)+'DCF Model'!$B$11*(1/(1+0.095)^2)+'DCF Model'!$B$11*(1/(1+0.095)^3)+'DCF Model'!$B$11*(1/(1+0.095)^4)+'DCF Model'!$B$11*(1/(1+0.095)^5))+((((('DCF Model'!$B$10*(1+0.08)-'DCF Model'!$B$11)*(1+0.075)-'DCF Model'!$B$11)*(1+0.075)-'DCF Model'!$B$11)*(1+0.07)-'DCF Model'!$B$11)*(1+0.07)-'DCF Model'!$B$11)*1.3*(1/(1+0.095)^5)
A6: 0.094 | B6: =('DCF Model'!$B$11*(1/(1+0.095)^1)+'DCF Model'!$B$11*(1/(1+0.095)^2)+'DCF Model'!$B$11*(1/(1+0.095)^3)+'DCF Model'!$B$11*(1/(1+0.095)^4)+'DCF Model'!$B$11*(1/(1+0.095)^5))+((((('DCF Model'!$B$10*(1+0.1)-'DCF Model'!$B$11)*(1+0.095)-'DCF Model'!$B$11)*(1+0.095)-'DCF Model'!$B$11)*(1+0.09)-'DCF Model'!$B$11)*(1+0.09)-'DCF Model'!$B$11)*0.9*(1/(1+0.095)^5) | C6: =('DCF Model'!$B$11*(1/(1+0.095)^1)+'DCF Model'!$B$11*(1/(1+0.095)^2)+'DCF Model'!$B$11*(1/(1+0.095)^3)+'DCF Model'!$B$11*(1/(1+0.095)^4)+'DCF Model'!$B$11*(1/(1+0.095)^5))+((((('DCF Model'!$B$10*(1+0.1)-'DCF Model'!$B$11)*(1+0.095)-'DCF Model'!$B$11)*(1+0.095)-'DCF Model'!$B$11)*(1+0.09)-'DCF Model'!$B$11)*(1+0.09)-'DCF Model'!$B$11)*1.0*(1/(1+0.095)^5) | D6: =('DCF Model'!$B$11*(1/(1+0.095)^1)+'DCF Model'!$B$11*(1/(1+0.095)^2)+'DCF Model'!$B$11*(1/(1+0.095)^3)+'DCF Model'!$B$11*(1/(1+0.095)^4)+'DCF Model'!$B$11*(1/(1+0.095)^5))+((((('DCF Model'!$B$10*(1+0.1)-'DCF Model'!$B$11)*(1+0.095)-'DCF Model'!$B$11)*(1+0.095)-'DCF Model'!$B$11)*(1+0.09)-'DCF Model'!$B$11)*(1+0.09)-'DCF Model'!$B$11)*1.1*(1/(1+0.095)^5) | E6: =('DCF Model'!$B$11*(1/(1+0.095)^1)+'DCF Model'!$B$11*(1/(1+0.095)^2)+'DCF Model'!$B$11*(1/(1+0.095)^3)+'DCF Model'!$B$11*(1/(1+0.095)^4)+'DCF Model'!$B$11*(1/(1+0.095)^5))+((((('DCF Model'!$B$10*(1+0.1)-'DCF Model'!$B$11)*(1+0.095)-'DCF Model'!$B$11)*(1+0.095)-'DCF Model'!$B$11)*(1+0.09)-'DCF Model'!$B$11)*(1+0.09)-'DCF Model'!$B$11)*1.2*(1/(1+0.095)^5) | F6: =('DCF Model'!$B$11*(1/(1+0.095)^1)+'DCF Model'!$B$11*(1/(1+0.095)^2)+'DCF Model'!$B$11*(1/(1+0.095)^3)+'DCF Model'!$B$11*(1/(1+0.095)^4)+'DCF Model'!$B$11*(1/(1+0.095)^5))+((((('DCF Model'!$B$10*(1+0.1)-'DCF Model'!$B$11)*(1+0.095)-'DCF Model'!$B$11)*(1+0.095)-'DCF Model'!$B$11)*(1+0.09)-'DCF Model'!$B$11)*(1+0.09)-'DCF Model'!$B$11)*1.3*(1/(1+0.095)^5)
A7: 0.114 | B7: =('DCF Model'!$B$11*(1/(1+0.095)^1)+'DCF Model'!$B$11*(1/(1+0.095)^2)+'DCF Model'!$B$11*(1/(1+0.095)^3)+'DCF Model'!$B$11*(1/(1+0.095)^4)+'DCF Model'!$B$11*(1/(1+0.095)^5))+((((('DCF Model'!$B$10*(1+0.12)-'DCF Model'!$B$11)*(1+0.115)-'DCF Model'!$B$11)*(1+0.115)-'DCF Model'!$B$11)*(1+0.11)-'DCF Model'!$B$11)*(1+0.11)-'DCF Model'!$B$11)*0.9*(1/(1+0.095)^5) | C7: =('DCF Model'!$B$11*(1/(1+0.095)^1)+'DCF Model'!$B$11*(1/(1+0.095)^2)+'DCF Model'!$B$11*(1/(1+0.095)^3)+'DCF Model'!$B$11*(1/(1+0.095)^4)+'DCF Model'!$B$11*(1/(1+0.095)^5))+((((('DCF Model'!$B$10*(1+0.12)-'DCF Model'!$B$11)*(1+0.115)-'DCF Model'!$B$11)*(1+0.115)-'DCF Model'!$B$11)*(1+0.11)-'DCF Model'!$B$11)*(1+0.11)-'DCF Model'!$B$11)*1.0*(1/(1+0.095)^5) | D7: =('DCF Model'!$B$11*(1/(1+0.095)^1)+'DCF Model'!$B$11*(1/(1+0.095)^2)+'DCF Model'!$B$11*(1/(1+0.095)^3)+'DCF Model'!$B$11*(1/(1+0.095)^4)+'DCF Model'!$B$11*(1/(1+0.095)^5))+((((('DCF Model'!$B$10*(1+0.12)-'DCF Model'!$B$11)*(1+0.115)-'DCF Model'!$B$11)*(1+0.115)-'DCF Model'!$B$11)*(1+0.11)-'DCF Model'!$B$11)*(1+0.11)-'DCF Model'!$B$11)*1.1*(1/(1+0.095)^5) | E7: =('DCF Model'!$B$11*(1/(1+0.095)^1)+'DCF Model'!$B$11*(1/(1+0.095)^2)+'DCF Model'!$B$11*(1/(1+0.095)^3)+'DCF Model'!$B$11*(1/(1+0.095)^4)+'DCF Model'!$B$11*(1/(1+0.095)^5))+((((('DCF Model'!$B$10*(1+0.12)-'DCF Model'!$B$11)*(1+0.115)-'DCF Model'!$B$11)*(1+0.115)-'DCF Model'!$B$11)*(1+0.11)-'DCF Model'!$B$11)*(1+0.11)-'DCF Model'!$B$11)*1.2*(1/(1+0.095)^5) | F7: =('DCF Model'!$B$11*(1/(1+0.095)^1)+'DCF Model'!$B$11*(1/(1+0.095)^2)+'DCF Model'!$B$11*(1/(1+0.095)^3)+'DCF Model'!$B$11*(1/(1+0.095)^4)+'DCF Model'!$B$11*(1/(1+0.095)^5))+((((('DCF Model'!$B$10*(1+0.12)-'DCF Model'!$B$11)*(1+0.115)-'DCF Model'!$B$11)*(1+0.115)-'DCF Model'!$B$11)*(1+0.11)-'DCF Model'!$B$11)*(1+0.11)-'DCF Model'!$B$11)*1.3*(1/(1+0.095)^5)
A8: 0.134 | B8: =('DCF Model'!$B$11*(1/(1+0.095)^1)+'DCF Model'!$B$11*(1/(1+0.095)^2)+'DCF Model'!$B$11*(1/(1+0.095)^3)+'DCF Model'!$B$11*(1/(1+0.095)^4)+'DCF Model'!$B$11*(1/(1+0.095)^5))+((((('DCF Model'!$B$10*(1+0.14)-'DCF Model'!$B$11)*(1+0.135)-'DCF Model'!$B$11)*(1+0.135)-'DCF Model'!$B$11)*(1+0.13)-'DCF Model'!$B$11)*(1+0.13)-'DCF Model'!$B$11)*0.9*(1/(1+0.095)^5) | C8: =('DCF Model'!$B$11*(1/(1+0.095)^1)+'DCF Model'!$B$11*(1/(1+0.095)^2)+'DCF Model'!$B$11*(1/(1+0.095)^3)+'DCF Model'!$B$11*(1/(1+0.095)^4)+'DCF Model'!$B$11*(1/(1+0.095)^5))+((((('DCF Model'!$B$10*(1+0.14)-'DCF Model'!$B$11)*(1+0.135)-'DCF Model'!$B$11)*(1+0.135)-'DCF Model'!$B$11)*(1+0.13)-'DCF Model'!$B$11)*(1+0.13)-'DCF Model'!$B$11)*1.0*(1/(1+0.095)^5) | D8: =('DCF Model'!$B$11*(1/(1+0.095)^1)+'DCF Model'!$B$11*(1/(1+0.095)^2)+'DCF Model'!$B$11*(1/(1+0.095)^3)+'DCF Model'!$B$11*(1/(1+0.095)^4)+'DCF Model'!$B$11*(1/(1+0.095)^5))+((((('DCF Model'!$B$10*(1+0.14)-'DCF Model'!$B$11)*(1+0.135)-'DCF Model'!$B$11)*(1+0.135)-'DCF Model'!$B$11)*(1+0.13)-'DCF Model'!$B$11)*(1+0.13)-'DCF Model'!$B$11)*1.1*(1/(1+0.095)^5) | E8: =('DCF Model'!$B$11*(1/(1+0.095)^1)+'DCF Model'!$B$11*(1/(1+0.095)^2)+'DCF Model'!$B$11*(1/(1+0.095)^3)+'DCF Model'!$B$11*(1/(1+0.095)^4)+'DCF Model'!$B$11*(1/(1+0.095)^5))+((((('DCF Model'!$B$10*(1+0.14)-'DCF Model'!$B$11)*(1+0.135)-'DCF Model'!$B$11)*(1+0.135)-'DCF Model'!$B$11)*(1+0.13)-'DCF Model'!$B$11)*(1+0.13)-'DCF Model'!$B$11)*1.2*(1/(1+0.095)^5) | F8: =('DCF Model'!$B$11*(1/(1+0.095)^1)+'DCF Model'!$B$11*(1/(1+0.095)^2)+'DCF Model'!$B$11*(1/(1+0.095)^3)+'DCF Model'!$B$11*(1/(1+0.095)^4)+'DCF Model'!$B$11*(1/(1+0.095)^5))+((((('DCF Model'!$B$10*(1+0.14)-'DCF Model'!$B$11)*(1+0.135)-'DCF Model'!$B$11)*(1+0.135)-'DCF Model'!$B$11)*(1+0.13)-'DCF Model'!$B$11)*(1+0.13)-'DCF Model'!$B$11)*1.3*(1/(1+0.095)^5)
A9: 0.154 | B9: =('DCF Model'!$B$11*(1/(1+0.095)^1)+'DCF Model'!$B$11*(1/(1+0.095)^2)+'DCF Model'!$B$11*(1/(1+0.095)^3)+'DCF Model'!$B$11*(1/(1+0.095)^4)+'DCF Model'!$B$11*(1/(1+0.095)^5))+((((('DCF Model'!$B$10*(1+0.16)-'DCF Model'!$B$11)*(1+0.155)-'DCF Model'!$B$11)*(1+0.155)-'DCF Model'!$B$11)*(1+0.15)-'DCF Model'!$B$11)*(1+0.15)-'DCF Model'!$B$11)*0.9*(1/(1+0.095)^5) | C9: =('DCF Model'!$B$11*(1/(1+0.095)^1)+'DCF Model'!$B$11*(1/(1+0.095)^2)+'DCF Model'!$B$11*(1/(1+0.095)^3)+'DCF Model'!$B$11*(1/(1+0.095)^4)+'DCF Model'!$B$11*(1/(1+0.095)^5))+((((('DCF Model'!$B$10*(1+0.16)-'DCF Model'!$B$11)*(1+0.155)-'DCF Model'!$B$11)*(1+0.155)-'DCF Model'!$B$11)*(1+0.15)-'DCF Model'!$B$11)*(1+0.15)-'DCF Model'!$B$11)*1.0*(1/(1+0.095)^5) | D9: =('DCF Model'!$B$11*(1/(1+0.095)^1)+'DCF Model'!$B$11*(1/(1+0.095)^2)+'DCF Model'!$B$11*(1/(1+0.095)^3)+'DCF Model'!$B$11*(1/(1+0.095)^4)+'DCF Model'!$B$11*(1/(1+0.095)^5))+((((('DCF Model'!$B$10*(1+0.16)-'DCF Model'!$B$11)*(1+0.155)-'DCF Model'!$B$11)*(1+0.155)-'DCF Model'!$B$11)*(1+0.15)-'DCF Model'!$B$11)*(1+0.15)-'DCF Model'!$B$11)*1.1*(1/(1+0.095)^5) | E9: =('DCF Model'!$B$11*(1/(1+0.095)^1)+'DCF Model'!$B$11*(1/(1+0.095)^2)+'DCF Model'!$B$11*(1/(1+0.095)^3)+'DCF Model'!$B$11*(1/(1+0.095)^4)+'DCF Model'!$B$11*(1/(1+0.095)^5))+((((('DCF Model'!$B$10*(1+0.16)-'DCF Model'!$B$11)*(1+0.155)-'DCF Model'!$B$11)*(1+0.155)-'DCF Model'!$B$11)*(1+0.15)-'DCF Model'!$B$11)*(1+0.15)-'DCF Model'!$B$11)*1.2*(1/(1+0.095)^5) | F9: =('DCF Model'!$B$11*(1/(1+0.095)^1)+'DCF Model'!$B$11*(1/(1+0.095)^2)+'DCF Model'!$B$11*(1/(1+0.095)^3)+'DCF Model'!$B$11*(1/(1+0.095)^4)+'DCF Model'!$B$11*(1/(1+0.095)^5))+((((('DCF Model'!$B$10*(1+0.16)-'DCF Model'!$B$11)*(1+0.155)-'DCF Model'!$B$11)*(1+0.155)-'DCF Model'!$B$11)*(1+0.15)-'DCF Model'!$B$11)*(1+0.15)-'DCF Model'!$B$11)*1.3*(1/(1+0.095)^5)
A11: Note: Cost of equity held at base case (9.5%). Rows = average annual BVPS growth rate over the 5-yr
A12: path (base path shifted uniformly -4pp to +4pp). Columns = exit price-to-book multiple applied to Year-5 BVPS.

Sheet Historical
A1: Historical Growth Rates
A3: Metric | B3: 3-Year CAGR | C3: 5-Year CAGR / Other
A4: BVPS | B4: 0.2421 | C4: 0.2138
A5: BVPS (10yr) | C5: 0.1208
A6: BVPS (since 1985, co-stated) | C6: 0.187
A7: EPS (misleading - see warning) | B7: 0.7003 | C7: 1.0242
A8: Revenue | B8: 0.185 | C8: 0.1871
A9: Shareholders' Equity (total) | B9: 0.1966 | C9: 0.1599
A11: Selected Growth Rate (base anchor): | B11: 0.1208
A12: Source: | B12: bvps_10yr_cagr
A14: Growth Divergence Warning:
A15: EPS 3yr/5yr CAGRs (70%/102%) and OCF are highly misleading for FRFHF: EPS growth off a depressed FY2020 base ($6.29) and OCF swinging from -$4.4bn (FY2022) to +$6.6bn (FY2021) purely on investment mark-to-market noise are not representative growth signals. BVPS 5yr CAGR (21.4%) is rate-cycle boosted (2023-2025 record interest income + underwriting hard market) and should NOT be extrapolated forward; the 10-year BVPS CAGR (12.1%) and the softening-cycle guidance in the analysis JSON are used to anchor the base case instead, consistent with management's own long-run 15% target and cautious 2026 cycle commentary.
A17: BVPS by Fiscal Year
A18: Period | B18: BVPS (US$)
A19: FY2015 | B19: 403.01
A20: FY2016 | B20: 367.4
A21: FY2017 | B21: 449.55
A22: FY2018 | B22: 432.46
A23: FY2019 | B23: 486.1
A24: FY2020 | B24: 478.33
A25: FY2021 | B25: 630.6
A26: FY2022 | B26: 657.68
A27: FY2023 | B27: 939.65
A28: FY2024 | B28: 1059.6
A29: FY2025 | B29: 1260.19
A30: Q1 2026 | B30: 1250.14

Sheet Sanity Check
A1: Sanity Check — Historical P/B Cross-Reference
A3: Base Intrinsic Value / Share | B3: ='DCF Model'!B33
A4: Implied P/B (Base IV / Q1-2026 BVPS) | B4: =B3/'DCF Model'!B10
A5: Normalized EPS Estimate (mid-cycle) | B5: 200
A6: Implied P/E (Base IV / Normalized EPS) | B6: =B3/B5
A8: Historical 10yr P/B Range
A9: Min (2020) | B9: 0.71
A10: Average (10yr) | B10: 1.07
A11: Max (2025) | B11: 1.51
A12: Current (Q1 2026) | B12: 1.32
A14: Sanity Check Passed: | B14: YES
A16: Diagnosis:
A17: Base-case intrinsic value of $1,490.68 implies a P/B of 1.19x on Q1-2026 BVPS ($1,250.14) and roughly 7.5x normalized EPS (~$200/share mid-cycle) - both comfortably inside the 10-year historical P/B band (0.71x-1.51x, avg 1.07x) and well below the peak multiple the stock has ever traded at. No FCF-DCF distortion risk exists here because the model is BV-compounding based, not OCF-based (OCF is negative in several periods and was explicitly excluded per methodology). Current price ($1,652, 1.32x BVPS) sits above the base case's implied fair multiple, consistent with a modest single-digit downside (-9.8%) in the base scenario and supports treating FRFHF as fairly-to-fully valued rather than deeply undervalued at current levels.
