Workbook

Sheet Inputs
A1: Blackstone Inc. (BX) -- Distributable Earnings DCF
A2: Valuation date: 2026-09-26 | Model: DE capitalization at cost of equity (asset-manager GP)
A5: Current price (USD, 2026-09-25 close) | C5: 118.42
A6: 52-week range | C6: 101.73 - 178.29
A9: DE Shares Outstanding (2Q'26, millions) | C9: 1243.813
A10: of which Participating Common Shares | C10: 799.935
A11: of which Blackstone Holdings Partnership Units | C11: 443.878
A12: LTM Distributable Earnings ($M) | C12: 7876.6
A13: LTM DE per DE-share ($) | C13: 6.15
A14: LTM Fee Related Earnings ($M) | C14: 6331.4
A15: LTM FRE per DE-share ($) | C15: 5.14
A17: Annual history ($M) | C17: FY2022 / FY2023 / FY2024 / FY2025
A18: Distributable Earnings | C18: 6,632.8 / 5,061.0 / 5,966.7 / 7,110.9
A19: Fee Related Earnings | C19: 4,412.6 / 4,349.3 / 5,282.1 / 5,737.5
A22: Outstanding debt (at par) | C22: 13192.7
A23: Cash and cash equivalents | C23: 2507
A24: Corporate treasury and other investments | C24: 9735
A25: Net liquid corporate (cash+treasury-debt) | C25: =C23+C24-C22
A26: Net liquid per DE-share | C26: =C25/C9
A28: Bridge treatment: NOT added -- DE already post-financing-cost;
A29: GP co-investments & net accrued performance revenue excluded to avoid
A30: double-counting future DE already captured in the growth path.
A33: Total AUM | C33: 1346.3
A34: Fee-earning AUM | C34: 961.6
A35: Perpetual capital AUM (48% of fee-earning) | C35: 555.6
A38: Risk-free rate | C38: 0.042
A39: Beta (alternative asset manager) | C39: 1.35
A40: Equity risk premium | C40: 0.05
A41: Cost of equity = Rf + Beta x ERP | C41: =C38+C39*C40

Sheet Summary
A1: BX -- Valuation Summary
A3: Scenario | B3: Weight | C3: Intrinsic Value/Share ($) | D3: Upside/Downside
A4: Bear | B4: 0.25 | C4: =Bear!C27 | D4: =C4/Inputs!C5-1
A5: Base | B5: 0.5 | C5: =Base!C27 | D5: =C5/Inputs!C5-1
A6: Bull | B6: 0.25 | C6: =Bull!C27 | D6: =C6/Inputs!C5-1
A7: Probability-weighted IV | C7: =SUMPRODUCT(B4:B6,C4:C6)
A8: Current price | C8: =Inputs!C5
A9: Upside/(downside), weighted | C9: =C7/Inputs!C5-1
A11: Band position (0%=Base, 100%=Bull) | C11: =(Inputs!C5-Base!C27)/(Bull!C27-Base!C27)
A14: Entry price at 15% hurdle rate (base case DE path)
A15: Hurdle rate | C15: 0.15
A16: Entry price ($) | C16: 69.89
A17: Discount to current price | C17: =C16/Inputs!C5-1
A19: Required Return Table (base case)
A20: Cost of equity | B20: 8% | C20: 9% | D20: 10% | E20: 11% | F20: 11.5% | G20: 12% | H20: 13% | I20: 15%
A21: Value/share ($) | B21: 203.55 | C21: 161.31 | D21: 133.22 | E21: 113.22 | F21: 105.24 | G21: 98.26 | H21: 86.67 | I21: 69.89
A24: Sensitivity: Cost of Equity (rows) x Terminal Growth (cols)
A25: CoE \ TG | B25: 2.5% | C25: 3.0% | D25: 3.5% | E25: 4.0% | F25: 4.5%
A26: 9% | B26: 135.6 | C26: 142.7 | D26: 151.2 | E26: 161.3 | F26: 173.7
A27: 10% | B27: 116.1 | C27: 121 | D27: 126.6 | E27: 133.2 | F27: 141
A28: 11% | B28: 101.3 | C28: 104.8 | D28: 108.7 | E28: 113.2 | F28: 118.4
A29: 12% | B29: 89.7 | C29: 92.2 | D29: 95.1 | E29: 98.3 | F29: 101.9
A30: 13% | B30: 80.3 | C30: 82.2 | D30: 84.3 | E30: 86.7 | F30: 89.3

Sheet Base
A1: BX -- Base case
A3: Cost of equity | C3: 0.11
A4: Terminal growth rate | C4: 0.04
A5: DE-share count annual growth | C5: 0.015
A6: Base LTM DE ($M) | C6: =Inputs!C12
A7: Base DE Shares Outstanding (M) | C7: =Inputs!C9
A9: Year | B9: DE growth % | C9: Distributable Earnings ($M) | D9: DE Shares Outstanding (M) | E9: DE per share ($) | F9: Discount factor | G9: PV of DE ($M)
A10: Y1 | B10: 0.11 | C10: =C6*(1+B10) | D10: =C7*(1+$C$5) | E10: =C10/D10 | F10: =1/(1+$C$3)^1 | G10: =C10*F10
A11: Y2 | B11: 0.1 | C11: =C10*(1+B11) | D11: =D10*(1+$C$5) | E11: =C11/D11 | F11: =1/(1+$C$3)^2 | G11: =C11*F11
A12: Y3 | B12: 0.1 | C12: =C11*(1+B12) | D12: =D11*(1+$C$5) | E12: =C12/D12 | F12: =1/(1+$C$3)^3 | G12: =C12*F12
A13: Y4 | B13: 0.09 | C13: =C12*(1+B13) | D13: =D12*(1+$C$5) | E13: =C13/D13 | F13: =1/(1+$C$3)^4 | G13: =C13*F13
A14: Y5 | B14: 0.09 | C14: =C13*(1+B14) | D14: =D13*(1+$C$5) | E14: =C14/D14 | F14: =1/(1+$C$3)^5 | G14: =C14*F14
A15: Y6 | B15: 0.08 | C15: =C14*(1+B15) | D15: =D14*(1+$C$5) | E15: =C15/D15 | F15: =1/(1+$C$3)^6 | G15: =C15*F15
A16: Y7 | B16: 0.07 | C16: =C15*(1+B16) | D16: =D15*(1+$C$5) | E16: =C16/D16 | F16: =1/(1+$C$3)^7 | G16: =C16*F16
A17: Y8 | B17: 0.07 | C17: =C16*(1+B17) | D17: =D16*(1+$C$5) | E17: =C17/D17 | F17: =1/(1+$C$3)^8 | G17: =C17*F17
A18: Y9 | B18: 0.06 | C18: =C17*(1+B18) | D18: =D17*(1+$C$5) | E18: =C18/D18 | F18: =1/(1+$C$3)^9 | G18: =C18*F18
A19: Y10 | B19: 0.06 | C19: =C18*(1+B19) | D19: =D18*(1+$C$5) | E19: =C19/D19 | F19: =1/(1+$C$3)^10 | G19: =C19*F19
A21: Sum PV of interim DE | G21: =SUM(G10:G19)
A22: Terminal DE (Year N+1) | C22: =C19*(1+C4)
A23: Terminal Value (Gordon growth) | C23: =C22/(C3-C4)
A24: PV of Terminal Value | C24: =C23*F19
A25: Equity Value ($M) | C25: =G21+C24
A26: Ending DE Shares Outstanding (M) | C26: =D19
A27: Intrinsic Value per Share ($) | C27: =C25/C26
A28: Current price ($) | C28: =Inputs!C5
A29: Upside/(downside) to current price | C29: =C27/C28-1
A30: Terminal value as % of equity value | C30: =C24/C25

Sheet Bull
A1: BX -- Bull case
A3: Cost of equity | C3: 0.1
A4: Terminal growth rate | C4: 0.045
A5: DE-share count annual growth | C5: 0.015
A6: Base LTM DE ($M) | C6: =Inputs!C12
A7: Base DE Shares Outstanding (M) | C7: =Inputs!C9
A9: Year | B9: DE growth % | C9: Distributable Earnings ($M) | D9: DE Shares Outstanding (M) | E9: DE per share ($) | F9: Discount factor | G9: PV of DE ($M)
A10: Y1 | B10: 0.15 | C10: =C6*(1+B10) | D10: =C7*(1+$C$5) | E10: =C10/D10 | F10: =1/(1+$C$3)^1 | G10: =C10*F10
A11: Y2 | B11: 0.14 | C11: =C10*(1+B11) | D11: =D10*(1+$C$5) | E11: =C11/D11 | F11: =1/(1+$C$3)^2 | G11: =C11*F11
A12: Y3 | B12: 0.13 | C12: =C11*(1+B12) | D12: =D11*(1+$C$5) | E12: =C12/D12 | F12: =1/(1+$C$3)^3 | G12: =C12*F12
A13: Y4 | B13: 0.12 | C13: =C12*(1+B13) | D13: =D12*(1+$C$5) | E13: =C13/D13 | F13: =1/(1+$C$3)^4 | G13: =C13*F13
A14: Y5 | B14: 0.11 | C14: =C13*(1+B14) | D14: =D13*(1+$C$5) | E14: =C14/D14 | F14: =1/(1+$C$3)^5 | G14: =C14*F14
A15: Y6 | B15: 0.1 | C15: =C14*(1+B15) | D15: =D14*(1+$C$5) | E15: =C15/D15 | F15: =1/(1+$C$3)^6 | G15: =C15*F15
A16: Y7 | B16: 0.09 | C16: =C15*(1+B16) | D16: =D15*(1+$C$5) | E16: =C16/D16 | F16: =1/(1+$C$3)^7 | G16: =C16*F16
A17: Y8 | B17: 0.08 | C17: =C16*(1+B17) | D17: =D16*(1+$C$5) | E17: =C17/D17 | F17: =1/(1+$C$3)^8 | G17: =C17*F17
A18: Y9 | B18: 0.08 | C18: =C17*(1+B18) | D18: =D17*(1+$C$5) | E18: =C18/D18 | F18: =1/(1+$C$3)^9 | G18: =C18*F18
A19: Y10 | B19: 0.07 | C19: =C18*(1+B19) | D19: =D18*(1+$C$5) | E19: =C19/D19 | F19: =1/(1+$C$3)^10 | G19: =C19*F19
A21: Sum PV of interim DE | G21: =SUM(G10:G19)
A22: Terminal DE (Year N+1) | C22: =C19*(1+C4)
A23: Terminal Value (Gordon growth) | C23: =C22/(C3-C4)
A24: PV of Terminal Value | C24: =C23*F19
A25: Equity Value ($M) | C25: =G21+C24
A26: Ending DE Shares Outstanding (M) | C26: =D19
A27: Intrinsic Value per Share ($) | C27: =C25/C26
A28: Current price ($) | C28: =Inputs!C5
A29: Upside/(downside) to current price | C29: =C27/C28-1
A30: Terminal value as % of equity value | C30: =C24/C25

Sheet Bear
A1: BX -- Bear case
A3: Cost of equity | C3: 0.125
A4: Terminal growth rate | C4: 0.03
A5: DE-share count annual growth | C5: 0.015
A6: Base LTM DE ($M) | C6: =Inputs!C12
A7: Base DE Shares Outstanding (M) | C7: =Inputs!C9
A9: Year | B9: DE growth % | C9: Distributable Earnings ($M) | D9: DE Shares Outstanding (M) | E9: DE per share ($) | F9: Discount factor | G9: PV of DE ($M)
A10: Y1 | B10: 0.02 | C10: =C6*(1+B10) | D10: =C7*(1+$C$5) | E10: =C10/D10 | F10: =1/(1+$C$3)^1 | G10: =C10*F10
A11: Y2 | B11: 0.03 | C11: =C10*(1+B11) | D11: =D10*(1+$C$5) | E11: =C11/D11 | F11: =1/(1+$C$3)^2 | G11: =C11*F11
A12: Y3 | B12: 0.04 | C12: =C11*(1+B12) | D12: =D11*(1+$C$5) | E12: =C12/D12 | F12: =1/(1+$C$3)^3 | G12: =C12*F12
A13: Y4 | B13: 0.05 | C13: =C12*(1+B13) | D13: =D12*(1+$C$5) | E13: =C13/D13 | F13: =1/(1+$C$3)^4 | G13: =C13*F13
A14: Y5 | B14: 0.05 | C14: =C13*(1+B14) | D14: =D13*(1+$C$5) | E14: =C14/D14 | F14: =1/(1+$C$3)^5 | G14: =C14*F14
A15: Y6 | B15: 0.05 | C15: =C14*(1+B15) | D15: =D14*(1+$C$5) | E15: =C15/D15 | F15: =1/(1+$C$3)^6 | G15: =C15*F15
A16: Y7 | B16: 0.05 | C16: =C15*(1+B16) | D16: =D15*(1+$C$5) | E16: =C16/D16 | F16: =1/(1+$C$3)^7 | G16: =C16*F16
A17: Y8 | B17: 0.05 | C17: =C16*(1+B17) | D17: =D16*(1+$C$5) | E17: =C17/D17 | F17: =1/(1+$C$3)^8 | G17: =C17*F17
A18: Y9 | B18: 0.05 | C18: =C17*(1+B18) | D18: =D17*(1+$C$5) | E18: =C18/D18 | F18: =1/(1+$C$3)^9 | G18: =C18*F18
A19: Y10 | B19: 0.05 | C19: =C18*(1+B19) | D19: =D18*(1+$C$5) | E19: =C19/D19 | F19: =1/(1+$C$3)^10 | G19: =C19*F19
A21: Sum PV of interim DE | G21: =SUM(G10:G19)
A22: Terminal DE (Year N+1) | C22: =C19*(1+C4)
A23: Terminal Value (Gordon growth) | C23: =C22/(C3-C4)
A24: PV of Terminal Value | C24: =C23*F19
A25: Equity Value ($M) | C25: =G21+C24
A26: Ending DE Shares Outstanding (M) | C26: =D19
A27: Intrinsic Value per Share ($) | C27: =C25/C26
A28: Current price ($) | C28: =Inputs!C5
A29: Upside/(downside) to current price | C29: =C27/C28-1
A30: Terminal value as % of equity value | C30: =C24/C25
