Workbook

Sheet DCF Model
A1: ARG.NZ AFFO-Capitalization Valuation Model (REIT)
A2: Gray cells are INPUTS - adjust to see valuation change. Model discounts AFFO at COST OF EQUITY (not WACC); no net-debt deduction (AFFO is post-interest).
A4: KEY INPUTS
A5: Current Stock Price (NZD) | B5: 1.045
A6: Shares Outstanding (M, FY2026) | B6: 873.5
A7: NTA per Share (NZD, FY2026) | B7: 1.6
A8: Net Debt (M, memo only - not subtracted) | B8: 852.126
A9: Reported AFFO FY2026 (M) | B9: 59.117
A10: Less: Stock-Based Comp (M) | B10: 0.299
A11: Base AFFO, after SBC (M) | B11: =B9-B10 -> 0
A12: Annual Share Dilution (DRP) | B12: 0.01
A14: Cost of Equity | B14: 0.095
A15: Exit AFFO Yield (Terminal) | B15: 0.07
A16: AFFO Annual Growth Rate (Base) | B16: 0.018
A18: PROJECTIONS (Base Case)
B19: FY2026 | C19: FY2027 | D19: FY2028 | E19: FY2029 | F19: FY2030 | G19: FY2031
A20: AFFO (NZD M) | B20: =B11 -> 0 | C20: =B20*(1+$B$16) -> 0 | D20: =C20*(1+$B$16) -> 0 | E20: =D20*(1+$B$16) -> 0 | F20: =E20*(1+$B$16) -> 0 | G20: =F20*(1+$B$16) -> 0
A21: Shares Outstanding (M) | B21: =B6 -> 0 | C21: =B21*(1+$B$12) -> 0 | D21: =C21*(1+$B$12) -> 0 | E21: =D21*(1+$B$12) -> 0 | F21: =E21*(1+$B$12) -> 0 | G21: =F21*(1+$B$12) -> 0
A22: Discount Factor (at CoE) | C22: =1/(1+$B$14)^1 -> 0 | D22: =1/(1+$B$14)^2 -> 0 | E22: =1/(1+$B$14)^3 -> 0 | F22: =1/(1+$B$14)^4 -> 0 | G22: =1/(1+$B$14)^5 -> 0
A23: PV of AFFO | C23: =C20*C22 -> 0 | D23: =D20*D22 -> 0 | E23: =E20*E22 -> 0 | F23: =F20*F22 -> 0 | G23: =G20*G22 -> 0
A25: VALUATION
A26: Sum of PV of AFFO (Yrs 1-5) | B26: =SUM(C23:G23) -> 0
A27: Terminal AFFO (Year 5) | B27: =G20 -> 0
A28: Terminal Value (= Terminal AFFO / Exit Yield) | B28: =B27/$B$15 -> 0
A29: PV of Terminal Value | B29: =B28*G22 -> 0
A30: Equity Value (Sum PV AFFO + PV Terminal) | B30: =B26+B29 -> 0
A31: Note: no net-debt deduction (AFFO is post-interest, equity-level)
A32: INTRINSIC VALUE/SHARE | B32: =B30/G21 -> 0
A34: ENTRY PRICE (15% IRR Target)
A35: PV of Yrs 1-5 AFFO @15% | B35: =NPV(0.15,C20:G20) -> 0
A36: PV of Terminal Value @15% | B36: =B28/(1.15^5) -> 0
A37: Entry Equity Value | B37: =B35+B36 -> 0
A38: Entry Price (15% CAGR) | B38: =B37/G21 -> 0
A40: UPSIDE / CROSS-CHECKS
A41: Upside to Intrinsic Value | B41: =(B32-B5)/B5 -> 0
A42: Upside to Entry Price | B42: =(B5-B38)/B5 -> 0
A43: Current Price P/AFFO (x) | B43: =B5/(B11/B6) -> 0
A44: Current Price P/NTA (x) | B44: =B5/B7 -> 0
A45: No-Growth AFFO-Cap Floor (per share) | B45: =(B11/B6)/B14 -> 0
A46: NTA Ceiling Proxy (per share) | B46: =B7 -> 0

Sheet Sensitivity
A1: Sensitivity Analysis
A2: Intrinsic Value by Cost of Equity & Exit AFFO Yield (Base-case 1.8% AFFO growth)
A4: CoE \ Exit Yield | B4: 0.05 | C4: 0.06 | D4: 0.07 | E4: 0.08 | F4: 0.09
A5: 0.075 | B5: =(NPV(0.075,'DCF Model'!$C$20:'DCF Model'!$G$20)+('DCF Model'!$G$20/0.05)/(1+0.075)^5)/'DCF Model'!$G$21 -> 0 | C5: =(NPV(0.075,'DCF Model'!$C$20:'DCF Model'!$G$20)+('DCF Model'!$G$20/0.06)/(1+0.075)^5)/'DCF Model'!$G$21 -> 0 | D5: =(NPV(0.075,'DCF Model'!$C$20:'DCF Model'!$G$20)+('DCF Model'!$G$20/0.07)/(1+0.075)^5)/'DCF Model'!$G$21 -> 0 | E5: =(NPV(0.075,'DCF Model'!$C$20:'DCF Model'!$G$20)+('DCF Model'!$G$20/0.08)/(1+0.075)^5)/'DCF Model'!$G$21 -> 0 | F5: =(NPV(0.075,'DCF Model'!$C$20:'DCF Model'!$G$20)+('DCF Model'!$G$20/0.09)/(1+0.075)^5)/'DCF Model'!$G$21 -> 0
A6: 0.085 | B6: =(NPV(0.085,'DCF Model'!$C$20:'DCF Model'!$G$20)+('DCF Model'!$G$20/0.05)/(1+0.085)^5)/'DCF Model'!$G$21 -> 0 | C6: =(NPV(0.085,'DCF Model'!$C$20:'DCF Model'!$G$20)+('DCF Model'!$G$20/0.06)/(1+0.085)^5)/'DCF Model'!$G$21 -> 0 | D6: =(NPV(0.085,'DCF Model'!$C$20:'DCF Model'!$G$20)+('DCF Model'!$G$20/0.07)/(1+0.085)^5)/'DCF Model'!$G$21 -> 0 | E6: =(NPV(0.085,'DCF Model'!$C$20:'DCF Model'!$G$20)+('DCF Model'!$G$20/0.08)/(1+0.085)^5)/'DCF Model'!$G$21 -> 0 | F6: =(NPV(0.085,'DCF Model'!$C$20:'DCF Model'!$G$20)+('DCF Model'!$G$20/0.09)/(1+0.085)^5)/'DCF Model'!$G$21 -> 0
A7: 0.095 | B7: =(NPV(0.095,'DCF Model'!$C$20:'DCF Model'!$G$20)+('DCF Model'!$G$20/0.05)/(1+0.095)^5)/'DCF Model'!$G$21 -> 0 | C7: =(NPV(0.095,'DCF Model'!$C$20:'DCF Model'!$G$20)+('DCF Model'!$G$20/0.06)/(1+0.095)^5)/'DCF Model'!$G$21 -> 0 | D7: =(NPV(0.095,'DCF Model'!$C$20:'DCF Model'!$G$20)+('DCF Model'!$G$20/0.07)/(1+0.095)^5)/'DCF Model'!$G$21 -> 0 | E7: =(NPV(0.095,'DCF Model'!$C$20:'DCF Model'!$G$20)+('DCF Model'!$G$20/0.08)/(1+0.095)^5)/'DCF Model'!$G$21 -> 0 | F7: =(NPV(0.095,'DCF Model'!$C$20:'DCF Model'!$G$20)+('DCF Model'!$G$20/0.09)/(1+0.095)^5)/'DCF Model'!$G$21 -> 0
A8: 0.105 | B8: =(NPV(0.105,'DCF Model'!$C$20:'DCF Model'!$G$20)+('DCF Model'!$G$20/0.05)/(1+0.105)^5)/'DCF Model'!$G$21 -> 0 | C8: =(NPV(0.105,'DCF Model'!$C$20:'DCF Model'!$G$20)+('DCF Model'!$G$20/0.06)/(1+0.105)^5)/'DCF Model'!$G$21 -> 0 | D8: =(NPV(0.105,'DCF Model'!$C$20:'DCF Model'!$G$20)+('DCF Model'!$G$20/0.07)/(1+0.105)^5)/'DCF Model'!$G$21 -> 0 | E8: =(NPV(0.105,'DCF Model'!$C$20:'DCF Model'!$G$20)+('DCF Model'!$G$20/0.08)/(1+0.105)^5)/'DCF Model'!$G$21 -> 0 | F8: =(NPV(0.105,'DCF Model'!$C$20:'DCF Model'!$G$20)+('DCF Model'!$G$20/0.09)/(1+0.105)^5)/'DCF Model'!$G$21 -> 0
A9: 0.115 | B9: =(NPV(0.115,'DCF Model'!$C$20:'DCF Model'!$G$20)+('DCF Model'!$G$20/0.05)/(1+0.115)^5)/'DCF Model'!$G$21 -> 0 | C9: =(NPV(0.115,'DCF Model'!$C$20:'DCF Model'!$G$20)+('DCF Model'!$G$20/0.06)/(1+0.115)^5)/'DCF Model'!$G$21 -> 0 | D9: =(NPV(0.115,'DCF Model'!$C$20:'DCF Model'!$G$20)+('DCF Model'!$G$20/0.07)/(1+0.115)^5)/'DCF Model'!$G$21 -> 0 | E9: =(NPV(0.115,'DCF Model'!$C$20:'DCF Model'!$G$20)+('DCF Model'!$G$20/0.08)/(1+0.115)^5)/'DCF Model'!$G$21 -> 0 | F9: =(NPV(0.115,'DCF Model'!$C$20:'DCF Model'!$G$20)+('DCF Model'!$G$20/0.09)/(1+0.115)^5)/'DCF Model'!$G$21 -> 0
A11: Note: AFFO path (C20:G20) uses the base-case 1.8% growth rate fixed on the DCF Model sheet;
A12: only cost of equity (discount rate) and exit yield (terminal capitalization) vary here.

Sheet FCF Quality
A1: AFFO Quality / Reconciliation
A2: Argosy AFFO history vs reported OCF-based FCF and NPAT (illustrates why AFFO, not reported FCF/NPAT, is the DCF base)
A4: Metric | B4: FY2020 | C4: FY2021 | D4: FY2022 | E4: FY2023 | F4: FY2024 | G4: FY2025 | H4: FY2026
A5: AFFO (NZD M, company-disclosed) | B5: 51.829 | C5: 60.446 | D5: 48.332 | E5: 58.085 | F5: 58.426 | G5: 54.59 | H5: 59.117
A6: Reported NPAT (NZD M) - incl. unrealised revaluations | B6: 98.5 | C6: 183.9 | D6: 179.5 | E6: -55.9 | F6: -35.6 | G6: 80.8 | H6: 79.9
A7: Reported FCF = OCF - Capex (NZD M) | B7: -41.013 | C7: 19.553 | D7: 13.591 | E7: 12.76 | F7: 24.342 | G7: 1.545 | H7: -2.898
A9: Observation:
A10: NPAT swings on unrealised fair-value gains/losses (e.g. FY2021 +$241.7m revaluation-driven, FY2023 -$80.8m)
A11: and reported FCF is frequently negative due to development capex timing.
A12: AFFO strips these distortions and approximates sustainable, post-interest equity cash flow (~$48-60m range, FY2020-26).

Sheet Historical
A1: Historical Growth Rates
A3: Metric | B3: Value
A4: AFFO 3yr CAGR (FY23-26) | B4: 0.0059
A5: AFFO 5yr CAGR (FY21-26) | B5: -0.0444
A6: Revenue 10yr CAGR | B6: 0.0272
A7: Revenue 5yr CAGR | B7: 0.0399
A8: Revenue 3yr CAGR | B8: 0.034
A9: NTA 10yr CAGR | B9: 0.0481
A10: NTA 5yr CAGR | B10: 0.009
A12: Selected Base-Case Growth Rate: | B12: 0.018
A13: Source: | B13: management-guided qualitative build: 9.3% under-renting reversion (3.5% annualised FY2026 rent-review uplift) partially offset by higher average interest cost as green bonds refinance; AFFO has been range-bound $48-60m for 7 years with no clear compounding trend, so base case uses low-single-digit growth rather than extrapolating a raw historical CAGR

Sheet Model_Info
A1: Model Provenance & Methodology Notes
A4: Built by | B4: Claude (dcf-analyst agent), Stock Research pipeline
A5: Build date | B5: 2026-08-04
A6: Share price date/source | B6: NZ$1.045, live Yahoo Finance quote fetched 2026-08-04 (ARG.NZ)
A7: Data vintage | B7: FY2026 Annual Result (20 May 2026) is the latest filing; H1-2026 (interim, Sep 2025) also incorporated for KPI context (occupancy, WALT)
A8: Model type | B8: AFFO-capitalization / cost-of-equity REIT model, NOT a standard owner-FCF WACC-based DCF
A9: Why not a standard FCF DCF | B9: Reported NPAT is dominated by unrealised property revaluations (FY2021 +$241.7m, FY2023 -$80.8m) and reported OCF-Capex FCF is frequently negative due to development capex timing. Company-disclosed AFFO (Adjusted Funds From Operations) is used instead as it already deducts maintenance capex and leasing incentives.
A10: Discount rate choice | B10: AFFO is measured AFTER interest expense (i.e., an equity-level cash flow), so it is discounted at the REIT cost of equity (~8.5-10.5% across scenarios), not WACC. Net debt is NOT subtracted a second time from the resulting equity value — doing so would double-count leverage already embedded in AFFO.
A11: Terminal value method | B11: Exit AFFO yield capitalization (Terminal AFFO / exit yield), consistent with the stock trading at roughly 13-24x AFFO/share (NZ$0.90-1.65) over the past 10 years. No 20x FCF cap applied — the capitalization multiple range (12.5x-16.7x across scenarios) is already conservative versus the historical trading range.
A12: Cross-checks applied | B12: Base-case IV ($0.89) checked to fall between (a) a no-growth AFFO-capitalization floor (~$0.71, current AFFO/share / cost of equity) and (b) FY2026 NTA/share ($1.60) as a replacement-value ceiling proxy.
A13: Base AFFO | B13: FY2026 reported AFFO $59.117m, less negligible SBC $0.299m = $58.818m owner AFFO base (6.73 cps)
A14: Growth assumption basis | B14: AFFO has been range-bound $48-60m for 7 years (FY2020-26) with no clear compounding trend. Base case uses 1.8% p.a., informed by 9.3% portfolio under-renting (3.5% annualised FY2026 rent-review uplift) offset by refinancing cost drag, rather than extrapolating any raw historical CAGR (several of which are negative or misleadingly high due to a strong FY2021 base year).
A15: Share dilution | B15: 1.0%/yr assumed from DRP (dividend reinvestment plan); no buyback programme; historical FY2022-26 share count CAGR was ~0.79%/yr. DRP was suspended for the Q4 FY2026 dividend following divestment proceeds, but the model uses the long-run 1%/yr rate as a conservative default.
... A19: Staleness warning | B19: All figures are point-in-time as of the FY2026 annual result and the 2026-08-04 share price. Re-verify before relying on this model for a live investment decision, particularly cost-of-equity and exit-yield assumptions which are judgement calls, not disclosed figures.
