Workbook

Sheet Model_Info
A1: NZX Limited (NZX.NZ) owner-FCF DCF model - version 1.0 (fresh build, supersedes nothing)
A2: Built by the dcf-analyst agent (Claude Fable 5) on 2026-08-24 at the user's request
A4: DATA VINTAGE - these figures go stale:
A5: Price NZ$1.535 - Yahoo Finance regular NZX close Fri 2026-08-21 04:59 UTC (run Mon 2026-08-24 NZT pre-open)
A6: Balance sheet 30-Jun-2026 (H1-2026 Interim Report): TotalDebt 73,525k incl ~19,300k IFRS-16 leases, own cash 15,137k -> net debt 58,388k
A7: Share count 329,241,123 (H1-2026; diluted EPS = basic 6.5c FY2025 so dilution negligible) - held FLAT, SBC fully expensed
A8: Guidance FY2026 EBITDA pre project/restructure costs 53.0-58.5m, maintained at H1-2026 (H1 actual 27.3m)
A9: All figures NZD THOUSANDS unless stated
A11: METHODOLOGY CHOICES:
A12: Model owner-FCF DCF, 10-year component build - operating company (exchange + funds mgmt + wealth platform)
A13: Revenue basis break: H1-2026 restated revenue GROSS (+12,303k FY2025, profit lines unaffected). Model drives off
A14: EBITDA/NPAT/FCF (basis-consistent); forward revenue projects from FY2025 gross 141,251k. Never CAGR FY2024 -> FY2025 raw.
... A26: CELL LEGEND: blue = hardcoded input, yellow fill = key driver row, black = formula, green = cross-sheet link

Sheet Actuals
A1: Metric (NZD k) | B1: FY2020 | C1: FY2021 | D1: FY2022 | E1: FY2023 | F1: FY2024 | G1: FY2025 | H1: H1-2026 | I1: Source
A2: Revenue (as reported) | B2: 78426 | C2: 87955 | D2: 95726 | E2: 108387 | F2: 120122 | G2: 141251 | H2: 76647 | I2: Metrics.csv; FY2025 & H1 rows GROSS basis, FY2024 and earlier NET basis - NOT comparable
A3: Revenue FY2025 restated NET | G3: 128948 | I3: 141,251 less 12,303 gross-up (H1-2026 Note 1) - use for CAGR vs history
A4: EBITDA (statutory) | B4: 34396 | C4: 34427 | D4: 35065 | E4: 38894 | F4: 46549 | G4: 51689 | H4: 26333 | I4: Basis-consistent across restatement
A5: EBITDA normalised (pre project costs) | E5: 40100 | F5: 48500 | G5: 53500 | H5: 27300 | I5: Company disclosure
A6: Net income | B6: 17586 | C6: 15015 | D6: 14159 | E6: 13554 | F6: 25033 | G6: 21475 | H6: 9842 | I6: Unaffected by restatement
A7: Operating cash flow | B7: 31234 | C7: 27392 | D7: 23436 | E7: 34439 | F7: 35887 | G7: 39492 | H7: 9507 | I7: H1 seasonally weak (listing fees collected H2... actually H1; cash seasonal)
A8: Capex | B8: 9972 | C8: 16920 | D8: 40496 | E8: 12395 | F8: 13423 | G8: 11638 | H8: 7347 | I8: FY2022 includes ~$25m SuperLife mgmt-rights acquisition
A9: Free cash flow (reported) | B9: 21262 | C9: 10472 | D9: -17060 | E9: 22044 | F9: 22464 | G9: 27854 | H9: 2160 | I9: Lumpy - never annualise a half
A10: SBC | B10: 695 | C10: 976 | D10: 1013 | E10: 1138 | F10: 962 | G10: 998 | H10: 467 | I10: Expensed inside EBITDA; tiny
A11: Dividend per share (cents) | B11: 6.1 | C11: 6.1 | D11: 6.1 | E11: 6.1 | F11: 6.1 | G11: 6.3 | H11: 3.2 | I11: 6.1c flat FY2016-FY2024; policy 70-90% of normalised FCF
A12: Total debt (incl IFRS-16 leases) | B12: 46015 | C12: 52524 | D12: 60713 | E12: 82317 | F12: 81194 | G12: 81159 | H12: 73525 | I12: Excludes third-party/clearing balances
A13: Cash (own, unrestricted) | B13: 32775 | C13: 29062 | D13: 20611 | E13: 24670 | F13: 28825 | G13: 32055 | H13: 15137 | I13: Excludes $20m clearing risk capital + ~$24.8m third-party funds
A14: Shares outstanding (k) | B14: 278001 | C14: 280690 | D14: 314709 | E14: 324205 | F14: 327022 | G14: 328535 | H14: 329241 | I14: 2021-22 capital raises

Sheet Assumptions
A1: Globals
A2: WACC | B2: 0.095 | C2: NZD-built: rf 4.4% + 0.9x5.0% ERP + 1.25pp illiquidity -> CoE 10.15%; Kd 4.3% AT; 90/10
A3: Tax rate | B3: 0.28 | C3: NZ statutory, flat
A4: TV cap multiple (x terminal FCF) | B4: 15 | C4: Mature small single-country franchise; Gordon binds in all three scenarios
A5: WC capture (% of revenue change) | B5: 0.02 | C5: Annual listing/participant fees billed in advance - small positive
A6: Net debt (30-Jun-2026) | B6: 58388 | C6: TotalDebt 73,525 incl leases, less own cash 15,137; H1 cash a seasonal low
A7: Diluted shares (k) | B7: 329241.12 | C7: H1-2026; held flat, SBC expensed
A8: Current price (NZ$) | B8: 1.535 | C8: NZX close Fri 2026-08-21
A9: Revenue FY2025 (gross basis, k) | B9: 141251 | C9: Restated per H1-2026 Note 1
A10: Hurdle rate (entry price) | B10: 0.15 | C10: House IRR hurdle
A12: Per scenario | B12: Bear | C12: Base | D12: Bull
A13: Terminal growth | B13: 0.015 | C13: 0.0225 | D13: 0.025
A14: Probability weight | B14: 0.25 | C14: 0.5 | D14: 0.25 | E14: =SUM(B14:D14) | F14: check - must equal 1.0
A16: Bear: issuer attrition accelerates (3 delistings in 14 months already; ASX NZ-linked turnover exceeds NZX cash-market turnover); IPO pipeline stays unconverted; passive fee compression outruns Smart FUM growth (H1-2026 Smart margin fell 45.4->42.2 ex-project despite +19% revenue); restructure costs permanent. Growth fades to ~1%, statutory margin ~32.5%. A stagnation bear, not solvency.
A17: Base: FY2026 mid-guidance; growth 11% decaying to 2.25% terminal - Smart FUM rides the KiwiSaver pool (contributions 3->3.5% Apr-2026, ->4% Apr-2028) and NZXWT scales with Craigs (2027), Markets flat as delistings offset pricing/data. Statutory margin 34.5->36.0; D&A converges to capex as the amortisation bubble rolls off.
A18: Bull: KiwiSaver increases AND asset-recycling IPOs land; Smart >$20b FUM with scale margins; Craigs migration opens the $275b registry market; NZX20 futures build; new CEO executes. Margins to ~38.5% statutory, growth 13% -> 3%.

Sheet DCF_Bear
A3: Year | B3: 2025A | C3: FY2026E | D3: FY2027E | E3: FY2028E | F3: FY2029E | G3: FY2030E | H3: FY2031E | I3: FY2032E | J3: FY2033E | K3: FY2034E | L3: FY2035E
A4: Index | B4: 0 | C4: 1 | D4: 2 | E4: 3 | F4: 4 | G4: 5 | H4: 6 | I4: 7 | J4: 8 | K4: 9 | L4: 10
A5: Revenue growth YoY | C5: 0.08 | D5: 0.03 | E5: 0.02 | F5: 0.015 | G5: 0.015 | H5: 0.015 | I5: 0.0125 | J5: 0.01 | K5: 0.01 | L5: 0.01
A6: Revenue | B6: 141251 | C6: =B6*(1+C5) | D6: =C6*(1+D5) | E6: =D6*(1+E5) | F6: =E6*(1+F5) | G6: =F6*(1+G5) | H6: =G6*(1+H5) | I6: =H6*(1+I5) | J6: =I6*(1+J5) | ... L6: =K6*(1+L5)
A7: Adj EBITDA margin (pre-SBC) | C7: 0.347 | D7: 0.342 | E7: 0.338 | F7: 0.336 | G7: 0.334 | H7: 0.333 | I7: 0.332 | J7: 0.332 | K7: 0.332 | L7: 0.332
A8: Adjusted EBITDA (pre-SBC) | C8: =C6*C7 | D8: =D6*D7 | E8: =E6*E7 | F8: =F6*F7 | G8: =G6*G7 | H8: =H6*H7 | I8: =I6*I7 | J8: =J6*J7 | ... L8: =L6*L7
A9: SBC % of revenue | C9: 0.007 | D9: 0.007 | E9: 0.007 | F9: 0.007 | G9: 0.007 | H9: 0.007 | I9: 0.007 | J9: 0.007 | K9: 0.007 | L9: 0.007
A10: SBC $ (negative) | C10: =-C6*C9 | D10: =-D6*D9 | E10: =-E6*E9 | F10: =-F6*F9 | G10: =-G6*G9 | H10: =-H6*H9 | I10: =-I6*I9 | J10: =-J6*J9 | ... L10: =-L6*L9
A11: Owner EBITDA (statutory) | C11: =C8+C10 | D11: =D8+D10 | E11: =E8+E10 | F11: =F8+F10 | G11: =G8+G10 | H11: =H8+H10 | I11: =I8+I10 | J11: =J8+J10 | ... L11: =L8+L10
A12: D&A % of revenue | C12: 0.134 | D12: 0.13 | E12: 0.124 | F12: 0.118 | G12: 0.112 | H12: 0.106 | I12: 0.102 | J12: 0.098 | K12: 0.095 | L12: 0.092
A13: D&A $ (negative) | C13: =-C6*C12 | D13: =-D6*D12 | E13: =-E6*E12 | F13: =-F6*F12 | G13: =-G6*G12 | H13: =-H6*H12 | I13: =-I6*I12 | J13: =-J6*J12 | ... L13: =-L6*L12
A14: EBIT | C14: =C11+C13 | D14: =D11+D13 | E14: =E11+E13 | F14: =F11+F13 | G14: =G11+G13 | H14: =H11+H13 | I14: =I11+I13 | J14: =J11+J13 | ... L14: =L11+L13
A15: Cash tax rate | C15: 0.28 | D15: 0.28 | E15: 0.28 | F15: 0.28 | G15: 0.28 | H15: 0.28 | I15: 0.28 | J15: 0.28 | K15: 0.28 | L15: 0.28
A16: NOPAT | C16: =C14*(1-C15) | D16: =D14*(1-D15) | E16: =E14*(1-E15) | F16: =F14*(1-F15) | G16: =G14*(1-G15) | H16: =H14*(1-H15) | I16: =I14*(1-I15) | J16: =J14*(1-J15) | ... L16: =L14*(1-L15)
A17: add back D&A | C17: =-C13 | D17: =-D13 | E17: =-E13 | F17: =-F13 | G17: =-G13 | H17: =-H13 | I17: =-I13 | J17: =-J13 | ... L17: =-L13
A18: Capex % of revenue (incl lease renewal) | C18: 0.096 | D18: 0.096 | E18: 0.095 | F18: 0.095 | G18: 0.094 | H18: 0.094 | I18: 0.093 | J18: 0.093 | K18: 0.092 | L18: 0.092
A19: Capex $ (negative) | C19: =-C6*C18 | D19: =-D6*D18 | E19: =-E6*E18 | F19: =-F6*F18 | G19: =-G6*G18 | H19: =-H6*H18 | I19: =-I6*I18 | J19: =-J6*J18 | ... L19: =-L6*L18
A20: Working capital | C20: =Assumptions!$B$5*(C6-B6) | D20: =Assumptions!$B$5*(D6-C6) | E20: =Assumptions!$B$5*(E6-D6) | F20: =Assumptions!$B$5*(F6-E6) | G20: =Assumptions!$B$5*(G6-F6) | H20: =Assumptions!$B$5*(H6-G6) | I20: =Assumptions!$B$5*(I6-H6) | J20: =Assumptions!$B$5*(J6-I6) | ... L20: =Assumptions!$B$5*(L6-K6)
A21: Unlevered owner FCF | C21: =C16+C17+C19+C20 | D21: =D16+D17+D19+D20 | E21: =E16+E17+E19+E20 | F21: =F16+F17+F19+F20 | G21: =G16+G17+G19+G20 | H21: =H16+H17+H19+H20 | I21: =I16+I17+I19+I20 | J21: =J16+J17+J19+J20 | ... L21: =L16+L17+L19+L20
A22: Discount factor | C22: =1/(1+Assumptions!$B$2)^C4 | D22: =1/(1+Assumptions!$B$2)^D4 | E22: =1/(1+Assumptions!$B$2)^E4 | F22: =1/(1+Assumptions!$B$2)^F4 | G22: =1/(1+Assumptions!$B$2)^G4 | H22: =1/(1+Assumptions!$B$2)^H4 | I22: =1/(1+Assumptions!$B$2)^I4 | J22: =1/(1+Assumptions!$B$2)^J4 | ... L22: =1/(1+Assumptions!$B$2)^L4
A23: PV of FCF | C23: =C21*C22 | D23: =D21*D22 | E23: =E21*E22 | F23: =F21*F22 | G23: =G21*G22 | H23: =H21*H22 | I23: =I21*I22 | J23: =J21*J22 | ... L23: =L21*L22
A24: Memo: FCF before SBC (street-style) | C24: =C21-C10 | D24: =D21-D10 | E24: =E21-E10 | F24: =F21-F10 | G24: =G21-G10 | H24: =H21-H10 | I24: =I21-I10 | J24: =J21-J10 | ... L24: =L21-L10
A25: Memo: implied owner-FCF margin | C25: =C21/C6 | D25: =D21/D6 | E25: =E21/E6 | F25: =F21/F6 | G25: =G21/G6 | H25: =H21/H6 | I25: =I21/I6 | J25: =J21/J6 | ... L25: =L21/L6
A26: Sum PV of FCF | B26: =SUM(C23:L23)
A27: Terminal growth | B27: =Assumptions!$B$13
A28: Terminal FCF | B28: =L21*(1+B27)
A29: Gordon TV | B29: =B28/(Assumptions!$B$2-B27)
A30: Cap TV | B30: =Assumptions!$B$4*L21
A31: TV used | B31: =MAX(0,MIN(B29,B30))
A32: Implied exit multiple | B32: =B31/L21
A33: PV of TV | B33: =B31*L22
A34: Enterprise value | B34: =B26+B33
A35: less net debt | B35: =-Assumptions!$B$6
A36: Equity value | B36: =B34+B35
A37: Diluted shares (k) | B37: =Assumptions!$B$7
A38: Value per share (NZ$) | B38: =B36/B37
A39: Upside vs price | B39: =B38/Assumptions!$B$8-1
A41: Street: PV of explicit SBC | B41: =SUMPRODUCT(-C10:L10,C22:L22)
A42: Street: PV of terminal SBC | B42: =(-L10*(1+B27)/(Assumptions!$B$2-B27))*L22
A43: Street value per share | B43: =(B36+B41+B42)/B37

Sheet DCF_Base
A3: Year | B3: 2025A | C3: FY2026E | D3: FY2027E | E3: FY2028E | F3: FY2029E | G3: FY2030E | H3: FY2031E | I3: FY2032E | J3: FY2033E | K3: FY2034E | L3: FY2035E
A4: Index | B4: 0 | C4: 1 | D4: 2 | E4: 3 | F4: 4 | G4: 5 | H4: 6 | I4: 7 | J4: 8 | K4: 9 | L4: 10
A5: Revenue growth YoY | C5: 0.11 | D5: 0.07 | E5: 0.06 | F5: 0.05 | G5: 0.045 | H5: 0.04 | I5: 0.035 | J5: 0.03 | K5: 0.025 | L5: 0.0225
A6: Revenue | B6: 141251 | C6: =B6*(1+C5) | D6: =C6*(1+D5) | E6: =D6*(1+E5) | F6: =E6*(1+F5) | G6: =F6*(1+G5) | H6: =G6*(1+H5) | I6: =H6*(1+I5) | J6: =I6*(1+J5) | ... L6: =K6*(1+L5)
A7: Adj EBITDA margin (pre-SBC) | C7: 0.352 | D7: 0.354 | E7: 0.356 | F7: 0.358 | G7: 0.36 | H7: 0.362 | I7: 0.363 | J7: 0.365 | K7: 0.366 | L7: 0.367
A8: Adjusted EBITDA (pre-SBC) | C8: =C6*C7 | D8: =D6*D7 | E8: =E6*E7 | F8: =F6*F7 | G8: =G6*G7 | H8: =H6*H7 | I8: =I6*I7 | J8: =J6*J7 | ... L8: =L6*L7
A9: SBC % of revenue | C9: 0.007 | D9: 0.007 | E9: 0.007 | F9: 0.007 | G9: 0.007 | H9: 0.007 | I9: 0.007 | J9: 0.007 | K9: 0.007 | L9: 0.007
A10: SBC $ (negative) | C10: =-C6*C9 | D10: =-D6*D9 | E10: =-E6*E9 | F10: =-F6*F9 | G10: =-G6*G9 | H10: =-H6*H9 | I10: =-I6*I9 | J10: =-J6*J9 | ... L10: =-L6*L9
A11: Owner EBITDA (statutory) | C11: =C8+C10 | D11: =D8+D10 | E11: =E8+E10 | F11: =F8+F10 | G11: =G8+G10 | H11: =H8+H10 | I11: =I8+I10 | J11: =J8+J10 | ... L11: =L8+L10
A12: D&A % of revenue | C12: 0.134 | D12: 0.13 | E12: 0.124 | F12: 0.118 | G12: 0.112 | H12: 0.106 | I12: 0.102 | J12: 0.098 | K12: 0.095 | L12: 0.092
A13: D&A $ (negative) | C13: =-C6*C12 | D13: =-D6*D12 | E13: =-E6*E12 | F13: =-F6*F12 | G13: =-G6*G12 | H13: =-H6*H12 | I13: =-I6*I12 | J13: =-J6*J12 | ... L13: =-L6*L12
A14: EBIT | C14: =C11+C13 | D14: =D11+D13 | E14: =E11+E13 | F14: =F11+F13 | G14: =G11+G13 | H14: =H11+H13 | I14: =I11+I13 | J14: =J11+J13 | ... L14: =L11+L13
A15: Cash tax rate | C15: 0.28 | D15: 0.28 | E15: 0.28 | F15: 0.28 | G15: 0.28 | H15: 0.28 | I15: 0.28 | J15: 0.28 | K15: 0.28 | L15: 0.28
A16: NOPAT | C16: =C14*(1-C15) | D16: =D14*(1-D15) | E16: =E14*(1-E15) | F16: =F14*(1-F15) | G16: =G14*(1-G15) | H16: =H14*(1-H15) | I16: =I14*(1-I15) | J16: =J14*(1-J15) | ... L16: =L14*(1-L15)
A17: add back D&A | C17: =-C13 | D17: =-D13 | E17: =-E13 | F17: =-F13 | G17: =-G13 | H17: =-H13 | I17: =-I13 | J17: =-J13 | ... L17: =-L13
A18: Capex % of revenue (incl lease renewal) | C18: 0.096 | D18: 0.096 | E18: 0.095 | F18: 0.095 | G18: 0.094 | H18: 0.094 | I18: 0.093 | J18: 0.093 | K18: 0.092 | L18: 0.092
A19: Capex $ (negative) | C19: =-C6*C18 | D19: =-D6*D18 | E19: =-E6*E18 | F19: =-F6*F18 | G19: =-G6*G18 | H19: =-H6*H18 | I19: =-I6*I18 | J19: =-J6*J18 | ... L19: =-L6*L18
A20: Working capital | C20: =Assumptions!$B$5*(C6-B6) | D20: =Assumptions!$B$5*(D6-C6) | E20: =Assumptions!$B$5*(E6-D6) | F20: =Assumptions!$B$5*(F6-E6) | G20: =Assumptions!$B$5*(G6-F6) | H20: =Assumptions!$B$5*(H6-G6) | I20: =Assumptions!$B$5*(I6-H6) | J20: =Assumptions!$B$5*(J6-I6) | ... L20: =Assumptions!$B$5*(L6-K6)
A21: Unlevered owner FCF | C21: =C16+C17+C19+C20 | D21: =D16+D17+D19+D20 | E21: =E16+E17+E19+E20 | F21: =F16+F17+F19+F20 | G21: =G16+G17+G19+G20 | H21: =H16+H17+H19+H20 | I21: =I16+I17+I19+I20 | J21: =J16+J17+J19+J20 | ... L21: =L16+L17+L19+L20
A22: Discount factor | C22: =1/(1+Assumptions!$B$2)^C4 | D22: =1/(1+Assumptions!$B$2)^D4 | E22: =1/(1+Assumptions!$B$2)^E4 | F22: =1/(1+Assumptions!$B$2)^F4 | G22: =1/(1+Assumptions!$B$2)^G4 | H22: =1/(1+Assumptions!$B$2)^H4 | I22: =1/(1+Assumptions!$B$2)^I4 | J22: =1/(1+Assumptions!$B$2)^J4 | ... L22: =1/(1+Assumptions!$B$2)^L4
A23: PV of FCF | C23: =C21*C22 | D23: =D21*D22 | E23: =E21*E22 | F23: =F21*F22 | G23: =G21*G22 | H23: =H21*H22 | I23: =I21*I22 | J23: =J21*J22 | ... L23: =L21*L22
A24: Memo: FCF before SBC (street-style) | C24: =C21-C10 | D24: =D21-D10 | E24: =E21-E10 | F24: =F21-F10 | G24: =G21-G10 | H24: =H21-H10 | I24: =I21-I10 | J24: =J21-J10 | ... L24: =L21-L10
A25: Memo: implied owner-FCF margin | C25: =C21/C6 | D25: =D21/D6 | E25: =E21/E6 | F25: =F21/F6 | G25: =G21/G6 | H25: =H21/H6 | I25: =I21/I6 | J25: =J21/J6 | ... L25: =L21/L6
A26: Sum PV of FCF | B26: =SUM(C23:L23)
A27: Terminal growth | B27: =Assumptions!$C$13
A28: Terminal FCF | B28: =L21*(1+B27)
A29: Gordon TV | B29: =B28/(Assumptions!$B$2-B27)
A30: Cap TV | B30: =Assumptions!$B$4*L21
A31: TV used | B31: =MAX(0,MIN(B29,B30))
A32: Implied exit multiple | B32: =B31/L21
A33: PV of TV | B33: =B31*L22
A34: Enterprise value | B34: =B26+B33
A35: less net debt | B35: =-Assumptions!$B$6
A36: Equity value | B36: =B34+B35
A37: Diluted shares (k) | B37: =Assumptions!$B$7
A38: Value per share (NZ$) | B38: =B36/B37
A39: Upside vs price | B39: =B38/Assumptions!$B$8-1
A41: Street: PV of explicit SBC | B41: =SUMPRODUCT(-C10:L10,C22:L22)
A42: Street: PV of terminal SBC | B42: =(-L10*(1+B27)/(Assumptions!$B$2-B27))*L22
A43: Street value per share | B43: =(B36+B41+B42)/B37

Sheet DCF_Bull
A3: Year | B3: 2025A | C3: FY2026E | D3: FY2027E | E3: FY2028E | F3: FY2029E | G3: FY2030E | H3: FY2031E | I3: FY2032E | J3: FY2033E | K3: FY2034E | L3: FY2035E
A4: Index | B4: 0 | C4: 1 | D4: 2 | E4: 3 | F4: 4 | G4: 5 | H4: 6 | I4: 7 | J4: 8 | K4: 9 | L4: 10
A5: Revenue growth YoY | C5: 0.13 | D5: 0.1 | E5: 0.09 | F5: 0.08 | G5: 0.07 | H5: 0.06 | I5: 0.05 | J5: 0.04 | K5: 0.035 | L5: 0.03
A6: Revenue | B6: 141251 | C6: =B6*(1+C5) | D6: =C6*(1+D5) | E6: =D6*(1+E5) | F6: =E6*(1+F5) | G6: =F6*(1+G5) | H6: =G6*(1+H5) | I6: =H6*(1+I5) | J6: =I6*(1+J5) | ... L6: =K6*(1+L5)
A7: Adj EBITDA margin (pre-SBC) | C7: 0.357 | D7: 0.362 | E7: 0.367 | F7: 0.372 | G7: 0.377 | H7: 0.382 | I7: 0.386 | J7: 0.389 | K7: 0.391 | L7: 0.392
A8: Adjusted EBITDA (pre-SBC) | C8: =C6*C7 | D8: =D6*D7 | E8: =E6*E7 | F8: =F6*F7 | G8: =G6*G7 | H8: =H6*H7 | I8: =I6*I7 | J8: =J6*J7 | ... L8: =L6*L7
A9: SBC % of revenue | C9: 0.007 | D9: 0.007 | E9: 0.007 | F9: 0.007 | G9: 0.007 | H9: 0.007 | I9: 0.007 | J9: 0.007 | K9: 0.007 | L9: 0.007
A10: SBC $ (negative) | C10: =-C6*C9 | D10: =-D6*D9 | E10: =-E6*E9 | F10: =-F6*F9 | G10: =-G6*G9 | H10: =-H6*H9 | I10: =-I6*I9 | J10: =-J6*J9 | ... L10: =-L6*L9
A11: Owner EBITDA (statutory) | C11: =C8+C10 | D11: =D8+D10 | E11: =E8+E10 | F11: =F8+F10 | G11: =G8+G10 | H11: =H8+H10 | I11: =I8+I10 | J11: =J8+J10 | ... L11: =L8+L10
A12: D&A % of revenue | C12: 0.134 | D12: 0.13 | E12: 0.124 | F12: 0.118 | G12: 0.112 | H12: 0.106 | I12: 0.102 | J12: 0.098 | K12: 0.095 | L12: 0.092
A13: D&A $ (negative) | C13: =-C6*C12 | D13: =-D6*D12 | E13: =-E6*E12 | F13: =-F6*F12 | G13: =-G6*G12 | H13: =-H6*H12 | I13: =-I6*I12 | J13: =-J6*J12 | ... L13: =-L6*L12
A14: EBIT | C14: =C11+C13 | D14: =D11+D13 | E14: =E11+E13 | F14: =F11+F13 | G14: =G11+G13 | H14: =H11+H13 | I14: =I11+I13 | J14: =J11+J13 | ... L14: =L11+L13
A15: Cash tax rate | C15: 0.28 | D15: 0.28 | E15: 0.28 | F15: 0.28 | G15: 0.28 | H15: 0.28 | I15: 0.28 | J15: 0.28 | K15: 0.28 | L15: 0.28
A16: NOPAT | C16: =C14*(1-C15) | D16: =D14*(1-D15) | E16: =E14*(1-E15) | F16: =F14*(1-F15) | G16: =G14*(1-G15) | H16: =H14*(1-H15) | I16: =I14*(1-I15) | J16: =J14*(1-J15) | ... L16: =L14*(1-L15)
A17: add back D&A | C17: =-C13 | D17: =-D13 | E17: =-E13 | F17: =-F13 | G17: =-G13 | H17: =-H13 | I17: =-I13 | J17: =-J13 | ... L17: =-L13
A18: Capex % of revenue (incl lease renewal) | C18: 0.096 | D18: 0.096 | E18: 0.095 | F18: 0.095 | G18: 0.094 | H18: 0.094 | I18: 0.093 | J18: 0.093 | K18: 0.092 | L18: 0.092
A19: Capex $ (negative) | C19: =-C6*C18 | D19: =-D6*D18 | E19: =-E6*E18 | F19: =-F6*F18 | G19: =-G6*G18 | H19: =-H6*H18 | I19: =-I6*I18 | J19: =-J6*J18 | ... L19: =-L6*L18
A20: Working capital | C20: =Assumptions!$B$5*(C6-B6) | D20: =Assumptions!$B$5*(D6-C6) | E20: =Assumptions!$B$5*(E6-D6) | F20: =Assumptions!$B$5*(F6-E6) | G20: =Assumptions!$B$5*(G6-F6) | H20: =Assumptions!$B$5*(H6-G6) | I20: =Assumptions!$B$5*(I6-H6) | J20: =Assumptions!$B$5*(J6-I6) | ... L20: =Assumptions!$B$5*(L6-K6)
A21: Unlevered owner FCF | C21: =C16+C17+C19+C20 | D21: =D16+D17+D19+D20 | E21: =E16+E17+E19+E20 | F21: =F16+F17+F19+F20 | G21: =G16+G17+G19+G20 | H21: =H16+H17+H19+H20 | I21: =I16+I17+I19+I20 | J21: =J16+J17+J19+J20 | ... L21: =L16+L17+L19+L20
A22: Discount factor | C22: =1/(1+Assumptions!$B$2)^C4 | D22: =1/(1+Assumptions!$B$2)^D4 | E22: =1/(1+Assumptions!$B$2)^E4 | F22: =1/(1+Assumptions!$B$2)^F4 | G22: =1/(1+Assumptions!$B$2)^G4 | H22: =1/(1+Assumptions!$B$2)^H4 | I22: =1/(1+Assumptions!$B$2)^I4 | J22: =1/(1+Assumptions!$B$2)^J4 | ... L22: =1/(1+Assumptions!$B$2)^L4
A23: PV of FCF | C23: =C21*C22 | D23: =D21*D22 | E23: =E21*E22 | F23: =F21*F22 | G23: =G21*G22 | H23: =H21*H22 | I23: =I21*I22 | J23: =J21*J22 | ... L23: =L21*L22
A24: Memo: FCF before SBC (street-style) | C24: =C21-C10 | D24: =D21-D10 | E24: =E21-E10 | F24: =F21-F10 | G24: =G21-G10 | H24: =H21-H10 | I24: =I21-I10 | J24: =J21-J10 | ... L24: =L21-L10
A25: Memo: implied owner-FCF margin | C25: =C21/C6 | D25: =D21/D6 | E25: =E21/E6 | F25: =F21/F6 | G25: =G21/G6 | H25: =H21/H6 | I25: =I21/I6 | J25: =J21/J6 | ... L25: =L21/L6
A26: Sum PV of FCF | B26: =SUM(C23:L23)
A27: Terminal growth | B27: =Assumptions!$D$13
A28: Terminal FCF | B28: =L21*(1+B27)
A29: Gordon TV | B29: =B28/(Assumptions!$B$2-B27)
A30: Cap TV | B30: =Assumptions!$B$4*L21
A31: TV used | B31: =MAX(0,MIN(B29,B30))
A32: Implied exit multiple | B32: =B31/L21
A33: PV of TV | B33: =B31*L22
A34: Enterprise value | B34: =B26+B33
A35: less net debt | B35: =-Assumptions!$B$6
A36: Equity value | B36: =B34+B35
A37: Diluted shares (k) | B37: =Assumptions!$B$7
A38: Value per share (NZ$) | B38: =B36/B37
A39: Upside vs price | B39: =B38/Assumptions!$B$8-1
A41: Street: PV of explicit SBC | B41: =SUMPRODUCT(-C10:L10,C22:L22)
A42: Street: PV of terminal SBC | B42: =(-L10*(1+B27)/(Assumptions!$B$2-B27))*L22
A43: Street value per share | B43: =(B36+B41+B42)/B37

Sheet FCF_Quality
A1: Reported FCF to owner FCF (NZD k)
B2: FY2020 | C2: FY2021 | D2: FY2022 | E2: FY2023 | F2: FY2024 | G2: FY2025
A3: Free cash flow (OCF - capex, company definition) | B3: 21262 | C3: 10472 | D3: -17060 | E3: 22044 | F3: 22464 | G3: 27854
A4: less: SBC (expensed in EBITDA; deducted here for the owner series) | B4: -695 | C4: -976 | D4: -1013 | E4: -1138 | F4: -962 | G4: -998
A5: less: interest income (n/a - net-debt company) | B5: 0 | C5: 0 | D5: 0 | E5: 0 | F5: 0 | G5: 0
A6: Owner FCF | B6: =SUM(B3:B5) | C6: =SUM(C3:C5) | D6: =SUM(D3:D5) | E6: =SUM(E3:E5) | F6: =SUM(F3:F5) | G6: =SUM(G3:G5)
A8: Memo: FY2022 capex 40,496k includes the ~$25m SuperLife management-rights acquisition (term-loan funded) - the FCF trough is deal-driven, not operational.
A9: Memo: reported FCF is LEVERED (OCF includes ~3.4m net finance costs); the DCF tabs build UNLEVERED FCF - FY2025 unlevered equivalent ~30.3m ties to the Y1 component build of ~30.1m.
A10: Memo: D&A 18,989k vs cash capex 11,638k in FY2025 - the NZXWT amortisation bubble; model converges D&A% to capex% by Y10 so the temporary tax shield is not perpetuated.
A11: Memo: mid-cycle normalised unlevered owner FCF ~29,500k = (norm EBITDA 53,500 - SBC 1,000 - capex incl lease renewal 13,600) x 0.72 + ~1,500 amortisation timing.

Sheet Valuation
A1: Scenario summary
B2: Bear | C2: Base | D2: Bull
A3: Value per share (NZ$) | B3: =DCF_Bear!$B$38 | C3: =DCF_Base!$B$38 | D3: =DCF_Bull!$B$38
A4: Upside vs price | B4: =DCF_Bear!$B$39 | C4: =DCF_Base!$B$39 | D4: =DCF_Bull!$B$39
A5: Probability | B5: =Assumptions!B$14 | C5: =Assumptions!C$14 | D5: =Assumptions!D$14
A6: Street value per share | B6: =DCF_Bear!$B$43 | C6: =DCF_Base!$B$43 | D6: =DCF_Bull!$B$43
A8: Probability-weighted value (NZ$) | B8: =SUMPRODUCT(B3:D3,B5:D5)
A9: Margin of safety at current price | B9: =1-Assumptions!$B$8/B8
A10: Street weighted value | B10: =SUMPRODUCT(B6:D6,B5:D5)
A11: Band position | B11: null - house/street band ~5c wide (SBC 0.7% of revenue), narrower than estimation error
A13: Required-return table (base case)
A14: Required return | B14: 0.09 | C14: 0.095 | D14: 0.1 | E14: 0.11 | F14: 0.12 | G14: 0.15
A15: Value per share (NZ$) | B15: =(SUMPRODUCT(DCF_Base!$C$21:$L$21/(1+B14)^DCF_Base!$C$4:$L$4)+DCF_Base!$B$31/(1+B14)^10-Assumptions!$B$6)/Assumptions!$B$7 | C15: =(SUMPRODUCT(DCF_Base!$C$21:$L$21/(1+C14)^DCF_Base!$C$4:$L$4)+DCF_Base!$B$31/(1+C14)^10-Assumptions!$B$6)/Assumptions!$B$7 | D15: =(SUMPRODUCT(DCF_Base!$C$21:$L$21/(1+D14)^DCF_Base!$C$4:$L$4)+DCF_Base!$B$31/(1+D14)^10-Assumptions!$B$6)/Assumptions!$B$7 | E15: =(SUMPRODUCT(DCF_Base!$C$21:$L$21/(1+E14)^DCF_Base!$C$4:$L$4)+DCF_Base!$B$31/(1+E14)^10-Assumptions!$B$6)/Assumptions!$B$7 | F15: =(SUMPRODUCT(DCF_Base!$C$21:$L$21/(1+F14)^DCF_Base!$C$4:$L$4)+DCF_Base!$B$31/(1+F14)^10-Assumptions!$B$6)/Assumptions!$B$7 | G15: =(SUMPRODUCT(DCF_Base!$C$21:$L$21/(1+G14)^DCF_Base!$C$4:$L$4)+DCF_Base!$B$31/(1+G14)^10-Assumptions!$B$6)/Assumptions!$B$7
A16: Note: 9.5% column is the model WACC; price NZ$1.535 exceeds even the 9% value - market accepts ~8.3% on base flows
A18: Entry prices at 15% hurdle
B19: Bear | C19: Base | D19: Bull
A20: Entry price (NZ$) | B20: =(SUMPRODUCT(DCF_Bear!$C$21:$L$21/(1+Assumptions!$B$10)^DCF_Bear!$C$4:$L$4)+DCF_Bear!$B$31/(1+Assumptions!$B$10)^10-Assumptions!$B$6)/Assumptions!$B$7 | C20: =(SUMPRODUCT(DCF_Base!$C$21:$L$21/(1+Assumptions!$B$10)^DCF_Base!$C$4:$L$4)+DCF_Base!$B$31/(1+Assumptions!$B$10)^10-Assumptions!$B$6)/Assumptions!$B$7 | D20: =(SUMPRODUCT(DCF_Bull!$C$21:$L$21/(1+Assumptions!$B$10)^DCF_Bull!$C$4:$L$4)+DCF_Bull!$B$31/(1+Assumptions!$B$10)^10-Assumptions!$B$6)/Assumptions!$B$7
A21: Weighted entry (buy-below) price | B21: =SUMPRODUCT(B20:D20,B5:D5)
A23: Sensitivity: WACC (rows) x terminal growth (cols), base case, NZ$/share
B24: 0.0125 | C24: 0.0175 | D24: 0.0225 | E24: 0.0275 | F24: 0.0325
A25: 0.075 | B25: =IF($A25>B$24,(SUMPRODUCT(DCF_Base!$C$21:$L$21/(1+$A25)^DCF_Base!$C$4:$L$4)+MAX(0,MIN(DCF_Base!$L$21*(1+B$24)/($A25-B$24),Assumptions!$B$4*DCF_Base!$L$21))/(1+$A25)^10-Assumptions!$B$6)/Assumptions!$B$7,"n/a") | C25: =IF($A25>C$24,(SUMPRODUCT(DCF_Base!$C$21:$L$21/(1+$A25)^DCF_Base!$C$4:$L$4)+MAX(0,MIN(DCF_Base!$L$21*(1+C$24)/($A25-C$24),Assumptions!$B$4*DCF_Base!$L$21))/(1+$A25)^10-Assumptions!$B$6)/Assumptions!$B$7,"n/a") | D25: =IF($A25>D$24,(SUMPRODUCT(DCF_Base!$C$21:$L$21/(1+$A25)^DCF_Base!$C$4:$L$4)+MAX(0,MIN(DCF_Base!$L$21*(1+D$24)/($A25-D$24),Assumptions!$B$4*DCF_Base!$L$21))/(1+$A25)^10-Assumptions!$B$6)/Assumptions!$B$7,"n/a") | E25: =IF($A25>E$24,(SUMPRODUCT(DCF_Base!$C$21:$L$21/(1+$A25)^DCF_Base!$C$4:$L$4)+MAX(0,MIN(DCF_Base!$L$21*(1+E$24)/($A25-E$24),Assumptions!$B$4*DCF_Base!$L$21))/(1+$A25)^10-Assumptions!$B$6)/Assumptions!$B$7,"n/a") | F25: =IF($A25>F$24,(SUMPRODUCT(DCF_Base!$C$21:$L$21/(1+$A25)^DCF_Base!$C$4:$L$4)+MAX(0,MIN(DCF_Base!$L$21*(1+F$24)/($A25-F$24),Assumptions!$B$4*DCF_Base!$L$21))/(1+$A25)^10-Assumptions!$B$6)/Assumptions!$B$7,"n/a")
A26: 0.085 | B26: =IF($A26>B$24,(SUMPRODUCT(DCF_Base!$C$21:$L$21/(1+$A26)^DCF_Base!$C$4:$L$4)+MAX(0,MIN(DCF_Base!$L$21*(1+B$24)/($A26-B$24),Assumptions!$B$4*DCF_Base!$L$21))/(1+$A26)^10-Assumptions!$B$6)/Assumptions!$B$7,"n/a") | C26: =IF($A26>C$24,(SUMPRODUCT(DCF_Base!$C$21:$L$21/(1+$A26)^DCF_Base!$C$4:$L$4)+MAX(0,MIN(DCF_Base!$L$21*(1+C$24)/($A26-C$24),Assumptions!$B$4*DCF_Base!$L$21))/(1+$A26)^10-Assumptions!$B$6)/Assumptions!$B$7,"n/a") | D26: =IF($A26>D$24,(SUMPRODUCT(DCF_Base!$C$21:$L$21/(1+$A26)^DCF_Base!$C$4:$L$4)+MAX(0,MIN(DCF_Base!$L$21*(1+D$24)/($A26-D$24),Assumptions!$B$4*DCF_Base!$L$21))/(1+$A26)^10-Assumptions!$B$6)/Assumptions!$B$7,"n/a") | E26: =IF($A26>E$24,(SUMPRODUCT(DCF_Base!$C$21:$L$21/(1+$A26)^DCF_Base!$C$4:$L$4)+MAX(0,MIN(DCF_Base!$L$21*(1+E$24)/($A26-E$24),Assumptions!$B$4*DCF_Base!$L$21))/(1+$A26)^10-Assumptions!$B$6)/Assumptions!$B$7,"n/a") | F26: =IF($A26>F$24,(SUMPRODUCT(DCF_Base!$C$21:$L$21/(1+$A26)^DCF_Base!$C$4:$L$4)+MAX(0,MIN(DCF_Base!$L$21*(1+F$24)/($A26-F$24),Assumptions!$B$4*DCF_Base!$L$21))/(1+$A26)^10-Assumptions!$B$6)/Assumptions!$B$7,"n/a")
A27: 0.095 | B27: =IF($A27>B$24,(SUMPRODUCT(DCF_Base!$C$21:$L$21/(1+$A27)^DCF_Base!$C$4:$L$4)+MAX(0,MIN(DCF_Base!$L$21*(1+B$24)/($A27-B$24),Assumptions!$B$4*DCF_Base!$L$21))/(1+$A27)^10-Assumptions!$B$6)/Assumptions!$B$7,"n/a") | C27: =IF($A27>C$24,(SUMPRODUCT(DCF_Base!$C$21:$L$21/(1+$A27)^DCF_Base!$C$4:$L$4)+MAX(0,MIN(DCF_Base!$L$21*(1+C$24)/($A27-C$24),Assumptions!$B$4*DCF_Base!$L$21))/(1+$A27)^10-Assumptions!$B$6)/Assumptions!$B$7,"n/a") | D27: =IF($A27>D$24,(SUMPRODUCT(DCF_Base!$C$21:$L$21/(1+$A27)^DCF_Base!$C$4:$L$4)+MAX(0,MIN(DCF_Base!$L$21*(1+D$24)/($A27-D$24),Assumptions!$B$4*DCF_Base!$L$21))/(1+$A27)^10-Assumptions!$B$6)/Assumptions!$B$7,"n/a") | E27: =IF($A27>E$24,(SUMPRODUCT(DCF_Base!$C$21:$L$21/(1+$A27)^DCF_Base!$C$4:$L$4)+MAX(0,MIN(DCF_Base!$L$21*(1+E$24)/($A27-E$24),Assumptions!$B$4*DCF_Base!$L$21))/(1+$A27)^10-Assumptions!$B$6)/Assumptions!$B$7,"n/a") | F27: =IF($A27>F$24,(SUMPRODUCT(DCF_Base!$C$21:$L$21/(1+$A27)^DCF_Base!$C$4:$L$4)+MAX(0,MIN(DCF_Base!$L$21*(1+F$24)/($A27-F$24),Assumptions!$B$4*DCF_Base!$L$21))/(1+$A27)^10-Assumptions!$B$6)/Assumptions!$B$7,"n/a")
A28: 0.105 | B28: =IF($A28>B$24,(SUMPRODUCT(DCF_Base!$C$21:$L$21/(1+$A28)^DCF_Base!$C$4:$L$4)+MAX(0,MIN(DCF_Base!$L$21*(1+B$24)/($A28-B$24),Assumptions!$B$4*DCF_Base!$L$21))/(1+$A28)^10-Assumptions!$B$6)/Assumptions!$B$7,"n/a") | C28: =IF($A28>C$24,(SUMPRODUCT(DCF_Base!$C$21:$L$21/(1+$A28)^DCF_Base!$C$4:$L$4)+MAX(0,MIN(DCF_Base!$L$21*(1+C$24)/($A28-C$24),Assumptions!$B$4*DCF_Base!$L$21))/(1+$A28)^10-Assumptions!$B$6)/Assumptions!$B$7,"n/a") | D28: =IF($A28>D$24,(SUMPRODUCT(DCF_Base!$C$21:$L$21/(1+$A28)^DCF_Base!$C$4:$L$4)+MAX(0,MIN(DCF_Base!$L$21*(1+D$24)/($A28-D$24),Assumptions!$B$4*DCF_Base!$L$21))/(1+$A28)^10-Assumptions!$B$6)/Assumptions!$B$7,"n/a") | E28: =IF($A28>E$24,(SUMPRODUCT(DCF_Base!$C$21:$L$21/(1+$A28)^DCF_Base!$C$4:$L$4)+MAX(0,MIN(DCF_Base!$L$21*(1+E$24)/($A28-E$24),Assumptions!$B$4*DCF_Base!$L$21))/(1+$A28)^10-Assumptions!$B$6)/Assumptions!$B$7,"n/a") | F28: =IF($A28>F$24,(SUMPRODUCT(DCF_Base!$C$21:$L$21/(1+$A28)^DCF_Base!$C$4:$L$4)+MAX(0,MIN(DCF_Base!$L$21*(1+F$24)/($A28-F$24),Assumptions!$B$4*DCF_Base!$L$21))/(1+$A28)^10-Assumptions!$B$6)/Assumptions!$B$7,"n/a")
A29: 0.115 | B29: =IF($A29>B$24,(SUMPRODUCT(DCF_Base!$C$21:$L$21/(1+$A29)^DCF_Base!$C$4:$L$4)+MAX(0,MIN(DCF_Base!$L$21*(1+B$24)/($A29-B$24),Assumptions!$B$4*DCF_Base!$L$21))/(1+$A29)^10-Assumptions!$B$6)/Assumptions!$B$7,"n/a") | C29: =IF($A29>C$24,(SUMPRODUCT(DCF_Base!$C$21:$L$21/(1+$A29)^DCF_Base!$C$4:$L$4)+MAX(0,MIN(DCF_Base!$L$21*(1+C$24)/($A29-C$24),Assumptions!$B$4*DCF_Base!$L$21))/(1+$A29)^10-Assumptions!$B$6)/Assumptions!$B$7,"n/a") | D29: =IF($A29>D$24,(SUMPRODUCT(DCF_Base!$C$21:$L$21/(1+$A29)^DCF_Base!$C$4:$L$4)+MAX(0,MIN(DCF_Base!$L$21*(1+D$24)/($A29-D$24),Assumptions!$B$4*DCF_Base!$L$21))/(1+$A29)^10-Assumptions!$B$6)/Assumptions!$B$7,"n/a") | E29: =IF($A29>E$24,(SUMPRODUCT(DCF_Base!$C$21:$L$21/(1+$A29)^DCF_Base!$C$4:$L$4)+MAX(0,MIN(DCF_Base!$L$21*(1+E$24)/($A29-E$24),Assumptions!$B$4*DCF_Base!$L$21))/(1+$A29)^10-Assumptions!$B$6)/Assumptions!$B$7,"n/a") | F29: =IF($A29>F$24,(SUMPRODUCT(DCF_Base!$C$21:$L$21/(1+$A29)^DCF_Base!$C$4:$L$4)+MAX(0,MIN(DCF_Base!$L$21*(1+F$24)/($A29-F$24),Assumptions!$B$4*DCF_Base!$L$21))/(1+$A29)^10-Assumptions!$B$6)/Assumptions!$B$7,"n/a")
A31: Flat cells are where the 15x terminal-FCF cap binds (entire 7.5% WACC row; high-g cells at 8.5-9.5%)
