Workbook

Sheet Summary
A1: Allied Farmers Limited (ALF.NZ) — DCF Valuation (Sum-of-Parts)
A2: Valuation date: 2026-08-09 Currency: NZD Gray cells are INPUTS
A4: KEY INPUTS
A5: Current Stock Price | B5: 0.6
A6: Shares Outstanding (M) | B6: 28.807
A7: Net Debt / (Net Cash) (M) | B7: -17.855
A8: -> negative = net cash added to equity value
A10: SCENARIO RESULTS
A11: Scenario | B11: Intrinsic Value | C11: Upside % | D11: Weight
A12: Bear | B12: ='DCF_Bear'!B33 | C12: ='DCF_Bear'!B34 | D12: 0.25
A13: Base | B13: ='DCF_Base'!B37 | C13: ='DCF_Base'!B38 | D13: 0.5
A14: Bull | B14: ='DCF_Bull'!B37 | C14: ='DCF_Bull'!B38 | D14: 0.25
A15: Probability-weighted | B15: =B12*D12+B13*D13+B14*D14 | C15: =(B15-B5)/B5*100
A17: Entry Price (15% IRR hurdle) | B17: =Entry_Price!B16
A18: Entry discount from current price (%) | B18: =(B5-B17)/B5*100
A20: Sanity Check Result
A21: Passed: | B21: TRUE
A22: See SanityCheck tab for full detail, including the caveat that P/E and EV/EBITDA implied multiples use FY2025 consolidated (pre-divestment) actuals and are of limited use; P/B is the meaningful anchor.
A26: Valuation Philosophy
A27: Allied Farmers is NOT valued as a mechanical FCF-CAGR DCF on its consolidated historical financials. On 1 December 2025 Allied completed the sale of its 67.8%-owned livestock agency NZ Farmers Livestock (NZFL), which historically generated ~85% of consolidated revenue and is now a discontinued operation. The surviving continuing business is small: 100%-owned NZRLM (external asset manager of NZX-listed farmland REIT NZL, earning management/transaction/performance fees), a Parent Operations segment (governance costs partly offset by rental/interest/dividend income from a $10.5m investment property, loan advances and a ~2.7% NZL shareholding), plus a large freed-up cash/liquid-investment pile from the sale proceeds. Continuing operations posted a PRE-TAX LOSS of $0.517m in H1 FY2026 (dominated by NZFL-sale transaction costs and step-up NZRLM costs) and NPAT of $3.542m for the half is dominated by the $2.110m sale gain and a $2.740m one-off tax benefit -- neither is a run-rate figure. This model is therefore a SUM-OF-PARTS / continuing-operations build: (1) a 5-year explicit DCF of the NZRLM fee stream plus Parent Operations' governance costs and redeployed-capital investment income, capitalized via Gordon growth/multiple cap, PLUS (2) a bridge of net cash and liquid financial assets (cash, ~2.7% NZL stake at market, outstanding loan advances, net NZFL continuing-involvement receivable) added at the balance-sheet date. The self-contained Waikato investment-property SPV (financed 1:1 by the non-recourse MC Redlands term loan, explicitly disclosed by the company as having 'no exposure to Allied Farmers' beyond the SPV) is excluded from both sides of the bridge as it nets to approximately zero equity value and carries no parent recourse. The $172.4m unrecognised tax-loss pool is treated as call-option memo value, not capitalized in the base case, but its likely near-term utilisation is reflected via a low effective cash tax rate in the base/bull cases (consistent with the $2.740m DTA/tax-benefit already recognised in H1 FY2026), with fuller taxation assumed in the bear case where shareholder-continuity or utilisation is less certain. Historical consolidated revenue/EPS/equity CAGRs are reported for disclosure only and are explicitly NOT used to drive the projections, because they are dominated by the divested NZFL business. This 2026-08-09 refresh re-verified every input against the H1 FY2026 (31-Dec-2025) interim report and the FY2025 annual report segment note directly -- the net cash bridge, NZRLM segment revenue/margins, Parent Operations costs, and total-debt reconciliation all tie out exactly to source, and no FY2026 annual report has yet been released (due on/before 29-Aug-2026) to warrant a change in the balance-sheet date. No inputs changed from the 2026-08-08 build; this file supersedes it with confirmatory re-verification.

Sheet WACC
A1: WACC Build-Up (%)
A3: Component | B3: Value (%) | C3: Note
A4: Risk-free rate | B4: 4.5
A5: Equity risk premium | B5: 5.5
A6: Beta | B6: 0.9
A7: Base cost of equity (= risk-free + beta x ERP) | B7: =B4+B6*B5
A8: Illiquidity premium | B8: 2.25 | C8: Market cap ~NZ$17.3m at current price; extremely thin trading, concentrated register (WAF Ltd 19.99%, Rem Trustee 12.45%, MD Milsom ~15.8%)
A9: Concentration premium | B9: 2.25 | C9: NZRLM's fee income depends almost entirely on a single external counterparty (NZL); mandate loss, internalisation or renegotiation risk (NZL's Feb-2026 KPMG capital review is a live example of fee-structure review, and NZL director Christopher Swasbrook's April-2026 board resignation plus an ongoing Propero board review at NZL are governance changes at the client entity worth monitoring, though neither has been linked to any change in the NZRLM mandate to date)
A10: Transition/execution premium | B10: 2 | C10: Business model in transition post-NZFL divestment; continuing operations currently loss-making (H1 FY2026 pre-tax loss $0.517m, and the Parent Operations segment alone ran a larger annualized loss than FY2025's full year once NZFL-sale transaction and finance costs are included); no committed redeployment pipeline disclosed for the freed sale proceeds/cash as of Aug-2026
A11: WACC — base | B11: =B7+B8+B9+B10
A12: WACC — bull | B12: 14.95 | C12: Lower than base once redeployment execution is proven and NZRLM/NZL growth is validated
A13: WACC — bear | B13: 17.45 | C13: Higher than base once concentration/transition risks have crystallized
A15: Re-verification note (2026-08-09)
A16: Re-checked 2026-08-09: continuing operations remain loss-making at the segment level (H1 FY2026 Parent Operations PBT of -$1.146m annualizes to roughly -$2.3m, worse than FY2025's full-year -$1.105m, largely reflecting one-off NZFL-sale transaction costs and MC Redlands finance costs during the transition half), and no committed redeployment pipeline for the ~$8.2m of freed capital has been disclosed. All three WACC premiums (illiquidity, concentration, transition/execution) remain justified and are held unchanged from the 2026-08-08 build; there is no new information supporting a reduction.

Sheet DCF_Base
A1: Base Case — Continuing-Operations DCF ($m)
A2: Gray cells are INPUTS. NZRLM revenue grows off the normalized 3-period base; PBT margin, parent-ops cost, redeployment income, and tax rate all ramp per assumptions below.
A3: Line | B3: FY2027 | C3: FY2028 | D3: FY2029 | E3: FY2030 | F3: FY2031
A5: NZRLM revenue base ($m, normalized) | B5: 3.057
A6: NZRLM revenue growth (%) | B6: 0.04 | C6: 0.05 | D6: 0.05 | E6: 0.05 | F6: 0.05
A7: NZRLM PBT margin (%) | B7: 0.44 | C7: 0.45 | D7: 0.45 | E7: 0.46 | F7: 0.46
A8: Parent Ops cost ($m/yr) | B8: -1.05 | C8: -1.05 | D8: -1.05 | E8: -1.05 | F8: -1.05
A9: Redeployable capital ($m) | B9: 8.2
A10: Redeploy yield (%) | B10: 0.06
A11: Redeploy deployment ramp (%) | B11: 0.7 | C11: 1 | D11: 1 | E11: 1 | F11: 1
A12: Effective cash tax rate (%) | B12: 0.05 | C12: 0.06 | D12: 0.07 | E12: 0.08 | F12: 0.09
A14: WACC (%) | B14: =WACC!$B$11
A15: Terminal growth (%) | B15: 2
A16: Terminal cap multiple (x) | B16: 15
A18: NZRLM revenue | B18: =$B$5*(1+B6) | C18: =B18*(1+C6) | D18: =C18*(1+D6) | E18: =D18*(1+E6) | F18: =E18*(1+F6)
A19: NZRLM PBT | B19: =B18*B7 | C19: =C18*C7 | D19: =D18*D7 | E19: =E18*E7 | F19: =F18*F7
A20: Parent ops cost | B20: =B8 | C20: =C8 | D20: =D8 | E20: =E8 | F20: =F8
A21: Redeployment investment income | B21: =$B$9*$B$10*B11 | C21: =$B$9*$B$10*C11 | D21: =$B$9*$B$10*D11 | E21: =$B$9*$B$10*E11 | F21: =$B$9*$B$10*F11
A22: Combined pre-tax income | B22: =B19+B20+B21 | C22: =C19+C20+C21 | D22: =D19+D20+D21 | E22: =E19+E20+E21 | F22: =F19+F20+F21
A23: NOPAT / Owner FCF | B23: =B22*(1-B12) | C23: =C22*(1-C12) | D23: =D22*(1-D12) | E23: =E22*(1-E12) | F23: =F22*(1-F12)
A24: Discount factor | B24: =1/(1+$B$14/100)^1 | C24: =1/(1+$B$14/100)^2 | D24: =1/(1+$B$14/100)^3 | E24: =1/(1+$B$14/100)^4 | F24: =1/(1+$B$14/100)^5
A25: PV of FCF | B25: =B23*B24 | C25: =C23*C24 | D25: =D23*D24 | E25: =E23*E24 | F25: =F23*F24
A27: Sum PV of FCF | B27: =SUM(B25:F25)
A28: Terminal FCF (yr 5) | B28: =F23
A29: Gordon terminal value | B29: =B28*(1+B15/100)/(B14/100-B15/100)
A30: Cap terminal value | B30: =B28*B16
A31: Terminal value (lower of Gordon / cap) | B31: =MIN(B29,B30)
A32: Terminal bound | B32: =IF(B31=B29,"gordon","cap")
A33: PV of terminal value | B33: =B31*F24
A34: Enterprise value (continuing ops) | B34: =B27+B33
A35: Less net debt (add net cash) | B35: =-Summary!B7
A36: Equity value | B36: =B34+B35
A37: Intrinsic value / share | B37: =B36/Summary!B6
A38: Upside vs current (%) | B38: =(B37-Summary!B5)/Summary!B5*100
A39: Terminal % of enterprise value | B39: =B33/B34*100
A40: Implied exit multiple (TV/FCF5) | B40: =B31/B28

Sheet DCF_Bull
A1: Bull Case — Continuing-Operations DCF ($m)
A3: Line | B3: FY2027 | C3: FY2028 | D3: FY2029 | E3: FY2030 | F3: FY2031
A5: NZRLM revenue base ($m, normalized) | B5: =DCF_Base!B5
A6: NZRLM revenue growth (%) | B6: 0.08 | C6: 0.1 | D6: 0.1 | E6: 0.09 | F6: 0.08
A7: NZRLM PBT margin (%) | B7: 0.46 | C7: 0.48 | D7: 0.49 | E7: 0.5 | F7: 0.5
A8: Parent Ops cost ($m/yr) | B8: -0.9 | C8: -0.9 | D8: -0.9 | E8: -0.9 | F8: -0.9
A9: Redeployable capital ($m) | B9: 8.2
A10: Redeploy yield (%) | B10: 0.08
A11: Redeploy deployment ramp (%) | B11: 0.8 | C11: 1 | D11: 1 | E11: 1 | F11: 1
A12: Effective cash tax rate (%) | B12: 0 | C12: 0 | D12: 0.02 | E12: 0.04 | F12: 0.05
A14: WACC (%) | B14: =WACC!$B$12
A15: Terminal growth (%) | B15: 2.5
A16: Terminal cap multiple (x) | B16: 16
A18: NZRLM revenue | B18: =$B$5*(1+B6) | C18: =B18*(1+C6) | D18: =C18*(1+D6) | E18: =D18*(1+E6) | F18: =E18*(1+F6)
A19: NZRLM PBT | B19: =B18*B7 | C19: =C18*C7 | D19: =D18*D7 | E19: =E18*E7 | F19: =F18*F7
A20: Parent ops cost | B20: =B8 | C20: =C8 | D20: =D8 | E20: =E8 | F20: =F8
A21: Redeployment investment income | B21: =$B$9*$B$10*B11 | C21: =$B$9*$B$10*C11 | D21: =$B$9*$B$10*D11 | E21: =$B$9*$B$10*E11 | F21: =$B$9*$B$10*F11
A22: Combined pre-tax income | B22: =B19+B20+B21 | C22: =C19+C20+C21 | D22: =D19+D20+D21 | E22: =E19+E20+E21 | F22: =F19+F20+F21
A23: NOPAT / Owner FCF | B23: =B22*(1-B12) | C23: =C22*(1-C12) | D23: =D22*(1-D12) | E23: =E22*(1-E12) | F23: =F22*(1-F12)
A24: Discount factor | B24: =1/(1+$B$14/100)^1 | C24: =1/(1+$B$14/100)^2 | D24: =1/(1+$B$14/100)^3 | E24: =1/(1+$B$14/100)^4 | F24: =1/(1+$B$14/100)^5
A25: PV of FCF | B25: =B23*B24 | C25: =C23*C24 | D25: =D23*D24 | E25: =E23*E24 | F25: =F23*F24
A27: Sum PV of FCF | B27: =SUM(B25:F25)
A28: Terminal FCF (yr 5) | B28: =F23
A29: Gordon terminal value | B29: =B28*(1+B15/100)/(B14/100-B15/100)
A30: Cap terminal value | B30: =B28*B16
A31: Terminal value (lower of Gordon / cap) | B31: =MIN(B29,B30)
A32: Terminal bound | B32: =IF(B31=B29,"gordon","cap")
A33: PV of terminal value | B33: =B31*F24
A34: Enterprise value (continuing ops) | B34: =B27+B33
A35: Less net debt (add net cash) | B35: =-Summary!B7
A36: Equity value | B36: =B34+B35
A37: Intrinsic value / share | B37: =B36/Summary!B6
A38: Upside vs current (%) | B38: =(B37-Summary!B5)/Summary!B5*100
A39: Terminal % of enterprise value | B39: =B33/B34*100
A40: Implied exit multiple (TV/FCF5) | B40: =B31/B28

Sheet DCF_Bear
A1: Bear Case — Continuing-Operations DCF ($m)
A2: Terminal value is FLOORED AT ZERO because year-5 FCF is negative in this scenario (see B31 formula) — a negative Gordon perpetuity is not meaningful.
A3: Line | B3: FY2027 | C3: FY2028 | D3: FY2029 | E3: FY2030 | F3: FY2031
A5: NZRLM revenue base ($m, normalized) | B5: =DCF_Base!B5
A6: NZRLM revenue growth (%) | B6: -0.05 | C6: 0 | D6: 0 | E6: 0.01 | F6: 0.01
A7: NZRLM PBT margin (%) | B7: 0.38 | C7: 0.36 | D7: 0.35 | E7: 0.35 | F7: 0.35
A8: Parent Ops cost ($m/yr) | B8: -1.3 | C8: -1.3 | D8: -1.3 | E8: -1.3 | F8: -1.3
A9: Redeployable capital ($m) | B9: 8.2
A10: Redeploy yield (%) | B10: 0.03
A11: Redeploy deployment ramp (%) | B11: 0.35 | C11: 0.5 | D11: 0.65 | E11: 0.8 | F11: 0.95
A12: Effective cash tax rate (%) — none assumed on losses | B12: 0 | C12: 0 | D12: 0 | E12: 0 | F12: 0
A14: WACC (%) | B14: =WACC!$B$13
A15: Terminal growth (%) — not used, TV floored at zero | B15: 1
A16: Terminal cap multiple (x) — not used, TV floored at zero | B16: 12
A18: NZRLM revenue | B18: =$B$5*(1+B6) | C18: =B18*(1+C6) | D18: =C18*(1+D6) | E18: =D18*(1+E6) | F18: =E18*(1+F6)
A19: NZRLM PBT | B19: =B18*B7 | C19: =C18*C7 | D19: =D18*D7 | E19: =E18*E7 | F19: =F18*F7
A20: Parent ops cost | B20: =B8 | C20: =C8 | D20: =D8 | E20: =E8 | F20: =F8
A21: Redeployment investment income | B21: =$B$9*$B$10*B11 | C21: =$B$9*$B$10*C11 | D21: =$B$9*$B$10*D11 | E21: =$B$9*$B$10*E11 | F21: =$B$9*$B$10*F11
A22: Combined pre-tax income / Owner FCF (no tax benefit on losses) | B22: =B19+B20+B21 | C22: =C19+C20+C21 | D22: =D19+D20+D21 | E22: =E19+E20+E21 | F22: =F19+F20+F21
A23: Discount factor | B23: =1/(1+$B$14/100)^1 | C23: =1/(1+$B$14/100)^2 | D23: =1/(1+$B$14/100)^3 | E23: =1/(1+$B$14/100)^4 | F23: =1/(1+$B$14/100)^5
A24: PV of FCF | B24: =B22*B23 | C24: =C22*C23 | D24: =D22*D23 | E24: =E22*E23 | F24: =F22*F23
A26: Sum PV of FCF | B26: =SUM(B24:F24)
A27: Terminal FCF (yr 5) | B27: =F22
A28: Terminal value (floored at zero — see note) | B28: =MAX(0,IF(F22>0,MIN(F22*(1+B15/100)/(B14/100-B15/100),F22*B16),0))
A29: PV of terminal value | B29: =B28*F23
A30: Enterprise value (continuing ops) | B30: =B26+B29
A31: Less net debt (add net cash) | B31: =-Summary!B7
A32: Equity value | B32: =B30+B31
A33: Intrinsic value / share | B33: =B32/Summary!B6
A34: Upside vs current (%) | B34: =(B33-Summary!B5)/Summary!B5*100

Sheet Entry_Price
A1: Entry Price — 15% IRR Hurdle (Base Case)
A2: Formula: (sum of base-case FCF_t / 1.15^t for t=1..5 + base-case Gordon terminal value / 1.15^5 - net_debt) / shares outstanding. TV uses WACC (fair price a buyer pays at exit); only the discounting back to today uses the 15% hurdle.
A4: Hurdle rate (%) | B4: 15
A6: Line | B6: FY2027 | C6: FY2028 | D6: FY2029 | E6: FY2030 | F6: FY2031
A7: Base-case FCF ($m) | B7: =DCF_Base!B23 | C7: =DCF_Base!C23 | D7: =DCF_Base!D23 | E7: =DCF_Base!E23 | F7: =DCF_Base!F23
A8: Discount factor @ hurdle | B8: =1/(1+$B$4/100)^1 | C8: =1/(1+$B$4/100)^2 | D8: =1/(1+$B$4/100)^3 | E8: =1/(1+$B$4/100)^4 | F8: =1/(1+$B$4/100)^5
A9: PV of FCF @ hurdle | B9: =B7*B8 | C9: =C7*C8 | D9: =D7*D8 | E9: =E7*E8 | F9: =F7*F8
A11: PV of interim FCF @ hurdle (sum) | B11: =SUM(B9:F9)
A12: Base-case Gordon terminal value (at WACC) | B12: =DCF_Base!B29
A13: PV of terminal value @ hurdle | B13: =B12*F8
A14: Less net debt (add net cash) | B14: =-Summary!B7
A15: Entry equity value | B15: =B11+B13+B14
A16: Entry price / share | B16: =B15/Summary!B6
A17: Entry discount from current price (%) | B17: =(Summary!B5-B16)/Summary!B5*100

Sheet Sensitivity
A1: Base-Case IV Sensitivity: WACC (rows) x Terminal Growth (cols)
A2: Base-case FCF path held constant (referenced from DCF_Base); only WACC and terminal growth vary here.
A4: WACC \ g | B4: 1.0% | C4: 1.5% | D4: 2.0% | E4: 2.5% | F4: 3.0%
A5: 13.95% | B5: =(SUMPRODUCT(DCF_Base!$B$23:$F$23,1/(1+13.95/100)^{1,2,3,4,5})+MIN(DCF_Base!$F$23*(1+1.0/100)/(13.95/100-1.0/100),DCF_Base!$F$23*DCF_Base!$B$16)/(1+13.95/100)^5-Summary!$B$7)/Summary!$B$6 | C5: =(SUMPRODUCT(DCF_Base!$B$23:$F$23,1/(1+13.95/100)^{1,2,3,4,5})+MIN(DCF_Base!$F$23*(1+1.5/100)/(13.95/100-1.5/100),DCF_Base!$F$23*DCF_Base!$B$16)/(1+13.95/100)^5-Summary!$B$7)/Summary!$B$6 | D5: =(SUMPRODUCT(DCF_Base!$B$23:$F$23,1/(1+13.95/100)^{1,2,3,4,5})+MIN(DCF_Base!$F$23*(1+2.0/100)/(13.95/100-2.0/100),DCF_Base!$F$23*DCF_Base!$B$16)/(1+13.95/100)^5-Summary!$B$7)/Summary!$B$6 | E5: =(SUMPRODUCT(DCF_Base!$B$23:$F$23,1/(1+13.95/100)^{1,2,3,4,5})+MIN(DCF_Base!$F$23*(1+2.5/100)/(13.95/100-2.5/100),DCF_Base!$F$23*DCF_Base!$B$16)/(1+13.95/100)^5-Summary!$B$7)/Summary!$B$6 | F5: =(SUMPRODUCT(DCF_Base!$B$23:$F$23,1/(1+13.95/100)^{1,2,3,4,5})+MIN(DCF_Base!$F$23*(1+3.0/100)/(13.95/100-3.0/100),DCF_Base!$F$23*DCF_Base!$B$16)/(1+13.95/100)^5-Summary!$B$7)/Summary!$B$6
A6: 14.95% | B6: =(SUMPRODUCT(DCF_Base!$B$23:$F$23,1/(1+14.95/100)^{1,2,3,4,5})+MIN(DCF_Base!$F$23*(1+1.0/100)/(14.95/100-1.0/100),DCF_Base!$F$23*DCF_Base!$B$16)/(1+14.95/100)^5-Summary!$B$7)/Summary!$B$6 | C6: =(SUMPRODUCT(DCF_Base!$B$23:$F$23,1/(1+14.95/100)^{1,2,3,4,5})+MIN(DCF_Base!$F$23*(1+1.5/100)/(14.95/100-1.5/100),DCF_Base!$F$23*DCF_Base!$B$16)/(1+14.95/100)^5-Summary!$B$7)/Summary!$B$6 | D6: =(SUMPRODUCT(DCF_Base!$B$23:$F$23,1/(1+14.95/100)^{1,2,3,4,5})+MIN(DCF_Base!$F$23*(1+2.0/100)/(14.95/100-2.0/100),DCF_Base!$F$23*DCF_Base!$B$16)/(1+14.95/100)^5-Summary!$B$7)/Summary!$B$6 | E6: =(SUMPRODUCT(DCF_Base!$B$23:$F$23,1/(1+14.95/100)^{1,2,3,4,5})+MIN(DCF_Base!$F$23*(1+2.5/100)/(14.95/100-2.5/100),DCF_Base!$F$23*DCF_Base!$B$16)/(1+14.95/100)^5-Summary!$B$7)/Summary!$B$6 | F6: =(SUMPRODUCT(DCF_Base!$B$23:$F$23,1/(1+14.95/100)^{1,2,3,4,5})+MIN(DCF_Base!$F$23*(1+3.0/100)/(14.95/100-3.0/100),DCF_Base!$F$23*DCF_Base!$B$16)/(1+14.95/100)^5-Summary!$B$7)/Summary!$B$6
A7: 15.95% | B7: =(SUMPRODUCT(DCF_Base!$B$23:$F$23,1/(1+15.95/100)^{1,2,3,4,5})+MIN(DCF_Base!$F$23*(1+1.0/100)/(15.95/100-1.0/100),DCF_Base!$F$23*DCF_Base!$B$16)/(1+15.95/100)^5-Summary!$B$7)/Summary!$B$6 | C7: =(SUMPRODUCT(DCF_Base!$B$23:$F$23,1/(1+15.95/100)^{1,2,3,4,5})+MIN(DCF_Base!$F$23*(1+1.5/100)/(15.95/100-1.5/100),DCF_Base!$F$23*DCF_Base!$B$16)/(1+15.95/100)^5-Summary!$B$7)/Summary!$B$6 | D7: =(SUMPRODUCT(DCF_Base!$B$23:$F$23,1/(1+15.95/100)^{1,2,3,4,5})+MIN(DCF_Base!$F$23*(1+2.0/100)/(15.95/100-2.0/100),DCF_Base!$F$23*DCF_Base!$B$16)/(1+15.95/100)^5-Summary!$B$7)/Summary!$B$6 | E7: =(SUMPRODUCT(DCF_Base!$B$23:$F$23,1/(1+15.95/100)^{1,2,3,4,5})+MIN(DCF_Base!$F$23*(1+2.5/100)/(15.95/100-2.5/100),DCF_Base!$F$23*DCF_Base!$B$16)/(1+15.95/100)^5-Summary!$B$7)/Summary!$B$6 | F7: =(SUMPRODUCT(DCF_Base!$B$23:$F$23,1/(1+15.95/100)^{1,2,3,4,5})+MIN(DCF_Base!$F$23*(1+3.0/100)/(15.95/100-3.0/100),DCF_Base!$F$23*DCF_Base!$B$16)/(1+15.95/100)^5-Summary!$B$7)/Summary!$B$6
A8: 16.95% | B8: =(SUMPRODUCT(DCF_Base!$B$23:$F$23,1/(1+16.95/100)^{1,2,3,4,5})+MIN(DCF_Base!$F$23*(1+1.0/100)/(16.95/100-1.0/100),DCF_Base!$F$23*DCF_Base!$B$16)/(1+16.95/100)^5-Summary!$B$7)/Summary!$B$6 | C8: =(SUMPRODUCT(DCF_Base!$B$23:$F$23,1/(1+16.95/100)^{1,2,3,4,5})+MIN(DCF_Base!$F$23*(1+1.5/100)/(16.95/100-1.5/100),DCF_Base!$F$23*DCF_Base!$B$16)/(1+16.95/100)^5-Summary!$B$7)/Summary!$B$6 | D8: =(SUMPRODUCT(DCF_Base!$B$23:$F$23,1/(1+16.95/100)^{1,2,3,4,5})+MIN(DCF_Base!$F$23*(1+2.0/100)/(16.95/100-2.0/100),DCF_Base!$F$23*DCF_Base!$B$16)/(1+16.95/100)^5-Summary!$B$7)/Summary!$B$6 | E8: =(SUMPRODUCT(DCF_Base!$B$23:$F$23,1/(1+16.95/100)^{1,2,3,4,5})+MIN(DCF_Base!$F$23*(1+2.5/100)/(16.95/100-2.5/100),DCF_Base!$F$23*DCF_Base!$B$16)/(1+16.95/100)^5-Summary!$B$7)/Summary!$B$6 | F8: =(SUMPRODUCT(DCF_Base!$B$23:$F$23,1/(1+16.95/100)^{1,2,3,4,5})+MIN(DCF_Base!$F$23*(1+3.0/100)/(16.95/100-3.0/100),DCF_Base!$F$23*DCF_Base!$B$16)/(1+16.95/100)^5-Summary!$B$7)/Summary!$B$6
A9: 17.95% | B9: =(SUMPRODUCT(DCF_Base!$B$23:$F$23,1/(1+17.95/100)^{1,2,3,4,5})+MIN(DCF_Base!$F$23*(1+1.0/100)/(17.95/100-1.0/100),DCF_Base!$F$23*DCF_Base!$B$16)/(1+17.95/100)^5-Summary!$B$7)/Summary!$B$6 | C9: =(SUMPRODUCT(DCF_Base!$B$23:$F$23,1/(1+17.95/100)^{1,2,3,4,5})+MIN(DCF_Base!$F$23*(1+1.5/100)/(17.95/100-1.5/100),DCF_Base!$F$23*DCF_Base!$B$16)/(1+17.95/100)^5-Summary!$B$7)/Summary!$B$6 | D9: =(SUMPRODUCT(DCF_Base!$B$23:$F$23,1/(1+17.95/100)^{1,2,3,4,5})+MIN(DCF_Base!$F$23*(1+2.0/100)/(17.95/100-2.0/100),DCF_Base!$F$23*DCF_Base!$B$16)/(1+17.95/100)^5-Summary!$B$7)/Summary!$B$6 | E9: =(SUMPRODUCT(DCF_Base!$B$23:$F$23,1/(1+17.95/100)^{1,2,3,4,5})+MIN(DCF_Base!$F$23*(1+2.5/100)/(17.95/100-2.5/100),DCF_Base!$F$23*DCF_Base!$B$16)/(1+17.95/100)^5-Summary!$B$7)/Summary!$B$6 | F9: =(SUMPRODUCT(DCF_Base!$B$23:$F$23,1/(1+17.95/100)^{1,2,3,4,5})+MIN(DCF_Base!$F$23*(1+3.0/100)/(17.95/100-3.0/100),DCF_Base!$F$23*DCF_Base!$B$16)/(1+17.95/100)^5-Summary!$B$7)/Summary!$B$6
A11: Rows = WACC (13.95% to 17.95%), Columns = terminal growth (1.0% to 3.0%). Base-case FCF path held constant; only WACC and terminal growth vary. Intrinsic value is not highly sensitive to these two inputs within this range (range $0.82-$0.92) because ~57% of enterprise value comes from the discounted operating cash flows/terminal value on a very small FCF base, while the dominant driver of total intrinsic value is the largely WACC-insensitive net-cash/liquid-investment bridge (~$17.9m, ~68% of total equity value in the base case).

Sheet SanityCheck
A1: Implied vs Historical Multiples
A2: Historical multiples (FY2017-2025) are computed on the OLD consolidated (NZFL-inclusive) business. P/E and EV/EBITDA implied-at-IV figures use FY2025 consolidated actuals and are of LIMITED USE post-divestment (retained for completeness). P/B against continuing-ops book value (~$29.2m) is the meaningful anchor.
A6: Metric | B6: Implied @ base IV | C6: 10yr avg (ex-outliers) | D6: 10yr max (ex-outliers)
A7: P/E (consolidated FY2025 — limited use) | B7: 8.6 | C7: 7.8 | D7: 13.2
A8: P/B (continuing-ops book value — meaningful anchor) | B8: 0.59 | C8: 1.36 | D8: 2.11
A9: EV/EBITDA (consolidated FY2025 — limited use) | B9: 4.6 | C9: 4 | D9: 5.1
A11: P/B check: market cap vs continuing-ops book value
A12: Continuing-ops shareholders equity ($m, H1 FY2026) | B12: 29.204
A13: Market cap at current price ($m) | B13: =Summary!B5*Summary!B6
A14: Market cap / book value (x) — current price | B14: =B13/B12
A15: IV-implied market cap ($m, base case) | B15: =DCF_Base!B37*Summary!B6
A16: IV-implied market cap / book value (x) | B16: =B15/B12
A18: Result | B18: PASSED (no trip)
A20: Year | B20: P/E | C20: P/B | D20: EV/EBITDA | E20: Outlier
A21: FY2017 | B21: 7.4 | C21: 11.29 | D21: 4.3 | E21: yes
A22: FY2018 | B22: 6.8 | C22: 4.64 | D22: 4.6 | E22: yes
A23: FY2019 | B23: 9.2 | C23: 2.64 | D23: 4.2 | E23: yes
A24: FY2020 | B24: 13.2 | C24: 2.11 | D24: 5.1
A25: FY2021 | B25: 8.8 | C25: 1.53 | D25: 4.4
A26: FY2022 | B26: 7.6 | C26: 1.51 | D26: 3.7
A27: FY2023 | B27: 5.9 | C27: 1.15 | D27: 3.7
A28: FY2024 | B28: 4.1 | C28: 0.97 | D28: 1.6
A29: FY2025 | B29: 7.5 | C29: 0.88 | D29: 4.1
A31: No trip -- with an explicit and important caveat. Allied is a transitioning micro-cap where the FY2025 consolidated actuals (EPS, EBITDA) still fully embed the divested NZFL business (~85% of that period's revenue), so implied P/E (8.6x) and EV/EBITDA (4.6x) computed against those actuals are close to meaningless as a check on THIS valuation -- they are not manufactured trips, but they are also not a genuine pass, because the earnings/EBITDA base they are measured against no longer exists. Recording them for completeness (both happen to sit within/near historical ranges, 8.6x vs 7.8x avg P/E and 4.6x vs 4.0x avg EV/EBITDA) is coincidental, not confirmatory. The ONE multiple that is genuinely meaningful post-divestment is P/B: continuing-operations book value is ~$29.2m against a market cap of only ~$17.3m (0.59x book) and against the base-case IV-implied market cap of ~$24.7m (0.85x book) -- both well under 1.0x, which is a sensible, non-alarming anchor for a business that is currently loss-making at the operating level and has not yet proven its capital-redeployment thesis. Base-case upside of 42.7% is under the 100% threshold. The IV is dominated by the ~$17.9m net-cash/liquid-investment bridge (~$0.62/share, ~68% of total base-case equity value) rather than aggressive operating projections.

Sheet Model_Info
A1: Model Provenance & Refresh Notes
A3: Ticker: ALF.NZ (Allied Farmers Limited, NZX Main Board)
A4: Built/refreshed by: DCF valuation agent (Claude), 2026-08-09
A5: Data vintage: share price $0.60 verified live from Yahoo Finance chart API on 2026-08-09; balance-sheet date is 31-Dec-2025 (H1 FY2026 interim report, the latest available — FY2026 annual report not yet released, due on/before 29-Aug-2026); segment P&L figures also cross-checked against the FY2025 (30-Jun-2025) and FY2024 annual report segment notes.
A7: METHODOLOGY (sum-of-parts, NOT a conventional FCF-CAGR DCF):
A8: 1. On 1-Dec-2025 Allied sold its 67.8%-owned NZ Farmers Livestock (NZFL), historically ~85% of consolidated revenue. All pre-divestment consolidated CAGRs (revenue, EPS, equity, FCF) are structurally broken and are NOT used to drive projections -- shown for disclosure only.
A9: 2. The going-forward business is valued as: (a) a 5-year explicit DCF of the continuing NZRLM (external manager of NZX-listed NZL) fee stream plus Parent Operations governance costs and redeployed-capital investment income, capitalized via Gordon growth / terminal-cap-multiple (lower of the two, recorded per scenario), PLUS (b) a net-cash/liquid-investment equity bridge (cash, ~2.7% NZL stake at market, loan advances, net NZFL continuing-involvement receivable) added at the balance-sheet date.
A10: 3. The $10.5m MC Redlands term loan and the $10.5m Waikato investment property it finances are EXCLUDED from both sides of the net-debt bridge -- the loan is explicitly disclosed as non-recourse to Allied beyond the ring-fenced SPV (Allied FLA Limited); including both sides nets to ~zero anyway.
A11: 4. The $172.4m unrecognised tax-loss pool is treated as call-option memo value, NOT capitalized as a lump-sum NPV addition. Its likely near-term utilisation is instead reflected via a low effective cash tax rate in the base/bull projections.
A12: 5. SBC is immaterial (~$0.028m FY2025) and is embedded within segment personnel-expense lines rather than separately deducted; no dilution adjustment applied (shares held flat).
A13: 6. Entry price uses the full formula: (sum FCF_t/1.15^t for t=1..5 + Gordon TV_5/1.15^5 - net_debt) / shares outstanding -- see the Entry_Price tab -- NOT a terminal-value-only shortcut.
A15: WHAT TO REFRESH AFTER THE NEXT DISCLOSURE:
... A27: IMPORTANT: this is a micro-cap, post-divestment transitional company. Every figure in this workbook reflects the state of disclosure as of 2026-08-09 and WILL go stale. Do not reuse without re-checking against the next filing.
