Workbook

Sheet Inputs
A1: Bank of Queensland (BOQ.AX) -- residual income on tangible book, A$m
A2: Current price (A$) | B2: 6.7
A3: Total equity 31-Aug-25 | B3: 5907
A4: Intangible assets 31-Aug-25 | B4: 1043
A5: TBV 31-Aug-25 | B5: =B3-B4
A6: Shares net of treasury 31-Aug-25 (m) | B6: 658.119
A7: FY26E statutory NPAT | B7: 285
A8: Dividends paid FY26 (20c+20c+15c special) | B8: =0.55*B6
A9: TBV 31-Aug-26E pre buyback | B9: =B5+B7-B8
A10: Assumed buyback A$m | B10: 200
A11: Buyback price | B11: 6.7
A12: Shares bought (m) | B12: =B10/B11
A13: TBV0 (post buyback) | B13: =B9-B10
A14: Shares0 (m) | B14: =B6-B12
A15: TBVPS0 | B15: =B13/B14
A16: Hurdle rate | B16: 0.15
A17: Weight bear | B17: 0.3
A18: Weight base | B18: 0.5
A19: Weight bull | B19: 0.2

Sheet Base
A1: Base scenario
A2: Cost of equity | B2: 0.105
A3: Terminal growth of RI | B3: 0.02
A4: Payout ratio | B4: 0.72
A5: Shares (m) | B5: =Inputs!B14
A7: Year | B7: Y1 FY27 (Sep26-Aug27) | C7: Y2 FY28 | D7: Y3 FY29 | E7: Y4 FY30 | F7: Y5 FY31
A8: TBV opening | B8: =Inputs!B13 | C8: =B15 | D8: =C15 | E8: =D15 | F8: =E15
A9: ROTE | B9: 0.079 | C9: 0.084 | D9: 0.089 | E9: 0.093 | F9: 0.095
A10: Cash earnings | B10: =B9*B8 | C10: =C9*C8 | D10: =D9*D8 | E10: =E9*E8 | F10: =F9*F8
A11: One-offs after tax | B11: 60 | C11: 40 | D11: 25 | E11: 15 | F11: 15
A12: Net income | B12: =B10-B11 | C12: =C10-C11 | D12: =D10-D11 | E12: =E10-E11 | F12: =F10-F11
A13: Dividends | B13: =$B$4*B10 | C13: =$B$4*C10 | D13: =$B$4*D10 | E13: =$B$4*E10 | F13: =$B$4*F10
A14: Retained | B14: =B12-B13 | C14: =C12-C13 | D14: =D12-D13 | E14: =E12-E13 | F14: =F12-F13
A15: TBV closing | B15: =B8+B14 | C15: =C8+C14 | D15: =D8+D14 | E15: =E8+E14 | F15: =F8+F14
A16: Equity charge | B16: =$B$2*B8 | C16: =$B$2*C8 | D16: =$B$2*D8 | E16: =$B$2*E8 | F16: =$B$2*F8
A17: Residual income | B17: =B12-B16 | C17: =C12-C16 | D17: =D12-D16 | E17: =E12-E16 | F17: =F12-F16
A18: Discount factor | B18: =1/(1+$B$2)^1 | C18: =1/(1+$B$2)^2 | D18: =1/(1+$B$2)^3 | E18: =1/(1+$B$2)^4 | F18: =1/(1+$B$2)^5
A19: PV residual income | B19: =B17*B18 | C19: =C17*C18 | D19: =D17*D18 | E19: =E17*E18 | F19: =F17*F18
A20: EPS | B20: =B12/$B$5 | C20: =C12/$B$5 | D20: =D12/$B$5 | E20: =E12/$B$5 | F20: =F12/$B$5
A21: DPS | B21: =B13/$B$5 | C21: =C13/$B$5 | D21: =D13/$B$5 | E21: =E13/$B$5 | F21: =F13/$B$5
A22: TBV/share | B22: =B15/$B$5 | C22: =C15/$B$5 | D22: =D15/$B$5 | E22: =E15/$B$5 | F22: =F15/$B$5
A24: Sum PV residual income | B24: =SUM(B19:F19)
A25: Terminal value (Gordon on Y5 RI) | B25: =F17*(1+B3)/(B2-B3)
A26: PV terminal | B26: =B25*F18
A27: Equity value | B27: =B8+B24+B26
A28: Intrinsic value / share | B28: =B27/B5
A29: Upside vs price | B29: =B28/Inputs!B2-1
A30: Terminal equity value Y5 | B30: =F15+B25
A31: Implied exit P/TBV | B31: =B30/F15
A32: Implied P/TBV of IV | B32: =B28/(B8/B5)
A34: Entry price @ hurdle
A35: PV dividends @ hurdle | B35: =B13/(1+Inputs!$B$16)^1+C13/(1+Inputs!$B$16)^2+D13/(1+Inputs!$B$16)^3+E13/(1+Inputs!$B$16)^4+F13/(1+Inputs!$B$16)^5
A36: PV terminal equity @ hurdle | B36: =B30/(1+Inputs!$B$16)^5
A37: Entry price / share | B37: =(B35+B36)/B5

Sheet Bull
A1: Bull scenario
A2: Cost of equity | B2: 0.095
A3: Terminal growth of RI | B3: 0.03
A4: Payout ratio | B4: 0.65
A5: Shares (m) | B5: =Inputs!B14
A7: Year | B7: Y1 FY27 (Sep26-Aug27) | C7: Y2 FY28 | D7: Y3 FY29 | E7: Y4 FY30 | F7: Y5 FY31
A8: TBV opening | B8: =Inputs!B13 | C8: =B15 | D8: =C15 | E8: =D15 | F8: =E15
A9: ROTE | B9: 0.084 | C9: 0.094 | D9: 0.104 | E9: 0.11 | F9: 0.115
A10: Cash earnings | B10: =B9*B8 | C10: =C9*C8 | D10: =D9*D8 | E10: =E9*E8 | F10: =F9*F8
A11: One-offs after tax | B11: 50 | C11: 25 | D11: 10 | E11: 0 | F11: 0
A12: Net income | B12: =B10-B11 | C12: =C10-C11 | D12: =D10-D11 | E12: =E10-E11 | F12: =F10-F11
A13: Dividends | B13: =$B$4*B10 | C13: =$B$4*C10 | D13: =$B$4*D10 | E13: =$B$4*E10 | F13: =$B$4*F10
A14: Retained | B14: =B12-B13 | C14: =C12-C13 | D14: =D12-D13 | E14: =E12-E13 | F14: =F12-F13
A15: TBV closing | B15: =B8+B14 | C15: =C8+C14 | D15: =D8+D14 | E15: =E8+E14 | F15: =F8+F14
A16: Equity charge | B16: =$B$2*B8 | C16: =$B$2*C8 | D16: =$B$2*D8 | E16: =$B$2*E8 | F16: =$B$2*F8
A17: Residual income | B17: =B12-B16 | C17: =C12-C16 | D17: =D12-D16 | E17: =E12-E16 | F17: =F12-F16
A18: Discount factor | B18: =1/(1+$B$2)^1 | C18: =1/(1+$B$2)^2 | D18: =1/(1+$B$2)^3 | E18: =1/(1+$B$2)^4 | F18: =1/(1+$B$2)^5
A19: PV residual income | B19: =B17*B18 | C19: =C17*C18 | D19: =D17*D18 | E19: =E17*E18 | F19: =F17*F18
A20: EPS | B20: =B12/$B$5 | C20: =C12/$B$5 | D20: =D12/$B$5 | E20: =E12/$B$5 | F20: =F12/$B$5
A21: DPS | B21: =B13/$B$5 | C21: =C13/$B$5 | D21: =D13/$B$5 | E21: =E13/$B$5 | F21: =F13/$B$5
A22: TBV/share | B22: =B15/$B$5 | C22: =C15/$B$5 | D22: =D15/$B$5 | E22: =E15/$B$5 | F22: =F15/$B$5
A24: Sum PV residual income | B24: =SUM(B19:F19)
A25: Terminal value (Gordon on Y5 RI) | B25: =F17*(1+B3)/(B2-B3)
A26: PV terminal | B26: =B25*F18
A27: Equity value | B27: =B8+B24+B26
A28: Intrinsic value / share | B28: =B27/B5
A29: Upside vs price | B29: =B28/Inputs!B2-1
A30: Terminal equity value Y5 | B30: =F15+B25
A31: Implied exit P/TBV | B31: =B30/F15
A32: Implied P/TBV of IV | B32: =B28/(B8/B5)
A34: Entry price @ hurdle
A35: PV dividends @ hurdle | B35: =B13/(1+Inputs!$B$16)^1+C13/(1+Inputs!$B$16)^2+D13/(1+Inputs!$B$16)^3+E13/(1+Inputs!$B$16)^4+F13/(1+Inputs!$B$16)^5
A36: PV terminal equity @ hurdle | B36: =B30/(1+Inputs!$B$16)^5
A37: Entry price / share | B37: =(B35+B36)/B5

Sheet Bear
A1: Bear scenario
A2: Cost of equity | B2: 0.11
A3: Terminal growth of RI | B3: 0.01
A4: Payout ratio | B4: 0.8
A5: Shares (m) | B5: =Inputs!B14
A7: Year | B7: Y1 FY27 (Sep26-Aug27) | C7: Y2 FY28 | D7: Y3 FY29 | E7: Y4 FY30 | F7: Y5 FY31
A8: TBV opening | B8: =Inputs!B13 | C8: =B15 | D8: =C15 | E8: =D15 | F8: =E15
A9: ROTE | B9: 0.07 | C9: 0.065 | D9: 0.068 | E9: 0.072 | F9: 0.075
A10: Cash earnings | B10: =B9*B8 | C10: =C9*C8 | D10: =D9*D8 | E10: =E9*E8 | F10: =F9*F8
A11: One-offs after tax | B11: 90 | C11: 180 | D11: 60 | E11: 40 | F11: 40
A12: Net income | B12: =B10-B11 | C12: =C10-C11 | D12: =D10-D11 | E12: =E10-E11 | F12: =F10-F11
A13: Dividends | B13: =$B$4*B10 | C13: =$B$4*C10 | D13: =$B$4*D10 | E13: =$B$4*E10 | F13: =$B$4*F10
A14: Retained | B14: =B12-B13 | C14: =C12-C13 | D14: =D12-D13 | E14: =E12-E13 | F14: =F12-F13
A15: TBV closing | B15: =B8+B14 | C15: =C8+C14 | D15: =D8+D14 | E15: =E8+E14 | F15: =F8+F14
A16: Equity charge | B16: =$B$2*B8 | C16: =$B$2*C8 | D16: =$B$2*D8 | E16: =$B$2*E8 | F16: =$B$2*F8
A17: Residual income | B17: =B12-B16 | C17: =C12-C16 | D17: =D12-D16 | E17: =E12-E16 | F17: =F12-F16
A18: Discount factor | B18: =1/(1+$B$2)^1 | C18: =1/(1+$B$2)^2 | D18: =1/(1+$B$2)^3 | E18: =1/(1+$B$2)^4 | F18: =1/(1+$B$2)^5
A19: PV residual income | B19: =B17*B18 | C19: =C17*C18 | D19: =D17*D18 | E19: =E17*E18 | F19: =F17*F18
A20: EPS | B20: =B12/$B$5 | C20: =C12/$B$5 | D20: =D12/$B$5 | E20: =E12/$B$5 | F20: =F12/$B$5
A21: DPS | B21: =B13/$B$5 | C21: =C13/$B$5 | D21: =D13/$B$5 | E21: =E13/$B$5 | F21: =F13/$B$5
A22: TBV/share | B22: =B15/$B$5 | C22: =C15/$B$5 | D22: =D15/$B$5 | E22: =E15/$B$5 | F22: =F15/$B$5
A24: Sum PV residual income | B24: =SUM(B19:F19)
A25: Terminal value (Gordon on Y5 RI) | B25: =F17*(1+B3)/(B2-B3)
A26: PV terminal | B26: =B25*F18
A27: Equity value | B27: =B8+B24+B26
A28: Intrinsic value / share | B28: =B27/B5
A29: Upside vs price | B29: =B28/Inputs!B2-1
A30: Terminal equity value Y5 | B30: =F15+B25
A31: Implied exit P/TBV | B31: =B30/F15
A32: Implied P/TBV of IV | B32: =B28/(B8/B5)
A34: Entry price @ hurdle
A35: PV dividends @ hurdle | B35: =B13/(1+Inputs!$B$16)^1+C13/(1+Inputs!$B$16)^2+D13/(1+Inputs!$B$16)^3+E13/(1+Inputs!$B$16)^4+F13/(1+Inputs!$B$16)^5
A36: PV terminal equity @ hurdle | B36: =B30/(1+Inputs!$B$16)^5
A37: Entry price / share | B37: =(B35+B36)/B5

Sheet Summary
A1: Summary
A2: Scenario | B2: IV / share | C2: Weight | D2: Entry price | E2: Upside
A3: Bear | B3: =Bear!B28 | C3: =Inputs!B17 | D3: =Bear!B37 | E3: =Bear!B29
A4: Base | B4: =Base!B28 | C4: =Inputs!B18 | D4: =Base!B37 | E4: =Base!B29
A5: Bull | B5: =Bull!B28 | C5: =Inputs!B19 | D5: =Bull!B37 | E5: =Bull!B29
A6: Weighted IV | B6: =SUMPRODUCT(B3:B5,C3:C5)
A7: Weighted entry price | D7: =SUMPRODUCT(D3:D5,C3:C5)
A8: Current price | B8: =Inputs!B2
A9: Weighted upside | B9: =B6/B8-1
A11: Note: 'cost of equity' replaces WACC; deposits are operating funding so net debt = 0 and nothing is subtracted from equity value.
