Workbook

Sheet DCF Model
A1: LULU DCF Valuation Model - Base Case
A2: Gray cells are INPUTS - adjust to see valuation change
A4: KEY INPUTS
A5: Current Stock Price | B5: 113.37
A6: Shares Outstanding (M, diluted) | B6: 115.4
A7: Cash & Equivalents (M) | B7: 1514.7
A8: Total Debt (M) | B8: 0
A9: Net Debt (M) | B9: =B8-B7 -> 0
A10: Base Year FCF (FY2025, M) | B10: 921.7
A12: WACC | B12: 0.1
A13: Terminal Growth Rate | B13: 0.025
A15: GROWTH ASSUMPTIONS (Base Case FCF growth) | B15: Y1 FY2026 | C15: Y2 FY2027 | D15: Y3 FY2028 | E15: Y4 FY2029 | F15: Y5 FY2030
A16: FCF Growth Rate | B16: -0.08 | C16: 0.08 | D16: 0.1 | E16: 0.08 | F16: 0.06
A18: PROJECTIONS
B19: Base FY25 | C19: Y1 FY2026 | D19: Y2 FY2027 | E19: Y3 FY2028 | F19: Y4 FY2029 | G19: Y5 FY2030
A20: Free Cash Flow | B20: =B10 -> 0 | C20: =B20*(1+B16) -> 0 | D20: =C20*(1+C16) -> 0 | E20: =D20*(1+D16) -> 0 | F20: =E20*(1+E16) -> 0 | G20: =F20*(1+F16) -> 0
A21: Discount Factor | C21: =1/(1+$B$12)^1 -> 0 | D21: =1/(1+$B$12)^2 -> 0 | E21: =1/(1+$B$12)^3 -> 0 | F21: =1/(1+$B$12)^4 -> 0 | G21: =1/(1+$B$12)^5 -> 0
A22: PV of FCF | C22: =C20*C21 -> 0 | D22: =D20*D21 -> 0 | E22: =E20*E21 -> 0 | F22: =F20*F21 -> 0 | G22: =G20*G21 -> 0
A24: VALUATION
A25: Sum of PV of FCF | B25: =SUM(C22:G22) -> 0
A26: Terminal FCF (Year 5 x (1+g)) | B26: =G20*(1+$B$13) -> 0
A27: Terminal Value | B27: =B26/($B$12-$B$13) -> 0
A28: PV of Terminal Value | B28: =B27*G21 -> 0
A29: Enterprise Value | B29: =B25+B28 -> 0
A30: Less: Net Debt | B30: =B9 -> 0
A31: Equity Value | B31: =B29-B30 -> 0
A32: INTRINSIC VALUE/SHARE | B32: =B31/B6 -> 0
A33: Terminal Value % of EV | B33: =B28/B29 -> 0
A34: Implied Exit Multiple (TV/FCF Y5) | B34: =B27/G20 -> 0
A36: ENTRY PRICE (15% IRR Target)
A37: PV of Yrs 1-5 FCF @15% | B37: =NPV(0.15,C20:G20) -> 0
A38: PV of Terminal Value @15% | B38: =B27/(1.15^5) -> 0
A39: Less: Net Debt | B39: =B9 -> 0
A40: Entry Price (15% CAGR) | B40: =(B37+B38-B39)/B6 -> 0
A42: Upside to Intrinsic Value | B42: =(B32-B5)/B5 -> 0
A43: Upside(+)/Discount(-) vs Entry Price | B43: =(B5-B40)/B5 -> 0

Sheet Scenarios
A1: LULU Scenario Comparison
A3: Metric | B3: Bear | C3: Base | D3: Bull
A4: Growth Rates (Y1-Y5) | B4: [-20, 0, 3, 4, 4] | C4: [-8, 8, 10, 8, 6] | D4: [2, 20, 18, 14, 10]
A5: WACC | B5: 0.115 | C5: 0.1 | D5: 0.09
A6: Terminal Growth | B6: 0.02 | C6: 0.025 | D6: 0.03
A7: Y5 FCF ($M) | B7: 821.5 | C7: 1153.3 | D7: 1669.4
A8: Terminal Value ($M) | B8: 8819.8 | C8: 15761.1 | D8: 28657.4
A9: Enterprise Value ($M) | B9: 7907.8 | C9: 13530.2 | D9: 23625.4
A10: Intrinsic Value/Share | B10: 81.65 | C10: 130.37 | D10: 217.85
A11: Upside/Downside | B11: -0.28 | C11: 0.15 | D11: 0.922
A12: Entry Price (15% IRR) | B12: 73.29 | C12: 109.52 | D12: 173.36
A13: Terminal % of EV | B13: 0.647 | C13: 0.723 | D13: 0.788
A14: Implied Exit Multiple | B14: 10.7 | C14: 13.7 | D14: 17.2
A16: Probability Weights
A17: Bear | B17: 0.25
A18: Base | B18: 0.5
A19: Bull | B19: 0.25
A20: Weighted IV | B20: 140.06
A21: Weighted Upside | B21: 0.235

Sheet Sensitivity
A1: Sensitivity Analysis (Base Case Growth Path)
A2: Intrinsic Value by WACC & Terminal Growth
A4: WACC \ Term G | B4: 0.015 | C4: 0.02 | D4: 0.025 | E4: 0.03 | F4: 0.035
A5: 0.08 | B5: =((('DCF Model'!$B$10*(1+'DCF Model'!$B$16)*(1+'DCF Model'!$C$16)*(1+'DCF Model'!$D$16)*(1+'DCF Model'!$E$16)*(1+'DCF Model'!$F$16)*(1+0.015)/(0.08-0.015))/(1+0.08)^5 + NPV(0.08,'DCF Model'!$C$20:'DCF Model'!$G$20) - 'DCF Model'!$B$9)/'DCF Model'!$B$6) -> 0 | C5: =((('DCF Model'!$B$10*(1+'DCF Model'!$B$16)*(1+'DCF Model'!$C$16)*(1+'DCF Model'!$D$16)*(1+'DCF Model'!$E$16)*(1+'DCF Model'!$F$16)*(1+0.02)/(0.08-0.02))/(1+0.08)^5 + NPV(0.08,'DCF Model'!$C$20:'DCF Model'!$G$20) - 'DCF Model'!$B$9)/'DCF Model'!$B$6) -> 0 | D5: =((('DCF Model'!$B$10*(1+'DCF Model'!$B$16)*(1+'DCF Model'!$C$16)*(1+'DCF Model'!$D$16)*(1+'DCF Model'!$E$16)*(1+'DCF Model'!$F$16)*(1+0.025)/(0.08-0.025))/(1+0.08)^5 + NPV(0.08,'DCF Model'!$C$20:'DCF Model'!$G$20) - 'DCF Model'!$B$9)/'DCF Model'!$B$6) -> 0 | E5: =((('DCF Model'!$B$10*(1+'DCF Model'!$B$16)*(1+'DCF Model'!$C$16)*(1+'DCF Model'!$D$16)*(1+'DCF Model'!$E$16)*(1+'DCF Model'!$F$16)*(1+0.03)/(0.08-0.03))/(1+0.08)^5 + NPV(0.08,'DCF Model'!$C$20:'DCF Model'!$G$20) - 'DCF Model'!$B$9)/'DCF Model'!$B$6) -> 0 | F5: =((('DCF Model'!$B$10*(1+'DCF Model'!$B$16)*(1+'DCF Model'!$C$16)*(1+'DCF Model'!$D$16)*(1+'DCF Model'!$E$16)*(1+'DCF Model'!$F$16)*(1+0.035)/(0.08-0.035))/(1+0.08)^5 + NPV(0.08,'DCF Model'!$C$20:'DCF Model'!$G$20) - 'DCF Model'!$B$9)/'DCF Model'!$B$6) -> 0
A6: 0.09 | B6: =((('DCF Model'!$B$10*(1+'DCF Model'!$B$16)*(1+'DCF Model'!$C$16)*(1+'DCF Model'!$D$16)*(1+'DCF Model'!$E$16)*(1+'DCF Model'!$F$16)*(1+0.015)/(0.09-0.015))/(1+0.09)^5 + NPV(0.09,'DCF Model'!$C$20:'DCF Model'!$G$20) - 'DCF Model'!$B$9)/'DCF Model'!$B$6) -> 0 | C6: =((('DCF Model'!$B$10*(1+'DCF Model'!$B$16)*(1+'DCF Model'!$C$16)*(1+'DCF Model'!$D$16)*(1+'DCF Model'!$E$16)*(1+'DCF Model'!$F$16)*(1+0.02)/(0.09-0.02))/(1+0.09)^5 + NPV(0.09,'DCF Model'!$C$20:'DCF Model'!$G$20) - 'DCF Model'!$B$9)/'DCF Model'!$B$6) -> 0 | D6: =((('DCF Model'!$B$10*(1+'DCF Model'!$B$16)*(1+'DCF Model'!$C$16)*(1+'DCF Model'!$D$16)*(1+'DCF Model'!$E$16)*(1+'DCF Model'!$F$16)*(1+0.025)/(0.09-0.025))/(1+0.09)^5 + NPV(0.09,'DCF Model'!$C$20:'DCF Model'!$G$20) - 'DCF Model'!$B$9)/'DCF Model'!$B$6) -> 0 | E6: =((('DCF Model'!$B$10*(1+'DCF Model'!$B$16)*(1+'DCF Model'!$C$16)*(1+'DCF Model'!$D$16)*(1+'DCF Model'!$E$16)*(1+'DCF Model'!$F$16)*(1+0.03)/(0.09-0.03))/(1+0.09)^5 + NPV(0.09,'DCF Model'!$C$20:'DCF Model'!$G$20) - 'DCF Model'!$B$9)/'DCF Model'!$B$6) -> 0 | F6: =((('DCF Model'!$B$10*(1+'DCF Model'!$B$16)*(1+'DCF Model'!$C$16)*(1+'DCF Model'!$D$16)*(1+'DCF Model'!$E$16)*(1+'DCF Model'!$F$16)*(1+0.035)/(0.09-0.035))/(1+0.09)^5 + NPV(0.09,'DCF Model'!$C$20:'DCF Model'!$G$20) - 'DCF Model'!$B$9)/'DCF Model'!$B$6) -> 0
A7: 0.1 | B7: =((('DCF Model'!$B$10*(1+'DCF Model'!$B$16)*(1+'DCF Model'!$C$16)*(1+'DCF Model'!$D$16)*(1+'DCF Model'!$E$16)*(1+'DCF Model'!$F$16)*(1+0.015)/(0.1-0.015))/(1+0.1)^5 + NPV(0.1,'DCF Model'!$C$20:'DCF Model'!$G$20) - 'DCF Model'!$B$9)/'DCF Model'!$B$6) -> 0 | C7: =((('DCF Model'!$B$10*(1+'DCF Model'!$B$16)*(1+'DCF Model'!$C$16)*(1+'DCF Model'!$D$16)*(1+'DCF Model'!$E$16)*(1+'DCF Model'!$F$16)*(1+0.02)/(0.1-0.02))/(1+0.1)^5 + NPV(0.1,'DCF Model'!$C$20:'DCF Model'!$G$20) - 'DCF Model'!$B$9)/'DCF Model'!$B$6) -> 0 | D7: =((('DCF Model'!$B$10*(1+'DCF Model'!$B$16)*(1+'DCF Model'!$C$16)*(1+'DCF Model'!$D$16)*(1+'DCF Model'!$E$16)*(1+'DCF Model'!$F$16)*(1+0.025)/(0.1-0.025))/(1+0.1)^5 + NPV(0.1,'DCF Model'!$C$20:'DCF Model'!$G$20) - 'DCF Model'!$B$9)/'DCF Model'!$B$6) -> 0 | E7: =((('DCF Model'!$B$10*(1+'DCF Model'!$B$16)*(1+'DCF Model'!$C$16)*(1+'DCF Model'!$D$16)*(1+'DCF Model'!$E$16)*(1+'DCF Model'!$F$16)*(1+0.03)/(0.1-0.03))/(1+0.1)^5 + NPV(0.1,'DCF Model'!$C$20:'DCF Model'!$G$20) - 'DCF Model'!$B$9)/'DCF Model'!$B$6) -> 0 | F7: =((('DCF Model'!$B$10*(1+'DCF Model'!$B$16)*(1+'DCF Model'!$C$16)*(1+'DCF Model'!$D$16)*(1+'DCF Model'!$E$16)*(1+'DCF Model'!$F$16)*(1+0.035)/(0.1-0.035))/(1+0.1)^5 + NPV(0.1,'DCF Model'!$C$20:'DCF Model'!$G$20) - 'DCF Model'!$B$9)/'DCF Model'!$B$6) -> 0
A8: 0.11 | B8: =((('DCF Model'!$B$10*(1+'DCF Model'!$B$16)*(1+'DCF Model'!$C$16)*(1+'DCF Model'!$D$16)*(1+'DCF Model'!$E$16)*(1+'DCF Model'!$F$16)*(1+0.015)/(0.11-0.015))/(1+0.11)^5 + NPV(0.11,'DCF Model'!$C$20:'DCF Model'!$G$20) - 'DCF Model'!$B$9)/'DCF Model'!$B$6) -> 0 | C8: =((('DCF Model'!$B$10*(1+'DCF Model'!$B$16)*(1+'DCF Model'!$C$16)*(1+'DCF Model'!$D$16)*(1+'DCF Model'!$E$16)*(1+'DCF Model'!$F$16)*(1+0.02)/(0.11-0.02))/(1+0.11)^5 + NPV(0.11,'DCF Model'!$C$20:'DCF Model'!$G$20) - 'DCF Model'!$B$9)/'DCF Model'!$B$6) -> 0 | D8: =((('DCF Model'!$B$10*(1+'DCF Model'!$B$16)*(1+'DCF Model'!$C$16)*(1+'DCF Model'!$D$16)*(1+'DCF Model'!$E$16)*(1+'DCF Model'!$F$16)*(1+0.025)/(0.11-0.025))/(1+0.11)^5 + NPV(0.11,'DCF Model'!$C$20:'DCF Model'!$G$20) - 'DCF Model'!$B$9)/'DCF Model'!$B$6) -> 0 | E8: =((('DCF Model'!$B$10*(1+'DCF Model'!$B$16)*(1+'DCF Model'!$C$16)*(1+'DCF Model'!$D$16)*(1+'DCF Model'!$E$16)*(1+'DCF Model'!$F$16)*(1+0.03)/(0.11-0.03))/(1+0.11)^5 + NPV(0.11,'DCF Model'!$C$20:'DCF Model'!$G$20) - 'DCF Model'!$B$9)/'DCF Model'!$B$6) -> 0 | F8: =((('DCF Model'!$B$10*(1+'DCF Model'!$B$16)*(1+'DCF Model'!$C$16)*(1+'DCF Model'!$D$16)*(1+'DCF Model'!$E$16)*(1+'DCF Model'!$F$16)*(1+0.035)/(0.11-0.035))/(1+0.11)^5 + NPV(0.11,'DCF Model'!$C$20:'DCF Model'!$G$20) - 'DCF Model'!$B$9)/'DCF Model'!$B$6) -> 0
A9: 0.12 | B9: =((('DCF Model'!$B$10*(1+'DCF Model'!$B$16)*(1+'DCF Model'!$C$16)*(1+'DCF Model'!$D$16)*(1+'DCF Model'!$E$16)*(1+'DCF Model'!$F$16)*(1+0.015)/(0.12-0.015))/(1+0.12)^5 + NPV(0.12,'DCF Model'!$C$20:'DCF Model'!$G$20) - 'DCF Model'!$B$9)/'DCF Model'!$B$6) -> 0 | C9: =((('DCF Model'!$B$10*(1+'DCF Model'!$B$16)*(1+'DCF Model'!$C$16)*(1+'DCF Model'!$D$16)*(1+'DCF Model'!$E$16)*(1+'DCF Model'!$F$16)*(1+0.02)/(0.12-0.02))/(1+0.12)^5 + NPV(0.12,'DCF Model'!$C$20:'DCF Model'!$G$20) - 'DCF Model'!$B$9)/'DCF Model'!$B$6) -> 0 | D9: =((('DCF Model'!$B$10*(1+'DCF Model'!$B$16)*(1+'DCF Model'!$C$16)*(1+'DCF Model'!$D$16)*(1+'DCF Model'!$E$16)*(1+'DCF Model'!$F$16)*(1+0.025)/(0.12-0.025))/(1+0.12)^5 + NPV(0.12,'DCF Model'!$C$20:'DCF Model'!$G$20) - 'DCF Model'!$B$9)/'DCF Model'!$B$6) -> 0 | E9: =((('DCF Model'!$B$10*(1+'DCF Model'!$B$16)*(1+'DCF Model'!$C$16)*(1+'DCF Model'!$D$16)*(1+'DCF Model'!$E$16)*(1+'DCF Model'!$F$16)*(1+0.03)/(0.12-0.03))/(1+0.12)^5 + NPV(0.12,'DCF Model'!$C$20:'DCF Model'!$G$20) - 'DCF Model'!$B$9)/'DCF Model'!$B$6) -> 0 | F9: =((('DCF Model'!$B$10*(1+'DCF Model'!$B$16)*(1+'DCF Model'!$C$16)*(1+'DCF Model'!$D$16)*(1+'DCF Model'!$E$16)*(1+'DCF Model'!$F$16)*(1+0.035)/(0.12-0.035))/(1+0.12)^5 + NPV(0.12,'DCF Model'!$C$20:'DCF Model'!$G$20) - 'DCF Model'!$B$9)/'DCF Model'!$B$6) -> 0
A11: Current Price: | B11: 113.37
A12: Implied WACC (approx) | B12: 0.107
A13: Implied Terminal Growth (approx) | B13: 0.023

Sheet Historical
A1: Historical Growth Rates
A3: Metric | B3: 3-Year CAGR | C3: 5-Year CAGR
A4: Revenue | B4: 0.11 | C4: 0.203
A5: EPS | B5: 0.257 | C5: 0.241
A6: Equity | B6: 0.164 | C6: 0.142
A7: FCF | B7: 0.411 | C7: 0.099
A8: Revenue 2yr CAGR (FY23-FY25) | B8: 0.074
A10: Growth Rate Source: | B10: revenue_2yr_cagr_fy23_fy25_anchored_to_fy2026_guidance
A12: Historical FCF Series ($M)
A13: FY2020 | B13: 574.1
A14: FY2021 | B14: 994.6
A15: FY2022 | B15: 327.8
A16: FY2023 | B16: 1644.3
A17: FY2024 | B17: 1583.5
A18: FY2025 | B18: 921.7

Sheet Sanity Check
A1: Sanity Check: Implied Multiples
A3: Scenario | B3: Price | C3: TTM P/E | D3: Fwd P/E (FY26 guide) | E3: P/B
A5: Bear | B5: 81.65 | C5: 6.61 | D5: 7.39 | E5: 1.95
A6: Base | B6: 130.37 | C6: 10.56 | D6: 11.8 | E6: 3.12
A7: Bull | B7: 217.85 | C7: 17.64 | D7: 19.72 | E7: 5.21
A8: Weighted | B8: 140.06 | C8: 11.34 | D8: 12.68 | E8: 3.35
A10: Current Market Multiples
A11: Trailing P/E (TTM) | B11: 9.18
A12: Forward P/E (FY26 guide) | B12: 10.26
A13: P/B | B13: 2.71
A14: EV/FCF (FY2025) | B14: 12.55
A15: EV/EBIT (FY2025) | B15: 5.23
A17: Historical Ranges
A18: P/E Hypergrowth (excluded) | B18: 37-73x (FY2018-FY2022, COVID/hypergrowth era -- excluded as DCF anchor)
A19: P/E Modern Range | B19: 13.2-28.3x (FY2024 28.3x, FY2025 13.2x -- the relevant comparison range)
A20: P/B Modern Range | B20: 4.2-11.9x (FY2024/FY2025, understated by aggressive buybacks reducing book value)
A21: EV/EBIT Modern Range | B21: 8.6-19.7x (FY2024/FY2025)
A23: Verdict
A24: PASS. Base case IV of $130.37 implies a TTM P/E of 10.6x and forward (FY26 guide) P/E of 11.8x -- both BELOW the FY2025 trough multiple of 13.2x and far below the FY2024 modern-range multiple of 28.3x. This means the base case is not assuming any re-rating at all; it is assuming the stock stays at a depressed multiple while FCF modestly recovers, and even so land at a 15% upside. The bull case (17.6-19.7x P/E, 5.2x P/B) implies a partial re-rating toward the low end of the FY2024 modern range -- plausible if the CEO transition succeeds, but explicitly does NOT reach the FY2024 28.3x level, let alone the hypergrowth-era 40-73x range. The bear case (6.6-7.4x P/E) implies further multiple compression below even today's 9.2x TTM level, consistent with a scenario where fundamentals keep deteriorating. Given the stock trades in the lower half of its 10-year range and multiples have already collapsed to multi-year lows, the base case's modest (+15%) upside without any multiple expansion is a conservative, credible result -- not an artifact of unrealistic re-rating assumptions.
