Workbook

Sheet Overview
A1: THIRD AGE HEALTH SERVICES LIMITED (TAH.NZ)
A2: DISCOUNTED CASH FLOW VALUATION MODEL
A3: As of December 30, 2025
A5: Company Description
A6: Third Age Health is New Zealand's premier provider of managed medical services for aged
A7: residential care facilities, private hospitals, and secure dementia centers. The company
A8: provides 24/7 healthcare services to elderly residents through two segments:
A9: 1) Aged Medical Residential Care Services - medical care for aged care sector
A10: 2) General Practice Medical Services - primary care services to community
A12: Key Investment Highlights
A13: • Aging population tailwind - NZ's 65+ population reaching 20% by 2028
A14: • Demand for 15,000 additional aged care beds by 2030
... A18: • Strong gross margins (~52%) and growing EBITDA margins
A20: Key Metrics Summary | B20: Current
A21: Share Price (NZD) | B21: 4.8
A22: Shares Outstanding (M) | B22: 9.95
A23: Market Cap (NZD M) | B23: =B21*B22 -> 47.76
A24: Net Debt (NZD M) | B24: 2.13
A25: Enterprise Value (NZD M) | B25: =B23+B24 -> 49.89
A26: TTM Revenue (NZD M) | B26: 20.32
A27: TTM EBITDA (NZD M) | B27: 4.68
A28: TTM Net Income (NZD M) | B28: 2.73
A29: TTM Free Cash Flow (NZD M) | B29: 3.5
A30: EV/Revenue | B30: =B25/B26 -> 2.4552165
A31: EV/EBITDA | B31: =B25/B27 -> 10.660256
A32: P/E Ratio | B32: =B23/B28 -> 17.494505
A33: EV/FCF | B33: =B25/B29 -> 14.254286
A34: FCF Yield (%) | B34: =B29/B23*100 -> 7.3283082

Sheet Historical Financials
A1: HISTORICAL FINANCIALS (NZD Millions)
A3: Fiscal Year End: March 31
B4: FY2022 | C4: FY2023 | D4: FY2024 | E4: FY2025 | F4: H1 FY2026
A5: Revenue | B5: 9.5 | C5: 11.5 | D5: 15.15 | E5: 19.08 | F5: 10.65
A6: Revenue Growth % | B6: N/A | C6: =C5/B5-1 -> 0.21052632 | D6: =D5/C5-1 -> 0.3173913 | E6: =E5/D5-1 -> 0.25940594 | F6: =F5/(E5/2)-1 -> 0.1163522
A8: Gross Profit | B8: 4.5 | C8: 5.5 | D8: 7.21 | E8: 9.95 | F8: 5.5
A9: Gross Margin % | B9: =B8/B5 -> 0.47368421 | C9: =C8/C5 -> 0.47826087 | D9: =D8/D5 -> 0.47590759 | E9: =E8/E5 -> 0.52148847 | F9: =F8/F5 -> 0.51643192
A11: EBITDA | B11: 1.8 | C11: 2.3 | D11: 3.2 | E11: 4.68 | F11: 2.8
A12: EBITDA Margin % | B12: =B11/B5 -> 0.18947368 | C12: =C11/C5 -> 0.2 | D12: =D11/D5 -> 0.21122112 | E12: =E11/E5 -> 0.24528302 | F12: =F11/F5 -> 0.2629108
A14: Depreciation & Amort. | B14: 0.2 | C14: 0.25 | D14: 0.35 | E14: 0.45 | F14: 0.25
A15: EBIT | B15: =B11-B14 -> 1.6 | C15: =C11-C14 -> 2.05 | D15: =D11-D14 -> 2.85 | E15: =E11-E14 -> 4.23 | F15: =F11-F14 -> 2.55
A16: EBIT Margin % | B16: =B15/B5 -> 0.16842105 | C16: =C15/C5 -> 0.17826087 | D16: =D15/D5 -> 0.18811881 | E16: =E15/E5 -> 0.22169811 | F16: =F15/F5 -> 0.23943662
A18: Interest Expense | B18: 0.1 | C18: 0.12 | D18: 0.18 | E18: 0.22 | F18: 0.12
A19: Pre-Tax Income | B19: =B15-B18 -> 1.5 | C19: =C15-C18 -> 1.93 | D19: =D15-D18 -> 2.67 | E19: =E15-E18 -> 4.01 | F19: =F15-F18 -> 2.43
A20: Income Tax (28%) | B20: =B19*0.28 -> 0.42 | C20: =C19*0.28 -> 0.5404 | D20: =D19*0.28 -> 0.7476 | E20: =E19*0.28 -> 1.1228 | F20: =F19*0.28 -> 0.6804
A21: Net Income | B21: =B19-B20 -> 1.08 | C21: =C19-C20 -> 1.3896 | D21: =D19-D20 -> 1.9224 | E21: =E19-E20 -> 2.8872 | F21: =F19-F20 -> 1.7496
A22: Net Margin % | B22: =B21/B5 -> 0.11368421 | C22: =C21/C5 -> 0.12083478 | D22: =D21/D5 -> 0.12689109 | E22: =E21/E5 -> 0.15132075 | F22: =F21/F5 -> 0.16428169
A24: Operating Cash Flow | B24: 1.6 | C24: 2.1 | D24: 3 | E24: 3.42 | F24: 2
A25: CapEx | B25: 0.05 | C25: 0.05 | D25: 0.05 | E25: 0.05 | F25: 0.03
A26: Free Cash Flow | B26: =B24-B25 -> 1.55 | C26: =C24-C25 -> 2.05 | D26: =D24-D25 -> 2.95 | E26: =E24-E25 -> 3.37 | F26: =F24-F25 -> 1.97
A27: FCF Conversion % | B27: =B26/B21 -> 1.4351852 | C27: =C26/C21 -> 1.4752447 | D27: =D26/D21 -> 1.5345402 | E27: =E26/E21 -> 1.1672208 | F27: =F26/F21 -> 1.1259717

Sheet DCF Assumptions
A1: DCF MODEL ASSUMPTIONS
A3: REVENUE ASSUMPTIONS
A4: Base Year Revenue (FY2025, NZD M) | B4: 19.08 | C4: Source: Company FY2025 Annual Report
A5: Year 1 Revenue Growth (FY2026) | B5: 0.3 | C5: Strong H1 momentum (+45%), Hub acquisition benefits
A6: Year 2 Revenue Growth (FY2027) | B6: 0.2 | C6: Continued organic growth + acquisitions
A7: Year 3 Revenue Growth (FY2028) | B7: 0.15 | C7: Industry tailwinds, 65+ population growth
A8: Year 4 Revenue Growth (FY2029) | B8: 0.12 | C8: Maturing growth trajectory
A9: Year 5 Revenue Growth (FY2030) | B9: 0.1 | C9: Sustainable long-term growth
A10: Terminal Growth Rate | B10: 0.025 | C10: NZ long-term GDP + population growth
A12: MARGIN ASSUMPTIONS
A13: EBITDA Margin Year 1 | B13: 0.25 | C13: Slight expansion from current 24.5%
A14: EBITDA Margin Year 2-3 | B14: 0.26 | C14: Scale benefits
A15: EBITDA Margin Year 4-5 | B15: 0.27 | C15: Operating leverage
A16: Terminal EBITDA Margin | B16: 0.27 | C16: Sustainable margin
A17: D&A as % of Revenue | B17: 0.023 | C17: Asset-light model
A18: CapEx as % of Revenue | B18: 0.005 | C18: Minimal capital requirements
A19: NWC Change as % of Rev Growth | B19: 0.05 | C19: Working capital efficiency
A22: WACC ASSUMPTIONS
A23: Risk-Free Rate (NZ 10Y Govt Bond) | B23: 0.045 | C23: Source: RBNZ, Dec 2025
A24: Equity Risk Premium | B24: 0.055 | C24: NZ market risk premium
A25: Unlevered Beta | B25: 0.8 | C25: Healthcare services sector
A26: Target Debt/Equity | B26: 0.4 | C26: Company target capital structure
A27: Cost of Debt (pre-tax) | B27: 0.07 | C27: Estimated bank lending rate
A28: Tax Rate | B28: 0.28 | C28: NZ corporate tax rate
A29: Company Specific Premium | B29: 0.02 | C29: Small cap / liquidity premium
A32: WACC CALCULATION
A33: Levered Beta | B33: =B25*(1+(1-B28)*B26) -> 1.0304
A34: Cost of Equity | B34: =B23+B33*B24+B29 -> 0.121672
A35: After-Tax Cost of Debt | B35: =B27*(1-B28) -> 0.0504
A36: Weight of Equity | B36: =1/(1+B26) -> 0.71428571
A37: Weight of Debt | B37: =B26/(1+B26) -> 0.28571429
A38: WACC | B38: =B34*B36+B35*B37 -> 0.10130857

Sheet DCF Model
A1: DISCOUNTED CASH FLOW MODEL
A3: Projection Period | B3: FY2026 | C3: FY2027 | D3: FY2028 | E3: FY2029 | F3: FY2030 | G3: Terminal
A4: Year | B4: 1 | C4: 2 | D4: 3 | E4: 4 | F4: 5
A6: REVENUE PROJECTIONS
A7: Revenue Growth Rate | B7: ='DCF Assumptions'!B5 -> 0.3 | C7: ='DCF Assumptions'!B6 -> 0.2 | D7: ='DCF Assumptions'!B7 -> 0.15 | E7: ='DCF Assumptions'!B8 -> 0.12 | F7: ='DCF Assumptions'!B9 -> 0.1 | G7: ='DCF Assumptions'!B10 -> 0.025
A8: Revenue (NZD M) | B8: ='DCF Assumptions'!B4*(1+B7) -> 24.804 | C8: =B8*(1+C7) -> 29.7648 | D8: =C8*(1+D7) -> 34.22952 | E8: =D8*(1+E7) -> 38.337062 | F8: =E8*(1+F7) -> 42.170769
A10: EBITDA CALCULATION
A11: EBITDA Margin | B11: ='DCF Assumptions'!B13 -> 0.25 | C11: ='DCF Assumptions'!B14 -> 0.26 | D11: ='DCF Assumptions'!B14 -> 0.26 | E11: ='DCF Assumptions'!B15 -> 0.27 | F11: ='DCF Assumptions'!B15 -> 0.27
A12: EBITDA (NZD M) | B12: =B8*B11 -> 6.201 | C12: =C8*C11 -> 7.738848 | D12: =D8*D11 -> 8.8996752 | E12: =E8*E11 -> 10.351007 | F12: =F8*F11 -> 11.386108
A14: FREE CASH FLOW CALCULATION
A15: EBITDA | B15: =B12 -> 6.201 | C15: =C12 -> 7.738848 | D15: =D12 -> 8.8996752 | E15: =E12 -> 10.351007 | F15: =F12 -> 11.386108
A16: Less: D&A | B16: =-B8*'DCF Assumptions'!$B$17 -> -0.570492 | C16: =-C8*'DCF Assumptions'!$B$17 -> -0.6845904 | D16: =-D8*'DCF Assumptions'!$B$17 -> -0.78727896 | E16: =-E8*'DCF Assumptions'!$B$17 -> -0.88175244 | F16: =-F8*'DCF Assumptions'!$B$17 -> -0.96992768
A17: EBIT | B17: =B15+B16 -> 5.630508 | C17: =C15+C16 -> 7.0542576 | D17: =D15+D16 -> 8.1123962 | E17: =E15+E16 -> 9.4692544 | F17: =F15+F16 -> 10.41618
A18: Less: Taxes (28%) | B18: =-B17*0.28 -> -1.5765422 | C18: =-C17*0.28 -> -1.9751921 | D18: =-D17*0.28 -> -2.2714709 | E18: =-E17*0.28 -> -2.6513912 | F18: =-F17*0.28 -> -2.9165304
A19: NOPAT (Net Operating Profit After Tax) | B19: =B17+B18 -> 4.0539658 | C19: =C17+C18 -> 5.0790655 | D19: =D17+D18 -> 5.8409253 | E19: =E17+E18 -> 6.8178632 | F19: =F17+F18 -> 7.4996495
A20: Add: D&A | B20: =-B16 -> 0.570492 | C20: =-C16 -> 0.6845904 | D20: =-D16 -> 0.78727896 | E20: =-E16 -> 0.88175244 | F20: =-F16 -> 0.96992768
A21: Less: CapEx | B21: =-B8*'DCF Assumptions'!$B$18 -> -0.12402 | C21: =-C8*'DCF Assumptions'!$B$18 -> -0.148824 | D21: =-D8*'DCF Assumptions'!$B$18 -> -0.1711476 | E21: =-E8*'DCF Assumptions'!$B$18 -> -0.19168531 | F21: =-F8*'DCF Assumptions'!$B$18 -> -0.21085384
A22: Less: Change in NWC | B22: =-(B8-'DCF Assumptions'!B4)*'DCF Assumptions'!$B$19 -> -0.2862 | C22: =-(C8-B8)*'DCF Assumptions'!$B$19 -> -0.24804 | D22: =-(D8-C8)*'DCF Assumptions'!$B$19 -> -0.223236 | E22: =-(E8-D8)*'DCF Assumptions'!$B$19 -> -0.20537712 | F22: =-(F8-E8)*'DCF Assumptions'!$B$19 -> -0.19168531
A23: Unlevered Free Cash Flow | B23: =B19+B20+B21+B22 -> 4.2142378 | C23: =C19+C20+C21+C22 -> 5.3667919 | D23: =D19+D20+D21+D22 -> 6.2338207 | E23: =E19+E20+E21+E22 -> 7.3025532 | F23: =F19+F20+F21+F22 -> 8.067038
A25: TERMINAL VALUE
A26: Terminal Growth Rate | B26: ='DCF Assumptions'!B10 -> 0.025
A27: Terminal EBITDA Margin | B27: ='DCF Assumptions'!B16 -> 0.27
A28: Terminal Year FCF | B28: =F23*(1+B26) -> 8.268714
A29: WACC | B29: ='DCF Assumptions'!B38 -> 0.10130857
A30: Terminal Value (Gordon Growth) | B30: =B28/(B29-B26) -> 108.35891
A31: Terminal Value / Final Year EBITDA | B31: =B30/F12 -> 9.5167654
A33: DCF VALUATION
A34: Discount Rate (WACC) | B34: ='DCF Assumptions'!B38 -> 0.10130857
A35: Discount Factor | B35: =1/(1+$B$34)^1 -> 0.90801073 | C35: =1/(1+$B$34)^2 -> 0.82448349 | D35: =1/(1+$B$34)^3 -> 0.74863985 | E35: =1/(1+$B$34)^4 -> 0.67977302 | F35: =1/(1+$B$34)^5 -> 0.61724119
A36: Present Value of FCF | B36: =B23*B35 -> 3.8265731 | C36: =C23*C35 -> 4.4248313 | D36: =D23*D35 -> 4.6668866 | E36: =E23*E35 -> 4.9640786 | F36: =F23*F35 -> 4.9793082
A37: PV of Terminal Value | F37: =B30*F35 -> 66.883586
A39: Sum of PV of FCFs | B39: =SUM(B36:F36) -> 22.861678
A40: PV of Terminal Value | B40: =F37 -> 66.883586
A41: Enterprise Value | B41: =B39+B40 -> 89.745264
A42: Less: Net Debt | B42: -2.13
A43: Equity Value (NZD M) | B43: =B41+B42 -> 87.615264
A44: Shares Outstanding (M) | B44: 9.95
A45: Implied Share Price (NZD) | B45: =B43/B44 -> 8.8055541
A47: Current Share Price (NZD) | B47: 4.8
A48: Upside / (Downside) % | B48: =(B45-B47)/B47 -> 0.83449044

Sheet Sensitivity
A1: SENSITIVITY ANALYSIS
A3: Base Case Implied Share Price (NZD) | B3: ='DCF Model'!B45 -> 8.8055541
A5: WACC vs Terminal Growth Rate
A7: Terminal Growth → | C7: 0.015 | D7: 0.02 | E7: 0.025 | F7: 0.03 | G7: 0.035
A8: WACC ↓
B9: 0.09 | C9: =(('DCF Model'!F23*(1+0.015))/(0.09-0.015)*1/(1+0.09)^5+'DCF Model'!B39+'DCF Model'!B42)/'DCF Model'!B44 -> 9.2147971 | D9: =(('DCF Model'!F23*(1+0.02))/(0.09-0.02)*1/(1+0.09)^5+'DCF Model'!B39+'DCF Model'!B42)/'DCF Model'!B44 -> 9.7618077 | E9: =(('DCF Model'!F23*(1+0.025))/(0.09-0.025)*1/(1+0.09)^5+'DCF Model'!B39+'DCF Model'!B42)/'DCF Model'!B44 -> 10.392974 | F9: =(('DCF Model'!F23*(1+0.03))/(0.09-0.03)*1/(1+0.09)^5+'DCF Model'!B39+'DCF Model'!B42)/'DCF Model'!B44 -> 11.129334 | G9: =(('DCF Model'!F23*(1+0.035))/(0.09-0.035)*1/(1+0.09)^5+'DCF Model'!B39+'DCF Model'!B42)/'DCF Model'!B44 -> 11.999578
B10: 0.1 | C10: =(('DCF Model'!F23*(1+0.015))/(0.1-0.015)*1/(1+0.1)^5+'DCF Model'!B39+'DCF Model'!B42)/'DCF Model'!B44 -> 8.0949731 | D10: =(('DCF Model'!F23*(1+0.02))/(0.1-0.02)*1/(1+0.1)^5+'DCF Model'!B39+'DCF Model'!B42)/'DCF Model'!B44 -> 8.5021483 | E10: =(('DCF Model'!F23*(1+0.025))/(0.1-0.025)*1/(1+0.1)^5+'DCF Model'!B39+'DCF Model'!B42)/'DCF Model'!B44 -> 8.9636136 | F10: =(('DCF Model'!F23*(1+0.03))/(0.1-0.03)*1/(1+0.1)^5+'DCF Model'!B39+'DCF Model'!B42)/'DCF Model'!B44 -> 9.4910025 | G10: =(('DCF Model'!F23*(1+0.035))/(0.1-0.035)*1/(1+0.1)^5+'DCF Model'!B39+'DCF Model'!B42)/'DCF Model'!B44 -> 10.099528
B11: 0.11 | C11: =(('DCF Model'!F23*(1+0.015))/(0.11-0.015)*1/(1+0.11)^5+'DCF Model'!B39+'DCF Model'!B42)/'DCF Model'!B44 -> 7.224242 | D11: =(('DCF Model'!F23*(1+0.02))/(0.11-0.02)*1/(1+0.11)^5+'DCF Model'!B39+'DCF Model'!B42)/'DCF Model'!B44 -> 7.5365643 | E11: =(('DCF Model'!F23*(1+0.025))/(0.11-0.025)*1/(1+0.11)^5+'DCF Model'!B39+'DCF Model'!B42)/'DCF Model'!B44 -> 7.8856304 | F11: =(('DCF Model'!F23*(1+0.03))/(0.11-0.03)*1/(1+0.11)^5+'DCF Model'!B39+'DCF Model'!B42)/'DCF Model'!B44 -> 8.2783297 | G11: =(('DCF Model'!F23*(1+0.035))/(0.11-0.035)*1/(1+0.11)^5+'DCF Model'!B39+'DCF Model'!B42)/'DCF Model'!B44 -> 8.723389
B12: 0.12 | C12: =(('DCF Model'!F23*(1+0.015))/(0.12-0.015)*1/(1+0.12)^5+'DCF Model'!B39+'DCF Model'!B42)/'DCF Model'!B44 -> 6.5306935 | D12: =(('DCF Model'!F23*(1+0.02))/(0.12-0.02)*1/(1+0.12)^5+'DCF Model'!B39+'DCF Model'!B42)/'DCF Model'!B44 -> 6.7760511 | E12: =(('DCF Model'!F23*(1+0.025))/(0.12-0.025)*1/(1+0.12)^5+'DCF Model'!B39+'DCF Model'!B42)/'DCF Model'!B44 -> 7.0472359 | F12: =(('DCF Model'!F23*(1+0.03))/(0.12-0.03)*1/(1+0.12)^5+'DCF Model'!B39+'DCF Model'!B42)/'DCF Model'!B44 -> 7.3485524 | G12: =(('DCF Model'!F23*(1+0.035))/(0.12-0.035)*1/(1+0.12)^5+'DCF Model'!B39+'DCF Model'!B42)/'DCF Model'!B44 -> 7.6853178
B13: 0.13 | C13: =(('DCF Model'!F23*(1+0.015))/(0.13-0.015)*1/(1+0.13)^5+'DCF Model'!B39+'DCF Model'!B42)/'DCF Model'!B44 -> 5.9674765 | D13: =(('DCF Model'!F23*(1+0.02))/(0.13-0.02)*1/(1+0.13)^5+'DCF Model'!B39+'DCF Model'!B42)/'DCF Model'!B44 -> 6.1640191 | E13: =(('DCF Model'!F23*(1+0.025))/(0.13-0.025)*1/(1+0.13)^5+'DCF Model'!B39+'DCF Model'!B42)/'DCF Model'!B44 -> 6.37928 | F13: =(('DCF Model'!F23*(1+0.03))/(0.13-0.03)*1/(1+0.13)^5+'DCF Model'!B39+'DCF Model'!B42)/'DCF Model'!B44 -> 6.6160671 | G13: =(('DCF Model'!F23*(1+0.035))/(0.13-0.035)*1/(1+0.13)^5+'DCF Model'!B39+'DCF Model'!B42)/'DCF Model'!B44 -> 6.8777791
A16: Revenue Growth vs EBITDA Margin
A18: EBITDA Margin → | C18: 0.23 | D18: 0.25 | E18: 0.27 | F18: 0.29 | G18: 0.31
A19: Rev Growth Y1 ↓
B20: 0.2
B21: 0.25
B22: 0.3
B23: 0.35
B24: 0.4
A26: Note: Base case highlighted in yellow

Sheet Valuation Summary
A1: VALUATION SUMMARY - FOOTBALL FIELD
A3: Valuation Methodology | B3: Low | C3: Base | D3: High
A4: DCF (WACC 10-12%, TG 2-3%) | B4: =MIN(Sensitivity!C13,Sensitivity!G9) -> 5.9674765 | C4: ='DCF Model'!B45 -> 8.8055541 | D4: =MAX(Sensitivity!C9,Sensitivity!G13) -> 9.2147971
A5: EV/EBITDA (7-12x) | B5: =(7*'DCF Model'!F12-'DCF Model'!B42)/'DCF Model'!B44 -> 8.2243973 | C5: =(9.5*'DCF Model'!F12-'DCF Model'!B42)/'DCF Model'!B44 -> 11.085228 | D5: =(12*'DCF Model'!F12-'DCF Model'!B42)/'DCF Model'!B44 -> 13.946059
A6: EV/Revenue (2-3x) | B6: =(2*'DCF Model'!F8-'DCF Model'!B42)/'DCF Model'!B44 -> 8.6906068 | C6: =(2.5*'DCF Model'!F8-'DCF Model'!B42)/'DCF Model'!B44 -> 10.809741 | D6: =(3*'DCF Model'!F8-'DCF Model'!B42)/'DCF Model'!B44 -> 12.928875
A7: P/E (15-25x) | B7: =15*'DCF Model'!F19/'DCF Model'!B44 -> 11.306004 | C7: =20*'DCF Model'!F19/'DCF Model'!B44 -> 15.074672 | D7: =25*'DCF Model'!F19/'DCF Model'!B44 -> 18.84334
A9: Current Share Price | B9: 4.8
A11: INVESTMENT RECOMMENDATION
A12: Based on DCF analysis, the intrinsic value of TAH.NZ appears to be
A13: above the current trading price, suggesting potential upside.
A15: Key Risks:
A16: • Healthcare worker shortages could pressure margins
A17: • Government funding policy changes
A18: • Competition from larger players
A19: • Key personnel risk (lean management team)
A20: • Small cap liquidity risk
