Workbook

Sheet Summary
A1: NOVO NORDISK (NVO) - DCF VALUATION MODEL
A2: Deep Dive Analysis & Discounted Cash Flow Valuation
A3: Model Date: January 4, 2026
A5: KEY VALUATION OUTPUTS
A6: Implied Share Price (Base Case) | B6: =DCF!E35 -> 347.11931 | C6: $
A7: Current Share Price | B7: 52.39 | C7: $
A8: Upside / (Downside) | B8: =(B6-B7)/B7 -> 5.6256787 | C8: %
A10: Enterprise Value | B10: =DCF!E30 -> 281.90392 | C10: $B
A11: Equity Value | B11: =DCF!E32 -> 0 | C11: $B
A12: Shares Outstanding (B) | B12: 4.45 | C12: #
A15: CURRENT MARKET DATA
A16: Stock Price (USD) | B16: 52.39 | C16: Source: Yahoo Finance, Jan 4, 2026
A17: Market Cap ($B) | B17: 232.8
A18: Enterprise Value ($B) | B18: 238.1
A19: Shares Outstanding (B) | B19: 4.45
A20: 52-Week High | B20: 93.8
A21: 52-Week Low | B21: 43.08
A22: Beta | B22: 0.35 | C22: 5-Year Monthly
A23: P/E Ratio (TTM) | B23: 14.28
A24: EV/EBITDA | B24: 10.03
A25: Dividend Yield | B25: 3.30%
A28: INVESTMENT THESIS
A29: STRENGTHS:
A30: • Dominant GLP-1 market leader with Ozempic and Wegovy franchises
A31: • FDA approval of oral Wegovy (Dec 2025) - first oral GLP-1 for obesity
A32: • CagriSema NDA filed (Dec 2025) - next-gen obesity treatment with 22.7% weight loss
A33: • 84.7% gross margin with strong operating leverage
A34: • 45+ million patients currently on Novo treatments globally
A36: RISKS:
A37: • Intensifying competition from Eli Lilly (Zepbound/Mounjaro)
A38: • Compounded GLP-1 usage impacting branded penetration
A39: • 2025 guidance reduced: 13-21% sales growth (from 16-24%)
A40: • Semaglutide patent expiry in select markets beginning 2026
A41: • Execution challenges under new leadership

Sheet Assumptions
A1: DCF MODEL ASSUMPTIONS
A3: REVENUE GROWTH ASSUMPTIONS
A4: Year | B4: Revenue Growth Rate | C4: Rationale
A5: 2024A | B5: 0.25 | C5: Actual: 25% growth driven by GLP-1 momentum
A6: 2025E | B6: 0.17 | C6: Guidance: 13-21% (midpoint 17%) - reduced due to compounding impact
A7: 2026E | B7: 0.15 | C7: Wegovy pill launch, CagriSema approval expected, continued expansion
A8: 2027E | B8: 0.13 | C8: Maturing GLP-1 market, increased competition from Lilly
A9: 2028E | B9: 0.11 | C9: Market penetration increasing, pricing pressure
A10: 2029E | B10: 0.09 | C10: Steady state growth approaching
A11: 2030E | B11: 0.07 | C11: Near-terminal growth rate
A14: MARGIN ASSUMPTIONS
A15: Metric | B15: Value | C15: Source/Note
A16: Gross Margin | B16: 0.847 | C16: 2024 Actual: 84.7%
A17: Operating Margin (Base) | B17: 0.44 | C17: 2024 Actual: ~44%
A18: Operating Margin (Terminal) | B18: 0.42 | C18: Slight compression due to competition
A19: D&A % of Revenue | B19: 0.025 | C19: Historical average
A20: CapEx % of Revenue | B20: 0.12 | C20: Elevated for capacity expansion
A21: Tax Rate | B21: 0.206 | C21: 2024 Actual: 20.6%
A22: NWC % of Revenue | B22: 0.05 | C22: Net Working Capital investment
A25: WACC ASSUMPTIONS
A26: Component | B26: Value | C26: Source/Calculation
A27: Risk-Free Rate | B27: 0.043 | C27: 10-Year US Treasury
A28: Equity Risk Premium | B28: 0.05 | C28: Historical ERP
A29: Beta (Levered) | B29: 0.75 | C29: Adjusted beta (Yahoo: 0.35, Infront: 1.14)
A30: Cost of Equity | B30: =B27+B28*B29 -> 0.0805 | C30: CAPM: Rf + Beta * ERP
A31: Cost of Debt (Pre-Tax) | B31: 0.045 | C31: Estimated based on credit rating
A32: Tax Rate | B32: 0.206 | C32: Effective tax rate
A33: Cost of Debt (After-Tax) | B33: =B31*(1-B32) -> 0.03573 | C33: Pre-tax * (1 - Tax Rate)
A34: Weight of Equity | B34: 0.94 | C34: Market value weights
A35: Weight of Debt | B35: 0.06 | C35: Total Debt / EV
A36: WACC | B36: =B30*B34+B33*B35 -> 0.0778138 | C36: Re*We + Rd*Wd
A39: TERMINAL VALUE ASSUMPTIONS
A40: Terminal Growth Rate | B40: 0.03 | C40: Long-term GDP + inflation proxy
A41: Exit EV/EBITDA Multiple | B41: 12 | C41: Peer comparison (conservative)

Sheet Projections
A1: FINANCIAL PROJECTIONS ($B USD)
A3: Metric | B3: 2024A | C3: 2025E | D3: 2026E | E3: 2027E | F3: 2028E | G3: 2029E | H3: 2030E
A4: Revenue
A5: Revenue Growth % | B5: 0.25 | C5: =Assumptions!B6 -> 0.17 | D5: =Assumptions!B7 -> 0.15 | E5: =Assumptions!B8 -> 0.13 | F5: =Assumptions!B9 -> 0.11 | G5: =Assumptions!B10 -> 0.09 | H5: =Assumptions!B11 -> 0.07
A6: Revenue | B6: 40.5 | C6: =B6*(1+C5) -> 47.385 | D6: =C6*(1+D5) -> 54.49275 | E6: =D6*(1+E5) -> 61.576808 | F6: =E6*(1+F5) -> 68.350256 | G6: =F6*(1+G5) -> 74.501779 | H6: =G6*(1+H5) -> 79.716904
A8: Profitability
A9: Gross Margin % | B9: 0.847 | C9: 0.845 | D9: 0.843 | E9: 0.84 | F9: 0.838 | G9: 0.835 | H9: 0.833
A10: Gross Profit | B10: =B6*B9 -> 34.3035 | C10: =C6*C9 -> 40.040325 | D10: =D6*D9 -> 45.937388 | E10: =E6*E9 -> 51.724518 | F10: =F6*F9 -> 57.277515 | G10: =G6*G9 -> 62.208986 | H10: =H6*H9 -> 66.404181
A11: Operating Margin % | B11: 0.44 | C11: 0.43 | D11: 0.43 | E11: 0.42 | F11: 0.42 | G11: 0.42 | H11: 0.42
A12: Operating Income (EBIT) | B12: =B6*B11 -> 17.82 | C12: =C6*C11 -> 20.37555 | D12: =D6*D11 -> 23.431883 | E12: =E6*E11 -> 25.862259 | F12: =F6*F11 -> 28.707108 | G12: =G6*G11 -> 31.290747 | H12: =H6*H11 -> 33.4811
A13: D&A % of Revenue | B13: 0.025 | C13: 0.025 | D13: 0.025 | E13: 0.025 | F13: 0.025 | G13: 0.025 | H13: 0.025
A14: Depreciation & Amortization | B14: =B6*B13 -> 1.0125 | C14: =C6*C13 -> 1.184625 | D14: =D6*D13 -> 1.3623188 | E14: =E6*E13 -> 1.5394202 | F14: =F6*F13 -> 1.7087564 | G14: =G6*G13 -> 1.8625445 | H14: =H6*H13 -> 1.9929226
A15: EBITDA | B15: =B12+B14 -> 18.8325 | C15: =C12+C14 -> 21.560175 | D15: =D12+D14 -> 24.794201 | E15: =E12+E14 -> 27.401679 | F15: =F12+F14 -> 30.415864 | G15: =G12+G14 -> 33.153292 | H15: =H12+H14 -> 35.474022
A16: EBITDA Margin % | B16: =B15/B6 -> 0.465 | C16: =C15/C6 -> 0.455 | D16: =D15/D6 -> 0.455 | E16: =E15/E6 -> 0.445 | F16: =F15/F6 -> 0.445 | G16: =G15/G6 -> 0.445 | H16: =H15/H6 -> 0.445
A18: Free Cash Flow Calculation
A19: EBIT | B19: =B12 -> 17.82 | C19: =C12 -> 20.37555 | D19: =D12 -> 23.431883 | E19: =E12 -> 25.862259 | F19: =F12 -> 28.707108 | G19: =G12 -> 31.290747 | H19: =H12 -> 33.4811
A20: Tax Rate | B20: 0.206 | C20: 0.206 | D20: 0.206 | E20: 0.206 | F20: 0.206 | G20: 0.206 | H20: 0.206
A21: Taxes | B21: =-B19*B20 -> -3.67092 | C21: =-C19*C20 -> -4.1973633 | D21: =-D19*D20 -> -4.8269678 | E21: =-E19*E20 -> -5.3276254 | F21: =-F19*F20 -> -5.9136642 | G21: =-G19*G20 -> -6.445894 | H21: =-H19*H20 -> -6.8971065
A22: NOPAT (EBIT * (1-T)) | B22: =B19+B21 -> 14.14908 | C22: =C19+C21 -> 16.178187 | D22: =D19+D21 -> 18.604915 | E22: =E19+E21 -> 20.534634 | F22: =F19+F21 -> 22.793443 | G22: =G19+G21 -> 24.844853 | H22: =H19+H21 -> 26.583993
A23: (+) D&A | B23: =B14 -> 1.0125 | C23: =C14 -> 1.184625 | D23: =D14 -> 1.3623188 | E23: =E14 -> 1.5394202 | F23: =F14 -> 1.7087564 | G23: =G14 -> 1.8625445 | H23: =H14 -> 1.9929226
A24: CapEx % of Revenue | B24: 0.16 | C24: 0.14 | D24: 0.12 | E24: 0.11 | F24: 0.1 | G24: 0.09 | H24: 0.08
A25: (-) CapEx | B25: =-B6*B24 -> -6.48 | C25: =-C6*C24 -> -6.6339 | D25: =-D6*D24 -> -6.53913 | E25: =-E6*E24 -> -6.7734488 | F25: =-F6*F24 -> -6.8350256 | G25: =-G6*G24 -> -6.7051601 | H25: =-H6*H24 -> -6.3773523
A26: NWC % of Revenue | B26: 0.05 | C26: 0.05 | D26: 0.05 | E26: 0.05 | F26: 0.05 | G26: 0.05 | H26: 0.05
A27: (-) Change in NWC | B27: -0.5 | C27: =-(C6-B6)*C26 -> -0.34425 | D27: =-(D6-C6)*D26 -> -0.3553875 | E27: =-(E6-D6)*E26 -> -0.35420287 | F27: =-(F6-E6)*F26 -> -0.33867244 | G27: =-(G6-F6)*G26 -> -0.30757615 | H27: =-(H6-G6)*H26 -> -0.26075623
A28: Unlevered Free Cash Flow | B28: =B22+B23+B25+B27 -> 8.18158 | C28: =C22+C23+C25+C27 -> 10.384662 | D28: =D22+D23+D25+D27 -> 13.072716 | E28: =E22+E23+E25+E27 -> 14.946402 | F28: =F22+F23+F25+F27 -> 17.328502 | G28: =G22+G23+G25+G27 -> 19.694662 | H28: =H22+H23+H25+H27 -> 21.938807

Sheet DCF
A1: DISCOUNTED CASH FLOW ANALYSIS
B3: 2025E | C3: 2026E | D3: 2027E | E3: 2028E | F3: 2029E | G3: 2030E
A4: Unlevered FCF | B4: =Projections!C28 -> 10.384662 | C4: =Projections!D28 -> 13.072716 | D4: =Projections!E28 -> 14.946402 | E4: =Projections!F28 -> 17.328502 | F4: =Projections!G28 -> 19.694662 | G4: =Projections!H28 -> 21.938807
A6: WACC | B6: =Assumptions!B36 -> 0.0778138
A7: Discount Period | B7: 0.5 | C7: 1.5 | D7: 2.5 | E7: 3.5 | F7: 4.5 | G7: 5.5
A8: Discount Factor | B8: =1/(1+$B$6)^B7 -> 0.96322585 | C8: =1/(1+$B$6)^C7 -> 0.89368484 | D8: =1/(1+$B$6)^D7 -> 0.82916441 | E8: =1/(1+$B$6)^E7 -> 0.76930209 | F8: =1/(1+$B$6)^F7 -> 0.71376159 | G8: =1/(1+$B$6)^G7 -> 0.66223088
A9: Present Value of FCF | B9: =B4*B8 -> 10.002775 | C9: =C4*C8 -> 11.682888 | D9: =D4*D8 -> 12.393025 | E9: =E4*E8 -> 13.330853 | F9: =F4*F8 -> 14.057293 | G9: =G4*G8 -> 14.528556
A12: TERMINAL VALUE CALCULATION
A14: Perpetuity Growth Method
A15: Terminal Growth Rate | B15: =Assumptions!B40 -> 0.03
A16: Terminal Year FCF (2030) | B16: =G4 -> 21.938807
A17: Terminal Value (Perpetuity) | B17: =B16*(1+B15)/(B6-B15) -> 472.60355
A18: PV of Terminal Value | B18: =B17*G8 -> 312.97266
A20: Exit Multiple Method
A21: Exit EV/EBITDA Multiple | B21: =Assumptions!B41 -> 12
A22: Terminal Year EBITDA | B22: =Projections!H15 -> 35.474022
A23: Terminal Value (Multiple) | B23: =B21*B22 -> 425.68827
A24: PV of Terminal Value | B24: =B23*G8 -> 281.90392
A27: ENTERPRISE VALUE CALCULATION
D28: Perpetuity | E28: Exit Multiple
A29: Sum of PV of FCFs | D29: =SUM(B9:G9) -> 75.995389 | E29: =SUM(B9:G9) -> 75.995389
A30: PV of Terminal Value | D30: =B18 -> 312.97266 | E30: =B24 -> 281.90392
A31: Enterprise Value | D31: =D29+D30 -> 388.96805 | E31: =E29+E30 -> 357.89931
A33: (-) Total Debt | D33: -15.9 | E33: -15.9
A34: (+) Cash & Equivalents | D34: 5.12 | E34: 5.12
A35: Equity Value | D35: =D31+D33+D34 -> 378.18805 | E35: =E31+E33+E34 -> 347.11931
A37: Shares Outstanding (B) | D37: 4.45 | E37: 4.45
A38: Implied Share Price | D38: =D35/D37 -> 84.986079 | E38: =E35/E37 -> 78.004338
A40: Current Share Price | D40: 52.39 | E40: 52.39
A41: Upside / (Downside) % | D41: =(D38-D40)/D40 -> 0.62218132 | E41: =(E38-E40)/E40 -> 0.48891656

Sheet Sensitivity
A1: SENSITIVITY ANALYSIS
A3: IMPLIED SHARE PRICE: WACC vs Terminal Growth Rate
B5: Terminal Growth Rate
C6: 0.02 | D6: 0.025 | E6: 0.03 | F6: 0.035 | G6: 0.04
A7: WACC | B7: 0.055 | C7: =($B$20+$B$21*(1+C6)/(B7-C6)*(1/(1+B7)^$B$22)-15.9+5.12)/4.45 -> 121.68294 | D7: =($B$20+$B$21*(1+D6)/(B7-D6)*(1/(1+B7)^$B$22)-15.9+5.12)/4.45 -> 140.133 | E7: =($B$20+$B$21*(1+E6)/(B7-E6)*(1/(1+B7)^$B$22)-15.9+5.12)/4.45 -> 165.96307 | F7: =($B$20+$B$21*(1+F6)/(B7-F6)*(1/(1+B7)^$B$22)-15.9+5.12)/4.45 -> 204.70819 | G7: =($B$20+$B$21*(1+G6)/(B7-G6)*(1/(1+B7)^$B$22)-15.9+5.12)/4.45 -> 269.28337
B8: 0.06 | C8: =($B$20+$B$21*(1+C6)/(B8-C6)*(1/(1+B8)^$B$22)-15.9+5.12)/4.45 -> 105.90053 | D8: =($B$20+$B$21*(1+D6)/(B8-D6)*(1/(1+B8)^$B$22)-15.9+5.12)/4.45 -> 119.44677 | E8: =($B$20+$B$21*(1+E6)/(B8-E6)*(1/(1+B8)^$B$22)-15.9+5.12)/4.45 -> 137.50841 | F8: =($B$20+$B$21*(1+F6)/(B8-F6)*(1/(1+B8)^$B$22)-15.9+5.12)/4.45 -> 162.79471 | G8: =($B$20+$B$21*(1+G6)/(B8-G6)*(1/(1+B8)^$B$22)-15.9+5.12)/4.45 -> 200.72417
B9: 0.065 | C9: =($B$20+$B$21*(1+C6)/(B9-C6)*(1/(1+B9)^$B$22)-15.9+5.12)/4.45 -> 93.689845 | D9: =($B$20+$B$21*(1+D6)/(B9-D6)*(1/(1+B9)^$B$22)-15.9+5.12)/4.45 -> 104.00504 | E9: =($B$20+$B$21*(1+E6)/(B9-E6)*(1/(1+B9)^$B$22)-15.9+5.12)/4.45 -> 117.26742 | F9: =($B$20+$B$21*(1+F6)/(B9-F6)*(1/(1+B9)^$B$22)-15.9+5.12)/4.45 -> 134.95061 | G9: =($B$20+$B$21*(1+G6)/(B9-G6)*(1/(1+B9)^$B$22)-15.9+5.12)/4.45 -> 159.70707
B10: 0.07 | C10: =($B$20+$B$21*(1+C6)/(B10-C6)*(1/(1+B10)^$B$22)-15.9+5.12)/4.45 -> 83.977352 | D10: =($B$20+$B$21*(1+D6)/(B10-D6)*(1/(1+B10)^$B$22)-15.9+5.12)/4.45 -> 92.057392 | E10: =($B$20+$B$21*(1+E6)/(B10-E6)*(1/(1+B10)^$B$22)-15.9+5.12)/4.45 -> 102.15744 | F10: =($B$20+$B$21*(1+F6)/(B10-F6)*(1/(1+B10)^$B$22)-15.9+5.12)/4.45 -> 115.14322 | G10: =($B$20+$B$21*(1+G6)/(B10-G6)*(1/(1+B10)^$B$22)-15.9+5.12)/4.45 -> 132.45759
B11: 0.075 | C11: =($B$20+$B$21*(1+C6)/(B11-C6)*(1/(1+B11)^$B$22)-15.9+5.12)/4.45 -> 76.079969 | D11: =($B$20+$B$21*(1+D6)/(B11-D6)*(1/(1+B11)^$B$22)-15.9+5.12)/4.45 -> 82.553663 | E11: =($B$20+$B$21*(1+E6)/(B11-E6)*(1/(1+B11)^$B$22)-15.9+5.12)/4.45 -> 90.465957 | F11: =($B$20+$B$21*(1+F6)/(B11-F6)*(1/(1+B11)^$B$22)-15.9+5.12)/4.45 -> 100.35632 | G11: =($B$20+$B$21*(1+G6)/(B11-G6)*(1/(1+B11)^$B$22)-15.9+5.12)/4.45 -> 113.07251
B12: 0.08 | C12: =($B$20+$B$21*(1+C6)/(B12-C6)*(1/(1+B12)^$B$22)-15.9+5.12)/4.45 -> 69.542368 | D12: =($B$20+$B$21*(1+D6)/(B12-D6)*(1/(1+B12)^$B$22)-15.9+5.12)/4.45 -> 74.82563 | E12: =($B$20+$B$21*(1+E6)/(B12-E6)*(1/(1+B12)^$B$22)-15.9+5.12)/4.45 -> 81.165544 | F12: =($B$20+$B$21*(1+F6)/(B12-F6)*(1/(1+B12)^$B$22)-15.9+5.12)/4.45 -> 88.914329 | G12: =($B$20+$B$21*(1+G6)/(B12-G6)*(1/(1+B12)^$B$22)-15.9+5.12)/4.45 -> 98.60031
B13: 0.085 | C13: =($B$20+$B$21*(1+C6)/(B13-C6)*(1/(1+B13)^$B$22)-15.9+5.12)/4.45 -> 64.049378 | D13: =($B$20+$B$21*(1+D6)/(B13-D6)*(1/(1+B13)^$B$22)-15.9+5.12)/4.45 -> 68.42787 | E13: =($B$20+$B$21*(1+E6)/(B13-E6)*(1/(1+B13)^$B$22)-15.9+5.12)/4.45 -> 73.602451 | F13: =($B$20+$B$21*(1+F6)/(B13-F6)*(1/(1+B13)^$B$22)-15.9+5.12)/4.45 -> 79.811949 | G13: =($B$20+$B$21*(1+G6)/(B13-G6)*(1/(1+B13)^$B$22)-15.9+5.12)/4.45 -> 87.401336
A17: Note: Base case WACC = | B17: =Assumptions!B36 -> 0.0778138 | C17: Terminal Growth = | D17: =Assumptions!B40 -> 0.03
A19: Reference Values (for sensitivity calculation):
A20: Sum of Explicit PV FCFs | B20: =DCF!D29 -> 75.995389
A21: Terminal Year FCF | B21: =DCF!B16 -> 21.938807
A22: Discount Period (Terminal) | B22: 5.5
A25: IMPLIED SHARE PRICE: WACC vs Exit EV/EBITDA Multiple
B27: Exit EV/EBITDA Multiple
C28: 9 | D28: 10 | E28: 11 | F28: 12 | G28: 13
A29: WACC | B29: 0.055 | C29: =($B$20+C28*$B$37*(1/(1+B29)^$B$22)-15.9+5.12)/4.45 -> 68.099814 | D29: =($B$20+D28*$B$37*(1/(1+B29)^$B$22)-15.9+5.12)/4.45 -> 74.038111 | E29: =($B$20+E28*$B$37*(1/(1+B29)^$B$22)-15.9+5.12)/4.45 -> 79.976408 | F29: =($B$20+F28*$B$37*(1/(1+B29)^$B$22)-15.9+5.12)/4.45 -> 85.914704 | G29: =($B$20+G28*$B$37*(1/(1+B29)^$B$22)-15.9+5.12)/4.45 -> 91.853001
B30: 0.06 | C30: =($B$20+C28*$B$37*(1/(1+B30)^$B$22)-15.9+5.12)/4.45 -> 66.727913 | D30: =($B$20+D28*$B$37*(1/(1+B30)^$B$22)-15.9+5.12)/4.45 -> 72.513776 | E30: =($B$20+E28*$B$37*(1/(1+B30)^$B$22)-15.9+5.12)/4.45 -> 78.299639 | F30: =($B$20+F28*$B$37*(1/(1+B30)^$B$22)-15.9+5.12)/4.45 -> 84.085502 | G30: =($B$20+G28*$B$37*(1/(1+B30)^$B$22)-15.9+5.12)/4.45 -> 89.871366
B31: 0.065 | C31: =($B$20+C28*$B$37*(1/(1+B31)^$B$22)-15.9+5.12)/4.45 -> 65.397437 | D31: =($B$20+D28*$B$37*(1/(1+B31)^$B$22)-15.9+5.12)/4.45 -> 71.035469 | E31: =($B$20+E28*$B$37*(1/(1+B31)^$B$22)-15.9+5.12)/4.45 -> 76.673502 | F31: =($B$20+F28*$B$37*(1/(1+B31)^$B$22)-15.9+5.12)/4.45 -> 82.311534 | G31: =($B$20+G28*$B$37*(1/(1+B31)^$B$22)-15.9+5.12)/4.45 -> 87.949567
B32: 0.07 | C32: =($B$20+C28*$B$37*(1/(1+B32)^$B$22)-15.9+5.12)/4.45 -> 64.106949 | D32: =($B$20+D28*$B$37*(1/(1+B32)^$B$22)-15.9+5.12)/4.45 -> 69.601594 | E32: =($B$20+E28*$B$37*(1/(1+B32)^$B$22)-15.9+5.12)/4.45 -> 75.09624 | F32: =($B$20+F28*$B$37*(1/(1+B32)^$B$22)-15.9+5.12)/4.45 -> 80.590885 | G32: =($B$20+G28*$B$37*(1/(1+B32)^$B$22)-15.9+5.12)/4.45 -> 86.08553
B33: 0.075 | C33: =($B$20+C28*$B$37*(1/(1+B33)^$B$22)-15.9+5.12)/4.45 -> 62.85507 | D33: =($B$20+D28*$B$37*(1/(1+B33)^$B$22)-15.9+5.12)/4.45 -> 68.210618 | E33: =($B$20+E28*$B$37*(1/(1+B33)^$B$22)-15.9+5.12)/4.45 -> 73.566165 | F33: =($B$20+F28*$B$37*(1/(1+B33)^$B$22)-15.9+5.12)/4.45 -> 78.921713 | G33: =($B$20+G28*$B$37*(1/(1+B33)^$B$22)-15.9+5.12)/4.45 -> 84.27726
B34: 0.08 | C34: =($B$20+C28*$B$37*(1/(1+B34)^$B$22)-15.9+5.12)/4.45 -> 61.640473 | D34: =($B$20+D28*$B$37*(1/(1+B34)^$B$22)-15.9+5.12)/4.45 -> 66.861065 | E34: =($B$20+E28*$B$37*(1/(1+B34)^$B$22)-15.9+5.12)/4.45 -> 72.081657 | F34: =($B$20+F28*$B$37*(1/(1+B34)^$B$22)-15.9+5.12)/4.45 -> 77.30225 | G34: =($B$20+G28*$B$37*(1/(1+B34)^$B$22)-15.9+5.12)/4.45 -> 82.522842
B35: 0.085 | C35: =($B$20+C28*$B$37*(1/(1+B35)^$B$22)-15.9+5.12)/4.45 -> 60.461882 | D35: =($B$20+D28*$B$37*(1/(1+B35)^$B$22)-15.9+5.12)/4.45 -> 65.55152 | E35: =($B$20+E28*$B$37*(1/(1+B35)^$B$22)-15.9+5.12)/4.45 -> 70.641157 | F35: =($B$20+F28*$B$37*(1/(1+B35)^$B$22)-15.9+5.12)/4.45 -> 75.730795 | G35: =($B$20+G28*$B$37*(1/(1+B35)^$B$22)-15.9+5.12)/4.45 -> 80.820433
A37: Terminal Year EBITDA | B37: =DCF!B22 -> 35.474022

Sheet Comps
A1: COMPARABLE COMPANY ANALYSIS
A3: Company | B3: Ticker | C3: Market Cap ($B) | D3: EV ($B) | E3: LTM Revenue ($B) | F3: LTM EBITDA ($B) | G3: EV/Revenue | H3: EV/EBITDA | I3: P/E | J3: Revenue Growth | K3: Gross Margin
A4: Novo Nordisk | B4: NVO | C4: 232.8 | D4: 238.1 | E4: 49.6 | F4: 23.2 | G4: =D4/E4 -> 4.8004032 | H4: =D4/F4 -> 10.262931 | I4: 14.3 | J4: 0.17 | K4: 0.847
A5: Eli Lilly | B5: LLY | C5: 968.5 | D5: 982 | E5: 45 | F5: 16.5 | G5: =D5/E5 -> 21.822222 | H5: =D5/F5 -> 59.515152 | I5: 65.2 | J5: 0.32 | K5: 0.81
A6: AstraZeneca | B6: AZN | C6: 210 | D6: 235 | E6: 54 | F6: 15.5 | G6: =D6/E6 -> 4.3518519 | H6: =D6/F6 -> 15.16129 | I6: 32.1 | J6: 0.18 | K6: 0.73
A7: Merck | B7: MRK | C7: 245 | D7: 270 | E7: 64 | F7: 28 | G7: =D7/E7 -> 4.21875 | H7: =D7/F7 -> 9.6428571 | I7: 15.8 | J7: 0.07 | K7: 0.76
A8: Pfizer | B8: PFE | C8: 142 | D8: 205 | E8: 58 | F8: 18 | G8: =D8/E8 -> 3.5344828 | H8: =D8/F8 -> 11.388889 | I8: 22.5 | J8: -0.05 | K8: 0.68
A9: AbbVie | B9: ABBV | C9: 315 | D9: 385 | E9: 56 | F9: 26 | G9: =D9/E9 -> 6.875 | H9: =D9/F9 -> 14.807692 | I9: 18.2 | J9: 0.04 | K9: 0.7
A11: Mean (excl. NVO) | G11: =AVERAGE(G5:G9) -> 8.1604614 | H11: =AVERAGE(H5:H9) -> 22.103176 | I11: =AVERAGE(I5:I9) -> 30.76 | J11: =AVERAGE(J5:J9) -> 0.112 | K11: =AVERAGE(K5:K9) -> 0.736
A12: Median (excl. NVO) | G12: =MEDIAN(G5:G9) -> 4.3518519 | H12: =MEDIAN(H5:H9) -> 14.807692 | I12: =MEDIAN(I5:I9) -> 22.5 | J12: =MEDIAN(J5:J9) -> 0.07 | K12: =MEDIAN(K5:K9) -> 0.73
A16: IMPLIED VALUATION FROM COMPS
A18: NVO LTM Revenue ($B) | B18: 49.6
A19: NVO LTM EBITDA ($B) | B19: 23.2
A20: Shares Outstanding (B) | B20: 4.45
A21: Net Debt ($B) | B21: 10.78
A23: Metric | B23: Multiple | C23: Implied EV | D23: Implied Equity | E23: Implied Price
A24: EV/Revenue (Mean) | B24: =G11 -> 8.1604614 | C24: =B24*B18 -> 404.75888 | D24: =C24-B21 -> 393.97888 | E24: =D24/B20 -> 88.534581
A25: EV/EBITDA (Mean) | B25: =H11 -> 22.103176 | C25: =B25*B19 -> 512.79368 | D25: =C25-B21 -> 502.01368 | E25: =D25/B20 -> 112.81206
