Workbook

Sheet Executive Summary
A1: GENMAB A/S (GMAB) - DCF VALUATION MODEL
A2: Deep Dive Analysis | January 2026
A4: COMPANY OVERVIEW | H4: KEY INVESTMENT HIGHLIGHTS
A5: Ticker | B5: GMAB (NASDAQ) | H5: ✓ DARZALEX royalties drive ~80% of revenue
A6: Headquarters | B6: Copenhagen, Denmark | H6: ✓ EPKINLY launch gaining momentum
A7: Industry | B7: Biotechnology - Antibody Therapeutics | H7: ✓ Strong late-stage pipeline (Rina-S, petosemtamab)
A8: Founded | B8: 1999 | H8: ✓ Net cash position of $3.3B
A9: CEO | B9: Jan van de Winkel, Ph.D. | H9: ✓ 2025 guidance: $3.3-3.7B revenue
A10: Employees | B10: ~2,500 | H10: ✓ $8B combined peak sales potential (3 lead assets)
A12: VALUATION SUMMARY
A13: Current Stock Price | B13: 33.9
A14: Shares Outstanding (M) | B14: 616
A15: Market Cap ($B) | B15: =B13*B14/1000 -> 20.8824
A16: Net Debt ($M) | B16: -3270
A17: Enterprise Value ($B) | B17: =B15+B16/1000 -> 17.6124
A19: DCF IMPLIED VALUES
A20: Enterprise Value ($B) | B20: =DCF!F35 -> 26.875055
A21: Equity Value ($B) | B21: =B20-B16/1000 -> 30.145055
A22: Implied Share Price | B22: =B21*1000/B14 -> 48.936777
A23: Upside/Downside | B23: =(B22-B13)/B13 -> 0.44356274

Sheet Assumptions
A1: KEY MODEL ASSUMPTIONS
A3: REVENUE ASSUMPTIONS
A4: Base Year Revenue ($M) | B4: 3100 | C4: 2024 Actual
A5: 2025E Revenue Growth | B5: 0.16 | C5: Mid-point of guidance ($3.5B)
A6: 2026E Revenue Growth | B6: 0.15 | C6: EPKINLY expansion + royalty growth
A7: 2027E Revenue Growth | B7: 0.14 | C7: Continued pipeline momentum
A8: 2028E Revenue Growth | B8: 0.12 | C8: Rina-S potential launch
A9: 2029E Revenue Growth | B9: 0.1 | C9: New indication approvals
A10: 2030E+ Terminal Growth | B10: 0.025 | C10: Long-term GDP growth rate
A12: MARGIN ASSUMPTIONS
A13: Gross Margin | B13: 0.94 | C13: Primarily royalty revenue (high margin)
A14: Operating Margin (2025E) | B14: 0.3 | C14: Investment phase
A15: Operating Margin (Terminal) | B15: 0.4 | C15: Mature company target
A16: Tax Rate | B16: 0.22 | C16: Danish corporate tax rate
A17: D&A % of Revenue | B17: 0.02 | C17: Asset-light model
A18: CapEx % of Revenue | B18: 0.015 | C18: Minimal capital requirements
A19: NWC % of Revenue Change | B19: 0.05 | C19: Working capital needs
A22: WACC ASSUMPTIONS
A23: Risk-Free Rate | B23: 0.0425 | C23: 10-Year US Treasury
A24: Equity Risk Premium | B24: 0.055 | C24: Historical average
A25: Beta (Levered) | B25: 0.79 | C25: 5-year weekly beta
A26: Cost of Debt (Pre-tax) | B26: 0.05 | C26: Estimated based on credit quality
A27: Debt/Capital | B27: 0.03 | C27: Minimal debt (~$142M)
A29: Cost of Equity | B29: =B23+B25*B24 -> 0.08595
A30: After-Tax Cost of Debt | B30: =B26*(1-B16) -> 0.039
A31: WACC | B31: =(1-B27)*B29+B27*B30 -> 0.0845415

Sheet Historical
A1: HISTORICAL FINANCIAL PERFORMANCE
A3: Metric | B3: 2020 | C3: 2021 | D3: 2022 | E3: 2023 | F3: 2024 | G3: Notes
A4: Revenue ($M) | B4: 2200 | C4: 1350 | D4: 2067 | E4: 2392 | F4: 3121 | G4: Strong DARZALEX growth
A5: YoY Growth | B5: - | C5: -38.6% | D5: 53.1% | E5: 15.7% | F5: 30.5% | G5: 2021 drop: AbbVie upfront ended
A6: Royalty Revenue ($M) | B6: 1800 | C6: 1200 | D6: 1700 | E6: 1958 | F6: 2479 | G6: ~80% of total revenue
A7: Operating Profit ($M) | B7: 899 | C7: 422 | D7: 895 | E7: 760 | F7: 958 | G7: Investing in pipeline
A8: Operating Margin | B8: 40.9% | C8: 31.3% | D8: 43.3% | E8: 31.8% | F8: 30.7%
A9: Net Income ($M) | B9: 850 | C9: 500 | D9: 700 | E9: 760 | F9: 1400 | G9: FX gains in 2024
A10: EPS ($) | B10: 12.9 | C10: 7.6 | D10: 10.6 | E10: 11.5 | F10: 21.4
A11: Free Cash Flow ($M) | B11: 800 | C11: 350 | D11: 650 | E11: 900 | F11: 1330 | G11: Asset-light model
A14: KEY PRODUCT METRICS
A15: DARZALEX Global Sales ($B) | B15: 5.8 | C15: 7 | D15: 8 | E15: 9.7 | F15: 11.7 | G15: J&J reports; 20%+ growth
A16: Kesimpta Global Sales ($B) | B16: 0.8 | C16: 1.5 | D16: 2 | E16: 2.5 | F16: 3.2 | G16: Novartis partner; MS drug
A17: EPKINLY Sales ($M) | B17: - | C17: - | D17: - | E17: 50 | F17: 281 | G17: Launched May 2023
A18: Tivdak Sales ($M) | B18: - | C18: - | D18: 100 | E18: 150 | F18: 200 | G18: Cervical cancer

Sheet DCF
A1: DISCOUNTED CASH FLOW VALUATION
A3: Metric | B3: 2024A | C3: 2025E | D3: 2026E | E3: 2027E | F3: 2028E | G3: 2029E | H3: Terminal
A4: Revenue ($M) | B4: =Assumptions!B4 -> 3100 | C4: =B4*(1+Assumptions!B5) -> 3596 | D4: =C4*(1+Assumptions!B6) -> 4135.4 | E4: =D4*(1+Assumptions!B7) -> 4714.356 | F4: =E4*(1+Assumptions!B8) -> 5280.0787 | G4: =F4*(1+Assumptions!B9) -> 5808.0866
A5: Revenue Growth | B5: 0.305 | C5: =Assumptions!B5 -> 0.16 | D5: =Assumptions!B6 -> 0.15 | E5: =Assumptions!B7 -> 0.14 | F5: =Assumptions!B8 -> 0.12 | G5: =Assumptions!B9 -> 0.1
A7: Operating Margin | B7: 0.307 | C7: 0.3 | D7: 0.32 | E7: 0.35 | F7: 0.38 | G7: 0.4
A8: Operating Income (EBIT) | B8: =B4*B7 -> 951.7 | C8: =C4*C7 -> 1078.8 | D8: =D4*D7 -> 1323.328 | E8: =E4*E7 -> 1650.0246 | F8: =F4*F7 -> 2006.4299 | G8: =G4*G7 -> 2323.2346
A9: Tax Rate | B9: =Assumptions!B16 -> 0.22 | C9: =Assumptions!B16 -> 0.22 | D9: =Assumptions!B16 -> 0.22 | E9: =Assumptions!B16 -> 0.22 | F9: =Assumptions!B16 -> 0.22 | G9: =Assumptions!B16 -> 0.22
A10: Taxes | B10: =B8*B9 -> 209.374 | C10: =C8*C9 -> 237.336 | D10: =D8*D9 -> 291.13216 | E10: =E8*E9 -> 363.00541 | F10: =F8*F9 -> 441.41458 | G10: =G8*G9 -> 511.11162
A11: NOPAT | B11: =B8-B10 -> 742.326 | C11: =C8-C10 -> 841.464 | D11: =D8-D10 -> 1032.1958 | E11: =E8-E10 -> 1287.0192 | F11: =F8-F10 -> 1565.0153 | G11: =G8-G10 -> 1812.123
A13: D&A (% of Rev) | B13: =Assumptions!B17 -> 0.02 | C13: =Assumptions!B17 -> 0.02 | D13: =Assumptions!B17 -> 0.02 | E13: =Assumptions!B17 -> 0.02 | F13: =Assumptions!B17 -> 0.02 | G13: =Assumptions!B17 -> 0.02
A14: D&A ($M) | B14: =B4*B13 -> 62 | C14: =C4*C13 -> 71.92 | D14: =D4*D13 -> 82.708 | E14: =E4*E13 -> 94.28712 | F14: =F4*F13 -> 105.60157 | G14: =G4*G13 -> 116.16173
A15: CapEx (% of Rev) | B15: =Assumptions!B18 -> 0.015 | C15: =Assumptions!B18 -> 0.015 | D15: =Assumptions!B18 -> 0.015 | E15: =Assumptions!B18 -> 0.015 | F15: =Assumptions!B18 -> 0.015 | G15: =Assumptions!B18 -> 0.015
A16: CapEx ($M) | B16: =B4*B15 -> 46.5 | C16: =C4*C15 -> 53.94 | D16: =D4*D15 -> 62.031 | E16: =E4*E15 -> 70.71534 | F16: =F4*F15 -> 79.201181 | G16: =G4*G15 -> 87.121299
A17: NWC (% of Rev Change) | B17: =Assumptions!B19 -> 0.05 | C17: =Assumptions!B19 -> 0.05 | D17: =Assumptions!B19 -> 0.05 | E17: =Assumptions!B19 -> 0.05 | F17: =Assumptions!B19 -> 0.05 | G17: =Assumptions!B19 -> 0.05
A18: Change in NWC ($M) | B18: 0 | C18: =(C4-B4)*C17 -> 24.8 | D18: =(D4-C4)*D17 -> 26.97 | E18: =(E4-D4)*E17 -> 28.9478 | F18: =(F4-E4)*F17 -> 28.286136 | G18: =(G4-F4)*G17 -> 26.400394
A20: Unlevered Free Cash Flow | B20: =B11+B14-B16-B18 -> 757.826 | C20: =C11+C14-C16-C18 -> 834.644 | D20: =D11+D14-D16-D18 -> 1025.9028 | E20: =E11+E14-E16-E18 -> 1281.6432 | F20: =F11+F14-F16-F18 -> 1563.1296 | G20: =G11+G14-G16-G18 -> 1814.7631
A22: TERMINAL VALUE
A23: Terminal Growth Rate | B23: =Assumptions!B10 -> 0.025
A24: WACC | B24: =Assumptions!B31 -> 0.0845415
A25: Terminal FCF | B25: =G20*(1+B23) -> 1860.1321
A26: Terminal Value (Gordon Growth) | B26: =B25/(B24-B23) -> 31240.935
A28: PRESENT VALUE CALCULATION
A29: Discount Period | C29: 0.5 | D29: 1.5 | E29: 2.5 | F29: 3.5 | G29: 4.5
A30: Discount Factor | C30: =1/(1+$B$24)^C29 -> 0.96023363 | D30: =1/(1+$B$24)^D29 -> 0.8853821 | E30: =1/(1+$B$24)^E29 -> 0.81636535 | F30: =1/(1+$B$24)^F29 -> 0.75272855 | G30: =1/(1+$B$24)^G29 -> 0.69405232
A31: PV of FCF | C31: =C20*C30 -> 801.45324 | D31: =D20*D30 -> 908.31601 | E31: =E20*E30 -> 1046.2891 | F31: =F20*F30 -> 1176.6123 | G31: =G20*G30 -> 1259.5405
A32: PV of Terminal Value | B32: =B26*G30 -> 21682.844
A34: Sum of PV FCFs | B34: =SUM(C31:G31) -> 5192.2111
A35: ENTERPRISE VALUE ($B) | B35: =(B34+B32)/1000 -> 26.875055 | F35: =B35 -> 26.875055

Sheet Sensitivity
A1: SENSITIVITY ANALYSIS
A3: WACC vs Terminal Growth Rate
A5: Base WACC: | B5: =Assumptions!B31 -> 0.0845415
A6: Base Terminal Growth: | B6: =Assumptions!B10 -> 0.025
C8: Terminal Growth Rate
B9: WACC | C9: 0.015 | D9: 0.02 | E9: 0.025 | F9: 0.03 | G9: 0.035
B10: 0.07 | C10: 54.56 | D10: 59.49 | E10: 65.51 | F10: 73.04 | G10: 82.71
B11: 0.075 | C11: 50.46 | D11: 54.56 | E11: 59.49 | F11: 65.51 | G11: 73.04
B12: 0.08 | C12: 46.99 | D12: 50.46 | E12: 54.56 | F12: 59.49 | G12: 65.51
B13: 0.085 | C13: 44.01 | D13: 46.99 | E13: 50.46 | F13: 54.56 | G13: 59.49
B14: 0.09 | C14: 41.43 | D14: 44.01 | E14: 46.99 | F14: 50.46 | G14: 54.56
B15: 0.095 | C15: 39.17 | D15: 41.43 | E15: 44.01 | F15: 46.99 | G15: 50.46
A18: Revenue CAGR vs Terminal Operating Margin
C20: Terminal Op Margin
B21: Rev CAGR | C21: 0.35 | D21: 0.38 | E21: 0.4 | F21: 0.42 | G21: 0.45
B22: 0.1 | C22: 38.96 | D22: 41.85 | E22: 43.77 | F22: 45.7 | G22: 48.58
B23: 0.12 | C23: 42.14 | D23: 45.29 | E23: 47.4 | F23: 49.5 | G23: 52.66
B24: 0.14 | C24: 45.54 | D24: 48.99 | E24: 51.29 | F24: 53.59 | G24: 57.04
B25: 0.16 | C25: 49.2 | D25: 52.96 | E25: 55.47 | F25: 57.98 | G25: 61.74
B26: 0.18 | C26: 53.12 | D26: 57.21 | E26: 59.95 | F26: 62.68 | G26: 66.78

Sheet Deep Dive
A1: GENMAB - BUSINESS DEEP DIVE
A3: BUSINESS MODEL
A4: Genmab is a Danish biotechnology company specializing in antibody therapeutics for cancer.
A5: The company generates revenue primarily through:
A7: 1. ROYALTY REVENUE (~80% of total):
A8: - DARZALEX (daratumumab): 12-20% royalty on J&J sales ($11.7B in 2024)
A9: - Kesimpta (ofatumumab): Royalty on Novartis MS drug (~$3.2B sales)
A10: - TEPEZZA, RYBREVANT, TECVAYLI, TALVEY: Smaller royalty streams
A12: 2. PRODUCT SALES & COLLABORATION REVENUE (~20%):
A13: - EPKINLY (epcoritamab): Co-developed with AbbVie, Genmab sells in US/Japan
A14: - Tivdak (tisotumab vedotin): Co-developed with Pfizer for cervical cancer
A16: KEY COMPETITIVE ADVANTAGES:
... A25: PIPELINE OVERVIEW
A26: Asset | B26: Target | C26: Stage | D26: Indication | E26: Partner
A27: EPKINLY (epcoritamab) | B27: CD3xCD20 | C27: Marketed/Phase 3 | D27: DLBCL, FL, other lymphomas | E27: AbbVie
A28: Rina-S (rinatabart sesutecan) | B28: FRα-ADC | C28: Phase 3 | D28: Ovarian, Endometrial cancer | E28: Wholly-owned
A29: Petosemtamab | B29: EGFRxLGR5 | C29: Phase 3 | D29: Head & neck cancer | E29: Merus (acquired)
A30: Tivdak (tisotumab vedotin) | B30: TF-ADC | C30: Marketed | D30: Cervical cancer | E30: Pfizer
A31: GEN1042 (BNT312) | B31: CD40x4-1BB | C31: Phase 2 | D31: Solid tumors | E31: BioNTech
A32: HexaBody-CD38 (GEN3014) | B32: CD38 | C32: Phase 1/2 | D32: Multiple myeloma | E32: Janssen option
A35: KEY RISKS
A36: • DARZALEX concentration: ~65% of royalty revenue from single product
A37: • Patent expirations: DARZALEX faces potential biosimilar competition ~2029-2032
A38: • Pipeline execution risk: Late-stage trial failures possible
A39: • Competition: CAR-T, other bispecifics competing in hematology
A40: • Litigation: AbbVie lawsuit over Rina-S trade secrets
A41: • Currency: DKK reporting with USD revenue creates FX volatility

Sheet Entry Price Analysis
A1: ENTRY PRICE ANALYSIS - TARGET RETURN CALCULATOR
A3: CURRENT VALUATION
A4: DCF Implied Fair Value (Today) | B4: ='Executive Summary'!B22 -> 48.936777
A5: Current Stock Price | B5: ='Executive Summary'!B13 -> 33.9
A6: Shares Outstanding (M) | B6: ='Executive Summary'!B14 -> 616
A8: 5-YEAR FORWARD PROJECTION
A9: Projection Year | B9: 2029
A10: Projected Revenue ($M) | B10: =DCF!G4 -> 5808.0866
A11: Projected Operating Margin | B11: =DCF!G7 -> 0.4
A12: Projected EBIT ($M) | B12: =B10*B11 -> 2323.2346
A13: Projected FCF ($M) | B13: =DCF!G20 -> 1814.7631
A15: WACC | B15: =Assumptions!B31 -> 0.0845415
A16: Terminal Growth Rate | B16: =Assumptions!B10 -> 0.025
A17: Terminal Value (from 2029) | B17: =B13*(1+B16)/(B15-B16) -> 31240.935
A18: Enterprise Value in 2029 ($M) | B18: =B17 -> 31240.935
A19: Net Cash in 2029 ($M) - Est. | B19: 5000
A20: Equity Value in 2029 ($M) | B20: =B18+B19 -> 36240.935
A21: Implied Share Price in 2029 | B21: =B20/B6 -> 58.832687
A23: TARGET RETURN ANALYSIS
A24: Target CAGR | B24: 0.15
A25: Investment Horizon (Years) | B25: 5
A26: Required Entry Price | B26: =B21/((1+B24)^B25) -> 29.250243
A28: Discount to Current Price | B28: =(B5-B26)/B5 -> 0.13716097
A29: Upside from Entry Price | B29: =(B21-B26)/B26 -> 1.0113572
A32: ENTRY PRICE BY TARGET RETURN
A33: Target CAGR | B33: Entry Price | C33: vs Current
A34: 0.1 | B34: =$B$21/((1+A34)^$B$25) -> 36.53047 | C34: =(B34-$B$5)/$B$5 -> 0.077594976
A35: 0.12 | B35: =$B$21/((1+A35)^$B$25) -> 33.383246 | C35: =(B35-$B$5)/$B$5 -> -0.015243468
A36: 0.15 | B36: =$B$21/((1+A36)^$B$25) -> 29.250243 | C36: =(B36-$B$5)/$B$5 -> -0.13716097
A37: 0.18 | B37: =$B$21/((1+A37)^$B$25) -> 25.71631 | C37: =(B37-$B$5)/$B$5 -> -0.2414068
A38: 0.2 | B38: =$B$21/((1+A38)^$B$25) -> 23.643537 | C38: =(B38-$B$5)/$B$5 -> -0.30255052
A39: 0.25 | B39: =$B$21/((1+A39)^$B$25) -> 19.278295 | C39: =(B39-$B$5)/$B$5 -> -0.43131874
A42: 15% CAGR BY TIME HORIZON
A43: Horizon (Yrs) | B43: Entry Price | C43: Notes
A44: 3 | B44: =$B$4*(1.1)^3/((1+0.15)^3) -> 42.827221 | C44: Short-term
A45: 5 | B45: =$B$21/((1+0.15)^5) -> 29.250243 | C45: Base case
A46: 7 | B46: =$B$4*(1.1)^7/((1+0.15)^7) -> 35.850835 | C46: Long-term
A47: 10 | B47: =$B$4*(1.1)^10/((1+0.15)^10) -> 31.375006 | C47: Very long-term
