Workbook

Sheet Model_Info
A1: SAN.NZ -- Sanford Limited DCF model
A2: Version | B2: v1.0, fresh build 2026-08-27. Supersedes nothing (first SAN.NZ valuation).
A3: Built by | B3: dcf-analyst agent (Claude, Fable 5), 27-Aug-2026, at the user's request via /research-stock SAN.NZ.
A4: Model | B4: Owner-FCF DCF, 10-year component build (FY2026E-FY2035E), three probability-weighted scenarios. Routed via dcf-methods SKILL: operating company, non-US cyclical (owner-fcf.md incl. section 7).
A5: Data vintage | B5: Price NZ$6.90 at 2026-08-27 04:59:43Z NZX regular close (Yahoo). Balance sheet 31-Mar-2026 H1 FY2026 interim (bank debt $120.0m, cash $17.856m). Shares 93.506m (FY2025 AR note 16; basic=diluted). FY2026 guidance from FY2025 AR + HY26 commentary (David Mair).
A6: Lease treatment | B6: Treatment B: full lease cash cost (2.8% of revenue; FY2025 principal 14.324 + lease interest 2.088 = 16.412) charged in the flows; lease liabilities ($41.4m) EXCLUDED from net debt. Never charge both.
A7: Mid-cycle basis | B7: FY2025 owner FCF $96m is a PEAK (WC release + $22m cash-tax underpayment). The model capitalizes a component-built mid-cycle: 20% EBITDA margin (base), 28% cash tax, capex ramping to 6% of revenue. Do not 'fix' year-1 FCF up to the FY2025 print.
A8: SBC | B8: Effectively zero ($219k FY2025, <0.05% of revenue). Rows kept explicit at 0% per house rule; street basis = house basis (band collapsed, n/a).
A9: NCI | B9: Negligible (-$2k FY2025 profit share); no adjustment.
A10: WACC | B10: 10.5% NZD, same all scenarios. rf 4.5% + 5.0% ERP x beta 0.9 + 1.25% NZX illiquidity + 1.0% structural biological/regulatory tail; cyclicality is charged in scenario flows/weights, not WACC.
A11: Whose judgment | B11: Scenario driver paths set by the dcf-analyst agent, 27-Aug-2026, from FY2025 AR / HY26 filings and the qualitative Analysis JSON. Not yet user-reviewed.
A12: Refresh after next print | B12: FY2026 annual result (~Nov-2026): net debt & cash tax catch-up, mussel inventory unwind, FY2027 guidance; re-judge year-1 growth/margin only unless evidence moves later years.
A13: Staleness | B13: Figures go stale: price within days; balance sheet at the FY2026 result; TACC decisions (ORH 3B closure from Jun-2026) can move the wildcatch outlook at any review.
A14: Cell colours | B14: BLUE = hardcoded input; YELLOW fill = key driver row (flex these); BLACK = formula; GREEN = cross-sheet link.

Sheet Actuals
A1: Period | B1: Revenue | C1: Adj EBITDA | D1: NPAT | E1: OCF | F1: Capex | G1: Reported FCF | H1: Equity | I1: Bank debt | J1: Cash
A2: FY2016 | B2: 463.469 | C2: 78.873 | D2: 37.813 | E2: 34.372 | F2: 42.148 | G2: -7.776 | H2: 557.737 | I2: 176.634 | J2: 3.589
A3: FY2017 | B3: 477.94 | C3: 82.547 | D3: 37.478 | E3: 50.28 | F3: 36.803 | G3: 13.477 | H3: 575.309 | I3: 186.121 | J3: 5.15
A4: FY2018 | B4: 514.976 | C4: 84.402 | D4: 42.3 | E4: 72.647 | F4: 24.739 | G4: 47.908 | H4: 581.349 | I4: 155 | J4: 2.63
A5: FY2019 | B5: 545.121 | C5: 85.729 | D5: 41.692 | E5: 48.652 | F5: 38.348 | G5: 10.304 | H5: 587.507 | I5: 139 | J5: 8.322
A6: FY2020 | B6: 468.849 | C6: 66.294 | D6: 22.433 | E6: 18.787 | F6: 43.2 | G6: -24.413 | H6: 610.962 | I6: 187.21 | J6: 2.957
A7: FY2021 | B7: 489.625 | C7: 52.603 | D7: 16.235 | E7: 32.233 | F7: 43.2 | G7: -10.967 | H7: 633.392 | I7: 182.5 | J7: 3.926
A8: FY2022 | B8: 531.887 | C8: 68.262 | D8: 55.772 | E8: 44.904 | F8: 53.442 | G8: -8.538 | H8: 664.485 | I8: 155 | J8: 9.534
A9: FY2023 | B9: 553.397 | C9: 81.534 | D9: 10.011 | E9: 41.053 | F9: 64.412 | G9: -23.359 | H9: 684.571 | I9: 203 | J9: 6.805
A10: FY2024 | B10: 582.913 | C10: 108.65 | D10: 19.67 | E10: 72.996 | F10: 45.916 | G10: 27.08 | H10: 703.993 | I10: 200 | J10: 14.475
A11: FY2025 | B11: 584.109 | C11: 140.992 | D11: 63.692 | E11: 135.342 | F11: 22.488 | G11: 112.854 | H11: 740.405 | I11: 105 | J11: 11.589
A12: H1 FY2026 | B12: 270.154 | C12: 81.768 | D12: 42.417 | E12: 13.693 | F12: 6.715 | G12: 6.978 | H12: 779.828 | I12: 120 | J12: 17.856
A14: Source: SAN.NZ core_metrics (metrics_normalized), NZD millions; adjudicated from annual reports (FY end 30-Sep). Adj EBITDA = company measure (adjusted EBIT + D&A). Bank debt excludes lease liabilities.
A15: Balance sheet snapshot 31-Mar-2026: bank loans 120.0, cash 17.856, net debt 102.144; lease liabilities 41.405 (FY2025). Shares 93.506m, basic = diluted, no buybacks -- count flat since FY2018.
A16: HY26 flags: NPAT includes $17.5m non-cash biological-asset FV gain; OCF collapsed to $13.7m on frozen mussel inventory build; cash tax paid $17.5m (FY2025 underpayment catch-up).

Sheet Assumptions
A1: Globals
A2: Current price (NZD) | B2: 6.9 | E2: Yahoo NZX close 2026-08-27 04:59:43Z
A3: Shares outstanding (m) | B3: 93.506 | E3: FY2025 note 16; basic = diluted; held flat
A4: Net debt (NZD m) | B4: 102.144 | E4: 31-Mar-2026: bank loans 120.0 - cash 17.856; leases excluded (treatment B)
A5: WACC % | B5: 10.5 | E5: NZD-built, itemized in Model_Info; same in all scenarios
A6: D&A % of revenue | B6: 3.7 | E6: Owned-asset D&A only (total 6.1% less ~2.4pp ROU depreciation, note 19)
A7: Lease cost % of revenue | B7: 2.8 | E7: Full lease cash: principal + lease interest (FY2025 16.412/584.1)
A8: WC capture % of revenue change | B8: -20 | E8: Each incremental revenue dollar absorbs ~20c of inventory/receivables (physical export business; sign negative)
A9: Terminal cap multiple (x FCF) | B9: 13 | E9: Cyclical: cap 12-15x per owner-fcf.md s4; binds nowhere (Gordon lower in all scenarios)
A10: Hurdle rate % | B10: 15 | E10: Entry-price IRR
A11: FY2025 revenue (NZD m) | B11: 584.109 | E11: Base for year-1 growth
A13: Per scenario
A14: Scenario | B14: Bear | C14: Base | D14: Bull
A15: Terminal growth % | B15: 1.5 | C15: 2 | D15: 2.5
A16: Probability weight | B16: 0.25 | C16: 0.5 | D16: 0.25 | E16: =IF(SUM(B16:D16)=1,"weights sum to 1.0 -- OK","ERROR: weights do not sum to 1")
A18: Scenario narratives
A19: Bear | B19: Record was weather and price: mussel yields mean-revert, scampi/China weak, a Big Glory Bay biological event and further TACC cuts; margins back to the 16% decade average, 6.5% capex, ~1% growth. Flows-only floor $1.96; quota/NTA backing cushions real-world downside but is deliberately not credited.
A20: Base | B20: FY2026 revenue -3.5%, then 2-3.5% (Western Firth mussels from FY2027 vs capped wildcatch/salmon). Half the Back-to-Basics gain structural: ex-bio-gain EBITDA margin fades 23.5% -> 20% mid-cycle (decade avg 15.7%). Capex normalizes 3.5% -> 6.0%; 28% cash tax; tg 2.0%.
A21: Bull | B21: Turnaround durable: margins hold ~23%, hoki/roughy pricing strong, scampi recovers, mussel pipeline compounds revenue 4-5% mid-decade, capex discipline 5%, wildcatch review monetises sub-scale assets; tg 2.5%.

Sheet DCF_Bear
A3: Year | B3: FY2025A | C3: FY2026E | D3: FY2027E | E3: FY2028E | F3: FY2029E | G3: FY2030E | H3: FY2031E | I3: FY2032E | J3: FY2033E | K3: FY2034E | L3: FY2035E
A4: Year index | B4: 0 | C4: 1 | D4: 2 | E4: 3 | F4: 4 | G4: 5 | H4: 6 | I4: 7 | J4: 8 | K4: 9 | L4: 10
A5: Revenue growth % (driver) | C5: -6 | D5: -2 | E5: 0 | F5: 1 | G5: 1 | H5: 1 | I5: 1 | J5: 1 | K5: 1 | L5: 1
A6: Revenue | B6: 584.109 | C6: =B6*(1+C5/100) | D6: =C6*(1+D5/100) | E6: =D6*(1+E5/100) | F6: =E6*(1+F5/100) | G6: =F6*(1+G5/100) | H6: =G6*(1+H5/100) | I6: =H6*(1+I5/100) | J6: =I6*(1+J5/100) | ... L6: =K6*(1+L5/100)
A7: Adj EBITDA margin % ex bio gains (driver) | B7: 24.1 | C7: 21 | D7: 18.5 | E7: 17 | F7: 16.5 | G7: 16 | H7: 16 | I7: 16 | J7: 16 | K7: 16 | L7: 16
A8: Adjusted EBITDA | B8: 140.992 | C8: =C6*C7/100 | D8: =D6*D7/100 | E8: =E6*E7/100 | F8: =F6*F7/100 | G8: =G6*G7/100 | H8: =H6*H7/100 | I8: =I6*I7/100 | J8: =J6*J7/100 | ... L8: =L6*L7/100
A9: SBC % of revenue (driver; SBC-zero filer) | C9: 0 | D9: 0 | E9: 0 | F9: 0 | G9: 0 | H9: 0 | I9: 0 | J9: 0 | K9: 0 | L9: 0
A10: SBC $ | B10: -0.219 | C10: =-C6*C9/100 | D10: =-D6*D9/100 | E10: =-E6*E9/100 | F10: =-F6*F9/100 | G10: =-G6*G9/100 | H10: =-H6*H9/100 | I10: =-I6*I9/100 | J10: =-J6*J9/100 | ... L10: =-L6*L9/100
A11: Lease cost % of revenue | C11: =Assumptions!$B$7 | D11: =Assumptions!$B$7 | E11: =Assumptions!$B$7 | F11: =Assumptions!$B$7 | G11: =Assumptions!$B$7 | H11: =Assumptions!$B$7 | I11: =Assumptions!$B$7 | J11: =Assumptions!$B$7 | ... L11: =Assumptions!$B$7
A12: Lease $ (principal + lease interest) | B12: -16.412 | C12: =-C6*C11/100 | D12: =-D6*D11/100 | E12: =-E6*E11/100 | F12: =-F6*F11/100 | G12: =-G6*G11/100 | H12: =-H6*H11/100 | I12: =-I6*I11/100 | J12: =-J6*J11/100 | ... L12: =-L6*L11/100
A13: D&A % of revenue (owned assets) | C13: =Assumptions!$B$6 | D13: =Assumptions!$B$6 | E13: =Assumptions!$B$6 | F13: =Assumptions!$B$6 | G13: =Assumptions!$B$6 | H13: =Assumptions!$B$6 | I13: =Assumptions!$B$6 | J13: =Assumptions!$B$6 | ... L13: =Assumptions!$B$6
A14: D&A $ | C14: =-C6*C13/100 | D14: =-D6*D13/100 | E14: =-E6*E13/100 | F14: =-F6*F13/100 | G14: =-G6*G13/100 | H14: =-H6*H13/100 | I14: =-I6*I13/100 | J14: =-J6*J13/100 | ... L14: =-L6*L13/100
A15: EBIT (SBC + lease expensed) | C15: =C8+C10+C12+C14 | D15: =D8+D10+D12+D14 | E15: =E8+E10+E12+E14 | F15: =F8+F10+F12+F14 | G15: =G8+G10+G12+G14 | H15: =H8+H10+H12+H14 | I15: =I8+I10+I12+I14 | J15: =J8+J10+J12+J14 | ... L15: =L8+L10+L12+L14
A16: Cash tax rate % (driver) | C16: 28 | D16: 28 | E16: 28 | F16: 28 | G16: 28 | H16: 28 | I16: 28 | J16: 28 | K16: 28 | L16: 28
A17: NOPAT | C17: =C15-MAX(0,C15)*C16/100 | D17: =D15-MAX(0,D15)*D16/100 | E17: =E15-MAX(0,E15)*E16/100 | F17: =F15-MAX(0,F15)*F16/100 | G17: =G15-MAX(0,G15)*G16/100 | H17: =H15-MAX(0,H15)*H16/100 | I17: =I15-MAX(0,I15)*I16/100 | J17: =J15-MAX(0,J15)*J16/100 | ... L17: =L15-MAX(0,L15)*L16/100
A18: add back D&A | C18: =-C14 | D18: =-D14 | E18: =-E14 | F18: =-F14 | G18: =-G14 | H18: =-H14 | I18: =-I14 | J18: =-J14 | ... L18: =-L14
A19: Capex % of revenue (driver) | C19: 4 | D19: 5 | E19: 5.5 | F19: 6 | G19: 6.5 | H19: 6.5 | I19: 6.5 | J19: 6.5 | K19: 6.5 | L19: 6.5
A20: Capex $ | B20: -22.488 | C20: =-C6*C19/100 | D20: =-D6*D19/100 | E20: =-E6*E19/100 | F20: =-F6*F19/100 | G20: =-G6*G19/100 | H20: =-H6*H19/100 | I20: =-I6*I19/100 | J20: =-J6*J19/100 | ... L20: =-L6*L19/100
A21: Working capital (on revenue CHANGE) | C21: =Assumptions!$B$8/100*(C6-B6) | D21: =Assumptions!$B$8/100*(D6-C6) | E21: =Assumptions!$B$8/100*(E6-D6) | F21: =Assumptions!$B$8/100*(F6-E6) | G21: =Assumptions!$B$8/100*(G6-F6) | H21: =Assumptions!$B$8/100*(H6-G6) | I21: =Assumptions!$B$8/100*(I6-H6) | J21: =Assumptions!$B$8/100*(J6-I6) | ... L21: =Assumptions!$B$8/100*(L6-K6)
A22: Unlevered owner FCF | C22: =C17+C18+C20+C21 | D22: =D17+D18+D20+D21 | E22: =E17+E18+E20+E21 | F22: =F17+F18+F20+F21 | G22: =G17+G18+G20+G21 | H22: =H17+H18+H20+H21 | I22: =I17+I18+I20+I21 | J22: =J17+J18+J20+J21 | ... L22: =L17+L18+L20+L21
A23: Discount factor | C23: =1/(1+Assumptions!$B$5/100)^C4 | D23: =1/(1+Assumptions!$B$5/100)^D4 | E23: =1/(1+Assumptions!$B$5/100)^E4 | F23: =1/(1+Assumptions!$B$5/100)^F4 | G23: =1/(1+Assumptions!$B$5/100)^G4 | H23: =1/(1+Assumptions!$B$5/100)^H4 | I23: =1/(1+Assumptions!$B$5/100)^I4 | J23: =1/(1+Assumptions!$B$5/100)^J4 | ... L23: =1/(1+Assumptions!$B$5/100)^L4
A24: PV of FCF | C24: =C22*C23 | D24: =D22*D23 | E24: =E22*E23 | F24: =F22*F23 | G24: =G22*G23 | H24: =H22*H23 | I24: =I22*I23 | J24: =J22*J23 | ... L24: =L22*L23
A26: Memo: owner FCF margin % | C26: =C22/C6*100 | D26: =D22/D6*100 | E26: =E22/E6*100 | F26: =F22/F6*100 | G26: =G22/G6*100 | H26: =H22/H6*100 | I26: =I22/I6*100 | J26: =J22/J6*100 | ... L26: =L22/L6*100
A28: Sum PV of FCF (FY26-35) | B28: =SUM(C24:L24)
A29: Terminal growth % | B29: =Assumptions!$B$15
A30: Terminal FCF (y10 x (1+g)) | B30: =L22*(1+B29/100)
A31: Gordon TV | B31: =IF(Assumptions!$B$5>B29,B30/((Assumptions!$B$5-B29)/100),B32)
A32: Cap TV (13x y10 FCF) | B32: =Assumptions!$B$9*L22
A33: TV used = MAX(0,MIN(Gordon,Cap)) | B33: =MAX(0,MIN(B31,B32))
A34: Implied exit multiple (x FCF) | B34: =IF(L22=0,"n/a",B33/L22)
A35: PV of terminal value | B35: =B33/(1+Assumptions!$B$5/100)^10
A36: Enterprise value | B36: =B28+B35
A37: less net debt | B37: =Assumptions!$B$4
A38: Equity value | B38: =B36-B37
A39: Diluted shares (m) | B39: =Assumptions!$B$3
A40: VALUE PER SHARE (NZD) | B40: =B38/B39
A41: Upside vs price % | B41: =(B40/Assumptions!$B$2-1)*100
A42: Entry price (15% IRR hurdle) | B42: =(SUMPRODUCT(C22:L22/(1+Assumptions!$B$10/100)^C4:L4)+B33/(1+Assumptions!$B$10/100)^10-B37)/B39
A44: Street-basis memo: SBC is ~zero, so street value = house value (band collapsed; see Model_Info).

Sheet DCF_Base
A3: Year | B3: FY2025A | C3: FY2026E | D3: FY2027E | E3: FY2028E | F3: FY2029E | G3: FY2030E | H3: FY2031E | I3: FY2032E | J3: FY2033E | K3: FY2034E | L3: FY2035E
A4: Year index | B4: 0 | C4: 1 | D4: 2 | E4: 3 | F4: 4 | G4: 5 | H4: 6 | I4: 7 | J4: 8 | K4: 9 | L4: 10
A5: Revenue growth % (driver) | C5: -3.5 | D5: 2 | E5: 3 | F5: 3.5 | G5: 3 | H5: 2.5 | I5: 2.5 | J5: 2 | K5: 2 | L5: 2
A6: Revenue | B6: 584.109 | C6: =B6*(1+C5/100) | D6: =C6*(1+D5/100) | E6: =D6*(1+E5/100) | F6: =E6*(1+F5/100) | G6: =F6*(1+G5/100) | H6: =G6*(1+H5/100) | I6: =H6*(1+I5/100) | J6: =I6*(1+J5/100) | ... L6: =K6*(1+L5/100)
A7: Adj EBITDA margin % ex bio gains (driver) | B7: 24.1 | C7: 23.5 | D7: 22 | E7: 21 | F7: 20.5 | G7: 20 | H7: 20 | I7: 20 | J7: 20 | K7: 20 | L7: 20
A8: Adjusted EBITDA | B8: 140.992 | C8: =C6*C7/100 | D8: =D6*D7/100 | E8: =E6*E7/100 | F8: =F6*F7/100 | G8: =G6*G7/100 | H8: =H6*H7/100 | I8: =I6*I7/100 | J8: =J6*J7/100 | ... L8: =L6*L7/100
A9: SBC % of revenue (driver; SBC-zero filer) | C9: 0 | D9: 0 | E9: 0 | F9: 0 | G9: 0 | H9: 0 | I9: 0 | J9: 0 | K9: 0 | L9: 0
A10: SBC $ | B10: -0.219 | C10: =-C6*C9/100 | D10: =-D6*D9/100 | E10: =-E6*E9/100 | F10: =-F6*F9/100 | G10: =-G6*G9/100 | H10: =-H6*H9/100 | I10: =-I6*I9/100 | J10: =-J6*J9/100 | ... L10: =-L6*L9/100
A11: Lease cost % of revenue | C11: =Assumptions!$B$7 | D11: =Assumptions!$B$7 | E11: =Assumptions!$B$7 | F11: =Assumptions!$B$7 | G11: =Assumptions!$B$7 | H11: =Assumptions!$B$7 | I11: =Assumptions!$B$7 | J11: =Assumptions!$B$7 | ... L11: =Assumptions!$B$7
A12: Lease $ (principal + lease interest) | B12: -16.412 | C12: =-C6*C11/100 | D12: =-D6*D11/100 | E12: =-E6*E11/100 | F12: =-F6*F11/100 | G12: =-G6*G11/100 | H12: =-H6*H11/100 | I12: =-I6*I11/100 | J12: =-J6*J11/100 | ... L12: =-L6*L11/100
A13: D&A % of revenue (owned assets) | C13: =Assumptions!$B$6 | D13: =Assumptions!$B$6 | E13: =Assumptions!$B$6 | F13: =Assumptions!$B$6 | G13: =Assumptions!$B$6 | H13: =Assumptions!$B$6 | I13: =Assumptions!$B$6 | J13: =Assumptions!$B$6 | ... L13: =Assumptions!$B$6
A14: D&A $ | C14: =-C6*C13/100 | D14: =-D6*D13/100 | E14: =-E6*E13/100 | F14: =-F6*F13/100 | G14: =-G6*G13/100 | H14: =-H6*H13/100 | I14: =-I6*I13/100 | J14: =-J6*J13/100 | ... L14: =-L6*L13/100
A15: EBIT (SBC + lease expensed) | C15: =C8+C10+C12+C14 | D15: =D8+D10+D12+D14 | E15: =E8+E10+E12+E14 | F15: =F8+F10+F12+F14 | G15: =G8+G10+G12+G14 | H15: =H8+H10+H12+H14 | I15: =I8+I10+I12+I14 | J15: =J8+J10+J12+J14 | ... L15: =L8+L10+L12+L14
A16: Cash tax rate % (driver) | C16: 28 | D16: 28 | E16: 28 | F16: 28 | G16: 28 | H16: 28 | I16: 28 | J16: 28 | K16: 28 | L16: 28
A17: NOPAT | C17: =C15-MAX(0,C15)*C16/100 | D17: =D15-MAX(0,D15)*D16/100 | E17: =E15-MAX(0,E15)*E16/100 | F17: =F15-MAX(0,F15)*F16/100 | G17: =G15-MAX(0,G15)*G16/100 | H17: =H15-MAX(0,H15)*H16/100 | I17: =I15-MAX(0,I15)*I16/100 | J17: =J15-MAX(0,J15)*J16/100 | ... L17: =L15-MAX(0,L15)*L16/100
A18: add back D&A | C18: =-C14 | D18: =-D14 | E18: =-E14 | F18: =-F14 | G18: =-G14 | H18: =-H14 | I18: =-I14 | J18: =-J14 | ... L18: =-L14
A19: Capex % of revenue (driver) | C19: 3.5 | D19: 4.5 | E19: 5 | F19: 5.5 | G19: 6 | H19: 6 | I19: 6 | J19: 6 | K19: 6 | L19: 6
A20: Capex $ | B20: -22.488 | C20: =-C6*C19/100 | D20: =-D6*D19/100 | E20: =-E6*E19/100 | F20: =-F6*F19/100 | G20: =-G6*G19/100 | H20: =-H6*H19/100 | I20: =-I6*I19/100 | J20: =-J6*J19/100 | ... L20: =-L6*L19/100
A21: Working capital (on revenue CHANGE) | C21: =Assumptions!$B$8/100*(C6-B6) | D21: =Assumptions!$B$8/100*(D6-C6) | E21: =Assumptions!$B$8/100*(E6-D6) | F21: =Assumptions!$B$8/100*(F6-E6) | G21: =Assumptions!$B$8/100*(G6-F6) | H21: =Assumptions!$B$8/100*(H6-G6) | I21: =Assumptions!$B$8/100*(I6-H6) | J21: =Assumptions!$B$8/100*(J6-I6) | ... L21: =Assumptions!$B$8/100*(L6-K6)
A22: Unlevered owner FCF | C22: =C17+C18+C20+C21 | D22: =D17+D18+D20+D21 | E22: =E17+E18+E20+E21 | F22: =F17+F18+F20+F21 | G22: =G17+G18+G20+G21 | H22: =H17+H18+H20+H21 | I22: =I17+I18+I20+I21 | J22: =J17+J18+J20+J21 | ... L22: =L17+L18+L20+L21
A23: Discount factor | C23: =1/(1+Assumptions!$B$5/100)^C4 | D23: =1/(1+Assumptions!$B$5/100)^D4 | E23: =1/(1+Assumptions!$B$5/100)^E4 | F23: =1/(1+Assumptions!$B$5/100)^F4 | G23: =1/(1+Assumptions!$B$5/100)^G4 | H23: =1/(1+Assumptions!$B$5/100)^H4 | I23: =1/(1+Assumptions!$B$5/100)^I4 | J23: =1/(1+Assumptions!$B$5/100)^J4 | ... L23: =1/(1+Assumptions!$B$5/100)^L4
A24: PV of FCF | C24: =C22*C23 | D24: =D22*D23 | E24: =E22*E23 | F24: =F22*F23 | G24: =G22*G23 | H24: =H22*H23 | I24: =I22*I23 | J24: =J22*J23 | ... L24: =L22*L23
A26: Memo: owner FCF margin % | C26: =C22/C6*100 | D26: =D22/D6*100 | E26: =E22/E6*100 | F26: =F22/F6*100 | G26: =G22/G6*100 | H26: =H22/H6*100 | I26: =I22/I6*100 | J26: =J22/J6*100 | ... L26: =L22/L6*100
A28: Sum PV of FCF (FY26-35) | B28: =SUM(C24:L24)
A29: Terminal growth % | B29: =Assumptions!$C$15
A30: Terminal FCF (y10 x (1+g)) | B30: =L22*(1+B29/100)
A31: Gordon TV | B31: =IF(Assumptions!$B$5>B29,B30/((Assumptions!$B$5-B29)/100),B32)
A32: Cap TV (13x y10 FCF) | B32: =Assumptions!$B$9*L22
A33: TV used = MAX(0,MIN(Gordon,Cap)) | B33: =MAX(0,MIN(B31,B32))
A34: Implied exit multiple (x FCF) | B34: =IF(L22=0,"n/a",B33/L22)
A35: PV of terminal value | B35: =B33/(1+Assumptions!$B$5/100)^10
A36: Enterprise value | B36: =B28+B35
A37: less net debt | B37: =Assumptions!$B$4
A38: Equity value | B38: =B36-B37
A39: Diluted shares (m) | B39: =Assumptions!$B$3
A40: VALUE PER SHARE (NZD) | B40: =B38/B39
A41: Upside vs price % | B41: =(B40/Assumptions!$B$2-1)*100
A42: Entry price (15% IRR hurdle) | B42: =(SUMPRODUCT(C22:L22/(1+Assumptions!$B$10/100)^C4:L4)+B33/(1+Assumptions!$B$10/100)^10-B37)/B39
A44: Street-basis memo: SBC is ~zero, so street value = house value (band collapsed; see Model_Info).

Sheet DCF_Bull
A3: Year | B3: FY2025A | C3: FY2026E | D3: FY2027E | E3: FY2028E | F3: FY2029E | G3: FY2030E | H3: FY2031E | I3: FY2032E | J3: FY2033E | K3: FY2034E | L3: FY2035E
A4: Year index | B4: 0 | C4: 1 | D4: 2 | E4: 3 | F4: 4 | G4: 5 | H4: 6 | I4: 7 | J4: 8 | K4: 9 | L4: 10
A5: Revenue growth % (driver) | C5: -2 | D5: 3.5 | E5: 5 | F5: 5 | G5: 4.5 | H5: 4 | I5: 3.5 | J5: 3 | K5: 2.5 | L5: 2.5
A6: Revenue | B6: 584.109 | C6: =B6*(1+C5/100) | D6: =C6*(1+D5/100) | E6: =D6*(1+E5/100) | F6: =E6*(1+F5/100) | G6: =F6*(1+G5/100) | H6: =G6*(1+H5/100) | I6: =H6*(1+I5/100) | J6: =I6*(1+J5/100) | ... L6: =K6*(1+L5/100)
A7: Adj EBITDA margin % ex bio gains (driver) | B7: 24.1 | C7: 25 | D7: 24 | E7: 23.5 | F7: 23 | G7: 23 | H7: 23 | I7: 23 | J7: 23 | K7: 23 | L7: 23
A8: Adjusted EBITDA | B8: 140.992 | C8: =C6*C7/100 | D8: =D6*D7/100 | E8: =E6*E7/100 | F8: =F6*F7/100 | G8: =G6*G7/100 | H8: =H6*H7/100 | I8: =I6*I7/100 | J8: =J6*J7/100 | ... L8: =L6*L7/100
A9: SBC % of revenue (driver; SBC-zero filer) | C9: 0 | D9: 0 | E9: 0 | F9: 0 | G9: 0 | H9: 0 | I9: 0 | J9: 0 | K9: 0 | L9: 0
A10: SBC $ | B10: -0.219 | C10: =-C6*C9/100 | D10: =-D6*D9/100 | E10: =-E6*E9/100 | F10: =-F6*F9/100 | G10: =-G6*G9/100 | H10: =-H6*H9/100 | I10: =-I6*I9/100 | J10: =-J6*J9/100 | ... L10: =-L6*L9/100
A11: Lease cost % of revenue | C11: =Assumptions!$B$7 | D11: =Assumptions!$B$7 | E11: =Assumptions!$B$7 | F11: =Assumptions!$B$7 | G11: =Assumptions!$B$7 | H11: =Assumptions!$B$7 | I11: =Assumptions!$B$7 | J11: =Assumptions!$B$7 | ... L11: =Assumptions!$B$7
A12: Lease $ (principal + lease interest) | B12: -16.412 | C12: =-C6*C11/100 | D12: =-D6*D11/100 | E12: =-E6*E11/100 | F12: =-F6*F11/100 | G12: =-G6*G11/100 | H12: =-H6*H11/100 | I12: =-I6*I11/100 | J12: =-J6*J11/100 | ... L12: =-L6*L11/100
A13: D&A % of revenue (owned assets) | C13: =Assumptions!$B$6 | D13: =Assumptions!$B$6 | E13: =Assumptions!$B$6 | F13: =Assumptions!$B$6 | G13: =Assumptions!$B$6 | H13: =Assumptions!$B$6 | I13: =Assumptions!$B$6 | J13: =Assumptions!$B$6 | ... L13: =Assumptions!$B$6
A14: D&A $ | C14: =-C6*C13/100 | D14: =-D6*D13/100 | E14: =-E6*E13/100 | F14: =-F6*F13/100 | G14: =-G6*G13/100 | H14: =-H6*H13/100 | I14: =-I6*I13/100 | J14: =-J6*J13/100 | ... L14: =-L6*L13/100
A15: EBIT (SBC + lease expensed) | C15: =C8+C10+C12+C14 | D15: =D8+D10+D12+D14 | E15: =E8+E10+E12+E14 | F15: =F8+F10+F12+F14 | G15: =G8+G10+G12+G14 | H15: =H8+H10+H12+H14 | I15: =I8+I10+I12+I14 | J15: =J8+J10+J12+J14 | ... L15: =L8+L10+L12+L14
A16: Cash tax rate % (driver) | C16: 28 | D16: 28 | E16: 28 | F16: 28 | G16: 28 | H16: 28 | I16: 28 | J16: 28 | K16: 28 | L16: 28
A17: NOPAT | C17: =C15-MAX(0,C15)*C16/100 | D17: =D15-MAX(0,D15)*D16/100 | E17: =E15-MAX(0,E15)*E16/100 | F17: =F15-MAX(0,F15)*F16/100 | G17: =G15-MAX(0,G15)*G16/100 | H17: =H15-MAX(0,H15)*H16/100 | I17: =I15-MAX(0,I15)*I16/100 | J17: =J15-MAX(0,J15)*J16/100 | ... L17: =L15-MAX(0,L15)*L16/100
A18: add back D&A | C18: =-C14 | D18: =-D14 | E18: =-E14 | F18: =-F14 | G18: =-G14 | H18: =-H14 | I18: =-I14 | J18: =-J14 | ... L18: =-L14
A19: Capex % of revenue (driver) | C19: 3.5 | D19: 4 | E19: 4.5 | F19: 5 | G19: 5 | H19: 5 | I19: 5 | J19: 5 | K19: 5 | L19: 5
A20: Capex $ | B20: -22.488 | C20: =-C6*C19/100 | D20: =-D6*D19/100 | E20: =-E6*E19/100 | F20: =-F6*F19/100 | G20: =-G6*G19/100 | H20: =-H6*H19/100 | I20: =-I6*I19/100 | J20: =-J6*J19/100 | ... L20: =-L6*L19/100
A21: Working capital (on revenue CHANGE) | C21: =Assumptions!$B$8/100*(C6-B6) | D21: =Assumptions!$B$8/100*(D6-C6) | E21: =Assumptions!$B$8/100*(E6-D6) | F21: =Assumptions!$B$8/100*(F6-E6) | G21: =Assumptions!$B$8/100*(G6-F6) | H21: =Assumptions!$B$8/100*(H6-G6) | I21: =Assumptions!$B$8/100*(I6-H6) | J21: =Assumptions!$B$8/100*(J6-I6) | ... L21: =Assumptions!$B$8/100*(L6-K6)
A22: Unlevered owner FCF | C22: =C17+C18+C20+C21 | D22: =D17+D18+D20+D21 | E22: =E17+E18+E20+E21 | F22: =F17+F18+F20+F21 | G22: =G17+G18+G20+G21 | H22: =H17+H18+H20+H21 | I22: =I17+I18+I20+I21 | J22: =J17+J18+J20+J21 | ... L22: =L17+L18+L20+L21
A23: Discount factor | C23: =1/(1+Assumptions!$B$5/100)^C4 | D23: =1/(1+Assumptions!$B$5/100)^D4 | E23: =1/(1+Assumptions!$B$5/100)^E4 | F23: =1/(1+Assumptions!$B$5/100)^F4 | G23: =1/(1+Assumptions!$B$5/100)^G4 | H23: =1/(1+Assumptions!$B$5/100)^H4 | I23: =1/(1+Assumptions!$B$5/100)^I4 | J23: =1/(1+Assumptions!$B$5/100)^J4 | ... L23: =1/(1+Assumptions!$B$5/100)^L4
A24: PV of FCF | C24: =C22*C23 | D24: =D22*D23 | E24: =E22*E23 | F24: =F22*F23 | G24: =G22*G23 | H24: =H22*H23 | I24: =I22*I23 | J24: =J22*J23 | ... L24: =L22*L23
A26: Memo: owner FCF margin % | C26: =C22/C6*100 | D26: =D22/D6*100 | E26: =E22/E6*100 | F26: =F22/F6*100 | G26: =G22/G6*100 | H26: =H22/H6*100 | I26: =I22/I6*100 | J26: =J22/J6*100 | ... L26: =L22/L6*100
A28: Sum PV of FCF (FY26-35) | B28: =SUM(C24:L24)
A29: Terminal growth % | B29: =Assumptions!$D$15
A30: Terminal FCF (y10 x (1+g)) | B30: =L22*(1+B29/100)
A31: Gordon TV | B31: =IF(Assumptions!$B$5>B29,B30/((Assumptions!$B$5-B29)/100),B32)
A32: Cap TV (13x y10 FCF) | B32: =Assumptions!$B$9*L22
A33: TV used = MAX(0,MIN(Gordon,Cap)) | B33: =MAX(0,MIN(B31,B32))
A34: Implied exit multiple (x FCF) | B34: =IF(L22=0,"n/a",B33/L22)
A35: PV of terminal value | B35: =B33/(1+Assumptions!$B$5/100)^10
A36: Enterprise value | B36: =B28+B35
A37: less net debt | B37: =Assumptions!$B$4
A38: Equity value | B38: =B36-B37
A39: Diluted shares (m) | B39: =Assumptions!$B$3
A40: VALUE PER SHARE (NZD) | B40: =B38/B39
A41: Upside vs price % | B41: =(B40/Assumptions!$B$2-1)*100
A42: Entry price (15% IRR hurdle) | B42: =(SUMPRODUCT(C22:L22/(1+Assumptions!$B$10/100)^C4:L4)+B33/(1+Assumptions!$B$10/100)^10-B37)/B39
A44: Street-basis memo: SBC is ~zero, so street value = house value (band collapsed; see Model_Info).

Sheet FCF_Quality
A1: Period | B1: Reported FCF (OCF - capex) | C1: less SBC | D1: less lease cash | E1: Owner FCF | F1: Reported FCF margin % | G1: Owner FCF margin % | H1: Cash tax paid | I1: Cash tax / PBT %
A2: FY2016 | B2: -7.776 | C2: 0.171 | D2: 0 | E2: =B2-C2-D2 | F2: =B2/463.469*100 | G2: =E2/463.469*100 | H2: 12.501 | I2: =H2/48.0*100
A3: FY2017 | B3: 13.477 | C3: 0.171 | D3: 0 | E3: =B3-C3-D3 | F3: =B3/477.94*100 | G3: =E3/477.94*100 | H3: 13.505 | I3: =H3/51.65*100
A4: FY2018 | B4: 47.908 | C4: 0.062 | D4: 0 | E4: =B4-C4-D4 | F4: =B4/514.976*100 | G4: =E4/514.976*100 | H4: 8.95 | I4: =H4/59.964*100
A5: FY2019 | B5: 10.304 | C5: -0.001 | D5: 0 | E5: =B5-C5-D5 | F5: =B5/545.121*100 | G5: =E5/545.121*100 | H5: 15.026 | I5: =H5/59.323*100
A6: FY2020 | B6: -24.413 | C6: -0.401 | D6: 10.94 | E6: =B6-C6-D6 | F6: =B6/468.849*100 | G6: =E6/468.849*100 | H6: 10.131 | I6: =H6/30.757*100
A7: FY2021 | B7: -10.967 | C7: -0.401 | D7: 11.017 | E7: =B7-C7-D7 | F7: =B7/489.625*100 | G7: =E7/489.625*100 | H7: 1.191 | I7: =H7/20.035*100
A8: FY2022 | B8: -8.538 | C8: 0.121 | D8: 11.359 | E8: =B8-C8-D8 | F8: =B8/531.887*100 | G8: =E8/531.887*100 | H8: 1.619 | I8: =H8/62.464*100
A9: FY2023 | B9: -23.359 | C9: -0.143 | D9: 12.36 | E9: =B9-C9-D9 | F9: =B9/553.397*100 | G9: =E9/553.397*100 | H9: 9.156 | I9: =H9/17.482*100
A10: FY2024 | B10: 27.08 | C10: 0 | D10: 15.171 | E10: =B10-C10-D10 | F10: =B10/582.913*100 | G10: =E10/582.913*100 | H10: 7.77 | I10: =H10/37.395*100
A11: FY2025 | B11: 112.854 | C11: 0.219 | D11: 16.412 | E11: =B11-C11-D11 | F11: =B11/584.109*100 | G11: =E11/584.109*100 | H11: 3.322 | I11: =H11/89.961*100
A12: H1 FY2026 | B12: 6.978 | C12: 0.125 | D12: 12.347 | E12: =B12-C12-D12 | F12: =B12/270.154*100 | G12: =E12/270.154*100 | H12: 17.493 | I12: =H12/59.781*100
A14: Lease cash: CF-statement lease payments (principal); FY2024/FY2025 use note-19 principal+interest (15.171/16.412); H1 FY2026 = 11.347 principal + ~1.0 est. interest. Pre-IFRS16 years (to FY2019) leases were already expensed in EBITDA -- 0 adjustment.
A15: Interest income NOT deducted: net-debt company, no separately-added cash pile (owner-fcf.md s1b).
A16: The FY2025 line is the peak-FCF exhibit: owner FCF $96.2m vs a $15m FY2016-25 median; cash tax paid 3.7% of PBT vs 28% statutory (H1 FY2026 paid $17.5m as the catch-up); H1 FY2026 owner FCF is NEGATIVE (~-$5.5m) on the mussel inventory build.
A17: Memo: no deferred-revenue tailwind exists in this business; the WC swing factor is inventory (frozen mussels) and receivables timing.

Sheet Valuation
A1: Scenario summary
B2: Value/share | C2: Upside % | D2: Weight | E2: Entry price (15%)
A3: Bear | B3: =DCF_Bear!$B$40 | C3: =(B3/Assumptions!$B$2-1)*100 | D3: =Assumptions!$B$16 | E3: =DCF_Bear!$B$42
A4: Base | B4: =DCF_Base!$B$40 | C4: =(B4/Assumptions!$B$2-1)*100 | D4: =Assumptions!$C$16 | E4: =DCF_Base!$B$42
A5: Bull | B5: =DCF_Bull!$B$40 | C5: =(B5/Assumptions!$B$2-1)*100 | D5: =Assumptions!$D$16 | E5: =DCF_Bull!$B$42
A7: Probability-weighted intrinsic value | B7: =SUMPRODUCT(B3:B5,D3:D5)
A8: Margin of safety at current price | B8: =1-Assumptions!$B$2/B7
A9: Probability-weighted entry price (15% hurdle) | B9: =SUMPRODUCT(E3:E5,D3:D5)
A10: Street weighted value (= house; SBC ~ 0) | B10: =B7
A11: Band position | B11: n/a -- SBC-zero filer, house = street
A13: Required-return table (base case; TV fixed at WACC-Gordon)
A14: Required return % | B14: 9 | C14: 10 | D14: 10.5 | E14: 11 | F14: 12 | G14: 15
A15: Value per share | B15: =(SUMPRODUCT(DCF_Base!$C$22:$L$22/(1+B14/100)^DCF_Base!$C$4:$L$4)+DCF_Base!$B$33/(1+B14/100)^10-Assumptions!$B$4)/Assumptions!$B$3 | C15: =(SUMPRODUCT(DCF_Base!$C$22:$L$22/(1+C14/100)^DCF_Base!$C$4:$L$4)+DCF_Base!$B$33/(1+C14/100)^10-Assumptions!$B$4)/Assumptions!$B$3 | D15: =(SUMPRODUCT(DCF_Base!$C$22:$L$22/(1+D14/100)^DCF_Base!$C$4:$L$4)+DCF_Base!$B$33/(1+D14/100)^10-Assumptions!$B$4)/Assumptions!$B$3 | E15: =(SUMPRODUCT(DCF_Base!$C$22:$L$22/(1+E14/100)^DCF_Base!$C$4:$L$4)+DCF_Base!$B$33/(1+E14/100)^10-Assumptions!$B$4)/Assumptions!$B$3 | F15: =(SUMPRODUCT(DCF_Base!$C$22:$L$22/(1+F14/100)^DCF_Base!$C$4:$L$4)+DCF_Base!$B$33/(1+F14/100)^10-Assumptions!$B$4)/Assumptions!$B$3 | G15: =(SUMPRODUCT(DCF_Base!$C$22:$L$22/(1+G14/100)^DCF_Base!$C$4:$L$4)+DCF_Base!$B$33/(1+G14/100)^10-Assumptions!$B$4)/Assumptions!$B$3
A17: Sensitivity: WACC (rows) x terminal growth (cols), base case, full TV recompute
B18: 1 | C18: 1.5 | D18: 2 | E18: 2.5 | F18: 3
A19: 8.5 | B19: =IF($A$19>B$18,(SUMPRODUCT(DCF_Base!$C$22:$L$22/(1+$A$19/100)^DCF_Base!$C$4:$L$4)+MAX(0,MIN(DCF_Base!$L$22*(1+B$18/100)/(($A$19-B$18)/100),Assumptions!$B$9*DCF_Base!$L$22))/(1+$A$19/100)^10-Assumptions!$B$4)/Assumptions!$B$3,"n/a") | C19: =IF($A$19>C$18,(SUMPRODUCT(DCF_Base!$C$22:$L$22/(1+$A$19/100)^DCF_Base!$C$4:$L$4)+MAX(0,MIN(DCF_Base!$L$22*(1+C$18/100)/(($A$19-C$18)/100),Assumptions!$B$9*DCF_Base!$L$22))/(1+$A$19/100)^10-Assumptions!$B$4)/Assumptions!$B$3,"n/a") | D19: =IF($A$19>D$18,(SUMPRODUCT(DCF_Base!$C$22:$L$22/(1+$A$19/100)^DCF_Base!$C$4:$L$4)+MAX(0,MIN(DCF_Base!$L$22*(1+D$18/100)/(($A$19-D$18)/100),Assumptions!$B$9*DCF_Base!$L$22))/(1+$A$19/100)^10-Assumptions!$B$4)/Assumptions!$B$3,"n/a") | E19: =IF($A$19>E$18,(SUMPRODUCT(DCF_Base!$C$22:$L$22/(1+$A$19/100)^DCF_Base!$C$4:$L$4)+MAX(0,MIN(DCF_Base!$L$22*(1+E$18/100)/(($A$19-E$18)/100),Assumptions!$B$9*DCF_Base!$L$22))/(1+$A$19/100)^10-Assumptions!$B$4)/Assumptions!$B$3,"n/a") | F19: =IF($A$19>F$18,(SUMPRODUCT(DCF_Base!$C$22:$L$22/(1+$A$19/100)^DCF_Base!$C$4:$L$4)+MAX(0,MIN(DCF_Base!$L$22*(1+F$18/100)/(($A$19-F$18)/100),Assumptions!$B$9*DCF_Base!$L$22))/(1+$A$19/100)^10-Assumptions!$B$4)/Assumptions!$B$3,"n/a")
A20: 9.5 | B20: =IF($A$20>B$18,(SUMPRODUCT(DCF_Base!$C$22:$L$22/(1+$A$20/100)^DCF_Base!$C$4:$L$4)+MAX(0,MIN(DCF_Base!$L$22*(1+B$18/100)/(($A$20-B$18)/100),Assumptions!$B$9*DCF_Base!$L$22))/(1+$A$20/100)^10-Assumptions!$B$4)/Assumptions!$B$3,"n/a") | C20: =IF($A$20>C$18,(SUMPRODUCT(DCF_Base!$C$22:$L$22/(1+$A$20/100)^DCF_Base!$C$4:$L$4)+MAX(0,MIN(DCF_Base!$L$22*(1+C$18/100)/(($A$20-C$18)/100),Assumptions!$B$9*DCF_Base!$L$22))/(1+$A$20/100)^10-Assumptions!$B$4)/Assumptions!$B$3,"n/a") | D20: =IF($A$20>D$18,(SUMPRODUCT(DCF_Base!$C$22:$L$22/(1+$A$20/100)^DCF_Base!$C$4:$L$4)+MAX(0,MIN(DCF_Base!$L$22*(1+D$18/100)/(($A$20-D$18)/100),Assumptions!$B$9*DCF_Base!$L$22))/(1+$A$20/100)^10-Assumptions!$B$4)/Assumptions!$B$3,"n/a") | E20: =IF($A$20>E$18,(SUMPRODUCT(DCF_Base!$C$22:$L$22/(1+$A$20/100)^DCF_Base!$C$4:$L$4)+MAX(0,MIN(DCF_Base!$L$22*(1+E$18/100)/(($A$20-E$18)/100),Assumptions!$B$9*DCF_Base!$L$22))/(1+$A$20/100)^10-Assumptions!$B$4)/Assumptions!$B$3,"n/a") | F20: =IF($A$20>F$18,(SUMPRODUCT(DCF_Base!$C$22:$L$22/(1+$A$20/100)^DCF_Base!$C$4:$L$4)+MAX(0,MIN(DCF_Base!$L$22*(1+F$18/100)/(($A$20-F$18)/100),Assumptions!$B$9*DCF_Base!$L$22))/(1+$A$20/100)^10-Assumptions!$B$4)/Assumptions!$B$3,"n/a")
A21: 10.5 | B21: =IF($A$21>B$18,(SUMPRODUCT(DCF_Base!$C$22:$L$22/(1+$A$21/100)^DCF_Base!$C$4:$L$4)+MAX(0,MIN(DCF_Base!$L$22*(1+B$18/100)/(($A$21-B$18)/100),Assumptions!$B$9*DCF_Base!$L$22))/(1+$A$21/100)^10-Assumptions!$B$4)/Assumptions!$B$3,"n/a") | C21: =IF($A$21>C$18,(SUMPRODUCT(DCF_Base!$C$22:$L$22/(1+$A$21/100)^DCF_Base!$C$4:$L$4)+MAX(0,MIN(DCF_Base!$L$22*(1+C$18/100)/(($A$21-C$18)/100),Assumptions!$B$9*DCF_Base!$L$22))/(1+$A$21/100)^10-Assumptions!$B$4)/Assumptions!$B$3,"n/a") | D21: =IF($A$21>D$18,(SUMPRODUCT(DCF_Base!$C$22:$L$22/(1+$A$21/100)^DCF_Base!$C$4:$L$4)+MAX(0,MIN(DCF_Base!$L$22*(1+D$18/100)/(($A$21-D$18)/100),Assumptions!$B$9*DCF_Base!$L$22))/(1+$A$21/100)^10-Assumptions!$B$4)/Assumptions!$B$3,"n/a") | E21: =IF($A$21>E$18,(SUMPRODUCT(DCF_Base!$C$22:$L$22/(1+$A$21/100)^DCF_Base!$C$4:$L$4)+MAX(0,MIN(DCF_Base!$L$22*(1+E$18/100)/(($A$21-E$18)/100),Assumptions!$B$9*DCF_Base!$L$22))/(1+$A$21/100)^10-Assumptions!$B$4)/Assumptions!$B$3,"n/a") | F21: =IF($A$21>F$18,(SUMPRODUCT(DCF_Base!$C$22:$L$22/(1+$A$21/100)^DCF_Base!$C$4:$L$4)+MAX(0,MIN(DCF_Base!$L$22*(1+F$18/100)/(($A$21-F$18)/100),Assumptions!$B$9*DCF_Base!$L$22))/(1+$A$21/100)^10-Assumptions!$B$4)/Assumptions!$B$3,"n/a")
A22: 11.5 | B22: =IF($A$22>B$18,(SUMPRODUCT(DCF_Base!$C$22:$L$22/(1+$A$22/100)^DCF_Base!$C$4:$L$4)+MAX(0,MIN(DCF_Base!$L$22*(1+B$18/100)/(($A$22-B$18)/100),Assumptions!$B$9*DCF_Base!$L$22))/(1+$A$22/100)^10-Assumptions!$B$4)/Assumptions!$B$3,"n/a") | C22: =IF($A$22>C$18,(SUMPRODUCT(DCF_Base!$C$22:$L$22/(1+$A$22/100)^DCF_Base!$C$4:$L$4)+MAX(0,MIN(DCF_Base!$L$22*(1+C$18/100)/(($A$22-C$18)/100),Assumptions!$B$9*DCF_Base!$L$22))/(1+$A$22/100)^10-Assumptions!$B$4)/Assumptions!$B$3,"n/a") | D22: =IF($A$22>D$18,(SUMPRODUCT(DCF_Base!$C$22:$L$22/(1+$A$22/100)^DCF_Base!$C$4:$L$4)+MAX(0,MIN(DCF_Base!$L$22*(1+D$18/100)/(($A$22-D$18)/100),Assumptions!$B$9*DCF_Base!$L$22))/(1+$A$22/100)^10-Assumptions!$B$4)/Assumptions!$B$3,"n/a") | E22: =IF($A$22>E$18,(SUMPRODUCT(DCF_Base!$C$22:$L$22/(1+$A$22/100)^DCF_Base!$C$4:$L$4)+MAX(0,MIN(DCF_Base!$L$22*(1+E$18/100)/(($A$22-E$18)/100),Assumptions!$B$9*DCF_Base!$L$22))/(1+$A$22/100)^10-Assumptions!$B$4)/Assumptions!$B$3,"n/a") | F22: =IF($A$22>F$18,(SUMPRODUCT(DCF_Base!$C$22:$L$22/(1+$A$22/100)^DCF_Base!$C$4:$L$4)+MAX(0,MIN(DCF_Base!$L$22*(1+F$18/100)/(($A$22-F$18)/100),Assumptions!$B$9*DCF_Base!$L$22))/(1+$A$22/100)^10-Assumptions!$B$4)/Assumptions!$B$3,"n/a")
A23: 12.5 | B23: =IF($A$23>B$18,(SUMPRODUCT(DCF_Base!$C$22:$L$22/(1+$A$23/100)^DCF_Base!$C$4:$L$4)+MAX(0,MIN(DCF_Base!$L$22*(1+B$18/100)/(($A$23-B$18)/100),Assumptions!$B$9*DCF_Base!$L$22))/(1+$A$23/100)^10-Assumptions!$B$4)/Assumptions!$B$3,"n/a") | C23: =IF($A$23>C$18,(SUMPRODUCT(DCF_Base!$C$22:$L$22/(1+$A$23/100)^DCF_Base!$C$4:$L$4)+MAX(0,MIN(DCF_Base!$L$22*(1+C$18/100)/(($A$23-C$18)/100),Assumptions!$B$9*DCF_Base!$L$22))/(1+$A$23/100)^10-Assumptions!$B$4)/Assumptions!$B$3,"n/a") | D23: =IF($A$23>D$18,(SUMPRODUCT(DCF_Base!$C$22:$L$22/(1+$A$23/100)^DCF_Base!$C$4:$L$4)+MAX(0,MIN(DCF_Base!$L$22*(1+D$18/100)/(($A$23-D$18)/100),Assumptions!$B$9*DCF_Base!$L$22))/(1+$A$23/100)^10-Assumptions!$B$4)/Assumptions!$B$3,"n/a") | E23: =IF($A$23>E$18,(SUMPRODUCT(DCF_Base!$C$22:$L$22/(1+$A$23/100)^DCF_Base!$C$4:$L$4)+MAX(0,MIN(DCF_Base!$L$22*(1+E$18/100)/(($A$23-E$18)/100),Assumptions!$B$9*DCF_Base!$L$22))/(1+$A$23/100)^10-Assumptions!$B$4)/Assumptions!$B$3,"n/a") | F23: =IF($A$23>F$18,(SUMPRODUCT(DCF_Base!$C$22:$L$22/(1+$A$23/100)^DCF_Base!$C$4:$L$4)+MAX(0,MIN(DCF_Base!$L$22*(1+F$18/100)/(($A$23-F$18)/100),Assumptions!$B$9*DCF_Base!$L$22))/(1+$A$23/100)^10-Assumptions!$B$4)/Assumptions!$B$3,"n/a")
