Workbook

Sheet DCF Model
A1: SPK.NZ DCF Valuation Model
A2: Gray cells are INPUTS - adjust to see valuation change
A4: KEY INPUTS
A5: Current Stock Price | B5: 1.875
A6: Shares Outstanding (M) | B6: 1890
A7: Cash & Equivalents (M) | B7: 85
A8: Total Debt (M) | B8: 1510
A9: Net Debt (M) | B9: =B8-B7
A10: Base Year FCF (M) | B10: 330
A12: WACC | B12: 0.09
A13: Terminal Growth Rate | B13: 0.015
A15: GROWTH ASSUMPTIONS | B15: Year 1 | C15: Year 2 | D15: Year 3 | E15: Year 4 | F15: Year 5
A16: FCF Growth Rate | B16: 0 | C16: -0.01 | D16: -0.01 | E16: 0 | F16: 0
A18: PROJECTIONS
B19: Base | C19: Year 1 | D19: Year 2 | E19: Year 3 | F19: Year 4 | G19: Year 5
A20: Free Cash Flow | B20: =B10 | C20: =B20*(1+B16) | D20: =C20*(1+C16) | E20: =D20*(1+D16) | F20: =E20*(1+E16) | G20: =F20*(1+F16)
A21: Discount Factor | C21: =1/(1+$B$12)^1 | D21: =1/(1+$B$12)^2 | E21: =1/(1+$B$12)^3 | F21: =1/(1+$B$12)^4 | G21: =1/(1+$B$12)^5
A22: PV of FCF | C22: =C20*C21 | D22: =D20*D21 | E22: =E20*E21 | F22: =F20*F21 | G22: =G20*G21
A24: VALUATION
A25: Sum of PV of FCF | B25: =SUM(C22:G22)
A26: Terminal FCF (Year 5 * (1+g)) | B26: =G20*(1+$B$13)
A27: Terminal Value | B27: =B26/($B$12-$B$13)
A28: PV of Terminal Value | B28: =B27*G21
A29: Enterprise Value | B29: =B25+B28
A30: Less: Net Debt | B30: =B9
A31: Equity Value | B31: =B29-B30
A32: INTRINSIC VALUE/SHARE | B32: =B31/B6
A34: ENTRY PRICE (15% CAGR Target)
A35: Terminal Value per Share | B35: =B27/B6
A36: Entry Price (15% CAGR) | B36: =B35/(1.15^5)
A38: Upside to IV | B38: =(B32-B5)/B5
A39: Upside to Entry Price | B39: =(B5-B36)/B5

Sheet Sensitivity
A1: Sensitivity Analysis
A2: Intrinsic Value by WACC & Terminal Growth
A4: WACC \ Term G | B4: 0.01 | C4: 0.015 | D4: 0.02 | E4: 0.025 | F4: 0.03
A5: 0.07 | B5: =('DCF Model'!$B$10*(1+'DCF Model'!$B$16)*(1+'DCF Model'!$C$16)*(1+'DCF Model'!$D$16)*(1+'DCF Model'!$E$16)*(1+'DCF Model'!$F$16)*(1+0.01)/(0.07-0.01))/(1+0.07)^5/'DCF Model'!$B$6+('DCF Model'!B25-'DCF Model'!B9)/'DCF Model'!$B$6 | C5: =('DCF Model'!$B$10*(1+'DCF Model'!$B$16)*(1+'DCF Model'!$C$16)*(1+'DCF Model'!$D$16)*(1+'DCF Model'!$E$16)*(1+'DCF Model'!$F$16)*(1+0.015)/(0.07-0.015))/(1+0.07)^5/'DCF Model'!$B$6+('DCF Model'!B25-'DCF Model'!B9)/'DCF Model'!$B$6 | D5: =('DCF Model'!$B$10*(1+'DCF Model'!$B$16)*(1+'DCF Model'!$C$16)*(1+'DCF Model'!$D$16)*(1+'DCF Model'!$E$16)*(1+'DCF Model'!$F$16)*(1+0.02)/(0.07-0.02))/(1+0.07)^5/'DCF Model'!$B$6+('DCF Model'!B25-'DCF Model'!B9)/'DCF Model'!$B$6 | E5: =('DCF Model'!$B$10*(1+'DCF Model'!$B$16)*(1+'DCF Model'!$C$16)*(1+'DCF Model'!$D$16)*(1+'DCF Model'!$E$16)*(1+'DCF Model'!$F$16)*(1+0.025)/(0.07-0.025))/(1+0.07)^5/'DCF Model'!$B$6+('DCF Model'!B25-'DCF Model'!B9)/'DCF Model'!$B$6 | F5: =('DCF Model'!$B$10*(1+'DCF Model'!$B$16)*(1+'DCF Model'!$C$16)*(1+'DCF Model'!$D$16)*(1+'DCF Model'!$E$16)*(1+'DCF Model'!$F$16)*(1+0.03)/(0.07-0.03))/(1+0.07)^5/'DCF Model'!$B$6+('DCF Model'!B25-'DCF Model'!B9)/'DCF Model'!$B$6
A6: 0.08 | B6: =('DCF Model'!$B$10*(1+'DCF Model'!$B$16)*(1+'DCF Model'!$C$16)*(1+'DCF Model'!$D$16)*(1+'DCF Model'!$E$16)*(1+'DCF Model'!$F$16)*(1+0.01)/(0.08-0.01))/(1+0.08)^5/'DCF Model'!$B$6+('DCF Model'!B25-'DCF Model'!B9)/'DCF Model'!$B$6 | C6: =('DCF Model'!$B$10*(1+'DCF Model'!$B$16)*(1+'DCF Model'!$C$16)*(1+'DCF Model'!$D$16)*(1+'DCF Model'!$E$16)*(1+'DCF Model'!$F$16)*(1+0.015)/(0.08-0.015))/(1+0.08)^5/'DCF Model'!$B$6+('DCF Model'!B25-'DCF Model'!B9)/'DCF Model'!$B$6 | D6: =('DCF Model'!$B$10*(1+'DCF Model'!$B$16)*(1+'DCF Model'!$C$16)*(1+'DCF Model'!$D$16)*(1+'DCF Model'!$E$16)*(1+'DCF Model'!$F$16)*(1+0.02)/(0.08-0.02))/(1+0.08)^5/'DCF Model'!$B$6+('DCF Model'!B25-'DCF Model'!B9)/'DCF Model'!$B$6 | E6: =('DCF Model'!$B$10*(1+'DCF Model'!$B$16)*(1+'DCF Model'!$C$16)*(1+'DCF Model'!$D$16)*(1+'DCF Model'!$E$16)*(1+'DCF Model'!$F$16)*(1+0.025)/(0.08-0.025))/(1+0.08)^5/'DCF Model'!$B$6+('DCF Model'!B25-'DCF Model'!B9)/'DCF Model'!$B$6 | F6: =('DCF Model'!$B$10*(1+'DCF Model'!$B$16)*(1+'DCF Model'!$C$16)*(1+'DCF Model'!$D$16)*(1+'DCF Model'!$E$16)*(1+'DCF Model'!$F$16)*(1+0.03)/(0.08-0.03))/(1+0.08)^5/'DCF Model'!$B$6+('DCF Model'!B25-'DCF Model'!B9)/'DCF Model'!$B$6
A7: 0.09 | B7: =('DCF Model'!$B$10*(1+'DCF Model'!$B$16)*(1+'DCF Model'!$C$16)*(1+'DCF Model'!$D$16)*(1+'DCF Model'!$E$16)*(1+'DCF Model'!$F$16)*(1+0.01)/(0.09-0.01))/(1+0.09)^5/'DCF Model'!$B$6+('DCF Model'!B25-'DCF Model'!B9)/'DCF Model'!$B$6 | C7: =('DCF Model'!$B$10*(1+'DCF Model'!$B$16)*(1+'DCF Model'!$C$16)*(1+'DCF Model'!$D$16)*(1+'DCF Model'!$E$16)*(1+'DCF Model'!$F$16)*(1+0.015)/(0.09-0.015))/(1+0.09)^5/'DCF Model'!$B$6+('DCF Model'!B25-'DCF Model'!B9)/'DCF Model'!$B$6 | D7: =('DCF Model'!$B$10*(1+'DCF Model'!$B$16)*(1+'DCF Model'!$C$16)*(1+'DCF Model'!$D$16)*(1+'DCF Model'!$E$16)*(1+'DCF Model'!$F$16)*(1+0.02)/(0.09-0.02))/(1+0.09)^5/'DCF Model'!$B$6+('DCF Model'!B25-'DCF Model'!B9)/'DCF Model'!$B$6 | E7: =('DCF Model'!$B$10*(1+'DCF Model'!$B$16)*(1+'DCF Model'!$C$16)*(1+'DCF Model'!$D$16)*(1+'DCF Model'!$E$16)*(1+'DCF Model'!$F$16)*(1+0.025)/(0.09-0.025))/(1+0.09)^5/'DCF Model'!$B$6+('DCF Model'!B25-'DCF Model'!B9)/'DCF Model'!$B$6 | F7: =('DCF Model'!$B$10*(1+'DCF Model'!$B$16)*(1+'DCF Model'!$C$16)*(1+'DCF Model'!$D$16)*(1+'DCF Model'!$E$16)*(1+'DCF Model'!$F$16)*(1+0.03)/(0.09-0.03))/(1+0.09)^5/'DCF Model'!$B$6+('DCF Model'!B25-'DCF Model'!B9)/'DCF Model'!$B$6
A8: 0.1 | B8: =('DCF Model'!$B$10*(1+'DCF Model'!$B$16)*(1+'DCF Model'!$C$16)*(1+'DCF Model'!$D$16)*(1+'DCF Model'!$E$16)*(1+'DCF Model'!$F$16)*(1+0.01)/(0.1-0.01))/(1+0.1)^5/'DCF Model'!$B$6+('DCF Model'!B25-'DCF Model'!B9)/'DCF Model'!$B$6 | C8: =('DCF Model'!$B$10*(1+'DCF Model'!$B$16)*(1+'DCF Model'!$C$16)*(1+'DCF Model'!$D$16)*(1+'DCF Model'!$E$16)*(1+'DCF Model'!$F$16)*(1+0.015)/(0.1-0.015))/(1+0.1)^5/'DCF Model'!$B$6+('DCF Model'!B25-'DCF Model'!B9)/'DCF Model'!$B$6 | D8: =('DCF Model'!$B$10*(1+'DCF Model'!$B$16)*(1+'DCF Model'!$C$16)*(1+'DCF Model'!$D$16)*(1+'DCF Model'!$E$16)*(1+'DCF Model'!$F$16)*(1+0.02)/(0.1-0.02))/(1+0.1)^5/'DCF Model'!$B$6+('DCF Model'!B25-'DCF Model'!B9)/'DCF Model'!$B$6 | E8: =('DCF Model'!$B$10*(1+'DCF Model'!$B$16)*(1+'DCF Model'!$C$16)*(1+'DCF Model'!$D$16)*(1+'DCF Model'!$E$16)*(1+'DCF Model'!$F$16)*(1+0.025)/(0.1-0.025))/(1+0.1)^5/'DCF Model'!$B$6+('DCF Model'!B25-'DCF Model'!B9)/'DCF Model'!$B$6 | F8: =('DCF Model'!$B$10*(1+'DCF Model'!$B$16)*(1+'DCF Model'!$C$16)*(1+'DCF Model'!$D$16)*(1+'DCF Model'!$E$16)*(1+'DCF Model'!$F$16)*(1+0.03)/(0.1-0.03))/(1+0.1)^5/'DCF Model'!$B$6+('DCF Model'!B25-'DCF Model'!B9)/'DCF Model'!$B$6
A9: 0.11 | B9: =('DCF Model'!$B$10*(1+'DCF Model'!$B$16)*(1+'DCF Model'!$C$16)*(1+'DCF Model'!$D$16)*(1+'DCF Model'!$E$16)*(1+'DCF Model'!$F$16)*(1+0.01)/(0.11-0.01))/(1+0.11)^5/'DCF Model'!$B$6+('DCF Model'!B25-'DCF Model'!B9)/'DCF Model'!$B$6 | C9: =('DCF Model'!$B$10*(1+'DCF Model'!$B$16)*(1+'DCF Model'!$C$16)*(1+'DCF Model'!$D$16)*(1+'DCF Model'!$E$16)*(1+'DCF Model'!$F$16)*(1+0.015)/(0.11-0.015))/(1+0.11)^5/'DCF Model'!$B$6+('DCF Model'!B25-'DCF Model'!B9)/'DCF Model'!$B$6 | D9: =('DCF Model'!$B$10*(1+'DCF Model'!$B$16)*(1+'DCF Model'!$C$16)*(1+'DCF Model'!$D$16)*(1+'DCF Model'!$E$16)*(1+'DCF Model'!$F$16)*(1+0.02)/(0.11-0.02))/(1+0.11)^5/'DCF Model'!$B$6+('DCF Model'!B25-'DCF Model'!B9)/'DCF Model'!$B$6 | E9: =('DCF Model'!$B$10*(1+'DCF Model'!$B$16)*(1+'DCF Model'!$C$16)*(1+'DCF Model'!$D$16)*(1+'DCF Model'!$E$16)*(1+'DCF Model'!$F$16)*(1+0.025)/(0.11-0.025))/(1+0.11)^5/'DCF Model'!$B$6+('DCF Model'!B25-'DCF Model'!B9)/'DCF Model'!$B$6 | F9: =('DCF Model'!$B$10*(1+'DCF Model'!$B$16)*(1+'DCF Model'!$C$16)*(1+'DCF Model'!$D$16)*(1+'DCF Model'!$E$16)*(1+'DCF Model'!$F$16)*(1+0.03)/(0.11-0.03))/(1+0.11)^5/'DCF Model'!$B$6+('DCF Model'!B25-'DCF Model'!B9)/'DCF Model'!$B$6

Sheet Historical
A1: Historical Growth Rates
A3: Metric | B3: 3-Year CAGR | C3: 5-Year CAGR
A4: Revenue | B4: -0.002 | C4: -0.002
A5: EPS | B5: -0.173 | C5: -0.095
A6: Equity | B6: -0.002 | C6: 0.009
A7: FCF | B7: -0.124 | C7: -0.029
A9: Selected Growth Rate: | B9: -0.004
A10: Source: | B10: blended_revenue_decline_offset_by_cost_out
