Workbook

Sheet Inputs
A1: Ticker | B1: ANZ.AX
A2: Valuation date | B2: 2026-09-21
A3: Model | B3: Residual income on tangible book at cost of equity (bank)
A4: Currency / units | B4: AUD millions
A5: Current price (AUD) | B5: 38.03
A6: Price as of | B6: 2026-09-21T06:11:49Z (16:11 AEST, ASX regular close incl. closing auction)
A7: Balance sheet date | B7: 2026-03-31
A8: Equity attributable to shareholders | B8: 71053
A9: Goodwill and other intangibles | B9: 5584
A10: Non-controlling interests (excluded) | B10: 703
A11: Tangible book value (NTA) | B11: =B8-B9
A12: Issued shares (m) | B12: 3014.2
A13: TBV per share | B13: =B11/B12
A14: TTM cash profit reported | B14: 5999
A15: Sep-25 half significant items (after tax) | B15: 1109
A16: TTM cash profit ex significant items | B16: =B14+B15
A17: TTM statutory net income | B17: 5899
A18: Dividend per share (annual) | B18: 1.66
A19: Hurdle rate (entry price) | B19: 0.15
A20: Current P/TBV | B20: =B5/B13
A21: Current P/E (TTM cash ex sig) | B21: =B5/(B16/B12)

Sheet History
A1: Period | B1: Revenue | C1: Statutory NI | D1: Cash profit | E1: Equity | F1: Shares (m) | G1: EPS | H1: DPS | I1: NIM % | J1: CET1 % | K1: Cash ROTE % | L1: NTA/share | M1: FY close price | N1: P/NTA
A2: H1 FY2016 | B2: 10265 | C2: 2738 | E2: 56500 | F2: 2917.6 | G2: 0.948 | H2: 0.8
A3: FY2016 | B3: 20529 | C3: 5709 | D3: 5889 | E3: 57927 | F3: 2891.7 | G3: 1.974 | H3: 1.6 | I3: 2.07
A4: H1 FY2017 | B4: 9996 | C4: 2911 | E4: 57908 | F4: 2906.6 | G4: 1.002 | H4: 0.8
A5: FY2017 | B5: 20273 | C5: 6406 | D5: 6938 | E5: 59075 | F5: 2910 | G5: 2.201 | H5: 1.6 | I5: 1.99
A6: H1 FY2018 | B6: 10175 | C6: 3323 | E6: 59500 | F6: 2909.8 | G6: 1.142 | H6: 0.8
A7: FY2018 | B7: 19831 | C7: 6400 | D7: 5805 | E7: 59383 | F7: 2888.3 | G7: 2.216 | H7: 1.6 | I7: 1.87 | J7: 11.4
A8: H1 FY2019 | B8: 9293 | C8: 3173 | E8: 59971 | F8: 2840.6 | G8: 1.117 | H8: 0.8
A9: FY2019 | B9: 18785 | C9: 5953 | D9: 6161 | E9: 60794 | F9: 2834.9 | G9: 2.1 | H9: 1.6 | I9: 1.76 | J9: 11.4
A10: H1 FY2020 | B10: 8893 | C10: 1545 | E10: 61375 | F10: 2829.7 | G10: 0.546 | H10: 0
A11: FY2020 | B11: 17637 | C11: 3577 | D11: 3660 | E11: 61297 | F11: 2831 | G11: 1.264 | H11: 0.6 | I11: 1.63 | J11: 11.3
A12: H1 FY2021 | B12: 8367 | C12: 2943 | E12: 62576 | F12: 2838 | G12: 1.037 | H12: 0.7
A13: FY2021 | B13: 17420 | C13: 6162 | D13: 6181 | E13: 63676 | F13: 2838.6 | G13: 2.171 | H13: 1.42 | I13: 1.64 | J13: 12.3 | K13: 10.6 | L13: 21.09 | M13: 28.15 | N13: =M13/L13
A14: H1 FY2022 | B14: 9542 | C14: 3530 | E14: 61756 | F14: 2862.5 | G14: 1.257 | H14: 0.72
A15: FY2022 | B15: 19426 | C15: 7119 | D15: 6496 | E15: 66401 | F15: 2847.5 | G15: 2.5 | H15: 1.46 | I15: 1.63 | J15: 12.3 | K15: 11.1 | L15: 20.75 | M15: 22.8 | N15: =M15/L15
A16: H1 FY2023 | B16: 10139 | C16: 3547 | E16: 69609 | F16: 2994.1 | G16: 1.185 | H16: 0.81
A17: FY2023 | B17: 20459 | C17: 7098 | D17: 7413 | E17: 70046 | F17: 2997.2 | G17: 2.368 | H17: 1.75 | I17: 1.7 | J17: 13.3 | K17: 11.6 | L17: 21.77 | M17: 25.66 | N17: =M17/L17
A18: H1 FY2024 | B18: 10145 | C18: 3407 | E18: 71074 | F18: 3001.8 | G18: 1.135 | H18: 0.83
A19: FY2024 | B19: 20521 | C19: 6595 | D19: 6725 | E19: 68760 | F19: 2998.4 | G19: 2.179 | H19: 1.66 | I19: 1.57 | J19: 12.2 | K19: 10.3 | L19: 21.6 | M19: 30.48 | N19: =M19/L19
A20: H1 FY2025 | B20: 11179 | C20: 3642 | E20: 72331 | F20: 2971.9 | G20: 1.225 | H20: 0.83
A21: FY2025 | B21: 22186 | C21: 5891 | D21: 5787 | E21: 71867 | F21: 2972.6 | G21: 1.982 | H21: 1.66 | I21: 1.55 | J21: 12 | K21: 8.8 | L21: 21.91 | M21: 33.21 | N21: =M21/L21
A22: H1 FY2026 | B22: 11079 | C22: 3650 | E22: 71756 | F22: 2997.7 | G22: 1.218 | L22: 21.72 | M22: 38.03 | N22: =M22/L22

Sheet Base
A1: BASE — residual income on tangible book
A3: Cost of equity | B3: 0.1
A4: Terminal growth of residual income | B4: 0.03
A5: Dividend payout ratio | B5: 0.7
A6: Opening TBV | B6: =Inputs!B11
A7: Shares (m) | B7: =Inputs!B12
A8: Hurdle rate | B8: =Inputs!B19
A10: Year | B10: 1 | C10: 2 | D10: 3 | E10: 4 | F10: 5
A11: ROTE on opening TBV | B11: 0.112 | C11: 0.115 | D11: 0.118 | E11: 0.12 | F11: 0.12
A12: One-off after tax | B12: 140 | C12: 140 | D12: 40 | E12: 0 | F12: 0
A13: Opening TBV | B13: =$B$6 | C13: =B18 | D13: =C18 | E13: =D18 | F13: =E18
A14: Underlying cash profit | B14: =B11*B13 | C14: =C11*C13 | D14: =D11*D13 | E14: =E11*E13 | F14: =F11*F13
A15: Net income | B15: =B14-B12 | C15: =C14-C12 | D15: =D14-D12 | E15: =E14-E12 | F15: =F14-F12
A16: Dividends | B16: =$B$5*B15 | C16: =$B$5*C15 | D16: =$B$5*D15 | E16: =$B$5*E15 | F16: =$B$5*F15
A17: Retained | B17: =B15-B16 | C17: =C15-C16 | D17: =D15-D16 | E17: =E15-E16 | F17: =F15-F16
A18: Closing TBV | B18: =B13+B17 | C18: =C13+C17 | D18: =D13+D17 | E18: =E13+E17 | F18: =F13+F17
A19: Equity charge (CoE x opening TBV) | B19: =$B$3*B13 | C19: =$B$3*C13 | D19: =$B$3*D13 | E19: =$B$3*E13 | F19: =$B$3*F13
A20: Residual income | B20: =B15-B19 | C20: =C15-C19 | D20: =D15-D19 | E20: =E15-E19 | F20: =F15-F19
A21: Discount factor | B21: =1/(1+$B$3)^B10 | C21: =1/(1+$B$3)^C10 | D21: =1/(1+$B$3)^D10 | E21: =1/(1+$B$3)^E10 | F21: =1/(1+$B$3)^F10
A22: PV residual income | B22: =B20*B21 | C22: =C20*C21 | D22: =D20*D21 | E22: =E20*E21 | F22: =F20*F21
A23: Hurdle discount factor | B23: =1/(1+$B$8)^B10 | C23: =1/(1+$B$8)^C10 | D23: =1/(1+$B$8)^D10 | E23: =1/(1+$B$8)^E10 | F23: =1/(1+$B$8)^F10
A24: PV dividends at hurdle | B24: =B16*B23 | C24: =C16*C23 | D24: =D16*D23 | E24: =E16*E23 | F24: =F16*F23
A25: EPS | B25: =B15/$B$7 | C25: =C15/$B$7 | D25: =D15/$B$7 | E25: =E15/$B$7 | F25: =F15/$B$7
A26: TBV per share | B26: =B18/$B$7 | C26: =C18/$B$7 | D26: =D18/$B$7 | E26: =E18/$B$7 | F26: =F18/$B$7
A28: Sum PV residual income | B28: =SUM(B22:F22)
A29: Terminal value (Gordon on Y5 RI) | B29: =F20*(1+B4)/(B3-B4)
A30: PV terminal value | B30: =B29*F21
A31: Equity value | B31: =B6+B28+B30
A32: Intrinsic value per share | B32: =B31/B7
A33: Upside vs price | B33: =B32/Inputs!B5-1
A34: Implied P/TBV of IV | B34: =B32/Inputs!B13
A35: Y5 terminal equity value (TBV5 + TV) | B35: =F18+B29
A36: Implied exit P/TBV | B36: =B35/F18
A37: Terminal % of value | B37: =B30/B31
A38: PV dividends at hurdle | B38: =SUM(B24:F24)
A39: PV terminal at hurdle | B39: =B35*F23
A40: Entry price (15% IRR) | B40: =(B38+B39)/B7

Sheet Bull
A1: BULL — residual income on tangible book
A3: Cost of equity | B3: 0.09
A4: Terminal growth of residual income | B4: 0.03
A5: Dividend payout ratio | B5: 0.7
A6: Opening TBV | B6: =Inputs!B11
A7: Shares (m) | B7: =Inputs!B12
A8: Hurdle rate | B8: =Inputs!B19
A10: Year | B10: 1 | C10: 2 | D10: 3 | E10: 4 | F10: 5
A11: ROTE on opening TBV | B11: 0.116 | C11: 0.125 | D11: 0.13 | E11: 0.135 | F11: 0.135
A12: One-off after tax | B12: 140 | C12: 100 | D12: 0 | E12: 0 | F12: 0
A13: Opening TBV | B13: =$B$6 | C13: =B18 | D13: =C18 | E13: =D18 | F13: =E18
A14: Underlying cash profit | B14: =B11*B13 | C14: =C11*C13 | D14: =D11*D13 | E14: =E11*E13 | F14: =F11*F13
A15: Net income | B15: =B14-B12 | C15: =C14-C12 | D15: =D14-D12 | E15: =E14-E12 | F15: =F14-F12
A16: Dividends | B16: =$B$5*B15 | C16: =$B$5*C15 | D16: =$B$5*D15 | E16: =$B$5*E15 | F16: =$B$5*F15
A17: Retained | B17: =B15-B16 | C17: =C15-C16 | D17: =D15-D16 | E17: =E15-E16 | F17: =F15-F16
A18: Closing TBV | B18: =B13+B17 | C18: =C13+C17 | D18: =D13+D17 | E18: =E13+E17 | F18: =F13+F17
A19: Equity charge (CoE x opening TBV) | B19: =$B$3*B13 | C19: =$B$3*C13 | D19: =$B$3*D13 | E19: =$B$3*E13 | F19: =$B$3*F13
A20: Residual income | B20: =B15-B19 | C20: =C15-C19 | D20: =D15-D19 | E20: =E15-E19 | F20: =F15-F19
A21: Discount factor | B21: =1/(1+$B$3)^B10 | C21: =1/(1+$B$3)^C10 | D21: =1/(1+$B$3)^D10 | E21: =1/(1+$B$3)^E10 | F21: =1/(1+$B$3)^F10
A22: PV residual income | B22: =B20*B21 | C22: =C20*C21 | D22: =D20*D21 | E22: =E20*E21 | F22: =F20*F21
A23: Hurdle discount factor | B23: =1/(1+$B$8)^B10 | C23: =1/(1+$B$8)^C10 | D23: =1/(1+$B$8)^D10 | E23: =1/(1+$B$8)^E10 | F23: =1/(1+$B$8)^F10
A24: PV dividends at hurdle | B24: =B16*B23 | C24: =C16*C23 | D24: =D16*D23 | E24: =E16*E23 | F24: =F16*F23
A25: EPS | B25: =B15/$B$7 | C25: =C15/$B$7 | D25: =D15/$B$7 | E25: =E15/$B$7 | F25: =F15/$B$7
A26: TBV per share | B26: =B18/$B$7 | C26: =C18/$B$7 | D26: =D18/$B$7 | E26: =E18/$B$7 | F26: =F18/$B$7
A28: Sum PV residual income | B28: =SUM(B22:F22)
A29: Terminal value (Gordon on Y5 RI) | B29: =F20*(1+B4)/(B3-B4)
A30: PV terminal value | B30: =B29*F21
A31: Equity value | B31: =B6+B28+B30
A32: Intrinsic value per share | B32: =B31/B7
A33: Upside vs price | B33: =B32/Inputs!B5-1
A34: Implied P/TBV of IV | B34: =B32/Inputs!B13
A35: Y5 terminal equity value (TBV5 + TV) | B35: =F18+B29
A36: Implied exit P/TBV | B36: =B35/F18
A37: Terminal % of value | B37: =B30/B31
A38: PV dividends at hurdle | B38: =SUM(B24:F24)
A39: PV terminal at hurdle | B39: =B35*F23
A40: Entry price (15% IRR) | B40: =(B38+B39)/B7

Sheet Bear
A1: BEAR — residual income on tangible book
A3: Cost of equity | B3: 0.11
A4: Terminal growth of residual income | B4: 0.025
A5: Dividend payout ratio | B5: 0.78
A6: Opening TBV | B6: =Inputs!B11
A7: Shares (m) | B7: =Inputs!B12
A8: Hurdle rate | B8: =Inputs!B19
A10: Year | B10: 1 | C10: 2 | D10: 3 | E10: 4 | F10: 5
A11: ROTE on opening TBV | B11: 0.1 | C11: 0.095 | D11: 0.095 | E11: 0.1 | F11: 0.1
A12: One-off after tax | B12: 250 | C12: 250 | D12: 150 | E12: 100 | F12: 100
A13: Opening TBV | B13: =$B$6 | C13: =B18 | D13: =C18 | E13: =D18 | F13: =E18
A14: Underlying cash profit | B14: =B11*B13 | C14: =C11*C13 | D14: =D11*D13 | E14: =E11*E13 | F14: =F11*F13
A15: Net income | B15: =B14-B12 | C15: =C14-C12 | D15: =D14-D12 | E15: =E14-E12 | F15: =F14-F12
A16: Dividends | B16: =$B$5*B15 | C16: =$B$5*C15 | D16: =$B$5*D15 | E16: =$B$5*E15 | F16: =$B$5*F15
A17: Retained | B17: =B15-B16 | C17: =C15-C16 | D17: =D15-D16 | E17: =E15-E16 | F17: =F15-F16
A18: Closing TBV | B18: =B13+B17 | C18: =C13+C17 | D18: =D13+D17 | E18: =E13+E17 | F18: =F13+F17
A19: Equity charge (CoE x opening TBV) | B19: =$B$3*B13 | C19: =$B$3*C13 | D19: =$B$3*D13 | E19: =$B$3*E13 | F19: =$B$3*F13
A20: Residual income | B20: =B15-B19 | C20: =C15-C19 | D20: =D15-D19 | E20: =E15-E19 | F20: =F15-F19
A21: Discount factor | B21: =1/(1+$B$3)^B10 | C21: =1/(1+$B$3)^C10 | D21: =1/(1+$B$3)^D10 | E21: =1/(1+$B$3)^E10 | F21: =1/(1+$B$3)^F10
A22: PV residual income | B22: =B20*B21 | C22: =C20*C21 | D22: =D20*D21 | E22: =E20*E21 | F22: =F20*F21
A23: Hurdle discount factor | B23: =1/(1+$B$8)^B10 | C23: =1/(1+$B$8)^C10 | D23: =1/(1+$B$8)^D10 | E23: =1/(1+$B$8)^E10 | F23: =1/(1+$B$8)^F10
A24: PV dividends at hurdle | B24: =B16*B23 | C24: =C16*C23 | D24: =D16*D23 | E24: =E16*E23 | F24: =F16*F23
A25: EPS | B25: =B15/$B$7 | C25: =C15/$B$7 | D25: =D15/$B$7 | E25: =E15/$B$7 | F25: =F15/$B$7
A26: TBV per share | B26: =B18/$B$7 | C26: =C18/$B$7 | D26: =D18/$B$7 | E26: =E18/$B$7 | F26: =F18/$B$7
A28: Sum PV residual income | B28: =SUM(B22:F22)
A29: Terminal value (Gordon on Y5 RI) | B29: =F20*(1+B4)/(B3-B4)
A30: PV terminal value | B30: =B29*F21
A31: Equity value | B31: =B6+B28+B30
A32: Intrinsic value per share | B32: =B31/B7
A33: Upside vs price | B33: =B32/Inputs!B5-1
A34: Implied P/TBV of IV | B34: =B32/Inputs!B13
A35: Y5 terminal equity value (TBV5 + TV) | B35: =F18+B29
A36: Implied exit P/TBV | B36: =B35/F18
A37: Terminal % of value | B37: =B30/B31
A38: PV dividends at hurdle | B38: =SUM(B24:F24)
A39: PV terminal at hurdle | B39: =B35*F23
A40: Entry price (15% IRR) | B40: =(B38+B39)/B7

Sheet Summary
A1: Scenario | B1: Weight | C1: Intrinsic value | D1: Upside | E1: Entry price | F1: Implied P/TBV | G1: Exit P/TBV
A2: Bear | B2: 0.2 | C2: =Bear!B32 | D2: =Bear!B33 | E2: =Bear!B40 | F2: =Bear!B34 | G2: =Bear!B36
A3: Base | B3: 0.5 | C3: =Base!B32 | D3: =Base!B33 | E3: =Base!B40 | F3: =Base!B34 | G3: =Base!B36
A4: Bull | B4: 0.3 | C4: =Bull!B32 | D4: =Bull!B33 | E4: =Bull!B40 | F4: =Bull!B34 | G4: =Bull!B36
A5: Weighted | B5: =SUM(B2:B4) | C5: =SUMPRODUCT(B2:B4,C2:C4) | D5: =C5/Inputs!B5-1 | E5: =SUMPRODUCT(B2:B4,E2:E4)
A7: Current price | B7: =Inputs!B5
A8: Sensitivity (base): rows CoE, cols terminal g — static values from build script
A9: CoE \ g | B9: 2 | C9: 2.5 | D9: 3 | E9: 3.5 | F9: 4
A10: 8 | B10: 36.54 | C10: 37.65 | D10: 38.98 | E10: 40.6 | F10: 42.64
A11: 9 | B11: 31.1 | C11: 31.68 | D11: 32.36 | E11: 33.16 | F11: 34.13
A12: 10 | B12: 27.03 | C12: 27.32 | D12: 27.64 | E12: 28.01 | F12: 28.45
A13: 11 | B13: 23.88 | C13: 23.98 | D13: 24.1 | E13: 24.24 | F13: 24.4
A14: 12 | B14: 21.35 | C14: 21.35 | D14: 21.35 | E14: 21.35 | F14: 21.35
A16: Sensitivity (base): rows CoE, cols steady-state ROTE from Y2 — static values
A17: CoE \ ROTE | B17: 10 | C17: 11 | D17: 12 | E17: 13 | F17: 14
A18: 8 | B18: 30.57 | C18: 34.83 | D18: 39.14 | E18: 43.53 | F18: 47.98
A19: 9 | B19: 25.49 | C19: 28.98 | D19: 32.51 | E19: 36.1 | F19: 39.75
A20: 10 | B20: 21.87 | C20: 24.8 | D20: 27.78 | E20: 30.8 | F20: 33.87
A21: 11 | B21: 19.15 | C21: 21.67 | D21: 24.23 | E21: 26.83 | F21: 29.48
A22: 12 | B22: 17.03 | C22: 19.24 | D22: 21.48 | E22: 23.75 | F22: 26.06
