Workbook

Sheet Summary
A1: Arch Capital Group Ltd. (ACGL) -- Valuation Summary
A2: BVPS compounding x exit P/B model | Valuation date 2026-09-25
A4: Scenario Results
A5: Scenario | B5: Intrinsic Value/sh | C5: Upside vs Price | D5: Entry Price @15% hurdle
A6: Bear | B6: ='Bear'!B28 | C6: =B6/Inputs!$B$6-1 | D6: ='Bear'!B32
A7: Base | B7: ='Base'!B28 | C7: =B7/Inputs!$B$6-1 | D7: ='Base'!B32
A8: Bull | B8: ='Bull'!B28 | C8: =B8/Inputs!$B$6-1 | D8: ='Bull'!B32
A10: Current price | B10: =Inputs!$B$6
A12: Probability-Weighted Value
A13: Bear weight | B13: =Inputs!$B$26
A14: Base weight | B14: =Inputs!$B$27
A15: Bull weight | B15: =Inputs!$B$28
A16: Weighted intrinsic value/sh | B16: =B6*Inputs!$B$26+B7*Inputs!$B$27+B8*Inputs!$B$28
A17: Weighted upside vs current price | B17: =B16/Inputs!$B$6-1
A18: Weighted entry price @15% hurdle | B18: ='Bear'!B32*Inputs!$B$26+'Base'!B32*Inputs!$B$27+'Bull'!B32*Inputs!$B$28
A20: Model Notes
A21: - Model routed via .claude/skills/dcf-methods/SKILL.md: 'Insurer, holdco, compounder-of-book' -> BVPS compounding x exit P/B.
A22: - Net debt is NOT deducted (non-FCF model rule) -- ROE-driven common equity compounding already nets financing costs.
A23: - Common book value per share of $68.04 (Q2 2026) is Arch's own disclosed figure, net of ~$298M implied preferred equity.
A24: - Virtually all capital return is via buyback (not dividend); >98% of intrinsic value in every scenario is the terminal exit price.
A25: - See ACGL_DCF.json valuation_philosophy and inputs.notes for full scenario narratives and risk discussion.

Sheet Inputs
A1: Arch Capital Group Ltd. (ACGL) -- DCF Model
A2: Model: BVPS compounding x exit P/B (insurer/holdco route -- dividends + terminal exit discounted at cost of equity)
A3: Valuation date: 2026-09-25
A5: Market & Balance Sheet Anchors
A6: Current price (USD) | B6: 95.02
A7: Price as of | B7: 2026-09-24 20:00:01 UTC regular close
A8: 52-week range | B8: 82.45 - 107.09
A9: Common book value per share (Q2 2026, company-disclosed) | B9: 68.04
A10: Common shares outstanding (period end, millions) | B10: 348.8
A11: GAAP shareholders' equity (m) | B11: 24030
A12: Balance sheet date | B12: 2026-06-30
A13: Currency / Quote currency | B13: USD / USD
A15: Implied common equity (m) = BVPS x shares | B15: =B9*B10
A16: Implied preferred equity (m) = GAAP equity - common equity | B16: =B11-B15
A17: Current price-to-book (x) | B17: =B6/B9
A19: Scenario Discount Rates & Exit Multiples
A20: Scenario | B20: Cost of Equity | C20: Exit P/B (Yr5) | D20: Starting P/B (for buybacks)
A21: Base | B21: 0.095 | C21: 1.35 | D21: 1.4
A22: Bull | B22: 0.09 | C22: 1.6 | D22: 1.4
A23: Bear | B23: 0.105 | C23: 1 | D23: 1.4
A25: Probability Weights
A26: Bear weight | B26: 0.25
A27: Base weight | B27: 0.5
A28: Bull weight | B28: 0.25
A30: Entry Price Hurdle
A31: Hurdle rate | B31: 0.15

Sheet Base
A1: ACGL -- Base Case
A2: Year-by-Year Book Value Compounding
A3: Metric | B3: FY2027E | C3: FY2028E | D3: FY2029E | E3: FY2030E | F3: FY2031E
A4: ROE (%) | B4: 0.165 | C4: 0.15 | D4: 0.14 | E4: 0.13 | F4: 0.13
A5: Common dividend payout (%) | B5: 0.04 | C5: 0.04 | D5: 0.04 | E5: 0.04 | F5: 0.04
A6: Buyback % of retained earnings | B6: 0.75 | C6: 0.75 | D6: 0.7 | E6: 0.65 | F6: 0.6
A7: Beginning common equity ($m) | B7: =Inputs!$B$15 | C7: =B16 | D7: =C16 | E7: =D16 | F7: =E16
A8: Net income to common ($m) | B8: =B7*B4 | C8: =C7*C4 | D8: =D7*D4 | E8: =E7*E4 | F8: =F7*F4
A9: Total common dividends ($m) | B9: =B8*B5 | C9: =C8*C5 | D9: =D8*D5 | E9: =E8*E5 | F9: =F8*F5
A10: Retained earnings ($m) | B10: =B8-B9 | C10: =C8-C9 | D10: =D8-D9 | E10: =E8-E9 | F10: =F8-F9
A11: Buyback cash spent ($m) | B11: =B10*B6 | C11: =C10*C6 | D11: =D10*D6 | E11: =E10*E6 | F11: =F10*F6
A12: Interpolated P/B for buybacks (x) | B12: =Inputs!$D$21+(Inputs!$C$21-Inputs!$D$21)*0.2 | C12: =Inputs!$D$21+(Inputs!$C$21-Inputs!$D$21)*0.4 | D12: =Inputs!$D$21+(Inputs!$C$21-Inputs!$D$21)*0.6 | E12: =Inputs!$D$21+(Inputs!$C$21-Inputs!$D$21)*0.8 | F12: =Inputs!$D$21+(Inputs!$C$21-Inputs!$D$21)*1.0
A13: Beginning shares (m) | B13: =Inputs!$B$10 | C13: =B17 | D13: =C17 | E13: =D17 | F13: =E17
A14: Assumed buyback price ($/sh) | B14: =B12*(B7/B13) | C14: =C12*(C7/C13) | D14: =D12*(D7/D13) | E14: =E12*(E7/E13) | F14: =F12*(F7/F13)
A15: Shares repurchased (m) | B15: =B11/B14 | C15: =C11/C14 | D15: =D11/D14 | E15: =E11/E14 | F15: =F11/F14
A16: Ending common equity ($m) | B16: =B7+B10-B11 | C16: =C7+C10-C11 | D16: =D7+D10-D11 | E16: =E7+E10-E11 | F16: =F7+F10-F11
A17: Ending shares (m) | B17: =B13-B15 | C17: =C13-C15 | D17: =D13-D15 | E17: =E13-E15 | F17: =F13-F15
A18: Ending BVPS ($) | B18: =B16/B17 | C18: =C16/C17 | D18: =D16/D17 | E18: =E16/E17 | F18: =F16/F17
A19: Dividend per share ($) | B19: =B9/B13 | C19: =C9/C13 | D19: =D9/D13 | E19: =E9/E13 | F19: =F9/F13
A21: Valuation (discount at Cost of Equity)
A22: Cost of equity | B22: =Inputs!$B$21
A23: Exit P/B (Year 5) | B23: =Inputs!$C$21
A24: Year-5 BVPS ($) | B24: =F18
A25: Exit price per share ($) | B25: =B23*B24
A26: PV of interim dividends ($/sh) | B26: =B19/(1+$B$22)^1+C19/(1+$B$22)^2+D19/(1+$B$22)^3+E19/(1+$B$22)^4+F19/(1+$B$22)^5
A27: PV of terminal exit ($/sh) | B27: =B25/(1+$B$22)^5
A28: Intrinsic value per share ($) | B28: =B26+B27
A29: Current price ($) | B29: =Inputs!$B$6
A30: Upside / (downside) | B30: =B28/B29-1
A32: Entry price at 15% hurdle ($) | B32: =B33+B34
A33: PV interim dividends at hurdle | B33: =B19/(1+Inputs!$B$31)^1+C19/(1+Inputs!$B$31)^2+D19/(1+Inputs!$B$31)^3+E19/(1+Inputs!$B$31)^4+F19/(1+Inputs!$B$31)^5
A34: PV terminal exit at hurdle | B34: =B25/(1+Inputs!$B$31)^5

Sheet Bull
A1: ACGL -- Bull Case
A2: Year-by-Year Book Value Compounding
A3: Metric | B3: FY2027E | C3: FY2028E | D3: FY2029E | E3: FY2030E | F3: FY2031E
A4: ROE (%) | B4: 0.18 | C4: 0.17 | D4: 0.16 | E4: 0.155 | F4: 0.15
A5: Common dividend payout (%) | B5: 0.04 | C5: 0.04 | D5: 0.04 | E5: 0.04 | F5: 0.04
A6: Buyback % of retained earnings | B6: 0.8 | C6: 0.8 | D6: 0.75 | E6: 0.7 | F6: 0.65
A7: Beginning common equity ($m) | B7: =Inputs!$B$15 | C7: =B16 | D7: =C16 | E7: =D16 | F7: =E16
A8: Net income to common ($m) | B8: =B7*B4 | C8: =C7*C4 | D8: =D7*D4 | E8: =E7*E4 | F8: =F7*F4
A9: Total common dividends ($m) | B9: =B8*B5 | C9: =C8*C5 | D9: =D8*D5 | E9: =E8*E5 | F9: =F8*F5
A10: Retained earnings ($m) | B10: =B8-B9 | C10: =C8-C9 | D10: =D8-D9 | E10: =E8-E9 | F10: =F8-F9
A11: Buyback cash spent ($m) | B11: =B10*B6 | C11: =C10*C6 | D11: =D10*D6 | E11: =E10*E6 | F11: =F10*F6
A12: Interpolated P/B for buybacks (x) | B12: =Inputs!$D$22+(Inputs!$C$22-Inputs!$D$22)*0.2 | C12: =Inputs!$D$22+(Inputs!$C$22-Inputs!$D$22)*0.4 | D12: =Inputs!$D$22+(Inputs!$C$22-Inputs!$D$22)*0.6 | E12: =Inputs!$D$22+(Inputs!$C$22-Inputs!$D$22)*0.8 | F12: =Inputs!$D$22+(Inputs!$C$22-Inputs!$D$22)*1.0
A13: Beginning shares (m) | B13: =Inputs!$B$10 | C13: =B17 | D13: =C17 | E13: =D17 | F13: =E17
A14: Assumed buyback price ($/sh) | B14: =B12*(B7/B13) | C14: =C12*(C7/C13) | D14: =D12*(D7/D13) | E14: =E12*(E7/E13) | F14: =F12*(F7/F13)
A15: Shares repurchased (m) | B15: =B11/B14 | C15: =C11/C14 | D15: =D11/D14 | E15: =E11/E14 | F15: =F11/F14
A16: Ending common equity ($m) | B16: =B7+B10-B11 | C16: =C7+C10-C11 | D16: =D7+D10-D11 | E16: =E7+E10-E11 | F16: =F7+F10-F11
A17: Ending shares (m) | B17: =B13-B15 | C17: =C13-C15 | D17: =D13-D15 | E17: =E13-E15 | F17: =F13-F15
A18: Ending BVPS ($) | B18: =B16/B17 | C18: =C16/C17 | D18: =D16/D17 | E18: =E16/E17 | F18: =F16/F17
A19: Dividend per share ($) | B19: =B9/B13 | C19: =C9/C13 | D19: =D9/D13 | E19: =E9/E13 | F19: =F9/F13
A21: Valuation (discount at Cost of Equity)
A22: Cost of equity | B22: =Inputs!$B$22
A23: Exit P/B (Year 5) | B23: =Inputs!$C$22
A24: Year-5 BVPS ($) | B24: =F18
A25: Exit price per share ($) | B25: =B23*B24
A26: PV of interim dividends ($/sh) | B26: =B19/(1+$B$22)^1+C19/(1+$B$22)^2+D19/(1+$B$22)^3+E19/(1+$B$22)^4+F19/(1+$B$22)^5
A27: PV of terminal exit ($/sh) | B27: =B25/(1+$B$22)^5
A28: Intrinsic value per share ($) | B28: =B26+B27
A29: Current price ($) | B29: =Inputs!$B$6
A30: Upside / (downside) | B30: =B28/B29-1
A32: Entry price at 15% hurdle ($) | B32: =B33+B34
A33: PV interim dividends at hurdle | B33: =B19/(1+Inputs!$B$31)^1+C19/(1+Inputs!$B$31)^2+D19/(1+Inputs!$B$31)^3+E19/(1+Inputs!$B$31)^4+F19/(1+Inputs!$B$31)^5
A34: PV terminal exit at hurdle | B34: =B25/(1+Inputs!$B$31)^5

Sheet Bear
A1: ACGL -- Bear Case
A2: Year-by-Year Book Value Compounding
A3: Metric | B3: FY2027E | C3: FY2028E | D3: FY2029E | E3: FY2030E | F3: FY2031E
A4: ROE (%) | B4: 0.13 | C4: 0.105 | D4: 0.095 | E4: 0.09 | F4: 0.09
A5: Common dividend payout (%) | B5: 0.04 | C5: 0.04 | D5: 0.04 | E5: 0.04 | F5: 0.04
A6: Buyback % of retained earnings | B6: 0.6 | C6: 0.55 | D6: 0.5 | E6: 0.5 | F6: 0.5
A7: Beginning common equity ($m) | B7: =Inputs!$B$15 | C7: =B16 | D7: =C16 | E7: =D16 | F7: =E16
A8: Net income to common ($m) | B8: =B7*B4 | C8: =C7*C4 | D8: =D7*D4 | E8: =E7*E4 | F8: =F7*F4
A9: Total common dividends ($m) | B9: =B8*B5 | C9: =C8*C5 | D9: =D8*D5 | E9: =E8*E5 | F9: =F8*F5
A10: Retained earnings ($m) | B10: =B8-B9 | C10: =C8-C9 | D10: =D8-D9 | E10: =E8-E9 | F10: =F8-F9
A11: Buyback cash spent ($m) | B11: =B10*B6 | C11: =C10*C6 | D11: =D10*D6 | E11: =E10*E6 | F11: =F10*F6
A12: Interpolated P/B for buybacks (x) | B12: =Inputs!$D$23+(Inputs!$C$23-Inputs!$D$23)*0.2 | C12: =Inputs!$D$23+(Inputs!$C$23-Inputs!$D$23)*0.4 | D12: =Inputs!$D$23+(Inputs!$C$23-Inputs!$D$23)*0.6 | E12: =Inputs!$D$23+(Inputs!$C$23-Inputs!$D$23)*0.8 | F12: =Inputs!$D$23+(Inputs!$C$23-Inputs!$D$23)*1.0
A13: Beginning shares (m) | B13: =Inputs!$B$10 | C13: =B17 | D13: =C17 | E13: =D17 | F13: =E17
A14: Assumed buyback price ($/sh) | B14: =B12*(B7/B13) | C14: =C12*(C7/C13) | D14: =D12*(D7/D13) | E14: =E12*(E7/E13) | F14: =F12*(F7/F13)
A15: Shares repurchased (m) | B15: =B11/B14 | C15: =C11/C14 | D15: =D11/D14 | E15: =E11/E14 | F15: =F11/F14
A16: Ending common equity ($m) | B16: =B7+B10-B11 | C16: =C7+C10-C11 | D16: =D7+D10-D11 | E16: =E7+E10-E11 | F16: =F7+F10-F11
A17: Ending shares (m) | B17: =B13-B15 | C17: =C13-C15 | D17: =D13-D15 | E17: =E13-E15 | F17: =F13-F15
A18: Ending BVPS ($) | B18: =B16/B17 | C18: =C16/C17 | D18: =D16/D17 | E18: =E16/E17 | F18: =F16/F17
A19: Dividend per share ($) | B19: =B9/B13 | C19: =C9/C13 | D19: =D9/D13 | E19: =E9/E13 | F19: =F9/F13
A21: Valuation (discount at Cost of Equity)
A22: Cost of equity | B22: =Inputs!$B$23
A23: Exit P/B (Year 5) | B23: =Inputs!$C$23
A24: Year-5 BVPS ($) | B24: =F18
A25: Exit price per share ($) | B25: =B23*B24
A26: PV of interim dividends ($/sh) | B26: =B19/(1+$B$22)^1+C19/(1+$B$22)^2+D19/(1+$B$22)^3+E19/(1+$B$22)^4+F19/(1+$B$22)^5
A27: PV of terminal exit ($/sh) | B27: =B25/(1+$B$22)^5
A28: Intrinsic value per share ($) | B28: =B26+B27
A29: Current price ($) | B29: =Inputs!$B$6
A30: Upside / (downside) | B30: =B28/B29-1
A32: Entry price at 15% hurdle ($) | B32: =B33+B34
A33: PV interim dividends at hurdle | B33: =B19/(1+Inputs!$B$31)^1+C19/(1+Inputs!$B$31)^2+D19/(1+Inputs!$B$31)^3+E19/(1+Inputs!$B$31)^4+F19/(1+Inputs!$B$31)^5
A34: PV terminal exit at hurdle | B34: =B25/(1+Inputs!$B$31)^5
