Workbook

Sheet Company Overview
A1: ADOBE INC. (NASDAQ: ADBE) - DCF VALUATION MODEL
A2: Analysis Date: January 2, 2026
A4: COMPANY OVERVIEW
A5: Ticker | B5: ADBE
A6: Company Name | B6: Adobe Inc.
A7: Exchange | B7: NASDAQ
A8: Sector | B8: Technology
A9: Industry | B9: Software - Application
A10: Headquarters | B10: San Jose, California
A11: Employees | B11: 30,000+
A12: Fiscal Year End | B12: November
A15: MARKET DATA
A16: Current Stock Price ($) | B16: 350 | C16: Source: Market data, Jan 2, 2026
A17: Shares Outstanding (M) | B17: 418.6 | C17: Source: Company filings
A18: Market Cap ($B) | B18: =B16*B17/1000 -> 146.51
A19: Total Debt ($B) | B19: 6.5 | C19: Source: FY2025 10-K
A20: Cash & Equivalents ($B) | B20: 7.5 | C20: Source: FY2025 10-K
A21: Enterprise Value ($B) | B21: =B18+B19-B20 -> 145.51
A24: KEY FINANCIAL METRICS (FY2025)
A25: Revenue ($B) | B25: 23.77 | C25: Source: FY2025 Earnings, Dec 2025
A26: Revenue Growth YoY (%) | B26: 11%
A27: Gross Margin (%) | B27: 89%
A28: Non-GAAP Operating Margin (%) | B28: 46%
A29: GAAP Net Income ($B) | B29: 7.13
A30: Non-GAAP Net Income ($B) | B30: 8.94
A31: Operating Cash Flow ($B) | B31: 10.03
A32: Free Cash Flow ($B) | B32: 9.9
A33: Total ARR ($B) | B33: 25.2
A34: GAAP EPS ($) | B34: 16.7
A35: Non-GAAP EPS ($) | B35: 20.94
A38: BUSINESS SEGMENTS (FY2025)
A39: Segment | B39: Revenue ($B) | C39: % of Total
A40: Digital Media | B40: 17.65 | C40: =B40/B42 -> 0.7425326
A41: Digital Experience | B41: 6.12 | C41: =B41/B42 -> 0.2574674
A42: Total Revenue | B42: =B40+B41 -> 23.77 | C42: 100%

Sheet Historical Financials
A1: ADOBE INC. - HISTORICAL FINANCIALS
A3: Metric | B3: FY2021 | C3: FY2022 | D3: FY2023 | E3: FY2024 | F3: FY2025
A4: Revenue ($B) | B4: 15.79 | C4: 17.61 | D4: 19.41 | E4: 21.51 | F4: 23.77
A5: YoY Growth (%) | C5: =C4/B4-1 -> 0.11526282 | D5: =D4/C4-1 -> 0.10221465 | E5: =E4/D4-1 -> 0.10819165 | F5: =F4/E4-1 -> 0.10506741
A6: Gross Profit ($B) | B6: 13.88 | C6: 15.28 | D6: 16.85 | E6: 18.76 | F6: 21.2
A7: Gross Margin (%) | B7: =B6/B4 -> 0.87903737 | C7: =C6/C4 -> 0.86768881 | D7: =D6/D4 -> 0.86810922 | E7: =E6/E4 -> 0.87215249 | F7: =F6/F4 -> 0.89188052
A8: Operating Income - GAAP ($B) | B8: 4.8 | C8: 5.04 | D8: 5.44 | E8: 6.74 | F8: 8.71
A9: Operating Margin - GAAP (%) | B9: =B8/B4 -> 0.30398987 | C9: =C8/C4 -> 0.28620102 | D9: =D8/D4 -> 0.2802679 | E9: =E8/E4 -> 0.31334263 | F9: =F8/F4 -> 0.36642827
A10: Operating Income - Non-GAAP ($B) | B10: 7.03 | C10: 7.74 | D10: 8.42 | E10: 10.02 | F10: 10.99
A11: Operating Margin - Non-GAAP (%) | B11: =B10/B4 -> 0.44521849 | C11: =C10/C4 -> 0.439523 | D11: =D10/D4 -> 0.43379701 | E11: =E10/E4 -> 0.46582985 | F11: =F10/F4 -> 0.4623475
A12: Net Income - GAAP ($B) | B12: 4.82 | C12: 4.76 | D12: 5.43 | E12: 5.56 | F12: 7.13
A13: Net Margin - GAAP (%) | B13: =B12/B4 -> 0.30525649 | C13: =C12/C4 -> 0.27030097 | D13: =D12/D4 -> 0.2797527 | E13: =E12/E4 -> 0.25848443 | F13: =F12/F4 -> 0.29995793
A14: Operating Cash Flow ($B) | B14: 7.23 | C14: 7.84 | D14: 7.3 | E14: 8.06 | F14: 10.03
A15: Capital Expenditures ($B) | B15: 0.35 | C15: 0.44 | D15: 0.36 | E15: 0.19 | F15: 0.13
A16: Free Cash Flow ($B) | B16: =B14-B15 -> 6.88 | C16: =C14-C15 -> 7.4 | D16: =D14-D15 -> 6.94 | E16: =E14-E15 -> 7.87 | F16: =F14-F15 -> 9.9
A17: FCF Margin (%) | B17: =B16/B4 -> 0.43571881 | C17: =C16/C4 -> 0.42021579 | D17: =D16/D4 -> 0.35754766 | E17: =E16/E4 -> 0.36587634 | F17: =F16/F4 -> 0.41649138
A19: EPS - GAAP ($) | B19: 10.02 | C19: 10.1 | D19: 11.82 | E19: 12.36 | F19: 16.7
A20: EPS - Non-GAAP ($) | B20: 14.48 | C20: 16.27 | D20: 18.14 | E20: 18.42 | F20: 20.94
A21: Shares Outstanding (M) | B21: 474 | C21: 462 | D21: 451 | E21: 442 | F21: 419

Sheet DCF Assumptions
A1: DCF MODEL ASSUMPTIONS
A3: REVENUE GROWTH ASSUMPTIONS
A4: Period | B4: Growth Rate (%) | C4: Rationale
A5: FY2026E | B5: 0.1 | C5: Analyst consensus ~10%, AI monetization
A6: FY2027E | B6: 0.09 | C6: Moderating growth, competitive pressures
A7: FY2028E | B7: 0.08 | C7: Continued moderation toward industry avg
A8: FY2029E | B8: 0.07 | C8: Approaching steady state
A9: FY2030E | B9: 0.06 | C9: Mature growth phase
A10: Terminal Growth Rate | B10: 0.03 | C10: Long-term GDP growth rate
A13: MARGIN & CONVERSION ASSUMPTIONS
A14: Metric | B14: Value | C14: Notes
A15: Gross Margin (%) | B15: 0.89 | C15: Maintain ~89% historical level
A16: Operating Margin - Target (%) | B16: 0.37 | C16: GAAP operating margin target
A17: D&A as % of Revenue | B17: 0.036 | C17: Based on historical trends
A18: CapEx as % of Revenue | B18: 0.01 | C18: Low capital intensity, asset-light model
A19: NWC Change as % of Revenue Change | B19: 0.03 | C19: Minimal working capital needs
A20: Tax Rate (%) | B20: 0.185 | C20: Non-GAAP effective tax rate
A24: WACC CALCULATION
A25: Component | B25: Value | C25: Source/Notes
A26: Risk-Free Rate (%) | B26: 0.042 | C26: 10-Year US Treasury yield
A27: Equity Risk Premium (%) | B27: 0.055 | C27: Historical market premium
A28: Beta (Levered) | B28: 1.1 | C28: 5-year monthly beta vs S&P 500
A29: Cost of Equity (%) | B29: =B26+B27*B28 -> 0.1025 | C29: CAPM: Rf + Beta * ERP
A30: Pre-Tax Cost of Debt (%) | B30: 0.045 | C30: Based on credit rating
A31: Tax Rate (%) | B31: 0.185 | C31: Effective tax rate
A32: After-Tax Cost of Debt (%) | B32: =B30*(1-B31) -> 0.036675
A33: Weight of Equity (%) | B33: 0.96 | C33: Market cap / Enterprise value
A34: Weight of Debt (%) | B34: =1-B33 -> 0.04
A35: WACC (%) | B35: =B29*B33+B32*B34 -> 0.099867 | C35: Weighted average cost of capital

Sheet DCF Model
A1: DISCOUNTED CASH FLOW VALUATION
A3: Key Assumptions (from Assumptions sheet)
A4: WACC | B4: ='DCF Assumptions'!B35 -> 0.099867
A5: Terminal Growth Rate | B5: ='DCF Assumptions'!B10 -> 0.03
A8: REVENUE PROJECTIONS ($B)
B9: FY2025A | C9: FY2026E | D9: FY2027E | E9: FY2028E | F9: FY2029E | G9: FY2030E
A10: Revenue ($B) | B10: 23.77 | C10: =B10*(1+'DCF Assumptions'!B5) -> 26.147 | D10: =C10*(1+'DCF Assumptions'!B6) -> 28.50023 | E10: =D10*(1+'DCF Assumptions'!B7) -> 30.780248 | F10: =E10*(1+'DCF Assumptions'!B8) -> 32.934866 | G10: =F10*(1+'DCF Assumptions'!B9) -> 34.910958
A11: YoY Growth (%) | C11: ='DCF Assumptions'!B5 -> 0.1 | D11: ='DCF Assumptions'!B6 -> 0.09 | E11: ='DCF Assumptions'!B7 -> 0.08 | F11: ='DCF Assumptions'!B8 -> 0.07 | G11: ='DCF Assumptions'!B9 -> 0.06
A14: FREE CASH FLOW BUILD ($B)
B15: FY2025A | C15: FY2026E | D15: FY2027E | E15: FY2028E | F15: FY2029E | G15: FY2030E
A16: Revenue | B16: =B10 -> 23.77 | C16: =C10 -> 26.147 | D16: =D10 -> 28.50023 | E16: =E10 -> 30.780248 | F16: =F10 -> 32.934866 | G16: =G10 -> 34.910958
A17: Operating Margin (%) | B17: 0.37 | C17: ='DCF Assumptions'!B16 -> 0.37 | D17: ='DCF Assumptions'!B16 -> 0.37 | E17: ='DCF Assumptions'!B16 -> 0.37 | F17: ='DCF Assumptions'!B16 -> 0.37 | G17: ='DCF Assumptions'!B16 -> 0.37
A18: EBIT (Operating Income) | B18: =B16*B17 -> 8.7949 | C18: =C16*C17 -> 9.67439 | D18: =D16*D17 -> 10.545085 | E18: =E16*E17 -> 11.388692 | F18: =F16*F17 -> 12.1859 | G18: =G16*G17 -> 12.917054
A19: Less: Taxes | B19: =B18*'DCF Assumptions'!$B$20 -> 1.6270565 | C19: =C18*'DCF Assumptions'!$B$20 -> 1.7897622 | D19: =D18*'DCF Assumptions'!$B$20 -> 1.9508407 | E19: =E18*'DCF Assumptions'!$B$20 -> 2.106908 | F19: =F18*'DCF Assumptions'!$B$20 -> 2.2543916 | G19: =G18*'DCF Assumptions'!$B$20 -> 2.3896551
A20: NOPAT (Net Op. Profit After Tax) | B20: =B18-B19 -> 7.1678435 | C20: =C18-C19 -> 7.8846279 | D20: =D18-D19 -> 8.5942444 | E20: =E18-E19 -> 9.2817839 | F20: =F18-F19 -> 9.9315088 | G20: =G18-G19 -> 10.527399
A21: Plus: D&A | B21: =B16*'DCF Assumptions'!$B$17 -> 0.85572 | C21: =C16*'DCF Assumptions'!$B$17 -> 0.941292 | D21: =D16*'DCF Assumptions'!$B$17 -> 1.0260083 | E21: =E16*'DCF Assumptions'!$B$17 -> 1.1080889 | F21: =F16*'DCF Assumptions'!$B$17 -> 1.1856552 | G21: =G16*'DCF Assumptions'!$B$17 -> 1.2567945
A22: Less: CapEx | B22: =B16*'DCF Assumptions'!$B$18 -> 0.2377 | C22: =C16*'DCF Assumptions'!$B$18 -> 0.26147 | D22: =D16*'DCF Assumptions'!$B$18 -> 0.2850023 | E22: =E16*'DCF Assumptions'!$B$18 -> 0.30780248 | F22: =F16*'DCF Assumptions'!$B$18 -> 0.32934866 | G22: =G16*'DCF Assumptions'!$B$18 -> 0.34910958
A23: Less: Change in NWC | B23: 0 | C23: =(C16-B16)*'DCF Assumptions'!$B$19 -> 0.07131 | D23: =(D16-C16)*'DCF Assumptions'!$B$19 -> 0.0705969 | E23: =(E16-D16)*'DCF Assumptions'!$B$19 -> 0.068400552 | F23: =(F16-E16)*'DCF Assumptions'!$B$19 -> 0.064638522 | G23: =(G16-F16)*'DCF Assumptions'!$B$19 -> 0.059282758
A24: Unlevered Free Cash Flow | B24: =B20+B21-B22-B23 -> 7.7858635 | C24: =C20+C21-C22-C23 -> 8.4931399 | D24: =D20+D21-D22-D23 -> 9.2646534 | E24: =E20+E21-E22-E23 -> 10.01367 | F24: =F20+F21-F22-F23 -> 10.723177 | G24: =G20+G21-G22-G23 -> 11.375801
A27: DCF VALUATION ($B)
B28: FY2026E | C28: FY2027E | D28: FY2028E | E28: FY2029E | F28: FY2030E | G28: Terminal
A29: Unlevered FCF | B29: =C24 -> 8.4931399 | C29: =D24 -> 9.2646534 | D29: =E24 -> 10.01367 | E29: =F24 -> 10.723177 | F29: =G24 -> 11.375801 | G29: =G24 -> 11.375801
A30: Terminal Value | G30: =G29*(1+$B$5)/($B$4-$B$5) -> 167.70543
A31: Discount Period | B31: 0.5 | C31: 1.5 | D31: 2.5 | E31: 3.5 | F31: 4.5 | G31: 4.5
A32: Discount Factor | B32: =1/(1+$B$4)^B31 -> 0.95352024 | C32: =1/(1+$B$4)^C31 -> 0.8669414 | D32: =1/(1+$B$4)^D31 -> 0.78822385 | E32: =1/(1+$B$4)^E31 -> 0.71665378 | F32: =1/(1+$B$4)^F31 -> 0.65158222 | G32: =1/(1+$B$4)^G31 -> 0.65158222
A33: Present Value of FCF | B33: =B29*B32 -> 8.0983807 | C33: =C29*C32 -> 8.0319116 | D33: =D29*D32 -> 7.8930134 | E33: =E29*E32 -> 7.6848052 | F33: =F29*F32 -> 7.41227 | G33: =G30*G32 -> 109.27388
A36: VALUATION SUMMARY
A37: Sum of PV of FCFs ($B) | B37: =SUM(B33:F33) -> 39.120381
A38: PV of Terminal Value ($B) | B38: =G33 -> 109.27388
A39: Enterprise Value ($B) | B39: =B37+B38 -> 148.39426
A40: Less: Total Debt ($B) | B40: 6.5
A41: Plus: Cash ($B) | B41: 7.5
A42: Equity Value ($B) | B42: =B39-B40+B41 -> 149.39426
A43: Shares Outstanding (M) | B43: 418.6
A44: Implied Share Price ($) | B44: =B42*1000/B43 -> 356.89025
A46: Current Share Price ($) | B46: 350
A47: Upside / (Downside) (%) | B47: =(B44-B46)/B46 -> 0.019686436

Sheet Sensitivity Analysis
A1: SENSITIVITY ANALYSIS
A3: IMPLIED SHARE PRICE SENSITIVITY: WACC vs TERMINAL GROWTH RATE
A5: Base Case Share Price ($) | B5: ='DCF Model'!B44 -> 356.89025
A6: Base WACC (%) | B6: ='DCF Model'!B4 -> 0.099867
A7: Base Terminal Growth (%) | B7: ='DCF Model'!B5 -> 0.03
B10: Terminal Growth Rate (%)
A11: WACC (%) | B11: 0.015 | C11: 0.02 | D11: 0.025 | E11: 0.03 | F11: 0.035 | G11: 0.04 | H11: 0.045
A12: 0.08 | B12: =(('DCF Model'!B37)+(11.5*(1+0.015)/(0.08-0.015)*((1+0.08)^-4.5))-6.5+7.5)*1000/418.6 -> 399.26434 | C12: =(('DCF Model'!B37)+(11.5*(1+0.02)/(0.08-0.02)*((1+0.08)^-4.5))-6.5+7.5)*1000/418.6 -> 426.16858 | D12: =(('DCF Model'!B37)+(11.5*(1+0.025)/(0.08-0.025)*((1+0.08)^-4.5))-6.5+7.5)*1000/418.6 -> 457.96451 | E12: =(('DCF Model'!B37)+(11.5*(1+0.03)/(0.08-0.03)*((1+0.08)^-4.5))-6.5+7.5)*1000/418.6 -> 496.11963 | F12: =(('DCF Model'!B37)+(11.5*(1+0.035)/(0.08-0.035)*((1+0.08)^-4.5))-6.5+7.5)*1000/418.6 -> 542.75366 | G12: =(('DCF Model'!B37)+(11.5*(1+0.04)/(0.08-0.04)*((1+0.08)^-4.5))-6.5+7.5)*1000/418.6 -> 601.0462 | H12: =(('DCF Model'!B37)+(11.5*(1+0.045)/(0.08-0.045)*((1+0.08)^-4.5))-6.5+7.5)*1000/418.6 -> 675.99375
A13: 0.09 | B13: =(('DCF Model'!B37)+(11.5*(1+0.015)/(0.09-0.015)*((1+0.09)^-4.5))-6.5+7.5)*1000/418.6 -> 348.12497 | C13: =(('DCF Model'!B37)+(11.5*(1+0.02)/(0.09-0.02)*((1+0.09)^-4.5))-6.5+7.5)*1000/418.6 -> 367.47656 | D13: =(('DCF Model'!B37)+(11.5*(1+0.025)/(0.09-0.025)*((1+0.09)^-4.5))-6.5+7.5)*1000/418.6 -> 389.80531 | E13: =(('DCF Model'!B37)+(11.5*(1+0.03)/(0.09-0.03)*((1+0.09)^-4.5))-6.5+7.5)*1000/418.6 -> 415.85552 | F13: =(('DCF Model'!B37)+(11.5*(1+0.035)/(0.09-0.035)*((1+0.09)^-4.5))-6.5+7.5)*1000/418.6 -> 446.64214 | G13: =(('DCF Model'!B37)+(11.5*(1+0.04)/(0.09-0.04)*((1+0.09)^-4.5))-6.5+7.5)*1000/418.6 -> 483.58608 | H13: =(('DCF Model'!B37)+(11.5*(1+0.045)/(0.09-0.045)*((1+0.09)^-4.5))-6.5+7.5)*1000/418.6 -> 528.73978
A14: 0.1 | B14: =(('DCF Model'!B37)+(11.5*(1+0.015)/(0.1-0.015)*((1+0.1)^-4.5))-6.5+7.5)*1000/418.6 -> 309.48227 | C14: =(('DCF Model'!B37)+(11.5*(1+0.02)/(0.1-0.02)*((1+0.1)^-4.5))-6.5+7.5)*1000/418.6 -> 323.95283 | D14: =(('DCF Model'!B37)+(11.5*(1+0.025)/(0.1-0.025)*((1+0.1)^-4.5))-6.5+7.5)*1000/418.6 -> 340.35279 | E14: =(('DCF Model'!B37)+(11.5*(1+0.03)/(0.1-0.03)*((1+0.1)^-4.5))-6.5+7.5)*1000/418.6 -> 359.09561 | F14: =(('DCF Model'!B37)+(11.5*(1+0.035)/(0.1-0.035)*((1+0.1)^-4.5))-6.5+7.5)*1000/418.6 -> 380.72194 | G14: =(('DCF Model'!B37)+(11.5*(1+0.04)/(0.1-0.04)*((1+0.1)^-4.5))-6.5+7.5)*1000/418.6 -> 405.95266 | H14: =(('DCF Model'!B37)+(11.5*(1+0.045)/(0.1-0.045)*((1+0.1)^-4.5))-6.5+7.5)*1000/418.6 -> 435.77078
A15: 0.105 | B15: =(('DCF Model'!B37)+(11.5*(1+0.015)/(0.105-0.015)*((1+0.105)^-4.5))-6.5+7.5)*1000/418.6 -> 293.53747 | C15: =(('DCF Model'!B37)+(11.5*(1+0.02)/(0.105-0.02)*((1+0.105)^-4.5))-6.5+7.5)*1000/418.6 -> 306.19763 | D15: =(('DCF Model'!B37)+(11.5*(1+0.025)/(0.105-0.025)*((1+0.105)^-4.5))-6.5+7.5)*1000/418.6 -> 320.44031 | E15: =(('DCF Model'!B37)+(11.5*(1+0.03)/(0.105-0.03)*((1+0.105)^-4.5))-6.5+7.5)*1000/418.6 -> 336.58202 | F15: =(('DCF Model'!B37)+(11.5*(1+0.035)/(0.105-0.035)*((1+0.105)^-4.5))-6.5+7.5)*1000/418.6 -> 355.02968 | G15: =(('DCF Model'!B37)+(11.5*(1+0.04)/(0.105-0.04)*((1+0.105)^-4.5))-6.5+7.5)*1000/418.6 -> 376.31545 | H15: =(('DCF Model'!B37)+(11.5*(1+0.045)/(0.105-0.045)*((1+0.105)^-4.5))-6.5+7.5)*1000/418.6 -> 401.14884
A16: 0.11 | B16: =(('DCF Model'!B37)+(11.5*(1+0.015)/(0.11-0.015)*((1+0.11)^-4.5))-6.5+7.5)*1000/418.6 -> 279.36599 | C16: =(('DCF Model'!B37)+(11.5*(1+0.02)/(0.11-0.02)*((1+0.11)^-4.5))-6.5+7.5)*1000/418.6 -> 290.51592 | D16: =(('DCF Model'!B37)+(11.5*(1+0.025)/(0.11-0.025)*((1+0.11)^-4.5))-6.5+7.5)*1000/418.6 -> 302.97761 | E16: =(('DCF Model'!B37)+(11.5*(1+0.03)/(0.11-0.03)*((1+0.11)^-4.5))-6.5+7.5)*1000/418.6 -> 316.997 | F16: =(('DCF Model'!B37)+(11.5*(1+0.035)/(0.11-0.035)*((1+0.11)^-4.5))-6.5+7.5)*1000/418.6 -> 332.88565 | G16: =(('DCF Model'!B37)+(11.5*(1+0.04)/(0.11-0.04)*((1+0.11)^-4.5))-6.5+7.5)*1000/418.6 -> 351.0441 | H16: =(('DCF Model'!B37)+(11.5*(1+0.045)/(0.11-0.045)*((1+0.11)^-4.5))-6.5+7.5)*1000/418.6 -> 371.99617
A17: 0.115 | B17: =(('DCF Model'!B37)+(11.5*(1+0.015)/(0.115-0.015)*((1+0.115)^-4.5))-6.5+7.5)*1000/418.6 -> 266.69922 | C17: =(('DCF Model'!B37)+(11.5*(1+0.02)/(0.115-0.02)*((1+0.115)^-4.5))-6.5+7.5)*1000/418.6 -> 276.57754 | D17: =(('DCF Model'!B37)+(11.5*(1+0.025)/(0.115-0.025)*((1+0.115)^-4.5))-6.5+7.5)*1000/418.6 -> 287.55345 | E17: =(('DCF Model'!B37)+(11.5*(1+0.03)/(0.115-0.03)*((1+0.115)^-4.5))-6.5+7.5)*1000/418.6 -> 299.82064 | F17: =(('DCF Model'!B37)+(11.5*(1+0.035)/(0.115-0.035)*((1+0.115)^-4.5))-6.5+7.5)*1000/418.6 -> 313.62123 | G17: =(('DCF Model'!B37)+(11.5*(1+0.04)/(0.115-0.04)*((1+0.115)^-4.5))-6.5+7.5)*1000/418.6 -> 329.2619 | H17: =(('DCF Model'!B37)+(11.5*(1+0.045)/(0.115-0.045)*((1+0.115)^-4.5))-6.5+7.5)*1000/418.6 -> 347.13695
A18: 0.12 | B18: =(('DCF Model'!B37)+(11.5*(1+0.015)/(0.12-0.015)*((1+0.12)^-4.5))-6.5+7.5)*1000/418.6 -> 255.3198 | C18: =(('DCF Model'!B37)+(11.5*(1+0.02)/(0.12-0.02)*((1+0.12)^-4.5))-6.5+7.5)*1000/418.6 -> 264.11846 | D18: =(('DCF Model'!B37)+(11.5*(1+0.025)/(0.12-0.025)*((1+0.12)^-4.5))-6.5+7.5)*1000/418.6 -> 273.84328 | E18: =(('DCF Model'!B37)+(11.5*(1+0.03)/(0.12-0.03)*((1+0.12)^-4.5))-6.5+7.5)*1000/418.6 -> 284.64865 | F18: =(('DCF Model'!B37)+(11.5*(1+0.035)/(0.12-0.035)*((1+0.12)^-4.5))-6.5+7.5)*1000/418.6 -> 296.72523 | G18: =(('DCF Model'!B37)+(11.5*(1+0.04)/(0.12-0.04)*((1+0.12)^-4.5))-6.5+7.5)*1000/418.6 -> 310.31139 | H18: =(('DCF Model'!B37)+(11.5*(1+0.045)/(0.12-0.045)*((1+0.12)^-4.5))-6.5+7.5)*1000/418.6 -> 325.70903

Sheet Investment Summary
A1: ADOBE INC. - INVESTMENT SUMMARY
A3: VALUATION SUMMARY
A4: Metric | B4: Value | C4: Notes
A5: Current Stock Price ($) | B5: ='Company Overview'!B16 -> 350 | C5: As of Jan 2, 2026
A6: DCF Implied Value ($) | B6: ='DCF Model'!B44 -> 356.89025 | C6: Base case scenario
A7: Upside / (Downside) (%) | B7: ='DCF Model'!B47 -> 0.019686436
A9: Market Cap ($B) | B9: ='Company Overview'!B19 -> 6.5
A10: Enterprise Value ($B) | B10: ='Company Overview'!B18 -> 146.51 | C10: DCF-derived
A11: EV / Revenue (FY25) | B11: ='DCF Model'!B39 -> 148.39426
A12: EV / EBITDA (FY25) | B12: ='DCF Model'!B39/'Company Overview'!B25 -> 6.2429222 | C12: ~10B EBITDA estimate
A13: P/E Ratio (GAAP) | B13: ='DCF Model'!B39/10 -> 14.839426
A14: P/E Ratio (Non-GAAP) | B14: ='Company Overview'!B16/'Company Overview'!B34 -> 20.958084
A15: FCF Yield (%) | B15: ='Company Overview'!B32*1000/('Company Overview'!B16*'Company Overview'!B17) -> 0.067572179
A18: KEY INVESTMENT THESIS POINTS
A19: 1. Market Leader: Dominant position in creative software (Photoshop, Illustrator, Premiere Pro) with ~89% gross margins
A20: 2. AI Integration: Firefly AI and generative AI features driving new revenue streams and competitive moat
A21: 3. Subscription Model: ~97%+ recurring revenue provides visibility and stability (ARR of $25.2B)
A22: 4. Strong FCF Generation: ~$10B annual FCF supports buybacks and strategic investments
A23: 5. Document Cloud Growth: Acrobat and PDF services growing 15%+ with AI-powered features
A24: 6. Enterprise Opportunity: Experience Cloud gaining traction with enterprise digital marketing
A27: KEY RISKS
A28: 1. AI Competition: Emerging AI tools (Canva, Figma, open-source) challenging Creative Cloud dominance
A29: 2. Valuation: Trading at premium multiples despite decelerating growth
A30: 3. Failed Figma Acquisition: $20B deal termination signals regulatory challenges for M&A growth
A31: 4. Macro Sensitivity: Marketing/creative budgets susceptible to economic downturns
A32: 5. Seat Count Pressure: AI may reduce per-user demand in some workflows
