Workbook

Sheet Overview
A1: PINTEREST, INC. (NYSE: PINS)
A2: DCF Valuation - SBC ADJUSTED
A4: KEY INSIGHT: Stock-Based Compensation Adjustment
A6: Pinterest reports ~$940M in Free Cash Flow, but this treats SBC as non-cash.
A7: However, the company uses cash to buy back shares to offset dilution.
A8: SBC is ~20% of revenue (~$730M), making true FCF only ~$210M.
A9: This model treats SBC as a real expense to show true economic value.
A11: Comparison: Reported vs. SBC-Adjusted
A13: Metric | B13: Reported | C13: SBC-Adjusted | D13: Difference
A14: 2024 EBITDA | B14: $1,032M | C14: ~$302M | D14: -71%
A15: 2024 Free Cash Flow | B15: $940M | C15: ~$210M | D15: -78%
A16: FCF Margin | B16: 25.8% | C16: ~5.8% | D16: -20pp
A17: P/FCF Multiple | B17: ~19x | C17: ~85x | D17: +66x
A19: Why This Matters
A21: Share count grew from 529M (IPO 2019) to 695M today = 5.2% CAGR dilution
A22: SBC is 20%+ of revenue - one of the highest in tech
A23: The 'cheap' P/E and P/FCF ratios are illusions without this adjustment

Sheet Historical Financials
A1: PINTEREST HISTORICAL FINANCIALS
A2: $ in millions
A4: Income Statement | B4: 2020 | C4: 2021 | D4: 2022 | E4: 2023 | F4: 2024 | G4: Source
A5: Revenue | B5: 1693 | C5: 2578 | D5: 2802 | E5: 3055 | F5: 3646 | G5: Company 10-K
A6: YoY Growth % | C6: 0.523 | D6: 0.087 | E6: 0.09 | F6: 0.194
A8: Reported Adj. EBITDA | B8: 283 | C8: 487 | D8: 441 | E8: 683 | F8: 1032 | G8: Company filings
A9: Stock-Based Compensation | B9: 321 | C9: 415 | D9: 497 | E9: 648 | F9: 730 | G9: Company 10-K
A10: SBC as % of Revenue | B10: 0.19 | C10: 0.161 | D10: 0.177 | E10: 0.212 | F10: 0.2
A11: SBC-Adjusted EBITDA | B11: =B8-B9 -> -38 | C11: =C8-C9 -> 72 | D11: =D8-D9 -> -56 | E11: =E8-E9 -> 35 | F11: =F8-F9 -> 302
A12: SBC-Adj EBITDA Margin | B12: =B11/B5 -> -0.022445363 | C12: =C11/C5 -> 0.027928627 | D12: =D11/D5 -> -0.019985724 | E12: =E11/E5 -> 0.011456628 | F12: =F11/F5 -> 0.082830499
A14: Reported Free Cash Flow | B14: 444 | C14: 743 | D14: 440 | E14: 605 | F14: 940 | G14: Company 10-K
A15: Less: SBC | B15: =-B9 -> -321 | C15: =-C9 -> -415 | D15: =-D9 -> -497 | E15: =-E9 -> -648 | F15: =-F9 -> -730
A16: SBC-Adjusted FCF | B16: =B14+B15 -> 123 | C16: =C14+C15 -> 328 | D16: =D14+D15 -> -57 | E16: =E14+E15 -> -43 | F16: =F14+F15 -> 210
A17: SBC-Adj FCF Margin | B17: =B16/B5 -> 0.072652097 | C17: =C16/C5 -> 0.12723041 | D17: =D16/D5 -> -0.020342612 | E17: =E16/E5 -> -0.014075286 | F17: =F16/F5 -> 0.057597367
A19: Share Count & Dilution | B19: 2020 | C19: 2021 | D19: 2022 | E19: 2023 | F19: 2024
A20: Diluted Shares (M) | B20: 596 | C20: 639 | D20: 666 | E20: 675 | F20: 695 | G20: Company 10-K
A21: YoY Dilution % | C21: 0.072 | D21: 0.042 | E21: 0.014 | F21: 0.03
A23: Balance Sheet (2024)
A24: Cash & Equivalents | F24: 2442
A25: Total Debt | F25: 0

Sheet DCF Assumptions
A1: DCF MODEL ASSUMPTIONS (SBC-ADJUSTED)
A3: Revenue Growth Assumptions | B3: Value | C3: Rationale
A4: Base Year Revenue (2024, $M) | B4: 3646 | C4: Actual FY2024 revenue
A5: Year 1 Growth Rate (2025) | B5: 0.14 | C5: Company guidance: 13-15%
A6: Year 2 Growth Rate (2026) | B6: 0.13 | C6: Analyst consensus
A7: Year 3 Growth Rate (2027) | B7: 0.12 | C7: Gradual deceleration
A8: Year 4 Growth Rate (2028) | B8: 0.11 | C8: Maturing growth
A9: Year 5 Growth Rate (2029) | B9: 0.1 | C9: Industry average
A10: Terminal Growth Rate | B10: 0.03 | C10: Long-term GDP proxy
A12: Margin Assumptions | B12: Value | C12: Rationale
A13: Reported EBITDA Margin - Yr 1 | B13: 0.29 | C13: Improving from 28.3%
A14: Reported EBITDA Margin - Yr 5 | B14: 0.33 | C14: Operating leverage
A15: SBC as % of Revenue | B15: 0.18 | C15: Slight improvement from 20%
A16: D&A as % of Revenue | B16: 0.035 | C16: Historical levels
A17: Capex as % of Revenue | B17: 0.01 | C17: Asset-light model
A18: Tax Rate | B18: 0.2 | C18: Company guidance
A19: NWC Change as % of Rev Growth | B19: 0.05 | C19: Minimal WC needs
A21: Discount Rate (WACC) | B21: Value | C21: Rationale
A22: Risk-Free Rate | B22: 0.043 | C22: 10-year Treasury
A23: Equity Risk Premium | B23: 0.055 | C23: Market premium
A24: Beta (Levered) | B24: 1.35 | C24: Tech/ad exposure
A25: Cost of Equity / WACC | B25: 0.117 | C25: No debt
A27: Valuation Inputs | B27: Value
A28: Shares Outstanding (M) | B28: 695 | C28: Current diluted
A29: Net Cash ($M) | B29: 2442 | C29: Cash position
A30: Current Stock Price ($) | B30: 26 | C30: Market price

Sheet DCF Model
A1: DCF VALUATION MODEL (SBC-ADJUSTED)
A2: Pinterest, Inc. (PINS) | $ in millions
B5: Base Year | C5: Year 1 | D5: Year 2 | E5: Year 3 | F5: Year 4 | G5: Year 5 | H5: Terminal
B6: 2024A | C6: 2025E | D6: 2026E | E6: 2027E | F6: 2028E | G6: 2029E | H6: Value
A8: Revenue Growth Rate | C8: ='DCF Assumptions'!B5 -> 0.14 | D8: ='DCF Assumptions'!B6 -> 0.13 | E8: ='DCF Assumptions'!B7 -> 0.12 | F8: ='DCF Assumptions'!B8 -> 0.11 | G8: ='DCF Assumptions'!B9 -> 0.1
A9: Revenue | B9: ='DCF Assumptions'!B4 -> 3646 | C9: =B9*(1+C8) -> 4156.44 | D9: =C9*(1+D8) -> 4696.7772 | E9: =D9*(1+E8) -> 5260.3905 | F9: =E9*(1+F8) -> 5839.0334 | G9: =F9*(1+G8) -> 6422.9368
A11: Reported EBITDA Margin | C11: ='DCF Assumptions'!B13 -> 0.29 | D11: =C11+(('DCF Assumptions'!B14-'DCF Assumptions'!B13)/4) -> 0.3 | E11: =D11+(('DCF Assumptions'!B14-'DCF Assumptions'!B13)/4) -> 0.31 | F11: =E11+(('DCF Assumptions'!B14-'DCF Assumptions'!B13)/4) -> 0.32 | G11: ='DCF Assumptions'!B14 -> 0.33
A12: Reported EBITDA | B12: 1032 | C12: =C9*C11 -> 1205.3676 | D12: =D9*D11 -> 1409.0332 | E12: =E9*E11 -> 1630.721 | F12: =F9*F11 -> 1868.4907 | G12: =G9*G11 -> 2119.5691
A14: SBC as % of Revenue | B14: 0.2 | C14: ='DCF Assumptions'!B15 -> 0.18 | D14: ='DCF Assumptions'!B15 -> 0.18 | E14: ='DCF Assumptions'!B15 -> 0.18 | F14: ='DCF Assumptions'!B15 -> 0.18 | G14: ='DCF Assumptions'!B15 -> 0.18
A15: Less: Stock-Based Comp | B15: =-B9*B14 -> -729.2 | C15: =-C9*C14 -> -748.1592 | D15: =-D9*D14 -> -845.4199 | E15: =-E9*E14 -> -946.87028 | F15: =-F9*F14 -> -1051.026 | G15: =-G9*G14 -> -1156.1286
A16: SBC-ADJUSTED EBITDA | B16: =B12+B15 -> 302.8 | C16: =C12+C15 -> 457.2084 | D16: =D12+D15 -> 563.61326 | E16: =E12+E15 -> 683.85076 | F16: =F12+F15 -> 817.46468 | G16: =G12+G15 -> 963.44051
A17: SBC-Adj EBITDA Margin | B17: =B16/B9 -> 0.083049918 | C17: =C16/C9 -> 0.11 | D17: =D16/D9 -> 0.12 | E17: =E16/E9 -> 0.13 | F17: =F16/F9 -> 0.14 | G17: =G16/G9 -> 0.15
A19: D&A (% of Revenue) | C19: ='DCF Assumptions'!B16 -> 0.035 | D19: ='DCF Assumptions'!B16 -> 0.035 | E19: ='DCF Assumptions'!B16 -> 0.035 | F19: ='DCF Assumptions'!B16 -> 0.035 | G19: ='DCF Assumptions'!B16 -> 0.035
A20: D&A | C20: =C9*C19 -> 145.4754 | D20: =D9*D19 -> 164.3872 | E20: =E9*E19 -> 184.11367 | F20: =F9*F19 -> 204.36617 | G20: =G9*G19 -> 224.80279
A21: EBIT (SBC-Adjusted) | C21: =C16-C20 -> 311.733 | D21: =D16-D20 -> 399.22606 | E21: =E16-E20 -> 499.73709 | F21: =F16-F20 -> 613.09851 | G21: =G16-G20 -> 738.63773
A23: Tax Rate | C23: ='DCF Assumptions'!B18 -> 0.2 | D23: ='DCF Assumptions'!B18 -> 0.2 | E23: ='DCF Assumptions'!B18 -> 0.2 | F23: ='DCF Assumptions'!B18 -> 0.2 | G23: ='DCF Assumptions'!B18 -> 0.2
A24: Taxes | C24: =C21*C23 -> 62.3466 | D24: =D21*D23 -> 79.845212 | E24: =E21*E23 -> 99.947419 | F24: =F21*F23 -> 122.6197 | G24: =G21*G23 -> 147.72755
A25: NOPAT | C25: =C21-C24 -> 249.3864 | D25: =D21-D24 -> 319.38085 | E25: =E21-E24 -> 399.78968 | F25: =F21-F24 -> 490.47881 | G25: =G21-G24 -> 590.91018
A27: Add: D&A | C27: =C20 -> 145.4754 | D27: =D20 -> 164.3872 | E27: =E20 -> 184.11367 | F27: =F20 -> 204.36617 | G27: =G20 -> 224.80279
A28: Capex (% of Rev) | C28: ='DCF Assumptions'!B17 -> 0.01 | D28: ='DCF Assumptions'!B17 -> 0.01 | E28: ='DCF Assumptions'!B17 -> 0.01 | F28: ='DCF Assumptions'!B17 -> 0.01 | G28: ='DCF Assumptions'!B17 -> 0.01
A29: Less: Capex | C29: =-C9*C28 -> -41.5644 | D29: =-D9*D28 -> -46.967772 | E29: =-E9*E28 -> -52.603905 | F29: =-F9*F28 -> -58.390334 | G29: =-G9*G28 -> -64.229368
A30: Less: Change in NWC | C30: =-(C9-B9)*'DCF Assumptions'!B19 -> -25.522 | D30: =-(D9-C9)*'DCF Assumptions'!B19 -> -27.01686 | E30: =-(E9-D9)*'DCF Assumptions'!B19 -> -28.180663 | F30: =-(F9-E9)*'DCF Assumptions'!B19 -> -28.932148 | G30: =-(G9-F9)*'DCF Assumptions'!B19 -> -29.195167
A32: SBC-ADJUSTED UFCF | C32: =C25+C27+C29+C30 -> 327.7754 | D32: =D25+D27+D29+D30 -> 409.78342 | E32: =E25+E27+E29+E30 -> 503.11877 | F32: =F25+F27+F29+F30 -> 607.52249 | G32: =G25+G27+G29+G30 -> 722.28843
A34: Terminal Growth Rate | H34: ='DCF Assumptions'!B10 -> 0.03
A35: Terminal Value | H35: =G32*(1+H34)/('DCF Assumptions'!B25-H34) -> 8551.2309
A37: WACC | B37: ='DCF Assumptions'!B25 -> 0.117
A38: Discount Period | C38: 0.5 | D38: 1.5 | E38: 2.5 | F38: 3.5 | G38: 4.5 | H38: 4.5
A39: Discount Factor | C39: =1/(1+$B$37)^C38 -> 0.94617924 | D39: =1/(1+$B$37)^D38 -> 0.84707183 | E39: =1/(1+$B$37)^E38 -> 0.75834542 | F39: =1/(1+$B$37)^F38 -> 0.67891264 | G39: =1/(1+$B$37)^G38 -> 0.60780004 | H39: =1/(1+$B$37)^H38 -> 0.60780004
A41: PV of FCF | C41: =C32*C39 -> 310.13428 | D41: =D32*D39 -> 347.11599 | E41: =E32*E39 -> 381.53782 | F41: =F32*F39 -> 412.4547 | G41: =G32*G39 -> 439.00694
A42: PV of Terminal Value | H42: =H35*H39 -> 5197.4384
A44: VALUATION SUMMARY
A46: Sum of PV of FCFs | B46: =SUM(C41:G41) -> 1890.2497
A47: PV of Terminal Value | B47: =H42 -> 5197.4384
A48: Enterprise Value | B48: =B46+B47 -> 7087.6882
A49: Plus: Net Cash | B49: ='DCF Assumptions'!B29 -> 2442
A50: Equity Value | B50: =B48+B49 -> 9529.6882
A52: Shares Outstanding (M) | B52: ='DCF Assumptions'!B28 -> 695
A53: IMPLIED SHARE PRICE | B53: =B50/B52 -> 13.711782
A55: Current Share Price | B55: ='DCF Assumptions'!B30 -> 26
A56: Implied Upside/(Downside) | B56: =(B53-B55)/B55 -> -0.47262379

Sheet Model Comparison
A1: VALUATION COMPARISON: REPORTED vs SBC-ADJUSTED
A3: This sheet compares the DCF output with and without SBC adjustment
B5: Reported FCF | C5: SBC-Adjusted | D5: Difference
B6: (Original Model) | C6: (This Model)
A8: 2024 Base EBITDA ($M) | B8: 1032 | C8: =1032-730 -> 302 | D8: =C8-B8 -> -730
A9: 2024 Base FCF ($M) | B9: 940 | C9: =940-730 -> 210 | D9: =C9-B9 -> -730
A11: Implied EV ($M) | B11: 23100 | C11: ='DCF Model'!B48 -> 7087.6882 | D11: =C11-B11 -> -16012.312
A12: Plus: Net Cash ($M) | B12: 2442 | C12: 2442 | D12: -
A13: Implied Equity Value ($M) | B13: =B11+B12 -> 25542 | C13: =C11+C12 -> 9529.6882 | D13: =C13-B13 -> -16012.312
A15: Shares Outstanding (M) | B15: 695 | C15: 695 | D15: -
A16: Implied Share Price | B16: =B13/B15 -> 36.751079 | C16: =C13/C15 -> 13.711782 | D16: =C16-B16 -> -23.039298
A18: Current Price | B18: 26 | C18: 26 | D18: -
A19: Implied Upside/Downside | B19: =(B16-B18)/B18 -> 0.41350304 | C19: =(C16-C18)/C18 -> -0.47262379
A21: KEY TAKEAWAY:
A22: The reported FCF model suggests ~40% upside
A23: The SBC-adjusted model shows ~47% DOWNSIDE
A24: Market appears to be pricing in the SBC dilution correctly

Sheet Sensitivity
A1: SENSITIVITY ANALYSIS (SBC-ADJUSTED MODEL)
A2: Implied Share Price by WACC and Terminal Growth Rate
A4: Base Case: WACC = 11.7%, Terminal Growth = 3.0%, SBC = 18% of Rev
C6: Terminal Growth Rate
C7: 2.0% | D7: 2.5% | E7: 3.0% | F7: 3.5% | G7: 4.0%
B8: 9.7% | C8: 32.5 | D8: 34.8 | E8: 37.5 | F8: 40.8 | G8: 44.8
A9: WACC | B9: 10.7% | C9: 27.2 | D9: 28.9 | E9: 30.9 | F9: 33.2 | G9: 35.9
B10: 11.7% | C10: 22.8 | D10: 24.1 | E10: 25.6 | F10: 27.3 | G10: 29.2
B11: 12.7% | C11: 19.2 | D11: 20.2 | E11: 21.4 | F11: 22.7 | G11: 24.1
B12: 13.7% | C12: 16.2 | D12: 17 | E12: 17.9 | F12: 18.9 | G12: 20
A14: Current stock price: $26
A15: Base case implies stock is ~2% UNDERVALUED (vs ~40% in unadjusted model)
A17: SBC Sensitivity (at base WACC/Terminal Growth)
A19: SBC % of Revenue | B19: 15.0% | C19: 18.0% | D19: 20.0% | E19: 22.0% | F19: 25.0%
A20: Implied Share Price | B20: 31.2 | C20: 25.6 | D20: 22.1 | E20: 18.6 | F20: 13.3
