Workbook

Sheet Inputs
A1: Ryman Healthcare (RYM.NZ) - NTA/BVPS path x exit P/B model
A2: Valuation date | B2: 2026-08-27
A3: Current price (NZD) | B3: 2.13
A4: Shares outstanding (m) | B4: 1015.722
A5: Book equity FY2026 (NZ$m) | B5: 4077.664
A6: BVPS FY2026 (NZD) | B6: =B5/B4
A7: Total debt FY2026 (NZ$m) | B7: 1581.036
A8: Cash FY2026 (NZ$m) | B8: 9.697
A9: Net debt (reference only - NOT subtracted) | B9: =B7-B8
A10: Statutory NPAT FY2026 (NZ$m) | B10: -171.345
A11: PBTF FY2026 (NZ$m) | B11: -73.309
A12: Operating EBITDAF FY2026 (NZ$m) | B12: 88.3
A13: Hurdle rate (entry price) | B13: 0.15
A14: Note | B14: Equity-level model: dividends + terminal (BVPS_Y5 x exit P/B) discounted at cost of equity. OCF is NOT FCF for an ORA/DMF operator; statutory NPAT is IAS-40 fair-value noise.

Sheet Base
A1: Base scenario
A2: Cost of equity | B2: 0.125
A3: Exit P/B | B3: 0.75
A4: Probability weight | B4: 0.5
A6: Year | B6: FY2027 | C6: FY2028 | D6: FY2029 | E6: FY2030 | F6: FY2031
A7: Statutory NPAT (NZ$m) | B7: 30 | C7: 120 | D7: 200 | E7: 250 | F7: 290
A8: Dividends paid (NZ$m) | B8: 0 | C8: 30 | D8: 50 | E8: 70 | F8: 90
A9: Book equity (NZ$m) | B9: =Inputs!B5+B7-B8 | C9: =B9+C7-C8 | D9: =C9+D7-D8 | E9: =D9+E7-E8 | F9: =E9+F7-F8
A10: BVPS (NZD) | B10: =B9/Inputs!B4 | C10: =C9/Inputs!B4 | D10: =D9/Inputs!B4 | E10: =E9/Inputs!B4 | F10: =F9/Inputs!B4
A11: DPS (NZD) | B11: =B8/Inputs!B4 | C11: =C8/Inputs!B4 | D11: =D8/Inputs!B4 | E11: =E8/Inputs!B4 | F11: =F8/Inputs!B4
A12: Discount factor | B12: =1/(1+$B$2)^1 | C12: =1/(1+$B$2)^2 | D12: =1/(1+$B$2)^3 | E12: =1/(1+$B$2)^4 | F12: =1/(1+$B$2)^5
A13: PV of DPS (NZD) | B13: =B11*B12 | C13: =C11*C12 | D13: =D11*D12 | E13: =E11*E12 | F13: =F11*F12
A15: PV of dividends / share | B15: =SUM(B13:F13)
A16: Terminal BVPS (Y5) | B16: =F10
A17: Terminal value / share (BVPS x exit P/B) | B17: =B16*$B$3
A18: PV of terminal / share | B18: =B17*F12
A19: Intrinsic value / share (NZD) | B19: =B15+B18
A20: Upside vs current price | B20: =B19/Inputs!B3-1
A21: Entry price @ 15% hurdle | B21: =B11/(1+Inputs!$B$13)^1+C11/(1+Inputs!$B$13)^2+D11/(1+Inputs!$B$13)^3+E11/(1+Inputs!$B$13)^4+F11/(1+Inputs!$B$13)^5+B17/(1+Inputs!$B$13)^5

Sheet Bull
A1: Bull scenario
A2: Cost of equity | B2: 0.11
A3: Exit P/B | B3: 1
A4: Probability weight | B4: 0.25
A6: Year | B6: FY2027 | C6: FY2028 | D6: FY2029 | E6: FY2030 | F6: FY2031
A7: Statutory NPAT (NZ$m) | B7: 100 | C7: 220 | D7: 320 | E7: 380 | F7: 430
A8: Dividends paid (NZ$m) | B8: 0 | C8: 60 | D8: 100 | E8: 140 | F8: 170
A9: Book equity (NZ$m) | B9: =Inputs!B5+B7-B8 | C9: =B9+C7-C8 | D9: =C9+D7-D8 | E9: =D9+E7-E8 | F9: =E9+F7-F8
A10: BVPS (NZD) | B10: =B9/Inputs!B4 | C10: =C9/Inputs!B4 | D10: =D9/Inputs!B4 | E10: =E9/Inputs!B4 | F10: =F9/Inputs!B4
A11: DPS (NZD) | B11: =B8/Inputs!B4 | C11: =C8/Inputs!B4 | D11: =D8/Inputs!B4 | E11: =E8/Inputs!B4 | F11: =F8/Inputs!B4
A12: Discount factor | B12: =1/(1+$B$2)^1 | C12: =1/(1+$B$2)^2 | D12: =1/(1+$B$2)^3 | E12: =1/(1+$B$2)^4 | F12: =1/(1+$B$2)^5
A13: PV of DPS (NZD) | B13: =B11*B12 | C13: =C11*C12 | D13: =D11*D12 | E13: =E11*E12 | F13: =F11*F12
A15: PV of dividends / share | B15: =SUM(B13:F13)
A16: Terminal BVPS (Y5) | B16: =F10
A17: Terminal value / share (BVPS x exit P/B) | B17: =B16*$B$3
A18: PV of terminal / share | B18: =B17*F12
A19: Intrinsic value / share (NZD) | B19: =B15+B18
A20: Upside vs current price | B20: =B19/Inputs!B3-1
A21: Entry price @ 15% hurdle | B21: =B11/(1+Inputs!$B$13)^1+C11/(1+Inputs!$B$13)^2+D11/(1+Inputs!$B$13)^3+E11/(1+Inputs!$B$13)^4+F11/(1+Inputs!$B$13)^5+B17/(1+Inputs!$B$13)^5

Sheet Bear
A1: Bear scenario
A2: Cost of equity | B2: 0.14
A3: Exit P/B | B3: 0.45
A4: Probability weight | B4: 0.25
A6: Year | B6: FY2027 | C6: FY2028 | D6: FY2029 | E6: FY2030 | F6: FY2031
A7: Statutory NPAT (NZ$m) | B7: -250 | C7: -120 | D7: -30 | E7: 20 | F7: 50
A8: Dividends paid (NZ$m) | B8: 0 | C8: 0 | D8: 0 | E8: 0 | F8: 0
A9: Book equity (NZ$m) | B9: =Inputs!B5+B7-B8 | C9: =B9+C7-C8 | D9: =C9+D7-D8 | E9: =D9+E7-E8 | F9: =E9+F7-F8
A10: BVPS (NZD) | B10: =B9/Inputs!B4 | C10: =C9/Inputs!B4 | D10: =D9/Inputs!B4 | E10: =E9/Inputs!B4 | F10: =F9/Inputs!B4
A11: DPS (NZD) | B11: =B8/Inputs!B4 | C11: =C8/Inputs!B4 | D11: =D8/Inputs!B4 | E11: =E8/Inputs!B4 | F11: =F8/Inputs!B4
A12: Discount factor | B12: =1/(1+$B$2)^1 | C12: =1/(1+$B$2)^2 | D12: =1/(1+$B$2)^3 | E12: =1/(1+$B$2)^4 | F12: =1/(1+$B$2)^5
A13: PV of DPS (NZD) | B13: =B11*B12 | C13: =C11*C12 | D13: =D11*D12 | E13: =E11*E12 | F13: =F11*F12
A15: PV of dividends / share | B15: =SUM(B13:F13)
A16: Terminal BVPS (Y5) | B16: =F10
A17: Terminal value / share (BVPS x exit P/B) | B17: =B16*$B$3
A18: PV of terminal / share | B18: =B17*F12
A19: Intrinsic value / share (NZD) | B19: =B15+B18
A20: Upside vs current price | B20: =B19/Inputs!B3-1
A21: Entry price @ 15% hurdle | B21: =B11/(1+Inputs!$B$13)^1+C11/(1+Inputs!$B$13)^2+D11/(1+Inputs!$B$13)^3+E11/(1+Inputs!$B$13)^4+F11/(1+Inputs!$B$13)^5+B17/(1+Inputs!$B$13)^5

Sheet Summary
A1: Probability-weighted valuation
A3: Scenario | B3: Weight | C3: IV (NZD) | D3: Entry @15% | E3: Upside
A4: Bear | B4: =Bear!B4 | C4: =Bear!B19 | D4: =Bear!B21 | E4: =Bear!B20
A5: Base | B5: =Base!B4 | C5: =Base!B19 | D5: =Base!B21 | E5: =Base!B20
A6: Bull | B6: =Bull!B4 | C6: =Bull!B19 | D6: =Bull!B21 | E6: =Bull!B20
A8: Weighted IV | C8: =SUMPRODUCT(B4:B6,C4:C6)
A9: Weighted entry price | C9: =SUMPRODUCT(B4:B6,D4:D6)
A10: Current price | C10: =Inputs!B3
A11: Weighted upside | C11: =C8/C10-1

Sheet Sensitivity
A1: Base-case IV/share: cost of equity (rows) x exit P/B (cols)
B3: 0.55 | C3: 0.65 | D3: 0.75 | E3: 0.85 | F3: 0.95
A4: 0.105 | B4: =Base!B11/(1+$A4)^1+Base!C11/(1+$A4)^2+Base!D11/(1+$A4)^3+Base!E11/(1+$A4)^4+Base!F11/(1+$A4)^5+Base!F10*B$3/(1+$A4)^5 | C4: =Base!B11/(1+$A4)^1+Base!C11/(1+$A4)^2+Base!D11/(1+$A4)^3+Base!E11/(1+$A4)^4+Base!F11/(1+$A4)^5+Base!F10*C$3/(1+$A4)^5 | D4: =Base!B11/(1+$A4)^1+Base!C11/(1+$A4)^2+Base!D11/(1+$A4)^3+Base!E11/(1+$A4)^4+Base!F11/(1+$A4)^5+Base!F10*D$3/(1+$A4)^5 | E4: =Base!B11/(1+$A4)^1+Base!C11/(1+$A4)^2+Base!D11/(1+$A4)^3+Base!E11/(1+$A4)^4+Base!F11/(1+$A4)^5+Base!F10*E$3/(1+$A4)^5 | F4: =Base!B11/(1+$A4)^1+Base!C11/(1+$A4)^2+Base!D11/(1+$A4)^3+Base!E11/(1+$A4)^4+Base!F11/(1+$A4)^5+Base!F10*F$3/(1+$A4)^5
A5: 0.115 | B5: =Base!B11/(1+$A5)^1+Base!C11/(1+$A5)^2+Base!D11/(1+$A5)^3+Base!E11/(1+$A5)^4+Base!F11/(1+$A5)^5+Base!F10*B$3/(1+$A5)^5 | C5: =Base!B11/(1+$A5)^1+Base!C11/(1+$A5)^2+Base!D11/(1+$A5)^3+Base!E11/(1+$A5)^4+Base!F11/(1+$A5)^5+Base!F10*C$3/(1+$A5)^5 | D5: =Base!B11/(1+$A5)^1+Base!C11/(1+$A5)^2+Base!D11/(1+$A5)^3+Base!E11/(1+$A5)^4+Base!F11/(1+$A5)^5+Base!F10*D$3/(1+$A5)^5 | E5: =Base!B11/(1+$A5)^1+Base!C11/(1+$A5)^2+Base!D11/(1+$A5)^3+Base!E11/(1+$A5)^4+Base!F11/(1+$A5)^5+Base!F10*E$3/(1+$A5)^5 | F5: =Base!B11/(1+$A5)^1+Base!C11/(1+$A5)^2+Base!D11/(1+$A5)^3+Base!E11/(1+$A5)^4+Base!F11/(1+$A5)^5+Base!F10*F$3/(1+$A5)^5
A6: 0.125 | B6: =Base!B11/(1+$A6)^1+Base!C11/(1+$A6)^2+Base!D11/(1+$A6)^3+Base!E11/(1+$A6)^4+Base!F11/(1+$A6)^5+Base!F10*B$3/(1+$A6)^5 | C6: =Base!B11/(1+$A6)^1+Base!C11/(1+$A6)^2+Base!D11/(1+$A6)^3+Base!E11/(1+$A6)^4+Base!F11/(1+$A6)^5+Base!F10*C$3/(1+$A6)^5 | D6: =Base!B11/(1+$A6)^1+Base!C11/(1+$A6)^2+Base!D11/(1+$A6)^3+Base!E11/(1+$A6)^4+Base!F11/(1+$A6)^5+Base!F10*D$3/(1+$A6)^5 | E6: =Base!B11/(1+$A6)^1+Base!C11/(1+$A6)^2+Base!D11/(1+$A6)^3+Base!E11/(1+$A6)^4+Base!F11/(1+$A6)^5+Base!F10*E$3/(1+$A6)^5 | F6: =Base!B11/(1+$A6)^1+Base!C11/(1+$A6)^2+Base!D11/(1+$A6)^3+Base!E11/(1+$A6)^4+Base!F11/(1+$A6)^5+Base!F10*F$3/(1+$A6)^5
A7: 0.135 | B7: =Base!B11/(1+$A7)^1+Base!C11/(1+$A7)^2+Base!D11/(1+$A7)^3+Base!E11/(1+$A7)^4+Base!F11/(1+$A7)^5+Base!F10*B$3/(1+$A7)^5 | C7: =Base!B11/(1+$A7)^1+Base!C11/(1+$A7)^2+Base!D11/(1+$A7)^3+Base!E11/(1+$A7)^4+Base!F11/(1+$A7)^5+Base!F10*C$3/(1+$A7)^5 | D7: =Base!B11/(1+$A7)^1+Base!C11/(1+$A7)^2+Base!D11/(1+$A7)^3+Base!E11/(1+$A7)^4+Base!F11/(1+$A7)^5+Base!F10*D$3/(1+$A7)^5 | E7: =Base!B11/(1+$A7)^1+Base!C11/(1+$A7)^2+Base!D11/(1+$A7)^3+Base!E11/(1+$A7)^4+Base!F11/(1+$A7)^5+Base!F10*E$3/(1+$A7)^5 | F7: =Base!B11/(1+$A7)^1+Base!C11/(1+$A7)^2+Base!D11/(1+$A7)^3+Base!E11/(1+$A7)^4+Base!F11/(1+$A7)^5+Base!F10*F$3/(1+$A7)^5
A8: 0.145 | B8: =Base!B11/(1+$A8)^1+Base!C11/(1+$A8)^2+Base!D11/(1+$A8)^3+Base!E11/(1+$A8)^4+Base!F11/(1+$A8)^5+Base!F10*B$3/(1+$A8)^5 | C8: =Base!B11/(1+$A8)^1+Base!C11/(1+$A8)^2+Base!D11/(1+$A8)^3+Base!E11/(1+$A8)^4+Base!F11/(1+$A8)^5+Base!F10*C$3/(1+$A8)^5 | D8: =Base!B11/(1+$A8)^1+Base!C11/(1+$A8)^2+Base!D11/(1+$A8)^3+Base!E11/(1+$A8)^4+Base!F11/(1+$A8)^5+Base!F10*D$3/(1+$A8)^5 | E8: =Base!B11/(1+$A8)^1+Base!C11/(1+$A8)^2+Base!D11/(1+$A8)^3+Base!E11/(1+$A8)^4+Base!F11/(1+$A8)^5+Base!F10*E$3/(1+$A8)^5 | F8: =Base!B11/(1+$A8)^1+Base!C11/(1+$A8)^2+Base!D11/(1+$A8)^3+Base!E11/(1+$A8)^4+Base!F11/(1+$A8)^5+Base!F10*F$3/(1+$A8)^5
