Workbook

Sheet Model_Info
A1: WBC.NZ residual-income (bank) valuation model
A2: Version 1.0, fresh build 2026-09-20 -- supersedes nothing (first WBC.NZ valuation).
A3: Built by the dcf-analyst agent (Claude Fable 5.1) on 2026-09-20 at the research-stock orchestrator's request.
A4: Figures go stale: price, FX, tangible book, share count and CET1 must be refreshed after each half-year result.
A6: DATA VINTAGE
A7: Price: NZ$43.08 WBC.NZ, NZX regular close 2026-09-18T04:59:55Z (Yahoo). ASX parity: WBC.AX A$34.75 close 2026-09-18.
A8: FX: AUDNZD 1.2435, Yahoo AUDNZD=X 2026-09-20T04:50Z. Parity 34.75 x 1.2435 = 43.21 vs 43.08 (0.3%).
A9: Balance sheet: 31-Mar-2026 interim results -- equity attributable A$70,761m, intangibles A$10,204m, NTA/share A$17.73, CET1 12.42%.
A10: Share count: 3,415m (3,420.3m on issue less ~5m treasury), 31-Mar-2026. AT1 conversion (diluted 3,594m) excluded.
A11: Guidance: none given. 1H26 framing: CET1 > 11.25%, ROTE and cost-to-income improvement via UNITE, provisions raised for the energy shock.
A13: METHODOLOGY
A14: Model: residual income on tangible book, implemented as PV(dividends per share) + PV(exit P/TBV x FY2031 TBVPS), discounted at AUD cost of equity.
... A26: CELL COLOURS: blue = hardcoded input; yellow fill = key lever; black = formula; green = cross-sheet link.

Sheet Actuals
A1: Metric (AUD m unless stated) | B1: FY2023 | C1: FY2024 | D1: H1 FY2025 | E1: FY2025 | F1: H1 FY2026 | G1: Source
A2: Revenue (net operating income) | B2: 21645 | C2: 21588 | D2: 10793 | E2: 22384 | F2: 11293 | G2: WBC.NZ_Metrics.csv
A3: Net interest income | B3: 18317 | C3: 18753 | D3: 9351 | E3: 19380 | F3: 9771 | G3: kpis NetInterestIncome
A4: Net profit attributable | B4: 7195 | C4: 6990 | D4: 3317 | E4: 6916 | F4: 3414 | G4: WBC.NZ_Metrics.csv
A5: Operating cash flow (NOT FCF) | B5: -10796 | C5: -19767 | D5: 11969 | E5: 9489 | F5: -6679 | G5: WBC.NZ_Metrics.csv -- loan/deposit flow artefact
A6: Equity attributable | B6: 72495 | C6: 71705 | D6: 72015 | E6: 72766 | F6: 70761 | G6: WBC.NZ_Metrics.csv
A7: Shares (m) | B7: 3502 | C7: 3476 | D7: 3416 | E7: 3422 | F7: 3415 | G7: WBC.NZ_Metrics.csv
A8: EPS basic (AUD) | B8: 2.053 | C8: 2.009 | D8: 0.967 | E8: 2.019 | F8: 0.999 | G8: WBC.NZ_Metrics.csv
A9: DPS (AUD) | B9: 1.42 | C9: 1.51 | D9: 0.76 | E9: 1.53 | F9: 0.77 | G9: WBC.NZ_Metrics.csv
A10: NTA per share (AUD) | D10: 17.97 | E10: 18.25 | F10: 17.73 | G10: kpis NetTangibleAssetsPerShare
A11: ROE % | B11: 10.09 | C11: 9.77 | D11: 9.42 | E11: 9.66 | F11: 9.58 | G11: kpis ROE
A12: ROTE % (statutory) | B12: 11.39 | C12: 11.01 | D12: 10.63 | E12: 11.13 | F12: 10.79 | G12: kpis ROTE
A13: NIM % | B13: 1.9 | C13: 1.95 | D13: 1.92 | E13: 1.94 | F13: 1.89 | G13: kpis NIM
A14: CET1 % | D14: 12.24 | E14: 12.53 | F14: 12.42 | G14: kpis CET1Ratio
A15: Payout ratio % | B15: 69.2 | C15: 74.62 | D15: 78.38 | E15: 73.14 | F15: 77.09 | G15: kpis DividendPayoutRatio
A16: Share repurchases | B16: 0 | C16: 1812 | D16: 565 | E16: 672 | F16: 2 | G16: kpis ShareRepurchases
A17: Share-based payments | B17: 90 | C17: 97 | D17: 54 | E17: 95 | F17: 58 | G17: WBC.NZ_Metrics.csv StockBasedComp
A18: Intangible assets (H1 FY2026) | D18: 10599 | E18: 10465 | F18: 10204 | G18: H1-2026 interim results balance sheet
A20: Buyback status: A$3.5bn program, A$2.5bn done by 31-Mar-2026 (88.8m shares at A$28.01 avg); A$1.0bn remaining, extended to 10-Nov-2026; only 50,000 shares bought in H1 FY2026.
A21: Guidance: none. 1H26 management framing -- CET1 12.42% vs 11.25% target (A$2.7bn surplus), ROTE ex-notables 11.0%, opex +4% (2% ex RAMS), provisions raised for the Middle-East energy shock.

Sheet Assumptions
A1: Global inputs
A2: Price NZD (WBC.NZ) | B2: 43.08 | C2: Yahoo NZX close 2026-09-18T04:59:55Z
A3: FX NZD per AUD | B3: 1.2435 | C3: Yahoo AUDNZD=X 2026-09-20
A4: Price AUD equivalent | B4: =B2/B3 | C4: formula
A5: Price AUD (WBC.AX) | B5: 34.75 | C5: ASX close 2026-09-18; parity check
A6: Equity attributable AUD m (31-Mar-2026) | B6: 70761 | C6: interim balance sheet
A7: Intangible assets AUD m | B7: 10204 | C7: interim balance sheet
A8: Tangible book AUD m (Mar-2026) | B8: =B6-B7 | C8: formula
A9: Shares m (ex treasury) | B9: 3415 | C9: interim results, NTA/share basis
A10: TBVPS Mar-2026 | B10: =B8/B9 | C10: formula -- ties to reported 17.73
A11: Stub annualised ROTE % | B11: 11.3 | C11: H2 FY2026 assumption
A12: Stub interim DPS AUD | B12: 0.77 | C12: paid 26-Jun-2026
A13: Tangible book Sep-2026E AUD m | B13: =B8+B11/100*B8*0.5-B12*B9 | C13: formula
A14: TBVPS Sep-2026E | B14: =B13/B9 | C14: formula -- starting TBVPS for the projection
A15: Buyback execution P/TBV | B15: 1.96 | C15: today's multiple 34.75/17.73
A16: Hurdle rate | B16: 0.15 | C16: 15% IRR entry price
A19: Scenario inputs
B20: Bear | C20: Base | D20: Bull
A21: Cost of equity % | B21: 10.5 | C21: 9.5 | D21: 9
A22: Exit P/TBV multiple | B22: 1.2 | C22: 1.5 | D22: 1.9
A23: Dividend payout % | B23: 72 | C23: 75 | D23: 75
A24: Probability weight | B24: 0.25 | C24: 0.5 | D24: 0.25
A25: Weights sum check | B25: =SUM(B24:D24)
A27: Narratives
A28: Bear | B28: NIM compresses toward 1.8% as mortgage competition and deposit mix shift persist, credit costs step up to ~20bps through the energy-price shock, UNITE delivers cost-out late; ROTE slides to 9.5%, at or below CoE. Payout trimmed to 72%, no further buybacks (capital retained for RWA growth and the higher provisioning). Exit at 1.2x TBV, the low end of Westpac's 2015-2024 range, at a 10.5% CoE.
A29: Base | B29: ROTE grinds from 11.2% to 12.0% as UNITE lowers cost-to-income from ~53% toward 50%, NIM holds ~1.9%, credit costs normalise ~10-12bps. 75% payout (FY2025 73%, 1H26 77%); the remaining 1.0bn of the buyback completes in FY2027 at ~1.96x TBV, then retention funds ~5% RWA growth with no further buybacks. Exit 1.5x TBV vs justified 1.38x; CoE 9.5%.
A30: Bull | B30: Rates and credit stay benign, UNITE hits its cost targets early, ROTE reaches 13.5% (peer-leading ex-CBA). Surplus capital above 11.25% CET1 recycled through 1.0-1.5bn/yr buybacks at today's multiple. Exit at 1.9x TBV (today's multiple sustained) at a 9.0% CoE.

Sheet DCF_Bear
A1: Bear scenario -- residual income on tangible book (AUD m, per-share AUD)
A3: Year | B3: FY2026E (Sep-26 stub) | C3: FY2027 | D3: FY2028 | E3: FY2029 | F3: FY2030 | G3: FY2031
A4: Year index | B4: 0 | C4: 1 | D4: 2 | E4: 3 | F4: 4 | G4: 5
A5: ROTE % (driver) | C5: 10.5 | D5: 10 | E5: 9.5 | F5: 9.5 | G5: 9.5
A6: Beginning tangible book | C6: =B14 | D6: =C14 | E6: =D14 | F6: =E14 | G6: =F14
A7: Net income = ROTE x beginning TBV | C7: =C5/100*C6 | D7: =D5/100*D6 | E7: =E5/100*E6 | F7: =F5/100*F6 | G7: =G5/100*G6
A8: Payout % (link) | C8: =Assumptions!B23 | D8: =Assumptions!B23 | E8: =Assumptions!B23 | F8: =Assumptions!B23 | G8: =Assumptions!B23
A9: Dividends | C9: =C7*C8/100 | D9: =D7*D8/100 | E9: =E7*E8/100 | F9: =F7*F8/100 | G9: =G7*G8/100
A10: Buyback AUD m (driver) | C10: 0 | D10: 0 | E10: 0 | F10: 0 | G10: 0
A11: Buyback price = P/TBV x prior TBVPS | C11: =Assumptions!$B$15*B15 | D11: =Assumptions!$B$15*C15 | E11: =Assumptions!$B$15*D15 | F11: =Assumptions!$B$15*E15 | G11: =Assumptions!$B$15*F15
A12: Shares repurchased (m) | C12: =C10/C11 | D12: =D10/D11 | E12: =E10/E11 | F12: =F10/F11 | G12: =G10/G11
A13: Ending shares (m) | B13: =Assumptions!B9 | C13: =B13-C12 | D13: =C13-D12 | E13: =D13-E12 | F13: =E13-F12 | G13: =F13-G12
A14: Ending tangible book | B14: =Assumptions!B13 | C14: =C6+C7-C9-C10 | D14: =D6+D7-D9-D10 | E14: =E6+E7-E9-E10 | F14: =F6+F7-F9-F10 | G14: =G6+G7-G9-G10
A15: Tangible book per share | B15: =B14/B13 | C15: =C14/C13 | D15: =D14/D13 | E15: =E14/E13 | F15: =F14/F13 | G15: =G14/G13
A16: DPS | C16: =C9/C13 | D16: =D9/D13 | E16: =E9/E13 | F16: =F9/F13 | G16: =G9/G13
A17: EPS (memo) | C17: =C7/C13 | D17: =D7/D13 | E17: =E7/E13 | F17: =F7/F13 | G17: =G7/G13
A18: Discount factor | C18: =1/(1+$B$36/100)^C4 | D18: =1/(1+$B$36/100)^D4 | E18: =1/(1+$B$36/100)^E4 | F18: =1/(1+$B$36/100)^F4 | G18: =1/(1+$B$36/100)^G4
A19: PV of DPS | C19: =C16*C18 | D19: =D16*D18 | E19: =E16*E18 | F19: =F16*F18 | G19: =G16*G18
A21: Memo: residual income per share = (ROTE - CoE) x prior TBVPS | C21: =(C5-$B$36)/100*B15 | D21: =(D5-$B$36)/100*C15 | E21: =(E5-$B$36)/100*D15 | F21: =(F5-$B$36)/100*E15 | G21: =(G5-$B$36)/100*F15
A22: Memo: PV residual income per share | C22: =C21*C18 | D22: =D21*D18 | E22: =E21*E18 | F22: =F21*F18 | G22: =G21*G18
A24: Sum of PV of DPS (AUD) | B24: =SUM(C19:G19)
A25: Exit P/TBV multiple (link) | B25: =Assumptions!B22
A26: FY2031 TBVPS (AUD) | B26: =G15
A27: Exit value per share (AUD) | B27: =B25*B26
A28: PV of exit value (AUD) | B28: =B27*G18
A29: Intrinsic value per share AUD | B29: =B24+B28
A30: FX NZD per AUD (link) | B30: =Assumptions!B3
A31: Intrinsic value per share NZD | B31: =B29*B30
A32: Price NZD (link) | B32: =Assumptions!B2
A33: Upside vs price | B33: =B31/B32-1
A34: Implied P/TBV of IV (on Sep-26E TBVPS) | B34: =B29/B15
A35: Terminal share of value | B35: =B28/B29
A36: Cost of equity % (link) | B36: =Assumptions!B21
A37: Residual-income cross-check: TBVPS0 + PV RI + PV exit premium (AUD, approx. with buybacks) | B37: =B15+SUM(C22:G22)+(B25-1)*B26*G18
A38: Implied P/E of IV on FY2027 EPS | B38: =B29/C17

Sheet DCF_Base
A1: Base scenario -- residual income on tangible book (AUD m, per-share AUD)
A3: Year | B3: FY2026E (Sep-26 stub) | C3: FY2027 | D3: FY2028 | E3: FY2029 | F3: FY2030 | G3: FY2031
A4: Year index | B4: 0 | C4: 1 | D4: 2 | E4: 3 | F4: 4 | G4: 5
A5: ROTE % (driver) | C5: 11.2 | D5: 11.4 | E5: 11.6 | F5: 11.8 | G5: 12
A6: Beginning tangible book | C6: =B14 | D6: =C14 | E6: =D14 | F6: =E14 | G6: =F14
A7: Net income = ROTE x beginning TBV | C7: =C5/100*C6 | D7: =D5/100*D6 | E7: =E5/100*E6 | F7: =F5/100*F6 | G7: =G5/100*G6
A8: Payout % (link) | C8: =Assumptions!C23 | D8: =Assumptions!C23 | E8: =Assumptions!C23 | F8: =Assumptions!C23 | G8: =Assumptions!C23
A9: Dividends | C9: =C7*C8/100 | D9: =D7*D8/100 | E9: =E7*E8/100 | F9: =F7*F8/100 | G9: =G7*G8/100
A10: Buyback AUD m (driver) | C10: 1000 | D10: 0 | E10: 0 | F10: 0 | G10: 0
A11: Buyback price = P/TBV x prior TBVPS | C11: =Assumptions!$B$15*B15 | D11: =Assumptions!$B$15*C15 | E11: =Assumptions!$B$15*D15 | F11: =Assumptions!$B$15*E15 | G11: =Assumptions!$B$15*F15
A12: Shares repurchased (m) | C12: =C10/C11 | D12: =D10/D11 | E12: =E10/E11 | F12: =F10/F11 | G12: =G10/G11
A13: Ending shares (m) | B13: =Assumptions!B9 | C13: =B13-C12 | D13: =C13-D12 | E13: =D13-E12 | F13: =E13-F12 | G13: =F13-G12
A14: Ending tangible book | B14: =Assumptions!B13 | C14: =C6+C7-C9-C10 | D14: =D6+D7-D9-D10 | E14: =E6+E7-E9-E10 | F14: =F6+F7-F9-F10 | G14: =G6+G7-G9-G10
A15: Tangible book per share | B15: =B14/B13 | C15: =C14/C13 | D15: =D14/D13 | E15: =E14/E13 | F15: =F14/F13 | G15: =G14/G13
A16: DPS | C16: =C9/C13 | D16: =D9/D13 | E16: =E9/E13 | F16: =F9/F13 | G16: =G9/G13
A17: EPS (memo) | C17: =C7/C13 | D17: =D7/D13 | E17: =E7/E13 | F17: =F7/F13 | G17: =G7/G13
A18: Discount factor | C18: =1/(1+$B$36/100)^C4 | D18: =1/(1+$B$36/100)^D4 | E18: =1/(1+$B$36/100)^E4 | F18: =1/(1+$B$36/100)^F4 | G18: =1/(1+$B$36/100)^G4
A19: PV of DPS | C19: =C16*C18 | D19: =D16*D18 | E19: =E16*E18 | F19: =F16*F18 | G19: =G16*G18
A21: Memo: residual income per share = (ROTE - CoE) x prior TBVPS | C21: =(C5-$B$36)/100*B15 | D21: =(D5-$B$36)/100*C15 | E21: =(E5-$B$36)/100*D15 | F21: =(F5-$B$36)/100*E15 | G21: =(G5-$B$36)/100*F15
A22: Memo: PV residual income per share | C22: =C21*C18 | D22: =D21*D18 | E22: =E21*E18 | F22: =F21*F18 | G22: =G21*G18
A24: Sum of PV of DPS (AUD) | B24: =SUM(C19:G19)
A25: Exit P/TBV multiple (link) | B25: =Assumptions!C22
A26: FY2031 TBVPS (AUD) | B26: =G15
A27: Exit value per share (AUD) | B27: =B25*B26
A28: PV of exit value (AUD) | B28: =B27*G18
A29: Intrinsic value per share AUD | B29: =B24+B28
A30: FX NZD per AUD (link) | B30: =Assumptions!B3
A31: Intrinsic value per share NZD | B31: =B29*B30
A32: Price NZD (link) | B32: =Assumptions!B2
A33: Upside vs price | B33: =B31/B32-1
A34: Implied P/TBV of IV (on Sep-26E TBVPS) | B34: =B29/B15
A35: Terminal share of value | B35: =B28/B29
A36: Cost of equity % (link) | B36: =Assumptions!C21
A37: Residual-income cross-check: TBVPS0 + PV RI + PV exit premium (AUD, approx. with buybacks) | B37: =B15+SUM(C22:G22)+(B25-1)*B26*G18
A38: Implied P/E of IV on FY2027 EPS | B38: =B29/C17

Sheet DCF_Bull
A1: Bull scenario -- residual income on tangible book (AUD m, per-share AUD)
A3: Year | B3: FY2026E (Sep-26 stub) | C3: FY2027 | D3: FY2028 | E3: FY2029 | F3: FY2030 | G3: FY2031
A4: Year index | B4: 0 | C4: 1 | D4: 2 | E4: 3 | F4: 4 | G4: 5
A5: ROTE % (driver) | C5: 11.5 | D5: 12 | E5: 12.5 | F5: 13 | G5: 13.5
A6: Beginning tangible book | C6: =B14 | D6: =C14 | E6: =D14 | F6: =E14 | G6: =F14
A7: Net income = ROTE x beginning TBV | C7: =C5/100*C6 | D7: =D5/100*D6 | E7: =E5/100*E6 | F7: =F5/100*F6 | G7: =G5/100*G6
A8: Payout % (link) | C8: =Assumptions!D23 | D8: =Assumptions!D23 | E8: =Assumptions!D23 | F8: =Assumptions!D23 | G8: =Assumptions!D23
A9: Dividends | C9: =C7*C8/100 | D9: =D7*D8/100 | E9: =E7*E8/100 | F9: =F7*F8/100 | G9: =G7*G8/100
A10: Buyback AUD m (driver) | C10: 1000 | D10: 1000 | E10: 1500 | F10: 1500 | G10: 1500
A11: Buyback price = P/TBV x prior TBVPS | C11: =Assumptions!$B$15*B15 | D11: =Assumptions!$B$15*C15 | E11: =Assumptions!$B$15*D15 | F11: =Assumptions!$B$15*E15 | G11: =Assumptions!$B$15*F15
A12: Shares repurchased (m) | C12: =C10/C11 | D12: =D10/D11 | E12: =E10/E11 | F12: =F10/F11 | G12: =G10/G11
A13: Ending shares (m) | B13: =Assumptions!B9 | C13: =B13-C12 | D13: =C13-D12 | E13: =D13-E12 | F13: =E13-F12 | G13: =F13-G12
A14: Ending tangible book | B14: =Assumptions!B13 | C14: =C6+C7-C9-C10 | D14: =D6+D7-D9-D10 | E14: =E6+E7-E9-E10 | F14: =F6+F7-F9-F10 | G14: =G6+G7-G9-G10
A15: Tangible book per share | B15: =B14/B13 | C15: =C14/C13 | D15: =D14/D13 | E15: =E14/E13 | F15: =F14/F13 | G15: =G14/G13
A16: DPS | C16: =C9/C13 | D16: =D9/D13 | E16: =E9/E13 | F16: =F9/F13 | G16: =G9/G13
A17: EPS (memo) | C17: =C7/C13 | D17: =D7/D13 | E17: =E7/E13 | F17: =F7/F13 | G17: =G7/G13
A18: Discount factor | C18: =1/(1+$B$36/100)^C4 | D18: =1/(1+$B$36/100)^D4 | E18: =1/(1+$B$36/100)^E4 | F18: =1/(1+$B$36/100)^F4 | G18: =1/(1+$B$36/100)^G4
A19: PV of DPS | C19: =C16*C18 | D19: =D16*D18 | E19: =E16*E18 | F19: =F16*F18 | G19: =G16*G18
A21: Memo: residual income per share = (ROTE - CoE) x prior TBVPS | C21: =(C5-$B$36)/100*B15 | D21: =(D5-$B$36)/100*C15 | E21: =(E5-$B$36)/100*D15 | F21: =(F5-$B$36)/100*E15 | G21: =(G5-$B$36)/100*F15
A22: Memo: PV residual income per share | C22: =C21*C18 | D22: =D21*D18 | E22: =E21*E18 | F22: =F21*F18 | G22: =G21*G18
A24: Sum of PV of DPS (AUD) | B24: =SUM(C19:G19)
A25: Exit P/TBV multiple (link) | B25: =Assumptions!D22
A26: FY2031 TBVPS (AUD) | B26: =G15
A27: Exit value per share (AUD) | B27: =B25*B26
A28: PV of exit value (AUD) | B28: =B27*G18
A29: Intrinsic value per share AUD | B29: =B24+B28
A30: FX NZD per AUD (link) | B30: =Assumptions!B3
A31: Intrinsic value per share NZD | B31: =B29*B30
A32: Price NZD (link) | B32: =Assumptions!B2
A33: Upside vs price | B33: =B31/B32-1
A34: Implied P/TBV of IV (on Sep-26E TBVPS) | B34: =B29/B15
A35: Terminal share of value | B35: =B28/B29
A36: Cost of equity % (link) | B36: =Assumptions!D21
A37: Residual-income cross-check: TBVPS0 + PV RI + PV exit premium (AUD, approx. with buybacks) | B37: =B15+SUM(C22:G22)+(B25-1)*B26*G18
A38: Implied P/E of IV on FY2027 EPS | B38: =B29/C17

Sheet Valuation
A1: Valuation summary (NZD unless stated)
A2: Scenario | B2: IV AUD | C2: IV NZD | D2: Upside | E2: Weight | F2: Entry price AUD @15% | G2: Entry price NZD @15%
A3: Bear | B3: =DCF_Bear!B29 | C3: =DCF_Bear!B31 | D3: =C3/Assumptions!$B$2-1 | E3: =Assumptions!B24 | F3: =SUMPRODUCT(DCF_Bear!C16:G16/(1+Assumptions!$B$16)^DCF_Bear!C4:G4)+DCF_Bear!B27/(1+Assumptions!$B$16)^5 | G3: =F3*Assumptions!$B$3
A4: Base | B4: =DCF_Base!B29 | C4: =DCF_Base!B31 | D4: =C4/Assumptions!$B$2-1 | E4: =Assumptions!C24 | F4: =SUMPRODUCT(DCF_Base!C16:G16/(1+Assumptions!$B$16)^DCF_Base!C4:G4)+DCF_Base!B27/(1+Assumptions!$B$16)^5 | G4: =F4*Assumptions!$B$3
A5: Bull | B5: =DCF_Bull!B29 | C5: =DCF_Bull!B31 | D5: =C5/Assumptions!$B$2-1 | E5: =Assumptions!D24 | F5: =SUMPRODUCT(DCF_Bull!C16:G16/(1+Assumptions!$B$16)^DCF_Bull!C4:G4)+DCF_Bull!B27/(1+Assumptions!$B$16)^5 | G5: =F5*Assumptions!$B$3
A6: Probability-weighted IV | B6: =SUMPRODUCT(B3:B5,E3:E5) | C6: =SUMPRODUCT(C3:C5,E3:E5) | D6: =C6/Assumptions!B2-1 | F6: =SUMPRODUCT(F3:F5,E3:E5) | G6: =SUMPRODUCT(G3:G5,E3:E5)
A7: Margin of safety vs weighted IV | B7: =1-Assumptions!B2/C6
A8: Band position (house = street; SBC immaterial) | B8: n/a -- band collapsed
A10: Required-return table (base case)
A11: Return % | B11: Value AUD | C11: Value NZD
A12: 8 | B12: =SUMPRODUCT(DCF_Base!$C$16:$G$16/(1+A12/100)^DCF_Base!$C$4:$G$4)+DCF_Base!$B$27/(1+A12/100)^5 | C12: =B12*Assumptions!$B$3
A13: 9 | B13: =SUMPRODUCT(DCF_Base!$C$16:$G$16/(1+A13/100)^DCF_Base!$C$4:$G$4)+DCF_Base!$B$27/(1+A13/100)^5 | C13: =B13*Assumptions!$B$3
A14: 9.5 | B14: =SUMPRODUCT(DCF_Base!$C$16:$G$16/(1+A14/100)^DCF_Base!$C$4:$G$4)+DCF_Base!$B$27/(1+A14/100)^5 | C14: =B14*Assumptions!$B$3
A15: 10 | B15: =SUMPRODUCT(DCF_Base!$C$16:$G$16/(1+A15/100)^DCF_Base!$C$4:$G$4)+DCF_Base!$B$27/(1+A15/100)^5 | C15: =B15*Assumptions!$B$3
A16: 11 | B16: =SUMPRODUCT(DCF_Base!$C$16:$G$16/(1+A16/100)^DCF_Base!$C$4:$G$4)+DCF_Base!$B$27/(1+A16/100)^5 | C16: =B16*Assumptions!$B$3
A17: 12 | B17: =SUMPRODUCT(DCF_Base!$C$16:$G$16/(1+A17/100)^DCF_Base!$C$4:$G$4)+DCF_Base!$B$27/(1+A17/100)^5 | C17: =B17*Assumptions!$B$3
A18: 15 | B18: =SUMPRODUCT(DCF_Base!$C$16:$G$16/(1+A18/100)^DCF_Base!$C$4:$G$4)+DCF_Base!$B$27/(1+A18/100)^5 | C18: =B18*Assumptions!$B$3
A21: Sensitivity (base case): rows = cost of equity %, columns = exit P/TBV; values NZD
B22: 1.2 | C22: 1.35 | D22: 1.5 | E22: 1.7 | F22: 1.9
A23: 8.5 | B23: =(SUMPRODUCT(DCF_Base!$C$16:$G$16/(1+$A23/100)^DCF_Base!$C$4:$G$4)+B$22*DCF_Base!$G$15/(1+$A23/100)^5)*Assumptions!$B$3 | C23: =(SUMPRODUCT(DCF_Base!$C$16:$G$16/(1+$A23/100)^DCF_Base!$C$4:$G$4)+C$22*DCF_Base!$G$15/(1+$A23/100)^5)*Assumptions!$B$3 | D23: =(SUMPRODUCT(DCF_Base!$C$16:$G$16/(1+$A23/100)^DCF_Base!$C$4:$G$4)+D$22*DCF_Base!$G$15/(1+$A23/100)^5)*Assumptions!$B$3 | E23: =(SUMPRODUCT(DCF_Base!$C$16:$G$16/(1+$A23/100)^DCF_Base!$C$4:$G$4)+E$22*DCF_Base!$G$15/(1+$A23/100)^5)*Assumptions!$B$3 | F23: =(SUMPRODUCT(DCF_Base!$C$16:$G$16/(1+$A23/100)^DCF_Base!$C$4:$G$4)+F$22*DCF_Base!$G$15/(1+$A23/100)^5)*Assumptions!$B$3
A24: 9 | B24: =(SUMPRODUCT(DCF_Base!$C$16:$G$16/(1+$A24/100)^DCF_Base!$C$4:$G$4)+B$22*DCF_Base!$G$15/(1+$A24/100)^5)*Assumptions!$B$3 | C24: =(SUMPRODUCT(DCF_Base!$C$16:$G$16/(1+$A24/100)^DCF_Base!$C$4:$G$4)+C$22*DCF_Base!$G$15/(1+$A24/100)^5)*Assumptions!$B$3 | D24: =(SUMPRODUCT(DCF_Base!$C$16:$G$16/(1+$A24/100)^DCF_Base!$C$4:$G$4)+D$22*DCF_Base!$G$15/(1+$A24/100)^5)*Assumptions!$B$3 | E24: =(SUMPRODUCT(DCF_Base!$C$16:$G$16/(1+$A24/100)^DCF_Base!$C$4:$G$4)+E$22*DCF_Base!$G$15/(1+$A24/100)^5)*Assumptions!$B$3 | F24: =(SUMPRODUCT(DCF_Base!$C$16:$G$16/(1+$A24/100)^DCF_Base!$C$4:$G$4)+F$22*DCF_Base!$G$15/(1+$A24/100)^5)*Assumptions!$B$3
A25: 9.5 | B25: =(SUMPRODUCT(DCF_Base!$C$16:$G$16/(1+$A25/100)^DCF_Base!$C$4:$G$4)+B$22*DCF_Base!$G$15/(1+$A25/100)^5)*Assumptions!$B$3 | C25: =(SUMPRODUCT(DCF_Base!$C$16:$G$16/(1+$A25/100)^DCF_Base!$C$4:$G$4)+C$22*DCF_Base!$G$15/(1+$A25/100)^5)*Assumptions!$B$3 | D25: =(SUMPRODUCT(DCF_Base!$C$16:$G$16/(1+$A25/100)^DCF_Base!$C$4:$G$4)+D$22*DCF_Base!$G$15/(1+$A25/100)^5)*Assumptions!$B$3 | E25: =(SUMPRODUCT(DCF_Base!$C$16:$G$16/(1+$A25/100)^DCF_Base!$C$4:$G$4)+E$22*DCF_Base!$G$15/(1+$A25/100)^5)*Assumptions!$B$3 | F25: =(SUMPRODUCT(DCF_Base!$C$16:$G$16/(1+$A25/100)^DCF_Base!$C$4:$G$4)+F$22*DCF_Base!$G$15/(1+$A25/100)^5)*Assumptions!$B$3
A26: 10 | B26: =(SUMPRODUCT(DCF_Base!$C$16:$G$16/(1+$A26/100)^DCF_Base!$C$4:$G$4)+B$22*DCF_Base!$G$15/(1+$A26/100)^5)*Assumptions!$B$3 | C26: =(SUMPRODUCT(DCF_Base!$C$16:$G$16/(1+$A26/100)^DCF_Base!$C$4:$G$4)+C$22*DCF_Base!$G$15/(1+$A26/100)^5)*Assumptions!$B$3 | D26: =(SUMPRODUCT(DCF_Base!$C$16:$G$16/(1+$A26/100)^DCF_Base!$C$4:$G$4)+D$22*DCF_Base!$G$15/(1+$A26/100)^5)*Assumptions!$B$3 | E26: =(SUMPRODUCT(DCF_Base!$C$16:$G$16/(1+$A26/100)^DCF_Base!$C$4:$G$4)+E$22*DCF_Base!$G$15/(1+$A26/100)^5)*Assumptions!$B$3 | F26: =(SUMPRODUCT(DCF_Base!$C$16:$G$16/(1+$A26/100)^DCF_Base!$C$4:$G$4)+F$22*DCF_Base!$G$15/(1+$A26/100)^5)*Assumptions!$B$3
A27: 11 | B27: =(SUMPRODUCT(DCF_Base!$C$16:$G$16/(1+$A27/100)^DCF_Base!$C$4:$G$4)+B$22*DCF_Base!$G$15/(1+$A27/100)^5)*Assumptions!$B$3 | C27: =(SUMPRODUCT(DCF_Base!$C$16:$G$16/(1+$A27/100)^DCF_Base!$C$4:$G$4)+C$22*DCF_Base!$G$15/(1+$A27/100)^5)*Assumptions!$B$3 | D27: =(SUMPRODUCT(DCF_Base!$C$16:$G$16/(1+$A27/100)^DCF_Base!$C$4:$G$4)+D$22*DCF_Base!$G$15/(1+$A27/100)^5)*Assumptions!$B$3 | E27: =(SUMPRODUCT(DCF_Base!$C$16:$G$16/(1+$A27/100)^DCF_Base!$C$4:$G$4)+E$22*DCF_Base!$G$15/(1+$A27/100)^5)*Assumptions!$B$3 | F27: =(SUMPRODUCT(DCF_Base!$C$16:$G$16/(1+$A27/100)^DCF_Base!$C$4:$G$4)+F$22*DCF_Base!$G$15/(1+$A27/100)^5)*Assumptions!$B$3
