Workbook

Sheet DCF Model
A1: GOOGL DCF Valuation Model
A2: Gray cells are INPUTS - adjust to see valuation change
A4: KEY INPUTS
A5: Current Stock Price | B5: 200
A6: Shares Outstanding (M) | B6: 6694
A7: Cash & Equivalents (M) | B7: 110701
A8: Total Debt (M) | B8: 0
A9: Net Debt (M) | B9: =B8-B7 -> 0
A11: Base Year FCF (M) | B11: 98400
A13: WACC | B13: 0.095
A14: Terminal Growth Rate | B14: 0.025
A16: GROWTH ASSUMPTIONS | B16: Year 1 | C16: Year 2 | D16: Year 3 | E16: Year 4 | F16: Year 5
A17: FCF Growth Rate | B17: 0.18 | C17: 0.16 | D17: 0.14 | E17: 0.12 | F17: 0.1
A19: PROJECTIONS
B20: Base | C20: Year 1 | D20: Year 2 | E20: Year 3 | F20: Year 4 | G20: Year 5
A21: Free Cash Flow | B21: =B11 -> 0 | C21: =B21*(1+B17) -> 0 | D21: =C21*(1+C17) -> 0 | E21: =D21*(1+D17) -> 0 | F21: =E21*(1+E17) -> 0 | G21: =F21*(1+F17) -> 0
A22: Discount Factor | C22: =1/(1+$B$13)^1 -> 0 | D22: =1/(1+$B$13)^2 -> 0 | E22: =1/(1+$B$13)^3 -> 0 | F22: =1/(1+$B$13)^4 -> 0 | G22: =1/(1+$B$13)^5 -> 0
A23: PV of FCF | C23: =C21*C22 -> 0 | D23: =D21*D22 -> 0 | E23: =E21*E22 -> 0 | F23: =F21*F22 -> 0 | G23: =G21*G22 -> 0
A25: VALUATION
A26: Sum of PV of FCF | B26: =SUM(C23:G23) -> 0
A27: Terminal FCF (Year 5 * (1+g)) | B27: =G21*(1+$B$14) -> 0
A28: Terminal Value | B28: =B27/($B$13-$B$14) -> 0
A29: PV of Terminal Value | B29: =B28*G22 -> 0
A30: Enterprise Value | B30: =B26+B29 -> 0
A31: Less: Net Debt | B31: =B9 -> 0
A32: Equity Value | B32: =B30-B31 -> 0
A33: INTRINSIC VALUE/SHARE | B33: =B32/B6 -> 0
A35: ENTRY PRICE (15% CAGR Target)
A36: Terminal Value per Share | B36: =B28/B6 -> 0
A37: Entry Price (15% CAGR) | B37: =B36/(1.15^5) -> 0
A39: Upside to IV | B39: =(B33-B5)/B5 -> 0
A40: Upside to Entry Price | B40: =(B37-B5)/B5 -> 0

Sheet Sensitivity
A1: Sensitivity Analysis
A2: Intrinsic Value by WACC & Terminal Growth
A4: WACC \ Term G | B4: 0.02 | C4: 0.025 | D4: 0.03 | E4: 0.035 | F4: 0.04
A5: 0.08 | B5: =(('DCF Model'!$B$11*(1+'DCF Model'!$B$17)*(1+'DCF Model'!$C$17)*(1+'DCF Model'!$D$17)*(1+'DCF Model'!$E$17)*(1+'DCF Model'!$F$17))*(1+0.02)/(0.08-0.02))/(1+0.08)^5/'DCF Model'!$B$6 -> 0 | C5: =(('DCF Model'!$B$11*(1+'DCF Model'!$B$17)*(1+'DCF Model'!$C$17)*(1+'DCF Model'!$D$17)*(1+'DCF Model'!$E$17)*(1+'DCF Model'!$F$17))*(1+0.025)/(0.08-0.025))/(1+0.08)^5/'DCF Model'!$B$6 -> 0 | D5: =(('DCF Model'!$B$11*(1+'DCF Model'!$B$17)*(1+'DCF Model'!$C$17)*(1+'DCF Model'!$D$17)*(1+'DCF Model'!$E$17)*(1+'DCF Model'!$F$17))*(1+0.03)/(0.08-0.03))/(1+0.08)^5/'DCF Model'!$B$6 -> 0 | E5: =(('DCF Model'!$B$11*(1+'DCF Model'!$B$17)*(1+'DCF Model'!$C$17)*(1+'DCF Model'!$D$17)*(1+'DCF Model'!$E$17)*(1+'DCF Model'!$F$17))*(1+0.035)/(0.08-0.035))/(1+0.08)^5/'DCF Model'!$B$6 -> 0 | F5: =(('DCF Model'!$B$11*(1+'DCF Model'!$B$17)*(1+'DCF Model'!$C$17)*(1+'DCF Model'!$D$17)*(1+'DCF Model'!$E$17)*(1+'DCF Model'!$F$17))*(1+0.04)/(0.08-0.04))/(1+0.08)^5/'DCF Model'!$B$6 -> 0
A6: 0.09 | B6: =(('DCF Model'!$B$11*(1+'DCF Model'!$B$17)*(1+'DCF Model'!$C$17)*(1+'DCF Model'!$D$17)*(1+'DCF Model'!$E$17)*(1+'DCF Model'!$F$17))*(1+0.02)/(0.09-0.02))/(1+0.09)^5/'DCF Model'!$B$6 -> 0 | C6: =(('DCF Model'!$B$11*(1+'DCF Model'!$B$17)*(1+'DCF Model'!$C$17)*(1+'DCF Model'!$D$17)*(1+'DCF Model'!$E$17)*(1+'DCF Model'!$F$17))*(1+0.025)/(0.09-0.025))/(1+0.09)^5/'DCF Model'!$B$6 -> 0 | D6: =(('DCF Model'!$B$11*(1+'DCF Model'!$B$17)*(1+'DCF Model'!$C$17)*(1+'DCF Model'!$D$17)*(1+'DCF Model'!$E$17)*(1+'DCF Model'!$F$17))*(1+0.03)/(0.09-0.03))/(1+0.09)^5/'DCF Model'!$B$6 -> 0 | E6: =(('DCF Model'!$B$11*(1+'DCF Model'!$B$17)*(1+'DCF Model'!$C$17)*(1+'DCF Model'!$D$17)*(1+'DCF Model'!$E$17)*(1+'DCF Model'!$F$17))*(1+0.035)/(0.09-0.035))/(1+0.09)^5/'DCF Model'!$B$6 -> 0 | F6: =(('DCF Model'!$B$11*(1+'DCF Model'!$B$17)*(1+'DCF Model'!$C$17)*(1+'DCF Model'!$D$17)*(1+'DCF Model'!$E$17)*(1+'DCF Model'!$F$17))*(1+0.04)/(0.09-0.04))/(1+0.09)^5/'DCF Model'!$B$6 -> 0
A7: 0.1 | B7: =(('DCF Model'!$B$11*(1+'DCF Model'!$B$17)*(1+'DCF Model'!$C$17)*(1+'DCF Model'!$D$17)*(1+'DCF Model'!$E$17)*(1+'DCF Model'!$F$17))*(1+0.02)/(0.1-0.02))/(1+0.1)^5/'DCF Model'!$B$6 -> 0 | C7: =(('DCF Model'!$B$11*(1+'DCF Model'!$B$17)*(1+'DCF Model'!$C$17)*(1+'DCF Model'!$D$17)*(1+'DCF Model'!$E$17)*(1+'DCF Model'!$F$17))*(1+0.025)/(0.1-0.025))/(1+0.1)^5/'DCF Model'!$B$6 -> 0 | D7: =(('DCF Model'!$B$11*(1+'DCF Model'!$B$17)*(1+'DCF Model'!$C$17)*(1+'DCF Model'!$D$17)*(1+'DCF Model'!$E$17)*(1+'DCF Model'!$F$17))*(1+0.03)/(0.1-0.03))/(1+0.1)^5/'DCF Model'!$B$6 -> 0 | E7: =(('DCF Model'!$B$11*(1+'DCF Model'!$B$17)*(1+'DCF Model'!$C$17)*(1+'DCF Model'!$D$17)*(1+'DCF Model'!$E$17)*(1+'DCF Model'!$F$17))*(1+0.035)/(0.1-0.035))/(1+0.1)^5/'DCF Model'!$B$6 -> 0 | F7: =(('DCF Model'!$B$11*(1+'DCF Model'!$B$17)*(1+'DCF Model'!$C$17)*(1+'DCF Model'!$D$17)*(1+'DCF Model'!$E$17)*(1+'DCF Model'!$F$17))*(1+0.04)/(0.1-0.04))/(1+0.1)^5/'DCF Model'!$B$6 -> 0
A8: 0.11 | B8: =(('DCF Model'!$B$11*(1+'DCF Model'!$B$17)*(1+'DCF Model'!$C$17)*(1+'DCF Model'!$D$17)*(1+'DCF Model'!$E$17)*(1+'DCF Model'!$F$17))*(1+0.02)/(0.11-0.02))/(1+0.11)^5/'DCF Model'!$B$6 -> 0 | C8: =(('DCF Model'!$B$11*(1+'DCF Model'!$B$17)*(1+'DCF Model'!$C$17)*(1+'DCF Model'!$D$17)*(1+'DCF Model'!$E$17)*(1+'DCF Model'!$F$17))*(1+0.025)/(0.11-0.025))/(1+0.11)^5/'DCF Model'!$B$6 -> 0 | D8: =(('DCF Model'!$B$11*(1+'DCF Model'!$B$17)*(1+'DCF Model'!$C$17)*(1+'DCF Model'!$D$17)*(1+'DCF Model'!$E$17)*(1+'DCF Model'!$F$17))*(1+0.03)/(0.11-0.03))/(1+0.11)^5/'DCF Model'!$B$6 -> 0 | E8: =(('DCF Model'!$B$11*(1+'DCF Model'!$B$17)*(1+'DCF Model'!$C$17)*(1+'DCF Model'!$D$17)*(1+'DCF Model'!$E$17)*(1+'DCF Model'!$F$17))*(1+0.035)/(0.11-0.035))/(1+0.11)^5/'DCF Model'!$B$6 -> 0 | F8: =(('DCF Model'!$B$11*(1+'DCF Model'!$B$17)*(1+'DCF Model'!$C$17)*(1+'DCF Model'!$D$17)*(1+'DCF Model'!$E$17)*(1+'DCF Model'!$F$17))*(1+0.04)/(0.11-0.04))/(1+0.11)^5/'DCF Model'!$B$6 -> 0
A9: 0.12 | B9: =(('DCF Model'!$B$11*(1+'DCF Model'!$B$17)*(1+'DCF Model'!$C$17)*(1+'DCF Model'!$D$17)*(1+'DCF Model'!$E$17)*(1+'DCF Model'!$F$17))*(1+0.02)/(0.12-0.02))/(1+0.12)^5/'DCF Model'!$B$6 -> 0 | C9: =(('DCF Model'!$B$11*(1+'DCF Model'!$B$17)*(1+'DCF Model'!$C$17)*(1+'DCF Model'!$D$17)*(1+'DCF Model'!$E$17)*(1+'DCF Model'!$F$17))*(1+0.025)/(0.12-0.025))/(1+0.12)^5/'DCF Model'!$B$6 -> 0 | D9: =(('DCF Model'!$B$11*(1+'DCF Model'!$B$17)*(1+'DCF Model'!$C$17)*(1+'DCF Model'!$D$17)*(1+'DCF Model'!$E$17)*(1+'DCF Model'!$F$17))*(1+0.03)/(0.12-0.03))/(1+0.12)^5/'DCF Model'!$B$6 -> 0 | E9: =(('DCF Model'!$B$11*(1+'DCF Model'!$B$17)*(1+'DCF Model'!$C$17)*(1+'DCF Model'!$D$17)*(1+'DCF Model'!$E$17)*(1+'DCF Model'!$F$17))*(1+0.035)/(0.12-0.035))/(1+0.12)^5/'DCF Model'!$B$6 -> 0 | F9: =(('DCF Model'!$B$11*(1+'DCF Model'!$B$17)*(1+'DCF Model'!$C$17)*(1+'DCF Model'!$D$17)*(1+'DCF Model'!$E$17)*(1+'DCF Model'!$F$17))*(1+0.04)/(0.12-0.04))/(1+0.12)^5/'DCF Model'!$B$6 -> 0

Sheet Historical
A1: Historical Growth Rates
A3: Metric | B3: 3-Year CAGR | C3: 5-Year CAGR
A4: Revenue | B4: 0.1079 | C4: 0.177
A5: EPS | B5: 0.0998 | C5: 0.2632
A6: Equity | B6: 0.078 | C6: 0.091
A7: FCF | B7: 0.1341 | C7: 0.2311
A9: Selected Growth Rate: | B9: 0.2311
A10: Source: | B10: fcf_5yr_cagr

Sheet Scenarios
A1: Scenario Comparison
A2: Base, Bull, and Bear Case Valuations
B4: Bear Case | C4: Base Case | D4: Bull Case
A6: Year 1 Growth | B6: 0.12 | C6: 0.18 | D6: 0.24
A7: Year 5 Growth | B7: 0.05 | C7: 0.1 | D7: 0.15
A8: WACC | B8: 0.105 | C8: 0.095 | D8: 0.09
A9: Terminal Growth | B9: 0.02 | C9: 0.025 | D9: 0.03
A11: VALUATION OUTPUTS
A12: Intrinsic Value per Share | B12: 246.45 | C12: 365.31 | D12: 522.45
A13: Upside from Current | B13: 0.232 | C13: 0.827 | D13: 1.612
A15: Probability Weighted IV | B15: 374.88
A16: Weights: Bear 25%, Base 50%, Bull 25%
