Workbook

Sheet DCF Model
A1: BRK-B - Berkshire Hathaway Inc. - Book Value Compounding Model (Base Case)
A2: Gray cells are INPUTS - adjust to see valuation change. Holdco/insurer model: BVPS compounding + exit P/B, NOT free-cash-flow DCF.
A4: KEY INPUTS
A5: Current Stock Price | B5: 505.48
A6: Shares Outstanding (M, B-equivalent) | B6: 2136.6
A7: Cash & Equivalents (US$M, parent BS line only) | B7: 40609
A8: Total Debt (US$M) | B8: n/a - not used (net_debt held at 0)
A9: Net Debt (US$M) | B9: 0
A10: Starting BVPS (Q2 2026) | B10: 351.11
A11: Annual Dividend per Share | B11: 0
A13: Cost of Equity (Base) | B13: 0.085
A14: Exit Price-to-Book (Base) | B14: 1.35
A16: GROWTH ASSUMPTIONS (BVPS growth; no dividend to add back)
B17: Year 1 | C17: Year 2 | D17: Year 3 | E17: Year 4 | F17: Year 5
A18: BVPS Growth Rate | B18: 0.095 | C18: 0.09 | D18: 0.085 | E18: 0.08 | F18: 0.08
A20: PROJECTIONS
B21: Base Yr | C21: Year 1 | D21: Year 2 | E21: Year 3 | F21: Year 4 | G21: Year 5
A22: Book Value per Share | B22: =B10 -> 351.11 | C22: =B22*(1+B18)-$B$11 -> 384.46545 | D22: =C22*(1+C18)-$B$11 -> 419.06734 | E22: =D22*(1+D18)-$B$11 -> 454.68806 | F22: =E22*(1+E18)-$B$11 -> 491.06311 | G22: =F22*(1+F18)-$B$11 -> 530.34816
A23: Dividend per Share | C23: =$B$11 -> 0 | D23: =$B$11 -> 0 | E23: =$B$11 -> 0 | F23: =$B$11 -> 0 | G23: =$B$11 -> 0
A24: Discount Factor (Cost of Equity) | C24: =1/(1+$B$13)^1 -> 0.92165899 | D24: =1/(1+$B$13)^2 -> 0.84945529 | E24: =1/(1+$B$13)^3 -> 0.7829081 | F24: =1/(1+$B$13)^4 -> 0.72157428 | G24: =1/(1+$B$13)^5 -> 0.66504542
A25: PV of Dividend | C25: =C23*C24 -> 0 | D25: =D23*D24 -> 0 | E25: =E23*E24 -> 0 | F25: =F23*F24 -> 0 | G25: =G23*G24 -> 0
A27: VALUATION
A28: Sum of PV of Dividends | B28: =SUM(C25:G25) -> 0
A29: Terminal BVPS (Year 5) | B29: =G22 -> 530.34816
A30: Exit Price-to-Book Multiple | B30: =B14 -> 1.35
A31: Terminal Value per Share | B31: =B29*B30 -> 715.97001
A32: PV of Terminal Value | B32: =B31*G24 -> 476.15258
A33: INTRINSIC VALUE / SHARE | B33: =B28+B32 -> 476.15258
A34: Upside / (Downside) vs Current Price | B34: =(B33-B5)/B5 -> -0.058018951
A36: ENTRY PRICE (15% CAGR Target)
A37: Target CAGR | B37: 0.15
A38: Reinvested Dividends FV (at target CAGR, to Yr 5) | B38: =C23*(1+$B$37)^4+D23*(1+$B$37)^3+E23*(1+$B$37)^2+F23*(1+$B$37)^1+G23*(1+$B$37)^0 -> 0
A39: Total Year-5 Value (Terminal Value + Reinvested Divs) | B39: =B31+B38 -> 715.97001
A40: Entry Price (15% CAGR) | B40: =B39/(1+$B$37)^5 -> 355.96363
A41: Current Price vs Entry Price | B41: =(B5-B40)/B5 -> 0.29579086
A43: Note: Berkshire pays no dividend, so dividend rows are zero and all scenario value sits in the
A44: terminal BVPS x exit-P/B leg, discounted at COST OF EQUITY (equity-holder view), not WACC -
A45: this is a per-share valuation, not enterprise value. See BRK-B_DCF.json inputs.notes for the
A46: shares-outstanding data gap and model-choice rationale.

Sheet Bull-Bear Scenarios
A1: Bull / Bear Scenario Detail
A3: BULL CASE
A4: Cost of Equity | B4: 0.075
A5: Exit Price-to-Book | B5: 1.55
B6: Year 1 | C6: Year 2 | D6: Year 3 | E6: Year 4 | F6: Year 5
A7: BVPS Growth Rate | B7: 0.12 | C7: 0.115 | D7: 0.11 | E7: 0.105 | F7: 0.1
A8: BVPS | B8: ='DCF Model'!$B$10 -> 351.11 | C8: =B8*(1+B7)-'DCF Model'!$B$11 -> 393.2432 | D8: =C8*(1+C7)-'DCF Model'!$B$11 -> 438.46617 | E8: =D8*(1+D7)-'DCF Model'!$B$11 -> 486.69745 | F8: =E8*(1+E7)-'DCF Model'!$B$11 -> 537.80068 | G8: =F8*(1+F7)-'DCF Model'!$B$11 -> 591.58075
A9: Dividend per Share | C9: ='DCF Model'!$B$11 -> 0 | D9: ='DCF Model'!$B$11 -> 0 | E9: ='DCF Model'!$B$11 -> 0 | F9: ='DCF Model'!$B$11 -> 0 | G9: ='DCF Model'!$B$11 -> 0
A10: Discount Factor | C10: =1/(1+B4)^1 -> 0.93023256 | D10: =1/(1+B4)^2 -> 0.86533261 | E10: =1/(1+B4)^3 -> 0.80496057 | F10: =1/(1+B4)^4 -> 0.74880053 | G10: =1/(1+B4)^5 -> 0.69655863
A11: PV of Dividend | C11: =C9*C10 -> 0 | D11: =D9*D10 -> 0 | E11: =E9*E10 -> 0 | F11: =F9*F10 -> 0 | G11: =G9*G10 -> 0
A13: Sum PV of Dividends | B13: =SUM(C11:G11) -> 0
A14: Terminal BVPS (Yr 5) | B14: =G8 -> 591.58075
A15: Terminal Value per Share | B15: =B14*B5 -> 916.95016
A16: PV of Terminal Value | B16: =B15*G10 -> 638.70955
A17: INTRINSIC VALUE / SHARE | B17: =B13+B16 -> 638.70955
A18: Upside / (Downside) | B18: =(B17-'DCF Model'!$B$5)/'DCF Model'!$B$5 -> 0.26357036
A20: BEAR CASE
A21: Cost of Equity | B21: 0.1
A22: Exit Price-to-Book | B22: 1.15
B23: Year 1 | C23: Year 2 | D23: Year 3 | E23: Year 4 | F23: Year 5
A24: BVPS Growth Rate | B24: 0.07 | C24: 0.065 | D24: 0.06 | E24: 0.06 | F24: 0.06
A25: BVPS | B25: ='DCF Model'!$B$10 -> 351.11 | C25: =B25*(1+B24)-'DCF Model'!$B$11 -> 375.6877 | D25: =C25*(1+C24)-'DCF Model'!$B$11 -> 400.1074 | E25: =D25*(1+D24)-'DCF Model'!$B$11 -> 424.11384 | F25: =E25*(1+E24)-'DCF Model'!$B$11 -> 449.56068 | G25: =F25*(1+F24)-'DCF Model'!$B$11 -> 476.53432
A26: Dividend per Share | C26: ='DCF Model'!$B$11 -> 0 | D26: ='DCF Model'!$B$11 -> 0 | E26: ='DCF Model'!$B$11 -> 0 | F26: ='DCF Model'!$B$11 -> 0 | G26: ='DCF Model'!$B$11 -> 0
A27: Discount Factor | C27: =1/(1+B21)^1 -> 0.90909091 | D27: =1/(1+B21)^2 -> 0.82644628 | E27: =1/(1+B21)^3 -> 0.7513148 | F27: =1/(1+B21)^4 -> 0.68301346 | G27: =1/(1+B21)^5 -> 0.62092132
A28: PV of Dividend | C28: =C26*C27 -> 0 | D28: =D26*D27 -> 0 | E28: =E26*E27 -> 0 | F28: =F26*F27 -> 0 | G28: =G26*G27 -> 0
A30: Sum PV of Dividends | B30: =SUM(C28:G28) -> 0
A31: Terminal BVPS (Yr 5) | B31: =G25 -> 476.53432
A32: Terminal Value per Share | B32: =B31*B22 -> 548.01446
A33: PV of Terminal Value | B33: =B32*G27 -> 340.27387
A34: INTRINSIC VALUE / SHARE | B34: =B30+B33 -> 340.27387
A35: Upside / (Downside) | B35: =(B34-'DCF Model'!$B$5)/'DCF Model'!$B$5 -> -0.32683021

Sheet Sensitivity
A1: Sensitivity Analysis
A2: Intrinsic Value/Share by BVPS Growth Rate (avg, base 5yr path shifted uniformly) & Exit Price-to-Book
A4: Growth \ Exit P/B | B4: 1.05 | C4: 1.2 | D4: 1.35 | E4: 1.5 | F4: 1.65
A5: 0.046 | B5: =('DCF Model'!$B$10*(1+0.055))*(1+0.05)*(1+0.045)*(1+0.04)*(1+0.04)*1.05*(1/(1+0.085)^5) -> 306.97891 | C5: =('DCF Model'!$B$10*(1+0.055))*(1+0.05)*(1+0.045)*(1+0.04)*(1+0.04)*1.2*(1/(1+0.085)^5) -> 350.83304 | D5: =('DCF Model'!$B$10*(1+0.055))*(1+0.05)*(1+0.045)*(1+0.04)*(1+0.04)*1.35*(1/(1+0.085)^5) -> 394.68717 | E5: =('DCF Model'!$B$10*(1+0.055))*(1+0.05)*(1+0.045)*(1+0.04)*(1+0.04)*1.5*(1/(1+0.085)^5) -> 438.54129 | F5: =('DCF Model'!$B$10*(1+0.055))*(1+0.05)*(1+0.045)*(1+0.04)*(1+0.04)*1.65*(1/(1+0.085)^5) -> 482.39542
A6: 0.066 | B6: =('DCF Model'!$B$10*(1+0.075))*(1+0.07)*(1+0.065)*(1+0.06)*(1+0.06)*1.05*(1/(1+0.085)^5) -> 337.47172 | C6: =('DCF Model'!$B$10*(1+0.075))*(1+0.07)*(1+0.065)*(1+0.06)*(1+0.06)*1.2*(1/(1+0.085)^5) -> 385.68197 | D6: =('DCF Model'!$B$10*(1+0.075))*(1+0.07)*(1+0.065)*(1+0.06)*(1+0.06)*1.35*(1/(1+0.085)^5) -> 433.89221 | E6: =('DCF Model'!$B$10*(1+0.075))*(1+0.07)*(1+0.065)*(1+0.06)*(1+0.06)*1.5*(1/(1+0.085)^5) -> 482.10246 | F6: =('DCF Model'!$B$10*(1+0.075))*(1+0.07)*(1+0.065)*(1+0.06)*(1+0.06)*1.65*(1/(1+0.085)^5) -> 530.31271
A7: 0.086 | B7: =('DCF Model'!$B$10*(1+0.095))*(1+0.09)*(1+0.085)*(1+0.08)*(1+0.08)*1.05*(1/(1+0.085)^5) -> 370.3409 | C7: =('DCF Model'!$B$10*(1+0.095))*(1+0.09)*(1+0.085)*(1+0.08)*(1+0.08)*1.2*(1/(1+0.085)^5) -> 423.24674 | D7: =('DCF Model'!$B$10*(1+0.095))*(1+0.09)*(1+0.085)*(1+0.08)*(1+0.08)*1.35*(1/(1+0.085)^5) -> 476.15258 | E7: =('DCF Model'!$B$10*(1+0.095))*(1+0.09)*(1+0.085)*(1+0.08)*(1+0.08)*1.5*(1/(1+0.085)^5) -> 529.05842 | F7: =('DCF Model'!$B$10*(1+0.095))*(1+0.09)*(1+0.085)*(1+0.08)*(1+0.08)*1.65*(1/(1+0.085)^5) -> 581.96427
A8: 0.106 | B8: =('DCF Model'!$B$10*(1+0.115))*(1+0.11)*(1+0.105)*(1+0.1)*(1+0.1)*1.05*(1/(1+0.085)^5) -> 405.72269 | C8: =('DCF Model'!$B$10*(1+0.115))*(1+0.11)*(1+0.105)*(1+0.1)*(1+0.1)*1.2*(1/(1+0.085)^5) -> 463.68308 | D8: =('DCF Model'!$B$10*(1+0.115))*(1+0.11)*(1+0.105)*(1+0.1)*(1+0.1)*1.35*(1/(1+0.085)^5) -> 521.64346 | E8: =('DCF Model'!$B$10*(1+0.115))*(1+0.11)*(1+0.105)*(1+0.1)*(1+0.1)*1.5*(1/(1+0.085)^5) -> 579.60385 | F8: =('DCF Model'!$B$10*(1+0.115))*(1+0.11)*(1+0.105)*(1+0.1)*(1+0.1)*1.65*(1/(1+0.085)^5) -> 637.56423
A9: 0.126 | B9: =('DCF Model'!$B$10*(1+0.135))*(1+0.13)*(1+0.125)*(1+0.12)*(1+0.12)*1.05*(1/(1+0.085)^5) -> 443.75849 | C9: =('DCF Model'!$B$10*(1+0.135))*(1+0.13)*(1+0.125)*(1+0.12)*(1+0.12)*1.2*(1/(1+0.085)^5) -> 507.15257 | D9: =('DCF Model'!$B$10*(1+0.135))*(1+0.13)*(1+0.125)*(1+0.12)*(1+0.12)*1.35*(1/(1+0.085)^5) -> 570.54664 | E9: =('DCF Model'!$B$10*(1+0.135))*(1+0.13)*(1+0.125)*(1+0.12)*(1+0.12)*1.5*(1/(1+0.085)^5) -> 633.94071 | F9: =('DCF Model'!$B$10*(1+0.135))*(1+0.13)*(1+0.125)*(1+0.12)*(1+0.12)*1.65*(1/(1+0.085)^5) -> 697.33478
A11: Note: Cost of equity held at base case (8.5%). Rows = average annual BVPS growth rate over the 5-yr
A12: path (base path shifted uniformly -4pp to +4pp). Columns = exit price-to-book multiple applied to Year-5 BVPS.
A13: No dividend term (Berkshire pays none), so this is pure terminal-value-at-exit-multiple, discounted at cost of equity.

Sheet Historical
A1: Historical Growth Rates
A3: Metric | B3: 3-Year CAGR | C3: 5-Year CAGR / Other
A4: Shareholders' Equity (BVPS proxy) | B4: 0.1432 | C4: 0.101
A5: Shareholders' Equity (10yr) | C5: 0.1082
A6: Shareholders' Equity (17yr, 2008-2025) | C6: 0.1147
A7: Equity TTM growth (Q2-25 to Q2-26) | C7: 0.1192
A8: Revenue | B8: 0.0065 | C8: 0.0862
A11: Selected Growth Rate (base anchor, Year 1): | B11: 0.095
A12: Source: | B12: equity_5yr_cagr, blended toward equity_3yr_cagr
A14: Growth Divergence Warning:
A15: Revenue growth (0.65% 3yr CAGR) diverges sharply from equity/BVPS growth (14.3% 3yr CAGR). This is
A16: EXPECTED for Berkshire, not a red flag: book value compounds from retained earnings, underwriting
A17: profit and investment gains, not top-line growth. Revenue CAGR is not a relevant proxy here.
A19: Data Gap Note:
A20: SEC XBRL share-count tags are unreliable for BRK-B post-2011 (dual-class Class A/B collapse),
A21: so historical BVPS-per-share cannot be cleanly reconstructed. Shareholders'-equity YoY growth is
A22: used as the BVPS-growth proxy; buybacks are confirmed immaterial (<1.2% of book value annualized
A23: in H1 2026), so equity growth and true BVPS growth should not differ materially in any given year.
A25: Shareholders' Equity by Fiscal Year (US$M)
A26: Period | B26: Equity (US$M)
A27: FY2008 | B27: 113707
A28: FY2009 | B28: 135785
A29: FY2010 | B29: 162934
A30: FY2011 | B30: 168961
A31: FY2012 | B31: 191588
A32: FY2013 | B32: 224485
A33: FY2014 | B33: 242096
A34: FY2015 | B34: 257696
A35: FY2016 | B35: 285428
A36: FY2017 | B36: 351954
A37: FY2018 | B37: 352500
A38: FY2019 | B38: 428563
... A45: Q2 2026 | B45: 750177

Sheet Sanity Check
A1: Sanity Check - Historical P/B Cross-Reference
A3: Base Intrinsic Value / Share | B3: ='DCF Model'!B33 -> 476.15258
A4: Implied P/B (Base IV / Q2-2026 BVPS) | B4: =B3/'DCF Model'!B10 -> 1.3561351
A5: Normalized EPS (illustrative, GAAP net income highly volatile) | B5: n/a - GAAP EPS not used (mark-to-market noise)
A8: Historical / Recent P/B Reference Points
A9: Buyback-comfort floor (management signaled, 2026) | B9: 1.1
A10: Post-2018 trading range - low | B10: 1.3
A11: Post-2018 trading range - high | B11: 1.6
A12: Current (Q2 2026 BVPS basis) | B12: ='DCF Model'!B5/'DCF Model'!B10 -> 1.4396628
A14: Sanity Check Passed: | B14: YES
A16: Diagnosis:
A17: Base-case intrinsic value implies an exit P/B of 1.35x on Year-5 BVPS, inside the post-2018 trading
A18: range (1.3x-1.6x) and above management's signaled buyback-comfort floor (~1.1x). Current price
A19: sits at ~1.44x Q2-2026 book, i.e. between the buyback floor and the top of the historical range -
A20: consistent with a modest single-digit downside in the base case, not a mispricing signal either way.
A21: scripts/sanity_check.py correctly detects model='book_value' and does not apply owner-FCF P/E,
A22: P/B or P/Sales multiple trip rules to this ticker (exit code 0, passed=null, rules_not_evaluated).
