Workbook

Sheet Summary
A1: CBA.AX residual income on tangible book
A2: Price (AUD) | B2: 152.33
A3: Shares (m) | B3: 1674
A4: Total equity 30-Jun-26 | B4: 78704
A5: Intangibles + goodwill | B5: 8515
A6: Tangible book | B6: =B4-B5
A7: TBV per share | B7: =B6/B3
A9: Scenario | B9: IV / share | C9: Weight | D9: Upside % | E9: Entry @15%
A10: bear | B10: ='Bear'!B24 | C10: 0.25 | D10: =B10/$B$2-1 | E10: 35.03
A11: base | B11: ='Base'!B24 | C11: 0.5 | D11: =B11/$B$2-1 | E11: 42.55
A12: bull | B12: ='Bull'!B24 | C12: 0.25 | D12: =B12/$B$2-1 | E12: 48.57
A13: Weighted IV | B13: =SUMPRODUCT(B10:B12,C10:C12) | D13: =B13/B2-1 | E13: =SUMPRODUCT(E10:E12,C10:C12)
A15: Market P/TBV | B15: =B2/B7
A16: Market P/E (FY26 cash EPS) | B16: =B2/6.569
A17: Market-implied cost of equity % (base flows) | B17: 6.47

Sheet Base
A1: base scenario
A2: Cost of equity % | B2: 9.5
A3: Terminal RI growth % | B3: 3
A4: Payout ratio % | B4: 75
A5: Opening TBV (m) | B5: =Summary!B6
A6: Shares (m) | B6: =Summary!B3
A8: Year | B8: FY2027 | C8: FY2028 | D8: FY2029 | E8: FY2030 | F8: FY2031 | G8: FY2032 | H8: FY2033 | I8: FY2034 | J8: FY2035 | K8: FY2036
A9: ROTE % | B9: 15.5 | C9: 15.5 | D9: 15.5 | E9: 15.3 | F9: 15.2 | G9: 15 | H9: 15 | I9: 15 | J9: 15 | K9: 15
A10: Opening TBV | B10: =$B$5 | C10: =B13 | D10: =C13 | E10: =D13 | F10: =E13 | G10: =F13 | H10: =G13 | I10: =H13 | J10: =I13 | K10: =J13
A11: NPAT | B11: =B9/100*B10 | C11: =C9/100*C10 | D11: =D9/100*D10 | E11: =E9/100*E10 | F11: =F9/100*F10 | G11: =G9/100*G10 | H11: =H9/100*H10 | I11: =I9/100*I10 | ... K11: =K9/100*K10
A12: Dividends | B12: =$B$4/100*B11 | C12: =$B$4/100*C11 | D12: =$B$4/100*D11 | E12: =$B$4/100*E11 | F12: =$B$4/100*F11 | G12: =$B$4/100*G11 | H12: =$B$4/100*H11 | I12: =$B$4/100*I11 | ... K12: =$B$4/100*K11
A13: Closing TBV | B13: =B10+B11-B12 | C13: =C10+C11-C12 | D13: =D10+D11-D12 | E13: =E10+E11-E12 | F13: =F10+F11-F12 | G13: =G10+G11-G12 | H13: =H10+H11-H12 | I13: =I10+I11-I12 | ... K13: =K10+K11-K12
A14: Residual income | B14: =B11-$B$2/100*B10 | C14: =C11-$B$2/100*C10 | D14: =D11-$B$2/100*D10 | E14: =E11-$B$2/100*E10 | F14: =F11-$B$2/100*F10 | G14: =G11-$B$2/100*G10 | H14: =H11-$B$2/100*H10 | I14: =I11-$B$2/100*I10 | ... K14: =K11-$B$2/100*K10
A15: Discount factor | B15: =1/(1+$B$2/100)^1 | C15: =1/(1+$B$2/100)^2 | D15: =1/(1+$B$2/100)^3 | E15: =1/(1+$B$2/100)^4 | F15: =1/(1+$B$2/100)^5 | G15: =1/(1+$B$2/100)^6 | H15: =1/(1+$B$2/100)^7 | I15: =1/(1+$B$2/100)^8 | J15: =1/(1+$B$2/100)^9 | K15: =1/(1+$B$2/100)^10
A16: PV residual income | B16: =B14*B15 | C16: =C14*C15 | D16: =D14*D15 | E16: =E14*E15 | F16: =F14*F15 | G16: =G14*G15 | H16: =H14*H15 | I16: =I14*I15 | ... K16: =K14*K15
A17: EPS | B17: =B11/$B$6 | C17: =C11/$B$6 | D17: =D11/$B$6 | E17: =E11/$B$6 | F17: =F11/$B$6 | G17: =G11/$B$6 | H17: =H11/$B$6 | I17: =I11/$B$6 | ... K17: =K11/$B$6
A18: DPS | B18: =B12/$B$6 | C18: =C12/$B$6 | D18: =D12/$B$6 | E18: =E12/$B$6 | F18: =F12/$B$6 | G18: =G12/$B$6 | H18: =H12/$B$6 | I18: =I12/$B$6 | ... K18: =K12/$B$6
A20: Sum PV residual income | B20: =SUM(B16:K16)
A21: Terminal RI value | B21: =K14*(1+B3/100)/(B2/100-B3/100)
A22: PV terminal | B22: =B21*K15
A23: Equity value (m) | B23: =B5+B20+B22
A24: Intrinsic value / share | B24: =B23/B6
A25: Implied P/TBV | B25: =B24/(B5/B6)
A26: Implied P/E on FY27 EPS | B26: =B24/B17
A27: Python check IV | B27: 80.05

Sheet Bull
A1: bull scenario
A2: Cost of equity % | B2: 9
A3: Terminal RI growth % | B3: 3.5
A4: Payout ratio % | B4: 75
A5: Opening TBV (m) | B5: =Summary!B6
A6: Shares (m) | B6: =Summary!B3
A8: Year | B8: FY2027 | C8: FY2028 | D8: FY2029 | E8: FY2030 | F8: FY2031 | G8: FY2032 | H8: FY2033 | I8: FY2034 | J8: FY2035 | K8: FY2036
A9: ROTE % | B9: 15.8 | C9: 16.2 | D9: 16.5 | E9: 16.8 | F9: 17 | G9: 17 | H9: 17 | I9: 17 | J9: 17 | K9: 17
A10: Opening TBV | B10: =$B$5 | C10: =B13 | D10: =C13 | E10: =D13 | F10: =E13 | G10: =F13 | H10: =G13 | I10: =H13 | J10: =I13 | K10: =J13
A11: NPAT | B11: =B9/100*B10 | C11: =C9/100*C10 | D11: =D9/100*D10 | E11: =E9/100*E10 | F11: =F9/100*F10 | G11: =G9/100*G10 | H11: =H9/100*H10 | I11: =I9/100*I10 | ... K11: =K9/100*K10
A12: Dividends | B12: =$B$4/100*B11 | C12: =$B$4/100*C11 | D12: =$B$4/100*D11 | E12: =$B$4/100*E11 | F12: =$B$4/100*F11 | G12: =$B$4/100*G11 | H12: =$B$4/100*H11 | I12: =$B$4/100*I11 | ... K12: =$B$4/100*K11
A13: Closing TBV | B13: =B10+B11-B12 | C13: =C10+C11-C12 | D13: =D10+D11-D12 | E13: =E10+E11-E12 | F13: =F10+F11-F12 | G13: =G10+G11-G12 | H13: =H10+H11-H12 | I13: =I10+I11-I12 | ... K13: =K10+K11-K12
A14: Residual income | B14: =B11-$B$2/100*B10 | C14: =C11-$B$2/100*C10 | D14: =D11-$B$2/100*D10 | E14: =E11-$B$2/100*E10 | F14: =F11-$B$2/100*F10 | G14: =G11-$B$2/100*G10 | H14: =H11-$B$2/100*H10 | I14: =I11-$B$2/100*I10 | ... K14: =K11-$B$2/100*K10
A15: Discount factor | B15: =1/(1+$B$2/100)^1 | C15: =1/(1+$B$2/100)^2 | D15: =1/(1+$B$2/100)^3 | E15: =1/(1+$B$2/100)^4 | F15: =1/(1+$B$2/100)^5 | G15: =1/(1+$B$2/100)^6 | H15: =1/(1+$B$2/100)^7 | I15: =1/(1+$B$2/100)^8 | J15: =1/(1+$B$2/100)^9 | K15: =1/(1+$B$2/100)^10
A16: PV residual income | B16: =B14*B15 | C16: =C14*C15 | D16: =D14*D15 | E16: =E14*E15 | F16: =F14*F15 | G16: =G14*G15 | H16: =H14*H15 | I16: =I14*I15 | ... K16: =K14*K15
A17: EPS | B17: =B11/$B$6 | C17: =C11/$B$6 | D17: =D11/$B$6 | E17: =E11/$B$6 | F17: =F11/$B$6 | G17: =G11/$B$6 | H17: =H11/$B$6 | I17: =I11/$B$6 | ... K17: =K11/$B$6
A18: DPS | B18: =B12/$B$6 | C18: =C12/$B$6 | D18: =D12/$B$6 | E18: =E12/$B$6 | F18: =F12/$B$6 | G18: =G12/$B$6 | H18: =H12/$B$6 | I18: =I12/$B$6 | ... K18: =K12/$B$6
A20: Sum PV residual income | B20: =SUM(B16:K16)
A21: Terminal RI value | B21: =K14*(1+B3/100)/(B2/100-B3/100)
A22: PV terminal | B22: =B21*K15
A23: Equity value (m) | B23: =B5+B20+B22
A24: Intrinsic value / share | B24: =B23/B6
A25: Implied P/TBV | B25: =B24/(B5/B6)
A26: Implied P/E on FY27 EPS | B26: =B24/B17
A27: Python check IV | B27: 104.72

Sheet Bear
A1: bear scenario
A2: Cost of equity % | B2: 10.5
A3: Terminal RI growth % | B3: 2.5
A4: Payout ratio % | B4: 80
A5: Opening TBV (m) | B5: =Summary!B6
A6: Shares (m) | B6: =Summary!B3
A8: Year | B8: FY2027 | C8: FY2028 | D8: FY2029 | E8: FY2030 | F8: FY2031 | G8: FY2032 | H8: FY2033 | I8: FY2034 | J8: FY2035 | K8: FY2036
A9: ROTE % | B9: 15 | C9: 14 | D9: 13 | E9: 12.5 | F9: 12.5 | G9: 12.5 | H9: 12.5 | I9: 12.5 | J9: 12.5 | K9: 12.5
A10: Opening TBV | B10: =$B$5 | C10: =B13 | D10: =C13 | E10: =D13 | F10: =E13 | G10: =F13 | H10: =G13 | I10: =H13 | J10: =I13 | K10: =J13
A11: NPAT | B11: =B9/100*B10 | C11: =C9/100*C10 | D11: =D9/100*D10 | E11: =E9/100*E10 | F11: =F9/100*F10 | G11: =G9/100*G10 | H11: =H9/100*H10 | I11: =I9/100*I10 | ... K11: =K9/100*K10
A12: Dividends | B12: =$B$4/100*B11 | C12: =$B$4/100*C11 | D12: =$B$4/100*D11 | E12: =$B$4/100*E11 | F12: =$B$4/100*F11 | G12: =$B$4/100*G11 | H12: =$B$4/100*H11 | I12: =$B$4/100*I11 | ... K12: =$B$4/100*K11
A13: Closing TBV | B13: =B10+B11-B12 | C13: =C10+C11-C12 | D13: =D10+D11-D12 | E13: =E10+E11-E12 | F13: =F10+F11-F12 | G13: =G10+G11-G12 | H13: =H10+H11-H12 | I13: =I10+I11-I12 | ... K13: =K10+K11-K12
A14: Residual income | B14: =B11-$B$2/100*B10 | C14: =C11-$B$2/100*C10 | D14: =D11-$B$2/100*D10 | E14: =E11-$B$2/100*E10 | F14: =F11-$B$2/100*F10 | G14: =G11-$B$2/100*G10 | H14: =H11-$B$2/100*H10 | I14: =I11-$B$2/100*I10 | ... K14: =K11-$B$2/100*K10
A15: Discount factor | B15: =1/(1+$B$2/100)^1 | C15: =1/(1+$B$2/100)^2 | D15: =1/(1+$B$2/100)^3 | E15: =1/(1+$B$2/100)^4 | F15: =1/(1+$B$2/100)^5 | G15: =1/(1+$B$2/100)^6 | H15: =1/(1+$B$2/100)^7 | I15: =1/(1+$B$2/100)^8 | J15: =1/(1+$B$2/100)^9 | K15: =1/(1+$B$2/100)^10
A16: PV residual income | B16: =B14*B15 | C16: =C14*C15 | D16: =D14*D15 | E16: =E14*E15 | F16: =F14*F15 | G16: =G14*G15 | H16: =H14*H15 | I16: =I14*I15 | ... K16: =K14*K15
A17: EPS | B17: =B11/$B$6 | C17: =C11/$B$6 | D17: =D11/$B$6 | E17: =E11/$B$6 | F17: =F11/$B$6 | G17: =G11/$B$6 | H17: =H11/$B$6 | I17: =I11/$B$6 | ... K17: =K11/$B$6
A18: DPS | B18: =B12/$B$6 | C18: =C12/$B$6 | D18: =D12/$B$6 | E18: =E12/$B$6 | F18: =F12/$B$6 | G18: =G12/$B$6 | H18: =H12/$B$6 | I18: =I12/$B$6 | ... K18: =K12/$B$6
A20: Sum PV residual income | B20: =SUM(B16:K16)
A21: Terminal RI value | B21: =K14*(1+B3/100)/(B2/100-B3/100)
A22: PV terminal | B22: =B21*K15
A23: Equity value (m) | B23: =B5+B20+B22
A24: Intrinsic value / share | B24: =B23/B6
A25: Implied P/TBV | B25: =B24/(B5/B6)
A26: Implied P/E on FY27 EPS | B26: =B24/B17
A27: Python check IV | B27: 54.14

Sheet Sensitivity
A1: Base IV/share: cost of equity (rows) x terminal RI growth (cols); computed values
B2: 2 | C2: 2.5 | D2: 3 | E2: 3.5 | F2: 4
A3: 8.5 | B3: 89.9 | C3: 92.25 | D3: 95.02 | E3: 98.35 | F3: 102.42
A4: 9 | B4: 83.05 | C4: 84.83 | D4: 86.91 | E4: 89.36 | F4: 92.31
A5: 9.5 | B5: 77.12 | C5: 78.48 | D5: 80.05 | E5: 81.88 | F5: 84.04
A6: 10 | B6: 71.95 | C6: 72.99 | D6: 74.18 | E6: 75.54 | F6: 77.14
A7: 10.5 | B7: 67.41 | C7: 68.2 | D7: 69.09 | E7: 70.12 | F7: 71.3
A10: Required return (base)
A11: return % | B11: 9 | C11: 10 | D11: 11 | E11: 12 | F11: 15
A12: value / share | B12: 86.91 | C12: 74.18 | D12: 64.65 | E12: 57.26 | F12: 42.55
