Workbook

Sheet Inputs
A1: Ticker | B1: BEN.AX
A2: Valuation date | B2: 2026-09-21
A3: Current price (AUD) | B3: 10.5
A4: Shares on issue (m, 30-Jun-26) | B4: 577.15
A5: Tangible book value (A$m, 30-Jun-26) | B5: 5306.5
A6: Book value (A$m) | B6: 6734.5
A7: Goodwill & intangibles (A$m) | B7: 1428
A8: FY26 cash earnings (A$m) | B8: 530.2
A9: FY26 cash ROTE (%) | B9: 10.1
A10: FY26 DPS (A$) | B10: 0.63
A11: Hurdle rate | B11: 0.15
A12: Weight bear | B12: 0.25
A13: Weight base | B13: 0.5
A14: Weight bull | B14: 0.25

Sheet Base
A1: Base scenario -- residual income on tangible book (A$m)
A2: Cost of equity (%) | B2: 10
A3: Terminal growth of RI (%) | B3: 3
A4: Dividend payout (% of cash earnings) | B4: 68
A6: Year | B6: Y1 FY27 (Jul26-Jun27) | C6: Y2 FY28 | D6: Y3 FY29 | E6: Y4 FY30 | F6: Y5 FY31
A7: Period index | B7: 1 | C7: 2 | D7: 3 | E7: 4 | F7: 5
A8: ROTE (%) | B8: 10.3 | C8: 10.6 | D8: 10.8 | E8: 11 | F8: 11
A9: One-offs after tax | B9: 80 | C9: 50 | D9: 30 | E9: 15 | F9: 15
A10: TBV opening | B10: =Inputs!$B$5 | C10: =B15 | D10: =C15 | E10: =D15 | F10: =E15
A11: Cash earnings | B11: =B8/100*B10 | C11: =C8/100*C10 | D11: =D8/100*D10 | E11: =E8/100*E10 | F11: =F8/100*F10
A12: Net income | B12: =B11-B9 | C12: =C11-C9 | D12: =D11-D9 | E12: =E11-E9 | F12: =F11-F9
A13: Dividends | B13: =$B$4/100*B11 | C13: =$B$4/100*C11 | D13: =$B$4/100*D11 | E13: =$B$4/100*E11 | F13: =$B$4/100*F11
A14: Retained | B14: =B12-B13 | C14: =C12-C13 | D14: =D12-D13 | E14: =E12-E13 | F14: =F12-F13
A15: TBV closing | B15: =B10+B14 | C15: =C10+C14 | D15: =D10+D14 | E15: =E10+E14 | F15: =F10+F14
A16: Equity charge | B16: =$B$2/100*B10 | C16: =$B$2/100*C10 | D16: =$B$2/100*D10 | E16: =$B$2/100*E10 | F16: =$B$2/100*F10
A17: Residual income | B17: =B12-B16 | C17: =C12-C16 | D17: =D12-D16 | E17: =E12-E16 | F17: =F12-F16
A18: Discount factor | B18: =1/(1+$B$2/100)^B7 | C18: =1/(1+$B$2/100)^C7 | D18: =1/(1+$B$2/100)^D7 | E18: =1/(1+$B$2/100)^E7 | F18: =1/(1+$B$2/100)^F7
A19: PV residual income | B19: =B17*B18 | C19: =C17*C18 | D19: =D17*D18 | E19: =E17*E18 | F19: =F17*F18
A20: EPS (A$) | B20: =B12/Inputs!$B$4 | C20: =C12/Inputs!$B$4 | D20: =D12/Inputs!$B$4 | E20: =E12/Inputs!$B$4 | F20: =F12/Inputs!$B$4
A21: DPS (A$) | B21: =B13/Inputs!$B$4 | C21: =C13/Inputs!$B$4 | D21: =D13/Inputs!$B$4 | E21: =E13/Inputs!$B$4 | F21: =F13/Inputs!$B$4
A22: TBV per share (A$) | B22: =B15/Inputs!$B$4 | C22: =C15/Inputs!$B$4 | D22: =D15/Inputs!$B$4 | E22: =E15/Inputs!$B$4 | F22: =F15/Inputs!$B$4
A23: PV dividends at hurdle | B23: =B13/(1+Inputs!$B$11)^B7 | C23: =C13/(1+Inputs!$B$11)^C7 | D23: =D13/(1+Inputs!$B$11)^D7 | E23: =E13/(1+Inputs!$B$11)^E7 | F23: =F13/(1+Inputs!$B$11)^F7
A25: Sum PV residual income | B25: =SUM(B19:F19)
A26: Terminal value (Gordon on Y5 RI) | B26: =F17*(1+B3/100)/(B2/100-B3/100)
A27: PV terminal | B27: =B26*F18
A28: Equity value | B28: =Inputs!$B$5+B25+B27
A29: Intrinsic value per share (A$) | B29: =B28/Inputs!$B$4
A30: Upside vs price (%) | B30: =(B29/Inputs!$B$3-1)*100
A31: Terminal equity value Y5 (TBV + TV) | B31: =F15+B26
A32: Implied exit P/TBV | B32: =B31/F15
A33: Terminal % of value | B33: =B27/B28*100
A35: PV dividends at hurdle | B35: =SUM(B23:F23)
A36: PV terminal equity at hurdle | B36: =B31/(1+Inputs!$B$11)^5
A37: Entry price (A$) | B37: =(B35+B36)/Inputs!$B$4
A38: Entry discount vs price (%) | B38: =(B37/Inputs!$B$3-1)*100

Sheet Bull
A1: Bull scenario -- residual income on tangible book (A$m)
A2: Cost of equity (%) | B2: 9
A3: Terminal growth of RI (%) | B3: 3
A4: Dividend payout (% of cash earnings) | B4: 65
A6: Year | B6: Y1 FY27 (Jul26-Jun27) | C6: Y2 FY28 | D6: Y3 FY29 | E6: Y4 FY30 | F6: Y5 FY31
A7: Period index | B7: 1 | C7: 2 | D7: 3 | E7: 4 | F7: 5
A8: ROTE (%) | B8: 10.6 | C8: 11.2 | D8: 11.8 | E8: 12.3 | F8: 12.5
A9: One-offs after tax | B9: 70 | C9: 30 | D9: 10 | E9: 0 | F9: 0
A10: TBV opening | B10: =Inputs!$B$5 | C10: =B15 | D10: =C15 | E10: =D15 | F10: =E15
A11: Cash earnings | B11: =B8/100*B10 | C11: =C8/100*C10 | D11: =D8/100*D10 | E11: =E8/100*E10 | F11: =F8/100*F10
A12: Net income | B12: =B11-B9 | C12: =C11-C9 | D12: =D11-D9 | E12: =E11-E9 | F12: =F11-F9
A13: Dividends | B13: =$B$4/100*B11 | C13: =$B$4/100*C11 | D13: =$B$4/100*D11 | E13: =$B$4/100*E11 | F13: =$B$4/100*F11
A14: Retained | B14: =B12-B13 | C14: =C12-C13 | D14: =D12-D13 | E14: =E12-E13 | F14: =F12-F13
A15: TBV closing | B15: =B10+B14 | C15: =C10+C14 | D15: =D10+D14 | E15: =E10+E14 | F15: =F10+F14
A16: Equity charge | B16: =$B$2/100*B10 | C16: =$B$2/100*C10 | D16: =$B$2/100*D10 | E16: =$B$2/100*E10 | F16: =$B$2/100*F10
A17: Residual income | B17: =B12-B16 | C17: =C12-C16 | D17: =D12-D16 | E17: =E12-E16 | F17: =F12-F16
A18: Discount factor | B18: =1/(1+$B$2/100)^B7 | C18: =1/(1+$B$2/100)^C7 | D18: =1/(1+$B$2/100)^D7 | E18: =1/(1+$B$2/100)^E7 | F18: =1/(1+$B$2/100)^F7
A19: PV residual income | B19: =B17*B18 | C19: =C17*C18 | D19: =D17*D18 | E19: =E17*E18 | F19: =F17*F18
A20: EPS (A$) | B20: =B12/Inputs!$B$4 | C20: =C12/Inputs!$B$4 | D20: =D12/Inputs!$B$4 | E20: =E12/Inputs!$B$4 | F20: =F12/Inputs!$B$4
A21: DPS (A$) | B21: =B13/Inputs!$B$4 | C21: =C13/Inputs!$B$4 | D21: =D13/Inputs!$B$4 | E21: =E13/Inputs!$B$4 | F21: =F13/Inputs!$B$4
A22: TBV per share (A$) | B22: =B15/Inputs!$B$4 | C22: =C15/Inputs!$B$4 | D22: =D15/Inputs!$B$4 | E22: =E15/Inputs!$B$4 | F22: =F15/Inputs!$B$4
A23: PV dividends at hurdle | B23: =B13/(1+Inputs!$B$11)^B7 | C23: =C13/(1+Inputs!$B$11)^C7 | D23: =D13/(1+Inputs!$B$11)^D7 | E23: =E13/(1+Inputs!$B$11)^E7 | F23: =F13/(1+Inputs!$B$11)^F7
A25: Sum PV residual income | B25: =SUM(B19:F19)
A26: Terminal value (Gordon on Y5 RI) | B26: =F17*(1+B3/100)/(B2/100-B3/100)
A27: PV terminal | B27: =B26*F18
A28: Equity value | B28: =Inputs!$B$5+B25+B27
A29: Intrinsic value per share (A$) | B29: =B28/Inputs!$B$4
A30: Upside vs price (%) | B30: =(B29/Inputs!$B$3-1)*100
A31: Terminal equity value Y5 (TBV + TV) | B31: =F15+B26
A32: Implied exit P/TBV | B32: =B31/F15
A33: Terminal % of value | B33: =B27/B28*100
A35: PV dividends at hurdle | B35: =SUM(B23:F23)
A36: PV terminal equity at hurdle | B36: =B31/(1+Inputs!$B$11)^5
A37: Entry price (A$) | B37: =(B35+B36)/Inputs!$B$4
A38: Entry discount vs price (%) | B38: =(B37/Inputs!$B$3-1)*100

Sheet Bear
A1: Bear scenario -- residual income on tangible book (A$m)
A2: Cost of equity (%) | B2: 11
A3: Terminal growth of RI (%) | B3: 2
A4: Dividend payout (% of cash earnings) | B4: 76
A6: Year | B6: Y1 FY27 (Jul26-Jun27) | C6: Y2 FY28 | D6: Y3 FY29 | E6: Y4 FY30 | F6: Y5 FY31
A7: Period index | B7: 1 | C7: 2 | D7: 3 | E7: 4 | F7: 5
A8: ROTE (%) | B8: 9.6 | C8: 9.2 | D8: 9.4 | E8: 9.8 | F8: 10
A9: One-offs after tax | B9: 120 | C9: 220 | D9: 90 | E9: 50 | F9: 50
A10: TBV opening | B10: =Inputs!$B$5 | C10: =B15 | D10: =C15 | E10: =D15 | F10: =E15
A11: Cash earnings | B11: =B8/100*B10 | C11: =C8/100*C10 | D11: =D8/100*D10 | E11: =E8/100*E10 | F11: =F8/100*F10
A12: Net income | B12: =B11-B9 | C12: =C11-C9 | D12: =D11-D9 | E12: =E11-E9 | F12: =F11-F9
A13: Dividends | B13: =$B$4/100*B11 | C13: =$B$4/100*C11 | D13: =$B$4/100*D11 | E13: =$B$4/100*E11 | F13: =$B$4/100*F11
A14: Retained | B14: =B12-B13 | C14: =C12-C13 | D14: =D12-D13 | E14: =E12-E13 | F14: =F12-F13
A15: TBV closing | B15: =B10+B14 | C15: =C10+C14 | D15: =D10+D14 | E15: =E10+E14 | F15: =F10+F14
A16: Equity charge | B16: =$B$2/100*B10 | C16: =$B$2/100*C10 | D16: =$B$2/100*D10 | E16: =$B$2/100*E10 | F16: =$B$2/100*F10
A17: Residual income | B17: =B12-B16 | C17: =C12-C16 | D17: =D12-D16 | E17: =E12-E16 | F17: =F12-F16
A18: Discount factor | B18: =1/(1+$B$2/100)^B7 | C18: =1/(1+$B$2/100)^C7 | D18: =1/(1+$B$2/100)^D7 | E18: =1/(1+$B$2/100)^E7 | F18: =1/(1+$B$2/100)^F7
A19: PV residual income | B19: =B17*B18 | C19: =C17*C18 | D19: =D17*D18 | E19: =E17*E18 | F19: =F17*F18
A20: EPS (A$) | B20: =B12/Inputs!$B$4 | C20: =C12/Inputs!$B$4 | D20: =D12/Inputs!$B$4 | E20: =E12/Inputs!$B$4 | F20: =F12/Inputs!$B$4
A21: DPS (A$) | B21: =B13/Inputs!$B$4 | C21: =C13/Inputs!$B$4 | D21: =D13/Inputs!$B$4 | E21: =E13/Inputs!$B$4 | F21: =F13/Inputs!$B$4
A22: TBV per share (A$) | B22: =B15/Inputs!$B$4 | C22: =C15/Inputs!$B$4 | D22: =D15/Inputs!$B$4 | E22: =E15/Inputs!$B$4 | F22: =F15/Inputs!$B$4
A23: PV dividends at hurdle | B23: =B13/(1+Inputs!$B$11)^B7 | C23: =C13/(1+Inputs!$B$11)^C7 | D23: =D13/(1+Inputs!$B$11)^D7 | E23: =E13/(1+Inputs!$B$11)^E7 | F23: =F13/(1+Inputs!$B$11)^F7
A25: Sum PV residual income | B25: =SUM(B19:F19)
A26: Terminal value (Gordon on Y5 RI) | B26: =F17*(1+B3/100)/(B2/100-B3/100)
A27: PV terminal | B27: =B26*F18
A28: Equity value | B28: =Inputs!$B$5+B25+B27
A29: Intrinsic value per share (A$) | B29: =B28/Inputs!$B$4
A30: Upside vs price (%) | B30: =(B29/Inputs!$B$3-1)*100
A31: Terminal equity value Y5 (TBV + TV) | B31: =F15+B26
A32: Implied exit P/TBV | B32: =B31/F15
A33: Terminal % of value | B33: =B27/B28*100
A35: PV dividends at hurdle | B35: =SUM(B23:F23)
A36: PV terminal equity at hurdle | B36: =B31/(1+Inputs!$B$11)^5
A37: Entry price (A$) | B37: =(B35+B36)/Inputs!$B$4
A38: Entry discount vs price (%) | B38: =(B37/Inputs!$B$3-1)*100

Sheet Valuation
A1: Scenario | B1: Weight | C1: IV (A$) | D1: Entry (A$) | E1: Upside %
A2: bear | B2: =Inputs!$B$12 | C2: =Bear!$B$29 | D2: =Bear!$B$37 | E2: =(C2/Inputs!$B$3-1)*100
A3: base | B3: =Inputs!$B$13 | C3: =Base!$B$29 | D3: =Base!$B$37 | E3: =(C3/Inputs!$B$3-1)*100
A4: bull | B4: =Inputs!$B$14 | C4: =Bull!$B$29 | D4: =Bull!$B$37 | E4: =(C4/Inputs!$B$3-1)*100
A6: Probability-weighted IV (A$) | B6: =SUMPRODUCT(B2:B4,C2:C4)
A7: Probability-weighted entry (A$) | B7: =SUMPRODUCT(B2:B4,D2:D4)
A8: Weighted upside (%) | B8: =(B6/Inputs!$B$3-1)*100
A9: Weights sum | B9: =SUM(B2:B4)

Sheet Sensitivity
A1: Base IV (A$/share): rows = cost of equity %, cols = terminal RI growth % (values, from model)
B2: 2 | C2: 2.5 | D2: 3 | E2: 3.5 | F2: 4
A3: 8 | B3: 13.19 | C3: 13.5 | D3: 13.88 | E3: 14.34 | F3: 14.91
A4: 9 | B4: 11.24 | C4: 11.38 | D4: 11.54 | E4: 11.73 | F4: 11.96
A5: 10 | B5: 9.78 | C5: 9.83 | D5: 9.88 | E5: 9.93 | F5: 10
A6: 11 | B6: 8.65 | C6: 8.64 | D6: 8.63 | E6: 8.61 | F6: 8.6
A7: 12 | B7: 7.75 | C7: 7.7 | D7: 7.66 | E7: 7.6 | F7: 7.54
A10: Base IV: rows = flat ROTE %, cols = cost of equity % (values, from model)
B11: 8 | C11: 9 | D11: 10 | E11: 11 | F11: 12
A12: 9 | B12: 10.33 | C12: 8.63 | D12: 7.41 | E12: 6.5 | F12: 5.79
A13: 10 | B13: 12.15 | C13: 10.13 | D13: 8.69 | E13: 7.6 | F13: 6.76
A14: 11 | B14: 14.01 | C14: 11.66 | D14: 9.99 | E14: 8.73 | F14: 7.75
A15: 12 | B15: 15.91 | C15: 13.23 | D15: 11.31 | E15: 9.88 | F15: 8.76
A16: 13 | B16: 17.85 | C16: 14.83 | D16: 12.67 | E16: 11.05 | F16: 9.8
