Workbook

Sheet Inputs
A1: SMI.NZ — Santana Minerals — Risked Project-NPV Model (2026-09-01)
A3: Model | B3: Risked project-NPV (sum-of-parts): P(permit) x project NPV + net cash + raise - dilution - overhead
A4: Why not owner-FCF DCF | B4: Pre-revenue single-asset developer; historical FCF is negative exploration spend
A6: Current price (NZD) | B6: 0.615 | C6: Yahoo NZX, 2026-09-01 01:06 UTC
A7: Current price (ASX, AUD) | B7: 0.51 | C7: Parity 0.51 x 1.2123 = NZ$0.618 — holds
A8: AUD/NZD | B8: 1.2123 | C8: Yahoo AUDNZD=X 2026-09-01; 52wk 1.1066-1.228
A9: AUD/USD | B9: 0.7169 | C9: For EV/oz sanity checks
A10: Shares fully diluted (m) | B10: 992.5 | C10: 986m FPO + 6.5m options — Aug-2026 D&D presentation
A11: Net cash (A$m) | B11: 185 | C11: Aug-2026 presentation; Dec-2025 BS (A$90m) superseded by Feb-2026 A$134.1m raise
A12: Pre-production capex (A$m) | B12: 277 | C12: PFS Jul-2025, incl 10% contingency
A13: Ore Reserve (Moz) | B13: 1.242 | C13: 15.0Mt @ 2.58 g/t
A14: Mineral Resource (Moz) | B14: 2.337 | C14: 2.1 g/t
A15: Spot gold (A$/oz) | B15: 6000 | C15: Aug-2026 presentation reference
A16: PFS NPV6.5 @ A$3,500 | B16: 780 | C16: A$m post-tax
A17: PFS NPV6.5 @ A$4,950 | B17: 1521 | C17: A$m post-tax
A18: Permit decision | B18: 16 Dec 2026 | C18: Draft Nov-2026; window extended 3x; four iwi s7 objections

Sheet Project_CF
A1: Project cash flows (A$m, real, post-tax, incl. all capex) — reconstructed from PFS Figure 3 @ A$4,950/oz
A3: LOM revenue @4,950 (A$m) | B3: 6177
A4: Pre-tax flow-through (royalty drag) | B4: 0.874
A5: Tax rate | B5: 0.28
A6: Production-year flow sum (Y1-Y14) | B6: =SUM(D9:Q9)
A8: Year | B8: Y-2 | C8: Y-1 | D8: Y1 | E8: Y2 | F8: Y3 | G8: Y4 | H8: Y5 | I8: Y6 | J8: Y7 | K8: Y8 | L8: Y9 | M8: Y10 | N8: Y11 | O8: Y12 | P8: Y13 | Q8: Y14
A9: FCF @ A$4,950 | B9: -43 | C9: -234 | D9: 95 | E9: 273 | F9: 267 | G9: 239 | H9: 258 | I9: 215 | J9: 245 | K9: 193 | L9: 254 | M9: 244 | N9: 180 | O9: 245 | P9: 101 | Q9: 2
A11: Scale factor formula: (prod_sum + (rev x (gold/4950 - 1)) x 0.874 x 0.72) / prod_sum — production years only; capex years unscaled

Sheet Scenarios
A1: Scenario NPVs — flows rescaled to scenario gold, discounted at REAL equity rate from valuation date
B3: Gold (A$/oz) | C3: Equity rate (real) | D3: Timing shift t0 (yrs) | E3: Scale factor | F3: Project NPV (A$m)
A4: Base | B4: 4500 | C4: 0.12 | D4: 1.5 | E4: =(Project_CF!$B$6+(Project_CF!$B$3*(B4/4950-1))*Project_CF!$B$4*(1-Project_CF!$B$5))/Project_CF!$B$6 | F4: =Project_CF!B$9/(1+$C4)^($D4+0)+Project_CF!C$9/(1+$C4)^($D4+1)+Project_CF!D$9*$E4/(1+$C4)^($D4+2)+Project_CF!E$9*$E4/(1+$C4)^($D4+3)+Project_CF!F$9*$E4/(1+$C4)^($D4+4)+Project_CF!G$9*$E4/(1+$C4)^($D4+5)+Project_CF!H$9*$E4/(1+$C4)^($D4+6)+Project_CF!I$9*$E4/(1+$C4)^($D4+7)+Project_CF!J$9*$E4/(1+$C4)^($D4+8)+Project_CF!K$9*$E4/(1+$C4)^($D4+9)+Project_CF!L$9*$E4/(1+$C4)^($D4+10)+Project_CF!M$9*$E4/(1+$C4)^($D4+11)+Project_CF!N$9*$E4/(1+$C4)^($D4+12)+Project_CF!O$9*$E4/(1+$C4)^($D4+13)+Project_CF!P$9*$E4/(1+$C4)^($D4+14)+Project_CF!Q$9*$E4/(1+$C4)^($D4+15)
A5: Bull | B5: 5500 | C5: 0.1 | D5: 1 | E5: =(Project_CF!$B$6+(Project_CF!$B$3*(B5/4950-1))*Project_CF!$B$4*(1-Project_CF!$B$5))/Project_CF!$B$6 | F5: =Project_CF!B$9/(1+$C5)^($D5+0)+Project_CF!C$9/(1+$C5)^($D5+1)+Project_CF!D$9*$E5/(1+$C5)^($D5+2)+Project_CF!E$9*$E5/(1+$C5)^($D5+3)+Project_CF!F$9*$E5/(1+$C5)^($D5+4)+Project_CF!G$9*$E5/(1+$C5)^($D5+5)+Project_CF!H$9*$E5/(1+$C5)^($D5+6)+Project_CF!I$9*$E5/(1+$C5)^($D5+7)+Project_CF!J$9*$E5/(1+$C5)^($D5+8)+Project_CF!K$9*$E5/(1+$C5)^($D5+9)+Project_CF!L$9*$E5/(1+$C5)^($D5+10)+Project_CF!M$9*$E5/(1+$C5)^($D5+11)+Project_CF!N$9*$E5/(1+$C5)^($D5+12)+Project_CF!O$9*$E5/(1+$C5)^($D5+13)+Project_CF!P$9*$E5/(1+$C5)^($D5+14)+Project_CF!Q$9*$E5/(1+$C5)^($D5+15)
A7: Discount-rate build-up (base): NZ rf 4.3% + ERP 5% x beta 1.2 + 2.5% single-asset/execution + 1.5% illiquidity - ~2.3% inflation = ~12% real. Permit risk NOT in the rate (charged via weights).

Sheet Valuation
A1: Equity bridge and per-share valuation
A3: A$m unless noted | B3: Bear | C3: Base | D3: Bull
A4: Project NPV | B4: 0 | C4: =Scenarios!F4 | D4: =Scenarios!F5
A5: Net cash | B5: 185 | C5: 185 | D5: 185
A6: Equity raise proceeds | B6: 0 | C6: 140 | D6: 25
A7: Raise price (A$/sh) | C7: 0.7 | D7: 0.9
A8: Overhead PV / wind-down | B8: -25 | C8: -10 | D8: -9
A9: Capex stress / debt fees | B9: 0 | C9: -28 | D9: -10
A10: Bear: land net recovery | B10: 15
A11: Bear: residual resource optionality | B11: 25
A12: Equity value | B12: =SUM(B4:B6)+SUM(B8:B11) | C12: =SUM(C4:C6)+SUM(C8:C9) | D12: =SUM(D4:D6)+SUM(D8:D9)
A13: Shares base (m) | B13: 992.5 | C13: 992.5 | D13: 992.5
A14: New shares from raise (m) | B14: 0 | C14: =C6/C7 | D14: =D6/D7
A15: Shares post-funding (m) | B15: =B13+B14 | C15: =C13+C14 | D15: =D13+D14
A16: IV per share (AUD) | B16: =B12/B15 | C16: =C12/C15 | D16: =D12/D15
A17: IV per share (NZD) | B17: =B16*Inputs!$B$8 | C17: =C16*Inputs!$B$8 | D17: =D16*Inputs!$B$8
A19: Probability weight | B19: 0.3 | C19: 0.5 | D19: 0.2
A20: Weighted IV (NZD) | B20: =SUMPRODUCT(B17:D17,B19:D19)
A21: Current price (NZD) | B21: =0.615
A22: Upside | B22: =B20/B21-1
A24: Entry price @15% hurdle, 3yr window: IV x ((1+r)/1.15)^3
A25: Entry price (NZD) | B25: =B17*((1.03)/1.15)^3 | C25: =C17*((1+Scenarios!C4)/1.15)^3 | D25: =D17*((1+Scenarios!C5)/1.15)^3
A26: Weighted entry (NZD) | B26: =SUMPRODUCT(B25:D25,B19:D19)

Sheet Sensitivity
A1: IV NZD/share — gold price (rows) x real equity rate (cols), base structure, UNWEIGHTED for permit risk
B3: 0.08 | C3: 0.1 | D3: 0.12 | E3: 0.14 | F3: 0.16 | H3: scale
A4: 3500 | B4: =(Project_CF!B$9/(1+0.08)^(1.5+0)+Project_CF!C$9/(1+0.08)^(1.5+1)+Project_CF!D$9*$H$4/(1+0.08)^(1.5+2)+Project_CF!E$9*$H$4/(1+0.08)^(1.5+3)+Project_CF!F$9*$H$4/(1+0.08)^(1.5+4)+Project_CF!G$9*$H$4/(1+0.08)^(1.5+5)+Project_CF!H$9*$H$4/(1+0.08)^(1.5+6)+Project_CF!I$9*$H$4/(1+0.08)^(1.5+7)+Project_CF!J$9*$H$4/(1+0.08)^(1.5+8)+Project_CF!K$9*$H$4/(1+0.08)^(1.5+9)+Project_CF!L$9*$H$4/(1+0.08)^(1.5+10)+Project_CF!M$9*$H$4/(1+0.08)^(1.5+11)+Project_CF!N$9*$H$4/(1+0.08)^(1.5+12)+Project_CF!O$9*$H$4/(1+0.08)^(1.5+13)+Project_CF!P$9*$H$4/(1+0.08)^(1.5+14)+Project_CF!Q$9*$H$4/(1+0.08)^(1.5+15)+185+140-38)/Valuation!$C$15*Inputs!$B$8 | C4: =(Project_CF!B$9/(1+0.1)^(1.5+0)+Project_CF!C$9/(1+0.1)^(1.5+1)+Project_CF!D$9*$H$4/(1+0.1)^(1.5+2)+Project_CF!E$9*$H$4/(1+0.1)^(1.5+3)+Project_CF!F$9*$H$4/(1+0.1)^(1.5+4)+Project_CF!G$9*$H$4/(1+0.1)^(1.5+5)+Project_CF!H$9*$H$4/(1+0.1)^(1.5+6)+Project_CF!I$9*$H$4/(1+0.1)^(1.5+7)+Project_CF!J$9*$H$4/(1+0.1)^(1.5+8)+Project_CF!K$9*$H$4/(1+0.1)^(1.5+9)+Project_CF!L$9*$H$4/(1+0.1)^(1.5+10)+Project_CF!M$9*$H$4/(1+0.1)^(1.5+11)+Project_CF!N$9*$H$4/(1+0.1)^(1.5+12)+Project_CF!O$9*$H$4/(1+0.1)^(1.5+13)+Project_CF!P$9*$H$4/(1+0.1)^(1.5+14)+Project_CF!Q$9*$H$4/(1+0.1)^(1.5+15)+185+140-38)/Valuation!$C$15*Inputs!$B$8 | D4: =(Project_CF!B$9/(1+0.12)^(1.5+0)+Project_CF!C$9/(1+0.12)^(1.5+1)+Project_CF!D$9*$H$4/(1+0.12)^(1.5+2)+Project_CF!E$9*$H$4/(1+0.12)^(1.5+3)+Project_CF!F$9*$H$4/(1+0.12)^(1.5+4)+Project_CF!G$9*$H$4/(1+0.12)^(1.5+5)+Project_CF!H$9*$H$4/(1+0.12)^(1.5+6)+Project_CF!I$9*$H$4/(1+0.12)^(1.5+7)+Project_CF!J$9*$H$4/(1+0.12)^(1.5+8)+Project_CF!K$9*$H$4/(1+0.12)^(1.5+9)+Project_CF!L$9*$H$4/(1+0.12)^(1.5+10)+Project_CF!M$9*$H$4/(1+0.12)^(1.5+11)+Project_CF!N$9*$H$4/(1+0.12)^(1.5+12)+Project_CF!O$9*$H$4/(1+0.12)^(1.5+13)+Project_CF!P$9*$H$4/(1+0.12)^(1.5+14)+Project_CF!Q$9*$H$4/(1+0.12)^(1.5+15)+185+140-38)/Valuation!$C$15*Inputs!$B$8 | E4: =(Project_CF!B$9/(1+0.14)^(1.5+0)+Project_CF!C$9/(1+0.14)^(1.5+1)+Project_CF!D$9*$H$4/(1+0.14)^(1.5+2)+Project_CF!E$9*$H$4/(1+0.14)^(1.5+3)+Project_CF!F$9*$H$4/(1+0.14)^(1.5+4)+Project_CF!G$9*$H$4/(1+0.14)^(1.5+5)+Project_CF!H$9*$H$4/(1+0.14)^(1.5+6)+Project_CF!I$9*$H$4/(1+0.14)^(1.5+7)+Project_CF!J$9*$H$4/(1+0.14)^(1.5+8)+Project_CF!K$9*$H$4/(1+0.14)^(1.5+9)+Project_CF!L$9*$H$4/(1+0.14)^(1.5+10)+Project_CF!M$9*$H$4/(1+0.14)^(1.5+11)+Project_CF!N$9*$H$4/(1+0.14)^(1.5+12)+Project_CF!O$9*$H$4/(1+0.14)^(1.5+13)+Project_CF!P$9*$H$4/(1+0.14)^(1.5+14)+Project_CF!Q$9*$H$4/(1+0.14)^(1.5+15)+185+140-38)/Valuation!$C$15*Inputs!$B$8 | F4: =(Project_CF!B$9/(1+0.16)^(1.5+0)+Project_CF!C$9/(1+0.16)^(1.5+1)+Project_CF!D$9*$H$4/(1+0.16)^(1.5+2)+Project_CF!E$9*$H$4/(1+0.16)^(1.5+3)+Project_CF!F$9*$H$4/(1+0.16)^(1.5+4)+Project_CF!G$9*$H$4/(1+0.16)^(1.5+5)+Project_CF!H$9*$H$4/(1+0.16)^(1.5+6)+Project_CF!I$9*$H$4/(1+0.16)^(1.5+7)+Project_CF!J$9*$H$4/(1+0.16)^(1.5+8)+Project_CF!K$9*$H$4/(1+0.16)^(1.5+9)+Project_CF!L$9*$H$4/(1+0.16)^(1.5+10)+Project_CF!M$9*$H$4/(1+0.16)^(1.5+11)+Project_CF!N$9*$H$4/(1+0.16)^(1.5+12)+Project_CF!O$9*$H$4/(1+0.16)^(1.5+13)+Project_CF!P$9*$H$4/(1+0.16)^(1.5+14)+Project_CF!Q$9*$H$4/(1+0.16)^(1.5+15)+185+140-38)/Valuation!$C$15*Inputs!$B$8 | H4: =(Project_CF!$B$6+(Project_CF!$B$3*($A4/4950-1))*Project_CF!$B$4*(1-Project_CF!$B$5))/Project_CF!$B$6
A5: 4000 | B5: =(Project_CF!B$9/(1+0.08)^(1.5+0)+Project_CF!C$9/(1+0.08)^(1.5+1)+Project_CF!D$9*$H$5/(1+0.08)^(1.5+2)+Project_CF!E$9*$H$5/(1+0.08)^(1.5+3)+Project_CF!F$9*$H$5/(1+0.08)^(1.5+4)+Project_CF!G$9*$H$5/(1+0.08)^(1.5+5)+Project_CF!H$9*$H$5/(1+0.08)^(1.5+6)+Project_CF!I$9*$H$5/(1+0.08)^(1.5+7)+Project_CF!J$9*$H$5/(1+0.08)^(1.5+8)+Project_CF!K$9*$H$5/(1+0.08)^(1.5+9)+Project_CF!L$9*$H$5/(1+0.08)^(1.5+10)+Project_CF!M$9*$H$5/(1+0.08)^(1.5+11)+Project_CF!N$9*$H$5/(1+0.08)^(1.5+12)+Project_CF!O$9*$H$5/(1+0.08)^(1.5+13)+Project_CF!P$9*$H$5/(1+0.08)^(1.5+14)+Project_CF!Q$9*$H$5/(1+0.08)^(1.5+15)+185+140-38)/Valuation!$C$15*Inputs!$B$8 | C5: =(Project_CF!B$9/(1+0.1)^(1.5+0)+Project_CF!C$9/(1+0.1)^(1.5+1)+Project_CF!D$9*$H$5/(1+0.1)^(1.5+2)+Project_CF!E$9*$H$5/(1+0.1)^(1.5+3)+Project_CF!F$9*$H$5/(1+0.1)^(1.5+4)+Project_CF!G$9*$H$5/(1+0.1)^(1.5+5)+Project_CF!H$9*$H$5/(1+0.1)^(1.5+6)+Project_CF!I$9*$H$5/(1+0.1)^(1.5+7)+Project_CF!J$9*$H$5/(1+0.1)^(1.5+8)+Project_CF!K$9*$H$5/(1+0.1)^(1.5+9)+Project_CF!L$9*$H$5/(1+0.1)^(1.5+10)+Project_CF!M$9*$H$5/(1+0.1)^(1.5+11)+Project_CF!N$9*$H$5/(1+0.1)^(1.5+12)+Project_CF!O$9*$H$5/(1+0.1)^(1.5+13)+Project_CF!P$9*$H$5/(1+0.1)^(1.5+14)+Project_CF!Q$9*$H$5/(1+0.1)^(1.5+15)+185+140-38)/Valuation!$C$15*Inputs!$B$8 | D5: =(Project_CF!B$9/(1+0.12)^(1.5+0)+Project_CF!C$9/(1+0.12)^(1.5+1)+Project_CF!D$9*$H$5/(1+0.12)^(1.5+2)+Project_CF!E$9*$H$5/(1+0.12)^(1.5+3)+Project_CF!F$9*$H$5/(1+0.12)^(1.5+4)+Project_CF!G$9*$H$5/(1+0.12)^(1.5+5)+Project_CF!H$9*$H$5/(1+0.12)^(1.5+6)+Project_CF!I$9*$H$5/(1+0.12)^(1.5+7)+Project_CF!J$9*$H$5/(1+0.12)^(1.5+8)+Project_CF!K$9*$H$5/(1+0.12)^(1.5+9)+Project_CF!L$9*$H$5/(1+0.12)^(1.5+10)+Project_CF!M$9*$H$5/(1+0.12)^(1.5+11)+Project_CF!N$9*$H$5/(1+0.12)^(1.5+12)+Project_CF!O$9*$H$5/(1+0.12)^(1.5+13)+Project_CF!P$9*$H$5/(1+0.12)^(1.5+14)+Project_CF!Q$9*$H$5/(1+0.12)^(1.5+15)+185+140-38)/Valuation!$C$15*Inputs!$B$8 | E5: =(Project_CF!B$9/(1+0.14)^(1.5+0)+Project_CF!C$9/(1+0.14)^(1.5+1)+Project_CF!D$9*$H$5/(1+0.14)^(1.5+2)+Project_CF!E$9*$H$5/(1+0.14)^(1.5+3)+Project_CF!F$9*$H$5/(1+0.14)^(1.5+4)+Project_CF!G$9*$H$5/(1+0.14)^(1.5+5)+Project_CF!H$9*$H$5/(1+0.14)^(1.5+6)+Project_CF!I$9*$H$5/(1+0.14)^(1.5+7)+Project_CF!J$9*$H$5/(1+0.14)^(1.5+8)+Project_CF!K$9*$H$5/(1+0.14)^(1.5+9)+Project_CF!L$9*$H$5/(1+0.14)^(1.5+10)+Project_CF!M$9*$H$5/(1+0.14)^(1.5+11)+Project_CF!N$9*$H$5/(1+0.14)^(1.5+12)+Project_CF!O$9*$H$5/(1+0.14)^(1.5+13)+Project_CF!P$9*$H$5/(1+0.14)^(1.5+14)+Project_CF!Q$9*$H$5/(1+0.14)^(1.5+15)+185+140-38)/Valuation!$C$15*Inputs!$B$8 | F5: =(Project_CF!B$9/(1+0.16)^(1.5+0)+Project_CF!C$9/(1+0.16)^(1.5+1)+Project_CF!D$9*$H$5/(1+0.16)^(1.5+2)+Project_CF!E$9*$H$5/(1+0.16)^(1.5+3)+Project_CF!F$9*$H$5/(1+0.16)^(1.5+4)+Project_CF!G$9*$H$5/(1+0.16)^(1.5+5)+Project_CF!H$9*$H$5/(1+0.16)^(1.5+6)+Project_CF!I$9*$H$5/(1+0.16)^(1.5+7)+Project_CF!J$9*$H$5/(1+0.16)^(1.5+8)+Project_CF!K$9*$H$5/(1+0.16)^(1.5+9)+Project_CF!L$9*$H$5/(1+0.16)^(1.5+10)+Project_CF!M$9*$H$5/(1+0.16)^(1.5+11)+Project_CF!N$9*$H$5/(1+0.16)^(1.5+12)+Project_CF!O$9*$H$5/(1+0.16)^(1.5+13)+Project_CF!P$9*$H$5/(1+0.16)^(1.5+14)+Project_CF!Q$9*$H$5/(1+0.16)^(1.5+15)+185+140-38)/Valuation!$C$15*Inputs!$B$8 | H5: =(Project_CF!$B$6+(Project_CF!$B$3*($A5/4950-1))*Project_CF!$B$4*(1-Project_CF!$B$5))/Project_CF!$B$6
A6: 4500 | B6: =(Project_CF!B$9/(1+0.08)^(1.5+0)+Project_CF!C$9/(1+0.08)^(1.5+1)+Project_CF!D$9*$H$6/(1+0.08)^(1.5+2)+Project_CF!E$9*$H$6/(1+0.08)^(1.5+3)+Project_CF!F$9*$H$6/(1+0.08)^(1.5+4)+Project_CF!G$9*$H$6/(1+0.08)^(1.5+5)+Project_CF!H$9*$H$6/(1+0.08)^(1.5+6)+Project_CF!I$9*$H$6/(1+0.08)^(1.5+7)+Project_CF!J$9*$H$6/(1+0.08)^(1.5+8)+Project_CF!K$9*$H$6/(1+0.08)^(1.5+9)+Project_CF!L$9*$H$6/(1+0.08)^(1.5+10)+Project_CF!M$9*$H$6/(1+0.08)^(1.5+11)+Project_CF!N$9*$H$6/(1+0.08)^(1.5+12)+Project_CF!O$9*$H$6/(1+0.08)^(1.5+13)+Project_CF!P$9*$H$6/(1+0.08)^(1.5+14)+Project_CF!Q$9*$H$6/(1+0.08)^(1.5+15)+185+140-38)/Valuation!$C$15*Inputs!$B$8 | C6: =(Project_CF!B$9/(1+0.1)^(1.5+0)+Project_CF!C$9/(1+0.1)^(1.5+1)+Project_CF!D$9*$H$6/(1+0.1)^(1.5+2)+Project_CF!E$9*$H$6/(1+0.1)^(1.5+3)+Project_CF!F$9*$H$6/(1+0.1)^(1.5+4)+Project_CF!G$9*$H$6/(1+0.1)^(1.5+5)+Project_CF!H$9*$H$6/(1+0.1)^(1.5+6)+Project_CF!I$9*$H$6/(1+0.1)^(1.5+7)+Project_CF!J$9*$H$6/(1+0.1)^(1.5+8)+Project_CF!K$9*$H$6/(1+0.1)^(1.5+9)+Project_CF!L$9*$H$6/(1+0.1)^(1.5+10)+Project_CF!M$9*$H$6/(1+0.1)^(1.5+11)+Project_CF!N$9*$H$6/(1+0.1)^(1.5+12)+Project_CF!O$9*$H$6/(1+0.1)^(1.5+13)+Project_CF!P$9*$H$6/(1+0.1)^(1.5+14)+Project_CF!Q$9*$H$6/(1+0.1)^(1.5+15)+185+140-38)/Valuation!$C$15*Inputs!$B$8 | D6: =(Project_CF!B$9/(1+0.12)^(1.5+0)+Project_CF!C$9/(1+0.12)^(1.5+1)+Project_CF!D$9*$H$6/(1+0.12)^(1.5+2)+Project_CF!E$9*$H$6/(1+0.12)^(1.5+3)+Project_CF!F$9*$H$6/(1+0.12)^(1.5+4)+Project_CF!G$9*$H$6/(1+0.12)^(1.5+5)+Project_CF!H$9*$H$6/(1+0.12)^(1.5+6)+Project_CF!I$9*$H$6/(1+0.12)^(1.5+7)+Project_CF!J$9*$H$6/(1+0.12)^(1.5+8)+Project_CF!K$9*$H$6/(1+0.12)^(1.5+9)+Project_CF!L$9*$H$6/(1+0.12)^(1.5+10)+Project_CF!M$9*$H$6/(1+0.12)^(1.5+11)+Project_CF!N$9*$H$6/(1+0.12)^(1.5+12)+Project_CF!O$9*$H$6/(1+0.12)^(1.5+13)+Project_CF!P$9*$H$6/(1+0.12)^(1.5+14)+Project_CF!Q$9*$H$6/(1+0.12)^(1.5+15)+185+140-38)/Valuation!$C$15*Inputs!$B$8 | E6: =(Project_CF!B$9/(1+0.14)^(1.5+0)+Project_CF!C$9/(1+0.14)^(1.5+1)+Project_CF!D$9*$H$6/(1+0.14)^(1.5+2)+Project_CF!E$9*$H$6/(1+0.14)^(1.5+3)+Project_CF!F$9*$H$6/(1+0.14)^(1.5+4)+Project_CF!G$9*$H$6/(1+0.14)^(1.5+5)+Project_CF!H$9*$H$6/(1+0.14)^(1.5+6)+Project_CF!I$9*$H$6/(1+0.14)^(1.5+7)+Project_CF!J$9*$H$6/(1+0.14)^(1.5+8)+Project_CF!K$9*$H$6/(1+0.14)^(1.5+9)+Project_CF!L$9*$H$6/(1+0.14)^(1.5+10)+Project_CF!M$9*$H$6/(1+0.14)^(1.5+11)+Project_CF!N$9*$H$6/(1+0.14)^(1.5+12)+Project_CF!O$9*$H$6/(1+0.14)^(1.5+13)+Project_CF!P$9*$H$6/(1+0.14)^(1.5+14)+Project_CF!Q$9*$H$6/(1+0.14)^(1.5+15)+185+140-38)/Valuation!$C$15*Inputs!$B$8 | F6: =(Project_CF!B$9/(1+0.16)^(1.5+0)+Project_CF!C$9/(1+0.16)^(1.5+1)+Project_CF!D$9*$H$6/(1+0.16)^(1.5+2)+Project_CF!E$9*$H$6/(1+0.16)^(1.5+3)+Project_CF!F$9*$H$6/(1+0.16)^(1.5+4)+Project_CF!G$9*$H$6/(1+0.16)^(1.5+5)+Project_CF!H$9*$H$6/(1+0.16)^(1.5+6)+Project_CF!I$9*$H$6/(1+0.16)^(1.5+7)+Project_CF!J$9*$H$6/(1+0.16)^(1.5+8)+Project_CF!K$9*$H$6/(1+0.16)^(1.5+9)+Project_CF!L$9*$H$6/(1+0.16)^(1.5+10)+Project_CF!M$9*$H$6/(1+0.16)^(1.5+11)+Project_CF!N$9*$H$6/(1+0.16)^(1.5+12)+Project_CF!O$9*$H$6/(1+0.16)^(1.5+13)+Project_CF!P$9*$H$6/(1+0.16)^(1.5+14)+Project_CF!Q$9*$H$6/(1+0.16)^(1.5+15)+185+140-38)/Valuation!$C$15*Inputs!$B$8 | H6: =(Project_CF!$B$6+(Project_CF!$B$3*($A6/4950-1))*Project_CF!$B$4*(1-Project_CF!$B$5))/Project_CF!$B$6
A7: 5000 | B7: =(Project_CF!B$9/(1+0.08)^(1.5+0)+Project_CF!C$9/(1+0.08)^(1.5+1)+Project_CF!D$9*$H$7/(1+0.08)^(1.5+2)+Project_CF!E$9*$H$7/(1+0.08)^(1.5+3)+Project_CF!F$9*$H$7/(1+0.08)^(1.5+4)+Project_CF!G$9*$H$7/(1+0.08)^(1.5+5)+Project_CF!H$9*$H$7/(1+0.08)^(1.5+6)+Project_CF!I$9*$H$7/(1+0.08)^(1.5+7)+Project_CF!J$9*$H$7/(1+0.08)^(1.5+8)+Project_CF!K$9*$H$7/(1+0.08)^(1.5+9)+Project_CF!L$9*$H$7/(1+0.08)^(1.5+10)+Project_CF!M$9*$H$7/(1+0.08)^(1.5+11)+Project_CF!N$9*$H$7/(1+0.08)^(1.5+12)+Project_CF!O$9*$H$7/(1+0.08)^(1.5+13)+Project_CF!P$9*$H$7/(1+0.08)^(1.5+14)+Project_CF!Q$9*$H$7/(1+0.08)^(1.5+15)+185+140-38)/Valuation!$C$15*Inputs!$B$8 | C7: =(Project_CF!B$9/(1+0.1)^(1.5+0)+Project_CF!C$9/(1+0.1)^(1.5+1)+Project_CF!D$9*$H$7/(1+0.1)^(1.5+2)+Project_CF!E$9*$H$7/(1+0.1)^(1.5+3)+Project_CF!F$9*$H$7/(1+0.1)^(1.5+4)+Project_CF!G$9*$H$7/(1+0.1)^(1.5+5)+Project_CF!H$9*$H$7/(1+0.1)^(1.5+6)+Project_CF!I$9*$H$7/(1+0.1)^(1.5+7)+Project_CF!J$9*$H$7/(1+0.1)^(1.5+8)+Project_CF!K$9*$H$7/(1+0.1)^(1.5+9)+Project_CF!L$9*$H$7/(1+0.1)^(1.5+10)+Project_CF!M$9*$H$7/(1+0.1)^(1.5+11)+Project_CF!N$9*$H$7/(1+0.1)^(1.5+12)+Project_CF!O$9*$H$7/(1+0.1)^(1.5+13)+Project_CF!P$9*$H$7/(1+0.1)^(1.5+14)+Project_CF!Q$9*$H$7/(1+0.1)^(1.5+15)+185+140-38)/Valuation!$C$15*Inputs!$B$8 | D7: =(Project_CF!B$9/(1+0.12)^(1.5+0)+Project_CF!C$9/(1+0.12)^(1.5+1)+Project_CF!D$9*$H$7/(1+0.12)^(1.5+2)+Project_CF!E$9*$H$7/(1+0.12)^(1.5+3)+Project_CF!F$9*$H$7/(1+0.12)^(1.5+4)+Project_CF!G$9*$H$7/(1+0.12)^(1.5+5)+Project_CF!H$9*$H$7/(1+0.12)^(1.5+6)+Project_CF!I$9*$H$7/(1+0.12)^(1.5+7)+Project_CF!J$9*$H$7/(1+0.12)^(1.5+8)+Project_CF!K$9*$H$7/(1+0.12)^(1.5+9)+Project_CF!L$9*$H$7/(1+0.12)^(1.5+10)+Project_CF!M$9*$H$7/(1+0.12)^(1.5+11)+Project_CF!N$9*$H$7/(1+0.12)^(1.5+12)+Project_CF!O$9*$H$7/(1+0.12)^(1.5+13)+Project_CF!P$9*$H$7/(1+0.12)^(1.5+14)+Project_CF!Q$9*$H$7/(1+0.12)^(1.5+15)+185+140-38)/Valuation!$C$15*Inputs!$B$8 | E7: =(Project_CF!B$9/(1+0.14)^(1.5+0)+Project_CF!C$9/(1+0.14)^(1.5+1)+Project_CF!D$9*$H$7/(1+0.14)^(1.5+2)+Project_CF!E$9*$H$7/(1+0.14)^(1.5+3)+Project_CF!F$9*$H$7/(1+0.14)^(1.5+4)+Project_CF!G$9*$H$7/(1+0.14)^(1.5+5)+Project_CF!H$9*$H$7/(1+0.14)^(1.5+6)+Project_CF!I$9*$H$7/(1+0.14)^(1.5+7)+Project_CF!J$9*$H$7/(1+0.14)^(1.5+8)+Project_CF!K$9*$H$7/(1+0.14)^(1.5+9)+Project_CF!L$9*$H$7/(1+0.14)^(1.5+10)+Project_CF!M$9*$H$7/(1+0.14)^(1.5+11)+Project_CF!N$9*$H$7/(1+0.14)^(1.5+12)+Project_CF!O$9*$H$7/(1+0.14)^(1.5+13)+Project_CF!P$9*$H$7/(1+0.14)^(1.5+14)+Project_CF!Q$9*$H$7/(1+0.14)^(1.5+15)+185+140-38)/Valuation!$C$15*Inputs!$B$8 | F7: =(Project_CF!B$9/(1+0.16)^(1.5+0)+Project_CF!C$9/(1+0.16)^(1.5+1)+Project_CF!D$9*$H$7/(1+0.16)^(1.5+2)+Project_CF!E$9*$H$7/(1+0.16)^(1.5+3)+Project_CF!F$9*$H$7/(1+0.16)^(1.5+4)+Project_CF!G$9*$H$7/(1+0.16)^(1.5+5)+Project_CF!H$9*$H$7/(1+0.16)^(1.5+6)+Project_CF!I$9*$H$7/(1+0.16)^(1.5+7)+Project_CF!J$9*$H$7/(1+0.16)^(1.5+8)+Project_CF!K$9*$H$7/(1+0.16)^(1.5+9)+Project_CF!L$9*$H$7/(1+0.16)^(1.5+10)+Project_CF!M$9*$H$7/(1+0.16)^(1.5+11)+Project_CF!N$9*$H$7/(1+0.16)^(1.5+12)+Project_CF!O$9*$H$7/(1+0.16)^(1.5+13)+Project_CF!P$9*$H$7/(1+0.16)^(1.5+14)+Project_CF!Q$9*$H$7/(1+0.16)^(1.5+15)+185+140-38)/Valuation!$C$15*Inputs!$B$8 | H7: =(Project_CF!$B$6+(Project_CF!$B$3*($A7/4950-1))*Project_CF!$B$4*(1-Project_CF!$B$5))/Project_CF!$B$6
A8: 5500 | B8: =(Project_CF!B$9/(1+0.08)^(1.5+0)+Project_CF!C$9/(1+0.08)^(1.5+1)+Project_CF!D$9*$H$8/(1+0.08)^(1.5+2)+Project_CF!E$9*$H$8/(1+0.08)^(1.5+3)+Project_CF!F$9*$H$8/(1+0.08)^(1.5+4)+Project_CF!G$9*$H$8/(1+0.08)^(1.5+5)+Project_CF!H$9*$H$8/(1+0.08)^(1.5+6)+Project_CF!I$9*$H$8/(1+0.08)^(1.5+7)+Project_CF!J$9*$H$8/(1+0.08)^(1.5+8)+Project_CF!K$9*$H$8/(1+0.08)^(1.5+9)+Project_CF!L$9*$H$8/(1+0.08)^(1.5+10)+Project_CF!M$9*$H$8/(1+0.08)^(1.5+11)+Project_CF!N$9*$H$8/(1+0.08)^(1.5+12)+Project_CF!O$9*$H$8/(1+0.08)^(1.5+13)+Project_CF!P$9*$H$8/(1+0.08)^(1.5+14)+Project_CF!Q$9*$H$8/(1+0.08)^(1.5+15)+185+140-38)/Valuation!$C$15*Inputs!$B$8 | C8: =(Project_CF!B$9/(1+0.1)^(1.5+0)+Project_CF!C$9/(1+0.1)^(1.5+1)+Project_CF!D$9*$H$8/(1+0.1)^(1.5+2)+Project_CF!E$9*$H$8/(1+0.1)^(1.5+3)+Project_CF!F$9*$H$8/(1+0.1)^(1.5+4)+Project_CF!G$9*$H$8/(1+0.1)^(1.5+5)+Project_CF!H$9*$H$8/(1+0.1)^(1.5+6)+Project_CF!I$9*$H$8/(1+0.1)^(1.5+7)+Project_CF!J$9*$H$8/(1+0.1)^(1.5+8)+Project_CF!K$9*$H$8/(1+0.1)^(1.5+9)+Project_CF!L$9*$H$8/(1+0.1)^(1.5+10)+Project_CF!M$9*$H$8/(1+0.1)^(1.5+11)+Project_CF!N$9*$H$8/(1+0.1)^(1.5+12)+Project_CF!O$9*$H$8/(1+0.1)^(1.5+13)+Project_CF!P$9*$H$8/(1+0.1)^(1.5+14)+Project_CF!Q$9*$H$8/(1+0.1)^(1.5+15)+185+140-38)/Valuation!$C$15*Inputs!$B$8 | D8: =(Project_CF!B$9/(1+0.12)^(1.5+0)+Project_CF!C$9/(1+0.12)^(1.5+1)+Project_CF!D$9*$H$8/(1+0.12)^(1.5+2)+Project_CF!E$9*$H$8/(1+0.12)^(1.5+3)+Project_CF!F$9*$H$8/(1+0.12)^(1.5+4)+Project_CF!G$9*$H$8/(1+0.12)^(1.5+5)+Project_CF!H$9*$H$8/(1+0.12)^(1.5+6)+Project_CF!I$9*$H$8/(1+0.12)^(1.5+7)+Project_CF!J$9*$H$8/(1+0.12)^(1.5+8)+Project_CF!K$9*$H$8/(1+0.12)^(1.5+9)+Project_CF!L$9*$H$8/(1+0.12)^(1.5+10)+Project_CF!M$9*$H$8/(1+0.12)^(1.5+11)+Project_CF!N$9*$H$8/(1+0.12)^(1.5+12)+Project_CF!O$9*$H$8/(1+0.12)^(1.5+13)+Project_CF!P$9*$H$8/(1+0.12)^(1.5+14)+Project_CF!Q$9*$H$8/(1+0.12)^(1.5+15)+185+140-38)/Valuation!$C$15*Inputs!$B$8 | E8: =(Project_CF!B$9/(1+0.14)^(1.5+0)+Project_CF!C$9/(1+0.14)^(1.5+1)+Project_CF!D$9*$H$8/(1+0.14)^(1.5+2)+Project_CF!E$9*$H$8/(1+0.14)^(1.5+3)+Project_CF!F$9*$H$8/(1+0.14)^(1.5+4)+Project_CF!G$9*$H$8/(1+0.14)^(1.5+5)+Project_CF!H$9*$H$8/(1+0.14)^(1.5+6)+Project_CF!I$9*$H$8/(1+0.14)^(1.5+7)+Project_CF!J$9*$H$8/(1+0.14)^(1.5+8)+Project_CF!K$9*$H$8/(1+0.14)^(1.5+9)+Project_CF!L$9*$H$8/(1+0.14)^(1.5+10)+Project_CF!M$9*$H$8/(1+0.14)^(1.5+11)+Project_CF!N$9*$H$8/(1+0.14)^(1.5+12)+Project_CF!O$9*$H$8/(1+0.14)^(1.5+13)+Project_CF!P$9*$H$8/(1+0.14)^(1.5+14)+Project_CF!Q$9*$H$8/(1+0.14)^(1.5+15)+185+140-38)/Valuation!$C$15*Inputs!$B$8 | F8: =(Project_CF!B$9/(1+0.16)^(1.5+0)+Project_CF!C$9/(1+0.16)^(1.5+1)+Project_CF!D$9*$H$8/(1+0.16)^(1.5+2)+Project_CF!E$9*$H$8/(1+0.16)^(1.5+3)+Project_CF!F$9*$H$8/(1+0.16)^(1.5+4)+Project_CF!G$9*$H$8/(1+0.16)^(1.5+5)+Project_CF!H$9*$H$8/(1+0.16)^(1.5+6)+Project_CF!I$9*$H$8/(1+0.16)^(1.5+7)+Project_CF!J$9*$H$8/(1+0.16)^(1.5+8)+Project_CF!K$9*$H$8/(1+0.16)^(1.5+9)+Project_CF!L$9*$H$8/(1+0.16)^(1.5+10)+Project_CF!M$9*$H$8/(1+0.16)^(1.5+11)+Project_CF!N$9*$H$8/(1+0.16)^(1.5+12)+Project_CF!O$9*$H$8/(1+0.16)^(1.5+13)+Project_CF!P$9*$H$8/(1+0.16)^(1.5+14)+Project_CF!Q$9*$H$8/(1+0.16)^(1.5+15)+185+140-38)/Valuation!$C$15*Inputs!$B$8 | H8: =(Project_CF!$B$6+(Project_CF!$B$3*($A8/4950-1))*Project_CF!$B$4*(1-Project_CF!$B$5))/Project_CF!$B$6
A9: 6000 | B9: =(Project_CF!B$9/(1+0.08)^(1.5+0)+Project_CF!C$9/(1+0.08)^(1.5+1)+Project_CF!D$9*$H$9/(1+0.08)^(1.5+2)+Project_CF!E$9*$H$9/(1+0.08)^(1.5+3)+Project_CF!F$9*$H$9/(1+0.08)^(1.5+4)+Project_CF!G$9*$H$9/(1+0.08)^(1.5+5)+Project_CF!H$9*$H$9/(1+0.08)^(1.5+6)+Project_CF!I$9*$H$9/(1+0.08)^(1.5+7)+Project_CF!J$9*$H$9/(1+0.08)^(1.5+8)+Project_CF!K$9*$H$9/(1+0.08)^(1.5+9)+Project_CF!L$9*$H$9/(1+0.08)^(1.5+10)+Project_CF!M$9*$H$9/(1+0.08)^(1.5+11)+Project_CF!N$9*$H$9/(1+0.08)^(1.5+12)+Project_CF!O$9*$H$9/(1+0.08)^(1.5+13)+Project_CF!P$9*$H$9/(1+0.08)^(1.5+14)+Project_CF!Q$9*$H$9/(1+0.08)^(1.5+15)+185+140-38)/Valuation!$C$15*Inputs!$B$8 | C9: =(Project_CF!B$9/(1+0.1)^(1.5+0)+Project_CF!C$9/(1+0.1)^(1.5+1)+Project_CF!D$9*$H$9/(1+0.1)^(1.5+2)+Project_CF!E$9*$H$9/(1+0.1)^(1.5+3)+Project_CF!F$9*$H$9/(1+0.1)^(1.5+4)+Project_CF!G$9*$H$9/(1+0.1)^(1.5+5)+Project_CF!H$9*$H$9/(1+0.1)^(1.5+6)+Project_CF!I$9*$H$9/(1+0.1)^(1.5+7)+Project_CF!J$9*$H$9/(1+0.1)^(1.5+8)+Project_CF!K$9*$H$9/(1+0.1)^(1.5+9)+Project_CF!L$9*$H$9/(1+0.1)^(1.5+10)+Project_CF!M$9*$H$9/(1+0.1)^(1.5+11)+Project_CF!N$9*$H$9/(1+0.1)^(1.5+12)+Project_CF!O$9*$H$9/(1+0.1)^(1.5+13)+Project_CF!P$9*$H$9/(1+0.1)^(1.5+14)+Project_CF!Q$9*$H$9/(1+0.1)^(1.5+15)+185+140-38)/Valuation!$C$15*Inputs!$B$8 | D9: =(Project_CF!B$9/(1+0.12)^(1.5+0)+Project_CF!C$9/(1+0.12)^(1.5+1)+Project_CF!D$9*$H$9/(1+0.12)^(1.5+2)+Project_CF!E$9*$H$9/(1+0.12)^(1.5+3)+Project_CF!F$9*$H$9/(1+0.12)^(1.5+4)+Project_CF!G$9*$H$9/(1+0.12)^(1.5+5)+Project_CF!H$9*$H$9/(1+0.12)^(1.5+6)+Project_CF!I$9*$H$9/(1+0.12)^(1.5+7)+Project_CF!J$9*$H$9/(1+0.12)^(1.5+8)+Project_CF!K$9*$H$9/(1+0.12)^(1.5+9)+Project_CF!L$9*$H$9/(1+0.12)^(1.5+10)+Project_CF!M$9*$H$9/(1+0.12)^(1.5+11)+Project_CF!N$9*$H$9/(1+0.12)^(1.5+12)+Project_CF!O$9*$H$9/(1+0.12)^(1.5+13)+Project_CF!P$9*$H$9/(1+0.12)^(1.5+14)+Project_CF!Q$9*$H$9/(1+0.12)^(1.5+15)+185+140-38)/Valuation!$C$15*Inputs!$B$8 | E9: =(Project_CF!B$9/(1+0.14)^(1.5+0)+Project_CF!C$9/(1+0.14)^(1.5+1)+Project_CF!D$9*$H$9/(1+0.14)^(1.5+2)+Project_CF!E$9*$H$9/(1+0.14)^(1.5+3)+Project_CF!F$9*$H$9/(1+0.14)^(1.5+4)+Project_CF!G$9*$H$9/(1+0.14)^(1.5+5)+Project_CF!H$9*$H$9/(1+0.14)^(1.5+6)+Project_CF!I$9*$H$9/(1+0.14)^(1.5+7)+Project_CF!J$9*$H$9/(1+0.14)^(1.5+8)+Project_CF!K$9*$H$9/(1+0.14)^(1.5+9)+Project_CF!L$9*$H$9/(1+0.14)^(1.5+10)+Project_CF!M$9*$H$9/(1+0.14)^(1.5+11)+Project_CF!N$9*$H$9/(1+0.14)^(1.5+12)+Project_CF!O$9*$H$9/(1+0.14)^(1.5+13)+Project_CF!P$9*$H$9/(1+0.14)^(1.5+14)+Project_CF!Q$9*$H$9/(1+0.14)^(1.5+15)+185+140-38)/Valuation!$C$15*Inputs!$B$8 | F9: =(Project_CF!B$9/(1+0.16)^(1.5+0)+Project_CF!C$9/(1+0.16)^(1.5+1)+Project_CF!D$9*$H$9/(1+0.16)^(1.5+2)+Project_CF!E$9*$H$9/(1+0.16)^(1.5+3)+Project_CF!F$9*$H$9/(1+0.16)^(1.5+4)+Project_CF!G$9*$H$9/(1+0.16)^(1.5+5)+Project_CF!H$9*$H$9/(1+0.16)^(1.5+6)+Project_CF!I$9*$H$9/(1+0.16)^(1.5+7)+Project_CF!J$9*$H$9/(1+0.16)^(1.5+8)+Project_CF!K$9*$H$9/(1+0.16)^(1.5+9)+Project_CF!L$9*$H$9/(1+0.16)^(1.5+10)+Project_CF!M$9*$H$9/(1+0.16)^(1.5+11)+Project_CF!N$9*$H$9/(1+0.16)^(1.5+12)+Project_CF!O$9*$H$9/(1+0.16)^(1.5+13)+Project_CF!P$9*$H$9/(1+0.16)^(1.5+14)+Project_CF!Q$9*$H$9/(1+0.16)^(1.5+15)+185+140-38)/Valuation!$C$15*Inputs!$B$8 | H9: =(Project_CF!$B$6+(Project_CF!$B$3*($A9/4950-1))*Project_CF!$B$4*(1-Project_CF!$B$5))/Project_CF!$B$6
A11: Weighted IV (NZD) vs P(bear), base:bull held 50:20
A12: P(bear) | B12: Weighted IV
A13: 0.15 | B13: =0.15*Valuation!$B$17+(1-0.15)*(5/7)*Valuation!$C$17+(1-0.15)*(2/7)*Valuation!$D$17
A14: 0.25 | B14: =0.25*Valuation!$B$17+(1-0.25)*(5/7)*Valuation!$C$17+(1-0.25)*(2/7)*Valuation!$D$17
A15: 0.3 | B15: =0.3*Valuation!$B$17+(1-0.3)*(5/7)*Valuation!$C$17+(1-0.3)*(2/7)*Valuation!$D$17
A16: 0.4 | B16: =0.4*Valuation!$B$17+(1-0.4)*(5/7)*Valuation!$C$17+(1-0.4)*(2/7)*Valuation!$D$17
A17: 0.5 | B17: =0.5*Valuation!$B$17+(1-0.5)*(5/7)*Valuation!$C$17+(1-0.5)*(2/7)*Valuation!$D$17
A18: 0.6 | B18: =0.6*Valuation!$B$17+(1-0.6)*(5/7)*Valuation!$C$17+(1-0.6)*(2/7)*Valuation!$D$17

Sheet Sanity
A1: Mining-developer sanity checks (standard P/E, P/B, EV/EBITDA replaced — meaningless pre-revenue)
A3: Market cap (A$m) | B3: =992.5*(0.615/1.2123)
A4: EV (A$m) | B4: =B3-185
A5: EV / resource oz (US$) | B5: =B4/2.337*0.7169 | C5: peer 30-100 pre-permit → top of band, justified (grade, infrastructure, decision 3.5 mo away)
A6: EV / reserve oz (US$) | B6: =B4/1.242*0.7169
A7: Price / unrisked spot NAV | B7: =B3/(1521+185) | C7: 0.30x — inside 0.2-0.5x pre-permit band
A8: Price / risked weighted NAV | B8: =(0.615/1.2123)/(Valuation!B20/1.2123) | C8: ~0.67x of the model's risked NAV
A9: Gold test | B9: Base A$4,500 = 25% below spot; no scenario needs gold above current levels
