Workbook

Sheet Model_Info
A1: PACIFIC EDGE LIMITED (PEB.NZ) - DCF MODEL - version 1.0 (fresh build, supersedes nothing)
A2: Built by: dcf-analyst agent (Claude Fable 5), 2026-08-24, at the user's request via the research pipeline.
A4: DATA VINTAGE - these figures go stale:
A5: Price NZ$0.25 - NZX close 2026-08-21 16:59 NZT (Yahoo Finance, verified live). Quote and financials both NZD.
A6: Balance sheet 31-Mar-2026 (FY2026 Annual Report): cash+ST deposits NZ$7.776m; IFRS-16 lease liabilities NZ$1.285m (no other debt).
A7: Cash anchor NZ$41.9m = 7.776 + est. NZ$34.1m net from the May-2026 NZ$25.4m placement and June-2026 NZ$10.7m retail offer; paired with FULL FY2027 flows so no burn is double-counted.
A8: Shares 1,263.3m EST = 1,022.632m on issue 31-Mar-2026 (AR note 18; the Metrics.csv 944.5m is the FY2026 weighted average) + est. 240.7m from the NZ$36.1m raise at an ESTIMATED NZ$0.15/share (issue price not stated in the AR; pre-draft-LCD price was NZ$0.174). Range 1,235-1,324m.
A9: Guidance: FY2027 target cash burn NZ$2.5m/month; LCD finalization expected end-CY2026 (company) to mid-CY2027 (Novitas 365-day outside date + 45-day effectiveness).
A11: METHODOLOGY (one line each):
A12: Model: scenario-weighted BINARY-EVENT valuation (Novitas draft LCD DL40378 finalizes vs fails) - the deal-completes/deal-breaks pattern applied to a reimbursement decision, because PEB is pre-profit (owner FCF negative every year FY2019-FY2026) and a historical-FCF DCF would be meaningless.
A13: Bull/Base: forward COMPONENT-BUILT 10-year owner-FCF DCFs (FY2027-FY2036); nothing extrapolated from the burned FY2026 base.
A14: Bear: wind-down asset/scenario value (NZ/APAC business + IP salvage + residual cash - restructuring), NOT a growth DCF; near zero by design.
... A23: CELL COLOURS: blue font = hardcoded input; yellow fill = key driver lever; black = formula; green font = cross-sheet link; green fill = headline value.

Sheet Actuals
A1: Reported history (source: PEB.NZ_Metrics.csv from FY2020-FY2026 Annual Reports; NZ$m)
B2: FY2019 | C2: FY2020 | D2: FY2021 | E2: FY2022 | F2: FY2023 | G2: FY2024 | H2: FY2025 | I2: FY2026
A3: Revenue (NZ$m) | B3: 3.817 | C3: 4.37 | D3: 7.701 | E3: 11.445 | F3: 19.616 | G3: 23.907 | H3: 21.846 | I3: 11.499
A4: Net income | B4: -17.918 | C4: -18.886 | D4: -14.223 | E4: -19.788 | F4: -26.965 | G4: -29.535 | H4: -29.936 | I4: -35.778
A5: Operating cash flow | B5: -17.507 | C5: -15.385 | D5: -13.57 | E5: -17.552 | F5: -25.575 | G5: -25.75 | H5: -24.74 | I5: -31.938
A6: Capex | B6: 0.156 | C6: 0.183 | D6: 0.378 | E6: 1.126 | F6: 2.909 | G6: 1.372 | H6: 1.273 | I6: 0.132
A7: Reported FCF | B7: -17.663 | C7: -15.568 | D7: -13.948 | E7: -18.678 | F7: -28.484 | G7: -27.122 | H7: -26.013 | I7: -32.07
A8: Shareholders' equity | B8: 13.91 | C8: 14.504 | D8: 25.109 | E8: 108.376 | F8: 82.763 | G8: 54.622 | H8: 26.085 | I8: 10.659
A9: Cash + ST deposits | B9: 12.847 | C9: 14.784 | D9: 23.129 | E9: 105.412 | F9: 77.791 | G9: 50.261 | H9: 22.568 | I9: 7.776
A10: Lease liabilities (only debt) | B10: 0.084 | C10: 1.554 | D10: 2.878 | E10: 1.923 | F10: 1.222 | G10: 4.073 | H10: 2.901 | I10: 1.285
A11: Weighted avg shares (m) | B11: 504.426 | C11: 581.344 | D11: 714.031 | E11: 767.924 | F11: 810.226 | G11: 810.727 | H11: 811.736 | I11: 944.534
A12: FY-end share price (NZ$) | B12: 0.253 | C12: 0.103 | D12: 1.15 | E12: 0.9 | F12: 0.465 | G12: 0.093 | H12: 0.098 | I12: 0.17
A14: Balance-sheet snapshot / share count: 1,022,631,578 shares ON ISSUE at 31-Mar-2026 (AR note 18). Aug-2025 raise: 207.3m shares at NZ$0.100 (NZ$20.7m). May/Jun-2026 raise: NZ$36.1m, est. NZ$0.15/share, est. +240.7m shares. Buybacks: none, ever.
A15: Guidance: FY2027 cash-burn target NZ$2.5m/month; runway 'over 12 months' from the raise, explicitly conditioned on Medicare progress. No revenue/EPS guidance issued.

Sheet Assumptions
A1: Global assumptions
A3: WACC (NZD-built) | B3: 0.16 | C3: 11% NZ small-cap CoE + 2% illiquidity + 1.5% single-product + 1.5% pre-profit financing. LCD binary charged in weights, not here.
A4: Terminal growth | B4: 0.03 | C4: Population/incidence + price; applies to bull and base.
A5: TV cap multiple (x FCF10) | B5: 15 | C5: Diagnostics, not a mature compounder; Gordon binds in both scenarios anyway.
A6: D&A % of revenue | B6: 0.02 | C6: Lab equipment + ROU amortisation.
A7: Capex % of revenue | B7: 0.025 | C7: Lab capacity rebuild as volumes recover.
A8: WC capture (on chg in revenue) | B8: -0.05 | C8: NEGATIVE: receivables build with growth (Medicare claim-by-claim pays slowly).
A9: Net cash (NZ$m, post-raise) | B9: 40.59 | C9: Cash 7.776 (31-Mar-26) + 34.1 est. net raise - 1.285 leases. Paired with FULL FY2027 flows.
A10: Current price (NZ$) | B10: 0.25 | C10: NZX close 2026-08-21 (Yahoo, verified live).
A11: Current shares (m, est.) | B11: 1263.3 | C11: 1,022.6m at 31-Mar-26 + est. 240.7m from NZ$36.1m raise at est. NZ$0.15.
A13: Per scenario | B13: Bear | C13: Base | D13: Bull
A14: Probability weight | B14: 0.2 | C14: 0.45 | D14: 0.35 | E14: =SUM(B14:D14) | F14: check: must equal 1.00
A15: Scenario shares (m) | B15: 1463.3 | C15: 1383.3 | D15: 1306.2
A16: Raise net proceeds (NZ$m) | B16: 10 | C16: 24 | D16: 15
A17: Raise year index | B17: 2 | C17: 2 | D17: 2
A18: Raise price (NZ$) | B18: 0.05 | C18: 0.2 | D18: 0.35
A20: Scenario shares basis: current 1,263.3m + bear 200m emergency raise at ~$0.05 / base 120m at ~$0.20 / bull 42.9m at ~$0.35 (all FY2028).
A22: BULL (35%): LCD DL40378 finalized broadly as drafted by ~end-CY2026; Cxbladder Triage/Triage Plus the ONLY covered urine biomarkers (de facto moat) at US$1,328; salesforce rebuilt; Surveillance Plus adds a leg from FY2029. Revenue NZ$15m -> NZ$166m by FY2036, mature EBITDA margin 30%.
A23: BASE (45%): LCD finalized LATE (toward the May-2027 outside date) and/or narrowed; slow US rebuild off 8-12 sales FTE; commercial payers + NZ/APAC carry the interim; one further NZ$25m raise FY2028. Revenue NZ$12.5m -> NZ$89m by FY2036, mature margin 26%.
A24: BEAR (20%): draft LCD retired or excludes Cxbladder (Novitas has reversed on this product before); cash ~NZ$4.4m at mid-2027 clarity; US wound down; residual = NZ/APAC (~NZ$8m) + IP salvage (~NZ$7m) + emergency raise; heavy dilution. See Bear_Scenario tab.

Sheet DCF_Base
A1: DCF_Base - component-built owner-FCF DCF, FY2027-FY2036 (NZ$m)
B3: 2026A | C3: FY2027E | D3: FY2028E | E3: FY2029E | F3: FY2030E | G3: FY2031E | H3: FY2032E | I3: FY2033E | J3: FY2034E | K3: FY2035E | L3: FY2036E
B4: 0 | C4: 1 | D4: 2 | E4: 3 | F4: 4 | G4: 5 | H4: 6 | I4: 7 | J4: 8 | K4: 9 | L4: 10
A5: Revenue growth YoY | C5: 0.087051 | D5: 0.6 | E5: 0.6 | F5: 0.375 | G5: 0.25 | H5: 0.181818 | I5: 0.123077 | J5: 0.09589 | K5: 0.0625 | L5: 0.047059
A6: Revenue | B6: 11.499 | C6: =B6*(1+C5) | D6: =C6*(1+D5) | E6: =D6*(1+E5) | F6: =E6*(1+F5) | G6: =F6*(1+G5) | H6: =G6*(1+H5) | I6: =H6*(1+I5) | J6: =I6*(1+J5) | ... L6: =K6*(1+L5)
A7: Adj EBITDA margin | C7: -2 | D7: -0.8 | E7: -0.2 | F7: 0.02 | G7: 0.1 | H7: 0.16 | I7: 0.2 | J7: 0.23 | K7: 0.25 | L7: 0.26
A8: Adjusted EBITDA | C8: =C6*C7 | D8: =D6*D7 | E8: =E6*E7 | F8: =F6*F7 | G8: =G6*G7 | H8: =H6*H7 | I8: =I6*I7 | J8: =J6*J7 | ... L8: =L6*L7
A9: SBC % of revenue | C9: 0.02 | D9: 0.017 | E9: 0.015 | F9: 0.015 | G9: 0.015 | H9: 0.015 | I9: 0.015 | J9: 0.015 | K9: 0.015 | L9: 0.015
A10: SBC (negative) | C10: =-C6*C9 | D10: =-D6*D9 | E10: =-E6*E9 | F10: =-F6*F9 | G10: =-G6*G9 | H10: =-H6*H9 | I10: =-I6*I9 | J10: =-J6*J9 | ... L10: =-L6*L9
A11: Owner EBITDA | C11: =C8+C10 | D11: =D8+D10 | E11: =E8+E10 | F11: =F8+F10 | G11: =G8+G10 | H11: =H8+H10 | I11: =I8+I10 | J11: =J8+J10 | ... L11: =L8+L10
A12: D&A (negative) | C12: =-C6*Assumptions!$B$6 | D12: =-D6*Assumptions!$B$6 | E12: =-E6*Assumptions!$B$6 | F12: =-F6*Assumptions!$B$6 | G12: =-G6*Assumptions!$B$6 | H12: =-H6*Assumptions!$B$6 | I12: =-I6*Assumptions!$B$6 | J12: =-J6*Assumptions!$B$6 | ... L12: =-L6*Assumptions!$B$6
A13: EBIT (SBC expensed) | C13: =C11+C12 | D13: =D11+D12 | E13: =E11+E12 | F13: =F11+F12 | G13: =G11+G12 | H13: =H11+H12 | I13: =I11+I12 | J13: =J11+J12 | ... L13: =L11+L12
A14: Cash tax rate | C14: 0 | D14: 0 | E14: 0 | F14: 0 | G14: 0 | H14: 0 | I14: 0.1 | J14: 0.15 | K14: 0.2 | L14: 0.25
A15: NOPAT (tax on positive EBIT only) | C15: =IF(C13>0,C13*(1-C14),C13) | D15: =IF(D13>0,D13*(1-D14),D13) | E15: =IF(E13>0,E13*(1-E14),E13) | F15: =IF(F13>0,F13*(1-F14),F13) | G15: =IF(G13>0,G13*(1-G14),G13) | H15: =IF(H13>0,H13*(1-H14),H13) | I15: =IF(I13>0,I13*(1-I14),I13) | J15: =IF(J13>0,J13*(1-J14),J13) | ... L15: =IF(L13>0,L13*(1-L14),L13)
A16: add back D&A | C16: =-C12 | D16: =-D12 | E16: =-E12 | F16: =-F12 | G16: =-G12 | H16: =-H12 | I16: =-I12 | J16: =-J12 | ... L16: =-L12
A17: less capex | C17: =-C6*Assumptions!$B$7 | D17: =-D6*Assumptions!$B$7 | E17: =-E6*Assumptions!$B$7 | F17: =-F6*Assumptions!$B$7 | G17: =-G6*Assumptions!$B$7 | H17: =-H6*Assumptions!$B$7 | I17: =-I6*Assumptions!$B$7 | J17: =-J6*Assumptions!$B$7 | ... L17: =-L6*Assumptions!$B$7
A18: add working capital | C18: =Assumptions!$B$8*(C6-B6) | D18: =Assumptions!$B$8*(D6-C6) | E18: =Assumptions!$B$8*(E6-D6) | F18: =Assumptions!$B$8*(F6-E6) | G18: =Assumptions!$B$8*(G6-F6) | H18: =Assumptions!$B$8*(H6-G6) | I18: =Assumptions!$B$8*(I6-H6) | J18: =Assumptions!$B$8*(J6-I6) | ... L18: =Assumptions!$B$8*(L6-K6)
A19: Unlevered owner FCF | C19: =C15+C16+C17+C18 | D19: =D15+D16+D17+D18 | E19: =E15+E16+E17+E18 | F19: =F15+F16+F17+F18 | G19: =G15+G16+G17+G18 | H19: =H15+H16+H17+H18 | I19: =I15+I16+I17+I18 | J19: =J15+J16+J17+J18 | ... L19: =L15+L16+L17+L18
A20: Discount factor | C20: =1/(1+Assumptions!$B$3)^C4 | D20: =1/(1+Assumptions!$B$3)^D4 | E20: =1/(1+Assumptions!$B$3)^E4 | F20: =1/(1+Assumptions!$B$3)^F4 | G20: =1/(1+Assumptions!$B$3)^G4 | H20: =1/(1+Assumptions!$B$3)^H4 | I20: =1/(1+Assumptions!$B$3)^I4 | J20: =1/(1+Assumptions!$B$3)^J4 | ... L20: =1/(1+Assumptions!$B$3)^L4
A21: PV of FCF | C21: =C19*C20 | D21: =D19*D20 | E21: =E19*E20 | F21: =F19*F20 | G21: =G19*G20 | H21: =H19*H20 | I21: =I19*I20 | J21: =J19*J20 | ... L21: =L19*L20
A23: Memo: FCF before SBC (company-style) | C23: =C19-C10 | D23: =D19-D10 | E23: =E19-E10 | F23: =F19-F10 | G23: =G19-G10 | H23: =H19-H10 | I23: =I19-I10 | J23: =J19-J10 | ... L23: =L19-L10
A24: Memo: implied owner-FCF margin | C24: =C19/C6 | D24: =D19/D6 | E24: =E19/E6 | F24: =F19/F6 | G24: =G19/G6 | H24: =H19/H6 | I24: =I19/I6 | J24: =J19/J6 | ... L24: =L19/L6
A26: Sum of PV of FCF | B26: =SUM(C21:L21)
A27: Terminal growth | B27: =Assumptions!$B$4
A28: Terminal FCF (FY2036 x (1+g)) | B28: =L19*(1+B27)
A29: Gordon TV | B29: =IF(Assumptions!$B$3>B27,B28/(Assumptions!$B$3-B27),9.9E+99)
A30: Cap TV (15x FCF10) | B30: =Assumptions!$B$5*L19
A31: TV used = MAX(0,MIN(Gordon,Cap)) | B31: =MAX(0,MIN(B29,B30))
A32: Implied exit multiple (TV/FCF10) | B32: =IF(L19>0,B31/L19,"n/a")
A33: PV of TV | B33: =B31*L20
A34: Enterprise value | B34: =B26+B33
A35: add net cash | B35: =Assumptions!$B$9
A36: add PV of FY2028 raise proceeds | B36: =Assumptions!C16/(1+Assumptions!$B$3)^Assumptions!C17
A37: Equity value | B37: =B34+B35+B36
A38: Scenario diluted shares (m) | B38: =Assumptions!C15
A39: VALUE PER SHARE (NZ$) | B39: =B37/B38
A40: Upside vs price | B40: =B39/Assumptions!$B$10-1
A42: Street memo (SBC as non-cash add-back) | B42: =SUMPRODUCT(-C10:L10/(1+Assumptions!$B$3)^C4:L4)
A43: PV of terminal SBC | B43: =(-L10)*(1+B27)/(Assumptions!$B$3-B27)*L20
A44: Street value per share | B44: =(B37+B42+B43)/B38

Sheet DCF_Bull
A1: DCF_Bull - component-built owner-FCF DCF, FY2027-FY2036 (NZ$m)
B3: 2026A | C3: FY2027E | D3: FY2028E | E3: FY2029E | F3: FY2030E | G3: FY2031E | H3: FY2032E | I3: FY2033E | J3: FY2034E | K3: FY2035E | L3: FY2036E
B4: 0 | C4: 1 | D4: 2 | E4: 3 | F4: 4 | G4: 5 | H4: 6 | I4: 7 | J4: 8 | K4: 9 | L4: 10
A5: Revenue growth YoY | C5: 0.304461 | D5: 1.266667 | E5: 0.617647 | F5: 0.418182 | G5: 0.25641 | H5: 0.204082 | I5: 0.135593 | J5: 0.104478 | K5: 0.067568 | L5: 0.050633
A6: Revenue | B6: 11.499 | C6: =B6*(1+C5) | D6: =C6*(1+D5) | E6: =D6*(1+E5) | F6: =E6*(1+F5) | G6: =F6*(1+G5) | H6: =G6*(1+H5) | I6: =H6*(1+I5) | J6: =I6*(1+J5) | ... L6: =K6*(1+L5)
A7: Adj EBITDA margin | C7: -1.7 | D7: -0.35 | E7: 0.03 | F7: 0.12 | G7: 0.19 | H7: 0.24 | I7: 0.27 | J7: 0.29 | K7: 0.3 | L7: 0.3
A8: Adjusted EBITDA | C8: =C6*C7 | D8: =D6*D7 | E8: =E6*E7 | F8: =F6*F7 | G8: =G6*G7 | H8: =H6*H7 | I8: =I6*I7 | J8: =J6*J7 | ... L8: =L6*L7
A9: SBC % of revenue | C9: 0.02 | D9: 0.017 | E9: 0.015 | F9: 0.015 | G9: 0.015 | H9: 0.015 | I9: 0.015 | J9: 0.015 | K9: 0.015 | L9: 0.015
A10: SBC (negative) | C10: =-C6*C9 | D10: =-D6*D9 | E10: =-E6*E9 | F10: =-F6*F9 | G10: =-G6*G9 | H10: =-H6*H9 | I10: =-I6*I9 | J10: =-J6*J9 | ... L10: =-L6*L9
A11: Owner EBITDA | C11: =C8+C10 | D11: =D8+D10 | E11: =E8+E10 | F11: =F8+F10 | G11: =G8+G10 | H11: =H8+H10 | I11: =I8+I10 | J11: =J8+J10 | ... L11: =L8+L10
A12: D&A (negative) | C12: =-C6*Assumptions!$B$6 | D12: =-D6*Assumptions!$B$6 | E12: =-E6*Assumptions!$B$6 | F12: =-F6*Assumptions!$B$6 | G12: =-G6*Assumptions!$B$6 | H12: =-H6*Assumptions!$B$6 | I12: =-I6*Assumptions!$B$6 | J12: =-J6*Assumptions!$B$6 | ... L12: =-L6*Assumptions!$B$6
A13: EBIT (SBC expensed) | C13: =C11+C12 | D13: =D11+D12 | E13: =E11+E12 | F13: =F11+F12 | G13: =G11+G12 | H13: =H11+H12 | I13: =I11+I12 | J13: =J11+J12 | ... L13: =L11+L12
A14: Cash tax rate | C14: 0 | D14: 0 | E14: 0 | F14: 0 | G14: 0.1 | H14: 0.15 | I14: 0.2 | J14: 0.24 | K14: 0.28 | L14: 0.28
A15: NOPAT (tax on positive EBIT only) | C15: =IF(C13>0,C13*(1-C14),C13) | D15: =IF(D13>0,D13*(1-D14),D13) | E15: =IF(E13>0,E13*(1-E14),E13) | F15: =IF(F13>0,F13*(1-F14),F13) | G15: =IF(G13>0,G13*(1-G14),G13) | H15: =IF(H13>0,H13*(1-H14),H13) | I15: =IF(I13>0,I13*(1-I14),I13) | J15: =IF(J13>0,J13*(1-J14),J13) | ... L15: =IF(L13>0,L13*(1-L14),L13)
A16: add back D&A | C16: =-C12 | D16: =-D12 | E16: =-E12 | F16: =-F12 | G16: =-G12 | H16: =-H12 | I16: =-I12 | J16: =-J12 | ... L16: =-L12
A17: less capex | C17: =-C6*Assumptions!$B$7 | D17: =-D6*Assumptions!$B$7 | E17: =-E6*Assumptions!$B$7 | F17: =-F6*Assumptions!$B$7 | G17: =-G6*Assumptions!$B$7 | H17: =-H6*Assumptions!$B$7 | I17: =-I6*Assumptions!$B$7 | J17: =-J6*Assumptions!$B$7 | ... L17: =-L6*Assumptions!$B$7
A18: add working capital | C18: =Assumptions!$B$8*(C6-B6) | D18: =Assumptions!$B$8*(D6-C6) | E18: =Assumptions!$B$8*(E6-D6) | F18: =Assumptions!$B$8*(F6-E6) | G18: =Assumptions!$B$8*(G6-F6) | H18: =Assumptions!$B$8*(H6-G6) | I18: =Assumptions!$B$8*(I6-H6) | J18: =Assumptions!$B$8*(J6-I6) | ... L18: =Assumptions!$B$8*(L6-K6)
A19: Unlevered owner FCF | C19: =C15+C16+C17+C18 | D19: =D15+D16+D17+D18 | E19: =E15+E16+E17+E18 | F19: =F15+F16+F17+F18 | G19: =G15+G16+G17+G18 | H19: =H15+H16+H17+H18 | I19: =I15+I16+I17+I18 | J19: =J15+J16+J17+J18 | ... L19: =L15+L16+L17+L18
A20: Discount factor | C20: =1/(1+Assumptions!$B$3)^C4 | D20: =1/(1+Assumptions!$B$3)^D4 | E20: =1/(1+Assumptions!$B$3)^E4 | F20: =1/(1+Assumptions!$B$3)^F4 | G20: =1/(1+Assumptions!$B$3)^G4 | H20: =1/(1+Assumptions!$B$3)^H4 | I20: =1/(1+Assumptions!$B$3)^I4 | J20: =1/(1+Assumptions!$B$3)^J4 | ... L20: =1/(1+Assumptions!$B$3)^L4
A21: PV of FCF | C21: =C19*C20 | D21: =D19*D20 | E21: =E19*E20 | F21: =F19*F20 | G21: =G19*G20 | H21: =H19*H20 | I21: =I19*I20 | J21: =J19*J20 | ... L21: =L19*L20
A23: Memo: FCF before SBC (company-style) | C23: =C19-C10 | D23: =D19-D10 | E23: =E19-E10 | F23: =F19-F10 | G23: =G19-G10 | H23: =H19-H10 | I23: =I19-I10 | J23: =J19-J10 | ... L23: =L19-L10
A24: Memo: implied owner-FCF margin | C24: =C19/C6 | D24: =D19/D6 | E24: =E19/E6 | F24: =F19/F6 | G24: =G19/G6 | H24: =H19/H6 | I24: =I19/I6 | J24: =J19/J6 | ... L24: =L19/L6
A26: Sum of PV of FCF | B26: =SUM(C21:L21)
A27: Terminal growth | B27: =Assumptions!$B$4
A28: Terminal FCF (FY2036 x (1+g)) | B28: =L19*(1+B27)
A29: Gordon TV | B29: =IF(Assumptions!$B$3>B27,B28/(Assumptions!$B$3-B27),9.9E+99)
A30: Cap TV (15x FCF10) | B30: =Assumptions!$B$5*L19
A31: TV used = MAX(0,MIN(Gordon,Cap)) | B31: =MAX(0,MIN(B29,B30))
A32: Implied exit multiple (TV/FCF10) | B32: =IF(L19>0,B31/L19,"n/a")
A33: PV of TV | B33: =B31*L20
A34: Enterprise value | B34: =B26+B33
A35: add net cash | B35: =Assumptions!$B$9
A36: add PV of FY2028 raise proceeds | B36: =Assumptions!D16/(1+Assumptions!$B$3)^Assumptions!D17
A37: Equity value | B37: =B34+B35+B36
A38: Scenario diluted shares (m) | B38: =Assumptions!D15
A39: VALUE PER SHARE (NZ$) | B39: =B37/B38
A40: Upside vs price | B40: =B39/Assumptions!$B$10-1
A42: Street memo (SBC as non-cash add-back) | B42: =SUMPRODUCT(-C10:L10/(1+Assumptions!$B$3)^C4:L4)
A43: PV of terminal SBC | B43: =(-L10)*(1+B27)/(Assumptions!$B$3-B27)*L20
A44: Street value per share | B44: =(B37+B42+B43)/B38

Sheet Bear_Scenario
A1: Bear: LCD retired / Cxbladder excluded - wind-down scenario value (NOT a growth DCF)
A3: Cash anchor post-raise (NZ$m) | B3: 41.9 | C3: 7.776 at 31-Mar-26 + est. 34.1 net raise
A4: Burn per month to clarity (NZ$m) | B4: 2.5 | C4: FY2027 management target
A5: Months to LCD failure clarity | B5: 15 | C5: Apr-2026 -> ~mid-CY2027 (Novitas outside date + effectiveness lag)
A6: Cash remaining at failure clarity | B6: =B3-B4*B5
A7: US wind-down cost | B7: -5 | C7: redundancies, lab exit, contracts
A8: NZ/APAC business value | B8: 8 | C8: ~NZ$2.5-3m revenue, market-dominant NZ, near regional profitability, ~3x sales
A9: IP / clinical-evidence salvage | B9: 7 | C9: STRATA/DRIVE evidence base + Cxbladder IP to an acquirer
A10: Emergency raise net proceeds | B10: 10 | C10: at ~NZ$0.05; +200m shares already in the scenario count
A11: less lease liabilities | B11: -1.285 | C11: IFRS-16
A12: Bear equity value | B12: =B6+B7+B8+B9+B10+B11
A13: Bear scenario shares (m) | B13: =Assumptions!B15
A14: BEAR VALUE PER SHARE (NZ$) | B14: =B12/B13
A15: Bear entry price (15% IRR, ~1yr to crystallization) | B15: =B14/1.15
A17: Deliberately near zero and not floored: management itself warns of 'significant restructuring' and further capital if the draft LCD is not finalized.

Sheet FCF_Quality
A1: Reported FCF reconciled to owner FCF (NZ$m). SBC FY2019-FY2022 are estimates (equity-statement rows incomplete in extracts); FY2023-FY2026 from the statements of changes in equity.
B2: FY2019 | C2: FY2020 | D2: FY2021 | E2: FY2022 | F2: FY2023 | G2: FY2024 | H2: FY2025 | I2: FY2026
A3: Free cash flow (company definition) | B3: -17.663 | C3: -15.568 | D3: -13.948 | E3: -18.678 | F3: -28.484 | G3: -27.122 | H3: -26.013 | I3: -32.07
A4: less: SBC (P&L charge) | B4: 0.4 | C4: 0.5 | D4: 2.82 | E4: 2.5 | F4: 1.455 | G4: 1.272 | H4: 1.374 | I4: 0.991
A5: less: interest income | B5: 0.323 | C5: 0.249 | D5: 0.351 | E5: 0.549 | F5: 2.761 | G5: 3.433 | H5: 1.925 | I5: 0.521
A6: Owner FCF | B6: =B3-B4-B5 | C6: =C3-C4-C5 | D6: =D3-D4-D5 | E6: =E3-E4-E5 | F6: =F3-F4-F5 | G6: =G3-G4-G5 | H6: =H3-H4-H5 | I6: =I3-I4-I5
A7: Revenue | B7: 3.817 | C7: 4.37 | D7: 7.701 | E7: 11.445 | F7: 19.616 | G7: 23.907 | H7: 21.846 | I7: 11.499
A8: Reported FCF margin | B8: =B3/B7 | C8: =C3/C7 | D8: =D3/D7 | E8: =E3/E7 | F8: =F3/F7 | G8: =G3/G7 | H8: =H3/H7 | I8: =I3/I7
A9: Owner FCF margin | B9: =B6/B7 | C9: =C6/C7 | D9: =D6/D7 | E9: =E6/E7 | F9: =F6/F7 | G9: =G6/G7 | H9: =H6/H7 | I9: =I6/I7
A11: Memo: no deferred-revenue tailwind exists (fee-per-test, no subscriptions). Cash tax rate 0% throughout - NZ tax losses accumulate; continuity of the NOL pool across repeated raises is uncertain, hence the projected tax ramp.
A12: Memo: interest income peaked FY2024 (NZ$3.4m) on the FY2022 NZ$100m raise pile - stripping it matters because the cash is separately added in the bridge.

Sheet Valuation
A1: Valuation summary (NZ$; probability-weighted binary-event model)
A3: Scenario | B3: Value/share | C3: Upside vs price | D3: Weight | E3: Street value/share
A4: Bear (LCD fails) | B4: =Bear_Scenario!B14 | C4: =B4/Assumptions!$B$10-1 | D4: =Assumptions!B14 | E4: =Bear_Scenario!B14
A5: Base (late/partial) | B5: =DCF_Base!B39 | C5: =B5/Assumptions!$B$10-1 | D5: =Assumptions!C14 | E5: =DCF_Base!B44
A6: Bull (as drafted) | B6: =DCF_Bull!B39 | C6: =B6/Assumptions!$B$10-1 | D6: =Assumptions!D14 | E6: =DCF_Bull!B44
A8: PROBABILITY-WEIGHTED IV | B8: =SUMPRODUCT(B4:B6,D4:D6)
A9: Street weighted IV | B9: =SUMPRODUCT(E4:E6,D4:D6)
A10: Margin of safety at current price | B10: =1-Assumptions!$B$10/B8
A11: Band position (price-house)/(street-house) | B11: =(Assumptions!$B$10-B8)/(B9-B8)
A12: Band note: degenerate by design - SBC ~1.5-2% of revenue makes the band ~NZ$0.005 wide; the price sits ~42 band-widths above the street ceiling. SBC treatment is not the debate here; the LCD probability is.
A15: 15%-hurdle entry prices (TV at WACC, discounted at 15%)
A16: Bear | B16: =Bear_Scenario!B15
A17: Base | B17: =(SUMPRODUCT(DCF_Base!$C$19:$L$19/1.15^DCF_Base!$C$4:$L$4)+DCF_Base!$B$31/1.15^10+Assumptions!$B$9+Assumptions!$C$16/1.15^Assumptions!$C$17)/Assumptions!$C$15
A18: Bull | B18: =(SUMPRODUCT(DCF_Bull!$C$19:$L$19/1.15^DCF_Bull!$C$4:$L$4)+DCF_Bull!$B$31/1.15^10+Assumptions!$B$9+Assumptions!$D$16/1.15^Assumptions!$D$17)/Assumptions!$D$15
A19: WEIGHTED ENTRY (buy-below) PRICE | B19: =SUMPRODUCT(B16:B18,D4:D6)
A22: Required-return table (base case; Gordon TV at the same rate, 15x cap)
A23: Required return | B23: Value/share
A24: 0.09 | B24: =IF($A24>Assumptions!$B$4,(SUMPRODUCT(DCF_Base!$C$19:$L$19/(1+$A24)^DCF_Base!$C$4:$L$4)+MAX(0,MIN(DCF_Base!$L$19*(1+Assumptions!$B$4)/($A24-Assumptions!$B$4),Assumptions!$B$5*DCF_Base!$L$19))/(1+$A24)^10+Assumptions!$B$9+Assumptions!$C$16/(1+$A24)^Assumptions!$C$17)/Assumptions!$C$15,"n/a")
A25: 0.1 | B25: =IF($A25>Assumptions!$B$4,(SUMPRODUCT(DCF_Base!$C$19:$L$19/(1+$A25)^DCF_Base!$C$4:$L$4)+MAX(0,MIN(DCF_Base!$L$19*(1+Assumptions!$B$4)/($A25-Assumptions!$B$4),Assumptions!$B$5*DCF_Base!$L$19))/(1+$A25)^10+Assumptions!$B$9+Assumptions!$C$16/(1+$A25)^Assumptions!$C$17)/Assumptions!$C$15,"n/a")
A26: 0.11 | B26: =IF($A26>Assumptions!$B$4,(SUMPRODUCT(DCF_Base!$C$19:$L$19/(1+$A26)^DCF_Base!$C$4:$L$4)+MAX(0,MIN(DCF_Base!$L$19*(1+Assumptions!$B$4)/($A26-Assumptions!$B$4),Assumptions!$B$5*DCF_Base!$L$19))/(1+$A26)^10+Assumptions!$B$9+Assumptions!$C$16/(1+$A26)^Assumptions!$C$17)/Assumptions!$C$15,"n/a")
A27: 0.12 | B27: =IF($A27>Assumptions!$B$4,(SUMPRODUCT(DCF_Base!$C$19:$L$19/(1+$A27)^DCF_Base!$C$4:$L$4)+MAX(0,MIN(DCF_Base!$L$19*(1+Assumptions!$B$4)/($A27-Assumptions!$B$4),Assumptions!$B$5*DCF_Base!$L$19))/(1+$A27)^10+Assumptions!$B$9+Assumptions!$C$16/(1+$A27)^Assumptions!$C$17)/Assumptions!$C$15,"n/a")
A28: 0.15 | B28: =IF($A28>Assumptions!$B$4,(SUMPRODUCT(DCF_Base!$C$19:$L$19/(1+$A28)^DCF_Base!$C$4:$L$4)+MAX(0,MIN(DCF_Base!$L$19*(1+Assumptions!$B$4)/($A28-Assumptions!$B$4),Assumptions!$B$5*DCF_Base!$L$19))/(1+$A28)^10+Assumptions!$B$9+Assumptions!$C$16/(1+$A28)^Assumptions!$C$17)/Assumptions!$C$15,"n/a")
A29: 0.16 | B29: =IF($A29>Assumptions!$B$4,(SUMPRODUCT(DCF_Base!$C$19:$L$19/(1+$A29)^DCF_Base!$C$4:$L$4)+MAX(0,MIN(DCF_Base!$L$19*(1+Assumptions!$B$4)/($A29-Assumptions!$B$4),Assumptions!$B$5*DCF_Base!$L$19))/(1+$A29)^10+Assumptions!$B$9+Assumptions!$C$16/(1+$A29)^Assumptions!$C$17)/Assumptions!$C$15,"n/a")
A32: Sensitivity: base value/share, WACC x terminal growth
B33: 0.02 | C33: 0.025 | D33: 0.03 | E33: 0.035 | F33: 0.04
A34: 0.14 | B34: =IF($A34>B$33,(SUMPRODUCT(DCF_Base!$C$19:$L$19/(1+$A34)^DCF_Base!$C$4:$L$4)+MAX(0,MIN(DCF_Base!$L$19*(1+B$33)/($A34-B$33),Assumptions!$B$5*DCF_Base!$L$19))/(1+$A34)^10+Assumptions!$B$9+Assumptions!$C$16/(1+$A34)^Assumptions!$C$17)/Assumptions!$C$15,"n/a") | C34: =IF($A34>C$33,(SUMPRODUCT(DCF_Base!$C$19:$L$19/(1+$A34)^DCF_Base!$C$4:$L$4)+MAX(0,MIN(DCF_Base!$L$19*(1+C$33)/($A34-C$33),Assumptions!$B$5*DCF_Base!$L$19))/(1+$A34)^10+Assumptions!$B$9+Assumptions!$C$16/(1+$A34)^Assumptions!$C$17)/Assumptions!$C$15,"n/a") | D34: =IF($A34>D$33,(SUMPRODUCT(DCF_Base!$C$19:$L$19/(1+$A34)^DCF_Base!$C$4:$L$4)+MAX(0,MIN(DCF_Base!$L$19*(1+D$33)/($A34-D$33),Assumptions!$B$5*DCF_Base!$L$19))/(1+$A34)^10+Assumptions!$B$9+Assumptions!$C$16/(1+$A34)^Assumptions!$C$17)/Assumptions!$C$15,"n/a") | E34: =IF($A34>E$33,(SUMPRODUCT(DCF_Base!$C$19:$L$19/(1+$A34)^DCF_Base!$C$4:$L$4)+MAX(0,MIN(DCF_Base!$L$19*(1+E$33)/($A34-E$33),Assumptions!$B$5*DCF_Base!$L$19))/(1+$A34)^10+Assumptions!$B$9+Assumptions!$C$16/(1+$A34)^Assumptions!$C$17)/Assumptions!$C$15,"n/a") | F34: =IF($A34>F$33,(SUMPRODUCT(DCF_Base!$C$19:$L$19/(1+$A34)^DCF_Base!$C$4:$L$4)+MAX(0,MIN(DCF_Base!$L$19*(1+F$33)/($A34-F$33),Assumptions!$B$5*DCF_Base!$L$19))/(1+$A34)^10+Assumptions!$B$9+Assumptions!$C$16/(1+$A34)^Assumptions!$C$17)/Assumptions!$C$15,"n/a")
A35: 0.15 | B35: =IF($A35>B$33,(SUMPRODUCT(DCF_Base!$C$19:$L$19/(1+$A35)^DCF_Base!$C$4:$L$4)+MAX(0,MIN(DCF_Base!$L$19*(1+B$33)/($A35-B$33),Assumptions!$B$5*DCF_Base!$L$19))/(1+$A35)^10+Assumptions!$B$9+Assumptions!$C$16/(1+$A35)^Assumptions!$C$17)/Assumptions!$C$15,"n/a") | C35: =IF($A35>C$33,(SUMPRODUCT(DCF_Base!$C$19:$L$19/(1+$A35)^DCF_Base!$C$4:$L$4)+MAX(0,MIN(DCF_Base!$L$19*(1+C$33)/($A35-C$33),Assumptions!$B$5*DCF_Base!$L$19))/(1+$A35)^10+Assumptions!$B$9+Assumptions!$C$16/(1+$A35)^Assumptions!$C$17)/Assumptions!$C$15,"n/a") | D35: =IF($A35>D$33,(SUMPRODUCT(DCF_Base!$C$19:$L$19/(1+$A35)^DCF_Base!$C$4:$L$4)+MAX(0,MIN(DCF_Base!$L$19*(1+D$33)/($A35-D$33),Assumptions!$B$5*DCF_Base!$L$19))/(1+$A35)^10+Assumptions!$B$9+Assumptions!$C$16/(1+$A35)^Assumptions!$C$17)/Assumptions!$C$15,"n/a") | E35: =IF($A35>E$33,(SUMPRODUCT(DCF_Base!$C$19:$L$19/(1+$A35)^DCF_Base!$C$4:$L$4)+MAX(0,MIN(DCF_Base!$L$19*(1+E$33)/($A35-E$33),Assumptions!$B$5*DCF_Base!$L$19))/(1+$A35)^10+Assumptions!$B$9+Assumptions!$C$16/(1+$A35)^Assumptions!$C$17)/Assumptions!$C$15,"n/a") | F35: =IF($A35>F$33,(SUMPRODUCT(DCF_Base!$C$19:$L$19/(1+$A35)^DCF_Base!$C$4:$L$4)+MAX(0,MIN(DCF_Base!$L$19*(1+F$33)/($A35-F$33),Assumptions!$B$5*DCF_Base!$L$19))/(1+$A35)^10+Assumptions!$B$9+Assumptions!$C$16/(1+$A35)^Assumptions!$C$17)/Assumptions!$C$15,"n/a")
A36: 0.16 | B36: =IF($A36>B$33,(SUMPRODUCT(DCF_Base!$C$19:$L$19/(1+$A36)^DCF_Base!$C$4:$L$4)+MAX(0,MIN(DCF_Base!$L$19*(1+B$33)/($A36-B$33),Assumptions!$B$5*DCF_Base!$L$19))/(1+$A36)^10+Assumptions!$B$9+Assumptions!$C$16/(1+$A36)^Assumptions!$C$17)/Assumptions!$C$15,"n/a") | C36: =IF($A36>C$33,(SUMPRODUCT(DCF_Base!$C$19:$L$19/(1+$A36)^DCF_Base!$C$4:$L$4)+MAX(0,MIN(DCF_Base!$L$19*(1+C$33)/($A36-C$33),Assumptions!$B$5*DCF_Base!$L$19))/(1+$A36)^10+Assumptions!$B$9+Assumptions!$C$16/(1+$A36)^Assumptions!$C$17)/Assumptions!$C$15,"n/a") | D36: =IF($A36>D$33,(SUMPRODUCT(DCF_Base!$C$19:$L$19/(1+$A36)^DCF_Base!$C$4:$L$4)+MAX(0,MIN(DCF_Base!$L$19*(1+D$33)/($A36-D$33),Assumptions!$B$5*DCF_Base!$L$19))/(1+$A36)^10+Assumptions!$B$9+Assumptions!$C$16/(1+$A36)^Assumptions!$C$17)/Assumptions!$C$15,"n/a") | E36: =IF($A36>E$33,(SUMPRODUCT(DCF_Base!$C$19:$L$19/(1+$A36)^DCF_Base!$C$4:$L$4)+MAX(0,MIN(DCF_Base!$L$19*(1+E$33)/($A36-E$33),Assumptions!$B$5*DCF_Base!$L$19))/(1+$A36)^10+Assumptions!$B$9+Assumptions!$C$16/(1+$A36)^Assumptions!$C$17)/Assumptions!$C$15,"n/a") | F36: =IF($A36>F$33,(SUMPRODUCT(DCF_Base!$C$19:$L$19/(1+$A36)^DCF_Base!$C$4:$L$4)+MAX(0,MIN(DCF_Base!$L$19*(1+F$33)/($A36-F$33),Assumptions!$B$5*DCF_Base!$L$19))/(1+$A36)^10+Assumptions!$B$9+Assumptions!$C$16/(1+$A36)^Assumptions!$C$17)/Assumptions!$C$15,"n/a")
A37: 0.17 | B37: =IF($A37>B$33,(SUMPRODUCT(DCF_Base!$C$19:$L$19/(1+$A37)^DCF_Base!$C$4:$L$4)+MAX(0,MIN(DCF_Base!$L$19*(1+B$33)/($A37-B$33),Assumptions!$B$5*DCF_Base!$L$19))/(1+$A37)^10+Assumptions!$B$9+Assumptions!$C$16/(1+$A37)^Assumptions!$C$17)/Assumptions!$C$15,"n/a") | C37: =IF($A37>C$33,(SUMPRODUCT(DCF_Base!$C$19:$L$19/(1+$A37)^DCF_Base!$C$4:$L$4)+MAX(0,MIN(DCF_Base!$L$19*(1+C$33)/($A37-C$33),Assumptions!$B$5*DCF_Base!$L$19))/(1+$A37)^10+Assumptions!$B$9+Assumptions!$C$16/(1+$A37)^Assumptions!$C$17)/Assumptions!$C$15,"n/a") | D37: =IF($A37>D$33,(SUMPRODUCT(DCF_Base!$C$19:$L$19/(1+$A37)^DCF_Base!$C$4:$L$4)+MAX(0,MIN(DCF_Base!$L$19*(1+D$33)/($A37-D$33),Assumptions!$B$5*DCF_Base!$L$19))/(1+$A37)^10+Assumptions!$B$9+Assumptions!$C$16/(1+$A37)^Assumptions!$C$17)/Assumptions!$C$15,"n/a") | E37: =IF($A37>E$33,(SUMPRODUCT(DCF_Base!$C$19:$L$19/(1+$A37)^DCF_Base!$C$4:$L$4)+MAX(0,MIN(DCF_Base!$L$19*(1+E$33)/($A37-E$33),Assumptions!$B$5*DCF_Base!$L$19))/(1+$A37)^10+Assumptions!$B$9+Assumptions!$C$16/(1+$A37)^Assumptions!$C$17)/Assumptions!$C$15,"n/a") | F37: =IF($A37>F$33,(SUMPRODUCT(DCF_Base!$C$19:$L$19/(1+$A37)^DCF_Base!$C$4:$L$4)+MAX(0,MIN(DCF_Base!$L$19*(1+F$33)/($A37-F$33),Assumptions!$B$5*DCF_Base!$L$19))/(1+$A37)^10+Assumptions!$B$9+Assumptions!$C$16/(1+$A37)^Assumptions!$C$17)/Assumptions!$C$15,"n/a")
A38: 0.18 | B38: =IF($A38>B$33,(SUMPRODUCT(DCF_Base!$C$19:$L$19/(1+$A38)^DCF_Base!$C$4:$L$4)+MAX(0,MIN(DCF_Base!$L$19*(1+B$33)/($A38-B$33),Assumptions!$B$5*DCF_Base!$L$19))/(1+$A38)^10+Assumptions!$B$9+Assumptions!$C$16/(1+$A38)^Assumptions!$C$17)/Assumptions!$C$15,"n/a") | C38: =IF($A38>C$33,(SUMPRODUCT(DCF_Base!$C$19:$L$19/(1+$A38)^DCF_Base!$C$4:$L$4)+MAX(0,MIN(DCF_Base!$L$19*(1+C$33)/($A38-C$33),Assumptions!$B$5*DCF_Base!$L$19))/(1+$A38)^10+Assumptions!$B$9+Assumptions!$C$16/(1+$A38)^Assumptions!$C$17)/Assumptions!$C$15,"n/a") | D38: =IF($A38>D$33,(SUMPRODUCT(DCF_Base!$C$19:$L$19/(1+$A38)^DCF_Base!$C$4:$L$4)+MAX(0,MIN(DCF_Base!$L$19*(1+D$33)/($A38-D$33),Assumptions!$B$5*DCF_Base!$L$19))/(1+$A38)^10+Assumptions!$B$9+Assumptions!$C$16/(1+$A38)^Assumptions!$C$17)/Assumptions!$C$15,"n/a") | E38: =IF($A38>E$33,(SUMPRODUCT(DCF_Base!$C$19:$L$19/(1+$A38)^DCF_Base!$C$4:$L$4)+MAX(0,MIN(DCF_Base!$L$19*(1+E$33)/($A38-E$33),Assumptions!$B$5*DCF_Base!$L$19))/(1+$A38)^10+Assumptions!$B$9+Assumptions!$C$16/(1+$A38)^Assumptions!$C$17)/Assumptions!$C$15,"n/a") | F38: =IF($A38>F$33,(SUMPRODUCT(DCF_Base!$C$19:$L$19/(1+$A38)^DCF_Base!$C$4:$L$4)+MAX(0,MIN(DCF_Base!$L$19*(1+F$33)/($A38-F$33),Assumptions!$B$5*DCF_Base!$L$19))/(1+$A38)^10+Assumptions!$B$9+Assumptions!$C$16/(1+$A38)^Assumptions!$C$17)/Assumptions!$C$15,"n/a")
A41: Current price NZ$0.25 for reference | B41: =Assumptions!$B$10
