Workbook

Sheet Model_Info
A1: IFT.NZ — Infratil Limited — Valuation Model
A3: Version | B3: 2026-08-28 refresh. Supersedes the 2026-06-29 model built at NZ$14.99 (originally NZ$15.32).
A4: Built by | B4: dcf-analyst agent (Claude Opus 5), 2026-08-28, at the user's request via the research pipeline.
A5: Model type | B5: Look-through proportionate earnings capitalization, blended with portfolio NAV/SOTP.
A6: Why not owner-FCF DCF | B6: Infratil is an externally managed infrastructure HOLDCO. Consolidated net income is portfolio-revaluation noise (FY25 -NZ$286.3m, FY26 +NZ$549.8m); there is no group revenue/margin structure; reported FCF is deeply negative by design because proportionate capex (NZ$2,687m FY26) is investment, not cost. Per dcf-methods SKILL.md the holdco/LIC straddle is valued in parts and stated as such.
A7: PRICE ANCHOR | B7: NZ$14.42 at 2026-08-27T23:54:54Z (2026-08-28 11:54 NZT), Yahoo regularMarketPrice, live regular-session print. GOES STALE — refresh before use.
A8: Balance sheet | B8: 31 March 2026 (FY2026 Annual Report). Net debt NZ$3,204.6m, restated to NZ$2,987.5m for NZ$217.1m Fortysouth proceeds received 10-Apr-2026 (Note 31).
A9: Share count | B9: 999,312,470 at 31-Mar-2026 (Annual Report lines 2435, 7585). Held FLAT — see Assumptions note; this UNDERSTATES likely dilution.
A10: Earnings base | B10: NZ$919.3m Proportionate EBITDAF (continuing) per the FY26 Annual Results Presentation reconciliation (IFT.NZ_Metrics_FY2026.txt lines 1058-1081), less NZ$35m estimated Morrison incentive fees = NZ$884.3m.
A11: KEY CORRECTION v prior | B11: Prior model used 989.4 - 124 = 865.4, which double-deducted corporate costs (the NZ$989.4m headline already nets them: 1,113.7 - 124.3 = 989.4 exactly) and omitted NZ$70.1m development spend. Fixed by taking the filing's own reconciled 919.3 line.
A12: Guidance | B12: FY27 Proportionate Operational EBITDAF NZ$1,300-1,400m, EXCLUDING corporate costs (basis changed from FY26). Corporate costs guided NZ$150-170m, development spend NZ$95-110m separately. Reaffirmed unchanged at the 18-Aug-2026 AGM.
A13: Scenario drivers | B13: Set by the dcf-analyst agent on 2026-08-28 from FY27 guidance rebased to the continuing basis. Y1 base 18% = guidance midpoint. Prior model's 20% was anchored to an inconsistent basis comparison and was CUT this cycle.
A14: NAV anchors | B14: TWO DATES. Statutory NZ$16.48/share (31-Mar-2026, restated for Fortysouth). Live NZ$18.52/share marking ONLY CDC to its 30-Jun-2026 independent valuation of A$18.5bn; all other assets at March marks. Do not mix.
... A18: STALENESS WARNING | B18: All figures go stale. Price is intraday. NAV marks are quarterly. Guidance is management's, not audited outcome.

Sheet Reconciliation
A1: Reconciliation vs prior version (2026-06-29 @ NZ$14.99)
A3: Prior per-share values (hardcoded, as published)
A4: Prior bear | B4: 7.21
A5: Prior base | B5: 15.8
A6: Prior bull | B6: 27.08
A7: Prior weighted | B7: 17.47
A8: Prior price | B8: 14.99
A10: Bridge (approximate attribution; live cells below are authoritative)
A11: Prior weighted IV | B11: 17.47
A12: FCF base corrected: remove double-counted corporate costs, deduct omitted development spend (865.4 -> 919.3) | B12: 1.08
A13: Deduct estimated Morrison incentive fees not captured in EBITDAF (-NZ$35m/yr) | B13: -0.71
A14: Net debt reduced for Fortysouth proceeds received 10-Apr-2026 (-NZ$217.1m) | B14: 0.22
A15: Y1 base growth cut 20% -> 18% on FY27 guidance basis change, with bull/bear rebased to the guidance range on a consistent basis | B15: -1.94
A16: Scenario weights shifted 20/50/30 -> 25/50/25 | B16: -0.77
A17: New weighted IV | B17: 15.35
A18: Bridge total (check) | B18: =B12+SUM(B13:B17)
A20: LIVE weighted IV (links to Valuation) | B20: =Valuation!B8
A21: The bridge is decomposed sequentially and individual line attributions are approximate because the growth and weighting changes interact; the endpoints are exact. The dominant driver of the NZ$2.12 decline is not the price move (which affects upside, not IV) but the combination of the corrected earnings base, the incentive-fee charge and the lower guidance-consistent growth rate.
A22: Price moved NZ$14.99 -> NZ$14.42 (-3.8%) since the prior refresh and NZ$15.32 -> NZ$14.42 (-5.9%) since the original build. Price does not affect intrinsic value; it affects upside, which falls from a reported 14.0% to 6.4% - most of that reduction is the IV correction, not the price.

Sheet Actuals
A1: Reported history and guidance (all hardcoded)
A3: Proportionate EBITDAF reconciliation (NZ$m) | B3: FY2025 | C3: FY2026 | D3: Source
A4: Operational EBITDAF | B4: 1008.1 | C4: 1113.7 | D4: Presentation line 1067
A5: less Development Spend | B5: -68.6 | C5: -70.1 | D5: Presentation line 1072
A6: less Corporate costs | B6: -112.8 | C6: -124.3 | D6: Presentation line 1073
A7: Total: Proportionate EBITDAF (continuing) | B7: =SUM(B4:B6) | C7: =SUM(C4:C6) | D7: Presentation line 1074: 826.7 (FY25) and 919.3 (FY26)
A8: Memo: headline "Prop Operational EBITDAF" | B8: 895.3 | C8: 989.4 | D8: Operational less corporate ONLY (dev NOT deducted)
A10: Balance sheet / capital (NZ$m)
A11: Net debt at 31-Mar-2026 | B11: 3204.6 | C11: FY26 Metrics CSV / balance sheet
A12: less Fortysouth proceeds recd 10-Apr-2026 | B12: -217.1 | C12: Annual Report Note 31 Events After Balance Date
A13: Total: Net debt used in model | B13: =SUM(B11:B12) | C13: restated
A14: Shares on issue (m) | B14: 999.3 | C14: Annual Report line 2435: 999,312,470
A15: Portfolio asset value 31-Mar-2026 | B15: 20624 | C15: Presentation line 983
A16: PV of management agreement | B16: -1168.4 | C16: NAV bridge; base+incentive fees, 5yr discounted
A17: Proportionate capex FY2026 | B17: 2686.6 | C17: Presentation line 1071
A18: SBC (KMP share based payments) | B18: 1.2 | C18: Annual Report Note 27 line 4505 — immaterial
A20: FY2027 guidance (NZ$m unless stated) | B20: Low | C20: High
A21: Proportionate Operational EBITDAF (EXCL corporate costs) | B21: 1300 | C21: 1400
A22: Corporate costs | B22: 150 | C22: 170
A23: Development spend (IFT share) | B23: 95 | C23: 110
A24: Proportionate capital expenditure | B24: 3800 | C24: 4400
A25: CDC EBITDAF (A$m, 100%) | B25: 680 | C25: 720
A26: One NZ EBITDAF | B26: 600 | C26: 640
A27: Longroad EBITDAF (US$m) | B27: 120 | C27: 135
A28: RHCNZ EBITDAF | B28: 115 | C28: 135
A29: Qscan EBITDAF (A$m) | B29: 90 | C29: 105
A30: Wellington Airport EBITDAF | B30: 130 | C30: 140
A32: Guidance on THIS MODEL's continuing basis (after dev spend AND corporate costs)
A33: Low = 1300 - 110 - 170 | B33: =1300-110-170 | C33: =B33/C7-1
A34: Mid = 1350 - 102.5 - 160 | B34: =1350-102.5-160 | C34: =B34/C7-1
A35: High = 1400 - 95 - 150 | B35: =1400-95-150 | C35: =B35/C7-1
A36: FY26 actual growth on continuing basis (826.7 -> 919.3) | B36: =C7/B7-1

Sheet Assumptions
A1: Global assumptions
A3: Earnings base FY2026 (continuing) | B3: 919.3 | E3: Actuals!C7 — filing reconciled bottom line
A4: less estimated Morrison incentive fees | B4: -35 | E4: EBITDAF definition excludes incentive fees; they accrue to the manager not shareholders. ESTIMATE — softest input in the model.
A5: Total: Base flow used (FY0) | B5: =B3+B4 | E5: last_fcf
A6: Net debt (restated) | B6: 2987.5 | E6: 31-Mar-2026 less Fortysouth proceeds
A7: Shares outstanding (m) | B7: 999.3 | E7: 31-Mar-2026, held FLAT — understates likely dilution
A8: Current price (NZ$) | B8: 14.42 | E8: 2026-08-28 11:54 NZT live — STALE ON READ
A9: Hurdle rate for entry price | B9: 0.15 | E9: house 15%
A10: NAV/share statutory 31-Mar-2026 | B10: 16.48 | E10: restated for Fortysouth
A11: NAV/share live (CDC @ 30-Jun-2026) | B11: 18.52 | E11: only CDC re-marked; others at March
A13: Per-scenario parameters | B13: Bear | C13: Base | D13: Bull
A14: WACC | B14: 0.12 | C14: 0.105 | D14: 0.095
A15: Terminal growth | B15: 0.02 | C15: 0.03 | D15: 0.035
A16: Probability weight | B16: 0.25 | C16: 0.5 | D16: 0.25
A17: Weights check (must = 100%) | B17: =SUM(B16:D16)
A19: Scenario narratives
A20: BEAR | B20: Y1 8% is deliberately set BELOW the bottom of FY27 guidance on the continuing basis (+11.0%) and below FY26 actual (11.2%), because the bear case is precisely the case where guidance is missed. Drivers: the AI capex cycle cools and CDC's contracted ramp slips; One NZ continues to deteriorate (its portfolio value FELL 8.8% in FY26, from NZ$3,713.5m to NZ$3,386.7m - the only major asset to decline and an underappreciated drag); NZ macro weakness hits Wellington Airport and RHCNZ; corporate costs and development spend keep compounding faster than earnings. WACC 12% prices concentration risk in a single asset (CDC = 43% of portfolio) plus the equity-issuance dependency. POST-JUNE EVIDENCE ADDED: the bear case now also carries CDC mark-to-model risk explicitly. CDC's independent valuation rose 23.6% in the June-2026 quarter to A$18.5bn while its OWN assessed cost of equity ROSE from 11.84% to 12.45% on a higher risk-free rate - i.e. the uplift came entirely from pipeline and contract assumptions (leasable pipeline 2.6GW -> 3.9GW through FY2040), against a headwind from the discount rate, not from cheaper capital. A 43%-of-portfolio unlisted asset re-marked upward 23.6% in one quarter on model inputs is precisely what a bear case should refuse to extrapolate. Additional dated risks now reflected: the OBBBA tightened IRA credit timelines (construction start by 4-Jul-2026, in-service by 31-Dec-2027, plus FEOC rules) which is a concrete threat to Longroad economics, and Longroad's underlying USD valuation has already EASED on higher base rates with the NZD-translated value rising only on FX; the July-2026 NZ government proposal to reallocate Spark/One NZ 2600MHz spectrum to 2degrees compounds One NZ's 8.8% FY26 value decline; and Wellington Airport passengers fell to 5.1m from 5.3m.
A21: BASE | B21: Y1 18% = FY27 guidance midpoint rebased to the continuing basis (see growth_divergence_warning). Reduced from the prior model's 20%, which was anchored to the headline guidance ratio without adjusting for the corporate-cost basis change. Y2-Y5 taper as the CDC ramp annualises and the development-spend and corporate-cost lines - both growing faster than EBITDAF - continue to absorb a rising share of look-through earnings. WACC 10.5% built in NZD to match NZD flows: NZ 10-yr government bond ~4.5% + beta 1.2 x ERP 5.0% + 0.5% complexity/external-management premium. Terminal 3.0% = long-run NZD nominal GDP. GUIDANCE REAFFIRMED: FY27 guidance of NZ$1,300-1,400m was explicitly reaffirmed unchanged at the 18-August-2026 AGM, five months into the financial year. That is recent, specific corroboration and it is why the base case still anchors Y1 to the guidance midpoint despite FY26 actual growth of only 11.2%.
A22: BULL | B22: Y1 26% approximates the TOP of FY27 guidance on the continuing basis (+25.6%), i.e. EBITDAF at NZ$1,400m with corporate costs and development spend at the LOW end of their guided ranges - the combination that maximises look-through earnings. Beyond Y1: CDC sustains the AI-datacentre ramp past the contracted 1GW, Longroad reaches its US$1bn run-rate EBITDAF ambition, Kao Data scales in the UK, and the NAV discount closes. WACC 9.5% reflects the completed debt-platform reset and BBB+ rating maturing.

Sheet DCF_Bear
A1: IFT.NZ — BEAR scenario
A2: Yellow = editable driver. Green = link. Orange = output.
A3: Year | B3: FY2026A | C3: FY2027E | D3: FY2028E | E3: FY2029E | F3: FY2030E | G3: FY2031E
A4: Year index | B4: 0 | C4: 1 | D4: 2 | E4: 3 | F4: 4 | G4: 5
A5: Growth in look-through earnings YoY <-- DRIVER | C5: 0.08 | D5: 0.06 | E5: 0.04 | F5: 0.03 | G5: 0.02
A6: Look-through earnings (prop. EBITDAF less incentive fees) | B6: =Assumptions!$B$5 | C6: =B6*(1+C5) | D6: =C6*(1+D5) | E6: =D6*(1+E5) | F6: =E6*(1+F5) | G6: =F6*(1+G5)
A7: Discount factor | C7: =1/(1+Assumptions!$B$14)^C4 | D7: =1/(1+Assumptions!$B$14)^D4 | E7: =1/(1+Assumptions!$B$14)^E4 | F7: =1/(1+Assumptions!$B$14)^F4 | G7: =1/(1+Assumptions!$B$14)^G4
A8: PV of earnings | C8: =C6*C7 | D8: =D6*D7 | E8: =E6*E7 | F8: =F6*F7 | G8: =G6*G7
A10: VALUATION
A11: Sum of PV of explicit earnings | B11: =SUM(C8:G8)
A12: Terminal growth | B12: =Assumptions!$B$15
A13: Terminal-year earnings | B13: =G6*(1+B12)
A14: Terminal value (Gordon) | B14: =B13/(Assumptions!$B$14-B12)
A15: Implied exit multiple (x terminal earnings) | B15: =B14/G6
A16: PV of terminal value | B16: =B14*G7
A17: Enterprise value | B17: =B11+B16
A18: less Net debt | B18: =-Assumptions!$B$6
A19: Equity value | B19: =B17+B18
A20: Shares outstanding (m) | B20: =Assumptions!$B$7
A21: VALUE PER SHARE (NZ$) | B21: =B19/B20
A22: Upside vs current price | B22: =B21/Assumptions!$B$8-1
A23: Terminal % of EV | B23: =B16/B17
A25: ENTRY PRICE at hurdle rate
A26: PV of earnings at hurdle | B26: =SUMPRODUCT(C6:G6,1/(1+Assumptions!$B$9)^C4:G4)
A27: PV of terminal value at hurdle | B27: =B14/(1+Assumptions!$B$9)^G4
A28: ENTRY PRICE (NZ$) | B28: =(B26+B27-Assumptions!$B$6)/Assumptions!$B$7
A29: Discount vs current price | B29: =B28/Assumptions!$B$8-1
A31: Memo: implied EV/EBITDAF on FY26 continuing 919.3 | B31: =B17/919.3

Sheet DCF_Base
A1: IFT.NZ — BASE scenario
A2: Yellow = editable driver. Green = link. Orange = output.
A3: Year | B3: FY2026A | C3: FY2027E | D3: FY2028E | E3: FY2029E | F3: FY2030E | G3: FY2031E
A4: Year index | B4: 0 | C4: 1 | D4: 2 | E4: 3 | F4: 4 | G4: 5
A5: Growth in look-through earnings YoY <-- DRIVER | C5: 0.18 | D5: 0.15 | E5: 0.12 | F5: 0.09 | G5: 0.07
A6: Look-through earnings (prop. EBITDAF less incentive fees) | B6: =Assumptions!$B$5 | C6: =B6*(1+C5) | D6: =C6*(1+D5) | E6: =D6*(1+E5) | F6: =E6*(1+F5) | G6: =F6*(1+G5)
A7: Discount factor | C7: =1/(1+Assumptions!$C$14)^C4 | D7: =1/(1+Assumptions!$C$14)^D4 | E7: =1/(1+Assumptions!$C$14)^E4 | F7: =1/(1+Assumptions!$C$14)^F4 | G7: =1/(1+Assumptions!$C$14)^G4
A8: PV of earnings | C8: =C6*C7 | D8: =D6*D7 | E8: =E6*E7 | F8: =F6*F7 | G8: =G6*G7
A10: VALUATION
A11: Sum of PV of explicit earnings | B11: =SUM(C8:G8)
A12: Terminal growth | B12: =Assumptions!$C$15
A13: Terminal-year earnings | B13: =G6*(1+B12)
A14: Terminal value (Gordon) | B14: =B13/(Assumptions!$C$14-B12)
A15: Implied exit multiple (x terminal earnings) | B15: =B14/G6
A16: PV of terminal value | B16: =B14*G7
A17: Enterprise value | B17: =B11+B16
A18: less Net debt | B18: =-Assumptions!$B$6
A19: Equity value | B19: =B17+B18
A20: Shares outstanding (m) | B20: =Assumptions!$B$7
A21: VALUE PER SHARE (NZ$) | B21: =B19/B20
A22: Upside vs current price | B22: =B21/Assumptions!$B$8-1
A23: Terminal % of EV | B23: =B16/B17
A25: ENTRY PRICE at hurdle rate
A26: PV of earnings at hurdle | B26: =SUMPRODUCT(C6:G6,1/(1+Assumptions!$B$9)^C4:G4)
A27: PV of terminal value at hurdle | B27: =B14/(1+Assumptions!$B$9)^G4
A28: ENTRY PRICE (NZ$) | B28: =(B26+B27-Assumptions!$B$6)/Assumptions!$B$7
A29: Discount vs current price | B29: =B28/Assumptions!$B$8-1
A31: Memo: implied EV/EBITDAF on FY26 continuing 919.3 | B31: =B17/919.3

Sheet DCF_Bull
A1: IFT.NZ — BULL scenario
A2: Yellow = editable driver. Green = link. Orange = output.
A3: Year | B3: FY2026A | C3: FY2027E | D3: FY2028E | E3: FY2029E | F3: FY2030E | G3: FY2031E
A4: Year index | B4: 0 | C4: 1 | D4: 2 | E4: 3 | F4: 4 | G4: 5
A5: Growth in look-through earnings YoY <-- DRIVER | C5: 0.26 | D5: 0.21 | E5: 0.17 | F5: 0.13 | G5: 0.1
A6: Look-through earnings (prop. EBITDAF less incentive fees) | B6: =Assumptions!$B$5 | C6: =B6*(1+C5) | D6: =C6*(1+D5) | E6: =D6*(1+E5) | F6: =E6*(1+F5) | G6: =F6*(1+G5)
A7: Discount factor | C7: =1/(1+Assumptions!$D$14)^C4 | D7: =1/(1+Assumptions!$D$14)^D4 | E7: =1/(1+Assumptions!$D$14)^E4 | F7: =1/(1+Assumptions!$D$14)^F4 | G7: =1/(1+Assumptions!$D$14)^G4
A8: PV of earnings | C8: =C6*C7 | D8: =D6*D7 | E8: =E6*E7 | F8: =F6*F7 | G8: =G6*G7
A10: VALUATION
A11: Sum of PV of explicit earnings | B11: =SUM(C8:G8)
A12: Terminal growth | B12: =Assumptions!$D$15
A13: Terminal-year earnings | B13: =G6*(1+B12)
A14: Terminal value (Gordon) | B14: =B13/(Assumptions!$D$14-B12)
A15: Implied exit multiple (x terminal earnings) | B15: =B14/G6
A16: PV of terminal value | B16: =B14*G7
A17: Enterprise value | B17: =B11+B16
A18: less Net debt | B18: =-Assumptions!$B$6
A19: Equity value | B19: =B17+B18
A20: Shares outstanding (m) | B20: =Assumptions!$B$7
A21: VALUE PER SHARE (NZ$) | B21: =B19/B20
A22: Upside vs current price | B22: =B21/Assumptions!$B$8-1
A23: Terminal % of EV | B23: =B16/B17
A25: ENTRY PRICE at hurdle rate
A26: PV of earnings at hurdle | B26: =SUMPRODUCT(C6:G6,1/(1+Assumptions!$B$9)^C4:G4)
A27: PV of terminal value at hurdle | B27: =B14/(1+Assumptions!$B$9)^G4
A28: ENTRY PRICE (NZ$) | B28: =(B26+B27-Assumptions!$B$6)/Assumptions!$B$7
A29: Discount vs current price | B29: =B28/Assumptions!$B$8-1
A31: Memo: implied EV/EBITDAF on FY26 continuing 919.3 | B31: =B17/919.3

Sheet Earnings_Quality
A1: Earnings quality — what the flow is and is NOT
B3: FY2025 | C3: FY2026 | D3: Note
A4: Operational EBITDAF (sum of investees) | B4: 1008.1 | C4: 1113.7 | D4: Infratil share of investee EBITDAF
A5: less Development spend | B5: -68.6 | C5: -70.1 | D5: Gurin/Galileo/Mint non-capitalised — REAL cash out
A6: less Corporate costs | B6: -112.8 | C6: -124.3 | D6: includes Morrison BASE fee NZ$101.4m FY26
A7: Total: Proportionate EBITDAF (continuing) | B7: =SUM(B4:B6) | C7: =SUM(C4:C6) | D7: the filing's own bottom line
A8: less est. Morrison INCENTIVE fees | B8: -35 | C8: -35 | D8: excluded from EBITDAF by definition — accrues to manager
A9: Total: Flow used in this model | B9: =B7+B8 | C9: =C7+C8 | D9: last_fcf
A11: THIS IS NOT FREE CASH FLOW
A12: Proportionate capital expenditure | B12: 2294.4 | C12: 2686.6
A13: Capex as multiple of look-through earnings | B13: =B12/B9 | C13: =C12/C9
A14: FY27 capex guidance low / high | B14: 3800 | C14: 4400
A15: Infratil is deeply cash-flow negative at the portfolio level BY DESIGN. The gap is funded with debt and equity issuance (shares 968.1m -> 999.3m in FY26; net debt 2,187.8 -> 3,204.6). This model values look-through EARNINGS, on the proposition that the capex compounds into value. Nothing here implies shareholders can extract NZ$884m a year.
A17: Memo: SBC (KMP share based payments) | B17: 1.2 | D17: Immaterial (0.13% of flow). For this externally managed holdco the compensation leak that matters is the Morrison fee, not SBC.

Sheet Valuation
A1: Valuation summary
A3: Scenario | B3: Value/share | C3: Upside | D3: Weight | E3: Entry @15%
A4: Bear | B4: ='DCF_Bear'!B21 | C4: =B4/Assumptions!$B$8-1 | D4: =Assumptions!B16 | E4: ='DCF_Bear'!B28
A5: Base | B5: ='DCF_Base'!B21 | C5: =B5/Assumptions!$B$8-1 | D5: =Assumptions!C16 | E5: ='DCF_Base'!B28
A6: Bull | B6: ='DCF_Bull'!B21 | C6: =B6/Assumptions!$B$8-1 | D6: =Assumptions!D16 | E6: ='DCF_Bull'!B28
A7: Current price | B7: =Assumptions!$B$8
A8: PROBABILITY-WEIGHTED IV | B8: =SUMPRODUCT(B4:B6,D4:D6) | C8: =B8/Assumptions!$B$8-1 | E8: =SUMPRODUCT(E4:E6,D4:D6)
A10: NAV cross-check
A11: NAV/share statutory (31-Mar-2026) | B11: =Assumptions!$B$10 | C11: =Assumptions!$B$8/B11 | D11: P/NAV
A12: NAV/share live (CDC @ 30-Jun-2026) | B12: =Assumptions!$B$11 | C12: =Assumptions!$B$8/B12 | D12: P/NAV
A13: Base IV as % of statutory NAV | B13: =B5/Assumptions!$B$10
A15: Sensitivity: value per share (rows WACC, cols terminal growth)
A16: WACC \ g | B16: 0.02 | C16: 0.025 | D16: 0.03 | E16: 0.035 | F16: 0.04
A17: 0.085 | B17: 18.52 | C17: 19.97 | D17: 21.68 | E17: 23.74 | F17: 26.26
A18: 0.095 | B18: 15.56 | C18: 16.6 | D18: 17.8 | E18: 19.19 | F18: 20.85
A19: 0.105 | B19: 13.3 | C19: 14.07 | D19: 14.95 | E19: 15.95 | F19: 17.11
A20: 0.115 | B20: 11.51 | C20: 12.11 | D20: 12.77 | E20: 13.52 | F20: 14.36
A21: 0.125 | B21: 10.07 | C21: 10.54 | D21: 11.06 | E21: 11.63 | F21: 12.27
A22: Grid is base-case growth path re-solved at each WACC/g pair (hardcoded from the JSON; base cell highlighted).
A24: Implied multiples vs 5-year trading history
B25: Now | C25: 5y avg | D25: 5y max
A26: EV/EBITDAF trailing (headline basis 989.4) | B26: =(Assumptions!$B$8*Assumptions!$B$7+Assumptions!$B$6)/989.4 | C26: 13.66 | D26: 15.01
A27: EV/EBITDAF forward (FY27 headline 1190) | B27: =(Assumptions!$B$8*Assumptions!$B$7+Assumptions!$B$6)/1190 | C27: 13.66 | D27: 15.01
A28: P/B (BVPS FY26 17.43) | B28: =Assumptions!$B$8/17.43 | C28: 0.71 | D28: 0.78
A30: Trailing multiples sit ABOVE their 5-year maxima; the FORWARD multiple sits inside the band. The model requires guidance delivery, not a re-rating.
