Workbook

Sheet DCF Model
A1: CRWD DCF Valuation Model — Base Case (Interactive)
A2: Gray cells are INPUTS — adjust to see results update automatically. All monetary values in USD millions.
A4: KEY INPUTS
A5: Current Stock Price (USD) | B5: 435
A6: Shares Outstanding (millions, diluted) | B6: 251.3
A7: Cash & Equivalents (M) | B7: 4323.3
A8: Total Debt (M) | B8: 744
A9: Net Debt (M) [Debt - Cash, negative = net cash] | B9: =B8-B7 -> 0
A10: Base Year FCF (M) [FY2025 actuals] | B10: 1067.9
A12: WACC | B12: 0.1
A13: Terminal Growth Rate | B13: 0.03
A15: FCF GROWTH ASSUMPTIONS (Base Case — gray cells are editable inputs)
C16: Year 1 (FY2026E) | D16: Year 2 (FY2027E) | E16: Year 3 (FY2028E) | F16: Year 4 (FY2029E) | G16: Year 5 (FY2030E)
A17: FCF Growth Rate | C17: 0.22 | D17: 0.2 | E17: 0.18 | F17: 0.15 | G17: 0.12
A19: PROJECTED FREE CASH FLOWS
B20: Y0 (Base) | C20: Year 1 (FY2026E) | D20: Year 2 (FY2027E) | E20: Year 3 (FY2028E) | F20: Year 4 (FY2029E) | G20: Year 5 (FY2030E)
A21: Free Cash Flow (M) | B21: =B10 -> 0 | C21: =B21*(1+C17) -> 0 | D21: =C21*(1+D17) -> 0 | E21: =D21*(1+E17) -> 0 | F21: =E21*(1+F17) -> 0 | G21: =F21*(1+G17) -> 0
A22: Discount Factor [1 / (1+WACC)^n] | C22: =1/(1+$B$12)^1 -> 0 | D22: =1/(1+$B$12)^2 -> 0 | E22: =1/(1+$B$12)^3 -> 0 | F22: =1/(1+$B$12)^4 -> 0 | G22: =1/(1+$B$12)^5 -> 0
A23: PV of Free Cash Flow (M) | C23: =C21*C22 -> 0 | D23: =D21*D22 -> 0 | E23: =E21*E22 -> 0 | F23: =F21*F22 -> 0 | G23: =G21*G22 -> 0
A25: VALUATION BRIDGE
A26: Sum of PV of FCF (M) | B26: =SUM(C23:G23) -> 0
A27: Terminal FCF [Y5 FCF x (1+g)] | B27: =G21*(1+$B$13) -> 0
A28: Terminal Value [Terminal FCF / (WACC - g)] | B28: =B27/($B$12-$B$13) -> 0
A29: PV of Terminal Value [TV x Y5 Discount Factor] | B29: =B28*G22 -> 0
A30: Enterprise Value (M) | B30: =B26+B29 -> 0
A31: Less: Net Debt (M) [negative = net cash adds value] | B31: =B9 -> 0
A32: Equity Value (M) | B32: =B30-B31 -> 0
A33: INTRINSIC VALUE PER SHARE (Base Case) | B33: =B32/B6 -> 0
A35: ENTRY PRICE TARGET (Required for 15% CAGR to Terminal Value)
A36: Terminal Value per Share | B36: =B28/B6 -> 0
A37: Entry Price for 15% CAGR [TV/share / (1.15)^5] | B37: =B36/(1.15^5) -> 0
A39: Upside / (Downside) to Intrinsic Value | B39: =(B33-B5)/B5 -> 0
A40: Premium vs Entry Price (buy below this for 15% CAGR) | B40: =(B5-B37)/B5 -> 0
A42: METHODOLOGY NOTE: FCF growth rates (C17:G17) reflect 22%/20%/18%/15%/12% annual FCF growth anchored to FY2026 management guidance (~22% revenue) and FY2027 target (~20% net new ARR growth). FCF used directly (not via revenue x margin), as FCF is the DCF driver. WACC of 10% reflects beta ~1.2, equity risk premium ~5.5%, risk-free rate ~4.5%. Equity CAGR not used as primary driver (distorted by GAAP losses on low post-IPO book value base). Sensitivity sheet shows IV across WACC 8-12% and terminal growth 2-4%.

Sheet Scenarios
A1: CRWD — Base / Bull / Bear Scenario Comparison
A2: All monetary values in USD millions unless noted.
B4: BASE CASE | C4: BULL CASE | D4: BEAR CASE
A5: SCENARIO ASSUMPTIONS
A6: WACC | B6: 0.1 | C6: 0.09 | D6: 0.12
A7: Terminal Growth | B7: 0.03 | C7: 0.035 | D7: 0.025
A8: Y1 FCF Growth | B8: 0.22 | C8: 0.28 | D8: 0.14
A9: Y2 FCF Growth | B9: 0.2 | C9: 0.25 | D9: 0.12
A10: Y3 FCF Growth | B10: 0.18 | C10: 0.22 | D10: 0.1
A11: Y4 FCF Growth | B11: 0.15 | C11: 0.2 | D11: 0.08
A12: Y5 FCF Growth | B12: 0.12 | C12: 0.17 | D12: 0.06
A13: PROJECTED FCF (M)
A14: Y1 FCF | B14: 1302.8 | C14: 1366.9 | D14: 1217.4
A15: Y2 FCF | B15: 1563.4 | C15: 1708.6 | D15: 1363.5
A16: Y3 FCF | B16: 1844.8 | C16: 2084.5 | D16: 1499.8
A17: Y4 FCF | B17: 2121.5 | C17: 2501.4 | D17: 1619.8
A18: Y5 FCF | B18: 2376.1 | C18: 2926.6 | D18: 1717
A19: VALUATION SUMMARY
A20: Sum of PV FCFs (M) | B20: 6786.3 | C20: 7976.1 | D20: 5245
A21: Terminal Value (M) | B21: 34962 | C21: 55072.8 | D21: 18526.3
A22: PV of Terminal Value (M) | B22: 21709.3 | C22: 35793.7 | D22: 10512.6
A23: Enterprise Value (M) | B23: 28495.6 | C23: 43769.8 | D23: 15757.6
A24: Net Debt (M) | B24: -3579.3 | C24: -3579.3 | D24: -3579.3
A25: Equity Value (M) | B25: 32074.9 | C25: 47349.1 | D25: 19336.9
A27: INTRINSIC VALUE PER SHARE | B27: 127.63 | C27: 188.44 | D27: 76.95
A28: Upside / (Downside) to Current $435 | B28: -0.707 | C28: -0.567 | D28: -0.823
A29: ENTRY PRICE (15% CAGR Target — years to terminal = 5)
A30: Terminal Value per Share | B30: 139.14 | C30: 219.24 | D30: 73.76
A31: Entry Price for 15% CAGR | B31: 69.16 | C31: 108.98 | D31: 36.67
A32: Discount from Current Price ($435) | B32: -0.841 | C32: -0.749 | D32: -0.916
A34: PROBABILITY-WEIGHTED VALUATION
A35: Bull Weight (25%) | B35: 47.11
A36: Base Weight (50%) | B36: 63.815
A37: Bear Weight (25%) | B37: 19.2375
A38: Probability-Weighted IV per Share | B38: 130.16 | C38: Current Price | D38: 435
A39: Upside to Probability-Weighted IV | B39: -0.70078161
A41: SCENARIO DESCRIPTIONS
A42: Base Case | B42: Steady post-outage recovery, 20-22% ARR growth sustained through FY2027-28, gradual deceleration as law of large numbers sets in. FCF margins improve modestly from ~27% toward ~30% as S&M leverage kicks in.
A43: Bull Case | B43: Platform consolidation accelerates: CrowdStrike captures outsized share of enterprise security consolidation, Charlotte AI drives premium upsells, $10B ARR vision materializes faster. FCF margins expand to 30%+ as platform leverage drives operating efficiency.
A44: Bear Case | B44: July 2024 trust deficit lingers, Microsoft competitive pressure intensifies, Delta litigation results in large settlement, ARR growth slows to low-teens. FCF margins compress as elevated S&M spend fails to reaccelerate growth.

Sheet Sensitivity
A1: CRWD Sensitivity Analysis — Base Case Intrinsic Value per Share
A2: Rows = WACC, Columns = Terminal Growth Rate. FCF growth rates held constant at base case (22/20/18/15/12%). Net Cash = $3,579M. Shares = 251.3M.
A4: WACC \ Term G | B4: 0.02 | C4: 0.025 | D4: 0.03 | E4: 0.035 | F4: 0.04
A5: 0.08 | B5: =('DCF Model'!C21/(1+0.08)^1+'DCF Model'!D21/(1+0.08)^2+'DCF Model'!E21/(1+0.08)^3+'DCF Model'!F21/(1+0.08)^4+'DCF Model'!G21/(1+0.08)^5+('DCF Model'!G21*(1+0.02)/(0.08-0.02))/(1+0.08)^5-'DCF Model'!B9)/'DCF Model'!B6 -> 0 | C5: =('DCF Model'!C21/(1+0.08)^1+'DCF Model'!D21/(1+0.08)^2+'DCF Model'!E21/(1+0.08)^3+'DCF Model'!F21/(1+0.08)^4+'DCF Model'!G21/(1+0.08)^5+('DCF Model'!G21*(1+0.025)/(0.08-0.025))/(1+0.08)^5-'DCF Model'!B9)/'DCF Model'!B6 -> 0 | D5: =('DCF Model'!C21/(1+0.08)^1+'DCF Model'!D21/(1+0.08)^2+'DCF Model'!E21/(1+0.08)^3+'DCF Model'!F21/(1+0.08)^4+'DCF Model'!G21/(1+0.08)^5+('DCF Model'!G21*(1+0.03)/(0.08-0.03))/(1+0.08)^5-'DCF Model'!B9)/'DCF Model'!B6 -> 0 | E5: =('DCF Model'!C21/(1+0.08)^1+'DCF Model'!D21/(1+0.08)^2+'DCF Model'!E21/(1+0.08)^3+'DCF Model'!F21/(1+0.08)^4+'DCF Model'!G21/(1+0.08)^5+('DCF Model'!G21*(1+0.035)/(0.08-0.035))/(1+0.08)^5-'DCF Model'!B9)/'DCF Model'!B6 -> 0 | F5: =('DCF Model'!C21/(1+0.08)^1+'DCF Model'!D21/(1+0.08)^2+'DCF Model'!E21/(1+0.08)^3+'DCF Model'!F21/(1+0.08)^4+'DCF Model'!G21/(1+0.08)^5+('DCF Model'!G21*(1+0.04)/(0.08-0.04))/(1+0.08)^5-'DCF Model'!B9)/'DCF Model'!B6 -> 0
A6: 0.09 | B6: =('DCF Model'!C21/(1+0.09)^1+'DCF Model'!D21/(1+0.09)^2+'DCF Model'!E21/(1+0.09)^3+'DCF Model'!F21/(1+0.09)^4+'DCF Model'!G21/(1+0.09)^5+('DCF Model'!G21*(1+0.02)/(0.09-0.02))/(1+0.09)^5-'DCF Model'!B9)/'DCF Model'!B6 -> 0 | C6: =('DCF Model'!C21/(1+0.09)^1+'DCF Model'!D21/(1+0.09)^2+'DCF Model'!E21/(1+0.09)^3+'DCF Model'!F21/(1+0.09)^4+'DCF Model'!G21/(1+0.09)^5+('DCF Model'!G21*(1+0.025)/(0.09-0.025))/(1+0.09)^5-'DCF Model'!B9)/'DCF Model'!B6 -> 0 | D6: =('DCF Model'!C21/(1+0.09)^1+'DCF Model'!D21/(1+0.09)^2+'DCF Model'!E21/(1+0.09)^3+'DCF Model'!F21/(1+0.09)^4+'DCF Model'!G21/(1+0.09)^5+('DCF Model'!G21*(1+0.03)/(0.09-0.03))/(1+0.09)^5-'DCF Model'!B9)/'DCF Model'!B6 -> 0 | E6: =('DCF Model'!C21/(1+0.09)^1+'DCF Model'!D21/(1+0.09)^2+'DCF Model'!E21/(1+0.09)^3+'DCF Model'!F21/(1+0.09)^4+'DCF Model'!G21/(1+0.09)^5+('DCF Model'!G21*(1+0.035)/(0.09-0.035))/(1+0.09)^5-'DCF Model'!B9)/'DCF Model'!B6 -> 0 | F6: =('DCF Model'!C21/(1+0.09)^1+'DCF Model'!D21/(1+0.09)^2+'DCF Model'!E21/(1+0.09)^3+'DCF Model'!F21/(1+0.09)^4+'DCF Model'!G21/(1+0.09)^5+('DCF Model'!G21*(1+0.04)/(0.09-0.04))/(1+0.09)^5-'DCF Model'!B9)/'DCF Model'!B6 -> 0
A7: 0.1 | B7: =('DCF Model'!C21/(1+0.1)^1+'DCF Model'!D21/(1+0.1)^2+'DCF Model'!E21/(1+0.1)^3+'DCF Model'!F21/(1+0.1)^4+'DCF Model'!G21/(1+0.1)^5+('DCF Model'!G21*(1+0.02)/(0.1-0.02))/(1+0.1)^5-'DCF Model'!B9)/'DCF Model'!B6 -> 0 | C7: =('DCF Model'!C21/(1+0.1)^1+'DCF Model'!D21/(1+0.1)^2+'DCF Model'!E21/(1+0.1)^3+'DCF Model'!F21/(1+0.1)^4+'DCF Model'!G21/(1+0.1)^5+('DCF Model'!G21*(1+0.025)/(0.1-0.025))/(1+0.1)^5-'DCF Model'!B9)/'DCF Model'!B6 -> 0 | D7: =('DCF Model'!C21/(1+0.1)^1+'DCF Model'!D21/(1+0.1)^2+'DCF Model'!E21/(1+0.1)^3+'DCF Model'!F21/(1+0.1)^4+'DCF Model'!G21/(1+0.1)^5+('DCF Model'!G21*(1+0.03)/(0.1-0.03))/(1+0.1)^5-'DCF Model'!B9)/'DCF Model'!B6 -> 0 | E7: =('DCF Model'!C21/(1+0.1)^1+'DCF Model'!D21/(1+0.1)^2+'DCF Model'!E21/(1+0.1)^3+'DCF Model'!F21/(1+0.1)^4+'DCF Model'!G21/(1+0.1)^5+('DCF Model'!G21*(1+0.035)/(0.1-0.035))/(1+0.1)^5-'DCF Model'!B9)/'DCF Model'!B6 -> 0 | F7: =('DCF Model'!C21/(1+0.1)^1+'DCF Model'!D21/(1+0.1)^2+'DCF Model'!E21/(1+0.1)^3+'DCF Model'!F21/(1+0.1)^4+'DCF Model'!G21/(1+0.1)^5+('DCF Model'!G21*(1+0.04)/(0.1-0.04))/(1+0.1)^5-'DCF Model'!B9)/'DCF Model'!B6 -> 0
A8: 0.11 | B8: =('DCF Model'!C21/(1+0.11)^1+'DCF Model'!D21/(1+0.11)^2+'DCF Model'!E21/(1+0.11)^3+'DCF Model'!F21/(1+0.11)^4+'DCF Model'!G21/(1+0.11)^5+('DCF Model'!G21*(1+0.02)/(0.11-0.02))/(1+0.11)^5-'DCF Model'!B9)/'DCF Model'!B6 -> 0 | C8: =('DCF Model'!C21/(1+0.11)^1+'DCF Model'!D21/(1+0.11)^2+'DCF Model'!E21/(1+0.11)^3+'DCF Model'!F21/(1+0.11)^4+'DCF Model'!G21/(1+0.11)^5+('DCF Model'!G21*(1+0.025)/(0.11-0.025))/(1+0.11)^5-'DCF Model'!B9)/'DCF Model'!B6 -> 0 | D8: =('DCF Model'!C21/(1+0.11)^1+'DCF Model'!D21/(1+0.11)^2+'DCF Model'!E21/(1+0.11)^3+'DCF Model'!F21/(1+0.11)^4+'DCF Model'!G21/(1+0.11)^5+('DCF Model'!G21*(1+0.03)/(0.11-0.03))/(1+0.11)^5-'DCF Model'!B9)/'DCF Model'!B6 -> 0 | E8: =('DCF Model'!C21/(1+0.11)^1+'DCF Model'!D21/(1+0.11)^2+'DCF Model'!E21/(1+0.11)^3+'DCF Model'!F21/(1+0.11)^4+'DCF Model'!G21/(1+0.11)^5+('DCF Model'!G21*(1+0.035)/(0.11-0.035))/(1+0.11)^5-'DCF Model'!B9)/'DCF Model'!B6 -> 0 | F8: =('DCF Model'!C21/(1+0.11)^1+'DCF Model'!D21/(1+0.11)^2+'DCF Model'!E21/(1+0.11)^3+'DCF Model'!F21/(1+0.11)^4+'DCF Model'!G21/(1+0.11)^5+('DCF Model'!G21*(1+0.04)/(0.11-0.04))/(1+0.11)^5-'DCF Model'!B9)/'DCF Model'!B6 -> 0
A9: 0.12 | B9: =('DCF Model'!C21/(1+0.12)^1+'DCF Model'!D21/(1+0.12)^2+'DCF Model'!E21/(1+0.12)^3+'DCF Model'!F21/(1+0.12)^4+'DCF Model'!G21/(1+0.12)^5+('DCF Model'!G21*(1+0.02)/(0.12-0.02))/(1+0.12)^5-'DCF Model'!B9)/'DCF Model'!B6 -> 0 | C9: =('DCF Model'!C21/(1+0.12)^1+'DCF Model'!D21/(1+0.12)^2+'DCF Model'!E21/(1+0.12)^3+'DCF Model'!F21/(1+0.12)^4+'DCF Model'!G21/(1+0.12)^5+('DCF Model'!G21*(1+0.025)/(0.12-0.025))/(1+0.12)^5-'DCF Model'!B9)/'DCF Model'!B6 -> 0 | D9: =('DCF Model'!C21/(1+0.12)^1+'DCF Model'!D21/(1+0.12)^2+'DCF Model'!E21/(1+0.12)^3+'DCF Model'!F21/(1+0.12)^4+'DCF Model'!G21/(1+0.12)^5+('DCF Model'!G21*(1+0.03)/(0.12-0.03))/(1+0.12)^5-'DCF Model'!B9)/'DCF Model'!B6 -> 0 | E9: =('DCF Model'!C21/(1+0.12)^1+'DCF Model'!D21/(1+0.12)^2+'DCF Model'!E21/(1+0.12)^3+'DCF Model'!F21/(1+0.12)^4+'DCF Model'!G21/(1+0.12)^5+('DCF Model'!G21*(1+0.035)/(0.12-0.035))/(1+0.12)^5-'DCF Model'!B9)/'DCF Model'!B6 -> 0 | F9: =('DCF Model'!C21/(1+0.12)^1+'DCF Model'!D21/(1+0.12)^2+'DCF Model'!E21/(1+0.12)^3+'DCF Model'!F21/(1+0.12)^4+'DCF Model'!G21/(1+0.12)^5+('DCF Model'!G21*(1+0.04)/(0.12-0.04))/(1+0.12)^5-'DCF Model'!B9)/'DCF Model'!B6 -> 0
A11: Green-highlighted cell = Base Case (WACC=10%, Terminal Growth=3%) = $127.63/share. Current price = $435.00. The table shows intrinsic value is significantly below current market price across all scenarios. For the stock to be fair value at $435, one must assume WACC ~8% with terminal growth ~4%, or extend the DCF horizon to 10+ years of above-model growth.

Sheet Historical
A1: CRWD — Historical Financials & Growth Rates
A2: Source: CRWD_Metrics.csv. Fiscal year ends January 31. All monetary values in USD millions.
A4: Period | B4: Revenue (M) | C4: FCF (M) | D4: EPS (GAAP) | E4: Equity (M) | F4: Rev YoY | G4: FCF YoY | H4: Equity YoY
A5: FY2020 | B5: 481.4 | C5: 12.5 | D5: -0.96 | E5: 742.6
A6: FY2021 | B6: 874.4 | C6: 292.9 | D6: -0.43 | E6: 871.9 | F6: 0.81636892 | G6: 22.432 | H6: 0.17411796
A7: FY2022 | B7: 1451.6 | C7: 441.8 | D7: -1.03 | E7: 1037.6 | F7: 0.66010979 | G7: 0.50836463 | H7: 0.19004473
A8: FY2023 | B8: 2241.2 | C8: 676.9 | D8: -0.79 | E8: 1487.4 | F8: 0.5439515 | G8: 0.53214124 | H8: 0.43350039
A9: FY2024 | B9: 3055.6 | C9: 940.2 | D9: 0.37 | E9: 2337.1 | F9: 0.36337676 | G9: 0.38897917 | H9: 0.5712653
A10: FY2025 | B10: 3953.6 | C10: 1067.9 | D10: -0.08 | E10: 3318.9 | F10: 0.29388663 | G10: 0.13582217 | H10: 0.42009328
A12: HISTORICAL CAGR SUMMARY
A13: Metric | B13: 3-Year CAGR | C13: 5-Year CAGR | D13: Notes
A14: Revenue | B14: 0.396 | C14: 0.524 | D14: FY2022-FY2025 (3yr) and FY2020-FY2025 (5yr). Law of large numbers causes deceleration.
A15: FCF | B15: 0.341 | C15: N/M | D15: 3yr: FY2022-FY2025. 5yr not meaningful: FY2020 base was $12.5M (near-breakeven). 3yr = 34.1%.
A16: Shareholders Equity | B16: 0.474 | C16: 0.347 | D16: High due to GAAP losses on low post-IPO book value base. Not used as DCF primary driver for CRWD.
A17: EPS (GAAP) | B17: N/M | C17: N/M | D17: Not calculable. GAAP EPS negative in 5 of 6 fiscal years. Non-GAAP EPS growing strongly (FY2026E: $3.70-3.72).
A18: SELECTED GROWTH RATE
A19: Selected Rate: | B19: 0.341 | C19: Source: fcf_3yr_cagr
A20: Equity CAGR (47.4% 3yr, 34.7% 5yr) is elevated due to low post-IPO book value base and GAAP losses masking retained earnings. FCF 5yr CAGR is meaningless (FY2020 base FCF of $12.5M is distorted). EPS CAGRs are not calculable due to persistent GAAP losses. FCF 3yr CAGR of 34.1% selected as primary growth rate anchor for a high-growth SaaS company, with near-term growth moderated to match ARR growth guidance (~21-22% for FY2026, ~20% for FY2027) and then decelerating toward terminal rate.
