Workbook

Sheet Scenario Model
A1: AFC.NZ Asset/Scenario Valuation Model
A2: NOT a growth DCF - AFC is a distressed NZX shell. Gray cells are INPUTS.
A3: See Model_Info tab for full methodology rationale and required refresh steps.
A5: KEY INPUTS
A6: Current Stock Price (NZ$) | B6: 0.001
A7: Shares Outstanding (millions) | B7: 3664.2532
A8: FY2026 Shareholders Equity (NZ$) | B8: 206390
A9: Total Debt (NZ$) | B9: 169364
A10: Cash & Equivalents (NZ$) | B10: 39437
A11: Net Debt (NZ$) [check: already inside equity] | B11: =B9-B10 -> 0
A13: Reported FCF FY2026 (NZ$) | B13: -631437
A14: Owner FCF FY2026 (NZ$, SBC=0 so same) | B14: =B13 -> 0
A16: SCENARIO ASSUMPTIONS (INPUTS - adjust freely)
B17: Bear | C17: Base | D17: Bull
A18: Tangible equity credited (NZ$) | B18: 0 | C18: 206390 | D18: 0
A19: Shell scarcity / RTO value (NZ$) | B19: 0 | C19: 500000 | D19: 2500000
A20: Equity Value (NZ$) | B20: =B18+B19 -> 0 | C20: =C18+C19 -> 0 | D20: =D18+D19 -> 0
A21: Intrinsic Value per Share (NZ$) | B21: =B20/($B$7*1000000) -> 0 | C21: =C20/($B$7*1000000) -> 0 | D21: =D20/($B$7*1000000) -> 0
A22: Upside/(Downside) vs Current Price | B22: =(B21-$B$6)/$B$6 -> 0 | C22: =(C21-$B$6)/$B$6 -> 0 | D22: =(D21-$B$6)/$B$6 -> 0
A24: PROBABILITY WEIGHTING
A25: Scenario weight (must sum to 100%) | B25: 0.55 | C25: 0.35 | D25: 0.1
A26: Weight check (should = 100%) | B26: =SUM(B25:D25) -> 0
A28: WEIGHTED INTRINSIC VALUE / SHARE | B28: =B21*B25+C21*C25+D21*D25 -> 0
A29: Weighted Upside/(Downside) | B29: =(B28-$B$6)/$B$6 -> 0
A31: SANITY CHECK
A32: Implied P/B at current price | B32: =($B$6*$B$7*1000000)/$B$8 -> 0
A33: Market cap at current price (NZ$) | B33: =$B$6*$B$7*1000000 -> 0
A34: Conclusion | B34: FAIL - all scenarios below current price
A36: Entry price note
A37: A standard 15%-IRR entry price formula does not apply to a non-cash-flowing shell (no distributable interim cash flow, no compounding exit value). Per the DCF JSON (entry_price.recommended_entry_price), the more decision-useful entry price IS the probability-weighted intrinsic value in B28 above - i.e. the maximum a rational buyer should pay given the scenario mix. Both the formal 15%-hurdle calc (in the JSON, NZ$0.0000958) and this weighted IV (NZ$0.000136) land far below the NZ$0.001 tradeable tick.

Sheet Sensitivity
A1: Sensitivity Analysis - Base Case
A2: Rows = % haircut applied to FY2026 book equity | Columns = shell scarcity value assumption (NZ$)
A4: Equity Haircut \ Shell Value | B4: 0 | C4: 250000 | D4: 500000 | E4: 750000 | F4: 1000000
A5: 0 | B5: =(('Scenario Model'!$B$8*(1-0.0))+0)/('Scenario Model'!$B$7*1000000) -> 0 | C5: =(('Scenario Model'!$B$8*(1-0.0))+250000)/('Scenario Model'!$B$7*1000000) -> 0 | D5: =(('Scenario Model'!$B$8*(1-0.0))+500000)/('Scenario Model'!$B$7*1000000) -> 0 | E5: =(('Scenario Model'!$B$8*(1-0.0))+750000)/('Scenario Model'!$B$7*1000000) -> 0 | F5: =(('Scenario Model'!$B$8*(1-0.0))+1000000)/('Scenario Model'!$B$7*1000000) -> 0
A6: 0.25 | B6: =(('Scenario Model'!$B$8*(1-0.25))+0)/('Scenario Model'!$B$7*1000000) -> 0 | C6: =(('Scenario Model'!$B$8*(1-0.25))+250000)/('Scenario Model'!$B$7*1000000) -> 0 | D6: =(('Scenario Model'!$B$8*(1-0.25))+500000)/('Scenario Model'!$B$7*1000000) -> 0 | E6: =(('Scenario Model'!$B$8*(1-0.25))+750000)/('Scenario Model'!$B$7*1000000) -> 0 | F6: =(('Scenario Model'!$B$8*(1-0.25))+1000000)/('Scenario Model'!$B$7*1000000) -> 0
A7: 0.5 | B7: =(('Scenario Model'!$B$8*(1-0.5))+0)/('Scenario Model'!$B$7*1000000) -> 0 | C7: =(('Scenario Model'!$B$8*(1-0.5))+250000)/('Scenario Model'!$B$7*1000000) -> 0 | D7: =(('Scenario Model'!$B$8*(1-0.5))+500000)/('Scenario Model'!$B$7*1000000) -> 0 | E7: =(('Scenario Model'!$B$8*(1-0.5))+750000)/('Scenario Model'!$B$7*1000000) -> 0 | F7: =(('Scenario Model'!$B$8*(1-0.5))+1000000)/('Scenario Model'!$B$7*1000000) -> 0
A8: 0.75 | B8: =(('Scenario Model'!$B$8*(1-0.75))+0)/('Scenario Model'!$B$7*1000000) -> 0 | C8: =(('Scenario Model'!$B$8*(1-0.75))+250000)/('Scenario Model'!$B$7*1000000) -> 0 | D8: =(('Scenario Model'!$B$8*(1-0.75))+500000)/('Scenario Model'!$B$7*1000000) -> 0 | E8: =(('Scenario Model'!$B$8*(1-0.75))+750000)/('Scenario Model'!$B$7*1000000) -> 0 | F8: =(('Scenario Model'!$B$8*(1-0.75))+1000000)/('Scenario Model'!$B$7*1000000) -> 0
A9: 1 | B9: =(('Scenario Model'!$B$8*(1-1.0))+0)/('Scenario Model'!$B$7*1000000) -> 0 | C9: =(('Scenario Model'!$B$8*(1-1.0))+250000)/('Scenario Model'!$B$7*1000000) -> 0 | D9: =(('Scenario Model'!$B$8*(1-1.0))+500000)/('Scenario Model'!$B$7*1000000) -> 0 | E9: =(('Scenario Model'!$B$8*(1-1.0))+750000)/('Scenario Model'!$B$7*1000000) -> 0 | F9: =(('Scenario Model'!$B$8*(1-1.0))+1000000)/('Scenario Model'!$B$7*1000000) -> 0
A11: Reference: Current price NZ$0.001 requires implied equity value of ~NZ$3,664,253 to be fair at the tick floor.

Sheet Historical
A1: Historical Growth Rates (context only - not used to drive valuation)
A3: Metric | B3: 3-Year CAGR | C3: 5-Year CAGR
A4: Revenue | B4: -0.4687 | C4: -0.2426
A5: Shareholders Equity | B5: -0.1801 | C5: -0.307
A6: EPS CAGR | B6: n/m | C6: n/m
A7: FCF CAGR | B7: n/m | C7: n/m
A9: Note:
A10: Reported FCF has been positive in exactly one year since FY2020 (FY2023: +NZ$18,709, immaterial and driven by working-capital timing, not repeatable earnings power). Every other year FY2020-FY2026 shows negative FCF, with FY2026 the worst on record at -NZ$631,437 despite revenue also collapsing to a seven-year low. There is no meaningful FCF history to extrapolate a growth DCF from. Stock-based compensation is nil throughout the disclosed history, so no SBC/dilution adjustment is needed - the entire valuation problem here is going-concern risk and revenue collapse, not share-based dilution.
A15: Growth rate source: | B15: not_applicable_asset_scenario_model

Sheet FCF Quality
A1: FCF Quality - Reported FCF History (SBC = NIL throughout, no adjustment needed)
A3: Metric | B3: FY2020 | C3: FY2021 | D3: FY2022 | E3: FY2023 | F3: FY2024 | G3: FY2025 | H3: FY2026
A4: Revenue (NZ$) | B4: 1234931 | C4: 646910 | D4: 415023 | E4: 1075442 | F4: 1324402 | G4: 741088 | H4: 161285
A5: Reported FCF (NZ$) | B5: -290903 | C5: -380450 | D5: -294999 | E5: 18709 | F5: -140788 | G5: -324569 | H5: -631437
A6: Less: SBC incl. equity taxes | B6: 0 | C6: 0 | D6: 0 | E6: 0 | F6: 0 | G6: 0 | H6: 0
A7: Less: Interest income | B7: 0 | C7: 0 | D7: 0 | E7: 0 | F7: 0 | G7: 0 | H7: 0
A8: Owner FCF (NZ$) | B8: =B5 -> 0 | C8: =C5 -> 0 | D8: =D5 -> 0 | E8: =E5 -> 0 | F8: =F5 -> 0 | G8: =G5 -> 0 | H8: =H5 -> 0
A9: Shareholders Equity (NZ$) | B9: 2563166 | C9: 1291315 | D9: 552890 | E9: 374469 | F9: 428380 | G9: 243574 | H9: 206390
A10: Owner FCF Margin | B10: =B8/B4 -> 0 | C10: =C8/C4 -> 0 | D10: =D8/D4 -> 0 | E10: =E8/E4 -> 0 | F10: =F8/F4 -> 0 | G10: =G8/G4 -> 0 | H10: =H8/H4 -> 0
A12: Memo: FY2023 +NZ$18,709 FCF is an isolated working-capital blip, not repeatable operating cash generation.
A13: Memo: FY2026 FCF of -NZ$631,437 is the worst on record despite revenue also collapsing to a 7-year low (cost base did not shrink proportionately).
A14: Memo: No SBC in AFC history (StockBasedComp = 0 every period in Metrics.csv). No deferred-revenue/working-capital tailwind exists in this business (unlike SaaS/subscription names) - FCF swings here reflect operating losses and related-party funding timing, not bookings growth.
A15: Memo: Cash tax rate is not meaningful - the Group has never had taxable profits in the post-2020 period and carries NZ$1.7m of unrecognized deferred tax assets (loss carryforwards) with no near-term utility.

Sheet Model_Info
A1: Model Provenance & Methodology
A3: Ticker | B3: AFC.NZ (AFC Group Holdings Limited, NZX)
A4: Model built by | B4: Claude agent (dcf-analyst workflow, with ticker-specific override instructions for a distressed shell)
A5: Valuation date | B5: 2026-08-01
A6: Data vintage | B6: FY2026 audited Annual Report (year ended 31-Mar-2026), released 30-Jun-2026. Share price verified live via Yahoo Finance chart API on 2026-08-01: NZ$0.001 (NZX minimum tick). Monthly price history (AFC.NZ_MonthlyPrices.txt) confirms the price has been pinned at or near this tick continuously since 2017.
A7: Methodology | B7: This is NOT a growth DCF. AFC is a distressed NZX shell: FY2026 revenue collapsed 78% YoY to NZ$161,285, net loss NZ$818,093, owner FCF negative in 6 of the last 7 fiscal years, SBC nil throughout. Per ticker-specific override rules, valuation uses a probability-weighted ASSET/SCENARIO approach: Bear = insolvency/wind-up ($0.0000/share); Base = FY2026 tangible equity (NZ$206,390) + NZ$500,000 shell-listing scarcity value ($0.000193/share); Bull = completed reverse-takeover valuing the shell at the top of NZX precedent, NZ$2,500,000 ($0.000682/share). Weights 55%/35%/10% (bear/base/bull), weighted IV = NZ$0.000136/share.
A8: Why not a standard DCF | B8: No repeatable positive owner FCF exists to project (FY2023 +NZ$18,709 is an immaterial one-off working-capital blip; every other year FY2020-2026 is negative, worst in FY2026 at -NZ$631,437). SBC is nil so no SBC adjustment is needed - the valuation problem here is going-concern risk and revenue collapse, not dilution.
A9: Key going-concern facts | B9: FY2026 auditor (Grant Thornton) issued a FULL DISCLAIMER OF OPINION - the second consecutive year (William Buck also disclaimed FY2025) - a more severe finding than a going-concern emphasis of matter. Working-capital deficit NZ$1.3M. H1-2026 (unaudited, 30-Sep-2025) equity was already negative (-NZ$120,066) before a NZ$780,908 related-party debt/interest forgiveness from NZ Silveray Group (NZSG) restored full-year equity to +NZ$206,390. Five related parties = 97% of FY2026 revenue; one related party = 99.7% of receivables. NZSG advanced a further NZ$200,000 post year-end (Apr/May 2026).
A10: RTO status | B10: Fast Track Group discussions are PRE-MOU as of the FY2026 Annual Report - management states AFC and FTG are "preparing to enter into a Memorandum of Understanding." No signed MOU, no transaction terms, no exchange ratio, no timeline disclosed. Treated as speculative option value in the Bull case only.
A11: Entry price treatment | B11: The standard 15%-IRR entry-price formula does not apply (no distributable interim cash flow, no compounding exit value in any scenario). Per the ticker override, entry price is reported as the probability-weighted intrinsic value (NZ$0.000136/share) with the formal 15%-hurdle calc (NZ$0.0000958/share) shown for reference in the DCF JSON. Both sit below the NZX minimum tradeable tick.
A12: What to refresh after next filing | B12: (1) Re-pull FY2027 half-year (H1-2027, to 30-Sep-2026) and/or full FY2027 Annual Report figures into Metrics.csv once released - watch particularly whether NZSG continues funding/forgiveness or withdraws support. (2) Check NZX company announcements for any signed MOU or binding RTO agreement with Fast Track Group - a signed MOU would justify re-weighting the bull scenario upward and/or modelling actual (rather than precedent-based) transaction terms. (3) Re-verify live share price (should remain pinned at NZ$0.001 tick absent a corporate action). (4) Check for a THIRD consecutive year of audit disclaimer/qualification, which would further support increasing the bear weight. (5) Confirm shares outstanding (3,664,253,194) has not changed via placement, RTO consideration shares, or consolidation.
A13: Cell colour conventions | B13: Gray-filled cells (light blue-gray, #dfe6e9) are INPUTS - safe to edit; all other cells are FORMULAS that recalculate automatically. Green-filled cells are headline RESULTS. Red-filled cells flag a FAILED sanity check / warning.
A14: Staleness warning | B14: All figures in this model reflect data as of the 2026-08-01 valuation date and the FY2026 (Mar-2026 year-end) Annual Report. They WILL go stale as new NZX announcements, half-year results, or RTO developments are released. Do not treat this file as current without re-checking the valuation_date field and the underlying Metrics.csv / Analysis.json refresh dates.
