Workbook

Sheet Assumptions
A1: MSFT DCF Valuation Model
A2: Gray cells are INPUTS - adjust to see valuation change on Base/Bull/Bear sheets
A4: VALUATION DATE / PRICE
A5: Valuation Date | B5: 2026-07-12
A6: Current Stock Price | B6: 385.1
A8: KEY INPUTS
A9: Shares Outstanding (M) | B9: 7465
A10: Cash & Equivalents (M) | B10: 94565
A11: Total Debt (M) | B11: 43151
A12: Net Debt (M) | B12: =B11-B10
A13: Base Year FCF (M) [FY2025 actual] | B13: 71611
A14: Base Revenue (M) [FY2025 actual] | B14: 281724
A16: SCENARIO ASSUMPTIONS
B17: Base | C17: Bull | D17: Bear
A18: WACC | B18: 0.1 | C18: 0.09 | D18: 0.12
A19: Terminal Growth Rate | B19: 0.03 | C19: 0.035 | D19: 0.02
A20: FCF Margin | B20: 0.254 | C20: 0.28 | D20: 0.22
A21: Growth Rate Year 1 | B21: 0.16 | C21: 0.2 | D21: 0.1
A22: Growth Rate Year 2 | B22: 0.14 | C22: 0.18 | D22: 0.08
A23: Growth Rate Year 3 | B23: 0.12 | C23: 0.16 | D23: 0.06
A24: Growth Rate Year 4 | B24: 0.1 | C24: 0.14 | D24: 0.05
A25: Growth Rate Year 5 | B25: 0.08 | C25: 0.12 | D25: 0.04
A27: ASSUMPTION NOTES
A28: BASE | B28: Growth starts at 16% reflecting Q3 FY2026 run rate (+18% YoY) with modest deceleration as AI normalizes post-capacity buildout. FCF margin anchored at FY2025 actual (25.4%), assuming capex moderates from $64B peak toward $50B range by Year 4-5 so margin holds steady. WACC 10% reflects MSFT AA+ credit quality offset by elevated capex risk and regulatory overhang. Assumptions unchanged from 2026-06-30 model — no new filings since last update; July 2026 news (workforce restructuring, Xbox reset, Microsoft Frontier Company launch) is cost-discipline/AI-monetization signal, not a driver of revised revenue or margin assumptions.
A29: BULL | B29: Azure capacity constraints lift in H2 CY2026, unlocking pent-up demand and sustaining 40%+ growth. AI ARR compounds from $37B: M365 Copilot seats scale from 20M toward 100M+, GitHub Copilot monetizes 140K enterprise orgs. $627B commercial RPO converts strongly. FCF margin expands to 28% as capex stabilizes and high-margin AI services grow as a share of mix. WACC 9% reflects strong execution and credit quality. Microsoft Frontier Company (launched July 2026) is a modest incremental upside lever for higher-margin AI implementation revenue, consistent with — not additive beyond — existing bull assumptions.
A30: BEAR | B30: Capex-to-revenue conversion disappoints — $190B CY2026 capex does not translate to commensurate revenue; asset impairments possible on short-lived GPU assets. Regulatory interventions (FTC antitrust, EU DMA gatekeeper designation) force licensing changes reducing Azure competitive advantage. OpenAI non-exclusive amendment erodes differentiation. FCF margin compressed to 22% by sustained high depreciation and elevated infrastructure costs per AI revenue dollar. WACC 12% reflects regulatory risk premium. July 2026 Xbox restructuring and ~4,800 layoffs are consistent with bear-case concerns about capital misallocation, though treated as cost-discipline rather than a further downgrade to bear assumptions.
A32: HISTORICAL GROWTH RATE SELECTION
A33: Selected Growth Rate | B33: 0.1452
A34: Source | B34: revenue_5yr_cagr
A35: Divergence Warning | B35: Equity CAGR (23.76%) diverges from Revenue CAGR (14.52%) by 63.6% — exceeds 30% threshold. Divergence driven by two factors: (1) strong earnings growth (18.82% EPS CAGR) building retained earnings faster than revenue growth, and (2) massive AI capex cycle compressing FCF (3.20% 3yr CAGR) well below revenue growth. Using Revenue CAGR as the primary selected rate as it best represents sustainable business growth trajectory. Equity CAGR is inflated by the earnings quality of the subscription model; FCF CAGR is temporarily depressed by $64.5B FY2025 capex. Base case growth rates set above selected rate to reflect Q3 FY2026 Azure +40% YoY momentum.

Sheet Base Case
A1: MSFT DCF — Base Case Case
A3: INPUTS (linked to Assumptions sheet)
A4: Current Stock Price | B4: =Assumptions!$B$6
A5: Shares Outstanding (M) | B5: =Assumptions!$B$9
A6: Net Debt (M) | B6: =Assumptions!$B$12
A7: Base Year FCF (M) | B7: =Assumptions!$B$13
A8: WACC | B8: =Assumptions!$B$18
A9: Terminal Growth Rate | B9: =Assumptions!$B$19
A10: FCF Margin | B10: =Assumptions!$B$20
A12: GROWTH RATES
B13: Year 1 | C13: Year 2 | D13: Year 3 | E13: Year 4 | F13: Year 5
A14: Growth Rate | B14: =Assumptions!$B$21 | C14: =Assumptions!$B$22 | D14: =Assumptions!$B$23 | E14: =Assumptions!$B$24 | F14: =Assumptions!$B$25
A16: PROJECTIONS
B17: Year 1 | C17: Year 2 | D17: Year 3 | E17: Year 4 | F17: Year 5
A18: Revenue | B18: =Assumptions!$B$14 | C18: =B18*(1+B14) | D18: =C18*(1+C14) | E18: =D18*(1+D14) | F18: =E18*(1+E14) | G18: =F18*(1+F14)
A19: Free Cash Flow | C19: =C18*$B$10 | D19: =D18*$B$10 | E19: =E18*$B$10 | F19: =F18*$B$10 | G19: =G18*$B$10
A20: Discount Factor | C20: =1/(1+$B$8)^1 | D20: =1/(1+$B$8)^2 | E20: =1/(1+$B$8)^3 | F20: =1/(1+$B$8)^4 | G20: =1/(1+$B$8)^5
A21: PV of FCF | C21: =C19*C20 | D21: =D19*D20 | E21: =E19*E20 | F21: =F19*F20 | G21: =G19*G20
A23: VALUATION
A24: Sum of PV of FCF (Y1-Y5) | B24: =SUM(C21:G21)
A25: Terminal FCF (Year 5 x (1+g)) | B25: =G19*(1+B9)
A26: Terminal Value | B26: =B25/(B8-B9)
A27: PV of Terminal Value | B27: =B26*G20
A28: Enterprise Value | B28: =B24+B27
A29: Less: Net Debt | B29: =B6
A30: Equity Value | B30: =B28-B29
A31: INTRINSIC VALUE / SHARE | B31: =B30/B5
A32: Upside / (Downside) to Current Price | B32: =(B31-B4)/B4
A34: ENTRY PRICE (15% CAGR Target)
A35: Terminal Value per Share | B35: =B26/B5
A36: Years to Terminal | B36: 5
A37: Entry Price (15% CAGR) | B37: =B35/(1.15^B36)
A38: Entry Discount from Current Price | B38: =(B4-B37)/B4*-1

Sheet Bull Case
A1: MSFT DCF — Bull Case Case
A3: INPUTS (linked to Assumptions sheet)
A4: Current Stock Price | B4: =Assumptions!$B$6
A5: Shares Outstanding (M) | B5: =Assumptions!$B$9
A6: Net Debt (M) | B6: =Assumptions!$B$12
A7: Base Year FCF (M) | B7: =Assumptions!$B$13
A8: WACC | B8: =Assumptions!$C$18
A9: Terminal Growth Rate | B9: =Assumptions!$C$19
A10: FCF Margin | B10: =Assumptions!$C$20
A12: GROWTH RATES
B13: Year 1 | C13: Year 2 | D13: Year 3 | E13: Year 4 | F13: Year 5
A14: Growth Rate | B14: =Assumptions!$C$21 | C14: =Assumptions!$C$22 | D14: =Assumptions!$C$23 | E14: =Assumptions!$C$24 | F14: =Assumptions!$C$25
A16: PROJECTIONS
B17: Year 1 | C17: Year 2 | D17: Year 3 | E17: Year 4 | F17: Year 5
A18: Revenue | B18: =Assumptions!$B$14 | C18: =B18*(1+B14) | D18: =C18*(1+C14) | E18: =D18*(1+D14) | F18: =E18*(1+E14) | G18: =F18*(1+F14)
A19: Free Cash Flow | C19: =C18*$B$10 | D19: =D18*$B$10 | E19: =E18*$B$10 | F19: =F18*$B$10 | G19: =G18*$B$10
A20: Discount Factor | C20: =1/(1+$B$8)^1 | D20: =1/(1+$B$8)^2 | E20: =1/(1+$B$8)^3 | F20: =1/(1+$B$8)^4 | G20: =1/(1+$B$8)^5
A21: PV of FCF | C21: =C19*C20 | D21: =D19*D20 | E21: =E19*E20 | F21: =F19*F20 | G21: =G19*G20
A23: VALUATION
A24: Sum of PV of FCF (Y1-Y5) | B24: =SUM(C21:G21)
A25: Terminal FCF (Year 5 x (1+g)) | B25: =G19*(1+B9)
A26: Terminal Value | B26: =B25/(B8-B9)
A27: PV of Terminal Value | B27: =B26*G20
A28: Enterprise Value | B28: =B24+B27
A29: Less: Net Debt | B29: =B6
A30: Equity Value | B30: =B28-B29
A31: INTRINSIC VALUE / SHARE | B31: =B30/B5
A32: Upside / (Downside) to Current Price | B32: =(B31-B4)/B4
A34: ENTRY PRICE (15% CAGR Target)
A35: Terminal Value per Share | B35: =B26/B5
A36: Years to Terminal | B36: 5
A37: Entry Price (15% CAGR) | B37: =B35/(1.15^B36)
A38: Entry Discount from Current Price | B38: =(B4-B37)/B4*-1

Sheet Bear Case
A1: MSFT DCF — Bear Case Case
A3: INPUTS (linked to Assumptions sheet)
A4: Current Stock Price | B4: =Assumptions!$B$6
A5: Shares Outstanding (M) | B5: =Assumptions!$B$9
A6: Net Debt (M) | B6: =Assumptions!$B$12
A7: Base Year FCF (M) | B7: =Assumptions!$B$13
A8: WACC | B8: =Assumptions!$D$18
A9: Terminal Growth Rate | B9: =Assumptions!$D$19
A10: FCF Margin | B10: =Assumptions!$D$20
A12: GROWTH RATES
B13: Year 1 | C13: Year 2 | D13: Year 3 | E13: Year 4 | F13: Year 5
A14: Growth Rate | B14: =Assumptions!$D$21 | C14: =Assumptions!$D$22 | D14: =Assumptions!$D$23 | E14: =Assumptions!$D$24 | F14: =Assumptions!$D$25
A16: PROJECTIONS
B17: Year 1 | C17: Year 2 | D17: Year 3 | E17: Year 4 | F17: Year 5
A18: Revenue | B18: =Assumptions!$B$14 | C18: =B18*(1+B14) | D18: =C18*(1+C14) | E18: =D18*(1+D14) | F18: =E18*(1+E14) | G18: =F18*(1+F14)
A19: Free Cash Flow | C19: =C18*$B$10 | D19: =D18*$B$10 | E19: =E18*$B$10 | F19: =F18*$B$10 | G19: =G18*$B$10
A20: Discount Factor | C20: =1/(1+$B$8)^1 | D20: =1/(1+$B$8)^2 | E20: =1/(1+$B$8)^3 | F20: =1/(1+$B$8)^4 | G20: =1/(1+$B$8)^5
A21: PV of FCF | C21: =C19*C20 | D21: =D19*D20 | E21: =E19*E20 | F21: =F19*F20 | G21: =G19*G20
A23: VALUATION
A24: Sum of PV of FCF (Y1-Y5) | B24: =SUM(C21:G21)
A25: Terminal FCF (Year 5 x (1+g)) | B25: =G19*(1+B9)
A26: Terminal Value | B26: =B25/(B8-B9)
A27: PV of Terminal Value | B27: =B26*G20
A28: Enterprise Value | B28: =B24+B27
A29: Less: Net Debt | B29: =B6
A30: Equity Value | B30: =B28-B29
A31: INTRINSIC VALUE / SHARE | B31: =B30/B5
A32: Upside / (Downside) to Current Price | B32: =(B31-B4)/B4
A34: ENTRY PRICE (15% CAGR Target)
A35: Terminal Value per Share | B35: =B26/B5
A36: Years to Terminal | B36: 5
A37: Entry Price (15% CAGR) | B37: =B35/(1.15^B36)
A38: Entry Discount from Current Price | B38: =(B4-B37)/B4*-1

Sheet Sensitivity
A1: Sensitivity Analysis — Base Case
A2: Intrinsic Value per Share by WACC & Terminal Growth
A4: WACC \ Term G | B4: 0.02 | C4: 0.025 | D4: 0.03 | E4: 0.035 | F4: 0.04
A5: 0.08 | B5: =('Base Case'!$G$19*(1+0.02))/(0.08-0.02)/(1+0.08)^5/'Base Case'!$B$5 | C5: =('Base Case'!$G$19*(1+0.025))/(0.08-0.025)/(1+0.08)^5/'Base Case'!$B$5 | D5: =('Base Case'!$G$19*(1+0.03))/(0.08-0.03)/(1+0.08)^5/'Base Case'!$B$5 | E5: =('Base Case'!$G$19*(1+0.035))/(0.08-0.035)/(1+0.08)^5/'Base Case'!$B$5 | F5: =('Base Case'!$G$19*(1+0.04))/(0.08-0.04)/(1+0.08)^5/'Base Case'!$B$5
A6: 0.09 | B6: =('Base Case'!$G$19*(1+0.02))/(0.09-0.02)/(1+0.09)^5/'Base Case'!$B$5 | C6: =('Base Case'!$G$19*(1+0.025))/(0.09-0.025)/(1+0.09)^5/'Base Case'!$B$5 | D6: =('Base Case'!$G$19*(1+0.03))/(0.09-0.03)/(1+0.09)^5/'Base Case'!$B$5 | E6: =('Base Case'!$G$19*(1+0.035))/(0.09-0.035)/(1+0.09)^5/'Base Case'!$B$5 | F6: =('Base Case'!$G$19*(1+0.04))/(0.09-0.04)/(1+0.09)^5/'Base Case'!$B$5
A7: 0.1 | B7: =('Base Case'!$G$19*(1+0.02))/(0.1-0.02)/(1+0.1)^5/'Base Case'!$B$5 | C7: =('Base Case'!$G$19*(1+0.025))/(0.1-0.025)/(1+0.1)^5/'Base Case'!$B$5 | D7: =('Base Case'!$G$19*(1+0.03))/(0.1-0.03)/(1+0.1)^5/'Base Case'!$B$5 | E7: =('Base Case'!$G$19*(1+0.035))/(0.1-0.035)/(1+0.1)^5/'Base Case'!$B$5 | F7: =('Base Case'!$G$19*(1+0.04))/(0.1-0.04)/(1+0.1)^5/'Base Case'!$B$5
A8: 0.11 | B8: =('Base Case'!$G$19*(1+0.02))/(0.11-0.02)/(1+0.11)^5/'Base Case'!$B$5 | C8: =('Base Case'!$G$19*(1+0.025))/(0.11-0.025)/(1+0.11)^5/'Base Case'!$B$5 | D8: =('Base Case'!$G$19*(1+0.03))/(0.11-0.03)/(1+0.11)^5/'Base Case'!$B$5 | E8: =('Base Case'!$G$19*(1+0.035))/(0.11-0.035)/(1+0.11)^5/'Base Case'!$B$5 | F8: =('Base Case'!$G$19*(1+0.04))/(0.11-0.04)/(1+0.11)^5/'Base Case'!$B$5
A9: 0.12 | B9: =('Base Case'!$G$19*(1+0.02))/(0.12-0.02)/(1+0.12)^5/'Base Case'!$B$5 | C9: =('Base Case'!$G$19*(1+0.025))/(0.12-0.025)/(1+0.12)^5/'Base Case'!$B$5 | D9: =('Base Case'!$G$19*(1+0.03))/(0.12-0.03)/(1+0.12)^5/'Base Case'!$B$5 | E9: =('Base Case'!$G$19*(1+0.035))/(0.12-0.035)/(1+0.12)^5/'Base Case'!$B$5 | F9: =('Base Case'!$G$19*(1+0.04))/(0.12-0.04)/(1+0.12)^5/'Base Case'!$B$5
A11: Note: Sensitivity uses Base Case Year 5 FCF as the terminal-year cash flow, discounted at each WACC over 5 years.

Sheet Historical
A1: MSFT Historical Financials
A3: Metric | B3: 3-Year CAGR | C3: 5-Year CAGR
A4: Revenue | B4: 0.1242 | C4: 0.1452
A5: EPS | B5: 0.1223 | C5: 0.1882
A6: Equity | B6: 0.2729 | C6: 0.2376
A7: FCF | B7: 0.032 | C7: 0.0962
A9: Selected Growth Rate: | B9: 0.1452
A10: Source: | B10: revenue_5yr_cagr
A13: ANNUAL FINANCIAL HISTORY (from Metrics CSV)
A14: Period | B14: Revenue | C14: GrossProfit | D14: GrossMargin | E14: OperatingIncome | F14: OperatingMargin | G14: NetIncome | H14: NetMargin | I14: EPS | J14: FreeCashFlow | K14: OperatingCashFlow | L14: CapEx | M14: ShareholdersEquity | N14: TotalDebt | O14: CashAndEquivalents | P14: SharesOutstanding | Q14: CloudRevenue | R14: ProductivityRevenue | S14: PersonalComputingRevenue
A15: FY2015 | B15: 93580 | C15: 64470 | D15: 68.9 | E15: 18161 | F15: 19.4 | G15: 12193 | H15: 13 | I15: 1.48 | J15: 23136 | K15: 29080 | L15: 5944 | M15: 80083 | N15: 27808 | O15: 96526 | P15: 8177
A16: FY2016 | B16: 85320 | C16: 58374 | D16: 68.4 | E16: 20182 | F16: 23.7 | G16: 16798 | H16: 19.7 | I16: 2.1 | J16: 24982 | K16: 33325 | L16: 8343 | M16: 83090 | N16: 40783 | O16: 113240 | P16: 7808
A17: FY2017 | B17: 89950 | C17: 55689 | D17: 61.9 | E17: 22326 | F17: 24.8 | G17: 21204 | H17: 23.6 | I17: 2.71 | J17: 31378 | K17: 39507 | L17: 8129 | M17: 87711 | N17: 76073 | O17: 132981 | P17: 7746
A18: FY2018 | B18: 110360 | C18: 72007 | D18: 65.3 | E18: 35058 | F18: 31.8 | G18: 16571 | H18: 15 | I18: 2.13 | J18: 32252 | K18: 43884 | L18: 11632 | M18: 82718 | N18: 72242 | O18: 133768 | P18: 7700
A19: FY2019 | B19: 125843 | C19: 82933 | D19: 65.9 | E19: 42959 | F19: 34.1 | G19: 39240 | H19: 31.2 | I19: 5.06 | J19: 38260 | K19: 52185 | L19: 13925 | M19: 102330 | N19: 66662 | O19: 133819 | P19: 7643
A20: FY2020 | B20: 143015 | C20: 96937 | D20: 67.8 | E20: 52959 | F20: 37 | G20: 44281 | H20: 31 | I20: 5.76 | J20: 45234 | K20: 60675 | L20: 15441 | M20: 118304 | N20: 66662 | O20: 133819 | P20: 7683 | Q20: 48366 | R20: 43076 | S20: 51573
A21: FY2021 | B21: 168088 | C21: 115856 | D21: 68.9 | E21: 69916 | F21: 41.6 | G21: 61271 | H21: 36.5 | I21: 8.05 | J21: 56118 | K21: 76740 | L21: 20622 | M21: 141988 | N21: 58146 | O21: 130334 | P21: 7608 | Q21: 60080 | R21: 48728 | S21: 59280
A22: FY2022 | B22: 198270 | C22: 135620 | D22: 68.4 | E22: 83383 | F22: 42.1 | G22: 72738 | H22: 36.7 | I22: 9.65 | J22: 65149 | K22: 89035 | L22: 23886 | M22: 166542 | N22: 49781 | O22: 104757 | P22: 7540 | Q22: 74965 | R22: 63364 | S22: 59941
A23: FY2023 | B23: 211915 | C23: 146052 | D23: 68.9 | E23: 88523 | F23: 41.8 | G23: 72361 | H23: 34.2 | I23: 9.68 | J23: 59475 | K23: 87582 | L23: 28107 | M23: 206223 | N23: 50074 | O23: 48305 | P23: 7472 | Q23: 87907 | R23: 69274 | S23: 54734
A24: FY2024 | B24: 245122 | C24: 171008 | D24: 69.8 | E24: 109433 | F24: 44.6 | G24: 88136 | H24: 36 | I24: 11.8 | J24: 74071 | K24: 118548 | L24: 44477 | M24: 268477 | N24: 51630 | O24: 75543 | P24: 7469 | Q24: 105362 | R24: 77728 | S24: 62032
A25: FY2025 | B25: 281724 | C25: 193893 | D25: 68.8 | E25: 128528 | F25: 45.6 | G25: 101832 | H25: 36.2 | I25: 13.64 | J25: 71611 | K25: 136162 | L25: 64551 | M25: 343479 | N25: 43151 | O25: 94565 | P25: 7465 | Q25: 106265 | R25: 120810 | S25: 54649
