Workbook

Sheet BVPS Model
A1: FIH.U - Fairfax India Holdings - Book Value Growth Model
A2: Holdco valuation: BVPS projected forward, exit at Price/Book multiple, discounted at Cost of Equity
A3: Gray cells = INPUTS (editable). Green cells = calculated outputs. No FCF DCF used - see 'Philosophy' tab.
A5: KEY INPUTS
A6: Current Stock Price ($) | B6: 17.85
A7: Shares Outstanding (M) | B7: 134.2
A8: Current BVPS - Q1 2026 ($) | B8: 19.08
A9: FY2025 BVPS ($, for reference) | B9: 22.94
A11: Annual BVPS Growth Rate (Base) | B11: 0.085
A12: Exit Price/Book Multiple (Base) | B12: 0.8
A13: Cost of Equity / WACC (Base) | B13: 0.11
A15: BVPS PROJECTION - BASE CASE
B16: Year 0 (Q1-2026) | C16: Year 1 | D16: Year 2 | E16: Year 3 | F16: Year 4 | G16: Year 5
A17: Projected BVPS ($) | B17: =B8 | C17: =B17*(1+$B$11) | D17: =C17*(1+$B$11) | E17: =D17*(1+$B$11) | F17: =E17*(1+$B$11) | G17: =F17*(1+$B$11)
A18: Discount Factor (at Cost of Equity) | C18: =1/(1+$B$13)^1 | D18: =1/(1+$B$13)^2 | E18: =1/(1+$B$13)^3 | F18: =1/(1+$B$13)^4 | G18: =1/(1+$B$13)^5
A20: VALUATION - BASE CASE
A21: BVPS at Year 5 ($) | B21: =G17
A22: Exit Price/Book Multiple | B22: =B12
A23: Exit Value per Share ($) | B23: =B21*B22
A24: Discount Factor (Year 5) | B24: =G18
A25: INTRINSIC VALUE PER SHARE | B25: =B23*B24
A26: Current Price ($) | B26: =B6
A27: Upside / (Downside) to IV | B27: =(B25-B6)/B6
A28: Implied P/B on Current BVPS | B28: =B25/B8
A30: ENTRY PRICE (15% CAGR Target, Base Case)
A31: Exit Value per Share (Year 5, undiscounted) | B31: =B23
A32: Years to Exit | B32: 5
A33: Entry Price for 15% CAGR | B33: =B31/(1.15^B32)
A34: Entry Price Discount vs Current | B34: =(B33-B6)/B6

Sheet Scenarios
A1: FIH.U - Scenario Comparison
A3: Assumption / Output | B3: Bear | C3: Base | D3: Bull
A4: Starting BVPS ($, Q1 2026) | B4: ='BVPS Model'!$B$8 | C4: ='BVPS Model'!$B$8 | D4: ='BVPS Model'!$B$8
A5: Annual BVPS Growth Rate | B5: 0.045 | C5: 0.085 | D5: 0.12
A6: Exit Price/Book Multiple | B6: 0.65 | C6: 0.8 | D6: 0.95
A7: Cost of Equity (WACC) | B7: 0.13 | C7: 0.11 | D7: 0.1
A9: BVPS at Year 5 ($) | B9: =B4*(1+B5)^5 | C9: =C4*(1+C5)^5 | D9: =D4*(1+D5)^5
A10: Exit Value per Share ($) | B10: =B9*B6 | C10: =C9*C6 | D10: =D9*D6
A11: Discount Factor (Year 5) | B11: =1/(1+B7)^5 | C11: =1/(1+C7)^5 | D11: =1/(1+D7)^5
A12: INTRINSIC VALUE PER SHARE | B12: =B10*B11 | C12: =C10*C11 | D12: =D10*D11
A13: Current Price ($) | B13: ='BVPS Model'!$B$6 | C13: ='BVPS Model'!$B$6 | D13: ='BVPS Model'!$B$6
A14: Upside / (Downside) | B14: =(B12-B13)/B13 | C14: =(C12-C13)/C13 | D14: =(D12-D13)/D13
A15: Entry Price (15% CAGR) | B15: =B10/(1.15^5) | C15: =C10/(1.15^5) | D15: =D10/(1.15^5)
A17: PROBABILITY-WEIGHTED VALUE
A18: Scenario Weight | B18: 0.25 | C18: 0.5 | D18: 0.25
A19: Weighted Intrinsic Value | B19: =SUMPRODUCT(B12:D12,B18:D18)
A20: Weighted Upside vs Current | B20: =(B19-'BVPS Model'!$B$6)/'BVPS Model'!$B$6
A22: Scenario Notes
A23: Bear: | B23: BVPS compounds only ~4.5%/yr - rupee depreciation accelerates (as seen in Q1 2026's -5.2% single-quarter move), the Anchorage/BIAL IPO is shelved again past the September 2026 long-stop (as happened with the prior long-stop), Indian public holdings (IIFL Finance, CSB Bank, 5paisa, Fairchem) stay in a bear market, and further impairments occur (as with Sanmar sold well below carrying value in April 2026). Exit P/B falls to 0.65x, a 2020-style trough discount reflecting a loss of market confidence in Level-3 private marks.
A24: Base: | B24: BVPS compounds ~8.5%/yr - between the 5yr (7.0%) and 10yr (9.2%) historical CAGR, reflecting India nominal GDP growth (~10-11%) less structural rupee depreciation (~2-3%/yr) less base+performance fee drag (~1.5%/yr), applied uniformly across 5 years (no deceleration needed since this is already a blended/normalized rate). Exit P/B of 0.80x reflects the persistent discount to book the stock has traded at every year since 2019 (versus 1.05-1.4x in the 2015-2018 period) - i.e., the market does NOT re-rate to book value even if BVPS keeps compounding.
A25: Bull: | B25: BVPS compounds 12%/yr - the Anchorage/BIAL IPO (long-stop September 16, 2026) crystallizes value and shifts ~85% of the portfolio to public mark-to-market (from 31% today), Indian public-holdings marks recover from the Q1 2026 trough, and continued accretive buybacks below book add per-share value. Exit P/B narrows to 0.95x as the IPO catalyst plus improved earnings transparency closes most (not all) of the historical discount.

Sheet Sensitivity
A1: Sensitivity Analysis - Base Case
A2: Intrinsic Value ($/share) by Cost of Equity (rows) x Exit Price/Book Multiple (columns)
A3: Uses Base-case Year-5 BVPS. Axis 2 is EXIT P/B (not Gordon-growth terminal growth) since there is no perpetuity FCF.
A5: Cost of Equity \ Exit P/B | B5: 0.65 | C5: 0.75 | D5: 0.8 | E5: 0.85 | F5: 0.95
A6: 0.09 | B6: ='BVPS Model'!$B$21*B$5/(1+$A6)^5 | C6: ='BVPS Model'!$B$21*C$5/(1+$A6)^5 | D6: ='BVPS Model'!$B$21*D$5/(1+$A6)^5 | E6: ='BVPS Model'!$B$21*E$5/(1+$A6)^5 | F6: ='BVPS Model'!$B$21*F$5/(1+$A6)^5
A7: 0.1 | B7: ='BVPS Model'!$B$21*B$5/(1+$A7)^5 | C7: ='BVPS Model'!$B$21*C$5/(1+$A7)^5 | D7: ='BVPS Model'!$B$21*D$5/(1+$A7)^5 | E7: ='BVPS Model'!$B$21*E$5/(1+$A7)^5 | F7: ='BVPS Model'!$B$21*F$5/(1+$A7)^5
A8: 0.11 | B8: ='BVPS Model'!$B$21*B$5/(1+$A8)^5 | C8: ='BVPS Model'!$B$21*C$5/(1+$A8)^5 | D8: ='BVPS Model'!$B$21*D$5/(1+$A8)^5 | E8: ='BVPS Model'!$B$21*E$5/(1+$A8)^5 | F8: ='BVPS Model'!$B$21*F$5/(1+$A8)^5
A9: 0.12 | B9: ='BVPS Model'!$B$21*B$5/(1+$A9)^5 | C9: ='BVPS Model'!$B$21*C$5/(1+$A9)^5 | D9: ='BVPS Model'!$B$21*D$5/(1+$A9)^5 | E9: ='BVPS Model'!$B$21*E$5/(1+$A9)^5 | F9: ='BVPS Model'!$B$21*F$5/(1+$A9)^5
A10: 0.13 | B10: ='BVPS Model'!$B$21*B$5/(1+$A10)^5 | C10: ='BVPS Model'!$B$21*C$5/(1+$A10)^5 | D10: ='BVPS Model'!$B$21*D$5/(1+$A10)^5 | E10: ='BVPS Model'!$B$21*E$5/(1+$A10)^5 | F10: ='BVPS Model'!$B$21*F$5/(1+$A10)^5

Sheet Historical
A1: Historical BVPS & Book Value Growth
A3: Period | B3: BVPS ($) | C3: Shareholders Equity ($M) | D3: Net Earnings ($M)
A4: FY2015 | B4: 9.5 | C4: 1013.3 | D4: 40.9
A5: FY2016 | B5: 10.25 | C5: 1075.4 | D5: 107.8
A6: FY2017 | B6: 14.46 | C6: 2132.5 | D6: 452.5
A7: FY2018 | B7: 13.86 | C7: 2117.9 | D7: 96.4
A8: FY2019 | B8: 16.89 | C8: 2577.9 | D8: 516.3
A9: FY2020 | B9: 16.37 | C9: 2446.9 | D9: -41.5
A10: FY2021 | B10: 19.65 | C10: 2774.8 | D10: 494.5
A11: FY2022 | B11: 19.11 | C11: 2642 | D11: 191.4
A12: FY2023 | B12: 21.85 | C12: 2958.7 | D12: 371.8
A13: FY2024 | B13: 20.96 | C13: 2826.5 | D13: -41.2
A14: FY2025 | B14: 22.94 | C14: 3079.6 | D14: 410.5
A15: Q1 2026 | B15: 19.08 | C15: 2560.4 | D15: -364.4
A17: BVPS CAGR 2015-2025 (10yr) | B17: =(B14/B4)^(1/10)-1
A18: BVPS CAGR 2020-2025 (5yr) | B18: =(B14/B9)^(1/5)-1
A20: Note: Net Earnings are mark-to-market portfolio gains/losses, NOT operating FCF.

Sheet Philosophy
A1: FIH.U - Valuation Philosophy & Sanity Check
A3: WHY NOT A CONVENTIONAL FCF DCF
A4: FCF DCF requires (1) operating cash generation distinct from investment marks, and (2) a stable margin/reinvestment structure to project forward. Fairfax India has neither: cash flow statement items are dominated by portfolio purchases/sales and mark-to-market non-cash items, and the 'business' is capital allocation into a concentrated, illiquid basket of Indian private and public holdings (BIAL alone ~55-62% of portfolio value) rather than a scalable operating model with a repeatable unit economics.
A6: METHODOLOGY SUMMARY
A7: Fairfax India is a permanent-capital investment holding company, not an operating business - it has no product revenue, no operating margin, and no free cash flow to discount. Reported 'net earnings' are unrealized/realized mark-to-market swings on a ~70% privately-valued (Level 3, internal DCF) portfolio of Indian equity and infrastructure stakes, and have ranged from -$364M to +$411M across the last five reported periods alone. Attempting a conventional revenue-growth/FCF-margin DCF on this entity would either double-count value already embedded in Level-3 marks or produce a meaningless output driven by noise in quarterly realized/unrealized gains. Instead, the company's own primary performance metric - Book Value Per Share - is projected forward using a growth rate anchored to its 10-year (9.2%) and 5-year (7.0%) historical CAGRs, net of the base+performance fee drag already embedded in reported BVPS. A scenario-specific EXIT PRICE-TO-BOOK multiple, calibrated to the stock's own trading history (1.05-1.4x at IPO/peak, but a persistent 0.6-0.85x discount every year since 2019), converts the projected Year-5 BVPS into an expected per-share market value; that value is discounted back 5 years at a cost-of-equity rate built up from risk-free + equity risk premium + small-cap + EM + Level-3-opacity components. The exit P/B multiple functions as the terminal value mechanism - there is no separate Gordon-growth perpetuity calculation, because there is no perpetual free cash flow stream to grow.
A9: COST OF EQUITY RATIONALE
A10: Built up from: risk-free rate (~4.3% US 10yr, since USD-reporting) + equity risk premium (~5%) + small/mid-cap size premium (~1.5%) + emerging-market/India-specific premium (~1.5%) + governance/Level-3 valuation-opacity premium (~1%) + controlled-company (Fairfax 95.3% voting control vs 43.6% equity interest) discount-rate premium, netted against the diversification benefit of a multi-asset portfolio versus a single operating company. Bull case uses 10% (IPO catalyst reduces valuation-opacity premium); bear case uses 13% (elevated EM/currency/execution risk premium in a stress scenario). For reference, BIAL itself (the largest single holding) is internally DCF'd by the company at 12.2%-17.2% after-tax discount rates, consistent with the range used here at the holdco level.
A12: SANITY CHECK
A13: Base-case IV of $13.62 implies 0.71x current BVPS ($19.08) and 0.59x FY2025 BVPS ($22.94) - both comfortably within, or below, the persistent 2019-2025 trading range of 0.6x-0.85x book, which is the expected result of discounting a 0.80x exit multiple back 5 years at 11% cost of equity. Bull case ($19.83) implies 1.04x current BVPS, at the high end of the historical range but still below the 2017-2018 peak of ~1.35x, consistent with a partial (not full) re-rating on the IPO catalyst. Bear case ($8.39) implies 0.44x current BVPS, below even the 2020 COVID trough of 0.60x, appropriately reflecting a severe stress scenario (IPO shelved again + accelerated rupee depreciation + Level-3 mark confidence crisis).
A15: Historical Price/Book Range: IPO 2015 ~1.05x | Peak 2017-18 ~1.35x | Post-2019 persistent 0.60x-0.85x | 2020 trough 0.60x
