Workbook

Sheet DCF Model
A1: APL.NZ NTA Realisation (Wind-Down) Model -- BASE CASE
A2: Gray cells are INPUTS - adjust to see valuation change. This is an asset-realisation model, not a growth FCF DCF.
A4: KEY INPUTS
A5: Current Stock Price | B5: 0.165
A6: Shares Outstanding (M) | B6: 362.7178
A7: Shareholders Equity / NTA (NZ$m) | B7: 111.31
A8: Current NTA per Share | B8: =B7/B6 -> 0
A9: Cash (NZ$m) | B9: 6.926
A10: Total Debt (NZ$m) | B10: 0
A11: Property Carrying Value (NZ$m) | B11: 105.5
A12: Occupancy % | B12: 0.756
A14: Cost of Equity (Base) | B14: 0.1875
A15: Realisation Horizon (years) | B15: 3
A16: Exit Price-to-NTA Multiple | B16: 0.75
A18: REALISATION PATH (BASE CASE)
B19: FY2027 | C19: FY2028 | D19: FY2029
A20: NTA per Share (projected) | B20: 0.3 | C20: 0.298 | D20: 0.298
A21: Dividend per Share | B21: 0.008 | C21: 0.01 | D21: 0.01
A22: Discount Factor | B22: =1/(1+$B$14)^1 -> 0 | C22: =1/(1+$B$14)^2 -> 0 | D22: =1/(1+$B$14)^3 -> 0
A23: PV of Dividend | B23: =B21*B22 -> 0 | C23: =C21*C22 -> 0 | D23: =D21*D22 -> 0
A25: VALUATION (BASE CASE)
A26: Sum of PV of Dividends | B26: =SUM(B23:D23) -> 0
A27: Exit NTA per Share (Year 3) | B27: =D20 -> 0
A28: Exit Value per Share (NTA x Multiple) | B28: =B27*B16 -> 0
A29: PV of Exit Value | B29: =B28*D22 -> 0
A30: INTRINSIC VALUE PER SHARE | B30: =B26+B29 -> 0
A31: Upside/(Downside) vs Current Price | B31: =(B30-B5)/B5 -> 0
A33: ENTRY PRICE (15% IRR Target)
A34: Hurdle Rate | B34: 0.15
A35: PV of Dividends @ Hurdle | B35: =NPV(B34,B21:D21) -> 0
A36: PV of Exit Value @ Hurdle | B36: =B28/(1+B34)^B15 -> 0
A37: ENTRY PRICE | B37: =B35+B36 -> 0
A38: Discount/(Premium) of Entry Price to Current | B38: =(B37-B5)/B5 -> 0
A40: SCENARIO SUMMARY (from JSON - not formula-linked)
A41: Scenario | B41: Cost of Equity | C41: Exit P/NTA | D41: Intrinsic Value | E41: Upside %
A42: Bear | B42: 0.2225 | C42: 0.55 | D42: 0.0845 | E42: -0.488
A43: Base | B43: 0.1875 | C43: 0.75 | D43: 0.1533 | E43: -0.071
A44: Bull | B44: 0.1525 | C44: 0.95 | D44: 0.2217 | E44: 0.344
A45: Probability-Weighted IV | B45: 0.1532
A46: Weights (Bear/Base/Bull) | B46: 0.25/0.5/0.25

Sheet Sensitivity
A1: Sensitivity Analysis
A2: Intrinsic Value/Share by Cost of Equity & Exit Price-to-NTA Multiple
A3: (Terminal growth is not meaningful for a wind-down vehicle; exit P/NTA multiple is the analogous lever)
A5: CoE \ Exit P/NTA | B5: 0.55 | C5: 0.65 | D5: 0.75 | E5: 0.85 | F5: 0.95
A6: 0.1475 | B6: =NPV(0.1475,'DCF Model'!$B$21:$D$21)+('DCF Model'!$D$20*0.55)/(1+0.1475)^'DCF Model'!$B$15 -> 0 | C6: =NPV(0.1475,'DCF Model'!$B$21:$D$21)+('DCF Model'!$D$20*0.65)/(1+0.1475)^'DCF Model'!$B$15 -> 0 | D6: =NPV(0.1475,'DCF Model'!$B$21:$D$21)+('DCF Model'!$D$20*0.75)/(1+0.1475)^'DCF Model'!$B$15 -> 0 | E6: =NPV(0.1475,'DCF Model'!$B$21:$D$21)+('DCF Model'!$D$20*0.85)/(1+0.1475)^'DCF Model'!$B$15 -> 0 | F6: =NPV(0.1475,'DCF Model'!$B$21:$D$21)+('DCF Model'!$D$20*0.95)/(1+0.1475)^'DCF Model'!$B$15 -> 0
A7: 0.1675 | B7: =NPV(0.1675,'DCF Model'!$B$21:$D$21)+('DCF Model'!$D$20*0.55)/(1+0.1675)^'DCF Model'!$B$15 -> 0 | C7: =NPV(0.1675,'DCF Model'!$B$21:$D$21)+('DCF Model'!$D$20*0.65)/(1+0.1675)^'DCF Model'!$B$15 -> 0 | D7: =NPV(0.1675,'DCF Model'!$B$21:$D$21)+('DCF Model'!$D$20*0.75)/(1+0.1675)^'DCF Model'!$B$15 -> 0 | E7: =NPV(0.1675,'DCF Model'!$B$21:$D$21)+('DCF Model'!$D$20*0.85)/(1+0.1675)^'DCF Model'!$B$15 -> 0 | F7: =NPV(0.1675,'DCF Model'!$B$21:$D$21)+('DCF Model'!$D$20*0.95)/(1+0.1675)^'DCF Model'!$B$15 -> 0
A8: 0.1875 | B8: =NPV(0.1875,'DCF Model'!$B$21:$D$21)+('DCF Model'!$D$20*0.55)/(1+0.1875)^'DCF Model'!$B$15 -> 0 | C8: =NPV(0.1875,'DCF Model'!$B$21:$D$21)+('DCF Model'!$D$20*0.65)/(1+0.1875)^'DCF Model'!$B$15 -> 0 | D8: =NPV(0.1875,'DCF Model'!$B$21:$D$21)+('DCF Model'!$D$20*0.75)/(1+0.1875)^'DCF Model'!$B$15 -> 0 | E8: =NPV(0.1875,'DCF Model'!$B$21:$D$21)+('DCF Model'!$D$20*0.85)/(1+0.1875)^'DCF Model'!$B$15 -> 0 | F8: =NPV(0.1875,'DCF Model'!$B$21:$D$21)+('DCF Model'!$D$20*0.95)/(1+0.1875)^'DCF Model'!$B$15 -> 0
A9: 0.2075 | B9: =NPV(0.2075,'DCF Model'!$B$21:$D$21)+('DCF Model'!$D$20*0.55)/(1+0.2075)^'DCF Model'!$B$15 -> 0 | C9: =NPV(0.2075,'DCF Model'!$B$21:$D$21)+('DCF Model'!$D$20*0.65)/(1+0.2075)^'DCF Model'!$B$15 -> 0 | D9: =NPV(0.2075,'DCF Model'!$B$21:$D$21)+('DCF Model'!$D$20*0.75)/(1+0.2075)^'DCF Model'!$B$15 -> 0 | E9: =NPV(0.2075,'DCF Model'!$B$21:$D$21)+('DCF Model'!$D$20*0.85)/(1+0.2075)^'DCF Model'!$B$15 -> 0 | F9: =NPV(0.2075,'DCF Model'!$B$21:$D$21)+('DCF Model'!$D$20*0.95)/(1+0.2075)^'DCF Model'!$B$15 -> 0
A10: 0.2275 | B10: =NPV(0.2275,'DCF Model'!$B$21:$D$21)+('DCF Model'!$D$20*0.55)/(1+0.2275)^'DCF Model'!$B$15 -> 0 | C10: =NPV(0.2275,'DCF Model'!$B$21:$D$21)+('DCF Model'!$D$20*0.65)/(1+0.2275)^'DCF Model'!$B$15 -> 0 | D10: =NPV(0.2275,'DCF Model'!$B$21:$D$21)+('DCF Model'!$D$20*0.75)/(1+0.2275)^'DCF Model'!$B$15 -> 0 | E10: =NPV(0.2275,'DCF Model'!$B$21:$D$21)+('DCF Model'!$D$20*0.85)/(1+0.2275)^'DCF Model'!$B$15 -> 0 | F10: =NPV(0.2275,'DCF Model'!$B$21:$D$21)+('DCF Model'!$D$20*0.95)/(1+0.2275)^'DCF Model'!$B$15 -> 0

Sheet FCF Quality
A1: NTA / Earnings Quality Reconciliation
A2: APL.NZ has no meaningful "free cash flow" concept to reconcile (see valuation_philosophy) -- this sheet instead reconciles reported earnings to NTA and to AFFO, the company's own cash-quality metric.
A4: Fiscal Year | B4: FY2015 | C4: FY2017 | D4: FY2018 | E4: FY2019 | F4: FY2020 | G4: FY2021 | H4: FY2022 | I4: FY2023 | J4: FY2024 | K4: FY2025 | L4: FY2026
A5: Shareholders Equity (NZ$m) | B5: 117.425 | C5: 117.073 | D5: 114.339 | E5: 112.314 | F5: 91.795 | G5: 162.361 | H5: 159.554 | I5: 146.505 | J5: 141.208 | K5: 117.374 | L5: 111.31
A6: Shares Outstanding (M) | B6: 161.92043 | C6: 161.92043 | D6: 161.92043 | E6: 161.92043 | F6: 161.92043 | G6: 362.7178 | H6: 362.7178 | I6: 362.7178 | J6: 362.7178 | K6: 362.7178 | L6: 362.7178
A7: NTA per Share | B7: 0.7252 | C7: 0.723 | D7: 0.7061 | E7: 0.6936 | F7: 0.5669 | G7: 0.4476 | H7: 0.4399 | I7: 0.4039 | J7: 0.3893 | K7: 0.3236 | L7: 0.3069
A8: Net Income / (Loss) (NZ$m) | B8: 5.076 | C8: 3.073 | D8: 3.095 | E8: 3.803 | F8: -14.688 | G8: 15.949 | H8: 2.931 | I8: -13.049 | J8: -5.297 | K8: -5.696 | L8: -3.164
A9: Note
A10: FY2021 equity/share step change reflects a real capital raise (shares 161.9m -> 362.7m), not restatement.
A11: FY2025-FY2026 sees 35 Graham Street sold (Nov-2024); portfolio is now single-asset (Munroe Lane) only.
A12: FY2026 AFFO (post leasing incentives) was only $0.169m vs $2.902m dividends paid -- distributions currently funded from cash, not earnings.
A13: Reported Net Income is dominated by IAS 40 unrealised fair-value revaluations in most years and is NOT a cash-earnings proxy.

Sheet Historical
A1: Historical P/NTA Discount
A3: Fiscal Year End | B3: Approx Price (NZ$) | C3: NTA/Share (NZ$) | D3: P/NTA Discount %
A4: FY2018 | B4: 0.58 | C4: 0.7061 | D4: =B4/C4-1 -> 0
A5: FY2019 | B5: 0.64 | C5: 0.6936 | D5: =B5/C5-1 -> 0
A6: FY2020 | B6: 0.415 | C6: 0.5669 | D6: =B6/C6-1 -> 0
A7: FY2021 | B7: 0.325 | C7: 0.4476 | D7: =B7/C7-1 -> 0
A8: FY2022 | B8: 0.265 | C8: 0.4399 | D8: =B8/C8-1 -> 0
A9: FY2023 | B9: 0.265 | C9: 0.4039 | D9: =B9/C9-1 -> 0
A10: FY2024 | B10: 0.21 | C10: 0.3893 | D10: =B10/C10-1 -> 0
A11: FY2025 | B11: 0.215 | C11: 0.3236 | D11: =B11/C11-1 -> 0
A12: FY2026 | B12: 0.163 | C12: 0.3069 | D12: =B12/C12-1 -> 0
A14: Tightest Discount: | B14: -0.077
A15: Widest Discount: | B15: -0.469
A16: Current Discount: | B16: -0.462

Sheet Model_Info
A1: Model Provenance & Methodology Notes
A3: Built by | B3: Claude (dcf-analyst agent), Stock Research Project
A4: Build date | B4: 2026-08-09
A5: Share price date/source | B5: NZ$0.165, Yahoo Finance intraday quote fetched 2026-08-09
A6: Data vintage | B6: FY2026 Annual Results (22-May-2026); Aug-2026 AGM (6-Aug-2026) and dividend increase announcement (0.25 cps for FY2027 Q1, ex-div 14-Aug-2026)
A7: Model type | B7: NTA / asset-realisation (wind-down) model -- NOT a standard growth FCF-to-firm DCF. See "DCF Model" sheet valuation_philosophy equivalent in the JSON output for full rationale.
A8: Why not a standard FCF DCF | B8: 35 Graham Street sold Nov-2024 (all historical revenue/NI CAGRs describe a dead 2-asset portfolio); reported NI dominated by IAS 40 fair-value swings; FY2026 AFFO ($0.169m) far below dividends paid ($2.902m); vehicle is explicitly being wound down, not grown.
A9: Discount rate | B9: Cost of equity build-up (18.75% base), NOT WACC -- company is debt-free (0% LVR since Nov-2024).
A10: Terminal value analogue | B10: Exit price-to-NTA multiple applied to projected Year-3 NTA/share, calibrated to APL.NZ's own historical P/NTA trading range (-7.7% tightest FY2019 to -46.9% widest, essentially today).
A11: Realisation horizon | B11: 3 years (FY2027-FY2029) -- this is the MODEL'S OWN ESTIMATE. No sale process, wind-up resolution or fixed timetable had been disclosed by management as of the 6-Aug-2026 AGM. Treat with real uncertainty in both directions.
A12: Net cash treatment | B12: NOT added a second time on top of exit NTA value -- the $6.926m cash balance is already embedded inside reported shareholders equity / NTA per share.
A13: SBC | B13: Verified nil. Externally managed vehicle (Centuria Funds Management NZ) with no equity incentive scheme.
A14: Cell colour convention | B14: Gray-shaded cells = editable inputs. White cells with borders = formulas. Green highlighted cells = key outputs (Intrinsic Value, Entry Price).
... A16: Staleness warning | B16: All figures in this workbook go stale after the next results release or any wind-up/sale announcement and MUST be re-checked before being relied upon.
