Workbook

Sheet DCF Model
A1: ADYEY (Adyen N.V.) DCF Valuation Model - BASE CASE
A2: Model built in EUR at ordinary-share level; converted to USD per ADR (1 ADR = 1/100 ordinary share). Gray cells are INPUTS.
A4: KEY INPUTS (EUR, millions except per-share/ADR)
A5: Current ADR Price (USD) | B5: 9.45
A6: EURUSD Exchange Rate | B6: 1.1446
A7: Ordinary Shares Outstanding (M, diluted) | B7: 31.5
A8: ADR Ratio (ordinary shares per ADR) | B8: 0.01
A9: Own-Cash (M EUR) | B9: 4987.3
A10: Lease Liabilities (M EUR) | B10: 252.4
A11: Net Cash (M EUR) | B11: =B9-B10 -> 0
A12: Net Debt (M EUR) [negative = net cash] | B12: =-B11 -> 0
A13: Base Year FCF (M EUR, FY2025) | B13: 1081.3
A15: WACC | B15: 0.105
A16: Terminal Growth Rate | B16: 0.03
A18: GROWTH ASSUMPTIONS (FCF growth, base case) | B18: FY2026 | C18: FY2027 | D18: FY2028 | E18: FY2029 | F18: FY2030
A19: FCF Growth Rate | B19: 0.2 | C19: 0.17 | D19: 0.15 | E19: 0.13 | F19: 0.115
A21: PROJECTIONS (EUR millions)
B22: FY2025 | C22: FY2026 | D22: FY2027 | E22: FY2028 | F22: FY2029 | G22: FY2030
A23: Free Cash Flow (EUR M) | B23: =B13 -> 0 | C23: =B23*(1+B19) -> 0 | D23: =C23*(1+C19) -> 0 | E23: =D23*(1+D19) -> 0 | F23: =E23*(1+E19) -> 0 | G23: =F23*(1+F19) -> 0
A24: Discount Factor | C24: =1/(1+$B$15)^1 -> 0 | D24: =1/(1+$B$15)^2 -> 0 | E24: =1/(1+$B$15)^3 -> 0 | F24: =1/(1+$B$15)^4 -> 0 | G24: =1/(1+$B$15)^5 -> 0
A25: PV of FCF (EUR M) | C25: =C23*C24 -> 0 | D25: =D23*D24 -> 0 | E25: =E23*E24 -> 0 | F25: =F23*F24 -> 0 | G25: =G23*G24 -> 0
A27: VALUATION (EUR millions)
A28: Sum of PV of FCF | B28: =SUM(C25:G25) -> 0
A29: Terminal FCF (Year 5 x (1+g)) | B29: =G23*(1+$B$16) -> 0
A30: Terminal Value | B30: =B29/($B$15-$B$16) -> 0
A31: PV of Terminal Value | B31: =B30*G24 -> 0
A32: Enterprise Value | B32: =B28+B31 -> 0
A33: Less: Net Debt | B33: =B12 -> 0
A34: Equity Value | B34: =B32-B33 -> 0
A35: INTRINSIC VALUE / ORDINARY SHARE (EUR) | B35: =B34/B7 -> 0
A36: INTRINSIC VALUE / ADR (USD) | B36: =B35*B6*B8 -> 0
A38: ENTRY PRICE (15% CAGR Target)
A39: Terminal Value per Ordinary Share (EUR) | B39: =B30/B7 -> 0
A40: Terminal Value per ADR (USD) | B40: =B39*B6*B8 -> 0
A41: Entry Price per ADR (15% CAGR, USD) | B41: =B40/(1.15^5) -> 0
A43: Upside to Intrinsic Value (ADR) | B43: =(B36-B5)/B5 -> 0
A44: Upside to Entry Price (ADR) | B44: =(B5-B41)/B5 -> 0
A46: Notes:
A47: Own-cash excludes merchant settlement funds (gross cash EUR 10,797.4m includes pass-through merchant balances not available to equity holders).
A48: FY2025 FCF (EUR 1,081.3m, +25.8% YoY) is NOT a peak - FY2026 guidance is 20-22% CC net revenue growth with flat EBITDA margin, implying continued FCF growth.

Sheet Scenarios
A1: Bull / Bear Scenario Comparison
A2: Independent of DCF Model sheet inputs - hardcoded scenario assumptions per Analysis JSON
B4: Base (ref) | C4: Bull | F4: Bear
A5: WACC | B5: 0.105 | C5: 0.09 | F5: 0.125
A6: Terminal Growth | B6: 0.03 | C6: 0.035 | F6: 0.025
A8: FCF Growth Rates (Y1-Y5)
B9: 0.2 | C9: 0.17 | D9: 0.15 | E9: 0.13 | F9: 0.115
B10: 0.24 | C10: 0.23 | D10: 0.21 | E10: 0.19 | F10: 0.17
B11: 0.13 | C11: 0.13 | D11: 0.12 | E11: 0.11 | F11: 0.1
A13: RESULTS SUMMARY (USD per ADR)
A14: Scenario | B14: Intrinsic Value | C14: Upside vs $9.45
A15: Bull | B15: 16.85 | C15: =(B15-9.45)/9.45 -> 0
A16: Base | B16: 10.7 | C16: =(B16-9.45)/9.45 -> 0
A17: Bear | B17: 7.58 | C17: =(B17-9.45)/9.45 -> 0
A19: Probability-Weighted IV | B19: =0.25*B15+0.50*B16+0.25*B17 -> 0
A20: Weights: Bull 25% / Base 50% / Bear 25%

Sheet Sensitivity
A1: Sensitivity Analysis
A2: Intrinsic Value per ADR (USD) by WACC & Terminal Growth - Base Case FCF path
A4: WACC \ Term G | B4: 0.02 | C4: 0.025 | D4: 0.03 | E4: 0.035 | F4: 0.04
A5: 0.085 | B5: =('DCF Model'!$B$13*(1+'DCF Model'!$B$19)*(1+'DCF Model'!$C$19)*(1+'DCF Model'!$D$19)*(1+'DCF Model'!$E$19)*(1+'DCF Model'!$F$19)*(1+0.02)/(0.085-0.02))/(1+0.085)^5/'DCF Model'!$B$7*'DCF Model'!$B$6*'DCF Model'!$B$8 -> 0 | C5: =('DCF Model'!$B$13*(1+'DCF Model'!$B$19)*(1+'DCF Model'!$C$19)*(1+'DCF Model'!$D$19)*(1+'DCF Model'!$E$19)*(1+'DCF Model'!$F$19)*(1+0.025)/(0.085-0.025))/(1+0.085)^5/'DCF Model'!$B$7*'DCF Model'!$B$6*'DCF Model'!$B$8 -> 0 | D5: =('DCF Model'!$B$13*(1+'DCF Model'!$B$19)*(1+'DCF Model'!$C$19)*(1+'DCF Model'!$D$19)*(1+'DCF Model'!$E$19)*(1+'DCF Model'!$F$19)*(1+0.03)/(0.085-0.03))/(1+0.085)^5/'DCF Model'!$B$7*'DCF Model'!$B$6*'DCF Model'!$B$8 -> 0 | E5: =('DCF Model'!$B$13*(1+'DCF Model'!$B$19)*(1+'DCF Model'!$C$19)*(1+'DCF Model'!$D$19)*(1+'DCF Model'!$E$19)*(1+'DCF Model'!$F$19)*(1+0.035)/(0.085-0.035))/(1+0.085)^5/'DCF Model'!$B$7*'DCF Model'!$B$6*'DCF Model'!$B$8 -> 0 | F5: =('DCF Model'!$B$13*(1+'DCF Model'!$B$19)*(1+'DCF Model'!$C$19)*(1+'DCF Model'!$D$19)*(1+'DCF Model'!$E$19)*(1+'DCF Model'!$F$19)*(1+0.04)/(0.085-0.04))/(1+0.085)^5/'DCF Model'!$B$7*'DCF Model'!$B$6*'DCF Model'!$B$8 -> 0
A6: 0.095 | B6: =('DCF Model'!$B$13*(1+'DCF Model'!$B$19)*(1+'DCF Model'!$C$19)*(1+'DCF Model'!$D$19)*(1+'DCF Model'!$E$19)*(1+'DCF Model'!$F$19)*(1+0.02)/(0.095-0.02))/(1+0.095)^5/'DCF Model'!$B$7*'DCF Model'!$B$6*'DCF Model'!$B$8 -> 0 | C6: =('DCF Model'!$B$13*(1+'DCF Model'!$B$19)*(1+'DCF Model'!$C$19)*(1+'DCF Model'!$D$19)*(1+'DCF Model'!$E$19)*(1+'DCF Model'!$F$19)*(1+0.025)/(0.095-0.025))/(1+0.095)^5/'DCF Model'!$B$7*'DCF Model'!$B$6*'DCF Model'!$B$8 -> 0 | D6: =('DCF Model'!$B$13*(1+'DCF Model'!$B$19)*(1+'DCF Model'!$C$19)*(1+'DCF Model'!$D$19)*(1+'DCF Model'!$E$19)*(1+'DCF Model'!$F$19)*(1+0.03)/(0.095-0.03))/(1+0.095)^5/'DCF Model'!$B$7*'DCF Model'!$B$6*'DCF Model'!$B$8 -> 0 | E6: =('DCF Model'!$B$13*(1+'DCF Model'!$B$19)*(1+'DCF Model'!$C$19)*(1+'DCF Model'!$D$19)*(1+'DCF Model'!$E$19)*(1+'DCF Model'!$F$19)*(1+0.035)/(0.095-0.035))/(1+0.095)^5/'DCF Model'!$B$7*'DCF Model'!$B$6*'DCF Model'!$B$8 -> 0 | F6: =('DCF Model'!$B$13*(1+'DCF Model'!$B$19)*(1+'DCF Model'!$C$19)*(1+'DCF Model'!$D$19)*(1+'DCF Model'!$E$19)*(1+'DCF Model'!$F$19)*(1+0.04)/(0.095-0.04))/(1+0.095)^5/'DCF Model'!$B$7*'DCF Model'!$B$6*'DCF Model'!$B$8 -> 0
A7: 0.105 | B7: =('DCF Model'!$B$13*(1+'DCF Model'!$B$19)*(1+'DCF Model'!$C$19)*(1+'DCF Model'!$D$19)*(1+'DCF Model'!$E$19)*(1+'DCF Model'!$F$19)*(1+0.02)/(0.105-0.02))/(1+0.105)^5/'DCF Model'!$B$7*'DCF Model'!$B$6*'DCF Model'!$B$8 -> 0 | C7: =('DCF Model'!$B$13*(1+'DCF Model'!$B$19)*(1+'DCF Model'!$C$19)*(1+'DCF Model'!$D$19)*(1+'DCF Model'!$E$19)*(1+'DCF Model'!$F$19)*(1+0.025)/(0.105-0.025))/(1+0.105)^5/'DCF Model'!$B$7*'DCF Model'!$B$6*'DCF Model'!$B$8 -> 0 | D7: =('DCF Model'!$B$13*(1+'DCF Model'!$B$19)*(1+'DCF Model'!$C$19)*(1+'DCF Model'!$D$19)*(1+'DCF Model'!$E$19)*(1+'DCF Model'!$F$19)*(1+0.03)/(0.105-0.03))/(1+0.105)^5/'DCF Model'!$B$7*'DCF Model'!$B$6*'DCF Model'!$B$8 -> 0 | E7: =('DCF Model'!$B$13*(1+'DCF Model'!$B$19)*(1+'DCF Model'!$C$19)*(1+'DCF Model'!$D$19)*(1+'DCF Model'!$E$19)*(1+'DCF Model'!$F$19)*(1+0.035)/(0.105-0.035))/(1+0.105)^5/'DCF Model'!$B$7*'DCF Model'!$B$6*'DCF Model'!$B$8 -> 0 | F7: =('DCF Model'!$B$13*(1+'DCF Model'!$B$19)*(1+'DCF Model'!$C$19)*(1+'DCF Model'!$D$19)*(1+'DCF Model'!$E$19)*(1+'DCF Model'!$F$19)*(1+0.04)/(0.105-0.04))/(1+0.105)^5/'DCF Model'!$B$7*'DCF Model'!$B$6*'DCF Model'!$B$8 -> 0
A8: 0.115 | B8: =('DCF Model'!$B$13*(1+'DCF Model'!$B$19)*(1+'DCF Model'!$C$19)*(1+'DCF Model'!$D$19)*(1+'DCF Model'!$E$19)*(1+'DCF Model'!$F$19)*(1+0.02)/(0.115-0.02))/(1+0.115)^5/'DCF Model'!$B$7*'DCF Model'!$B$6*'DCF Model'!$B$8 -> 0 | C8: =('DCF Model'!$B$13*(1+'DCF Model'!$B$19)*(1+'DCF Model'!$C$19)*(1+'DCF Model'!$D$19)*(1+'DCF Model'!$E$19)*(1+'DCF Model'!$F$19)*(1+0.025)/(0.115-0.025))/(1+0.115)^5/'DCF Model'!$B$7*'DCF Model'!$B$6*'DCF Model'!$B$8 -> 0 | D8: =('DCF Model'!$B$13*(1+'DCF Model'!$B$19)*(1+'DCF Model'!$C$19)*(1+'DCF Model'!$D$19)*(1+'DCF Model'!$E$19)*(1+'DCF Model'!$F$19)*(1+0.03)/(0.115-0.03))/(1+0.115)^5/'DCF Model'!$B$7*'DCF Model'!$B$6*'DCF Model'!$B$8 -> 0 | E8: =('DCF Model'!$B$13*(1+'DCF Model'!$B$19)*(1+'DCF Model'!$C$19)*(1+'DCF Model'!$D$19)*(1+'DCF Model'!$E$19)*(1+'DCF Model'!$F$19)*(1+0.035)/(0.115-0.035))/(1+0.115)^5/'DCF Model'!$B$7*'DCF Model'!$B$6*'DCF Model'!$B$8 -> 0 | F8: =('DCF Model'!$B$13*(1+'DCF Model'!$B$19)*(1+'DCF Model'!$C$19)*(1+'DCF Model'!$D$19)*(1+'DCF Model'!$E$19)*(1+'DCF Model'!$F$19)*(1+0.04)/(0.115-0.04))/(1+0.115)^5/'DCF Model'!$B$7*'DCF Model'!$B$6*'DCF Model'!$B$8 -> 0
A9: 0.125 | B9: =('DCF Model'!$B$13*(1+'DCF Model'!$B$19)*(1+'DCF Model'!$C$19)*(1+'DCF Model'!$D$19)*(1+'DCF Model'!$E$19)*(1+'DCF Model'!$F$19)*(1+0.02)/(0.125-0.02))/(1+0.125)^5/'DCF Model'!$B$7*'DCF Model'!$B$6*'DCF Model'!$B$8 -> 0 | C9: =('DCF Model'!$B$13*(1+'DCF Model'!$B$19)*(1+'DCF Model'!$C$19)*(1+'DCF Model'!$D$19)*(1+'DCF Model'!$E$19)*(1+'DCF Model'!$F$19)*(1+0.025)/(0.125-0.025))/(1+0.125)^5/'DCF Model'!$B$7*'DCF Model'!$B$6*'DCF Model'!$B$8 -> 0 | D9: =('DCF Model'!$B$13*(1+'DCF Model'!$B$19)*(1+'DCF Model'!$C$19)*(1+'DCF Model'!$D$19)*(1+'DCF Model'!$E$19)*(1+'DCF Model'!$F$19)*(1+0.03)/(0.125-0.03))/(1+0.125)^5/'DCF Model'!$B$7*'DCF Model'!$B$6*'DCF Model'!$B$8 -> 0 | E9: =('DCF Model'!$B$13*(1+'DCF Model'!$B$19)*(1+'DCF Model'!$C$19)*(1+'DCF Model'!$D$19)*(1+'DCF Model'!$E$19)*(1+'DCF Model'!$F$19)*(1+0.035)/(0.125-0.035))/(1+0.125)^5/'DCF Model'!$B$7*'DCF Model'!$B$6*'DCF Model'!$B$8 -> 0 | F9: =('DCF Model'!$B$13*(1+'DCF Model'!$B$19)*(1+'DCF Model'!$C$19)*(1+'DCF Model'!$D$19)*(1+'DCF Model'!$E$19)*(1+'DCF Model'!$F$19)*(1+0.04)/(0.125-0.04))/(1+0.125)^5/'DCF Model'!$B$7*'DCF Model'!$B$6*'DCF Model'!$B$8 -> 0
A11: Note: grid shows terminal-value-driven IV (dominant term); full model (DCF Model sheet) also includes PV of explicit FCF years 1-5.

Sheet Historical
A1: Historical Growth Rates
A3: Metric | B3: 3-Year CAGR | C3: 5-Year CAGR
A4: Net Revenue | B4: 0.211 | C4: 0.281
A5: EBITDA | B5: 0.196 | C5: 0.254
A6: Equity (Book Value) | B6: 0.299 | C6: 0.341
A7: FCF | B7: 0.212 | C7: 0.256
A9: Selected Growth Rate: | B9: 0.211
A10: Source: | B10: revenue_3yr_cagr (net revenue), cross-checked against fcf_3yr_cagr (21.2%) and FY2026 guidance (20-22% CC)
A12: Divergence Warning:
A13: Shareholders'-equity CAGR (~30% 3yr / ~34% 5yr) is materially higher than net-revenue CAGR (~21% 3yr / ~28% 5yr) and FCF CAGR (~21% 3yr / ~26% 5yr). This divergence is an artifact of 100% earnings retention (Adyen pays no dividends and conducts no buybacks), not superior underlying economics. Net-revenue CAGR (~21%) is used as the primary anchor for FY2026 base-case growth, consistent with management's own 20-22% CC guidance and Q1-2026 actual (+20% CC).
