Workbook

Sheet DCF Model
A1: DELL DCF Valuation Model (Base Case)
A2: Gray cells are INPUTS - change them to see the valuation update automatically | Units: USD Millions
A3: IMPORTANT: Dell has negative shareholders equity since 2016 EMC leveraged acquisition, making equity CAGR unusable. Historical FCF CAGRs are distorted by VMware spinoff (2021) and AI server working capital dynamics. Growth rates anchored to management FY2026 guidance (+17% revenue) and AI infrastructure cycle analysis. Base FCF normalized to $5,500M vs. reported FY2025 of $1,869M (which was depressed by rapid AI server inventory/AR build).
A7: KEY INPUTS
A8: Current Stock Price ($) | B8: 117
A9: Shares Outstanding (M) | B9: 720
A10: Cash & Equivalents (M) | B10: 3633
A11: Total Debt (M) | B11: 24567
A12: Net Debt = Debt - Cash (M) | B12: =B11-B10 -> 0
A13: Normalized Base Year FCF (M) | B13: 5500 | C13: FY2025 reported FCF was $1,869M - normalized to $5,500M; see Notes sheet
A15: WACC (Discount Rate) | B15: 0.1
A16: Terminal Growth Rate | B16: 0.03
A18: BASE CASE FCF GROWTH RATES (EDITABLE)
B19: Year 1 | C19: Year 2 | D19: Year 3 | E19: Year 4 | F19: Year 5
A20: FCF Growth Rate | B20: 0.15 | C20: 0.13 | D20: 0.11 | E20: 0.09 | F20: 0.07
A21: Context | B21: AI ramp +17% rev | C21: Strong AI+CSG refresh | D21: AI cycle maturing | E21: Deceleration | F21: Normalizing
A23: FREE CASH FLOW PROJECTIONS
B24: Year 1 | C24: Year 2 | D24: Year 3 | E24: Year 4 | F24: Year 5
A25: Free Cash Flow (M) | B25: =B13*(1+B20) -> 0 | C25: =B25*(1+C20) -> 0 | D25: =C25*(1+D20) -> 0 | E25: =D25*(1+E20) -> 0 | F25: =E25*(1+F20) -> 0
A26: Discount Factor | B26: =1/(1+$B$15)^1 -> 0 | C26: =1/(1+$B$15)^2 -> 0 | D26: =1/(1+$B$15)^3 -> 0 | E26: =1/(1+$B$15)^4 -> 0 | F26: =1/(1+$B$15)^5 -> 0
A27: PV of FCF (M) | B27: =B25*B26 -> 0 | C27: =C25*C26 -> 0 | D27: =D25*D26 -> 0 | E27: =E25*E26 -> 0 | F27: =F25*F26 -> 0
A29: VALUATION SUMMARY
A30: Sum of PV of FCF (M) | B30: =SUM(B27:F27) -> 0
A31: Terminal FCF = Y5 x (1 + Terminal g) | B31: =F25*(1+$B$16) -> 0
A32: Terminal Value = Terminal FCF / (WACC - g) | B32: =B31/($B$15-$B$16) -> 0
A33: PV of Terminal Value (M) | B33: =B32*F26 -> 0
A34: Enterprise Value (M) | B34: =B30+B33 -> 0
A35: Less: Net Debt (M) | B35: =B12 -> 0
A36: Equity Value (M) | B36: =B34-B35 -> 0
A37: INTRINSIC VALUE PER SHARE | B37: =B36/B9 -> 0
A39: ENTRY PRICE ANALYSIS (Target: 15% Annual Return)
A40: Terminal Value per Share | B40: =B32/B9 -> 0
A41: Entry Price for 15% CAGR (5yr) | B41: =B40/(1.15^5) -> 0
A43: RETURN METRICS
A44: Upside / (Downside) to Intrinsic Value | B44: =(B37-B8)/B8 -> 0
A45: Stock vs. Entry Price (negative = stock above entry) | B45: =(B41-B8)/B8 -> 0
A46: PV Terminal as % of Enterprise Value | B46: =B33/B34 -> 0
A47: Net Debt / Enterprise Value | B47: =B12/B34 -> 0

Sheet Scenarios
A1: DELL - Base / Bull / Bear Scenario Comparison
A2: All values USD Millions. FCF projections based on normalized base FCF of $5,500M. Net debt $20,934M. Shares 720M.
A4: Metric | B4: BASE CASE | C4: BULL CASE | D4: BEAR CASE
A5: --- ASSUMPTIONS ---
A6: Growth Rates (Y1-Y5) | B6: 15%, 13%, 11%, 9%, 7% | C6: 20%, 18%, 15%, 12%, 10% | D6: 8%, 5%, 3%, 2%, 1%
A7: WACC | B7: 10.0% | C7: 9.0% | D7: 12.0%
A8: Terminal Growth Rate | B8: 3.0% | C8: 3.5% | D8: 2.0%
A9: --- FCF PROJECTIONS ---
A10: Year 1 FCF (M) | B10: $6,325 | C10: $6,600 | D10: $5,940
A11: Year 2 FCF (M) | B11: $7,147 | C11: $7,788 | D11: $6,237
A12: Year 3 FCF (M) | B12: $7,933 | C12: $8,956 | D12: $6,424
A13: Year 4 FCF (M) | B13: $8,647 | C13: $10,031 | D13: $6,553
A14: Year 5 FCF (M) | B14: $9,253 | C14: $11,034 | D14: $6,618
A15: --- VALUATION ---
A16: Sum PV of FCF (M) | B16: $29,267 | C16: $33,807 | D16: $22,765
A17: Terminal Value (M) | B17: $136,148 | C17: $207,641 | D17: $67,505
A18: PV of Terminal Value (M) | B18: $84,537 | C18: $134,952 | D18: $38,304
A19: Enterprise Value (M) | B19: $113,804 | C19: $168,759 | D19: $61,069
A20: Less: Net Debt (M) | B20: $20,934 | C20: $20,934 | D20: $20,934
A21: Equity Value (M) | B21: $92,870 | C21: $147,825 | D21: $40,135
A22: --- OUTPUT ---
A23: Intrinsic Value per Share | B23: $128.99 | C23: $205.31 | D23: $55.74
A24: Upside / Downside vs. $117 | B24: +10.2% | C24: +75.5% | D24: -52.4%
A25: Entry Price (15% CAGR Target) | B25: $94.01 | C25: $143.38 | D25: $46.61
A26: --- PROBABILITY WEIGHTING ---
A27: Scenario Weight | B27: 50% | C27: 25% | D27: 25%
A28: Probability-Weighted IV | B28: $129.76 | C28: vs. $117.00 current | D28: +10.9% upside

Sheet Sensitivity
A1: DELL Sensitivity Analysis - Intrinsic Value per Share (Base Case)
A2: Rows = WACC | Columns = Terminal Growth Rate | Values = Intrinsic Value per Share. Formulas reference DCF Model inputs automatically.
A4: WACC \ Term G | B4: 0.02 | C4: 0.025 | D4: 0.03 | E4: 0.035 | F4: 0.04
A5: 0.08 | B5: =('DCF Model'!$B$13*(1+'DCF Model'!$B$20)*(1+'DCF Model'!$C$20)*(1+'DCF Model'!$D$20)*(1+'DCF Model'!$E$20)*(1+'DCF Model'!$F$20)*(1+0.02)/(0.08-0.02)/(1+0.08)^5+'DCF Model'!$B$13*(1+'DCF Model'!$B$20)/(1+0.08)^1+'DCF Model'!$B$13*(1+'DCF Model'!$B$20)*(1+'DCF Model'!$C$20)/(1+0.08)^2+'DCF Model'!$B$13*(1+'DCF Model'!$B$20)*(1+'DCF Model'!$C$20)*(1+'DCF Model'!$D$20)/(1+0.08)^3+'DCF Model'!$B$13*(1+'DCF Model'!$B$20)*(1+'DCF Model'!$C$20)*(1+'DCF Model'!$D$20)*(1+'DCF Model'!$E$20)/(1+0.08)^4+'DCF Model'!$B$13*(1+'DCF Model'!$B$20)*(1+'DCF Model'!$C$20)*(1+'DCF Model'!$D$20)*(1+'DCF Model'!$E$20)*(1+'DCF Model'!$F$20)/(1+0.08)^5-'DCF Model'!$B$12)/'DCF Model'!$B$9 -> 0 | C5: =('DCF Model'!$B$13*(1+'DCF Model'!$B$20)*(1+'DCF Model'!$C$20)*(1+'DCF Model'!$D$20)*(1+'DCF Model'!$E$20)*(1+'DCF Model'!$F$20)*(1+0.025)/(0.08-0.025)/(1+0.08)^5+'DCF Model'!$B$13*(1+'DCF Model'!$B$20)/(1+0.08)^1+'DCF Model'!$B$13*(1+'DCF Model'!$B$20)*(1+'DCF Model'!$C$20)/(1+0.08)^2+'DCF Model'!$B$13*(1+'DCF Model'!$B$20)*(1+'DCF Model'!$C$20)*(1+'DCF Model'!$D$20)/(1+0.08)^3+'DCF Model'!$B$13*(1+'DCF Model'!$B$20)*(1+'DCF Model'!$C$20)*(1+'DCF Model'!$D$20)*(1+'DCF Model'!$E$20)/(1+0.08)^4+'DCF Model'!$B$13*(1+'DCF Model'!$B$20)*(1+'DCF Model'!$C$20)*(1+'DCF Model'!$D$20)*(1+'DCF Model'!$E$20)*(1+'DCF Model'!$F$20)/(1+0.08)^5-'DCF Model'!$B$12)/'DCF Model'!$B$9 -> 0 | D5: =('DCF Model'!$B$13*(1+'DCF Model'!$B$20)*(1+'DCF Model'!$C$20)*(1+'DCF Model'!$D$20)*(1+'DCF Model'!$E$20)*(1+'DCF Model'!$F$20)*(1+0.03)/(0.08-0.03)/(1+0.08)^5+'DCF Model'!$B$13*(1+'DCF Model'!$B$20)/(1+0.08)^1+'DCF Model'!$B$13*(1+'DCF Model'!$B$20)*(1+'DCF Model'!$C$20)/(1+0.08)^2+'DCF Model'!$B$13*(1+'DCF Model'!$B$20)*(1+'DCF Model'!$C$20)*(1+'DCF Model'!$D$20)/(1+0.08)^3+'DCF Model'!$B$13*(1+'DCF Model'!$B$20)*(1+'DCF Model'!$C$20)*(1+'DCF Model'!$D$20)*(1+'DCF Model'!$E$20)/(1+0.08)^4+'DCF Model'!$B$13*(1+'DCF Model'!$B$20)*(1+'DCF Model'!$C$20)*(1+'DCF Model'!$D$20)*(1+'DCF Model'!$E$20)*(1+'DCF Model'!$F$20)/(1+0.08)^5-'DCF Model'!$B$12)/'DCF Model'!$B$9 -> 0 | E5: =('DCF Model'!$B$13*(1+'DCF Model'!$B$20)*(1+'DCF Model'!$C$20)*(1+'DCF Model'!$D$20)*(1+'DCF Model'!$E$20)*(1+'DCF Model'!$F$20)*(1+0.035)/(0.08-0.035)/(1+0.08)^5+'DCF Model'!$B$13*(1+'DCF Model'!$B$20)/(1+0.08)^1+'DCF Model'!$B$13*(1+'DCF Model'!$B$20)*(1+'DCF Model'!$C$20)/(1+0.08)^2+'DCF Model'!$B$13*(1+'DCF Model'!$B$20)*(1+'DCF Model'!$C$20)*(1+'DCF Model'!$D$20)/(1+0.08)^3+'DCF Model'!$B$13*(1+'DCF Model'!$B$20)*(1+'DCF Model'!$C$20)*(1+'DCF Model'!$D$20)*(1+'DCF Model'!$E$20)/(1+0.08)^4+'DCF Model'!$B$13*(1+'DCF Model'!$B$20)*(1+'DCF Model'!$C$20)*(1+'DCF Model'!$D$20)*(1+'DCF Model'!$E$20)*(1+'DCF Model'!$F$20)/(1+0.08)^5-'DCF Model'!$B$12)/'DCF Model'!$B$9 -> 0 | F5: =('DCF Model'!$B$13*(1+'DCF Model'!$B$20)*(1+'DCF Model'!$C$20)*(1+'DCF Model'!$D$20)*(1+'DCF Model'!$E$20)*(1+'DCF Model'!$F$20)*(1+0.04)/(0.08-0.04)/(1+0.08)^5+'DCF Model'!$B$13*(1+'DCF Model'!$B$20)/(1+0.08)^1+'DCF Model'!$B$13*(1+'DCF Model'!$B$20)*(1+'DCF Model'!$C$20)/(1+0.08)^2+'DCF Model'!$B$13*(1+'DCF Model'!$B$20)*(1+'DCF Model'!$C$20)*(1+'DCF Model'!$D$20)/(1+0.08)^3+'DCF Model'!$B$13*(1+'DCF Model'!$B$20)*(1+'DCF Model'!$C$20)*(1+'DCF Model'!$D$20)*(1+'DCF Model'!$E$20)/(1+0.08)^4+'DCF Model'!$B$13*(1+'DCF Model'!$B$20)*(1+'DCF Model'!$C$20)*(1+'DCF Model'!$D$20)*(1+'DCF Model'!$E$20)*(1+'DCF Model'!$F$20)/(1+0.08)^5-'DCF Model'!$B$12)/'DCF Model'!$B$9 -> 0
A6: 0.09 | B6: =('DCF Model'!$B$13*(1+'DCF Model'!$B$20)*(1+'DCF Model'!$C$20)*(1+'DCF Model'!$D$20)*(1+'DCF Model'!$E$20)*(1+'DCF Model'!$F$20)*(1+0.02)/(0.09-0.02)/(1+0.09)^5+'DCF Model'!$B$13*(1+'DCF Model'!$B$20)/(1+0.09)^1+'DCF Model'!$B$13*(1+'DCF Model'!$B$20)*(1+'DCF Model'!$C$20)/(1+0.09)^2+'DCF Model'!$B$13*(1+'DCF Model'!$B$20)*(1+'DCF Model'!$C$20)*(1+'DCF Model'!$D$20)/(1+0.09)^3+'DCF Model'!$B$13*(1+'DCF Model'!$B$20)*(1+'DCF Model'!$C$20)*(1+'DCF Model'!$D$20)*(1+'DCF Model'!$E$20)/(1+0.09)^4+'DCF Model'!$B$13*(1+'DCF Model'!$B$20)*(1+'DCF Model'!$C$20)*(1+'DCF Model'!$D$20)*(1+'DCF Model'!$E$20)*(1+'DCF Model'!$F$20)/(1+0.09)^5-'DCF Model'!$B$12)/'DCF Model'!$B$9 -> 0 | C6: =('DCF Model'!$B$13*(1+'DCF Model'!$B$20)*(1+'DCF Model'!$C$20)*(1+'DCF Model'!$D$20)*(1+'DCF Model'!$E$20)*(1+'DCF Model'!$F$20)*(1+0.025)/(0.09-0.025)/(1+0.09)^5+'DCF Model'!$B$13*(1+'DCF Model'!$B$20)/(1+0.09)^1+'DCF Model'!$B$13*(1+'DCF Model'!$B$20)*(1+'DCF Model'!$C$20)/(1+0.09)^2+'DCF Model'!$B$13*(1+'DCF Model'!$B$20)*(1+'DCF Model'!$C$20)*(1+'DCF Model'!$D$20)/(1+0.09)^3+'DCF Model'!$B$13*(1+'DCF Model'!$B$20)*(1+'DCF Model'!$C$20)*(1+'DCF Model'!$D$20)*(1+'DCF Model'!$E$20)/(1+0.09)^4+'DCF Model'!$B$13*(1+'DCF Model'!$B$20)*(1+'DCF Model'!$C$20)*(1+'DCF Model'!$D$20)*(1+'DCF Model'!$E$20)*(1+'DCF Model'!$F$20)/(1+0.09)^5-'DCF Model'!$B$12)/'DCF Model'!$B$9 -> 0 | D6: =('DCF Model'!$B$13*(1+'DCF Model'!$B$20)*(1+'DCF Model'!$C$20)*(1+'DCF Model'!$D$20)*(1+'DCF Model'!$E$20)*(1+'DCF Model'!$F$20)*(1+0.03)/(0.09-0.03)/(1+0.09)^5+'DCF Model'!$B$13*(1+'DCF Model'!$B$20)/(1+0.09)^1+'DCF Model'!$B$13*(1+'DCF Model'!$B$20)*(1+'DCF Model'!$C$20)/(1+0.09)^2+'DCF Model'!$B$13*(1+'DCF Model'!$B$20)*(1+'DCF Model'!$C$20)*(1+'DCF Model'!$D$20)/(1+0.09)^3+'DCF Model'!$B$13*(1+'DCF Model'!$B$20)*(1+'DCF Model'!$C$20)*(1+'DCF Model'!$D$20)*(1+'DCF Model'!$E$20)/(1+0.09)^4+'DCF Model'!$B$13*(1+'DCF Model'!$B$20)*(1+'DCF Model'!$C$20)*(1+'DCF Model'!$D$20)*(1+'DCF Model'!$E$20)*(1+'DCF Model'!$F$20)/(1+0.09)^5-'DCF Model'!$B$12)/'DCF Model'!$B$9 -> 0 | E6: =('DCF Model'!$B$13*(1+'DCF Model'!$B$20)*(1+'DCF Model'!$C$20)*(1+'DCF Model'!$D$20)*(1+'DCF Model'!$E$20)*(1+'DCF Model'!$F$20)*(1+0.035)/(0.09-0.035)/(1+0.09)^5+'DCF Model'!$B$13*(1+'DCF Model'!$B$20)/(1+0.09)^1+'DCF Model'!$B$13*(1+'DCF Model'!$B$20)*(1+'DCF Model'!$C$20)/(1+0.09)^2+'DCF Model'!$B$13*(1+'DCF Model'!$B$20)*(1+'DCF Model'!$C$20)*(1+'DCF Model'!$D$20)/(1+0.09)^3+'DCF Model'!$B$13*(1+'DCF Model'!$B$20)*(1+'DCF Model'!$C$20)*(1+'DCF Model'!$D$20)*(1+'DCF Model'!$E$20)/(1+0.09)^4+'DCF Model'!$B$13*(1+'DCF Model'!$B$20)*(1+'DCF Model'!$C$20)*(1+'DCF Model'!$D$20)*(1+'DCF Model'!$E$20)*(1+'DCF Model'!$F$20)/(1+0.09)^5-'DCF Model'!$B$12)/'DCF Model'!$B$9 -> 0 | F6: =('DCF Model'!$B$13*(1+'DCF Model'!$B$20)*(1+'DCF Model'!$C$20)*(1+'DCF Model'!$D$20)*(1+'DCF Model'!$E$20)*(1+'DCF Model'!$F$20)*(1+0.04)/(0.09-0.04)/(1+0.09)^5+'DCF Model'!$B$13*(1+'DCF Model'!$B$20)/(1+0.09)^1+'DCF Model'!$B$13*(1+'DCF Model'!$B$20)*(1+'DCF Model'!$C$20)/(1+0.09)^2+'DCF Model'!$B$13*(1+'DCF Model'!$B$20)*(1+'DCF Model'!$C$20)*(1+'DCF Model'!$D$20)/(1+0.09)^3+'DCF Model'!$B$13*(1+'DCF Model'!$B$20)*(1+'DCF Model'!$C$20)*(1+'DCF Model'!$D$20)*(1+'DCF Model'!$E$20)/(1+0.09)^4+'DCF Model'!$B$13*(1+'DCF Model'!$B$20)*(1+'DCF Model'!$C$20)*(1+'DCF Model'!$D$20)*(1+'DCF Model'!$E$20)*(1+'DCF Model'!$F$20)/(1+0.09)^5-'DCF Model'!$B$12)/'DCF Model'!$B$9 -> 0
A7: 0.1 | B7: =('DCF Model'!$B$13*(1+'DCF Model'!$B$20)*(1+'DCF Model'!$C$20)*(1+'DCF Model'!$D$20)*(1+'DCF Model'!$E$20)*(1+'DCF Model'!$F$20)*(1+0.02)/(0.1-0.02)/(1+0.1)^5+'DCF Model'!$B$13*(1+'DCF Model'!$B$20)/(1+0.1)^1+'DCF Model'!$B$13*(1+'DCF Model'!$B$20)*(1+'DCF Model'!$C$20)/(1+0.1)^2+'DCF Model'!$B$13*(1+'DCF Model'!$B$20)*(1+'DCF Model'!$C$20)*(1+'DCF Model'!$D$20)/(1+0.1)^3+'DCF Model'!$B$13*(1+'DCF Model'!$B$20)*(1+'DCF Model'!$C$20)*(1+'DCF Model'!$D$20)*(1+'DCF Model'!$E$20)/(1+0.1)^4+'DCF Model'!$B$13*(1+'DCF Model'!$B$20)*(1+'DCF Model'!$C$20)*(1+'DCF Model'!$D$20)*(1+'DCF Model'!$E$20)*(1+'DCF Model'!$F$20)/(1+0.1)^5-'DCF Model'!$B$12)/'DCF Model'!$B$9 -> 0 | C7: =('DCF Model'!$B$13*(1+'DCF Model'!$B$20)*(1+'DCF Model'!$C$20)*(1+'DCF Model'!$D$20)*(1+'DCF Model'!$E$20)*(1+'DCF Model'!$F$20)*(1+0.025)/(0.1-0.025)/(1+0.1)^5+'DCF Model'!$B$13*(1+'DCF Model'!$B$20)/(1+0.1)^1+'DCF Model'!$B$13*(1+'DCF Model'!$B$20)*(1+'DCF Model'!$C$20)/(1+0.1)^2+'DCF Model'!$B$13*(1+'DCF Model'!$B$20)*(1+'DCF Model'!$C$20)*(1+'DCF Model'!$D$20)/(1+0.1)^3+'DCF Model'!$B$13*(1+'DCF Model'!$B$20)*(1+'DCF Model'!$C$20)*(1+'DCF Model'!$D$20)*(1+'DCF Model'!$E$20)/(1+0.1)^4+'DCF Model'!$B$13*(1+'DCF Model'!$B$20)*(1+'DCF Model'!$C$20)*(1+'DCF Model'!$D$20)*(1+'DCF Model'!$E$20)*(1+'DCF Model'!$F$20)/(1+0.1)^5-'DCF Model'!$B$12)/'DCF Model'!$B$9 -> 0 | D7: =('DCF Model'!$B$13*(1+'DCF Model'!$B$20)*(1+'DCF Model'!$C$20)*(1+'DCF Model'!$D$20)*(1+'DCF Model'!$E$20)*(1+'DCF Model'!$F$20)*(1+0.03)/(0.1-0.03)/(1+0.1)^5+'DCF Model'!$B$13*(1+'DCF Model'!$B$20)/(1+0.1)^1+'DCF Model'!$B$13*(1+'DCF Model'!$B$20)*(1+'DCF Model'!$C$20)/(1+0.1)^2+'DCF Model'!$B$13*(1+'DCF Model'!$B$20)*(1+'DCF Model'!$C$20)*(1+'DCF Model'!$D$20)/(1+0.1)^3+'DCF Model'!$B$13*(1+'DCF Model'!$B$20)*(1+'DCF Model'!$C$20)*(1+'DCF Model'!$D$20)*(1+'DCF Model'!$E$20)/(1+0.1)^4+'DCF Model'!$B$13*(1+'DCF Model'!$B$20)*(1+'DCF Model'!$C$20)*(1+'DCF Model'!$D$20)*(1+'DCF Model'!$E$20)*(1+'DCF Model'!$F$20)/(1+0.1)^5-'DCF Model'!$B$12)/'DCF Model'!$B$9 -> 0 | E7: =('DCF Model'!$B$13*(1+'DCF Model'!$B$20)*(1+'DCF Model'!$C$20)*(1+'DCF Model'!$D$20)*(1+'DCF Model'!$E$20)*(1+'DCF Model'!$F$20)*(1+0.035)/(0.1-0.035)/(1+0.1)^5+'DCF Model'!$B$13*(1+'DCF Model'!$B$20)/(1+0.1)^1+'DCF Model'!$B$13*(1+'DCF Model'!$B$20)*(1+'DCF Model'!$C$20)/(1+0.1)^2+'DCF Model'!$B$13*(1+'DCF Model'!$B$20)*(1+'DCF Model'!$C$20)*(1+'DCF Model'!$D$20)/(1+0.1)^3+'DCF Model'!$B$13*(1+'DCF Model'!$B$20)*(1+'DCF Model'!$C$20)*(1+'DCF Model'!$D$20)*(1+'DCF Model'!$E$20)/(1+0.1)^4+'DCF Model'!$B$13*(1+'DCF Model'!$B$20)*(1+'DCF Model'!$C$20)*(1+'DCF Model'!$D$20)*(1+'DCF Model'!$E$20)*(1+'DCF Model'!$F$20)/(1+0.1)^5-'DCF Model'!$B$12)/'DCF Model'!$B$9 -> 0 | F7: =('DCF Model'!$B$13*(1+'DCF Model'!$B$20)*(1+'DCF Model'!$C$20)*(1+'DCF Model'!$D$20)*(1+'DCF Model'!$E$20)*(1+'DCF Model'!$F$20)*(1+0.04)/(0.1-0.04)/(1+0.1)^5+'DCF Model'!$B$13*(1+'DCF Model'!$B$20)/(1+0.1)^1+'DCF Model'!$B$13*(1+'DCF Model'!$B$20)*(1+'DCF Model'!$C$20)/(1+0.1)^2+'DCF Model'!$B$13*(1+'DCF Model'!$B$20)*(1+'DCF Model'!$C$20)*(1+'DCF Model'!$D$20)/(1+0.1)^3+'DCF Model'!$B$13*(1+'DCF Model'!$B$20)*(1+'DCF Model'!$C$20)*(1+'DCF Model'!$D$20)*(1+'DCF Model'!$E$20)/(1+0.1)^4+'DCF Model'!$B$13*(1+'DCF Model'!$B$20)*(1+'DCF Model'!$C$20)*(1+'DCF Model'!$D$20)*(1+'DCF Model'!$E$20)*(1+'DCF Model'!$F$20)/(1+0.1)^5-'DCF Model'!$B$12)/'DCF Model'!$B$9 -> 0
A8: 0.11 | B8: =('DCF Model'!$B$13*(1+'DCF Model'!$B$20)*(1+'DCF Model'!$C$20)*(1+'DCF Model'!$D$20)*(1+'DCF Model'!$E$20)*(1+'DCF Model'!$F$20)*(1+0.02)/(0.11-0.02)/(1+0.11)^5+'DCF Model'!$B$13*(1+'DCF Model'!$B$20)/(1+0.11)^1+'DCF Model'!$B$13*(1+'DCF Model'!$B$20)*(1+'DCF Model'!$C$20)/(1+0.11)^2+'DCF Model'!$B$13*(1+'DCF Model'!$B$20)*(1+'DCF Model'!$C$20)*(1+'DCF Model'!$D$20)/(1+0.11)^3+'DCF Model'!$B$13*(1+'DCF Model'!$B$20)*(1+'DCF Model'!$C$20)*(1+'DCF Model'!$D$20)*(1+'DCF Model'!$E$20)/(1+0.11)^4+'DCF Model'!$B$13*(1+'DCF Model'!$B$20)*(1+'DCF Model'!$C$20)*(1+'DCF Model'!$D$20)*(1+'DCF Model'!$E$20)*(1+'DCF Model'!$F$20)/(1+0.11)^5-'DCF Model'!$B$12)/'DCF Model'!$B$9 -> 0 | C8: =('DCF Model'!$B$13*(1+'DCF Model'!$B$20)*(1+'DCF Model'!$C$20)*(1+'DCF Model'!$D$20)*(1+'DCF Model'!$E$20)*(1+'DCF Model'!$F$20)*(1+0.025)/(0.11-0.025)/(1+0.11)^5+'DCF Model'!$B$13*(1+'DCF Model'!$B$20)/(1+0.11)^1+'DCF Model'!$B$13*(1+'DCF Model'!$B$20)*(1+'DCF Model'!$C$20)/(1+0.11)^2+'DCF Model'!$B$13*(1+'DCF Model'!$B$20)*(1+'DCF Model'!$C$20)*(1+'DCF Model'!$D$20)/(1+0.11)^3+'DCF Model'!$B$13*(1+'DCF Model'!$B$20)*(1+'DCF Model'!$C$20)*(1+'DCF Model'!$D$20)*(1+'DCF Model'!$E$20)/(1+0.11)^4+'DCF Model'!$B$13*(1+'DCF Model'!$B$20)*(1+'DCF Model'!$C$20)*(1+'DCF Model'!$D$20)*(1+'DCF Model'!$E$20)*(1+'DCF Model'!$F$20)/(1+0.11)^5-'DCF Model'!$B$12)/'DCF Model'!$B$9 -> 0 | D8: =('DCF Model'!$B$13*(1+'DCF Model'!$B$20)*(1+'DCF Model'!$C$20)*(1+'DCF Model'!$D$20)*(1+'DCF Model'!$E$20)*(1+'DCF Model'!$F$20)*(1+0.03)/(0.11-0.03)/(1+0.11)^5+'DCF Model'!$B$13*(1+'DCF Model'!$B$20)/(1+0.11)^1+'DCF Model'!$B$13*(1+'DCF Model'!$B$20)*(1+'DCF Model'!$C$20)/(1+0.11)^2+'DCF Model'!$B$13*(1+'DCF Model'!$B$20)*(1+'DCF Model'!$C$20)*(1+'DCF Model'!$D$20)/(1+0.11)^3+'DCF Model'!$B$13*(1+'DCF Model'!$B$20)*(1+'DCF Model'!$C$20)*(1+'DCF Model'!$D$20)*(1+'DCF Model'!$E$20)/(1+0.11)^4+'DCF Model'!$B$13*(1+'DCF Model'!$B$20)*(1+'DCF Model'!$C$20)*(1+'DCF Model'!$D$20)*(1+'DCF Model'!$E$20)*(1+'DCF Model'!$F$20)/(1+0.11)^5-'DCF Model'!$B$12)/'DCF Model'!$B$9 -> 0 | E8: =('DCF Model'!$B$13*(1+'DCF Model'!$B$20)*(1+'DCF Model'!$C$20)*(1+'DCF Model'!$D$20)*(1+'DCF Model'!$E$20)*(1+'DCF Model'!$F$20)*(1+0.035)/(0.11-0.035)/(1+0.11)^5+'DCF Model'!$B$13*(1+'DCF Model'!$B$20)/(1+0.11)^1+'DCF Model'!$B$13*(1+'DCF Model'!$B$20)*(1+'DCF Model'!$C$20)/(1+0.11)^2+'DCF Model'!$B$13*(1+'DCF Model'!$B$20)*(1+'DCF Model'!$C$20)*(1+'DCF Model'!$D$20)/(1+0.11)^3+'DCF Model'!$B$13*(1+'DCF Model'!$B$20)*(1+'DCF Model'!$C$20)*(1+'DCF Model'!$D$20)*(1+'DCF Model'!$E$20)/(1+0.11)^4+'DCF Model'!$B$13*(1+'DCF Model'!$B$20)*(1+'DCF Model'!$C$20)*(1+'DCF Model'!$D$20)*(1+'DCF Model'!$E$20)*(1+'DCF Model'!$F$20)/(1+0.11)^5-'DCF Model'!$B$12)/'DCF Model'!$B$9 -> 0 | F8: =('DCF Model'!$B$13*(1+'DCF Model'!$B$20)*(1+'DCF Model'!$C$20)*(1+'DCF Model'!$D$20)*(1+'DCF Model'!$E$20)*(1+'DCF Model'!$F$20)*(1+0.04)/(0.11-0.04)/(1+0.11)^5+'DCF Model'!$B$13*(1+'DCF Model'!$B$20)/(1+0.11)^1+'DCF Model'!$B$13*(1+'DCF Model'!$B$20)*(1+'DCF Model'!$C$20)/(1+0.11)^2+'DCF Model'!$B$13*(1+'DCF Model'!$B$20)*(1+'DCF Model'!$C$20)*(1+'DCF Model'!$D$20)/(1+0.11)^3+'DCF Model'!$B$13*(1+'DCF Model'!$B$20)*(1+'DCF Model'!$C$20)*(1+'DCF Model'!$D$20)*(1+'DCF Model'!$E$20)/(1+0.11)^4+'DCF Model'!$B$13*(1+'DCF Model'!$B$20)*(1+'DCF Model'!$C$20)*(1+'DCF Model'!$D$20)*(1+'DCF Model'!$E$20)*(1+'DCF Model'!$F$20)/(1+0.11)^5-'DCF Model'!$B$12)/'DCF Model'!$B$9 -> 0
A9: 0.12 | B9: =('DCF Model'!$B$13*(1+'DCF Model'!$B$20)*(1+'DCF Model'!$C$20)*(1+'DCF Model'!$D$20)*(1+'DCF Model'!$E$20)*(1+'DCF Model'!$F$20)*(1+0.02)/(0.12-0.02)/(1+0.12)^5+'DCF Model'!$B$13*(1+'DCF Model'!$B$20)/(1+0.12)^1+'DCF Model'!$B$13*(1+'DCF Model'!$B$20)*(1+'DCF Model'!$C$20)/(1+0.12)^2+'DCF Model'!$B$13*(1+'DCF Model'!$B$20)*(1+'DCF Model'!$C$20)*(1+'DCF Model'!$D$20)/(1+0.12)^3+'DCF Model'!$B$13*(1+'DCF Model'!$B$20)*(1+'DCF Model'!$C$20)*(1+'DCF Model'!$D$20)*(1+'DCF Model'!$E$20)/(1+0.12)^4+'DCF Model'!$B$13*(1+'DCF Model'!$B$20)*(1+'DCF Model'!$C$20)*(1+'DCF Model'!$D$20)*(1+'DCF Model'!$E$20)*(1+'DCF Model'!$F$20)/(1+0.12)^5-'DCF Model'!$B$12)/'DCF Model'!$B$9 -> 0 | C9: =('DCF Model'!$B$13*(1+'DCF Model'!$B$20)*(1+'DCF Model'!$C$20)*(1+'DCF Model'!$D$20)*(1+'DCF Model'!$E$20)*(1+'DCF Model'!$F$20)*(1+0.025)/(0.12-0.025)/(1+0.12)^5+'DCF Model'!$B$13*(1+'DCF Model'!$B$20)/(1+0.12)^1+'DCF Model'!$B$13*(1+'DCF Model'!$B$20)*(1+'DCF Model'!$C$20)/(1+0.12)^2+'DCF Model'!$B$13*(1+'DCF Model'!$B$20)*(1+'DCF Model'!$C$20)*(1+'DCF Model'!$D$20)/(1+0.12)^3+'DCF Model'!$B$13*(1+'DCF Model'!$B$20)*(1+'DCF Model'!$C$20)*(1+'DCF Model'!$D$20)*(1+'DCF Model'!$E$20)/(1+0.12)^4+'DCF Model'!$B$13*(1+'DCF Model'!$B$20)*(1+'DCF Model'!$C$20)*(1+'DCF Model'!$D$20)*(1+'DCF Model'!$E$20)*(1+'DCF Model'!$F$20)/(1+0.12)^5-'DCF Model'!$B$12)/'DCF Model'!$B$9 -> 0 | D9: =('DCF Model'!$B$13*(1+'DCF Model'!$B$20)*(1+'DCF Model'!$C$20)*(1+'DCF Model'!$D$20)*(1+'DCF Model'!$E$20)*(1+'DCF Model'!$F$20)*(1+0.03)/(0.12-0.03)/(1+0.12)^5+'DCF Model'!$B$13*(1+'DCF Model'!$B$20)/(1+0.12)^1+'DCF Model'!$B$13*(1+'DCF Model'!$B$20)*(1+'DCF Model'!$C$20)/(1+0.12)^2+'DCF Model'!$B$13*(1+'DCF Model'!$B$20)*(1+'DCF Model'!$C$20)*(1+'DCF Model'!$D$20)/(1+0.12)^3+'DCF Model'!$B$13*(1+'DCF Model'!$B$20)*(1+'DCF Model'!$C$20)*(1+'DCF Model'!$D$20)*(1+'DCF Model'!$E$20)/(1+0.12)^4+'DCF Model'!$B$13*(1+'DCF Model'!$B$20)*(1+'DCF Model'!$C$20)*(1+'DCF Model'!$D$20)*(1+'DCF Model'!$E$20)*(1+'DCF Model'!$F$20)/(1+0.12)^5-'DCF Model'!$B$12)/'DCF Model'!$B$9 -> 0 | E9: =('DCF Model'!$B$13*(1+'DCF Model'!$B$20)*(1+'DCF Model'!$C$20)*(1+'DCF Model'!$D$20)*(1+'DCF Model'!$E$20)*(1+'DCF Model'!$F$20)*(1+0.035)/(0.12-0.035)/(1+0.12)^5+'DCF Model'!$B$13*(1+'DCF Model'!$B$20)/(1+0.12)^1+'DCF Model'!$B$13*(1+'DCF Model'!$B$20)*(1+'DCF Model'!$C$20)/(1+0.12)^2+'DCF Model'!$B$13*(1+'DCF Model'!$B$20)*(1+'DCF Model'!$C$20)*(1+'DCF Model'!$D$20)/(1+0.12)^3+'DCF Model'!$B$13*(1+'DCF Model'!$B$20)*(1+'DCF Model'!$C$20)*(1+'DCF Model'!$D$20)*(1+'DCF Model'!$E$20)/(1+0.12)^4+'DCF Model'!$B$13*(1+'DCF Model'!$B$20)*(1+'DCF Model'!$C$20)*(1+'DCF Model'!$D$20)*(1+'DCF Model'!$E$20)*(1+'DCF Model'!$F$20)/(1+0.12)^5-'DCF Model'!$B$12)/'DCF Model'!$B$9 -> 0 | F9: =('DCF Model'!$B$13*(1+'DCF Model'!$B$20)*(1+'DCF Model'!$C$20)*(1+'DCF Model'!$D$20)*(1+'DCF Model'!$E$20)*(1+'DCF Model'!$F$20)*(1+0.04)/(0.12-0.04)/(1+0.12)^5+'DCF Model'!$B$13*(1+'DCF Model'!$B$20)/(1+0.12)^1+'DCF Model'!$B$13*(1+'DCF Model'!$B$20)*(1+'DCF Model'!$C$20)/(1+0.12)^2+'DCF Model'!$B$13*(1+'DCF Model'!$B$20)*(1+'DCF Model'!$C$20)*(1+'DCF Model'!$D$20)/(1+0.12)^3+'DCF Model'!$B$13*(1+'DCF Model'!$B$20)*(1+'DCF Model'!$C$20)*(1+'DCF Model'!$D$20)*(1+'DCF Model'!$E$20)/(1+0.12)^4+'DCF Model'!$B$13*(1+'DCF Model'!$B$20)*(1+'DCF Model'!$C$20)*(1+'DCF Model'!$D$20)*(1+'DCF Model'!$E$20)*(1+'DCF Model'!$F$20)/(1+0.12)^5-'DCF Model'!$B$12)/'DCF Model'!$B$9 -> 0
A11: Color key: | B11: >15% above $117 | C11: Above $117 | D11: Within 15% below $117 | E11: Below $99.45 (>15% down)

Sheet Historical
A1: DELL Historical Financial Data (FY2020-FY2025)
A2: Source: Dell Technologies 10-K filings. All USD Millions. FY2021/prior includes VMware as continuing operations.
A3: Period | B3: Revenue | C3: Gross Profit | D3: Op. Income | E3: Net Income | F3: EPS Diluted | G3: Op. Cash Flow | H3: CapEx | I3: Free Cash Flow
A4: FY2020 | B4: 92154 | C4: 28933 | D4: 2622 | E4: 4616 | F4: 6.03 | G4: 9291 | H4: 2576 | I4: 6715
A5: FY2021* | B5: 94224 | C5: 29417 | D5: 5144 | E5: 3250 | F5: 4.22 | G5: 11407 | H5: 2082 | I5: 9325
A6: FY2022 | B6: 101197 | C6: 21891 | D6: 4659 | E6: 5563 | F6: 7.02 | G6: 10307 | H6: 2796 | I6: 7511
A7: FY2023 | B7: 102301 | C7: 22686 | D7: 5771 | E7: 2442 | F7: 3.24 | G7: 3565 | H7: 3003 | I7: 562
A8: FY2024 | B8: 88425 | C8: 21069 | D8: 5411 | E8: 3388 | F8: 4.6 | G8: 8676 | H8: 2756 | I8: 5920
A9: FY2025 | B9: 95567 | C9: 21250 | D9: 6237 | E9: 4592 | F9: 6.38 | G9: 4521 | H9: 2652 | I9: 1869
A10: * FY2021 includes VMware as continuing operations (spun off Nov 2021). FY2022 restated to exclude VMware. FY2023 FCF depressed by post-spinoff CapEx surge. FY2025 FCF depressed by AI server inventory and receivables build during rapid growth phase. DCF normalized base FCF = $5,500M.
A12: GROWTH RATES
A13: Metric | B13: 3-Year CAGR | C13: 5-Year CAGR | D13: Status
A14: Revenue (FY2022/FY2020 -> FY2025) | B14: -0.018 | C14: 0.007 | D14: Distorted by VMware spinoff and PC cycle decline
A15: EPS Diluted | B15: -0.031 | C15: 0.011 | D15: Distorted by post-spinoff structure changes
A16: Shareholders Equity | B16: N/A | C16: N/A | D16: NOT APPLICABLE - Negative equity from EMC leverage
A17: Free Cash Flow | B17: -0.376 | C17: -0.236 | D17: Severely distorted by FCF volatility ($562M to $9,325M range)
A18: Selected Growth Rate: | B18: 0.12 | C18: Source: forward_guidance_adjusted | D18: Base case Y1 growth of 15% aligned with FY2026 management guidance of +17% revenue growth

Sheet Notes
A1: DELL DCF Model - Key Assumptions and Analyst Notes
A3: Valuation Date | B3: 2026-02-18
A4: Current Stock Price | B4: $117.00
A5: Shares Outstanding | B5: 720M diluted
A6: Cash & Equivalents | B6: $3,633M (FY2025 year-end)
A7: Total Debt | B7: $24,567M (FY2025 year-end)
A8: Net Debt | B8: $20,934M = Total Debt - Cash
A9: Normalized Base FCF | B9: $5,500M | FY2025 reported FCF was $1,869M (depressed by AI server working capital build). Historical FCFs: FY2020 $6,715M | FY2021 $9,325M | FY2022 $7,511M | FY2023 $562M | FY2024 $5,920M | FY2025 $1,869M. Conservative normalized estimate of $5,500M used vs. 4-year average of ~$7,368M.
A10: EQUITY CAGR WARNING | B10: EQUITY CAGR UNUSABLE: Dell has had negative shareholders equity in every year since the 2016 EMC leveraged acquisition. Equity deficit as of FY2025: -$1,482M. Equity CAGR cannot be calculated and has been excluded from the growth rate selection process. FCF CAGRs are also distorted by VMware spinoff (FY2021-FY2022) and AI server working capital dynamics (FY2023, FY2025). Growth rate anchored to forward revenue guidance and AI infrastructure cycle analysis instead of historical CAGRs.
A11: Growth Rate Rationale | B11: Historical CAGRs are severely distorted: Dell spun off VMware in Nov 2021 causing apparent revenue contraction; FCF depressed in FY2023 by post-spinoff CapEx spike and in FY2025 by working capital consumption from rapid AI server growth. Management guidance for FY2026 is +17% revenue growth with AI server shipments of ~$25B (up 150%+ YoY). Forward-looking growth is anchored to management guidance and the AI infrastructure cycle with deceleration toward terminal rate over 5 years. Base case Y1 growth of 15% is slightly below the guided +17%, reflecting FCF vs. revenue timing differences. Selected blended growth rate of 12% represents a mid-cycle average across the 5-year projection period.
A13: Base Case Narrative | B13: AI server demand drives strong near-term ISG growth aligned with management guidance (~+17% revenue); Windows 10 end-of-life refresh cycle supports CSG recovery; FCF gradually recovers from depressed FY2025 as working capital normalizes; AI server margins stable-to-slightly improving post-Blackwell ramp; growth decelerates as AI capex cycle matures by FY2029-FY2030.
A14: Bull Case Narrative | B14: AI infrastructure buildout accelerates beyond current expectations; Dell captures enterprise AI wallet share with full-stack solutions (servers, storage, networking, services); margin expansion as AI server mix shifts toward enterprise and sovereign customers with better pricing; robust Windows 11 refresh and AI PC adoption drive CSG outperformance; international sovereign AI programs add incremental ISG revenue; FCF conversion improves materially as working capital normalizes and services attach revenue grows.
A15: Bear Case Narrative | B15: Hyperscaler AI capex moderates sharply as DeepSeek-style model efficiency improvements reduce hardware demand; tariff escalation adds supply chain cost pressure not fully passable to customers; AI server margins remain structurally compressed with SMCI and ODM competition intensifying; CSG commercial refresh weaker than expected; high debt burden ($20.9B net debt) constrains financial flexibility; FCF remains below historical norms due to persistent working capital pressures and elevated interest expense.
... A33: Analyst Note 5 | B33: At $117/share, Dell trades at approximately 13.5x FY2026 guided GAAP EPS of ~$8.38 and ~12x non-GAAP EPS of ~$9.92. For a hardware company with thin blended operating margins (~6.5% GAAP), significant debt, and commodity-exposed revenue streams, this multiple is not obviously cheap without clear FCF improvement.
