Workbook

Sheet Model_Info
A2: SAN.PA -- Sanofi S.A. -- Owner-FCF DCF model
A3: Version | B3: v1.0, 2026-08-30. Fresh build; supersedes nothing (first valuation of this ticker).
A4: Built by | B4: dcf-analyst agent (Claude, Fable 5), 2026-08-30, at the user's request.
A5: Data vintage | B5: Price EUR77.25 (Yahoo regular close, 2026-08-28T15:38Z, verified live 2026-08-30). Balance sheet: FY2025 (Dec-31-2025) -- total debt EUR18,702m, cash EUR7,657m, company-stated net debt EUR11.0bn (reconciles). Shares: 1,196.6m (Q2-2026 weighted average). Guidance: Q2-2026 upgrade (Jul-30-2026): ~10% CER sales growth, business EPS slightly faster, ~21% ETR, EUR1bn buyback completed.
A6: Methodology 1 | B6: Owner-FCF DCF, 10-year component build (dcf-methods/references/owner-fcf.md). Operating pharma; not a bank/REIT/LIC.
A7: Methodology 2 | B7: Operating anchor is BUSINESS (non-GAAP) earnings, never IFRS NI -- IFRS NI carries disposal gains (FY2020 Regeneron, FY2025 Opella) and acquisition amortization.
A8: Methodology 3 | B8: EBITDA margin driver is a CASH-EBITDA margin: business EBITDA (~35% FY2025) net of ~4.5-5.5pp recurring restructuring/litigation cash leakage, calibrated to statutory owner FCF (OCF - capex - SBC = EUR6,899m FY2025).
A9: Methodology 4 | B9: Dupixent patent cliff shapes the model: ramp to ~EUR56bn sales by 2030, then NEGATIVE group growth 2032-34 (US LOE ~2031+ on ~36% of sales), terminal growth only 1.0-2.0%, TV capped at 15x FCF (12x bear). The cap binds in all scenarios.
A10: Methodology 5 | B10: SBC (EUR313m, 0.7% of sales) fully EXPENSED in flows; share count held FLAT at 1,196.6m (charging both = double count). Count is actually falling ~2%/yr on funded buybacks -- flat is conservative.
A11: Methodology 6 | B11: WACC 7.5% EUR-built: rf 3.2% (10y OAT) + 0.8 beta x 5.0% ERP + 1.0pp pipeline/patent-cliff concentration premium, blended with 2.7% after-tax debt at ~11% weight. SAME WACC in all scenarios -- risk charged once, in the rate.
A12: Methodology 7 | B12: Leases (IFRS 16): treatment A -- lease liabilities inside net debt, principal not deducted from flows, renewal inside the 7.0-8.1% capex path.
A13: Judgment | B13: Scenario driver paths are the dcf-analyst agent's judgment, set 2026-08-30 from FY2025 results, Q2-2026 upgraded guidance and the Analysis JSON (tolebrutinib CRL, amlitelimab discontinuation, CEO change, US policy risks). Weights 25/50/25 bear/base/bull.
A14: Refresh next print | B14: After Q3-2026 (late Oct-2026): price, net debt + date, share count, FY2026 guidance delivery, Dupixent US trajectory, tariff/MFN developments, any pipeline news. These figures GO STALE.
A15: Cell legend | B15: BLUE font = hardcoded input. YELLOW fill = key driver lever. Black = formula. GREEN font = cross-sheet link. Only driver rows (growth, margin, SBC%, tax) plus Assumptions inputs are hardcoded.

Sheet Actuals
A1: Reported history (EUR millions; source: SAN.PA_Metrics.csv <- annual reports)
B3: FY2016 | C3: FY2017 | D3: FY2018 | E3: FY2019 | F3: FY2020 | G3: FY2021 | H3: FY2022 | I3: FY2023 | J3: FY2024 | K3: FY2025
A4: Revenue | B4: 33809 | C4: 35072 | D4: 34463 | E4: 36126 | F4: 36041 | G4: 37761 | H4: 37651 | I4: 37817 | J4: 41081 | K4: 43626
A5: Operating income (IFRS) | B5: 6531 | C5: 5804 | D5: 4676 | E5: 3051 | F5: 14113 | G5: 8126 | H5: 10162 | I5: 6960 | J5: 7252 | K5: 6344
A6: Net income (IFRS) | B6: 4709 | C6: 8416 | D6: 4306 | E6: 2754 | F6: 12294 | G6: 6223 | H6: 8371 | I6: 5400 | J6: 5560 | K6: 7813
A7: Operating cash flow | B7: 7838 | C7: 7379 | D7: 5547 | E7: 7715 | F7: 7418 | G7: 10522 | H7: 10526 | I7: 10258 | J7: 9081 | K7: 10750
A8: Capex | B8: -1340 | C8: -1394 | D8: -1459 | E8: -1787 | F8: -2083 | G8: -2043 | H8: -2103 | I8: -2906 | J8: -3195 | K8: -3538
A9: FCF (OCF-capex) | B9: 6498 | C9: 5985 | D9: 4088 | E9: 5928 | F9: 5335 | G9: 8479 | H9: 8423 | I9: 7352 | J9: 5886 | K9: 7212
A10: SBC | B10: 241 | C10: 263 | D10: 284 | E10: 252 | F10: 274 | G10: 244 | H10: 234 | I10: 260 | J10: 278 | K10: 313
A11: Shareholders equity | B11: 57552 | C11: 58070 | D11: 58876 | E11: 59056 | F11: 63106 | G11: 68681 | H11: 74784 | I11: 74040 | J11: 77507 | K11: 71376
A12: Total debt | B12: 18509 | C12: 15468 | D12: 24586 | E12: 24568 | F12: 22631 | G12: 20250 | H12: 19218 | I12: 16531 | J12: 16137 | K12: 18702
A13: Cash | B13: 10273 | C13: 10315 | D13: 6925 | E13: 9427 | F13: 13915 | G13: 10098 | H13: 12736 | I13: 8710 | J13: 7441 | K13: 7657
A14: Dividend per share | B14: 2.93 | C14: 2.96 | D14: 3.03 | E14: 3.07 | F14: 3.15 | G14: 3.2 | H14: 3.33 | I14: 3.56 | J14: 3.76 | K14: 3.92
A17: Note: IFRS net income distorted by disposals: FY2017 animal-health swap, FY2020 Regeneron stake sale, FY2025 Opella gain.
A18: Note: FY2025 business (non-GAAP): operating income EUR12,149m (27.8% margin), net income EUR9,555m, business EPS EUR7.83. H1-2026 business EPS EUR3.97 (+22.7%).
A19: Note: FY2025 company-defined FCF EUR9.9bn is BEFORE restructuring/acquisitions/disposals; statutory OCF-capex EUR7,212m is the model base.
A20: Note: Balance sheet FY2025 (Dec-31-2025): net debt EUR11.0bn company-stated = 18,702 - 7,657. Ratings Aa3 / AA stable.
A21: Note: Shares: 1,196.6m Q2-2026 weighted avg; falling ~2%/yr (EUR5bn buyback 2025, EUR1bn 2026 completed by end-Apr).
A22: Note: Guidance FY2026 (upgraded Jul-30-2026): sales ~+10% CER (~-1pp FX), business EPS slightly faster than sales, ETR ~21%. Dupixent 2030 ambition ~EUR25bn; vaccines cut to ~EUR9bn.

Sheet Assumptions
A1: Global assumptions (BLUE = input)
A3: WACC | B3: 0.075 | C3: EUR-built: rf 3.2% + 0.8 beta x 5.0% ERP + 1.0pp concentration premium; ~11% debt at 2.7% after tax. Same across scenarios.
A4: D&A % of revenue | B4: 0.073 | C4: ~EUR3.2bn operating D&A / FY2025 sales; tax-shield line only.
A5: WC capture on revenue change | B5: -0.05 | C5: Pharma WC consumes ~5% of each revenue increase (receivables+inventory net of payables); releases cash in shrink years.
A6: Net debt (EUR m) | B6: 11045 | C6: Dec-31-2025: 18,702 debt (incl. lease liabilities) - 7,657 cash; company-stated EUR11.0bn.
A7: Diluted shares (m) | B7: 1196.6 | C7: Q2-2026 weighted average. Held flat -- SBC fully expensed.
A8: Current price (EUR) | B8: 77.25 | C8: Yahoo regular close 2026-08-28T15:38Z, verified 2026-08-30.
A9: Hurdle rate | B9: 0.15 | C9: Entry-price IRR.
A10: FY2025 revenue (EUR m) | B10: 43626 | C10: Base year for all scenarios.
A12: Capex % of revenue path (shared by all scenarios; onshoring-elevated, tapering) | C12: 0.081 | D12: 0.081 | E12: 0.08 | F12: 0.078 | G12: 0.076 | H12: 0.074 | I12: 0.072 | J12: 0.07 | K12: 0.07 | L12: 0.07
A14: Per-scenario terminal & weights | B14: Bear | C14: Base | D14: Bull
A15: Terminal growth | B15: 0.01 | C15: 0.015 | D15: 0.02
A16: TV cap (x FCF10) | B16: 12 | C16: 15 | D16: 15
A17: Probability weight | B17: 0.25 | C17: 0.5 | D17: 0.25
A18: Weights sum (must be 1.0) | B18: =SUM(B17:D17)
A20: Base narrative | B20: Guidance lands: +9% 2026 reported, ~EUR56bn by 2030 (Dupixent ~EUR25bn, launches ~EUR10bn, vaccines ~EUR9bn flat); cash-EBITDA margin 30.5%->32%; 2031-35 Dupixent US LOE takes group growth to -2/-3% in 2032-33; tax 21%; terminal 1.5%, 15x cap binds.
A21: Bull narrative | B21: Dupixent beats EUR25bn and lifecycle mgmt blunts the cliff to a plateau; Garijo R&D reset works, launches exceed EUR10bn; US policy settled by onshoring; margin to 33%; terminal 2.0%, 15x cap.
A22: Bear narrative | B22: 232 tariffs + IRA/MFN pricing + vaccine-policy decline hit together; Ebglyss/Tezspire cap Dupixent near EUR20bn; dead successor pipeline means a steeper 2031-34 cliff (-5/-6%); margin erodes to 26%; tax to 23%; terminal 1.0%, 12x cap.

Sheet DCF_Bear
B3: 2025A | C3: 2026E | D3: 2027E | E3: 2028E | F3: 2029E | G3: 2030E | H3: 2031E | I3: 2032E | J3: 2033E | K3: 2034E | L3: 2035E
B4: 0 | C4: 1 | D4: 2 | E4: 3 | F4: 4 | G4: 5 | H4: 6 | I4: 7 | J4: 8 | K4: 9 | L4: 10
A5: Revenue growth YoY | C5: 0.07 | D5: 0.03 | E5: 0.02 | F5: 0.01 | G5: 0 | H5: -0.02 | I5: -0.05 | J5: -0.06 | K5: -0.03 | L5: -0.01
A6: Revenue | B6: =Assumptions!$B$10 | C6: =B6*(1+C5) | D6: =C6*(1+D5) | E6: =D6*(1+E5) | F6: =E6*(1+F5) | G6: =F6*(1+G5) | H6: =G6*(1+H5) | I6: =H6*(1+I5) | J6: =I6*(1+J5) | ... L6: =K6*(1+L5)
A7: Adj (cash) EBITDA margin | C7: 0.295 | D7: 0.295 | E7: 0.29 | F7: 0.285 | G7: 0.28 | H7: 0.275 | I7: 0.27 | J7: 0.265 | K7: 0.26 | L7: 0.26
A8: Adjusted EBITDA | C8: =C6*C7 | D8: =D6*D7 | E8: =E6*E7 | F8: =F6*F7 | G8: =G6*G7 | H8: =H6*H7 | I8: =I6*I7 | J8: =J6*J7 | ... L8: =L6*L7
A9: SBC % of revenue | C9: 0.007 | D9: 0.007 | E9: 0.007 | F9: 0.007 | G9: 0.007 | H9: 0.007 | I9: 0.007 | J9: 0.007 | K9: 0.007 | L9: 0.007
A10: SBC | C10: =-C6*C9 | D10: =-D6*D9 | E10: =-E6*E9 | F10: =-F6*F9 | G10: =-G6*G9 | H10: =-H6*H9 | I10: =-I6*I9 | J10: =-J6*J9 | ... L10: =-L6*L9
A11: Owner EBITDA | C11: =C8+C10 | D11: =D8+D10 | E11: =E8+E10 | F11: =F8+F10 | G11: =G8+G10 | H11: =H8+H10 | I11: =I8+I10 | J11: =J8+J10 | ... L11: =L8+L10
A12: D&A | C12: =-C6*Assumptions!$B$4 | D12: =-D6*Assumptions!$B$4 | E12: =-E6*Assumptions!$B$4 | F12: =-F6*Assumptions!$B$4 | G12: =-G6*Assumptions!$B$4 | H12: =-H6*Assumptions!$B$4 | I12: =-I6*Assumptions!$B$4 | J12: =-J6*Assumptions!$B$4 | ... L12: =-L6*Assumptions!$B$4
A13: EBIT (SBC expensed) | C13: =C11+C12 | D13: =D11+D12 | E13: =E11+E12 | F13: =F11+F12 | G13: =G11+G12 | H13: =H11+H12 | I13: =I11+I12 | J13: =J11+J12 | ... L13: =L11+L12
A14: Cash tax rate | C14: 0.21 | D14: 0.215 | E14: 0.22 | F14: 0.225 | G14: 0.23 | H14: 0.23 | I14: 0.23 | J14: 0.23 | K14: 0.23 | L14: 0.23
A15: NOPAT | C15: =C13*(1-C14) | D15: =D13*(1-D14) | E15: =E13*(1-E14) | F15: =F13*(1-F14) | G15: =G13*(1-G14) | H15: =H13*(1-H14) | I15: =I13*(1-I14) | J15: =J13*(1-J14) | ... L15: =L13*(1-L14)
A16: add back D&A | C16: =-C12 | D16: =-D12 | E16: =-E12 | F16: =-F12 | G16: =-G12 | H16: =-H12 | I16: =-I12 | J16: =-J12 | ... L16: =-L12
A17: less capex | C17: =-C6*Assumptions!C$12 | D17: =-D6*Assumptions!D$12 | E17: =-E6*Assumptions!E$12 | F17: =-F6*Assumptions!F$12 | G17: =-G6*Assumptions!G$12 | H17: =-H6*Assumptions!H$12 | I17: =-I6*Assumptions!I$12 | J17: =-J6*Assumptions!J$12 | ... L17: =-L6*Assumptions!L$12
A18: add WC (on rev change) | C18: =Assumptions!$B$5*(C6-B6) | D18: =Assumptions!$B$5*(D6-C6) | E18: =Assumptions!$B$5*(E6-D6) | F18: =Assumptions!$B$5*(F6-E6) | G18: =Assumptions!$B$5*(G6-F6) | H18: =Assumptions!$B$5*(H6-G6) | I18: =Assumptions!$B$5*(I6-H6) | J18: =Assumptions!$B$5*(J6-I6) | ... L18: =Assumptions!$B$5*(L6-K6)
A19: Unlevered owner FCF | C19: =C15+C16+C17+C18 | D19: =D15+D16+D17+D18 | E19: =E15+E16+E17+E18 | F19: =F15+F16+F17+F18 | G19: =G15+G16+G17+G18 | H19: =H15+H16+H17+H18 | I19: =I15+I16+I17+I18 | J19: =J15+J16+J17+J18 | ... L19: =L15+L16+L17+L18
A20: Discount factor | C20: =1/(1+Assumptions!$B$3)^C4 | D20: =1/(1+Assumptions!$B$3)^D4 | E20: =1/(1+Assumptions!$B$3)^E4 | F20: =1/(1+Assumptions!$B$3)^F4 | G20: =1/(1+Assumptions!$B$3)^G4 | H20: =1/(1+Assumptions!$B$3)^H4 | I20: =1/(1+Assumptions!$B$3)^I4 | J20: =1/(1+Assumptions!$B$3)^J4 | ... L20: =1/(1+Assumptions!$B$3)^L4
A21: PV of FCF | C21: =C19*C20 | D21: =D19*D20 | E21: =E19*E20 | F21: =F19*F20 | G21: =G19*G20 | H21: =H19*H20 | I21: =I19*I20 | J21: =J19*J20 | ... L21: =L19*L20
A23: Memo: FCF before SBC (company-style) | C23: =C19-C10 | D23: =D19-D10 | E23: =E19-E10 | F23: =F19-F10 | G23: =G19-G10 | H23: =H19-H10 | I23: =I19-I10 | J23: =J19-J10 | ... L23: =L19-L10
A24: Memo: implied owner-FCF margin | C24: =C19/C6 | D24: =D19/D6 | E24: =E19/E6 | F24: =F19/F6 | G24: =G19/G6 | H24: =H19/H6 | I24: =I19/I6 | J24: =J19/J6 | ... L24: =L19/L6
A26: Sum of PV (explicit years) | B26: =SUM(C21:L21)
A27: Terminal growth | B27: =Assumptions!$B$15
A28: Terminal FCF | B28: =L19*(1+B27)
A29: Gordon TV | B29: =B28/(Assumptions!$B$3-B27)
A30: Cap TV | B30: =Assumptions!$B$16*L19
A31: TV used | B31: =MAX(0,MIN(B29,B30))
A32: Implied exit multiple | B32: =B31/L19
A33: PV of TV | B33: =B31*L20
A34: Enterprise value | B34: =B26+B33
A35: less net debt | B35: =-Assumptions!$B$6
A36: Equity value | B36: =B34+B35
A37: Diluted shares (m) | B37: =Assumptions!$B$7
A38: VALUE PER SHARE | B38: =B36/B37
A39: Upside vs price | B39: =B38/Assumptions!$B$8-1
A41: Street memo: PV explicit SBC | B41: =SUMPRODUCT(-C10:L10/(1+Assumptions!$B$3)^C4:L4)
A42: Street memo: PV terminal SBC | B42: =(-L10*(1+B27)/(Assumptions!$B$3-B27))*L20
A43: Street value per share | B43: =(B36+B41+B42)/B37

Sheet DCF_Base
B3: 2025A | C3: 2026E | D3: 2027E | E3: 2028E | F3: 2029E | G3: 2030E | H3: 2031E | I3: 2032E | J3: 2033E | K3: 2034E | L3: 2035E
B4: 0 | C4: 1 | D4: 2 | E4: 3 | F4: 4 | G4: 5 | H4: 6 | I4: 7 | J4: 8 | K4: 9 | L4: 10
A5: Revenue growth YoY | C5: 0.09 | D5: 0.05 | E5: 0.045 | F5: 0.04 | G5: 0.035 | H5: 0.01 | I5: -0.02 | J5: -0.03 | K5: -0.01 | L5: 0.01
A6: Revenue | B6: =Assumptions!$B$10 | C6: =B6*(1+C5) | D6: =C6*(1+D5) | E6: =D6*(1+E5) | F6: =E6*(1+F5) | G6: =F6*(1+G5) | H6: =G6*(1+H5) | I6: =H6*(1+I5) | J6: =I6*(1+J5) | ... L6: =K6*(1+L5)
A7: Adj (cash) EBITDA margin | C7: 0.305 | D7: 0.31 | E7: 0.315 | F7: 0.3175 | G7: 0.32 | H7: 0.315 | I7: 0.305 | J7: 0.3 | K7: 0.3 | L7: 0.3
A8: Adjusted EBITDA | C8: =C6*C7 | D8: =D6*D7 | E8: =E6*E7 | F8: =F6*F7 | G8: =G6*G7 | H8: =H6*H7 | I8: =I6*I7 | J8: =J6*J7 | ... L8: =L6*L7
A9: SBC % of revenue | C9: 0.007 | D9: 0.007 | E9: 0.007 | F9: 0.007 | G9: 0.007 | H9: 0.007 | I9: 0.007 | J9: 0.007 | K9: 0.007 | L9: 0.007
A10: SBC | C10: =-C6*C9 | D10: =-D6*D9 | E10: =-E6*E9 | F10: =-F6*F9 | G10: =-G6*G9 | H10: =-H6*H9 | I10: =-I6*I9 | J10: =-J6*J9 | ... L10: =-L6*L9
A11: Owner EBITDA | C11: =C8+C10 | D11: =D8+D10 | E11: =E8+E10 | F11: =F8+F10 | G11: =G8+G10 | H11: =H8+H10 | I11: =I8+I10 | J11: =J8+J10 | ... L11: =L8+L10
A12: D&A | C12: =-C6*Assumptions!$B$4 | D12: =-D6*Assumptions!$B$4 | E12: =-E6*Assumptions!$B$4 | F12: =-F6*Assumptions!$B$4 | G12: =-G6*Assumptions!$B$4 | H12: =-H6*Assumptions!$B$4 | I12: =-I6*Assumptions!$B$4 | J12: =-J6*Assumptions!$B$4 | ... L12: =-L6*Assumptions!$B$4
A13: EBIT (SBC expensed) | C13: =C11+C12 | D13: =D11+D12 | E13: =E11+E12 | F13: =F11+F12 | G13: =G11+G12 | H13: =H11+H12 | I13: =I11+I12 | J13: =J11+J12 | ... L13: =L11+L12
A14: Cash tax rate | C14: 0.21 | D14: 0.21 | E14: 0.21 | F14: 0.21 | G14: 0.21 | H14: 0.21 | I14: 0.21 | J14: 0.21 | K14: 0.21 | L14: 0.21
A15: NOPAT | C15: =C13*(1-C14) | D15: =D13*(1-D14) | E15: =E13*(1-E14) | F15: =F13*(1-F14) | G15: =G13*(1-G14) | H15: =H13*(1-H14) | I15: =I13*(1-I14) | J15: =J13*(1-J14) | ... L15: =L13*(1-L14)
A16: add back D&A | C16: =-C12 | D16: =-D12 | E16: =-E12 | F16: =-F12 | G16: =-G12 | H16: =-H12 | I16: =-I12 | J16: =-J12 | ... L16: =-L12
A17: less capex | C17: =-C6*Assumptions!C$12 | D17: =-D6*Assumptions!D$12 | E17: =-E6*Assumptions!E$12 | F17: =-F6*Assumptions!F$12 | G17: =-G6*Assumptions!G$12 | H17: =-H6*Assumptions!H$12 | I17: =-I6*Assumptions!I$12 | J17: =-J6*Assumptions!J$12 | ... L17: =-L6*Assumptions!L$12
A18: add WC (on rev change) | C18: =Assumptions!$B$5*(C6-B6) | D18: =Assumptions!$B$5*(D6-C6) | E18: =Assumptions!$B$5*(E6-D6) | F18: =Assumptions!$B$5*(F6-E6) | G18: =Assumptions!$B$5*(G6-F6) | H18: =Assumptions!$B$5*(H6-G6) | I18: =Assumptions!$B$5*(I6-H6) | J18: =Assumptions!$B$5*(J6-I6) | ... L18: =Assumptions!$B$5*(L6-K6)
A19: Unlevered owner FCF | C19: =C15+C16+C17+C18 | D19: =D15+D16+D17+D18 | E19: =E15+E16+E17+E18 | F19: =F15+F16+F17+F18 | G19: =G15+G16+G17+G18 | H19: =H15+H16+H17+H18 | I19: =I15+I16+I17+I18 | J19: =J15+J16+J17+J18 | ... L19: =L15+L16+L17+L18
A20: Discount factor | C20: =1/(1+Assumptions!$B$3)^C4 | D20: =1/(1+Assumptions!$B$3)^D4 | E20: =1/(1+Assumptions!$B$3)^E4 | F20: =1/(1+Assumptions!$B$3)^F4 | G20: =1/(1+Assumptions!$B$3)^G4 | H20: =1/(1+Assumptions!$B$3)^H4 | I20: =1/(1+Assumptions!$B$3)^I4 | J20: =1/(1+Assumptions!$B$3)^J4 | ... L20: =1/(1+Assumptions!$B$3)^L4
A21: PV of FCF | C21: =C19*C20 | D21: =D19*D20 | E21: =E19*E20 | F21: =F19*F20 | G21: =G19*G20 | H21: =H19*H20 | I21: =I19*I20 | J21: =J19*J20 | ... L21: =L19*L20
A23: Memo: FCF before SBC (company-style) | C23: =C19-C10 | D23: =D19-D10 | E23: =E19-E10 | F23: =F19-F10 | G23: =G19-G10 | H23: =H19-H10 | I23: =I19-I10 | J23: =J19-J10 | ... L23: =L19-L10
A24: Memo: implied owner-FCF margin | C24: =C19/C6 | D24: =D19/D6 | E24: =E19/E6 | F24: =F19/F6 | G24: =G19/G6 | H24: =H19/H6 | I24: =I19/I6 | J24: =J19/J6 | ... L24: =L19/L6
A26: Sum of PV (explicit years) | B26: =SUM(C21:L21)
A27: Terminal growth | B27: =Assumptions!$C$15
A28: Terminal FCF | B28: =L19*(1+B27)
A29: Gordon TV | B29: =B28/(Assumptions!$B$3-B27)
A30: Cap TV | B30: =Assumptions!$C$16*L19
A31: TV used | B31: =MAX(0,MIN(B29,B30))
A32: Implied exit multiple | B32: =B31/L19
A33: PV of TV | B33: =B31*L20
A34: Enterprise value | B34: =B26+B33
A35: less net debt | B35: =-Assumptions!$B$6
A36: Equity value | B36: =B34+B35
A37: Diluted shares (m) | B37: =Assumptions!$B$7
A38: VALUE PER SHARE | B38: =B36/B37
A39: Upside vs price | B39: =B38/Assumptions!$B$8-1
A41: Street memo: PV explicit SBC | B41: =SUMPRODUCT(-C10:L10/(1+Assumptions!$B$3)^C4:L4)
A42: Street memo: PV terminal SBC | B42: =(-L10*(1+B27)/(Assumptions!$B$3-B27))*L20
A43: Street value per share | B43: =(B36+B41+B42)/B37

Sheet DCF_Bull
B3: 2025A | C3: 2026E | D3: 2027E | E3: 2028E | F3: 2029E | G3: 2030E | H3: 2031E | I3: 2032E | J3: 2033E | K3: 2034E | L3: 2035E
B4: 0 | C4: 1 | D4: 2 | E4: 3 | F4: 4 | G4: 5 | H4: 6 | I4: 7 | J4: 8 | K4: 9 | L4: 10
A5: Revenue growth YoY | C5: 0.1 | D5: 0.07 | E5: 0.06 | F5: 0.055 | G5: 0.05 | H5: 0.03 | I5: 0 | J5: -0.01 | K5: 0.01 | L5: 0.02
A6: Revenue | B6: =Assumptions!$B$10 | C6: =B6*(1+C5) | D6: =C6*(1+D5) | E6: =D6*(1+E5) | F6: =E6*(1+F5) | G6: =F6*(1+G5) | H6: =G6*(1+H5) | I6: =H6*(1+I5) | J6: =I6*(1+J5) | ... L6: =K6*(1+L5)
A7: Adj (cash) EBITDA margin | C7: 0.31 | D7: 0.3175 | E7: 0.3225 | F7: 0.3275 | G7: 0.33 | H7: 0.33 | I7: 0.32 | J7: 0.315 | K7: 0.315 | L7: 0.315
A8: Adjusted EBITDA | C8: =C6*C7 | D8: =D6*D7 | E8: =E6*E7 | F8: =F6*F7 | G8: =G6*G7 | H8: =H6*H7 | I8: =I6*I7 | J8: =J6*J7 | ... L8: =L6*L7
A9: SBC % of revenue | C9: 0.007 | D9: 0.007 | E9: 0.007 | F9: 0.007 | G9: 0.007 | H9: 0.007 | I9: 0.007 | J9: 0.007 | K9: 0.007 | L9: 0.007
A10: SBC | C10: =-C6*C9 | D10: =-D6*D9 | E10: =-E6*E9 | F10: =-F6*F9 | G10: =-G6*G9 | H10: =-H6*H9 | I10: =-I6*I9 | J10: =-J6*J9 | ... L10: =-L6*L9
A11: Owner EBITDA | C11: =C8+C10 | D11: =D8+D10 | E11: =E8+E10 | F11: =F8+F10 | G11: =G8+G10 | H11: =H8+H10 | I11: =I8+I10 | J11: =J8+J10 | ... L11: =L8+L10
A12: D&A | C12: =-C6*Assumptions!$B$4 | D12: =-D6*Assumptions!$B$4 | E12: =-E6*Assumptions!$B$4 | F12: =-F6*Assumptions!$B$4 | G12: =-G6*Assumptions!$B$4 | H12: =-H6*Assumptions!$B$4 | I12: =-I6*Assumptions!$B$4 | J12: =-J6*Assumptions!$B$4 | ... L12: =-L6*Assumptions!$B$4
A13: EBIT (SBC expensed) | C13: =C11+C12 | D13: =D11+D12 | E13: =E11+E12 | F13: =F11+F12 | G13: =G11+G12 | H13: =H11+H12 | I13: =I11+I12 | J13: =J11+J12 | ... L13: =L11+L12
A14: Cash tax rate | C14: 0.21 | D14: 0.21 | E14: 0.21 | F14: 0.21 | G14: 0.21 | H14: 0.21 | I14: 0.21 | J14: 0.21 | K14: 0.21 | L14: 0.21
A15: NOPAT | C15: =C13*(1-C14) | D15: =D13*(1-D14) | E15: =E13*(1-E14) | F15: =F13*(1-F14) | G15: =G13*(1-G14) | H15: =H13*(1-H14) | I15: =I13*(1-I14) | J15: =J13*(1-J14) | ... L15: =L13*(1-L14)
A16: add back D&A | C16: =-C12 | D16: =-D12 | E16: =-E12 | F16: =-F12 | G16: =-G12 | H16: =-H12 | I16: =-I12 | J16: =-J12 | ... L16: =-L12
A17: less capex | C17: =-C6*Assumptions!C$12 | D17: =-D6*Assumptions!D$12 | E17: =-E6*Assumptions!E$12 | F17: =-F6*Assumptions!F$12 | G17: =-G6*Assumptions!G$12 | H17: =-H6*Assumptions!H$12 | I17: =-I6*Assumptions!I$12 | J17: =-J6*Assumptions!J$12 | ... L17: =-L6*Assumptions!L$12
A18: add WC (on rev change) | C18: =Assumptions!$B$5*(C6-B6) | D18: =Assumptions!$B$5*(D6-C6) | E18: =Assumptions!$B$5*(E6-D6) | F18: =Assumptions!$B$5*(F6-E6) | G18: =Assumptions!$B$5*(G6-F6) | H18: =Assumptions!$B$5*(H6-G6) | I18: =Assumptions!$B$5*(I6-H6) | J18: =Assumptions!$B$5*(J6-I6) | ... L18: =Assumptions!$B$5*(L6-K6)
A19: Unlevered owner FCF | C19: =C15+C16+C17+C18 | D19: =D15+D16+D17+D18 | E19: =E15+E16+E17+E18 | F19: =F15+F16+F17+F18 | G19: =G15+G16+G17+G18 | H19: =H15+H16+H17+H18 | I19: =I15+I16+I17+I18 | J19: =J15+J16+J17+J18 | ... L19: =L15+L16+L17+L18
A20: Discount factor | C20: =1/(1+Assumptions!$B$3)^C4 | D20: =1/(1+Assumptions!$B$3)^D4 | E20: =1/(1+Assumptions!$B$3)^E4 | F20: =1/(1+Assumptions!$B$3)^F4 | G20: =1/(1+Assumptions!$B$3)^G4 | H20: =1/(1+Assumptions!$B$3)^H4 | I20: =1/(1+Assumptions!$B$3)^I4 | J20: =1/(1+Assumptions!$B$3)^J4 | ... L20: =1/(1+Assumptions!$B$3)^L4
A21: PV of FCF | C21: =C19*C20 | D21: =D19*D20 | E21: =E19*E20 | F21: =F19*F20 | G21: =G19*G20 | H21: =H19*H20 | I21: =I19*I20 | J21: =J19*J20 | ... L21: =L19*L20
A23: Memo: FCF before SBC (company-style) | C23: =C19-C10 | D23: =D19-D10 | E23: =E19-E10 | F23: =F19-F10 | G23: =G19-G10 | H23: =H19-H10 | I23: =I19-I10 | J23: =J19-J10 | ... L23: =L19-L10
A24: Memo: implied owner-FCF margin | C24: =C19/C6 | D24: =D19/D6 | E24: =E19/E6 | F24: =F19/F6 | G24: =G19/G6 | H24: =H19/H6 | I24: =I19/I6 | J24: =J19/J6 | ... L24: =L19/L6
A26: Sum of PV (explicit years) | B26: =SUM(C21:L21)
A27: Terminal growth | B27: =Assumptions!$D$15
A28: Terminal FCF | B28: =L19*(1+B27)
A29: Gordon TV | B29: =B28/(Assumptions!$B$3-B27)
A30: Cap TV | B30: =Assumptions!$D$16*L19
A31: TV used | B31: =MAX(0,MIN(B29,B30))
A32: Implied exit multiple | B32: =B31/L19
A33: PV of TV | B33: =B31*L20
A34: Enterprise value | B34: =B26+B33
A35: less net debt | B35: =-Assumptions!$B$6
A36: Equity value | B36: =B34+B35
A37: Diluted shares (m) | B37: =Assumptions!$B$7
A38: VALUE PER SHARE | B38: =B36/B37
A39: Upside vs price | B39: =B38/Assumptions!$B$8-1
A41: Street memo: PV explicit SBC | B41: =SUMPRODUCT(-C10:L10/(1+Assumptions!$B$3)^C4:L4)
A42: Street memo: PV terminal SBC | B42: =(-L10*(1+B27)/(Assumptions!$B$3-B27))*L20
A43: Street value per share | B43: =(B36+B41+B42)/B37

Sheet FCF_Quality
A1: Reported FCF reconciled to owner FCF (EUR millions)
B3: FY2016 | C3: FY2017 | D3: FY2018 | E3: FY2019 | F3: FY2020 | G3: FY2021 | H3: FY2022 | I3: FY2023 | J3: FY2024 | K3: FY2025
A4: Revenue | B4: 33809 | C4: 35072 | D4: 34463 | E4: 36126 | F4: 36041 | G4: 37761 | H4: 37651 | I4: 37817 | J4: 41081 | K4: 43626
A5: Free cash flow (OCF - capex) | B5: 6498 | C5: 5985 | D5: 4088 | E5: 5928 | F5: 5335 | G5: 8479 | H5: 8423 | I5: 7352 | J5: 5886 | K5: 7212
A6: less: SBC (no separate equity-tax line disclosed) | B6: -241 | C6: -263 | D6: -284 | E6: -252 | F6: -274 | G6: -244 | H6: -234 | I6: -260 | J6: -278 | K6: -313
A7: less: interest income (n/a -- net-debt company) | B7: 0 | C7: 0 | D7: 0 | E7: 0 | F7: 0 | G7: 0 | H7: 0 | I7: 0 | J7: 0 | K7: 0
A8: Owner FCF (FCF less SBC less interest income) | B8: =B5+B6+B7 | C8: =C5+C6+C7 | D8: =D5+D6+D7 | E8: =E5+E6+E7 | F8: =F5+F6+F7 | G8: =G5+G6+G7 | H8: =H5+H6+H7 | I8: =I5+I6+I7 | ... K8: =K5+K6+K7
A9: Reported FCF margin | B9: =B5/B4 | C9: =C5/C4 | D9: =D5/D4 | E9: =E5/E4 | F9: =F5/F4 | G9: =G5/G4 | H9: =H5/H4 | I9: =I5/I4 | ... K9: =K5/K4
A10: Owner FCF margin | B10: =B8/B4 | C10: =C8/C4 | D10: =D8/D4 | E10: =E8/E4 | F10: =F8/F4 | G10: =G8/G4 | H10: =H8/H4 | I10: =I8/I4 | ... K10: =K8/K4
A12: Memo: FY2025 company-defined FCF EUR9,900m (18.5% of sales) is BEFORE restructuring/acquisitions/disposals -- the ~EUR2bn gap to the EUR7,212m statutory figure is recurring restructuring and similar cash costs; the model's cash-EBITDA margin nets these.
A13: Memo: FY2024 owner-FCF margin (13.7%) depressed by Opella separation costs and the capex ramp; FY2021-22 margins (~21.8%) include the since-divested Opella consumer business.
A14: Memo: capex ramp EUR2.0bn (FY2021) -> EUR3.5bn (FY2025) reflects US onshoring/biologics capacity; modeled at 8.1% of sales tapering to 7.0%.
A15: Memo: cash tax rate ~21% guided FY2026 (H1-2026 ETR 21.8%); no abnormal credits in the base year.

Sheet Valuation
A1: Valuation summary
A3: Scenario | B3: Value/share | C3: Upside | D3: Weight | E3: Street value/share | F3: Entry price (15% IRR)
A4: Bear | B4: =DCF_Bear!$B$38 | C4: =B4/Assumptions!$B$8-1 | D4: =Assumptions!$B$17 | E4: =DCF_Bear!$B$43 | F4: =(SUMPRODUCT(DCF_Bear!$C$19:$L$19/(1+Assumptions!$B$9)^DCF_Bear!$C$4:$L$4)+DCF_Bear!$B$31/(1+Assumptions!$B$9)^10-Assumptions!$B$6)/Assumptions!$B$7
A5: Base | B5: =DCF_Base!$B$38 | C5: =B5/Assumptions!$B$8-1 | D5: =Assumptions!$C$17 | E5: =DCF_Base!$B$43 | F5: =(SUMPRODUCT(DCF_Base!$C$19:$L$19/(1+Assumptions!$B$9)^DCF_Base!$C$4:$L$4)+DCF_Base!$B$31/(1+Assumptions!$B$9)^10-Assumptions!$B$6)/Assumptions!$B$7
A6: Bull | B6: =DCF_Bull!$B$38 | C6: =B6/Assumptions!$B$8-1 | D6: =Assumptions!$D$17 | E6: =DCF_Bull!$B$43 | F6: =(SUMPRODUCT(DCF_Bull!$C$19:$L$19/(1+Assumptions!$B$9)^DCF_Bull!$C$4:$L$4)+DCF_Bull!$B$31/(1+Assumptions!$B$9)^10-Assumptions!$B$6)/Assumptions!$B$7
A8: Probability-weighted IV | B8: =SUMPRODUCT(B4:B6,D4:D6)
A9: Margin of safety vs price | B9: =1-Assumptions!$B$8/B8
A10: Street weighted IV | B10: =SUMPRODUCT(E4:E6,D4:D6)
A11: Band position (0=house,1=street) | B11: =(Assumptions!$B$8-B8)/(B10-B8) | C11: Note: negative = price below even the house (fully-SBC-expensed) basis; band only ~EUR4.7 wide since SBC is 0.7% of sales.
A12: Weighted entry price (15% IRR) | B12: =SUMPRODUCT(F4:F6,D4:D6)
A15: Required-return table (base case; TV built at house WACC, discounting varies)
A16: Required return | B16: 0.075 | C16: 0.09 | D16: 0.1 | E16: 0.11 | F16: 0.12 | G16: 0.15
A17: Value per share | B17: =(SUMPRODUCT(DCF_Base!$C$19:$L$19/(1+B16)^DCF_Base!$C$4:$L$4)+DCF_Base!$B$31/(1+B16)^10-Assumptions!$B$6)/Assumptions!$B$7 | C17: =(SUMPRODUCT(DCF_Base!$C$19:$L$19/(1+C16)^DCF_Base!$C$4:$L$4)+DCF_Base!$B$31/(1+C16)^10-Assumptions!$B$6)/Assumptions!$B$7 | D17: =(SUMPRODUCT(DCF_Base!$C$19:$L$19/(1+D16)^DCF_Base!$C$4:$L$4)+DCF_Base!$B$31/(1+D16)^10-Assumptions!$B$6)/Assumptions!$B$7 | E17: =(SUMPRODUCT(DCF_Base!$C$19:$L$19/(1+E16)^DCF_Base!$C$4:$L$4)+DCF_Base!$B$31/(1+E16)^10-Assumptions!$B$6)/Assumptions!$B$7 | F17: =(SUMPRODUCT(DCF_Base!$C$19:$L$19/(1+F16)^DCF_Base!$C$4:$L$4)+DCF_Base!$B$31/(1+F16)^10-Assumptions!$B$6)/Assumptions!$B$7 | G17: =(SUMPRODUCT(DCF_Base!$C$19:$L$19/(1+G16)^DCF_Base!$C$4:$L$4)+DCF_Base!$B$31/(1+G16)^10-Assumptions!$B$6)/Assumptions!$B$7
A20: Sensitivity: base-case value per share -- rows WACC, cols terminal growth (TV recomputed per cell, 15x cap)
C21: 0.005 | D21: 0.01 | E21: 0.015 | F21: 0.02 | G21: 0.025
B22: 0.055 | C22: =IF($B22>C$21,(SUMPRODUCT(DCF_Base!$C$19:$L$19/(1+$B22)^DCF_Base!$C$4:$L$4)+MAX(0,MIN(DCF_Base!$L$19*(1+C$21)/($B22-C$21),Assumptions!$C$16*DCF_Base!$L$19))/(1+$B22)^10-Assumptions!$B$6)/Assumptions!$B$7,"n/a") | D22: =IF($B22>D$21,(SUMPRODUCT(DCF_Base!$C$19:$L$19/(1+$B22)^DCF_Base!$C$4:$L$4)+MAX(0,MIN(DCF_Base!$L$19*(1+D$21)/($B22-D$21),Assumptions!$C$16*DCF_Base!$L$19))/(1+$B22)^10-Assumptions!$B$6)/Assumptions!$B$7,"n/a") | E22: =IF($B22>E$21,(SUMPRODUCT(DCF_Base!$C$19:$L$19/(1+$B22)^DCF_Base!$C$4:$L$4)+MAX(0,MIN(DCF_Base!$L$19*(1+E$21)/($B22-E$21),Assumptions!$C$16*DCF_Base!$L$19))/(1+$B22)^10-Assumptions!$B$6)/Assumptions!$B$7,"n/a") | F22: =IF($B22>F$21,(SUMPRODUCT(DCF_Base!$C$19:$L$19/(1+$B22)^DCF_Base!$C$4:$L$4)+MAX(0,MIN(DCF_Base!$L$19*(1+F$21)/($B22-F$21),Assumptions!$C$16*DCF_Base!$L$19))/(1+$B22)^10-Assumptions!$B$6)/Assumptions!$B$7,"n/a") | G22: =IF($B22>G$21,(SUMPRODUCT(DCF_Base!$C$19:$L$19/(1+$B22)^DCF_Base!$C$4:$L$4)+MAX(0,MIN(DCF_Base!$L$19*(1+G$21)/($B22-G$21),Assumptions!$C$16*DCF_Base!$L$19))/(1+$B22)^10-Assumptions!$B$6)/Assumptions!$B$7,"n/a")
B23: 0.065 | C23: =IF($B23>C$21,(SUMPRODUCT(DCF_Base!$C$19:$L$19/(1+$B23)^DCF_Base!$C$4:$L$4)+MAX(0,MIN(DCF_Base!$L$19*(1+C$21)/($B23-C$21),Assumptions!$C$16*DCF_Base!$L$19))/(1+$B23)^10-Assumptions!$B$6)/Assumptions!$B$7,"n/a") | D23: =IF($B23>D$21,(SUMPRODUCT(DCF_Base!$C$19:$L$19/(1+$B23)^DCF_Base!$C$4:$L$4)+MAX(0,MIN(DCF_Base!$L$19*(1+D$21)/($B23-D$21),Assumptions!$C$16*DCF_Base!$L$19))/(1+$B23)^10-Assumptions!$B$6)/Assumptions!$B$7,"n/a") | E23: =IF($B23>E$21,(SUMPRODUCT(DCF_Base!$C$19:$L$19/(1+$B23)^DCF_Base!$C$4:$L$4)+MAX(0,MIN(DCF_Base!$L$19*(1+E$21)/($B23-E$21),Assumptions!$C$16*DCF_Base!$L$19))/(1+$B23)^10-Assumptions!$B$6)/Assumptions!$B$7,"n/a") | F23: =IF($B23>F$21,(SUMPRODUCT(DCF_Base!$C$19:$L$19/(1+$B23)^DCF_Base!$C$4:$L$4)+MAX(0,MIN(DCF_Base!$L$19*(1+F$21)/($B23-F$21),Assumptions!$C$16*DCF_Base!$L$19))/(1+$B23)^10-Assumptions!$B$6)/Assumptions!$B$7,"n/a") | G23: =IF($B23>G$21,(SUMPRODUCT(DCF_Base!$C$19:$L$19/(1+$B23)^DCF_Base!$C$4:$L$4)+MAX(0,MIN(DCF_Base!$L$19*(1+G$21)/($B23-G$21),Assumptions!$C$16*DCF_Base!$L$19))/(1+$B23)^10-Assumptions!$B$6)/Assumptions!$B$7,"n/a")
B24: 0.075 | C24: =IF($B24>C$21,(SUMPRODUCT(DCF_Base!$C$19:$L$19/(1+$B24)^DCF_Base!$C$4:$L$4)+MAX(0,MIN(DCF_Base!$L$19*(1+C$21)/($B24-C$21),Assumptions!$C$16*DCF_Base!$L$19))/(1+$B24)^10-Assumptions!$B$6)/Assumptions!$B$7,"n/a") | D24: =IF($B24>D$21,(SUMPRODUCT(DCF_Base!$C$19:$L$19/(1+$B24)^DCF_Base!$C$4:$L$4)+MAX(0,MIN(DCF_Base!$L$19*(1+D$21)/($B24-D$21),Assumptions!$C$16*DCF_Base!$L$19))/(1+$B24)^10-Assumptions!$B$6)/Assumptions!$B$7,"n/a") | E24: =IF($B24>E$21,(SUMPRODUCT(DCF_Base!$C$19:$L$19/(1+$B24)^DCF_Base!$C$4:$L$4)+MAX(0,MIN(DCF_Base!$L$19*(1+E$21)/($B24-E$21),Assumptions!$C$16*DCF_Base!$L$19))/(1+$B24)^10-Assumptions!$B$6)/Assumptions!$B$7,"n/a") | F24: =IF($B24>F$21,(SUMPRODUCT(DCF_Base!$C$19:$L$19/(1+$B24)^DCF_Base!$C$4:$L$4)+MAX(0,MIN(DCF_Base!$L$19*(1+F$21)/($B24-F$21),Assumptions!$C$16*DCF_Base!$L$19))/(1+$B24)^10-Assumptions!$B$6)/Assumptions!$B$7,"n/a") | G24: =IF($B24>G$21,(SUMPRODUCT(DCF_Base!$C$19:$L$19/(1+$B24)^DCF_Base!$C$4:$L$4)+MAX(0,MIN(DCF_Base!$L$19*(1+G$21)/($B24-G$21),Assumptions!$C$16*DCF_Base!$L$19))/(1+$B24)^10-Assumptions!$B$6)/Assumptions!$B$7,"n/a")
B25: 0.085 | C25: =IF($B25>C$21,(SUMPRODUCT(DCF_Base!$C$19:$L$19/(1+$B25)^DCF_Base!$C$4:$L$4)+MAX(0,MIN(DCF_Base!$L$19*(1+C$21)/($B25-C$21),Assumptions!$C$16*DCF_Base!$L$19))/(1+$B25)^10-Assumptions!$B$6)/Assumptions!$B$7,"n/a") | D25: =IF($B25>D$21,(SUMPRODUCT(DCF_Base!$C$19:$L$19/(1+$B25)^DCF_Base!$C$4:$L$4)+MAX(0,MIN(DCF_Base!$L$19*(1+D$21)/($B25-D$21),Assumptions!$C$16*DCF_Base!$L$19))/(1+$B25)^10-Assumptions!$B$6)/Assumptions!$B$7,"n/a") | E25: =IF($B25>E$21,(SUMPRODUCT(DCF_Base!$C$19:$L$19/(1+$B25)^DCF_Base!$C$4:$L$4)+MAX(0,MIN(DCF_Base!$L$19*(1+E$21)/($B25-E$21),Assumptions!$C$16*DCF_Base!$L$19))/(1+$B25)^10-Assumptions!$B$6)/Assumptions!$B$7,"n/a") | F25: =IF($B25>F$21,(SUMPRODUCT(DCF_Base!$C$19:$L$19/(1+$B25)^DCF_Base!$C$4:$L$4)+MAX(0,MIN(DCF_Base!$L$19*(1+F$21)/($B25-F$21),Assumptions!$C$16*DCF_Base!$L$19))/(1+$B25)^10-Assumptions!$B$6)/Assumptions!$B$7,"n/a") | G25: =IF($B25>G$21,(SUMPRODUCT(DCF_Base!$C$19:$L$19/(1+$B25)^DCF_Base!$C$4:$L$4)+MAX(0,MIN(DCF_Base!$L$19*(1+G$21)/($B25-G$21),Assumptions!$C$16*DCF_Base!$L$19))/(1+$B25)^10-Assumptions!$B$6)/Assumptions!$B$7,"n/a")
B26: 0.095 | C26: =IF($B26>C$21,(SUMPRODUCT(DCF_Base!$C$19:$L$19/(1+$B26)^DCF_Base!$C$4:$L$4)+MAX(0,MIN(DCF_Base!$L$19*(1+C$21)/($B26-C$21),Assumptions!$C$16*DCF_Base!$L$19))/(1+$B26)^10-Assumptions!$B$6)/Assumptions!$B$7,"n/a") | D26: =IF($B26>D$21,(SUMPRODUCT(DCF_Base!$C$19:$L$19/(1+$B26)^DCF_Base!$C$4:$L$4)+MAX(0,MIN(DCF_Base!$L$19*(1+D$21)/($B26-D$21),Assumptions!$C$16*DCF_Base!$L$19))/(1+$B26)^10-Assumptions!$B$6)/Assumptions!$B$7,"n/a") | E26: =IF($B26>E$21,(SUMPRODUCT(DCF_Base!$C$19:$L$19/(1+$B26)^DCF_Base!$C$4:$L$4)+MAX(0,MIN(DCF_Base!$L$19*(1+E$21)/($B26-E$21),Assumptions!$C$16*DCF_Base!$L$19))/(1+$B26)^10-Assumptions!$B$6)/Assumptions!$B$7,"n/a") | F26: =IF($B26>F$21,(SUMPRODUCT(DCF_Base!$C$19:$L$19/(1+$B26)^DCF_Base!$C$4:$L$4)+MAX(0,MIN(DCF_Base!$L$19*(1+F$21)/($B26-F$21),Assumptions!$C$16*DCF_Base!$L$19))/(1+$B26)^10-Assumptions!$B$6)/Assumptions!$B$7,"n/a") | G26: =IF($B26>G$21,(SUMPRODUCT(DCF_Base!$C$19:$L$19/(1+$B26)^DCF_Base!$C$4:$L$4)+MAX(0,MIN(DCF_Base!$L$19*(1+G$21)/($B26-G$21),Assumptions!$C$16*DCF_Base!$L$19))/(1+$B26)^10-Assumptions!$B$6)/Assumptions!$B$7,"n/a")
