Workbook

Sheet Summary
A1: SUM.NZ — DCF Summary
A3: Current price (NZD) | B3: =Assumptions!$B$17
A4: Valuation date | B4: 2026-08-28
A6: Scenario | B6: Weight | C6: Intrinsic Value (NZD) | D6: Upside % | E6: Entry @15% (NZD)
A7: Bull | B7: 0.2 | C7: =Bull!$B$30 | D7: =(C7/$B$3-1)*100 | E7: =Bull!$B$39
A8: Base | B8: 0.5 | C8: =Base!$B$30 | D8: =(C8/$B$3-1)*100 | E8: =Base!$B$39
A9: Bear | B9: 0.3 | C9: =Bear!$B$30 | D9: =(C9/$B$3-1)*100 | E9: =Bear!$B$39
A10: Prob-weighted | B10: =SUM(B7:B9) | C10: =SUMPRODUCT(B7:B9,C7:C9) | D10: =(C10/$B$3-1)*100 | E10: =SUMPRODUCT(B7:B9,E7:E9)
A12: NTA / share (NZD) | B12: =Assumptions!$B$16
A13: Price / NTA | B13: =$B$3/Assumptions!$B$16
A14: Weighted IV / NTA | B14: =C10/Assumptions!$B$16
A16: Reconciliation vs prior DCF (2026-06-30)
A17: Prior weighted IV (2026-06-30) | B17: 16.81
A18: Share count refreshed 242.361m -> 243.483m (dividend reinvestment plan) | B18: -0.07
A19: Methodology: single growth rate on UP -> component build (deliveries x margin/unit + resales x gain/resale + core op) | B19: 0.15
A20: H1-2026 evidence: build rate capped at 600-700/yr, development margin compression to 20%, partly offset by improving core operating earnings and resale gains | B20: -3.25
A21: Scenario weights 25/50/25 -> 30/50/20 | B21: -0.74
A22: New weighted IV | B22: 12.9
A24: Methodology
A25: FCF proxy is UNDERLYING PROFIT, NOT operating cash flow. For ORA/DMF retirement village operators, reported operating cash flow ($279.9m in 1H26) is inflated by resident occupation-right receipts, which are capital/financing inflows the company must continuously redeploy into new units. Underlying Profit is discounted at the cost of EQUITY (it is already after finance costs, so net debt is NOT subtracted again) with an exit-P/E cap tied to the 10yr realised range. UPDATE 2026-08-28: Underlying Profit is now built COMPONENT-WISE (development margin = deliveries x margin/unit; resale gains = resale volume x gain/resale; plus core operating earnings) rather than grown at a single rate. This was required because the H1-2026 result changed the two components in opposite directions and a single growth rate cannot express that.

Sheet Assumptions
A1: Summerset Group (SUM.NZ) — DCF Model
A2: Valuation date 2026-08-28 | Price NZD 8.49 | 2026-08-28T00:48:19Z (2026-08-28 12:48 NZST), Yahoo regularMarketPrice, regular session
A3: FCF basis: UNDERLYING PROFIT (not operating cash flow). Discounted at cost of EQUITY; net debt NOT subtracted (UP is post-finance-cost).
A4: Yellow cells are inputs. Every other number on Base/Bull/Bear/Summary is a live formula.
A6: Inputs
A7: Shares outstanding (m) | B7: 243.483
A8: Total debt (NZDm) | B8: 2074.831
A9: Cash (NZDm) | B9: 14.099
A10: Net debt (NZDm) | B10: 2058
A11: Gearing % | B11: 36.9
A12: 1H2026 Underlying Profit (NZDm) | B12: 103.445
A13: 1H2025 Underlying Profit (NZDm) | B13: 106.608
A14: FY2025 Underlying Profit (NZDm) | B14: 234.153
A15: 1H2026 NPAT NZ IFRS (NZDm) | B15: 171.439
A16: NTA per share (NZD) | B16: 14.4133
A17: Current price (NZD) | B17: 8.49
A19: Note: NTA is reported in CENTS in the filing (1,441.33) = NZD 14.4133.

Sheet Base
A1: Base Case
A2: Build rate held at management's 600-700/yr cap: new sales converge from FY25's 805 (which drew down completed stock) to ~655. Development margin per unit recovers from 1H26's depressed $142k toward the $186k ex-Cambridge/Whangarei normalised level as the lightweight-design buildings clear, consistent with 20-25% guidance. Resale gains compound with the maturing installed base ($2.0b embedded value). Core operating earnings turn positive by Y3 on the $30-40m cost-out programme and occupancy ramp. Cost of equity 11%.
A4: Cost of equity (%) | B4: 11
A5: Terminal growth (%) | B5: 3
A6: Exit P/E cap (x) | B6: 14.9
A8: Driver | B8: Y1 | C8: Y2 | D8: Y3 | E8: Y4 | F8: Y5
A9: Deliveries (units) | B9: 780 | C9: 720 | D9: 680 | E9: 660 | F9: 655
A10: Dev margin per unit (NZD k) | B10: 155 | C10: 165 | D10: 172 | E10: 178 | F10: 182
A11: Resales (units) | B11: 830 | C11: 875 | D11: 920 | E11: 965 | F11: 1010
A12: Resale gain per resale (NZD k) | B12: 139 | C12: 143 | D12: 147 | E12: 152 | F12: 157
A13: Core operating earnings (NZDm) | B13: -14 | C13: -6 | D13: 1 | E13: 7 | F13: 12
A15: Underlying Profit build | B15: Y1 | C15: Y2 | D15: Y3 | E15: Y4 | F15: Y5
A16: Development margin (NZDm) | B16: =B9*B10/1000 | C16: =C9*C10/1000 | D16: =D9*D10/1000 | E16: =E9*E10/1000 | F16: =F9*F10/1000
A17: Realised resale gains (NZDm) | B17: =B11*B12/1000 | C17: =C11*C12/1000 | D17: =D11*D12/1000 | E17: =E11*E12/1000 | F17: =F11*F12/1000
A18: UNDERLYING PROFIT (NZDm) | B18: =B16+B17+B13 | C18: =C16+C17+C13 | D18: =D16+D17+D13 | E18: =E16+E17+E13 | F18: =F16+F17+F13
A19: Discount factor | B19: =1/(1+$B$4/100)^1 | C19: =1/(1+$B$4/100)^2 | D19: =1/(1+$B$4/100)^3 | E19: =1/(1+$B$4/100)^4 | F19: =1/(1+$B$4/100)^5
A20: PV of Underlying Profit | B20: =B18*B19 | C20: =C18*C19 | D20: =D18*D19 | E20: =E18*E19 | F20: =F18*F19
A22: Sum PV of explicit UP | B22: =SUM(B20:F20)
A23: Terminal UP (Y5 x (1+g)) | B23: =F18*(1+$B$5/100)
A24: TV — Gordon growth | B24: =$B$23/(($B$4-$B$5)/100)
A25: TV — exit P/E cap | B25: =F18*$B$6
A26: Terminal value (lesser) | B26: =MIN($B$24,$B$25)
A27: Exit P/E cap binding? | B27: =IF($B$25<$B$24,"YES","no — Gordon binds")
A28: PV of terminal value | B28: =$B$26*F19
A29: EQUITY VALUE (NZDm) | B29: =$B$22+$B$28
A30: INTRINSIC VALUE / SHARE (NZD) | B30: =$B$29/Assumptions!$B$7
A31: Upside vs current price % | B31: =($B$30/Assumptions!$B$17-1)*100
A32: Terminal % of value | B32: =$B$28/$B$29*100
A33: Implied P/UP on Y1 | B33: =$B$29/B18
A34: IV / NTA (x) | B34: =$B$30/Assumptions!$B$16
A36: Entry price at 15% hurdle
A37: PV interim UP @15% | B37: =B18/1.15^1+C18/1.15^2+D18/1.15^3+E18/1.15^4+F18/1.15^5
A38: PV terminal @15% | B38: =$B$26/1.15^5
A39: ENTRY PRICE (NZD) | B39: =($B$37+$B$38)/Assumptions!$B$7

Sheet Bull
A1: Bull Case
A2: NZ property recovers, resale velocity and ORA pricing lift, land bank optionality lets Summerset reaccelerate deliveries toward 850 (management explicitly retains this option), margins return to 25%+, Australia scales to three villages. Core operating earnings inflect strongly on operating leverage. Cost of equity 10%, exit P/E capped at 22x.
A4: Cost of equity (%) | B4: 10
A5: Terminal growth (%) | B5: 3.5
A6: Exit P/E cap (x) | B6: 22
A8: Driver | B8: Y1 | C8: Y2 | D8: Y3 | E8: Y4 | F8: Y5
A9: Deliveries (units) | B9: 800 | C9: 780 | D9: 800 | E9: 830 | F9: 850
A10: Dev margin per unit (NZD k) | B10: 165 | C10: 185 | D10: 200 | E10: 210 | F10: 218
A11: Resales (units) | B11: 850 | C11: 910 | D11: 975 | E11: 1040 | F11: 1100
A12: Resale gain per resale (NZD k) | B12: 142 | C12: 150 | D12: 158 | E12: 166 | F12: 174
A13: Core operating earnings (NZDm) | B13: -10 | C13: 2 | D13: 14 | E13: 26 | F13: 38
A15: Underlying Profit build | B15: Y1 | C15: Y2 | D15: Y3 | E15: Y4 | F15: Y5
A16: Development margin (NZDm) | B16: =B9*B10/1000 | C16: =C9*C10/1000 | D16: =D9*D10/1000 | E16: =E9*E10/1000 | F16: =F9*F10/1000
A17: Realised resale gains (NZDm) | B17: =B11*B12/1000 | C17: =C11*C12/1000 | D17: =D11*D12/1000 | E17: =E11*E12/1000 | F17: =F11*F12/1000
A18: UNDERLYING PROFIT (NZDm) | B18: =B16+B17+B13 | C18: =C16+C17+C13 | D18: =D16+D17+D13 | E18: =E16+E17+E13 | F18: =F16+F17+F13
A19: Discount factor | B19: =1/(1+$B$4/100)^1 | C19: =1/(1+$B$4/100)^2 | D19: =1/(1+$B$4/100)^3 | E19: =1/(1+$B$4/100)^4 | F19: =1/(1+$B$4/100)^5
A20: PV of Underlying Profit | B20: =B18*B19 | C20: =C18*C19 | D20: =D18*D19 | E20: =E18*E19 | F20: =F18*F19
A22: Sum PV of explicit UP | B22: =SUM(B20:F20)
A23: Terminal UP (Y5 x (1+g)) | B23: =F18*(1+$B$5/100)
A24: TV — Gordon growth | B24: =$B$23/(($B$4-$B$5)/100)
A25: TV — exit P/E cap | B25: =F18*$B$6
A26: Terminal value (lesser) | B26: =MIN($B$24,$B$25)
A27: Exit P/E cap binding? | B27: =IF($B$25<$B$24,"YES","no — Gordon binds")
A28: PV of terminal value | B28: =$B$26*F19
A29: EQUITY VALUE (NZDm) | B29: =$B$22+$B$28
A30: INTRINSIC VALUE / SHARE (NZD) | B30: =$B$29/Assumptions!$B$7
A31: Upside vs current price % | B31: =($B$30/Assumptions!$B$17-1)*100
A32: Terminal % of value | B32: =$B$28/$B$29*100
A33: Implied P/UP on Y1 | B33: =$B$29/B18
A34: IV / NTA (x) | B34: =$B$30/Assumptions!$B$16
A36: Entry price at 15% hurdle
A37: PV interim UP @15% | B37: =B18/1.15^1+C18/1.15^2+D18/1.15^3+E18/1.15^4+F18/1.15^5
A38: PV terminal @15% | B38: =$B$26/1.15^5
A39: ENTRY PRICE (NZD) | B39: =($B$37+$B$38)/Assumptions!$B$7

Sheet Bear
A1: Bear Case
A2: Build rate settles at the bottom of the 600-700 band, development margin stays at the 1H26 20% rate as the adverse mix (serviced apartments -11%, memory care -2%) persists rather than reverting, NZ property stagnates, Australia execution slips, and core operating earnings stay negative. Cost of equity 12.5%, exit P/E 12.7x (10yr minimum).
A4: Cost of equity (%) | B4: 12.5
A5: Terminal growth (%) | B5: 2
A6: Exit P/E cap (x) | B6: 12.7
A8: Driver | B8: Y1 | C8: Y2 | D8: Y3 | E8: Y4 | F8: Y5
A9: Deliveries (units) | B9: 740 | C9: 660 | D9: 620 | E9: 600 | F9: 600
A10: Dev margin per unit (NZD k) | B10: 138 | C10: 138 | D10: 140 | E10: 142 | F10: 145
A11: Resales (units) | B11: 800 | C11: 820 | D11: 845 | E11: 870 | F11: 895
A12: Resale gain per resale (NZD k) | B12: 132 | C12: 130 | D12: 130 | E12: 131 | F12: 133
A13: Core operating earnings (NZDm) | B13: -22 | C13: -20 | D13: -18 | E13: -16 | F13: -14
A15: Underlying Profit build | B15: Y1 | C15: Y2 | D15: Y3 | E15: Y4 | F15: Y5
A16: Development margin (NZDm) | B16: =B9*B10/1000 | C16: =C9*C10/1000 | D16: =D9*D10/1000 | E16: =E9*E10/1000 | F16: =F9*F10/1000
A17: Realised resale gains (NZDm) | B17: =B11*B12/1000 | C17: =C11*C12/1000 | D17: =D11*D12/1000 | E17: =E11*E12/1000 | F17: =F11*F12/1000
A18: UNDERLYING PROFIT (NZDm) | B18: =B16+B17+B13 | C18: =C16+C17+C13 | D18: =D16+D17+D13 | E18: =E16+E17+E13 | F18: =F16+F17+F13
A19: Discount factor | B19: =1/(1+$B$4/100)^1 | C19: =1/(1+$B$4/100)^2 | D19: =1/(1+$B$4/100)^3 | E19: =1/(1+$B$4/100)^4 | F19: =1/(1+$B$4/100)^5
A20: PV of Underlying Profit | B20: =B18*B19 | C20: =C18*C19 | D20: =D18*D19 | E20: =E18*E19 | F20: =F18*F19
A22: Sum PV of explicit UP | B22: =SUM(B20:F20)
A23: Terminal UP (Y5 x (1+g)) | B23: =F18*(1+$B$5/100)
A24: TV — Gordon growth | B24: =$B$23/(($B$4-$B$5)/100)
A25: TV — exit P/E cap | B25: =F18*$B$6
A26: Terminal value (lesser) | B26: =MIN($B$24,$B$25)
A27: Exit P/E cap binding? | B27: =IF($B$25<$B$24,"YES","no — Gordon binds")
A28: PV of terminal value | B28: =$B$26*F19
A29: EQUITY VALUE (NZDm) | B29: =$B$22+$B$28
A30: INTRINSIC VALUE / SHARE (NZD) | B30: =$B$29/Assumptions!$B$7
A31: Upside vs current price % | B31: =($B$30/Assumptions!$B$17-1)*100
A32: Terminal % of value | B32: =$B$28/$B$29*100
A33: Implied P/UP on Y1 | B33: =$B$29/B18
A34: IV / NTA (x) | B34: =$B$30/Assumptions!$B$16
A36: Entry price at 15% hurdle
A37: PV interim UP @15% | B37: =B18/1.15^1+C18/1.15^2+D18/1.15^3+E18/1.15^4+F18/1.15^5
A38: PV terminal @15% | B38: =$B$26/1.15^5
A39: ENTRY PRICE (NZD) | B39: =($B$37+$B$38)/Assumptions!$B$7

Sheet Sensitivity
A1: Base-case IV / share: cost of equity (rows) x terminal growth (cols)
A2: Live: recomputes the full base component build at each cell. Plateaus top-left are the exit P/E cap binding.
A4: CoE \ g | B4: 2 | C4: 2.5 | D4: 3 | E4: 3.5 | F4: 4
A5: 9 | B5: =((Base!B$18/(1+9/100)^1+Base!C$18/(1+9/100)^2+Base!D$18/(1+9/100)^3+Base!E$18/(1+9/100)^4+Base!F$18/(1+9/100)^5)+MIN(Base!$F$18*(1+2.0/100)/((9-2.0)/100),Base!$F$18*Base!$B$6)/(1+9/100)^5)/Assumptions!$B$7 | C5: =((Base!B$18/(1+9/100)^1+Base!C$18/(1+9/100)^2+Base!D$18/(1+9/100)^3+Base!E$18/(1+9/100)^4+Base!F$18/(1+9/100)^5)+MIN(Base!$F$18*(1+2.5/100)/((9-2.5)/100),Base!$F$18*Base!$B$6)/(1+9/100)^5)/Assumptions!$B$7 | D5: =((Base!B$18/(1+9/100)^1+Base!C$18/(1+9/100)^2+Base!D$18/(1+9/100)^3+Base!E$18/(1+9/100)^4+Base!F$18/(1+9/100)^5)+MIN(Base!$F$18*(1+3.0/100)/((9-3.0)/100),Base!$F$18*Base!$B$6)/(1+9/100)^5)/Assumptions!$B$7 | E5: =((Base!B$18/(1+9/100)^1+Base!C$18/(1+9/100)^2+Base!D$18/(1+9/100)^3+Base!E$18/(1+9/100)^4+Base!F$18/(1+9/100)^5)+MIN(Base!$F$18*(1+3.5/100)/((9-3.5)/100),Base!$F$18*Base!$B$6)/(1+9/100)^5)/Assumptions!$B$7 | F5: =((Base!B$18/(1+9/100)^1+Base!C$18/(1+9/100)^2+Base!D$18/(1+9/100)^3+Base!E$18/(1+9/100)^4+Base!F$18/(1+9/100)^5)+MIN(Base!$F$18*(1+4.0/100)/((9-4.0)/100),Base!$F$18*Base!$B$6)/(1+9/100)^5)/Assumptions!$B$7
A6: 10 | B6: =((Base!B$18/(1+10/100)^1+Base!C$18/(1+10/100)^2+Base!D$18/(1+10/100)^3+Base!E$18/(1+10/100)^4+Base!F$18/(1+10/100)^5)+MIN(Base!$F$18*(1+2.0/100)/((10-2.0)/100),Base!$F$18*Base!$B$6)/(1+10/100)^5)/Assumptions!$B$7 | C6: =((Base!B$18/(1+10/100)^1+Base!C$18/(1+10/100)^2+Base!D$18/(1+10/100)^3+Base!E$18/(1+10/100)^4+Base!F$18/(1+10/100)^5)+MIN(Base!$F$18*(1+2.5/100)/((10-2.5)/100),Base!$F$18*Base!$B$6)/(1+10/100)^5)/Assumptions!$B$7 | D6: =((Base!B$18/(1+10/100)^1+Base!C$18/(1+10/100)^2+Base!D$18/(1+10/100)^3+Base!E$18/(1+10/100)^4+Base!F$18/(1+10/100)^5)+MIN(Base!$F$18*(1+3.0/100)/((10-3.0)/100),Base!$F$18*Base!$B$6)/(1+10/100)^5)/Assumptions!$B$7 | E6: =((Base!B$18/(1+10/100)^1+Base!C$18/(1+10/100)^2+Base!D$18/(1+10/100)^3+Base!E$18/(1+10/100)^4+Base!F$18/(1+10/100)^5)+MIN(Base!$F$18*(1+3.5/100)/((10-3.5)/100),Base!$F$18*Base!$B$6)/(1+10/100)^5)/Assumptions!$B$7 | F6: =((Base!B$18/(1+10/100)^1+Base!C$18/(1+10/100)^2+Base!D$18/(1+10/100)^3+Base!E$18/(1+10/100)^4+Base!F$18/(1+10/100)^5)+MIN(Base!$F$18*(1+4.0/100)/((10-4.0)/100),Base!$F$18*Base!$B$6)/(1+10/100)^5)/Assumptions!$B$7
A7: 11 | B7: =((Base!B$18/(1+11/100)^1+Base!C$18/(1+11/100)^2+Base!D$18/(1+11/100)^3+Base!E$18/(1+11/100)^4+Base!F$18/(1+11/100)^5)+MIN(Base!$F$18*(1+2.0/100)/((11-2.0)/100),Base!$F$18*Base!$B$6)/(1+11/100)^5)/Assumptions!$B$7 | C7: =((Base!B$18/(1+11/100)^1+Base!C$18/(1+11/100)^2+Base!D$18/(1+11/100)^3+Base!E$18/(1+11/100)^4+Base!F$18/(1+11/100)^5)+MIN(Base!$F$18*(1+2.5/100)/((11-2.5)/100),Base!$F$18*Base!$B$6)/(1+11/100)^5)/Assumptions!$B$7 | D7: =((Base!B$18/(1+11/100)^1+Base!C$18/(1+11/100)^2+Base!D$18/(1+11/100)^3+Base!E$18/(1+11/100)^4+Base!F$18/(1+11/100)^5)+MIN(Base!$F$18*(1+3.0/100)/((11-3.0)/100),Base!$F$18*Base!$B$6)/(1+11/100)^5)/Assumptions!$B$7 | E7: =((Base!B$18/(1+11/100)^1+Base!C$18/(1+11/100)^2+Base!D$18/(1+11/100)^3+Base!E$18/(1+11/100)^4+Base!F$18/(1+11/100)^5)+MIN(Base!$F$18*(1+3.5/100)/((11-3.5)/100),Base!$F$18*Base!$B$6)/(1+11/100)^5)/Assumptions!$B$7 | F7: =((Base!B$18/(1+11/100)^1+Base!C$18/(1+11/100)^2+Base!D$18/(1+11/100)^3+Base!E$18/(1+11/100)^4+Base!F$18/(1+11/100)^5)+MIN(Base!$F$18*(1+4.0/100)/((11-4.0)/100),Base!$F$18*Base!$B$6)/(1+11/100)^5)/Assumptions!$B$7
A8: 12 | B8: =((Base!B$18/(1+12/100)^1+Base!C$18/(1+12/100)^2+Base!D$18/(1+12/100)^3+Base!E$18/(1+12/100)^4+Base!F$18/(1+12/100)^5)+MIN(Base!$F$18*(1+2.0/100)/((12-2.0)/100),Base!$F$18*Base!$B$6)/(1+12/100)^5)/Assumptions!$B$7 | C8: =((Base!B$18/(1+12/100)^1+Base!C$18/(1+12/100)^2+Base!D$18/(1+12/100)^3+Base!E$18/(1+12/100)^4+Base!F$18/(1+12/100)^5)+MIN(Base!$F$18*(1+2.5/100)/((12-2.5)/100),Base!$F$18*Base!$B$6)/(1+12/100)^5)/Assumptions!$B$7 | D8: =((Base!B$18/(1+12/100)^1+Base!C$18/(1+12/100)^2+Base!D$18/(1+12/100)^3+Base!E$18/(1+12/100)^4+Base!F$18/(1+12/100)^5)+MIN(Base!$F$18*(1+3.0/100)/((12-3.0)/100),Base!$F$18*Base!$B$6)/(1+12/100)^5)/Assumptions!$B$7 | E8: =((Base!B$18/(1+12/100)^1+Base!C$18/(1+12/100)^2+Base!D$18/(1+12/100)^3+Base!E$18/(1+12/100)^4+Base!F$18/(1+12/100)^5)+MIN(Base!$F$18*(1+3.5/100)/((12-3.5)/100),Base!$F$18*Base!$B$6)/(1+12/100)^5)/Assumptions!$B$7 | F8: =((Base!B$18/(1+12/100)^1+Base!C$18/(1+12/100)^2+Base!D$18/(1+12/100)^3+Base!E$18/(1+12/100)^4+Base!F$18/(1+12/100)^5)+MIN(Base!$F$18*(1+4.0/100)/((12-4.0)/100),Base!$F$18*Base!$B$6)/(1+12/100)^5)/Assumptions!$B$7
A9: 13 | B9: =((Base!B$18/(1+13/100)^1+Base!C$18/(1+13/100)^2+Base!D$18/(1+13/100)^3+Base!E$18/(1+13/100)^4+Base!F$18/(1+13/100)^5)+MIN(Base!$F$18*(1+2.0/100)/((13-2.0)/100),Base!$F$18*Base!$B$6)/(1+13/100)^5)/Assumptions!$B$7 | C9: =((Base!B$18/(1+13/100)^1+Base!C$18/(1+13/100)^2+Base!D$18/(1+13/100)^3+Base!E$18/(1+13/100)^4+Base!F$18/(1+13/100)^5)+MIN(Base!$F$18*(1+2.5/100)/((13-2.5)/100),Base!$F$18*Base!$B$6)/(1+13/100)^5)/Assumptions!$B$7 | D9: =((Base!B$18/(1+13/100)^1+Base!C$18/(1+13/100)^2+Base!D$18/(1+13/100)^3+Base!E$18/(1+13/100)^4+Base!F$18/(1+13/100)^5)+MIN(Base!$F$18*(1+3.0/100)/((13-3.0)/100),Base!$F$18*Base!$B$6)/(1+13/100)^5)/Assumptions!$B$7 | E9: =((Base!B$18/(1+13/100)^1+Base!C$18/(1+13/100)^2+Base!D$18/(1+13/100)^3+Base!E$18/(1+13/100)^4+Base!F$18/(1+13/100)^5)+MIN(Base!$F$18*(1+3.5/100)/((13-3.5)/100),Base!$F$18*Base!$B$6)/(1+13/100)^5)/Assumptions!$B$7 | F9: =((Base!B$18/(1+13/100)^1+Base!C$18/(1+13/100)^2+Base!D$18/(1+13/100)^3+Base!E$18/(1+13/100)^4+Base!F$18/(1+13/100)^5)+MIN(Base!$F$18*(1+4.0/100)/((13-4.0)/100),Base!$F$18*Base!$B$6)/(1+13/100)^5)/Assumptions!$B$7
