Workbook

Sheet Shell Valuation
A1: RTO.NZ Asset/Scenario Shell Valuation Model
A2: This is NOT a growth DCF - RTO Limited is a dormant cash shell with no operating business.
A3: Gray cells are INPUTS - adjust to see valuation change
A5: KEY INPUTS
A6: Current Stock Price (RTO.NZ) | B6: 0.118
A7: Shares Outstanding | B7: 10000026
A8: FY2026 Cash (NZD) | B8: 114903
A9: FY2026 Total Debt (NZD) | B9: 0
A10: FY2026 Total Liabilities (NZD) | B10: 14956
A11: FY2026 Shareholders' Equity / NTA (NZD) | B11: 187125
A12: Pending Shareholder Loan (NZD, not yet drawn) | B12: 200000
A14: NTA per Share (formula) | B14: =B11/B7 -> 0
A15: Market Cap (formula) | B15: =B6*B7 -> 0
A16: Price / NTA multiple (formula) | B16: =B15/B11 -> 0
A18: SCENARIO ASSUMPTIONS
B19: Bear | C19: Base | D19: Bull
A20: Probability Weight | B20: 0.6 | C20: 0.32 | D20: 0.08
A21: Weights sum check (formula) | B21: =SUM(B20:D20) -> 0
A23: Bear: Residual equity value after loan/wind-up (NZD) | B23: 20000
A24: Base: Tangible equity / NTA (NZD) | B24: 187125
A25: Base: Shell scarcity value (NZD) | B25: 500000
A26: Base: Total equity value (formula) | B26: =B24+B25 -> 0
A27: Bull: Upper-precedent completed-RTO shell value (NZD) | B27: 2500000
A29: SCENARIO INTRINSIC VALUES (per share, formulas)
B30: Bear | C30: Base | D30: Bull
A31: Equity Value (NZD) | B31: =B23 -> 0 | C31: =B26 -> 0 | D31: =B27 -> 0
A32: Intrinsic Value / Share | B32: =B31/$B$7 -> 0 | C32: =C31/$B$7 -> 0 | D32: =D31/$B$7 -> 0
A33: Implied P/NTA multiple | B33: =B31/$B$11 -> 0 | C33: =C31/$B$11 -> 0 | D33: =D31/$B$11 -> 0
A34: Upside / (Downside) vs Current Price | B34: =(B32-$B$6)/$B$6 -> 0 | C34: =(C32-$B$6)/$B$6 -> 0 | D34: =(D32-$B$6)/$B$6 -> 0
A36: PROBABILITY-WEIGHTED VALUATION
A37: Weighted Intrinsic Value / Share | B37: =B20*B32+C20*C32+D20*D32 -> 0
A38: Weighted Upside / (Downside) vs Current Price | B38: =(B37-$B$6)/$B$6 -> 0
A39: Weighted Implied P/NTA multiple | B39: =B37*$B$7/$B$11 -> 0
A41: ENTRY PRICE (no IRR mechanics - shell has no distributable cash flow)
A42: Recommended Entry Price = Probability-Weighted Intrinsic Value | B42: =B37 -> 0
A43: Discount required vs current price to reach entry price (formula) | B43: =(B6-B42)/B6 -> 0
A45: Note: RTO Limited pays no dividends and has never generated distributable
A46: free cash flow. A standard 15%-IRR entry-price/exit formula does not apply.
A47: The probability-weighted intrinsic value above IS the entry-price answer.

Sheet Sensitivity
A1: Sensitivity Analysis - Base Case
A2: Intrinsic Value/Share by NTA Haircut (rows) and Shell Scarcity Value (columns)
A3: All cells are FORMULAS referencing the Shell Valuation sheet inputs.
A5: Haircut \ Shell $ | B5: 0 | C5: 250000 | D5: 500000 | E5: 750000 | F5: 1000000
A6: 0 | B6: =('Shell Valuation'!$B$11*(1-0.0)+0)/'Shell Valuation'!$B$7 -> 0 | C6: =('Shell Valuation'!$B$11*(1-0.0)+250000)/'Shell Valuation'!$B$7 -> 0 | D6: =('Shell Valuation'!$B$11*(1-0.0)+500000)/'Shell Valuation'!$B$7 -> 0 | E6: =('Shell Valuation'!$B$11*(1-0.0)+750000)/'Shell Valuation'!$B$7 -> 0 | F6: =('Shell Valuation'!$B$11*(1-0.0)+1000000)/'Shell Valuation'!$B$7 -> 0
A7: 0.25 | B7: =('Shell Valuation'!$B$11*(1-0.25)+0)/'Shell Valuation'!$B$7 -> 0 | C7: =('Shell Valuation'!$B$11*(1-0.25)+250000)/'Shell Valuation'!$B$7 -> 0 | D7: =('Shell Valuation'!$B$11*(1-0.25)+500000)/'Shell Valuation'!$B$7 -> 0 | E7: =('Shell Valuation'!$B$11*(1-0.25)+750000)/'Shell Valuation'!$B$7 -> 0 | F7: =('Shell Valuation'!$B$11*(1-0.25)+1000000)/'Shell Valuation'!$B$7 -> 0
A8: 0.5 | B8: =('Shell Valuation'!$B$11*(1-0.5)+0)/'Shell Valuation'!$B$7 -> 0 | C8: =('Shell Valuation'!$B$11*(1-0.5)+250000)/'Shell Valuation'!$B$7 -> 0 | D8: =('Shell Valuation'!$B$11*(1-0.5)+500000)/'Shell Valuation'!$B$7 -> 0 | E8: =('Shell Valuation'!$B$11*(1-0.5)+750000)/'Shell Valuation'!$B$7 -> 0 | F8: =('Shell Valuation'!$B$11*(1-0.5)+1000000)/'Shell Valuation'!$B$7 -> 0
A9: 0.75 | B9: =('Shell Valuation'!$B$11*(1-0.75)+0)/'Shell Valuation'!$B$7 -> 0 | C9: =('Shell Valuation'!$B$11*(1-0.75)+250000)/'Shell Valuation'!$B$7 -> 0 | D9: =('Shell Valuation'!$B$11*(1-0.75)+500000)/'Shell Valuation'!$B$7 -> 0 | E9: =('Shell Valuation'!$B$11*(1-0.75)+750000)/'Shell Valuation'!$B$7 -> 0 | F9: =('Shell Valuation'!$B$11*(1-0.75)+1000000)/'Shell Valuation'!$B$7 -> 0
A10: 1 | B10: =('Shell Valuation'!$B$11*(1-1.0)+0)/'Shell Valuation'!$B$7 -> 0 | C10: =('Shell Valuation'!$B$11*(1-1.0)+250000)/'Shell Valuation'!$B$7 -> 0 | D10: =('Shell Valuation'!$B$11*(1-1.0)+500000)/'Shell Valuation'!$B$7 -> 0 | E10: =('Shell Valuation'!$B$11*(1-1.0)+750000)/'Shell Valuation'!$B$7 -> 0 | F10: =('Shell Valuation'!$B$11*(1-1.0)+1000000)/'Shell Valuation'!$B$7 -> 0
A12: Current Price Reference | B12: ='Shell Valuation'!$B$6 -> 0
A13: Note
A14: Only the top-right corner (0% haircut, $1.0M shell value) approaches the current
A15: market price - requiring simultaneously crediting full unhaircut book value AND
A16: assuming near-maximum plausible shell premium. Not the modal outcome.

Sheet FCF Quality
A1: Cash Burn / "FCF Quality" Reconciliation
A2: RTO Limited has NO free cash flow to reconcile - this sheet documents WHY, and shows
A3: the full historical cash-burn series in place of an owner-FCF build.
A5: Period | B5: FY2021 | C5: FY2022 | D5: FY2023 | E5: FY2024 | F5: FY2025 | G5: FY2026
A6: Operating Cash Flow (NZD millions) | B6: 0.18201 | C6: 0.127124 | D6: -0.280052 | E6: -0.229058 | F6: -0.346307 | G6: -0.173632
A7: Net Income (NZD millions) | B7: -0.779559 | C7: -0.455083 | D7: -0.264717 | E7: -0.245732 | F7: -0.055236 | G7: -0.173831
A8: Shareholders' Equity / NTA (NZD millions) | B8: 0.190764 | C8: 0.230983 | D8: 0.950726 | E8: 0.166193 | F8: 0.360956 | G8: 0.187125
A10: Reported FCF (company definition) | B10: -173632
A11: Less: SBC incl. equity-award taxes | B11: 0
A12: Less: Interest income | B12: 1031
A13: Owner FCF (formula) | B13: =B10-B11-B12 -> 0
A15: Why no FCF projection exists:
A16: The mortgage-lending business was discontinued in FY2023. Every year since has
A17: been a cash outflow funded by drawing down the cash balance, not by operations.
A18: FY2026 total income of $70,031 is $69,000 one-off reimbursement + $1,031 bank
A19: interest - neither is repeatable operating revenue. There is no owner-FCF base
A20: to project forward; this is why the model values scenarios on NTA + option value.
A22: Cash Runway Check
A23: FY2026 Cash (NZD) | B23: ='Shell Valuation'!$B$8 -> 0
A24: FY2026 Annual Burn (NZD) | B24: 173632
A25: Runway (years, formula) | B25: =B23/B24 -> 0

Sheet Historical
A1: Historical Growth Rates
A2: Not applicable in the conventional sense - see notes below.
A4: Metric | B4: 3-Year CAGR | C4: 5-Year CAGR
A5: Revenue | B5: n/a | C5: n/a
A6: EPS | B6: n/a | C6: n/a
A7: Equity / NTA | B7: -0.4183 | C7: -0.0038
A8: FCF | B8: n/a | C8: n/a
A9: Growth Rate Source: | B9: not_applicable_asset_scenario_model
A11: Note:
A12: No meaningful revenue, EPS, or FCF history exists to extrapolate. The only genuinely trending series is NTA per share, which nearly halved in FY2026 alone (3.61c to 1.87c) purely from overhead burn with no offsetting revenue. This is why the valuation approach below abandons growth-rate selection entirely in favour of scenario-weighted asset/option valuation.

Sheet Model_Info
A1: Model Provenance & Methodology Notes
A4: Ticker | B4: RTO.NZ (RTO Limited, formerly Blackwell Global Holdings Limited / BGI.NZ)
A5: Built by | B5: Claude agent (DCF/valuation workflow), per project CLAUDE.md instructions
A6: Valuation date | B6: 2026-08-13
A7: Price date/source | B7: Yahoo Finance chart API, regularMarketPrice, verified 13-Aug-2026 ~12:04 NZT (251 daily bars, RTO.NZ actively trading)
A8: Price used | B8: NZ$0.118 (RTO.NZ) - NOT the dead BGI.NZ quote of $0.004 frozen at 30-Apr-2024
A9: Filing vintage | B9: FY2026 Annual Report (year ended 31 March 2026), signed by auditor William Buck 24 June 2026
A10: Methodology | B10: Asset/scenario-weighted valuation, NOT a growth DCF. RTO Limited has no operating business, no revenue, and no positive FCF history since the mortgage-lending business was discontinued in FY2023. Value is modelled as a probability-weighted mix of bear (wind-up/dilutive rescue), base (persistent shell plus modest scarcity premium), and bull (prompt favourable-terms RTO) scenarios. This mirrors the approach used for AFC.NZ and this company's own prior model under the BGI.NZ ticker.
A11: Key methodology choices | B11: (1) Base case = FY2026 NTA ($187,125) + NZ$500,000 shell scarcity value, anchored to AFC.NZ NZX shell-value precedent (NZ$0.5-1.5M range). (2) Bull case = NZ$2.5M upper-precedent completed-RTO shell value (pre-dilution retained economic claim). (3) Bear case = NZ$20,000 residual after the pending $200,000 shareholder loan (once drawn) ranks ahead of equity in a wind-up. (4) Probability weights 60% bear / 32% base / 8% bull, reflecting a multi-year pattern of unconverted RTO "discussions", an explicit going-concern qualification, and under 8 months of pre-loan cash runway.
A12: What changed from the prior (BGI.NZ) model | B12: ONLY the price and every figure derived from it: current_price ($0.004 dead BGI.NZ quote -> $0.118 live RTO.NZ quote), upside for all three scenarios, weighted upside, entry-price discount narrative, sensitivity matrix read note, and sanity-check P/NTA multiple/trip reasons. The underlying scenario dollar values (bear $20,000 / base $687,125 / bull $2,500,000 equity value) are UNCHANGED - they do not depend on the market price.
A13: What to refresh after next filing/print | B13: FY2027 annual report (expected ~June 2027): update cash, NTA, burn rate, going-concern status, and status of the $200,000 shareholder loan (drawn? repaid? converted?) and of any RTO transaction. Re-verify RTO.NZ live price at that time - do not reuse this file's $0.118 without checking it is still current.
A14: Cell colour convention | B14: Gray-filled cells (light blue-gray, #dfe6e9) on the Shell Valuation sheet are INPUTS - edit these to see the model recalculate. White cells are FORMULAS derived from the inputs. Green cells are headline OUTPUTS (weighted intrinsic value, entry price). Red cell is the weighted upside/downside, flagged red because it is currently a large negative number.
A15: Known limitation | B15: Figures go stale. Cash, NTA, and burn rate are FY2026 year-end (31-Mar-2026) figures; by the time this is read, roughly 4-5 months of further burn (and the pending shareholder loan draw) will likely have occurred but are not reflected in the balance-sheet inputs above.
