Workbook

Sheet Inputs
A1: NZ Rural Land Company (NZL.NZ) — AFFO holding-period model at cost of equity
A2: Valuation date | B2: 2026-08-23
A3: Model | B3: 5yr attributable AFFO/dividend stream at CoE + exit P/B x NAV terminal (REIT row; NOT owner-FCF DCF)
A4: Current price (NZD, close 2026-08-21) | B4: 0.935
A5: Shares outstanding (m) | B5: 146.13853
A6: NAV per share FY2025 (NZD) | B6: 1.6094
A7: FY2025 AFFO attributable to NZL ($m) | B7: 7.932
A8: FY2025 AFFO attributable (cps) | B8: 5.43
A9: FY2025 consolidated AFFO ($m) — NOT valued | B9: 11.014
A10: Redeemable LP units, Roc 25% ($m) — in liabilities; NAV already net | B10: 79.563
A11: Bank debt drawn ($m) — NOT deducted (AFFO post-interest) | B11: 132.717
A12: Cash ($m) | B12: 5.918
A13: Gearing (%) | B13: 29.4
A14: Weighted debt term (yrs) — refi risk | B14: 1.45
A15: WALT (yrs) | B15: 11.6
A16: Hurdle rate (entry price) | B16: 0.15
A17: FY26 guidance $8.25-8.75m — WITHDRAWN Jul-2026 (Kiwi Crunch receivership, ~5.8% rent; +7.3% related-party rent at risk)

Sheet Summary
A1: Probability-weighted valuation
A3: Scenario | B3: Weight | C3: IV (NZD) | D3: Upside | E3: Implied P/B | F3: Entry price
A4: Bear | B4: 0.25 | C4: =Bear!B22 | D4: =Bear!B23 | E4: =Bear!B24 | F4: =Bear!B28
A5: Base | B5: 0.5 | C5: =Base!B22 | D5: =Base!B23 | E5: =Base!B24 | F5: =Base!B28
A6: Bull | B6: 0.25 | C6: =Bull!B22 | D6: =Bull!B23 | E6: =Bull!B24 | F6: =Bull!B28
A8: Weighted IV (NZD) | B8: =SUMPRODUCT(B4:B6,C4:C6)
A9: Weighted entry price (NZD) | B9: =SUMPRODUCT(B4:B6,F4:F6)
A10: Current price | B10: =Inputs!B4
A11: Weighted upside | B11: =B8/B10-1
A13: Sanity band: exit P/B must lie in 0.52-0.74 (NZL has never closed a FY above 0.74x book)

Sheet Base
A1: Base scenario
A3: Y1 AFFO/share (cps) | B3: 5.5
A4: Growth Y2-Y5 | C4: 0.045 | D4: 0.04 | E4: 0.035 | F4: 0.03
A5: Payout ratio | B5: 0.95
A6: NAV/share growth p.a. | B6: 0.01
A7: Exit P/B (constrained to 0.52-0.74 observed band) | B7: 0.63
A8: Cost of equity | B8: 0.0925
A9: NAV0 (NZD) | B9: =Inputs!B6
A11: Year | C11: FY2026 | D11: FY2027 | E11: FY2028 | F11: FY2029 | G11: FY2030
A12: AFFO/share (cps) | C12: =B3 | D12: =C12*(1+C4) | E12: =D12*(1+D4) | F12: =E12*(1+E4) | G12: =F12*(1+F4)
A13: Dividend/share (cps) | C13: =C12*$B$5 | D13: =D12*$B$5 | E13: =E12*$B$5 | F13: =F12*$B$5 | G13: =G12*$B$5
A14: NAV/share (NZD) | C14: =$B$9*(1+$B$6)^1 | D14: =$B$9*(1+$B$6)^2 | E14: =$B$9*(1+$B$6)^3 | F14: =$B$9*(1+$B$6)^4 | G14: =$B$9*(1+$B$6)^5
A15: Discount factor | C15: =1/(1+$B$8)^1 | D15: =1/(1+$B$8)^2 | E15: =1/(1+$B$8)^3 | F15: =1/(1+$B$8)^4 | G15: =1/(1+$B$8)^5
A16: PV dividend (cps) | C16: =C13*C15 | D16: =D13*D15 | E16: =E13*E15 | F16: =F13*F15 | G16: =G13*G15
A18: Sum PV dividends (cps) | B18: =SUM(C16:G16)
A19: Exit value = exit P/B x Y5 NAV (cps) | B19: =B7*G14*100
A20: PV exit (cps) | B20: =B19*G15
A21: Intrinsic value (cps) | B21: =B18+B20
A22: Intrinsic value (NZD/share) | B22: =B21/100
A23: Upside vs price | B23: =B22/Inputs!B4-1
A24: Implied P/B at IV | B24: =B22/Inputs!B6
A25: Implied trailing AFFO yield at IV | B25: =Inputs!B8/B21
A26: Terminal % of value | B26: =B20/B21
A28: Entry price at hurdle (NZD) | B28: =(SUMPRODUCT(C13:G13,1/(1+Inputs!B16)^{1,2,3,4,5})+B19/(1+Inputs!B16)^5)/100

Sheet Bull
A1: Bull scenario
A3: Y1 AFFO/share (cps) | B3: 5.82
A4: Growth Y2-Y5 | C4: 0.055 | D4: 0.05 | E4: 0.045 | F4: 0.04
A5: Payout ratio | B5: 0.95
A6: NAV/share growth p.a. | B6: 0.025
A7: Exit P/B (constrained to 0.52-0.74 observed band) | B7: 0.74
A8: Cost of equity | B8: 0.0875
A9: NAV0 (NZD) | B9: =Inputs!B6
A11: Year | C11: FY2026 | D11: FY2027 | E11: FY2028 | F11: FY2029 | G11: FY2030
A12: AFFO/share (cps) | C12: =B3 | D12: =C12*(1+C4) | E12: =D12*(1+D4) | F12: =E12*(1+E4) | G12: =F12*(1+F4)
A13: Dividend/share (cps) | C13: =C12*$B$5 | D13: =D12*$B$5 | E13: =E12*$B$5 | F13: =F12*$B$5 | G13: =G12*$B$5
A14: NAV/share (NZD) | C14: =$B$9*(1+$B$6)^1 | D14: =$B$9*(1+$B$6)^2 | E14: =$B$9*(1+$B$6)^3 | F14: =$B$9*(1+$B$6)^4 | G14: =$B$9*(1+$B$6)^5
A15: Discount factor | C15: =1/(1+$B$8)^1 | D15: =1/(1+$B$8)^2 | E15: =1/(1+$B$8)^3 | F15: =1/(1+$B$8)^4 | G15: =1/(1+$B$8)^5
A16: PV dividend (cps) | C16: =C13*C15 | D16: =D13*D15 | E16: =E13*E15 | F16: =F13*F15 | G16: =G13*G15
A18: Sum PV dividends (cps) | B18: =SUM(C16:G16)
A19: Exit value = exit P/B x Y5 NAV (cps) | B19: =B7*G14*100
A20: PV exit (cps) | B20: =B19*G15
A21: Intrinsic value (cps) | B21: =B18+B20
A22: Intrinsic value (NZD/share) | B22: =B21/100
A23: Upside vs price | B23: =B22/Inputs!B4-1
A24: Implied P/B at IV | B24: =B22/Inputs!B6
A25: Implied trailing AFFO yield at IV | B25: =Inputs!B8/B21
A26: Terminal % of value | B26: =B20/B21
A28: Entry price at hurdle (NZD) | B28: =(SUMPRODUCT(C13:G13,1/(1+Inputs!B16)^{1,2,3,4,5})+B19/(1+Inputs!B16)^5)/100

Sheet Bear
A1: Bear scenario
A3: Y1 AFFO/share (cps) | B3: 4.6
A4: Growth Y2-Y5 | C4: 0.02 | D4: 0.03 | E4: 0.03 | F4: 0.025
A5: Payout ratio | B5: 0.9
A6: NAV/share growth p.a. | B6: -0.015
A7: Exit P/B (constrained to 0.52-0.74 observed band) | B7: 0.52
A8: Cost of equity | B8: 0.105
A9: NAV0 (NZD) | B9: =Inputs!B6
A11: Year | C11: FY2026 | D11: FY2027 | E11: FY2028 | F11: FY2029 | G11: FY2030
A12: AFFO/share (cps) | C12: =B3 | D12: =C12*(1+C4) | E12: =D12*(1+D4) | F12: =E12*(1+E4) | G12: =F12*(1+F4)
A13: Dividend/share (cps) | C13: =C12*$B$5 | D13: =D12*$B$5 | E13: =E12*$B$5 | F13: =F12*$B$5 | G13: =G12*$B$5
A14: NAV/share (NZD) | C14: =$B$9*(1+$B$6)^1 | D14: =$B$9*(1+$B$6)^2 | E14: =$B$9*(1+$B$6)^3 | F14: =$B$9*(1+$B$6)^4 | G14: =$B$9*(1+$B$6)^5
A15: Discount factor | C15: =1/(1+$B$8)^1 | D15: =1/(1+$B$8)^2 | E15: =1/(1+$B$8)^3 | F15: =1/(1+$B$8)^4 | G15: =1/(1+$B$8)^5
A16: PV dividend (cps) | C16: =C13*C15 | D16: =D13*D15 | E16: =E13*E15 | F16: =F13*F15 | G16: =G13*G15
A18: Sum PV dividends (cps) | B18: =SUM(C16:G16)
A19: Exit value = exit P/B x Y5 NAV (cps) | B19: =B7*G14*100
A20: PV exit (cps) | B20: =B19*G15
A21: Intrinsic value (cps) | B21: =B18+B20
A22: Intrinsic value (NZD/share) | B22: =B21/100
A23: Upside vs price | B23: =B22/Inputs!B4-1
A24: Implied P/B at IV | B24: =B22/Inputs!B6
A25: Implied trailing AFFO yield at IV | B25: =Inputs!B8/B21
A26: Terminal % of value | B26: =B20/B21
A28: Entry price at hurdle (NZD) | B28: =(SUMPRODUCT(C13:G13,1/(1+Inputs!B16)^{1,2,3,4,5})+B19/(1+Inputs!B16)^5)/100

Sheet Sensitivity
A1: Base-case IV (NZD/share): cost of equity (rows) x exit P/B (cols)
B3: 0.52 | C3: 0.557 | D3: 0.63 | E3: 0.7 | F3: 0.74
A4: 0.0825 | B4: =(SUMPRODUCT(Base!$C$13:$G$13,1/(1+$A4)^{1,2,3,4,5})+B$3*Base!$G$14*100/(1+$A4)^5)/100 | C4: =(SUMPRODUCT(Base!$C$13:$G$13,1/(1+$A4)^{1,2,3,4,5})+C$3*Base!$G$14*100/(1+$A4)^5)/100 | D4: =(SUMPRODUCT(Base!$C$13:$G$13,1/(1+$A4)^{1,2,3,4,5})+D$3*Base!$G$14*100/(1+$A4)^5)/100 | E4: =(SUMPRODUCT(Base!$C$13:$G$13,1/(1+$A4)^{1,2,3,4,5})+E$3*Base!$G$14*100/(1+$A4)^5)/100 | F4: =(SUMPRODUCT(Base!$C$13:$G$13,1/(1+$A4)^{1,2,3,4,5})+F$3*Base!$G$14*100/(1+$A4)^5)/100
A5: 0.0875 | B5: =(SUMPRODUCT(Base!$C$13:$G$13,1/(1+$A5)^{1,2,3,4,5})+B$3*Base!$G$14*100/(1+$A5)^5)/100 | C5: =(SUMPRODUCT(Base!$C$13:$G$13,1/(1+$A5)^{1,2,3,4,5})+C$3*Base!$G$14*100/(1+$A5)^5)/100 | D5: =(SUMPRODUCT(Base!$C$13:$G$13,1/(1+$A5)^{1,2,3,4,5})+D$3*Base!$G$14*100/(1+$A5)^5)/100 | E5: =(SUMPRODUCT(Base!$C$13:$G$13,1/(1+$A5)^{1,2,3,4,5})+E$3*Base!$G$14*100/(1+$A5)^5)/100 | F5: =(SUMPRODUCT(Base!$C$13:$G$13,1/(1+$A5)^{1,2,3,4,5})+F$3*Base!$G$14*100/(1+$A5)^5)/100
A6: 0.0925 | B6: =(SUMPRODUCT(Base!$C$13:$G$13,1/(1+$A6)^{1,2,3,4,5})+B$3*Base!$G$14*100/(1+$A6)^5)/100 | C6: =(SUMPRODUCT(Base!$C$13:$G$13,1/(1+$A6)^{1,2,3,4,5})+C$3*Base!$G$14*100/(1+$A6)^5)/100 | D6: =(SUMPRODUCT(Base!$C$13:$G$13,1/(1+$A6)^{1,2,3,4,5})+D$3*Base!$G$14*100/(1+$A6)^5)/100 | E6: =(SUMPRODUCT(Base!$C$13:$G$13,1/(1+$A6)^{1,2,3,4,5})+E$3*Base!$G$14*100/(1+$A6)^5)/100 | F6: =(SUMPRODUCT(Base!$C$13:$G$13,1/(1+$A6)^{1,2,3,4,5})+F$3*Base!$G$14*100/(1+$A6)^5)/100
A7: 0.0975 | B7: =(SUMPRODUCT(Base!$C$13:$G$13,1/(1+$A7)^{1,2,3,4,5})+B$3*Base!$G$14*100/(1+$A7)^5)/100 | C7: =(SUMPRODUCT(Base!$C$13:$G$13,1/(1+$A7)^{1,2,3,4,5})+C$3*Base!$G$14*100/(1+$A7)^5)/100 | D7: =(SUMPRODUCT(Base!$C$13:$G$13,1/(1+$A7)^{1,2,3,4,5})+D$3*Base!$G$14*100/(1+$A7)^5)/100 | E7: =(SUMPRODUCT(Base!$C$13:$G$13,1/(1+$A7)^{1,2,3,4,5})+E$3*Base!$G$14*100/(1+$A7)^5)/100 | F7: =(SUMPRODUCT(Base!$C$13:$G$13,1/(1+$A7)^{1,2,3,4,5})+F$3*Base!$G$14*100/(1+$A7)^5)/100
A8: 0.1025 | B8: =(SUMPRODUCT(Base!$C$13:$G$13,1/(1+$A8)^{1,2,3,4,5})+B$3*Base!$G$14*100/(1+$A8)^5)/100 | C8: =(SUMPRODUCT(Base!$C$13:$G$13,1/(1+$A8)^{1,2,3,4,5})+C$3*Base!$G$14*100/(1+$A8)^5)/100 | D8: =(SUMPRODUCT(Base!$C$13:$G$13,1/(1+$A8)^{1,2,3,4,5})+D$3*Base!$G$14*100/(1+$A8)^5)/100 | E8: =(SUMPRODUCT(Base!$C$13:$G$13,1/(1+$A8)^{1,2,3,4,5})+E$3*Base!$G$14*100/(1+$A8)^5)/100 | F8: =(SUMPRODUCT(Base!$C$13:$G$13,1/(1+$A8)^{1,2,3,4,5})+F$3*Base!$G$14*100/(1+$A8)^5)/100

Sheet Historical PB
A1: NZL has NEVER closed a fiscal year above 0.74x book since Dec-2020 IPO — discount is structural
A3: FY | B3: FY-end price | C3: NAV/share | D3: P/B
A4: FY2021 (Jun) | B4: 1.034 | C4: 1.397 | D4: 0.74
A5: FY2022 (Jun) | B5: 1.006 | C5: 1.656 | D5: 0.607
A6: FY2022-6moStub | B6: 1.055 | C6: 1.652 | D6: 0.639
A7: FY2023 | B7: 0.94 | C7: 1.602 | D7: 0.587
A8: FY2024 | B8: 0.9 | C8: 1.617 | D8: 0.557
A9: FY2025 | B9: 1.04 | C9: 1.609 | D9: 0.646
A10: Current (2026-08-21) | B10: 0.935 | C10: 1.6094 | D10: 0.581
A11: Mean 0.63 / Min 0.557 / Max 0.740 — exit P/B assumptions: bear 0.52, base 0.63, bull 0.74
