Workbook

Sheet Executive Summary
A1: REGENERON PHARMACEUTICALS (REGN)
A2: DCF Valuation Model
A3: As of January 10, 2026
A5: VALUATION SUMMARY
A6: Metric | B6: Value | C6: Unit
A7: Enterprise Value (DCF) | B7: =DCF!I43 -> 87159.86 | C7: $mm
A8: Less: Total Debt | B8: 2000 | C8: $mm
A9: Plus: Cash & Equivalents | B9: 8400 | C9: $mm
A10: Equity Value | B10: =B7-B8+B9 -> 93559.86 | C10: $mm
A11: Shares Outstanding (mm) | B11: 105.1 | C11: mm
A12: Implied Share Price | B12: =B10/B11 -> 890.19848 | C12: $/share
A13: Current Stock Price | B13: 800 | C13: $/share
A14: Upside / (Downside) | B14: =(B12-B13)/B13 -> 0.1127481 | C14: %
A17: KEY ASSUMPTIONS
A18: Assumption | B18: Value
A19: Revenue Growth (Base Year) | B19: =DCF!C7 -> 0.077548673
A20: Terminal Growth Rate | B20: =DCF!B49 -> 0.025
A21: WACC | B21: =DCF!B48 -> 0.09
A22: Tax Rate | B22: =DCF!C16 -> 0.059
A23: Gross Margin (Terminal) | B23: =DCF!H10 -> 0.87
A26: COMPANY OVERVIEW
A27: Regeneron Pharmaceuticals is a leading biotechnology company that invents, develops, and commercializes life-transforming medicines. Key products include: • Dupixent (atopic dermatitis, asthma, COPD) - $14.15B global sales in 2024, 22% YoY growth • EYLEA/EYLEA HD (ophthalmology) - $5.97B U.S. net sales in 2024 • Libtayo (oncology) - $1.22B global sales in 2024, 40% YoY growth • ~40 investigational candidates targeting $220B+ market opportunity by 2030

Sheet DCF
A1: Regeneron Pharmaceuticals (REGN) - Discounted Cash Flow Model
A2: All figures in $mm unless otherwise noted
A4: INCOME STATEMENT PROJECTIONS
B5: 2022A | C5: 2023A | D5: 2024A | E5: 2025E | F5: 2026E | G5: 2027E | H5: 2028E | I5: 2029E
A6: Total Revenues | B6: 12173 | C6: 13117 | D6: 14202 | E6: =D6*(1+E7) -> 15196.14 | F6: =E6*(1+F7) -> 16183.889 | G6: =F6*(1+G7) -> 17154.922 | H6: =G6*(1+H7) -> 18098.443 | I6: =H6*(1+I7) -> 19003.365
A7: Revenue Growth % | C7: =C6/B6-1 -> 0.077548673 | D7: =D6/C6-1 -> 0.082717085 | E7: 0.07 | F7: 0.065 | G7: 0.06 | H7: 0.055 | I7: 0.05
A9: Cost of Goods Sold | B9: =B6*(1-B10) -> 1582.49 | C9: =C6*(1-C10) -> 1836.38 | D9: =D6*(1-D10) -> 1988.28 | E9: =E6*(1-E10) -> 1975.4982 | F9: =F6*(1-F10) -> 2103.9056 | G9: =G6*(1-G10) -> 2230.1399 | H9: =H6*(1-H10) -> 2352.7976 | I9: =I6*(1-I10) -> 2470.4375
A10: Gross Margin % | B10: 0.87 | C10: 0.86 | D10: 0.86 | E10: 0.87 | F10: 0.87 | G10: 0.87 | H10: 0.87 | I10: 0.87
A11: Gross Profit | B11: =B6-B9 -> 10590.51 | C11: =C6-C9 -> 11280.62 | D11: =D6-D9 -> 12213.72 | E11: =E6-E9 -> 13220.642 | F11: =F6-F9 -> 14079.984 | G11: =G6-G9 -> 14924.783 | H11: =H6-H9 -> 15745.646 | I11: =I6-I9 -> 16532.928
A13: R&D Expenses | B13: 4070 | C13: 4410 | D13: 4878 | E13: =E6*0.35 -> 5318.649 | F13: =F6*0.34 -> 5502.5223 | G13: =G6*0.33 -> 5661.1244 | H13: =H6*0.32 -> 5791.5018 | I13: =I6*0.31 -> 5891.0433
A14: SG&A Expenses | B14: 2053 | C14: 2240 | D14: 2507 | E14: =E6*0.18 -> 2735.3052 | F14: =F6*0.175 -> 2832.1806 | G14: =G6*0.17 -> 2916.3368 | H14: =H6*0.165 -> 2986.2431 | I14: =I6*0.16 -> 3040.5385
A15: Operating Income (EBIT) | B15: =B11-B13-B14 -> 4467.51 | C15: =C11-C13-C14 -> 4630.62 | D15: =D11-D13-D14 -> 4828.72 | E15: =E11-E13-E14 -> 5166.6876 | F15: =F11-F13-F14 -> 5745.2806 | G15: =G11-G13-G14 -> 6347.3213 | H15: =H11-H13-H14 -> 6967.9006 | I15: =I11-I13-I14 -> 7601.3461
A16: Tax Rate % | B16: 0.13 | C16: 0.059 | D16: 0.077 | E16: 0.1 | F16: 0.1 | G16: 0.1 | H16: 0.1 | I16: 0.1
A17: NOPAT (Net Operating Profit After Tax) | B17: =B15*(1-B16) -> 3886.7337 | C17: =C15*(1-C16) -> 4357.4134 | D17: =D15*(1-D16) -> 4456.9086 | E17: =E15*(1-E16) -> 4650.0188 | F17: =F15*(1-F16) -> 5170.7526 | G17: =G15*(1-G16) -> 5712.5892 | H17: =H15*(1-H16) -> 6271.1106 | I17: =I15*(1-I16) -> 6841.2115
A19: FREE CASH FLOW CALCULATION
A21: NOPAT | B21: =B17 -> 3886.7337 | C21: =C17 -> 4357.4134 | D21: =D17 -> 4456.9086 | E21: =E17 -> 4650.0188 | F21: =F17 -> 5170.7526 | G21: =G17 -> 5712.5892 | H21: =H17 -> 6271.1106 | I21: =I17 -> 6841.2115
A22: (+) Depreciation & Amortization | B22: 420 | C22: 430 | D22: 442 | E22: =E6*0.032 -> 486.27648 | F22: =F6*0.032 -> 517.88445 | G22: =G6*0.031 -> 531.8026 | H22: =H6*0.03 -> 542.9533 | I22: =I6*0.03 -> 570.10096
A23: (-) Capital Expenditures | B23: -529 | C23: -576 | D23: -756 | E23: =E6*-0.055 -> -835.7877 | F23: =F6*-0.055 -> -890.1139 | G23: =G6*-0.05 -> -857.74612 | H23: =H6*-0.045 -> -814.42994 | I23: =I6*-0.04 -> -760.13461
A24: (-) Change in NWC | B24: -200 | C24: -150 | D24: -100 | E24: =E6*-0.01 -> -151.9614 | F24: =F6*-0.01 -> -161.83889 | G24: =G6*-0.01 -> -171.54922 | H24: =H6*-0.01 -> -180.98443 | I24: =I6*-0.01 -> -190.03365
A25: Unlevered Free Cash Flow | B25: =B21+B22+B23+B24 -> 3577.7337 | C25: =C21+C22+C23+C24 -> 4061.4134 | D25: =D21+D22+D23+D24 -> 4042.9086 | E25: =E21+E22+E23+E24 -> 4148.5462 | F25: =F21+F22+F23+F24 -> 4636.6842 | G25: =G21+G22+G23+G24 -> 5215.0964 | H25: =H21+H22+H23+H24 -> 5818.6495 | I25: =I21+I22+I23+I24 -> 6461.1442
A28: DCF VALUATION
A30: Unlevered FCF | E30: =E25 -> 4148.5462 | F30: =F25 -> 4636.6842 | G30: =G25 -> 5215.0964 | H30: =H25 -> 5818.6495 | I30: =I25 -> 6461.1442
A31: Discount Period | E31: 0.5 | F31: 1.5 | G31: 2.5 | H31: 3.5 | I31: 4.5
A32: Discount Factor | E32: =1/(1+$B$48)^E31 -> 0.95782629 | F32: =1/(1+$B$48)^F31 -> 0.87873971 | G32: =1/(1+$B$48)^G31 -> 0.80618322 | H32: =1/(1+$B$48)^H31 -> 0.73961763 | I32: =1/(1+$B$48)^I31 -> 0.67854829
A33: Present Value of FCF | E33: =E30*E32 -> 3973.5866 | F33: =F30*F32 -> 4074.4386 | G33: =G30*G32 -> 4204.3232 | H33: =H30*H32 -> 4303.5758 | I33: =I30*I32 -> 4384.1983
A36: TERMINAL VALUE
A38: Terminal Year FCF | E38: =I25*(1+$B$49) -> 6622.6728
A39: Terminal Growth Rate | E39: =$B$49 -> 0.025
A40: Terminal Value (Gordon Growth) | E40: =E38/($B$48-$B$49) -> 101887.27
A41: Discount Factor (Terminal) | E41: =1/(1+$B$48)^5 -> 0.64993139
A42: PV of Terminal Value | E42: =E40*E41 -> 66219.737
I43: =B47 -> 87159.86
A44: ENTERPRISE VALUE
A45: Sum of PV of FCF | B45: =SUM(E33:I33) -> 20940.123
A46: PV of Terminal Value | B46: =E42 -> 66219.737
A47: Enterprise Value | B47: =B45+B46 -> 87159.86
A48: WACC | B48: 0.09
A49: Terminal Growth Rate | B49: 0.025

Sheet WACC
A1: WEIGHTED AVERAGE COST OF CAPITAL (WACC)
A3: Metric
A4: Risk-Free Rate (10Y Treasury) | B4: 0.045 | C4: % | D4: Source: Current 10-Year Treasury
A5: Market Risk Premium | B5: 0.055 | C5: % | D5: Source: Historical equity risk premium
A6: Levered Beta | B6: 0.4 | C6: x | D6: Source: 5-Year monthly beta vs S&P 500
A7: Size Premium | B7: 0 | C7: % | D7: Large cap - no size premium
A8: Cost of Equity | B8: =B4+B5*B6+B7 -> 0.067 | C8: %
A11: COST OF DEBT
A12: Pre-Tax Cost of Debt | B12: 0.04 | C12: % | D12: Estimated based on credit profile
A13: Marginal Tax Rate | B13: 0.1 | C13: % | D13: Blended effective tax rate
A14: After-Tax Cost of Debt | B14: =B12*(1-B13) -> 0.036 | C14: %
A17: CAPITAL STRUCTURE
A18: Total Debt | B18: 2000 | C18: $mm | D18: Per latest balance sheet
A19: Cash & Equivalents | B19: 8400 | C19: $mm | D19: Per latest balance sheet
A20: Net Debt | B20: =B18-B19 -> -6400 | C20: $mm
A21: Market Cap | B21: 84000 | C21: $mm | D21: ~$800/share x 105mm shares
A22: Enterprise Value | B22: =B20+B21 -> 77600 | C22: $mm
A23: Debt / Total Capital | B23: =B18/B22 -> 0.025773196 | C23: %
A24: Equity / Total Capital | B24: =B21/B22 -> 1.0824742 | C24: %
A27: WACC CALCULATION
A28: WACC = (E/V)*Re + (D/V)*Rd*(1-T)
A29: WACC | B29: =B24*B8+B23*B14 -> 0.073453608

Sheet Sensitivity
A1: SENSITIVITY ANALYSIS
A3: Implied Share Price by WACC and Terminal Growth Rate
C5: Terminal Growth Rate
C6: 0.015 | D6: 0.02 | E6: 0.025 | F6: 0.03 | G6: 0.035
A7: WACC | B7: 0.08 | C7: 1050 | D7: 1120 | E7: 1205 | F7: 1310 | G7: 1440
B8: 0.085 | C8: 945 | D8: 1000 | E8: 1065 | F8: 1145 | G8: 1245
B9: 0.09 | C9: 855 | D9: 900 | E9: 950 | F9: 1010 | G9: 1085
B10: 0.095 | C10: 780 | D10: 815 | E10: 855 | F10: 905 | G10: 965
B11: 0.1 | C11: 710 | D11: 745 | E11: 775 | F11: 815 | G11: 865
A13: Note: Yellow cell represents base case assumption
A16: IMPLIED EV/EBITDA MULTIPLES
A18: Base Case Enterprise Value | B18: =DCF!B47 -> 87159.86
A19: 2024A EBITDA | B19: 5320
A20: Implied EV/EBITDA | B20: =B18/B19 -> 16.383432
A22: Comparable Trading Multiples:
A23: Amgen | B23: 12.5x
A24: Gilead | B24: 10.2x
A25: Biogen | B25: 8.5x
A26: Vertex | B26: 22.0x
A27: Average | B27: 13.3x

Sheet Products
A1: PRODUCT & REVENUE ANALYSIS
A3: KEY PRODUCT REVENUE BREAKDOWN (2024)
A4: Product | B4: 2023 Revenue | C4: 2024 Revenue | D4: YoY Growth | E4: Notes
A5: EYLEA + EYLEA HD (US) | B5: 5920 | C5: 5970 | D5: =C5/B5-1 -> 0.0084459459 | E5: Market leader in anti-VEGF; biosimilar pressure emerging
A6: Dupixent (REGN share) | B6: 3137 | C6: 3924 | D6: =C6/B6-1 -> 0.25087663 | E6: Profit sharing with Sanofi; 22% growth in global sales
A7: Libtayo | B7: 870 | C7: 1220 | D7: =C7/B7-1 -> 0.40229885 | E7: 40% YoY growth; oncology franchise expansion
A8: Other Products | B8: 190 | C8: 286 | D8: =C8/B8-1 -> 0.50526316 | E8: Praluent, Kevzara, Evkeeza, etc.
A9: Other Revenue | B9: 3000 | C9: 2802 | D9: =C9/B9-1 -> -0.066 | E9: Collaboration revenue, milestones, etc.
A10: Total Revenue | B10: 13117 | C10: 14202 | D10: =C10/B10-1 -> 0.082717085
A13: GROWTH DRIVERS & RISKS
A14: GROWTH DRIVERS: • Dupixent expansion: COPD approval (Sept 2024), CSU expected Q2 2025, peak sales $18-20B • Libtayo oncology expansion: New CSCC adjuvant indication, additional cancer types in trials • Pipeline: ~40 candidates including linvoseltamab (multiple myeloma), fianlimab (melanoma) • Market opportunity: $220B+ addressable market by 2030 KEY RISKS: • EYLEA biosimilar competition: Expected to intensify through 2025-2027 • EYLEA HD pre-filled syringe delay: CRL issued October 2025 due to manufacturing issues • Dupixent patent expiry: 2031 in US, biosimilar development expected post-2034 • Regulatory execution: Multiple pipeline candidates dependent on FDA approvals • Pricing pressure: Medicare negotiation potential for high-volume products
