Workbook

Sheet Inputs
A1: Scottish Mortgage Investment Trust plc (SMT.L) - NAV + exit discount model
A2: Per-share figures in pence (GBp); money in GBP millions
A3: Current price (GBp) | B3: 1636.5
A4: NAV per share cum fair (p), 8 Oct 2026 | B4: 1776.31
A5: NAV per share cum par (p), 8 Oct 2026 | B5: 1737.94
A6: Shares outstanding (m), 1 Oct 2026 | B6: 1046.1919
A7: FY2026 dividend per share (p) | B7: 4.57
A8: Hurdle rate | B8: 0.15
A9: Horizon (years) | B9: 5
A10: Discount to NAV at fair today | B10: =B3/B4-1
A11: Discount to NAV at par today | B11: =B3/B5-1

Sheet Base
A1: Base scenario
A2: NAV total return p.a. (%) | B2: 9
A3: Exit discount to NAV (%) | B3: -8
A4: Cost of equity (%) | B4: 10
A5: Dividend growth p.a. (%) | B5: 4
A7: Year | B7: 1 | C7: 2 | D7: 3 | E7: 4 | F7: 5
A8: NAV per share (p) | B8: =Inputs!$B$4*(1+$B$2/100)-B9 | C8: =B8*(1+$B$2/100)-C9 | D8: =C8*(1+$B$2/100)-D9 | E8: =D8*(1+$B$2/100)-E9 | F8: =E8*(1+$B$2/100)-F9
A9: Dividend per share (p) | B9: =Inputs!$B$7*(1+$B$5/100) | C9: =B9*(1+$B$5/100) | D9: =C9*(1+$B$5/100) | E9: =D9*(1+$B$5/100) | F9: =E9*(1+$B$5/100)
A10: Discount factor @ CoE | B10: =1/(1+$B$4/100)^B7 | C10: =1/(1+$B$4/100)^C7 | D10: =1/(1+$B$4/100)^D7 | E10: =1/(1+$B$4/100)^E7 | F10: =1/(1+$B$4/100)^F7
A11: PV dividend @ CoE | B11: =B9*B10 | C11: =C9*C10 | D11: =D9*D10 | E11: =E9*E10 | F11: =F9*F10
A12: Discount factor @ hurdle | B12: =1/(1+Inputs!$B$8)^B7 | C12: =1/(1+Inputs!$B$8)^C7 | D12: =1/(1+Inputs!$B$8)^D7 | E12: =1/(1+Inputs!$B$8)^E7 | F12: =1/(1+Inputs!$B$8)^F7
A13: PV dividend @ hurdle | B13: =B9*B12 | C13: =C9*C12 | D13: =D9*D12 | E13: =E9*E12 | F13: =F9*F12
A15: Year-5 exit price = NAV5 x (1 + exit discount) | B15: =F8*(1+$B$3/100)
A16: PV exit @ CoE | B16: =B15*F10
A17: PV dividends @ CoE | B17: =SUM(B11:F11)
A18: Intrinsic value (p) | B18: =B16+B17
A19: Upside vs price | B19: =B18/Inputs!$B$3-1
A20: Implied P/NAV (fair) today | B20: =B18/Inputs!$B$4-1
A21: Exit value share of IV | B21: =B16/B18
A23: PV exit @ hurdle | B23: =B15*F12
A24: PV dividends @ hurdle | B24: =SUM(B13:F13)
A25: Entry price @ hurdle (p) | B25: =B23+B24
A26: Entry discount from current | B26: =B25/Inputs!$B$3-1

Sheet Bull
A1: Bull scenario
A2: NAV total return p.a. (%) | B2: 15
A3: Exit discount to NAV (%) | B3: 0
A4: Cost of equity (%) | B4: 10
A5: Dividend growth p.a. (%) | B5: 5
A7: Year | B7: 1 | C7: 2 | D7: 3 | E7: 4 | F7: 5
A8: NAV per share (p) | B8: =Inputs!$B$4*(1+$B$2/100)-B9 | C8: =B8*(1+$B$2/100)-C9 | D8: =C8*(1+$B$2/100)-D9 | E8: =D8*(1+$B$2/100)-E9 | F8: =E8*(1+$B$2/100)-F9
A9: Dividend per share (p) | B9: =Inputs!$B$7*(1+$B$5/100) | C9: =B9*(1+$B$5/100) | D9: =C9*(1+$B$5/100) | E9: =D9*(1+$B$5/100) | F9: =E9*(1+$B$5/100)
A10: Discount factor @ CoE | B10: =1/(1+$B$4/100)^B7 | C10: =1/(1+$B$4/100)^C7 | D10: =1/(1+$B$4/100)^D7 | E10: =1/(1+$B$4/100)^E7 | F10: =1/(1+$B$4/100)^F7
A11: PV dividend @ CoE | B11: =B9*B10 | C11: =C9*C10 | D11: =D9*D10 | E11: =E9*E10 | F11: =F9*F10
A12: Discount factor @ hurdle | B12: =1/(1+Inputs!$B$8)^B7 | C12: =1/(1+Inputs!$B$8)^C7 | D12: =1/(1+Inputs!$B$8)^D7 | E12: =1/(1+Inputs!$B$8)^E7 | F12: =1/(1+Inputs!$B$8)^F7
A13: PV dividend @ hurdle | B13: =B9*B12 | C13: =C9*C12 | D13: =D9*D12 | E13: =E9*E12 | F13: =F9*F12
A15: Year-5 exit price = NAV5 x (1 + exit discount) | B15: =F8*(1+$B$3/100)
A16: PV exit @ CoE | B16: =B15*F10
A17: PV dividends @ CoE | B17: =SUM(B11:F11)
A18: Intrinsic value (p) | B18: =B16+B17
A19: Upside vs price | B19: =B18/Inputs!$B$3-1
A20: Implied P/NAV (fair) today | B20: =B18/Inputs!$B$4-1
A21: Exit value share of IV | B21: =B16/B18
A23: PV exit @ hurdle | B23: =B15*F12
A24: PV dividends @ hurdle | B24: =SUM(B13:F13)
A25: Entry price @ hurdle (p) | B25: =B23+B24
A26: Entry discount from current | B26: =B25/Inputs!$B$3-1

Sheet Bear
A1: Bear scenario
A2: NAV total return p.a. (%) | B2: 0
A3: Exit discount to NAV (%) | B3: -15
A4: Cost of equity (%) | B4: 10
A5: Dividend growth p.a. (%) | B5: 2
A7: Year | B7: 1 | C7: 2 | D7: 3 | E7: 4 | F7: 5
A8: NAV per share (p) | B8: =Inputs!$B$4*(1+$B$2/100)-B9 | C8: =B8*(1+$B$2/100)-C9 | D8: =C8*(1+$B$2/100)-D9 | E8: =D8*(1+$B$2/100)-E9 | F8: =E8*(1+$B$2/100)-F9
A9: Dividend per share (p) | B9: =Inputs!$B$7*(1+$B$5/100) | C9: =B9*(1+$B$5/100) | D9: =C9*(1+$B$5/100) | E9: =D9*(1+$B$5/100) | F9: =E9*(1+$B$5/100)
A10: Discount factor @ CoE | B10: =1/(1+$B$4/100)^B7 | C10: =1/(1+$B$4/100)^C7 | D10: =1/(1+$B$4/100)^D7 | E10: =1/(1+$B$4/100)^E7 | F10: =1/(1+$B$4/100)^F7
A11: PV dividend @ CoE | B11: =B9*B10 | C11: =C9*C10 | D11: =D9*D10 | E11: =E9*E10 | F11: =F9*F10
A12: Discount factor @ hurdle | B12: =1/(1+Inputs!$B$8)^B7 | C12: =1/(1+Inputs!$B$8)^C7 | D12: =1/(1+Inputs!$B$8)^D7 | E12: =1/(1+Inputs!$B$8)^E7 | F12: =1/(1+Inputs!$B$8)^F7
A13: PV dividend @ hurdle | B13: =B9*B12 | C13: =C9*C12 | D13: =D9*D12 | E13: =E9*E12 | F13: =F9*F12
A15: Year-5 exit price = NAV5 x (1 + exit discount) | B15: =F8*(1+$B$3/100)
A16: PV exit @ CoE | B16: =B15*F10
A17: PV dividends @ CoE | B17: =SUM(B11:F11)
A18: Intrinsic value (p) | B18: =B16+B17
A19: Upside vs price | B19: =B18/Inputs!$B$3-1
A20: Implied P/NAV (fair) today | B20: =B18/Inputs!$B$4-1
A21: Exit value share of IV | B21: =B16/B18
A23: PV exit @ hurdle | B23: =B15*F12
A24: PV dividends @ hurdle | B24: =SUM(B13:F13)
A25: Entry price @ hurdle (p) | B25: =B23+B24
A26: Entry discount from current | B26: =B25/Inputs!$B$3-1

Sheet Summary
A1: Scenario | B1: Weight | C1: Intrinsic value (p) | D1: Entry price (p)
A2: bear | B2: 0.25 | C2: =Bear!B18 | D2: =Bear!B25
A3: base | B3: 0.5 | C3: =Base!B18 | D3: =Base!B25
A4: bull | B4: 0.25 | C4: =Bull!B18 | D4: =Bull!B25
A5: Probability-weighted | B5: =SUM(B2:B4) | C5: =SUMPRODUCT(B2:B4,C2:C4) | D5: =SUMPRODUCT(B2:B4,D2:D4)
A6: Weighted upside vs price | C6: =C5/Inputs!B3-1

Sheet RequiredReturn
A1: Required return (%) | B1: Value per share (p), base paths
A2: 8 | B2: =Base!B9/(1+$A2/100)^1+Base!C9/(1+$A2/100)^2+Base!D9/(1+$A2/100)^3+Base!E9/(1+$A2/100)^4+Base!F9/(1+$A2/100)^5+Base!B15/(1+$A2/100)^5
A3: 9 | B3: =Base!B9/(1+$A3/100)^1+Base!C9/(1+$A3/100)^2+Base!D9/(1+$A3/100)^3+Base!E9/(1+$A3/100)^4+Base!F9/(1+$A3/100)^5+Base!B15/(1+$A3/100)^5
A4: 10 | B4: =Base!B9/(1+$A4/100)^1+Base!C9/(1+$A4/100)^2+Base!D9/(1+$A4/100)^3+Base!E9/(1+$A4/100)^4+Base!F9/(1+$A4/100)^5+Base!B15/(1+$A4/100)^5
A5: 12 | B5: =Base!B9/(1+$A5/100)^1+Base!C9/(1+$A5/100)^2+Base!D9/(1+$A5/100)^3+Base!E9/(1+$A5/100)^4+Base!F9/(1+$A5/100)^5+Base!B15/(1+$A5/100)^5
A6: 15 | B6: =Base!B9/(1+$A6/100)^1+Base!C9/(1+$A6/100)^2+Base!D9/(1+$A6/100)^3+Base!E9/(1+$A6/100)^4+Base!F9/(1+$A6/100)^5+Base!B15/(1+$A6/100)^5

Sheet Sensitivity
A1: Intrinsic value (p) at base CoE: rows = exit discount %, cols = NAV total return % p.a.
A2: exit \ TR | B2: 3 | C2: 6 | D2: 9 | E2: 12 | F2: 15
A3: -15 | B3: =B$10*(1+$A3/100)/(1+Base!$B$4/100)^5+B$11 | C3: =C$10*(1+$A3/100)/(1+Base!$B$4/100)^5+C$11 | D3: =D$10*(1+$A3/100)/(1+Base!$B$4/100)^5+D$11 | E3: =E$10*(1+$A3/100)/(1+Base!$B$4/100)^5+E$11 | F3: =F$10*(1+$A3/100)/(1+Base!$B$4/100)^5+F$11
A4: -10 | B4: =B$10*(1+$A4/100)/(1+Base!$B$4/100)^5+B$11 | C4: =C$10*(1+$A4/100)/(1+Base!$B$4/100)^5+C$11 | D4: =D$10*(1+$A4/100)/(1+Base!$B$4/100)^5+D$11 | E4: =E$10*(1+$A4/100)/(1+Base!$B$4/100)^5+E$11 | F4: =F$10*(1+$A4/100)/(1+Base!$B$4/100)^5+F$11
A5: -8 | B5: =B$10*(1+$A5/100)/(1+Base!$B$4/100)^5+B$11 | C5: =C$10*(1+$A5/100)/(1+Base!$B$4/100)^5+C$11 | D5: =D$10*(1+$A5/100)/(1+Base!$B$4/100)^5+D$11 | E5: =E$10*(1+$A5/100)/(1+Base!$B$4/100)^5+E$11 | F5: =F$10*(1+$A5/100)/(1+Base!$B$4/100)^5+F$11
A6: -5 | B6: =B$10*(1+$A6/100)/(1+Base!$B$4/100)^5+B$11 | C6: =C$10*(1+$A6/100)/(1+Base!$B$4/100)^5+C$11 | D6: =D$10*(1+$A6/100)/(1+Base!$B$4/100)^5+D$11 | E6: =E$10*(1+$A6/100)/(1+Base!$B$4/100)^5+E$11 | F6: =F$10*(1+$A6/100)/(1+Base!$B$4/100)^5+F$11
A7: 0 | B7: =B$10*(1+$A7/100)/(1+Base!$B$4/100)^5+B$11 | C7: =C$10*(1+$A7/100)/(1+Base!$B$4/100)^5+C$11 | D7: =D$10*(1+$A7/100)/(1+Base!$B$4/100)^5+D$11 | E7: =E$10*(1+$A7/100)/(1+Base!$B$4/100)^5+E$11 | F7: =F$10*(1+$A7/100)/(1+Base!$B$4/100)^5+F$11
A10: helper: NAV5 by TR | B10: =Inputs!$B$4*(1+B$2/100)^5-Base!B9*(1+B$2/100)^4-Base!C9*(1+B$2/100)^3-Base!D9*(1+B$2/100)^2-Base!E9*(1+B$2/100)^1-Base!F9*(1+B$2/100)^0 | C10: =Inputs!$B$4*(1+C$2/100)^5-Base!B9*(1+C$2/100)^4-Base!C9*(1+C$2/100)^3-Base!D9*(1+C$2/100)^2-Base!E9*(1+C$2/100)^1-Base!F9*(1+C$2/100)^0 | D10: =Inputs!$B$4*(1+D$2/100)^5-Base!B9*(1+D$2/100)^4-Base!C9*(1+D$2/100)^3-Base!D9*(1+D$2/100)^2-Base!E9*(1+D$2/100)^1-Base!F9*(1+D$2/100)^0 | E10: =Inputs!$B$4*(1+E$2/100)^5-Base!B9*(1+E$2/100)^4-Base!C9*(1+E$2/100)^3-Base!D9*(1+E$2/100)^2-Base!E9*(1+E$2/100)^1-Base!F9*(1+E$2/100)^0 | F10: =Inputs!$B$4*(1+F$2/100)^5-Base!B9*(1+F$2/100)^4-Base!C9*(1+F$2/100)^3-Base!D9*(1+F$2/100)^2-Base!E9*(1+F$2/100)^1-Base!F9*(1+F$2/100)^0
A11: helper: PV dividends @ CoE (base path) | B11: =Base!$B$17 | C11: =Base!$B$17 | D11: =Base!$B$17 | E11: =Base!$B$17 | F11: =Base!$B$17
