Workbook

Sheet Model_Info
A1: KKS.F DCF model — Kaspi.kz, Frankfurt EUR line
A2: Version | B2: 1.0 fresh build 2026-08-26 (no prior DCF)
A3: Built by | B3: dcf-analyst agent (Claude, Fable 5) on 2026-08-26 at the research orchestrator's request
A4: Model | B4: Discounted distributable earnings at KZT cost of equity (dividend-discount form of residual income). Kaspi is a deposit-funded lender: deposits are operating funding, OCF/FCF meaningless, net debt = 0.
A5: Why not owner-FCF | B5: FY2024 OCF is a loan/deposit working-capital artefact; FY2025 FCF NULL. SKILL.md bank row.
A6: Currency layer | B6: Flows and discount rate in KZT; per-share KZT / EURKZT spot 534.26 (Yahoo, 2026-08-26) = EUR. No separate FX haircut: the KZT rate already embeds expected depreciation.
A7: Price | B7: EUR 92.80, Yahoo KKS.F regular close 2026-08-25 19:55 UTC; Nasdaq KSPI USD 108.75 (1 ADS = 1 share)
A8: Balance sheet | B8: 30-Jun-2026 interim: equity attributable KZT 2,639,116m; goodwill 459,118m; deposits 8,132,007m; loans 7,439,812m
A9: Shares | B9: 190.73m Q2-2026 weighted diluted; 190.03m period-end outstanding. Held flat (SBC inside IFRS NI; buybacks absorb exercises).
A10: Base earnings | B10: FY2025 attributable net income KZT 1,073,177m (NCI -5,470m already removed; EPS 5,631). TTM Q2-2026 1,069,921m.
A11: Guidance | B11: FY2026 reiterated 10-Aug-2026: adj. EBITDA ~+5%, GMV ~+20%, TPV ~+15%, avg net loans ~+15%; H1-2026 attributable NI -0.6%
A12: Tax | B12: Bank rate 20% -> 25% from 2026 (H1-2026 effective 21.4%); absorbed in the FY2026 +1% base growth
A13: NCI | B13: Charged once: flows are attributable; no NCI stock deducted (Hepsiburada 86.74% owned)
... A20: Colour legend | B20: Blue = hardcoded input; yellow fill = key lever; black = formula; green = cross-sheet link

Sheet Actuals
A1: Metric | B1: FY2020 | C1: FY2021 | D1: FY2022 | E1: FY2023 | F1: FY2024 | G1: FY2025 | H1: H1-2025 | I1: H1-2026 | J1: Source
A2: Revenue (KZT m) | B2: 641437 | C2: 884822 | D2: 1270592 | E2: 1913490 | F2: 2532156 | G2: 4046074 | J2: Metrics.csv; FY2025 includes Hepsiburada from Jan-2025
A3: Net income attributable (KZT m) | B3: 260964 | C3: 431914 | D3: 585026 | E3: 841351 | F3: 1039739 | G3: 1073177 | H3: 509383 | I3: 506127 | J3: Metrics.csv / interim H1-2026 p.3
A4: Net income total incl. NCI (KZT m) | F4: 1056834 | G4: 1067707 | H4: 512678 | I4: 510796 | J4: FY2025 presentation p.44; interim
A5: EPS diluted (KZT) | B5: 1361 | C5: 2247 | D5: 3051 | E5: 4431 | F5: 5477 | G5: 5631 | H5: 2664 | I5: 2654 | J5: Metrics.csv
A6: Equity attributable (KZT m) | B6: 391118 | C6: 499727 | D6: 819165 | E6: 1078123 | F6: 1517224 | G6: 2491843 | H6: 1954446 | I6: 2639116 | J6: balance sheets
A7: Customer deposits (KZT m) | B7: 2150581 | C7: 2763043 | D7: 4000690 | E7: 5441456 | F7: 6561950 | G7: 7531286 | H7: 6696338 | I7: 8132007 | J7: kpis table
A8: Loans to customers (KZT m) | B8: 1404554 | C8: 2430737 | D8: 3154810 | E8: 4235957 | F8: 5746600 | G8: 7172162 | I8: 7439812 | J8: kpis table
A9: Dividends paid (KZT m) | B9: 175368 | C9: 340362 | D9: 210102 | E9: 560132 | F9: 646056 | G9: 0 | H9: 0 | I9: 323201 | J9: cash flow statements
A10: Share buybacks (KZT m) | D10: 63672 | E10: 60703 | F10: 2852 | G10: 50274 | I10: 28368 | J10: kpis / interim note 14
A11: Diluted wavg shares (m) | B11: 193.72 | C11: 194.34 | D11: 193.99 | E11: 192.06 | F11: 191.43 | G11: 191.9 | H11: 191.23 | I11: 190.73 | J11: Metrics.csv
A12: Goodwill (KZT m) | F12: 17438 | G12: 447128 | I12: 459118 | J12: FY2025 note 13; interim BS
A15: FY2026 guidance (reiterated 10-Aug-2026)
A16: Adj. EBITDA ~+5%; GMV ~+20%; TPV ~+15%; avg net loan portfolio ~+15%; constant currency at 1-Jan-2026 rates; no NBK rate cuts assumed
A17: Dividends: KZT 850 (Apr-2026), 850 (Jun-2026) declared; 1,000 proposed 6-Aug-2026 for Q2-2026

Sheet Assumptions
A1: Globals
A2: Price (EUR) | B2: 92.8 | C2: Yahoo KKS.F close 2026-08-25
A3: EUR/KZT spot | B3: 534.26 | C3: Yahoo EURKZT=X 2026-08-26
A4: Price (KZT equivalent) | B4: =B2*B3 | C4: formula
A5: Diluted shares (m) | B5: 190.73 | C5: Q2-2026 weighted diluted, held flat
A6: FY2025 attributable net income (KZT m) | B6: 1073177 | C6: NCI already removed
A7: Cost of equity (KZT) | B7: 0.19 | C7: rf 13% + 1.1 x 5.5% ERP; same for all scenarios
A8: Exit P/E cap (x year-5 NI) | B8: 12 | C8: ceiling on Gordon terminal
A9: Hurdle rate (EUR) | B9: 0.15
A10: KZT risk-free | B10: 0.13 | C10: Kazakhstan 10y
A11: EUR risk-free | B11: 0.027 | C11: Bund 10y
A12: Hurdle rate (KZT, interest parity) | B12: =(1+B9)*(1+B10)/(1+B11)-1 | C12: formula
A13: Net debt (KZT m) | B13: 0 | C13: Bank: deposits/bonds are operating funding
A14: FY2025 EPS (KZT) | B14: 5631 | C14: sanity multiples
A15: FY2025 BVPS (KZT) | B15: 13115 | C15: equity 2,491,843 / 190.0m
A17: Per scenario | B17: Bear | C17: Base | D17: Bull
A18: Terminal growth (nominal KZT) | B18: 0.04 | C18: 0.06 | D18: 0.07
A19: Probability weight | B19: 0.25 | C19: 0.5 | D19: 0.25
A20: Weights check (must be 1) | B20: =SUM(B19:D19)
A22: Scenario narratives
A23: Bear | B23: Kazakhstan consumer-lending cap tightened toward ~40% APR and risk-based pricing, NBK holds rates high through 2027 so deposit costs stay >14%, cost of risk drifts up from 0.7%, Türkiye keeps absorbing capital (Hepsi Bank build) without reaching profitability, and the sanctions/class-action overhang crystallises in a settlement. Attributable NI falls 5% in FY2026 then grows ~1-4%; payout trimmed to 60% to fund capital. Terminal growth 4% nominal KZT.
A24: Base | B24: FY2026 lands on guidance: adjusted EBITDA +5%, attributable NI ~+1% (H1 -0.6%), with the 25% bank tax rate and higher reserve requirements fully absorbed. From FY2027 Kazakhstan underlying growth (13-18% in FY2025) reasserts at ~10-11% as Türkiye losses narrow toward breakeven, rate cuts begin to ease deposit costs and Marketplace VAS/advertising lifts take rates; growth then fades to 9% by FY2030. Payout 66% in FY2026 (KZT 850/850/1,000/1,000 declared and proposed) then 70%, leaving 30% retention which at ~40% ROE funds ~12% growth. Terminal growth 6% nominal KZT (5% inflation target + ~1% real).
A25: Bull | B25: NBK cutting cycle arrives in 2027 and Fintech margins rebuild, Kasper/Alaqan lift engagement and Marketplace take rates, Hepsiburada closes part of its engagement gap and Hepsi Bank replicates the Kazakhstan fintech playbook from 2027, so consolidated attributable NI compounds 12-16% in FY2027-30. Payout rises to 75% as Türkiye capital needs peak in 2026-27. Terminal growth 7% nominal KZT.

Sheet DDM_Bear
A1: Bear scenario — discounted distributable earnings (KZT m)
A3: Year | B3: 2025A | C3: FY2026E | D3: FY2027E | E3: FY2028E | F3: FY2029E | G3: FY2030E
A4: Index | B4: 0 | C4: 1 | D4: 2 | E4: 3 | F4: 4 | G4: 5
A5: NI growth YoY (driver) | C5: -0.05 | D5: 0.01 | E5: 0.03 | F5: 0.04 | G5: 0.04
A6: Attributable net income | B6: =Assumptions!$B$6 | C6: =B6*(1+C5) | D6: =C6*(1+D5) | E6: =D6*(1+E5) | F6: =E6*(1+F5) | G6: =F6*(1+G5)
A7: Payout ratio (driver) | C7: 0.62 | D7: 0.6 | E7: 0.6 | F7: 0.6 | G7: 0.6
A8: Distributable earnings (dividends + buybacks) | C8: =C6*C7 | D8: =D6*D7 | E8: =E6*E7 | F8: =F6*F7 | G8: =G6*G7
A9: Retained earnings | C9: =C6-C8 | D9: =D6-D8 | E9: =E6-E8 | F9: =F6-F8 | G9: =G6-G8
A10: EPS (KZT) | B10: =B6/Assumptions!$B$5 | C10: =C6/Assumptions!$B$5 | D10: =D6/Assumptions!$B$5 | E10: =E6/Assumptions!$B$5 | F10: =F6/Assumptions!$B$5 | G10: =G6/Assumptions!$B$5
A11: DPS (KZT) | C11: =C8/Assumptions!$B$5 | D11: =D8/Assumptions!$B$5 | E11: =E8/Assumptions!$B$5 | F11: =F8/Assumptions!$B$5 | G11: =G8/Assumptions!$B$5
A12: Discount factor | B12: 1 | C12: =1/(1+Assumptions!$B$7)^C4 | D12: =1/(1+Assumptions!$B$7)^D4 | E12: =1/(1+Assumptions!$B$7)^E4 | F12: =1/(1+Assumptions!$B$7)^F4 | G12: =1/(1+Assumptions!$B$7)^G4
A13: PV of distributions | C13: =C8*C12 | D13: =D8*D12 | E13: =E8*E12 | F13: =F8*F12 | G13: =G8*G12
A16: Sum of PV distributions | B16: =SUM(C13:G13)
A17: Terminal growth | B17: =Assumptions!B18
A18: Terminal distribution (Y5 x (1+g)) | B18: =G8*(1+B17)
A19: Gordon TV | B19: =B18/(Assumptions!$B$7-B17)
A20: Cap TV (exit P/E x Y5 NI) | B20: =Assumptions!$B$8*G6
A21: TV used = MAX(0, MIN(Gordon, cap)) | B21: =MAX(0,MIN(B19,B20))
A22: Implied exit P/E | B22: =B21/G6
A23: PV of TV | B23: =B21*G12
A24: Equity value (KZT m) | B24: =B16+B23
A25: less net debt | B25: =Assumptions!$B$13
A26: Equity value to shareholders | B26: =B24-B25
A27: Diluted shares (m) | B27: =Assumptions!$B$5
A28: Value per share (KZT) | B28: =B26/B27
A29: Value per share (EUR) | B29: =B28/Assumptions!$B$3
A30: Upside vs price | B30: =B29/Assumptions!$B$2-1
A31: Terminal % of value | B31: =B23/B24
A32: Implied P/E on FY2025 EPS | B32: =B28/Assumptions!$B$14
A33: Implied P/B on FY2025 BVPS | B33: =B28/Assumptions!$B$15
A35: Entry price (KZT) at KZT hurdle | B35: =(SUMPRODUCT(C8:G8/(1+Assumptions!$B$12)^C4:G4)+B21/(1+Assumptions!$B$12)^5-B25)/B27
A36: Entry price (EUR) | B36: =B35/Assumptions!$B$3

Sheet DDM_Base
A1: Base scenario — discounted distributable earnings (KZT m)
A3: Year | B3: 2025A | C3: FY2026E | D3: FY2027E | E3: FY2028E | F3: FY2029E | G3: FY2030E
A4: Index | B4: 0 | C4: 1 | D4: 2 | E4: 3 | F4: 4 | G4: 5
A5: NI growth YoY (driver) | C5: 0.01 | D5: 0.1 | E5: 0.11 | F5: 0.1 | G5: 0.09
A6: Attributable net income | B6: =Assumptions!$B$6 | C6: =B6*(1+C5) | D6: =C6*(1+D5) | E6: =D6*(1+E5) | F6: =E6*(1+F5) | G6: =F6*(1+G5)
A7: Payout ratio (driver) | C7: 0.66 | D7: 0.7 | E7: 0.7 | F7: 0.7 | G7: 0.7
A8: Distributable earnings (dividends + buybacks) | C8: =C6*C7 | D8: =D6*D7 | E8: =E6*E7 | F8: =F6*F7 | G8: =G6*G7
A9: Retained earnings | C9: =C6-C8 | D9: =D6-D8 | E9: =E6-E8 | F9: =F6-F8 | G9: =G6-G8
A10: EPS (KZT) | B10: =B6/Assumptions!$B$5 | C10: =C6/Assumptions!$B$5 | D10: =D6/Assumptions!$B$5 | E10: =E6/Assumptions!$B$5 | F10: =F6/Assumptions!$B$5 | G10: =G6/Assumptions!$B$5
A11: DPS (KZT) | C11: =C8/Assumptions!$B$5 | D11: =D8/Assumptions!$B$5 | E11: =E8/Assumptions!$B$5 | F11: =F8/Assumptions!$B$5 | G11: =G8/Assumptions!$B$5
A12: Discount factor | B12: 1 | C12: =1/(1+Assumptions!$B$7)^C4 | D12: =1/(1+Assumptions!$B$7)^D4 | E12: =1/(1+Assumptions!$B$7)^E4 | F12: =1/(1+Assumptions!$B$7)^F4 | G12: =1/(1+Assumptions!$B$7)^G4
A13: PV of distributions | C13: =C8*C12 | D13: =D8*D12 | E13: =E8*E12 | F13: =F8*F12 | G13: =G8*G12
A16: Sum of PV distributions | B16: =SUM(C13:G13)
A17: Terminal growth | B17: =Assumptions!C18
A18: Terminal distribution (Y5 x (1+g)) | B18: =G8*(1+B17)
A19: Gordon TV | B19: =B18/(Assumptions!$B$7-B17)
A20: Cap TV (exit P/E x Y5 NI) | B20: =Assumptions!$B$8*G6
A21: TV used = MAX(0, MIN(Gordon, cap)) | B21: =MAX(0,MIN(B19,B20))
A22: Implied exit P/E | B22: =B21/G6
A23: PV of TV | B23: =B21*G12
A24: Equity value (KZT m) | B24: =B16+B23
A25: less net debt | B25: =Assumptions!$B$13
A26: Equity value to shareholders | B26: =B24-B25
A27: Diluted shares (m) | B27: =Assumptions!$B$5
A28: Value per share (KZT) | B28: =B26/B27
A29: Value per share (EUR) | B29: =B28/Assumptions!$B$3
A30: Upside vs price | B30: =B29/Assumptions!$B$2-1
A31: Terminal % of value | B31: =B23/B24
A32: Implied P/E on FY2025 EPS | B32: =B28/Assumptions!$B$14
A33: Implied P/B on FY2025 BVPS | B33: =B28/Assumptions!$B$15
A35: Entry price (KZT) at KZT hurdle | B35: =(SUMPRODUCT(C8:G8/(1+Assumptions!$B$12)^C4:G4)+B21/(1+Assumptions!$B$12)^5-B25)/B27
A36: Entry price (EUR) | B36: =B35/Assumptions!$B$3

Sheet DDM_Bull
A1: Bull scenario — discounted distributable earnings (KZT m)
A3: Year | B3: 2025A | C3: FY2026E | D3: FY2027E | E3: FY2028E | F3: FY2029E | G3: FY2030E
A4: Index | B4: 0 | C4: 1 | D4: 2 | E4: 3 | F4: 4 | G4: 5
A5: NI growth YoY (driver) | C5: 0.03 | D5: 0.15 | E5: 0.16 | F5: 0.14 | G5: 0.12
A6: Attributable net income | B6: =Assumptions!$B$6 | C6: =B6*(1+C5) | D6: =C6*(1+D5) | E6: =D6*(1+E5) | F6: =E6*(1+F5) | G6: =F6*(1+G5)
A7: Payout ratio (driver) | C7: 0.68 | D7: 0.72 | E7: 0.75 | F7: 0.75 | G7: 0.75
A8: Distributable earnings (dividends + buybacks) | C8: =C6*C7 | D8: =D6*D7 | E8: =E6*E7 | F8: =F6*F7 | G8: =G6*G7
A9: Retained earnings | C9: =C6-C8 | D9: =D6-D8 | E9: =E6-E8 | F9: =F6-F8 | G9: =G6-G8
A10: EPS (KZT) | B10: =B6/Assumptions!$B$5 | C10: =C6/Assumptions!$B$5 | D10: =D6/Assumptions!$B$5 | E10: =E6/Assumptions!$B$5 | F10: =F6/Assumptions!$B$5 | G10: =G6/Assumptions!$B$5
A11: DPS (KZT) | C11: =C8/Assumptions!$B$5 | D11: =D8/Assumptions!$B$5 | E11: =E8/Assumptions!$B$5 | F11: =F8/Assumptions!$B$5 | G11: =G8/Assumptions!$B$5
A12: Discount factor | B12: 1 | C12: =1/(1+Assumptions!$B$7)^C4 | D12: =1/(1+Assumptions!$B$7)^D4 | E12: =1/(1+Assumptions!$B$7)^E4 | F12: =1/(1+Assumptions!$B$7)^F4 | G12: =1/(1+Assumptions!$B$7)^G4
A13: PV of distributions | C13: =C8*C12 | D13: =D8*D12 | E13: =E8*E12 | F13: =F8*F12 | G13: =G8*G12
A16: Sum of PV distributions | B16: =SUM(C13:G13)
A17: Terminal growth | B17: =Assumptions!D18
A18: Terminal distribution (Y5 x (1+g)) | B18: =G8*(1+B17)
A19: Gordon TV | B19: =B18/(Assumptions!$B$7-B17)
A20: Cap TV (exit P/E x Y5 NI) | B20: =Assumptions!$B$8*G6
A21: TV used = MAX(0, MIN(Gordon, cap)) | B21: =MAX(0,MIN(B19,B20))
A22: Implied exit P/E | B22: =B21/G6
A23: PV of TV | B23: =B21*G12
A24: Equity value (KZT m) | B24: =B16+B23
A25: less net debt | B25: =Assumptions!$B$13
A26: Equity value to shareholders | B26: =B24-B25
A27: Diluted shares (m) | B27: =Assumptions!$B$5
A28: Value per share (KZT) | B28: =B26/B27
A29: Value per share (EUR) | B29: =B28/Assumptions!$B$3
A30: Upside vs price | B30: =B29/Assumptions!$B$2-1
A31: Terminal % of value | B31: =B23/B24
A32: Implied P/E on FY2025 EPS | B32: =B28/Assumptions!$B$14
A33: Implied P/B on FY2025 BVPS | B33: =B28/Assumptions!$B$15
A35: Entry price (KZT) at KZT hurdle | B35: =(SUMPRODUCT(C8:G8/(1+Assumptions!$B$12)^C4:G4)+B21/(1+Assumptions!$B$12)^5-B25)/B27
A36: Entry price (EUR) | B36: =B35/Assumptions!$B$3

Sheet Valuation
A1: Valuation summary (EUR per share unless stated)
A3: Scenario | B3: Value KZT | C3: Value EUR | D3: Upside | E3: Weight | F3: Entry EUR
A4: Bear | B4: =DDM_Bear!B28 | C4: =DDM_Bear!B29 | D4: =DDM_Bear!B30 | E4: =Assumptions!B19 | F4: =DDM_Bear!B36
A5: Base | B5: =DDM_Base!B28 | C5: =DDM_Base!B29 | D5: =DDM_Base!B30 | E5: =Assumptions!C19 | F5: =DDM_Base!B36
A6: Bull | B6: =DDM_Bull!B28 | C6: =DDM_Bull!B29 | D6: =DDM_Bull!B30 | E6: =Assumptions!D19 | F6: =DDM_Bull!B36
A8: Probability-weighted IV (EUR) | B8: =SUMPRODUCT(C4:C6,E4:E6)
A9: Probability-weighted IV (KZT) | B9: =SUMPRODUCT(B4:B6,E4:E6)
A10: Margin of safety vs price | B10: =1-Assumptions!$B$2/B8
A11: Weighted entry price (EUR, 15% EUR hurdle) | B11: =SUMPRODUCT(F4:F6,E4:E6)
A12: Band position (house vs street) | B12: n/a — SBC inside IFRS NI, band collapsed
A14: Required-return table (base case, EUR/share)
A15: KZT required return | B15: Value EUR
A16: 0.15 | B16: =(SUMPRODUCT(DDM_Base!$C$8:$G$8/(1+A16)^DDM_Base!$C$4:$G$4)+DDM_Base!$B$21/(1+A16)^5-Assumptions!$B$13)/Assumptions!$B$5/Assumptions!$B$3
A17: 0.17 | B17: =(SUMPRODUCT(DDM_Base!$C$8:$G$8/(1+A17)^DDM_Base!$C$4:$G$4)+DDM_Base!$B$21/(1+A17)^5-Assumptions!$B$13)/Assumptions!$B$5/Assumptions!$B$3
A18: 0.19 | B18: =(SUMPRODUCT(DDM_Base!$C$8:$G$8/(1+A18)^DDM_Base!$C$4:$G$4)+DDM_Base!$B$21/(1+A18)^5-Assumptions!$B$13)/Assumptions!$B$5/Assumptions!$B$3
A19: 0.21 | B19: =(SUMPRODUCT(DDM_Base!$C$8:$G$8/(1+A19)^DDM_Base!$C$4:$G$4)+DDM_Base!$B$21/(1+A19)^5-Assumptions!$B$13)/Assumptions!$B$5/Assumptions!$B$3
A20: 0.25 | B20: =(SUMPRODUCT(DDM_Base!$C$8:$G$8/(1+A20)^DDM_Base!$C$4:$G$4)+DDM_Base!$B$21/(1+A20)^5-Assumptions!$B$13)/Assumptions!$B$5/Assumptions!$B$3
A21: =Assumptions!$B$12 | B21: =(SUMPRODUCT(DDM_Base!$C$8:$G$8/(1+A21)^DDM_Base!$C$4:$G$4)+DDM_Base!$B$21/(1+A21)^5-Assumptions!$B$13)/Assumptions!$B$5/Assumptions!$B$3 | C21: KZT hurdle (15% EUR)
A23: Sensitivity: base case, cost of equity (rows) x terminal growth (cols), EUR/share
B24: 0.05 | C24: 0.055 | D24: 0.06 | E24: 0.065 | F24: 0.07
A25: 0.17 | B25: =IF($A25>B$24,(SUMPRODUCT(DDM_Base!$C$8:$G$8/(1+$A25)^DDM_Base!$C$4:$G$4)+MAX(0,MIN(DDM_Base!$G$8*(1+B$24)/($A25-B$24),Assumptions!$B$8*DDM_Base!$G$6))/(1+$A25)^5-Assumptions!$B$13)/Assumptions!$B$5/Assumptions!$B$3,"n/a") | C25: =IF($A25>C$24,(SUMPRODUCT(DDM_Base!$C$8:$G$8/(1+$A25)^DDM_Base!$C$4:$G$4)+MAX(0,MIN(DDM_Base!$G$8*(1+C$24)/($A25-C$24),Assumptions!$B$8*DDM_Base!$G$6))/(1+$A25)^5-Assumptions!$B$13)/Assumptions!$B$5/Assumptions!$B$3,"n/a") | D25: =IF($A25>D$24,(SUMPRODUCT(DDM_Base!$C$8:$G$8/(1+$A25)^DDM_Base!$C$4:$G$4)+MAX(0,MIN(DDM_Base!$G$8*(1+D$24)/($A25-D$24),Assumptions!$B$8*DDM_Base!$G$6))/(1+$A25)^5-Assumptions!$B$13)/Assumptions!$B$5/Assumptions!$B$3,"n/a") | E25: =IF($A25>E$24,(SUMPRODUCT(DDM_Base!$C$8:$G$8/(1+$A25)^DDM_Base!$C$4:$G$4)+MAX(0,MIN(DDM_Base!$G$8*(1+E$24)/($A25-E$24),Assumptions!$B$8*DDM_Base!$G$6))/(1+$A25)^5-Assumptions!$B$13)/Assumptions!$B$5/Assumptions!$B$3,"n/a") | F25: =IF($A25>F$24,(SUMPRODUCT(DDM_Base!$C$8:$G$8/(1+$A25)^DDM_Base!$C$4:$G$4)+MAX(0,MIN(DDM_Base!$G$8*(1+F$24)/($A25-F$24),Assumptions!$B$8*DDM_Base!$G$6))/(1+$A25)^5-Assumptions!$B$13)/Assumptions!$B$5/Assumptions!$B$3,"n/a")
A26: 0.18 | B26: =IF($A26>B$24,(SUMPRODUCT(DDM_Base!$C$8:$G$8/(1+$A26)^DDM_Base!$C$4:$G$4)+MAX(0,MIN(DDM_Base!$G$8*(1+B$24)/($A26-B$24),Assumptions!$B$8*DDM_Base!$G$6))/(1+$A26)^5-Assumptions!$B$13)/Assumptions!$B$5/Assumptions!$B$3,"n/a") | C26: =IF($A26>C$24,(SUMPRODUCT(DDM_Base!$C$8:$G$8/(1+$A26)^DDM_Base!$C$4:$G$4)+MAX(0,MIN(DDM_Base!$G$8*(1+C$24)/($A26-C$24),Assumptions!$B$8*DDM_Base!$G$6))/(1+$A26)^5-Assumptions!$B$13)/Assumptions!$B$5/Assumptions!$B$3,"n/a") | D26: =IF($A26>D$24,(SUMPRODUCT(DDM_Base!$C$8:$G$8/(1+$A26)^DDM_Base!$C$4:$G$4)+MAX(0,MIN(DDM_Base!$G$8*(1+D$24)/($A26-D$24),Assumptions!$B$8*DDM_Base!$G$6))/(1+$A26)^5-Assumptions!$B$13)/Assumptions!$B$5/Assumptions!$B$3,"n/a") | E26: =IF($A26>E$24,(SUMPRODUCT(DDM_Base!$C$8:$G$8/(1+$A26)^DDM_Base!$C$4:$G$4)+MAX(0,MIN(DDM_Base!$G$8*(1+E$24)/($A26-E$24),Assumptions!$B$8*DDM_Base!$G$6))/(1+$A26)^5-Assumptions!$B$13)/Assumptions!$B$5/Assumptions!$B$3,"n/a") | F26: =IF($A26>F$24,(SUMPRODUCT(DDM_Base!$C$8:$G$8/(1+$A26)^DDM_Base!$C$4:$G$4)+MAX(0,MIN(DDM_Base!$G$8*(1+F$24)/($A26-F$24),Assumptions!$B$8*DDM_Base!$G$6))/(1+$A26)^5-Assumptions!$B$13)/Assumptions!$B$5/Assumptions!$B$3,"n/a")
A27: 0.19 | B27: =IF($A27>B$24,(SUMPRODUCT(DDM_Base!$C$8:$G$8/(1+$A27)^DDM_Base!$C$4:$G$4)+MAX(0,MIN(DDM_Base!$G$8*(1+B$24)/($A27-B$24),Assumptions!$B$8*DDM_Base!$G$6))/(1+$A27)^5-Assumptions!$B$13)/Assumptions!$B$5/Assumptions!$B$3,"n/a") | C27: =IF($A27>C$24,(SUMPRODUCT(DDM_Base!$C$8:$G$8/(1+$A27)^DDM_Base!$C$4:$G$4)+MAX(0,MIN(DDM_Base!$G$8*(1+C$24)/($A27-C$24),Assumptions!$B$8*DDM_Base!$G$6))/(1+$A27)^5-Assumptions!$B$13)/Assumptions!$B$5/Assumptions!$B$3,"n/a") | D27: =IF($A27>D$24,(SUMPRODUCT(DDM_Base!$C$8:$G$8/(1+$A27)^DDM_Base!$C$4:$G$4)+MAX(0,MIN(DDM_Base!$G$8*(1+D$24)/($A27-D$24),Assumptions!$B$8*DDM_Base!$G$6))/(1+$A27)^5-Assumptions!$B$13)/Assumptions!$B$5/Assumptions!$B$3,"n/a") | E27: =IF($A27>E$24,(SUMPRODUCT(DDM_Base!$C$8:$G$8/(1+$A27)^DDM_Base!$C$4:$G$4)+MAX(0,MIN(DDM_Base!$G$8*(1+E$24)/($A27-E$24),Assumptions!$B$8*DDM_Base!$G$6))/(1+$A27)^5-Assumptions!$B$13)/Assumptions!$B$5/Assumptions!$B$3,"n/a") | F27: =IF($A27>F$24,(SUMPRODUCT(DDM_Base!$C$8:$G$8/(1+$A27)^DDM_Base!$C$4:$G$4)+MAX(0,MIN(DDM_Base!$G$8*(1+F$24)/($A27-F$24),Assumptions!$B$8*DDM_Base!$G$6))/(1+$A27)^5-Assumptions!$B$13)/Assumptions!$B$5/Assumptions!$B$3,"n/a")
A28: 0.2 | B28: =IF($A28>B$24,(SUMPRODUCT(DDM_Base!$C$8:$G$8/(1+$A28)^DDM_Base!$C$4:$G$4)+MAX(0,MIN(DDM_Base!$G$8*(1+B$24)/($A28-B$24),Assumptions!$B$8*DDM_Base!$G$6))/(1+$A28)^5-Assumptions!$B$13)/Assumptions!$B$5/Assumptions!$B$3,"n/a") | C28: =IF($A28>C$24,(SUMPRODUCT(DDM_Base!$C$8:$G$8/(1+$A28)^DDM_Base!$C$4:$G$4)+MAX(0,MIN(DDM_Base!$G$8*(1+C$24)/($A28-C$24),Assumptions!$B$8*DDM_Base!$G$6))/(1+$A28)^5-Assumptions!$B$13)/Assumptions!$B$5/Assumptions!$B$3,"n/a") | D28: =IF($A28>D$24,(SUMPRODUCT(DDM_Base!$C$8:$G$8/(1+$A28)^DDM_Base!$C$4:$G$4)+MAX(0,MIN(DDM_Base!$G$8*(1+D$24)/($A28-D$24),Assumptions!$B$8*DDM_Base!$G$6))/(1+$A28)^5-Assumptions!$B$13)/Assumptions!$B$5/Assumptions!$B$3,"n/a") | E28: =IF($A28>E$24,(SUMPRODUCT(DDM_Base!$C$8:$G$8/(1+$A28)^DDM_Base!$C$4:$G$4)+MAX(0,MIN(DDM_Base!$G$8*(1+E$24)/($A28-E$24),Assumptions!$B$8*DDM_Base!$G$6))/(1+$A28)^5-Assumptions!$B$13)/Assumptions!$B$5/Assumptions!$B$3,"n/a") | F28: =IF($A28>F$24,(SUMPRODUCT(DDM_Base!$C$8:$G$8/(1+$A28)^DDM_Base!$C$4:$G$4)+MAX(0,MIN(DDM_Base!$G$8*(1+F$24)/($A28-F$24),Assumptions!$B$8*DDM_Base!$G$6))/(1+$A28)^5-Assumptions!$B$13)/Assumptions!$B$5/Assumptions!$B$3,"n/a")
A29: 0.21 | B29: =IF($A29>B$24,(SUMPRODUCT(DDM_Base!$C$8:$G$8/(1+$A29)^DDM_Base!$C$4:$G$4)+MAX(0,MIN(DDM_Base!$G$8*(1+B$24)/($A29-B$24),Assumptions!$B$8*DDM_Base!$G$6))/(1+$A29)^5-Assumptions!$B$13)/Assumptions!$B$5/Assumptions!$B$3,"n/a") | C29: =IF($A29>C$24,(SUMPRODUCT(DDM_Base!$C$8:$G$8/(1+$A29)^DDM_Base!$C$4:$G$4)+MAX(0,MIN(DDM_Base!$G$8*(1+C$24)/($A29-C$24),Assumptions!$B$8*DDM_Base!$G$6))/(1+$A29)^5-Assumptions!$B$13)/Assumptions!$B$5/Assumptions!$B$3,"n/a") | D29: =IF($A29>D$24,(SUMPRODUCT(DDM_Base!$C$8:$G$8/(1+$A29)^DDM_Base!$C$4:$G$4)+MAX(0,MIN(DDM_Base!$G$8*(1+D$24)/($A29-D$24),Assumptions!$B$8*DDM_Base!$G$6))/(1+$A29)^5-Assumptions!$B$13)/Assumptions!$B$5/Assumptions!$B$3,"n/a") | E29: =IF($A29>E$24,(SUMPRODUCT(DDM_Base!$C$8:$G$8/(1+$A29)^DDM_Base!$C$4:$G$4)+MAX(0,MIN(DDM_Base!$G$8*(1+E$24)/($A29-E$24),Assumptions!$B$8*DDM_Base!$G$6))/(1+$A29)^5-Assumptions!$B$13)/Assumptions!$B$5/Assumptions!$B$3,"n/a") | F29: =IF($A29>F$24,(SUMPRODUCT(DDM_Base!$C$8:$G$8/(1+$A29)^DDM_Base!$C$4:$G$4)+MAX(0,MIN(DDM_Base!$G$8*(1+F$24)/($A29-F$24),Assumptions!$B$8*DDM_Base!$G$6))/(1+$A29)^5-Assumptions!$B$13)/Assumptions!$B$5/Assumptions!$B$3,"n/a")
