Workbook

Sheet Summary
A1: AMZN DCF Summary — Amazon.com, Inc. | F1: Current Price: | G1: 232.11
A2: Valuation date: 2026-07-26 | Current price: $232.11
A4: Scenario | B4: Intrinsic Value | C4: Upside vs Current | D4: Entry Price (15% IRR) | E4: Entry Discount
A5: Base Case | B5: ='Base Case'!B36 | C5: ='Base Case'!B46 | D5: ='Base Case'!B44 | E5: ='Base Case'!B47
A6: Bull Case | B6: ='Bull Case'!B36 | C6: ='Bull Case'!B46 | D6: ='Bull Case'!B44 | E6: ='Bull Case'!B47
A7: Bear Case | B7: ='Bear Case'!B36 | C7: ='Bear Case'!B46 | D7: ='Bear Case'!B44 | E7: ='Bear Case'!B47
A9: Probability Weights
A10: Bull weight | B10: 0.25
A11: Base weight | B11: 0.5
A12: Bear weight | B12: 0.25
A13: Probability-Weighted IV | B13: =B5*B11+B6*B10+B7*B12
A14: Upside vs Current (Weighted) | B14: =(B13-G1)/G1
A16: Key Modeling Notes
A17: - FY2025 FCF ($11.2B) is a capex-cycle trough (guided ~$200B FY2026 capex for AI/data centers) - NOT used as DCF base directly.
A18: - Model projects Revenue x FCF-margin path instead: margin starts depressed (2.5%-4.5% Y1) and normalizes toward 8.5%-12% of revenue by Y5.
A19: - Revenue growth (11.7% 3yr / 13.2% 5yr CAGR) used as growth driver, NOT equity CAGR (41.2%/34.5%, inflated by 100% retention + non-cash equity-stake gains).
A20: - Net debt = -$24,015M (NET CASH), using cash + marketable securities ($143.1B) less total debt ($119,074M) per Q1-2026 10-Q.
A21: - Entry price = PV of Yrs 1-5 FCF @15% + PV of Terminal Value (Gordon, at WACC) @15% - net debt, all divided by shares.

Sheet Base Case
A1: AMZN DCF Valuation Model — Base Case
A2: Gray cells are INPUTS - adjust to see valuation change
A4: KEY INPUTS
A5: Current Stock Price | B5: 232.11
A6: Shares Outstanding (M) | B6: 10754
A7: Cash & Equivalents (M) | B7: 101816
A8: Marketable Securities (M) | B8: 41273
A9: Total Debt (M) | B9: 119074
A10: Net Debt (M) [Debt - Cash - MktSec] | B10: =B9-B7-B8
A11: Base Year Revenue (M, FY2025) | B11: 716924
A13: WACC | B13: 0.095
A14: Terminal Growth Rate | B14: 0.0275
A16: GROWTH & MARGIN ASSUMPTIONS
B17: Year 1 | C17: Year 2 | D17: Year 3 | E17: Year 4 | F17: Year 5
A18: Revenue Growth Rate | B18: 0.105 | C18: 0.1 | D18: 0.095 | E18: 0.09 | F18: 0.085
A19: FCF Margin (% of Revenue) | B19: 0.025 | C19: 0.045 | D19: 0.06 | E19: 0.075 | F19: 0.085
A21: PROJECTIONS
B22: Base | C22: Year 1 | D22: Year 2 | E22: Year 3 | F22: Year 4 | G22: Year 5
A23: Revenue | B23: =B11 | C23: =B23*(1+B18) | D23: =C23*(1+C18) | E23: =D23*(1+D18) | F23: =E23*(1+E18) | G23: =F23*(1+F18)
A24: Free Cash Flow | C24: =C23*B19 | D24: =D23*C19 | E24: =E23*D19 | F24: =F23*E19 | G24: =G23*F19
A25: Discount Factor | C25: =1/(1+$B$13)^1 | D25: =1/(1+$B$13)^2 | E25: =1/(1+$B$13)^3 | F25: =1/(1+$B$13)^4 | G25: =1/(1+$B$13)^5
A26: PV of FCF | C26: =C24*C25 | D26: =D24*D25 | E26: =E24*E25 | F26: =F24*F25 | G26: =G24*G25
A28: VALUATION
A29: Sum of PV of FCF | B29: =SUM(C26:G26)
A30: Terminal FCF (Year 5 x (1+g)) | B30: =G24*(1+$B$14)
A31: Terminal Value | B31: =B30/($B$13-$B$14)
A32: PV of Terminal Value | B32: =B31*G25
A33: Enterprise Value | B33: =B29+B32
A34: Less: Net Debt | B34: =B10
A35: Equity Value | B35: =B33-B34
A36: INTRINSIC VALUE/SHARE | B36: =B35/B6
A37: Terminal % of Enterprise Value | B37: =B32/B33
A38: Implied Exit Multiple (TV/FCF_Y5) | B38: =B31/G24
A40: ENTRY PRICE (15% IRR Target)
A41: PV of Yrs 1-5 FCF @15% | B41: =NPV(0.15,C24:G24)
A42: PV of Terminal Value @15% | B42: =B31/(1.15^5)
A43: Less: Net Debt | B43: =B10
A44: Entry Price (15% IRR) | B44: =(B41+B42-B43)/B6
A46: Upside to Intrinsic Value | B46: =(B36-B5)/B5
A47: Discount of Entry Price vs Current | B47: =(B5-B44)/B5

Sheet Bull Case
A1: AMZN DCF Valuation Model — Bull Case
A2: Gray cells are INPUTS - adjust to see valuation change
A4: KEY INPUTS
A5: Current Stock Price | B5: 232.11
A6: Shares Outstanding (M) | B6: 10754
A7: Cash & Equivalents (M) | B7: 101816
A8: Marketable Securities (M) | B8: 41273
A9: Total Debt (M) | B9: 119074
A10: Net Debt (M) [Debt - Cash - MktSec] | B10: =B9-B7-B8
A11: Base Year Revenue (M, FY2025) | B11: 716924
A13: WACC | B13: 0.0875
A14: Terminal Growth Rate | B14: 0.0325
A16: GROWTH & MARGIN ASSUMPTIONS
B17: Year 1 | C17: Year 2 | D17: Year 3 | E17: Year 4 | F17: Year 5
A18: Revenue Growth Rate | B18: 0.15 | C18: 0.145 | D18: 0.135 | E18: 0.125 | F18: 0.115
A19: FCF Margin (% of Revenue) | B19: 0.045 | C19: 0.07 | D19: 0.09 | E19: 0.105 | F19: 0.12
A21: PROJECTIONS
B22: Base | C22: Year 1 | D22: Year 2 | E22: Year 3 | F22: Year 4 | G22: Year 5
A23: Revenue | B23: =B11 | C23: =B23*(1+B18) | D23: =C23*(1+C18) | E23: =D23*(1+D18) | F23: =E23*(1+E18) | G23: =F23*(1+F18)
A24: Free Cash Flow | C24: =C23*B19 | D24: =D23*C19 | E24: =E23*D19 | F24: =F23*E19 | G24: =G23*F19
A25: Discount Factor | C25: =1/(1+$B$13)^1 | D25: =1/(1+$B$13)^2 | E25: =1/(1+$B$13)^3 | F25: =1/(1+$B$13)^4 | G25: =1/(1+$B$13)^5
A26: PV of FCF | C26: =C24*C25 | D26: =D24*D25 | E26: =E24*E25 | F26: =F24*F25 | G26: =G24*G25
A28: VALUATION
A29: Sum of PV of FCF | B29: =SUM(C26:G26)
A30: Terminal FCF (Year 5 x (1+g)) | B30: =G24*(1+$B$14)
A31: Terminal Value | B31: =B30/($B$13-$B$14)
A32: PV of Terminal Value | B32: =B31*G25
A33: Enterprise Value | B33: =B29+B32
A34: Less: Net Debt | B34: =B10
A35: Equity Value | B35: =B33-B34
A36: INTRINSIC VALUE/SHARE | B36: =B35/B6
A37: Terminal % of Enterprise Value | B37: =B32/B33
A38: Implied Exit Multiple (TV/FCF_Y5) | B38: =B31/G24
A40: ENTRY PRICE (15% IRR Target)
A41: PV of Yrs 1-5 FCF @15% | B41: =NPV(0.15,C24:G24)
A42: PV of Terminal Value @15% | B42: =B31/(1.15^5)
A43: Less: Net Debt | B43: =B10
A44: Entry Price (15% IRR) | B44: =(B41+B42-B43)/B6
A46: Upside to Intrinsic Value | B46: =(B36-B5)/B5
A47: Discount of Entry Price vs Current | B47: =(B5-B44)/B5

Sheet Bear Case
A1: AMZN DCF Valuation Model — Bear Case
A2: Gray cells are INPUTS - adjust to see valuation change
A4: KEY INPUTS
A5: Current Stock Price | B5: 232.11
A6: Shares Outstanding (M) | B6: 10754
A7: Cash & Equivalents (M) | B7: 101816
A8: Marketable Securities (M) | B8: 41273
A9: Total Debt (M) | B9: 119074
A10: Net Debt (M) [Debt - Cash - MktSec] | B10: =B9-B7-B8
A11: Base Year Revenue (M, FY2025) | B11: 716924
A13: WACC | B13: 0.1075
A14: Terminal Growth Rate | B14: 0.02
A16: GROWTH & MARGIN ASSUMPTIONS
B17: Year 1 | C17: Year 2 | D17: Year 3 | E17: Year 4 | F17: Year 5
A18: Revenue Growth Rate | B18: 0.07 | C18: 0.065 | D18: 0.06 | E18: 0.055 | F18: 0.05
A19: FCF Margin (% of Revenue) | B19: 0.01 | C19: 0.02 | D19: 0.03 | E19: 0.04 | F19: 0.05
A21: PROJECTIONS
B22: Base | C22: Year 1 | D22: Year 2 | E22: Year 3 | F22: Year 4 | G22: Year 5
A23: Revenue | B23: =B11 | C23: =B23*(1+B18) | D23: =C23*(1+C18) | E23: =D23*(1+D18) | F23: =E23*(1+E18) | G23: =F23*(1+F18)
A24: Free Cash Flow | C24: =C23*B19 | D24: =D23*C19 | E24: =E23*D19 | F24: =F23*E19 | G24: =G23*F19
A25: Discount Factor | C25: =1/(1+$B$13)^1 | D25: =1/(1+$B$13)^2 | E25: =1/(1+$B$13)^3 | F25: =1/(1+$B$13)^4 | G25: =1/(1+$B$13)^5
A26: PV of FCF | C26: =C24*C25 | D26: =D24*D25 | E26: =E24*E25 | F26: =F24*F25 | G26: =G24*G25
A28: VALUATION
A29: Sum of PV of FCF | B29: =SUM(C26:G26)
A30: Terminal FCF (Year 5 x (1+g)) | B30: =G24*(1+$B$14)
A31: Terminal Value | B31: =B30/($B$13-$B$14)
A32: PV of Terminal Value | B32: =B31*G25
A33: Enterprise Value | B33: =B29+B32
A34: Less: Net Debt | B34: =B10
A35: Equity Value | B35: =B33-B34
A36: INTRINSIC VALUE/SHARE | B36: =B35/B6
A37: Terminal % of Enterprise Value | B37: =B32/B33
A38: Implied Exit Multiple (TV/FCF_Y5) | B38: =B31/G24
A40: ENTRY PRICE (15% IRR Target)
A41: PV of Yrs 1-5 FCF @15% | B41: =NPV(0.15,C24:G24)
A42: PV of Terminal Value @15% | B42: =B31/(1.15^5)
A43: Less: Net Debt | B43: =B10
A44: Entry Price (15% IRR) | B44: =(B41+B42-B43)/B6
A46: Upside to Intrinsic Value | B46: =(B36-B5)/B5
A47: Discount of Entry Price vs Current | B47: =(B5-B44)/B5

Sheet Sensitivity
A1: Sensitivity Analysis — Base Case
A2: Intrinsic Value by WACC & Terminal Growth (USD/share)
A4: WACC \ Term G | B4: 0.0175 | C4: 0.0225 | D4: 0.0275 | E4: 0.0325 | F4: 0.0375
A5: 0.075 | B5: =((((('Base Case'!$B$11*(1+'Base Case'!$B$18))*'Base Case'!$B$19)/(1+0.075)^1+((('Base Case'!$B$11*(1+'Base Case'!$B$18))*(1+'Base Case'!$C$18))*'Base Case'!$C$19)/(1+0.075)^2+(((('Base Case'!$B$11*(1+'Base Case'!$B$18))*(1+'Base Case'!$C$18))*(1+'Base Case'!$D$18))*'Base Case'!$D$19)/(1+0.075)^3+((((('Base Case'!$B$11*(1+'Base Case'!$B$18))*(1+'Base Case'!$C$18))*(1+'Base Case'!$D$18))*(1+'Base Case'!$E$18))*'Base Case'!$E$19)/(1+0.075)^4+(((((('Base Case'!$B$11*(1+'Base Case'!$B$18))*(1+'Base Case'!$C$18))*(1+'Base Case'!$D$18))*(1+'Base Case'!$E$18))*(1+'Base Case'!$F$18))*'Base Case'!$F$19)/(1+0.075)^5)+(((((((('Base Case'!$B$11*(1+'Base Case'!$B$18))*(1+'Base Case'!$C$18))*(1+'Base Case'!$D$18))*(1+'Base Case'!$E$18))*(1+'Base Case'!$F$18))*'Base Case'!$F$19)*(1+0.0175))/(0.075-0.0175))/(1+0.075)^5)-'Base Case'!$B$10)/'Base Case'!$B$6 | C5: =((((('Base Case'!$B$11*(1+'Base Case'!$B$18))*'Base Case'!$B$19)/(1+0.075)^1+((('Base Case'!$B$11*(1+'Base Case'!$B$18))*(1+'Base Case'!$C$18))*'Base Case'!$C$19)/(1+0.075)^2+(((('Base Case'!$B$11*(1+'Base Case'!$B$18))*(1+'Base Case'!$C$18))*(1+'Base Case'!$D$18))*'Base Case'!$D$19)/(1+0.075)^3+((((('Base Case'!$B$11*(1+'Base Case'!$B$18))*(1+'Base Case'!$C$18))*(1+'Base Case'!$D$18))*(1+'Base Case'!$E$18))*'Base Case'!$E$19)/(1+0.075)^4+(((((('Base Case'!$B$11*(1+'Base Case'!$B$18))*(1+'Base Case'!$C$18))*(1+'Base Case'!$D$18))*(1+'Base Case'!$E$18))*(1+'Base Case'!$F$18))*'Base Case'!$F$19)/(1+0.075)^5)+(((((((('Base Case'!$B$11*(1+'Base Case'!$B$18))*(1+'Base Case'!$C$18))*(1+'Base Case'!$D$18))*(1+'Base Case'!$E$18))*(1+'Base Case'!$F$18))*'Base Case'!$F$19)*(1+0.0225))/(0.075-0.0225))/(1+0.075)^5)-'Base Case'!$B$10)/'Base Case'!$B$6 | D5: =((((('Base Case'!$B$11*(1+'Base Case'!$B$18))*'Base Case'!$B$19)/(1+0.075)^1+((('Base Case'!$B$11*(1+'Base Case'!$B$18))*(1+'Base Case'!$C$18))*'Base Case'!$C$19)/(1+0.075)^2+(((('Base Case'!$B$11*(1+'Base Case'!$B$18))*(1+'Base Case'!$C$18))*(1+'Base Case'!$D$18))*'Base Case'!$D$19)/(1+0.075)^3+((((('Base Case'!$B$11*(1+'Base Case'!$B$18))*(1+'Base Case'!$C$18))*(1+'Base Case'!$D$18))*(1+'Base Case'!$E$18))*'Base Case'!$E$19)/(1+0.075)^4+(((((('Base Case'!$B$11*(1+'Base Case'!$B$18))*(1+'Base Case'!$C$18))*(1+'Base Case'!$D$18))*(1+'Base Case'!$E$18))*(1+'Base Case'!$F$18))*'Base Case'!$F$19)/(1+0.075)^5)+(((((((('Base Case'!$B$11*(1+'Base Case'!$B$18))*(1+'Base Case'!$C$18))*(1+'Base Case'!$D$18))*(1+'Base Case'!$E$18))*(1+'Base Case'!$F$18))*'Base Case'!$F$19)*(1+0.0275))/(0.075-0.0275))/(1+0.075)^5)-'Base Case'!$B$10)/'Base Case'!$B$6 | E5: =((((('Base Case'!$B$11*(1+'Base Case'!$B$18))*'Base Case'!$B$19)/(1+0.075)^1+((('Base Case'!$B$11*(1+'Base Case'!$B$18))*(1+'Base Case'!$C$18))*'Base Case'!$C$19)/(1+0.075)^2+(((('Base Case'!$B$11*(1+'Base Case'!$B$18))*(1+'Base Case'!$C$18))*(1+'Base Case'!$D$18))*'Base Case'!$D$19)/(1+0.075)^3+((((('Base Case'!$B$11*(1+'Base Case'!$B$18))*(1+'Base Case'!$C$18))*(1+'Base Case'!$D$18))*(1+'Base Case'!$E$18))*'Base Case'!$E$19)/(1+0.075)^4+(((((('Base Case'!$B$11*(1+'Base Case'!$B$18))*(1+'Base Case'!$C$18))*(1+'Base Case'!$D$18))*(1+'Base Case'!$E$18))*(1+'Base Case'!$F$18))*'Base Case'!$F$19)/(1+0.075)^5)+(((((((('Base Case'!$B$11*(1+'Base Case'!$B$18))*(1+'Base Case'!$C$18))*(1+'Base Case'!$D$18))*(1+'Base Case'!$E$18))*(1+'Base Case'!$F$18))*'Base Case'!$F$19)*(1+0.0325))/(0.075-0.0325))/(1+0.075)^5)-'Base Case'!$B$10)/'Base Case'!$B$6 | F5: =((((('Base Case'!$B$11*(1+'Base Case'!$B$18))*'Base Case'!$B$19)/(1+0.075)^1+((('Base Case'!$B$11*(1+'Base Case'!$B$18))*(1+'Base Case'!$C$18))*'Base Case'!$C$19)/(1+0.075)^2+(((('Base Case'!$B$11*(1+'Base Case'!$B$18))*(1+'Base Case'!$C$18))*(1+'Base Case'!$D$18))*'Base Case'!$D$19)/(1+0.075)^3+((((('Base Case'!$B$11*(1+'Base Case'!$B$18))*(1+'Base Case'!$C$18))*(1+'Base Case'!$D$18))*(1+'Base Case'!$E$18))*'Base Case'!$E$19)/(1+0.075)^4+(((((('Base Case'!$B$11*(1+'Base Case'!$B$18))*(1+'Base Case'!$C$18))*(1+'Base Case'!$D$18))*(1+'Base Case'!$E$18))*(1+'Base Case'!$F$18))*'Base Case'!$F$19)/(1+0.075)^5)+(((((((('Base Case'!$B$11*(1+'Base Case'!$B$18))*(1+'Base Case'!$C$18))*(1+'Base Case'!$D$18))*(1+'Base Case'!$E$18))*(1+'Base Case'!$F$18))*'Base Case'!$F$19)*(1+0.0375))/(0.075-0.0375))/(1+0.075)^5)-'Base Case'!$B$10)/'Base Case'!$B$6
A6: 0.085 | B6: =((((('Base Case'!$B$11*(1+'Base Case'!$B$18))*'Base Case'!$B$19)/(1+0.085)^1+((('Base Case'!$B$11*(1+'Base Case'!$B$18))*(1+'Base Case'!$C$18))*'Base Case'!$C$19)/(1+0.085)^2+(((('Base Case'!$B$11*(1+'Base Case'!$B$18))*(1+'Base Case'!$C$18))*(1+'Base Case'!$D$18))*'Base Case'!$D$19)/(1+0.085)^3+((((('Base Case'!$B$11*(1+'Base Case'!$B$18))*(1+'Base Case'!$C$18))*(1+'Base Case'!$D$18))*(1+'Base Case'!$E$18))*'Base Case'!$E$19)/(1+0.085)^4+(((((('Base Case'!$B$11*(1+'Base Case'!$B$18))*(1+'Base Case'!$C$18))*(1+'Base Case'!$D$18))*(1+'Base Case'!$E$18))*(1+'Base Case'!$F$18))*'Base Case'!$F$19)/(1+0.085)^5)+(((((((('Base Case'!$B$11*(1+'Base Case'!$B$18))*(1+'Base Case'!$C$18))*(1+'Base Case'!$D$18))*(1+'Base Case'!$E$18))*(1+'Base Case'!$F$18))*'Base Case'!$F$19)*(1+0.0175))/(0.085-0.0175))/(1+0.085)^5)-'Base Case'!$B$10)/'Base Case'!$B$6 | C6: =((((('Base Case'!$B$11*(1+'Base Case'!$B$18))*'Base Case'!$B$19)/(1+0.085)^1+((('Base Case'!$B$11*(1+'Base Case'!$B$18))*(1+'Base Case'!$C$18))*'Base Case'!$C$19)/(1+0.085)^2+(((('Base Case'!$B$11*(1+'Base Case'!$B$18))*(1+'Base Case'!$C$18))*(1+'Base Case'!$D$18))*'Base Case'!$D$19)/(1+0.085)^3+((((('Base Case'!$B$11*(1+'Base Case'!$B$18))*(1+'Base Case'!$C$18))*(1+'Base Case'!$D$18))*(1+'Base Case'!$E$18))*'Base Case'!$E$19)/(1+0.085)^4+(((((('Base Case'!$B$11*(1+'Base Case'!$B$18))*(1+'Base Case'!$C$18))*(1+'Base Case'!$D$18))*(1+'Base Case'!$E$18))*(1+'Base Case'!$F$18))*'Base Case'!$F$19)/(1+0.085)^5)+(((((((('Base Case'!$B$11*(1+'Base Case'!$B$18))*(1+'Base Case'!$C$18))*(1+'Base Case'!$D$18))*(1+'Base Case'!$E$18))*(1+'Base Case'!$F$18))*'Base Case'!$F$19)*(1+0.0225))/(0.085-0.0225))/(1+0.085)^5)-'Base Case'!$B$10)/'Base Case'!$B$6 | D6: =((((('Base Case'!$B$11*(1+'Base Case'!$B$18))*'Base Case'!$B$19)/(1+0.085)^1+((('Base Case'!$B$11*(1+'Base Case'!$B$18))*(1+'Base Case'!$C$18))*'Base Case'!$C$19)/(1+0.085)^2+(((('Base Case'!$B$11*(1+'Base Case'!$B$18))*(1+'Base Case'!$C$18))*(1+'Base Case'!$D$18))*'Base Case'!$D$19)/(1+0.085)^3+((((('Base Case'!$B$11*(1+'Base Case'!$B$18))*(1+'Base Case'!$C$18))*(1+'Base Case'!$D$18))*(1+'Base Case'!$E$18))*'Base Case'!$E$19)/(1+0.085)^4+(((((('Base Case'!$B$11*(1+'Base Case'!$B$18))*(1+'Base Case'!$C$18))*(1+'Base Case'!$D$18))*(1+'Base Case'!$E$18))*(1+'Base Case'!$F$18))*'Base Case'!$F$19)/(1+0.085)^5)+(((((((('Base Case'!$B$11*(1+'Base Case'!$B$18))*(1+'Base Case'!$C$18))*(1+'Base Case'!$D$18))*(1+'Base Case'!$E$18))*(1+'Base Case'!$F$18))*'Base Case'!$F$19)*(1+0.0275))/(0.085-0.0275))/(1+0.085)^5)-'Base Case'!$B$10)/'Base Case'!$B$6 | E6: =((((('Base Case'!$B$11*(1+'Base Case'!$B$18))*'Base Case'!$B$19)/(1+0.085)^1+((('Base Case'!$B$11*(1+'Base Case'!$B$18))*(1+'Base Case'!$C$18))*'Base Case'!$C$19)/(1+0.085)^2+(((('Base Case'!$B$11*(1+'Base Case'!$B$18))*(1+'Base Case'!$C$18))*(1+'Base Case'!$D$18))*'Base Case'!$D$19)/(1+0.085)^3+((((('Base Case'!$B$11*(1+'Base Case'!$B$18))*(1+'Base Case'!$C$18))*(1+'Base Case'!$D$18))*(1+'Base Case'!$E$18))*'Base Case'!$E$19)/(1+0.085)^4+(((((('Base Case'!$B$11*(1+'Base Case'!$B$18))*(1+'Base Case'!$C$18))*(1+'Base Case'!$D$18))*(1+'Base Case'!$E$18))*(1+'Base Case'!$F$18))*'Base Case'!$F$19)/(1+0.085)^5)+(((((((('Base Case'!$B$11*(1+'Base Case'!$B$18))*(1+'Base Case'!$C$18))*(1+'Base Case'!$D$18))*(1+'Base Case'!$E$18))*(1+'Base Case'!$F$18))*'Base Case'!$F$19)*(1+0.0325))/(0.085-0.0325))/(1+0.085)^5)-'Base Case'!$B$10)/'Base Case'!$B$6 | F6: =((((('Base Case'!$B$11*(1+'Base Case'!$B$18))*'Base Case'!$B$19)/(1+0.085)^1+((('Base Case'!$B$11*(1+'Base Case'!$B$18))*(1+'Base Case'!$C$18))*'Base Case'!$C$19)/(1+0.085)^2+(((('Base Case'!$B$11*(1+'Base Case'!$B$18))*(1+'Base Case'!$C$18))*(1+'Base Case'!$D$18))*'Base Case'!$D$19)/(1+0.085)^3+((((('Base Case'!$B$11*(1+'Base Case'!$B$18))*(1+'Base Case'!$C$18))*(1+'Base Case'!$D$18))*(1+'Base Case'!$E$18))*'Base Case'!$E$19)/(1+0.085)^4+(((((('Base Case'!$B$11*(1+'Base Case'!$B$18))*(1+'Base Case'!$C$18))*(1+'Base Case'!$D$18))*(1+'Base Case'!$E$18))*(1+'Base Case'!$F$18))*'Base Case'!$F$19)/(1+0.085)^5)+(((((((('Base Case'!$B$11*(1+'Base Case'!$B$18))*(1+'Base Case'!$C$18))*(1+'Base Case'!$D$18))*(1+'Base Case'!$E$18))*(1+'Base Case'!$F$18))*'Base Case'!$F$19)*(1+0.0375))/(0.085-0.0375))/(1+0.085)^5)-'Base Case'!$B$10)/'Base Case'!$B$6
A7: 0.095 | B7: =((((('Base Case'!$B$11*(1+'Base Case'!$B$18))*'Base Case'!$B$19)/(1+0.095)^1+((('Base Case'!$B$11*(1+'Base Case'!$B$18))*(1+'Base Case'!$C$18))*'Base Case'!$C$19)/(1+0.095)^2+(((('Base Case'!$B$11*(1+'Base Case'!$B$18))*(1+'Base Case'!$C$18))*(1+'Base Case'!$D$18))*'Base Case'!$D$19)/(1+0.095)^3+((((('Base Case'!$B$11*(1+'Base Case'!$B$18))*(1+'Base Case'!$C$18))*(1+'Base Case'!$D$18))*(1+'Base Case'!$E$18))*'Base Case'!$E$19)/(1+0.095)^4+(((((('Base Case'!$B$11*(1+'Base Case'!$B$18))*(1+'Base Case'!$C$18))*(1+'Base Case'!$D$18))*(1+'Base Case'!$E$18))*(1+'Base Case'!$F$18))*'Base Case'!$F$19)/(1+0.095)^5)+(((((((('Base Case'!$B$11*(1+'Base Case'!$B$18))*(1+'Base Case'!$C$18))*(1+'Base Case'!$D$18))*(1+'Base Case'!$E$18))*(1+'Base Case'!$F$18))*'Base Case'!$F$19)*(1+0.0175))/(0.095-0.0175))/(1+0.095)^5)-'Base Case'!$B$10)/'Base Case'!$B$6 | C7: =((((('Base Case'!$B$11*(1+'Base Case'!$B$18))*'Base Case'!$B$19)/(1+0.095)^1+((('Base Case'!$B$11*(1+'Base Case'!$B$18))*(1+'Base Case'!$C$18))*'Base Case'!$C$19)/(1+0.095)^2+(((('Base Case'!$B$11*(1+'Base Case'!$B$18))*(1+'Base Case'!$C$18))*(1+'Base Case'!$D$18))*'Base Case'!$D$19)/(1+0.095)^3+((((('Base Case'!$B$11*(1+'Base Case'!$B$18))*(1+'Base Case'!$C$18))*(1+'Base Case'!$D$18))*(1+'Base Case'!$E$18))*'Base Case'!$E$19)/(1+0.095)^4+(((((('Base Case'!$B$11*(1+'Base Case'!$B$18))*(1+'Base Case'!$C$18))*(1+'Base Case'!$D$18))*(1+'Base Case'!$E$18))*(1+'Base Case'!$F$18))*'Base Case'!$F$19)/(1+0.095)^5)+(((((((('Base Case'!$B$11*(1+'Base Case'!$B$18))*(1+'Base Case'!$C$18))*(1+'Base Case'!$D$18))*(1+'Base Case'!$E$18))*(1+'Base Case'!$F$18))*'Base Case'!$F$19)*(1+0.0225))/(0.095-0.0225))/(1+0.095)^5)-'Base Case'!$B$10)/'Base Case'!$B$6 | D7: =((((('Base Case'!$B$11*(1+'Base Case'!$B$18))*'Base Case'!$B$19)/(1+0.095)^1+((('Base Case'!$B$11*(1+'Base Case'!$B$18))*(1+'Base Case'!$C$18))*'Base Case'!$C$19)/(1+0.095)^2+(((('Base Case'!$B$11*(1+'Base Case'!$B$18))*(1+'Base Case'!$C$18))*(1+'Base Case'!$D$18))*'Base Case'!$D$19)/(1+0.095)^3+((((('Base Case'!$B$11*(1+'Base Case'!$B$18))*(1+'Base Case'!$C$18))*(1+'Base Case'!$D$18))*(1+'Base Case'!$E$18))*'Base Case'!$E$19)/(1+0.095)^4+(((((('Base Case'!$B$11*(1+'Base Case'!$B$18))*(1+'Base Case'!$C$18))*(1+'Base Case'!$D$18))*(1+'Base Case'!$E$18))*(1+'Base Case'!$F$18))*'Base Case'!$F$19)/(1+0.095)^5)+(((((((('Base Case'!$B$11*(1+'Base Case'!$B$18))*(1+'Base Case'!$C$18))*(1+'Base Case'!$D$18))*(1+'Base Case'!$E$18))*(1+'Base Case'!$F$18))*'Base Case'!$F$19)*(1+0.0275))/(0.095-0.0275))/(1+0.095)^5)-'Base Case'!$B$10)/'Base Case'!$B$6 | E7: =((((('Base Case'!$B$11*(1+'Base Case'!$B$18))*'Base Case'!$B$19)/(1+0.095)^1+((('Base Case'!$B$11*(1+'Base Case'!$B$18))*(1+'Base Case'!$C$18))*'Base Case'!$C$19)/(1+0.095)^2+(((('Base Case'!$B$11*(1+'Base Case'!$B$18))*(1+'Base Case'!$C$18))*(1+'Base Case'!$D$18))*'Base Case'!$D$19)/(1+0.095)^3+((((('Base Case'!$B$11*(1+'Base Case'!$B$18))*(1+'Base Case'!$C$18))*(1+'Base Case'!$D$18))*(1+'Base Case'!$E$18))*'Base Case'!$E$19)/(1+0.095)^4+(((((('Base Case'!$B$11*(1+'Base Case'!$B$18))*(1+'Base Case'!$C$18))*(1+'Base Case'!$D$18))*(1+'Base Case'!$E$18))*(1+'Base Case'!$F$18))*'Base Case'!$F$19)/(1+0.095)^5)+(((((((('Base Case'!$B$11*(1+'Base Case'!$B$18))*(1+'Base Case'!$C$18))*(1+'Base Case'!$D$18))*(1+'Base Case'!$E$18))*(1+'Base Case'!$F$18))*'Base Case'!$F$19)*(1+0.0325))/(0.095-0.0325))/(1+0.095)^5)-'Base Case'!$B$10)/'Base Case'!$B$6 | F7: =((((('Base Case'!$B$11*(1+'Base Case'!$B$18))*'Base Case'!$B$19)/(1+0.095)^1+((('Base Case'!$B$11*(1+'Base Case'!$B$18))*(1+'Base Case'!$C$18))*'Base Case'!$C$19)/(1+0.095)^2+(((('Base Case'!$B$11*(1+'Base Case'!$B$18))*(1+'Base Case'!$C$18))*(1+'Base Case'!$D$18))*'Base Case'!$D$19)/(1+0.095)^3+((((('Base Case'!$B$11*(1+'Base Case'!$B$18))*(1+'Base Case'!$C$18))*(1+'Base Case'!$D$18))*(1+'Base Case'!$E$18))*'Base Case'!$E$19)/(1+0.095)^4+(((((('Base Case'!$B$11*(1+'Base Case'!$B$18))*(1+'Base Case'!$C$18))*(1+'Base Case'!$D$18))*(1+'Base Case'!$E$18))*(1+'Base Case'!$F$18))*'Base Case'!$F$19)/(1+0.095)^5)+(((((((('Base Case'!$B$11*(1+'Base Case'!$B$18))*(1+'Base Case'!$C$18))*(1+'Base Case'!$D$18))*(1+'Base Case'!$E$18))*(1+'Base Case'!$F$18))*'Base Case'!$F$19)*(1+0.0375))/(0.095-0.0375))/(1+0.095)^5)-'Base Case'!$B$10)/'Base Case'!$B$6
A8: 0.105 | B8: =((((('Base Case'!$B$11*(1+'Base Case'!$B$18))*'Base Case'!$B$19)/(1+0.105)^1+((('Base Case'!$B$11*(1+'Base Case'!$B$18))*(1+'Base Case'!$C$18))*'Base Case'!$C$19)/(1+0.105)^2+(((('Base Case'!$B$11*(1+'Base Case'!$B$18))*(1+'Base Case'!$C$18))*(1+'Base Case'!$D$18))*'Base Case'!$D$19)/(1+0.105)^3+((((('Base Case'!$B$11*(1+'Base Case'!$B$18))*(1+'Base Case'!$C$18))*(1+'Base Case'!$D$18))*(1+'Base Case'!$E$18))*'Base Case'!$E$19)/(1+0.105)^4+(((((('Base Case'!$B$11*(1+'Base Case'!$B$18))*(1+'Base Case'!$C$18))*(1+'Base Case'!$D$18))*(1+'Base Case'!$E$18))*(1+'Base Case'!$F$18))*'Base Case'!$F$19)/(1+0.105)^5)+(((((((('Base Case'!$B$11*(1+'Base Case'!$B$18))*(1+'Base Case'!$C$18))*(1+'Base Case'!$D$18))*(1+'Base Case'!$E$18))*(1+'Base Case'!$F$18))*'Base Case'!$F$19)*(1+0.0175))/(0.105-0.0175))/(1+0.105)^5)-'Base Case'!$B$10)/'Base Case'!$B$6 | C8: =((((('Base Case'!$B$11*(1+'Base Case'!$B$18))*'Base Case'!$B$19)/(1+0.105)^1+((('Base Case'!$B$11*(1+'Base Case'!$B$18))*(1+'Base Case'!$C$18))*'Base Case'!$C$19)/(1+0.105)^2+(((('Base Case'!$B$11*(1+'Base Case'!$B$18))*(1+'Base Case'!$C$18))*(1+'Base Case'!$D$18))*'Base Case'!$D$19)/(1+0.105)^3+((((('Base Case'!$B$11*(1+'Base Case'!$B$18))*(1+'Base Case'!$C$18))*(1+'Base Case'!$D$18))*(1+'Base Case'!$E$18))*'Base Case'!$E$19)/(1+0.105)^4+(((((('Base Case'!$B$11*(1+'Base Case'!$B$18))*(1+'Base Case'!$C$18))*(1+'Base Case'!$D$18))*(1+'Base Case'!$E$18))*(1+'Base Case'!$F$18))*'Base Case'!$F$19)/(1+0.105)^5)+(((((((('Base Case'!$B$11*(1+'Base Case'!$B$18))*(1+'Base Case'!$C$18))*(1+'Base Case'!$D$18))*(1+'Base Case'!$E$18))*(1+'Base Case'!$F$18))*'Base Case'!$F$19)*(1+0.0225))/(0.105-0.0225))/(1+0.105)^5)-'Base Case'!$B$10)/'Base Case'!$B$6 | D8: =((((('Base Case'!$B$11*(1+'Base Case'!$B$18))*'Base Case'!$B$19)/(1+0.105)^1+((('Base Case'!$B$11*(1+'Base Case'!$B$18))*(1+'Base Case'!$C$18))*'Base Case'!$C$19)/(1+0.105)^2+(((('Base Case'!$B$11*(1+'Base Case'!$B$18))*(1+'Base Case'!$C$18))*(1+'Base Case'!$D$18))*'Base Case'!$D$19)/(1+0.105)^3+((((('Base Case'!$B$11*(1+'Base Case'!$B$18))*(1+'Base Case'!$C$18))*(1+'Base Case'!$D$18))*(1+'Base Case'!$E$18))*'Base Case'!$E$19)/(1+0.105)^4+(((((('Base Case'!$B$11*(1+'Base Case'!$B$18))*(1+'Base Case'!$C$18))*(1+'Base Case'!$D$18))*(1+'Base Case'!$E$18))*(1+'Base Case'!$F$18))*'Base Case'!$F$19)/(1+0.105)^5)+(((((((('Base Case'!$B$11*(1+'Base Case'!$B$18))*(1+'Base Case'!$C$18))*(1+'Base Case'!$D$18))*(1+'Base Case'!$E$18))*(1+'Base Case'!$F$18))*'Base Case'!$F$19)*(1+0.0275))/(0.105-0.0275))/(1+0.105)^5)-'Base Case'!$B$10)/'Base Case'!$B$6 | E8: =((((('Base Case'!$B$11*(1+'Base Case'!$B$18))*'Base Case'!$B$19)/(1+0.105)^1+((('Base Case'!$B$11*(1+'Base Case'!$B$18))*(1+'Base Case'!$C$18))*'Base Case'!$C$19)/(1+0.105)^2+(((('Base Case'!$B$11*(1+'Base Case'!$B$18))*(1+'Base Case'!$C$18))*(1+'Base Case'!$D$18))*'Base Case'!$D$19)/(1+0.105)^3+((((('Base Case'!$B$11*(1+'Base Case'!$B$18))*(1+'Base Case'!$C$18))*(1+'Base Case'!$D$18))*(1+'Base Case'!$E$18))*'Base Case'!$E$19)/(1+0.105)^4+(((((('Base Case'!$B$11*(1+'Base Case'!$B$18))*(1+'Base Case'!$C$18))*(1+'Base Case'!$D$18))*(1+'Base Case'!$E$18))*(1+'Base Case'!$F$18))*'Base Case'!$F$19)/(1+0.105)^5)+(((((((('Base Case'!$B$11*(1+'Base Case'!$B$18))*(1+'Base Case'!$C$18))*(1+'Base Case'!$D$18))*(1+'Base Case'!$E$18))*(1+'Base Case'!$F$18))*'Base Case'!$F$19)*(1+0.0325))/(0.105-0.0325))/(1+0.105)^5)-'Base Case'!$B$10)/'Base Case'!$B$6 | F8: =((((('Base Case'!$B$11*(1+'Base Case'!$B$18))*'Base Case'!$B$19)/(1+0.105)^1+((('Base Case'!$B$11*(1+'Base Case'!$B$18))*(1+'Base Case'!$C$18))*'Base Case'!$C$19)/(1+0.105)^2+(((('Base Case'!$B$11*(1+'Base Case'!$B$18))*(1+'Base Case'!$C$18))*(1+'Base Case'!$D$18))*'Base Case'!$D$19)/(1+0.105)^3+((((('Base Case'!$B$11*(1+'Base Case'!$B$18))*(1+'Base Case'!$C$18))*(1+'Base Case'!$D$18))*(1+'Base Case'!$E$18))*'Base Case'!$E$19)/(1+0.105)^4+(((((('Base Case'!$B$11*(1+'Base Case'!$B$18))*(1+'Base Case'!$C$18))*(1+'Base Case'!$D$18))*(1+'Base Case'!$E$18))*(1+'Base Case'!$F$18))*'Base Case'!$F$19)/(1+0.105)^5)+(((((((('Base Case'!$B$11*(1+'Base Case'!$B$18))*(1+'Base Case'!$C$18))*(1+'Base Case'!$D$18))*(1+'Base Case'!$E$18))*(1+'Base Case'!$F$18))*'Base Case'!$F$19)*(1+0.0375))/(0.105-0.0375))/(1+0.105)^5)-'Base Case'!$B$10)/'Base Case'!$B$6
A9: 0.115 | B9: =((((('Base Case'!$B$11*(1+'Base Case'!$B$18))*'Base Case'!$B$19)/(1+0.115)^1+((('Base Case'!$B$11*(1+'Base Case'!$B$18))*(1+'Base Case'!$C$18))*'Base Case'!$C$19)/(1+0.115)^2+(((('Base Case'!$B$11*(1+'Base Case'!$B$18))*(1+'Base Case'!$C$18))*(1+'Base Case'!$D$18))*'Base Case'!$D$19)/(1+0.115)^3+((((('Base Case'!$B$11*(1+'Base Case'!$B$18))*(1+'Base Case'!$C$18))*(1+'Base Case'!$D$18))*(1+'Base Case'!$E$18))*'Base Case'!$E$19)/(1+0.115)^4+(((((('Base Case'!$B$11*(1+'Base Case'!$B$18))*(1+'Base Case'!$C$18))*(1+'Base Case'!$D$18))*(1+'Base Case'!$E$18))*(1+'Base Case'!$F$18))*'Base Case'!$F$19)/(1+0.115)^5)+(((((((('Base Case'!$B$11*(1+'Base Case'!$B$18))*(1+'Base Case'!$C$18))*(1+'Base Case'!$D$18))*(1+'Base Case'!$E$18))*(1+'Base Case'!$F$18))*'Base Case'!$F$19)*(1+0.0175))/(0.115-0.0175))/(1+0.115)^5)-'Base Case'!$B$10)/'Base Case'!$B$6 | C9: =((((('Base Case'!$B$11*(1+'Base Case'!$B$18))*'Base Case'!$B$19)/(1+0.115)^1+((('Base Case'!$B$11*(1+'Base Case'!$B$18))*(1+'Base Case'!$C$18))*'Base Case'!$C$19)/(1+0.115)^2+(((('Base Case'!$B$11*(1+'Base Case'!$B$18))*(1+'Base Case'!$C$18))*(1+'Base Case'!$D$18))*'Base Case'!$D$19)/(1+0.115)^3+((((('Base Case'!$B$11*(1+'Base Case'!$B$18))*(1+'Base Case'!$C$18))*(1+'Base Case'!$D$18))*(1+'Base Case'!$E$18))*'Base Case'!$E$19)/(1+0.115)^4+(((((('Base Case'!$B$11*(1+'Base Case'!$B$18))*(1+'Base Case'!$C$18))*(1+'Base Case'!$D$18))*(1+'Base Case'!$E$18))*(1+'Base Case'!$F$18))*'Base Case'!$F$19)/(1+0.115)^5)+(((((((('Base Case'!$B$11*(1+'Base Case'!$B$18))*(1+'Base Case'!$C$18))*(1+'Base Case'!$D$18))*(1+'Base Case'!$E$18))*(1+'Base Case'!$F$18))*'Base Case'!$F$19)*(1+0.0225))/(0.115-0.0225))/(1+0.115)^5)-'Base Case'!$B$10)/'Base Case'!$B$6 | D9: =((((('Base Case'!$B$11*(1+'Base Case'!$B$18))*'Base Case'!$B$19)/(1+0.115)^1+((('Base Case'!$B$11*(1+'Base Case'!$B$18))*(1+'Base Case'!$C$18))*'Base Case'!$C$19)/(1+0.115)^2+(((('Base Case'!$B$11*(1+'Base Case'!$B$18))*(1+'Base Case'!$C$18))*(1+'Base Case'!$D$18))*'Base Case'!$D$19)/(1+0.115)^3+((((('Base Case'!$B$11*(1+'Base Case'!$B$18))*(1+'Base Case'!$C$18))*(1+'Base Case'!$D$18))*(1+'Base Case'!$E$18))*'Base Case'!$E$19)/(1+0.115)^4+(((((('Base Case'!$B$11*(1+'Base Case'!$B$18))*(1+'Base Case'!$C$18))*(1+'Base Case'!$D$18))*(1+'Base Case'!$E$18))*(1+'Base Case'!$F$18))*'Base Case'!$F$19)/(1+0.115)^5)+(((((((('Base Case'!$B$11*(1+'Base Case'!$B$18))*(1+'Base Case'!$C$18))*(1+'Base Case'!$D$18))*(1+'Base Case'!$E$18))*(1+'Base Case'!$F$18))*'Base Case'!$F$19)*(1+0.0275))/(0.115-0.0275))/(1+0.115)^5)-'Base Case'!$B$10)/'Base Case'!$B$6 | E9: =((((('Base Case'!$B$11*(1+'Base Case'!$B$18))*'Base Case'!$B$19)/(1+0.115)^1+((('Base Case'!$B$11*(1+'Base Case'!$B$18))*(1+'Base Case'!$C$18))*'Base Case'!$C$19)/(1+0.115)^2+(((('Base Case'!$B$11*(1+'Base Case'!$B$18))*(1+'Base Case'!$C$18))*(1+'Base Case'!$D$18))*'Base Case'!$D$19)/(1+0.115)^3+((((('Base Case'!$B$11*(1+'Base Case'!$B$18))*(1+'Base Case'!$C$18))*(1+'Base Case'!$D$18))*(1+'Base Case'!$E$18))*'Base Case'!$E$19)/(1+0.115)^4+(((((('Base Case'!$B$11*(1+'Base Case'!$B$18))*(1+'Base Case'!$C$18))*(1+'Base Case'!$D$18))*(1+'Base Case'!$E$18))*(1+'Base Case'!$F$18))*'Base Case'!$F$19)/(1+0.115)^5)+(((((((('Base Case'!$B$11*(1+'Base Case'!$B$18))*(1+'Base Case'!$C$18))*(1+'Base Case'!$D$18))*(1+'Base Case'!$E$18))*(1+'Base Case'!$F$18))*'Base Case'!$F$19)*(1+0.0325))/(0.115-0.0325))/(1+0.115)^5)-'Base Case'!$B$10)/'Base Case'!$B$6 | F9: =((((('Base Case'!$B$11*(1+'Base Case'!$B$18))*'Base Case'!$B$19)/(1+0.115)^1+((('Base Case'!$B$11*(1+'Base Case'!$B$18))*(1+'Base Case'!$C$18))*'Base Case'!$C$19)/(1+0.115)^2+(((('Base Case'!$B$11*(1+'Base Case'!$B$18))*(1+'Base Case'!$C$18))*(1+'Base Case'!$D$18))*'Base Case'!$D$19)/(1+0.115)^3+((((('Base Case'!$B$11*(1+'Base Case'!$B$18))*(1+'Base Case'!$C$18))*(1+'Base Case'!$D$18))*(1+'Base Case'!$E$18))*'Base Case'!$E$19)/(1+0.115)^4+(((((('Base Case'!$B$11*(1+'Base Case'!$B$18))*(1+'Base Case'!$C$18))*(1+'Base Case'!$D$18))*(1+'Base Case'!$E$18))*(1+'Base Case'!$F$18))*'Base Case'!$F$19)/(1+0.115)^5)+(((((((('Base Case'!$B$11*(1+'Base Case'!$B$18))*(1+'Base Case'!$C$18))*(1+'Base Case'!$D$18))*(1+'Base Case'!$E$18))*(1+'Base Case'!$F$18))*'Base Case'!$F$19)*(1+0.0375))/(0.115-0.0375))/(1+0.115)^5)-'Base Case'!$B$10)/'Base Case'!$B$6
A11: Note: Matrix uses Base Case revenue growth & FCF margin path; only WACC and terminal growth vary.

Sheet Historical
A1: Historical Growth Rates
A3: Metric | B3: 3-Year CAGR | C3: 5-Year CAGR
A4: Revenue | B4: 0.117 | C4: 0.132
A5: EPS | B5: N/A | C5: 0.28
A6: Equity/Book Value | B6: 0.412 | C6: 0.345
A7: Free Cash Flow | B7: N/A | C7: N/A
A9: Selected Growth Driver: | B9: 0.117
A10: Source: | B10: revenue_3yr_cagr (with 5yr cagr of 13.2% as corroborating upper bound)
A12: Divergence Warning:
A13: Equity CAGR (41.2% 3yr / 34.5% 5yr) diverges massively (>200%) from revenue CAGR (11.7%/13.2%). This is NOT treated as a red flag on revenue quality -- it reflects that Amazon retains 100% of net income (no dividends, minimal buybacks in this window) while GAAP net income has been inflated by large non-cash equity-stake gains (Rivian warrants, Anthropic investment mark-ups: +$15.2B in FY2025, +$16.8B in Q1 2026 alone) that compound book value far faster than the underlying operating business. Per standard practice, equity CAGR is REJECTED as the growth driver here and revenue CAGR is used instead, consistent with the task-level guidance for this ticker.
A16: Historical Revenue & FCF (FY2016-FY2025, $M)
A18: Period | B18: Revenue | C18: FCF
A19: FY2016 | B19: 135987 | C19: 10535
A20: FY2017 | B20: 177866 | C20: 8376
A21: FY2018 | B21: 232887 | C21: 19400
A22: FY2019 | B22: 280522 | C22: 25825
A23: FY2020 | B23: 386064 | C23: 31020
A24: FY2021 | B24: 469822 | C24: -9069
A25: FY2022 | B25: 513983 | C25: -11569
A26: FY2023 | B26: 574785 | C26: 36813
A27: FY2024 | B27: 637959 | C27: 38219
A28: FY2025 | B28: 716924 | C28: 11194
