Workbook

Sheet Inputs
A1: AGY.AX — Argosy Minerals — Risked Project-NPV Model (2026-09-21)
A3: Model | B3: Risked project-NPV (sum-of-parts): P(funded FID) x Argosy carried share x project NPV + net cash + raise - burn - overhead
A4: Why not owner-FCF DCF | B4: Pre-revenue single-asset developer; historical FCF is overhead + JV advances
A6: Current price (A$) | B6: 0.033
A7: Price as of | B7: 2026-09-21T06:10:31Z regular close (ASX)
A8: AUDUSD | B8: 0.7132
A9: Shares (m, 31-Dec-2025) | B9: 1543.42
A10: Net cash (A$m, 31-Dec-2025) | B10: 4.165
A11: Listed options (m) | B11: 40
A12: Option strike (A$) | B12: 0.04
A13: Resource (kt LCE) | B13: 731.801
A14: Expert FV of 77.5% (A$m, Dec-24) | B14: 75.9
A15: Weight bear | B15: 0.5
A16: Weight base | B16: 0.35
A17: Weight bull | B17: 0.15
A18: Hurdle | B18: 0.15

Sheet Base_CF
A1: Base_CF: 100% project, real US$m, unlevered post-tax. t=1 is calendar 2027.
A2: Lithium price (US$/t real) | B2: 15000
A3: Opex (US$/t) | B3: 5500
A4: Freight/marketing (US$/t) | B4: 300
A5: Royalty + export duty | B5: 0.075
A6: Tax rate | B6: 0.35
A7: Initial capex (US$m) | B7: 250
A8: Sustaining capex % of initial | B8: 0.03
A9: WC % of revenue change | B9: 0.1
A10: Tax depreciation years | B10: 10
A11: Real discount rate | B11: 0.12
A12: First production t | B12: 5
A13: Nameplate tpa | B13: 12000
... A21: Hurdle rate | B21: 0.15
A23: t | B23: 1 | C23: 2 | D23: 3 | E23: 4 | F23: 5 | G23: 6 | H23: 7 | I23: 8 | J23: 9 | K23: 10 | L23: 11 | M23: 12 | N23: 13 | O23: 14 | P23: 15 | Q23: 16 | R23: 17 | S23: 18 | T23: 19 | U23: 20 | V23: 21 | W23: 22 | X23: 23 | Y23: 24 | Z23: 25 | AA23: 26 | AB23: 27 | AC23: 28 | AD23: 29 | AE23: 30
A24: Year | B24: =2026+B23 | C24: =2026+C23 | D24: =2026+D23 | E24: =2026+E23 | F24: =2026+F23 | G24: =2026+G23 | H24: =2026+H23 | I24: =2026+I23 | ... AE24: =2026+AE23
A25: k = t - first_t | B25: =B23-$B$12 | C25: =C23-$B$12 | D25: =D23-$B$12 | E25: =E23-$B$12 | F25: =F23-$B$12 | G25: =G23-$B$12 | H25: =H23-$B$12 | I25: =I23-$B$12 | ... AE25: =AE23-$B$12
A26: Utilisation | B26: =IF(OR(B25<0,B25>=$B$16),0,IF(B25=0,$B$14,IF(B25=1,$B$15,1))) | C26: =IF(OR(C25<0,C25>=$B$16),0,IF(C25=0,$B$14,IF(C25=1,$B$15,1))) | D26: =IF(OR(D25<0,D25>=$B$16),0,IF(D25=0,$B$14,IF(D25=1,$B$15,1))) | E26: =IF(OR(E25<0,E25>=$B$16),0,IF(E25=0,$B$14,IF(E25=1,$B$15,1))) | F26: =IF(OR(F25<0,F25>=$B$16),0,IF(F25=0,$B$14,IF(F25=1,$B$15,1))) | G26: =IF(OR(G25<0,G25>=$B$16),0,IF(G25=0,$B$14,IF(G25=1,$B$15,1))) | H26: =IF(OR(H25<0,H25>=$B$16),0,IF(H25=0,$B$14,IF(H25=1,$B$15,1))) | I26: =IF(OR(I25<0,I25>=$B$16),0,IF(I25=0,$B$14,IF(I25=1,$B$15,1))) | ... AE26: =IF(OR(AE25<0,AE25>=$B$16),0,IF(AE25=0,$B$14,IF(AE25=1,$B$15,1)))
A27: Production (t) | B27: =$B$13*B26 | C27: =$B$13*C26 | D27: =$B$13*D26 | E27: =$B$13*E26 | F27: =$B$13*F26 | G27: =$B$13*G26 | H27: =$B$13*H26 | I27: =$B$13*I26 | ... AE27: =$B$13*AE26
A28: Revenue | B28: =B27*$B$2/1000000 | C28: =C27*$B$2/1000000 | D28: =D27*$B$2/1000000 | E28: =E27*$B$2/1000000 | F28: =F27*$B$2/1000000 | G28: =G27*$B$2/1000000 | H28: =H27*$B$2/1000000 | I28: =I27*$B$2/1000000 | ... AE28: =AE27*$B$2/1000000
A29: Levies | B29: =B28*$B$5 | C29: =C28*$B$5 | D29: =D28*$B$5 | E29: =E28*$B$5 | F29: =F28*$B$5 | G29: =G28*$B$5 | H29: =H28*$B$5 | I29: =I28*$B$5 | ... AE29: =AE28*$B$5
A30: Opex | B30: =B27*($B$3+$B$4)/1000000 | C30: =C27*($B$3+$B$4)/1000000 | D30: =D27*($B$3+$B$4)/1000000 | E30: =E27*($B$3+$B$4)/1000000 | F30: =F27*($B$3+$B$4)/1000000 | G30: =G27*($B$3+$B$4)/1000000 | H30: =H27*($B$3+$B$4)/1000000 | I30: =I27*($B$3+$B$4)/1000000 | ... AE30: =AE27*($B$3+$B$4)/1000000
A31: EBITDA | B31: =B28-B29-B30 | C31: =C28-C29-C30 | D31: =D28-D29-D30 | E31: =E28-E29-E30 | F31: =F28-F29-F30 | G31: =G28-G29-G30 | H31: =H28-H29-H30 | I31: =I28-I29-I30 | ... AE31: =AE28-AE29-AE30
A32: Capex | B32: =$B$7*(IF(B23=$B$17,$B$18,0)+IF(B23=$B$19,$B$20,0))+IF(AND(B25>=0,B25<$B$16),$B$7*$B$8,0) | C32: =$B$7*(IF(C23=$B$17,$B$18,0)+IF(C23=$B$19,$B$20,0))+IF(AND(C25>=0,C25<$B$16),$B$7*$B$8,0) | D32: =$B$7*(IF(D23=$B$17,$B$18,0)+IF(D23=$B$19,$B$20,0))+IF(AND(D25>=0,D25<$B$16),$B$7*$B$8,0) | E32: =$B$7*(IF(E23=$B$17,$B$18,0)+IF(E23=$B$19,$B$20,0))+IF(AND(E25>=0,E25<$B$16),$B$7*$B$8,0) | F32: =$B$7*(IF(F23=$B$17,$B$18,0)+IF(F23=$B$19,$B$20,0))+IF(AND(F25>=0,F25<$B$16),$B$7*$B$8,0) | G32: =$B$7*(IF(G23=$B$17,$B$18,0)+IF(G23=$B$19,$B$20,0))+IF(AND(G25>=0,G25<$B$16),$B$7*$B$8,0) | H32: =$B$7*(IF(H23=$B$17,$B$18,0)+IF(H23=$B$19,$B$20,0))+IF(AND(H25>=0,H25<$B$16),$B$7*$B$8,0) | I32: =$B$7*(IF(I23=$B$17,$B$18,0)+IF(I23=$B$19,$B$20,0))+IF(AND(I25>=0,I25<$B$16),$B$7*$B$8,0) | ... AE32: =$B$7*(IF(AE23=$B$17,$B$18,0)+IF(AE23=$B$19,$B$20,0))+IF(AND(AE25>=0,AE25<$B$16),$B$7*$B$8,0)
A33: Tax depreciation | B33: =IF(AND(B25>=0,B25<$B$10),$B$7/$B$10,0) | C33: =IF(AND(C25>=0,C25<$B$10),$B$7/$B$10,0) | D33: =IF(AND(D25>=0,D25<$B$10),$B$7/$B$10,0) | E33: =IF(AND(E25>=0,E25<$B$10),$B$7/$B$10,0) | F33: =IF(AND(F25>=0,F25<$B$10),$B$7/$B$10,0) | G33: =IF(AND(G25>=0,G25<$B$10),$B$7/$B$10,0) | H33: =IF(AND(H25>=0,H25<$B$10),$B$7/$B$10,0) | I33: =IF(AND(I25>=0,I25<$B$10),$B$7/$B$10,0) | ... AE33: =IF(AND(AE25>=0,AE25<$B$10),$B$7/$B$10,0)
A34: Cash tax | B34: =MAX(0,B31-B33)*$B$6 | C34: =MAX(0,C31-C33)*$B$6 | D34: =MAX(0,D31-D33)*$B$6 | E34: =MAX(0,E31-E33)*$B$6 | F34: =MAX(0,F31-F33)*$B$6 | G34: =MAX(0,G31-G33)*$B$6 | H34: =MAX(0,H31-H33)*$B$6 | I34: =MAX(0,I31-I33)*$B$6 | ... AE34: =MAX(0,AE31-AE33)*$B$6
A35: dWC | B35: =IF(B25>=$B$16,0,$B$9*(B28-0)) | C35: =IF(C25>=$B$16,0,$B$9*(C28-B28)) | D35: =IF(D25>=$B$16,0,$B$9*(D28-C28)) | E35: =IF(E25>=$B$16,0,$B$9*(E28-D28)) | F35: =IF(F25>=$B$16,0,$B$9*(F28-E28)) | G35: =IF(G25>=$B$16,0,$B$9*(G28-F28)) | H35: =IF(H25>=$B$16,0,$B$9*(H28-G28)) | I35: =IF(I25>=$B$16,0,$B$9*(I28-H28)) | J35: =IF(J25>=$B$16,0,$B$9*(J28-I28)) | ... AE35: =IF(AE25>=$B$16,0,$B$9*(AE28-AD28))
A36: FCF | B36: =B31-B34-B32-B35 | C36: =C31-C34-C32-C35 | D36: =D31-D34-D32-D35 | E36: =E31-E34-E32-E35 | F36: =F31-F34-F32-F35 | G36: =G31-G34-G32-G35 | H36: =H31-H34-H32-H35 | I36: =I31-I34-I32-I35 | ... AE36: =AE31-AE34-AE32-AE35
A37: DF | B37: =1/(1+$B$11)^B23 | C37: =1/(1+$B$11)^C23 | D37: =1/(1+$B$11)^D23 | E37: =1/(1+$B$11)^E23 | F37: =1/(1+$B$11)^F23 | G37: =1/(1+$B$11)^G23 | H37: =1/(1+$B$11)^H23 | I37: =1/(1+$B$11)^I23 | ... AE37: =1/(1+$B$11)^AE23
A38: PV | B38: =B36*B37 | C38: =C36*C37 | D38: =D36*D37 | E38: =E36*E37 | F38: =F36*F37 | G38: =G36*G37 | H38: =H36*H37 | I38: =I36*I37 | ... AE38: =AE36*AE37
A39: DF @ hurdle | B39: =1/(1+$B$21)^B23 | C39: =1/(1+$B$21)^C23 | D39: =1/(1+$B$21)^D23 | E39: =1/(1+$B$21)^E23 | F39: =1/(1+$B$21)^F23 | G39: =1/(1+$B$21)^G23 | H39: =1/(1+$B$21)^H23 | I39: =1/(1+$B$21)^I23 | ... AE39: =1/(1+$B$21)^AE23
A40: PV @ hurdle | B40: =B36*B39 | C40: =C36*C39 | D40: =D36*D39 | E40: =E36*E39 | F40: =F36*F39 | G40: =G36*G39 | H40: =H36*H39 | I40: =I36*I39 | ... AE40: =AE36*AE39
A42: Project NPV (US$m) | B42: =SUM(B38:AE38)
A43: Project NPV @ hurdle (US$m) | B43: =SUM(B40:AE40)

Sheet Bull_CF
A1: Bull_CF: 100% project, real US$m, unlevered post-tax. t=1 is calendar 2027.
A2: Lithium price (US$/t real) | B2: 17000
A3: Opex (US$/t) | B3: 5000
A4: Freight/marketing (US$/t) | B4: 300
A5: Royalty + export duty | B5: 0.045
A6: Tax rate | B6: 0.25
A7: Initial capex (US$m) | B7: 230
A8: Sustaining capex % of initial | B8: 0.03
A9: WC % of revenue change | B9: 0.1
A10: Tax depreciation years | B10: 10
A11: Real discount rate | B11: 0.12
A12: First production t | B12: 3
A13: Nameplate tpa | B13: 12000
... A21: Hurdle rate | B21: 0.15
A23: t | B23: 1 | C23: 2 | D23: 3 | E23: 4 | F23: 5 | G23: 6 | H23: 7 | I23: 8 | J23: 9 | K23: 10 | L23: 11 | M23: 12 | N23: 13 | O23: 14 | P23: 15 | Q23: 16 | R23: 17 | S23: 18 | T23: 19 | U23: 20 | V23: 21 | W23: 22 | X23: 23 | Y23: 24 | Z23: 25 | AA23: 26 | AB23: 27 | AC23: 28 | AD23: 29 | AE23: 30
A24: Year | B24: =2026+B23 | C24: =2026+C23 | D24: =2026+D23 | E24: =2026+E23 | F24: =2026+F23 | G24: =2026+G23 | H24: =2026+H23 | I24: =2026+I23 | ... AE24: =2026+AE23
A25: k = t - first_t | B25: =B23-$B$12 | C25: =C23-$B$12 | D25: =D23-$B$12 | E25: =E23-$B$12 | F25: =F23-$B$12 | G25: =G23-$B$12 | H25: =H23-$B$12 | I25: =I23-$B$12 | ... AE25: =AE23-$B$12
A26: Utilisation | B26: =IF(OR(B25<0,B25>=$B$16),0,IF(B25=0,$B$14,IF(B25=1,$B$15,1))) | C26: =IF(OR(C25<0,C25>=$B$16),0,IF(C25=0,$B$14,IF(C25=1,$B$15,1))) | D26: =IF(OR(D25<0,D25>=$B$16),0,IF(D25=0,$B$14,IF(D25=1,$B$15,1))) | E26: =IF(OR(E25<0,E25>=$B$16),0,IF(E25=0,$B$14,IF(E25=1,$B$15,1))) | F26: =IF(OR(F25<0,F25>=$B$16),0,IF(F25=0,$B$14,IF(F25=1,$B$15,1))) | G26: =IF(OR(G25<0,G25>=$B$16),0,IF(G25=0,$B$14,IF(G25=1,$B$15,1))) | H26: =IF(OR(H25<0,H25>=$B$16),0,IF(H25=0,$B$14,IF(H25=1,$B$15,1))) | I26: =IF(OR(I25<0,I25>=$B$16),0,IF(I25=0,$B$14,IF(I25=1,$B$15,1))) | ... AE26: =IF(OR(AE25<0,AE25>=$B$16),0,IF(AE25=0,$B$14,IF(AE25=1,$B$15,1)))
A27: Production (t) | B27: =$B$13*B26 | C27: =$B$13*C26 | D27: =$B$13*D26 | E27: =$B$13*E26 | F27: =$B$13*F26 | G27: =$B$13*G26 | H27: =$B$13*H26 | I27: =$B$13*I26 | ... AE27: =$B$13*AE26
A28: Revenue | B28: =B27*$B$2/1000000 | C28: =C27*$B$2/1000000 | D28: =D27*$B$2/1000000 | E28: =E27*$B$2/1000000 | F28: =F27*$B$2/1000000 | G28: =G27*$B$2/1000000 | H28: =H27*$B$2/1000000 | I28: =I27*$B$2/1000000 | ... AE28: =AE27*$B$2/1000000
A29: Levies | B29: =B28*$B$5 | C29: =C28*$B$5 | D29: =D28*$B$5 | E29: =E28*$B$5 | F29: =F28*$B$5 | G29: =G28*$B$5 | H29: =H28*$B$5 | I29: =I28*$B$5 | ... AE29: =AE28*$B$5
A30: Opex | B30: =B27*($B$3+$B$4)/1000000 | C30: =C27*($B$3+$B$4)/1000000 | D30: =D27*($B$3+$B$4)/1000000 | E30: =E27*($B$3+$B$4)/1000000 | F30: =F27*($B$3+$B$4)/1000000 | G30: =G27*($B$3+$B$4)/1000000 | H30: =H27*($B$3+$B$4)/1000000 | I30: =I27*($B$3+$B$4)/1000000 | ... AE30: =AE27*($B$3+$B$4)/1000000
A31: EBITDA | B31: =B28-B29-B30 | C31: =C28-C29-C30 | D31: =D28-D29-D30 | E31: =E28-E29-E30 | F31: =F28-F29-F30 | G31: =G28-G29-G30 | H31: =H28-H29-H30 | I31: =I28-I29-I30 | ... AE31: =AE28-AE29-AE30
A32: Capex | B32: =$B$7*(IF(B23=$B$17,$B$18,0)+IF(B23=$B$19,$B$20,0))+IF(AND(B25>=0,B25<$B$16),$B$7*$B$8,0) | C32: =$B$7*(IF(C23=$B$17,$B$18,0)+IF(C23=$B$19,$B$20,0))+IF(AND(C25>=0,C25<$B$16),$B$7*$B$8,0) | D32: =$B$7*(IF(D23=$B$17,$B$18,0)+IF(D23=$B$19,$B$20,0))+IF(AND(D25>=0,D25<$B$16),$B$7*$B$8,0) | E32: =$B$7*(IF(E23=$B$17,$B$18,0)+IF(E23=$B$19,$B$20,0))+IF(AND(E25>=0,E25<$B$16),$B$7*$B$8,0) | F32: =$B$7*(IF(F23=$B$17,$B$18,0)+IF(F23=$B$19,$B$20,0))+IF(AND(F25>=0,F25<$B$16),$B$7*$B$8,0) | G32: =$B$7*(IF(G23=$B$17,$B$18,0)+IF(G23=$B$19,$B$20,0))+IF(AND(G25>=0,G25<$B$16),$B$7*$B$8,0) | H32: =$B$7*(IF(H23=$B$17,$B$18,0)+IF(H23=$B$19,$B$20,0))+IF(AND(H25>=0,H25<$B$16),$B$7*$B$8,0) | I32: =$B$7*(IF(I23=$B$17,$B$18,0)+IF(I23=$B$19,$B$20,0))+IF(AND(I25>=0,I25<$B$16),$B$7*$B$8,0) | ... AE32: =$B$7*(IF(AE23=$B$17,$B$18,0)+IF(AE23=$B$19,$B$20,0))+IF(AND(AE25>=0,AE25<$B$16),$B$7*$B$8,0)
A33: Tax depreciation | B33: =IF(AND(B25>=0,B25<$B$10),$B$7/$B$10,0) | C33: =IF(AND(C25>=0,C25<$B$10),$B$7/$B$10,0) | D33: =IF(AND(D25>=0,D25<$B$10),$B$7/$B$10,0) | E33: =IF(AND(E25>=0,E25<$B$10),$B$7/$B$10,0) | F33: =IF(AND(F25>=0,F25<$B$10),$B$7/$B$10,0) | G33: =IF(AND(G25>=0,G25<$B$10),$B$7/$B$10,0) | H33: =IF(AND(H25>=0,H25<$B$10),$B$7/$B$10,0) | I33: =IF(AND(I25>=0,I25<$B$10),$B$7/$B$10,0) | ... AE33: =IF(AND(AE25>=0,AE25<$B$10),$B$7/$B$10,0)
A34: Cash tax | B34: =MAX(0,B31-B33)*$B$6 | C34: =MAX(0,C31-C33)*$B$6 | D34: =MAX(0,D31-D33)*$B$6 | E34: =MAX(0,E31-E33)*$B$6 | F34: =MAX(0,F31-F33)*$B$6 | G34: =MAX(0,G31-G33)*$B$6 | H34: =MAX(0,H31-H33)*$B$6 | I34: =MAX(0,I31-I33)*$B$6 | ... AE34: =MAX(0,AE31-AE33)*$B$6
A35: dWC | B35: =IF(B25>=$B$16,0,$B$9*(B28-0)) | C35: =IF(C25>=$B$16,0,$B$9*(C28-B28)) | D35: =IF(D25>=$B$16,0,$B$9*(D28-C28)) | E35: =IF(E25>=$B$16,0,$B$9*(E28-D28)) | F35: =IF(F25>=$B$16,0,$B$9*(F28-E28)) | G35: =IF(G25>=$B$16,0,$B$9*(G28-F28)) | H35: =IF(H25>=$B$16,0,$B$9*(H28-G28)) | I35: =IF(I25>=$B$16,0,$B$9*(I28-H28)) | J35: =IF(J25>=$B$16,0,$B$9*(J28-I28)) | ... AE35: =IF(AE25>=$B$16,0,$B$9*(AE28-AD28))
A36: FCF | B36: =B31-B34-B32-B35 | C36: =C31-C34-C32-C35 | D36: =D31-D34-D32-D35 | E36: =E31-E34-E32-E35 | F36: =F31-F34-F32-F35 | G36: =G31-G34-G32-G35 | H36: =H31-H34-H32-H35 | I36: =I31-I34-I32-I35 | ... AE36: =AE31-AE34-AE32-AE35
A37: DF | B37: =1/(1+$B$11)^B23 | C37: =1/(1+$B$11)^C23 | D37: =1/(1+$B$11)^D23 | E37: =1/(1+$B$11)^E23 | F37: =1/(1+$B$11)^F23 | G37: =1/(1+$B$11)^G23 | H37: =1/(1+$B$11)^H23 | I37: =1/(1+$B$11)^I23 | ... AE37: =1/(1+$B$11)^AE23
A38: PV | B38: =B36*B37 | C38: =C36*C37 | D38: =D36*D37 | E38: =E36*E37 | F38: =F36*F37 | G38: =G36*G37 | H38: =H36*H37 | I38: =I36*I37 | ... AE38: =AE36*AE37
A39: DF @ hurdle | B39: =1/(1+$B$21)^B23 | C39: =1/(1+$B$21)^C23 | D39: =1/(1+$B$21)^D23 | E39: =1/(1+$B$21)^E23 | F39: =1/(1+$B$21)^F23 | G39: =1/(1+$B$21)^G23 | H39: =1/(1+$B$21)^H23 | I39: =1/(1+$B$21)^I23 | ... AE39: =1/(1+$B$21)^AE23
A40: PV @ hurdle | B40: =B36*B39 | C40: =C36*C39 | D40: =D36*D39 | E40: =E36*E39 | F40: =F36*F39 | G40: =G36*G39 | H40: =H36*H39 | I40: =I36*I39 | ... AE40: =AE36*AE39
A42: Project NPV (US$m) | B42: =SUM(B38:AE38)
A43: Project NPV @ hurdle (US$m) | B43: =SUM(B40:AE40)

Sheet Valuation
A1: Equity bridge and per-share valuation (A$m unless noted)
B3: Bear | C3: Base | D3: Bull
A4: Project NPV (US$m, 100%) | B4: 0 | C4: ='Base_CF'!$B$42 | D4: ='Bull_CF'!$B$42
A5: Project NPV (A$m) | B5: 0 | C5: =C4/Inputs!$B$8 | D5: =D4/Inputs!$B$8
A6: Argosy effective share | C6: 0.4 | D6: 0.55
A7: Attributable NPV (A$m) | B7: =Inputs!$B$14*B9 | C7: =C5*C6 | D7: =D5*D6
A8: Net cash | B8: =Inputs!$B$10 | C8: =Inputs!$B$10 | D8: =Inputs!$B$10
A9: Bear: expert FV haircut retained | B9: 0.2
A10: Pre-FID raise (A$m) | B10: 5 | C10: 12 | D10: 6
A11: Raise price (A$) | B11: 0.02 | C11: 0.03 | D11: 0.06
A12: Pre-FID burn | B12: -5 | C12: -12 | D12: -6
A13: Post-FID overhead PV | B13: 0 | C13: -7 | D13: -7
A14: Options in the money? (1/0) | B14: 0 | C14: 0 | D14: 1
A15: Option proceeds | B15: =B14*Inputs!$B$11*Inputs!$B$12 | C15: =C14*Inputs!$B$11*Inputs!$B$12 | D15: =D14*Inputs!$B$11*Inputs!$B$12
A16: Equity value | B16: =B7+B8+B10+B12+B13+B15 | C16: =C7+C8+C10+C12+C13+C15 | D16: =D7+D8+D10+D12+D13+D15
A17: Shares (m) | B17: =Inputs!$B$9+B10/B11+B14*Inputs!$B$11 | C17: =Inputs!$B$9+C10/C11+C14*Inputs!$B$11 | D17: =Inputs!$B$9+D10/D11+D14*Inputs!$B$11
A18: IV per share (A$) | B18: =B16/B17 | C18: =C16/C17 | D18: =D16/D17
A19: Upside vs price | B19: =B18/Inputs!$B$6-1 | C19: =C18/Inputs!$B$6-1 | D19: =D18/Inputs!$B$6-1
A21: Weights | B21: =Inputs!$B$15 | C21: =Inputs!$B$16 | D21: =Inputs!$B$17
A22: Weighted IV (A$) | B22: =SUMPRODUCT(B18:D18,B21:D21)
A24: Entry price @ 15% hurdle
A25: Project NPV @ hurdle (US$m) | B25: 0 | C25: ='Base_CF'!$B$43 | D25: ='Bull_CF'!$B$43
A26: Equity @ hurdle (A$m) | B26: =B16/(1+Inputs!$B$18)^2 | C26: =C25/Inputs!$B$8*C6+C8+C10+C12+C13+C15 | D26: =D25/Inputs!$B$8*D6+D8+D10+D12+D13+D15
A27: Entry price (A$) | B27: =B26/B17 | C27: =C26/C17 | D27: =D26/D17
A28: Weighted entry price (A$) | B28: =SUMPRODUCT(B27:D27,B21:D21)

Sheet Sensitivity
A1: Base IV A$/share — lithium price (rows, US$/t) x real discount rate (cols). Static values from model script; base structure, unweighted.
B2: 8 | C2: 10 | D2: 12 | E2: 14 | F2: 16
A3: 11000 | B3: 0.0098 | C3: -0.0006 | D3: -0.0077 | E3: -0.0126 | F3: -0.0158
A4: 13000 | B4: 0.0402 | C4: 0.0232 | D4: 0.0112 | E4: 0.0027 | F4: -0.0034
A5: 15000 | B5: 0.07 | C5: 0.0468 | D5: 0.0301 | E5: 0.0179 | F5: 0.0091
A6: 17000 | B6: 0.0998 | C6: 0.0701 | D6: 0.0488 | E6: 0.0332 | F6: 0.0216
A7: 19000 | B7: 0.1296 | C7: 0.0934 | D7: 0.0673 | E7: 0.0483 | F7: 0.034
A8: 21000 | B8: 0.1594 | C8: 0.1167 | D8: 0.0858 | E8: 0.0632 | F8: 0.0464
A10: Weighted IV vs P(bear) | B10: 0.3 | C10: 0.4 | D10: 0.5 | E10: 0.6 | F10: 0.7 | G10: 0.8
B11: 0.0513 | C11: 0.0455 | D11: 0.0397 | E11: 0.0339 | F11: 0.0282 | G11: 0.0224
A12: Market-implied P(bear) | B12: 0.616

Sheet Sanity
A1: Developer sanity checks (P/E, P/B, EV/EBITDA meaningless pre-revenue)
A2: Market cap (A$m) | B2: =Inputs!B9*Inputs!B6
A3: EV (A$m) | B3: =B2-Inputs!B10
A4: EV / resource t LCE (US$, 100%) | B4: =B3*Inputs!B8/Inputs!B13*1000
A5: Unrisked base NAV/share (A$, 77.5%, no farm-down) | B5: =(0.775*Valuation!C5+Inputs!B10)/Inputs!B9
A6: Price / unrisked NAV | B6: =Inputs!B6/B5
A7: Price / weighted IV | B7: =Inputs!B6/Valuation!B22
A8: CGU book value (A$m) | B8: 82
