Workbook

Sheet DCF Model
A1: AFL - Aflac Incorporated — Book Value Compounding Model (Base Case)
A2: Gray cells are INPUTS - adjust to see valuation change. Insurer model: BVPS compounding + exit P/B, NOT free-cash-flow DCF.
A4: KEY INPUTS
A5: Current Stock Price | B5: 114.01
A6: Shares Outstanding (M) | B6: 505.578
A7: Cash & Equivalents (US$M) | B7: 6120
A8: Total Debt (US$M, N/A - insurer, not netted) | B8: 0
A9: Net Debt (US$M, held at zero) | B9: 0
A10: Starting BVPS (Q2 2026) | B10: 59.96
A11: Annual Dividend per Share (Year 1, current run-rate) | B11: 2.44
A13: Cost of Equity (Base) | B13: 0.09
A14: Exit Price-to-Book (Base) | B14: 2
A16: GROWTH ASSUMPTIONS (BVPS growth rate; NET of dividend already — dividend NOT subtracted again in compounding, see note row 45)
B17: Year 1 | C17: Year 2 | D17: Year 3 | E17: Year 4 | F17: Year 5
A18: BVPS Growth Rate | B18: 0.11 | C18: 0.1 | D18: 0.09 | E18: 0.085 | F18: 0.08
A20: PROJECTIONS
B21: Base Yr | C21: Year 1 | D21: Year 2 | E21: Year 3 | F21: Year 4 | G21: Year 5
A22: Book Value per Share | B22: =B10 | C22: =B22*(1+B18) | D22: =C22*(1+C18) | E22: =D22*(1+D18) | F22: =E22*(1+E18) | G22: =F22*(1+F18)
A23: Dividend per Share | C23: 2.44 | D23: 2.63 | E23: 2.83 | F23: 3.03 | G23: 3.23
A24: Discount Factor (Cost of Equity) | C24: =1/(1+$B$13)^1 | D24: =1/(1+$B$13)^2 | E24: =1/(1+$B$13)^3 | F24: =1/(1+$B$13)^4 | G24: =1/(1+$B$13)^5
A25: PV of Dividend | C25: =C23*C24 | D25: =D23*D24 | E25: =E23*E24 | F25: =F23*F24 | G25: =G23*G24
A27: VALUATION
A28: Sum of PV of Dividends | B28: =SUM(C25:G25)
A29: Terminal BVPS (Year 5) | B29: =G22
A30: Exit Price-to-Book Multiple | B30: =B14
A31: Terminal Value per Share | B31: =B29*B30
A32: PV of Terminal Value | B32: =B31*G24
A33: INTRINSIC VALUE / SHARE | B33: =B28+B32
A34: Upside / (Downside) vs Current Price | B34: =(B33-B5)/B5
A36: ENTRY PRICE (15% CAGR Target)
A37: Target CAGR | B37: 0.15
A38: Reinvested Dividends FV (at target CAGR, to Yr 5) | B38: =C23*(1+$B$37)^4+D23*(1+$B$37)^3+E23*(1+$B$37)^2+F23*(1+$B$37)^1+G23*(1+$B$37)^0
A39: Total Year-5 Value (Terminal Value + Reinvested Divs) | B39: =B31+B38
A40: Entry Price (15% CAGR) | B40: =B39/(1+$B$37)^5
A41: Current Price vs Entry Price | B41: =(B5-B40)/B5
A43: Note: unlike FRFHF, the dividend is NOT subtracted from the compounding BVPS path — bvps_growth_rates
A44: are calibrated from HISTORICAL BVPS CAGRs, which are already net-of-dividend (reported equity falls by the
A45: dividend paid). Subtracting it again would double-count ~4%/yr of drag. Dividend is discounted separately.
A46: Discounting uses COST OF EQUITY (equity-holder view), not WACC — net debt held at zero (insurer funding, not leverage).

Sheet Bull-Bear Scenarios
A1: Bull / Bear Scenario Detail
A3: BULL CASE
A4: Cost of Equity | B4: 0.085
A5: Exit Price-to-Book | B5: 2.3
B6: Year 1 | C6: Year 2 | D6: Year 3 | E6: Year 4 | F6: Year 5
A7: BVPS Growth Rate | B7: 0.14 | C7: 0.13 | D7: 0.12 | E7: 0.11 | F7: 0.1
A8: BVPS | B8: ='DCF Model'!$B$10 | C8: =B8*(1+B7) | D8: =C8*(1+C7) | E8: =D8*(1+D7) | F8: =E8*(1+E7) | G8: =F8*(1+F7)
A9: Dividend per Share | C9: 2.44 | D9: 2.68 | E9: 2.93 | F9: 3.18 | G9: 3.43
A10: Discount Factor | C10: =1/(1+B4)^1 | D10: =1/(1+B4)^2 | E10: =1/(1+B4)^3 | F10: =1/(1+B4)^4 | G10: =1/(1+B4)^5
A11: PV of Dividend | C11: =C9*C10 | D11: =D9*D10 | E11: =E9*E10 | F11: =F9*F10 | G11: =G9*G10
A13: Sum PV of Dividends | B13: =SUM(C11:G11)
A14: Terminal BVPS (Yr 5) | B14: =G8
A15: Terminal Value per Share | B15: =B14*B5
A16: PV of Terminal Value | B16: =B15*G10
A17: INTRINSIC VALUE / SHARE | B17: =B13+B16
A18: Upside / (Downside) | B18: =(B17-'DCF Model'!$B$5)/'DCF Model'!$B$5
A20: BEAR CASE
A21: Cost of Equity | B21: 0.1
A22: Exit Price-to-Book | B22: 1.5
B23: Year 1 | C23: Year 2 | D23: Year 3 | E23: Year 4 | F23: Year 5
A24: BVPS Growth Rate | B24: 0.05 | C24: 0.045 | D24: 0.04 | E24: 0.04 | F24: 0.04
A25: BVPS | B25: ='DCF Model'!$B$10 | C25: =B25*(1+B24) | D25: =C25*(1+C24) | E25: =D25*(1+D24) | F25: =E25*(1+E24) | G25: =F25*(1+F24)
A26: Dividend per Share | C26: 2.44 | D26: 2.52 | E26: 2.6 | F26: 2.68 | G26: 2.76
A27: Discount Factor | C27: =1/(1+B21)^1 | D27: =1/(1+B21)^2 | E27: =1/(1+B21)^3 | F27: =1/(1+B21)^4 | G27: =1/(1+B21)^5
A28: PV of Dividend | C28: =C26*C27 | D28: =D26*D27 | E28: =E26*E27 | F28: =F26*F27 | G28: =G26*G27
A30: Sum PV of Dividends | B30: =SUM(C28:G28)
A31: Terminal BVPS (Yr 5) | B31: =G25
A32: Terminal Value per Share | B32: =B31*B22
A33: PV of Terminal Value | B33: =B32*G27
A34: INTRINSIC VALUE / SHARE | B34: =B30+B33
A35: Upside / (Downside) | B35: =(B34-'DCF Model'!$B$5)/'DCF Model'!$B$5

Sheet Sensitivity
A1: Sensitivity Analysis
A2: Intrinsic Value/Share by BVPS Growth Rate (avg, base 5yr path shifted uniformly) & Exit Price-to-Book
A4: Growth \ Exit P/B | B4: 1.6 | C4: 1.8 | D4: 2 | E4: 2.2 | F4: 2.4
A5: 0.053 | B5: =('DCF Model'!$C$23*(1/(1+0.09)^1)+'DCF Model'!$D$23*(1/(1+0.09)^2)+'DCF Model'!$E$23*(1/(1+0.09)^3)+'DCF Model'!$F$23*(1/(1+0.09)^4)+'DCF Model'!$G$23*(1/(1+0.09)^5))+(((('DCF Model'!$B$10*(1+0.07)*(1+0.060000000000000005))*(1+0.049999999999999996))*(1+0.045000000000000005))*(1+0.04))*1.6*(1/(1+0.09)^5) | C5: =('DCF Model'!$C$23*(1/(1+0.09)^1)+'DCF Model'!$D$23*(1/(1+0.09)^2)+'DCF Model'!$E$23*(1/(1+0.09)^3)+'DCF Model'!$F$23*(1/(1+0.09)^4)+'DCF Model'!$G$23*(1/(1+0.09)^5))+(((('DCF Model'!$B$10*(1+0.07)*(1+0.060000000000000005))*(1+0.049999999999999996))*(1+0.045000000000000005))*(1+0.04))*1.8*(1/(1+0.09)^5) | D5: =('DCF Model'!$C$23*(1/(1+0.09)^1)+'DCF Model'!$D$23*(1/(1+0.09)^2)+'DCF Model'!$E$23*(1/(1+0.09)^3)+'DCF Model'!$F$23*(1/(1+0.09)^4)+'DCF Model'!$G$23*(1/(1+0.09)^5))+(((('DCF Model'!$B$10*(1+0.07)*(1+0.060000000000000005))*(1+0.049999999999999996))*(1+0.045000000000000005))*(1+0.04))*2.0*(1/(1+0.09)^5) | E5: =('DCF Model'!$C$23*(1/(1+0.09)^1)+'DCF Model'!$D$23*(1/(1+0.09)^2)+'DCF Model'!$E$23*(1/(1+0.09)^3)+'DCF Model'!$F$23*(1/(1+0.09)^4)+'DCF Model'!$G$23*(1/(1+0.09)^5))+(((('DCF Model'!$B$10*(1+0.07)*(1+0.060000000000000005))*(1+0.049999999999999996))*(1+0.045000000000000005))*(1+0.04))*2.2*(1/(1+0.09)^5) | F5: =('DCF Model'!$C$23*(1/(1+0.09)^1)+'DCF Model'!$D$23*(1/(1+0.09)^2)+'DCF Model'!$E$23*(1/(1+0.09)^3)+'DCF Model'!$F$23*(1/(1+0.09)^4)+'DCF Model'!$G$23*(1/(1+0.09)^5))+(((('DCF Model'!$B$10*(1+0.07)*(1+0.060000000000000005))*(1+0.049999999999999996))*(1+0.045000000000000005))*(1+0.04))*2.4*(1/(1+0.09)^5)
A6: 0.073 | B6: =('DCF Model'!$C$23*(1/(1+0.09)^1)+'DCF Model'!$D$23*(1/(1+0.09)^2)+'DCF Model'!$E$23*(1/(1+0.09)^3)+'DCF Model'!$F$23*(1/(1+0.09)^4)+'DCF Model'!$G$23*(1/(1+0.09)^5))+(((('DCF Model'!$B$10*(1+0.09)*(1+0.08))*(1+0.06999999999999999))*(1+0.065))*(1+0.06))*1.6*(1/(1+0.09)^5) | C6: =('DCF Model'!$C$23*(1/(1+0.09)^1)+'DCF Model'!$D$23*(1/(1+0.09)^2)+'DCF Model'!$E$23*(1/(1+0.09)^3)+'DCF Model'!$F$23*(1/(1+0.09)^4)+'DCF Model'!$G$23*(1/(1+0.09)^5))+(((('DCF Model'!$B$10*(1+0.09)*(1+0.08))*(1+0.06999999999999999))*(1+0.065))*(1+0.06))*1.8*(1/(1+0.09)^5) | D6: =('DCF Model'!$C$23*(1/(1+0.09)^1)+'DCF Model'!$D$23*(1/(1+0.09)^2)+'DCF Model'!$E$23*(1/(1+0.09)^3)+'DCF Model'!$F$23*(1/(1+0.09)^4)+'DCF Model'!$G$23*(1/(1+0.09)^5))+(((('DCF Model'!$B$10*(1+0.09)*(1+0.08))*(1+0.06999999999999999))*(1+0.065))*(1+0.06))*2.0*(1/(1+0.09)^5) | E6: =('DCF Model'!$C$23*(1/(1+0.09)^1)+'DCF Model'!$D$23*(1/(1+0.09)^2)+'DCF Model'!$E$23*(1/(1+0.09)^3)+'DCF Model'!$F$23*(1/(1+0.09)^4)+'DCF Model'!$G$23*(1/(1+0.09)^5))+(((('DCF Model'!$B$10*(1+0.09)*(1+0.08))*(1+0.06999999999999999))*(1+0.065))*(1+0.06))*2.2*(1/(1+0.09)^5) | F6: =('DCF Model'!$C$23*(1/(1+0.09)^1)+'DCF Model'!$D$23*(1/(1+0.09)^2)+'DCF Model'!$E$23*(1/(1+0.09)^3)+'DCF Model'!$F$23*(1/(1+0.09)^4)+'DCF Model'!$G$23*(1/(1+0.09)^5))+(((('DCF Model'!$B$10*(1+0.09)*(1+0.08))*(1+0.06999999999999999))*(1+0.065))*(1+0.06))*2.4*(1/(1+0.09)^5)
A7: 0.093 | B7: =('DCF Model'!$C$23*(1/(1+0.09)^1)+'DCF Model'!$D$23*(1/(1+0.09)^2)+'DCF Model'!$E$23*(1/(1+0.09)^3)+'DCF Model'!$F$23*(1/(1+0.09)^4)+'DCF Model'!$G$23*(1/(1+0.09)^5))+(((('DCF Model'!$B$10*(1+0.11)*(1+0.1))*(1+0.09))*(1+0.085))*(1+0.08))*1.6*(1/(1+0.09)^5) | C7: =('DCF Model'!$C$23*(1/(1+0.09)^1)+'DCF Model'!$D$23*(1/(1+0.09)^2)+'DCF Model'!$E$23*(1/(1+0.09)^3)+'DCF Model'!$F$23*(1/(1+0.09)^4)+'DCF Model'!$G$23*(1/(1+0.09)^5))+(((('DCF Model'!$B$10*(1+0.11)*(1+0.1))*(1+0.09))*(1+0.085))*(1+0.08))*1.8*(1/(1+0.09)^5) | D7: =('DCF Model'!$C$23*(1/(1+0.09)^1)+'DCF Model'!$D$23*(1/(1+0.09)^2)+'DCF Model'!$E$23*(1/(1+0.09)^3)+'DCF Model'!$F$23*(1/(1+0.09)^4)+'DCF Model'!$G$23*(1/(1+0.09)^5))+(((('DCF Model'!$B$10*(1+0.11)*(1+0.1))*(1+0.09))*(1+0.085))*(1+0.08))*2.0*(1/(1+0.09)^5) | E7: =('DCF Model'!$C$23*(1/(1+0.09)^1)+'DCF Model'!$D$23*(1/(1+0.09)^2)+'DCF Model'!$E$23*(1/(1+0.09)^3)+'DCF Model'!$F$23*(1/(1+0.09)^4)+'DCF Model'!$G$23*(1/(1+0.09)^5))+(((('DCF Model'!$B$10*(1+0.11)*(1+0.1))*(1+0.09))*(1+0.085))*(1+0.08))*2.2*(1/(1+0.09)^5) | F7: =('DCF Model'!$C$23*(1/(1+0.09)^1)+'DCF Model'!$D$23*(1/(1+0.09)^2)+'DCF Model'!$E$23*(1/(1+0.09)^3)+'DCF Model'!$F$23*(1/(1+0.09)^4)+'DCF Model'!$G$23*(1/(1+0.09)^5))+(((('DCF Model'!$B$10*(1+0.11)*(1+0.1))*(1+0.09))*(1+0.085))*(1+0.08))*2.4*(1/(1+0.09)^5)
A8: 0.113 | B8: =('DCF Model'!$C$23*(1/(1+0.09)^1)+'DCF Model'!$D$23*(1/(1+0.09)^2)+'DCF Model'!$E$23*(1/(1+0.09)^3)+'DCF Model'!$F$23*(1/(1+0.09)^4)+'DCF Model'!$G$23*(1/(1+0.09)^5))+(((('DCF Model'!$B$10*(1+0.13)*(1+0.12000000000000001))*(1+0.11))*(1+0.10500000000000001))*(1+0.1))*1.6*(1/(1+0.09)^5) | C8: =('DCF Model'!$C$23*(1/(1+0.09)^1)+'DCF Model'!$D$23*(1/(1+0.09)^2)+'DCF Model'!$E$23*(1/(1+0.09)^3)+'DCF Model'!$F$23*(1/(1+0.09)^4)+'DCF Model'!$G$23*(1/(1+0.09)^5))+(((('DCF Model'!$B$10*(1+0.13)*(1+0.12000000000000001))*(1+0.11))*(1+0.10500000000000001))*(1+0.1))*1.8*(1/(1+0.09)^5) | D8: =('DCF Model'!$C$23*(1/(1+0.09)^1)+'DCF Model'!$D$23*(1/(1+0.09)^2)+'DCF Model'!$E$23*(1/(1+0.09)^3)+'DCF Model'!$F$23*(1/(1+0.09)^4)+'DCF Model'!$G$23*(1/(1+0.09)^5))+(((('DCF Model'!$B$10*(1+0.13)*(1+0.12000000000000001))*(1+0.11))*(1+0.10500000000000001))*(1+0.1))*2.0*(1/(1+0.09)^5) | E8: =('DCF Model'!$C$23*(1/(1+0.09)^1)+'DCF Model'!$D$23*(1/(1+0.09)^2)+'DCF Model'!$E$23*(1/(1+0.09)^3)+'DCF Model'!$F$23*(1/(1+0.09)^4)+'DCF Model'!$G$23*(1/(1+0.09)^5))+(((('DCF Model'!$B$10*(1+0.13)*(1+0.12000000000000001))*(1+0.11))*(1+0.10500000000000001))*(1+0.1))*2.2*(1/(1+0.09)^5) | F8: =('DCF Model'!$C$23*(1/(1+0.09)^1)+'DCF Model'!$D$23*(1/(1+0.09)^2)+'DCF Model'!$E$23*(1/(1+0.09)^3)+'DCF Model'!$F$23*(1/(1+0.09)^4)+'DCF Model'!$G$23*(1/(1+0.09)^5))+(((('DCF Model'!$B$10*(1+0.13)*(1+0.12000000000000001))*(1+0.11))*(1+0.10500000000000001))*(1+0.1))*2.4*(1/(1+0.09)^5)
A9: 0.133 | B9: =('DCF Model'!$C$23*(1/(1+0.09)^1)+'DCF Model'!$D$23*(1/(1+0.09)^2)+'DCF Model'!$E$23*(1/(1+0.09)^3)+'DCF Model'!$F$23*(1/(1+0.09)^4)+'DCF Model'!$G$23*(1/(1+0.09)^5))+(((('DCF Model'!$B$10*(1+0.15)*(1+0.14))*(1+0.13))*(1+0.125))*(1+0.12))*1.6*(1/(1+0.09)^5) | C9: =('DCF Model'!$C$23*(1/(1+0.09)^1)+'DCF Model'!$D$23*(1/(1+0.09)^2)+'DCF Model'!$E$23*(1/(1+0.09)^3)+'DCF Model'!$F$23*(1/(1+0.09)^4)+'DCF Model'!$G$23*(1/(1+0.09)^5))+(((('DCF Model'!$B$10*(1+0.15)*(1+0.14))*(1+0.13))*(1+0.125))*(1+0.12))*1.8*(1/(1+0.09)^5) | D9: =('DCF Model'!$C$23*(1/(1+0.09)^1)+'DCF Model'!$D$23*(1/(1+0.09)^2)+'DCF Model'!$E$23*(1/(1+0.09)^3)+'DCF Model'!$F$23*(1/(1+0.09)^4)+'DCF Model'!$G$23*(1/(1+0.09)^5))+(((('DCF Model'!$B$10*(1+0.15)*(1+0.14))*(1+0.13))*(1+0.125))*(1+0.12))*2.0*(1/(1+0.09)^5) | E9: =('DCF Model'!$C$23*(1/(1+0.09)^1)+'DCF Model'!$D$23*(1/(1+0.09)^2)+'DCF Model'!$E$23*(1/(1+0.09)^3)+'DCF Model'!$F$23*(1/(1+0.09)^4)+'DCF Model'!$G$23*(1/(1+0.09)^5))+(((('DCF Model'!$B$10*(1+0.15)*(1+0.14))*(1+0.13))*(1+0.125))*(1+0.12))*2.2*(1/(1+0.09)^5) | F9: =('DCF Model'!$C$23*(1/(1+0.09)^1)+'DCF Model'!$D$23*(1/(1+0.09)^2)+'DCF Model'!$E$23*(1/(1+0.09)^3)+'DCF Model'!$F$23*(1/(1+0.09)^4)+'DCF Model'!$G$23*(1/(1+0.09)^5))+(((('DCF Model'!$B$10*(1+0.15)*(1+0.14))*(1+0.13))*(1+0.125))*(1+0.12))*2.4*(1/(1+0.09)^5)
A11: Note: Cost of equity held at base case (9.0%). Rows = average annual BVPS growth rate over the 5-yr
A12: path (base path shifted uniformly -4pp to +4pp). Columns = exit price-to-book multiple applied to Year-5 BVPS.

Sheet Historical
A1: Historical Growth Rates
A3: Metric | B3: 3-Year CAGR | C3: 5-Year CAGR / Other
A4: BVPS | B4: 0.2041 | C4: 0.033
A5: BVPS (8yr, post-split FY2017-25) | C5: 0.0754
A6: EPS (misleading - see warning) | B6: -0.0053 | C6: 0.0045
A7: Revenue (misleading - FX translation, see warning) | B7: -0.0357 | C7: -0.0497
A8: Shareholders' Equity (total) | B8: 0.1355 | C8: -0.0255
A10: Selected Growth Rate (base anchor, Year 1): | B10: 0.11
A11: Source: | B11: blend: bvps_8yr_cagr_post_split (structural) + buyback pace, faded from 3yr run-rate
A13: Growth Divergence Warning:
A14: BVPS CAGRs are dominated by AOCI (rate mark-to-market on the JGB/USD book): the 3yr figure (20.4%) is inflated by recovery from the 2021-22 rate-shock AOCI trough; the 5yr figure (3.3%) is depressed by an artificially high FY2020 AOCI-peak base. Revenue CAGRs are negative almost entirely on USD/JPY translation, not business decline. EPS CAGRs are near-zero because FY2025 GAAP EPS was depressed ~29% YoY by net investment losses/CECL allowances against a record management-adjusted EPS of $7.49. The 8yr post-split BVPS CAGR (7.5%) spans a full rate cycle and is the most defensible structural anchor, blended with the ~5-6%/yr buyback-driven share count decline.
A17: BVPS by Fiscal Year (post-split only)
A18: Period | B18: BVPS (US$)
A19: FY2017 | B19: 30.83
A20: FY2018 | B20: 30.29
A21: FY2019 | B21: 38.8
A22: FY2020 | B22: 46.86
A23: FY2021 | B23: 25.17
A24: FY2022 | B24: 31.58
A25: FY2023 | B25: 36.72
A26: FY2024 | B26: 46.19
A27: FY2025 | B27: 55.13
A28: Q2 2026 | B28: 59.96

Sheet Sanity Check
A1: Sanity Check — Historical P/B Cross-Reference
A3: Base Intrinsic Value / Share | B3: ='DCF Model'!B33
A4: Implied P/B (Base IV / Q2-2026 BVPS) | B4: =B3/'DCF Model'!B10
A5: Normalized EPS Estimate (mid-cycle) | B5: 8
A6: Implied P/E (Base IV / Normalized EPS) | B6: =B3/B5
A8: Historical Post-2022 P/B Range (AOCI-stabilized)
A9: Min (FY2022 year-end) | B9: 2.05
A10: Average (FY2022-25 year-end) | B10: 2.2
A11: Max (FY2024 year-end) | B11: 2.37
A12: Current (Q2 2026) | B12: 1.9
A14: Sanity Check Passed: | B14: YES
A16: Diagnosis:
A17: Base-case intrinsic value of $132.43 implies a P/B of 2.21x on Q2-2026 BVPS ($59.96) - inside the post-2022 (AOCI-stabilized) trading range of 2.05x-2.37x - and roughly 16.6x a normalized ~$8.00/share earnings estimate (management's own record FY2025 adjusted EPS was $7.49). Current price ($114.01, 1.90x BVPS) sits slightly below the post-2022 P/B range, consistent with the model's modest +16% base-case upside. Pre-2022 P/B figures (as low as 1.02x FY2020, as high as 2.43x FY2021) were excluded from the historical band because they were mechanically distorted by the near-zero-to-rising-rate AOCI shock on the JGB portfolio, not by a change in franchise value.
