Workbook

Sheet Model_Info
A1: RUA.NZ - Rua Bioscience Limited - scenario valuation model, version 1.0 (fresh build, supersedes nothing)
A2: Built by: dcf-analyst agent (Claude, model claude-fable-5) on 2026-08-27 at the user's request (research-stock workflow)
A3: MODEL: probability-weighted scenario model on a forward (FY2028E) EV/Sales multiple. NOT a discounted-FCF model.
A4: Why: owner FCF negative in every period on record (nothing to discount); book value not audit-assured (PwC disclaimer of opinion FY2024 AND FY2025); not a receivership (going concern basis, revenue +92% YoY at H1 FY2026). Routed per dcf-methods SKILL: straddles distressed / operating-company rows.
A5: Discount rate: 28% NZD cost of equity (NZ micro-cap base ~11% + illiquidity 5% + audit-disclaimer information risk 4% + concentration 4% + pre-profitability 3%). Insolvency risk is NOT in the rate - it is the 60% branch inside the 40%-weighted bear scenario. Charged once.
A6: Dilution is modelled explicitly per scenario: base +140m shares (NZ$3.5m at $0.025), bear recap +250m (NZ$3.0m at $0.012), bull none. Share count is NOT held flat - dilution here is rescue issuance, not SBC.
A7: Data vintage: price NZ$0.035 at 2026-08-27T04:59:43Z (Yahoo, NZX regular close). Balance sheet 31-Dec-2025 (H1 FY2026 interim) - 8 MONTHS STALE; cash today likely lower. Shares: 339.402m ordinary (Aug-2026) + 8.733m warrants ($0.015, in the money) = 348.135m diluted. Guidance: H1 FY2026 going-concern note (signed 26-Feb-2026) + 16-Jul-2026 UK deal announcement.
A8: Scenario drivers are the dcf-analyst agent's judgment, set 2026-08-27, following the user's framing (bear = near-total loss at meaningful weight).
A9: REFRESH after the FY2026 annual report (~Sep/Oct 2026): cash, borrowings, share count, audit opinion (a third disclaimer would raise the bear weight), facility sale status, first UK-deal revenue evidence.
A10: Cell legend: BLUE font = hardcoded input. YELLOW fill = key driver lever. Black = formula. GREEN font = cross-sheet link.
A11: These figures go stale. Verify price, cash and share count before acting on any number in this file.

Sheet Actuals
A1: Metric (NZD m) | B1: FY2021 | C1: FY2022 | D1: FY2023 | E1: FY2024 | F1: FY2025 | G1: H1 FY2025 | H1: H1 FY2026 | I1: Source note
A2: Revenue | B2: 0 | C2: 0.024 | D2: 0.358 | E2: 0.086 | F2: 1.511 | G2: 0.694 | H2: 1.334 | I2: Metrics.csv from core_metrics; filings in whole NZD
A3: Net income | B3: -4.418 | C3: -8.636 | D3: -5.959 | E3: -13.719 | F3: -3.456 | G3: -1.802 | H3: -1.793 | I3: FY2024 includes ~NZ$8.5m impairment
A4: Operating cash flow | B4: -4.447 | C4: -6.845 | D4: -5.92 | E4: -3.736 | F4: -2.787 | G4: -1.943 | H4: -1.52 | I4: Burn halved from FY2023 peak
A5: Free cash flow | B5: -5.849 | C5: -7.245 | D5: -5.994 | E5: -3.738 | F5: -2.791 | H5: -1.52 | I5: Never positive in any period on record
A6: SBC | B6: 0.5 | C6: 0.139 | D6: 0.127 | E6: 0.135 | F6: 0.042 | G6: 0.027 | H6: 0.07 | I6: Share-based payment expense notes
A7: Shareholders equity | B7: 28.834 | C7: 24.198 | D7: 20.12 | E7: 6.767 | F7: 4.891 | H7: 5.845 | I7: NOT audit-assured: disclaimer of opinion FY2024 + FY2025
A8: Cash | B8: 3.359 | C8: 1.897 | D8: 2.529 | E8: 0.895 | F8: 0.241 | G8: 0.539 | H8: 2.166 | I8: Dec-2025 cash reflects the Dec-2025 rights offer
A9: Total debt | B9: 0.955 | C9: 0.824 | D9: 0.115 | E9: 0.148 | F9: 0.804 | H9: 1.813 | I9: H1 FY2026 borrowings incl. warrant-sweetened facilities
A10: Shares outstanding (m) | B10: 140.263 | C10: 149.879 | D10: 158.136 | E10: 159.751 | F10: 223.648 | H10: 338.042 | I10: +112% in 18 months; ~339.4m + 8.733m warrants by Aug-2026
A12: Balance-sheet snapshot date: 31-Dec-2025 (8 months stale at valuation date)
A13: Held-for-sale Gisborne facility, net: NZ$0.861m carrying value (H1 FY2026 note 17)
A14: Goodwill: NZ$2.195m - within the assets PwC could not corroborate
A15: Buybacks: zero in every period (ShareRepurchases all 0)

Sheet Assumptions
A1: Global assumptions
A2: Current price (NZD) | B2: 0.035 | C2: Yahoo 2026-08-27T04:59:43Z, NZX regular close; 52w 0.026-0.059
A3: Diluted shares today (m) | B3: 348.135 | C3: 339.402m ordinary (Aug-2026) + 8.733m warrants at $0.015 (in the money)
A4: Cost of equity | B4: 0.28 | C4: NZ micro-cap ~11% + illiquidity 5% + audit-disclaimer 4% + concentration 4% + pre-profit 3%. EXCLUDES insolvency (in bear weight).
A5: Hurdle rate (entry price) | B5: 0.15 | C5: Repo standard 15% IRR
A6: Horizon (years to exit) | B6: 2 | C6: Exit valued at end FY2028
A7: Net cash at 31-Dec-2025 (NZDm) | B7: 0.353 | C7: Cash 2.166 less borrowings 1.813; 8 months stale, treat as ~0
A9: Probability weights
A10: Bear weight | B10: 0.4 | C10: Two consecutive audit disclaimers + ~7 months runway + conditional going concern
A11: Base weight | B11: 0.4 | C11: One further dilutive raise; UK deal partial conversion
A12: Bull weight | B12: 0.2 | C12: UK deal converts fully AND Germany holds AND TGA spares Australia AND no raise - several independent things
A13: Weight check (must be 1.0) | B13: =SUM(B10:B12)
A15: Scenario narratives
A16: Bear | C16: Australia (TGA review) and Germany (EUR4/g compression) squeeze revenue; UK deal underdelivers; facility sale delays; runway exhausted. 60% insolvency (equity ~0) / 40% punitive recap at $0.012 (+250m shares), business limps at ~NZ$2.5m revenue, 0.6x exit.
A17: Base | C17: Revenue 2.8 -> 4.5 -> 6.0 (UK deal partial); facility sells ~NZ$0.7m net; ONE further raise NZ$3.5m at $0.025 (+140m shares); exit 1.5x FY2028E sales, net cash ~0.
A18: Bull | C18: UK deal converts (~NZ$5m/yr), revenue 2.9 -> 7.0 -> 10.5; breakeven during FY2027; facility sale + warrant proceeds bridge burn with NO further raise; exit 2.5x with NZ$1.2m net cash.

Sheet Scenario_Base
A1: Scenario Base
A3: Revenue FY2026E (NZDm) | B3: 2.8 | C3: Driver: H1 FY2026 actual NZ$1.334m + H2 estimate
A4: Growth FY2027E | B4: 0.60714286 | C4: Driver
A5: Growth FY2028E | B5: 0.33333333 | C5: Driver
A6: Revenue FY2027E | B6: =B3*(1+B4)
A7: Revenue FY2028E | B7: =B6*(1+B5)
A9: Exit EV/Sales multiple | B9: 1.5 | C9: Driver: sub-scale unprofitable distributor multiple, not branded pharma
A10: Net cash at exit (NZDm) | B10: 0 | C10: Driver
A11: Exit EV (NZDm) | B11: =B9*B7
A12: Exit equity value (NZDm) | B12: =B11+B10
A14: Further raise, net (NZDm) | B14: 3.5 | C14: Driver: rescue-raise size
A15: Raise price (NZD) | B15: 0.025 | C15: Driver: Nov-2024 rights precedent $0.025 at 47.9% discount
A16: New shares (m) | B16: =IF(B15=0,0,B14/B15)
A17: Diluted shares at exit (m) | B17: =Assumptions!B3+B16
A19: PV of exit equity at CoE (NZDm) | B19: =B12/(1+Assumptions!B4)^Assumptions!B6
A20: Value per share (NZD) | B20: =B19/B17
A21: Upside vs price | B21: =B20/Assumptions!B2-1
A23: Entry price at 15% hurdle (NZD) | B23: =B12/(1+Assumptions!B5)^Assumptions!B6/B17

Sheet Scenario_Bull
A1: Scenario Bull
A3: Revenue FY2026E (NZDm) | B3: 2.9 | C3: Driver: H1 FY2026 actual NZ$1.334m + H2 estimate
A4: Growth FY2027E | B4: 1.4137931 | C4: Driver
A5: Growth FY2028E | B5: 0.5 | C5: Driver
A6: Revenue FY2027E | B6: =B3*(1+B4)
A7: Revenue FY2028E | B7: =B6*(1+B5)
A9: Exit EV/Sales multiple | B9: 2.5 | C9: Driver: sub-scale unprofitable distributor multiple, not branded pharma
A10: Net cash at exit (NZDm) | B10: 1.2 | C10: Driver
A11: Exit EV (NZDm) | B11: =B9*B7
A12: Exit equity value (NZDm) | B12: =B11+B10
A14: Further raise, net (NZDm) | B14: 0 | C14: Driver: rescue-raise size
A15: Raise price (NZD) | B15: 0 | C15: Driver: Nov-2024 rights precedent $0.025 at 47.9% discount
A16: New shares (m) | B16: =IF(B15=0,0,B14/B15)
A17: Diluted shares at exit (m) | B17: =Assumptions!B3+B16
A19: PV of exit equity at CoE (NZDm) | B19: =B12/(1+Assumptions!B4)^Assumptions!B6
A20: Value per share (NZD) | B20: =B19/B17
A21: Upside vs price | B21: =B20/Assumptions!B2-1
A23: Entry price at 15% hurdle (NZD) | B23: =B12/(1+Assumptions!B5)^Assumptions!B6/B17

Sheet Scenario_Bear
A1: Scenario Bear
A3: Revenue FY2026E (NZDm) | B3: 2.6 | C3: Driver: H1 FY2026 actual NZ$1.334m + H2 estimate
A4: Growth FY2027E | B4: -0.076923077 | C4: Driver
A5: Growth FY2028E | B5: 0.041666667 | C5: Driver
A6: Revenue FY2027E | B6: =B3*(1+B4)
A7: Revenue FY2028E | B7: =B6*(1+B5)
A9: Exit EV/Sales multiple | B9: 0.6 | C9: Driver: sub-scale unprofitable distributor multiple, not branded pharma
A10: Net cash at exit (NZDm) | B10: 0.5 | C10: Driver
A11: Exit EV (NZDm) | B11: =B9*B7
A12: Exit equity value (NZDm) | B12: =B11+B10
A14: Further raise, net (NZDm) | B14: 3 | C14: Driver: rescue-raise size
A15: Raise price (NZD) | B15: 0.012 | C15: Driver: Nov-2024 rights precedent $0.025 at 47.9% discount
A16: New shares (m) | B16: =IF(B15=0,0,B14/B15)
A17: Diluted shares at exit (m) | B17: =Assumptions!B3+B16
A19: PV of exit equity at CoE (NZDm) | B19: =B12/(1+Assumptions!B4)^Assumptions!B6
A20: Recap-branch value per share (NZD) | B20: =B19/B17
A21: Upside vs price | B21: =B20/Assumptions!B2-1
A23: Recap-branch entry at 15% (NZD) | B23: =B12/(1+Assumptions!B5)^Assumptions!B6/B17
A25: P(insolvency | bear) | B25: 0.6 | C25: Driver: wind-down leaves ~0 for equity (verified-tangible ~2.8 less debt 1.8 less costs)
A26: Insolvency equity value / share | B26: 0 | C26: Creditor waterfall residual
A27: BEAR value per share (blend) | B27: =B25*B26+(1-B25)*B20
A28: Upside vs price | B28: =B27/Assumptions!B2-1
A29: BEAR entry at 15% (blend) | B29: =B25*B26+(1-B25)*B23

Sheet Valuation
A1: RUA.NZ probability-weighted valuation (NZD per share)
B3: Bear | C3: Base | D3: Bull
A4: Value per share | B4: =Scenario_Bear!B27 | C4: =Scenario_Base!B20 | D4: =Scenario_Bull!B20
A5: Weight | B5: =Assumptions!B10 | C5: =Assumptions!B11 | D5: =Assumptions!B12
A6: Upside vs price | B6: =Scenario_Bear!B28 | C6: =Scenario_Base!B21 | D6: =Scenario_Bull!B21
A7: Entry price (15% hurdle) | B7: =Scenario_Bear!B29 | C7: =Scenario_Base!B23 | D7: =Scenario_Bull!B23
A9: Probability-weighted IV | B9: =SUMPRODUCT(B4:D4,B5:D5)
A10: Current price | B10: =Assumptions!B2
A11: Upside (weighted) | B11: =B9/B10-1
A12: Weighted entry price (15%) | B12: =SUMPRODUCT(B7:D7,B5:D5)
A13: Note: weighted entry sits ABOVE weighted IV because the 15% hurdle is below the 28% risk-appropriate CoE. Both are less than half the current price.
A15: Required-return table (base scenario)
A16: Required return | B16: 0.09 | C16: 0.1 | D16: 0.11 | E16: 0.12 | F16: 0.15 | G16: 0.28
A17: Base value per share | B17: =Scenario_Base!B12/(1+B16)^Assumptions!B6/Scenario_Base!B17 | C17: =Scenario_Base!B12/(1+C16)^Assumptions!B6/Scenario_Base!B17 | D17: =Scenario_Base!B12/(1+D16)^Assumptions!B6/Scenario_Base!B17 | E17: =Scenario_Base!B12/(1+E16)^Assumptions!B6/Scenario_Base!B17 | F17: =Scenario_Base!B12/(1+F16)^Assumptions!B6/Scenario_Base!B17 | G17: =Scenario_Base!B12/(1+G16)^Assumptions!B6/Scenario_Base!B17
A19: Sensitivity: cost of equity (rows) x exit EV/Sales (cols), base scenario
B20: 0.75 | C20: 1 | D20: 1.5 | E20: 2 | F20: 2.5
A21: 0.2 | B21: =(B$20*Scenario_Base!$B$7+Scenario_Base!$B$10)/(1+$A21)^Assumptions!$B$6/Scenario_Base!$B$17 | C21: =(C$20*Scenario_Base!$B$7+Scenario_Base!$B$10)/(1+$A21)^Assumptions!$B$6/Scenario_Base!$B$17 | D21: =(D$20*Scenario_Base!$B$7+Scenario_Base!$B$10)/(1+$A21)^Assumptions!$B$6/Scenario_Base!$B$17 | E21: =(E$20*Scenario_Base!$B$7+Scenario_Base!$B$10)/(1+$A21)^Assumptions!$B$6/Scenario_Base!$B$17 | F21: =(F$20*Scenario_Base!$B$7+Scenario_Base!$B$10)/(1+$A21)^Assumptions!$B$6/Scenario_Base!$B$17
A22: 0.24 | B22: =(B$20*Scenario_Base!$B$7+Scenario_Base!$B$10)/(1+$A22)^Assumptions!$B$6/Scenario_Base!$B$17 | C22: =(C$20*Scenario_Base!$B$7+Scenario_Base!$B$10)/(1+$A22)^Assumptions!$B$6/Scenario_Base!$B$17 | D22: =(D$20*Scenario_Base!$B$7+Scenario_Base!$B$10)/(1+$A22)^Assumptions!$B$6/Scenario_Base!$B$17 | E22: =(E$20*Scenario_Base!$B$7+Scenario_Base!$B$10)/(1+$A22)^Assumptions!$B$6/Scenario_Base!$B$17 | F22: =(F$20*Scenario_Base!$B$7+Scenario_Base!$B$10)/(1+$A22)^Assumptions!$B$6/Scenario_Base!$B$17
A23: 0.28 | B23: =(B$20*Scenario_Base!$B$7+Scenario_Base!$B$10)/(1+$A23)^Assumptions!$B$6/Scenario_Base!$B$17 | C23: =(C$20*Scenario_Base!$B$7+Scenario_Base!$B$10)/(1+$A23)^Assumptions!$B$6/Scenario_Base!$B$17 | D23: =(D$20*Scenario_Base!$B$7+Scenario_Base!$B$10)/(1+$A23)^Assumptions!$B$6/Scenario_Base!$B$17 | E23: =(E$20*Scenario_Base!$B$7+Scenario_Base!$B$10)/(1+$A23)^Assumptions!$B$6/Scenario_Base!$B$17 | F23: =(F$20*Scenario_Base!$B$7+Scenario_Base!$B$10)/(1+$A23)^Assumptions!$B$6/Scenario_Base!$B$17
A24: 0.32 | B24: =(B$20*Scenario_Base!$B$7+Scenario_Base!$B$10)/(1+$A24)^Assumptions!$B$6/Scenario_Base!$B$17 | C24: =(C$20*Scenario_Base!$B$7+Scenario_Base!$B$10)/(1+$A24)^Assumptions!$B$6/Scenario_Base!$B$17 | D24: =(D$20*Scenario_Base!$B$7+Scenario_Base!$B$10)/(1+$A24)^Assumptions!$B$6/Scenario_Base!$B$17 | E24: =(E$20*Scenario_Base!$B$7+Scenario_Base!$B$10)/(1+$A24)^Assumptions!$B$6/Scenario_Base!$B$17 | F24: =(F$20*Scenario_Base!$B$7+Scenario_Base!$B$10)/(1+$A24)^Assumptions!$B$6/Scenario_Base!$B$17
A25: 0.36 | B25: =(B$20*Scenario_Base!$B$7+Scenario_Base!$B$10)/(1+$A25)^Assumptions!$B$6/Scenario_Base!$B$17 | C25: =(C$20*Scenario_Base!$B$7+Scenario_Base!$B$10)/(1+$A25)^Assumptions!$B$6/Scenario_Base!$B$17 | D25: =(D$20*Scenario_Base!$B$7+Scenario_Base!$B$10)/(1+$A25)^Assumptions!$B$6/Scenario_Base!$B$17 | E25: =(E$20*Scenario_Base!$B$7+Scenario_Base!$B$10)/(1+$A25)^Assumptions!$B$6/Scenario_Base!$B$17 | F25: =(F$20*Scenario_Base!$B$7+Scenario_Base!$B$10)/(1+$A25)^Assumptions!$B$6/Scenario_Base!$B$17
A27: Reading: no cell reaches the NZ$0.035 price - not even 2.5x at 20% CoE. The market pays ~4.3x run-rate sales today.
